{
  "type": "Feature",
  "properties": {
    "gn:admin1_code":"15.0",
    "gn:asciiname":"Unt'o-gol",
    "gn:country_code":"KP",
    "gn:dem":285,
    "gn:feature_class":"P",
    "gn:feature_code":"PPL",
    "gn:name":"\u016cnt\u2019o-gol",
    "gn:population":0,
    "gn:timezone":"Asia/Pyongyang",
    "iso:country":"KP",
    "name:kor_x_preferred":[
        "\uc740\ud1a0\uace8"
    ],
    "name:kor_x_variant":[
        "\u016cnt\u2019o-gol"
    ],
    "wof:name":"Unt'o-gol",
    "wof:placetype":"locality"
},
  "geometry": {"coordinates":[126.59,39.41667],"type":"Point"}
}