{
  "type": "Feature",
  "properties": {
    "gn:admin1_code":"12.0",
    "gn:asciiname":"Ponghwa-dong",
    "gn:country_code":"KP",
    "gn:dem":12,
    "gn:feature_class":"P",
    "gn:feature_code":"PPL",
    "gn:name":"Ponghwa-dong",
    "gn:population":0,
    "gn:timezone":"Asia/Pyongyang",
    "iso:country":"KP",
    "name:kor_x_preferred":[
        "\ubd09\ud654\ub3d9"
    ],
    "name:und_x_variant":[
        "Miry\u014fk-tong",
        "Mir\u016dk-tong",
        "Ponghwa-dong",
        "Bonghwa-dong",
        "Bonghwadong"
    ],
    "wof:name":"Ponghwa-dong",
    "wof:placetype":"locality"
},
  "geometry": {"coordinates":[125.71666999999999,39.05],"type":"Point"}
}