{
  "type": "Feature",
  "properties": {
    "gn:admin1_code":"9.0",
    "gn:asciiname":"Sinhung-ni",
    "gn:country_code":"KP",
    "gn:dem":65,
    "gn:feature_class":"P",
    "gn:feature_code":"PPL",
    "gn:name":"Sinh\u016dng-ni",
    "gn:population":0,
    "gn:timezone":"Asia/Pyongyang",
    "iso:country":"KP",
    "name:und_x_variant":[
        "\uc2e0\ud765\ub9ac",
        "Sinh\u016dng-ni"
    ],
    "wof:name":"Sinhung-ni",
    "wof:placetype":"locality"
},
  "geometry": {"coordinates":[127.79000000000001,38.94972],"type":"Point"}
}