{
  "type": "Feature",
  "properties": {
    "gn:admin1_code":"11.0",
    "gn:asciiname":"Soyaksu",
    "gn:country_code":"KP",
    "gn:dem":26,
    "gn:feature_class":"P",
    "gn:feature_code":"PPL",
    "gn:name":"S\u014fyaksu",
    "gn:population":0,
    "gn:timezone":"Asia/Pyongyang",
    "iso:country":"KP",
    "name:kor_x_preferred":[
        "\uc11c\uc57d\uc218"
    ],
    "name:und_x_variant":[
        "S\u014fyaksu"
    ],
    "wof:name":"Soyaksu",
    "wof:placetype":"locality"
},
  "geometry": {"coordinates":[124.61444,39.89444],"type":"Point"}
}