{
  "type": "Feature",
  "properties": {
    "gn:admin1_code":"9.0",
    "gn:asciiname":"Song-dong",
    "gn:country_code":"KP",
    "gn:dem":327,
    "gn:feature_class":"P",
    "gn:feature_code":"PPL",
    "gn:name":"S\u014fng-dong",
    "gn:population":0,
    "gn:timezone":"Asia/Pyongyang",
    "iso:country":"KP",
    "name:und_x_variant":[
        "\uc131\ub3d9",
        "Song-dong",
        "S\u014fng-dong"
    ],
    "wof:name":"Song-dong",
    "wof:placetype":"locality"
},
  "geometry": {"coordinates":[126.95332999999999,38.82639],"type":"Point"}
}