{
  "type": "Feature",
  "properties": {
    "gn:admin1_code":"17.0",
    "gn:asciiname":"Hoyang-dong",
    "gn:country_code":"KP",
    "gn:dem":59,
    "gn:feature_class":"P",
    "gn:feature_code":"PPL",
    "gn:name":"Hoyang-dong",
    "gn:population":0,
    "gn:timezone":"Asia/Pyongyang",
    "iso:country":"KP",
    "name:und_x_variant":[
        "\ud638\uc591\ub3d9",
        "Hoyang-dong"
    ],
    "wof:name":"Hoyang-dong",
    "wof:placetype":"locality"
},
  "geometry": {"coordinates":[129.19638999999998,40.76056],"type":"Point"}
}