{
  "type": "Feature",
  "properties": {
    "gn:admin1_code":"11.0",
    "gn:asciiname":"Kop'o-burak",
    "gn:country_code":"KP",
    "gn:dem":16,
    "gn:feature_class":"P",
    "gn:feature_code":"PPL",
    "gn:name":"K\u014fp\u2019o-burak",
    "gn:population":0,
    "gn:timezone":"Asia/Pyongyang",
    "iso:country":"KP",
    "name:kor_x_preferred":[
        "\uac70\ud3ec\ub9ac"
    ],
    "name:kor_x_variant":[
        "K\u014fp\u2019o-ri",
        "K\u014fp\u2019o-burak",
        "\uac70\ud3ec\ubd80\ub77d"
    ],
    "wof:name":"Kop'o-burak",
    "wof:placetype":"locality"
},
  "geometry": {"coordinates":[124.92863,39.67971],"type":"Point"}
}