{
  "type": "Feature",
  "properties": {
    "gn:admin1_code":"0.0",
    "gn:asciiname":"Sinyon-nodongjagu",
    "gn:country_code":"KP",
    "gn:dem":227,
    "gn:feature_class":"P",
    "gn:feature_code":"PPL",
    "gn:name":"Siny\u014fn-nodongjagu",
    "gn:population":0,
    "gn:timezone":"Asia/Pyongyang",
    "iso:country":"KP",
    "name:kor_x_preferred":[
        "\uc2e0\uc5f0\ub85c\ub3d9\uc790\uad6c"
    ],
    "name:und_x_variant":[
        "Siny\u014fn-nodongjagu"
    ],
    "wof:name":"Sinyon-nodongjagu",
    "wof:placetype":"locality"
},
  "geometry": {"coordinates":[125.01667,40.41667],"type":"Point"}
}