{
  "type": "Feature",
  "properties": {
    "gn:admin1_code":"18.0",
    "gn:asciiname":"Chosal-li",
    "gn:country_code":"KP",
    "gn:dem":13,
    "gn:feature_class":"P",
    "gn:feature_code":"PPLL",
    "gn:name":"Chosal-li",
    "gn:population":0,
    "gn:timezone":"Asia/Pyongyang",
    "iso:country":"KP",
    "name:und_x_variant":[
        "Chosan-dong",
        "Chosan-ni",
        "\uc870\uc0b0\ub9ac",
        "Chosal-li"
    ],
    "wof:name":"Chosal-li",
    "wof:placetype":"locality"
},
  "geometry": {"coordinates":[130.63167000000001,42.36611],"type":"Point"}
}