{
  "type": "Feature",
  "properties": {
    "gn:admin1_code":"15.0",
    "gn:asciiname":"Wolli-dong",
    "gn:country_code":"KP",
    "gn:dem":10,
    "gn:feature_class":"P",
    "gn:feature_code":"PPL",
    "gn:name":"W\u014flli-dong",
    "gn:population":0,
    "gn:timezone":"Asia/Pyongyang",
    "iso:country":"KP",
    "name:kor_x_preferred":[
        "\uc6d4\ub9ac\ub3d9"
    ],
    "name:kor_x_variant":[
        "W\u014flli-dong"
    ],
    "wof:name":"Wolli-dong",
    "wof:placetype":"locality"
},
  "geometry": {"coordinates":[125.51694000000001,38.73694],"type":"Point"}
}