{
  "type": "Feature",
  "properties": {
    "gn:admin1_code":"3.0",
    "gn:asciiname":"Mi-dong",
    "gn:country_code":"KP",
    "gn:dem":502,
    "gn:feature_class":"P",
    "gn:feature_code":"PPL",
    "gn:name":"Mi-dong",
    "gn:population":0,
    "gn:timezone":"Asia/Pyongyang",
    "iso:country":"KP",
    "name:kor_x_preferred":[
        "\ubbf8\ub3d9"
    ],
    "wof:name":"Mi-dong",
    "wof:placetype":"locality"
},
  "geometry": {"coordinates":[126.86499999999999,39.31944],"type":"Point"}
}