{
  "type": "Feature",
  "properties": {
    "gn:admin1_code":"3.0",
    "gn:asciiname":"Toksong",
    "gn:country_code":"KP",
    "gn:dem":97,
    "gn:feature_class":"P",
    "gn:feature_code":"PPL",
    "gn:name":"T\u014fks\u014fng",
    "gn:population":0,
    "gn:timezone":"Asia/Pyongyang",
    "iso:country":"KP",
    "name:und_x_variant":[
        "T\u014fks\u014fng",
        "\ub355\uc131",
        "T\u014fks\u014fng-\u016dp"
    ],
    "wof:name":"Toksong",
    "wof:placetype":"locality"
},
  "geometry": {"coordinates":[128.27011999999999,40.31814],"type":"Point"}
}