{
  "type": "Feature",
  "properties": {
    "gn:admin1_code":"12.0",
    "gn:admin2_code":"Kangdong-gun",
    "gn:asciiname":"Changmarum",
    "gn:country_code":"KP",
    "gn:dem":133,
    "gn:feature_class":"P",
    "gn:feature_code":"PPL",
    "gn:name":"Changmar\u016dm",
    "gn:population":0,
    "gn:timezone":"Asia/Pyongyang",
    "iso:country":"KP",
    "name:kor_x_preferred":[
        "\uc7a5\ub9d0\uc74c"
    ],
    "name:und_x_variant":[
        "Changmar\u016dm",
        "Changma\u016dm",
        "Jangmareum"
    ],
    "wof:name":"Changmarum",
    "wof:placetype":"locality"
},
  "geometry": {"coordinates":[126.14566000000001,39.07802],"type":"Point"}
}