{
  "type": "Feature",
  "properties": {
    "gn:admin1_code":"18.0",
    "gn:asciiname":"Myongho",
    "gn:country_code":"KP",
    "gn:dem":27,
    "gn:feature_class":"P",
    "gn:feature_code":"PPL",
    "gn:name":"My\u014fngho",
    "gn:population":0,
    "gn:timezone":"Asia/Pyongyang",
    "iso:country":"KP",
    "name:und_x_variant":[
        "\uba85\ud638",
        "My\u014fngho",
        "Myeongho"
    ],
    "wof:name":"Myongho",
    "wof:placetype":"locality"
},
  "geometry": {"coordinates":[130.24972,42.2121],"type":"Point"}
}