{
  "type": "Feature",
  "properties": {
    "gn:admin1_code":"12.0",
    "gn:asciiname":"Soisang-dong",
    "gn:country_code":"KP",
    "gn:dem":14,
    "gn:feature_class":"P",
    "gn:feature_code":"PPL",
    "gn:name":"Soisang-dong",
    "gn:population":0,
    "gn:timezone":"Asia/Pyongyang",
    "iso:country":"KP",
    "name:kor_x_preferred":[
        "\uc18c\uc774\uc0c1\ub3d9"
    ],
    "name:und_x_variant":[
        "Soisangdong"
    ],
    "wof:name":"Soisang-dong",
    "wof:placetype":"locality"
},
  "geometry": {"coordinates":[125.62895,38.93046],"type":"Point"}
}