{
  "type": "Feature",
  "properties": {
    "gn:admin1_code":"17.0",
    "gn:asciiname":"Pangp'o",
    "gn:country_code":"KP",
    "gn:dem":493,
    "gn:feature_class":"P",
    "gn:feature_code":"PPL",
    "gn:name":"Pangp\u2019o",
    "gn:population":0,
    "gn:timezone":"Asia/Pyongyang",
    "iso:country":"KP",
    "wof:name":"Pangp'o",
    "wof:placetype":"locality"
},
  "geometry": {"coordinates":[129.61667,40.91667],"type":"Point"}
}