{
  "type": "Feature",
  "properties": {
    "gn:admin1_code":"15.0",
    "gn:admin2_code":"1869039",
    "gn:asciiname":"Sangdal-li",
    "gn:country_code":"KP",
    "gn:dem":7,
    "gn:feature_class":"P",
    "gn:feature_code":"PPL",
    "gn:name":"Sangdal-li",
    "gn:population":0,
    "gn:timezone":"Asia/Pyongyang",
    "iso:country":"KP",
    "name:und_x_variant":[
        "Sangdan-ni",
        "Sangdal-li"
    ],
    "wof:name":"Sangdal-li",
    "wof:placetype":"locality"
},
  "geometry": {"coordinates":[125.42806000000002,39.48556],"type":"Point"}
}