{
  "type": "Feature",
  "properties": {
    "gn:admin1_code":"9.0",
    "gn:asciiname":"Kanun-gol",
    "gn:country_code":"KP",
    "gn:dem":650,
    "gn:feature_class":"P",
    "gn:feature_code":"PPL",
    "gn:name":"Kan\u016dn-gol",
    "gn:population":0,
    "gn:timezone":"Asia/Pyongyang",
    "iso:country":"KP",
    "name:und_x_variant":[
        "Se-dong",
        "\uac00\ub294\uace8",
        "Kan\u016dn-gol"
    ],
    "wof:name":"Kanun-gol",
    "wof:placetype":"locality"
},
  "geometry": {"coordinates":[128.07083,38.71389],"type":"Point"}
}