{
  "type": "Feature",
  "properties": {
    "gn:admin1_code":"3.0",
    "gn:asciiname":"Hagokt'an",
    "gn:country_code":"KP",
    "gn:dem":329,
    "gn:feature_class":"P",
    "gn:feature_code":"PPL",
    "gn:name":"Hagokt\u2019an",
    "gn:population":0,
    "gn:timezone":"Asia/Pyongyang",
    "iso:country":"KP",
    "name:und_x_variant":[
        "\ud558\uace1\ud0c4",
        "Hagokt\u2019an"
    ],
    "wof:name":"Hagokt'an",
    "wof:placetype":"locality"
},
  "geometry": {"coordinates":[126.83360999999999,39.71417],"type":"Point"}
}