{
  "type": "Feature",
  "properties": {
    "gn:admin1_code":"3.0",
    "gn:asciiname":"Hwanggokchung-ch'on",
    "gn:country_code":"KP",
    "gn:dem":568,
    "gn:feature_class":"P",
    "gn:feature_code":"PPL",
    "gn:name":"Hwanggokchung-ch\u2019on",
    "gn:population":0,
    "gn:timezone":"Asia/Pyongyang",
    "iso:country":"KP",
    "name:und_x_variant":[
        "\ud669\uace1\uc911\ucd0c",
        "Hwanggokchung-ch\u2019on"
    ],
    "wof:name":"Hwanggokchung-ch'on",
    "wof:placetype":"locality"
},
  "geometry": {"coordinates":[128.61222000000001,40.74278],"type":"Point"}
}