{
  "type": "Feature",
  "properties": {
    "gn:admin1_code":"13.0",
    "gn:asciiname":"Yongjo",
    "gn:cc2":"KP",
    "gn:country_code":"KP",
    "gn:dem":637,
    "gn:feature_class":"P",
    "gn:feature_code":"PPL",
    "gn:name":"Y\u014fngj\u014f",
    "gn:population":0,
    "gn:timezone":"Asia/Pyongyang",
    "iso:country":"KP",
    "name:und_x_variant":[
        "Y\u014fngj\u014f-dong",
        "Y\u014fngj\u014f"
    ],
    "wof:name":"Yongjo",
    "wof:placetype":"locality"
},
  "geometry": {"coordinates":[127.06583000000001,41.37806],"type":"Point"}
}