{
  "type": "Feature",
  "properties": {
    "gn:admin1_code":"6.0",
    "gn:asciiname":"Chunghak-tong",
    "gn:country_code":"KP",
    "gn:dem":105,
    "gn:feature_class":"P",
    "gn:feature_code":"PPL",
    "gn:name":"Chunghak-tong",
    "gn:population":0,
    "gn:timezone":"Asia/Pyongyang",
    "iso:country":"KP",
    "name:kor_x_preferred":[
        "\uc911\ud559\ub3d9"
    ],
    "wof:name":"Chunghak-tong",
    "wof:placetype":"locality"
},
  "geometry": {"coordinates":[125.76972000000001,38.15333],"type":"Point"}
}