{
  "type": "Feature",
  "properties": {
    "gn:admin1_code":"11.0",
    "gn:asciiname":"Sangwon-dong",
    "gn:country_code":"KP",
    "gn:dem":129,
    "gn:feature_class":"P",
    "gn:feature_code":"PPL",
    "gn:name":"Sangw\u014fn-dong",
    "gn:population":0,
    "gn:timezone":"Asia/Pyongyang",
    "iso:country":"KP",
    "name:und_x_variant":[
        "\uc0c1\uc6d0\ub3d9",
        "Sangw\u014fn-ni",
        "Sangw\u014fn-dong"
    ],
    "wof:name":"Sangwon-dong",
    "wof:placetype":"locality"
},
  "geometry": {"coordinates":[125.9175,40.11139],"type":"Point"}
}