{
  "type": "Feature",
  "properties": {
    "gn:admin1_code":"9.0",
    "gn:asciiname":"Non-gol",
    "gn:country_code":"KP",
    "gn:dem":459,
    "gn:feature_class":"P",
    "gn:feature_code":"PPL",
    "gn:name":"Non-gol",
    "gn:population":0,
    "gn:timezone":"Asia/Pyongyang",
    "iso:country":"KP",
    "wof:name":"Non-gol",
    "wof:placetype":"locality"
},
  "geometry": {"coordinates":[127.96861,38.55],"type":"Point"}
}