{
  "type": "Feature",
  "properties": {
    "gn:admin1_code":"0.0",
    "gn:asciiname":"Ch'onma-ri",
    "gn:country_code":"KP",
    "gn:dem":135,
    "gn:feature_class":"P",
    "gn:feature_code":"PPL",
    "gn:name":"Ch\u2019\u014fnma-ri",
    "gn:population":0,
    "gn:timezone":"Asia/Pyongyang",
    "iso:country":"KP",
    "wof:name":"Ch'onma-ri",
    "wof:placetype":"locality"
},
  "geometry": {"coordinates":[125.61667,38.26667],"type":"Point"}
}