{
  "type": "Feature",
  "properties": {
    "gn:admin1_code":"3.0",
    "gn:admin2_code":"K\u016dmya-gun",
    "gn:asciiname":"Chinhung-ni",
    "gn:cc2":"KP",
    "gn:country_code":"KP",
    "gn:dem":6,
    "gn:feature_class":"P",
    "gn:feature_code":"PPL",
    "gn:name":"Chinh\u016dng-ni",
    "gn:population":0,
    "gn:timezone":"Asia/Pyongyang",
    "iso:country":"KP",
    "name:eng_x_preferred":[
        "Chinhung"
    ],
    "name:eng_x_variant":[
        "Chinhung-ni"
    ],
    "name:und_x_variant":[
        "Chinh\u016dn-ni",
        "Chink\u014d-ri",
        "Chinkojo",
        "Chinh\u016dng-ni",
        "\uc9c4\ud765\ub9ac"
    ],
    "wof:name":"Chinhung",
    "wof:placetype":"locality"
},
  "geometry": {"coordinates":[127.38388999999999,39.45361],"type":"Point"}
}