{
  "type": "Feature",
  "properties": {
    "gn:admin1_code":"11.0",
    "gn:asciiname":"Ch'ongjon-dong",
    "gn:country_code":"KP",
    "gn:dem":162,
    "gn:feature_class":"P",
    "gn:feature_code":"PPL",
    "gn:name":"Ch\u2019\u014fngj\u014fn-dong",
    "gn:population":0,
    "gn:timezone":"Asia/Pyongyang",
    "iso:country":"KP",
    "name:und_x_variant":[
        "\uccad\uc804\ub3d9",
        "Ch\u2019\u014fngj\u014fn-dong"
    ],
    "wof:name":"Ch'ongjon-dong",
    "wof:placetype":"locality"
},
  "geometry": {"coordinates":[125.04722,40.37528],"type":"Point"}
}