{
  "type": "Feature",
  "properties": {
    "gn:admin1_code":"3.0",
    "gn:asciiname":"Tok-kol",
    "gn:country_code":"KP",
    "gn:dem":233,
    "gn:feature_class":"P",
    "gn:feature_code":"PPL",
    "gn:name":"T\u014fk-kol",
    "gn:population":0,
    "gn:timezone":"Asia/Pyongyang",
    "iso:country":"KP",
    "name:kor_x_preferred":[
        "\ub355\uace8"
    ],
    "wof:name":"Tok-kol",
    "wof:placetype":"locality"
},
  "geometry": {"coordinates":[127.05806,39.3025],"type":"Point"}
}