{
  "type": "Feature",
  "properties": {
    "gn:admin1_code":"9.0",
    "gn:asciiname":"Chaha-gol",
    "gn:country_code":"KP",
    "gn:dem":585,
    "gn:feature_class":"P",
    "gn:feature_code":"PPL",
    "gn:name":"Chaha-gol",
    "gn:population":0,
    "gn:timezone":"Asia/Pyongyang",
    "iso:country":"KP",
    "name:kor_x_preferred":[
        "\uc790\ud558\uace8"
    ],
    "name:und_x_variant":[
        "Chaha-kol",
        "Chaha-gol"
    ],
    "wof:name":"Chaha-gol",
    "wof:placetype":"locality"
},
  "geometry": {"coordinates":[127.21250000000001,38.90333],"type":"Point"}
}