{
  "type": "Feature",
  "properties": {
    "gn:admin1_code":"3.0",
    "gn:asciiname":"Tonghung-ni",
    "gn:country_code":"KP",
    "gn:dem":30,
    "gn:feature_class":"P",
    "gn:feature_code":"PPL",
    "gn:name":"Tongh\u016dng-ni",
    "gn:population":0,
    "gn:timezone":"Asia/Pyongyang",
    "iso:country":"KP",
    "name:und_x_variant":[
        "\ub3d9\ud765\ub9ac",
        "Tongh\u016dng-ni"
    ],
    "wof:name":"Tonghung-ni",
    "wof:placetype":"locality"
},
  "geometry": {"coordinates":[127.97360999999999,40.03722],"type":"Point"}
}