{
  "type": "Feature",
  "properties": {
    "gn:admin1_code":"15.0",
    "gn:admin2_code":"1869039",
    "gn:asciiname":"Taep'yongniyung-ni",
    "gn:country_code":"KP",
    "gn:dem":23,
    "gn:feature_class":"P",
    "gn:feature_code":"PPL",
    "gn:name":"Taep\u2019y\u014fngniyung-ni",
    "gn:population":0,
    "gn:timezone":"Asia/Pyongyang",
    "iso:country":"KP",
    "wof:name":"Taep'yongniyung-ni",
    "wof:placetype":"locality"
},
  "geometry": {"coordinates":[125.55167,39.39444],"type":"Point"}
}