{
  "type": "Feature",
  "properties": {
    "gn:admin1_code":"3.0",
    "gn:asciiname":"Kumch'on-dong",
    "gn:country_code":"KP",
    "gn:dem":610,
    "gn:feature_class":"P",
    "gn:feature_code":"PPL",
    "gn:name":"K\u016dmch\u2019\u014fn-dong",
    "gn:population":0,
    "gn:timezone":"Asia/Pyongyang",
    "iso:country":"KP",
    "name:und_x_variant":[
        "\uae08\ucc9c\ub3d9",
        "K\u016dmch\u2019\u014fn-dong"
    ],
    "wof:name":"Kumch'on-dong",
    "wof:placetype":"locality"
},
  "geometry": {"coordinates":[128.92083,40.73],"type":"Point"}
}