{
  "type": "Feature",
  "properties": {
    "gn:admin1_code":"9.0",
    "gn:asciiname":"Tongha-ri",
    "gn:country_code":"KP",
    "gn:dem":190,
    "gn:feature_class":"P",
    "gn:feature_code":"PPL",
    "gn:name":"Tongha-ri",
    "gn:population":0,
    "gn:timezone":"Asia/Pyongyang",
    "iso:country":"KP",
    "name:kor_x_preferred":[
        "\ub3d9\ud558\ub9ac"
    ],
    "wof:name":"Tongha-ri",
    "wof:placetype":"locality"
},
  "geometry": {"coordinates":[127.41249999999999,38.9175],"type":"Point"}
}