{
  "type": "Feature",
  "properties": {
    "gn:admin1_code":"6.0",
    "gn:asciiname":"Polch'i-dong",
    "gn:country_code":"KP",
    "gn:dem":17,
    "gn:feature_class":"P",
    "gn:feature_code":"PPL",
    "gn:name":"P\u014flch\u2019i-dong",
    "gn:population":0,
    "gn:timezone":"Asia/Pyongyang",
    "iso:country":"KP",
    "name:und_x_variant":[
        "Nach\u2019i-dong",
        "P\u014flchae-dong",
        "\ubc8c\uce58\ub3d9",
        "P\u014flch\u2019i-dong"
    ],
    "wof:name":"Polch'i-dong",
    "wof:placetype":"locality"
},
  "geometry": {"coordinates":[124.7925,38.5325],"type":"Point"}
}