{
  "type": "Feature",
  "properties": {
    "gn:admin1_code":"7.0",
    "gn:asciiname":"Changsan-dong",
    "gn:country_code":"KP",
    "gn:dem":178,
    "gn:feature_class":"P",
    "gn:feature_code":"PPL",
    "gn:name":"Changsan-dong",
    "gn:population":0,
    "gn:timezone":"Asia/Pyongyang",
    "iso:country":"KP",
    "name:kor_x_preferred":[
        "\uc7a5\uc0b0\ub3d9"
    ],
    "wof:name":"Changsan-dong",
    "wof:placetype":"locality"
},
  "geometry": {"coordinates":[126.71722,38.74917],"type":"Point"}
}