{
  "type": "Feature",
  "properties": {
    "gn:admin1_code":"7.0",
    "gn:asciiname":"Yundu",
    "gn:country_code":"KP",
    "gn:dem":93,
    "gn:feature_class":"P",
    "gn:feature_code":"PPL",
    "gn:name":"Yundu",
    "gn:population":0,
    "gn:timezone":"Asia/Pyongyang",
    "iso:country":"KP",
    "wof:name":"Yundu",
    "wof:placetype":"locality"
},
  "geometry": {"coordinates":[126.15083,38.24778],"type":"Point"}
}