{
  "type": "Feature",
  "properties": {
    "gn:admin1_code":"11.0",
    "gn:asciiname":"Komsan-dong",
    "gn:country_code":"KP",
    "gn:dem":88,
    "gn:feature_class":"P",
    "gn:feature_code":"PPL",
    "gn:name":"K\u014fmsan-dong",
    "gn:population":0,
    "gn:timezone":"Asia/Pyongyang",
    "iso:country":"KP",
    "name:kor_x_preferred":[
        "K\u014fmsan-dong"
    ],
    "name:kor_x_variant":[
        "\uac80\uc0b0\ub3d9"
    ],
    "wof:name":"Komsan-dong",
    "wof:placetype":"locality"
},
  "geometry": {"coordinates":[125.05472,39.75917000000001],"type":"Point"}
}