{
  "type": "Feature",
  "properties": {
    "gn:admin1_code":"3.0",
    "gn:asciiname":"Ch'onggyejang",
    "gn:country_code":"KP",
    "gn:dem":148,
    "gn:feature_class":"P",
    "gn:feature_code":"PPL",
    "gn:name":"Ch\u2019\u014fnggyejang",
    "gn:population":0,
    "gn:timezone":"Asia/Pyongyang",
    "iso:country":"KP",
    "name:und_x_variant":[
        "\uccad\uacc4\uc7a5",
        "Ch\u2019\u014fnggyejang"
    ],
    "wof:name":"Ch'onggyejang",
    "wof:placetype":"locality"
},
  "geometry": {"coordinates":[128.89528000000001,40.47944],"type":"Point"}
}