{
  "type": "Feature",
  "properties": {
    "gn:admin1_code":"1.0",
    "gn:asciiname":"Madung-ni",
    "gn:country_code":"KP",
    "gn:dem":1011,
    "gn:feature_class":"P",
    "gn:feature_code":"PPL",
    "gn:name":"Mad\u016dng-ni",
    "gn:population":0,
    "gn:timezone":"Asia/Pyongyang",
    "iso:country":"KP",
    "name:kor_x_preferred":[
        "\ub9c8\ub4f1\ub9ac"
    ],
    "name:kor_x_variant":[
        "Mad\u016dng-ni"
    ],
    "wof:name":"Madung-ni",
    "wof:placetype":"locality"
},
  "geometry": {"coordinates":[127.18167,40.70972],"type":"Point"}
}