{
  "type": "Feature",
  "properties": {
    "gn:admin1_code":"15.0",
    "gn:asciiname":"Pongdong-ni",
    "gn:country_code":"KP",
    "gn:dem":320,
    "gn:feature_class":"P",
    "gn:feature_code":"PPL",
    "gn:name":"Pongd\u014fng-ni",
    "gn:population":0,
    "gn:timezone":"Asia/Pyongyang",
    "iso:country":"KP",
    "name:und_x_variant":[
        "\ubd09\ub355\ub9ac",
        "Pongd\u014fng-ni"
    ],
    "wof:name":"Pongdong-ni",
    "wof:placetype":"locality"
},
  "geometry": {"coordinates":[126.56417,39.84417],"type":"Point"}
}