{
  "type": "Feature",
  "properties": {
    "gn:admin1_code":"15.0",
    "gn:asciiname":"Hungsang-ni",
    "gn:country_code":"KP",
    "gn:dem":52,
    "gn:feature_class":"P",
    "gn:feature_code":"PPL",
    "gn:name":"H\u016dngsang-ni",
    "gn:population":0,
    "gn:timezone":"Asia/Pyongyang",
    "iso:country":"KP",
    "name:eng_x_preferred":[
        "Hungsang"
    ],
    "name:eng_x_variant":[
        "Hungsang-ni"
    ],
    "wof:name":"Hungsang",
    "wof:placetype":"locality"
},
  "geometry": {"coordinates":[125.93167,39.2775],"type":"Point"}
}