{
  "type": "Feature",
  "properties": {
    "gn:admin1_code":"15.0",
    "gn:admin2_code":"T\u014fkch\u2019\u014fn-si",
    "gn:asciiname":"Namdok-tong",
    "gn:country_code":"KP",
    "gn:dem":139,
    "gn:feature_class":"P",
    "gn:feature_code":"PPL",
    "gn:name":"Namd\u014fk-tong",
    "gn:population":0,
    "gn:timezone":"Asia/Pyongyang",
    "iso:country":"KP",
    "wof:name":"Namdok-tong",
    "wof:placetype":"locality"
},
  "geometry": {"coordinates":[126.28972,39.70694],"type":"Point"}
}