{
  "type": "Feature",
  "properties": {
    "gn:admin1_code":"1.0",
    "gn:asciiname":"Ch'agabol",
    "gn:country_code":"KP",
    "gn:dem":198,
    "gn:feature_class":"P",
    "gn:feature_code":"PPL",
    "gn:name":"Ch\u2019agab\u014fl",
    "gn:population":0,
    "gn:timezone":"Asia/Pyongyang",
    "iso:country":"KP",
    "name:und_x_variant":[
        "Ch\u2019agatt\u016dl",
        "Ch\u2019agad\u016dl",
        "\ucc28\uac00\ubc8c",
        "Ch\u2019agab\u014fl"
    ],
    "wof:name":"Ch'agabol",
    "wof:placetype":"locality"
},
  "geometry": {"coordinates":[126.29361000000002,41.18167],"type":"Point"}
}