{
  "type": "Feature",
  "properties": {
    "gn:admin1_code":"0.0",
    "gn:asciiname":"Kangbyon",
    "gn:country_code":"KP",
    "gn:dem":38,
    "gn:feature_class":"P",
    "gn:feature_code":"PPL",
    "gn:name":"Kangby\u014fn",
    "gn:population":0,
    "gn:timezone":"Asia/Pyongyang",
    "iso:country":"KP",
    "name:kor_x_preferred":[
        "\uac15\ubcc0"
    ],
    "name:und_x_variant":[
        "Kangby\u014fn"
    ],
    "wof:name":"Kangbyon",
    "wof:placetype":"locality"
},
  "geometry": {"coordinates":[125.34999999999999,37.68333],"type":"Point"}
}