{
  "type": "Feature",
  "properties": {
    "gn:admin1_code":"7.0",
    "gn:asciiname":"Kung-dong",
    "gn:country_code":"KP",
    "gn:dem":193,
    "gn:feature_class":"P",
    "gn:feature_code":"PPL",
    "gn:name":"Kung-dong",
    "gn:population":0,
    "gn:timezone":"Asia/Pyongyang",
    "iso:country":"KP",
    "wof:name":"Kung-dong",
    "wof:placetype":"locality"
},
  "geometry": {"coordinates":[126.25278,38.60083],"type":"Point"}
}