{
  "type": "Feature",
  "properties": {
    "gn:admin1_code":"17.0",
    "gn:asciiname":"Iom-ni",
    "gn:cc2":"KP",
    "gn:country_code":"KP",
    "gn:dem":28,
    "gn:feature_class":"P",
    "gn:feature_code":"PPL",
    "gn:name":"I\u014fm-ni",
    "gn:population":0,
    "gn:timezone":"Asia/Pyongyang",
    "iso:country":"KP",
    "name:eng_x_preferred":[
        "Iom"
    ],
    "name:eng_x_variant":[
        "Iom-ni"
    ],
    "name:und_x_variant":[
        "I\u014fm-dong",
        "\uc774\uc5c4\ub9ac",
        "I\u014fm-ni"
    ],
    "wof:name":"Iom",
    "wof:placetype":"locality"
},
  "geometry": {"coordinates":[129.62806,41.31389],"type":"Point"}
}