{
  "type": "Feature",
  "properties": {
    "gn:admin1_code":"13.0",
    "gn:asciiname":"Karim-ni",
    "gn:country_code":"KP",
    "gn:dem":842,
    "gn:feature_class":"P",
    "gn:feature_code":"PPL",
    "gn:name":"Karim-ni",
    "gn:population":0,
    "gn:timezone":"Asia/Pyongyang",
    "iso:country":"KP",
    "name:kor_x_preferred":[
        "\uac00\ub9bc\ub9ac"
    ],
    "wof:name":"Karim-ni",
    "wof:placetype":"locality"
},
  "geometry": {"coordinates":[128.22861,41.01167],"type":"Point"}
}