{
  "type": "Feature",
  "properties": {
    "gn:admin1_code":"3.0",
    "gn:asciiname":"P'ungso-ri",
    "gn:country_code":"KP",
    "gn:dem":111,
    "gn:feature_class":"P",
    "gn:feature_code":"PPL",
    "gn:name":"P\u2019ungs\u014f-ri",
    "gn:population":0,
    "gn:timezone":"Asia/Pyongyang",
    "iso:country":"KP",
    "name:und_x_variant":[
        "\ud48d\uc11c\ub9ac",
        "P\u2019ungs\u014f-ri"
    ],
    "wof:name":"P'ungso-ri",
    "wof:placetype":"locality"
},
  "geometry": {"coordinates":[127.83917,40.07639],"type":"Point"}
}