{
  "type": "Feature",
  "properties": {
    "gn:admin1_code":"17.0",
    "gn:asciiname":"Koulchidaech'on",
    "gn:country_code":"KP",
    "gn:dem":259,
    "gn:feature_class":"P",
    "gn:feature_code":"PPL",
    "gn:name":"K\u014f\u016dlchidaech\u2019on",
    "gn:population":0,
    "gn:timezone":"Asia/Pyongyang",
    "iso:country":"KP",
    "name:und_x_variant":[
        "\uac70\uc744\uc9c0\ub300\ucd0c",
        "K\u014f\u016dlchidaech\u2019on"
    ],
    "wof:name":"Koulchidaech'on",
    "wof:placetype":"locality"
},
  "geometry": {"coordinates":[129.93444,42.79528],"type":"Point"}
}