{
  "type": "Feature",
  "properties": {
    "gn:admin1_code":"12.0",
    "gn:asciiname":"Chonsa-dong",
    "gn:country_code":"KP",
    "gn:dem":101,
    "gn:feature_class":"P",
    "gn:feature_code":"PPL",
    "gn:name":"Chonsa-dong",
    "gn:population":0,
    "gn:timezone":"Asia/Pyongyang",
    "iso:country":"KP",
    "name:kor_x_preferred":[
        "\uc874\uc0ac\ub3d9"
    ],
    "name:und_x_variant":[
        "Jonsadong"
    ],
    "wof:name":"Chonsa-dong",
    "wof:placetype":"locality"
},
  "geometry": {"coordinates":[125.90667000000001,39.16278],"type":"Point"}
}