{
  "type": "Feature",
  "properties": {
    "gn:admin1_code":"11.0",
    "gn:asciiname":"Sokha-ri",
    "gn:country_code":"KP",
    "gn:dem":224,
    "gn:feature_class":"P",
    "gn:feature_code":"PPL",
    "gn:name":"S\u014fkha-ri",
    "gn:population":0,
    "gn:timezone":"Asia/Pyongyang",
    "iso:country":"KP",
    "name:kor_x_preferred":[
        "S\u014fkha-ri"
    ],
    "name:kor_x_variant":[
        "\uc11d\ud558\ub9ac"
    ],
    "wof:name":"Sokha-ri",
    "wof:placetype":"locality"
},
  "geometry": {"coordinates":[125.00583,39.94417],"type":"Point"}
}