{
  "type": "Feature",
  "properties": {
    "gn:admin1_code":"1.0",
    "gn:asciiname":"Sanggap",
    "gn:country_code":"KP",
    "gn:dem":127,
    "gn:feature_class":"P",
    "gn:feature_code":"PPL",
    "gn:name":"Sanggap",
    "gn:population":0,
    "gn:timezone":"Asia/Pyongyang",
    "iso:country":"KP",
    "name:und_x_variant":[
        "\uc0c1\uac11",
        "Sanggap"
    ],
    "wof:name":"Sanggap",
    "wof:placetype":"locality"
},
  "geometry": {"coordinates":[126.16889,40.08139],"type":"Point"}
}