{
  "type": "Feature",
  "properties": {
    "gn:admin1_code":"17.0",
    "gn:asciiname":"Sinbang-gol",
    "gn:country_code":"KP",
    "gn:dem":191,
    "gn:feature_class":"P",
    "gn:feature_code":"PPL",
    "gn:name":"Sinbang-gol",
    "gn:population":0,
    "gn:timezone":"Asia/Pyongyang",
    "iso:country":"KP",
    "name:und_x_variant":[
        "\uc2e0\ubc29\uace8",
        "Sinbang-gol"
    ],
    "wof:name":"Sinbang-gol",
    "wof:placetype":"locality"
},
  "geometry": {"coordinates":[130.28,42.54583],"type":"Point"}
}