{
  "type": "Feature",
  "properties": {
    "gn:admin1_code":"1.0",
    "gn:asciiname":"Hongp'och'am",
    "gn:country_code":"KP",
    "gn:dem":157,
    "gn:feature_class":"P",
    "gn:feature_code":"PPL",
    "gn:name":"Hongp\u2019och\u2019am",
    "gn:population":0,
    "gn:timezone":"Asia/Pyongyang",
    "iso:country":"KP",
    "name:und_x_variant":[
        "\ud64d\ud3ec\ucc38",
        "Hongp\u2019och\u2019am"
    ],
    "wof:name":"Hongp'och'am",
    "wof:placetype":"locality"
},
  "geometry": {"coordinates":[126.25417,40.10167],"type":"Point"}
}