{
  "type": "Feature",
  "properties": {
    "gn:admin1_code":"17.0",
    "gn:asciiname":"Umnae-dong",
    "gn:country_code":"KP",
    "gn:dem":137,
    "gn:feature_class":"P",
    "gn:feature_code":"PPL",
    "gn:name":"\u016cmnae-dong",
    "gn:population":0,
    "gn:timezone":"Asia/Pyongyang",
    "iso:country":"KP",
    "name:und_x_variant":[
        "\uc74d\ub0b4\ub3d9",
        "\u016cmnae-dong"
    ],
    "wof:name":"Umnae-dong",
    "wof:placetype":"locality"
},
  "geometry": {"coordinates":[129.46778,41.19472],"type":"Point"}
}