{
  "type": "Feature",
  "properties": {
    "gn:admin1_code":"1.0",
    "gn:asciiname":"T'am-ni",
    "gn:country_code":"KP",
    "gn:dem":173,
    "gn:feature_class":"P",
    "gn:feature_code":"PPL",
    "gn:name":"T\u2019am-ni",
    "gn:population":0,
    "gn:timezone":"Asia/Pyongyang",
    "iso:country":"KP",
    "wof:name":"T'am-ni",
    "wof:placetype":"locality"
},
  "geometry": {"coordinates":[125.87721999999999,40.84917],"type":"Point"}
}