{
  "type": "Feature",
  "properties": {
    "gn:admin1_code":"15.0",
    "gn:asciiname":"Taeojigae",
    "gn:country_code":"KP",
    "gn:dem":709,
    "gn:feature_class":"P",
    "gn:feature_code":"PPL",
    "gn:name":"Tae\u014fjigae",
    "gn:population":0,
    "gn:timezone":"Asia/Pyongyang",
    "iso:country":"KP",
    "name:und_x_variant":[
        "\ub300\uc5b4\uc9c0\uac1c",
        "Tae\u014fjigae"
    ],
    "wof:name":"Taeojigae",
    "wof:placetype":"locality"
},
  "geometry": {"coordinates":[126.98944,40.02861],"type":"Point"}
}