{
  "type": "Feature",
  "properties": {
    "gn:admin1_code":"15.0",
    "gn:asciiname":"Oeson",
    "gn:country_code":"KP",
    "gn:dem":123,
    "gn:feature_class":"P",
    "gn:feature_code":"PPL",
    "gn:name":"Oes\u014fn",
    "gn:population":0,
    "gn:timezone":"Asia/Pyongyang",
    "iso:country":"KP",
    "name:kor_x_preferred":[
        "\uc678\uc120"
    ],
    "name:kor_x_variant":[
        "Oes\u014fn"
    ],
    "wof:name":"Oeson",
    "wof:placetype":"locality"
},
  "geometry": {"coordinates":[126.46972,38.92528],"type":"Point"}
}