{
  "type": "Feature",
  "properties": {
    "gn:admin1_code":"11.0",
    "gn:asciiname":"Wolch'ol-li",
    "gn:country_code":"KP",
    "gn:dem":144,
    "gn:feature_class":"P",
    "gn:feature_code":"PPL",
    "gn:name":"W\u014flch\u2019\u014fl-li",
    "gn:population":0,
    "gn:timezone":"Asia/Pyongyang",
    "iso:country":"KP",
    "name:kor_x_preferred":[
        "W\u014flch\u2019\u014fl-li"
    ],
    "name:kor_x_variant":[
        "\uc6d4\ucc9c\ub9ac"
    ],
    "name:und_x_variant":[
        "W\u014flch\u2019\u014fn-ni"
    ],
    "wof:name":"Wolch'ol-li",
    "wof:placetype":"locality"
},
  "geometry": {"coordinates":[124.93778,39.81722],"type":"Point"}
}