{
  "type": "Feature",
  "properties": {
    "gn:admin1_code":"11.0",
    "gn:asciiname":"Sogu-dong",
    "gn:country_code":"KP",
    "gn:dem":31,
    "gn:feature_class":"P",
    "gn:feature_code":"PPL",
    "gn:name":"S\u014fgu-dong",
    "gn:population":0,
    "gn:timezone":"Asia/Pyongyang",
    "iso:country":"KP",
    "name:kor_x_preferred":[
        "\uc11c\uad6c\ub3d9"
    ],
    "name:kor_x_variant":[
        "S\u014fgu-dong"
    ],
    "wof:name":"Sogu-dong",
    "wof:placetype":"locality"
},
  "geometry": {"coordinates":[125.38916999999999,39.68083],"type":"Point"}
}