{
  "type": "Feature",
  "properties": {
    "gn:admin1_code":"7.0",
    "gn:asciiname":"Sojae-gol",
    "gn:country_code":"KP",
    "gn:dem":153,
    "gn:feature_class":"P",
    "gn:feature_code":"PPL",
    "gn:name":"S\u014fjae-gol",
    "gn:population":0,
    "gn:timezone":"Asia/Pyongyang",
    "iso:country":"KP",
    "wof:name":"Sojae-gol",
    "wof:placetype":"locality"
},
  "geometry": {"coordinates":[126.185,38.36028],"type":"Point"}
}