{
  "type": "Feature",
  "properties": {
    "gn:admin1_code":"6.0",
    "gn:asciiname":"Kwanch'ol-li",
    "gn:country_code":"KP",
    "gn:dem":83,
    "gn:feature_class":"P",
    "gn:feature_code":"PPL",
    "gn:name":"Kwanch\u2019\u014fl-li",
    "gn:population":0,
    "gn:timezone":"Asia/Pyongyang",
    "iso:country":"KP",
    "name:kor_x_preferred":[
        "\uad00\ucc9c\ub9ac"
    ],
    "name:kor_x_variant":[
        "Kwanch\u2019\u014fl-li"
    ],
    "wof:name":"Kwanch'ol-li",
    "wof:placetype":"locality"
},
  "geometry": {"coordinates":[125.25,38.36139],"type":"Point"}
}