{
  "type": "Feature",
  "properties": {
    "gn:admin1_code":"6.0",
    "gn:asciiname":"Chon-dong",
    "gn:country_code":"KP",
    "gn:dem":35,
    "gn:feature_class":"P",
    "gn:feature_code":"PPL",
    "gn:name":"Ch\u014fn-dong",
    "gn:population":0,
    "gn:timezone":"Asia/Pyongyang",
    "iso:country":"KP",
    "name:kor_x_preferred":[
        "\uc804\ub3d9"
    ],
    "name:kor_x_variant":[
        "Ch\u014fn-dong"
    ],
    "wof:name":"Chon-dong",
    "wof:placetype":"locality"
},
  "geometry": {"coordinates":[125.36056000000001,38.42778],"type":"Point"}
}