{
  "type": "Feature",
  "properties": {
    "gn:admin1_code":"1.0",
    "gn:asciiname":"Toktang-dong",
    "gn:country_code":"KP",
    "gn:dem":417,
    "gn:feature_class":"P",
    "gn:feature_code":"PPL",
    "gn:name":"T\u014fktang-dong",
    "gn:population":0,
    "gn:timezone":"Asia/Pyongyang",
    "iso:country":"KP",
    "name:und_x_variant":[
        "\ub355\ub2f9\ub3d9",
        "T\u014fktang-dong"
    ],
    "wof:name":"Toktang-dong",
    "wof:placetype":"locality"
},
  "geometry": {"coordinates":[125.89917,40.52889],"type":"Point"}
}