{
  "type": "Feature",
  "properties": {
    "gn:admin1_code":"11.0",
    "gn:asciiname":"Kump'ung-ni",
    "gn:country_code":"KP",
    "gn:dem":242,
    "gn:feature_class":"P",
    "gn:feature_code":"PPL",
    "gn:name":"K\u016dmp\u2019ung-ni",
    "gn:population":0,
    "gn:timezone":"Asia/Pyongyang",
    "iso:country":"KP",
    "name:und_x_variant":[
        "\uae08\ud48d\ub9ac",
        "K\u016dmp\u2019ung-ni"
    ],
    "wof:name":"Kump'ung-ni",
    "wof:placetype":"locality"
},
  "geometry": {"coordinates":[125.40889,40.205],"type":"Point"}
}