{
  "type": "Feature",
  "properties": {
    "gn:admin1_code":"15.0",
    "gn:admin2_code":"Pukch\u2019ang-gun",
    "gn:asciiname":"Yollyu-ri",
    "gn:country_code":"KP",
    "gn:dem":168,
    "gn:feature_class":"P",
    "gn:feature_code":"PPL",
    "gn:name":"Y\u014fllyu-ri",
    "gn:population":0,
    "gn:timezone":"Asia/Pyongyang",
    "iso:country":"KP",
    "wof:name":"Yollyu-ri",
    "wof:placetype":"locality"
},
  "geometry": {"coordinates":[126.28055999999999,39.52806],"type":"Point"}
}