{
  "type": "Feature",
  "properties": {
    "gn:admin1_code":"17.0",
    "gn:asciiname":"Yusong-dong",
    "gn:country_code":"KP",
    "gn:dem":305,
    "gn:feature_class":"P",
    "gn:feature_code":"PPL",
    "gn:name":"Yus\u014fng-dong",
    "gn:population":0,
    "gn:timezone":"Asia/Pyongyang",
    "iso:country":"KP",
    "name:und_x_variant":[
        "\uc720\uc131\ub3d9",
        "Yus\u014fng-dong"
    ],
    "wof:name":"Yusong-dong",
    "wof:placetype":"locality"
},
  "geometry": {"coordinates":[130.19138999999998,42.36806],"type":"Point"}
}