{
  "type": "Feature",
  "properties": {
    "gn:admin1_code":"17.0",
    "gn:asciiname":"Hach'on",
    "gn:country_code":"KP",
    "gn:dem":120,
    "gn:feature_class":"P",
    "gn:feature_code":"PPL",
    "gn:name":"Hach\u2019on",
    "gn:population":0,
    "gn:timezone":"Asia/Pyongyang",
    "iso:country":"KP",
    "name:und_x_variant":[
        "\ud558\ucd0c",
        "Hach\u2019on"
    ],
    "wof:name":"Hach'on",
    "wof:placetype":"locality"
},
  "geometry": {"coordinates":[129.3725,40.8725],"type":"Point"}
}