{
  "type": "Feature",
  "properties": {
    "gn:admin1_code":"11.0",
    "gn:asciiname":"Tokhung-dong",
    "gn:country_code":"KP",
    "gn:dem":51,
    "gn:feature_class":"P",
    "gn:feature_code":"PPL",
    "gn:name":"T\u014fkh\u016dng-dong",
    "gn:population":0,
    "gn:timezone":"Asia/Pyongyang",
    "iso:country":"KP",
    "name:kor_x_preferred":[
        "\ub355\ud765\ub3d9"
    ],
    "name:kor_x_variant":[
        "T\u014fkh\u016dng-dong"
    ],
    "wof:name":"Tokhung-dong",
    "wof:placetype":"locality"
},
  "geometry": {"coordinates":[125.30222000000001,39.69278],"type":"Point"}
}