{
  "type": "Feature",
  "properties": {
    "gn:admin1_code":"1.0",
    "gn:asciiname":"Ch'angp'yong-dong",
    "gn:country_code":"KP",
    "gn:dem":688,
    "gn:feature_class":"P",
    "gn:feature_code":"PPL",
    "gn:name":"Ch\u2019angp\u2019y\u014fng-dong",
    "gn:population":0,
    "gn:timezone":"Asia/Pyongyang",
    "iso:country":"KP",
    "name:und_x_variant":[
        "\ucc3d\ud3c9\ub3d9",
        "Ch\u2019angp\u2019y\u014fng-dong"
    ],
    "wof:name":"Ch'angp'yong-dong",
    "wof:placetype":"locality"
},
  "geometry": {"coordinates":[126.9525,41.14139],"type":"Point"}
}