{
  "type": "Feature",
  "properties": {
    "gn:admin1_code":"7.0",
    "gn:asciiname":"Saejol-gol",
    "gn:country_code":"KP",
    "gn:dem":336,
    "gn:feature_class":"P",
    "gn:feature_code":"PPL",
    "gn:name":"Saej\u014fl-gol",
    "gn:population":0,
    "gn:timezone":"Asia/Pyongyang",
    "iso:country":"KP",
    "name:kor_x_preferred":[
        "\uc0c8\uc808\uace8"
    ],
    "name:kor_x_variant":[
        "Saej\u014fl-gol"
    ],
    "wof:name":"Saejol-gol",
    "wof:placetype":"locality"
},
  "geometry": {"coordinates":[126.32138999999999,38.48861],"type":"Point"}
}