{
  "type": "Feature",
  "properties": {
    "gn:admin1_code":"12.0",
    "gn:asciiname":"Kajang-ni",
    "gn:country_code":"KP",
    "gn:dem":23,
    "gn:feature_class":"P",
    "gn:feature_code":"PPL",
    "gn:name":"Kajang-ni",
    "gn:population":0,
    "gn:timezone":"Asia/Pyongyang",
    "iso:country":"KP",
    "name:und_x_variant":[
        "\uac00\uc7a5\ub9ac",
        "Kajang-ni",
        "Gajangni"
    ],
    "wof:name":"Kajang-ni",
    "wof:placetype":"locality"
},
  "geometry": {"coordinates":[125.77187000000001,38.95855],"type":"Point"}
}