{
  "type": "Feature",
  "properties": {
    "gn:admin1_code":"13.0",
    "gn:asciiname":"Tongjung-ni",
    "gn:country_code":"KP",
    "gn:dem":804,
    "gn:feature_class":"P",
    "gn:feature_code":"PPL",
    "gn:name":"Tongjung-ni",
    "gn:population":0,
    "gn:timezone":"Asia/Pyongyang",
    "iso:country":"KP",
    "name:kor_x_preferred":[
        "\ub3d9\uc911\ub9ac"
    ],
    "wof:name":"Tongjung-ni",
    "wof:placetype":"locality"
},
  "geometry": {"coordinates":[128.22861,41.30556],"type":"Point"}
}