{
  "type": "Feature",
  "properties": {
    "gn:admin1_code":"7.0",
    "gn:asciiname":"Kuhyon-dong",
    "gn:country_code":"KP",
    "gn:dem":35,
    "gn:feature_class":"P",
    "gn:feature_code":"PPL",
    "gn:name":"Kuhy\u014fn-dong",
    "gn:population":0,
    "gn:timezone":"Asia/Pyongyang",
    "iso:country":"KP",
    "name:und_x_variant":[
        "\uad6c\ud604\ub3d9",
        "Kuhy\u014fn-dong"
    ],
    "wof:name":"Kuhyon-dong",
    "wof:placetype":"locality"
},
  "geometry": {"coordinates":[125.79167,38.80778],"type":"Point"}
}