{
  "type": "Feature",
  "properties": {
    "gn:admin1_code":"15.0",
    "gn:admin2_code":"1869039",
    "gn:asciiname":"Ch'osal-li",
    "gn:country_code":"KP",
    "gn:dem":17,
    "gn:feature_class":"P",
    "gn:feature_code":"PPL",
    "gn:name":"Ch\u2019\u014fsal-li",
    "gn:population":0,
    "gn:timezone":"Asia/Pyongyang",
    "iso:country":"KP",
    "name:und_x_variant":[
        "Ch\u2019\u014fsan-ni",
        "Ch\u2019\u014fsal-li"
    ],
    "wof:name":"Ch'osal-li",
    "wof:placetype":"locality"
},
  "geometry": {"coordinates":[125.50888999999999,39.40333],"type":"Point"}
}