{
  "type": "Feature",
  "properties": {
    "gn:admin1_code":"3.0",
    "gn:asciiname":"P'yongch'on",
    "gn:country_code":"KP",
    "gn:dem":146,
    "gn:feature_class":"P",
    "gn:feature_code":"PPL",
    "gn:name":"P\u2019y\u014fngch\u2019on",
    "gn:population":0,
    "gn:timezone":"Asia/Pyongyang",
    "iso:country":"KP",
    "name:und_x_variant":[
        "Chongpyong",
        "\ud3c9\ucd0c",
        "P\u2019y\u014fngch\u2019on"
    ],
    "wof:name":"P'yongch'on",
    "wof:placetype":"locality"
},
  "geometry": {"coordinates":[128.92250000000001,40.655],"type":"Point"}
}