{
  "type": "Feature",
  "properties": {
    "gn:admin1_code":"11.0",
    "gn:asciiname":"T'ohyol-li",
    "gn:country_code":"KP",
    "gn:dem":78,
    "gn:feature_class":"P",
    "gn:feature_code":"PPL",
    "gn:name":"T\u2019ohy\u014fl-li",
    "gn:population":0,
    "gn:timezone":"Asia/Pyongyang",
    "iso:country":"KP",
    "name:kor_x_preferred":[
        "T\u2019ohy\u014fl-li"
    ],
    "name:kor_x_variant":[
        "\ud1a0\ud604\ub9ac"
    ],
    "wof:name":"T'ohyol-li",
    "wof:placetype":"locality"
},
  "geometry": {"coordinates":[124.88028,39.89306],"type":"Point"}
}