{
  "type": "Feature",
  "properties": {
    "gn:admin1_code":"1.0",
    "gn:asciiname":"Habyol-tong",
    "gn:country_code":"KP",
    "gn:dem":243,
    "gn:feature_class":"P",
    "gn:feature_code":"PPL",
    "gn:name":"Haby\u014fl-tong",
    "gn:population":0,
    "gn:timezone":"Asia/Pyongyang",
    "iso:country":"KP",
    "name:und_x_variant":[
        "\ud558\ubcc4\ub3d9",
        "Haby\u014fl-tong"
    ],
    "wof:name":"Habyol-tong",
    "wof:placetype":"locality"
},
  "geometry": {"coordinates":[126.40528,40.2575],"type":"Point"}
}