{
  "type": "Feature",
  "properties": {
    "gn:admin1_code":"11.0",
    "gn:asciiname":"So-gol",
    "gn:country_code":"KP",
    "gn:dem":36,
    "gn:feature_class":"P",
    "gn:feature_code":"PPL",
    "gn:name":"S\u014f-gol",
    "gn:population":0,
    "gn:timezone":"Asia/Pyongyang",
    "iso:country":"KP",
    "name:kor_x_preferred":[
        "S\u014f-gol"
    ],
    "name:kor_x_variant":[
        "\uc11c\uace8"
    ],
    "name:und_x_variant":[
        "S\u014f-dong"
    ],
    "wof:name":"So-gol",
    "wof:placetype":"locality"
},
  "geometry": {"coordinates":[124.99028,39.75444],"type":"Point"}
}