{
  "type": "Feature",
  "properties": {
    "gn:admin1_code":"1.0",
    "gn:asciiname":"Kuryong-ni",
    "gn:country_code":"KP",
    "gn:dem":370,
    "gn:feature_class":"P",
    "gn:feature_code":"PPL",
    "gn:name":"Kuryong-ni",
    "gn:population":0,
    "gn:timezone":"Asia/Pyongyang",
    "iso:country":"KP",
    "name:eng_x_preferred":[
        "Kuryong"
    ],
    "name:eng_x_variant":[
        "Kuryong-ni"
    ],
    "name:und_x_variant":[
        "\uad6c\ub8e1\ub9ac",
        "Kuryong-ni"
    ],
    "wof:name":"Kuryong",
    "wof:placetype":"locality"
},
  "geometry": {"coordinates":[125.65722,40.43389],"type":"Point"}
}