{
  "type": "Feature",
  "properties": {
    "gn:admin1_code":"13.0",
    "gn:asciiname":"Ch'angp'yong-ni",
    "gn:country_code":"KP",
    "gn:dem":1000,
    "gn:feature_class":"P",
    "gn:feature_code":"PPL",
    "gn:name":"Ch\u2019angp\u2019y\u014fng-ni",
    "gn:population":0,
    "gn:timezone":"Asia/Pyongyang",
    "iso:country":"KP",
    "name:eng_x_preferred":[
        "Ch'angp'yong"
    ],
    "name:eng_x_variant":[
        "Ch'angp'yong-ni"
    ],
    "wof:name":"Ch'angp'yong",
    "wof:placetype":"locality"
},
  "geometry": {"coordinates":[128.30000000000001,41.28333],"type":"Point"}
}