{
  "type": "Feature",
  "properties": {
    "gn:admin1_code":"12.0",
    "gn:asciiname":"Tumugol",
    "gn:country_code":"KP",
    "gn:dem":31,
    "gn:feature_class":"P",
    "gn:feature_code":"PPL",
    "gn:name":"Tumugol",
    "gn:population":0,
    "gn:timezone":"Asia/Pyongyang",
    "iso:country":"KP",
    "name:kor_x_preferred":[
        "\ub450\ubb34\uace8"
    ],
    "name:und_x_variant":[
        "Tumukol",
        "Tumugol",
        "Dumugol"
    ],
    "wof:name":"Tumugol",
    "wof:placetype":"locality"
},
  "geometry": {"coordinates":[125.89444,39.07778],"type":"Point"}
}