{
  "type": "Feature",
  "properties": {
    "gn:admin1_code":"9.0",
    "gn:asciiname":"Komisong-ni",
    "gn:country_code":"KP",
    "gn:dem":151,
    "gn:feature_class":"P",
    "gn:feature_code":"PPL",
    "gn:name":"Komis\u014fng-ni",
    "gn:population":0,
    "gn:timezone":"Asia/Pyongyang",
    "iso:country":"KP",
    "name:eng_x_preferred":[
        "Komisong"
    ],
    "name:eng_x_variant":[
        "Komisong-ni"
    ],
    "name:kor_x_preferred":[
        "Komis\u014fng-ni"
    ],
    "wof:name":"Komisong",
    "wof:placetype":"locality"
},
  "geometry": {"coordinates":[128.28333000000001,38.45],"type":"Point"}
}