{
  "type": "Feature",
  "properties": {
    "gn:admin1_code":"13.0",
    "gn:asciiname":"Noul-li",
    "gn:country_code":"KP",
    "gn:dem":1159,
    "gn:feature_class":"P",
    "gn:feature_code":"PPL",
    "gn:name":"No\u016dl-li",
    "gn:population":0,
    "gn:timezone":"Asia/Pyongyang",
    "iso:country":"KP",
    "name:und_x_variant":[
        "No\u016dn-ni",
        "\ub178\uc740\ub9ac",
        "No\u016dl-li"
    ],
    "wof:name":"Noul-li",
    "wof:placetype":"locality"
},
  "geometry": {"coordinates":[128.18806000000001,40.64333],"type":"Point"}
}