{
  "type": "Feature",
  "properties": {
    "gn:admin1_code":"6.0",
    "gn:asciiname":"Soegwi-gol",
    "gn:country_code":"KP",
    "gn:dem":92,
    "gn:feature_class":"P",
    "gn:feature_code":"PPL",
    "gn:name":"Soegwi-gol",
    "gn:population":0,
    "gn:timezone":"Asia/Pyongyang",
    "iso:country":"KP",
    "wof:name":"Soegwi-gol",
    "wof:placetype":"locality"
},
  "geometry": {"coordinates":[125.25972,38.56028],"type":"Point"}
}