{
  "type": "Feature",
  "properties": {
    "gn:admin1_code":"3.0",
    "gn:asciiname":"Sinp'o-ri",
    "gn:country_code":"KP",
    "gn:dem":8,
    "gn:feature_class":"P",
    "gn:feature_code":"PPL",
    "gn:name":"Sinp\u2019o-ri",
    "gn:population":0,
    "gn:timezone":"Asia/Pyongyang",
    "iso:country":"KP",
    "name:und_x_variant":[
        "\uc2e0\ud3ec\ub9ac",
        "Sinp\u2019o-ri"
    ],
    "wof:name":"Sinp'o-ri",
    "wof:placetype":"locality"
},
  "geometry": {"coordinates":[127.93083,39.98639],"type":"Point"}
}