{
  "type": "Feature",
  "properties": {
    "gn:admin1_code":"11.0",
    "gn:asciiname":"Kwanha-ri",
    "gn:cc2":"KP",
    "gn:country_code":"KP",
    "gn:dem":45,
    "gn:feature_class":"P",
    "gn:feature_code":"PPL",
    "gn:name":"Kwanha-ri",
    "gn:population":0,
    "gn:timezone":"Asia/Pyongyang",
    "iso:country":"KP",
    "name:kor_x_preferred":[
        "\uad00\ud558\ub9ac"
    ],
    "name:und_x_variant":[
        "Kwanha-dong",
        "Kwanha-ri"
    ],
    "wof:name":"Kwanha-ri",
    "wof:placetype":"locality"
},
  "geometry": {"coordinates":[125.63333,39.81667],"type":"Point"}
}