{
  "type": "Feature",
  "properties": {
    "gn:admin1_code":"1.0",
    "gn:asciiname":"Tongmun-ni",
    "gn:cc2":"KP",
    "gn:country_code":"KP",
    "gn:dem":242,
    "gn:feature_class":"P",
    "gn:feature_code":"PPL",
    "gn:name":"Tongmun-ni",
    "gn:population":0,
    "gn:timezone":"Asia/Pyongyang",
    "iso:country":"KP",
    "name:eng_x_preferred":[
        "Tongmun"
    ],
    "name:eng_x_variant":[
        "Tongmun-ni"
    ],
    "name:und_x_variant":[
        "Tongmun-dong",
        "Tongmun-ni"
    ],
    "wof:name":"Tongmun",
    "wof:placetype":"locality"
},
  "geometry": {"coordinates":[126.37555999999999,40.12333],"type":"Point"}
}