{
  "type": "Feature",
  "properties": {
    "gn:admin1_code":"15.0",
    "gn:asciiname":"Ch'onp'yong-ni",
    "gn:country_code":"KP",
    "gn:dem":1167,
    "gn:feature_class":"P",
    "gn:feature_code":"PPL",
    "gn:name":"Ch\u2019\u014fnp\u2019yong-ni",
    "gn:population":0,
    "gn:timezone":"Asia/Pyongyang",
    "iso:country":"KP",
    "name:eng_x_preferred":[
        "Ch'onp'yong"
    ],
    "name:eng_x_variant":[
        "Ch'onp'yong-ni"
    ],
    "name:und_x_variant":[
        "Ch\u2019\u014fnb\u014fl-li",
        "\ucc9c\ud3c9\ub9ac",
        "Ch\u2019\u014fnp\u2019yong-ni"
    ],
    "wof:name":"Ch'onp'yong",
    "wof:placetype":"locality"
},
  "geometry": {"coordinates":[127.14444,40.14639],"type":"Point"}
}