{
  "type": "Feature",
  "properties": {
    "gn:admin1_code":"7.0",
    "gn:admin2_code":"T\u2019osan-gun",
    "gn:asciiname":"Popsu-dong",
    "gn:country_code":"KP",
    "gn:dem":118,
    "gn:feature_class":"P",
    "gn:feature_code":"PPL",
    "gn:name":"P\u014fpsu-dong",
    "gn:population":0,
    "gn:timezone":"Asia/Pyongyang",
    "iso:country":"KP",
    "wof:name":"Popsu-dong",
    "wof:placetype":"locality"
},
  "geometry": {"coordinates":[126.74583,38.24806],"type":"Point"}
}