{
  "type": "Feature",
  "properties": {
    "gn:admin1_code":"6.0",
    "gn:asciiname":"Hwap'yong-dong",
    "gn:country_code":"KP",
    "gn:dem":40,
    "gn:feature_class":"P",
    "gn:feature_code":"PPL",
    "gn:name":"Hwap\u2019y\u014fng-dong",
    "gn:population":0,
    "gn:timezone":"Asia/Pyongyang",
    "iso:country":"KP",
    "name:kor_x_preferred":[
        "\ud654\ud3c9\ub3d9"
    ],
    "name:und_x_variant":[
        "Hwap\u2019y\u014fng-dong"
    ],
    "wof:name":"Hwap'yong-dong",
    "wof:placetype":"locality"
},
  "geometry": {"coordinates":[125.44861000000002,38.48278],"type":"Point"}
}