{
  "type": "Feature",
  "properties": {
    "gn:admin1_code":"6.0",
    "gn:asciiname":"Chinam-ni",
    "gn:country_code":"KP",
    "gn:dem":138,
    "gn:feature_class":"P",
    "gn:feature_code":"PPL",
    "gn:name":"Chinam-ni",
    "gn:population":0,
    "gn:timezone":"Asia/Pyongyang",
    "iso:country":"KP",
    "name:eng_x_preferred":[
        "Chinam"
    ],
    "name:eng_x_variant":[
        "Chinam-ni"
    ],
    "name:kor_x_preferred":[
        "\uc9c4\uc554\ub9ac"
    ],
    "wof:name":"Chinam",
    "wof:placetype":"locality"
},
  "geometry": {"coordinates":[125.47611000000001,38.21472],"type":"Point"}
}