{
  "type": "Feature",
  "properties": {
    "gn:admin1_code":"15.0",
    "gn:asciiname":"Mok-tong",
    "gn:country_code":"KP",
    "gn:dem":115,
    "gn:feature_class":"P",
    "gn:feature_code":"PPL",
    "gn:name":"Mok-tong",
    "gn:population":0,
    "gn:timezone":"Asia/Pyongyang",
    "iso:country":"KP",
    "name:kor_x_preferred":[
        "\ubaa9\ub3d9"
    ],
    "wof:name":"Mok-tong",
    "wof:placetype":"locality"
},
  "geometry": {"coordinates":[126.39667,39.28778],"type":"Point"}
}