{
  "type": "Feature",
  "properties": {
    "gn:admin1_code":"1.0",
    "gn:asciiname":"Changhang-dong",
    "gn:country_code":"KP",
    "gn:dem":349,
    "gn:feature_class":"P",
    "gn:feature_code":"PPL",
    "gn:name":"Changhang-dong",
    "gn:population":0,
    "gn:timezone":"Asia/Pyongyang",
    "iso:country":"KP",
    "name:und_x_variant":[
        "\uc7a5\ud56d\ub3d9",
        "Changhang-dong"
    ],
    "wof:name":"Changhang-dong",
    "wof:placetype":"locality"
},
  "geometry": {"coordinates":[126.47139,41.19278],"type":"Point"}
}