{
  "type": "Feature",
  "properties": {
    "gn:admin1_code":"6.0",
    "gn:asciiname":"Masan",
    "gn:country_code":"KP",
    "gn:dem":153,
    "gn:feature_class":"P",
    "gn:feature_code":"PPL",
    "gn:name":"Masan",
    "gn:population":0,
    "gn:timezone":"Asia/Pyongyang",
    "iso:country":"KP",
    "name:deu_x_preferred":[
        "Masan"
    ],
    "name:fas_x_preferred":[
        "\u0645\u0627\u0633\u0627\u0646"
    ],
    "name:fra_x_preferred":[
        "Masan"
    ],
    "name:ita_x_preferred":[
        "Masan"
    ],
    "name:jpn_x_preferred":[
        "\u99ac\u5c71\u5e02"
    ],
    "name:kor_x_preferred":[
        "\ub9c8\uc0b0\uc2dc"
    ],
    "name:lav_x_preferred":[
        "Masana"
    ],
    "name:lfn_x_preferred":[
        "Masan"
    ],
    "name:nno_x_preferred":[
        "Masan"
    ],
    "name:nor_x_preferred":[
        "Masan"
    ],
    "name:pol_x_preferred":[
        "Masan"
    ],
    "name:por_x_preferred":[
        "Masan"
    ],
    "name:rus_x_preferred":[
        "\u041c\u0430\u0441\u0430\u043d"
    ],
    "name:spa_x_preferred":[
        "Masan"
    ],
    "name:swe_x_preferred":[
        "Masan"
    ],
    "name:tgl_x_preferred":[
        "Masan"
    ],
    "name:uzb_x_preferred":[
        "Masan"
    ],
    "name:vie_x_preferred":[
        "Masan"
    ],
    "name:war_x_preferred":[
        "Masan"
    ],
    "name:zho_x_preferred":[
        "\u9a6c\u5c71\u5e02"
    ],
    "wof:name":"Masan",
    "wof:placetype":"locality"
},
  "geometry": {"coordinates":[125.60306,38.2325],"type":"Point"}
}