{
  "type": "Feature",
  "properties": {
    "gn:admin1_code":"7.0",
    "gn:asciiname":"Kunjang",
    "gn:country_code":"KP",
    "gn:dem":150,
    "gn:feature_class":"P",
    "gn:feature_code":"PPL",
    "gn:name":"Kunjang",
    "gn:population":0,
    "gn:timezone":"Asia/Pyongyang",
    "iso:country":"KP",
    "wof:name":"Kunjang",
    "wof:placetype":"locality"
},
  "geometry": {"coordinates":[126.12833000000001,38.26917],"type":"Point"}
}