{
  "type": "Feature",
  "properties": {
    "gn:admin1_code":"15.0",
    "gn:asciiname":"Pango-ri",
    "gn:country_code":"KP",
    "gn:dem":41,
    "gn:feature_class":"P",
    "gn:feature_code":"PPL",
    "gn:name":"Pang\u014f-ri",
    "gn:population":0,
    "gn:timezone":"Asia/Pyongyang",
    "iso:country":"KP",
    "name:und_x_variant":[
        "\ubc29\uc5b4\ub9ac",
        "Pang\u014f-ri"
    ],
    "wof:name":"Pango-ri",
    "wof:placetype":"locality"
},
  "geometry": {"coordinates":[125.39221999999999,38.88861],"type":"Point"}
}