{
  "type": "Feature",
  "properties": {
    "gn:admin1_code":"6.0",
    "gn:asciiname":"Pulmuk-kol",
    "gn:cc2":"KP",
    "gn:country_code":"KP",
    "gn:dem":14,
    "gn:feature_class":"P",
    "gn:feature_code":"PPL",
    "gn:name":"Pulmuk-kol",
    "gn:population":0,
    "gn:timezone":"Asia/Pyongyang",
    "iso:country":"KP",
    "name:und_x_variant":[
        "P\u2019ulmu-gol",
        "Pulmuk-kol"
    ],
    "wof:name":"Pulmuk-kol",
    "wof:placetype":"locality"
},
  "geometry": {"coordinates":[126.10333,37.93389000000001],"type":"Point"}
}