{
  "type": "Feature",
  "properties": {
    "gn:admin1_code":"15.0",
    "gn:asciiname":"usgoin",
    "gn:country_code":"KP",
    "gn:dem":283,
    "gn:feature_class":"P",
    "gn:feature_code":"PPL",
    "gn:name":"\uc6c3\uace0\uc778",
    "gn:population":0,
    "gn:timezone":"Asia/Pyongyang",
    "iso:country":"KP",
    "wof:name":"usgoin",
    "wof:placetype":"locality"
},
  "geometry": {"coordinates":[126.60222,39.41944],"type":"Point"}
}