{
  "type": "Feature",
  "properties": {
    "gn:admin1_code":"15.0",
    "gn:asciiname":"Siryoul",
    "gn:country_code":"KP",
    "gn:dem":349,
    "gn:feature_class":"P",
    "gn:feature_code":"PPL",
    "gn:name":"Siry\u014ful",
    "gn:population":0,
    "gn:timezone":"Asia/Pyongyang",
    "iso:country":"KP",
    "name:und_x_variant":[
        "\uc2e4\uc5ec\uc6b8",
        "Siry\u014ful"
    ],
    "wof:name":"Siryoul",
    "wof:placetype":"locality"
},
  "geometry": {"coordinates":[126.64833,39.955],"type":"Point"}
}