{
  "type": "Feature",
  "properties": {
    "gn:admin1_code":"6.0",
    "gn:asciiname":"Kyongsa-dong",
    "gn:country_code":"KP",
    "gn:dem":175,
    "gn:feature_class":"P",
    "gn:feature_code":"PPL",
    "gn:name":"Ky\u014fngsa-dong",
    "gn:population":0,
    "gn:timezone":"Asia/Pyongyang",
    "iso:country":"KP",
    "wof:name":"Kyongsa-dong",
    "wof:placetype":"locality"
},
  "geometry": {"coordinates":[125.65582999999999,38.21361],"type":"Point"}
}