{
  "type": "Feature",
  "properties": {
    "gn:admin1_code":"15.0",
    "gn:asciiname":"Tae-dong",
    "gn:country_code":"KP",
    "gn:dem":354,
    "gn:feature_class":"P",
    "gn:feature_code":"PPL",
    "gn:name":"Tae-dong",
    "gn:population":0,
    "gn:timezone":"Asia/Pyongyang",
    "iso:country":"KP",
    "name:und_x_variant":[
        "\ub300\ub3d9",
        "Tae-dong"
    ],
    "wof:name":"Tae-dong",
    "wof:placetype":"locality"
},
  "geometry": {"coordinates":[126.63,39.16139],"type":"Point"}
}