{
  "type": "Feature",
  "properties": {
    "gn:admin1_code":"17.0",
    "gn:asciiname":"Yondae-dong",
    "gn:country_code":"KP",
    "gn:dem":343,
    "gn:feature_class":"P",
    "gn:feature_code":"PPL",
    "gn:name":"Y\u014fndae-dong",
    "gn:population":0,
    "gn:timezone":"Asia/Pyongyang",
    "iso:country":"KP",
    "name:und_x_variant":[
        "\uc5f0\ub300\ub3d9",
        "Y\u014fndae-dong"
    ],
    "wof:name":"Yondae-dong",
    "wof:placetype":"locality"
},
  "geometry": {"coordinates":[129.37693999999999,41.12278],"type":"Point"}
}