{
  "type": "Feature",
  "properties": {
    "gn:admin1_code":"17.0",
    "gn:asciiname":"Tolp'o-dong",
    "gn:country_code":"KP",
    "gn:dem":23,
    "gn:feature_class":"P",
    "gn:feature_code":"PPL",
    "gn:name":"Tolp\u2019o-dong",
    "gn:population":0,
    "gn:timezone":"Asia/Pyongyang",
    "iso:country":"KP",
    "name:und_x_variant":[
        "\ub3cc\ud3ec\ub3d9",
        "Tolp\u2019o-dong"
    ],
    "wof:name":"Tolp'o-dong",
    "wof:placetype":"locality"
},
  "geometry": {"coordinates":[130.07083,42.13083],"type":"Point"}
}