{
  "type": "Feature",
  "properties": {
    "gn:admin1_code":"15.0",
    "gn:asciiname":"Songp'yong-ni",
    "gn:country_code":"KP",
    "gn:dem":253,
    "gn:feature_class":"P",
    "gn:feature_code":"PPL",
    "gn:name":"Songp\u2019y\u014fng-ni",
    "gn:population":0,
    "gn:timezone":"Asia/Pyongyang",
    "iso:country":"KP",
    "name:eng_x_preferred":[
        "Songp'yong"
    ],
    "name:eng_x_variant":[
        "Songp'yong-ni"
    ],
    "name:und_x_variant":[
        "Sh\u014dhei-ri",
        "Sh\u014dhy\u014d-ri",
        "\uc1a1\ud3c9\ub9ac",
        "Songp\u2019y\u014fng-ni"
    ],
    "wof:name":"Songp'yong",
    "wof:placetype":"locality"
},
  "geometry": {"coordinates":[126.56139,39.90722],"type":"Point"}
}