{
  "type": "Feature",
  "properties": {
    "gn:admin1_code":"15.0",
    "gn:asciiname":"Unhung-ni",
    "gn:country_code":"KP",
    "gn:dem":26,
    "gn:feature_class":"P",
    "gn:feature_code":"PPL",
    "gn:name":"Unh\u016dng-ni",
    "gn:population":0,
    "gn:timezone":"Asia/Pyongyang",
    "iso:country":"KP",
    "name:eng_x_preferred":[
        "Unhung"
    ],
    "name:eng_x_variant":[
        "Unhung-ni"
    ],
    "name:kor_x_preferred":[
        "\uc6b4\ud765\ub9ac"
    ],
    "name:kor_x_variant":[
        "Unh\u016dng-ni"
    ],
    "wof:name":"Unhung",
    "wof:placetype":"locality"
},
  "geometry": {"coordinates":[125.63111000000001,39.58917],"type":"Point"}
}