{
  "type": "Feature",
  "properties": {
    "gn:admin1_code":"15.0",
    "gn:admin2_code":"1871865",
    "gn:asciiname":"Hangmong-ni",
    "gn:country_code":"KP",
    "gn:dem":89,
    "gn:feature_class":"P",
    "gn:feature_code":"PPL",
    "gn:name":"Hangmong-ni",
    "gn:population":0,
    "gn:timezone":"Asia/Pyongyang",
    "iso:country":"KP",
    "name:eng_x_preferred":[
        "Hangmong"
    ],
    "name:eng_x_variant":[
        "Hangmong-ni"
    ],
    "wof:name":"Hangmong",
    "wof:placetype":"locality"
},
  "geometry": {"coordinates":[125.65833000000001,39.3125],"type":"Point"}
}