{
  "type": "Feature",
  "properties": {
    "gn:admin1_code":"1.0",
    "gn:asciiname":"Yondang-ni",
    "gn:country_code":"KP",
    "gn:dem":1086,
    "gn:feature_class":"P",
    "gn:feature_code":"PPL",
    "gn:name":"Y\u014fndang-ni",
    "gn:population":0,
    "gn:timezone":"Asia/Pyongyang",
    "iso:country":"KP",
    "name:eng_x_preferred":[
        "Yondang"
    ],
    "name:eng_x_variant":[
        "Yondang-ni"
    ],
    "name:kor_x_preferred":[
        "\uc5f0\ub2f9\ub9ac"
    ],
    "name:kor_x_variant":[
        "Y\u014fndang-ni"
    ],
    "wof:name":"Yondang",
    "wof:placetype":"locality"
},
  "geometry": {"coordinates":[127.14194000000001,40.9525],"type":"Point"}
}