{
  "type": "Feature",
  "properties": {
    "gn:admin1_code":"11.0",
    "gn:asciiname":"Kwangp'yong-ni",
    "gn:country_code":"KP",
    "gn:dem":48,
    "gn:feature_class":"P",
    "gn:feature_code":"PPL",
    "gn:name":"Kwangp\u2019y\u014fng-ni",
    "gn:population":0,
    "gn:timezone":"Asia/Pyongyang",
    "iso:country":"KP",
    "name:kor_x_preferred":[
        "\uad11\ud3c9\ub9ac"
    ],
    "name:und_x_variant":[
        "Kwangp\u2019y\u014fng-ni"
    ],
    "wof:name":"Kwangp'yong-ni",
    "wof:placetype":"locality"
},
  "geometry": {"coordinates":[125.48333,39.91667],"type":"Point"}
}