{
  "type": "Feature",
  "properties": {
    "gn:admin1_code":"3.0",
    "gn:asciiname":"Sabudok",
    "gn:country_code":"KP",
    "gn:dem":303,
    "gn:feature_class":"P",
    "gn:feature_code":"PPL",
    "gn:name":"Sabud\u014fk",
    "gn:population":0,
    "gn:timezone":"Asia/Pyongyang",
    "iso:country":"KP",
    "name:und_x_variant":[
        "\uc0ac\ubd80\ub355",
        "Sabud\u014fk"
    ],
    "wof:name":"Sabudok",
    "wof:placetype":"locality"
},
  "geometry": {"coordinates":[128.93138999999999,40.625],"type":"Point"}
}