{
  "type": "Feature",
  "properties": {
    "gn:admin1_code":"17.0",
    "gn:asciiname":"Ch'angch'ol-li",
    "gn:country_code":"KP",
    "gn:dem":9,
    "gn:feature_class":"P",
    "gn:feature_code":"PPL",
    "gn:name":"Ch\u2019angch\u2019ol-li",
    "gn:population":0,
    "gn:timezone":"Asia/Pyongyang",
    "iso:country":"KP",
    "name:und_x_variant":[
        "Ch\u2019angch\u2019on-ni",
        "Ch\u2019angch\u2019on-dong",
        "\ucc3d\ucd0c\ub9ac",
        "Ch\u2019angch\u2019ol-li"
    ],
    "wof:name":"Ch'angch'ol-li",
    "wof:placetype":"locality"
},
  "geometry": {"coordinates":[129.37,40.79083],"type":"Point"}
}