{
  "type": "Feature",
  "properties": {
    "gn:admin1_code":"6.0",
    "gn:asciiname":"Kaso-dong",
    "gn:country_code":"KP",
    "gn:dem":7,
    "gn:feature_class":"P",
    "gn:feature_code":"PPL",
    "gn:name":"Kas\u014f-dong",
    "gn:population":0,
    "gn:timezone":"Asia/Pyongyang",
    "iso:country":"KP",
    "name:kor_x_preferred":[
        "\uac00\uc11c\ub3d9"
    ],
    "name:und_x_variant":[
        "Kas\u014f-dong"
    ],
    "wof:name":"Kaso-dong",
    "wof:placetype":"locality"
},
  "geometry": {"coordinates":[124.8875,38.26333],"type":"Point"}
}