{
  "type": "Feature",
  "properties": {
    "gn:admin1_code":"7.0",
    "gn:asciiname":"Sangbaek-tong",
    "gn:country_code":"KP",
    "gn:dem":69,
    "gn:feature_class":"P",
    "gn:feature_code":"PPL",
    "gn:name":"Sangbaek-tong",
    "gn:population":0,
    "gn:timezone":"Asia/Pyongyang",
    "iso:country":"KP",
    "wof:name":"Sangbaek-tong",
    "wof:placetype":"locality"
},
  "geometry": {"coordinates":[125.87860999999999,38.34389],"type":"Point"}
}