{
  "type": "Feature",
  "properties": {
    "gn:admin1_code":"12.0",
    "gn:asciiname":"Hanwang-ni",
    "gn:country_code":"KP",
    "gn:dem":35,
    "gn:feature_class":"P",
    "gn:feature_code":"PPL",
    "gn:name":"Hanwang-ni",
    "gn:population":0,
    "gn:timezone":"Asia/Pyongyang",
    "iso:country":"KP",
    "name:eng_x_preferred":[
        "Hanwang"
    ],
    "name:eng_x_variant":[
        "Hanwang-ni"
    ],
    "name:kor_x_preferred":[
        "\ud55c\uc655\ub9ac"
    ],
    "name:und_x_variant":[
        "Hanwangni"
    ],
    "wof:name":"Hanwang",
    "wof:placetype":"locality"
},
  "geometry": {"coordinates":[125.98027999999999,39.21417],"type":"Point"}
}