{
  "type": "Feature",
  "properties": {
    "gn:admin1_code":"6.0",
    "gn:admin2_code":"Yongy\u014fn-gun",
    "gn:asciiname":"Pongt'ae-ri",
    "gn:country_code":"KP",
    "gn:dem":35,
    "gn:feature_class":"P",
    "gn:feature_code":"PPL",
    "gn:name":"Pongt\u2019ae-ri",
    "gn:population":0,
    "gn:timezone":"Asia/Pyongyang",
    "iso:country":"KP",
    "name:kor_x_preferred":[
        "Pongt\u2019ae-ri"
    ],
    "name:kor_x_variant":[
        "\ubd09\ud0dc\ub9ac"
    ],
    "wof:name":"Pongt'ae-ri",
    "wof:placetype":"locality"
},
  "geometry": {"coordinates":[124.88943999999999,38.1925],"type":"Point"}
}