{
  "type": "Feature",
  "properties": {
    "gn:admin1_code":"7.0",
    "gn:asciiname":"Paengnyon'gwangsan",
    "gn:country_code":"KP",
    "gn:dem":443,
    "gn:feature_class":"P",
    "gn:feature_code":"PPL",
    "gn:name":"Paengny\u014fn\u2019gwangsan",
    "gn:population":0,
    "gn:timezone":"Asia/Pyongyang",
    "iso:country":"KP",
    "name:kor_x_preferred":[
        "\ubc31\ub828\uad11\uc0b0"
    ],
    "name:und_x_variant":[
        "Paengny\u014fn\u2019gwangsan",
        "Paengny\u014fn-Kwangsan"
    ],
    "wof:name":"Paengnyon'gwangsan",
    "wof:placetype":"locality"
},
  "geometry": {"coordinates":[126.96693999999999,38.93611],"type":"Point"}
}