{
  "type": "Feature",
  "properties": {
    "gn:admin1_code":"9.0",
    "gn:asciiname":"Toksal-li",
    "gn:country_code":"KP",
    "gn:dem":32,
    "gn:feature_class":"P",
    "gn:feature_code":"PPL",
    "gn:name":"T\u014fksal-li",
    "gn:population":0,
    "gn:timezone":"Asia/Pyongyang",
    "iso:country":"KP",
    "name:und_x_variant":[
        "T\u014fksan-ni",
        "T\u014fksal-li",
        "\ub355\uc0b0\ub9ac"
    ],
    "wof:name":"Toksal-li",
    "wof:placetype":"locality"
},
  "geometry": {"coordinates":[127.33269,39.18875],"type":"Point"}
}