{
  "type": "Feature",
  "properties": {
    "gn:admin1_code":"11.0",
    "gn:asciiname":"Songjae-ri",
    "gn:country_code":"KP",
    "gn:dem":26,
    "gn:feature_class":"P",
    "gn:feature_code":"PPL",
    "gn:name":"S\u014fngjae-ri",
    "gn:population":0,
    "gn:timezone":"Asia/Pyongyang",
    "iso:country":"KP",
    "name:und_x_variant":[
        "S\u014fngjae",
        "\uc131\uc7ac\ub9ac",
        "S\u014fngjae-ri"
    ],
    "wof:name":"Songjae-ri",
    "wof:placetype":"locality"
},
  "geometry": {"coordinates":[124.57971999999999,39.87528],"type":"Point"}
}