{
  "type": "Feature",
  "properties": {
    "gn:admin1_code":"11.0",
    "gn:asciiname":"Suha-ri",
    "gn:country_code":"KP",
    "gn:dem":92,
    "gn:feature_class":"P",
    "gn:feature_code":"PPL",
    "gn:name":"Suha-ri",
    "gn:population":0,
    "gn:timezone":"Asia/Pyongyang",
    "iso:country":"KP",
    "name:und_x_variant":[
        "\uc218\ud558\ub9ac",
        "Suha-ri"
    ],
    "wof:name":"Suha-ri",
    "wof:placetype":"locality"
},
  "geometry": {"coordinates":[124.79443999999999,40.15222],"type":"Point"}
}