{
  "type": "Feature",
  "properties": {
    "gn:admin1_code":"17.0",
    "gn:asciiname":"Koraegumi",
    "gn:cc2":"KP",
    "gn:country_code":"KP",
    "gn:dem":98,
    "gn:feature_class":"P",
    "gn:feature_code":"PPL",
    "gn:name":"Koraegumi",
    "gn:population":0,
    "gn:timezone":"Asia/Pyongyang",
    "iso:country":"KP",
    "name:kor_x_preferred":[
        "\ucf54\ub798\uad6c\ubbf8"
    ],
    "name:und_x_variant":[
        "Ky\u014fnggumi",
        "Koraegumi"
    ],
    "wof:name":"Koraegumi",
    "wof:placetype":"locality"
},
  "geometry": {"coordinates":[129.76667,41.31667],"type":"Point"}
}