{
  "type": "Feature",
  "properties": {
    "gn:admin1_code":"0.0",
    "gn:asciiname":"Yujong-ni",
    "gn:country_code":"KP",
    "gn:dem":259,
    "gn:feature_class":"P",
    "gn:feature_code":"PPL",
    "gn:name":"Yuj\u014fng-ni",
    "gn:population":0,
    "gn:timezone":"Asia/Pyongyang",
    "iso:country":"KP",
    "name:kor_x_preferred":[
        "\uc720\uc815\ub9ac"
    ],
    "name:und_x_variant":[
        "Yuj\u014fng-ni"
    ],
    "wof:name":"Yujong-ni",
    "wof:placetype":"locality"
},
  "geometry": {"coordinates":[127.21666999999999,38.31667],"type":"Point"}
}