{
  "type": "Feature",
  "properties": {
    "gn:admin1_code":"3.0",
    "gn:asciiname":"Hunggyong-ni",
    "gn:country_code":"KP",
    "gn:dem":47,
    "gn:feature_class":"P",
    "gn:feature_code":"PPL",
    "gn:name":"H\u016dnggy\u014fng-ni",
    "gn:population":0,
    "gn:timezone":"Asia/Pyongyang",
    "iso:country":"KP",
    "name:und_x_variant":[
        "H\u016dnggy\u014fng",
        "\ud765\uacbd\ub9ac",
        "H\u016dnggy\u014fng-ni"
    ],
    "wof:name":"Hunggyong-ni",
    "wof:placetype":"locality"
},
  "geometry": {"coordinates":[127.75694,39.9275],"type":"Point"}
}