{
  "type": "Feature",
  "properties": {
    "gn:admin1_code":"15.0",
    "gn:asciiname":"juamgol",
    "gn:country_code":"KP",
    "gn:dem":724,
    "gn:feature_class":"P",
    "gn:feature_code":"PPL",
    "gn:name":"\uc8fc\uc554\uace8",
    "gn:population":0,
    "gn:timezone":"Asia/Pyongyang",
    "iso:country":"KP",
    "wof:name":"juamgol",
    "wof:placetype":"locality"
},
  "geometry": {"coordinates":[126.70833,39.41417],"type":"Point"}
}