{
  "type": "Feature",
  "properties": {
    "gn:admin1_code":"17.0",
    "gn:asciiname":"Sinhung-dong",
    "gn:country_code":"KP",
    "gn:dem":79,
    "gn:feature_class":"P",
    "gn:feature_code":"PPL",
    "gn:name":"Sinh\u016dng-dong",
    "gn:population":0,
    "gn:timezone":"Asia/Pyongyang",
    "iso:country":"KP",
    "name:und_x_variant":[
        "Shink\u014f-d\u014f",
        "\uc2e0\ud765\ub3d9",
        "Sinh\u016dng-dong"
    ],
    "wof:name":"Sinhung-dong",
    "wof:placetype":"locality"
},
  "geometry": {"coordinates":[130.05528000000001,42.17833],"type":"Point"}
}