{
  "type": "Feature",
  "properties": {
    "gn:admin1_code":"13.0",
    "gn:asciiname":"Posuptogi",
    "gn:country_code":"KP",
    "gn:dem":1267,
    "gn:feature_class":"P",
    "gn:feature_code":"PPL",
    "gn:name":"Pos\u016dpt\u014fgi",
    "gn:population":0,
    "gn:timezone":"Asia/Pyongyang",
    "iso:country":"KP",
    "wof:name":"Posuptogi",
    "wof:placetype":"locality"
},
  "geometry": {"coordinates":[128.42778000000001,41.44222],"type":"Point"}
}