{
  "type": "Feature",
  "properties": {
    "gn:admin1_code":"9.0",
    "gn:asciiname":"Sirang-ni",
    "gn:country_code":"KP",
    "gn:dem":21,
    "gn:feature_class":"P",
    "gn:feature_code":"PPL",
    "gn:name":"Sirang-ni",
    "gn:population":0,
    "gn:timezone":"Asia/Pyongyang",
    "iso:country":"KP",
    "name:kor_x_preferred":[
        "\uc2dc\ub791\ub9ac"
    ],
    "wof:name":"Sirang-ni",
    "wof:placetype":"locality"
},
  "geometry": {"coordinates":[128.27417,38.62083],"type":"Point"}
}