{
  "type": "Feature",
  "properties": {
    "gn:admin1_code":"6.0",
    "gn:admin2_code":"Changp'ung-gun",
    "gn:asciiname":"Hangdong-ni",
    "gn:country_code":"KP",
    "gn:dem":122,
    "gn:feature_class":"P",
    "gn:feature_code":"PPL",
    "gn:name":"Hangdong-ni",
    "gn:population":0,
    "gn:timezone":"Asia/Pyongyang",
    "iso:country":"KP",
    "wof:name":"Hangdong-ni",
    "wof:placetype":"locality"
},
  "geometry": {"coordinates":[126.80167,38.02028],"type":"Point"}
}