{
  "type": "Feature",
  "properties": {
    "gn:admin1_code":"13.0",
    "gn:asciiname":"Talch'un-dong",
    "gn:country_code":"KP",
    "gn:dem":1256,
    "gn:feature_class":"P",
    "gn:feature_code":"PPL",
    "gn:name":"Talch\u2019un-dong",
    "gn:population":0,
    "gn:timezone":"Asia/Pyongyang",
    "iso:country":"KP",
    "name:und_x_variant":[
        "Namh\u016dng-dong",
        "Talch\u2019un-gol",
        "Talch\u2019un-dong"
    ],
    "wof:name":"Talch'un-dong",
    "wof:placetype":"locality"
},
  "geometry": {"coordinates":[128.53056000000001,41.25861],"type":"Point"}
}