{
  "type": "Feature",
  "properties": {
    "gn:admin1_code":"12.0",
    "gn:admin2_code":"Kangdong-gun",
    "gn:asciiname":"Solbak-tong",
    "gn:country_code":"KP",
    "gn:dem":145,
    "gn:feature_class":"P",
    "gn:feature_code":"PPL",
    "gn:name":"Solbak-tong",
    "gn:population":0,
    "gn:timezone":"Asia/Pyongyang",
    "iso:country":"KP",
    "name:eng_x_preferred":[
        "Solbak"
    ],
    "name:eng_x_variant":[
        "Solbak-tong"
    ],
    "name:kor_x_preferred":[
        "\uc194\ubc15\ub3d9"
    ],
    "name:und_x_variant":[
        "Solbakdong"
    ],
    "wof:name":"Solbak",
    "wof:placetype":"locality"
},
  "geometry": {"coordinates":[126.21463,39.0792],"type":"Point"}
}