{
  "type": "Feature",
  "properties": {
    "gn:admin1_code":"1.0",
    "gn:asciiname":"Chugam-dong",
    "gn:country_code":"KP",
    "gn:dem":396,
    "gn:feature_class":"P",
    "gn:feature_code":"PPL",
    "gn:name":"Chugam-dong",
    "gn:population":0,
    "gn:timezone":"Asia/Pyongyang",
    "iso:country":"KP",
    "name:und_x_variant":[
        "\uc8fd\uc554\ub3d9",
        "Chugam-dong"
    ],
    "wof:name":"Chugam-dong",
    "wof:placetype":"locality"
},
  "geometry": {"coordinates":[126.65416999999999,41.35222],"type":"Point"}
}