{
  "type": "Feature",
  "properties": {
    "gn:admin1_code":"1.0",
    "gn:asciiname":"Kumsan-dong",
    "gn:country_code":"KP",
    "gn:dem":111,
    "gn:feature_class":"P",
    "gn:feature_code":"PPL",
    "gn:name":"K\u016dmsan-dong",
    "gn:population":0,
    "gn:timezone":"Asia/Pyongyang",
    "iso:country":"KP",
    "name:und_x_variant":[
        "\uae08\uc0b0\ub3d9",
        "K\u016dmsan-dong"
    ],
    "wof:name":"Kumsan-dong",
    "wof:placetype":"locality"
},
  "geometry": {"coordinates":[126.25639,40.12111],"type":"Point"}
}