{
  "type": "Feature",
  "properties": {
    "gn:admin1_code":"6.0",
    "gn:asciiname":"Kurhae-ri",
    "gn:country_code":"KP",
    "gn:dem":6,
    "gn:feature_class":"P",
    "gn:feature_code":"PPL",
    "gn:name":"Kurhae-ri",
    "gn:population":0,
    "gn:timezone":"Asia/Pyongyang",
    "iso:country":"KP",
    "name:kor_x_preferred":[
        "\uad74\ud574\ub9ac"
    ],
    "wof:name":"Kurhae-ri",
    "wof:placetype":"locality"
},
  "geometry": {"coordinates":[125.655,38.48167],"type":"Point"}
}