{
  "type": "Feature",
  "properties": {
    "gn:admin1_code":"12.0",
    "gn:asciiname":"Ch'onggye-dong",
    "gn:country_code":"KP",
    "gn:dem":34,
    "gn:feature_class":"P",
    "gn:feature_code":"PPL",
    "gn:name":"Ch\u2019\u014fnggye-dong",
    "gn:population":0,
    "gn:timezone":"Asia/Pyongyang",
    "iso:country":"KP",
    "name:kor_x_preferred":[
        "Ch\u2019\u014fnggye-dong"
    ],
    "name:kor_x_variant":[
        "\uccad\uacc4\ub3d9"
    ],
    "name:und_x_variant":[
        "Seikei-ri",
        "Ch\u2019\u014fngge-ri",
        "Seikei",
        "Ch\u2019\u014fnggye-ri"
    ],
    "wof:name":"Ch'onggye-dong",
    "wof:placetype":"locality"
},
  "geometry": {"coordinates":[125.75384,39.09831],"type":"Point"}
}