{
  "type": "Feature",
  "properties": {
    "gn:admin1_code":"3.0",
    "gn:asciiname":"Yonbong-ni",
    "gn:country_code":"KP",
    "gn:dem":209,
    "gn:feature_class":"P",
    "gn:feature_code":"PPL",
    "gn:name":"Y\u014fnbong-ni",
    "gn:population":0,
    "gn:timezone":"Asia/Pyongyang",
    "iso:country":"KP",
    "name:und_x_variant":[
        "\uc5f0\ubd09\ub9ac",
        "Y\u014fnbong-ni"
    ],
    "wof:name":"Yonbong-ni",
    "wof:placetype":"locality"
},
  "geometry": {"coordinates":[127.94,40.16167],"type":"Point"}
}