{
  "type": "Feature",
  "properties": {
    "gn:admin1_code":"15.0",
    "gn:asciiname":"Wibang-ni",
    "gn:country_code":"KP",
    "gn:dem":24,
    "gn:feature_class":"P",
    "gn:feature_code":"PPL",
    "gn:name":"Wibang-ni",
    "gn:population":0,
    "gn:timezone":"Asia/Pyongyang",
    "iso:country":"KP",
    "name:eng_x_preferred":[
        "Wibang"
    ],
    "name:eng_x_variant":[
        "Wibang-ni"
    ],
    "name:und_x_variant":[
        "Wibu-ri",
        "Wibang-ni"
    ],
    "wof:name":"Wibang",
    "wof:placetype":"locality"
},
  "geometry": {"coordinates":[125.59361,39.09],"type":"Point"}
}