{
  "type": "Feature",
  "properties": {
    "gn:admin1_code":"1.0",
    "gn:asciiname":"Chunggalp'a",
    "gn:country_code":"KP",
    "gn:dem":157,
    "gn:feature_class":"P",
    "gn:feature_code":"PPL",
    "gn:name":"Chunggalp\u2019a",
    "gn:population":0,
    "gn:timezone":"Asia/Pyongyang",
    "iso:country":"KP",
    "name:und_x_variant":[
        "\uc911\uac08\ud30c",
        "Chunggalp\u2019a"
    ],
    "wof:name":"Chunggalp'a",
    "wof:placetype":"locality"
},
  "geometry": {"coordinates":[125.67471999999999,40.66694],"type":"Point"}
}