{
  "type": "Feature",
  "properties": {
    "gn:admin1_code":"1.0",
    "gn:asciiname":"Yangdong-ni",
    "gn:country_code":"KP",
    "gn:dem":442,
    "gn:feature_class":"P",
    "gn:feature_code":"PPL",
    "gn:name":"Yangd\u014fng-ni",
    "gn:population":0,
    "gn:timezone":"Asia/Pyongyang",
    "iso:country":"KP",
    "wof:name":"Yangdong-ni",
    "wof:placetype":"locality"
},
  "geometry": {"coordinates":[126.63249999999999,41.28778],"type":"Point"}
}