{
  "type": "Feature",
  "properties": {
    "gn:admin1_code":"0.0",
    "gn:asciiname":"Ahyon-ni",
    "gn:cc2":"KP",
    "gn:country_code":"KP",
    "gn:dem":2,
    "gn:feature_class":"P",
    "gn:feature_code":"PPL",
    "gn:name":"Ahy\u014fn-ni",
    "gn:population":0,
    "gn:timezone":"Asia/Pyongyang",
    "iso:country":"KP",
    "name:und_x_variant":[
        "S\u014fa-ri",
        "Gaken-ri",
        "Ahy\u014fn-ni"
    ],
    "wof:name":"Ahyon-ni",
    "wof:placetype":"locality"
},
  "geometry": {"coordinates":[128.28333000000001,38.73333],"type":"Point"}
}