{
  "type": "Feature",
  "properties": {
    "gn:admin1_code":"12.0",
    "gn:admin2_code":"Sangw\u014fn-gun",
    "gn:asciiname":"Utkal-gol",
    "gn:cc2":"KP",
    "gn:country_code":"KP",
    "gn:dem":37,
    "gn:feature_class":"P",
    "gn:feature_code":"PPL",
    "gn:name":"Utkal-gol",
    "gn:population":0,
    "gn:timezone":"Asia/Pyongyang",
    "iso:country":"KP",
    "name:und_x_variant":[
        "Utkal-kol",
        "Utkal-gol"
    ],
    "wof:name":"Utkal-gol",
    "wof:placetype":"locality"
},
  "geometry": {"coordinates":[126.03333000000001,38.97917],"type":"Point"}
}