{
  "type": "Feature",
  "properties": {
    "gn:admin1_code":"15.0",
    "gn:asciiname":"P'ungp'yong-dong",
    "gn:country_code":"KP",
    "gn:dem":263,
    "gn:feature_class":"P",
    "gn:feature_code":"PPL",
    "gn:name":"P\u2019ungp\u2019y\u014fng-dong",
    "gn:population":0,
    "gn:timezone":"Asia/Pyongyang",
    "iso:country":"KP",
    "name:und_x_variant":[
        "\ud48d\ud3c9\ub3d9",
        "P\u2019ungp\u2019y\u014fng-dong"
    ],
    "wof:name":"P'ungp'yong-dong",
    "wof:placetype":"locality"
},
  "geometry": {"coordinates":[126.64972,39.20083],"type":"Point"}
}