{
  "type": "Feature",
  "properties": {
    "gn:admin1_code":"1.0",
    "gn:asciiname":"Kungno-dong",
    "gn:country_code":"KP",
    "gn:dem":340,
    "gn:feature_class":"P",
    "gn:feature_code":"PPL",
    "gn:name":"Kungno-dong",
    "gn:population":0,
    "gn:timezone":"Asia/Pyongyang",
    "iso:country":"KP",
    "name:und_x_variant":[
        "\uad81\ub178\ub3d9",
        "Kungno-dong"
    ],
    "wof:name":"Kungno-dong",
    "wof:placetype":"locality"
},
  "geometry": {"coordinates":[125.81999999999999,40.37306],"type":"Point"}
}