{
  "type": "Feature",
  "properties": {
    "gn:admin1_code":"9.0",
    "gn:asciiname":"Kump'ung-ni",
    "gn:country_code":"KP",
    "gn:dem":714,
    "gn:feature_class":"P",
    "gn:feature_code":"PPL",
    "gn:name":"K\u016dmp\u2019ung-ni",
    "gn:population":0,
    "gn:timezone":"Asia/Pyongyang",
    "iso:country":"KP",
    "name:eng_x_preferred":[
        "Kump'ung"
    ],
    "name:eng_x_variant":[
        "Kump'ung-ni"
    ],
    "name:und_x_variant":[
        "\uae08\ud48d\ub9ac",
        "K\u016dmp\u2019ung-ni"
    ],
    "wof:name":"Kump'ung",
    "wof:placetype":"locality"
},
  "geometry": {"coordinates":[127.95028000000001,38.69417],"type":"Point"}
}