{
  "type": "Feature",
  "properties": {
    "gn:admin1_code":"0.0",
    "gn:asciiname":"Namsong",
    "gn:country_code":"KP",
    "gn:dem":15,
    "gn:feature_class":"P",
    "gn:feature_code":"PPL",
    "gn:name":"Namsong",
    "gn:population":0,
    "gn:timezone":"Asia/Pyongyang",
    "iso:country":"KP",
    "name:kor_x_preferred":[
        "\ub0a8\uc1a1"
    ],
    "wof:name":"Namsong",
    "wof:placetype":"locality"
},
  "geometry": {"coordinates":[124.59650000000001,39.90341],"type":"Point"}
}