{
  "type": "Feature",
  "properties": {
    "gn:admin1_code":"6.0",
    "gn:admin2_code":"1876380",
    "gn:asciiname":"Tokhyol-li",
    "gn:country_code":"KP",
    "gn:dem":24,
    "gn:feature_class":"P",
    "gn:feature_code":"PPL",
    "gn:name":"T\u014fkhy\u014fl-li",
    "gn:population":0,
    "gn:timezone":"Asia/Pyongyang",
    "iso:country":"KP",
    "name:und_x_variant":[
        "T\u014fkhy\u014fn-ni",
        "T\u014fkhy\u014fl-li"
    ],
    "wof:name":"Tokhyol-li",
    "wof:placetype":"locality"
},
  "geometry": {"coordinates":[126.455,37.87361],"type":"Point"}
}