{
  "type": "Feature",
  "properties": {
    "gn:admin1_code":"15.0",
    "gn:asciiname":"Sijon-dong",
    "gn:country_code":"KP",
    "gn:dem":209,
    "gn:feature_class":"P",
    "gn:feature_code":"PPL",
    "gn:name":"Sij\u014fn-dong",
    "gn:population":0,
    "gn:timezone":"Asia/Pyongyang",
    "iso:country":"KP",
    "name:kor_x_preferred":[
        "\uc2dc\uc804\ub3d9"
    ],
    "name:kor_x_variant":[
        "Sij\u014fn-dong"
    ],
    "wof:name":"Sijon-dong",
    "wof:placetype":"locality"
},
  "geometry": {"coordinates":[126.56889,38.99667],"type":"Point"}
}