{
  "type": "Feature",
  "properties": {
    "gn:admin1_code":"0.0",
    "gn:asciiname":"Tojimi",
    "gn:country_code":"KP",
    "gn:dem":20,
    "gn:feature_class":"P",
    "gn:feature_code":"PPL",
    "gn:name":"Tojimi",
    "gn:population":0,
    "gn:timezone":"Asia/Pyongyang",
    "iso:country":"KP",
    "name:kor_x_preferred":[
        "\ub3c4\uc9c0\ubbf8"
    ],
    "wof:name":"Tojimi",
    "wof:placetype":"locality"
},
  "geometry": {"coordinates":[125.53333000000001,38.73333],"type":"Point"}
}