{
  "type": "Feature",
  "properties": {
    "gn:admin1_code":"6.0",
    "gn:admin2_code":"P'anmun-gun",
    "gn:asciiname":"Chorangch'on",
    "gn:country_code":"KP",
    "gn:dem":13,
    "gn:feature_class":"P",
    "gn:feature_code":"PPL",
    "gn:name":"Chorangch\u2019on",
    "gn:population":0,
    "gn:timezone":"Asia/Pyongyang",
    "iso:country":"KP",
    "name:kor_x_preferred":[
        "\uc870\ub791\ucd0c"
    ],
    "name:und_x_variant":[
        "Chorangch\u2019on",
        "Chonangch\u2019on",
        "Choryang-ch\u2019on"
    ],
    "wof:name":"Chorangch'on",
    "wof:placetype":"locality"
},
  "geometry": {"coordinates":[126.54358000000001,37.80049],"type":"Point"}
}