{
  "type": "Feature",
  "properties": {
    "gn:admin1_code":"9.0",
    "gn:asciiname":"Sajamok",
    "gn:country_code":"KP",
    "gn:dem":429,
    "gn:feature_class":"P",
    "gn:feature_code":"PPL",
    "gn:name":"Sajamok",
    "gn:population":0,
    "gn:timezone":"Asia/Pyongyang",
    "iso:country":"KP",
    "wof:name":"Sajamok",
    "wof:placetype":"locality"
},
  "geometry": {"coordinates":[127.28167000000001,38.56639000000001],"type":"Point"}
}