{
  "type": "Feature",
  "properties": {
    "gn:admin1_code":"1.0",
    "gn:asciiname":"Sodang-dong",
    "gn:country_code":"KP",
    "gn:dem":224,
    "gn:feature_class":"P",
    "gn:feature_code":"PPL",
    "gn:name":"S\u014fdang-dong",
    "gn:population":0,
    "gn:timezone":"Asia/Pyongyang",
    "iso:country":"KP",
    "wof:name":"Sodang-dong",
    "wof:placetype":"locality"
},
  "geometry": {"coordinates":[125.77722,40.81972],"type":"Point"}
}