{
  "type": "Feature",
  "properties": {
    "gn:admin1_code":"17.0",
    "gn:asciiname":"Kyo-dong",
    "gn:country_code":"KP",
    "gn:dem":120,
    "gn:feature_class":"P",
    "gn:feature_code":"PPL",
    "gn:name":"Kyo-dong",
    "gn:population":0,
    "gn:timezone":"Asia/Pyongyang",
    "iso:country":"KP",
    "name:und_x_variant":[
        "Ky\u014f-d\u014f",
        "\uad50\ub3d9",
        "Kyo-dong"
    ],
    "wof:name":"Kyo-dong",
    "wof:placetype":"locality"
},
  "geometry": {"coordinates":[129.82889,41.90139],"type":"Point"}
}