{
  "type": "Feature",
  "properties": {
    "gn:admin1_code":"15.0",
    "gn:asciiname":"Yongp'o-dong",
    "gn:country_code":"KP",
    "gn:dem":297,
    "gn:feature_class":"P",
    "gn:feature_code":"PPL",
    "gn:name":"Yongp\u2019o-dong",
    "gn:population":0,
    "gn:timezone":"Asia/Pyongyang",
    "iso:country":"KP",
    "name:kor_x_preferred":[
        "\uc6a9\ud3ec\ub3d9"
    ],
    "name:kor_x_variant":[
        "Yongp\u2019o-dong"
    ],
    "name:und_x_variant":[
        "Yongp\u2019o-ni"
    ],
    "wof:name":"Yongp'o-dong",
    "wof:placetype":"locality"
},
  "geometry": {"coordinates":[126.37833000000001,39.13889],"type":"Point"}
}