{
  "type": "Feature",
  "properties": {
    "gn:admin1_code":"6.0",
    "gn:asciiname":"Paksan-dong",
    "gn:country_code":"KP",
    "gn:dem":45,
    "gn:feature_class":"P",
    "gn:feature_code":"PPL",
    "gn:name":"Paksan-dong",
    "gn:population":0,
    "gn:timezone":"Asia/Pyongyang",
    "iso:country":"KP",
    "name:und_x_variant":[
        "\ubc15\uc0b0\ub3d9",
        "Paksan-dong"
    ],
    "wof:name":"Paksan-dong",
    "wof:placetype":"locality"
},
  "geometry": {"coordinates":[125.03639,38.51722],"type":"Point"}
}