{
  "type": "Feature",
  "properties": {
    "gn:admin1_code":"1.0",
    "gn:asciiname":"Tongsan-dong",
    "gn:country_code":"KP",
    "gn:dem":273,
    "gn:feature_class":"P",
    "gn:feature_code":"PPL",
    "gn:name":"Tongsan-dong",
    "gn:population":0,
    "gn:timezone":"Asia/Pyongyang",
    "iso:country":"KP",
    "name:und_x_variant":[
        "\ub3d9\uc0b0\ub3d9",
        "Tongsan-dong"
    ],
    "wof:name":"Tongsan-dong",
    "wof:placetype":"locality"
},
  "geometry": {"coordinates":[126.35639,41.06417],"type":"Point"}
}