{
  "type": "Feature",
  "properties": {
    "gn:admin1_code":"3.0",
    "gn:asciiname":"Nagwon",
    "gn:country_code":"KP",
    "gn:dem":8,
    "gn:feature_class":"P",
    "gn:feature_code":"PPL",
    "gn:name":"Nagw\u014fn",
    "gn:population":0,
    "gn:timezone":"Asia/Pyongyang",
    "iso:country":"KP",
    "name:und_x_variant":[
        "T\u2019oejo-\u016dp",
        "Taich\u014d",
        "T\u2019oejo",
        "T\u2019oejo-dong",
        "Taiko",
        "\ub77d\uc6d0",
        "Nagw\u014fn-\u016dp",
        "Nagw\u014fn"
    ],
    "wof:name":"Nagwon",
    "wof:placetype":"locality"
},
  "geometry": {"coordinates":[127.77472,39.90361],"type":"Point"}
}