{
  "type": "Feature",
  "properties": {
    "gn:admin1_code":"9.0",
    "gn:asciiname":"Hajol-li",
    "gn:country_code":"KP",
    "gn:dem":262,
    "gn:feature_class":"P",
    "gn:feature_code":"PPL",
    "gn:name":"Haj\u014fl-li",
    "gn:population":0,
    "gn:timezone":"Asia/Pyongyang",
    "iso:country":"KP",
    "name:kor_x_preferred":[
        "\ud558\uc808\ub9ac"
    ],
    "name:kor_x_variant":[
        "Haj\u014fl-li"
    ],
    "name:und_x_variant":[
        "Hasa-ri"
    ],
    "wof:name":"Hajol-li",
    "wof:placetype":"locality"
},
  "geometry": {"coordinates":[127.405,38.90889],"type":"Point"}
}