{
  "type": "Feature",
  "properties": {
    "gn:admin1_code":"7.0",
    "gn:asciiname":"Pongch'on-dong",
    "gn:country_code":"KP",
    "gn:dem":47,
    "gn:feature_class":"P",
    "gn:feature_code":"PPL",
    "gn:name":"Pongch\u2019\u014fn-dong",
    "gn:population":0,
    "gn:timezone":"Asia/Pyongyang",
    "iso:country":"KP",
    "name:kor_x_preferred":[
        "\ubd09\ucc9c\ub3d9"
    ],
    "name:kor_x_variant":[
        "Pongch\u2019\u014fn-dong"
    ],
    "wof:name":"Pongch'on-dong",
    "wof:placetype":"locality"
},
  "geometry": {"coordinates":[126.49472,38.28611],"type":"Point"}
}