{
  "type": "Feature",
  "properties": {
    "gn:admin1_code":"9.0",
    "gn:asciiname":"Polmal",
    "gn:country_code":"KP",
    "gn:dem":116,
    "gn:feature_class":"P",
    "gn:feature_code":"PPL",
    "gn:name":"P\u014flmal",
    "gn:population":0,
    "gn:timezone":"Asia/Pyongyang",
    "iso:country":"KP",
    "wof:name":"Polmal",
    "wof:placetype":"locality"
},
  "geometry": {"coordinates":[127.03222,38.4025],"type":"Point"}
}