{
  "type": "Feature",
  "properties": {
    "gn:admin1_code":"1.0",
    "gn:asciiname":"Chik-tong",
    "gn:country_code":"KP",
    "gn:dem":865,
    "gn:feature_class":"P",
    "gn:feature_code":"PPL",
    "gn:name":"Chik-tong",
    "gn:population":0,
    "gn:timezone":"Asia/Pyongyang",
    "iso:country":"KP",
    "name:und_x_variant":[
        "\uc9c1\ub3d9",
        "Chik-tong"
    ],
    "wof:name":"Chik-tong",
    "wof:placetype":"locality"
},
  "geometry": {"coordinates":[126.89055999999999,41.07333],"type":"Point"}
}