{
  "type": "Feature",
  "properties": {
    "gn:admin1_code":"7.0",
    "gn:asciiname":"Karyoul",
    "gn:country_code":"KP",
    "gn:dem":47,
    "gn:feature_class":"P",
    "gn:feature_code":"PPL",
    "gn:name":"Kary\u014ful",
    "gn:population":0,
    "gn:timezone":"Asia/Pyongyang",
    "iso:country":"KP",
    "name:kor_x_preferred":[
        "\uac08\uc5ec\uc6b8"
    ],
    "name:kor_x_variant":[
        "Kary\u014ful"
    ],
    "wof:name":"Karyoul",
    "wof:placetype":"locality"
},
  "geometry": {"coordinates":[126.54694000000001,38.33583],"type":"Point"}
}