{
  "type": "Feature",
  "properties": {
    "gn:admin1_code":"11.0",
    "gn:asciiname":"Paep'ung-ni",
    "gn:country_code":"KP",
    "gn:dem":151,
    "gn:feature_class":"P",
    "gn:feature_code":"PPL",
    "gn:name":"Paep\u2019ung-ni",
    "gn:population":0,
    "gn:timezone":"Asia/Pyongyang",
    "iso:country":"KP",
    "name:und_x_variant":[
        "\ubc30\ud48d\ub9ac",
        "Paep\u2019ung-ni"
    ],
    "wof:name":"Paep'ung-ni",
    "wof:placetype":"locality"
},
  "geometry": {"coordinates":[125.30361000000001,40.59778],"type":"Point"}
}