{
  "type": "Feature",
  "properties": {
    "gn:admin1_code":"6.0",
    "gn:asciiname":"Tokpau",
    "gn:country_code":"KP",
    "gn:dem":60,
    "gn:feature_class":"P",
    "gn:feature_code":"PPL",
    "gn:name":"Tokpau",
    "gn:population":0,
    "gn:timezone":"Asia/Pyongyang",
    "iso:country":"KP",
    "name:und_x_variant":[
        "Tokpawi",
        "\ub3c5\ubc14\uc6b0",
        "Tokpau"
    ],
    "wof:name":"Tokpau",
    "wof:placetype":"locality"
},
  "geometry": {"coordinates":[125.39221999999999,38.18722],"type":"Point"}
}