{
  "type": "Feature",
  "properties": {
    "gn:admin1_code":"3.0",
    "gn:asciiname":"Chagunjik-kol",
    "gn:country_code":"KP",
    "gn:dem":476,
    "gn:feature_class":"P",
    "gn:feature_code":"PPL",
    "gn:name":"Chag\u016dnjik-kol",
    "gn:population":0,
    "gn:timezone":"Asia/Pyongyang",
    "iso:country":"KP",
    "name:und_x_variant":[
        "\uc791\uc740\uc9c1\uace8",
        "Chag\u016dnjik-kol"
    ],
    "wof:name":"Chagunjik-kol",
    "wof:placetype":"locality"
},
  "geometry": {"coordinates":[127.97972,40.40833],"type":"Point"}
}