{
  "type": "Feature",
  "properties": {
    "gn:admin1_code":"1.0",
    "gn:asciiname":"Puhung-dong",
    "gn:country_code":"KP",
    "gn:dem":739,
    "gn:feature_class":"P",
    "gn:feature_code":"PPL",
    "gn:name":"Puh\u016dng-dong",
    "gn:population":0,
    "gn:timezone":"Asia/Pyongyang",
    "iso:country":"KP",
    "name:und_x_variant":[
        "\ubd80\ud76b\ub3d9",
        "Puh\u016dng-dong"
    ],
    "wof:name":"Puhung-dong",
    "wof:placetype":"locality"
},
  "geometry": {"coordinates":[126.95833,41.20278],"type":"Point"}
}