{
  "type": "Feature",
  "properties": {
    "gn:admin1_code":"12.0",
    "gn:asciiname":"Sinha-dong",
    "gn:country_code":"KP",
    "gn:dem":21,
    "gn:feature_class":"P",
    "gn:feature_code":"PPL",
    "gn:name":"Sinha-dong",
    "gn:population":0,
    "gn:timezone":"Asia/Pyongyang",
    "iso:country":"KP",
    "name:kor_x_preferred":[
        "Saegae-ma\u016dl"
    ],
    "name:kor_x_variant":[
        "\uc0c8\uac1c\ub9c8\uc744"
    ],
    "name:und_x_variant":[
        "\uc2e0\ud558\ub3d9",
        "Sinha-dong",
        "Sinhadong"
    ],
    "wof:name":"Sinha-dong",
    "wof:placetype":"locality"
},
  "geometry": {"coordinates":[125.79541,38.971],"type":"Point"}
}