{
  "type": "Feature",
  "properties": {
    "gn:admin1_code":"1.0",
    "gn:asciiname":"Simnip'yong",
    "gn:country_code":"KP",
    "gn:dem":1093,
    "gn:feature_class":"P",
    "gn:feature_code":"PPL",
    "gn:name":"Simnip\u2019y\u014fng",
    "gn:population":0,
    "gn:timezone":"Asia/Pyongyang",
    "iso:country":"KP",
    "name:kor_x_preferred":[
        "\uc2ed\ub9ac\ud3c9"
    ],
    "name:kor_x_variant":[
        "Simnip\u2019y\u014fng"
    ],
    "wof:name":"Simnip'yong",
    "wof:placetype":"locality"
},
  "geometry": {"coordinates":[127.08194,40.86056],"type":"Point"}
}