{
  "type": "Feature",
  "properties": {
    "gn:admin1_code":"6.0",
    "gn:asciiname":"Ch'onma-dong",
    "gn:country_code":"KP",
    "gn:dem":83,
    "gn:feature_class":"P",
    "gn:feature_code":"PPL",
    "gn:name":"Ch\u2019\u014fnma-dong",
    "gn:population":0,
    "gn:timezone":"Asia/Pyongyang",
    "iso:country":"KP",
    "wof:name":"Ch'onma-dong",
    "wof:placetype":"locality"
},
  "geometry": {"coordinates":[125.59889,38.27583],"type":"Point"}
}