{
  "type": "Feature",
  "properties": {
    "gn:admin1_code":"11.0",
    "gn:asciiname":"Unsang-dong",
    "gn:country_code":"KP",
    "gn:dem":258,
    "gn:feature_class":"P",
    "gn:feature_code":"PPL",
    "gn:name":"Unsang-dong",
    "gn:population":0,
    "gn:timezone":"Asia/Pyongyang",
    "iso:country":"KP",
    "name:und_x_variant":[
        "\uc6b4\uc0c1\ub3d9",
        "Unsang-dong"
    ],
    "wof:name":"Unsang-dong",
    "wof:placetype":"locality"
},
  "geometry": {"coordinates":[125.16028,40.22333],"type":"Point"}
}