{
  "type": "Feature",
  "properties": {
    "gn:admin1_code":"7.0",
    "gn:asciiname":"Man-dong",
    "gn:country_code":"KP",
    "gn:dem":605,
    "gn:feature_class":"P",
    "gn:feature_code":"PPL",
    "gn:name":"Man-dong",
    "gn:population":0,
    "gn:timezone":"Asia/Pyongyang",
    "iso:country":"KP",
    "name:und_x_variant":[
        "\ub9cc\ub3d9",
        "Man-dong"
    ],
    "wof:name":"Man-dong",
    "wof:placetype":"locality"
},
  "geometry": {"coordinates":[126.67389,39.13083],"type":"Point"}
}