{
  "type": "Feature",
  "properties": {
    "gn:admin1_code":"11.0",
    "gn:asciiname":"P'anmang-ni",
    "gn:country_code":"KP",
    "gn:dem":407,
    "gn:feature_class":"P",
    "gn:feature_code":"PPL",
    "gn:name":"P\u2019anmang-ni",
    "gn:population":0,
    "gn:timezone":"Asia/Pyongyang",
    "iso:country":"KP",
    "name:eng_x_preferred":[
        "P'anmang"
    ],
    "name:eng_x_variant":[
        "P'anmang-ni"
    ],
    "name:und_x_variant":[
        "P\u2019ammang-ni",
        "\ud310\ub9c9\ub9ac",
        "P\u2019anmang-ni"
    ],
    "wof:name":"P'anmang",
    "wof:placetype":"locality"
},
  "geometry": {"coordinates":[125.56305999999999,40.56611],"type":"Point"}
}