{
  "type": "Feature",
  "properties": {
    "gn:admin1_code":"1.0",
    "gn:asciiname":"Chonp'yong-dong",
    "gn:country_code":"KP",
    "gn:dem":406,
    "gn:feature_class":"P",
    "gn:feature_code":"PPL",
    "gn:name":"Ch\u014fnp\u2019y\u014fng-dong",
    "gn:population":0,
    "gn:timezone":"Asia/Pyongyang",
    "iso:country":"KP",
    "name:und_x_variant":[
        "Senhy\u014d-d\u014d",
        "\uc804\ud3c9\ub3d9",
        "Ch\u014fnp\u2019y\u014fng-dong"
    ],
    "wof:name":"Chonp'yong-dong",
    "wof:placetype":"locality"
},
  "geometry": {"coordinates":[126.74527999999999,41.39722],"type":"Point"}
}