{
  "type": "Feature",
  "properties": {
    "gn:admin1_code":"17.0",
    "gn:asciiname":"Ch'onp'yong-dong",
    "gn:country_code":"KP",
    "gn:dem":982,
    "gn:feature_class":"P",
    "gn:feature_code":"PPL",
    "gn:name":"Ch\u2019\u014fnp\u2019y\u014fng-dong",
    "gn:population":0,
    "gn:timezone":"Asia/Pyongyang",
    "iso:country":"KP",
    "name:und_x_variant":[
        "\ucc9c\ud3c9\ub3d9",
        "Ch\u2019\u014fnp\u2019y\u014fng-dong"
    ],
    "wof:name":"Ch'onp'yong-dong",
    "wof:placetype":"locality"
},
  "geometry": {"coordinates":[129.42500000000001,41.92611],"type":"Point"}
}