{
  "type": "Feature",
  "properties": {
    "gn:admin1_code":"7.0",
    "gn:asciiname":"Samgori",
    "gn:country_code":"KP",
    "gn:dem":83,
    "gn:feature_class":"P",
    "gn:feature_code":"PPL",
    "gn:name":"Samg\u014fri",
    "gn:population":0,
    "gn:timezone":"Asia/Pyongyang",
    "iso:country":"KP",
    "name:kor_x_preferred":[
        "\uc0bc\uac70\ub9ac"
    ],
    "name:kor_x_variant":[
        "Samg\u014fri"
    ],
    "wof:name":"Samgori",
    "wof:placetype":"locality"
},
  "geometry": {"coordinates":[126.49861,38.52806],"type":"Point"}
}