{
  "type": "Feature",
  "properties": {
    "gn:admin1_code":"3.0",
    "gn:asciiname":"Chaeal-li",
    "gn:country_code":"KP",
    "gn:dem":29,
    "gn:feature_class":"P",
    "gn:feature_code":"PPL",
    "gn:name":"Chaeal-li",
    "gn:population":0,
    "gn:timezone":"Asia/Pyongyang",
    "iso:country":"KP",
    "name:und_x_variant":[
        "\uc7ac\uc548\ub9ac",
        "Chaeal-li"
    ],
    "wof:name":"Chaeal-li",
    "wof:placetype":"locality"
},
  "geometry": {"coordinates":[127.41361000000001,39.84417],"type":"Point"}
}