{
  "type": "Feature",
  "properties": {
    "gn:admin1_code":"15.0",
    "gn:asciiname":"Parambyoru",
    "gn:cc2":"KP",
    "gn:country_code":"KP",
    "gn:dem":11,
    "gn:feature_class":"P",
    "gn:feature_code":"PPL",
    "gn:name":"Paramby\u014fru",
    "gn:population":0,
    "gn:timezone":"Asia/Pyongyang",
    "iso:country":"KP",
    "name:und_x_variant":[
        "P\u2019ungy\u014fn-dong",
        "Paramby\u014fru"
    ],
    "wof:name":"Parambyoru",
    "wof:placetype":"locality"
},
  "geometry": {"coordinates":[125.49306,38.8825],"type":"Point"}
}