{
  "type": "Feature",
  "properties": {
    "gn:admin1_code":"0.0",
    "gn:asciiname":"Toltari",
    "gn:cc2":"KP",
    "gn:country_code":"KP",
    "gn:dem":40,
    "gn:feature_class":"P",
    "gn:feature_code":"PPL",
    "gn:name":"Toltari",
    "gn:population":0,
    "gn:timezone":"Asia/Pyongyang",
    "iso:country":"KP",
    "name:kor_x_preferred":[
        "\ub3cc\ud0c0\ub9ac"
    ],
    "name:und_x_variant":[
        "S\u014fkkyo",
        "Toltari"
    ],
    "wof:name":"Toltari",
    "wof:placetype":"locality"
},
  "geometry": {"coordinates":[125.16667,37.93333],"type":"Point"}
}