{
  "type": "Feature",
  "properties": {
    "gn:admin1_code":"6.0",
    "gn:asciiname":"Sinwol",
    "gn:country_code":"KP",
    "gn:dem":37,
    "gn:feature_class":"P",
    "gn:feature_code":"PPL",
    "gn:name":"Sinw\u014fl",
    "gn:population":0,
    "gn:timezone":"Asia/Pyongyang",
    "iso:country":"KP",
    "name:kor_x_preferred":[
        "Sinw\u014fl"
    ],
    "name:kor_x_variant":[
        "\uc2e0\uc6d4"
    ],
    "wof:name":"Sinwol",
    "wof:placetype":"locality"
},
  "geometry": {"coordinates":[125.64445000000001,38.37625],"type":"Point"}
}