{
  "type": "Feature",
  "properties": {
    "gn:admin1_code":"15.0",
    "gn:asciiname":"Naenam-dong",
    "gn:country_code":"KP",
    "gn:dem":942,
    "gn:feature_class":"P",
    "gn:feature_code":"PPL",
    "gn:name":"Naenam-dong",
    "gn:population":0,
    "gn:timezone":"Asia/Pyongyang",
    "iso:country":"KP",
    "name:und_x_variant":[
        "\ub0b4\ub0a8\ub3d9",
        "Naenam-dong"
    ],
    "wof:name":"Naenam-dong",
    "wof:placetype":"locality"
},
  "geometry": {"coordinates":[126.94287,40.29082],"type":"Point"}
}