{
  "type": "Feature",
  "properties": {
    "gn:admin1_code":"9.0",
    "gn:asciiname":"Norumegi",
    "gn:country_code":"KP",
    "gn:dem":157,
    "gn:feature_class":"P",
    "gn:feature_code":"PPL",
    "gn:name":"Norumegi",
    "gn:population":0,
    "gn:timezone":"Asia/Pyongyang",
    "iso:country":"KP",
    "name:kor_x_preferred":[
        "\ub178\ub8e8\uba54\uae30"
    ],
    "wof:name":"Norumegi",
    "wof:placetype":"locality"
},
  "geometry": {"coordinates":[126.84999999999999,38.53917],"type":"Point"}
}