{
  "type": "Feature",
  "properties": {
    "gn:admin1_code":"3.0",
    "gn:admin2_code":"H\u014fch'\u014fn-gun",
    "gn:asciiname":"Samal-tong",
    "gn:country_code":"KP",
    "gn:dem":762,
    "gn:feature_class":"P",
    "gn:feature_code":"PPL",
    "gn:name":"Samal-tong",
    "gn:population":0,
    "gn:timezone":"Asia/Pyongyang",
    "iso:country":"KP",
    "name:eng_x_preferred":[
        "Samal"
    ],
    "name:eng_x_variant":[
        "Samal-tong"
    ],
    "name:und_x_variant":[
        "Sama-dong",
        "\uc0ac\ub9d0\ub3d9",
        "Samal-tong"
    ],
    "wof:name":"Samal",
    "wof:placetype":"locality"
},
  "geometry": {"coordinates":[128.72971999999999,40.76333],"type":"Point"}
}