{
  "type": "Feature",
  "properties": {
    "gn:admin1_code":"11.0",
    "gn:asciiname":"Sae-gol",
    "gn:country_code":"KP",
    "gn:dem":28,
    "gn:feature_class":"P",
    "gn:feature_code":"PPL",
    "gn:name":"Sae-gol",
    "gn:population":0,
    "gn:timezone":"Asia/Pyongyang",
    "iso:country":"KP",
    "name:kor_x_preferred":[
        "\uc0db\uace8"
    ],
    "name:kor_x_variant":[
        "\uc0c8\uace8",
        "\uc0ac\uc774\uace8"
    ],
    "name:und_x_variant":[
        "Saek-kol",
        "Sae-gol",
        "Sai-gol"
    ],
    "wof:name":"Sae-gol",
    "wof:placetype":"locality"
},
  "geometry": {"coordinates":[124.96666999999999,39.71389],"type":"Point"}
}