{
  "type": "Feature",
  "properties": {
    "gn:admin1_code":"3.0",
    "gn:asciiname":"Kaeyonmal",
    "gn:country_code":"KP",
    "gn:dem":23,
    "gn:feature_class":"P",
    "gn:feature_code":"PPL",
    "gn:name":"Kaey\u014fnmal",
    "gn:population":0,
    "gn:timezone":"Asia/Pyongyang",
    "iso:country":"KP",
    "name:und_x_variant":[
        "\uac1c\uc5f0\ub9d0",
        "Kaey\u014fnmal"
    ],
    "wof:name":"Kaeyonmal",
    "wof:placetype":"locality"
},
  "geometry": {"coordinates":[127.28583,39.55944],"type":"Point"}
}