{
  "type": "Feature",
  "properties": {
    "gn:admin1_code":"6.0",
    "gn:asciiname":"Saet'o",
    "gn:country_code":"KP",
    "gn:dem":72,
    "gn:feature_class":"P",
    "gn:feature_code":"PPL",
    "gn:name":"Saet\u2019\u014f",
    "gn:population":0,
    "gn:timezone":"Asia/Pyongyang",
    "iso:country":"KP",
    "name:und_x_variant":[
        "\uc0c8\ud130",
        "Saet\u2019\u014f"
    ],
    "wof:name":"Saet'o",
    "wof:placetype":"locality"
},
  "geometry": {"coordinates":[125.37888999999998,38.19222],"type":"Point"}
}