{
  "type": "Feature",
  "properties": {
    "gn:admin1_code":"3.0",
    "gn:asciiname":"Yujommal",
    "gn:country_code":"KP",
    "gn:dem":58,
    "gn:feature_class":"P",
    "gn:feature_code":"PPL",
    "gn:name":"Yuj\u014fmmal",
    "gn:population":0,
    "gn:timezone":"Asia/Pyongyang",
    "iso:country":"KP",
    "name:und_x_variant":[
        "\uc720\uc810\ub9d0",
        "Yuj\u014fmmal"
    ],
    "wof:name":"Yujommal",
    "wof:placetype":"locality"
},
  "geometry": {"coordinates":[127.20139,39.51333],"type":"Point"}
}