{
  "type": "Feature",
  "properties": {
    "gn:admin1_code":"11.0",
    "gn:asciiname":"Paegunch'am",
    "gn:country_code":"KP",
    "gn:dem":126,
    "gn:feature_class":"P",
    "gn:feature_code":"PPL",
    "gn:name":"Paegunch\u2019am",
    "gn:population":0,
    "gn:timezone":"Asia/Pyongyang",
    "iso:country":"KP",
    "name:und_x_variant":[
        "\ubc31\uc6b4\ucc38"
    ],
    "wof:name":"Paegunch'am",
    "wof:placetype":"locality"
},
  "geometry": {"coordinates":[126.21389000000001,40.05611],"type":"Point"}
}