{
  "type": "Feature",
  "properties": {
    "gn:admin1_code":"3.0",
    "gn:asciiname":"K'un-gol",
    "gn:country_code":"KP",
    "gn:dem":55,
    "gn:feature_class":"P",
    "gn:feature_code":"PPL",
    "gn:name":"K\u2019\u016dn-gol",
    "gn:population":0,
    "gn:timezone":"Asia/Pyongyang",
    "iso:country":"KP",
    "name:und_x_variant":[
        "\ud070\uace8",
        "K\u2019\u016dn-gol"
    ],
    "wof:name":"K'un-gol",
    "wof:placetype":"locality"
},
  "geometry": {"coordinates":[128.78778,40.40833],"type":"Point"}
}