{
  "type": "Feature",
  "properties": {
    "gn:admin1_code":"1.0",
    "gn:asciiname":"Kodang-dong",
    "gn:country_code":"KP",
    "gn:dem":373,
    "gn:feature_class":"P",
    "gn:feature_code":"PPL",
    "gn:name":"Kodang-dong",
    "gn:population":0,
    "gn:timezone":"Asia/Pyongyang",
    "iso:country":"KP",
    "name:und_x_variant":[
        "\uace0\ub2f9\ub3d9",
        "Kodang-dong"
    ],
    "wof:name":"Kodang-dong",
    "wof:placetype":"locality"
},
  "geometry": {"coordinates":[126.59222,41.01],"type":"Point"}
}