{
  "type": "Feature",
  "properties": {
    "gn:admin1_code":"3.0",
    "gn:asciiname":"Nojol-li",
    "gn:country_code":"KP",
    "gn:dem":192,
    "gn:feature_class":"P",
    "gn:feature_code":"PPL",
    "gn:name":"Noj\u014fl-li",
    "gn:population":0,
    "gn:timezone":"Asia/Pyongyang",
    "iso:country":"KP",
    "name:und_x_variant":[
        "Noj\u014fn-ni",
        "Noj\u014fl-li"
    ],
    "wof:name":"Nojol-li",
    "wof:placetype":"locality"
},
  "geometry": {"coordinates":[127.24083,39.85944],"type":"Point"}
}