{
  "type": "Feature",
  "properties": {
    "gn:admin1_code":"6.0",
    "gn:asciiname":"Taebang-dong",
    "gn:country_code":"KP",
    "gn:dem":106,
    "gn:feature_class":"P",
    "gn:feature_code":"PPL",
    "gn:name":"Taebang-dong",
    "gn:population":0,
    "gn:timezone":"Asia/Pyongyang",
    "iso:country":"KP",
    "name:kor_x_preferred":[
        "\ub300\ubc29\ub3d9"
    ],
    "wof:name":"Taebang-dong",
    "wof:placetype":"locality"
},
  "geometry": {"coordinates":[126.09083,38.06639000000001],"type":"Point"}
}