{
  "type": "Feature",
  "properties": {
    "gn:admin1_code":"15.0",
    "gn:asciiname":"P'ilmo-ri",
    "gn:country_code":"KP",
    "gn:dem":51,
    "gn:feature_class":"P",
    "gn:feature_code":"PPL",
    "gn:name":"P\u2019ilmo-ri",
    "gn:population":0,
    "gn:timezone":"Asia/Pyongyang",
    "iso:country":"KP",
    "wof:name":"P'ilmo-ri",
    "wof:placetype":"locality"
},
  "geometry": {"coordinates":[125.43083,38.91194],"type":"Point"}
}