{
  "type": "Feature",
  "properties": {
    "gn:admin1_code":"3.0",
    "gn:asciiname":"Chongdong-ni",
    "gn:country_code":"KP",
    "gn:dem":227,
    "gn:feature_class":"P",
    "gn:feature_code":"PPL",
    "gn:name":"Ch\u014fngdong-ni",
    "gn:population":0,
    "gn:timezone":"Asia/Pyongyang",
    "iso:country":"KP",
    "name:und_x_variant":[
        "Teid\u014d-ri",
        "Ch\u014fngdong-ni",
        "\uccad\ub3d9\ub9ac"
    ],
    "wof:name":"Chongdong-ni",
    "wof:placetype":"locality"
},
  "geometry": {"coordinates":[128.61106999999998,40.45191],"type":"Point"}
}