{
  "type": "Feature",
  "properties": {
    "gn:admin1_code":"0.0",
    "gn:asciiname":"Kaeulgol",
    "gn:country_code":"KP",
    "gn:dem":20,
    "gn:feature_class":"P",
    "gn:feature_code":"PPL",
    "gn:name":"Kae\u016dlgol",
    "gn:population":0,
    "gn:timezone":"Asia/Pyongyang",
    "iso:country":"KP",
    "name:kor_x_preferred":[
        "\uac1c\uc744\uace8"
    ],
    "name:und_x_variant":[
        "K\u014f-dong",
        "K\u014ful-mol",
        "Kae\u016dlgol"
    ],
    "wof:name":"Kaeulgol",
    "wof:placetype":"locality"
},
  "geometry": {"coordinates":[125.25,37.98333],"type":"Point"}
}