{
  "type": "Feature",
  "properties": {
    "gn:admin1_code":"13.0",
    "gn:asciiname":"Najung-ni",
    "gn:country_code":"KP",
    "gn:dem":467,
    "gn:feature_class":"P",
    "gn:feature_code":"PPL",
    "gn:name":"Najung-ni",
    "gn:population":0,
    "gn:timezone":"Asia/Pyongyang",
    "iso:country":"KP",
    "name:kor_x_preferred":[
        "\ub098\uc8fd\ub9ac"
    ],
    "name:und_x_variant":[
        "Najuk-tong",
        "Najung-ni"
    ],
    "wof:name":"Najung-ni",
    "wof:placetype":"locality"
},
  "geometry": {"coordinates":[127.3588,41.47085],"type":"Point"}
}