{
  "type": "Feature",
  "properties": {
    "gn:admin1_code":"13.0",
    "gn:asciiname":"Tonggye-rodongjagu",
    "gn:cc2":"KP",
    "gn:country_code":"KP",
    "gn:dem":1120,
    "gn:feature_class":"P",
    "gn:feature_code":"PPL",
    "gn:name":"Tonggye-rodongjagu",
    "gn:population":0,
    "gn:timezone":"Asia/Pyongyang",
    "iso:country":"KP",
    "name:und_x_variant":[
        "Tonggye-ri",
        "Tonggye-nodongjagu",
        "Tonggye-rodongjagu",
        "\ub3d9\uacc4\ub85c\ub3d9\uc790\uad6c"
    ],
    "wof:name":"Tonggye-rodongjagu",
    "wof:placetype":"locality"
},
  "geometry": {"coordinates":[128.81416999999999,41.59139],"type":"Point"}
}