{
  "type": "Feature",
  "properties": {
    "gn:admin1_code":"11.0",
    "gn:asciiname":"Kusong-ni",
    "gn:country_code":"KP",
    "gn:dem":59,
    "gn:feature_class":"P",
    "gn:feature_code":"PPL",
    "gn:name":"Kus\u014fng-ni",
    "gn:population":0,
    "gn:timezone":"Asia/Pyongyang",
    "iso:country":"KP",
    "name:kor_x_preferred":[
        "\uad6c\uc131\ub9ac"
    ],
    "name:kor_x_variant":[
        "Kus\u014fng-ni"
    ],
    "wof:name":"Kusong-ni",
    "wof:placetype":"locality"
},
  "geometry": {"coordinates":[125.51083,39.72694],"type":"Point"}
}