{
  "type": "Feature",
  "properties": {
    "gn:admin1_code":"9.0",
    "gn:asciiname":"Changjaek-kol",
    "gn:country_code":"KP",
    "gn:dem":85,
    "gn:feature_class":"P",
    "gn:feature_code":"PPL",
    "gn:name":"Changjaek-kol",
    "gn:population":0,
    "gn:timezone":"Asia/Pyongyang",
    "iso:country":"KP",
    "wof:name":"Changjaek-kol",
    "wof:placetype":"locality"
},
  "geometry": {"coordinates":[126.90222,38.3275],"type":"Point"}
}