{
  "type": "Feature",
  "properties": {
    "gn:admin1_code":"3.0",
    "gn:asciiname":"Songsal-li",
    "gn:country_code":"KP",
    "gn:dem":13,
    "gn:feature_class":"P",
    "gn:feature_code":"PPL",
    "gn:name":"Songsal-li",
    "gn:population":0,
    "gn:timezone":"Asia/Pyongyang",
    "iso:country":"KP",
    "name:und_x_variant":[
        "Songsan-ni",
        "\uc1a1\uc0b0\ub9ac",
        "Songsal-li"
    ],
    "wof:name":"Songsal-li",
    "wof:placetype":"locality"
},
  "geometry": {"coordinates":[127.85250000000001,39.95306],"type":"Point"}
}