{
  "type": "Feature",
  "properties": {
    "gn:admin1_code":"3.0",
    "gn:asciiname":"Songgong-ni",
    "gn:country_code":"KP",
    "gn:dem":140,
    "gn:feature_class":"P",
    "gn:feature_code":"PPL",
    "gn:name":"S\u014fnggong-ni",
    "gn:population":0,
    "gn:timezone":"Asia/Pyongyang",
    "iso:country":"KP",
    "name:eng_x_preferred":[
        "Songgong"
    ],
    "name:eng_x_variant":[
        "Songgong-ni"
    ],
    "name:und_x_variant":[
        "S\u014fnggong-ni",
        "\uc131\uace1\ub9ac"
    ],
    "wof:name":"Songgong",
    "wof:placetype":"locality"
},
  "geometry": {"coordinates":[128.6711,40.39523],"type":"Point"}
}