{
  "type": "Feature",
  "properties": {
    "gn:admin1_code":"3.0",
    "gn:asciiname":"Sinp'yong-ni",
    "gn:country_code":"KP",
    "gn:dem":5,
    "gn:feature_class":"P",
    "gn:feature_code":"PPL",
    "gn:name":"Sinp\u2019y\u014fng-ni",
    "gn:population":0,
    "gn:timezone":"Asia/Pyongyang",
    "iso:country":"KP",
    "name:und_x_variant":[
        "\uc2e0\ud3c9\ub9ac",
        "Sinp\u2019y\u014fng-ni"
    ],
    "wof:name":"Sinp'yong-ni",
    "wof:placetype":"locality"
},
  "geometry": {"coordinates":[127.49388999999999,39.78194000000001],"type":"Point"}
}