{
  "type": "Feature",
  "properties": {
    "gn:admin1_code":"17.0",
    "gn:asciiname":"Chik-kol",
    "gn:cc2":"KP",
    "gn:country_code":"KP",
    "gn:dem":31,
    "gn:feature_class":"P",
    "gn:feature_code":"PPL",
    "gn:name":"Chik-kol",
    "gn:population":0,
    "gn:timezone":"Asia/Pyongyang",
    "iso:country":"KP",
    "name:und_x_variant":[
        "Chikkok",
        "\uc9c1\uace8",
        "Chik-kol"
    ],
    "wof:name":"Chik-kol",
    "wof:placetype":"locality"
},
  "geometry": {"coordinates":[129.62806,41.65944],"type":"Point"}
}