{
  "type": "Feature",
  "properties": {
    "gn:admin1_code":"15.0",
    "gn:asciiname":"Mamyong-ni",
    "gn:country_code":"KP",
    "gn:dem":45,
    "gn:feature_class":"P",
    "gn:feature_code":"PPL",
    "gn:name":"Mamy\u014fng-ni",
    "gn:population":0,
    "gn:timezone":"Asia/Pyongyang",
    "iso:country":"KP",
    "name:eng_x_preferred":[
        "Mamyong"
    ],
    "name:eng_x_variant":[
        "Mamyong-ni"
    ],
    "name:und_x_variant":[
        "\ub9c8\uba85\ub9ac",
        "Mamy\u014fng-ni"
    ],
    "wof:name":"Mamyong",
    "wof:placetype":"locality"
},
  "geometry": {"coordinates":[125.37528,38.80861],"type":"Point"}
}