{
  "type": "Feature",
  "properties": {
    "gn:admin1_code":"15.0",
    "gn:asciiname":"Kusongmal",
    "gn:country_code":"KP",
    "gn:dem":178,
    "gn:feature_class":"P",
    "gn:feature_code":"PPL",
    "gn:name":"Kus\u014fngmal",
    "gn:population":0,
    "gn:timezone":"Asia/Pyongyang",
    "iso:country":"KP",
    "name:kor_x_preferred":[
        "\uad6c\uc11d\ub9d0"
    ],
    "name:kor_x_variant":[
        "Kus\u014fngmal"
    ],
    "wof:name":"Kusongmal",
    "wof:placetype":"locality"
},
  "geometry": {"coordinates":[126.48444000000001,39.34972],"type":"Point"}
}