{
  "type": "Feature",
  "properties": {
    "gn:admin1_code":"11.0",
    "gn:asciiname":"Nae-gol",
    "gn:country_code":"KP",
    "gn:dem":36,
    "gn:feature_class":"P",
    "gn:feature_code":"PPL",
    "gn:name":"Nae-gol",
    "gn:population":0,
    "gn:timezone":"Asia/Pyongyang",
    "iso:country":"KP",
    "wof:name":"Nae-gol",
    "wof:placetype":"locality"
},
  "geometry": {"coordinates":[124.57889,40.20167],"type":"Point"}
}