{
  "type": "Feature",
  "properties": {
    "gn:admin1_code":"17.0",
    "gn:admin2_code":"2038910",
    "gn:asciiname":"Tungyon-dong",
    "gn:country_code":"KP",
    "gn:dem":925,
    "gn:feature_class":"P",
    "gn:feature_code":"PPL",
    "gn:name":"T\u016dngy\u014fn-dong",
    "gn:population":0,
    "gn:timezone":"Asia/Pyongyang",
    "iso:country":"KP",
    "wof:name":"Tungyon-dong",
    "wof:placetype":"locality"
},
  "geometry": {"coordinates":[129.12611000000001,41.85861],"type":"Point"}
}