{
  "type": "Feature",
  "properties": {
    "gn:admin1_code":"11.0",
    "gn:asciiname":"Okkae",
    "gn:country_code":"KP",
    "gn:dem":24,
    "gn:feature_class":"P",
    "gn:feature_code":"PPL",
    "gn:name":"Okkae",
    "gn:population":0,
    "gn:timezone":"Asia/Pyongyang",
    "iso:country":"KP",
    "name:kor_x_preferred":[
        "\uc625\uac1c"
    ],
    "wof:name":"Okkae",
    "wof:placetype":"locality"
},
  "geometry": {"coordinates":[125.4075,39.66833],"type":"Point"}
}