{
  "type": "Feature",
  "properties": {
    "gn:admin1_code":"6.0",
    "gn:asciiname":"Chang-ch'on",
    "gn:country_code":"KP",
    "gn:dem":162,
    "gn:feature_class":"P",
    "gn:feature_code":"PPL",
    "gn:name":"Chang-ch\u2019on",
    "gn:population":0,
    "gn:timezone":"Asia/Pyongyang",
    "iso:country":"KP",
    "name:kor_x_preferred":[
        "\uc7a5\ucd0c"
    ],
    "name:und_x_variant":[
        "Chang-ch\u2019on"
    ],
    "wof:name":"Chang-ch'on",
    "wof:placetype":"locality"
},
  "geometry": {"coordinates":[125.52,38.18306],"type":"Point"}
}