{
  "type": "Feature",
  "properties": {
    "gn:admin1_code":"1.0",
    "gn:asciiname":"Kamt'ang-ni",
    "gn:country_code":"KP",
    "gn:dem":232,
    "gn:feature_class":"P",
    "gn:feature_code":"PPL",
    "gn:name":"Kamt\u2019ang-ni",
    "gn:population":0,
    "gn:timezone":"Asia/Pyongyang",
    "iso:country":"KP",
    "name:und_x_variant":[
        "\uac10\ud0d5\ub9ac",
        "Kamt\u2019ang-ni"
    ],
    "wof:name":"Kamt'ang-ni",
    "wof:placetype":"locality"
},
  "geometry": {"coordinates":[126.19138999999998,40.94111],"type":"Point"}
}