{
  "type": "Feature",
  "properties": {
    "gn:admin1_code":"15.0",
    "gn:admin2_code":"Kaech'\u014fn-si",
    "gn:asciiname":"Changnakch'am",
    "gn:country_code":"KP",
    "gn:dem":118,
    "gn:feature_class":"P",
    "gn:feature_code":"PPL",
    "gn:name":"Changnakch\u2019am",
    "gn:population":0,
    "gn:timezone":"Asia/Pyongyang",
    "iso:country":"KP",
    "name:kor_x_preferred":[
        "\uc7a5\ub77d\ucc38"
    ],
    "name:und_x_variant":[
        "Changnakch\u2019am"
    ],
    "wof:name":"Changnakch'am",
    "wof:placetype":"locality"
},
  "geometry": {"coordinates":[126.00583,39.65917],"type":"Point"}
}