{
  "type": "Feature",
  "properties": {
    "gn:admin1_code":"6.0",
    "gn:asciiname":"Paeksu-dong",
    "gn:country_code":"KP",
    "gn:dem":27,
    "gn:feature_class":"P",
    "gn:feature_code":"PPL",
    "gn:name":"Paeksu-dong",
    "gn:population":0,
    "gn:timezone":"Asia/Pyongyang",
    "iso:country":"KP",
    "name:kor_x_preferred":[
        "\ubc31\uc218\ub3d9"
    ],
    "wof:name":"Paeksu-dong",
    "wof:placetype":"locality"
},
  "geometry": {"coordinates":[124.92722000000001,38.12028],"type":"Point"}
}