{
  "type": "Feature",
  "properties": {
    "gn:admin1_code":"6.0",
    "gn:asciiname":"Wollae-dong",
    "gn:country_code":"KP",
    "gn:dem":12,
    "gn:feature_class":"P",
    "gn:feature_code":"PPL",
    "gn:name":"W\u014fllae-dong",
    "gn:population":0,
    "gn:timezone":"Asia/Pyongyang",
    "iso:country":"KP",
    "name:eng_x_preferred":[
        "Wolnae-dong"
    ],
    "name:kor_x_preferred":[
        "\uc6b0\ub798\ub3d9"
    ],
    "wof:name":"Wollae-dong",
    "wof:placetype":"locality"
},
  "geometry": {"coordinates":[124.81694,38.0575],"type":"Point"}
}