{
  "type": "Feature",
  "properties": {
    "gn:admin1_code":"15.0",
    "gn:asciiname":"Koch'a",
    "gn:country_code":"KP",
    "gn:dem":444,
    "gn:feature_class":"P",
    "gn:feature_code":"PPL",
    "gn:name":"K\u014fch\u2019a",
    "gn:population":0,
    "gn:timezone":"Asia/Pyongyang",
    "iso:country":"KP",
    "name:und_x_variant":[
        "\uac70\ucc28",
        "K\u014fch\u2019a"
    ],
    "wof:name":"Koch'a",
    "wof:placetype":"locality"
},
  "geometry": {"coordinates":[126.80722,39.28944],"type":"Point"}
}