{
  "type": "Feature",
  "properties": {
    "gn:admin1_code":"9.0",
    "gn:asciiname":"Pangsong-ni",
    "gn:country_code":"KP",
    "gn:dem":302,
    "gn:feature_class":"P",
    "gn:feature_code":"PPL",
    "gn:name":"Pangs\u014fng-ni",
    "gn:population":0,
    "gn:timezone":"Asia/Pyongyang",
    "iso:country":"KP",
    "name:und_x_variant":[
        "\ubc29\uc131\ub9ac",
        "Pangs\u014fng-ni"
    ],
    "wof:name":"Pangsong-ni",
    "wof:placetype":"locality"
},
  "geometry": {"coordinates":[127.69499999999999,38.52333],"type":"Point"}
}