{
  "type": "Feature",
  "properties": {
    "gn:admin1_code":"11.0",
    "gn:asciiname":"Yongsu-dong",
    "gn:country_code":"KP",
    "gn:dem":137,
    "gn:feature_class":"P",
    "gn:feature_code":"PPL",
    "gn:name":"Yongsu-dong",
    "gn:population":0,
    "gn:timezone":"Asia/Pyongyang",
    "iso:country":"KP",
    "name:und_x_variant":[
        "\uc6a9\uc218\ub3d9",
        "Yongsu-dong"
    ],
    "wof:name":"Yongsu-dong",
    "wof:placetype":"locality"
},
  "geometry": {"coordinates":[125.54222,40.03278],"type":"Point"}
}