{
  "type": "Feature",
  "properties": {
    "gn:admin1_code":"9.0",
    "gn:asciiname":"Mi-gol",
    "gn:country_code":"KP",
    "gn:dem":201,
    "gn:feature_class":"P",
    "gn:feature_code":"PPL",
    "gn:name":"Mi-gol",
    "gn:population":0,
    "gn:timezone":"Asia/Pyongyang",
    "iso:country":"KP",
    "name:und_x_variant":[
        "\ubbf8\uace8",
        "Mi-gol"
    ],
    "wof:name":"Mi-gol",
    "wof:placetype":"locality"
},
  "geometry": {"coordinates":[127.79194,38.39333],"type":"Point"}
}