{
  "type": "Feature",
  "properties": {
    "gn:admin1_code":"11.0",
    "gn:asciiname":"P'odo-ri",
    "gn:country_code":"KP",
    "gn:dem":116,
    "gn:feature_class":"P",
    "gn:feature_code":"PPL",
    "gn:name":"P\u2019odo-ri",
    "gn:population":0,
    "gn:timezone":"Asia/Pyongyang",
    "iso:country":"KP",
    "name:und_x_variant":[
        "\ud3ec\ub3c4\ub9ac",
        "P\u2019odo-ri"
    ],
    "wof:name":"P'odo-ri",
    "wof:placetype":"locality"
},
  "geometry": {"coordinates":[124.68167,40.10639000000001],"type":"Point"}
}