{
  "type": "Feature",
  "properties": {
    "gn:admin1_code":"0.0",
    "gn:asciiname":"Sinmang-ni",
    "gn:country_code":"KP",
    "gn:dem":511,
    "gn:feature_class":"P",
    "gn:feature_code":"PPL",
    "gn:name":"Sinmang-ni",
    "gn:population":0,
    "gn:timezone":"Asia/Pyongyang",
    "iso:country":"KP",
    "name:und_x_variant":[
        "\uc2e0\ub9c9\ub9ac",
        "Sinmang-ni"
    ],
    "wof:name":"Sinmang-ni",
    "wof:placetype":"locality"
},
  "geometry": {"coordinates":[126.63333,39.81667],"type":"Point"}
}