{
  "type": "Feature",
  "properties": {
    "gn:admin1_code":"15.0",
    "gn:asciiname":"Ullyong-gol",
    "gn:country_code":"KP",
    "gn:dem":78,
    "gn:feature_class":"P",
    "gn:feature_code":"PPL",
    "gn:name":"Ullyong-gol",
    "gn:population":0,
    "gn:timezone":"Asia/Pyongyang",
    "iso:country":"KP",
    "name:und_x_variant":[
        "Ullyong-dong",
        "Ullyong-ni",
        "Ullyong-gol"
    ],
    "wof:name":"Ullyong-gol",
    "wof:placetype":"locality"
},
  "geometry": {"coordinates":[125.38167,39.00917000000001],"type":"Point"}
}