{
  "type": "Feature",
  "properties": {
    "gn:admin1_code":"7.0",
    "gn:asciiname":"Ch'uranjol-li",
    "gn:country_code":"KP",
    "gn:dem":287,
    "gn:feature_class":"P",
    "gn:feature_code":"PPL",
    "gn:name":"Ch\u2019uranj\u014fl-li",
    "gn:population":0,
    "gn:timezone":"Asia/Pyongyang",
    "iso:country":"KP",
    "name:und_x_variant":[
        "Ch\u2019uranj\u014fn-ni",
        "\ucd94\ub780\uc804\ub9ac",
        "Ch\u2019uranj\u014fl-li"
    ],
    "wof:name":"Ch'uranjol-li",
    "wof:placetype":"locality"
},
  "geometry": {"coordinates":[126.88889,39.03694],"type":"Point"}
}