{
  "type": "Feature",
  "properties": {
    "gn:admin1_code":"0.0",
    "gn:asciiname":"Kirhung-ni",
    "gn:country_code":"KP",
    "gn:dem":44,
    "gn:feature_class":"P",
    "gn:feature_code":"PPL",
    "gn:name":"Kirh\u016dng-ni",
    "gn:population":0,
    "gn:timezone":"Asia/Pyongyang",
    "iso:country":"KP",
    "name:eng_x_preferred":[
        "Kirhung"
    ],
    "name:eng_x_variant":[
        "Kirhung-ni"
    ],
    "name:kor_x_preferred":[
        "\uae38\ud765\ub9ac"
    ],
    "name:und_x_variant":[
        "Kirh\u016dng-ni"
    ],
    "wof:name":"Kirhung",
    "wof:placetype":"locality"
},
  "geometry": {"coordinates":[125.76667,39.86667],"type":"Point"}
}