{
  "type": "Feature",
  "properties": {
    "gn:admin1_code":"6.0",
    "gn:asciiname":"Toch'on-dong",
    "gn:country_code":"KP",
    "gn:dem":9,
    "gn:feature_class":"P",
    "gn:feature_code":"PPL",
    "gn:name":"Toch\u2019on-dong",
    "gn:population":0,
    "gn:timezone":"Asia/Pyongyang",
    "iso:country":"KP",
    "name:und_x_variant":[
        "\ub3c4\ucd0c\ub3d9",
        "Toch\u2019on-dong"
    ],
    "wof:name":"Toch'on-dong",
    "wof:placetype":"locality"
},
  "geometry": {"coordinates":[125.27889,38.07972],"type":"Point"}
}