{
  "type": "Feature",
  "properties": {
    "gn:admin1_code":"7.0",
    "gn:asciiname":"Oyong-dong",
    "gn:country_code":"KP",
    "gn:dem":65,
    "gn:feature_class":"P",
    "gn:feature_code":"PPL",
    "gn:name":"\u014ey\u014fng-dong",
    "gn:population":0,
    "gn:timezone":"Asia/Pyongyang",
    "iso:country":"KP",
    "wof:name":"Oyong-dong",
    "wof:placetype":"locality"
},
  "geometry": {"coordinates":[126.00943999999998,38.65306],"type":"Point"}
}