{
  "type": "Feature",
  "properties": {
    "gn:admin1_code":"7.0",
    "gn:asciiname":"Sosan",
    "gn:country_code":"KP",
    "gn:dem":95,
    "gn:feature_class":"P",
    "gn:feature_code":"PPL",
    "gn:name":"S\u014fsan",
    "gn:population":0,
    "gn:timezone":"Asia/Pyongyang",
    "iso:country":"KP",
    "wof:name":"Sosan",
    "wof:placetype":"locality"
},
  "geometry": {"coordinates":[126.14082999999999,38.25111],"type":"Point"}
}