{
  "type": "Feature",
  "properties": {
    "gn:admin1_code":"6.0",
    "gn:asciiname":"Sangdu-dong",
    "gn:country_code":"KP",
    "gn:dem":83,
    "gn:feature_class":"P",
    "gn:feature_code":"PPL",
    "gn:name":"Sangdu-dong",
    "gn:population":0,
    "gn:timezone":"Asia/Pyongyang",
    "iso:country":"KP",
    "name:und_x_variant":[
        "\uc0c1\ub450\ub3d9",
        "Sangdu-dong"
    ],
    "wof:name":"Sangdu-dong",
    "wof:placetype":"locality"
},
  "geometry": {"coordinates":[125.22750000000001,38.19111],"type":"Point"}
}