{
  "type": "Feature",
  "properties": {
    "gn:admin1_code":"12.0",
    "gn:asciiname":"Kandongjang-ni",
    "gn:cc2":"KP",
    "gn:country_code":"KP",
    "gn:dem":68,
    "gn:feature_class":"P",
    "gn:feature_code":"PPL",
    "gn:name":"Kandongjang-ni",
    "gn:population":0,
    "gn:timezone":"Asia/Pyongyang",
    "iso:country":"KP",
    "name:kor_x_preferred":[
        "\uac04\ub3d9\uc7a5\ub9ac"
    ],
    "name:und_x_variant":[
        "Kangdongjang-ni",
        "Kandongjang-ni"
    ],
    "wof:name":"Kandongjang-ni",
    "wof:placetype":"locality"
},
  "geometry": {"coordinates":[125.96611,38.74389],"type":"Point"}
}