{
  "type": "Feature",
  "properties": {
    "gn:admin1_code":"3.0",
    "gn:asciiname":"Posi-dong",
    "gn:country_code":"KP",
    "gn:dem":355,
    "gn:feature_class":"P",
    "gn:feature_code":"PPL",
    "gn:name":"Posi-dong",
    "gn:population":0,
    "gn:timezone":"Asia/Pyongyang",
    "iso:country":"KP",
    "name:und_x_variant":[
        "\ubcf4\uc2dc\ub3d9",
        "Posi-dong"
    ],
    "wof:name":"Posi-dong",
    "wof:placetype":"locality"
},
  "geometry": {"coordinates":[127.21138999999999,39.98778],"type":"Point"}
}