{
  "type": "Feature",
  "properties": {
    "gn:admin1_code":"1.0",
    "gn:asciiname":"Yong-dong",
    "gn:country_code":"KP",
    "gn:dem":636,
    "gn:feature_class":"P",
    "gn:feature_code":"PPL",
    "gn:name":"Y\u014fng-dong",
    "gn:population":0,
    "gn:timezone":"Asia/Pyongyang",
    "iso:country":"KP",
    "name:und_x_variant":[
        "\uc601\ub3d9",
        "Y\u014fng-dong"
    ],
    "wof:name":"Yong-dong",
    "wof:placetype":"locality"
},
  "geometry": {"coordinates":[126.80722,41.13639000000001],"type":"Point"}
}