{
  "type": "Feature",
  "properties": {
    "gn:admin1_code":"7.0",
    "gn:asciiname":"Hullyong-dong",
    "gn:country_code":"KP",
    "gn:dem":201,
    "gn:feature_class":"P",
    "gn:feature_code":"PPL",
    "gn:name":"H\u016dlly\u014fng-dong",
    "gn:population":0,
    "gn:timezone":"Asia/Pyongyang",
    "iso:country":"KP",
    "name:und_x_variant":[
        "\ud758\ub839\ub3d9",
        "H\u016dlly\u014fng-dong"
    ],
    "wof:name":"Hullyong-dong",
    "wof:placetype":"locality"
},
  "geometry": {"coordinates":[126.76443999999999,39.01028],"type":"Point"}
}