{
  "type": "Feature",
  "properties": {
    "gn:admin1_code":"9.0",
    "gn:asciiname":"Sop'ung-ni",
    "gn:country_code":"KP",
    "gn:dem":431,
    "gn:feature_class":"P",
    "gn:feature_code":"PPL",
    "gn:name":"Sop\u2019ung-ni",
    "gn:population":0,
    "gn:timezone":"Asia/Pyongyang",
    "iso:country":"KP",
    "name:und_x_variant":[
        "\uc18c\ud48d\ub9ac",
        "Sop\u2019ung-ni"
    ],
    "wof:name":"Sop'ung-ni",
    "wof:placetype":"locality"
},
  "geometry": {"coordinates":[127.63694,38.72694],"type":"Point"}
}