{
  "type": "Feature",
  "properties": {
    "gn:admin1_code":"9.0",
    "gn:admin2_code":"Ch'\u014fnnae-gun",
    "gn:asciiname":"Anhung-ni",
    "gn:country_code":"KP",
    "gn:dem":14,
    "gn:feature_class":"P",
    "gn:feature_code":"PPL",
    "gn:name":"Anh\u016dng-ni",
    "gn:population":0,
    "gn:timezone":"Asia/Pyongyang",
    "iso:country":"KP",
    "name:und_x_variant":[
        "Anh\u016dng-ni",
        "\uc548\ud765\ub9ac"
    ],
    "wof:name":"Anhung-ni",
    "wof:placetype":"locality"
},
  "geometry": {"coordinates":[127.40278000000001,39.40222],"type":"Point"}
}