{
  "type": "Feature",
  "properties": {
    "gn:admin1_code":"15.0",
    "gn:asciiname":"Togant'o",
    "gn:country_code":"KP",
    "gn:dem":613,
    "gn:feature_class":"P",
    "gn:feature_code":"PPL",
    "gn:name":"Togant\u2019\u014f",
    "gn:population":0,
    "gn:timezone":"Asia/Pyongyang",
    "iso:country":"KP",
    "name:und_x_variant":[
        "\ub3c5\uc548\ud130",
        "Togant\u2019\u014f"
    ],
    "wof:name":"Togant'o",
    "wof:placetype":"locality"
},
  "geometry": {"coordinates":[126.98361,40.08028],"type":"Point"}
}