{
  "type": "Feature",
  "properties": {
    "gn:admin1_code":"11.0",
    "gn:asciiname":"Inp'yong-ni",
    "gn:country_code":"KP",
    "gn:dem":98,
    "gn:feature_class":"P",
    "gn:feature_code":"PPL",
    "gn:name":"Inp\u2019y\u014fng-ni",
    "gn:population":0,
    "gn:timezone":"Asia/Pyongyang",
    "iso:country":"KP",
    "name:eng_x_preferred":[
        "Inp'yong"
    ],
    "name:eng_x_variant":[
        "Inp'yong-ni"
    ],
    "name:und_x_variant":[
        "\uc778\ud3c9\ub9ac",
        "Inp\u2019y\u014fng-ni"
    ],
    "wof:name":"Inp'yong",
    "wof:placetype":"locality"
},
  "geometry": {"coordinates":[124.84,40.28889],"type":"Point"}
}