{
  "type": "Feature",
  "properties": {
    "gn:admin1_code":"15.0",
    "gn:asciiname":"Munha-ri",
    "gn:country_code":"KP",
    "gn:dem":56,
    "gn:feature_class":"P",
    "gn:feature_code":"PPL",
    "gn:name":"Munha-ri",
    "gn:population":0,
    "gn:timezone":"Asia/Pyongyang",
    "iso:country":"KP",
    "wof:name":"Munha-ri",
    "wof:placetype":"locality"
},
  "geometry": {"coordinates":[125.99083,39.34861],"type":"Point"}
}