{
  "type": "Feature",
  "properties": {
    "gn:admin1_code":"17.0",
    "gn:asciiname":"Songmang-ni",
    "gn:country_code":"KP",
    "gn:dem":27,
    "gn:feature_class":"P",
    "gn:feature_code":"PPL",
    "gn:name":"S\u014fngmang-ni",
    "gn:population":0,
    "gn:timezone":"Asia/Pyongyang",
    "iso:country":"KP",
    "name:und_x_variant":[
        "S\u014fngmak-tong",
        "\uc11d\ub9c9\ub9ac",
        "S\u014fngmang-nodongjagu",
        "S\u014fngmang-ni"
    ],
    "wof:name":"Songmang-ni",
    "wof:placetype":"locality"
},
  "geometry": {"coordinates":[129.73306000000002,41.87917],"type":"Point"}
}