{
  "type": "Feature",
  "properties": {
    "gn:admin1_code":"17.0",
    "gn:asciiname":"Manch'ul-li",
    "gn:country_code":"KP",
    "gn:dem":16,
    "gn:feature_class":"P",
    "gn:feature_code":"PPL",
    "gn:name":"Manch\u2019ul-li",
    "gn:population":0,
    "gn:timezone":"Asia/Pyongyang",
    "iso:country":"KP",
    "name:und_x_variant":[
        "Banshun-d\u014d",
        "Manch\u2019un-dong",
        "Manch\u2019un-ni",
        "\ubb38\ucd98\ub9ac",
        "Manch\u2019ul-li"
    ],
    "wof:name":"Manch'ul-li",
    "wof:placetype":"locality"
},
  "geometry": {"coordinates":[129.15472,40.57],"type":"Point"}
}