{
  "type": "Feature",
  "properties": {
    "gn:admin1_code":"1.0",
    "gn:asciiname":"Chagunnolmegi-gol",
    "gn:country_code":"KP",
    "gn:dem":839,
    "gn:feature_class":"P",
    "gn:feature_code":"PPL",
    "gn:name":"Chag\u016dnn\u014flmegi-gol",
    "gn:population":0,
    "gn:timezone":"Asia/Pyongyang",
    "iso:country":"KP",
    "name:und_x_variant":[
        "\uc791\uc740\ub110\uba54\uae30\uace8",
        "Chag\u016dnn\u014flmegi-gol"
    ],
    "wof:name":"Chagunnolmegi-gol",
    "wof:placetype":"locality"
},
  "geometry": {"coordinates":[126.84332999999999,40.38833],"type":"Point"}
}