{
  "type": "Feature",
  "properties": {
    "gn:admin1_code":"1.0",
    "gn:asciiname":"Tunggong-ni",
    "gn:country_code":"KP",
    "gn:dem":338,
    "gn:feature_class":"P",
    "gn:feature_code":"PPL",
    "gn:name":"T\u016dnggong-ni",
    "gn:population":0,
    "gn:timezone":"Asia/Pyongyang",
    "iso:country":"KP",
    "name:und_x_variant":[
        "T\u016dnggong-dong",
        "\ub4f1\uacf5\ub9ac",
        "T\u016dnggong-ni"
    ],
    "wof:name":"Tunggong-ni",
    "wof:placetype":"locality"
},
  "geometry": {"coordinates":[126.44917,41.18778],"type":"Point"}
}