{
  "type": "Feature",
  "properties": {
    "gn:admin1_code":"3.0",
    "gn:asciiname":"Ip'yongch'on",
    "gn:country_code":"KP",
    "gn:dem":510,
    "gn:feature_class":"P",
    "gn:feature_code":"PPL",
    "gn:name":"Ip\u2019y\u014fngch\u2019on",
    "gn:population":0,
    "gn:timezone":"Asia/Pyongyang",
    "iso:country":"KP",
    "name:und_x_variant":[
        "\uc774\ud3c9\ucd0c",
        "Ip\u2019y\u014fngch\u2019on"
    ],
    "wof:name":"Ip'yongch'on",
    "wof:placetype":"locality"
},
  "geometry": {"coordinates":[127.99611000000002,40.44972],"type":"Point"}
}