{
  "type": "Feature",
  "properties": {
    "gn:admin1_code":"0.0",
    "gn:asciiname":"Naengjong-ni",
    "gn:country_code":"KP",
    "gn:dem":71,
    "gn:feature_class":"P",
    "gn:feature_code":"PPL",
    "gn:name":"Naengj\u014fng-ni",
    "gn:population":0,
    "gn:timezone":"Asia/Pyongyang",
    "iso:country":"KP",
    "name:eng_x_preferred":[
        "Naengjong"
    ],
    "name:eng_x_variant":[
        "Naengjong-ni"
    ],
    "name:kor_x_preferred":[
        "\ub0c9\uc815\ub9ac"
    ],
    "name:und_x_variant":[
        "Naengj\u014fng-ni"
    ],
    "wof:name":"Naengjong",
    "wof:placetype":"locality"
},
  "geometry": {"coordinates":[125.36667,38.93333],"type":"Point"}
}