{
  "type": "Feature",
  "properties": {
    "gn:admin1_code":"15.0",
    "gn:asciiname":"Songsu-ri",
    "gn:country_code":"KP",
    "gn:dem":338,
    "gn:feature_class":"P",
    "gn:feature_code":"PPL",
    "gn:name":"Songsu-ri",
    "gn:population":0,
    "gn:timezone":"Asia/Pyongyang",
    "iso:country":"KP",
    "name:und_x_variant":[
        "\uc1a1\uc218\ub9ac",
        "Songsu-ri"
    ],
    "wof:name":"Songsu-ri",
    "wof:placetype":"locality"
},
  "geometry": {"coordinates":[126.63694,39.60639000000001],"type":"Point"}
}