{
  "type": "Feature",
  "properties": {
    "gn:admin1_code":"3.0",
    "gn:asciiname":"Tumudok",
    "gn:country_code":"KP",
    "gn:dem":203,
    "gn:feature_class":"P",
    "gn:feature_code":"PPL",
    "gn:name":"Tumud\u014fk",
    "gn:population":0,
    "gn:timezone":"Asia/Pyongyang",
    "iso:country":"KP",
    "name:und_x_variant":[
        "Tumud\u014fk",
        "\ub450\ubb34\ub355"
    ],
    "wof:name":"Tumudok",
    "wof:placetype":"locality"
},
  "geometry": {"coordinates":[128.17517000000001,40.21133],"type":"Point"}
}