{
  "type": "Feature",
  "properties": {
    "gn:admin1_code":"0.0",
    "gn:asciiname":"Sagot-tong",
    "gn:country_code":"KP",
    "gn:dem":5,
    "gn:feature_class":"P",
    "gn:feature_code":"PPL",
    "gn:name":"Sagot-tong",
    "gn:population":0,
    "gn:timezone":"Asia/Pyongyang",
    "iso:country":"KP",
    "name:eng_x_preferred":[
        "Sagot"
    ],
    "name:eng_x_variant":[
        "Sagot-tong"
    ],
    "name:kor_x_preferred":[
        "\uc0ac\uacf3\ub3d9"
    ],
    "wof:name":"Sagot",
    "wof:placetype":"locality"
},
  "geometry": {"coordinates":[125.51667,38.73333],"type":"Point"}
}