{
  "type": "Feature",
  "properties": {
    "gn:admin1_code":"9.0",
    "gn:asciiname":"Taeyangch'on",
    "gn:country_code":"KP",
    "gn:dem":118,
    "gn:feature_class":"P",
    "gn:feature_code":"PPL",
    "gn:name":"Taeyangch\u2019on",
    "gn:population":0,
    "gn:timezone":"Asia/Pyongyang",
    "iso:country":"KP",
    "name:und_x_variant":[
        "\ub300\uc591\ucd0c",
        "Taeyangch\u2019on"
    ],
    "wof:name":"Taeyangch'on",
    "wof:placetype":"locality"
},
  "geometry": {"coordinates":[127.86028,38.84639],"type":"Point"}
}