{
  "type": "Feature",
  "properties": {
    "gn:admin1_code":"11.0",
    "gn:asciiname":"Okhyol-li",
    "gn:country_code":"KP",
    "gn:dem":45,
    "gn:feature_class":"P",
    "gn:feature_code":"PPL",
    "gn:name":"Okhy\u014fl-li",
    "gn:population":0,
    "gn:timezone":"Asia/Pyongyang",
    "iso:country":"KP",
    "name:kor_x_preferred":[
        "\uc625\ud604\ub9ac"
    ],
    "name:und_x_variant":[
        "Okhy\u014fl-li",
        "Okhy\u014fn-ni"
    ],
    "wof:name":"Okhyol-li",
    "wof:placetype":"locality"
},
  "geometry": {"coordinates":[125.54139000000001,39.8125],"type":"Point"}
}