{
  "type": "Feature",
  "properties": {
    "gn:admin1_code":"11.0",
    "gn:asciiname":"Taep'ung-ni",
    "gn:country_code":"KP",
    "gn:dem":299,
    "gn:feature_class":"P",
    "gn:feature_code":"PPL",
    "gn:name":"Taep\u2019ung-ni",
    "gn:population":0,
    "gn:timezone":"Asia/Pyongyang",
    "iso:country":"KP",
    "name:eng_x_preferred":[
        "Taep'ung"
    ],
    "name:eng_x_variant":[
        "Taep'ung-ni"
    ],
    "name:und_x_variant":[
        "\ub300\ud48d\ub9ac",
        "Taep\u2019ung-ni"
    ],
    "wof:name":"Taep'ung",
    "wof:placetype":"locality"
},
  "geometry": {"coordinates":[125.53833,40.46583],"type":"Point"}
}