{
  "type": "Feature",
  "properties": {
    "gn:admin1_code":"3.0",
    "gn:asciiname":"Changhwa-ch'on",
    "gn:country_code":"KP",
    "gn:dem":370,
    "gn:feature_class":"P",
    "gn:feature_code":"PPL",
    "gn:name":"Changhwa-ch\u2019on",
    "gn:population":0,
    "gn:timezone":"Asia/Pyongyang",
    "iso:country":"KP",
    "name:und_x_variant":[
        "\uc7a5\ud654\ucd0c",
        "Changhwa-ch\u2019on"
    ],
    "wof:name":"Changhwa-ch'on",
    "wof:placetype":"locality"
},
  "geometry": {"coordinates":[128.29832999999999,40.52389],"type":"Point"}
}