{
  "type": "Feature",
  "properties": {
    "gn:admin1_code":"12.0",
    "gn:asciiname":"Saekch'ong-gol",
    "gn:country_code":"KP",
    "gn:dem":125,
    "gn:feature_class":"P",
    "gn:feature_code":"PPL",
    "gn:name":"Saekch\u2019\u014fng-gol",
    "gn:population":0,
    "gn:timezone":"Asia/Pyongyang",
    "iso:country":"KP",
    "name:und_x_variant":[
        "\uc0c9\uccad\uace8",
        "Saekch\u2019\u014fng-gol"
    ],
    "wof:name":"Saekch'ong-gol",
    "wof:placetype":"locality"
},
  "geometry": {"coordinates":[125.99333,38.82889],"type":"Point"}
}