{
  "type": "Feature",
  "properties": {
    "gn:admin1_code":"0.0",
    "gn:asciiname":"Pan'gok-tong",
    "gn:country_code":"KP",
    "gn:dem":104,
    "gn:feature_class":"P",
    "gn:feature_code":"PPL",
    "gn:name":"Pan\u2019gok-tong",
    "gn:population":0,
    "gn:timezone":"Asia/Pyongyang",
    "iso:country":"KP",
    "name:kor_x_preferred":[
        "\ubc18\uace1\ub3d9"
    ],
    "name:und_x_variant":[
        "Pan\u2019gok-tong"
    ],
    "wof:name":"Pan'gok-tong",
    "wof:placetype":"locality"
},
  "geometry": {"coordinates":[125.16667,38.13333],"type":"Point"}
}