{
  "type": "Feature",
  "properties": {
    "gn:admin1_code":"6.0",
    "gn:asciiname":"Kandong-ni",
    "gn:country_code":"KP",
    "gn:dem":136,
    "gn:feature_class":"P",
    "gn:feature_code":"PPL",
    "gn:name":"Kandong-ni",
    "gn:population":0,
    "gn:timezone":"Asia/Pyongyang",
    "iso:country":"KP",
    "name:kor_x_preferred":[
        "\uac04\ub3d9\ub9ac"
    ],
    "wof:name":"Kandong-ni",
    "wof:placetype":"locality"
},
  "geometry": {"coordinates":[125.56194000000001,38.24444],"type":"Point"}
}