{
  "type": "Feature",
  "properties": {
    "gn:admin1_code":"6.0",
    "gn:asciiname":"Choktul-li",
    "gn:country_code":"KP",
    "gn:dem":23,
    "gn:feature_class":"P",
    "gn:feature_code":"PPL",
    "gn:name":"Ch\u014fktul-li",
    "gn:population":0,
    "gn:timezone":"Asia/Pyongyang",
    "iso:country":"KP",
    "name:kor_x_preferred":[
        "\uc801\ub450\ub9ac"
    ],
    "name:kor_x_variant":[
        "Ch\u014fktul-li"
    ],
    "wof:name":"Choktul-li",
    "wof:placetype":"locality"
},
  "geometry": {"coordinates":[125.43917,38.62306],"type":"Point"}
}