{
  "type": "Feature",
  "properties": {
    "gn:admin1_code":"17.0",
    "gn:admin2_code":"\u016cnd\u014fk-kun",
    "gn:asciiname":"Sansokkok",
    "gn:country_code":"KP",
    "gn:dem":168,
    "gn:feature_class":"P",
    "gn:feature_code":"PPL",
    "gn:name":"Sans\u014fkkok",
    "gn:population":0,
    "gn:timezone":"Asia/Pyongyang",
    "iso:country":"KP",
    "name:und_x_variant":[
        "\uc0b0\uc11d\uace1",
        "Sans\u014fkkok"
    ],
    "wof:name":"Sansokkok",
    "wof:placetype":"locality"
},
  "geometry": {"coordinates":[130.22471999999999,42.48278],"type":"Point"}
}