{
  "type": "Feature",
  "properties": {
    "gn:admin1_code":"7.0",
    "gn:asciiname":"Taejong-kol",
    "gn:country_code":"KP",
    "gn:dem":227,
    "gn:feature_class":"P",
    "gn:feature_code":"PPL",
    "gn:name":"Taej\u014fng-kol",
    "gn:population":0,
    "gn:timezone":"Asia/Pyongyang",
    "iso:country":"KP",
    "wof:name":"Taejong-kol",
    "wof:placetype":"locality"
},
  "geometry": {"coordinates":[126.70972,38.46917],"type":"Point"}
}