{
  "type": "Feature",
  "properties": {
    "gn:admin1_code":"11.0",
    "gn:asciiname":"Wolbong-ni",
    "gn:country_code":"KP",
    "gn:dem":19,
    "gn:feature_class":"P",
    "gn:feature_code":"PPL",
    "gn:name":"W\u014flbong-ni",
    "gn:population":0,
    "gn:timezone":"Asia/Pyongyang",
    "iso:country":"KP",
    "name:und_x_variant":[
        "W\u014flbong-dong",
        "\uc6d4\ubd09\ub9ac",
        "W\u014flbong-ni"
    ],
    "wof:name":"Wolbong-ni",
    "wof:placetype":"locality"
},
  "geometry": {"coordinates":[124.68389000000001,39.75861],"type":"Point"}
}