{
  "type": "Feature",
  "properties": {
    "gn:admin1_code":"11.0",
    "gn:asciiname":"Chungdongch'am",
    "gn:country_code":"KP",
    "gn:dem":76,
    "gn:feature_class":"P",
    "gn:feature_code":"PPL",
    "gn:name":"Chungdongch\u2019am",
    "gn:population":0,
    "gn:timezone":"Asia/Pyongyang",
    "iso:country":"KP",
    "wof:name":"Chungdongch'am",
    "wof:placetype":"locality"
},
  "geometry": {"coordinates":[125.79944,39.77222],"type":"Point"}
}