{
  "type": "Feature",
  "properties": {
    "gn:admin1_code":"12.0",
    "gn:admin2_code":"Sangw\u014fn-gun",
    "gn:asciiname":"Kwijang-gol",
    "gn:cc2":"KP",
    "gn:country_code":"KP",
    "gn:dem":122,
    "gn:feature_class":"P",
    "gn:feature_code":"PPL",
    "gn:name":"Kwijang-gol",
    "gn:population":0,
    "gn:timezone":"Asia/Pyongyang",
    "iso:country":"KP",
    "name:und_x_variant":[
        "Kwijang-kol",
        "Kwijang-gol"
    ],
    "wof:name":"Kwijang-gol",
    "wof:placetype":"locality"
},
  "geometry": {"coordinates":[126.14778,38.85306],"type":"Point"}
}