{
  "type": "Feature",
  "properties": {
    "gn:admin1_code":"18.0",
    "gn:admin2_code":"Najins\u014fnbong-si",
    "gn:asciiname":"P'igaegok",
    "gn:country_code":"KP",
    "gn:dem":17,
    "gn:feature_class":"P",
    "gn:feature_code":"PPL",
    "gn:name":"P\u2019igaegok",
    "gn:population":0,
    "gn:timezone":"Asia/Pyongyang",
    "iso:country":"KP",
    "name:und_x_variant":[
        "\ud53c\uac1c\uace1",
        "P\u2019igaegok",
        "Pigaegok"
    ],
    "wof:name":"P'igaegok",
    "wof:placetype":"locality"
},
  "geometry": {"coordinates":[130.28638999999998,42.26639],"type":"Point"}
}