{
  "type": "Feature",
  "properties": {
    "gn:admin1_code":"7.0",
    "gn:asciiname":"Pultang-gol",
    "gn:country_code":"KP",
    "gn:dem":130,
    "gn:feature_class":"P",
    "gn:feature_code":"PPL",
    "gn:name":"Pultang-gol",
    "gn:population":0,
    "gn:timezone":"Asia/Pyongyang",
    "iso:country":"KP",
    "wof:name":"Pultang-gol",
    "wof:placetype":"locality"
},
  "geometry": {"coordinates":[126.10833,38.60694],"type":"Point"}
}