{
  "type": "Feature",
  "properties": {
    "gn:admin1_code":"6.0",
    "gn:asciiname":"Podunamu-gol",
    "gn:country_code":"KP",
    "gn:dem":44,
    "gn:feature_class":"P",
    "gn:feature_code":"PPL",
    "gn:name":"P\u014fd\u016dnamu-gol",
    "gn:population":0,
    "gn:timezone":"Asia/Pyongyang",
    "iso:country":"KP",
    "name:und_x_variant":[
        "\ubc84\ub4dc\ub098\ubb34\uace8",
        "P\u014fd\u016dnamu-gol"
    ],
    "wof:name":"Podunamu-gol",
    "wof:placetype":"locality"
},
  "geometry": {"coordinates":[126.32693999999999,38.18556],"type":"Point"}
}