{
  "type": "Feature",
  "properties": {
    "gn:admin1_code":"6.0",
    "gn:asciiname":"Sanggum-dong",
    "gn:country_code":"KP",
    "gn:dem":41,
    "gn:feature_class":"P",
    "gn:feature_code":"PPL",
    "gn:name":"Sangg\u016dm-dong",
    "gn:population":0,
    "gn:timezone":"Asia/Pyongyang",
    "iso:country":"KP",
    "name:und_x_variant":[
        "\uc0c1\uae08\ub3d9",
        "Sangg\u016dm-dong"
    ],
    "wof:name":"Sanggum-dong",
    "wof:placetype":"locality"
},
  "geometry": {"coordinates":[125.2625,38.14611],"type":"Point"}
}