{
  "type": "Feature",
  "properties": {
    "gn:admin1_code":"6.0",
    "gn:admin2_code":"Paech\u2019\u014fn-gun",
    "gn:asciiname":"Ch'angdong-ni",
    "gn:country_code":"KP",
    "gn:dem":8,
    "gn:feature_class":"P",
    "gn:feature_code":"PPL",
    "gn:name":"Ch\u2019angdong-ni",
    "gn:population":0,
    "gn:timezone":"Asia/Pyongyang",
    "iso:country":"KP",
    "wof:name":"Ch'angdong-ni",
    "wof:placetype":"locality"
},
  "geometry": {"coordinates":[126.3125,37.87583],"type":"Point"}
}