{
  "type": "Feature",
  "properties": {
    "gn:admin1_code":"6.0",
    "gn:asciiname":"Soksa-dong",
    "gn:country_code":"KP",
    "gn:dem":101,
    "gn:feature_class":"P",
    "gn:feature_code":"PPL",
    "gn:name":"S\u014fksa-dong",
    "gn:population":0,
    "gn:timezone":"Asia/Pyongyang",
    "iso:country":"KP",
    "name:kor_x_preferred":[
        "\uc11d\uc0ac\ub3d9"
    ],
    "name:kor_x_variant":[
        "S\u014fksa-dong"
    ],
    "wof:name":"Soksa-dong",
    "wof:placetype":"locality"
},
  "geometry": {"coordinates":[125.37333,38.50083],"type":"Point"}
}