{
  "type": "Feature",
  "properties": {
    "gn:admin1_code":"11.0",
    "gn:asciiname":"Sujil-li",
    "gn:country_code":"KP",
    "gn:dem":26,
    "gn:feature_class":"P",
    "gn:feature_code":"PPL",
    "gn:name":"Sujil-li",
    "gn:population":0,
    "gn:timezone":"Asia/Pyongyang",
    "iso:country":"KP",
    "name:und_x_variant":[
        "\uc218\uc9c4\ub9ac",
        "Sujil-li"
    ],
    "wof:name":"Sujil-li",
    "wof:placetype":"locality"
},
  "geometry": {"coordinates":[124.61194,40.25722],"type":"Point"}
}