{
  "type": "Feature",
  "properties": {
    "gn:admin1_code":"11.0",
    "gn:asciiname":"Ullim-ni",
    "gn:country_code":"KP",
    "gn:dem":56,
    "gn:feature_class":"P",
    "gn:feature_code":"PPL",
    "gn:name":"Ullim-ni",
    "gn:population":0,
    "gn:timezone":"Asia/Pyongyang",
    "iso:country":"KP",
    "name:und_x_variant":[
        "\uc6b4\ub9bc\ub9ac",
        "Ullim-ni"
    ],
    "wof:name":"Ullim-ni",
    "wof:placetype":"locality"
},
  "geometry": {"coordinates":[124.60833,40.08139],"type":"Point"}
}