{
  "type": "Feature",
  "properties": {
    "gn:admin1_code":"1.0",
    "gn:asciiname":"Hoedong-ni",
    "gn:country_code":"KP",
    "gn:dem":527,
    "gn:feature_class":"P",
    "gn:feature_code":"PPL",
    "gn:name":"Hoed\u014fng-ni",
    "gn:population":0,
    "gn:timezone":"Asia/Pyongyang",
    "iso:country":"KP",
    "name:und_x_variant":[
        "Hoed\u014fng-ni",
        "\ud68c\ub355\ucc38",
        "Hoed\u014fkch\u2019am",
        "\ud68c\ub355\ub9ac"
    ],
    "wof:name":"Hoedong-ni",
    "wof:placetype":"locality"
},
  "geometry": {"coordinates":[126.364,40.72306],"type":"Point"}
}