{
  "type": "Feature",
  "properties": {
    "gn:admin1_code":"9.0",
    "gn:admin2_code":"Ch\u2019\u014fnnae-gun",
    "gn:asciiname":"Naeoryu-gol",
    "gn:country_code":"KP",
    "gn:dem":25,
    "gn:feature_class":"P",
    "gn:feature_code":"PPL",
    "gn:name":"Naeoryu-gol",
    "gn:population":0,
    "gn:timezone":"Asia/Pyongyang",
    "iso:country":"KP",
    "name:und_x_variant":[
        "Anoryu-dong",
        "Naeoryu-gol",
        "\ub0b4\uc624\ub958\uace8"
    ],
    "wof:name":"Naeoryu-gol",
    "wof:placetype":"locality"
},
  "geometry": {"coordinates":[127.24694,39.35611],"type":"Point"}
}