{
  "type": "Feature",
  "properties": {
    "gn:admin1_code":"9.0",
    "gn:asciiname":"Naeryongdae",
    "gn:country_code":"KP",
    "gn:dem":384,
    "gn:feature_class":"P",
    "gn:feature_code":"PPL",
    "gn:name":"Naery\u014fngdae",
    "gn:population":0,
    "gn:timezone":"Asia/Pyongyang",
    "iso:country":"KP",
    "name:und_x_variant":[
        "Naireitai",
        "\ub0b4\ub839\ub300",
        "Naery\u014fngdae"
    ],
    "wof:name":"Naeryongdae",
    "wof:placetype":"locality"
},
  "geometry": {"coordinates":[127.63916999999999,38.94944],"type":"Point"}
}