{
  "type": "Feature",
  "properties": {
    "gn:admin1_code":"3.0",
    "gn:asciiname":"Taet'onggi-ri",
    "gn:country_code":"KP",
    "gn:dem":919,
    "gn:feature_class":"P",
    "gn:feature_code":"PPL",
    "gn:name":"Taet\u2019onggi-ri",
    "gn:population":0,
    "gn:timezone":"Asia/Pyongyang",
    "iso:country":"KP",
    "name:kor_x_preferred":[
        "\ub300\ud1b5\uae30\ub9ac"
    ],
    "name:und_x_variant":[
        "Daits\u016bki-ri",
        "Taetan",
        "Taet\u2019onggi-ri"
    ],
    "wof:name":"Taet'onggi-ri",
    "wof:placetype":"locality"
},
  "geometry": {"coordinates":[127.62396,41.07685],"type":"Point"}
}