{
  "type": "Feature",
  "properties": {
    "gn:admin1_code":"3.0",
    "gn:asciiname":"Kkach'i-gol",
    "gn:country_code":"KP",
    "gn:dem":201,
    "gn:feature_class":"P",
    "gn:feature_code":"PPL",
    "gn:name":"Kkach\u2019i-gol",
    "gn:population":0,
    "gn:timezone":"Asia/Pyongyang",
    "iso:country":"KP",
    "name:und_x_variant":[
        "\uae4c\uce58\uace8",
        "Kkach\u2019i-gol"
    ],
    "wof:name":"Kkach'i-gol",
    "wof:placetype":"locality"
},
  "geometry": {"coordinates":[126.81944,39.57028],"type":"Point"}
}