{
  "type": "Feature",
  "properties": {
    "gn:admin1_code":"6.0",
    "gn:admin2_code":"1876380",
    "gn:asciiname":"Oksal-li",
    "gn:country_code":"KP",
    "gn:dem":15,
    "gn:feature_class":"P",
    "gn:feature_code":"PPL",
    "gn:name":"Oksal-li",
    "gn:population":0,
    "gn:timezone":"Asia/Pyongyang",
    "iso:country":"KP",
    "name:und_x_variant":[
        "Gyokusan-ri",
        "Oksan-ni",
        "Oksal-li"
    ],
    "wof:name":"Oksal-li",
    "wof:placetype":"locality"
},
  "geometry": {"coordinates":[126.44361000000001,37.93583],"type":"Point"}
}