{
  "type": "Feature",
  "properties": {
    "gn:admin1_code":"7.0",
    "gn:asciiname":"Tokchong-gol",
    "gn:country_code":"KP",
    "gn:dem":34,
    "gn:feature_class":"P",
    "gn:feature_code":"PPL",
    "gn:name":"Tokch\u014fng-gol",
    "gn:population":0,
    "gn:timezone":"Asia/Pyongyang",
    "iso:country":"KP",
    "name:und_x_variant":[
        "Tokch\u014fng-kol",
        "\ub3c5\uc815\uace8",
        "Tokch\u014fng-gol"
    ],
    "wof:name":"Tokchong-gol",
    "wof:placetype":"locality"
},
  "geometry": {"coordinates":[126.44833,38.08778],"type":"Point"}
}