{
  "type": "Feature",
  "properties": {
    "gn:admin1_code":"9.0",
    "gn:admin2_code":"Kos\u0171ng-gun",
    "gn:asciiname":"Ponghwa-ri",
    "gn:country_code":"KP",
    "gn:dem":225,
    "gn:feature_class":"P",
    "gn:feature_code":"PPL",
    "gn:name":"Ponghwa-ri",
    "gn:population":0,
    "gn:timezone":"Asia/Pyongyang",
    "iso:country":"KP",
    "name:kor_x_preferred":[
        "\ubd09\ud654\ub9ac"
    ],
    "name:und_x_variant":[
        "Pongha-ri",
        "Ponghwa-ri"
    ],
    "wof:name":"Ponghwa-ri",
    "wof:placetype":"locality"
},
  "geometry": {"coordinates":[128.28083000000001,38.69222],"type":"Point"}
}