{
  "type": "Feature",
  "properties": {
    "gn:admin1_code":"9.0",
    "gn:admin2_code":"1875980",
    "gn:asciiname":"Suyangjong",
    "gn:country_code":"KP",
    "gn:dem":308,
    "gn:feature_class":"P",
    "gn:feature_code":"PPL",
    "gn:name":"Suyangj\u014fng",
    "gn:population":0,
    "gn:timezone":"Asia/Pyongyang",
    "iso:country":"KP",
    "wof:name":"Suyangjong",
    "wof:placetype":"locality"
},
  "geometry": {"coordinates":[127.43389000000001,38.40333],"type":"Point"}
}