{
  "type": "Feature",
  "properties": {
    "gn:admin1_code":"11.0",
    "gn:asciiname":"Onjong",
    "gn:country_code":"KP",
    "gn:dem":92,
    "gn:feature_class":"P",
    "gn:feature_code":"PPL",
    "gn:name":"Onj\u014fng",
    "gn:population":0,
    "gn:timezone":"Asia/Pyongyang",
    "iso:country":"KP",
    "name:kor_x_preferred":[
        "\uc628\uc815"
    ],
    "name:und_x_variant":[
        "Onj\u014fng"
    ],
    "wof:name":"Onjong",
    "wof:placetype":"locality"
},
  "geometry": {"coordinates":[125.91278,39.85222],"type":"Point"}
}