{
  "type": "Feature",
  "properties": {
    "gn:admin1_code":"17.0",
    "gn:asciiname":"Samso",
    "gn:country_code":"KP",
    "gn:dem":691,
    "gn:feature_class":"P",
    "gn:feature_code":"PPL",
    "gn:name":"Samso",
    "gn:population":0,
    "gn:timezone":"Asia/Pyongyang",
    "iso:country":"KP",
    "name:und_x_variant":[
        "\uc0bc\uc18c",
        "Sam-dong"
    ],
    "wof:name":"Samso",
    "wof:placetype":"locality"
},
  "geometry": {"coordinates":[129.24222,42.03972],"type":"Point"}
}