{
  "type": "Feature",
  "properties": {
    "gn:admin1_code":"7.0",
    "gn:asciiname":"Ch'u-dong",
    "gn:country_code":"KP",
    "gn:dem":346,
    "gn:feature_class":"P",
    "gn:feature_code":"PPL",
    "gn:name":"Ch\u2019u-dong",
    "gn:population":0,
    "gn:timezone":"Asia/Pyongyang",
    "iso:country":"KP",
    "name:kor_x_preferred":[
        "\ucd94\ub3d9"
    ],
    "name:kor_x_variant":[
        "Ch\u2019u-dong"
    ],
    "wof:name":"Ch'u-dong",
    "wof:placetype":"locality"
},
  "geometry": {"coordinates":[126.925,39.01167],"type":"Point"}
}