{
  "type": "Feature",
  "properties": {
    "gn:admin1_code":"12.0",
    "gn:asciiname":"Kani-dong",
    "gn:country_code":"KP",
    "gn:dem":48,
    "gn:feature_class":"P",
    "gn:feature_code":"PPL",
    "gn:name":"Kani-dong",
    "gn:population":0,
    "gn:timezone":"Asia/Pyongyang",
    "iso:country":"KP",
    "name:kor_x_preferred":[
        "\uac00\ub2c8\ub3d9"
    ],
    "name:und_x_variant":[
        "Ganidong"
    ],
    "wof:name":"Kani-dong",
    "wof:placetype":"locality"
},
  "geometry": {"coordinates":[125.74861,39.16861],"type":"Point"}
}