{
  "type": "Feature",
  "properties": {
    "gn:admin1_code":"17.0",
    "gn:asciiname":"No-dong",
    "gn:country_code":"KP",
    "gn:dem":46,
    "gn:feature_class":"P",
    "gn:feature_code":"PPL",
    "gn:name":"No-dong",
    "gn:population":0,
    "gn:timezone":"Asia/Pyongyang",
    "iso:country":"KP",
    "name:und_x_variant":[
        "\ub178\ub3d9",
        "No-dong"
    ],
    "wof:name":"No-dong",
    "wof:placetype":"locality"
},
  "geometry": {"coordinates":[130.29471999999998,42.65861],"type":"Point"}
}