{
  "type": "Feature",
  "properties": {
    "gn:admin1_code":"6.0",
    "gn:asciiname":"Ant'ul",
    "gn:country_code":"KP",
    "gn:dem":92,
    "gn:feature_class":"P",
    "gn:feature_code":"PPL",
    "gn:name":"Ant\u2019\u016dl",
    "gn:population":0,
    "gn:timezone":"Asia/Pyongyang",
    "iso:country":"KP",
    "name:kor_x_preferred":[
        "\uc548\ud2c0"
    ],
    "name:kor_x_variant":[
        "Ant\u2019\u016dl"
    ],
    "wof:name":"Ant'ul",
    "wof:placetype":"locality"
},
  "geometry": {"coordinates":[125.37860999999999,38.29944],"type":"Point"}
}