{
  "type": "Feature",
  "properties": {
    "gn:admin1_code":"1.0",
    "gn:asciiname":"Changt'oha-dong",
    "gn:country_code":"KP",
    "gn:dem":185,
    "gn:feature_class":"P",
    "gn:feature_code":"PPL",
    "gn:name":"Changt\u2019oha-dong",
    "gn:population":0,
    "gn:timezone":"Asia/Pyongyang",
    "iso:country":"KP",
    "name:und_x_variant":[
        "\uc7a5\ud1a0\ud558\ub3d9",
        "Changt\u2019oha-dong"
    ],
    "wof:name":"Changt'oha-dong",
    "wof:placetype":"locality"
},
  "geometry": {"coordinates":[125.74083,40.81583],"type":"Point"}
}