{
  "type": "Feature",
  "properties": {
    "gn:admin1_code":"3.0",
    "gn:asciiname":"Pongsu-dong",
    "gn:country_code":"KP",
    "gn:dem":1035,
    "gn:feature_class":"P",
    "gn:feature_code":"PPL",
    "gn:name":"Pongsu-dong",
    "gn:population":0,
    "gn:timezone":"Asia/Pyongyang",
    "iso:country":"KP",
    "name:und_x_variant":[
        "\ubd09\uc218\ub3d9",
        "Pongsu-dong"
    ],
    "wof:name":"Pongsu-dong",
    "wof:placetype":"locality"
},
  "geometry": {"coordinates":[128.61583000000002,40.82],"type":"Point"}
}