{
  "type": "Feature",
  "properties": {
    "gn:admin1_code":"9.0",
    "gn:asciiname":"Sanjo-ri",
    "gn:country_code":"KP",
    "gn:dem":338,
    "gn:feature_class":"P",
    "gn:feature_code":"PPL",
    "gn:name":"Sanj\u014f-ri",
    "gn:population":0,
    "gn:timezone":"Asia/Pyongyang",
    "iso:country":"KP",
    "name:und_x_variant":[
        "\uc0b0\uc800\ub9ac",
        "Sanj\u014f-ri"
    ],
    "wof:name":"Sanjo-ri",
    "wof:placetype":"locality"
},
  "geometry": {"coordinates":[127.09166999999999,38.99333],"type":"Point"}
}