{
  "type": "Feature",
  "properties": {
    "gn:admin1_code":"3.0",
    "gn:asciiname":"Sangso-ri",
    "gn:country_code":"KP",
    "gn:dem":509,
    "gn:feature_class":"P",
    "gn:feature_code":"PPL",
    "gn:name":"Sangs\u014f-ri",
    "gn:population":0,
    "gn:timezone":"Asia/Pyongyang",
    "iso:country":"KP",
    "name:und_x_variant":[
        "\uc0c1\uc11c\ub9ac",
        "Sangs\u014f-ri"
    ],
    "wof:name":"Sangso-ri",
    "wof:placetype":"locality"
},
  "geometry": {"coordinates":[127.14472000000001,40.02861],"type":"Point"}
}