{
  "type": "Feature",
  "properties": {
    "gn:admin1_code":"11.0",
    "gn:asciiname":"Yonghung-ni",
    "gn:country_code":"KP",
    "gn:dem":203,
    "gn:feature_class":"P",
    "gn:feature_code":"PPL",
    "gn:name":"Yongh\u016dng-ni",
    "gn:population":0,
    "gn:timezone":"Asia/Pyongyang",
    "iso:country":"KP",
    "name:und_x_variant":[
        "\uc6a9\ud765\ub9ac",
        "Yongh\u016dng-ni"
    ],
    "wof:name":"Yonghung-ni",
    "wof:placetype":"locality"
},
  "geometry": {"coordinates":[126.08306,40.03222],"type":"Point"}
}