{
  "type": "Feature",
  "properties": {
    "gn:admin1_code":"17.0",
    "gn:asciiname":"Sunam-dong",
    "gn:country_code":"KP",
    "gn:dem":356,
    "gn:feature_class":"P",
    "gn:feature_code":"PPL",
    "gn:name":"Sunam-dong",
    "gn:population":0,
    "gn:timezone":"Asia/Pyongyang",
    "iso:country":"KP",
    "name:und_x_variant":[
        "\uc218\ub0a8\ub3d9",
        "Sunam-dong"
    ],
    "wof:name":"Sunam-dong",
    "wof:placetype":"locality"
},
  "geometry": {"coordinates":[129.82083,42.39861],"type":"Point"}
}