{
  "type": "Feature",
  "properties": {
    "gn:admin1_code":"17.0",
    "gn:asciiname":"Nonggyong-dong",
    "gn:country_code":"KP",
    "gn:dem":69,
    "gn:feature_class":"P",
    "gn:feature_code":"PPL",
    "gn:name":"Nonggy\u014fng-dong",
    "gn:population":0,
    "gn:timezone":"Asia/Pyongyang",
    "iso:country":"KP",
    "name:und_x_variant":[
        "\ub18d\uacbd\ub3d9",
        "Nonggy\u014fng-dong"
    ],
    "wof:name":"Nonggyong-dong",
    "wof:placetype":"locality"
},
  "geometry": {"coordinates":[130.33306000000002,42.53083],"type":"Point"}
}