{
  "type": "Feature",
  "properties": {
    "gn:admin1_code":"7.0",
    "gn:asciiname":"Tae-dong",
    "gn:country_code":"KP",
    "gn:dem":264,
    "gn:feature_class":"P",
    "gn:feature_code":"PPL",
    "gn:name":"Tae-dong",
    "gn:population":0,
    "gn:timezone":"Asia/Pyongyang",
    "iso:country":"KP",
    "wof:name":"Tae-dong",
    "wof:placetype":"locality"
},
  "geometry": {"coordinates":[126.26472,38.53417],"type":"Point"}
}