{
  "type": "Feature",
  "properties": {
    "gn:admin1_code":"9.0",
    "gn:asciiname":"Minamni-gol",
    "gn:country_code":"KP",
    "gn:dem":277,
    "gn:feature_class":"P",
    "gn:feature_code":"PPL",
    "gn:name":"Minamni-gol",
    "gn:population":0,
    "gn:timezone":"Asia/Pyongyang",
    "iso:country":"KP",
    "name:und_x_variant":[
        "\ubbf8\ub0a8\ub9ac\uace8",
        "Minamri-gol",
        "Minamni-gol"
    ],
    "wof:name":"Minamni-gol",
    "wof:placetype":"locality"
},
  "geometry": {"coordinates":[127.52500000000001,38.36889],"type":"Point"}
}