{
  "type": "Feature",
  "properties": {
    "gn:admin1_code":"1.0",
    "gn:asciiname":"Suoguch'am",
    "gn:country_code":"KP",
    "gn:dem":274,
    "gn:feature_class":"P",
    "gn:feature_code":"PPL",
    "gn:name":"Su\u014fguch\u2019am",
    "gn:population":0,
    "gn:timezone":"Asia/Pyongyang",
    "iso:country":"KP",
    "name:und_x_variant":[
        "\uc218\uc5b4\uad6c\ucc38",
        "Su\u014fguch\u2019am"
    ],
    "wof:name":"Suoguch'am",
    "wof:placetype":"locality"
},
  "geometry": {"coordinates":[126.21639,40.28944],"type":"Point"}
}