{
  "type": "Feature",
  "properties": {
    "gn:admin1_code":"15.0",
    "gn:asciiname":"Pindwi",
    "gn:country_code":"KP",
    "gn:dem":256,
    "gn:feature_class":"P",
    "gn:feature_code":"PPL",
    "gn:name":"Pindwi",
    "gn:population":0,
    "gn:timezone":"Asia/Pyongyang",
    "iso:country":"KP",
    "name:und_x_variant":[
        "\ube48\ub4a4",
        "Pindwi"
    ],
    "wof:name":"Pindwi",
    "wof:placetype":"locality"
},
  "geometry": {"coordinates":[126.6425,39.73056],"type":"Point"}
}