{
  "type": "Feature",
  "properties": {
    "gn:admin1_code":"15.0",
    "gn:asciiname":"Sinsong-ni",
    "gn:country_code":"KP",
    "gn:dem":151,
    "gn:feature_class":"P",
    "gn:feature_code":"PPL",
    "gn:name":"Sins\u014fng-ni",
    "gn:population":0,
    "gn:timezone":"Asia/Pyongyang",
    "iso:country":"KP",
    "name:und_x_variant":[
        "\uc2e0\uc131\ub9ac",
        "Sins\u014fng-nodongjagu",
        "Sins\u014fng-ni"
    ],
    "wof:name":"Sinsong-ni",
    "wof:placetype":"locality"
},
  "geometry": {"coordinates":[126.23193999999999,39.75806],"type":"Point"}
}