{
  "type": "Feature",
  "properties": {
    "gn:admin1_code":"15.0",
    "gn:asciiname":"Tujon-dong",
    "gn:country_code":"KP",
    "gn:dem":191,
    "gn:feature_class":"P",
    "gn:feature_code":"PPL",
    "gn:name":"Tuj\u014fn-dong",
    "gn:population":0,
    "gn:timezone":"Asia/Pyongyang",
    "iso:country":"KP",
    "name:kor_x_preferred":[
        "\ub450\uc804\ub3d9"
    ],
    "name:kor_x_variant":[
        "Tuj\u014fn-dong"
    ],
    "wof:name":"Tujon-dong",
    "wof:placetype":"locality"
},
  "geometry": {"coordinates":[126.435,39.04667],"type":"Point"}
}