{
  "type": "Feature",
  "properties": {
    "gn:admin1_code":"11.0",
    "gn:asciiname":"Oryong",
    "gn:country_code":"KP",
    "gn:dem":16,
    "gn:feature_class":"P",
    "gn:feature_code":"PPL",
    "gn:name":"\u014ery\u014fng",
    "gn:population":0,
    "gn:timezone":"Asia/Pyongyang",
    "iso:country":"KP",
    "name:und_x_variant":[
        "\uc5b4\ub839",
        "\u014ery\u014fng"
    ],
    "wof:name":"Oryong",
    "wof:placetype":"locality"
},
  "geometry": {"coordinates":[124.6052,39.73739000000001],"type":"Point"}
}