{
  "type": "Feature",
  "properties": {
    "gn:admin1_code":"15.0",
    "gn:asciiname":"Tongjol-li",
    "gn:country_code":"KP",
    "gn:dem":9,
    "gn:feature_class":"P",
    "gn:feature_code":"PPL",
    "gn:name":"Tongj\u014fl-li",
    "gn:population":0,
    "gn:timezone":"Asia/Pyongyang",
    "iso:country":"KP",
    "name:kor_x_preferred":[
        "\ub3d9\uc804\ub9ac"
    ],
    "name:kor_x_variant":[
        "Tongj\u014fl-li"
    ],
    "wof:name":"Tongjol-li",
    "wof:placetype":"locality"
},
  "geometry": {"coordinates":[125.59694,38.69278],"type":"Point"}
}