{
  "type": "Feature",
  "properties": {
    "gn:admin1_code":"6.0",
    "gn:asciiname":"Sanghak-tong",
    "gn:country_code":"KP",
    "gn:dem":183,
    "gn:feature_class":"P",
    "gn:feature_code":"PPL",
    "gn:name":"Sanghak-tong",
    "gn:population":0,
    "gn:timezone":"Asia/Pyongyang",
    "iso:country":"KP",
    "wof:name":"Sanghak-tong",
    "wof:placetype":"locality"
},
  "geometry": {"coordinates":[125.63222,38.23528],"type":"Point"}
}