{
  "type": "Feature",
  "properties": {
    "gn:admin1_code":"7.0",
    "gn:asciiname":"Changjwa-dong",
    "gn:country_code":"KP",
    "gn:dem":62,
    "gn:feature_class":"P",
    "gn:feature_code":"PPL",
    "gn:name":"Changjwa-dong",
    "gn:population":0,
    "gn:timezone":"Asia/Pyongyang",
    "iso:country":"KP",
    "name:und_x_variant":[
        "\uc7a5\uc88c\ub3d9",
        "Changjwa-dong"
    ],
    "wof:name":"Changjwa-dong",
    "wof:placetype":"locality"
},
  "geometry": {"coordinates":[126.54555999999999,38.25],"type":"Point"}
}