{
  "type": "Feature",
  "properties": {
    "gn:admin1_code":"11.0",
    "gn:asciiname":"Soha-dong",
    "gn:country_code":"KP",
    "gn:dem":13,
    "gn:feature_class":"P",
    "gn:feature_code":"PPL",
    "gn:name":"S\u014fha-dong",
    "gn:population":0,
    "gn:timezone":"Asia/Pyongyang",
    "iso:country":"KP",
    "name:und_x_variant":[
        "\uc11c\ud558\ub3d9",
        "S\u014fha-dong"
    ],
    "wof:name":"Soha-dong",
    "wof:placetype":"locality"
},
  "geometry": {"coordinates":[124.57193999999998,40.06722],"type":"Point"}
}