{
  "type": "Feature",
  "properties": {
    "gn:admin1_code":"15.0",
    "gn:asciiname":"Sangnimsan",
    "gn:country_code":"KP",
    "gn:dem":176,
    "gn:feature_class":"P",
    "gn:feature_code":"PPL",
    "gn:name":"Sangnimsan",
    "gn:population":0,
    "gn:timezone":"Asia/Pyongyang",
    "iso:country":"KP",
    "name:kor_x_preferred":[
        "\uc0c1\ub9bc\uc0b0"
    ],
    "wof:name":"Sangnimsan",
    "wof:placetype":"locality"
},
  "geometry": {"coordinates":[125.56222,39.21417],"type":"Point"}
}