{
  "type": "Feature",
  "properties": {
    "gn:admin1_code":"6.0",
    "gn:asciiname":"Ibam-ni",
    "gn:country_code":"KP",
    "gn:dem":107,
    "gn:feature_class":"P",
    "gn:feature_code":"PPL",
    "gn:name":"Ibam-ni",
    "gn:population":0,
    "gn:timezone":"Asia/Pyongyang",
    "iso:country":"KP",
    "name:eng_x_preferred":[
        "Ibam"
    ],
    "name:eng_x_variant":[
        "Ibam-ni"
    ],
    "wof:name":"Ibam",
    "wof:placetype":"locality"
},
  "geometry": {"coordinates":[126.15861,38.12889],"type":"Point"}
}