{
  "type": "Feature",
  "properties": {
    "gn:admin1_code":"11.0",
    "gn:asciiname":"Osal-li",
    "gn:cc2":"KP",
    "gn:country_code":"KP",
    "gn:dem":26,
    "gn:feature_class":"P",
    "gn:feature_code":"PPL",
    "gn:name":"Osal-li",
    "gn:population":0,
    "gn:timezone":"Asia/Pyongyang",
    "iso:country":"KP",
    "name:kor_x_preferred":[
        "\uc624\uc0b0\ub9ac"
    ],
    "name:und_x_variant":[
        "Osan-ni",
        "Osal-li"
    ],
    "wof:name":"Osal-li",
    "wof:placetype":"locality"
},
  "geometry": {"coordinates":[125.29333,39.6025],"type":"Point"}
}