{
  "type": "Feature",
  "properties": {
    "gn:admin1_code":"11.0",
    "gn:asciiname":"Ijong-ni",
    "gn:country_code":"KP",
    "gn:dem":157,
    "gn:feature_class":"P",
    "gn:feature_code":"PPL",
    "gn:name":"Ij\u014fng-ni",
    "gn:population":0,
    "gn:timezone":"Asia/Pyongyang",
    "iso:country":"KP",
    "name:eng_x_preferred":[
        "Ijong"
    ],
    "name:eng_x_variant":[
        "Ijong-ni"
    ],
    "wof:name":"Ijong",
    "wof:placetype":"locality"
},
  "geometry": {"coordinates":[124.88556,40.35083],"type":"Point"}
}