{
  "type": "Feature",
  "properties": {
    "gn:admin1_code":"15.0",
    "gn:asciiname":"Kyegyo-dong",
    "gn:country_code":"KP",
    "gn:dem":42,
    "gn:feature_class":"P",
    "gn:feature_code":"PPL",
    "gn:name":"Kyegyo-dong",
    "gn:population":0,
    "gn:timezone":"Asia/Pyongyang",
    "iso:country":"KP",
    "wof:name":"Kyegyo-dong",
    "wof:placetype":"locality"
},
  "geometry": {"coordinates":[125.98917,39.24111],"type":"Point"}
}