{
  "type": "Feature",
  "properties": {
    "gn:admin1_code":"17.0",
    "gn:asciiname":"Komoru",
    "gn:country_code":"KP",
    "gn:dem":6,
    "gn:feature_class":"P",
    "gn:feature_code":"PPL",
    "gn:name":"K\u014fmoru",
    "gn:population":0,
    "gn:timezone":"Asia/Pyongyang",
    "iso:country":"KP",
    "name:und_x_variant":[
        "K\u014fu",
        "\uac70\ubaa8\ub8e8",
        "K\u014fmoru"
    ],
    "wof:name":"Komoru",
    "wof:placetype":"locality"
},
  "geometry": {"coordinates":[129.33306000000002,40.7375],"type":"Point"}
}