{
  "type": "Feature",
  "properties": {
    "gn:admin1_code":"6.0",
    "gn:asciiname":"Hangnyong-dong",
    "gn:country_code":"KP",
    "gn:dem":11,
    "gn:feature_class":"P",
    "gn:feature_code":"PPL",
    "gn:name":"Hangny\u014fng-dong",
    "gn:population":0,
    "gn:timezone":"Asia/Pyongyang",
    "iso:country":"KP",
    "name:kor_x_preferred":[
        "Hangny\u014fng-dong"
    ],
    "name:kor_x_variant":[
        "\ud559\ub839\ub3d9"
    ],
    "wof:name":"Hangnyong-dong",
    "wof:placetype":"locality"
},
  "geometry": {"coordinates":[125.09556000000001,38.09583],"type":"Point"}
}