{
  "type": "Feature",
  "properties": {
    "gn:admin1_code":"17.0",
    "gn:asciiname":"Hap'ungch'on-dong",
    "gn:country_code":"KP",
    "gn:dem":96,
    "gn:feature_class":"P",
    "gn:feature_code":"PPL",
    "gn:name":"Hap\u2019ungch\u2019\u014fn-dong",
    "gn:population":0,
    "gn:timezone":"Asia/Pyongyang",
    "iso:country":"KP",
    "name:und_x_variant":[
        "\ud558\ud48d\ucc9c\ub3d9",
        "Hap\u2019ungch\u2019\u014fn-tong",
        "Hap\u2019ungch\u2019\u014fn-dong"
    ],
    "wof:name":"Hap'ungch'on-dong",
    "wof:placetype":"locality"
},
  "geometry": {"coordinates":[130.04083,42.93583],"type":"Point"}
}