{
  "type": "Feature",
  "properties": {
    "gn:admin1_code":"6.0",
    "gn:asciiname":"Sohulgot",
    "gn:country_code":"KP",
    "gn:dem":71,
    "gn:feature_class":"P",
    "gn:feature_code":"PPL",
    "gn:name":"Soh\u016dlgot",
    "gn:population":0,
    "gn:timezone":"Asia/Pyongyang",
    "iso:country":"KP",
    "name:kor_x_preferred":[
        "\uc18c\ud758\uacf6"
    ],
    "name:und_x_variant":[
        "Soolgwan",
        "Somalkot",
        "Soh\u016dlgot",
        "\uc18c\ud758\uacf3"
    ],
    "wof:name":"Sohulgot",
    "wof:placetype":"locality"
},
  "geometry": {"coordinates":[125.25472000000001,37.90556],"type":"Point"}
}