{
  "type": "Feature",
  "properties": {
    "gn:admin1_code":"17.0",
    "gn:asciiname":"Changp'yong-ni",
    "gn:country_code":"KP",
    "gn:dem":112,
    "gn:feature_class":"P",
    "gn:feature_code":"PPLL",
    "gn:name":"Changp\u2019y\u014fng-ni",
    "gn:population":0,
    "gn:timezone":"Asia/Pyongyang",
    "iso:country":"KP",
    "name:und_x_variant":[
        "\uc7a5\ud3c9\ub9ac",
        "Changp\u2019y\u014fng-ni"
    ],
    "wof:name":"Changp'yong-ni",
    "wof:placetype":"locality"
},
  "geometry": {"coordinates":[130.26417000000001,42.615],"type":"Point"}
}