{
  "type": "Feature",
  "properties": {
    "gn:admin1_code":"13.0",
    "gn:asciiname":"Maktokpol",
    "gn:country_code":"KP",
    "gn:dem":1139,
    "gn:feature_class":"P",
    "gn:feature_code":"PPL",
    "gn:name":"Makt\u014fkp\u014fl",
    "gn:population":0,
    "gn:timezone":"Asia/Pyongyang",
    "iso:country":"KP",
    "name:und_x_variant":[
        "\ub9c9\ub355\ubc8c",
        "Makt\u014fkp\u014fl"
    ],
    "wof:name":"Maktokpol",
    "wof:placetype":"locality"
},
  "geometry": {"coordinates":[128.30222000000001,40.81333],"type":"Point"}
}