{
  "type": "Feature",
  "properties": {
    "gn:admin1_code":"3.0",
    "gn:asciiname":"Kogae-gol",
    "gn:country_code":"KP",
    "gn:dem":319,
    "gn:feature_class":"P",
    "gn:feature_code":"PPL",
    "gn:name":"Kogae-gol",
    "gn:population":0,
    "gn:timezone":"Asia/Pyongyang",
    "iso:country":"KP",
    "name:und_x_variant":[
        "Kogae-kol",
        "Kogae-dong",
        "\uace0\uac1c\uace8",
        "Kogae-gol"
    ],
    "wof:name":"Kogae-gol",
    "wof:placetype":"locality"
},
  "geometry": {"coordinates":[127.26611,39.92306],"type":"Point"}
}