{
  "type": "Feature",
  "properties": {
    "gn:admin1_code":"3.0",
    "gn:asciiname":"Kun-gol",
    "gn:country_code":"KP",
    "gn:dem":583,
    "gn:feature_class":"P",
    "gn:feature_code":"PPL",
    "gn:name":"K\u016dn-gol",
    "gn:population":0,
    "gn:timezone":"Asia/Pyongyang",
    "iso:country":"KP",
    "name:und_x_variant":[
        "\ud070\uace8",
        "K\u016dn-gol"
    ],
    "wof:name":"Kun-gol",
    "wof:placetype":"locality"
},
  "geometry": {"coordinates":[128.66806,40.56417],"type":"Point"}
}