{
  "type": "Feature",
  "properties": {
    "gn:admin1_code":"3.0",
    "gn:asciiname":"Songdondae",
    "gn:country_code":"KP",
    "gn:dem":99,
    "gn:feature_class":"P",
    "gn:feature_code":"PPL",
    "gn:name":"Songdondae",
    "gn:population":0,
    "gn:timezone":"Asia/Pyongyang",
    "iso:country":"KP",
    "name:und_x_variant":[
        "\uc1a1\ub3c8\ub300"
    ],
    "wof:name":"Songdondae",
    "wof:placetype":"locality"
},
  "geometry": {"coordinates":[128.23278999999999,40.15122],"type":"Point"}
}