{
  "type": "Feature",
  "properties": {
    "gn:admin1_code":"17.0",
    "gn:asciiname":"Chaet'o",
    "gn:country_code":"KP",
    "gn:dem":313,
    "gn:feature_class":"P",
    "gn:feature_code":"PPL",
    "gn:name":"Chaet\u2019\u014f",
    "gn:population":0,
    "gn:timezone":"Asia/Pyongyang",
    "iso:country":"KP",
    "name:und_x_variant":[
        "\uc7ac\ud130",
        "Chaet\u2019\u014f"
    ],
    "wof:name":"Chaet'o",
    "wof:placetype":"locality"
},
  "geometry": {"coordinates":[129.11667,40.88472],"type":"Point"}
}