{
  "type": "Feature",
  "properties": {
    "gn:admin1_code":"6.0",
    "gn:asciiname":"Kuryong-dong",
    "gn:country_code":"KP",
    "gn:dem":231,
    "gn:feature_class":"P",
    "gn:feature_code":"PPL",
    "gn:name":"Kuryong-dong",
    "gn:population":0,
    "gn:timezone":"Asia/Pyongyang",
    "iso:country":"KP",
    "name:kor_x_preferred":[
        "\uad6c\ub8e1\ub3d9"
    ],
    "wof:name":"Kuryong-dong",
    "wof:placetype":"locality"
},
  "geometry": {"coordinates":[125.55194,38.19222],"type":"Point"}
}