{
  "type": "Feature",
  "properties": {
    "gn:admin1_code":"15.0",
    "gn:asciiname":"Yongsu-dong",
    "gn:country_code":"KP",
    "gn:dem":100,
    "gn:feature_class":"P",
    "gn:feature_code":"PPL",
    "gn:name":"Yongsu-dong",
    "gn:population":0,
    "gn:timezone":"Asia/Pyongyang",
    "iso:country":"KP",
    "wof:name":"Yongsu-dong",
    "wof:placetype":"locality"
},
  "geometry": {"coordinates":[125.44472,39.09472],"type":"Point"}
}