{
  "type": "Feature",
  "properties": {
    "gn:admin1_code":"9.0",
    "gn:asciiname":"Murung-dong",
    "gn:cc2":"KP",
    "gn:country_code":"KP",
    "gn:dem":104,
    "gn:feature_class":"P",
    "gn:feature_code":"PPL",
    "gn:name":"Mur\u016dng-dong",
    "gn:population":0,
    "gn:timezone":"Asia/Pyongyang",
    "iso:country":"KP",
    "name:und_x_variant":[
        "Bury\u014d-d\u014d",
        "Mur\u016dng-dong"
    ],
    "wof:name":"Murung-dong",
    "wof:placetype":"locality"
},
  "geometry": {"coordinates":[126.83944,38.35639000000001],"type":"Point"}
}