{
  "type": "Feature",
  "properties": {
    "iso:country":"KP",
    "qs:gn_country":"KP",
    "qs:gn_fcode":"PPLX",
    "qs:gn_pop":0,
    "qs:name":"S\u014fjae-dong",
    "qs:name_adm0":"North Korea",
    "qs:name_adm1":"P\u00b4yongyang-si",
    "qs:photos":2,
    "qs:photos_1k":1,
    "qs:photos_9k":1,
    "qs:photos_9r":1,
    "qs:photos_all":2,
    "qs:photos_sr":1,
    "qs:placetype":"Suburb",
    "qs:pop_sr":"0",
    "qs:woe_adm0":23424865,
    "wof:name":"S\u014fjae-dong",
    "wof:placetype":"neighbourhood"
},
  "geometry": {"coordinates":[125.71194,39.04444],"type":"Point"}
}