{
  "type": "Feature",
  "properties": {
    "gn:admin1_code":"1.0",
    "gn:asciiname":"Mol-gol",
    "gn:country_code":"KP",
    "gn:dem":330,
    "gn:feature_class":"P",
    "gn:feature_code":"PPL",
    "gn:name":"M\u014fl-gol",
    "gn:population":0,
    "gn:timezone":"Asia/Pyongyang",
    "iso:country":"KP",
    "name:und_x_variant":[
        "M\u014fl-kol",
        "\uba40\uace8",
        "W\u014fn-dong",
        "M\u014fl-gol"
    ],
    "wof:name":"Mol-gol",
    "wof:placetype":"locality"
},
  "geometry": {"coordinates":[126.76528,41.69278],"type":"Point"}
}