{
  "type": "Feature",
  "properties": {
    "gn:admin1_code":"17.0",
    "gn:asciiname":"Namyang-nodongjagu",
    "gn:cc2":"KP",
    "gn:country_code":"KP",
    "gn:dem":99,
    "gn:feature_class":"P",
    "gn:feature_code":"PPL",
    "gn:name":"Namyang-nodongjagu",
    "gn:population":0,
    "gn:timezone":"Asia/Pyongyang",
    "iso:country":"KP",
    "name:fra_x_preferred":[
        "Namyang"
    ],
    "name:jpn_x_preferred":[
        "\u5357\u967d\u52b4\u50cd\u8005\u533a"
    ],
    "name:kor_x_preferred":[
        "\ub0a8\uc591\ub85c\ub3d9\uc790\uad6c"
    ],
    "name:nld_x_preferred":[
        "Namyang"
    ],
    "name:nor_x_preferred":[
        "Namyang"
    ],
    "name:swe_x_preferred":[
        "Namyang"
    ],
    "name:und_x_variant":[
        "Nany\u014d-d\u014d",
        "Nany\u014d",
        "Namyang",
        "Ons\u014fng-\u016dp",
        "Ons\u014fng",
        "Namyang-nodongjagu"
    ],
    "name:vie_x_preferred":[
        "Namyang"
    ],
    "name:zho_x_preferred":[
        "\u5357\u967d\u52de\u52d5\u8005\u5340"
    ],
    "wof:name":"Namyang-nodongjagu",
    "wof:placetype":"locality"
},
  "geometry": {"coordinates":[129.85721999999998,42.95389],"type":"Point"}
}