{
  "type": "Feature",
  "properties": {
    "gn:admin1_code":"7.0",
    "gn:asciiname":"Yongbong-dong",
    "gn:country_code":"KP",
    "gn:dem":192,
    "gn:feature_class":"P",
    "gn:feature_code":"PPL",
    "gn:name":"Yongbong-dong",
    "gn:population":0,
    "gn:timezone":"Asia/Pyongyang",
    "iso:country":"KP",
    "wof:name":"Yongbong-dong",
    "wof:placetype":"locality"
},
  "geometry": {"coordinates":[126.28417,38.72111],"type":"Point"}
}