{
  "type": "Feature",
  "properties": {
    "gn:admin1_code":"1.0",
    "gn:asciiname":"Yongam-dong",
    "gn:country_code":"KP",
    "gn:dem":323,
    "gn:feature_class":"P",
    "gn:feature_code":"PPL",
    "gn:name":"Yongam-dong",
    "gn:population":0,
    "gn:timezone":"Asia/Pyongyang",
    "iso:country":"KP",
    "name:und_x_variant":[
        "\uc6a9\uc554\ub3d9",
        "Yongam-dong"
    ],
    "wof:name":"Yongam-dong",
    "wof:placetype":"locality"
},
  "geometry": {"coordinates":[126.35028,40.96778],"type":"Point"}
}