{
  "type": "Feature",
  "properties": {
    "gn:admin1_code":"6.0",
    "gn:asciiname":"Sach'ol-li",
    "gn:country_code":"KP",
    "gn:dem":61,
    "gn:feature_class":"P",
    "gn:feature_code":"PPL",
    "gn:name":"Sach\u2019\u014fl-li",
    "gn:population":0,
    "gn:timezone":"Asia/Pyongyang",
    "iso:country":"KP",
    "name:kor_x_preferred":[
        "\uc0ac\ucc9c\ub9ac"
    ],
    "name:und_x_variant":[
        "Sach\u2019\u014fn-ni",
        "Sach\u2019\u014fl-li"
    ],
    "wof:name":"Sach'ol-li",
    "wof:placetype":"locality"
},
  "geometry": {"coordinates":[125.46556,38.08472],"type":"Point"}
}