{
  "type": "Feature",
  "properties": {
    "gn:admin1_code":"9.0",
    "gn:asciiname":"P'anmi-dong",
    "gn:country_code":"KP",
    "gn:dem":49,
    "gn:feature_class":"P",
    "gn:feature_code":"PPL",
    "gn:name":"P\u2019anmi-dong",
    "gn:population":0,
    "gn:timezone":"Asia/Pyongyang",
    "iso:country":"KP",
    "wof:name":"P'anmi-dong",
    "wof:placetype":"locality"
},
  "geometry": {"coordinates":[127.56972,39.0625],"type":"Point"}
}