{
  "type": "Feature",
  "properties": {
    "gn:admin1_code":"9.0",
    "gn:admin2_code":"Ch\u2019\u014frw\u014fn-gun",
    "gn:asciiname":"Samsa-ri",
    "gn:country_code":"KP",
    "gn:dem":274,
    "gn:feature_class":"P",
    "gn:feature_code":"PPL",
    "gn:name":"Samsa-ri",
    "gn:population":0,
    "gn:timezone":"Asia/Pyongyang",
    "iso:country":"KP",
    "wof:name":"Samsa-ri",
    "wof:placetype":"locality"
},
  "geometry": {"coordinates":[127.22194,38.33667],"type":"Point"}
}