{
  "type": "Feature",
  "properties": {
    "gn:admin1_code":"7.0",
    "gn:asciiname":"Sokhyol-li",
    "gn:country_code":"KP",
    "gn:dem":304,
    "gn:feature_class":"P",
    "gn:feature_code":"PPL",
    "gn:name":"S\u014fkhy\u014fl-li",
    "gn:population":0,
    "gn:timezone":"Asia/Pyongyang",
    "iso:country":"KP",
    "name:kor_x_preferred":[
        "\uc11d\ud604\ub9ac"
    ],
    "name:kor_x_variant":[
        "S\u014fkhy\u014fl-li"
    ],
    "name:und_x_variant":[
        "S\u014fkhy\u014fn-ni"
    ],
    "wof:name":"Sokhyol-li",
    "wof:placetype":"locality"
},
  "geometry": {"coordinates":[126.42333000000001,38.86139],"type":"Point"}
}