{
  "type": "Feature",
  "properties": {
    "gn:admin1_code":"9.0",
    "gn:asciiname":"Kolp'aji",
    "gn:country_code":"KP",
    "gn:dem":153,
    "gn:feature_class":"P",
    "gn:feature_code":"PPL",
    "gn:name":"Kolp\u2019aji",
    "gn:population":0,
    "gn:timezone":"Asia/Pyongyang",
    "iso:country":"KP",
    "wof:name":"Kolp'aji",
    "wof:placetype":"locality"
},
  "geometry": {"coordinates":[127.04611,38.40028],"type":"Point"}
}