{
  "type": "Feature",
  "properties": {
    "gn:admin1_code":"6.0",
    "gn:asciiname":"Inbong-ni",
    "gn:country_code":"KP",
    "gn:dem":18,
    "gn:feature_class":"P",
    "gn:feature_code":"PPL",
    "gn:name":"Inbong-ni",
    "gn:population":0,
    "gn:timezone":"Asia/Pyongyang",
    "iso:country":"KP",
    "name:eng_x_preferred":[
        "Inbong"
    ],
    "name:eng_x_variant":[
        "Inbong-ni"
    ],
    "name:und_x_variant":[
        "\uc778\ubd09\ub9ac",
        "Inbong-ni"
    ],
    "wof:name":"Inbong",
    "wof:placetype":"locality"
},
  "geometry": {"coordinates":[125.52028,37.87056],"type":"Point"}
}