{
  "type": "Feature",
  "properties": {
    "gn:admin1_code":"7.0",
    "gn:asciiname":"Togo-ri",
    "gn:country_code":"KP",
    "gn:dem":97,
    "gn:feature_class":"P",
    "gn:feature_code":"PPL",
    "gn:name":"T\u014fg\u014f-ri",
    "gn:population":0,
    "gn:timezone":"Asia/Pyongyang",
    "iso:country":"KP",
    "wof:name":"Togo-ri",
    "wof:placetype":"locality"
},
  "geometry": {"coordinates":[126.18416999999999,38.4475],"type":"Point"}
}