{
  "type": "Feature",
  "properties": {
    "gn:admin1_code":"15.0",
    "gn:asciiname":"Chech'ung-gol",
    "gn:country_code":"KP",
    "gn:dem":28,
    "gn:feature_class":"P",
    "gn:feature_code":"PPL",
    "gn:name":"Chech\u2019ung-gol",
    "gn:population":0,
    "gn:timezone":"Asia/Pyongyang",
    "iso:country":"KP",
    "wof:name":"Chech'ung-gol",
    "wof:placetype":"locality"
},
  "geometry": {"coordinates":[125.51194,39.10167],"type":"Point"}
}