{
  "type": "Feature",
  "properties": {
    "gn:admin1_code":"17.0",
    "gn:asciiname":"Kanggon-dong",
    "gn:country_code":"KP",
    "gn:dem":413,
    "gn:feature_class":"P",
    "gn:feature_code":"PPL",
    "gn:name":"Kangg\u014fn-dong",
    "gn:population":0,
    "gn:timezone":"Asia/Pyongyang",
    "iso:country":"KP",
    "wof:name":"Kanggon-dong",
    "wof:placetype":"locality"
},
  "geometry": {"coordinates":[129.65000000000001,40.93333],"type":"Point"}
}