{
  "type": "Feature",
  "properties": {
    "gn:admin1_code":"7.0",
    "gn:asciiname":"Wolch'ol-li",
    "gn:country_code":"KP",
    "gn:dem":54,
    "gn:feature_class":"P",
    "gn:feature_code":"PPL",
    "gn:name":"W\u014flch\u2019\u014fl-li",
    "gn:population":0,
    "gn:timezone":"Asia/Pyongyang",
    "iso:country":"KP",
    "name:kor_x_preferred":[
        "\uc6d4\ucc9c\ub9ac"
    ],
    "name:kor_x_variant":[
        "W\u014flch\u2019\u014fl-li"
    ],
    "wof:name":"Wolch'ol-li",
    "wof:placetype":"locality"
},
  "geometry": {"coordinates":[126.44556,38.37],"type":"Point"}
}