{
  "type": "Feature",
  "properties": {
    "gn:admin1_code":"0.0",
    "gn:asciiname":"Habung-ni",
    "gn:country_code":"KP",
    "gn:dem":49,
    "gn:feature_class":"P",
    "gn:feature_code":"PPL",
    "gn:name":"Habung-ni",
    "gn:population":0,
    "gn:timezone":"Asia/Pyongyang",
    "iso:country":"KP",
    "name:kor_x_preferred":[
        "\ud558\ubd81\ub9ac"
    ],
    "wof:name":"Habung-ni",
    "wof:placetype":"locality"
},
  "geometry": {"coordinates":[125.57167,39.74694],"type":"Point"}
}