{
  "type": "Feature",
  "properties": {
    "gn:admin1_code":"11.0",
    "gn:asciiname":"Soak",
    "gn:country_code":"KP",
    "gn:dem":79,
    "gn:feature_class":"P",
    "gn:feature_code":"PPL",
    "gn:name":"S\u014fak",
    "gn:population":0,
    "gn:timezone":"Asia/Pyongyang",
    "iso:country":"KP",
    "name:deu_x_preferred":[
        "Soak"
    ],
    "name:und_x_variant":[
        "\uc11c\uc545",
        "S\u014fak"
    ],
    "wof:name":"Soak",
    "wof:placetype":"locality"
},
  "geometry": {"coordinates":[124.78139,40.33361],"type":"Point"}
}