{
  "type": "Feature",
  "properties": {
    "gn:admin1_code":"1.0",
    "gn:asciiname":"Hap'yongch'am",
    "gn:country_code":"KP",
    "gn:dem":418,
    "gn:feature_class":"P",
    "gn:feature_code":"PPL",
    "gn:name":"Hap\u2019y\u014fngch\u2019am",
    "gn:population":0,
    "gn:timezone":"Asia/Pyongyang",
    "iso:country":"KP",
    "name:und_x_variant":[
        "\ud558\ud3c9\ucc38",
        "Hap\u2019y\u014fngch\u2019am"
    ],
    "wof:name":"Hap'yongch'am",
    "wof:placetype":"locality"
},
  "geometry": {"coordinates":[126.58778,40.22194],"type":"Point"}
}