{
  "type": "Feature",
  "properties": {
    "gn:admin1_code":"6.0",
    "gn:asciiname":"Kuryong-ni",
    "gn:country_code":"KP",
    "gn:dem":13,
    "gn:feature_class":"P",
    "gn:feature_code":"PPL",
    "gn:name":"Kuryong-ni",
    "gn:population":0,
    "gn:timezone":"Asia/Pyongyang",
    "iso:country":"KP",
    "name:kor_x_preferred":[
        "\uad6c\ub8e1\ub9ac"
    ],
    "name:und_x_variant":[
        "Kuyong-ni"
    ],
    "wof:name":"Kuryong-ni",
    "wof:placetype":"locality"
},
  "geometry": {"coordinates":[126.1225,37.79583],"type":"Point"}
}