{
  "type": "Feature",
  "properties": {
    "gn:admin1_code":"17.0",
    "gn:asciiname":"T'app'yong-dong",
    "gn:country_code":"KP",
    "gn:dem":55,
    "gn:feature_class":"P",
    "gn:feature_code":"PPL",
    "gn:name":"T\u2019app\u2019y\u014fng-dong",
    "gn:population":0,
    "gn:timezone":"Asia/Pyongyang",
    "iso:country":"KP",
    "name:und_x_variant":[
        "T\u2019app\u2019y\u014fng-ni",
        "\ud0d1\ud3c9\ub3d9",
        "T\u2019app\u2019y\u014fng-dong"
    ],
    "wof:name":"T'app'yong-dong",
    "wof:placetype":"locality"
},
  "geometry": {"coordinates":[129.21306000000001,40.81222],"type":"Point"}
}