{
  "type": "Feature",
  "properties": {
    "gn:admin1_code":"17.0",
    "gn:asciiname":"Ponggang-ni",
    "gn:country_code":"KP",
    "gn:dem":17,
    "gn:feature_class":"P",
    "gn:feature_code":"PPLL",
    "gn:name":"Ponggang-ni",
    "gn:population":0,
    "gn:timezone":"Asia/Pyongyang",
    "iso:country":"KP",
    "name:eng_x_preferred":[
        "Ponggang"
    ],
    "name:eng_x_variant":[
        "Ponggang-ni"
    ],
    "name:und_x_variant":[
        "H\u014fk\u014f",
        "Ponggang",
        "H\u014fk\u014f-d\u014f",
        "Ponggang-dong",
        "\ubd09\uac15\ub9ac",
        "Ponggang-ni"
    ],
    "wof:name":"Ponggang",
    "wof:placetype":"locality"
},
  "geometry": {"coordinates":[129.65528,41.34278],"type":"Point"}
}