{
  "type": "Feature",
  "properties": {
    "gn:admin1_code":"9.0",
    "gn:asciiname":"Chuktae-ri",
    "gn:country_code":"KP",
    "gn:dem":312,
    "gn:feature_class":"P",
    "gn:feature_code":"PPL",
    "gn:name":"Chuktae-ri",
    "gn:population":0,
    "gn:timezone":"Asia/Pyongyang",
    "iso:country":"KP",
    "name:und_x_variant":[
        "\uc8fd\ub300\ub9ac",
        "Chuktae-ri"
    ],
    "wof:name":"Chuktae-ri",
    "wof:placetype":"locality"
},
  "geometry": {"coordinates":[127.60944000000001,38.3575],"type":"Point"}
}