{
  "type": "Feature",
  "properties": {
    "gn:admin1_code":"13.0",
    "gn:asciiname":"Sindong-ni",
    "gn:country_code":"KP",
    "gn:dem":1439,
    "gn:feature_class":"P",
    "gn:feature_code":"PPL",
    "gn:name":"Sind\u014fng-ni",
    "gn:population":0,
    "gn:timezone":"Asia/Pyongyang",
    "iso:country":"KP",
    "name:eng_x_preferred":[
        "Sindong"
    ],
    "name:eng_x_variant":[
        "Sindong-ni"
    ],
    "wof:name":"Sindong",
    "wof:placetype":"locality"
},
  "geometry": {"coordinates":[128.77610999999999,41.02472],"type":"Point"}
}