{
  "type": "Feature",
  "properties": {
    "gn:admin1_code":"9.0",
    "gn:asciiname":"P'o-ri",
    "gn:country_code":"KP",
    "gn:dem":48,
    "gn:feature_class":"P",
    "gn:feature_code":"PPL",
    "gn:name":"P\u2019o-ri",
    "gn:population":0,
    "gn:timezone":"Asia/Pyongyang",
    "iso:country":"KP",
    "name:und_x_variant":[
        "P\u2019o-ri",
        "\ud3ec\ub9ac"
    ],
    "wof:name":"P'o-ri",
    "wof:placetype":"locality"
},
  "geometry": {"coordinates":[127.42471999999999,39.07417],"type":"Point"}
}