{
  "type": "Feature",
  "properties": {
    "gn:admin1_code":"7.0",
    "gn:asciiname":"Won'galgogae",
    "gn:country_code":"KP",
    "gn:dem":97,
    "gn:feature_class":"P",
    "gn:feature_code":"PPL",
    "gn:name":"W\u014fn\u2019galgogae",
    "gn:population":0,
    "gn:timezone":"Asia/Pyongyang",
    "iso:country":"KP",
    "name:und_x_variant":[
        "W\u014fn\u2019galkogae",
        "W\u014fn\u2019galgogae"
    ],
    "wof:name":"Won'galgogae",
    "wof:placetype":"locality"
},
  "geometry": {"coordinates":[126.63833,38.36472],"type":"Point"}
}