{
  "type": "Feature",
  "properties": {
    "gn:admin1_code":"13.0",
    "gn:asciiname":"Usang-ni",
    "gn:country_code":"KP",
    "gn:dem":821,
    "gn:feature_class":"P",
    "gn:feature_code":"PPL",
    "gn:name":"Usang-ni",
    "gn:population":0,
    "gn:timezone":"Asia/Pyongyang",
    "iso:country":"KP",
    "name:kor_x_preferred":[
        "\uc6b0\uc0c1\ub9ac"
    ],
    "wof:name":"Usang-ni",
    "wof:placetype":"locality"
},
  "geometry": {"coordinates":[128.22693999999998,41.14722],"type":"Point"}
}