{
  "type": "Feature",
  "properties": {
    "gn:admin1_code":"18.0",
    "gn:asciiname":"Yonghyon-dong",
    "gn:country_code":"KP",
    "gn:dem":8,
    "gn:feature_class":"P",
    "gn:feature_code":"PPL",
    "gn:name":"Yonghy\u014fn-dong",
    "gn:population":0,
    "gn:timezone":"Asia/Pyongyang",
    "iso:country":"KP",
    "name:und_x_variant":[
        "\uc6a9\ud604\ub3d9",
        "Chosal-li",
        "Yonghy\u014fn-dong",
        "Yonghyeondong"
    ],
    "wof:name":"Yonghyon-dong",
    "wof:placetype":"locality"
},
  "geometry": {"coordinates":[130.62738000000002,42.40475],"type":"Point"}
}