{
  "type": "Feature",
  "properties": {
    "gn:admin1_code":"15.0",
    "gn:asciiname":"Song-dong",
    "gn:country_code":"KP",
    "gn:dem":434,
    "gn:feature_class":"P",
    "gn:feature_code":"PPL",
    "gn:name":"Song-dong",
    "gn:population":0,
    "gn:timezone":"Asia/Pyongyang",
    "iso:country":"KP",
    "name:und_x_variant":[
        "\uc1a1\ub3d9",
        "Song-dong"
    ],
    "wof:name":"Song-dong",
    "wof:placetype":"locality"
},
  "geometry": {"coordinates":[126.60138999999999,39.78694],"type":"Point"}
}