{
  "type": "Feature",
  "properties": {
    "gn:admin1_code":"17.0",
    "gn:asciiname":"Yuk-tong",
    "gn:country_code":"KP",
    "gn:dem":343,
    "gn:feature_class":"P",
    "gn:feature_code":"PPL",
    "gn:name":"Yuk-tong",
    "gn:population":0,
    "gn:timezone":"Asia/Pyongyang",
    "iso:country":"KP",
    "name:und_x_variant":[
        "\uc721\ub3d9",
        "Yuk-tong"
    ],
    "wof:name":"Yuk-tong",
    "wof:placetype":"locality"
},
  "geometry": {"coordinates":[129.3425,42.41722],"type":"Point"}
}