{
  "type": "Feature",
  "properties": {
    "gn:admin1_code":"0.0",
    "gn:asciiname":"Hakhyon-dong",
    "gn:country_code":"KP",
    "gn:dem":51,
    "gn:feature_class":"P",
    "gn:feature_code":"PPL",
    "gn:name":"Hakhy\u014fn-dong",
    "gn:population":0,
    "gn:timezone":"Asia/Pyongyang",
    "iso:country":"KP",
    "name:kor_x_preferred":[
        "\ud559\ud604\ub3d9"
    ],
    "name:und_x_variant":[
        "Hakhy\u014fn-dong"
    ],
    "wof:name":"Hakhyon-dong",
    "wof:placetype":"locality"
},
  "geometry": {"coordinates":[125.31667,37.91667],"type":"Point"}
}