{
  "type": "Feature",
  "properties": {
    "gn:admin1_code":"15.0",
    "gn:asciiname":"Ryonghori'nongol",
    "gn:country_code":"KP",
    "gn:dem":67,
    "gn:feature_class":"P",
    "gn:feature_code":"PPL",
    "gn:name":"Ryonghori\u2019nongol",
    "gn:population":0,
    "gn:timezone":"Asia/Pyongyang",
    "iso:country":"KP",
    "name:kor_x_preferred":[
        "\ub8e1\ud638\ub9ac\ub17c\uace8"
    ],
    "name:und_x_variant":[
        "Ryonghori\u2019nongol",
        "Yonghori-Non-gol"
    ],
    "wof:name":"Ryonghori'nongol",
    "wof:placetype":"locality"
},
  "geometry": {"coordinates":[125.85056000000002,39.66056],"type":"Point"}
}