{
  "type": "Feature",
  "properties": {
    "gn:admin1_code":"6.0",
    "gn:asciiname":"Yangji",
    "gn:country_code":"KP",
    "gn:dem":34,
    "gn:feature_class":"P",
    "gn:feature_code":"PPL",
    "gn:name":"Yangji",
    "gn:population":0,
    "gn:timezone":"Asia/Pyongyang",
    "iso:country":"KP",
    "name:und_x_variant":[
        "\uc591\uc9c0",
        "Yangji"
    ],
    "wof:name":"Yangji",
    "wof:placetype":"locality"
},
  "geometry": {"coordinates":[125.6075,37.97472],"type":"Point"}
}