{
  "type": "Feature",
  "properties": {
    "gn:admin1_code":"12.0",
    "gn:asciiname":"Sobang-dong",
    "gn:country_code":"KP",
    "gn:dem":45,
    "gn:feature_class":"P",
    "gn:feature_code":"PPL",
    "gn:name":"S\u014fbang-dong",
    "gn:population":0,
    "gn:timezone":"Asia/Pyongyang",
    "iso:country":"KP",
    "name:kor_x_preferred":[
        "\uc11c\ubc29\ub3d9"
    ],
    "name:und_x_variant":[
        "S\u014fbang-dong",
        "Seobangdong"
    ],
    "wof:name":"Sobang-dong",
    "wof:placetype":"locality"
},
  "geometry": {"coordinates":[125.72,39.10917],"type":"Point"}
}