{
  "type": "Feature",
  "properties": {
    "gn:admin1_code":"11.0",
    "gn:asciiname":"Chol-gol",
    "gn:country_code":"KP",
    "gn:dem":225,
    "gn:feature_class":"P",
    "gn:feature_code":"PPL",
    "gn:name":"Ch\u014fl-gol",
    "gn:population":0,
    "gn:timezone":"Asia/Pyongyang",
    "iso:country":"KP",
    "name:und_x_variant":[
        "Sa-dong",
        "Ch\u014fl-gol"
    ],
    "wof:name":"Chol-gol",
    "wof:placetype":"locality"
},
  "geometry": {"coordinates":[124.66667,39.63333],"type":"Point"}
}