{
  "type": "Feature",
  "properties": {
    "gn:admin1_code":"1.0",
    "gn:asciiname":"Munam-dong",
    "gn:country_code":"KP",
    "gn:dem":374,
    "gn:feature_class":"P",
    "gn:feature_code":"PPL",
    "gn:name":"Munam-dong",
    "gn:population":0,
    "gn:timezone":"Asia/Pyongyang",
    "iso:country":"KP",
    "name:und_x_variant":[
        "\ubb38\uc554\ub3d9",
        "Munam-dong"
    ],
    "wof:name":"Munam-dong",
    "wof:placetype":"locality"
},
  "geometry": {"coordinates":[125.85861,40.55472],"type":"Point"}
}