{
  "type": "Feature",
  "properties": {
    "gn:admin1_code":"6.0",
    "gn:asciiname":"Somak-tong",
    "gn:country_code":"KP",
    "gn:dem":157,
    "gn:feature_class":"P",
    "gn:feature_code":"PPL",
    "gn:name":"Somak-tong",
    "gn:population":0,
    "gn:timezone":"Asia/Pyongyang",
    "iso:country":"KP",
    "name:eng_x_preferred":[
        "Somak"
    ],
    "name:eng_x_variant":[
        "Somak-tong"
    ],
    "wof:name":"Somak",
    "wof:placetype":"locality"
},
  "geometry": {"coordinates":[125.59556000000001,38.22722],"type":"Point"}
}