{
  "type": "Feature",
  "properties": {
    "gn:admin1_code":"13.0",
    "gn:asciiname":"Songgi-ri",
    "gn:country_code":"KP",
    "gn:dem":649,
    "gn:feature_class":"P",
    "gn:feature_code":"PPL",
    "gn:name":"S\u014fnggi-ri",
    "gn:population":0,
    "gn:timezone":"Asia/Pyongyang",
    "iso:country":"KP",
    "wof:name":"Songgi-ri",
    "wof:placetype":"locality"
},
  "geometry": {"coordinates":[128.02056000000002,41.38917],"type":"Point"}
}