{
  "type": "Feature",
  "properties": {
    "gn:admin1_code":"11.0",
    "gn:asciiname":"Soin-dong",
    "gn:country_code":"KP",
    "gn:dem":138,
    "gn:feature_class":"P",
    "gn:feature_code":"PPL",
    "gn:name":"S\u014fin-dong",
    "gn:population":0,
    "gn:timezone":"Asia/Pyongyang",
    "iso:country":"KP",
    "name:und_x_variant":[
        "\uc11c\uc778\ub3d9",
        "S\u014fin-dong"
    ],
    "wof:name":"Soin-dong",
    "wof:placetype":"locality"
},
  "geometry": {"coordinates":[124.49639000000001,40.08444],"type":"Point"}
}