{
  "type": "Feature",
  "properties": {
    "gn:admin1_code":"15.0",
    "gn:asciiname":"Pongha-ri",
    "gn:country_code":"KP",
    "gn:dem":204,
    "gn:feature_class":"P",
    "gn:feature_code":"PPL",
    "gn:name":"Pongha-ri",
    "gn:population":0,
    "gn:timezone":"Asia/Pyongyang",
    "iso:country":"KP",
    "name:kor_x_preferred":[
        "\ubd09\ud558\ub9ac"
    ],
    "wof:name":"Pongha-ri",
    "wof:placetype":"locality"
},
  "geometry": {"coordinates":[125.98833,39.60472],"type":"Point"}
}