{
  "type": "Feature",
  "properties": {
    "gn:admin1_code":"3.0",
    "gn:asciiname":"An-ch'on",
    "gn:country_code":"KP",
    "gn:dem":205,
    "gn:feature_class":"P",
    "gn:feature_code":"PPL",
    "gn:name":"An-ch\u2019on",
    "gn:population":0,
    "gn:timezone":"Asia/Pyongyang",
    "iso:country":"KP",
    "name:und_x_variant":[
        "An-ch\u2019on",
        "\uc548\ucd0c"
    ],
    "wof:name":"An-ch'on",
    "wof:placetype":"locality"
},
  "geometry": {"coordinates":[128.66111000000001,40.40306],"type":"Point"}
}