{
  "type": "Feature",
  "properties": {
    "gn:admin1_code":"0.0",
    "gn:asciiname":"Yongdong-ni",
    "gn:cc2":"KP",
    "gn:country_code":"KP",
    "gn:dem":11,
    "gn:feature_class":"P",
    "gn:feature_code":"PPL",
    "gn:name":"Yongdong-ni",
    "gn:population":0,
    "gn:timezone":"Asia/Pyongyang",
    "iso:country":"KP",
    "name:kor_x_preferred":[
        "\uc6a9\ub3d9\ub9ac"
    ],
    "name:und_x_variant":[
        "Ry\u016bd\u014d-ri",
        "Yongdong-ni"
    ],
    "wof:name":"Yongdong-ni",
    "wof:placetype":"locality"
},
  "geometry": {"coordinates":[127.90000000000001,40.03333],"type":"Point"}
}