{
  "type": "Feature",
  "properties": {
    "gn:admin1_code":"17.0",
    "gn:asciiname":"So-dong",
    "gn:country_code":"KP",
    "gn:dem":448,
    "gn:feature_class":"P",
    "gn:feature_code":"PPL",
    "gn:name":"So-dong",
    "gn:population":0,
    "gn:timezone":"Asia/Pyongyang",
    "iso:country":"KP",
    "name:und_x_variant":[
        "\uc18c\ub3d9",
        "So-dong"
    ],
    "wof:name":"So-dong",
    "wof:placetype":"locality"
},
  "geometry": {"coordinates":[129.30916999999999,41.09778],"type":"Point"}
}