{
  "type": "Feature",
  "properties": {
    "gn:admin1_code":"7.0",
    "gn:asciiname":"Songgal-li",
    "gn:country_code":"KP",
    "gn:dem":15,
    "gn:feature_class":"P",
    "gn:feature_code":"PPL",
    "gn:name":"Songgal-li",
    "gn:population":0,
    "gn:timezone":"Asia/Pyongyang",
    "iso:country":"KP",
    "name:kor_x_preferred":[
        "\uc1a1\uac08\ub9ac"
    ],
    "wof:name":"Songgal-li",
    "wof:placetype":"locality"
},
  "geometry": {"coordinates":[125.55916999999999,38.55194],"type":"Point"}
}