{
  "type": "Feature",
  "properties": {
    "gn:admin1_code":"6.0",
    "gn:admin2_code":"Kaep'ung-gun",
    "gn:asciiname":"Haean-gol",
    "gn:country_code":"KP",
    "gn:dem":74,
    "gn:feature_class":"P",
    "gn:feature_code":"PPL",
    "gn:name":"Haean-gol",
    "gn:population":0,
    "gn:timezone":"Asia/Pyongyang",
    "iso:country":"KP",
    "name:und_x_variant":[
        "Haean-dong",
        "Haean-gol"
    ],
    "wof:name":"Haean-gol",
    "wof:placetype":"locality"
},
  "geometry": {"coordinates":[126.48556000000001,37.98667],"type":"Point"}
}