{
  "type": "Feature",
  "properties": {
    "gn:admin1_code":"9.0",
    "gn:asciiname":"Kamaso",
    "gn:country_code":"KP",
    "gn:dem":90,
    "gn:feature_class":"P",
    "gn:feature_code":"PPL",
    "gn:name":"Kamaso",
    "gn:population":0,
    "gn:timezone":"Asia/Pyongyang",
    "iso:country":"KP",
    "wof:name":"Kamaso",
    "wof:placetype":"locality"
},
  "geometry": {"coordinates":[126.83972,38.335],"type":"Point"}
}