{
  "type": "Feature",
  "properties": {
    "gn:admin1_code":"6.0",
    "gn:asciiname":"Changhae",
    "gn:country_code":"KP",
    "gn:dem":15,
    "gn:feature_class":"P",
    "gn:feature_code":"PPL",
    "gn:name":"Changhae",
    "gn:population":0,
    "gn:timezone":"Asia/Pyongyang",
    "iso:country":"KP",
    "name:und_x_variant":[
        "\uc7a5\ud574",
        "Changhae"
    ],
    "wof:name":"Changhae",
    "wof:placetype":"locality"
},
  "geometry": {"coordinates":[125.31583000000001,37.82139],"type":"Point"}
}