{
  "type": "Feature",
  "properties": {
    "gn:admin1_code":"15.0",
    "gn:asciiname":"Samhwa-dong",
    "gn:country_code":"KP",
    "gn:dem":55,
    "gn:feature_class":"P",
    "gn:feature_code":"PPL",
    "gn:name":"Samhwa-dong",
    "gn:population":0,
    "gn:timezone":"Asia/Pyongyang",
    "iso:country":"KP",
    "wof:name":"Samhwa-dong",
    "wof:placetype":"locality"
},
  "geometry": {"coordinates":[125.90111,39.24611],"type":"Point"}
}