{
  "type": "Feature",
  "properties": {
    "gn:admin1_code":"11.0",
    "gn:asciiname":"Puk-kol",
    "gn:country_code":"KP",
    "gn:dem":18,
    "gn:feature_class":"P",
    "gn:feature_code":"PPL",
    "gn:name":"Puk-kol",
    "gn:population":0,
    "gn:timezone":"Asia/Pyongyang",
    "iso:country":"KP",
    "name:und_x_variant":[
        "Pukko",
        "\ubd81\uace8",
        "Puk-kol"
    ],
    "wof:name":"Puk-kol",
    "wof:placetype":"locality"
},
  "geometry": {"coordinates":[124.36667,39.89528],"type":"Point"}
}