{
  "type": "Feature",
  "properties": {
    "gn:admin1_code":"11.0",
    "gn:asciiname":"Changha-dong",
    "gn:country_code":"KP",
    "gn:dem":371,
    "gn:feature_class":"P",
    "gn:feature_code":"PPL",
    "gn:name":"Changha-dong",
    "gn:population":0,
    "gn:timezone":"Asia/Pyongyang",
    "iso:country":"KP",
    "name:und_x_variant":[
        "\uc7a5\ud558\ub3d9",
        "Changha-dong"
    ],
    "wof:name":"Changha-dong",
    "wof:placetype":"locality"
},
  "geometry": {"coordinates":[125.25972,40.36972],"type":"Point"}
}