{
  "type": "Feature",
  "properties": {
    "gn:admin1_code":"6.0",
    "gn:asciiname":"Hadunjon",
    "gn:country_code":"KP",
    "gn:dem":62,
    "gn:feature_class":"P",
    "gn:feature_code":"PPL",
    "gn:name":"Hadunj\u014fn",
    "gn:population":0,
    "gn:timezone":"Asia/Pyongyang",
    "iso:country":"KP",
    "name:kor_x_preferred":[
        "\ud558\ub454\uc804"
    ],
    "name:und_x_variant":[
        "Hadunj\u014fn"
    ],
    "wof:name":"Hadunjon",
    "wof:placetype":"locality"
},
  "geometry": {"coordinates":[125.57193999999998,38.29889],"type":"Point"}
}