{
  "type": "Feature",
  "properties": {
    "gn:admin1_code":"7.0",
    "gn:asciiname":"Ch'angch'ol-li",
    "gn:country_code":"KP",
    "gn:dem":132,
    "gn:feature_class":"P",
    "gn:feature_code":"PPL",
    "gn:name":"Ch\u2019angch\u2019ol-li",
    "gn:population":0,
    "gn:timezone":"Asia/Pyongyang",
    "iso:country":"KP",
    "wof:name":"Ch'angch'ol-li",
    "wof:placetype":"locality"
},
  "geometry": {"coordinates":[126.09860999999999,38.51472],"type":"Point"}
}