{
  "type": "Feature",
  "properties": {
    "gn:admin1_code":"11.0",
    "gn:asciiname":"Choyang-gol",
    "gn:country_code":"KP",
    "gn:dem":74,
    "gn:feature_class":"P",
    "gn:feature_code":"PPL",
    "gn:name":"Choyang-gol",
    "gn:population":0,
    "gn:timezone":"Asia/Pyongyang",
    "iso:country":"KP",
    "name:und_x_variant":[
        "Choyang-kol",
        "\uc870\uc591\uace8",
        "Choyang-gol"
    ],
    "wof:name":"Choyang-gol",
    "wof:placetype":"locality"
},
  "geometry": {"coordinates":[124.59639,40.09389],"type":"Point"}
}