{
  "type": "Feature",
  "properties": {
    "gn:admin1_code":"6.0",
    "gn:asciiname":"Yomjon-dong",
    "gn:country_code":"KP",
    "gn:dem":10,
    "gn:feature_class":"P",
    "gn:feature_code":"PPL",
    "gn:name":"Y\u014fmj\u014fn-dong",
    "gn:population":0,
    "gn:timezone":"Asia/Pyongyang",
    "iso:country":"KP",
    "name:und_x_variant":[
        "Y\u014fmj\u014fm-dong",
        "\uc5fc\uc804\ub3d9",
        "Y\u014fmj\u014fn-dong"
    ],
    "wof:name":"Yomjon-dong",
    "wof:placetype":"locality"
},
  "geometry": {"coordinates":[125.02861,37.935],"type":"Point"}
}