{
  "type": "Feature",
  "properties": {
    "gn:admin1_code":"15.0",
    "gn:asciiname":"Sinhung-ni",
    "gn:country_code":"KP",
    "gn:dem":595,
    "gn:feature_class":"P",
    "gn:feature_code":"PPL",
    "gn:name":"Sinh\u016dng-ni",
    "gn:population":0,
    "gn:timezone":"Asia/Pyongyang",
    "iso:country":"KP",
    "name:und_x_variant":[
        "\uc2e0\ud765\ub9ac",
        "Sinh\u016dng-ni"
    ],
    "wof:name":"Sinhung-ni",
    "wof:placetype":"locality"
},
  "geometry": {"coordinates":[126.78888999999999,40.03028],"type":"Point"}
}