{
  "type": "Feature",
  "properties": {
    "gn:admin1_code":"11.0",
    "gn:asciiname":"Ibam-dong",
    "gn:country_code":"KP",
    "gn:dem":15,
    "gn:feature_class":"P",
    "gn:feature_code":"PPL",
    "gn:name":"Ibam-dong",
    "gn:population":0,
    "gn:timezone":"Asia/Pyongyang",
    "iso:country":"KP",
    "name:kor_x_preferred":[
        "\uc785\uc554\ub3d9"
    ],
    "wof:name":"Ibam-dong",
    "wof:placetype":"locality"
},
  "geometry": {"coordinates":[125.11417,39.64083],"type":"Point"}
}