{
  "type": "Feature",
  "properties": {
    "gn:admin1_code":"15.0",
    "gn:asciiname":"Tongnyol-li",
    "gn:country_code":"KP",
    "gn:dem":293,
    "gn:feature_class":"P",
    "gn:feature_code":"PPL",
    "gn:name":"T\u014fngny\u014fl-li",
    "gn:population":0,
    "gn:timezone":"Asia/Pyongyang",
    "iso:country":"KP",
    "name:kor_x_preferred":[
        "\ub355\ub828\ub9ac"
    ],
    "name:kor_x_variant":[
        "T\u014fngny\u014fl-li"
    ],
    "name:und_x_variant":[
        "T\u014fngny\u014fn-ni"
    ],
    "wof:name":"Tongnyol-li",
    "wof:placetype":"locality"
},
  "geometry": {"coordinates":[126.35250000000001,39.11083],"type":"Point"}
}