{
  "type": "Feature",
  "properties": {
    "gn:admin1_code":"1.0",
    "gn:asciiname":"Ch'unsan-dong",
    "gn:country_code":"KP",
    "gn:dem":180,
    "gn:feature_class":"P",
    "gn:feature_code":"PPL",
    "gn:name":"Ch\u2019unsan-dong",
    "gn:population":0,
    "gn:timezone":"Asia/Pyongyang",
    "iso:country":"KP",
    "name:und_x_variant":[
        "\ucd98\uc0b0\ub3d9",
        "Ch\u2019unsan-dong"
    ],
    "wof:name":"Ch'unsan-dong",
    "wof:placetype":"locality"
},
  "geometry": {"coordinates":[126.1225,41.03028],"type":"Point"}
}