{
  "type": "Feature",
  "properties": {
    "gn:admin1_code":"3.0",
    "gn:asciiname":"Kaehwa-ri",
    "gn:country_code":"KP",
    "gn:dem":946,
    "gn:feature_class":"P",
    "gn:feature_code":"PPL",
    "gn:name":"Kaehwa-ri",
    "gn:population":0,
    "gn:timezone":"Asia/Pyongyang",
    "iso:country":"KP",
    "name:kor_x_preferred":[
        "\uac1c\ud654\ub9ac"
    ],
    "wof:name":"Kaehwa-ri",
    "wof:placetype":"locality"
},
  "geometry": {"coordinates":[127.48139,40.95583],"type":"Point"}
}