{
  "type": "Feature",
  "properties": {
    "gn:admin1_code":"12.0",
    "gn:asciiname":"Yongjil-li",
    "gn:cc2":"KP",
    "gn:country_code":"KP",
    "gn:dem":20,
    "gn:feature_class":"P",
    "gn:feature_code":"PPL",
    "gn:name":"Y\u014fngjil-li",
    "gn:population":0,
    "gn:timezone":"Asia/Pyongyang",
    "iso:country":"KP",
    "name:kor_x_preferred":[
        "\uc601\uc9c4\ub9ac"
    ],
    "name:und_x_variant":[
        "Y\u014fngjin-ni",
        "Y\u014fngjil-li",
        "Yeongjilli"
    ],
    "wof:name":"Yongjil-li",
    "wof:placetype":"locality"
},
  "geometry": {"coordinates":[125.5925,38.865],"type":"Point"}
}