{
  "type": "Feature",
  "properties": {
    "gn:admin1_code":"1.0",
    "gn:asciiname":"Hwap'yong-dong",
    "gn:country_code":"KP",
    "gn:dem":329,
    "gn:feature_class":"P",
    "gn:feature_code":"PPL",
    "gn:name":"Hwap\u2019y\u014fng-dong",
    "gn:population":0,
    "gn:timezone":"Asia/Pyongyang",
    "iso:country":"KP",
    "name:und_x_variant":[
        "\ud654\ud3c9\ub3d9",
        "Hwap\u2019y\u014fng-dong"
    ],
    "wof:name":"Hwap'yong-dong",
    "wof:placetype":"locality"
},
  "geometry": {"coordinates":[126.65056,41.475],"type":"Point"}
}