{
  "type": "Feature",
  "properties": {
    "gn:admin1_code":"15.0",
    "gn:asciiname":"Malch'ijin",
    "gn:country_code":"KP",
    "gn:dem":24,
    "gn:feature_class":"P",
    "gn:feature_code":"PPL",
    "gn:name":"Malch\u2019ijin",
    "gn:population":0,
    "gn:timezone":"Asia/Pyongyang",
    "iso:country":"KP",
    "name:und_x_variant":[
        "Mach\u2019ijin",
        "Malch\u2019ijin"
    ],
    "wof:name":"Malch'ijin",
    "wof:placetype":"locality"
},
  "geometry": {"coordinates":[125.29583,38.69806],"type":"Point"}
}