{
  "type": "Feature",
  "properties": {
    "gn:admin1_code":"12.0",
    "gn:asciiname":"Yangha-dong",
    "gn:country_code":"KP",
    "gn:dem":90,
    "gn:feature_class":"P",
    "gn:feature_code":"PPL",
    "gn:name":"Yangha-dong",
    "gn:population":0,
    "gn:timezone":"Asia/Pyongyang",
    "iso:country":"KP",
    "name:kor_x_preferred":[
        "\uc591\ud558\ub3d9"
    ],
    "name:und_x_variant":[
        "Yanghadong"
    ],
    "wof:name":"Yangha-dong",
    "wof:placetype":"locality"
},
  "geometry": {"coordinates":[125.80389,39.18833],"type":"Point"}
}