{
  "type": "Feature",
  "properties": {
    "iso:country":"KP",
    "name:eng_x_preferred":[
        "Hwajeong 2(i)-dong"
    ],
    "name:kor_x_preferred":[
        "\ud654\uc8152\ub3d9"
    ],
    "qs:gn_pop":0,
    "qs:name":"\ud654\uc8152\ub3d9",
    "qs:name_adm0":"\ud55c\uad6d",
    "qs:name_adm1":"\uacbd\uae30\ub3c4",
    "qs:photos":156,
    "qs:photos_1k":32,
    "qs:photos_9k":1,
    "qs:photos_9r":4,
    "qs:photos_all":156,
    "qs:photos_sr":4,
    "qs:placetype":"Suburb",
    "qs:pop_sr":"0",
    "qs:woe_adm0":23424868,
    "wof:name":"Hwajeong 2(i)-dong",
    "wof:placetype":"neighbourhood"
},
  "geometry": {"coordinates":[126.6425,38.0625],"type":"Point"}
}