{
  "type": "Feature",
  "properties": {
    "gn:admin1_code":"12.0",
    "gn:asciiname":"Sil-li",
    "gn:country_code":"KP",
    "gn:dem":20,
    "gn:feature_class":"P",
    "gn:feature_code":"PPL",
    "gn:name":"Sil-li",
    "gn:population":0,
    "gn:timezone":"Asia/Pyongyang",
    "iso:country":"KP",
    "name:kor_x_preferred":[
        "\uc2e0\ub9ac"
    ],
    "name:und_x_variant":[
        "Silli"
    ],
    "wof:name":"Sil-li",
    "wof:placetype":"locality"
},
  "geometry": {"coordinates":[125.86278,39.03083],"type":"Point"}
}