{
  "type": "Feature",
  "properties": {
    "gn:admin1_code":"11.0",
    "gn:asciiname":"Taedong-ni",
    "gn:country_code":"KP",
    "gn:dem":352,
    "gn:feature_class":"P",
    "gn:feature_code":"PPL",
    "gn:name":"Taedong-ni",
    "gn:population":0,
    "gn:timezone":"Asia/Pyongyang",
    "iso:country":"KP",
    "name:und_x_variant":[
        "Tae-dong",
        "\ub300\ub3d9\ub9ac",
        "Taedong-ni"
    ],
    "wof:name":"Taedong-ni",
    "wof:placetype":"locality"
},
  "geometry": {"coordinates":[125.61917,40.26],"type":"Point"}
}