{
  "type": "Feature",
  "properties": {
    "gn:admin1_code":"3.0",
    "gn:asciiname":"Paegam-ni",
    "gn:country_code":"KP",
    "gn:dem":1274,
    "gn:feature_class":"P",
    "gn:feature_code":"PPL",
    "gn:name":"Paegam-ni",
    "gn:population":0,
    "gn:timezone":"Asia/Pyongyang",
    "iso:country":"KP",
    "name:eng_x_preferred":[
        "Paegam"
    ],
    "name:eng_x_variant":[
        "Paegam-ni"
    ],
    "name:und_x_variant":[
        "\ubc31\uc554\ub9ac",
        "Paegam-ni"
    ],
    "wof:name":"Paegam",
    "wof:placetype":"locality"
},
  "geometry": {"coordinates":[127.59361,40.4425],"type":"Point"}
}