{
  "type": "Feature",
  "properties": {
    "gn:admin1_code":"17.0",
    "gn:asciiname":"Kwangyon-gol",
    "gn:country_code":"KP",
    "gn:dem":51,
    "gn:feature_class":"P",
    "gn:feature_code":"PPL",
    "gn:name":"Kwangy\u014fn-gol",
    "gn:population":0,
    "gn:timezone":"Asia/Pyongyang",
    "iso:country":"KP",
    "name:und_x_variant":[
        "Kwangny\u014fn\u2019gok",
        "\uad11\uc5f0\uace8",
        "Kwangny\u014fn\u2019gol",
        "Kwangy\u014fn-gol"
    ],
    "wof:name":"Kwangyon-gol",
    "wof:placetype":"locality"
},
  "geometry": {"coordinates":[129.62111000000002,41.64389],"type":"Point"}
}