{
  "type": "Feature",
  "properties": {
    "gn:admin1_code":"17.0",
    "gn:asciiname":"Songjo",
    "gn:country_code":"KP",
    "gn:dem":77,
    "gn:feature_class":"P",
    "gn:feature_code":"PPL",
    "gn:name":"Songj\u014f",
    "gn:population":0,
    "gn:timezone":"Asia/Pyongyang",
    "iso:country":"KP",
    "name:und_x_variant":[
        "\uc1a1\uc800",
        "Songj\u014f"
    ],
    "wof:name":"Songjo",
    "wof:placetype":"locality"
},
  "geometry": {"coordinates":[130.18916999999999,42.65556],"type":"Point"}
}