{
  "type": "Feature",
  "properties": {
    "gn:admin1_code":"15.0",
    "gn:asciiname":"Waryong-ni",
    "gn:country_code":"KP",
    "gn:dem":866,
    "gn:feature_class":"P",
    "gn:feature_code":"PPL",
    "gn:name":"Waryong-ni",
    "gn:population":0,
    "gn:timezone":"Asia/Pyongyang",
    "iso:country":"KP",
    "name:eng_x_preferred":[
        "Waryong"
    ],
    "name:eng_x_variant":[
        "Waryong-ni"
    ],
    "name:und_x_variant":[
        "\uc640\ub8e1\ub9ac",
        "Waryong-ni"
    ],
    "wof:name":"Waryong",
    "wof:placetype":"locality"
},
  "geometry": {"coordinates":[126.92083,40.22361],"type":"Point"}
}