{
  "type": "Feature",
  "properties": {
    "gn:admin1_code":"7.0",
    "gn:asciiname":"Ch'umok-tong",
    "gn:country_code":"KP",
    "gn:dem":254,
    "gn:feature_class":"P",
    "gn:feature_code":"PPL",
    "gn:name":"Ch\u2019umok-tong",
    "gn:population":0,
    "gn:timezone":"Asia/Pyongyang",
    "iso:country":"KP",
    "name:eng_x_preferred":[
        "Ch'umok"
    ],
    "name:eng_x_variant":[
        "Ch'umok-tong"
    ],
    "name:kor_x_preferred":[
        "\ucd94\ubaa9\ub3d9"
    ],
    "name:kor_x_variant":[
        "Ch\u2019umok-tong"
    ],
    "wof:name":"Ch'umok",
    "wof:placetype":"locality"
},
  "geometry": {"coordinates":[126.69777999999999,38.94333],"type":"Point"}
}