{
  "type": "Feature",
  "properties": {
    "gn:admin1_code":"11.0",
    "gn:asciiname":"Changsongmun",
    "gn:country_code":"KP",
    "gn:dem":107,
    "gn:feature_class":"P",
    "gn:feature_code":"PPL",
    "gn:name":"Changs\u014fngmun",
    "gn:population":0,
    "gn:timezone":"Asia/Pyongyang",
    "iso:country":"KP",
    "name:und_x_variant":[
        "\uc7a5\uc131\ubb38",
        "Changs\u014fngmun"
    ],
    "wof:name":"Changsongmun",
    "wof:placetype":"locality"
},
  "geometry": {"coordinates":[125.52500000000001,40.08472],"type":"Point"}
}