{
  "type": "Feature",
  "properties": {
    "gn:admin1_code":"17.0",
    "gn:asciiname":"Songbuk-tong",
    "gn:country_code":"KP",
    "gn:dem":76,
    "gn:feature_class":"P",
    "gn:feature_code":"PPL",
    "gn:name":"S\u014fngbuk-tong",
    "gn:population":0,
    "gn:timezone":"Asia/Pyongyang",
    "iso:country":"KP",
    "name:und_x_variant":[
        "\uc131\ubd81\ub3d9",
        "S\u014fngbuk-tong"
    ],
    "wof:name":"Songbuk-tong",
    "wof:placetype":"locality"
},
  "geometry": {"coordinates":[129.69611,41.6875],"type":"Point"}
}