{
  "type": "Feature",
  "properties": {
    "gn:admin1_code":"17.0",
    "gn:asciiname":"Sanso-dong",
    "gn:country_code":"KP",
    "gn:dem":38,
    "gn:feature_class":"P",
    "gn:feature_code":"PPL",
    "gn:name":"Sans\u014f-dong",
    "gn:population":0,
    "gn:timezone":"Asia/Pyongyang",
    "iso:country":"KP",
    "name:und_x_variant":[
        "\uc0b0\uc11c\ub3d9",
        "Sans\u014f-dong"
    ],
    "wof:name":"Sanso-dong",
    "wof:placetype":"locality"
},
  "geometry": {"coordinates":[130.35249999999999,42.60667],"type":"Point"}
}