{
  "type": "Feature",
  "properties": {
    "gn:admin1_code":"7.0",
    "gn:asciiname":"Wolsoul",
    "gn:country_code":"KP",
    "gn:dem":253,
    "gn:feature_class":"P",
    "gn:feature_code":"PPL",
    "gn:name":"W\u014fls\u014ful",
    "gn:population":0,
    "gn:timezone":"Asia/Pyongyang",
    "iso:country":"KP",
    "wof:name":"Wolsoul",
    "wof:placetype":"locality"
},
  "geometry": {"coordinates":[126.21361,38.54694],"type":"Point"}
}