{
  "type": "Feature",
  "properties": {
    "gn:admin1_code":"7.0",
    "gn:asciiname":"Saen-gol",
    "gn:country_code":"KP",
    "gn:dem":123,
    "gn:feature_class":"P",
    "gn:feature_code":"PPL",
    "gn:name":"Saen-gol",
    "gn:population":0,
    "gn:timezone":"Asia/Pyongyang",
    "iso:country":"KP",
    "name:kor_x_preferred":[
        "\uc0cc\uace8"
    ],
    "wof:name":"Saen-gol",
    "wof:placetype":"locality"
},
  "geometry": {"coordinates":[126.65361,38.87667],"type":"Point"}
}