{
  "type": "Feature",
  "properties": {
    "gn:admin1_code":"6.0",
    "gn:asciiname":"Namsaet'o",
    "gn:country_code":"KP",
    "gn:dem":19,
    "gn:feature_class":"P",
    "gn:feature_code":"PPL",
    "gn:name":"Namsaet\u2019\u014f",
    "gn:population":0,
    "gn:timezone":"Asia/Pyongyang",
    "iso:country":"KP",
    "name:und_x_variant":[
        "Namsindae",
        "Namsaet\u2019\u014f"
    ],
    "wof:name":"Namsaet'o",
    "wof:placetype":"locality"
},
  "geometry": {"coordinates":[125.89917,37.89972],"type":"Point"}
}