{
  "type": "Feature",
  "properties": {
    "gn:admin1_code":"15.0",
    "gn:asciiname":"Chon'gi-dong",
    "gn:country_code":"KP",
    "gn:dem":325,
    "gn:feature_class":"P",
    "gn:feature_code":"PPL",
    "gn:name":"Ch\u014fn\u2019gi-dong",
    "gn:population":0,
    "gn:timezone":"Asia/Pyongyang",
    "iso:country":"KP",
    "name:kor_x_preferred":[
        "\uc804\uae30\ub3d9"
    ],
    "name:kor_x_variant":[
        "Ch\u014fn\u2019gi-dong"
    ],
    "wof:name":"Chon'gi-dong",
    "wof:placetype":"locality"
},
  "geometry": {"coordinates":[126.96444,39.15611],"type":"Point"}
}