{
  "type": "Feature",
  "properties": {
    "gn:admin1_code":"6.0",
    "gn:asciiname":"Kusok-tong",
    "gn:country_code":"KP",
    "gn:dem":54,
    "gn:feature_class":"P",
    "gn:feature_code":"PPL",
    "gn:name":"Kus\u014fk-tong",
    "gn:population":0,
    "gn:timezone":"Asia/Pyongyang",
    "iso:country":"KP",
    "name:eng_x_preferred":[
        "Kusok"
    ],
    "name:eng_x_variant":[
        "Kusok-tong"
    ],
    "name:kor_x_preferred":[
        "\uad6c\uc11d\ub3d9"
    ],
    "name:und_x_variant":[
        "Kus\u014fk-tong"
    ],
    "wof:name":"Kusok",
    "wof:placetype":"locality"
},
  "geometry": {"coordinates":[125.87111,38.02028],"type":"Point"}
}