{
  "type": "Feature",
  "properties": {
    "gn:admin1_code":"0.0",
    "gn:asciiname":"Sanghung-ni",
    "gn:country_code":"KP",
    "gn:dem":26,
    "gn:feature_class":"P",
    "gn:feature_code":"PPL",
    "gn:name":"Sangh\u016dng-ni",
    "gn:population":0,
    "gn:timezone":"Asia/Pyongyang",
    "iso:country":"KP",
    "name:kor_x_preferred":[
        "\uc0c1\ud765\ub9ac"
    ],
    "name:und_x_variant":[
        "Sangh\u016dng-ni"
    ],
    "wof:name":"Sanghung-ni",
    "wof:placetype":"locality"
},
  "geometry": {"coordinates":[125.81667,38.85],"type":"Point"}
}