{
  "type": "Feature",
  "properties": {
    "gn:admin1_code":"11.0",
    "gn:asciiname":"Kogumam-dong",
    "gn:country_code":"KP",
    "gn:dem":49,
    "gn:feature_class":"P",
    "gn:feature_code":"PPL",
    "gn:name":"Kog\u016dmam-dong",
    "gn:population":0,
    "gn:timezone":"Asia/Pyongyang",
    "iso:country":"KP",
    "name:kor_x_preferred":[
        "Kog\u016dmam-dong"
    ],
    "name:kor_x_variant":[
        "\uace0\uae08\uc554\ub3d9"
    ],
    "wof:name":"Kogumam-dong",
    "wof:placetype":"locality"
},
  "geometry": {"coordinates":[124.87083,39.78806],"type":"Point"}
}