{
  "type": "Feature",
  "properties": {
    "gn:admin1_code":"11.0",
    "gn:asciiname":"Tongsam-ni",
    "gn:country_code":"KP",
    "gn:dem":17,
    "gn:feature_class":"P",
    "gn:feature_code":"PPL",
    "gn:name":"Tongsam-ni",
    "gn:population":0,
    "gn:timezone":"Asia/Pyongyang",
    "iso:country":"KP",
    "name:kor_x_preferred":[
        "\ub3d9\uc0bc\ub9ac"
    ],
    "wof:name":"Tongsam-ni",
    "wof:placetype":"locality"
},
  "geometry": {"coordinates":[125.57583,39.68667],"type":"Point"}
}