{
  "type": "Feature",
  "properties": {
    "gn:admin1_code":"7.0",
    "gn:asciiname":"Ch'on'gok-tong",
    "gn:country_code":"KP",
    "gn:dem":217,
    "gn:feature_class":"P",
    "gn:feature_code":"PPL",
    "gn:name":"Ch\u2019\u014fn\u2019gok-tong",
    "gn:population":0,
    "gn:timezone":"Asia/Pyongyang",
    "iso:country":"KP",
    "name:eng_x_preferred":[
        "Ch'on'gok"
    ],
    "name:eng_x_variant":[
        "Ch'on'gok-tong"
    ],
    "name:kor_x_preferred":[
        "\ucc9c\uace1\ub3d9"
    ],
    "name:kor_x_variant":[
        "Ch\u2019\u014fn\u2019gok-tong"
    ],
    "wof:name":"Ch'on'gok",
    "wof:placetype":"locality"
},
  "geometry": {"coordinates":[126.51972000000001,38.61083],"type":"Point"}
}