{
  "type": "Feature",
  "properties": {
    "gn:admin1_code":"7.0",
    "gn:asciiname":"Sangnung-dong",
    "gn:country_code":"KP",
    "gn:dem":302,
    "gn:feature_class":"P",
    "gn:feature_code":"PPL",
    "gn:name":"Sangn\u016dng-dong",
    "gn:population":0,
    "gn:timezone":"Asia/Pyongyang",
    "iso:country":"KP",
    "name:kor_x_preferred":[
        "\uc0c1\ub989\ub3d9"
    ],
    "name:kor_x_variant":[
        "Sangn\u016dng-dong"
    ],
    "wof:name":"Sangnung-dong",
    "wof:placetype":"locality"
},
  "geometry": {"coordinates":[126.41667,38.7875],"type":"Point"}
}