{
  "type": "Feature",
  "properties": {
    "gn:admin1_code":"11.0",
    "gn:asciiname":"Ch'ahungil-tong",
    "gn:country_code":"KP",
    "gn:dem":138,
    "gn:feature_class":"P",
    "gn:feature_code":"PPL",
    "gn:name":"Ch\u2019ah\u016dngil-tong",
    "gn:population":0,
    "gn:timezone":"Asia/Pyongyang",
    "iso:country":"KP",
    "name:und_x_variant":[
        "\ucc28\ud7651\ub3d9",
        "Ch\u2019ah\u016dng",
        "Ch\u2019ah\u016dng-dong",
        "Ch\u2019ah\u016dngil-tong"
    ],
    "wof:name":"Ch'ahungil-tong",
    "wof:placetype":"locality"
},
  "geometry": {"coordinates":[125.20972,40.05139000000001],"type":"Point"}
}