{
  "type": "Feature",
  "properties": {
    "gn:admin1_code":"3.0",
    "gn:asciiname":"Changhung-ni",
    "gn:country_code":"KP",
    "gn:dem":10,
    "gn:feature_class":"P",
    "gn:feature_code":"PPL",
    "gn:name":"Changh\u016dng-ni",
    "gn:population":0,
    "gn:timezone":"Asia/Pyongyang",
    "iso:country":"KP",
    "name:eng_x_preferred":[
        "Changhung"
    ],
    "name:eng_x_variant":[
        "Changhung-ni"
    ],
    "name:und_x_variant":[
        "\uc7a5\ud765\ub9ac",
        "Changh\u016dng-ni"
    ],
    "wof:name":"Changhung",
    "wof:placetype":"locality"
},
  "geometry": {"coordinates":[127.45193999999999,39.84528],"type":"Point"}
}