{
  "type": "Feature",
  "properties": {
    "gn:admin1_code":"3.0",
    "gn:asciiname":"Ipsong-ni",
    "gn:country_code":"KP",
    "gn:dem":402,
    "gn:feature_class":"P",
    "gn:feature_code":"PPL",
    "gn:name":"Ips\u014fng-ni",
    "gn:population":0,
    "gn:timezone":"Asia/Pyongyang",
    "iso:country":"KP",
    "name:und_x_variant":[
        "\ub9bd\uc11d\ub9ac",
        "Ips\u014fng-ni"
    ],
    "wof:name":"Ipsong-ni",
    "wof:placetype":"locality"
},
  "geometry": {"coordinates":[126.83611000000001,39.77667],"type":"Point"}
}