{
  "type": "Feature",
  "properties": {
    "gn:admin1_code":"7.0",
    "gn:asciiname":"Chach'ang-ni",
    "gn:country_code":"KP",
    "gn:dem":191,
    "gn:feature_class":"P",
    "gn:feature_code":"PPL",
    "gn:name":"Chach\u2019ang-ni",
    "gn:population":0,
    "gn:timezone":"Asia/Pyongyang",
    "iso:country":"KP",
    "name:eng_x_preferred":[
        "Chach'ang"
    ],
    "name:eng_x_variant":[
        "Chach'ang-ni"
    ],
    "wof:name":"Chach'ang",
    "wof:placetype":"locality"
},
  "geometry": {"coordinates":[126.11167,38.28722],"type":"Point"}
}