{
  "type": "Feature",
  "properties": {
    "gn:admin1_code":"7.0",
    "gn:admin2_code":"Y\u014fnsan-gun",
    "gn:asciiname":"Twi-gol",
    "gn:country_code":"KP",
    "gn:dem":149,
    "gn:feature_class":"P",
    "gn:feature_code":"PPL",
    "gn:name":"Twi-gol",
    "gn:population":0,
    "gn:timezone":"Asia/Pyongyang",
    "iso:country":"KP",
    "wof:name":"Twi-gol",
    "wof:placetype":"locality"
},
  "geometry": {"coordinates":[126.17028000000001,38.85806],"type":"Point"}
}