{
  "type": "Feature",
  "properties": {
    "gn:admin1_code":"3.0",
    "gn:asciiname":"Tongha-ri",
    "gn:country_code":"KP",
    "gn:dem":146,
    "gn:feature_class":"P",
    "gn:feature_code":"PPL",
    "gn:name":"Tongha-ri",
    "gn:population":0,
    "gn:timezone":"Asia/Pyongyang",
    "iso:country":"KP",
    "name:und_x_variant":[
        "\ub3d9\ud558\ub9ac",
        "Tongha-ri"
    ],
    "wof:name":"Tongha-ri",
    "wof:placetype":"locality"
},
  "geometry": {"coordinates":[127.20694,39.62389],"type":"Point"}
}