{
  "type": "Feature",
  "properties": {
    "gn:admin1_code":"11.0",
    "gn:asciiname":"Songch'ang-dong",
    "gn:country_code":"KP",
    "gn:dem":74,
    "gn:feature_class":"P",
    "gn:feature_code":"PPL",
    "gn:name":"Songch\u2019ang-dong",
    "gn:population":0,
    "gn:timezone":"Asia/Pyongyang",
    "iso:country":"KP",
    "name:kor_x_preferred":[
        "\uc1a1\ucc3d\ub3d9"
    ],
    "name:kor_x_variant":[
        "Songch\u2019ang-dong"
    ],
    "name:und_x_variant":[
        "Songch\u2019ang-do"
    ],
    "wof:name":"Songch'ang-dong",
    "wof:placetype":"locality"
},
  "geometry": {"coordinates":[125.41,39.74722],"type":"Point"}
}