{
  "type": "Feature",
  "properties": {
    "gn:admin1_code":"6.0",
    "gn:asciiname":"Tangam-dong",
    "gn:country_code":"KP",
    "gn:dem":48,
    "gn:feature_class":"P",
    "gn:feature_code":"PPL",
    "gn:name":"Tangam-dong",
    "gn:population":0,
    "gn:timezone":"Asia/Pyongyang",
    "iso:country":"KP",
    "name:kor_x_preferred":[
        "\ub2f9\uc554\ub3d9"
    ],
    "name:und_x_variant":[
        "Tangam"
    ],
    "wof:name":"Tangam-dong",
    "wof:placetype":"locality"
},
  "geometry": {"coordinates":[125.65783,38.35807],"type":"Point"}
}