{
  "type": "Feature",
  "properties": {
    "gn:admin1_code":"1.0",
    "gn:asciiname":"Yongp'ung-ni",
    "gn:country_code":"KP",
    "gn:dem":314,
    "gn:feature_class":"P",
    "gn:feature_code":"PPL",
    "gn:name":"Yongp\u2019ung-ni",
    "gn:population":0,
    "gn:timezone":"Asia/Pyongyang",
    "iso:country":"KP",
    "name:und_x_variant":[
        "\ub8e1\ud48d\ub9ac",
        "Yongp\u2019ung-ni"
    ],
    "wof:name":"Yongp'ung-ni",
    "wof:placetype":"locality"
},
  "geometry": {"coordinates":[125.87056,40.52],"type":"Point"}
}