{
  "type": "Feature",
  "properties": {
    "gn:admin1_code":"3.0",
    "gn:asciiname":"Changdong-ni",
    "gn:country_code":"KP",
    "gn:dem":304,
    "gn:feature_class":"P",
    "gn:feature_code":"PPL",
    "gn:name":"Changdong-ni",
    "gn:population":0,
    "gn:timezone":"Asia/Pyongyang",
    "iso:country":"KP",
    "name:eng_x_preferred":[
        "Changdong"
    ],
    "name:eng_x_variant":[
        "Changdong-ni"
    ],
    "name:und_x_variant":[
        "\uc7a5\ub3d9\ub9ac"
    ],
    "wof:name":"Changdong",
    "wof:placetype":"locality"
},
  "geometry": {"coordinates":[128.51611,40.30917],"type":"Point"}
}