{
  "type": "Feature",
  "properties": {
    "gn:admin1_code":"15.0",
    "gn:asciiname":"Haryung-ni",
    "gn:country_code":"KP",
    "gn:dem":22,
    "gn:feature_class":"P",
    "gn:feature_code":"PPL",
    "gn:name":"Haryung-ni",
    "gn:population":0,
    "gn:timezone":"Asia/Pyongyang",
    "iso:country":"KP",
    "name:eng_x_preferred":[
        "Haryung"
    ],
    "name:eng_x_variant":[
        "Haryung-ni"
    ],
    "wof:name":"Haryung",
    "wof:placetype":"locality"
},
  "geometry": {"coordinates":[125.53361,38.93944],"type":"Point"}
}