{
  "type": "Feature",
  "properties": {
    "gn:admin1_code":"9.0",
    "gn:asciiname":"P'yongmal",
    "gn:country_code":"KP",
    "gn:dem":134,
    "gn:feature_class":"P",
    "gn:feature_code":"PPL",
    "gn:name":"P\u2019y\u014fngmal",
    "gn:population":0,
    "gn:timezone":"Asia/Pyongyang",
    "iso:country":"KP",
    "wof:name":"P'yongmal",
    "wof:placetype":"locality"
},
  "geometry": {"coordinates":[126.80361000000001,38.46306],"type":"Point"}
}