{
  "type": "Feature",
  "properties": {
    "gn:admin1_code":"7.0",
    "gn:asciiname":"Up'ung-dong",
    "gn:country_code":"KP",
    "gn:dem":52,
    "gn:feature_class":"P",
    "gn:feature_code":"PPL",
    "gn:name":"Up\u2019ung-dong",
    "gn:population":0,
    "gn:timezone":"Asia/Pyongyang",
    "iso:country":"KP",
    "wof:name":"Up'ung-dong",
    "wof:placetype":"locality"
},
  "geometry": {"coordinates":[125.87444000000001,38.35028],"type":"Point"}
}