{
  "type": "Feature",
  "properties": {
    "gn:admin1_code":"11.0",
    "gn:asciiname":"Pup'yong-ni",
    "gn:country_code":"KP",
    "gn:dem":53,
    "gn:feature_class":"P",
    "gn:feature_code":"PPL",
    "gn:name":"Pup\u2019y\u014fng-ni",
    "gn:population":0,
    "gn:timezone":"Asia/Pyongyang",
    "iso:country":"KP",
    "name:eng_x_preferred":[
        "Pup'yong"
    ],
    "name:eng_x_variant":[
        "Pup'yong-ni"
    ],
    "name:kor_x_preferred":[
        "\ubd80\ud3c9\ub9ac"
    ],
    "name:und_x_variant":[
        "Pup\u2019y\u014fng-ni"
    ],
    "wof:name":"Pup'yong",
    "wof:placetype":"locality"
},
  "geometry": {"coordinates":[125.43889,39.93417],"type":"Point"}
}