{
  "type": "Feature",
  "properties": {
    "gn:admin1_code":"3.0",
    "gn:asciiname":"Ch'angmal",
    "gn:country_code":"KP",
    "gn:dem":154,
    "gn:feature_class":"P",
    "gn:feature_code":"PPL",
    "gn:name":"Ch\u2019angmal",
    "gn:population":0,
    "gn:timezone":"Asia/Pyongyang",
    "iso:country":"KP",
    "name:kor_x_preferred":[
        "\ucc3d\ub9d0"
    ],
    "name:kor_x_variant":[
        "Ch\u2019angmal"
    ],
    "name:und_x_variant":[
        "Ch\u2019ang-ma\u016dl"
    ],
    "wof:name":"Ch'angmal",
    "wof:placetype":"locality"
},
  "geometry": {"coordinates":[126.95528,39.45889],"type":"Point"}
}