{
  "type": "Feature",
  "properties": {
    "gn:admin1_code":"1.0",
    "gn:asciiname":"Maebongch'am",
    "gn:country_code":"KP",
    "gn:dem":718,
    "gn:feature_class":"P",
    "gn:feature_code":"PPL",
    "gn:name":"Maebongch\u2019am",
    "gn:population":0,
    "gn:timezone":"Asia/Pyongyang",
    "iso:country":"KP",
    "name:und_x_variant":[
        "\ub9e4\ubd09\ucc38",
        "Maebongch\u2019am"
    ],
    "wof:name":"Maebongch'am",
    "wof:placetype":"locality"
},
  "geometry": {"coordinates":[126.77306000000002,40.2475],"type":"Point"}
}