{
  "type": "Feature",
  "properties": {
    "gn:admin1_code":"6.0",
    "gn:admin2_code":"Changp\u2019ung-gun",
    "gn:asciiname":"Sangsokchuwon",
    "gn:country_code":"KP",
    "gn:dem":83,
    "gn:feature_class":"P",
    "gn:feature_code":"PPL",
    "gn:name":"Sangs\u014fkchuw\u014fn",
    "gn:population":0,
    "gn:timezone":"Asia/Pyongyang",
    "iso:country":"KP",
    "name:und_x_variant":[
        "Sangsokchuwan",
        "Sangs\u014fkchuw\u014fn"
    ],
    "wof:name":"Sangsokchuwon",
    "wof:placetype":"locality"
},
  "geometry": {"coordinates":[126.79667000000001,38.02917],"type":"Point"}
}