{
  "type": "Feature",
  "properties": {
    "gn:admin1_code":"9.0",
    "gn:asciiname":"Naemul-li",
    "gn:cc2":"KP",
    "gn:country_code":"KP",
    "gn:dem":201,
    "gn:feature_class":"P",
    "gn:feature_code":"PPL",
    "gn:name":"Naemul-li",
    "gn:population":0,
    "gn:timezone":"Asia/Pyongyang",
    "iso:country":"KP",
    "name:und_x_variant":[
        "Naemun-ni",
        "Naemul-li"
    ],
    "wof:name":"Naemul-li",
    "wof:placetype":"locality"
},
  "geometry": {"coordinates":[127.06139,38.33472],"type":"Point"}
}