{
  "type": "Feature",
  "properties": {
    "gn:admin1_code":"11.0",
    "gn:asciiname":"Sanggwang-dong",
    "gn:country_code":"KP",
    "gn:dem":221,
    "gn:feature_class":"P",
    "gn:feature_code":"PPL",
    "gn:name":"Sanggwang-dong",
    "gn:population":0,
    "gn:timezone":"Asia/Pyongyang",
    "iso:country":"KP",
    "wof:name":"Sanggwang-dong",
    "wof:placetype":"locality"
},
  "geometry": {"coordinates":[124.91916999999999,40.32667],"type":"Point"}
}