{
  "type": "Feature",
  "properties": {
    "gn:admin1_code":"12.0",
    "gn:admin2_code":"Sangw\u014fn-gun",
    "gn:asciiname":"Chon-ch'on",
    "gn:country_code":"KP",
    "gn:dem":71,
    "gn:feature_class":"P",
    "gn:feature_code":"PPL",
    "gn:name":"Ch\u014fn-ch\u2019on",
    "gn:population":0,
    "gn:timezone":"Asia/Pyongyang",
    "iso:country":"KP",
    "wof:name":"Chon-ch'on",
    "wof:placetype":"locality"
},
  "geometry": {"coordinates":[126.10167,38.94139000000001],"type":"Point"}
}