{
  "type": "Feature",
  "properties": {
    "gn:admin1_code":"11.0",
    "gn:asciiname":"Tokp'ung-ni",
    "gn:country_code":"KP",
    "gn:dem":148,
    "gn:feature_class":"P",
    "gn:feature_code":"PPL",
    "gn:name":"T\u014fkp\u2019ung-ni",
    "gn:population":0,
    "gn:timezone":"Asia/Pyongyang",
    "iso:country":"KP",
    "name:und_x_variant":[
        "\ub355\ud48d\ub9ac",
        "T\u014fkp\u2019ung-ni"
    ],
    "wof:name":"Tokp'ung-ni",
    "wof:placetype":"locality"
},
  "geometry": {"coordinates":[125.30611,40.02722],"type":"Point"}
}