{
  "type": "Feature",
  "properties": {
    "gn:admin1_code":"0.0",
    "gn:asciiname":"Sinjakkori",
    "gn:cc2":"KP",
    "gn:country_code":"KP",
    "gn:dem":52,
    "gn:feature_class":"P",
    "gn:feature_code":"PPL",
    "gn:name":"Sinjakk\u014fri",
    "gn:population":0,
    "gn:timezone":"Asia/Pyongyang",
    "iso:country":"KP",
    "name:kor_x_preferred":[
        "\uc2e0\uc791\uac70\ub9ac"
    ],
    "name:und_x_variant":[
        "Sinjakka",
        "Sinjakk\u014fri"
    ],
    "wof:name":"Sinjakkori",
    "wof:placetype":"locality"
},
  "geometry": {"coordinates":[125.38333,38.73333],"type":"Point"}
}