{
  "type": "Feature",
  "properties": {
    "gn:admin1_code":"3.0",
    "gn:asciiname":"Hamanch'on",
    "gn:country_code":"KP",
    "gn:dem":24,
    "gn:feature_class":"P",
    "gn:feature_code":"PPL",
    "gn:name":"Hamanch\u2019on",
    "gn:population":0,
    "gn:timezone":"Asia/Pyongyang",
    "iso:country":"KP",
    "name:und_x_variant":[
        "\ud568\uc548\ucd0c",
        "Hamanch\u2019on"
    ],
    "wof:name":"Hamanch'on",
    "wof:placetype":"locality"
},
  "geometry": {"coordinates":[127.46083,39.99222],"type":"Point"}
}