{
  "type": "Feature",
  "properties": {
    "gn:admin1_code":"12.0",
    "gn:asciiname":"Kwangjong-ni",
    "gn:country_code":"KP",
    "gn:dem":39,
    "gn:feature_class":"P",
    "gn:feature_code":"PPL",
    "gn:name":"Kwangj\u014fng-ni",
    "gn:population":0,
    "gn:timezone":"Asia/Pyongyang",
    "iso:country":"KP",
    "name:eng_x_preferred":[
        "Kwangjong"
    ],
    "name:eng_x_variant":[
        "Kwangjong-ni"
    ],
    "wof:name":"Kwangjong",
    "wof:placetype":"locality"
},
  "geometry": {"coordinates":[125.98611,39.02],"type":"Point"}
}