{
  "type": "Feature",
  "properties": {
    "gn:admin1_code":"3.0",
    "gn:asciiname":"Mujaemok",
    "gn:country_code":"KP",
    "gn:dem":40,
    "gn:feature_class":"P",
    "gn:feature_code":"PPL",
    "gn:name":"Mujaemok",
    "gn:population":0,
    "gn:timezone":"Asia/Pyongyang",
    "iso:country":"KP",
    "name:und_x_variant":[
        "\ubb34\uc7ac\ubaa9",
        "Mujaemok"
    ],
    "wof:name":"Mujaemok",
    "wof:placetype":"locality"
},
  "geometry": {"coordinates":[127.38611000000002,39.87417],"type":"Point"}
}