{
  "type": "Feature",
  "properties": {
    "gn:admin1_code":"17.0",
    "gn:asciiname":"Songp'yong",
    "gn:country_code":"KP",
    "gn:dem":366,
    "gn:feature_class":"P",
    "gn:feature_code":"PPL",
    "gn:name":"Songp\u2019y\u014fng",
    "gn:population":0,
    "gn:timezone":"Asia/Pyongyang",
    "iso:country":"KP",
    "name:und_x_variant":[
        "\uc1a1\ud3c9",
        "Songp\u2019y\u014fng"
    ],
    "wof:name":"Songp'yong",
    "wof:placetype":"locality"
},
  "geometry": {"coordinates":[129.82832999999999,42.31111],"type":"Point"}
}