{
  "type": "Feature",
  "properties": {
    "gn:admin1_code":"3.0",
    "gn:asciiname":"Yongsil-li",
    "gn:country_code":"KP",
    "gn:dem":316,
    "gn:feature_class":"P",
    "gn:feature_code":"PPL",
    "gn:name":"Yongsil-li",
    "gn:population":0,
    "gn:timezone":"Asia/Pyongyang",
    "iso:country":"KP",
    "name:und_x_variant":[
        "Yongsin-ni",
        "\ub8e1\uc2e0\ub9ac",
        "Yongsil-li"
    ],
    "wof:name":"Yongsil-li",
    "wof:placetype":"locality"
},
  "geometry": {"coordinates":[128.00083000000001,40.19778],"type":"Point"}
}