{
  "type": "Feature",
  "properties": {
    "gn:admin1_code":"11.0",
    "gn:asciiname":"T'oeha-ri",
    "gn:country_code":"KP",
    "gn:dem":85,
    "gn:feature_class":"P",
    "gn:feature_code":"PPL",
    "gn:name":"T\u2019oeha-ri",
    "gn:population":0,
    "gn:timezone":"Asia/Pyongyang",
    "iso:country":"KP",
    "name:kor_x_preferred":[
        "\ud1f4\ud558\ub9ac"
    ],
    "name:und_x_variant":[
        "T\u2019oeha-ri"
    ],
    "wof:name":"T'oeha-ri",
    "wof:placetype":"locality"
},
  "geometry": {"coordinates":[125.41167,39.95944],"type":"Point"}
}