{
  "type": "Feature",
  "properties": {
    "gn:admin1_code":"9.0",
    "gn:asciiname":"Hasu-dong",
    "gn:country_code":"KP",
    "gn:dem":408,
    "gn:feature_class":"P",
    "gn:feature_code":"PPL",
    "gn:name":"Hasu-dong",
    "gn:population":0,
    "gn:timezone":"Asia/Pyongyang",
    "iso:country":"KP",
    "name:kor_x_preferred":[
        "\ud558\uc218\ub3d9"
    ],
    "wof:name":"Hasu-dong",
    "wof:placetype":"locality"
},
  "geometry": {"coordinates":[127.30417,38.70056],"type":"Point"}
}