{
  "type": "Feature",
  "properties": {
    "gn:admin1_code":"15.0",
    "gn:asciiname":"Chomak-kol",
    "gn:country_code":"KP",
    "gn:dem":198,
    "gn:feature_class":"P",
    "gn:feature_code":"PPL",
    "gn:name":"Chomak-kol",
    "gn:population":0,
    "gn:timezone":"Asia/Pyongyang",
    "iso:country":"KP",
    "wof:name":"Chomak-kol",
    "wof:placetype":"locality"
},
  "geometry": {"coordinates":[125.78556,39.24528],"type":"Point"}
}