{
  "type": "Feature",
  "properties": {
    "gn:admin1_code":"6.0",
    "gn:asciiname":"Chaegung-dong",
    "gn:cc2":"KP",
    "gn:country_code":"KP",
    "gn:dem":59,
    "gn:feature_class":"P",
    "gn:feature_code":"PPL",
    "gn:name":"Chaegung-dong",
    "gn:population":0,
    "gn:timezone":"Asia/Pyongyang",
    "iso:country":"KP",
    "name:kor_x_preferred":[
        "\uc7ac\uad81\ub3d9"
    ],
    "name:und_x_variant":[
        "Chegung-dong",
        "Chaegung-dong"
    ],
    "wof:name":"Chaegung-dong",
    "wof:placetype":"locality"
},
  "geometry": {"coordinates":[125.42167000000001,38.30722],"type":"Point"}
}