{
  "type": "Feature",
  "properties": {
    "gn:admin1_code":"11.0",
    "gn:asciiname":"Ch'okch'ol-li",
    "gn:country_code":"KP",
    "gn:dem":52,
    "gn:feature_class":"P",
    "gn:feature_code":"PPL",
    "gn:name":"Ch\u2019okch\u2019\u014fl-li",
    "gn:population":0,
    "gn:timezone":"Asia/Pyongyang",
    "iso:country":"KP",
    "name:und_x_variant":[
        "\ucd09\ucc9c\ub9ac",
        "Ch\u2019okch\u2019\u014fl-li"
    ],
    "wof:name":"Ch'okch'ol-li",
    "wof:placetype":"locality"
},
  "geometry": {"coordinates":[124.73083,40.06444000000001],"type":"Point"}
}