{
  "type": "Feature",
  "properties": {
    "gn:admin1_code":"7.0",
    "gn:admin2_code":"Y\u014fnsan-gun",
    "gn:asciiname":"Yangji-mal",
    "gn:country_code":"KP",
    "gn:dem":98,
    "gn:feature_class":"P",
    "gn:feature_code":"PPL",
    "gn:name":"Yangji-mal",
    "gn:population":0,
    "gn:timezone":"Asia/Pyongyang",
    "iso:country":"KP",
    "wof:name":"Yangji-mal",
    "wof:placetype":"locality"
},
  "geometry": {"coordinates":[126.14722,38.93917],"type":"Point"}
}