{
  "type": "Feature",
  "properties": {
    "gn:admin1_code":"11.0",
    "gn:asciiname":"Munja",
    "gn:country_code":"KP",
    "gn:dem":67,
    "gn:feature_class":"P",
    "gn:feature_code":"PPL",
    "gn:name":"Munja",
    "gn:population":0,
    "gn:timezone":"Asia/Pyongyang",
    "iso:country":"KP",
    "name:und_x_variant":[
        "Muncha",
        "Munja"
    ],
    "wof:name":"Munja",
    "wof:placetype":"locality"
},
  "geometry": {"coordinates":[125.72360999999999,39.81917],"type":"Point"}
}