{
  "type": "Feature",
  "properties": {
    "gn:admin1_code":"11.0",
    "gn:asciiname":"Tongsang-gol",
    "gn:country_code":"KP",
    "gn:dem":25,
    "gn:feature_class":"P",
    "gn:feature_code":"PPL",
    "gn:name":"Tongsang-gol",
    "gn:population":0,
    "gn:timezone":"Asia/Pyongyang",
    "iso:country":"KP",
    "name:und_x_variant":[
        "\ub3d9\uc0c1\uace8",
        "Tongsang-gol"
    ],
    "wof:name":"Tongsang-gol",
    "wof:placetype":"locality"
},
  "geometry": {"coordinates":[124.56,40.16333],"type":"Point"}
}