{
  "type": "Feature",
  "properties": {
    "gn:admin1_code":"15.0",
    "gn:admin2_code":"P\u2019y\u014fngs\u014fng-si",
    "gn:asciiname":"Uyon-dong",
    "gn:country_code":"KP",
    "gn:dem":37,
    "gn:feature_class":"P",
    "gn:feature_code":"PPL",
    "gn:name":"Uy\u014fn-dong",
    "gn:population":0,
    "gn:timezone":"Asia/Pyongyang",
    "iso:country":"KP",
    "name:kor_x_preferred":[
        "\uc6b0\uc5f0\ub3d9"
    ],
    "name:und_x_variant":[
        "Uy\u014fn-dong",
        "Uyeondong"
    ],
    "wof:name":"Uyon-dong",
    "wof:placetype":"locality"
},
  "geometry": {"coordinates":[126.02833,39.23],"type":"Point"}
}