{
  "type": "Feature",
  "properties": {
    "gn:admin1_code":"6.0",
    "gn:asciiname":"Tojang",
    "gn:country_code":"KP",
    "gn:dem":9,
    "gn:feature_class":"P",
    "gn:feature_code":"PPL",
    "gn:name":"Tojang",
    "gn:population":0,
    "gn:timezone":"Asia/Pyongyang",
    "iso:country":"KP",
    "name:und_x_variant":[
        "\ub3c4\uc7a5",
        "Tojang"
    ],
    "wof:name":"Tojang",
    "wof:placetype":"locality"
},
  "geometry": {"coordinates":[125.26111000000002,37.73472],"type":"Point"}
}