{
  "type": "Feature",
  "properties": {
    "gn:admin1_code":"3.0",
    "gn:asciiname":"Turim-ch'on",
    "gn:country_code":"KP",
    "gn:dem":29,
    "gn:feature_class":"P",
    "gn:feature_code":"PPL",
    "gn:name":"Turim-ch\u2019on",
    "gn:population":0,
    "gn:timezone":"Asia/Pyongyang",
    "iso:country":"KP",
    "name:und_x_variant":[
        "Turim-ch\u2019on",
        "\ub450\ub9bc\ucd0c"
    ],
    "wof:name":"Turim-ch'on",
    "wof:placetype":"locality"
},
  "geometry": {"coordinates":[128.27391,40.16688],"type":"Point"}
}