{
  "type": "Feature",
  "properties": {
    "gn:admin1_code":"11.0",
    "gn:asciiname":"Musong-ni",
    "gn:country_code":"KP",
    "gn:dem":22,
    "gn:feature_class":"P",
    "gn:feature_code":"PPL",
    "gn:name":"Musong-ni",
    "gn:population":0,
    "gn:timezone":"Asia/Pyongyang",
    "iso:country":"KP",
    "name:kor_x_preferred":[
        "\ubb34\uc1a1\ub9ac"
    ],
    "name:kor_x_variant":[
        "Musong-ma\u016dl",
        "\ubb34\uc1a1\ub9c8\uc744"
    ],
    "wof:name":"Musong-ni",
    "wof:placetype":"locality"
},
  "geometry": {"coordinates":[124.91867000000001,39.69862],"type":"Point"}
}