{
  "type": "Feature",
  "properties": {
    "gn:admin1_code":"6.0",
    "gn:asciiname":"Saenmal",
    "gn:cc2":"KP",
    "gn:country_code":"KP",
    "gn:dem":13,
    "gn:feature_class":"P",
    "gn:feature_code":"PPL",
    "gn:name":"Saenmal",
    "gn:population":0,
    "gn:timezone":"Asia/Pyongyang",
    "iso:country":"KP",
    "name:und_x_variant":[
        "Sae-mal",
        "Saet-mal",
        "Saenmal"
    ],
    "wof:name":"Saenmal",
    "wof:placetype":"locality"
},
  "geometry": {"coordinates":[126.09193999999999,37.81806],"type":"Point"}
}