{
  "type": "Feature",
  "properties": {
    "gn:admin1_code":"3.0",
    "gn:asciiname":"Somch'on",
    "gn:country_code":"KP",
    "gn:dem":231,
    "gn:feature_class":"P",
    "gn:feature_code":"PPL",
    "gn:name":"S\u014fmch\u2019on",
    "gn:population":0,
    "gn:timezone":"Asia/Pyongyang",
    "iso:country":"KP",
    "name:und_x_variant":[
        "\uc12c\ucd0c",
        "S\u014fmch\u2019on"
    ],
    "wof:name":"Somch'on",
    "wof:placetype":"locality"
},
  "geometry": {"coordinates":[128.86528000000001,40.6975],"type":"Point"}
}