{
  "type": "Feature",
  "properties": {
    "gn:admin1_code":"17.0",
    "gn:asciiname":"Tojang-gol",
    "gn:cc2":"KP",
    "gn:country_code":"KP",
    "gn:dem":99,
    "gn:feature_class":"P",
    "gn:feature_code":"PPL",
    "gn:name":"Tojang-gol",
    "gn:population":0,
    "gn:timezone":"Asia/Pyongyang",
    "iso:country":"KP",
    "name:und_x_variant":[
        "Tojangkol",
        "Tojanggok",
        "\ub3c4\uc7a5\uace8",
        "Tojang-gol"
    ],
    "wof:name":"Tojang-gol",
    "wof:placetype":"locality"
},
  "geometry": {"coordinates":[129.59,41.62806],"type":"Point"}
}