{
  "type": "Feature",
  "properties": {
    "gn:admin1_code":"3.0",
    "gn:asciiname":"Ch'on'gich'on",
    "gn:country_code":"KP",
    "gn:dem":184,
    "gn:feature_class":"P",
    "gn:feature_code":"PPL",
    "gn:name":"Ch\u2019\u014fn\u2019gich\u2019on",
    "gn:population":0,
    "gn:timezone":"Asia/Pyongyang",
    "iso:country":"KP",
    "name:und_x_variant":[
        "\ucc9c\uae30\ucd0c",
        "Ch\u2019\u014fn\u2019gich\u2019on"
    ],
    "wof:name":"Ch'on'gich'on",
    "wof:placetype":"locality"
},
  "geometry": {"coordinates":[126.85056000000002,39.59361],"type":"Point"}
}