{
  "type": "Feature",
  "properties": {
    "gn:admin1_code":"1.0",
    "gn:asciiname":"Naeryu-dong",
    "gn:country_code":"KP",
    "gn:dem":459,
    "gn:feature_class":"P",
    "gn:feature_code":"PPL",
    "gn:name":"Naeryu-dong",
    "gn:population":0,
    "gn:timezone":"Asia/Pyongyang",
    "iso:country":"KP",
    "name:und_x_variant":[
        "\ub0b4\ub958\ub3d9",
        "Naeryu-dong"
    ],
    "wof:name":"Naeryu-dong",
    "wof:placetype":"locality"
},
  "geometry": {"coordinates":[126.47499999999999,40.32306],"type":"Point"}
}