{
  "type": "Feature",
  "properties": {
    "gn:admin1_code":"1.0",
    "gn:admin2_code":"Tongsin-gun",
    "gn:asciiname":"Yoch'im-dong",
    "gn:country_code":"KP",
    "gn:dem":455,
    "gn:feature_class":"P",
    "gn:feature_code":"PPL",
    "gn:name":"Y\u014fch\u2019im-dong",
    "gn:population":0,
    "gn:timezone":"Asia/Pyongyang",
    "iso:country":"KP",
    "name:kor_x_preferred":[
        "\uc5ec\uce68\ub3d9"
    ],
    "name:und_x_variant":[
        "Y\u014fch\u2019im-dong"
    ],
    "wof:name":"Yoch'im-dong",
    "wof:placetype":"locality"
},
  "geometry": {"coordinates":[126.65722,40.36028],"type":"Point"}
}