{
  "type": "Feature",
  "properties": {
    "gn:admin1_code":"6.0",
    "gn:asciiname":"Mamyong-ni",
    "gn:country_code":"KP",
    "gn:dem":9,
    "gn:feature_class":"P",
    "gn:feature_code":"PPL",
    "gn:name":"Mamy\u014fng-ni",
    "gn:population":0,
    "gn:timezone":"Asia/Pyongyang",
    "iso:country":"KP",
    "name:eng_x_preferred":[
        "Mamyong"
    ],
    "name:eng_x_variant":[
        "Mamyong-ni"
    ],
    "wof:name":"Mamyong",
    "wof:placetype":"locality"
},
  "geometry": {"coordinates":[125.47638999999999,38.44139],"type":"Point"}
}