{
  "type": "Feature",
  "properties": {
    "gn:admin1_code":"7.0",
    "gn:asciiname":"Pae-gol",
    "gn:country_code":"KP",
    "gn:dem":212,
    "gn:feature_class":"P",
    "gn:feature_code":"PPL",
    "gn:name":"Pae-gol",
    "gn:population":0,
    "gn:timezone":"Asia/Pyongyang",
    "iso:country":"KP",
    "wof:name":"Pae-gol",
    "wof:placetype":"locality"
},
  "geometry": {"coordinates":[126.23389,38.56556],"type":"Point"}
}