{
  "type": "Feature",
  "properties": {
    "gn:admin1_code":"9.0",
    "gn:admin2_code":"P\u2019y\u0171nggang-gun",
    "gn:asciiname":"Oryongp'o",
    "gn:country_code":"KP",
    "gn:dem":346,
    "gn:feature_class":"P",
    "gn:feature_code":"PPL",
    "gn:name":"\u014eryongp\u2019o",
    "gn:population":0,
    "gn:timezone":"Asia/Pyongyang",
    "iso:country":"KP",
    "wof:name":"Oryongp'o",
    "wof:placetype":"locality"
},
  "geometry": {"coordinates":[127.32111,38.39889],"type":"Point"}
}