{
  "type": "Feature",
  "properties": {
    "gn:admin1_code":"12.0",
    "gn:asciiname":"Chi-ri",
    "gn:country_code":"KP",
    "gn:dem":5,
    "gn:feature_class":"P",
    "gn:feature_code":"PPL",
    "gn:name":"Chi-ri",
    "gn:population":0,
    "gn:timezone":"Asia/Pyongyang",
    "iso:country":"KP",
    "name:kor_x_preferred":[
        "\uc9c0\ub9ac"
    ],
    "name:und_x_variant":[
        "Jiri"
    ],
    "wof:name":"Chi-ri",
    "wof:placetype":"locality"
},
  "geometry": {"coordinates":[126.08324,39.14964000000001],"type":"Point"}
}