{
  "type": "Feature",
  "properties": {
    "gn:admin1_code":"6.0",
    "gn:admin2_code":"Paech\u2019\u014fn-gun",
    "gn:asciiname":"Pamgaeul",
    "gn:country_code":"KP",
    "gn:dem":19,
    "gn:feature_class":"P",
    "gn:feature_code":"PPL",
    "gn:name":"Pamgaeul",
    "gn:population":0,
    "gn:timezone":"Asia/Pyongyang",
    "iso:country":"KP",
    "name:und_x_variant":[
        "Pamgae-gol",
        "Pamgaeul"
    ],
    "wof:name":"Pamgaeul",
    "wof:placetype":"locality"
},
  "geometry": {"coordinates":[126.35556,37.91694],"type":"Point"}
}