{
  "type": "Feature",
  "properties": {
    "gn:admin1_code":"6.0",
    "gn:asciiname":"Tongho-ri",
    "gn:country_code":"KP",
    "gn:dem":141,
    "gn:feature_class":"P",
    "gn:feature_code":"PPL",
    "gn:name":"Tongho-ri",
    "gn:population":0,
    "gn:timezone":"Asia/Pyongyang",
    "iso:country":"KP",
    "wof:name":"Tongho-ri",
    "wof:placetype":"locality"
},
  "geometry": {"coordinates":[125.54833000000001,38.15417],"type":"Point"}
}