{
  "type": "Feature",
  "properties": {
    "gn:admin1_code":"12.0",
    "gn:asciiname":"Pidulbau",
    "gn:country_code":"KP",
    "gn:dem":127,
    "gn:feature_class":"P",
    "gn:feature_code":"PPL",
    "gn:name":"Pid\u016dlbau",
    "gn:population":0,
    "gn:timezone":"Asia/Pyongyang",
    "iso:country":"KP",
    "name:kor_x_preferred":[
        "\ube44\ub4e4\ubc14\uc6b0"
    ],
    "name:und_x_variant":[
        "Pid\u016dlbau",
        "Bideulbau"
    ],
    "wof:name":"Pidulbau",
    "wof:placetype":"locality"
},
  "geometry": {"coordinates":[125.83667,39.20389],"type":"Point"}
}