{
  "type": "Feature",
  "properties": {
    "gn:admin1_code":"15.0",
    "gn:asciiname":"Sama-dong",
    "gn:country_code":"KP",
    "gn:dem":433,
    "gn:feature_class":"P",
    "gn:feature_code":"PPL",
    "gn:name":"Sama-dong",
    "gn:population":0,
    "gn:timezone":"Asia/Pyongyang",
    "iso:country":"KP",
    "name:kor_x_preferred":[
        "\uc0ac\ub9c8\ub3d9"
    ],
    "wof:name":"Sama-dong",
    "wof:placetype":"locality"
},
  "geometry": {"coordinates":[126.4425,39.13639000000001],"type":"Point"}
}