{
  "type": "Feature",
  "properties": {
    "gn:admin1_code":"1.0",
    "gn:asciiname":"Hyolp'yong-dong",
    "gn:country_code":"KP",
    "gn:dem":275,
    "gn:feature_class":"P",
    "gn:feature_code":"PPL",
    "gn:name":"Hy\u014flp\u2019y\u014fng-dong",
    "gn:population":0,
    "gn:timezone":"Asia/Pyongyang",
    "iso:country":"KP",
    "name:und_x_variant":[
        "\ud608\ud3c9\ub3d9",
        "Hy\u014flp\u2019y\u014fng-dong"
    ],
    "wof:name":"Hyolp'yong-dong",
    "wof:placetype":"locality"
},
  "geometry": {"coordinates":[126.38083,41.16333],"type":"Point"}
}