{
  "type": "Feature",
  "properties": {
    "gn:admin1_code":"12.0",
    "gn:admin2_code":"Kangdong-gun",
    "gn:asciiname":"Yongbong-ni",
    "gn:country_code":"KP",
    "gn:dem":53,
    "gn:feature_class":"P",
    "gn:feature_code":"PPL",
    "gn:name":"Yongbong-ni",
    "gn:population":0,
    "gn:timezone":"Asia/Pyongyang",
    "iso:country":"KP",
    "name:eng_x_preferred":[
        "Yongbong"
    ],
    "name:eng_x_variant":[
        "Yongbong-ni"
    ],
    "name:kor_x_preferred":[
        "\uc6a9\ubcf5\ub9ac"
    ],
    "name:und_x_variant":[
        "Yongbongni"
    ],
    "wof:name":"Yongbong",
    "wof:placetype":"locality"
},
  "geometry": {"coordinates":[126.06222,39.11083],"type":"Point"}
}