{
  "type": "Feature",
  "properties": {
    "gn:admin1_code":"1.0",
    "gn:asciiname":"Unsu-ri",
    "gn:country_code":"KP",
    "gn:dem":1157,
    "gn:feature_class":"P",
    "gn:feature_code":"PPL",
    "gn:name":"Unsu-ri",
    "gn:population":0,
    "gn:timezone":"Asia/Pyongyang",
    "iso:country":"KP",
    "name:kor_x_preferred":[
        "\uc6b4\uc218\ub9ac"
    ],
    "name:und_x_variant":[
        "Unsu-nodongjagu",
        "Unsu-ri"
    ],
    "wof:name":"Unsu-ri",
    "wof:placetype":"locality"
},
  "geometry": {"coordinates":[127.06667,40.66667],"type":"Point"}
}