{
  "type": "Feature",
  "properties": {
    "gn:admin1_code":"6.0",
    "gn:asciiname":"Wolch'ol-li",
    "gn:country_code":"KP",
    "gn:dem":11,
    "gn:feature_class":"P",
    "gn:feature_code":"PPL",
    "gn:name":"W\u014flch\u2019\u014fl-li",
    "gn:population":0,
    "gn:timezone":"Asia/Pyongyang",
    "iso:country":"KP",
    "name:und_x_variant":[
        "W\u014flch\u2019\u014fn-ni",
        "\uc6d4\ucd0c\ub9ac",
        "My\u014fngch\u2019\u014fn-ni",
        "W\u014flch\u2019\u014fl-li"
    ],
    "wof:name":"Wolch'ol-li",
    "wof:placetype":"locality"
},
  "geometry": {"coordinates":[125.12361,37.99861],"type":"Point"}
}