{
  "type": "Feature",
  "properties": {
    "gn:admin1_code":"11.0",
    "gn:asciiname":"Yuga-dong",
    "gn:country_code":"KP",
    "gn:dem":122,
    "gn:feature_class":"P",
    "gn:feature_code":"PPL",
    "gn:name":"Yuga-dong",
    "gn:population":0,
    "gn:timezone":"Asia/Pyongyang",
    "iso:country":"KP",
    "name:kor_x_preferred":[
        "\uc720\uac00\ub3d9"
    ],
    "wof:name":"Yuga-dong",
    "wof:placetype":"locality"
},
  "geometry": {"coordinates":[124.94861000000002,39.90889],"type":"Point"}
}