{
  "type": "Feature",
  "properties": {
    "gn:admin1_code":"11.0",
    "gn:asciiname":"Tongsong-ni",
    "gn:country_code":"KP",
    "gn:dem":17,
    "gn:feature_class":"P",
    "gn:feature_code":"PPL",
    "gn:name":"Tongs\u014fng-ni",
    "gn:population":0,
    "gn:timezone":"Asia/Pyongyang",
    "iso:country":"KP",
    "name:eng_x_preferred":[
        "Tongsong"
    ],
    "name:eng_x_variant":[
        "Tongsong-ni"
    ],
    "name:und_x_variant":[
        "Tongs\u014fng-dong",
        "\ub3d9\uc131\ub9ac",
        "Tongs\u014fng-ni"
    ],
    "wof:name":"Tongsong",
    "wof:placetype":"locality"
},
  "geometry": {"coordinates":[124.575,39.91722],"type":"Point"}
}