{
  "type": "Feature",
  "properties": {
    "gn:admin1_code":"1.0",
    "gn:asciiname":"Yonmu-ri",
    "gn:country_code":"KP",
    "gn:dem":138,
    "gn:feature_class":"P",
    "gn:feature_code":"PPL",
    "gn:name":"Y\u014fnmu-ri",
    "gn:population":0,
    "gn:timezone":"Asia/Pyongyang",
    "iso:country":"KP",
    "name:und_x_variant":[
        "Y\u014fnmu-dong",
        "\ub828\ubb34\ub9ac",
        "Y\u014fnmu-ri"
    ],
    "wof:name":"Yonmu-ri",
    "wof:placetype":"locality"
},
  "geometry": {"coordinates":[125.7325,40.83611],"type":"Point"}
}