{
  "type": "Feature",
  "properties": {
    "gn:admin1_code":"15.0",
    "gn:admin2_code":"Y\u014fngw\u014fn-gun",
    "gn:asciiname":"Hwasul-li",
    "gn:cc2":"KP",
    "gn:country_code":"KP",
    "gn:dem":237,
    "gn:feature_class":"P",
    "gn:feature_code":"PPL",
    "gn:name":"Hwasul-li",
    "gn:population":0,
    "gn:timezone":"Asia/Pyongyang",
    "iso:country":"KP",
    "name:kor_x_preferred":[
        "\ud654\uc21c\ub9ac"
    ],
    "name:und_x_variant":[
        "Hwasun-ni",
        "Hwasul-li"
    ],
    "wof:name":"Hwasul-li",
    "wof:placetype":"locality"
},
  "geometry": {"coordinates":[126.53222,39.86361],"type":"Point"}
}