{
  "type": "Feature",
  "properties": {
    "gn:admin1_code":"0.0",
    "gn:asciiname":"Wonhak",
    "gn:country_code":"KP",
    "gn:dem":94,
    "gn:feature_class":"P",
    "gn:feature_code":"PPL",
    "gn:name":"W\u014fnhak",
    "gn:population":0,
    "gn:timezone":"Asia/Pyongyang",
    "iso:country":"KP",
    "name:kor_x_preferred":[
        "\uc6d0\ud559"
    ],
    "name:und_x_variant":[
        "W\u014fnhak"
    ],
    "wof:name":"Wonhak",
    "wof:placetype":"locality"
},
  "geometry": {"coordinates":[124.54656,39.9818],"type":"Point"}
}