{
  "type": "Feature",
  "properties": {
    "gn:admin1_code":"15.0",
    "gn:asciiname":"Saengdong-ni",
    "gn:country_code":"KP",
    "gn:dem":792,
    "gn:feature_class":"P",
    "gn:feature_code":"PPL",
    "gn:name":"Saengd\u014fng-ni",
    "gn:population":0,
    "gn:timezone":"Asia/Pyongyang",
    "iso:country":"KP",
    "name:und_x_variant":[
        "\uc0dd\ub355\ub9ac",
        "Saengd\u014fng-ni"
    ],
    "wof:name":"Saengdong-ni",
    "wof:placetype":"locality"
},
  "geometry": {"coordinates":[126.97194,40.20806],"type":"Point"}
}