{
  "type": "Feature",
  "properties": {
    "gn:admin1_code":"0.0",
    "gn:asciiname":"Tanggol",
    "gn:cc2":"KP",
    "gn:country_code":"KP",
    "gn:dem":7,
    "gn:feature_class":"P",
    "gn:feature_code":"PPL",
    "gn:name":"Tanggol",
    "gn:population":0,
    "gn:timezone":"Asia/Pyongyang",
    "iso:country":"KP",
    "name:kor_x_preferred":[
        "\ub2f9\uace8"
    ],
    "name:und_x_variant":[
        "Tanggok",
        "Tanggol"
    ],
    "wof:name":"Tanggol",
    "wof:placetype":"locality"
},
  "geometry": {"coordinates":[124.78333000000001,39.81667],"type":"Point"}
}