{
  "type": "Feature",
  "properties": {
    "gn:admin1_code":"3.0",
    "gn:asciiname":"Samgo-ri",
    "gn:country_code":"KP",
    "gn:dem":327,
    "gn:feature_class":"P",
    "gn:feature_code":"PPL",
    "gn:name":"Samg\u014f-ri",
    "gn:population":0,
    "gn:timezone":"Asia/Pyongyang",
    "iso:country":"KP",
    "name:und_x_variant":[
        "Samg\u014f-ri",
        "\uc0bc\uac70\ub9ac"
    ],
    "wof:name":"Samgo-ri",
    "wof:placetype":"locality"
},
  "geometry": {"coordinates":[128.53559999999999,40.45696],"type":"Point"}
}