{
  "type": "Feature",
  "properties": {
    "gn:admin1_code":"3.0",
    "gn:admin2_code":"K\u016dmya-gun",
    "gn:asciiname":"Tokkumi-ri",
    "gn:country_code":"KP",
    "gn:dem":25,
    "gn:feature_class":"P",
    "gn:feature_code":"PPL",
    "gn:name":"Tokkumi-ri",
    "gn:population":0,
    "gn:timezone":"Asia/Pyongyang",
    "iso:country":"KP",
    "wof:name":"Tokkumi-ri",
    "wof:placetype":"locality"
},
  "geometry": {"coordinates":[127.48528,39.44056],"type":"Point"}
}