{
  "type": "Feature",
  "properties": {
    "gn:admin1_code":"6.0",
    "gn:asciiname":"Koup-tong",
    "gn:country_code":"KP",
    "gn:dem":86,
    "gn:feature_class":"P",
    "gn:feature_code":"PPL",
    "gn:name":"Ko\u016dp-tong",
    "gn:population":0,
    "gn:timezone":"Asia/Pyongyang",
    "iso:country":"KP",
    "name:kor_x_preferred":[
        "\uace0\uc74d\ub3d9"
    ],
    "name:kor_x_variant":[
        "Ko\u016dp-tong"
    ],
    "wof:name":"Koup-tong",
    "wof:placetype":"locality"
},
  "geometry": {"coordinates":[125.13083,38.36972],"type":"Point"}
}