{
  "type": "Feature",
  "properties": {
    "gn:admin1_code":"6.0",
    "gn:asciiname":"Polmal",
    "gn:cc2":"KP",
    "gn:country_code":"KP",
    "gn:dem":135,
    "gn:feature_class":"P",
    "gn:feature_code":"PPL",
    "gn:name":"P\u014flmal",
    "gn:population":0,
    "gn:timezone":"Asia/Pyongyang",
    "iso:country":"KP",
    "name:und_x_variant":[
        "P\u014fl-ma\u016dl",
        "P\u014flmal"
    ],
    "wof:name":"Polmal",
    "wof:placetype":"locality"
},
  "geometry": {"coordinates":[125.50833,38.17778],"type":"Point"}
}