{
  "type": "Feature",
  "properties": {
    "gn:admin1_code":"3.0",
    "gn:asciiname":"Sanich'on",
    "gn:country_code":"KP",
    "gn:dem":645,
    "gn:feature_class":"P",
    "gn:feature_code":"PPL",
    "gn:name":"Sanich\u2019on",
    "gn:population":0,
    "gn:timezone":"Asia/Pyongyang",
    "iso:country":"KP",
    "name:und_x_variant":[
        "\uc0ac\ub2c8\ucd0c",
        "Sanich\u2019on"
    ],
    "wof:name":"Sanich'on",
    "wof:placetype":"locality"
},
  "geometry": {"coordinates":[127.71028,40.37778],"type":"Point"}
}