{
  "type": "Feature",
  "properties": {
    "gn:admin1_code":"15.0",
    "gn:admin2_code":"Hoech\u2019ang-gun",
    "gn:asciiname":"Taedong-ni",
    "gn:country_code":"KP",
    "gn:dem":133,
    "gn:feature_class":"P",
    "gn:feature_code":"PPL",
    "gn:name":"Taed\u014fng-ni",
    "gn:population":0,
    "gn:timezone":"Asia/Pyongyang",
    "iso:country":"KP",
    "name:eng_x_preferred":[
        "Taedong"
    ],
    "name:eng_x_variant":[
        "Taedong-ni"
    ],
    "wof:name":"Taedong",
    "wof:placetype":"locality"
},
  "geometry": {"coordinates":[126.23556000000001,39.11806],"type":"Point"}
}