{
  "type": "Feature",
  "properties": {
    "gn:admin1_code":"15.0",
    "gn:asciiname":"Wa-dong",
    "gn:country_code":"KP",
    "gn:dem":164,
    "gn:feature_class":"P",
    "gn:feature_code":"PPL",
    "gn:name":"Wa-dong",
    "gn:population":0,
    "gn:timezone":"Asia/Pyongyang",
    "iso:country":"KP",
    "name:kor_x_preferred":[
        "\uc640\ub3d9"
    ],
    "wof:name":"Wa-dong",
    "wof:placetype":"locality"
},
  "geometry": {"coordinates":[126.45917,39.2675],"type":"Point"}
}