{
  "type": "Feature",
  "properties": {
    "gn:admin1_code":"3.0",
    "gn:asciiname":"Nodong-ni",
    "gn:cc2":"KP",
    "gn:country_code":"KP",
    "gn:dem":20,
    "gn:feature_class":"P",
    "gn:feature_code":"PPL",
    "gn:name":"Nodong-ni",
    "gn:population":0,
    "gn:timezone":"Asia/Pyongyang",
    "iso:country":"KP",
    "name:und_x_variant":[
        "Nadong-ni",
        "Rod\u014d-ri",
        "\ub178\ub3d9\ub9ac",
        "Nodong-ni"
    ],
    "wof:name":"Nodong-ni",
    "wof:placetype":"locality"
},
  "geometry": {"coordinates":[128.79806000000002,40.41417],"type":"Point"}
}