{
  "type": "Feature",
  "properties": {
    "gn:admin1_code":"7.0",
    "gn:asciiname":"Kumsong-ni",
    "gn:country_code":"KP",
    "gn:dem":83,
    "gn:feature_class":"P",
    "gn:feature_code":"PPL",
    "gn:name":"K\u016dms\u014fng-ni",
    "gn:population":0,
    "gn:timezone":"Asia/Pyongyang",
    "iso:country":"KP",
    "name:kor_x_preferred":[
        "\uae08\uc131\ub9ac"
    ],
    "name:und_x_variant":[
        "K\u016dms\u014fng-ni"
    ],
    "wof:name":"Kumsong-ni",
    "wof:placetype":"locality"
},
  "geometry": {"coordinates":[126.60138999999999,38.43694],"type":"Point"}
}