{
  "type": "Feature",
  "properties": {
    "gn:admin1_code":"12.0",
    "gn:asciiname":"Sojae-dong",
    "gn:country_code":"KP",
    "gn:dem":12,
    "gn:feature_class":"P",
    "gn:feature_code":"PPL",
    "gn:name":"Sojae-dong",
    "gn:population":0,
    "gn:timezone":"Asia/Pyongyang",
    "iso:country":"KP",
    "name:und_x_variant":[
        "S\u014fje-dong",
        "\uc18c\uc7ac\ub3d9",
        "Sojae-dong",
        "Sojaedong"
    ],
    "wof:name":"Sojae-dong",
    "wof:placetype":"locality"
},
  "geometry": {"coordinates":[125.79139000000001,38.98194],"type":"Point"}
}