{
  "type": "Feature",
  "properties": {
    "gn:admin1_code":"6.0",
    "gn:asciiname":"Tongdol",
    "gn:country_code":"KP",
    "gn:dem":11,
    "gn:feature_class":"P",
    "gn:feature_code":"PPL",
    "gn:name":"Tongdol",
    "gn:population":0,
    "gn:timezone":"Asia/Pyongyang",
    "iso:country":"KP",
    "name:und_x_variant":[
        "\ub3d9\ub3cc",
        "Tongdol"
    ],
    "wof:name":"Tongdol",
    "wof:placetype":"locality"
},
  "geometry": {"coordinates":[125.61750000000001,37.84278],"type":"Point"}
}