{
  "type": "Feature",
  "properties": {
    "gn:admin1_code":"6.0",
    "gn:asciiname":"Sillyang-dong",
    "gn:country_code":"KP",
    "gn:dem":107,
    "gn:feature_class":"P",
    "gn:feature_code":"PPL",
    "gn:name":"Sillyang-dong",
    "gn:population":0,
    "gn:timezone":"Asia/Pyongyang",
    "iso:country":"KP",
    "wof:name":"Sillyang-dong",
    "wof:placetype":"locality"
},
  "geometry": {"coordinates":[125.69889000000001,38.22694],"type":"Point"}
}