{
  "type": "Feature",
  "properties": {
    "gn:admin1_code":"9.0",
    "gn:asciiname":"Tong-ni",
    "gn:country_code":"KP",
    "gn:dem":731,
    "gn:feature_class":"P",
    "gn:feature_code":"PPL",
    "gn:name":"T\u014fng-ni",
    "gn:population":0,
    "gn:timezone":"Asia/Pyongyang",
    "iso:country":"KP",
    "name:kor_x_preferred":[
        "\ub355\ub9ac"
    ],
    "name:kor_x_variant":[
        "T\u014fng-ni"
    ],
    "wof:name":"Tong-ni",
    "wof:placetype":"locality"
},
  "geometry": {"coordinates":[127.2525,38.77278],"type":"Point"}
}