{
  "type": "Feature",
  "properties": {
    "gn:admin1_code":"3.0",
    "gn:admin2_code":"K\u016dmya-gun",
    "gn:asciiname":"Udang-ni",
    "gn:country_code":"KP",
    "gn:dem":10,
    "gn:feature_class":"P",
    "gn:feature_code":"PPL",
    "gn:name":"Udang-ni",
    "gn:population":0,
    "gn:timezone":"Asia/Pyongyang",
    "iso:country":"KP",
    "name:eng_x_preferred":[
        "Udang"
    ],
    "name:eng_x_variant":[
        "Udang-ni"
    ],
    "wof:name":"Udang",
    "wof:placetype":"locality"
},
  "geometry": {"coordinates":[127.36111,39.49],"type":"Point"}
}