{
  "type": "Feature",
  "properties": {
    "gn:admin1_code":"12.0",
    "gn:asciiname":"Soong-ni",
    "gn:country_code":"KP",
    "gn:dem":47,
    "gn:feature_class":"P",
    "gn:feature_code":"PPL",
    "gn:name":"Soong-ni",
    "gn:population":0,
    "gn:timezone":"Asia/Pyongyang",
    "iso:country":"KP",
    "name:und_x_variant":[
        "\uc18c\uc639\ub9ac",
        "Soong-ni"
    ],
    "wof:name":"Soong-ni",
    "wof:placetype":"locality"
},
  "geometry": {"coordinates":[125.87944,38.84667],"type":"Point"}
}