{
  "type": "Feature",
  "properties": {
    "gn:admin1_code":"11.0",
    "gn:asciiname":"Tongnin-dong",
    "gn:country_code":"KP",
    "gn:dem":41,
    "gn:feature_class":"P",
    "gn:feature_code":"PPL",
    "gn:name":"Tongnin-dong",
    "gn:population":0,
    "gn:timezone":"Asia/Pyongyang",
    "iso:country":"KP",
    "name:und_x_variant":[
        "\ub3d9\ub9b0\ub3d9",
        "Tongnin-dong"
    ],
    "wof:name":"Tongnin-dong",
    "wof:placetype":"locality"
},
  "geometry": {"coordinates":[124.52083,40.08],"type":"Point"}
}