{
  "type": "Feature",
  "properties": {
    "gn:admin1_code":"6.0",
    "gn:asciiname":"Undong-ni",
    "gn:country_code":"KP",
    "gn:dem":69,
    "gn:feature_class":"P",
    "gn:feature_code":"PPL",
    "gn:name":"\u016cndong-ni",
    "gn:population":0,
    "gn:timezone":"Asia/Pyongyang",
    "iso:country":"KP",
    "name:und_x_variant":[
        "\uc740\ub3d9\ub9ac",
        "\u016cndong-ni"
    ],
    "wof:name":"Undong-ni",
    "wof:placetype":"locality"
},
  "geometry": {"coordinates":[125.32611,37.98778],"type":"Point"}
}