{
  "type": "Feature",
  "properties": {
    "gn:admin1_code":"6.0",
    "gn:asciiname":"Namsan",
    "gn:country_code":"KP",
    "gn:dem":40,
    "gn:feature_class":"P",
    "gn:feature_code":"PPL",
    "gn:name":"Namsan",
    "gn:population":0,
    "gn:timezone":"Asia/Pyongyang",
    "iso:country":"KP",
    "name:ceb_x_preferred":[
        "Namsan"
    ],
    "name:deu_x_preferred":[
        "Namsan"
    ],
    "name:fra_x_preferred":[
        "Namsan"
    ],
    "name:hun_x_preferred":[
        "Namszan"
    ],
    "name:por_x_preferred":[
        "Namsan"
    ],
    "name:rus_x_preferred":[
        "\u041d\u0430\u043c\u0441\u0430\u043d"
    ],
    "name:sco_x_preferred":[
        "Namsan"
    ],
    "name:spa_x_preferred":[
        "Namsan"
    ],
    "name:swe_x_preferred":[
        "Namsan"
    ],
    "wof:name":"Namsan",
    "wof:placetype":"locality"
},
  "geometry": {"coordinates":[125.59721999999999,38.34417],"type":"Point"}
}