{
  "type": "Feature",
  "properties": {
    "gn:admin1_code":"12.0",
    "gn:admin2_code":"Kangdong-gun",
    "gn:asciiname":"Ch'ongt'al-li",
    "gn:country_code":"KP",
    "gn:dem":93,
    "gn:feature_class":"P",
    "gn:feature_code":"PPL",
    "gn:name":"Ch\u2019\u014fngt\u2019al-li",
    "gn:population":0,
    "gn:timezone":"Asia/Pyongyang",
    "iso:country":"KP",
    "name:kor_x_preferred":[
        "\uccad\ud0c4\ub9ac"
    ],
    "name:und_x_variant":[
        "Ch\u2019\u014fngt\u2019al-li",
        "Cheongtalli"
    ],
    "wof:name":"Ch'ongt'al-li",
    "wof:placetype":"locality"
},
  "geometry": {"coordinates":[126.12555999999999,38.99417],"type":"Point"}
}