{
  "type": "Feature",
  "properties": {
    "gn:admin1_code":"12.0",
    "gn:asciiname":"Sogoumul",
    "gn:country_code":"KP",
    "gn:dem":89,
    "gn:feature_class":"P",
    "gn:feature_code":"PPL",
    "gn:name":"Sogoumul",
    "gn:population":0,
    "gn:timezone":"Asia/Pyongyang",
    "iso:country":"KP",
    "name:und_x_variant":[
        "Sogoj\u014fng",
        "\uc18c\uace0\uc6b0\ubb3c",
        "Sogoumul"
    ],
    "wof:name":"Sogoumul",
    "wof:placetype":"locality"
},
  "geometry": {"coordinates":[125.89778,38.88194],"type":"Point"}
}