{
  "type": "Feature",
  "properties": {
    "gn:admin1_code":"13.0",
    "gn:asciiname":"Ch'abo-ri",
    "gn:country_code":"KP",
    "gn:dem":881,
    "gn:feature_class":"P",
    "gn:feature_code":"PPL",
    "gn:name":"Ch\u2019abo-ri",
    "gn:population":0,
    "gn:timezone":"Asia/Pyongyang",
    "iso:country":"KP",
    "name:kor_x_preferred":[
        "\ucc28\ubcf4\ub9ac"
    ],
    "name:und_x_variant":[
        "Ch\u2019ap\u2019o-ri",
        "Ch\u2019abo-ri"
    ],
    "wof:name":"Ch'abo-ri",
    "wof:placetype":"locality"
},
  "geometry": {"coordinates":[127.73902,41.29422],"type":"Point"}
}