{
  "type": "Feature",
  "properties": {
    "gn:admin1_code":"1.0",
    "gn:asciiname":"Hwasindonggangjang-dong",
    "gn:country_code":"KP",
    "gn:dem":415,
    "gn:feature_class":"P",
    "gn:feature_code":"PPL",
    "gn:name":"Hwasindonggangjang-dong",
    "gn:population":0,
    "gn:timezone":"Asia/Pyongyang",
    "iso:country":"KP",
    "name:und_x_variant":[
        "Kangjang-dong",
        "\ud654\uc2e0\ub3d9\uac15\uc7a5\ub3d9",
        "Hwasindongkangjang-dong",
        "Hwasindonggangjang-dong"
    ],
    "wof:name":"Hwasindonggangjang-dong",
    "wof:placetype":"locality"
},
  "geometry": {"coordinates":[125.92972,40.75611],"type":"Point"}
}