{
  "type": "Feature",
  "properties": {
    "gn:admin1_code":"6.0",
    "gn:asciiname":"Kwonp'yong-dong",
    "gn:country_code":"KP",
    "gn:dem":6,
    "gn:feature_class":"P",
    "gn:feature_code":"PPL",
    "gn:name":"Kw\u014fnp\u2019y\u014fng-dong",
    "gn:population":0,
    "gn:timezone":"Asia/Pyongyang",
    "iso:country":"KP",
    "name:und_x_variant":[
        "\uad8c\ud3c9\ub3d9",
        "Kw\u014fnp\u2019y\u014fng-dong"
    ],
    "wof:name":"Kwonp'yong-dong",
    "wof:placetype":"locality"
},
  "geometry": {"coordinates":[125.0825,38.54778],"type":"Point"}
}