{
  "type": "Feature",
  "properties": {
    "gn:admin1_code":"15.0",
    "gn:asciiname":"Pukch'ang",
    "gn:country_code":"KP",
    "gn:dem":142,
    "gn:feature_class":"P",
    "gn:feature_code":"PPL",
    "gn:name":"Pukch\u2019ang",
    "gn:population":0,
    "gn:timezone":"Asia/Pyongyang",
    "iso:country":"KP",
    "name:kor_x_preferred":[
        "\ubd81\ucc3d"
    ],
    "name:kor_x_variant":[
        "Pukch\u2019ang"
    ],
    "wof:name":"Pukch'ang",
    "wof:placetype":"locality"
},
  "geometry": {"coordinates":[126.37111000000002,39.3575],"type":"Point"}
}