{
  "type": "Feature",
  "properties": {
    "gn:admin1_code":"9.0",
    "gn:asciiname":"Tujondong-ni",
    "gn:country_code":"KP",
    "gn:dem":369,
    "gn:feature_class":"P",
    "gn:feature_code":"PPL",
    "gn:name":"Tuj\u014fndong-ni",
    "gn:population":0,
    "gn:timezone":"Asia/Pyongyang",
    "iso:country":"KP",
    "name:und_x_variant":[
        "\ub450\uc804\ub3d9\ub9ac",
        "Tuj\u014fndong-ni"
    ],
    "wof:name":"Tujondong-ni",
    "wof:placetype":"locality"
},
  "geometry": {"coordinates":[127.68028,38.68444],"type":"Point"}
}