{
  "type": "Feature",
  "properties": {
    "gn:admin1_code":"11.0",
    "gn:asciiname":"Pu-dong",
    "gn:country_code":"KP",
    "gn:dem":99,
    "gn:feature_class":"P",
    "gn:feature_code":"PPL",
    "gn:name":"Pu-dong",
    "gn:population":0,
    "gn:timezone":"Asia/Pyongyang",
    "iso:country":"KP",
    "name:und_x_variant":[
        "\ubd80\ub3d9",
        "Pu-dong"
    ],
    "wof:name":"Pu-dong",
    "wof:placetype":"locality"
},
  "geometry": {"coordinates":[125.82472,40.04417],"type":"Point"}
}