{
  "type": "Feature",
  "properties": {
    "gn:admin1_code":"7.0",
    "gn:asciiname":"Hyojamun",
    "gn:country_code":"KP",
    "gn:dem":202,
    "gn:feature_class":"P",
    "gn:feature_code":"PPL",
    "gn:name":"Hyojamun",
    "gn:population":0,
    "gn:timezone":"Asia/Pyongyang",
    "iso:country":"KP",
    "wof:name":"Hyojamun",
    "wof:placetype":"locality"
},
  "geometry": {"coordinates":[126.68028,38.45778],"type":"Point"}
}