{
  "type": "Feature",
  "properties": {
    "gn:admin1_code":"6.0",
    "gn:asciiname":"Komch'ol-li",
    "gn:country_code":"KP",
    "gn:dem":102,
    "gn:feature_class":"P",
    "gn:feature_code":"PPL",
    "gn:name":"K\u014fmch\u2019ol-li",
    "gn:population":0,
    "gn:timezone":"Asia/Pyongyang",
    "iso:country":"KP",
    "name:kor_x_preferred":[
        "\uac80\ucc9c\ub9ac"
    ],
    "name:und_x_variant":[
        "K\u014fmch\u2019on-ni",
        "K\u014fmch\u2019ol-li"
    ],
    "wof:name":"Komch'ol-li",
    "wof:placetype":"locality"
},
  "geometry": {"coordinates":[125.72722,38.23472],"type":"Point"}
}