{
  "type": "Feature",
  "properties": {
    "gn:admin1_code":"6.0",
    "gn:asciiname":"Hwasan-dong",
    "gn:country_code":"KP",
    "gn:dem":68,
    "gn:feature_class":"P",
    "gn:feature_code":"PPL",
    "gn:name":"Hwasan-dong",
    "gn:population":0,
    "gn:timezone":"Asia/Pyongyang",
    "iso:country":"KP",
    "name:kor_x_preferred":[
        "\ud654\uc0b0\ub3d9"
    ],
    "wof:name":"Hwasan-dong",
    "wof:placetype":"locality"
},
  "geometry": {"coordinates":[125.17055999999999,38.34944],"type":"Point"}
}