{
  "type": "Feature",
  "properties": {
    "gn:admin1_code":"3.0",
    "gn:asciiname":"Yonggwang-dong",
    "gn:country_code":"KP",
    "gn:dem":25,
    "gn:feature_class":"P",
    "gn:feature_code":"PPL",
    "gn:name":"Y\u014fnggwang-dong",
    "gn:population":0,
    "gn:timezone":"Asia/Pyongyang",
    "iso:country":"KP",
    "name:und_x_variant":[
        "\uc601\uad11\ub3d9",
        "Y\u014fnggwang-dong"
    ],
    "wof:name":"Yonggwang-dong",
    "wof:placetype":"locality"
},
  "geometry": {"coordinates":[127.59278,39.89639],"type":"Point"}
}