{
  "type": "Feature",
  "properties": {
    "gn:admin1_code":"0.0",
    "gn:asciiname":"Taech'ol-li",
    "gn:country_code":"KP",
    "gn:dem":75,
    "gn:feature_class":"P",
    "gn:feature_code":"PPL",
    "gn:name":"Taech\u2019ol-li",
    "gn:population":0,
    "gn:timezone":"Asia/Pyongyang",
    "iso:country":"KP",
    "name:kor_x_preferred":[
        "\ub300\ucd0c\ub9ac"
    ],
    "name:und_x_variant":[
        "Taech\u2019ol-li",
        "Taech\u2019on-ni"
    ],
    "wof:name":"Taech'ol-li",
    "wof:placetype":"locality"
},
  "geometry": {"coordinates":[126.15000000000001,38.23333],"type":"Point"}
}