{
  "type": "Feature",
  "properties": {
    "gn:admin1_code":"0.0",
    "gn:asciiname":"Sang-ni",
    "gn:country_code":"KP",
    "gn:dem":4,
    "gn:feature_class":"P",
    "gn:feature_code":"PPL",
    "gn:name":"Sang-ni",
    "gn:population":0,
    "gn:timezone":"Asia/Pyongyang",
    "iso:country":"KP",
    "name:kor_x_preferred":[
        "\uc0c1\ub9ac"
    ],
    "wof:name":"Sang-ni",
    "wof:placetype":"locality"
},
  "geometry": {"coordinates":[127.53333000000001,39.81667],"type":"Point"}
}