{
  "type": "Feature",
  "properties": {
    "gn:admin1_code":"7.0",
    "gn:admin2_code":"T\u2019osan-gun",
    "gn:asciiname":"Tangdunch'i",
    "gn:country_code":"KP",
    "gn:dem":209,
    "gn:feature_class":"P",
    "gn:feature_code":"PPL",
    "gn:name":"Tangdunch\u2019i",
    "gn:population":0,
    "gn:timezone":"Asia/Pyongyang",
    "iso:country":"KP",
    "wof:name":"Tangdunch'i",
    "wof:placetype":"locality"
},
  "geometry": {"coordinates":[126.72833,38.23444],"type":"Point"}
}