{
  "type": "Feature",
  "properties": {
    "gn:admin1_code":"17.0",
    "gn:admin2_code":"Kimch'aek-si",
    "gn:asciiname":"Ch'onghak-tong",
    "gn:country_code":"KP",
    "gn:dem":803,
    "gn:feature_class":"P",
    "gn:feature_code":"PPL",
    "gn:name":"Ch\u2019\u014fnghak-tong",
    "gn:population":0,
    "gn:timezone":"Asia/Pyongyang",
    "iso:country":"KP",
    "name:und_x_variant":[
        "Ch\u2019\u014fnghang-ni",
        "\uccad\ud559\ub3d9",
        "Ch\u2019\u014fnghak-tong"
    ],
    "wof:name":"Ch'onghak-tong",
    "wof:placetype":"locality"
},
  "geometry": {"coordinates":[128.98139,40.85944],"type":"Point"}
}