{
  "type": "Feature",
  "properties": {
    "gn:admin1_code":"3.0",
    "gn:asciiname":"Konch'ol-li",
    "gn:country_code":"KP",
    "gn:dem":315,
    "gn:feature_class":"P",
    "gn:feature_code":"PPL",
    "gn:name":"K\u014fnch\u2019\u014fl-li",
    "gn:population":0,
    "gn:timezone":"Asia/Pyongyang",
    "iso:country":"KP",
    "name:kor_x_preferred":[
        "\uac74\ucc9c\ub9ac"
    ],
    "name:kor_x_variant":[
        "K\u014fnch\u2019\u014fl-li"
    ],
    "wof:name":"Konch'ol-li",
    "wof:placetype":"locality"
},
  "geometry": {"coordinates":[126.91110999999999,39.35583],"type":"Point"}
}