{
  "type": "Feature",
  "properties": {
    "gn:admin1_code":"17.0",
    "gn:asciiname":"Hagam-dong",
    "gn:country_code":"KP",
    "gn:dem":57,
    "gn:feature_class":"P",
    "gn:feature_code":"PPL",
    "gn:name":"Hagam-dong",
    "gn:population":0,
    "gn:timezone":"Asia/Pyongyang",
    "iso:country":"KP",
    "name:und_x_variant":[
        "\ud559\uc554\ub3d9",
        "Hagam-dong"
    ],
    "wof:name":"Hagam-dong",
    "wof:placetype":"locality"
},
  "geometry": {"coordinates":[129.63,41.23444],"type":"Point"}
}