{
  "type": "Feature",
  "properties": {
    "gn:admin1_code":"1.0",
    "gn:asciiname":"Ch'odokch'am",
    "gn:country_code":"KP",
    "gn:dem":340,
    "gn:feature_class":"P",
    "gn:feature_code":"PPL",
    "gn:name":"Ch\u2019od\u014fkch\u2019am",
    "gn:population":0,
    "gn:timezone":"Asia/Pyongyang",
    "iso:country":"KP",
    "name:und_x_variant":[
        "\ucd08\ub355\ucc38",
        "Ch\u2019od\u014fkch\u2019am"
    ],
    "wof:name":"Ch'odokch'am",
    "wof:placetype":"locality"
},
  "geometry": {"coordinates":[126.36861,40.11278],"type":"Point"}
}