{
  "type": "Feature",
  "properties": {
    "gn:admin1_code":"11.0",
    "gn:asciiname":"Wonch'ang",
    "gn:country_code":"KP",
    "gn:dem":80,
    "gn:feature_class":"P",
    "gn:feature_code":"PPL",
    "gn:name":"W\u014fnch\u2019ang",
    "gn:population":0,
    "gn:timezone":"Asia/Pyongyang",
    "iso:country":"KP",
    "name:kor_x_preferred":[
        "\uc6d0\ucc3d"
    ],
    "name:und_x_variant":[
        "W\u014fnch\u2019ang"
    ],
    "wof:name":"Wonch'ang",
    "wof:placetype":"locality"
},
  "geometry": {"coordinates":[125.41972,39.82833],"type":"Point"}
}