{
  "type": "Feature",
  "properties": {
    "gn:admin1_code":"17.0",
    "gn:asciiname":"Soegol",
    "gn:cc2":"KP",
    "gn:country_code":"KP",
    "gn:dem":302,
    "gn:feature_class":"P",
    "gn:feature_code":"PPL",
    "gn:name":"Soegol",
    "gn:population":0,
    "gn:timezone":"Asia/Pyongyang",
    "iso:country":"KP",
    "name:und_x_variant":[
        "K\u016dmgok",
        "Soegol"
    ],
    "wof:name":"Soegol",
    "wof:placetype":"locality"
},
  "geometry": {"coordinates":[129.53333000000001,41.33333],"type":"Point"}
}