{
  "type": "Feature",
  "properties": {
    "gn:admin1_code":"15.0",
    "gn:asciiname":"Kohung-ni",
    "gn:country_code":"KP",
    "gn:dem":122,
    "gn:feature_class":"P",
    "gn:feature_code":"PPL",
    "gn:name":"K\u014fh\u016dng-ni",
    "gn:population":0,
    "gn:timezone":"Asia/Pyongyang",
    "iso:country":"KP",
    "name:eng_x_preferred":[
        "Kohung"
    ],
    "name:eng_x_variant":[
        "Kohung-ni"
    ],
    "name:kor_x_preferred":[
        "\uac70\ud765\ub9ac"
    ],
    "name:kor_x_variant":[
        "K\u014fh\u016dng-ni"
    ],
    "wof:name":"Kohung",
    "wof:placetype":"locality"
},
  "geometry": {"coordinates":[126.31417,39.33778],"type":"Point"}
}