{
  "type": "Feature",
  "properties": {
    "gn:admin1_code":"15.0",
    "gn:admin2_code":"1871865",
    "gn:asciiname":"Tojol-li",
    "gn:country_code":"KP",
    "gn:dem":79,
    "gn:feature_class":"P",
    "gn:feature_code":"PPL",
    "gn:name":"Toj\u014fl-li",
    "gn:population":0,
    "gn:timezone":"Asia/Pyongyang",
    "iso:country":"KP",
    "wof:name":"Tojol-li",
    "wof:placetype":"locality"
},
  "geometry": {"coordinates":[125.61917,39.25917000000001],"type":"Point"}
}