{
  "type": "Feature",
  "properties": {
    "gn:admin1_code":"9.0",
    "gn:asciiname":"Ch'onum-ni",
    "gn:country_code":"KP",
    "gn:dem":445,
    "gn:feature_class":"P",
    "gn:feature_code":"PPL",
    "gn:name":"Ch\u2019\u014fn\u016dm-ni",
    "gn:population":0,
    "gn:timezone":"Asia/Pyongyang",
    "iso:country":"KP",
    "name:und_x_variant":[
        "\ucc9c\uc74d\ub9ac",
        "Ch\u2019\u014fn\u016dm-ni"
    ],
    "wof:name":"Ch'onum-ni",
    "wof:placetype":"locality"
},
  "geometry": {"coordinates":[127.64444,38.64944000000001],"type":"Point"}
}