{
  "type": "Feature",
  "properties": {
    "gn:admin1_code":"6.0",
    "gn:asciiname":"Ch'ungam",
    "gn:country_code":"KP",
    "gn:dem":17,
    "gn:feature_class":"P",
    "gn:feature_code":"PPL",
    "gn:name":"Ch\u2019ungam",
    "gn:population":0,
    "gn:timezone":"Asia/Pyongyang",
    "iso:country":"KP",
    "name:kor_x_preferred":[
        "\ucda9\uc554"
    ],
    "name:und_x_variant":[
        "Ch\u2019ungam"
    ],
    "wof:name":"Ch'ungam",
    "wof:placetype":"locality"
},
  "geometry": {"coordinates":[125.88500000000001,37.91611],"type":"Point"}
}