{
  "type": "Feature",
  "properties": {
    "gn:admin1_code":"6.0",
    "gn:asciiname":"Sambong-ni",
    "gn:country_code":"KP",
    "gn:dem":19,
    "gn:feature_class":"P",
    "gn:feature_code":"PPL",
    "gn:name":"Sambong-ni",
    "gn:population":0,
    "gn:timezone":"Asia/Pyongyang",
    "iso:country":"KP",
    "name:und_x_variant":[
        "\uc0bc\ubd09\ub9ac",
        "Sambong-ni"
    ],
    "wof:name":"Sambong-ni",
    "wof:placetype":"locality"
},
  "geometry": {"coordinates":[125.61472000000001,37.94972],"type":"Point"}
}