{
  "type": "Feature",
  "properties": {
    "gn:admin1_code":"15.0",
    "gn:admin2_code":"1869039",
    "gn:asciiname":"Nansal-li",
    "gn:country_code":"KP",
    "gn:dem":14,
    "gn:feature_class":"P",
    "gn:feature_code":"PPL",
    "gn:name":"Nansal-li",
    "gn:population":0,
    "gn:timezone":"Asia/Pyongyang",
    "iso:country":"KP",
    "name:und_x_variant":[
        "Nansan-ni",
        "T\u014fsan-ni",
        "Nansal-li"
    ],
    "wof:name":"Nansal-li",
    "wof:placetype":"locality"
},
  "geometry": {"coordinates":[125.48639,39.39611],"type":"Point"}
}