{
  "type": "Feature",
  "properties": {
    "gn:admin1_code":"6.0",
    "gn:asciiname":"T'aeyang-dong",
    "gn:country_code":"KP",
    "gn:dem":73,
    "gn:feature_class":"P",
    "gn:feature_code":"PPL",
    "gn:name":"T\u2019aeyang-dong",
    "gn:population":0,
    "gn:timezone":"Asia/Pyongyang",
    "iso:country":"KP",
    "wof:name":"T'aeyang-dong",
    "wof:placetype":"locality"
},
  "geometry": {"coordinates":[125.49583,38.28167],"type":"Point"}
}