{
  "type": "Feature",
  "properties": {
    "gn:admin1_code":"6.0",
    "gn:asciiname":"Taegi-dong",
    "gn:country_code":"KP",
    "gn:dem":14,
    "gn:feature_class":"P",
    "gn:feature_code":"PPL",
    "gn:name":"Taegi-dong",
    "gn:population":0,
    "gn:timezone":"Asia/Pyongyang",
    "iso:country":"KP",
    "name:kor_x_preferred":[
        "\ub300\uae30\ub3d9"
    ],
    "name:kor_x_variant":[
        "\ub300\uae30"
    ],
    "name:und_x_variant":[
        "Taegi"
    ],
    "wof:name":"Taegi-dong",
    "wof:placetype":"locality"
},
  "geometry": {"coordinates":[125.62183,38.42931],"type":"Point"}
}