{
  "type": "Feature",
  "properties": {
    "gn:admin1_code":"7.0",
    "gn:asciiname":"Sangnyul-li",
    "gn:country_code":"KP",
    "gn:dem":157,
    "gn:feature_class":"P",
    "gn:feature_code":"PPL",
    "gn:name":"Sangnyul-li",
    "gn:population":0,
    "gn:timezone":"Asia/Pyongyang",
    "iso:country":"KP",
    "wof:name":"Sangnyul-li",
    "wof:placetype":"locality"
},
  "geometry": {"coordinates":[126.20083,38.60333],"type":"Point"}
}