{
  "type": "Feature",
  "properties": {
    "gn:admin1_code":"9.0",
    "gn:asciiname":"Kyongsang-ni",
    "gn:country_code":"KP",
    "gn:dem":269,
    "gn:feature_class":"P",
    "gn:feature_code":"PPL",
    "gn:name":"Ky\u014fngsang-ni",
    "gn:population":0,
    "gn:timezone":"Asia/Pyongyang",
    "iso:country":"KP",
    "name:und_x_variant":[
        "\uacbd\uc0c1\ub9ac",
        "Ky\u014fngsang-ni"
    ],
    "wof:name":"Kyongsang-ni",
    "wof:placetype":"locality"
},
  "geometry": {"coordinates":[127.61139,38.38528],"type":"Point"}
}