{
  "type": "Feature",
  "properties": {
    "gn:admin1_code":"13.0",
    "gn:asciiname":"Kangch'o-ri",
    "gn:country_code":"KP",
    "gn:dem":960,
    "gn:feature_class":"P",
    "gn:feature_code":"PPL",
    "gn:name":"Kangch\u2019o-ri",
    "gn:population":0,
    "gn:timezone":"Asia/Pyongyang",
    "iso:country":"KP",
    "name:kor_x_preferred":[
        "\uac15\ucd08\ub9ac"
    ],
    "name:und_x_variant":[
        "Kangch\u2019o-ri"
    ],
    "wof:name":"Kangch'o-ri",
    "wof:placetype":"locality"
},
  "geometry": {"coordinates":[128.14028000000002,41.16],"type":"Point"}
}