{
  "type": "Feature",
  "properties": {
    "gn:admin1_code":"6.0",
    "gn:asciiname":"Noch'ol-li",
    "gn:country_code":"KP",
    "gn:dem":10,
    "gn:feature_class":"P",
    "gn:feature_code":"PPL",
    "gn:name":"Noch\u2019\u014fl-li",
    "gn:population":0,
    "gn:timezone":"Asia/Pyongyang",
    "iso:country":"KP",
    "name:und_x_variant":[
        "Noch\u2019\u014fn-ni",
        "Noch\u2019\u014fl-li"
    ],
    "wof:name":"Noch'ol-li",
    "wof:placetype":"locality"
},
  "geometry": {"coordinates":[126.16528,37.85528],"type":"Point"}
}