{
  "type": "Feature",
  "properties": {
    "gn:admin1_code":"7.0",
    "gn:asciiname":"Saok-tong",
    "gn:country_code":"KP",
    "gn:dem":113,
    "gn:feature_class":"P",
    "gn:feature_code":"PPL",
    "gn:name":"Saok-tong",
    "gn:population":0,
    "gn:timezone":"Asia/Pyongyang",
    "iso:country":"KP",
    "name:eng_x_preferred":[
        "Saok"
    ],
    "name:eng_x_variant":[
        "Saok-tong"
    ],
    "name:kor_x_preferred":[
        "\uc0ac\uc625\ub3d9"
    ],
    "wof:name":"Saok",
    "wof:placetype":"locality"
},
  "geometry": {"coordinates":[126.39528,38.46861],"type":"Point"}
}