{
  "type": "Feature",
  "properties": {
    "gn:admin1_code":"0.0",
    "gn:asciiname":"Sujungdae",
    "gn:cc2":"KP",
    "gn:country_code":"KP",
    "gn:dem":1087,
    "gn:feature_class":"P",
    "gn:feature_code":"PPL",
    "gn:name":"Sujungdae",
    "gn:population":0,
    "gn:timezone":"Asia/Pyongyang",
    "iso:country":"KP",
    "name:und_x_variant":[
        "Sujungt\u2019ae",
        "Sujungdae"
    ],
    "wof:name":"Sujungdae",
    "wof:placetype":"locality"
},
  "geometry": {"coordinates":[128.33333000000002,41.55],"type":"Point"}
}