{
  "type": "Feature",
  "properties": {
    "gn:admin1_code":"7.0",
    "gn:asciiname":"Sangch'ang-dong",
    "gn:country_code":"KP",
    "gn:dem":73,
    "gn:feature_class":"P",
    "gn:feature_code":"PPL",
    "gn:name":"Sangch\u2019ang-dong",
    "gn:population":0,
    "gn:timezone":"Asia/Pyongyang",
    "iso:country":"KP",
    "wof:name":"Sangch'ang-dong",
    "wof:placetype":"locality"
},
  "geometry": {"coordinates":[125.98860999999999,38.38278],"type":"Point"}
}