{
  "type": "Feature",
  "properties": {
    "gn:admin1_code":"1.0",
    "gn:asciiname":"Hwach'un-dong",
    "gn:country_code":"KP",
    "gn:dem":554,
    "gn:feature_class":"P",
    "gn:feature_code":"PPL",
    "gn:name":"Hwach\u2019un-dong",
    "gn:population":0,
    "gn:timezone":"Asia/Pyongyang",
    "iso:country":"KP",
    "name:und_x_variant":[
        "\ud654\ucd98\ub3d9",
        "Hwach\u2019un-dong"
    ],
    "wof:name":"Hwach'un-dong",
    "wof:placetype":"locality"
},
  "geometry": {"coordinates":[125.99222,40.71111],"type":"Point"}
}