{
  "type": "Feature",
  "properties": {
    "gn:admin1_code":"11.0",
    "gn:asciiname":"Tansong-ni",
    "gn:country_code":"KP",
    "gn:dem":90,
    "gn:feature_class":"P",
    "gn:feature_code":"PPL",
    "gn:name":"Tans\u014fng-ni",
    "gn:population":0,
    "gn:timezone":"Asia/Pyongyang",
    "iso:country":"KP",
    "name:und_x_variant":[
        "Tanj\u014d-ri",
        "\ub2e8\uc131\ub9ac",
        "Tans\u014fng-ni"
    ],
    "wof:name":"Tansong-ni",
    "wof:placetype":"locality"
},
  "geometry": {"coordinates":[124.90278000000001,40.39667],"type":"Point"}
}