{
  "type": "Feature",
  "properties": {
    "gn:admin1_code":"9.0",
    "gn:asciiname":"Paeksong",
    "gn:country_code":"KP",
    "gn:dem":617,
    "gn:feature_class":"P",
    "gn:feature_code":"PPL",
    "gn:name":"Paeksong",
    "gn:population":0,
    "gn:timezone":"Asia/Pyongyang",
    "iso:country":"KP",
    "name:und_x_variant":[
        "\ubc31\uc1a1",
        "Paeksong"
    ],
    "wof:name":"Paeksong",
    "wof:placetype":"locality"
},
  "geometry": {"coordinates":[127.74917000000001,38.68111],"type":"Point"}
}