{
  "type": "Feature",
  "properties": {
    "gn:admin1_code":"0.0",
    "gn:asciiname":"Ch'agol",
    "gn:country_code":"KP",
    "gn:dem":912,
    "gn:feature_class":"P",
    "gn:feature_code":"PPL",
    "gn:name":"Ch\u2019agol",
    "gn:population":0,
    "gn:timezone":"Asia/Pyongyang",
    "iso:country":"KP",
    "name:kor_x_preferred":[
        "\ucc28\uace8"
    ],
    "name:und_x_variant":[
        "Ch\u2019akol",
        "Ch\u2019agol"
    ],
    "wof:name":"Ch'agol",
    "wof:placetype":"locality"
},
  "geometry": {"coordinates":[127.73583000000001,41.28806],"type":"Point"}
}