{
  "type": "Feature",
  "properties": {
    "gn:admin1_code":"15.0",
    "gn:asciiname":"Samgori",
    "gn:country_code":"KP",
    "gn:dem":35,
    "gn:feature_class":"P",
    "gn:feature_code":"PPL",
    "gn:name":"Samg\u014fri",
    "gn:population":0,
    "gn:timezone":"Asia/Pyongyang",
    "iso:country":"KP",
    "wof:name":"Samgori",
    "wof:placetype":"locality"
},
  "geometry": {"coordinates":[125.60556,39.1275],"type":"Point"}
}