{
  "type": "Feature",
  "properties": {
    "gn:admin1_code":"12.0",
    "gn:asciiname":"Chagunoryu-ri",
    "gn:country_code":"KP",
    "gn:dem":38,
    "gn:feature_class":"P",
    "gn:feature_code":"PPL",
    "gn:name":"Chag\u016dnoryu-ri",
    "gn:population":0,
    "gn:timezone":"Asia/Pyongyang",
    "iso:country":"KP",
    "name:und_x_variant":[
        "\uc791\uc740\uc624\ub958\ub9ac",
        "Chag\u016dnoryu-ri",
        "Jageunoryuri"
    ],
    "wof:name":"Chagunoryu-ri",
    "wof:placetype":"locality"
},
  "geometry": {"coordinates":[125.90639,38.9925],"type":"Point"}
}