{
  "type": "Feature",
  "properties": {
    "gn:admin1_code":"0.0",
    "gn:asciiname":"Hak-tong",
    "gn:country_code":"KP",
    "gn:dem":65,
    "gn:feature_class":"P",
    "gn:feature_code":"PPL",
    "gn:name":"Hak-tong",
    "gn:population":0,
    "gn:timezone":"Asia/Pyongyang",
    "iso:country":"KP",
    "name:kor_x_preferred":[
        "\ud559\ub3d9"
    ],
    "wof:name":"Hak-tong",
    "wof:placetype":"locality"
},
  "geometry": {"coordinates":[125.40000000000001,38.18333],"type":"Point"}
}