{
  "type": "Feature",
  "properties": {
    "gn:admin1_code":"12.0",
    "gn:asciiname":"K'ungol",
    "gn:country_code":"KP",
    "gn:dem":100,
    "gn:feature_class":"P",
    "gn:feature_code":"PPL",
    "gn:name":"K\u2019\u016dngol",
    "gn:population":0,
    "gn:timezone":"Asia/Pyongyang",
    "iso:country":"KP",
    "name:kor_x_preferred":[
        "K\u2019\u016dngol"
    ],
    "name:kor_x_variant":[
        "\ud070\uace8",
        "Chajigol-ma\u016dl",
        "\uc790\uc9c0\uace8\ub9c8\uc744"
    ],
    "name:und_x_variant":[
        "Chagi-dong",
        "Chaji-dong",
        "Keungol"
    ],
    "wof:name":"K'ungol",
    "wof:placetype":"locality"
},
  "geometry": {"coordinates":[125.83944,39.16222],"type":"Point"}
}