{
  "type": "Feature",
  "properties": {
    "gn:admin1_code":"3.0",
    "gn:asciiname":"Saech'on",
    "gn:country_code":"KP",
    "gn:dem":264,
    "gn:feature_class":"P",
    "gn:feature_code":"PPL",
    "gn:name":"Saech\u2019on",
    "gn:population":0,
    "gn:timezone":"Asia/Pyongyang",
    "iso:country":"KP",
    "name:und_x_variant":[
        "\uc0c8\ucd0c",
        "Saech\u2019on"
    ],
    "wof:name":"Saech'on",
    "wof:placetype":"locality"
},
  "geometry": {"coordinates":[127.25306,39.87833],"type":"Point"}
}