{
  "type": "Feature",
  "properties": {
    "gn:admin1_code":"3.0",
    "gn:asciiname":"Chuk-kol",
    "gn:country_code":"KP",
    "gn:dem":304,
    "gn:feature_class":"P",
    "gn:feature_code":"PPL",
    "gn:name":"Chuk-kol",
    "gn:population":0,
    "gn:timezone":"Asia/Pyongyang",
    "iso:country":"KP",
    "name:und_x_variant":[
        "\uc8fd\uace8",
        "Chuk-kol"
    ],
    "wof:name":"Chuk-kol",
    "wof:placetype":"locality"
},
  "geometry": {"coordinates":[127.25583,39.9275],"type":"Point"}
}