{
  "type": "Feature",
  "properties": {
    "gn:admin1_code":"15.0",
    "gn:asciiname":"jang-gol",
    "gn:country_code":"KP",
    "gn:dem":477,
    "gn:feature_class":"P",
    "gn:feature_code":"PPL",
    "gn:name":"\uc7a5\uace8",
    "gn:population":0,
    "gn:timezone":"Asia/Pyongyang",
    "iso:country":"KP",
    "wof:name":"jang-gol",
    "wof:placetype":"locality"
},
  "geometry": {"coordinates":[126.61972,39.48],"type":"Point"}
}