{
  "type": "Feature",
  "properties": {
    "gn:admin1_code":"6.0",
    "gn:asciiname":"Kungnak-tong",
    "gn:country_code":"KP",
    "gn:dem":72,
    "gn:feature_class":"P",
    "gn:feature_code":"PPL",
    "gn:name":"K\u016dngnak-tong",
    "gn:population":0,
    "gn:timezone":"Asia/Pyongyang",
    "iso:country":"KP",
    "name:kor_x_preferred":[
        "\uadf9\ub77d\ub3d9"
    ],
    "name:und_x_variant":[
        "K\u016dngnak-tong"
    ],
    "wof:name":"Kungnak-tong",
    "wof:placetype":"locality"
},
  "geometry": {"coordinates":[125.44194,38.30028],"type":"Point"}
}