{
  "type": "Feature",
  "properties": {
    "gn:admin1_code":"6.0",
    "gn:asciiname":"Araenung-gol",
    "gn:country_code":"KP",
    "gn:dem":43,
    "gn:feature_class":"P",
    "gn:feature_code":"PPL",
    "gn:name":"Araen\u016dng-gol",
    "gn:population":0,
    "gn:timezone":"Asia/Pyongyang",
    "iso:country":"KP",
    "name:kor_x_preferred":[
        "\uc544\ub798\ub2a5\uace8"
    ],
    "name:kor_x_variant":[
        "Araen\u016dng-gol"
    ],
    "wof:name":"Araenung-gol",
    "wof:placetype":"locality"
},
  "geometry": {"coordinates":[125.3925,38.37417],"type":"Point"}
}