{
  "type": "Feature",
  "properties": {
    "gn:admin1_code":"6.0",
    "gn:admin2_code":"Changp\u2019ung-gun",
    "gn:asciiname":"Hyogyong-kol",
    "gn:country_code":"KP",
    "gn:dem":277,
    "gn:feature_class":"P",
    "gn:feature_code":"PPL",
    "gn:name":"Hyogy\u014fng-kol",
    "gn:population":0,
    "gn:timezone":"Asia/Pyongyang",
    "iso:country":"KP",
    "wof:name":"Hyogyong-kol",
    "wof:placetype":"locality"
},
  "geometry": {"coordinates":[126.63361,38.16806],"type":"Point"}
}