{
  "type": "Feature",
  "properties": {
    "gn:admin1_code":"6.0",
    "gn:asciiname":"Chungsan",
    "gn:country_code":"KP",
    "gn:dem":22,
    "gn:feature_class":"P",
    "gn:feature_code":"PPL",
    "gn:name":"Ch\u016dngsan",
    "gn:population":0,
    "gn:timezone":"Asia/Pyongyang",
    "iso:country":"KP",
    "name:kor_x_preferred":[
        "\uc99d\uc0b0"
    ],
    "name:kor_x_variant":[
        "Ch\u016dngsan"
    ],
    "wof:name":"Chungsan",
    "wof:placetype":"locality"
},
  "geometry": {"coordinates":[125.43361000000002,38.64361],"type":"Point"}
}