{
  "type": "Feature",
  "properties": {
    "gn:admin1_code":"15.0",
    "gn:asciiname":"Nangnim-ni",
    "gn:country_code":"KP",
    "gn:dem":834,
    "gn:feature_class":"P",
    "gn:feature_code":"PPL",
    "gn:name":"Nangnim-ni",
    "gn:population":0,
    "gn:timezone":"Asia/Pyongyang",
    "iso:country":"KP",
    "name:und_x_variant":[
        "\ub791\ub9bc\ub9ac",
        "Nangnim-ni"
    ],
    "wof:name":"Nangnim-ni",
    "wof:placetype":"locality"
},
  "geometry": {"coordinates":[126.95440000000001,40.26819],"type":"Point"}
}