{
  "type": "Feature",
  "properties": {
    "gn:admin1_code":"11.0",
    "gn:asciiname":"Chungdan",
    "gn:country_code":"KP",
    "gn:dem":23,
    "gn:feature_class":"P",
    "gn:feature_code":"PPL",
    "gn:name":"Chungdan",
    "gn:population":0,
    "gn:timezone":"Asia/Pyongyang",
    "iso:country":"KP",
    "name:kor_x_preferred":[
        "\uc911\ub2e8"
    ],
    "wof:name":"Chungdan",
    "wof:placetype":"locality"
},
  "geometry": {"coordinates":[124.94455000000001,39.7499],"type":"Point"}
}