{
  "type": "Feature",
  "properties": {
    "gn:admin1_code":"15.0",
    "gn:asciiname":"Saek-kol",
    "gn:cc2":"KP",
    "gn:country_code":"KP",
    "gn:dem":108,
    "gn:feature_class":"P",
    "gn:feature_code":"PPL",
    "gn:name":"Saek-kol",
    "gn:population":0,
    "gn:timezone":"Asia/Pyongyang",
    "iso:country":"KP",
    "name:kor_x_preferred":[
        "\uc0db\uace8"
    ],
    "name:und_x_variant":[
        "Kan-dong",
        "Saet-kol",
        "Kand\u014d",
        "Saek-kol"
    ],
    "wof:name":"Saek-kol",
    "wof:placetype":"locality"
},
  "geometry": {"coordinates":[125.95361,39.62639],"type":"Point"}
}