{
  "type": "Feature",
  "properties": {
    "gn:admin1_code":"6.0",
    "gn:asciiname":"Sinwang-dong",
    "gn:cc2":"KP",
    "gn:country_code":"KP",
    "gn:dem":12,
    "gn:feature_class":"P",
    "gn:feature_code":"PPL",
    "gn:name":"Sinwang-dong",
    "gn:population":0,
    "gn:timezone":"Asia/Pyongyang",
    "iso:country":"KP",
    "name:und_x_variant":[
        "Ky\u014fngji-ri",
        "Sinwang-dong"
    ],
    "wof:name":"Sinwang-dong",
    "wof:placetype":"locality"
},
  "geometry": {"coordinates":[125.44528,38.45],"type":"Point"}
}