{
  "type": "Feature",
  "properties": {
    "gn:admin1_code":"1.0",
    "gn:asciiname":"Pusung-dong",
    "gn:country_code":"KP",
    "gn:dem":486,
    "gn:feature_class":"P",
    "gn:feature_code":"PPL",
    "gn:name":"Pusung-dong",
    "gn:population":0,
    "gn:timezone":"Asia/Pyongyang",
    "iso:country":"KP",
    "name:und_x_variant":[
        "\ubd80\uc22d\ub3d9",
        "Pusung-dong"
    ],
    "wof:name":"Pusung-dong",
    "wof:placetype":"locality"
},
  "geometry": {"coordinates":[125.68028,40.31],"type":"Point"}
}