{
  "type": "Feature",
  "properties": {
    "gn:admin1_code":"12.0",
    "gn:asciiname":"Taesan-dong",
    "gn:country_code":"KP",
    "gn:dem":61,
    "gn:feature_class":"P",
    "gn:feature_code":"PPL",
    "gn:name":"Taesan-dong",
    "gn:population":0,
    "gn:timezone":"Asia/Pyongyang",
    "iso:country":"KP",
    "name:und_x_variant":[
        "\ub300\uc0b0\ub3d9",
        "Taesan-dong",
        "Daesandong"
    ],
    "wof:name":"Taesan-dong",
    "wof:placetype":"locality"
},
  "geometry": {"coordinates":[125.91777999999999,38.95139],"type":"Point"}
}