{
  "type": "Feature",
  "properties": {
    "gn:admin1_code":"3.0",
    "gn:asciiname":"Songjong-ch'on",
    "gn:country_code":"KP",
    "gn:dem":43,
    "gn:feature_class":"P",
    "gn:feature_code":"PPL",
    "gn:name":"Songj\u014fng-ch\u2019on",
    "gn:population":0,
    "gn:timezone":"Asia/Pyongyang",
    "iso:country":"KP",
    "name:und_x_variant":[
        "\uc1a1\uc815\ucd0c",
        "Songj\u014fng-ch\u2019on"
    ],
    "wof:name":"Songjong-ch'on",
    "wof:placetype":"locality"
},
  "geometry": {"coordinates":[128.84971999999999,40.54],"type":"Point"}
}