{
  "type": "Feature",
  "properties": {
    "gn:admin1_code":"3.0",
    "gn:asciiname":"Chol-gol",
    "gn:country_code":"KP",
    "gn:dem":284,
    "gn:feature_class":"P",
    "gn:feature_code":"PPL",
    "gn:name":"Ch\u014fl-gol",
    "gn:population":0,
    "gn:timezone":"Asia/Pyongyang",
    "iso:country":"KP",
    "name:und_x_variant":[
        "\uc808\uace8",
        "Ch\u014fl-gol"
    ],
    "wof:name":"Chol-gol",
    "wof:placetype":"locality"
},
  "geometry": {"coordinates":[127.96028,40.14778],"type":"Point"}
}