{
  "type": "Feature",
  "properties": {
    "gn:admin1_code":"11.0",
    "gn:asciiname":"Pukkok",
    "gn:country_code":"KP",
    "gn:dem":23,
    "gn:feature_class":"P",
    "gn:feature_code":"PPL",
    "gn:name":"Pukkok",
    "gn:population":0,
    "gn:timezone":"Asia/Pyongyang",
    "iso:country":"KP",
    "name:und_x_variant":[
        "\ubd81\uace1",
        "Pukkok"
    ],
    "wof:name":"Pukkok",
    "wof:placetype":"locality"
},
  "geometry": {"coordinates":[124.61750000000001,40.26639],"type":"Point"}
}