{
  "type": "Feature",
  "properties": {
    "gn:admin1_code":"6.0",
    "gn:admin2_code":"P'anmun-gun",
    "gn:asciiname":"Kajae-dong",
    "gn:country_code":"KP",
    "gn:dem":108,
    "gn:feature_class":"P",
    "gn:feature_code":"PPL",
    "gn:name":"Kajae-dong",
    "gn:population":0,
    "gn:timezone":"Asia/Pyongyang",
    "iso:country":"KP",
    "wof:name":"Kajae-dong",
    "wof:placetype":"locality"
},
  "geometry": {"coordinates":[126.62333,37.99806],"type":"Point"}
}