{
  "type": "Feature",
  "properties": {
    "gn:admin1_code":"3.0",
    "gn:admin2_code":"K\u016dmya-gun",
    "gn:asciiname":"Chodo-ri",
    "gn:country_code":"KP",
    "gn:dem":9,
    "gn:feature_class":"P",
    "gn:feature_code":"PPL",
    "gn:name":"Ch\u014fdo-ri",
    "gn:population":0,
    "gn:timezone":"Asia/Pyongyang",
    "iso:country":"KP",
    "name:kor_x_preferred":[
        "\uc800\ub3c4\ub9ac"
    ],
    "name:und_x_variant":[
        "Ch\u014fdo-ri"
    ],
    "wof:name":"Chodo-ri",
    "wof:placetype":"locality"
},
  "geometry": {"coordinates":[127.47693999999998,39.39056],"type":"Point"}
}