{
  "type": "Feature",
  "properties": {
    "gn:admin1_code":"6.0",
    "gn:asciiname":"Nurumnigogae",
    "gn:cc2":"KP",
    "gn:country_code":"KP",
    "gn:dem":49,
    "gn:feature_class":"P",
    "gn:feature_code":"PPL",
    "gn:name":"N\u016dr\u016dmnigogae",
    "gn:population":0,
    "gn:timezone":"Asia/Pyongyang",
    "iso:country":"KP",
    "name:kor_x_preferred":[
        "\ub290\ub985\ub9ac\uace0\uac1c"
    ],
    "name:und_x_variant":[
        "N\u016dr\u016dpkogae",
        "N\u016dr\u016dmnigogae"
    ],
    "wof:name":"Nurumnigogae",
    "wof:placetype":"locality"
},
  "geometry": {"coordinates":[125.46639,38.07639],"type":"Point"}
}