{
  "type": "Feature",
  "properties": {
    "gn:admin1_code":"15.0",
    "gn:admin2_code":"S\u014fngch\u2019\u014fn-gun",
    "gn:asciiname":"Hwamong-ni",
    "gn:country_code":"KP",
    "gn:dem":66,
    "gn:feature_class":"P",
    "gn:feature_code":"PPL",
    "gn:name":"Hwamong-ni",
    "gn:population":0,
    "gn:timezone":"Asia/Pyongyang",
    "iso:country":"KP",
    "name:eng_x_preferred":[
        "Hwamong"
    ],
    "name:eng_x_variant":[
        "Hwamong-ni"
    ],
    "wof:name":"Hwamong",
    "wof:placetype":"locality"
},
  "geometry": {"coordinates":[126.0825,39.24806],"type":"Point"}
}