{
  "type": "Feature",
  "properties": {
    "gn:admin1_code":"15.0",
    "gn:admin2_code":"1869039",
    "gn:asciiname":"T'ojom-ni",
    "gn:country_code":"KP",
    "gn:dem":103,
    "gn:feature_class":"P",
    "gn:feature_code":"PPL",
    "gn:name":"T\u2019oj\u014fm-ni",
    "gn:population":0,
    "gn:timezone":"Asia/Pyongyang",
    "iso:country":"KP",
    "name:eng_x_preferred":[
        "T'ojom"
    ],
    "name:eng_x_variant":[
        "T'ojom-ni"
    ],
    "wof:name":"T'ojom",
    "wof:placetype":"locality"
},
  "geometry": {"coordinates":[125.68194,39.37583],"type":"Point"}
}