{
  "type": "Feature",
  "properties": {
    "gn:admin1_code":"0.0",
    "gn:asciiname":"Undong-ni",
    "gn:country_code":"KP",
    "gn:dem":104,
    "gn:feature_class":"P",
    "gn:feature_code":"PPL",
    "gn:name":"\u016cnd\u014fng-ni",
    "gn:population":0,
    "gn:timezone":"Asia/Pyongyang",
    "iso:country":"KP",
    "name:kor_x_preferred":[
        "\uc740\ub355\ub9ac"
    ],
    "name:und_x_variant":[
        "\u016cnd\u014fng-ni"
    ],
    "wof:name":"Undong-ni",
    "wof:placetype":"locality"
},
  "geometry": {"coordinates":[125.45,39.98333],"type":"Point"}
}