{
  "type": "Feature",
  "properties": {
    "gn:admin1_code":"6.0",
    "gn:asciiname":"Yangji-mal",
    "gn:country_code":"KP",
    "gn:dem":71,
    "gn:feature_class":"P",
    "gn:feature_code":"PPL",
    "gn:name":"Yangji-mal",
    "gn:population":0,
    "gn:timezone":"Asia/Pyongyang",
    "iso:country":"KP",
    "wof:name":"Yangji-mal",
    "wof:placetype":"locality"
},
  "geometry": {"coordinates":[126.00667,38.07306],"type":"Point"}
}