{
  "type": "Feature",
  "properties": {
    "gn:admin1_code":"3.0",
    "gn:admin2_code":"K\u016dmya-gun",
    "gn:asciiname":"Songjae-ri",
    "gn:country_code":"KP",
    "gn:dem":18,
    "gn:feature_class":"P",
    "gn:feature_code":"PPL",
    "gn:name":"Songjae-ri",
    "gn:population":0,
    "gn:timezone":"Asia/Pyongyang",
    "iso:country":"KP",
    "wof:name":"Songjae-ri",
    "wof:placetype":"locality"
},
  "geometry": {"coordinates":[127.28749999999999,39.4875],"type":"Point"}
}