{
  "type": "Feature",
  "properties": {
    "gn:admin1_code":"15.0",
    "gn:asciiname":"Handae-dong",
    "gn:country_code":"KP",
    "gn:dem":286,
    "gn:feature_class":"P",
    "gn:feature_code":"PPL",
    "gn:name":"Handae-dong",
    "gn:population":0,
    "gn:timezone":"Asia/Pyongyang",
    "iso:country":"KP",
    "name:und_x_variant":[
        "\ud55c\ub300\ub3d9",
        "Handae-dong"
    ],
    "wof:name":"Handae-dong",
    "wof:placetype":"locality"
},
  "geometry": {"coordinates":[126.53528,39.88583],"type":"Point"}
}