{
  "type": "Feature",
  "properties": {
    "gn:admin1_code":"7.0",
    "gn:asciiname":"P'och'on",
    "gn:country_code":"KP",
    "gn:dem":12,
    "gn:feature_class":"P",
    "gn:feature_code":"PPL",
    "gn:name":"P\u2019och\u2019on",
    "gn:population":0,
    "gn:timezone":"Asia/Pyongyang",
    "iso:country":"KP",
    "name:kor_x_preferred":[
        "\ud3ec\ucd0c"
    ],
    "name:kor_x_variant":[
        "P\u2019och\u2019on"
    ],
    "wof:name":"P'och'on",
    "wof:placetype":"locality"
},
  "geometry": {"coordinates":[125.59417000000001,38.5875],"type":"Point"}
}