{
  "type": "Feature",
  "properties": {
    "gn:admin1_code":"12.0",
    "gn:admin2_code":"S\u016dngho-guy\u014fk",
    "gn:asciiname":"Utho-gol",
    "gn:cc2":"KP",
    "gn:country_code":"KP",
    "gn:dem":82,
    "gn:feature_class":"P",
    "gn:feature_code":"PPL",
    "gn:name":"Utho-gol",
    "gn:population":0,
    "gn:timezone":"Asia/Pyongyang",
    "iso:country":"KP",
    "name:und_x_variant":[
        "Utho-kol",
        "Utho-gol"
    ],
    "wof:name":"Utho-gol",
    "wof:placetype":"locality"
},
  "geometry": {"coordinates":[126.06667,39.03556],"type":"Point"}
}