{
  "type": "Feature",
  "properties": {
    "gn:admin1_code":"3.0",
    "gn:asciiname":"Chongnyong-ch'on",
    "gn:country_code":"KP",
    "gn:dem":2,
    "gn:feature_class":"P",
    "gn:feature_code":"PPL",
    "gn:name":"Chongnyong-ch\u2019on",
    "gn:population":0,
    "gn:timezone":"Asia/Pyongyang",
    "iso:country":"KP",
    "name:und_x_variant":[
        "Chongnyong-ch\u2019on",
        "\uccad\ub8e1\ucd0c"
    ],
    "wof:name":"Chongnyong-ch'on",
    "wof:placetype":"locality"
},
  "geometry": {"coordinates":[128.42806000000002,40.12056],"type":"Point"}
}