{
  "type": "Feature",
  "properties": {
    "gn:admin1_code":"9.0",
    "gn:asciiname":"Nungmol",
    "gn:country_code":"KP",
    "gn:dem":256,
    "gn:feature_class":"P",
    "gn:feature_code":"PPL",
    "gn:name":"N\u016dngmol",
    "gn:population":0,
    "gn:timezone":"Asia/Pyongyang",
    "iso:country":"KP",
    "name:und_x_variant":[
        "\ub2a5\ubab0",
        "N\u016dngmol"
    ],
    "wof:name":"Nungmol",
    "wof:placetype":"locality"
},
  "geometry": {"coordinates":[127.82556,38.42833],"type":"Point"}
}