{
  "type": "Feature",
  "properties": {
    "gn:admin1_code":"11.0",
    "gn:asciiname":"Yongdaltongjunggok",
    "gn:country_code":"KP",
    "gn:dem":39,
    "gn:feature_class":"P",
    "gn:feature_code":"PPL",
    "gn:name":"Y\u014fngdaltongjunggok",
    "gn:population":0,
    "gn:timezone":"Asia/Pyongyang",
    "iso:country":"KP",
    "name:und_x_variant":[
        "\uc601\ub2ec\ub3d9\uc911\uace1",
        "Y\u014fngdaltongjunggok"
    ],
    "wof:name":"Yongdaltongjunggok",
    "wof:placetype":"locality"
},
  "geometry": {"coordinates":[124.61611000000001,40.20861],"type":"Point"}
}