{
  "type": "Feature",
  "properties": {
    "gn:admin1_code":"11.0",
    "gn:asciiname":"Songmol-gol",
    "gn:country_code":"KP",
    "gn:dem":26,
    "gn:feature_class":"P",
    "gn:feature_code":"PPL",
    "gn:name":"Songmol-gol",
    "gn:population":0,
    "gn:timezone":"Asia/Pyongyang",
    "iso:country":"KP",
    "name:kor_x_preferred":[
        "\uc1a1\ubab0\uace8"
    ],
    "name:und_x_variant":[
        "Solmoru-gol",
        "Songu-dong",
        "Songmol-gol"
    ],
    "wof:name":"Songmol-gol",
    "wof:placetype":"locality"
},
  "geometry": {"coordinates":[124.99120000000001,39.74332],"type":"Point"}
}