{
  "type": "Feature",
  "properties": {
    "gn:admin1_code":"11.0",
    "gn:asciiname":"Songjong-ni",
    "gn:country_code":"KP",
    "gn:dem":36,
    "gn:feature_class":"P",
    "gn:feature_code":"PPL",
    "gn:name":"Songj\u014fng-ni",
    "gn:population":0,
    "gn:timezone":"Asia/Pyongyang",
    "iso:country":"KP",
    "name:und_x_variant":[
        "Songj\u014fng-dong",
        "\uc1a1\uc815\ub9ac",
        "Songj\u014fn-ni",
        "Songj\u014fng-ni"
    ],
    "wof:name":"Songjong-ni",
    "wof:placetype":"locality"
},
  "geometry": {"coordinates":[124.51443999999999,40.01917],"type":"Point"}
}