{
  "type": "Feature",
  "properties": {
    "gn:admin1_code":"0.0",
    "gn:asciiname":"Kang-ch'on",
    "gn:country_code":"KP",
    "gn:dem":51,
    "gn:feature_class":"P",
    "gn:feature_code":"PPL",
    "gn:name":"Kang-ch\u2019on",
    "gn:population":0,
    "gn:timezone":"Asia/Pyongyang",
    "iso:country":"KP",
    "name:kor_x_preferred":[
        "\uac15\ucd0c"
    ],
    "name:und_x_variant":[
        "Kang-ch\u2019on"
    ],
    "wof:name":"Kang-ch'on",
    "wof:placetype":"locality"
},
  "geometry": {"coordinates":[125.58333,37.81667],"type":"Point"}
}