{
  "type": "Feature",
  "properties": {
    "gn:admin1_code":"1.0",
    "gn:asciiname":"Norumogi-ri",
    "gn:country_code":"KP",
    "gn:dem":760,
    "gn:feature_class":"P",
    "gn:feature_code":"PPL",
    "gn:name":"Norumogi-ri",
    "gn:population":0,
    "gn:timezone":"Asia/Pyongyang",
    "iso:country":"KP",
    "name:kor_x_preferred":[
        "\ub178\ub8e8\ubaa9\uc774\ub9ac"
    ],
    "wof:name":"Norumogi-ri",
    "wof:placetype":"locality"
},
  "geometry": {"coordinates":[127.46228000000001,41.10568],"type":"Point"}
}