{
  "type": "Feature",
  "properties": {
    "gn:admin1_code":"15.0",
    "gn:asciiname":"Namsan-dong",
    "gn:country_code":"KP",
    "gn:dem":20,
    "gn:feature_class":"P",
    "gn:feature_code":"PPL",
    "gn:name":"Namsan-dong",
    "gn:population":0,
    "gn:timezone":"Asia/Pyongyang",
    "iso:country":"KP",
    "name:ceb_x_preferred":[
        "Namsan-dong"
    ],
    "name:kor_x_preferred":[
        "\ub0a8\uc0b0\ub3d9"
    ],
    "name:nld_x_preferred":[
        "Namsan-dong"
    ],
    "name:swe_x_preferred":[
        "Namsan-dong"
    ],
    "name:zho_x_preferred":[
        "\u5357\u5c71\u6d1e"
    ],
    "wof:name":"Namsan-dong",
    "wof:placetype":"locality"
},
  "geometry": {"coordinates":[125.545,39.09417],"type":"Point"}
}