{
  "type": "Feature",
  "properties": {
    "gn:admin1_code":"3.0",
    "gn:asciiname":"Pamnamubol",
    "gn:country_code":"KP",
    "gn:dem":91,
    "gn:feature_class":"P",
    "gn:feature_code":"PPL",
    "gn:name":"Pamnamub\u014fl",
    "gn:population":0,
    "gn:timezone":"Asia/Pyongyang",
    "iso:country":"KP",
    "name:kor_x_preferred":[
        "\ubc24\ub098\ubb34\ubc8c"
    ],
    "name:kor_x_variant":[
        "Pamnamub\u014fl"
    ],
    "wof:name":"Pamnamubol",
    "wof:placetype":"locality"
},
  "geometry": {"coordinates":[127.09721999999999,39.66056],"type":"Point"}
}