{
  "type": "Feature",
  "properties": {
    "gn:admin1_code":"12.0",
    "gn:asciiname":"Chungch'u-dong",
    "gn:country_code":"KP",
    "gn:dem":74,
    "gn:feature_class":"P",
    "gn:feature_code":"PPL",
    "gn:name":"Chungch\u2019u-dong",
    "gn:population":0,
    "gn:timezone":"Asia/Pyongyang",
    "iso:country":"KP",
    "name:kor_x_preferred":[
        "Chungch\u2019u-dong"
    ],
    "name:kor_x_variant":[
        "\uc911\ucd94\ub3d9"
    ],
    "name:und_x_variant":[
        "Jungchudong"
    ],
    "wof:name":"Chungch'u-dong",
    "wof:placetype":"locality"
},
  "geometry": {"coordinates":[125.80126,39.14006],"type":"Point"}
}