{
  "type": "Feature",
  "properties": {
    "gn:admin1_code":"9.0",
    "gn:asciiname":"Hwat'ong-ni",
    "gn:country_code":"KP",
    "gn:dem":18,
    "gn:feature_class":"P",
    "gn:feature_code":"PPL",
    "gn:name":"Hwat\u2019ong-ni",
    "gn:population":0,
    "gn:timezone":"Asia/Pyongyang",
    "iso:country":"KP",
    "name:kor_x_preferred":[
        "\ud654\ud1b5\ub9ac"
    ],
    "name:und_x_variant":[
        "Hwat\u2019ong-ni"
    ],
    "wof:name":"Hwat'ong-ni",
    "wof:placetype":"locality"
},
  "geometry": {"coordinates":[127.73444000000001,39.07472],"type":"Point"}
}