{
  "type": "Feature",
  "properties": {
    "gn:admin1_code":"1.0",
    "gn:asciiname":"Kokha",
    "gn:country_code":"KP",
    "gn:dem":270,
    "gn:feature_class":"P",
    "gn:feature_code":"PPL",
    "gn:name":"Kokha",
    "gn:population":0,
    "gn:timezone":"Asia/Pyongyang",
    "iso:country":"KP",
    "name:kor_x_preferred":[
        "\uace1\ud558"
    ],
    "name:kor_x_variant":[
        "\uace1\ud569",
        "\uace1\ud574"
    ],
    "name:und_x_variant":[
        "Kokhap",
        "Kokhae"
    ],
    "wof:name":"Kokha",
    "wof:placetype":"locality"
},
  "geometry": {"coordinates":[126.49719,40.98322],"type":"Point"}
}