{
  "type": "Feature",
  "properties": {
    "gn:admin1_code":"7.0",
    "gn:asciiname":"Woryang-ni",
    "gn:country_code":"KP",
    "gn:dem":256,
    "gn:feature_class":"P",
    "gn:feature_code":"PPL",
    "gn:name":"W\u014fryang-ni",
    "gn:population":0,
    "gn:timezone":"Asia/Pyongyang",
    "iso:country":"KP",
    "name:kor_x_preferred":[
        "\uc6d4\uc591\ub9ac"
    ],
    "name:kor_x_variant":[
        "W\u014fryang-ni"
    ],
    "wof:name":"Woryang-ni",
    "wof:placetype":"locality"
},
  "geometry": {"coordinates":[126.60722,38.68556],"type":"Point"}
}