{
  "type": "Feature",
  "properties": {
    "gn:admin1_code":"11.0",
    "gn:asciiname":"Hyang-dong",
    "gn:country_code":"KP",
    "gn:dem":10,
    "gn:feature_class":"P",
    "gn:feature_code":"PPL",
    "gn:name":"Hyang-dong",
    "gn:population":0,
    "gn:timezone":"Asia/Pyongyang",
    "iso:country":"KP",
    "name:und_x_variant":[
        "\ud5a5\ub3d9",
        "Hyang-dong"
    ],
    "wof:name":"Hyang-dong",
    "wof:placetype":"locality"
},
  "geometry": {"coordinates":[124.61028,39.84972],"type":"Point"}
}