{
  "type": "Feature",
  "properties": {
    "gn:admin1_code":"1.0",
    "gn:asciiname":"Sapyongji",
    "gn:country_code":"KP",
    "gn:dem":1077,
    "gn:feature_class":"P",
    "gn:feature_code":"PPL",
    "gn:name":"Sapy\u014fngji",
    "gn:population":0,
    "gn:timezone":"Asia/Pyongyang",
    "iso:country":"KP",
    "name:kor_x_preferred":[
        "\uc0ac\ud3c9\uc9c0"
    ],
    "name:kor_x_variant":[
        "Sapy\u014fngji"
    ],
    "wof:name":"Sapyongji",
    "wof:placetype":"locality"
},
  "geometry": {"coordinates":[127.075,40.85028],"type":"Point"}
}