{
  "type": "Feature",
  "properties": {
    "gn:admin1_code":"6.0",
    "gn:asciiname":"Ulmusan",
    "gn:cc2":"KP",
    "gn:country_code":"KP",
    "gn:dem":22,
    "gn:feature_class":"P",
    "gn:feature_code":"PPL",
    "gn:name":"Ulmusan",
    "gn:population":0,
    "gn:timezone":"Asia/Pyongyang",
    "iso:country":"KP",
    "name:und_x_variant":[
        "S\u014fryung-ni",
        "Ulmusan"
    ],
    "wof:name":"Ulmusan",
    "wof:placetype":"locality"
},
  "geometry": {"coordinates":[126.01611,37.97528],"type":"Point"}
}