{
  "type": "Feature",
  "properties": {
    "gn:admin1_code":"1.0",
    "gn:asciiname":"Yahak-tong",
    "gn:country_code":"KP",
    "gn:dem":466,
    "gn:feature_class":"P",
    "gn:feature_code":"PPL",
    "gn:name":"Yahak-tong",
    "gn:population":0,
    "gn:timezone":"Asia/Pyongyang",
    "iso:country":"KP",
    "name:und_x_variant":[
        "\uc57c\ud559\ub3d9",
        "Yahak-tong"
    ],
    "wof:name":"Yahak-tong",
    "wof:placetype":"locality"
},
  "geometry": {"coordinates":[126.57778,41.33],"type":"Point"}
}