{
  "type": "Feature",
  "properties": {
    "gn:admin1_code":"12.0",
    "gn:asciiname":"Sogam-ni",
    "gn:country_code":"KP",
    "gn:dem":35,
    "gn:feature_class":"P",
    "gn:feature_code":"PPL",
    "gn:name":"S\u014fgam-ni",
    "gn:population":0,
    "gn:timezone":"Asia/Pyongyang",
    "iso:country":"KP",
    "name:und_x_variant":[
        "\uc11c\uac10\ub9ac",
        "S\u014fgam-ni",
        "Seogamni"
    ],
    "wof:name":"Sogam-ni",
    "wof:placetype":"locality"
},
  "geometry": {"coordinates":[125.73027999999999,38.97167],"type":"Point"}
}