{
  "type": "Feature",
  "properties": {
    "gn:admin1_code":"17.0",
    "gn:asciiname":"Tokch'on",
    "gn:country_code":"KP",
    "gn:dem":87,
    "gn:feature_class":"P",
    "gn:feature_code":"PPL",
    "gn:name":"T\u014fkch\u2019on",
    "gn:population":0,
    "gn:timezone":"Asia/Pyongyang",
    "iso:country":"KP",
    "name:und_x_variant":[
        "\ub355\ucd0c",
        "T\u014fkch\u2019on"
    ],
    "wof:name":"Tokch'on",
    "wof:placetype":"locality"
},
  "geometry": {"coordinates":[129.27278000000001,40.88833],"type":"Point"}
}