{
  "type": "Feature",
  "properties": {
    "gn:admin1_code":"3.0",
    "gn:asciiname":"Saesulmak",
    "gn:country_code":"KP",
    "gn:dem":33,
    "gn:feature_class":"P",
    "gn:feature_code":"PPL",
    "gn:name":"Saesulmak",
    "gn:population":0,
    "gn:timezone":"Asia/Pyongyang",
    "iso:country":"KP",
    "name:kor_x_preferred":[
        "\uc0c8\uc220\ub9c9"
    ],
    "wof:name":"Saesulmak",
    "wof:placetype":"locality"
},
  "geometry": {"coordinates":[127.17806000000002,39.39944000000001],"type":"Point"}
}