{
  "type": "Feature",
  "properties": {
    "gn:admin1_code":"17.0",
    "gn:asciiname":"Karumjang",
    "gn:country_code":"KP",
    "gn:dem":476,
    "gn:feature_class":"P",
    "gn:feature_code":"PPL",
    "gn:name":"Kar\u016dmjang",
    "gn:population":0,
    "gn:timezone":"Asia/Pyongyang",
    "iso:country":"KP",
    "name:und_x_variant":[
        "Ch\u2019ils\u014fng-dong",
        "Ch\u2019ils\u014fng-ni",
        "Kar\u016dmjang",
        "\uac00\ub984\uc7a5"
    ],
    "wof:name":"Karumjang",
    "wof:placetype":"locality"
},
  "geometry": {"coordinates":[129.20332999999999,42.24556],"type":"Point"}
}