{
  "type": "Feature",
  "properties": {
    "gn:admin1_code":"11.0",
    "gn:asciiname":"Kyonil-tong",
    "gn:country_code":"KP",
    "gn:dem":6,
    "gn:feature_class":"P",
    "gn:feature_code":"PPL",
    "gn:name":"Ky\u014fnil-tong",
    "gn:population":0,
    "gn:timezone":"Asia/Pyongyang",
    "iso:country":"KP",
    "name:und_x_variant":[
        "\uacac\uc77c\ub3d9",
        "Ky\u014fnil-li",
        "Ky\u014fnil-tong"
    ],
    "wof:name":"Kyonil-tong",
    "wof:placetype":"locality"
},
  "geometry": {"coordinates":[124.3875,39.97917],"type":"Point"}
}