{
  "type": "Feature",
  "properties": {
    "gn:admin1_code":"11.0",
    "gn:asciiname":"Kurim-ni",
    "gn:country_code":"KP",
    "gn:dem":114,
    "gn:feature_class":"P",
    "gn:feature_code":"PPL",
    "gn:name":"Kurim-ni",
    "gn:population":0,
    "gn:timezone":"Asia/Pyongyang",
    "iso:country":"KP",
    "name:eng_x_preferred":[
        "Kurim"
    ],
    "name:eng_x_variant":[
        "Kurim-ni"
    ],
    "wof:name":"Kurim",
    "wof:placetype":"locality"
},
  "geometry": {"coordinates":[125.19028,39.94833],"type":"Point"}
}