{
  "type": "Feature",
  "properties": {
    "gn:admin1_code":"0.0",
    "gn:asciiname":"Solgwal-li",
    "gn:country_code":"KP",
    "gn:dem":965,
    "gn:feature_class":"P",
    "gn:feature_code":"PPL",
    "gn:name":"S\u014flgwal-li",
    "gn:population":0,
    "gn:timezone":"Asia/Pyongyang",
    "iso:country":"KP",
    "name:kor_x_preferred":[
        "\uc124\uad00\ub9ac"
    ],
    "name:und_x_variant":[
        "Setsukan-ri",
        "S\u014flgwan-ni",
        "S\u014flgwal-li"
    ],
    "wof:name":"Solgwal-li",
    "wof:placetype":"locality"
},
  "geometry": {"coordinates":[127.16667,40.81667],"type":"Point"}
}