{
  "type": "Feature",
  "properties": {
    "gn:admin1_code":"13.0",
    "gn:asciiname":"Sangnamgye",
    "gn:country_code":"KP",
    "gn:dem":1356,
    "gn:feature_class":"P",
    "gn:feature_code":"PPL",
    "gn:name":"Sangnamgye",
    "gn:population":0,
    "gn:timezone":"Asia/Pyongyang",
    "iso:country":"KP",
    "name:kor_x_preferred":[
        "\uc0c1\ub0a8\uacc4"
    ],
    "wof:name":"Sangnamgye",
    "wof:placetype":"locality"
},
  "geometry": {"coordinates":[128.82388999999998,41.22389],"type":"Point"}
}