{
  "type": "Feature",
  "properties": {
    "gn:admin1_code":"12.0",
    "gn:asciiname":"K'un'galmaegol",
    "gn:country_code":"KP",
    "gn:dem":9,
    "gn:feature_class":"P",
    "gn:feature_code":"PPL",
    "gn:name":"K\u2019\u016dn\u2019galmaegol",
    "gn:population":0,
    "gn:timezone":"Asia/Pyongyang",
    "iso:country":"KP",
    "name:kor_x_preferred":[
        "\ud070\uac08\ub9e4\uace8"
    ],
    "name:kor_x_variant":[
        "\ub300\ub9e4\ub3d9"
    ],
    "name:und_x_variant":[
        "K\u2019\u016dn\u2019galmaegol",
        "Taemae-dong",
        "Keungalmaegol"
    ],
    "wof:name":"K'un'galmaegol",
    "wof:placetype":"locality"
},
  "geometry": {"coordinates":[125.67438,38.95642],"type":"Point"}
}