{
  "type": "Feature",
  "properties": {
    "gn:admin1_code":"9.0",
    "gn:asciiname":"Hangp'yong-ni",
    "gn:country_code":"KP",
    "gn:dem":18,
    "gn:feature_class":"P",
    "gn:feature_code":"PPL",
    "gn:name":"Hangp\u2019y\u014fng-ni",
    "gn:population":0,
    "gn:timezone":"Asia/Pyongyang",
    "iso:country":"KP",
    "name:kor_x_preferred":[
        "\ud56d\ud3c9\ub9ac"
    ],
    "name:und_x_variant":[
        "Hangp\u2019y\u014fng-ni"
    ],
    "wof:name":"Hangp'yong-ni",
    "wof:placetype":"locality"
},
  "geometry": {"coordinates":[127.77,39.0425],"type":"Point"}
}