{
  "type": "Feature",
  "properties": {
    "gn:admin1_code":"7.0",
    "gn:asciiname":"Malmi",
    "gn:country_code":"KP",
    "gn:dem":28,
    "gn:feature_class":"P",
    "gn:feature_code":"PPL",
    "gn:name":"Malmi",
    "gn:population":0,
    "gn:timezone":"Asia/Pyongyang",
    "iso:country":"KP",
    "name:fin_x_preferred":[
        "Malmi"
    ],
    "name:swe_x_preferred":[
        "Malmi"
    ],
    "name:und_x_variant":[
        "\ub9d0\ubbf8",
        "Malmi"
    ],
    "wof:name":"Malmi",
    "wof:placetype":"locality"
},
  "geometry": {"coordinates":[126.41333,38.03833],"type":"Point"}
}