{
  "type": "Feature",
  "properties": {
    "gn:admin1_code":"15.0",
    "gn:asciiname":"Hwanghak-tong",
    "gn:country_code":"KP",
    "gn:dem":56,
    "gn:feature_class":"P",
    "gn:feature_code":"PPL",
    "gn:name":"Hwanghak-tong",
    "gn:population":0,
    "gn:timezone":"Asia/Pyongyang",
    "iso:country":"KP",
    "name:eng_x_preferred":[
        "Hwanghak"
    ],
    "name:eng_x_variant":[
        "Hwanghak-tong"
    ],
    "name:kor_x_preferred":[
        "\ud669\ud559\ub3d9"
    ],
    "wof:name":"Hwanghak",
    "wof:placetype":"locality"
},
  "geometry": {"coordinates":[126.04139000000001,39.42056],"type":"Point"}
}