{
  "type": "Feature",
  "properties": {
    "gn:admin1_code":"11.0",
    "gn:asciiname":"Wonsan",
    "gn:country_code":"KP",
    "gn:dem":25,
    "gn:feature_class":"P",
    "gn:feature_code":"PPL",
    "gn:name":"W\u014fnsan",
    "gn:population":0,
    "gn:timezone":"Asia/Pyongyang",
    "iso:country":"KP",
    "name:ace_x_preferred":[
        "Wonsan"
    ],
    "name:ara_x_preferred":[
        "\u0648\u0648\u0646\u0633\u0627\u0646"
    ],
    "name:aze_x_preferred":[
        "Vonsan"
    ],
    "name:bel_x_preferred":[
        "\u0412\u0430\u043d\u0441\u0430\u043d"
    ],
    "name:bul_x_preferred":[
        "\u0423\u044a\u043d\u0441\u0430\u043d"
    ],
    "name:cat_x_preferred":[
        "Wonsan"
    ],
    "name:ceb_x_preferred":[
        "W\u014fnsan"
    ],
    "name:ces_x_preferred":[
        "Wonsan"
    ],
    "name:dan_x_preferred":[
        "Wonsan"
    ],
    "name:deu_x_preferred":[
        "W\u014fnsan"
    ],
    "name:epo_x_preferred":[
        "Vonsano"
    ],
    "name:est_x_preferred":[
        "W\u014fnsan"
    ],
    "name:eus_x_preferred":[
        "Wonsan"
    ],
    "name:fas_x_preferred":[
        "\u0648\u0646\u0633\u0627\u0646"
    ],
    "name:fin_x_preferred":[
        "Wonsan"
    ],
    "name:fra_x_preferred":[
        "Wonsan"
    ],
    "name:heb_x_preferred":[
        "\u05d5\u05d5\u05e0\u05e1\u05df"
    ],
    "name:hun_x_preferred":[
        "Vonszan"
    ],
    "name:hye_x_preferred":[
        "\u054e\u0578\u0576\u057d\u0561\u0576"
    ],
    "name:ind_x_preferred":[
        "W\u014fnsan"
    ],
    "name:ita_x_preferred":[
        "W\u014fnsan"
    ],
    "name:jpn_x_preferred":[
        "\u5143\u5c71\u5e02"
    ],
    "name:kal_x_preferred":[
        "Wonsan"
    ],
    "name:kor_x_preferred":[
        "\uc6d0\uc0b0\uc2dc"
    ],
    "name:lit_x_preferred":[
        "Vonsanas"
    ],
    "name:mon_x_preferred":[
        "\u0412\u043e\u043d\u044c\u0441\u0430\u043d\u044c"
    ],
    "name:mri_x_preferred":[
        "Wonsan"
    ],
    "name:mzn_x_preferred":[
        "\u0648\u0646\u0633\u0627\u0646"
    ],
    "name:nds_x_preferred":[
        "Wonsan"
    ],
    "name:nld_x_preferred":[
        "W\u014fnsan"
    ],
    "name:nor_x_preferred":[
        "Wonsan"
    ],
    "name:pnb_x_preferred":[
        "\u0648\u0646\u0633\u0627\u0646"
    ],
    "name:pol_x_preferred":[
        "W\u014fnsan"
    ],
    "name:por_x_preferred":[
        "Wonsan"
    ],
    "name:ron_x_preferred":[
        "Wonsan"
    ],
    "name:rus_x_preferred":[
        "\u0412\u043e\u043d\u0441\u0430\u043d"
    ],
    "name:sco_x_preferred":[
        "Wonsan"
    ],
    "name:slk_x_preferred":[
        "Wonsan"
    ],
    "name:spa_x_preferred":[
        "W\u014fnsan"
    ],
    "name:swa_x_preferred":[
        "Wonsan"
    ],
    "name:swe_x_preferred":[
        "Wonsan"
    ],
    "name:tgl_x_preferred":[
        "Wonsan"
    ],
    "name:tha_x_preferred":[
        "\u0e27\u0e47\u0e2d\u0e19\u0e0b\u0e31\u0e19"
    ],
    "name:tur_x_preferred":[
        "Wonsan"
    ],
    "name:ukr_x_preferred":[
        "\u0412\u043e\u043d\u0441\u0430\u043d"
    ],
    "name:und_x_variant":[
        "\uc6d0\uc0b0"
    ],
    "name:urd_x_preferred":[
        "\u0648\u0648\u0646\u0633\u0627\u0646"
    ],
    "name:vie_x_preferred":[
        "Wonsan"
    ],
    "name:war_x_preferred":[
        "Wonsan"
    ],
    "name:zho_x_preferred":[
        "\u5143\u5c71\u5e02"
    ],
    "wof:name":"Wonsan",
    "wof:placetype":"locality"
},
  "geometry": {"coordinates":[124.55389,39.91917],"type":"Point"}
}