{
  "type": "Feature",
  "properties": {
    "gn:admin1_code":"11.0",
    "gn:asciiname":"Wonsan",
    "gn:country_code":"KP",
    "gn:dem":25,
    "gn:feature_class":"P",
    "gn:feature_code":"PPL",
    "gn:name":"W\u014fnsan",
    "gn:population":0,
    "gn:timezone":"Asia/Pyongyang",
    "iso:country":"KP",
    "name:und_x_variant":[
        "\uc6d0\uc0b0",
        "W\u014fnsan"
    ],
    "wof:name":"Wonsan",
    "wof:placetype":"locality"
},
  "geometry": {"coordinates":[124.55389,39.91917],"type":"Point"}
}