{
  "type": "Feature",
  "properties": {
    "gn:admin1_code":"12.0",
    "gn:asciiname":"Saesom",
    "gn:country_code":"KP",
    "gn:dem":5,
    "gn:feature_class":"P",
    "gn:feature_code":"PPL",
    "gn:name":"Saes\u014fm",
    "gn:population":0,
    "gn:timezone":"Asia/Pyongyang",
    "iso:country":"KP",
    "name:kor_x_preferred":[
        "\uc0c8\uc12c"
    ],
    "name:und_x_variant":[
        "Sindo",
        "Saes\u014fm",
        "Saeseom"
    ],
    "wof:name":"Saesom",
    "wof:placetype":"locality"
},
  "geometry": {"coordinates":[125.59438,38.92449000000001],"type":"Point"}
}