{
  "type": "Feature",
  "properties": {
    "gn:admin1_code":"9.0",
    "gn:asciiname":"Tonghung-ni",
    "gn:country_code":"KP",
    "gn:dem":110,
    "gn:feature_class":"P",
    "gn:feature_code":"PPL",
    "gn:name":"Tongh\u016dng-ni",
    "gn:population":0,
    "gn:timezone":"Asia/Pyongyang",
    "iso:country":"KP",
    "name:kor_x_preferred":[
        "\ub3d9\ud765\ub9ac"
    ],
    "name:kor_x_variant":[
        "Tongh\u016dng-ni"
    ],
    "name:und_x_variant":[
        "Tongbong-ni"
    ],
    "wof:name":"Tonghung-ni",
    "wof:placetype":"locality"
},
  "geometry": {"coordinates":[127.13,39.24333],"type":"Point"}
}