{
  "type": "Feature",
  "properties": {
    "gn:admin1_code":"15.0",
    "gn:asciiname":"Araejongmaru",
    "gn:country_code":"KP",
    "gn:dem":12,
    "gn:feature_class":"P",
    "gn:feature_code":"PPL",
    "gn:name":"Araej\u014fngmaru",
    "gn:population":0,
    "gn:timezone":"Asia/Pyongyang",
    "iso:country":"KP",
    "name:und_x_variant":[
        "Haj\u014fngmaru",
        "Arae-ch\u014fngmaru",
        "Araej\u014fngmaru"
    ],
    "wof:name":"Araejongmaru",
    "wof:placetype":"locality"
},
  "geometry": {"coordinates":[125.34278,39.0875],"type":"Point"}
}