{
  "type": "Feature",
  "properties": {
    "gn:admin1_code":"7.0",
    "gn:asciiname":"Pujo-dong",
    "gn:country_code":"KP",
    "gn:dem":271,
    "gn:feature_class":"P",
    "gn:feature_code":"PPL",
    "gn:name":"Pujo-dong",
    "gn:population":0,
    "gn:timezone":"Asia/Pyongyang",
    "iso:country":"KP",
    "name:kor_x_preferred":[
        "\ubd80\uc870\ub3d9"
    ],
    "wof:name":"Pujo-dong",
    "wof:placetype":"locality"
},
  "geometry": {"coordinates":[126.66889,38.62194],"type":"Point"}
}