{
  "type": "Feature",
  "properties": {
    "gn:admin1_code":"3.0",
    "gn:asciiname":"Changja-ri",
    "gn:country_code":"KP",
    "gn:dem":62,
    "gn:feature_class":"P",
    "gn:feature_code":"PPL",
    "gn:name":"Changja-ri",
    "gn:population":0,
    "gn:timezone":"Asia/Pyongyang",
    "iso:country":"KP",
    "name:und_x_variant":[
        "\uc7a5\uc790\ub9ac",
        "Changja-ri"
    ],
    "wof:name":"Changja-ri",
    "wof:placetype":"locality"
},
  "geometry": {"coordinates":[127.23139,39.68361],"type":"Point"}
}