{
  "type": "Feature",
  "properties": {
    "gn:admin1_code":"6.0",
    "gn:asciiname":"Sinch'on",
    "gn:country_code":"KP",
    "gn:dem":9,
    "gn:feature_class":"P",
    "gn:feature_code":"PPL",
    "gn:name":"Sinch\u2019on",
    "gn:population":0,
    "gn:timezone":"Asia/Pyongyang",
    "iso:country":"KP",
    "name:kor_x_preferred":[
        "Sinch\u2019on"
    ],
    "name:kor_x_variant":[
        "\uc2e0\ucd0c"
    ],
    "wof:name":"Sinch'on",
    "wof:placetype":"locality"
},
  "geometry": {"coordinates":[124.91528,38.18472],"type":"Point"}
}