{
  "type": "Feature",
  "properties": {
    "gn:admin1_code":"7.0",
    "gn:admin2_code":"Insan-gun",
    "gn:asciiname":"Yulmok-tong",
    "gn:country_code":"KP",
    "gn:dem":257,
    "gn:feature_class":"P",
    "gn:feature_code":"PPL",
    "gn:name":"Yulmok-tong",
    "gn:population":0,
    "gn:timezone":"Asia/Pyongyang",
    "iso:country":"KP",
    "wof:name":"Yulmok-tong",
    "wof:placetype":"locality"
},
  "geometry": {"coordinates":[125.94693999999998,38.16611],"type":"Point"}
}