{
  "type": "Feature",
  "properties": {
    "gn:admin1_code":"11.0",
    "gn:asciiname":"Songp'yong-ni",
    "gn:country_code":"KP",
    "gn:dem":177,
    "gn:feature_class":"P",
    "gn:feature_code":"PPL",
    "gn:name":"S\u014fngp\u2019y\u014fng-ni",
    "gn:population":0,
    "gn:timezone":"Asia/Pyongyang",
    "iso:country":"KP",
    "name:und_x_variant":[
        "\uc131\ud3c9\ub9ac",
        "S\u014fngp\u2019y\u014fng-ni"
    ],
    "wof:name":"Songp'yong-ni",
    "wof:placetype":"locality"
},
  "geometry": {"coordinates":[125.48917,40.24833],"type":"Point"}
}