{
  "type": "Feature",
  "properties": {
    "gn:admin1_code":"12.0",
    "gn:asciiname":"Maehyol-li",
    "gn:cc2":"KP",
    "gn:country_code":"KP",
    "gn:dem":28,
    "gn:feature_class":"P",
    "gn:feature_code":"PPL",
    "gn:name":"Maehy\u014fl-li",
    "gn:population":0,
    "gn:timezone":"Asia/Pyongyang",
    "iso:country":"KP",
    "name:kor_x_preferred":[
        "\ub9e4\ud604\ub9ac"
    ],
    "name:und_x_variant":[
        "Maehy\u014fn-ni",
        "Maehy\u014fl-li",
        "Maehyeolli"
    ],
    "wof:name":"Maehyol-li",
    "wof:placetype":"locality"
},
  "geometry": {"coordinates":[125.58333,38.86667],"type":"Point"}
}