{
  "type": "Feature",
  "properties": {
    "gn:admin1_code":"11.0",
    "gn:asciiname":"Okp'o-ri",
    "gn:country_code":"KP",
    "gn:dem":241,
    "gn:feature_class":"P",
    "gn:feature_code":"PPL",
    "gn:name":"Okp\u2019o-ri",
    "gn:population":0,
    "gn:timezone":"Asia/Pyongyang",
    "iso:country":"KP",
    "name:und_x_variant":[
        "\uc625\ud3ec\ub9ac",
        "Okp\u2019o-ri"
    ],
    "wof:name":"Okp'o-ri",
    "wof:placetype":"locality"
},
  "geometry": {"coordinates":[125.24472,40.43778],"type":"Point"}
}