{
  "type": "Feature",
  "properties": {
    "gn:admin1_code":"6.0",
    "gn:asciiname":"Sangbonghyon",
    "gn:country_code":"KP",
    "gn:dem":29,
    "gn:feature_class":"P",
    "gn:feature_code":"PPL",
    "gn:name":"Sangbonghy\u014fn",
    "gn:population":0,
    "gn:timezone":"Asia/Pyongyang",
    "iso:country":"KP",
    "name:und_x_variant":[
        "Sambonghy\u014fn",
        "\uc0c1\ubd09\ud604",
        "Sangbonghy\u014fn"
    ],
    "wof:name":"Sangbonghyon",
    "wof:placetype":"locality"
},
  "geometry": {"coordinates":[125.61360999999999,37.83139],"type":"Point"}
}