{
  "type": "Feature",
  "properties": {
    "gn:admin1_code":"9.0",
    "gn:asciiname":"Hasahyol-li",
    "gn:country_code":"KP",
    "gn:dem":139,
    "gn:feature_class":"P",
    "gn:feature_code":"PPL",
    "gn:name":"Hasahy\u014fl-li",
    "gn:population":0,
    "gn:timezone":"Asia/Pyongyang",
    "iso:country":"KP",
    "name:kor_x_preferred":[
        "\ud558\uc0ac\ud604\ub9ac"
    ],
    "name:kor_x_variant":[
        "Hasahy\u014fl-li"
    ],
    "wof:name":"Hasahyol-li",
    "wof:placetype":"locality"
},
  "geometry": {"coordinates":[127.46222,38.945],"type":"Point"}
}