{
  "type": "Feature",
  "properties": {
    "gn:admin1_code":"3.0",
    "gn:admin2_code":"Tanch\u2019\u014fn-si",
    "gn:asciiname":"Chungdogi",
    "gn:country_code":"KP",
    "gn:dem":1100,
    "gn:feature_class":"P",
    "gn:feature_code":"PPL",
    "gn:name":"Chungd\u014fgi",
    "gn:population":0,
    "gn:timezone":"Asia/Pyongyang",
    "iso:country":"KP",
    "wof:name":"Chungdogi",
    "wof:placetype":"locality"
},
  "geometry": {"coordinates":[128.84,41.01278],"type":"Point"}
}