{
  "type": "Feature",
  "properties": {
    "gn:admin1_code":"11.0",
    "gn:asciiname":"Mado-ri",
    "gn:country_code":"KP",
    "gn:dem":10,
    "gn:feature_class":"P",
    "gn:feature_code":"PPL",
    "gn:name":"Mado-ri",
    "gn:population":0,
    "gn:timezone":"Asia/Pyongyang",
    "iso:country":"KP",
    "name:und_x_variant":[
        "\ub9c8\ub3c4\ub9ac",
        "Mado-ri"
    ],
    "wof:name":"Mado-ri",
    "wof:placetype":"locality"
},
  "geometry": {"coordinates":[124.46693999999999,40.15139],"type":"Point"}
}