{
  "type": "Feature",
  "properties": {
    "gn:admin1_code":"6.0",
    "gn:asciiname":"Kongjang-dong",
    "gn:country_code":"KP",
    "gn:dem":14,
    "gn:feature_class":"P",
    "gn:feature_code":"PPL",
    "gn:name":"Kongjang-dong",
    "gn:population":0,
    "gn:timezone":"Asia/Pyongyang",
    "iso:country":"KP",
    "name:kor_x_preferred":[
        "\uacf5\uc7a5\ub3d9"
    ],
    "wof:name":"Kongjang-dong",
    "wof:placetype":"locality"
},
  "geometry": {"coordinates":[125.58333,38.59056],"type":"Point"}
}