{
  "type": "Feature",
  "properties": {
    "gn:admin1_code":"3.0",
    "gn:asciiname":"Hadok-tong",
    "gn:country_code":"KP",
    "gn:dem":13,
    "gn:feature_class":"P",
    "gn:feature_code":"PPL",
    "gn:name":"Had\u014fk-tong",
    "gn:population":0,
    "gn:timezone":"Asia/Pyongyang",
    "iso:country":"KP",
    "name:eng_x_preferred":[
        "Hadok"
    ],
    "name:eng_x_variant":[
        "Hadok-tong"
    ],
    "name:und_x_variant":[
        "\ud558\ub355\ub3d9",
        "Had\u014fng-ni",
        "Had\u014fk-tong"
    ],
    "wof:name":"Hadok",
    "wof:placetype":"locality"
},
  "geometry": {"coordinates":[127.63333,39.85],"type":"Point"}
}