{
  "type": "Feature",
  "properties": {
    "gn:admin1_code":"12.0",
    "gn:admin2_code":"Kangdong-gun",
    "gn:asciiname":"Mulgo-ri",
    "gn:country_code":"KP",
    "gn:dem":55,
    "gn:feature_class":"P",
    "gn:feature_code":"PPL",
    "gn:name":"Mulg\u014f-ri",
    "gn:population":0,
    "gn:timezone":"Asia/Pyongyang",
    "iso:country":"KP",
    "name:kor_x_preferred":[
        "\ubb3c\uac70\ub9ac"
    ],
    "name:und_x_variant":[
        "Mulk\u014fri",
        "Mulg\u014f-ri",
        "Mulgeori"
    ],
    "wof:name":"Mulgo-ri",
    "wof:placetype":"locality"
},
  "geometry": {"coordinates":[126.11056000000001,38.99333],"type":"Point"}
}