{
  "type": "Feature",
  "properties": {
    "gn:admin1_code":"9.0",
    "gn:asciiname":"Tadae-dong",
    "gn:country_code":"KP",
    "gn:dem":170,
    "gn:feature_class":"P",
    "gn:feature_code":"PPL",
    "gn:name":"Tadae-dong",
    "gn:population":0,
    "gn:timezone":"Asia/Pyongyang",
    "iso:country":"KP",
    "wof:name":"Tadae-dong",
    "wof:placetype":"locality"
},
  "geometry": {"coordinates":[127.01278000000001,38.41472],"type":"Point"}
}