{
  "type": "Feature",
  "properties": {
    "gn:admin1_code":"7.0",
    "gn:asciiname":"Pulgunbau",
    "gn:country_code":"KP",
    "gn:dem":105,
    "gn:feature_class":"P",
    "gn:feature_code":"PPL",
    "gn:name":"Pulg\u016dnbau",
    "gn:population":0,
    "gn:timezone":"Asia/Pyongyang",
    "iso:country":"KP",
    "name:kor_x_preferred":[
        "\ubd89\uc740\ubc14\uc6b0"
    ],
    "name:kor_x_variant":[
        "Pulg\u016dnbau"
    ],
    "wof:name":"Pulgunbau",
    "wof:placetype":"locality"
},
  "geometry": {"coordinates":[126.41667,38.54167],"type":"Point"}
}