{
  "type": "Feature",
  "properties": {
    "gn:admin1_code":"12.0",
    "gn:asciiname":"Tangjong-ni",
    "gn:country_code":"KP",
    "gn:dem":27,
    "gn:feature_class":"P",
    "gn:feature_code":"PPL",
    "gn:name":"Tangj\u014fng-ni",
    "gn:population":0,
    "gn:timezone":"Asia/Pyongyang",
    "iso:country":"KP",
    "name:und_x_variant":[
        "\ub2f9\uc815\ub9ac",
        "Tangj\u014fng-ni",
        "Dangjeongni"
    ],
    "wof:name":"Tangjong-ni",
    "wof:placetype":"locality"
},
  "geometry": {"coordinates":[125.81493,38.92047],"type":"Point"}
}