{
  "type": "Feature",
  "properties": {
    "gn:admin1_code":"11.0",
    "gn:asciiname":"Kan-dong",
    "gn:country_code":"KP",
    "gn:dem":195,
    "gn:feature_class":"P",
    "gn:feature_code":"PPL",
    "gn:name":"Kan-dong",
    "gn:population":0,
    "gn:timezone":"Asia/Pyongyang",
    "iso:country":"KP",
    "name:und_x_variant":[
        "\uac04\ub3d9",
        "Kan-dong"
    ],
    "wof:name":"Kan-dong",
    "wof:placetype":"locality"
},
  "geometry": {"coordinates":[126.07417,40.01389],"type":"Point"}
}