{
  "type": "Feature",
  "properties": {
    "gn:admin1_code":"15.0",
    "gn:admin2_code":"T\u014fkch\u2019\u014fn-gun",
    "gn:asciiname":"Yonch'ang-gol",
    "gn:country_code":"KP",
    "gn:dem":197,
    "gn:feature_class":"P",
    "gn:feature_code":"PPL",
    "gn:name":"Y\u014fnch\u2019ang-gol",
    "gn:population":0,
    "gn:timezone":"Asia/Pyongyang",
    "iso:country":"KP",
    "wof:name":"Yonch'ang-gol",
    "wof:placetype":"locality"
},
  "geometry": {"coordinates":[126.36139,39.8125],"type":"Point"}
}