{
  "type": "Feature",
  "properties": {
    "gn:admin1_code":"6.0",
    "gn:asciiname":"Tangmol",
    "gn:country_code":"KP",
    "gn:dem":63,
    "gn:feature_class":"P",
    "gn:feature_code":"PPL",
    "gn:name":"Tangmol",
    "gn:population":0,
    "gn:timezone":"Asia/Pyongyang",
    "iso:country":"KP",
    "name:und_x_variant":[
        "Tangmoro",
        "\ub2f9\ubab0",
        "Tangmol"
    ],
    "wof:name":"Tangmol",
    "wof:placetype":"locality"
},
  "geometry": {"coordinates":[125.37778,38.15833],"type":"Point"}
}