{
  "type": "Feature",
  "properties": {
    "gn:admin1_code":"15.0",
    "gn:admin2_code":"P'y\u014fngw\u014fn-gun",
    "gn:asciiname":"Chunggyo-dong",
    "gn:country_code":"KP",
    "gn:dem":9,
    "gn:feature_class":"P",
    "gn:feature_code":"PPL",
    "gn:name":"Chunggyo-dong",
    "gn:population":0,
    "gn:timezone":"Asia/Pyongyang",
    "iso:country":"KP",
    "name:kor_x_preferred":[
        "\uc911\uad50\ub3d9"
    ],
    "wof:name":"Chunggyo-dong",
    "wof:placetype":"locality"
},
  "geometry": {"coordinates":[125.50055999999999,39.31389],"type":"Point"}
}