{
  "type": "Feature",
  "properties": {
    "gn:admin1_code":"7.0",
    "gn:asciiname":"Ch'ang-gol",
    "gn:country_code":"KP",
    "gn:dem":135,
    "gn:feature_class":"P",
    "gn:feature_code":"PPL",
    "gn:name":"Ch\u2019ang-gol",
    "gn:population":0,
    "gn:timezone":"Asia/Pyongyang",
    "iso:country":"KP",
    "wof:name":"Ch'ang-gol",
    "wof:placetype":"locality"
},
  "geometry": {"coordinates":[126.03778,38.60833],"type":"Point"}
}