{
  "type": "Feature",
  "properties": {
    "gn:admin1_code":"15.0",
    "gn:asciiname":"Hamsan-dong",
    "gn:country_code":"KP",
    "gn:dem":81,
    "gn:feature_class":"P",
    "gn:feature_code":"PPL",
    "gn:name":"Hamsan-dong",
    "gn:population":0,
    "gn:timezone":"Asia/Pyongyang",
    "iso:country":"KP",
    "wof:name":"Hamsan-dong",
    "wof:placetype":"locality"
},
  "geometry": {"coordinates":[125.85666999999999,39.40667],"type":"Point"}
}