{
  "type": "Feature",
  "properties": {
    "gn:admin1_code":"15.0",
    "gn:admin2_code":"Y\u014fngw\u014fn-gun",
    "gn:asciiname":"Tungnyong-dong",
    "gn:country_code":"KP",
    "gn:dem":331,
    "gn:feature_class":"P",
    "gn:feature_code":"PPL",
    "gn:name":"T\u016dngnyong-dong",
    "gn:population":0,
    "gn:timezone":"Asia/Pyongyang",
    "iso:country":"KP",
    "wof:name":"Tungnyong-dong",
    "wof:placetype":"locality"
},
  "geometry": {"coordinates":[126.44972,39.90944],"type":"Point"}
}