{
  "type": "Feature",
  "properties": {
    "gn:admin1_code":"1.0",
    "gn:admin2_code":"Nangnim-gun",
    "gn:asciiname":"Galbanni",
    "gn:country_code":"KP",
    "gn:dem":859,
    "gn:feature_class":"P",
    "gn:feature_code":"PPL",
    "gn:name":"Galbanni",
    "gn:population":0,
    "gn:timezone":"Asia/Pyongyang",
    "iso:country":"KP",
    "name:kor_x_preferred":[
        "\uac08\ubc2d\ub9ac"
    ],
    "name:und_x_variant":[
        "Kalbat-ni",
        "Galbanni"
    ],
    "wof:name":"Galbanni",
    "wof:placetype":"locality"
},
  "geometry": {"coordinates":[127.29416999999999,40.94222],"type":"Point"}
}