{
  "type": "Feature",
  "properties": {
    "gn:admin1_code":"6.0",
    "gn:asciiname":"Orumdol",
    "gn:country_code":"KP",
    "gn:dem":30,
    "gn:feature_class":"P",
    "gn:feature_code":"PPL",
    "gn:name":"\u014er\u016dmdol",
    "gn:population":0,
    "gn:timezone":"Asia/Pyongyang",
    "iso:country":"KP",
    "wof:name":"Orumdol",
    "wof:placetype":"locality"
},
  "geometry": {"coordinates":[126.11056000000001,37.96222],"type":"Point"}
}