{
  "type": "Feature",
  "properties": {
    "gn:admin1_code":"7.0",
    "gn:asciiname":"Sindae-dong",
    "gn:country_code":"KP",
    "gn:dem":84,
    "gn:feature_class":"P",
    "gn:feature_code":"PPL",
    "gn:name":"Sindae-dong",
    "gn:population":0,
    "gn:timezone":"Asia/Pyongyang",
    "iso:country":"KP",
    "name:und_x_variant":[
        "\uc2e0\ub300\ub3d9",
        "Sindae-dong"
    ],
    "wof:name":"Sindae-dong",
    "wof:placetype":"locality"
},
  "geometry": {"coordinates":[126.58194,38.16],"type":"Point"}
}