{
  "type": "Feature",
  "properties": {
    "gn:admin1_code":"6.0",
    "gn:asciiname":"Chigyongjang",
    "gn:country_code":"KP",
    "gn:dem":27,
    "gn:feature_class":"P",
    "gn:feature_code":"PPL",
    "gn:name":"Chigy\u014fngjang",
    "gn:population":0,
    "gn:timezone":"Asia/Pyongyang",
    "iso:country":"KP",
    "name:und_x_variant":[
        "\uc9c0\uacbd\uc7a5",
        "Chigy\u014fngjang"
    ],
    "wof:name":"Chigyongjang",
    "wof:placetype":"locality"
},
  "geometry": {"coordinates":[125.605,37.91194],"type":"Point"}
}