{
  "type": "Feature",
  "properties": {
    "gn:admin1_code":"12.0",
    "gn:asciiname":"Marumul",
    "gn:cc2":"KP",
    "gn:country_code":"KP",
    "gn:dem":10,
    "gn:feature_class":"P",
    "gn:feature_code":"PPL",
    "gn:name":"Marumul",
    "gn:population":0,
    "gn:timezone":"Asia/Pyongyang",
    "iso:country":"KP",
    "name:kor_x_preferred":[
        "\ub9d0\uc6b0\ubb3c"
    ],
    "name:und_x_variant":[
        "Maj\u014fng",
        "Marumul"
    ],
    "wof:name":"Marumul",
    "wof:placetype":"locality"
},
  "geometry": {"coordinates":[125.67778,38.90889],"type":"Point"}
}