{
  "type": "Feature",
  "properties": {
    "gn:admin1_code":"3.0",
    "gn:asciiname":"Sanghamjon",
    "gn:country_code":"KP",
    "gn:dem":255,
    "gn:feature_class":"P",
    "gn:feature_code":"PPL",
    "gn:name":"Sanghamj\u014fn",
    "gn:population":0,
    "gn:timezone":"Asia/Pyongyang",
    "iso:country":"KP",
    "name:und_x_variant":[
        "Sanghamj\u014fn",
        "\uc0c1\ud568\uc804"
    ],
    "wof:name":"Sanghamjon",
    "wof:placetype":"locality"
},
  "geometry": {"coordinates":[128.24893,40.46276],"type":"Point"}
}