{
  "type": "Feature",
  "properties": {
    "gn:admin1_code":"6.0",
    "gn:asciiname":"Chinch'on-dong",
    "gn:country_code":"KP",
    "gn:dem":103,
    "gn:feature_class":"P",
    "gn:feature_code":"PPL",
    "gn:name":"Chinch\u2019\u014fn-dong",
    "gn:population":0,
    "gn:timezone":"Asia/Pyongyang",
    "iso:country":"KP",
    "name:kor_x_preferred":[
        "\uc9c4\ucc9c\ub3d9"
    ],
    "name:kor_x_variant":[
        "Chinch\u2019\u014fn-dong"
    ],
    "wof:name":"Chinch'on-dong",
    "wof:placetype":"locality"
},
  "geometry": {"coordinates":[125.16222,38.32056],"type":"Point"}
}