{
  "type": "Feature",
  "properties": {
    "gn:admin1_code":"9.0",
    "gn:admin2_code":"P\u2019y\u014fnggang-gun",
    "gn:asciiname":"Pokkye-ri",
    "gn:country_code":"KP",
    "gn:dem":346,
    "gn:feature_class":"P",
    "gn:feature_code":"PPL",
    "gn:name":"Pokkye-ri",
    "gn:population":0,
    "gn:timezone":"Asia/Pyongyang",
    "iso:country":"KP",
    "name:und_x_variant":[
        "Fukkei-ri",
        "P\u2019y\u014fnggang-\u016dp",
        "P\u2019y\u014fnggang",
        "Pokkye",
        "Pokkye-ri"
    ],
    "wof:name":"Pokkye-ri",
    "wof:placetype":"locality"
},
  "geometry": {"coordinates":[127.25943999999998,38.44556],"type":"Point"}
}