{
  "type": "Feature",
  "properties": {
    "gn:admin1_code":"6.0",
    "gn:admin2_code":"Kwail-gun",
    "gn:asciiname":"Unsal-li",
    "gn:cc2":"KP",
    "gn:country_code":"KP",
    "gn:dem":40,
    "gn:feature_class":"P",
    "gn:feature_code":"PPL",
    "gn:name":"Unsal-li",
    "gn:population":0,
    "gn:timezone":"Asia/Pyongyang",
    "iso:country":"KP",
    "name:und_x_variant":[
        "Unsan-ni",
        "Unsal-li"
    ],
    "wof:name":"Unsal-li",
    "wof:placetype":"locality"
},
  "geometry": {"coordinates":[124.97583,38.37333],"type":"Point"}
}