{
  "type": "Feature",
  "properties": {
    "gn:admin1_code":"3.0",
    "gn:admin2_code":"K\u016dmya-gun",
    "gn:asciiname":"Hungam-ni",
    "gn:country_code":"KP",
    "gn:dem":2,
    "gn:feature_class":"P",
    "gn:feature_code":"PPL",
    "gn:name":"H\u016dngam-ni",
    "gn:population":0,
    "gn:timezone":"Asia/Pyongyang",
    "iso:country":"KP",
    "name:und_x_variant":[
        "H\u016dngam-ni",
        "\ud765\uc554\ub9ac"
    ],
    "wof:name":"Hungam-ni",
    "wof:placetype":"locality"
},
  "geometry": {"coordinates":[127.34166999999999,39.47389],"type":"Point"}
}