{
  "type": "Feature",
  "properties": {
    "gn:admin1_code":"9.0",
    "gn:asciiname":"Sanggumal-li",
    "gn:country_code":"KP",
    "gn:dem":473,
    "gn:feature_class":"P",
    "gn:feature_code":"PPL",
    "gn:name":"Sanggumal-li",
    "gn:population":0,
    "gn:timezone":"Asia/Pyongyang",
    "iso:country":"KP",
    "name:und_x_variant":[
        "\uc0c1\uad6c\ub9cc\ub9ac",
        "Sanggumal-li"
    ],
    "wof:name":"Sanggumal-li",
    "wof:placetype":"locality"
},
  "geometry": {"coordinates":[127.79000000000001,38.63333],"type":"Point"}
}