{
  "type": "Feature",
  "properties": {
    "gn:admin1_code":"12.0",
    "gn:asciiname":"Mangbawi",
    "gn:country_code":"KP",
    "gn:dem":32,
    "gn:feature_class":"P",
    "gn:feature_code":"PPL",
    "gn:name":"Mangbawi",
    "gn:population":0,
    "gn:timezone":"Asia/Pyongyang",
    "iso:country":"KP",
    "name:kor_x_preferred":[
        "\ub9dd\ubc14\uc704"
    ],
    "name:kor_x_variant":[
        "\ub9dd\ubc14\uc6b0"
    ],
    "name:und_x_variant":[
        "Mangam",
        "Mangbawi",
        "Mangbau"
    ],
    "wof:name":"Mangbawi",
    "wof:placetype":"locality"
},
  "geometry": {"coordinates":[125.86727999999999,38.93399],"type":"Point"}
}