{
  "type": "Feature",
  "properties": {
    "gn:admin1_code":"3.0",
    "gn:asciiname":"Yuhung-ni",
    "gn:country_code":"KP",
    "gn:dem":6,
    "gn:feature_class":"P",
    "gn:feature_code":"PPL",
    "gn:name":"Yuh\u016dng-ni",
    "gn:population":0,
    "gn:timezone":"Asia/Pyongyang",
    "iso:country":"KP",
    "name:und_x_variant":[
        "\uc720\ud765\ub9ac",
        "Yuh\u016dng-ni"
    ],
    "wof:name":"Yuhung-ni",
    "wof:placetype":"locality"
},
  "geometry": {"coordinates":[127.46083,39.63444000000001],"type":"Point"}
}