{
  "type": "Feature",
  "properties": {
    "gn:admin1_code":"6.0",
    "gn:asciiname":"Kangsok-tong",
    "gn:country_code":"KP",
    "gn:dem":64,
    "gn:feature_class":"P",
    "gn:feature_code":"PPL",
    "gn:name":"Kangs\u014fk-tong",
    "gn:population":0,
    "gn:timezone":"Asia/Pyongyang",
    "iso:country":"KP",
    "name:eng_x_preferred":[
        "Kangsok"
    ],
    "name:eng_x_variant":[
        "Kangsok-tong"
    ],
    "name:und_x_variant":[
        "\uac15\uc11d\ub3d9",
        "Kangs\u014fk-tong"
    ],
    "wof:name":"Kangsok",
    "wof:placetype":"locality"
},
  "geometry": {"coordinates":[125.23333,38.16694],"type":"Point"}
}