{
  "type": "Feature",
  "properties": {
    "gn:admin1_code":"0.0",
    "gn:asciiname":"Puwang-ni",
    "gn:country_code":"KP",
    "gn:dem":81,
    "gn:feature_class":"P",
    "gn:feature_code":"PPL",
    "gn:name":"Puwang-ni",
    "gn:population":0,
    "gn:timezone":"Asia/Pyongyang",
    "iso:country":"KP",
    "name:eng_x_preferred":[
        "Puwang"
    ],
    "name:eng_x_variant":[
        "Puwang-ni"
    ],
    "name:kor_x_preferred":[
        "\ubd80\uc655\ub9ac"
    ],
    "wof:name":"Puwang",
    "wof:placetype":"locality"
},
  "geometry": {"coordinates":[125.15000000000001,38.38333],"type":"Point"}
}