{
  "type": "Feature",
  "properties": {
    "gn:admin1_code":"6.0",
    "gn:asciiname":"Maok-tong",
    "gn:country_code":"KP",
    "gn:dem":75,
    "gn:feature_class":"P",
    "gn:feature_code":"PPL",
    "gn:name":"Maok-tong",
    "gn:population":0,
    "gn:timezone":"Asia/Pyongyang",
    "iso:country":"KP",
    "name:eng_x_preferred":[
        "Maok"
    ],
    "name:eng_x_variant":[
        "Maok-tong"
    ],
    "name:kor_x_preferred":[
        "\ub9c8\uc625\ub3d9"
    ],
    "wof:name":"Maok",
    "wof:placetype":"locality"
},
  "geometry": {"coordinates":[126.22778,38.18833],"type":"Point"}
}