{
  "type": "Feature",
  "properties": {
    "gn:admin1_code":"0.0",
    "gn:asciiname":"Sangp'yong",
    "gn:country_code":"KP",
    "gn:dem":6,
    "gn:feature_class":"P",
    "gn:feature_code":"PPL",
    "gn:name":"Sangp\u2019y\u014fng",
    "gn:population":0,
    "gn:timezone":"Asia/Pyongyang",
    "iso:country":"KP",
    "name:kor_x_preferred":[
        "\uc0c1\ud3c9"
    ],
    "name:und_x_variant":[
        "Sangp\u2019y\u014fng"
    ],
    "wof:name":"Sangp'yong",
    "wof:placetype":"locality"
},
  "geometry": {"coordinates":[127.34999999999999,39.28333],"type":"Point"}
}