{
  "type": "Feature",
  "properties": {
    "gn:admin1_code":"11.0",
    "gn:asciiname":"Wonsep'yong-ni",
    "gn:country_code":"KP",
    "gn:dem":66,
    "gn:feature_class":"P",
    "gn:feature_code":"PPL",
    "gn:name":"W\u014fnsep\u2019y\u014fng-ni",
    "gn:population":0,
    "gn:timezone":"Asia/Pyongyang",
    "iso:country":"KP",
    "name:eng_x_preferred":[
        "Wonsep'yong"
    ],
    "name:eng_x_variant":[
        "Wonsep'yong-ni"
    ],
    "name:und_x_variant":[
        "W\u014fnsep\u2019y\u014fng-dong",
        "\uc6d0\uc138\ud3c9\ub9ac",
        "W\u014fnsep\u2019y\u014fng-ni"
    ],
    "wof:name":"Wonsep'yong",
    "wof:placetype":"locality"
},
  "geometry": {"coordinates":[124.67889,39.7975],"type":"Point"}
}