{
  "type": "Feature",
  "properties": {
    "gn:admin1_code":"17.0",
    "gn:asciiname":"Taemal-ch'on",
    "gn:country_code":"KP",
    "gn:dem":194,
    "gn:feature_class":"P",
    "gn:feature_code":"PPL",
    "gn:name":"Taemal-ch\u2019on",
    "gn:population":0,
    "gn:timezone":"Asia/Pyongyang",
    "iso:country":"KP",
    "wof:name":"Taemal-ch'on",
    "wof:placetype":"locality"
},
  "geometry": {"coordinates":[129.61667,41.35],"type":"Point"}
}