{
  "type": "Feature",
  "properties": {
    "gn:admin1_code":"17.0",
    "gn:asciiname":"Hamyol-lodongjagu",
    "gn:country_code":"KP",
    "gn:dem":48,
    "gn:feature_class":"P",
    "gn:feature_code":"PPLL",
    "gn:name":"Hamy\u014fl-lodongjagu",
    "gn:population":0,
    "gn:timezone":"Asia/Pyongyang",
    "iso:country":"KP",
    "name:und_x_variant":[
        "Kamen-d\u014f",
        "Hamy\u014fn-dong",
        "Kamen",
        "Hamy\u014fn-ni",
        "Hamy\u014fn-nodongjagu",
        "\ud558\uba74\ub85c\ub3d9\uc790\uad6c",
        "Hamy\u014fl-lodongjagu"
    ],
    "wof:name":"Hamyol-lodongjagu",
    "wof:placetype":"locality"
},
  "geometry": {"coordinates":[130.19666999999998,42.85611],"type":"Point"}
}