{
  "type": "Feature",
  "properties": {
    "gn:admin1_code":"6.0",
    "gn:asciiname":"Kwangsok-tong",
    "gn:country_code":"KP",
    "gn:dem":184,
    "gn:feature_class":"P",
    "gn:feature_code":"PPL",
    "gn:name":"Kwangs\u014fk-tong",
    "gn:population":0,
    "gn:timezone":"Asia/Pyongyang",
    "iso:country":"KP",
    "wof:name":"Kwangsok-tong",
    "wof:placetype":"locality"
},
  "geometry": {"coordinates":[125.62888999999998,38.21139],"type":"Point"}
}