{
  "type": "Feature",
  "properties": {
    "gn:admin1_code":"0.0",
    "gn:asciiname":"Namyang-ni",
    "gn:country_code":"KP",
    "gn:dem":225,
    "gn:feature_class":"P",
    "gn:feature_code":"PPL",
    "gn:name":"Namyang-ni",
    "gn:population":0,
    "gn:timezone":"Asia/Pyongyang",
    "iso:country":"KP",
    "name:eng_x_preferred":[
        "Namyang"
    ],
    "name:eng_x_variant":[
        "Namyang-ni"
    ],
    "name:kor_x_preferred":[
        "\ub0a8\uc591\ub9ac"
    ],
    "wof:name":"Namyang",
    "wof:placetype":"locality"
},
  "geometry": {"coordinates":[126.41667,39.71667],"type":"Point"}
}