{
  "type": "Feature",
  "properties": {
    "gn:admin1_code":"9.0",
    "gn:admin2_code":"Sep\u2019o-gun",
    "gn:asciiname":"Sep'o-up",
    "gn:country_code":"KP",
    "gn:dem":562,
    "gn:feature_class":"P",
    "gn:feature_code":"PPL",
    "gn:name":"Sep\u2019o-\u016dp",
    "gn:population":0,
    "gn:timezone":"Asia/Pyongyang",
    "iso:country":"KP",
    "name:und_x_variant":[
        "Senpori",
        "Sep\u2019o",
        "Shenpo",
        "Sempo-ri",
        "Sep\u2019o-ri",
        "Sep\u2019o-\u016dp"
    ],
    "wof:name":"Sep'o-up",
    "wof:placetype":"locality"
},
  "geometry": {"coordinates":[127.35972,38.64139],"type":"Point"}
}