{
  "type": "Feature",
  "properties": {
    "gn:admin1_code":"11.0",
    "gn:asciiname":"Anyang-ni",
    "gn:country_code":"KP",
    "gn:dem":360,
    "gn:feature_class":"P",
    "gn:feature_code":"PPL",
    "gn:name":"Anyang-ni",
    "gn:population":0,
    "gn:timezone":"Asia/Pyongyang",
    "iso:country":"KP",
    "name:und_x_variant":[
        "\uc548\uc591\ub9ac",
        "Anyang-ni"
    ],
    "wof:name":"Anyang-ni",
    "wof:placetype":"locality"
},
  "geometry": {"coordinates":[125.5575,40.45611],"type":"Point"}
}