{
  "type": "Feature",
  "properties": {
    "gn:admin1_code":"6.0",
    "gn:asciiname":"Sangmik-kol",
    "gn:cc2":"KP",
    "gn:country_code":"KP",
    "gn:dem":201,
    "gn:feature_class":"P",
    "gn:feature_code":"PPL",
    "gn:name":"Sangmik-kol",
    "gn:population":0,
    "gn:timezone":"Asia/Pyongyang",
    "iso:country":"KP",
    "name:und_x_variant":[
        "Sangmi-gol",
        "Sangmik-kol"
    ],
    "wof:name":"Sangmik-kol",
    "wof:placetype":"locality"
},
  "geometry": {"coordinates":[125.66222,38.17111],"type":"Point"}
}