{
  "type": "Feature",
  "properties": {
    "gn:admin1_code":"11.0",
    "gn:asciiname":"Ch'ang-dong",
    "gn:country_code":"KP",
    "gn:dem":158,
    "gn:feature_class":"P",
    "gn:feature_code":"PPL",
    "gn:name":"Ch\u2019ang-dong",
    "gn:population":0,
    "gn:timezone":"Asia/Pyongyang",
    "iso:country":"KP",
    "name:und_x_variant":[
        "\ucc3d\ub3d9",
        "Ch\u2019ang-dong"
    ],
    "wof:name":"Ch'ang-dong",
    "wof:placetype":"locality"
},
  "geometry": {"coordinates":[125.82167,40.15222],"type":"Point"}
}