{
  "type": "Feature",
  "properties": {
    "gn:admin1_code":"9.0",
    "gn:asciiname":"Sangch'on",
    "gn:country_code":"KP",
    "gn:dem":176,
    "gn:feature_class":"P",
    "gn:feature_code":"PPL",
    "gn:name":"Sangch\u2019on",
    "gn:population":0,
    "gn:timezone":"Asia/Pyongyang",
    "iso:country":"KP",
    "wof:name":"Sangch'on",
    "wof:placetype":"locality"
},
  "geometry": {"coordinates":[127.01694000000001,38.32861],"type":"Point"}
}