{
  "type": "Feature",
  "properties": {
    "gn:admin1_code":"6.0",
    "gn:asciiname":"Suyok-tong",
    "gn:country_code":"KP",
    "gn:dem":10,
    "gn:feature_class":"P",
    "gn:feature_code":"PPL",
    "gn:name":"Suy\u014fk-tong",
    "gn:population":0,
    "gn:timezone":"Asia/Pyongyang",
    "iso:country":"KP",
    "name:kor_x_preferred":[
        "Suy\u014fk-tong"
    ],
    "name:kor_x_variant":[
        "\uc218\uc5ed\ub3d9",
        "Suy\u014fk",
        "\uc218\uc5ed"
    ],
    "wof:name":"Suyok-tong",
    "wof:placetype":"locality"
},
  "geometry": {"coordinates":[125.61083000000001,38.36833],"type":"Point"}
}