{
  "type": "Feature",
  "properties": {
    "gn:admin1_code":"15.0",
    "gn:admin2_code":"Sukch\u2019on-gun",
    "gn:asciiname":"Yakchol-li",
    "gn:country_code":"KP",
    "gn:dem":15,
    "gn:feature_class":"P",
    "gn:feature_code":"PPL",
    "gn:name":"Yakch\u014fl-li",
    "gn:population":0,
    "gn:timezone":"Asia/Pyongyang",
    "iso:country":"KP",
    "name:kor_x_preferred":[
        "Yakch\u014fl-li"
    ],
    "name:und_x_variant":[
        "Yakch\u014fn-ni"
    ],
    "wof:name":"Yakchol-li",
    "wof:placetype":"locality"
},
  "geometry": {"coordinates":[125.49972,39.33167],"type":"Point"}
}