{
  "type": "Feature",
  "properties": {
    "gn:admin1_code":"11.0",
    "gn:asciiname":"Naeoktongsambong-ni",
    "gn:country_code":"KP",
    "gn:dem":103,
    "gn:feature_class":"P",
    "gn:feature_code":"PPL",
    "gn:name":"Naeoktongsambong-ni",
    "gn:population":0,
    "gn:timezone":"Asia/Pyongyang",
    "iso:country":"KP",
    "name:und_x_variant":[
        "\ub0b4\uc625\ub3d9\uc0bc\ubd09\ub9ac",
        "Naeoktongsambong-ni"
    ],
    "wof:name":"Naeoktongsambong-ni",
    "wof:placetype":"locality"
},
  "geometry": {"coordinates":[124.79389,40.26222],"type":"Point"}
}