{
  "type": "Feature",
  "properties": {
    "gn:admin1_code":"17.0",
    "gn:asciiname":"Ch'anggok",
    "gn:country_code":"KP",
    "gn:dem":121,
    "gn:feature_class":"P",
    "gn:feature_code":"PPL",
    "gn:name":"Ch\u2019anggok",
    "gn:population":0,
    "gn:timezone":"Asia/Pyongyang",
    "iso:country":"KP",
    "name:und_x_variant":[
        "\ucc3d\uace1",
        "Ch\u2019anggok"
    ],
    "wof:name":"Ch'anggok",
    "wof:placetype":"locality"
},
  "geometry": {"coordinates":[130.28306000000001,42.53278],"type":"Point"}
}