{
  "type": "Feature",
  "properties": {
    "gn:admin1_code":"15.0",
    "gn:asciiname":"Hagung-ni",
    "gn:country_code":"KP",
    "gn:dem":330,
    "gn:feature_class":"P",
    "gn:feature_code":"PPL",
    "gn:name":"Hagung-ni",
    "gn:population":0,
    "gn:timezone":"Asia/Pyongyang",
    "iso:country":"KP",
    "name:und_x_variant":[
        "\ud558\uad6d\ub9ac",
        "Hagung-ni"
    ],
    "wof:name":"Hagung-ni",
    "wof:placetype":"locality"
},
  "geometry": {"coordinates":[126.78667,39.18583],"type":"Point"}
}