{
  "type": "Feature",
  "properties": {
    "gn:admin1_code":"1.0",
    "gn:asciiname":"Sodang-gol",
    "gn:country_code":"KP",
    "gn:dem":225,
    "gn:feature_class":"P",
    "gn:feature_code":"PPL",
    "gn:name":"S\u014fdang-gol",
    "gn:population":0,
    "gn:timezone":"Asia/Pyongyang",
    "iso:country":"KP",
    "name:und_x_variant":[
        "S\u014fdang-dong",
        "\uc11c\ub2f9\uace8",
        "S\u014fdang-gol"
    ],
    "wof:name":"Sodang-gol",
    "wof:placetype":"locality"
},
  "geometry": {"coordinates":[126.16139,40.99667],"type":"Point"}
}