{
  "type": "Feature",
  "properties": {
    "gn:admin1_code":"6.0",
    "gn:asciiname":"Tolmoru",
    "gn:cc2":"KP",
    "gn:country_code":"KP",
    "gn:dem":131,
    "gn:feature_class":"P",
    "gn:feature_code":"PPL",
    "gn:name":"Tolmoru",
    "gn:population":0,
    "gn:timezone":"Asia/Pyongyang",
    "iso:country":"KP",
    "name:und_x_variant":[
        "Tolmol",
        "Tolmoru"
    ],
    "wof:name":"Tolmoru",
    "wof:placetype":"locality"
},
  "geometry": {"coordinates":[125.96111000000001,38.12694000000001],"type":"Point"}
}