{
  "type": "Feature",
  "properties": {
    "gn:admin1_code":"7.0",
    "gn:asciiname":"Komul-li",
    "gn:country_code":"KP",
    "gn:dem":109,
    "gn:feature_class":"P",
    "gn:feature_code":"PPL",
    "gn:name":"K\u014fmul-li",
    "gn:population":0,
    "gn:timezone":"Asia/Pyongyang",
    "iso:country":"KP",
    "name:und_x_variant":[
        "K\u014fmun-ni",
        "\uac70\ubb38\ub9ac",
        "K\u014fmul-li"
    ],
    "wof:name":"Komul-li",
    "wof:placetype":"locality"
},
  "geometry": {"coordinates":[126.2325,38.4425],"type":"Point"}
}