{
  "type": "Feature",
  "properties": {
    "gn:admin1_code":"11.0",
    "gn:asciiname":"Karodongwonbaengma-dong",
    "gn:country_code":"KP",
    "gn:dem":70,
    "gn:feature_class":"P",
    "gn:feature_code":"PPL",
    "gn:name":"Karodongw\u014fnbaengma-dong",
    "gn:population":0,
    "gn:timezone":"Asia/Pyongyang",
    "iso:country":"KP",
    "name:und_x_variant":[
        "\uac00\ub85c\ub3d9\uc6d0\ubc31\ub9c8\ub3d9",
        "Karodongw\u014fnbaengma-dong"
    ],
    "wof:name":"Karodongwonbaengma-dong",
    "wof:placetype":"locality"
},
  "geometry": {"coordinates":[124.5825,40.11889],"type":"Point"}
}