{
  "type": "Feature",
  "properties": {
    "gn:admin1_code":"7.0",
    "gn:asciiname":"Pyolp'o-dong",
    "gn:country_code":"KP",
    "gn:dem":8,
    "gn:feature_class":"P",
    "gn:feature_code":"PPL",
    "gn:name":"Py\u014flp\u2019o-dong",
    "gn:population":0,
    "gn:timezone":"Asia/Pyongyang",
    "iso:country":"KP",
    "name:kor_x_preferred":[
        "\ubcc4\ud3ec\ub3d9"
    ],
    "name:kor_x_variant":[
        "Py\u014flp\u2019o-dong"
    ],
    "wof:name":"Pyolp'o-dong",
    "wof:placetype":"locality"
},
  "geometry": {"coordinates":[125.54971999999999,38.54361],"type":"Point"}
}