{
  "type": "Feature",
  "properties": {
    "gn:admin1_code":"0.0",
    "gn:asciiname":"Koal-li",
    "gn:country_code":"KP",
    "gn:dem":428,
    "gn:feature_class":"P",
    "gn:feature_code":"PPL",
    "gn:name":"Koal-li",
    "gn:population":0,
    "gn:timezone":"Asia/Pyongyang",
    "iso:country":"KP",
    "name:kor_x_preferred":[
        "\uace0\uc548\ub9ac"
    ],
    "name:und_x_variant":[
        "Koan-ni"
    ],
    "wof:name":"Koal-li",
    "wof:placetype":"locality"
},
  "geometry": {"coordinates":[125.58333,40.63333],"type":"Point"}
}