{
  "type": "Feature",
  "properties": {
    "gn:admin1_code":"3.0",
    "gn:asciiname":"Musang-dong",
    "gn:country_code":"KP",
    "gn:dem":103,
    "gn:feature_class":"P",
    "gn:feature_code":"PPL",
    "gn:name":"Musang-dong",
    "gn:population":0,
    "gn:timezone":"Asia/Pyongyang",
    "iso:country":"KP",
    "name:und_x_variant":[
        "\ubb34\uc0c1\ub3d9",
        "Musang-dong"
    ],
    "wof:name":"Musang-dong",
    "wof:placetype":"locality"
},
  "geometry": {"coordinates":[127.37972000000001,39.93111],"type":"Point"}
}