{
  "type": "Feature",
  "properties": {
    "gn:admin1_code":"15.0",
    "gn:asciiname":"Sunhu",
    "gn:country_code":"KP",
    "gn:dem":35,
    "gn:feature_class":"P",
    "gn:feature_code":"PPL",
    "gn:name":"Sunhu",
    "gn:population":0,
    "gn:timezone":"Asia/Pyongyang",
    "iso:country":"KP",
    "name:mai_x_preferred":[
        "\u0938\u0941\u0901"
    ],
    "name:msa_x_preferred":[
        "Sunhoo"
    ],
    "name:nep_x_preferred":[
        "\u0938\u0941\u0901"
    ],
    "name:pol_x_preferred":[
        "Sunhoo"
    ],
    "wof:name":"Sunhu",
    "wof:placetype":"locality"
},
  "geometry": {"coordinates":[125.33222000000001,39.03972],"type":"Point"}
}