{
  "type": "Feature",
  "properties": {
    "gn:admin1_code":"9.0",
    "gn:asciiname":"Sep'o-ri",
    "gn:country_code":"KP",
    "gn:dem":200,
    "gn:feature_class":"P",
    "gn:feature_code":"PPL",
    "gn:name":"Sep\u2019o-ri",
    "gn:population":0,
    "gn:timezone":"Asia/Pyongyang",
    "iso:country":"KP",
    "name:kor_x_preferred":[
        "\uc138\ud3ec\ub9ac"
    ],
    "name:kor_x_variant":[
        "Sep\u2019o-ri"
    ],
    "name:und_x_variant":[
        "Saiho-ri",
        "Shink\u014dsan",
        "Sin\u2019gosan"
    ],
    "wof:name":"Sep'o-ri",
    "wof:placetype":"locality"
},
  "geometry": {"coordinates":[127.4225,38.86417],"type":"Point"}
}