{
  "type": "Feature",
  "properties": {
    "gn:admin1_code":"17.0",
    "gn:asciiname":"Sujong-dong",
    "gn:country_code":"KP",
    "gn:dem":55,
    "gn:feature_class":"P",
    "gn:feature_code":"PPL",
    "gn:name":"Suj\u014fng-dong",
    "gn:population":0,
    "gn:timezone":"Asia/Pyongyang",
    "iso:country":"KP",
    "name:und_x_variant":[
        "\uc218\uc815\ub3d9",
        "Suj\u014fng-dong"
    ],
    "wof:name":"Sujong-dong",
    "wof:placetype":"locality"
},
  "geometry": {"coordinates":[130.26027999999999,42.655],"type":"Point"}
}