{
  "type": "Feature",
  "properties": {
    "gn:admin1_code":"12.0",
    "gn:asciiname":"Sahoegol",
    "gn:country_code":"KP",
    "gn:dem":55,
    "gn:feature_class":"P",
    "gn:feature_code":"PPL",
    "gn:name":"Sahoegol",
    "gn:population":0,
    "gn:timezone":"Asia/Pyongyang",
    "iso:country":"KP",
    "name:kor_x_preferred":[
        "\uc0ac\ud68c\uace8"
    ],
    "name:und_x_variant":[
        "Sahoekol",
        "Sahoegol"
    ],
    "wof:name":"Sahoegol",
    "wof:placetype":"locality"
},
  "geometry": {"coordinates":[125.86516,39.19379],"type":"Point"}
}