{
  "type": "Feature",
  "properties": {
    "gn:admin1_code":"17.0",
    "gn:asciiname":"Hwangbyondok",
    "gn:country_code":"KP",
    "gn:dem":229,
    "gn:feature_class":"P",
    "gn:feature_code":"PPL",
    "gn:name":"Hwangby\u014fnd\u014fk",
    "gn:population":0,
    "gn:timezone":"Asia/Pyongyang",
    "iso:country":"KP",
    "name:und_x_variant":[
        "\ud669\ubcc0\ub355",
        "Hwangby\u014fnd\u014fk"
    ],
    "wof:name":"Hwangbyondok",
    "wof:placetype":"locality"
},
  "geometry": {"coordinates":[129.63611,40.91417],"type":"Point"}
}