{
  "type": "Feature",
  "properties": {
    "gn:admin1_code":"11.0",
    "gn:asciiname":"Soso-ri",
    "gn:country_code":"KP",
    "gn:dem":88,
    "gn:feature_class":"P",
    "gn:feature_code":"PPL",
    "gn:name":"S\u014fso-ri",
    "gn:population":0,
    "gn:timezone":"Asia/Pyongyang",
    "iso:country":"KP",
    "name:kor_x_preferred":[
        "\uc11c\uc18c\ub9ac"
    ],
    "name:kor_x_variant":[
        "S\u014fso-ri"
    ],
    "wof:name":"Soso-ri",
    "wof:placetype":"locality"
},
  "geometry": {"coordinates":[125.32222,39.66472],"type":"Point"}
}