{
  "type": "Feature",
  "properties": {
    "gn:admin1_code":"13.0",
    "gn:asciiname":"Kwaesallyong-gol",
    "gn:country_code":"KP",
    "gn:dem":1099,
    "gn:feature_class":"P",
    "gn:feature_code":"PPL",
    "gn:name":"Kwaesally\u014fng-gol",
    "gn:population":0,
    "gn:timezone":"Asia/Pyongyang",
    "iso:country":"KP",
    "wof:name":"Kwaesallyong-gol",
    "wof:placetype":"locality"
},
  "geometry": {"coordinates":[128.54056,41.05722],"type":"Point"}
}