{
  "type": "Feature",
  "properties": {
    "gn:admin1_code":"9.0",
    "gn:asciiname":"Sinanjung-ni",
    "gn:country_code":"KP",
    "gn:dem":387,
    "gn:feature_class":"P",
    "gn:feature_code":"PPL",
    "gn:name":"Sinanjung-ni",
    "gn:population":0,
    "gn:timezone":"Asia/Pyongyang",
    "iso:country":"KP",
    "name:und_x_variant":[
        "An-An",
        "Shin-Sin",
        "Ch\u016b-Chung",
        "Sinanjung-ri",
        "Shin-an",
        "Shinanch\u016b-ri",
        "Shinanch\u016b",
        "\uc2e0\uc548\uc911\ub9ac",
        "Sinanjung-ni"
    ],
    "wof:name":"Sinanjung-ni",
    "wof:placetype":"locality"
},
  "geometry": {"coordinates":[127.71472,38.64111],"type":"Point"}
}