{
  "type": "Feature",
  "properties": {
    "gn:admin1_code":"17.0",
    "gn:asciiname":"Sangch'on",
    "gn:country_code":"KP",
    "gn:dem":155,
    "gn:feature_class":"P",
    "gn:feature_code":"PPL",
    "gn:name":"Sangch\u2019on",
    "gn:population":0,
    "gn:timezone":"Asia/Pyongyang",
    "iso:country":"KP",
    "name:und_x_variant":[
        "\uc0c1\ucd0c",
        "Sangch\u2019on"
    ],
    "wof:name":"Sangch'on",
    "wof:placetype":"locality"
},
  "geometry": {"coordinates":[130.32138999999998,42.5625],"type":"Point"}
}