{
  "type": "Feature",
  "properties": {
    "gn:admin1_code":"0.0",
    "gn:asciiname":"Majangch'am",
    "gn:country_code":"KP",
    "gn:dem":316,
    "gn:feature_class":"P",
    "gn:feature_code":"PPL",
    "gn:name":"Majangch\u2019am",
    "gn:population":0,
    "gn:timezone":"Asia/Pyongyang",
    "iso:country":"KP",
    "name:kor_x_preferred":[
        "\ub9c8\uc7a5\ucc38"
    ],
    "name:und_x_variant":[
        "Majangch\u2019am"
    ],
    "wof:name":"Majangch'am",
    "wof:placetype":"locality"
},
  "geometry": {"coordinates":[125.59999999999999,40.25],"type":"Point"}
}