{
  "type": "Feature",
  "properties": {
    "gn:admin1_code":"17.0",
    "gn:asciiname":"Hwangyong-dong",
    "gn:country_code":"KP",
    "gn:dem":558,
    "gn:feature_class":"P",
    "gn:feature_code":"PPL",
    "gn:name":"Hwangyong-dong",
    "gn:population":0,
    "gn:timezone":"Asia/Pyongyang",
    "iso:country":"KP",
    "wof:name":"Hwangyong-dong",
    "wof:placetype":"locality"
},
  "geometry": {"coordinates":[129.98333,42.36667],"type":"Point"}
}