{
  "type": "Feature",
  "properties": {
    "gn:admin1_code":"12.0",
    "gn:admin2_code":"Sangw\u014fn-gun",
    "gn:asciiname":"Kosari-gol",
    "gn:cc2":"KP",
    "gn:country_code":"KP",
    "gn:dem":134,
    "gn:feature_class":"P",
    "gn:feature_code":"PPL",
    "gn:name":"Kosari-gol",
    "gn:population":0,
    "gn:timezone":"Asia/Pyongyang",
    "iso:country":"KP",
    "name:und_x_variant":[
        "Kosari-kol",
        "Kosari-gol"
    ],
    "wof:name":"Kosari-gol",
    "wof:placetype":"locality"
},
  "geometry": {"coordinates":[126.12555999999999,38.80139000000001],"type":"Point"}
}