{
  "type": "Feature",
  "properties": {
    "gn:admin1_code":"11.0",
    "gn:asciiname":"Mipa-dong",
    "gn:country_code":"KP",
    "gn:dem":35,
    "gn:feature_class":"P",
    "gn:feature_code":"PPL",
    "gn:name":"Mipa-dong",
    "gn:population":0,
    "gn:timezone":"Asia/Pyongyang",
    "iso:country":"KP",
    "name:kor_x_preferred":[
        "\ubbf8\ud30c\ub3d9"
    ],
    "wof:name":"Mipa-dong",
    "wof:placetype":"locality"
},
  "geometry": {"coordinates":[125.35527999999999,39.64583],"type":"Point"}
}