{
  "type": "Feature",
  "properties": {
    "gn:admin1_code":"6.0",
    "gn:asciiname":"Kop'o-ri",
    "gn:country_code":"KP",
    "gn:dem":115,
    "gn:feature_class":"P",
    "gn:feature_code":"PPL",
    "gn:name":"Kop\u2019o-ri",
    "gn:population":0,
    "gn:timezone":"Asia/Pyongyang",
    "iso:country":"KP",
    "name:kor_x_preferred":[
        "\uace0\ud3ec\ub9ac"
    ],
    "name:und_x_variant":[
        "Kop\u2019o-ri"
    ],
    "wof:name":"Kop'o-ri",
    "wof:placetype":"locality"
},
  "geometry": {"coordinates":[126.1125,38.03],"type":"Point"}
}