{
  "type": "Feature",
  "properties": {
    "gn:admin1_code":"7.0",
    "gn:asciiname":"Yongjong-dong",
    "gn:country_code":"KP",
    "gn:dem":20,
    "gn:feature_class":"P",
    "gn:feature_code":"PPL",
    "gn:name":"Yongj\u014fng-dong",
    "gn:population":0,
    "gn:timezone":"Asia/Pyongyang",
    "iso:country":"KP",
    "name:kor_x_preferred":[
        "\uc6a9\uc815\ub3d9"
    ],
    "name:kor_x_variant":[
        "Yongj\u014fng-dong"
    ],
    "wof:name":"Yongjong-dong",
    "wof:placetype":"locality"
},
  "geometry": {"coordinates":[125.52861,38.53861],"type":"Point"}
}