{
  "type": "Feature",
  "properties": {
    "gn:admin1_code":"11.0",
    "gn:asciiname":"Tongju-ri",
    "gn:country_code":"KP",
    "gn:dem":176,
    "gn:feature_class":"P",
    "gn:feature_code":"PPL",
    "gn:name":"Tongju-ri",
    "gn:population":0,
    "gn:timezone":"Asia/Pyongyang",
    "iso:country":"KP",
    "name:und_x_variant":[
        "Hekid\u014d",
        "Pyokuton",
        "Py\u014fktong",
        "\ub3d9\uc8fc\ub9ac",
        "Tongju-ri"
    ],
    "wof:name":"Tongju-ri",
    "wof:placetype":"locality"
},
  "geometry": {"coordinates":[125.435,40.62417],"type":"Point"}
}