{
  "type": "Feature",
  "properties": {
    "gn:admin1_code":"9.0",
    "gn:asciiname":"Changdong-ni",
    "gn:country_code":"KP",
    "gn:dem":475,
    "gn:feature_class":"P",
    "gn:feature_code":"PPL",
    "gn:name":"Changd\u014fng-ni",
    "gn:population":0,
    "gn:timezone":"Asia/Pyongyang",
    "iso:country":"KP",
    "name:eng_x_preferred":[
        "Changdong"
    ],
    "name:eng_x_variant":[
        "Changdong-ni"
    ],
    "wof:name":"Changdong",
    "wof:placetype":"locality"
},
  "geometry": {"coordinates":[127.46778,38.51667],"type":"Point"}
}