{
  "type": "Feature",
  "properties": {
    "gn:admin1_code":"3.0",
    "gn:asciiname":"Ant'o",
    "gn:country_code":"KP",
    "gn:dem":28,
    "gn:feature_class":"P",
    "gn:feature_code":"PPL",
    "gn:name":"Ant\u2019\u014f",
    "gn:population":0,
    "gn:timezone":"Asia/Pyongyang",
    "iso:country":"KP",
    "name:und_x_variant":[
        "\uc548\ud130",
        "Ant\u2019\u014f"
    ],
    "wof:name":"Ant'o",
    "wof:placetype":"locality"
},
  "geometry": {"coordinates":[127.47499999999999,39.60167],"type":"Point"}
}