{
  "type": "Feature",
  "properties": {
    "gn:admin1_code":"18.0",
    "gn:admin2_code":"Najins\u014fnbong-si",
    "gn:asciiname":"Pip'ahang",
    "gn:country_code":"KP",
    "gn:dem":9,
    "gn:feature_class":"P",
    "gn:feature_code":"PPL",
    "gn:name":"Pip\u2019ahang",
    "gn:population":0,
    "gn:timezone":"Asia/Pyongyang",
    "iso:country":"KP",
    "name:und_x_variant":[
        "\ube44\ud30c\ud56d",
        "Pip\u2019ahang",
        "Bipahang"
    ],
    "wof:name":"Pip'ahang",
    "wof:placetype":"locality"
},
  "geometry": {"coordinates":[130.39528000000001,42.30639],"type":"Point"}
}