{
  "type": "Feature",
  "properties": {
    "gn:admin1_code":"3.0",
    "gn:asciiname":"Yurimjang",
    "gn:country_code":"KP",
    "gn:dem":32,
    "gn:feature_class":"P",
    "gn:feature_code":"PPL",
    "gn:name":"Yurimjang",
    "gn:population":0,
    "gn:timezone":"Asia/Pyongyang",
    "iso:country":"KP",
    "name:und_x_variant":[
        "\uc720\ub9bc\uc7a5",
        "Yurimjang"
    ],
    "wof:name":"Yurimjang",
    "wof:placetype":"locality"
},
  "geometry": {"coordinates":[128.90388999999999,40.4725],"type":"Point"}
}