{
  "type": "Feature",
  "properties": {
    "gn:admin1_code":"6.0",
    "gn:asciiname":"Tongnyong-gol",
    "gn:country_code":"KP",
    "gn:dem":14,
    "gn:feature_class":"P",
    "gn:feature_code":"PPL",
    "gn:name":"Tongny\u014fng-gol",
    "gn:population":0,
    "gn:timezone":"Asia/Pyongyang",
    "iso:country":"KP",
    "name:und_x_variant":[
        "Tongny\u014fng-dong",
        "\ub3d9\ub839\uace8",
        "Tongny\u014fng-gol"
    ],
    "wof:name":"Tongnyong-gol",
    "wof:placetype":"locality"
},
  "geometry": {"coordinates":[125.53111,37.785],"type":"Point"}
}