{
  "type": "Feature",
  "properties": {
    "gn:admin1_code":"3.0",
    "gn:asciiname":"Changdok",
    "gn:country_code":"KP",
    "gn:dem":1389,
    "gn:feature_class":"P",
    "gn:feature_code":"PPL",
    "gn:name":"Changd\u014fk",
    "gn:population":0,
    "gn:timezone":"Asia/Pyongyang",
    "iso:country":"KP",
    "name:und_x_variant":[
        "\uc7a5\ub355",
        "Changd\u014fk"
    ],
    "wof:name":"Changdok",
    "wof:placetype":"locality"
},
  "geometry": {"coordinates":[128.46528000000001,40.85889],"type":"Point"}
}