{
  "type": "Feature",
  "properties": {
    "gn:admin1_code":"15.0",
    "gn:asciiname":"Ssangsil",
    "gn:country_code":"KP",
    "gn:dem":356,
    "gn:feature_class":"P",
    "gn:feature_code":"PPL",
    "gn:name":"Ssangsil",
    "gn:population":0,
    "gn:timezone":"Asia/Pyongyang",
    "iso:country":"KP",
    "name:und_x_variant":[
        "\uc30d\uc2e4",
        "Ssangsil"
    ],
    "wof:name":"Ssangsil",
    "wof:placetype":"locality"
},
  "geometry": {"coordinates":[126.60611000000002,39.3525],"type":"Point"}
}