{
  "type": "Feature",
  "properties": {
    "gn:admin1_code":"7.0",
    "gn:asciiname":"Kokp'o",
    "gn:country_code":"KP",
    "gn:dem":5,
    "gn:feature_class":"P",
    "gn:feature_code":"PPL",
    "gn:name":"Kokp\u2019o",
    "gn:population":0,
    "gn:timezone":"Asia/Pyongyang",
    "iso:country":"KP",
    "wof:name":"Kokp'o",
    "wof:placetype":"locality"
},
  "geometry": {"coordinates":[125.70278,38.5125],"type":"Point"}
}