{
  "type": "Feature",
  "properties": {
    "gn:admin1_code":"3.0",
    "gn:asciiname":"Ch'ail-lodongjagu",
    "gn:country_code":"KP",
    "gn:dem":1349,
    "gn:feature_class":"P",
    "gn:feature_code":"PPL",
    "gn:name":"Ch\u2019ail-lodongjagu",
    "gn:population":0,
    "gn:timezone":"Asia/Pyongyang",
    "iso:country":"KP",
    "name:kor_x_preferred":[
        "\ucc28\uc77c\ub85c\ub3d9\uc790\uad6c"
    ],
    "name:kor_x_variant":[
        "Ch\u2019ail-lodongjagu"
    ],
    "name:und_x_variant":[
        "Ch\u2019ail-li"
    ],
    "wof:name":"Ch'ail-lodongjagu",
    "wof:placetype":"locality"
},
  "geometry": {"coordinates":[127.65278000000001,40.59861],"type":"Point"}
}