{
  "type": "Feature",
  "properties": {
    "gn:admin1_code":"9.0",
    "gn:asciiname":"Hajinp'yong-ni",
    "gn:country_code":"KP",
    "gn:dem":379,
    "gn:feature_class":"P",
    "gn:feature_code":"PPL",
    "gn:name":"Hajinp\u2019y\u014fng-ni",
    "gn:population":0,
    "gn:timezone":"Asia/Pyongyang",
    "iso:country":"KP",
    "name:und_x_variant":[
        "\ud558\uc9c4\ud3c9\ub9ac",
        "Hajinp\u2019y\u014fng-ni"
    ],
    "wof:name":"Hajinp'yong-ni",
    "wof:placetype":"locality"
},
  "geometry": {"coordinates":[127.60111000000001,38.73194],"type":"Point"}
}