{
  "type": "Feature",
  "properties": {
    "gn:admin1_code":"13.0",
    "gn:asciiname":"T'ongnam-gol",
    "gn:country_code":"KP",
    "gn:dem":898,
    "gn:feature_class":"P",
    "gn:feature_code":"PPL",
    "gn:name":"T\u2019ongnam-gol",
    "gn:population":0,
    "gn:timezone":"Asia/Pyongyang",
    "iso:country":"KP",
    "name:kor_x_preferred":[
        "\ud1b5\ub0a8\uace8"
    ],
    "name:und_x_variant":[
        "T\u2019ongnam-kol",
        "T\u2019ongnam-gol"
    ],
    "wof:name":"T'ongnam-gol",
    "wof:placetype":"locality"
},
  "geometry": {"coordinates":[128.28583,41.02306],"type":"Point"}
}