{
  "type": "Feature",
  "properties": {
    "gn:admin1_code":"17.0",
    "gn:asciiname":"Simun-dong",
    "gn:cc2":"KP",
    "gn:country_code":"KP",
    "gn:dem":27,
    "gn:feature_class":"P",
    "gn:feature_code":"PPL",
    "gn:name":"Simun-dong",
    "gn:population":0,
    "gn:timezone":"Asia/Pyongyang",
    "iso:country":"KP",
    "name:und_x_variant":[
        "Chaemun-dong",
        "\uc2dc\ubb38\ub3d9",
        "Simun-dong"
    ],
    "wof:name":"Simun-dong",
    "wof:placetype":"locality"
},
  "geometry": {"coordinates":[129.61972,41.44528],"type":"Point"}
}