{
  "type": "Feature",
  "properties": {
    "gn:admin1_code":"1.0",
    "gn:asciiname":"Imyong-dong",
    "gn:country_code":"KP",
    "gn:dem":448,
    "gn:feature_class":"P",
    "gn:feature_code":"PPL",
    "gn:name":"Imy\u014fng-dong",
    "gn:population":0,
    "gn:timezone":"Asia/Pyongyang",
    "iso:country":"KP",
    "name:und_x_variant":[
        "\uc774\uba85\ub3d9",
        "Imy\u014fng-dong"
    ],
    "wof:name":"Imyong-dong",
    "wof:placetype":"locality"
},
  "geometry": {"coordinates":[126.46361,40.30056],"type":"Point"}
}