{
  "type": "Feature",
  "properties": {
    "gn:admin1_code":"1.0",
    "gn:asciiname":"Kyoch'am",
    "gn:country_code":"KP",
    "gn:dem":201,
    "gn:feature_class":"P",
    "gn:feature_code":"PPL",
    "gn:name":"Kyoch\u2019am",
    "gn:population":0,
    "gn:timezone":"Asia/Pyongyang",
    "iso:country":"KP",
    "name:und_x_variant":[
        "\uad50\ucc38",
        "Kyoch\u2019am"
    ],
    "wof:name":"Kyoch'am",
    "wof:placetype":"locality"
},
  "geometry": {"coordinates":[126.36667,40.2075],"type":"Point"}
}