{
  "type": "Feature",
  "properties": {
    "gn:admin1_code":"11.0",
    "gn:asciiname":"Talsal-li",
    "gn:country_code":"KP",
    "gn:dem":262,
    "gn:feature_class":"P",
    "gn:feature_code":"PPL",
    "gn:name":"Talsal-li",
    "gn:population":0,
    "gn:timezone":"Asia/Pyongyang",
    "iso:country":"KP",
    "name:und_x_variant":[
        "Talsan-dong",
        "\ub2ec\uc0b0\ub9ac",
        "Talsan-ni",
        "Talsal-li"
    ],
    "wof:name":"Talsal-li",
    "wof:placetype":"locality"
},
  "geometry": {"coordinates":[125.26111000000002,40.42806],"type":"Point"}
}