{
  "type": "Feature",
  "properties": {
    "gn:admin1_code":"17.0",
    "gn:asciiname":"Kyohyang-ni",
    "gn:country_code":"KP",
    "gn:dem":120,
    "gn:feature_class":"P",
    "gn:feature_code":"PPL",
    "gn:name":"Kyohyang-ni",
    "gn:population":0,
    "gn:timezone":"Asia/Pyongyang",
    "iso:country":"KP",
    "name:und_x_variant":[
        "Kyohang-ni",
        "Kyohang-dong",
        "\uad50\ud5a5\ub9ac",
        "Kyohyang-ni"
    ],
    "wof:name":"Kyohyang-ni",
    "wof:placetype":"locality"
},
  "geometry": {"coordinates":[129.56111000000001,40.89556],"type":"Point"}
}