{
  "type": "Feature",
  "properties": {
    "gn:admin1_code":"1.0",
    "gn:asciiname":"Sangmuch'ae-ri",
    "gn:country_code":"KP",
    "gn:dem":649,
    "gn:feature_class":"P",
    "gn:feature_code":"PPL",
    "gn:name":"Sangmuch\u2019ae-ri",
    "gn:population":0,
    "gn:timezone":"Asia/Pyongyang",
    "iso:country":"KP",
    "name:und_x_variant":[
        "Sangmuch\u2019ae-ri",
        "\uc0c1\ubb34\ucc44\ub9ac"
    ],
    "wof:name":"Sangmuch'ae-ri",
    "wof:placetype":"locality"
},
  "geometry": {"coordinates":[126.45538999999999,40.87638],"type":"Point"}
}