{
  "type": "Feature",
  "properties": {
    "gn:admin1_code":"6.0",
    "gn:admin2_code":"Changp\u2019ung-gun",
    "gn:asciiname":"Sokch'ol-li",
    "gn:country_code":"KP",
    "gn:dem":141,
    "gn:feature_class":"P",
    "gn:feature_code":"PPL",
    "gn:name":"S\u014fkch\u2019ol-li",
    "gn:population":0,
    "gn:timezone":"Asia/Pyongyang",
    "iso:country":"KP",
    "name:und_x_variant":[
        "S\u014fkch\u2019on-ni",
        "S\u014fkch\u2019ol-li"
    ],
    "wof:name":"Sokch'ol-li",
    "wof:placetype":"locality"
},
  "geometry": {"coordinates":[126.67917,38.1725],"type":"Point"}
}