{
  "type": "Feature",
  "properties": {
    "gn:admin1_code":"9.0",
    "gn:asciiname":"Hama-dong",
    "gn:country_code":"KP",
    "gn:dem":148,
    "gn:feature_class":"P",
    "gn:feature_code":"PPL",
    "gn:name":"Hama-dong",
    "gn:population":0,
    "gn:timezone":"Asia/Pyongyang",
    "iso:country":"KP",
    "name:kor_x_preferred":[
        "\ud558\ub9c8\ub3d9"
    ],
    "wof:name":"Hama-dong",
    "wof:placetype":"locality"
},
  "geometry": {"coordinates":[126.91194,38.24639000000001],"type":"Point"}
}