{
  "type": "Feature",
  "properties": {
    "gn:admin1_code":"17.0",
    "gn:asciiname":"Pukkan-dong",
    "gn:country_code":"KP",
    "gn:dem":209,
    "gn:feature_class":"P",
    "gn:feature_code":"PPL",
    "gn:name":"Pukkan-dong",
    "gn:population":0,
    "gn:timezone":"Asia/Pyongyang",
    "iso:country":"KP",
    "name:und_x_variant":[
        "Pukkangok",
        "Pukkan-dong"
    ],
    "wof:name":"Pukkan-dong",
    "wof:placetype":"locality"
},
  "geometry": {"coordinates":[129.50361000000001,40.8975],"type":"Point"}
}