{
  "type": "Feature",
  "properties": {
    "gn:admin1_code":"7.0",
    "gn:asciiname":"P'ilt'an",
    "gn:country_code":"KP",
    "gn:dem":108,
    "gn:feature_class":"P",
    "gn:feature_code":"PPL",
    "gn:name":"P\u2019ilt\u2019an",
    "gn:population":0,
    "gn:timezone":"Asia/Pyongyang",
    "iso:country":"KP",
    "wof:name":"P'ilt'an",
    "wof:placetype":"locality"
},
  "geometry": {"coordinates":[126.14972,38.67833],"type":"Point"}
}