{
  "type": "Feature",
  "properties": {
    "gn:admin1_code":"13.0",
    "gn:asciiname":"Hwangt'oam",
    "gn:country_code":"KP",
    "gn:dem":1370,
    "gn:feature_class":"P",
    "gn:feature_code":"PPL",
    "gn:name":"Hwangt\u2019oam",
    "gn:population":0,
    "gn:timezone":"Asia/Pyongyang",
    "iso:country":"KP",
    "wof:name":"Hwangt'oam",
    "wof:placetype":"locality"
},
  "geometry": {"coordinates":[128.87721999999999,41.365],"type":"Point"}
}