{
  "type": "Feature",
  "properties": {
    "gn:admin1_code":"7.0",
    "gn:asciiname":"Kambaksan-gol",
    "gn:country_code":"KP",
    "gn:dem":290,
    "gn:feature_class":"P",
    "gn:feature_code":"PPL",
    "gn:name":"Kambaksan-gol",
    "gn:population":0,
    "gn:timezone":"Asia/Pyongyang",
    "iso:country":"KP",
    "wof:name":"Kambaksan-gol",
    "wof:placetype":"locality"
},
  "geometry": {"coordinates":[126.23417000000001,38.6625],"type":"Point"}
}