{
  "type": "Feature",
  "properties": {
    "gn:admin1_code":"0.0",
    "gn:asciiname":"Hao-ri",
    "gn:country_code":"KP",
    "gn:dem":67,
    "gn:feature_class":"P",
    "gn:feature_code":"PPL",
    "gn:name":"Hao-ri",
    "gn:population":0,
    "gn:timezone":"Asia/Pyongyang",
    "iso:country":"KP",
    "name:kor_x_preferred":[
        "\ud558\uc624\ub9ac"
    ],
    "wof:name":"Hao-ri",
    "wof:placetype":"locality"
},
  "geometry": {"coordinates":[125.18333,38.25],"type":"Point"}
}