{
  "type": "Feature",
  "properties": {
    "gn:admin1_code":"1.0",
    "gn:asciiname":"Kobi-dong",
    "gn:country_code":"KP",
    "gn:dem":367,
    "gn:feature_class":"P",
    "gn:feature_code":"PPL",
    "gn:name":"Kobi-dong",
    "gn:population":0,
    "gn:timezone":"Asia/Pyongyang",
    "iso:country":"KP",
    "name:und_x_variant":[
        "\uace0\ube44\ub3d9",
        "Kobi-dong"
    ],
    "wof:name":"Kobi-dong",
    "wof:placetype":"locality"
},
  "geometry": {"coordinates":[126.91361000000001,41.79361],"type":"Point"}
}