{
  "type": "Feature",
  "properties": {
    "gn:admin1_code":"0.0",
    "gn:asciiname":"Sap'o-ri",
    "gn:country_code":"KP",
    "gn:dem":24,
    "gn:feature_class":"P",
    "gn:feature_code":"PPL",
    "gn:name":"Sap\u2019o-ri",
    "gn:population":0,
    "gn:timezone":"Asia/Pyongyang",
    "iso:country":"KP",
    "name:kor_x_preferred":[
        "\uc0ac\ud3ec\ub9ac"
    ],
    "name:und_x_variant":[
        "Kyep\u2019o-ri",
        "Sap\u2019o-ri"
    ],
    "wof:name":"Sap'o-ri",
    "wof:placetype":"locality"
},
  "geometry": {"coordinates":[125.65000000000001,38.75],"type":"Point"}
}