{
  "type": "Feature",
  "properties": {
    "gn:admin1_code":"15.0",
    "gn:asciiname":"Tang-gol",
    "gn:country_code":"KP",
    "gn:dem":178,
    "gn:feature_class":"P",
    "gn:feature_code":"PPL",
    "gn:name":"Tang-gol",
    "gn:population":0,
    "gn:timezone":"Asia/Pyongyang",
    "iso:country":"KP",
    "wof:name":"Tang-gol",
    "wof:placetype":"locality"
},
  "geometry": {"coordinates":[125.79222,39.29806],"type":"Point"}
}