{
  "type": "Feature",
  "properties": {
    "gn:admin1_code":"1.0",
    "gn:asciiname":"Songnyong-nodongjagu",
    "gn:country_code":"KP",
    "gn:dem":400,
    "gn:feature_class":"P",
    "gn:feature_code":"PPL",
    "gn:name":"S\u014fngnyong-nodongjagu",
    "gn:population":0,
    "gn:timezone":"Asia/Pyongyang",
    "iso:country":"KP",
    "name:und_x_variant":[
        "\uc131\ub8e1\ub85c\ub3d9\uc790\uad6c",
        "S\u014fngnyong-nodongjagu"
    ],
    "wof:name":"Songnyong-nodongjagu",
    "wof:placetype":"locality"
},
  "geometry": {"coordinates":[126.53861000000001,40.75889],"type":"Point"}
}