{
  "type": "Feature",
  "properties": {
    "gn:admin1_code":"6.0",
    "gn:asciiname":"Yongbong-ni",
    "gn:cc2":"KP",
    "gn:country_code":"KP",
    "gn:dem":50,
    "gn:feature_class":"P",
    "gn:feature_code":"PPL",
    "gn:name":"Y\u014fngbong-ni",
    "gn:population":0,
    "gn:timezone":"Asia/Pyongyang",
    "iso:country":"KP",
    "name:und_x_variant":[
        "Y\u014fnbong-ni",
        "Y\u014fngbong-ni"
    ],
    "wof:name":"Yongbong-ni",
    "wof:placetype":"locality"
},
  "geometry": {"coordinates":[125.40472,38.37222],"type":"Point"}
}