{
  "type": "Feature",
  "properties": {
    "gn:admin1_code":"17.0",
    "gn:asciiname":"Sahak-kol",
    "gn:country_code":"KP",
    "gn:dem":252,
    "gn:feature_class":"P",
    "gn:feature_code":"PPL",
    "gn:name":"Sahak-kol",
    "gn:population":0,
    "gn:timezone":"Asia/Pyongyang",
    "iso:country":"KP",
    "name:und_x_variant":[
        "\uc0ac\ud56b\uace8",
        "Sahak-kol"
    ],
    "wof:name":"Sahak-kol",
    "wof:placetype":"locality"
},
  "geometry": {"coordinates":[129.76722000000001,42.44861],"type":"Point"}
}