{
  "type": "Feature",
  "properties": {
    "gn:admin1_code":"0.0",
    "gn:asciiname":"Sonam",
    "gn:country_code":"KP",
    "gn:dem":43,
    "gn:feature_class":"P",
    "gn:feature_code":"PPL",
    "gn:name":"S\u014fnam",
    "gn:population":0,
    "gn:timezone":"Asia/Pyongyang",
    "iso:country":"KP",
    "name:kor_x_preferred":[
        "\uc120\uc554"
    ],
    "name:und_x_variant":[
        "S\u014fnam"
    ],
    "wof:name":"Sonam",
    "wof:placetype":"locality"
},
  "geometry": {"coordinates":[124.69387999999999,39.89263],"type":"Point"}
}