{
  "type": "Feature",
  "properties": {
    "gn:admin1_code":"17.0",
    "gn:asciiname":"Songno-gol",
    "gn:country_code":"KP",
    "gn:dem":223,
    "gn:feature_class":"P",
    "gn:feature_code":"PPL",
    "gn:name":"Songno-gol",
    "gn:population":0,
    "gn:timezone":"Asia/Pyongyang",
    "iso:country":"KP",
    "name:und_x_variant":[
        "Songno-kol",
        "\uc1a1\ub85c\uace8",
        "Songno-gol"
    ],
    "wof:name":"Songno-gol",
    "wof:placetype":"locality"
},
  "geometry": {"coordinates":[129.36306000000002,41.01806],"type":"Point"}
}