{
  "type": "Feature",
  "properties": {
    "gn:admin1_code":"12.0",
    "gn:asciiname":"Moro-ri",
    "gn:country_code":"KP",
    "gn:dem":21,
    "gn:feature_class":"P",
    "gn:feature_code":"PPL",
    "gn:name":"Moro-ri",
    "gn:population":0,
    "gn:timezone":"Asia/Pyongyang",
    "iso:country":"KP",
    "name:kor_x_preferred":[
        "\ubaa8\ub85c\ub9ac"
    ],
    "name:und_x_variant":[
        "Morori"
    ],
    "wof:name":"Moro-ri",
    "wof:placetype":"locality"
},
  "geometry": {"coordinates":[125.66025,39.10276],"type":"Point"}
}