{
  "type": "Feature",
  "properties": {
    "gn:admin1_code":"15.0",
    "gn:asciiname":"Kumgong-ni",
    "gn:country_code":"KP",
    "gn:dem":125,
    "gn:feature_class":"P",
    "gn:feature_code":"PPL",
    "gn:name":"K\u016dmgong-ni",
    "gn:population":0,
    "gn:timezone":"Asia/Pyongyang",
    "iso:country":"KP",
    "name:kor_x_preferred":[
        "\uae08\uace1\ub9ac"
    ],
    "name:kor_x_variant":[
        "K\u016dmgong-ni"
    ],
    "wof:name":"Kumgong-ni",
    "wof:placetype":"locality"
},
  "geometry": {"coordinates":[126.32277999999999,39.40667],"type":"Point"}
}