{
  "type": "Feature",
  "properties": {
    "gn:admin1_code":"11.0",
    "gn:asciiname":"Ponghung-ni",
    "gn:country_code":"KP",
    "gn:dem":31,
    "gn:feature_class":"P",
    "gn:feature_code":"PPL",
    "gn:name":"Pongh\u016dng-ni",
    "gn:population":0,
    "gn:timezone":"Asia/Pyongyang",
    "iso:country":"KP",
    "wof:name":"Ponghung-ni",
    "wof:placetype":"locality"
},
  "geometry": {"coordinates":[125.60889,39.72417],"type":"Point"}
}