{
  "type": "Feature",
  "properties": {
    "gn:admin1_code":"1.0",
    "gn:asciiname":"Onch'och'am",
    "gn:country_code":"KP",
    "gn:dem":226,
    "gn:feature_class":"P",
    "gn:feature_code":"PPL",
    "gn:name":"Onch\u2019och\u2019am",
    "gn:population":0,
    "gn:timezone":"Asia/Pyongyang",
    "iso:country":"KP",
    "name:und_x_variant":[
        "\uc628\ucd08\ucc38",
        "Onch\u2019och\u2019am"
    ],
    "wof:name":"Onch'och'am",
    "wof:placetype":"locality"
},
  "geometry": {"coordinates":[126.43389000000001,40.18917],"type":"Point"}
}