{
  "type": "Feature",
  "properties": {
    "gn:admin1_code":"3.0",
    "gn:asciiname":"Yonghang-ni",
    "gn:country_code":"KP",
    "gn:dem":3,
    "gn:feature_class":"P",
    "gn:feature_code":"PPL",
    "gn:name":"Yonghang-ni",
    "gn:population":0,
    "gn:timezone":"Asia/Pyongyang",
    "iso:country":"KP",
    "name:eng_x_preferred":[
        "Yonghang"
    ],
    "name:eng_x_variant":[
        "Yonghang-ni"
    ],
    "name:und_x_variant":[
        "Ry\u016bk\u014d-ri",
        "Yonghang-ni",
        "\uc6a9\ud56d\ub9ac"
    ],
    "wof:name":"Yonghang",
    "wof:placetype":"locality"
},
  "geometry": {"coordinates":[128.6576,40.20827],"type":"Point"}
}