{
  "type": "Feature",
  "properties": {
    "gn:admin1_code":"3.0",
    "gn:asciiname":"Ch'ongsong-ni",
    "gn:country_code":"KP",
    "gn:dem":98,
    "gn:feature_class":"P",
    "gn:feature_code":"PPL",
    "gn:name":"Ch\u2019\u014fngsong-ni",
    "gn:population":0,
    "gn:timezone":"Asia/Pyongyang",
    "iso:country":"KP",
    "name:und_x_variant":[
        "\uccad\uc1a1\ub9ac",
        "Ch\u2019\u014fngsong-ni"
    ],
    "wof:name":"Ch'ongsong-ni",
    "wof:placetype":"locality"
},
  "geometry": {"coordinates":[127.68556,39.97583],"type":"Point"}
}