{
  "type": "Feature",
  "properties": {
    "gn:admin1_code":"7.0",
    "gn:asciiname":"Malmegu-ri",
    "gn:country_code":"KP",
    "gn:dem":97,
    "gn:feature_class":"P",
    "gn:feature_code":"PPL",
    "gn:name":"Malmegu-ri",
    "gn:population":0,
    "gn:timezone":"Asia/Pyongyang",
    "iso:country":"KP",
    "wof:name":"Malmegu-ri",
    "wof:placetype":"locality"
},
  "geometry": {"coordinates":[126.72221999999999,38.26694000000001],"type":"Point"}
}