{
  "type": "Feature",
  "properties": {
    "gn:admin1_code":"3.0",
    "gn:asciiname":"Songgye",
    "gn:country_code":"KP",
    "gn:dem":293,
    "gn:feature_class":"P",
    "gn:feature_code":"PPL",
    "gn:name":"Songgye",
    "gn:population":0,
    "gn:timezone":"Asia/Pyongyang",
    "iso:country":"KP",
    "name:und_x_variant":[
        "\uc1a1\uacc4",
        "Songgye"
    ],
    "wof:name":"Songgye",
    "wof:placetype":"locality"
},
  "geometry": {"coordinates":[128.00833,40.19361],"type":"Point"}
}