{
  "type": "Feature",
  "properties": {
    "gn:admin1_code":"6.0",
    "gn:asciiname":"Ori-gol",
    "gn:country_code":"KP",
    "gn:dem":32,
    "gn:feature_class":"P",
    "gn:feature_code":"PPL",
    "gn:name":"Ori-gol",
    "gn:population":0,
    "gn:timezone":"Asia/Pyongyang",
    "iso:country":"KP",
    "name:und_x_variant":[
        "Ori-dong",
        "\uc624\ub9ac\uace8",
        "Ori-gol"
    ],
    "wof:name":"Ori-gol",
    "wof:placetype":"locality"
},
  "geometry": {"coordinates":[125.29056,38.09361],"type":"Point"}
}