{
  "type": "Feature",
  "properties": {
    "gn:admin1_code":"11.0",
    "gn:asciiname":"Uihung-ni",
    "gn:country_code":"KP",
    "gn:dem":169,
    "gn:feature_class":"P",
    "gn:feature_code":"PPL",
    "gn:name":"\u016cih\u016dng-ni",
    "gn:population":0,
    "gn:timezone":"Asia/Pyongyang",
    "iso:country":"KP",
    "name:kor_x_preferred":[
        "\uc758\ud765\ub9ac"
    ],
    "name:und_x_variant":[
        "\u016cih\u016dng-ni"
    ],
    "wof:name":"Uihung-ni",
    "wof:placetype":"locality"
},
  "geometry": {"coordinates":[125.29778,40.61028],"type":"Point"}
}