{
  "type": "Feature",
  "properties": {
    "gn:admin1_code":"9.0",
    "gn:asciiname":"Mangil-li",
    "gn:country_code":"KP",
    "gn:dem":234,
    "gn:feature_class":"P",
    "gn:feature_code":"PPL",
    "gn:name":"Mangil-li",
    "gn:population":0,
    "gn:timezone":"Asia/Pyongyang",
    "iso:country":"KP",
    "wof:name":"Mangil-li",
    "wof:placetype":"locality"
},
  "geometry": {"coordinates":[127.07472,38.48583],"type":"Point"}
}