{
  "type": "Feature",
  "properties": {
    "gn:admin1_code":"9.0",
    "gn:admin2_code":"Munch\u2019\u0171n-si",
    "gn:asciiname":"Hwangsong-ni",
    "gn:country_code":"KP",
    "gn:dem":24,
    "gn:feature_class":"P",
    "gn:feature_code":"PPL",
    "gn:name":"Hwangs\u014fng-ni",
    "gn:population":0,
    "gn:timezone":"Asia/Pyongyang",
    "iso:country":"KP",
    "name:eng_x_preferred":[
        "Hwangsong"
    ],
    "name:eng_x_variant":[
        "Hwangsong-ni"
    ],
    "wof:name":"Hwangsong",
    "wof:placetype":"locality"
},
  "geometry": {"coordinates":[127.36194,39.29306],"type":"Point"}
}