{
  "type": "Feature",
  "properties": {
    "gn:admin1_code":"3.0",
    "gn:asciiname":"Kudogi",
    "gn:country_code":"KP",
    "gn:dem":414,
    "gn:feature_class":"P",
    "gn:feature_code":"PPL",
    "gn:name":"Kud\u014fgi",
    "gn:population":0,
    "gn:timezone":"Asia/Pyongyang",
    "iso:country":"KP",
    "name:kor_x_preferred":[
        "\uad6c\ub355\uc774"
    ],
    "name:kor_x_variant":[
        "Kud\u014fgi"
    ],
    "wof:name":"Kudogi",
    "wof:placetype":"locality"
},
  "geometry": {"coordinates":[127.04389,39.69167],"type":"Point"}
}