{
  "type": "Feature",
  "properties": {
    "gn:admin1_code":"0.0",
    "gn:asciiname":"Sangnu-dong",
    "gn:country_code":"KP",
    "gn:dem":45,
    "gn:feature_class":"P",
    "gn:feature_code":"PPL",
    "gn:name":"Sangnu-dong",
    "gn:population":0,
    "gn:timezone":"Asia/Pyongyang",
    "iso:country":"KP",
    "name:kor_x_preferred":[
        "\uc0c1\ub8e8\ub3d9"
    ],
    "wof:name":"Sangnu-dong",
    "wof:placetype":"locality"
},
  "geometry": {"coordinates":[125.63333,38.28333],"type":"Point"}
}