{
  "type": "Feature",
  "properties": {
    "gn:admin1_code":"3.0",
    "gn:asciiname":"T'ong-ni",
    "gn:country_code":"KP",
    "gn:dem":504,
    "gn:feature_class":"P",
    "gn:feature_code":"PPL",
    "gn:name":"T\u2019ong-ni",
    "gn:population":0,
    "gn:timezone":"Asia/Pyongyang",
    "iso:country":"KP",
    "name:und_x_variant":[
        "\ud1b5\ub9ac",
        "T\u2019ong-ni"
    ],
    "wof:name":"T'ong-ni",
    "wof:placetype":"locality"
},
  "geometry": {"coordinates":[128.45361,40.68833],"type":"Point"}
}