{
  "type": "Feature",
  "properties": {
    "gn:admin1_code":"6.0",
    "gn:asciiname":"Hongji-dong",
    "gn:country_code":"KP",
    "gn:dem":84,
    "gn:feature_class":"P",
    "gn:feature_code":"PPL",
    "gn:name":"Hongji-dong",
    "gn:population":0,
    "gn:timezone":"Asia/Pyongyang",
    "iso:country":"KP",
    "name:fas_x_preferred":[
        "\u0647\u0648\u0646\u06af\u062c\u06cc-\u062f\u0648\u0646\u06af"
    ],
    "name:kor_x_preferred":[
        "\ud64d\uc9c0\ub3d9"
    ],
    "name:sco_x_preferred":[
        "Hongji-dong"
    ],
    "name:vie_x_preferred":[
        "Hongji-dong"
    ],
    "wof:name":"Hongji-dong",
    "wof:placetype":"locality"
},
  "geometry": {"coordinates":[125.69917,38.25694],"type":"Point"}
}