{
  "type": "Feature",
  "properties": {
    "gn:admin1_code":"7.0",
    "gn:asciiname":"Ch'ilchon-dong",
    "gn:country_code":"KP",
    "gn:dem":218,
    "gn:feature_class":"P",
    "gn:feature_code":"PPL",
    "gn:name":"Ch\u2019ilch\u014fn-dong",
    "gn:population":0,
    "gn:timezone":"Asia/Pyongyang",
    "iso:country":"KP",
    "name:kor_x_preferred":[
        "\uce60\uc804\ub3d9"
    ],
    "name:kor_x_variant":[
        "Ch\u2019ilch\u014fn-dong"
    ],
    "name:und_x_variant":[
        "Chilchon"
    ],
    "wof:name":"Ch'ilchon-dong",
    "wof:placetype":"locality"
},
  "geometry": {"coordinates":[126.55667,38.68361],"type":"Point"}
}