{
  "type": "Feature",
  "properties": {
    "gn:admin1_code":"7.0",
    "gn:asciiname":"Mu-dong",
    "gn:country_code":"KP",
    "gn:dem":13,
    "gn:feature_class":"P",
    "gn:feature_code":"PPL",
    "gn:name":"Mu-dong",
    "gn:population":0,
    "gn:timezone":"Asia/Pyongyang",
    "iso:country":"KP",
    "name:und_x_variant":[
        "\ubb34\ub3d9",
        "Mu-dong"
    ],
    "wof:name":"Mu-dong",
    "wof:placetype":"locality"
},
  "geometry": {"coordinates":[125.72499999999999,38.80361],"type":"Point"}
}