{
  "type": "Feature",
  "properties": {
    "gn:admin1_code":"11.0",
    "gn:asciiname":"Mangilgogae",
    "gn:country_code":"KP",
    "gn:dem":225,
    "gn:feature_class":"P",
    "gn:feature_code":"PPL",
    "gn:name":"Mangilgogae",
    "gn:population":0,
    "gn:timezone":"Asia/Pyongyang",
    "iso:country":"KP",
    "name:und_x_variant":[
        "Mangilgok",
        "Mangil-kol",
        "Mangil-gol",
        "\ub9dd\uc77c\uace8",
        "Mangilgogae"
    ],
    "wof:name":"Mangilgogae",
    "wof:placetype":"locality"
},
  "geometry": {"coordinates":[124.71250000000001,39.94833],"type":"Point"}
}