{
  "type": "Feature",
  "properties": {
    "gn:admin1_code":"6.0",
    "gn:asciiname":"Sangnyong-dong",
    "gn:country_code":"KP",
    "gn:dem":23,
    "gn:feature_class":"P",
    "gn:feature_code":"PPL",
    "gn:name":"Sangny\u014fng-dong",
    "gn:population":0,
    "gn:timezone":"Asia/Pyongyang",
    "iso:country":"KP",
    "name:und_x_variant":[
        "\uc0ad\ub155\ub3d9",
        "Sangny\u014fng-dong"
    ],
    "wof:name":"Sangnyong-dong",
    "wof:placetype":"locality"
},
  "geometry": {"coordinates":[126.37972000000001,38.15167],"type":"Point"}
}