{
  "type": "Feature",
  "properties": {
    "gn:admin1_code":"1.0",
    "gn:asciiname":"Oejung-nodongjagu",
    "gn:country_code":"KP",
    "gn:dem":678,
    "gn:feature_class":"P",
    "gn:feature_code":"PPL",
    "gn:name":"Oejung-nodongjagu",
    "gn:population":0,
    "gn:timezone":"Asia/Pyongyang",
    "iso:country":"KP",
    "name:kor_x_preferred":[
        "\uc678\uc911\ub85c\ub3d9\uc790\uad6c"
    ],
    "name:und_x_variant":[
        "\uc678\uc911\ub85c\ub3d9\uc790\uad6c",
        "Oejung-nodongjagu"
    ],
    "wof:name":"Oejung-nodongjagu",
    "wof:placetype":"locality"
},
  "geometry": {"coordinates":[126.63593,40.71133],"type":"Point"}
}