{
  "type": "Feature",
  "properties": {
    "gn:admin1_code":"3.0",
    "gn:asciiname":"Kwangdong-ni",
    "gn:country_code":"KP",
    "gn:dem":224,
    "gn:feature_class":"P",
    "gn:feature_code":"PPL",
    "gn:name":"Kwangd\u014fng-ni",
    "gn:population":0,
    "gn:timezone":"Asia/Pyongyang",
    "iso:country":"KP",
    "name:und_x_variant":[
        "\uad11\ub355\ub9ac",
        "Kwangd\u014fng-ni"
    ],
    "wof:name":"Kwangdong-ni",
    "wof:placetype":"locality"
},
  "geometry": {"coordinates":[127.68194,40.02083],"type":"Point"}
}