{
  "type": "Feature",
  "properties": {
    "gn:admin1_code":"11.0",
    "gn:asciiname":"Kandongch'am",
    "gn:country_code":"KP",
    "gn:dem":172,
    "gn:feature_class":"P",
    "gn:feature_code":"PPL",
    "gn:name":"Kandongch\u2019am",
    "gn:population":0,
    "gn:timezone":"Asia/Pyongyang",
    "iso:country":"KP",
    "name:und_x_variant":[
        "\uac04\ub3d9\ucc38",
        "Kandongch\u2019am"
    ],
    "wof:name":"Kandongch'am",
    "wof:placetype":"locality"
},
  "geometry": {"coordinates":[126.04167,40.09139],"type":"Point"}
}