{
  "type": "Feature",
  "properties": {
    "gn:admin1_code":"15.0",
    "gn:asciiname":"Karhyon-dong",
    "gn:country_code":"KP",
    "gn:dem":90,
    "gn:feature_class":"P",
    "gn:feature_code":"PPL",
    "gn:name":"Karhy\u014fn-dong",
    "gn:population":0,
    "gn:timezone":"Asia/Pyongyang",
    "iso:country":"KP",
    "name:kor_x_preferred":[
        "\uac08\ud604\ub3d9"
    ],
    "name:und_x_variant":[
        "Karhy\u014fn-dong"
    ],
    "wof:name":"Karhyon-dong",
    "wof:placetype":"locality"
},
  "geometry": {"coordinates":[125.87806,39.58861],"type":"Point"}
}