{
  "type": "Feature",
  "properties": {
    "gn:admin1_code":"13.0",
    "gn:asciiname":"Chiktong-ni",
    "gn:country_code":"KP",
    "gn:dem":767,
    "gn:feature_class":"P",
    "gn:feature_code":"PPL",
    "gn:name":"Chiktong-ni",
    "gn:population":0,
    "gn:timezone":"Asia/Pyongyang",
    "iso:country":"KP",
    "name:eng_x_preferred":[
        "Chiktong"
    ],
    "name:eng_x_variant":[
        "Chiktong-ni"
    ],
    "wof:name":"Chiktong",
    "wof:placetype":"locality"
},
  "geometry": {"coordinates":[128.04167000000001,41.37167],"type":"Point"}
}