{
  "type": "Feature",
  "properties": {
    "gn:admin1_code":"13.0",
    "gn:asciiname":"Chiktong-ni",
    "gn:country_code":"KP",
    "gn:dem":767,
    "gn:feature_class":"P",
    "gn:feature_code":"PPL",
    "gn:name":"Chiktong-ni",
    "gn:population":0,
    "gn:timezone":"Asia/Pyongyang",
    "iso:country":"KP",
    "wof:name":"Chiktong-ni",
    "wof:placetype":"locality"
},
  "geometry": {"coordinates":[128.04166999999998,41.37167],"type":"Point"}
}