{
  "type": "Feature",
  "properties": {
    "gn:admin1_code":"0.0",
    "gn:asciiname":"Pongnae",
    "gn:country_code":"KP",
    "gn:dem":13,
    "gn:feature_class":"P",
    "gn:feature_code":"PPL",
    "gn:name":"Pongnae",
    "gn:population":0,
    "gn:timezone":"Asia/Pyongyang",
    "iso:country":"KP",
    "name:kor_x_preferred":[
        "\ubd09\ub0b4"
    ],
    "wof:name":"Pongnae",
    "wof:placetype":"locality"
},
  "geometry": {"coordinates":[125.90000000000001,38.01667],"type":"Point"}
}