{
  "type": "Feature",
  "properties": {
    "gn:admin1_code":"6.0",
    "gn:asciiname":"Punhyang-ni",
    "gn:cc2":"KP",
    "gn:country_code":"KP",
    "gn:dem":20,
    "gn:feature_class":"P",
    "gn:feature_code":"PPL",
    "gn:name":"Punhyang-ni",
    "gn:population":0,
    "gn:timezone":"Asia/Pyongyang",
    "iso:country":"KP",
    "name:und_x_variant":[
        "P\u014fnhyang-ni",
        "Punhyang-ni"
    ],
    "wof:name":"Punhyang-ni",
    "wof:placetype":"locality"
},
  "geometry": {"coordinates":[126.0325,37.9225],"type":"Point"}
}