{
  "type": "Feature",
  "properties": {
    "gn:admin1_code":"15.0",
    "gn:asciiname":"Saen-mal",
    "gn:country_code":"KP",
    "gn:dem":55,
    "gn:feature_class":"P",
    "gn:feature_code":"PPL",
    "gn:name":"Saen-mal",
    "gn:population":0,
    "gn:timezone":"Asia/Pyongyang",
    "iso:country":"KP",
    "name:und_x_variant":[
        "Kan-ni",
        "Saen-ma\u016dl",
        "Saen-mal"
    ],
    "wof:name":"Saen-mal",
    "wof:placetype":"locality"
},
  "geometry": {"coordinates":[125.96722,39.48222],"type":"Point"}
}