{
  "type": "Feature",
  "properties": {
    "gn:admin1_code":"17.0",
    "gn:asciiname":"Namsok",
    "gn:country_code":"KP",
    "gn:dem":648,
    "gn:feature_class":"P",
    "gn:feature_code":"PPL",
    "gn:name":"Nams\u014fk",
    "gn:population":0,
    "gn:timezone":"Asia/Pyongyang",
    "iso:country":"KP",
    "name:und_x_variant":[
        "Nams\u014fk",
        "\ub0a8\uc11d"
    ],
    "wof:name":"Namsok",
    "wof:placetype":"locality"
},
  "geometry": {"coordinates":[129.21475000000001,42.0504],"type":"Point"}
}