{
  "type": "Feature",
  "properties": {
    "gn:admin1_code":"7.0",
    "gn:asciiname":"Tang-gol",
    "gn:cc2":"KP",
    "gn:country_code":"KP",
    "gn:dem":107,
    "gn:feature_class":"P",
    "gn:feature_code":"PPL",
    "gn:name":"Tang-gol",
    "gn:population":0,
    "gn:timezone":"Asia/Pyongyang",
    "iso:country":"KP",
    "name:und_x_variant":[
        "Tang-dong",
        "Tang-gol"
    ],
    "wof:name":"Tang-gol",
    "wof:placetype":"locality"
},
  "geometry": {"coordinates":[125.90028,38.31083],"type":"Point"}
}