{
  "type": "Feature",
  "properties": {
    "gn:admin1_code":"6.0",
    "gn:admin2_code":"1876380",
    "gn:asciiname":"Muksong-ni",
    "gn:country_code":"KP",
    "gn:dem":55,
    "gn:feature_class":"P",
    "gn:feature_code":"PPL",
    "gn:name":"Muksong-ni",
    "gn:population":0,
    "gn:timezone":"Asia/Pyongyang",
    "iso:country":"KP",
    "name:und_x_variant":[
        "M\u014fksong-ni",
        "Muksong-ni"
    ],
    "wof:name":"Muksong-ni",
    "wof:placetype":"locality"
},
  "geometry": {"coordinates":[126.49861,37.90083],"type":"Point"}
}