{
  "type": "Feature",
  "properties": {
    "gn:admin1_code":"15.0",
    "gn:asciiname":"Pudang",
    "gn:country_code":"KP",
    "gn:dem":59,
    "gn:feature_class":"P",
    "gn:feature_code":"PPL",
    "gn:name":"Pudang",
    "gn:population":0,
    "gn:timezone":"Asia/Pyongyang",
    "iso:country":"KP",
    "name:kor_x_preferred":[
        "\ubd80\ub2f9"
    ],
    "wof:name":"Pudang",
    "wof:placetype":"locality"
},
  "geometry": {"coordinates":[126.18194,39.2675],"type":"Point"}
}