{
  "type": "Feature",
  "properties": {
    "gn:admin1_code":"0.0",
    "gn:asciiname":"Naet'o",
    "gn:country_code":"KP",
    "gn:dem":327,
    "gn:feature_class":"P",
    "gn:feature_code":"PPL",
    "gn:name":"Naet\u2019\u014f",
    "gn:population":0,
    "gn:timezone":"Asia/Pyongyang",
    "iso:country":"KP",
    "name:kor_x_preferred":[
        "\ub0b4\ud130"
    ],
    "name:und_x_variant":[
        "Naedae",
        "Naet\u2019\u014f"
    ],
    "wof:name":"Naet'o",
    "wof:placetype":"locality"
},
  "geometry": {"coordinates":[125.65000000000001,38.18333],"type":"Point"}
}