{
  "type": "Feature",
  "properties": {
    "gn:admin1_code":"1.0",
    "gn:asciiname":"Ch'ongsang-ni",
    "gn:country_code":"KP",
    "gn:dem":163,
    "gn:feature_class":"P",
    "gn:feature_code":"PPL",
    "gn:name":"Ch\u2019ongsang-ni",
    "gn:population":0,
    "gn:timezone":"Asia/Pyongyang",
    "iso:country":"KP",
    "name:eng_x_preferred":[
        "Ch'ongsang"
    ],
    "name:eng_x_variant":[
        "Ch'ongsang-ni"
    ],
    "name:und_x_variant":[
        "\uccad\uc0c1\ub9ac",
        "Ch\u2019ongsang-ni"
    ],
    "wof:name":"Ch'ongsang",
    "wof:placetype":"locality"
},
  "geometry": {"coordinates":[126.31056,40.21722],"type":"Point"}
}