{
  "type": "Feature",
  "properties": {
    "gn:admin1_code":"3.0",
    "gn:asciiname":"Songhung-ni",
    "gn:country_code":"KP",
    "gn:dem":451,
    "gn:feature_class":"P",
    "gn:feature_code":"PPL",
    "gn:name":"Songh\u016dng-ni",
    "gn:population":0,
    "gn:timezone":"Asia/Pyongyang",
    "iso:country":"KP",
    "name:und_x_variant":[
        "Songh\u016dng-dong",
        "Palchon",
        "\uc1a1\ud765\ub9ac",
        "Palch\u014fn-nodongjagu",
        "Songh\u016dng-ni"
    ],
    "wof:name":"Songhung-ni",
    "wof:placetype":"locality"
},
  "geometry": {"coordinates":[127.55500000000001,40.3475],"type":"Point"}
}