{
  "type": "Feature",
  "properties": {
    "gn:admin1_code":"6.0",
    "gn:admin2_code":"P'anmun-gun",
    "gn:asciiname":"Chwahu-ri",
    "gn:country_code":"KP",
    "gn:dem":41,
    "gn:feature_class":"P",
    "gn:feature_code":"PPL",
    "gn:name":"Chwahu-ri",
    "gn:population":0,
    "gn:timezone":"Asia/Pyongyang",
    "iso:country":"KP",
    "wof:name":"Chwahu-ri",
    "wof:placetype":"locality"
},
  "geometry": {"coordinates":[126.60028,37.86972],"type":"Point"}
}