{
  "type": "Feature",
  "properties": {
    "gn:admin1_code":"7.0",
    "gn:asciiname":"Pongson-gol",
    "gn:country_code":"KP",
    "gn:dem":80,
    "gn:feature_class":"P",
    "gn:feature_code":"PPL",
    "gn:name":"Pongs\u014fn-gol",
    "gn:population":0,
    "gn:timezone":"Asia/Pyongyang",
    "iso:country":"KP",
    "wof:name":"Pongson-gol",
    "wof:placetype":"locality"
},
  "geometry": {"coordinates":[126.73166999999999,38.29],"type":"Point"}
}