{
  "type": "Feature",
  "properties": {
    "gn:admin1_code":"17.0",
    "gn:asciiname":"Chungch'on",
    "gn:country_code":"KP",
    "gn:dem":77,
    "gn:feature_class":"P",
    "gn:feature_code":"PPL",
    "gn:name":"Chungch\u2019on",
    "gn:population":0,
    "gn:timezone":"Asia/Pyongyang",
    "iso:country":"KP",
    "name:und_x_variant":[
        "\uc911\ucd0c",
        "Chungch\u2019on"
    ],
    "wof:name":"Chungch'on",
    "wof:placetype":"locality"
},
  "geometry": {"coordinates":[129.30500000000001,40.83139],"type":"Point"}
}