{
  "type": "Feature",
  "properties": {
    "gn:admin1_code":"11.0",
    "gn:asciiname":"Sogwi-ri",
    "gn:country_code":"KP",
    "gn:dem":100,
    "gn:feature_class":"P",
    "gn:feature_code":"PPL",
    "gn:name":"Sogwi-ri",
    "gn:population":0,
    "gn:timezone":"Asia/Pyongyang",
    "iso:country":"KP",
    "name:kor_x_preferred":[
        "\uc18c\uadc0\ub9ac"
    ],
    "wof:name":"Sogwi-ri",
    "wof:placetype":"locality"
},
  "geometry": {"coordinates":[125.45444000000001,39.73611],"type":"Point"}
}