{
  "type": "Feature",
  "properties": {
    "gn:admin1_code":"7.0",
    "gn:asciiname":"Chinmok-tong",
    "gn:country_code":"KP",
    "gn:dem":74,
    "gn:feature_class":"P",
    "gn:feature_code":"PPL",
    "gn:name":"Chinmok-tong",
    "gn:population":0,
    "gn:timezone":"Asia/Pyongyang",
    "iso:country":"KP",
    "name:kor_x_preferred":[
        "\uc9c4\ubaa9\ub3d9"
    ],
    "wof:name":"Chinmok-tong",
    "wof:placetype":"locality"
},
  "geometry": {"coordinates":[126.51778,38.40528],"type":"Point"}
}