{
  "type": "Feature",
  "properties": {
    "gn:admin1_code":"15.0",
    "gn:asciiname":"Chang-dong",
    "gn:country_code":"KP",
    "gn:dem":203,
    "gn:feature_class":"P",
    "gn:feature_code":"PPL",
    "gn:name":"Chang-dong",
    "gn:population":0,
    "gn:timezone":"Asia/Pyongyang",
    "iso:country":"KP",
    "name:kor_x_preferred":[
        "\uc7a5\ub3d9"
    ],
    "wof:name":"Chang-dong",
    "wof:placetype":"locality"
},
  "geometry": {"coordinates":[126.39806000000002,39.21167],"type":"Point"}
}