{
  "type": "Feature",
  "properties": {
    "gn:admin1_code":"17.0",
    "gn:asciiname":"An'gandok",
    "gn:country_code":"KP",
    "gn:dem":83,
    "gn:feature_class":"P",
    "gn:feature_code":"PPL",
    "gn:name":"An\u2019gand\u014fk",
    "gn:population":0,
    "gn:timezone":"Asia/Pyongyang",
    "iso:country":"KP",
    "name:und_x_variant":[
        "\uc548\uac04\ub355",
        "An\u2019gand\u014fk"
    ],
    "wof:name":"An'gandok",
    "wof:placetype":"locality"
},
  "geometry": {"coordinates":[129.54778000000002,41.61972],"type":"Point"}
}