{
  "type": "Feature",
  "properties": {
    "gn:admin1_code":"6.0",
    "gn:asciiname":"Hasokkyo",
    "gn:country_code":"KP",
    "gn:dem":9,
    "gn:feature_class":"P",
    "gn:feature_code":"PPL",
    "gn:name":"Has\u014fkkyo",
    "gn:population":0,
    "gn:timezone":"Asia/Pyongyang",
    "iso:country":"KP",
    "name:kor_x_preferred":[
        "\ud558\uc11d\uad50"
    ],
    "name:und_x_variant":[
        "Has\u014fkkyo"
    ],
    "wof:name":"Hasokkyo",
    "wof:placetype":"locality"
},
  "geometry": {"coordinates":[125.12778,38.57444],"type":"Point"}
}