{
  "type": "Feature",
  "properties": {
    "gn:admin1_code":"6.0",
    "gn:asciiname":"Sinch'on",
    "gn:country_code":"KP",
    "gn:dem":7,
    "gn:feature_class":"P",
    "gn:feature_code":"PPL",
    "gn:name":"Sinch\u2019on",
    "gn:population":0,
    "gn:timezone":"Asia/Pyongyang",
    "iso:country":"KP",
    "name:und_x_variant":[
        "Shinson",
        "Sinch\u2019on"
    ],
    "wof:name":"Sinch'on",
    "wof:placetype":"locality"
},
  "geometry": {"coordinates":[125.50333000000001,38.41],"type":"Point"}
}