{
  "type": "Feature",
  "properties": {
    "gn:admin1_code":"9.0",
    "gn:asciiname":"Sudok",
    "gn:country_code":"KP",
    "gn:dem":423,
    "gn:feature_class":"P",
    "gn:feature_code":"PPL",
    "gn:name":"Sud\u014fk",
    "gn:population":0,
    "gn:timezone":"Asia/Pyongyang",
    "iso:country":"KP",
    "name:und_x_variant":[
        "\uc218\ub355"
    ],
    "wof:name":"Sudok",
    "wof:placetype":"locality"
},
  "geometry": {"coordinates":[127.76361,38.5775],"type":"Point"}
}