{
  "type": "Feature",
  "properties": {
    "gn:admin1_code":"1.0",
    "gn:asciiname":"Tolmol",
    "gn:country_code":"KP",
    "gn:dem":161,
    "gn:feature_class":"P",
    "gn:feature_code":"PPL",
    "gn:name":"T\u014flmol",
    "gn:population":0,
    "gn:timezone":"Asia/Pyongyang",
    "iso:country":"KP",
    "name:und_x_variant":[
        "\ub3cc\ubab0",
        "T\u014flmal",
        "T\u014flmol"
    ],
    "wof:name":"Tolmol",
    "wof:placetype":"locality"
},
  "geometry": {"coordinates":[125.73888999999998,40.82861],"type":"Point"}
}