{
  "type": "Feature",
  "properties": {
    "gn:admin1_code":"11.0",
    "gn:asciiname":"Amdu-ri",
    "gn:country_code":"KP",
    "gn:dem":19,
    "gn:feature_class":"P",
    "gn:feature_code":"PPL",
    "gn:name":"Amdu-ri",
    "gn:population":0,
    "gn:timezone":"Asia/Pyongyang",
    "iso:country":"KP",
    "name:kor_x_preferred":[
        "\uc554\ub450\ub9ac"
    ],
    "wof:name":"Amdu-ri",
    "wof:placetype":"locality"
},
  "geometry": {"coordinates":[125.00132000000001,39.68566],"type":"Point"}
}