{
  "type": "Feature",
  "properties": {
    "gn:admin1_code":"6.0",
    "gn:asciiname":"Naegwe-dong",
    "gn:country_code":"KP",
    "gn:dem":14,
    "gn:feature_class":"P",
    "gn:feature_code":"PPL",
    "gn:name":"Naegwe-dong",
    "gn:population":0,
    "gn:timezone":"Asia/Pyongyang",
    "iso:country":"KP",
    "name:kor_x_preferred":[
        "\ub0b4\uada4\ub3d9"
    ],
    "wof:name":"Naegwe-dong",
    "wof:placetype":"locality"
},
  "geometry": {"coordinates":[125.03333000000001,38.21833],"type":"Point"}
}