{
  "type": "Feature",
  "properties": {
    "gn:admin1_code":"17.0",
    "gn:asciiname":"Kosong-ni",
    "gn:country_code":"KP",
    "gn:dem":256,
    "gn:feature_class":"P",
    "gn:feature_code":"PPLL",
    "gn:name":"Kos\u014fng-ni",
    "gn:population":0,
    "gn:timezone":"Asia/Pyongyang",
    "iso:country":"KP",
    "name:eng_x_preferred":[
        "Kosong"
    ],
    "name:eng_x_variant":[
        "Kosong-ni"
    ],
    "name:und_x_variant":[
        "Kos\u014fng-dong",
        "\uace0\uc131\ub9ac",
        "Kos\u014fng-ni"
    ],
    "wof:name":"Kosong",
    "wof:placetype":"locality"
},
  "geometry": {"coordinates":[129.38111000000001,41.15528],"type":"Point"}
}