{
  "type": "Feature",
  "properties": {
    "gn:admin1_code":"7.0",
    "gn:asciiname":"Anbong-ni",
    "gn:country_code":"KP",
    "gn:dem":92,
    "gn:feature_class":"P",
    "gn:feature_code":"PPL",
    "gn:name":"Anbong-ni",
    "gn:population":0,
    "gn:timezone":"Asia/Pyongyang",
    "iso:country":"KP",
    "name:eng_x_preferred":[
        "Anbong"
    ],
    "name:eng_x_variant":[
        "Anbong-ni"
    ],
    "name:kor_x_preferred":[
        "\uc548\ubd09\ub9ac"
    ],
    "wof:name":"Anbong",
    "wof:placetype":"locality"
},
  "geometry": {"coordinates":[126.81417,38.30917],"type":"Point"}
}