{
  "type": "Feature",
  "properties": {
    "gn:admin1_code":"11.0",
    "gn:asciiname":"Yongmun-dong",
    "gn:country_code":"KP",
    "gn:dem":55,
    "gn:feature_class":"P",
    "gn:feature_code":"PPL",
    "gn:name":"Yongmun-dong",
    "gn:population":0,
    "gn:timezone":"Asia/Pyongyang",
    "iso:country":"KP",
    "name:ceb_x_preferred":[
        "Yongmun-dong"
    ],
    "name:kor_x_preferred":[
        "\uc6a9\ubb38\ub3d9"
    ],
    "name:urd_x_preferred":[
        "\u06cc\u0648\u0646\u06af\u0645\u0646-\u0688\u0648\u0646\u06af"
    ],
    "name:vie_x_preferred":[
        "Yongmun-dong"
    ],
    "name:zho_x_preferred":[
        "\u9f99\u95e8\u6d1e"
    ],
    "wof:name":"Yongmun-dong",
    "wof:placetype":"locality"
},
  "geometry": {"coordinates":[124.54389,40.14972],"type":"Point"}
}