{
  "type": "Feature",
  "properties": {
    "gn:admin1_code":"11.0",
    "gn:asciiname":"Yongmun-dong",
    "gn:country_code":"KP",
    "gn:dem":55,
    "gn:feature_class":"P",
    "gn:feature_code":"PPL",
    "gn:name":"Yongmun-dong",
    "gn:population":0,
    "gn:timezone":"Asia/Pyongyang",
    "iso:country":"KP",
    "name:und_x_variant":[
        "\uc6a9\ubb38\ub3d9",
        "Yongmun-dong"
    ],
    "wof:name":"Yongmun-dong",
    "wof:placetype":"locality"
},
  "geometry": {"coordinates":[124.54389,40.14972],"type":"Point"}
}