{
  "type": "Feature",
  "properties": {
    "gn:admin1_code":"6.0",
    "gn:asciiname":"Chik-tong",
    "gn:country_code":"KP",
    "gn:dem":5,
    "gn:feature_class":"P",
    "gn:feature_code":"PPL",
    "gn:name":"Chik-tong",
    "gn:population":0,
    "gn:timezone":"Asia/Pyongyang",
    "iso:country":"KP",
    "name:kor_x_preferred":[
        "\uc9c1\ub3d9"
    ],
    "wof:name":"Chik-tong",
    "wof:placetype":"locality"
},
  "geometry": {"coordinates":[126.20722000000001,37.92444],"type":"Point"}
}