{
  "type": "Feature",
  "properties": {
    "gn:admin1_code":"12.0",
    "gn:admin2_code":"Kangdong-gun",
    "gn:asciiname":"Paksodae",
    "gn:country_code":"KP",
    "gn:dem":109,
    "gn:feature_class":"P",
    "gn:feature_code":"PPL",
    "gn:name":"Paksodae",
    "gn:population":0,
    "gn:timezone":"Asia/Pyongyang",
    "iso:country":"KP",
    "name:kor_x_preferred":[
        "\ubc16\uc18c\ub300"
    ],
    "name:und_x_variant":[
        "Pakksodae",
        "Baksodae"
    ],
    "wof:name":"Paksodae",
    "wof:placetype":"locality"
},
  "geometry": {"coordinates":[126.12321,39.02511],"type":"Point"}
}