{
  "type": "Feature",
  "properties": {
    "gn:admin1_code":"6.0",
    "gn:asciiname":"Sogul-li",
    "gn:country_code":"KP",
    "gn:dem":35,
    "gn:feature_class":"P",
    "gn:feature_code":"PPL",
    "gn:name":"S\u014fgul-li",
    "gn:population":0,
    "gn:timezone":"Asia/Pyongyang",
    "iso:country":"KP",
    "name:kor_x_preferred":[
        "\uc11d\uc6b4\ub9ac"
    ],
    "name:kor_x_variant":[
        "S\u014fgul-li"
    ],
    "wof:name":"Sogul-li",
    "wof:placetype":"locality"
},
  "geometry": {"coordinates":[125.45638999999998,38.57944000000001],"type":"Point"}
}