{
  "type": "Feature",
  "properties": {
    "gn:admin1_code":"6.0",
    "gn:asciiname":"Mat'an-dong",
    "gn:country_code":"KP",
    "gn:dem":16,
    "gn:feature_class":"P",
    "gn:feature_code":"PPL",
    "gn:name":"Mat\u2019an-dong",
    "gn:population":0,
    "gn:timezone":"Asia/Pyongyang",
    "iso:country":"KP",
    "name:und_x_variant":[
        "\ub9c8\ud0c4\ub3d9",
        "Mat\u2019an-dong"
    ],
    "wof:name":"Mat'an-dong",
    "wof:placetype":"locality"
},
  "geometry": {"coordinates":[126.42222,38.15889],"type":"Point"}
}