{
  "type": "Feature",
  "properties": {
    "iso:country":"KP",
    "ne:ADM0CAP":0.0,
    "ne:ADM0NAME":"North Korea",
    "ne:ADM0_A3":"PRK",
    "ne:ADM1NAME":"Hwanghae-bukto",
    "ne:ADMIN1_COD":0,
    "ne:CAPALT":0,
    "ne:CHANGED":0,
    "ne:CHECKME":0,
    "ne:COMPARE":0,
    "ne:DIFFASCII":0,
    "ne:ELEVATION":0.0,
    "ne:FEATURECLA":"Populated place",
    "ne:GEONAMEID":-1,
    "ne:GEONAMESNO":"No GeoNames match due to small population, not in GeoNames, or poor NEV placement.",
    "ne:GN_POP":0,
    "ne:GTOPO30":0.0,
    "ne:ISO_A2":"KP",
    "ne:LABELRANK":6,
    "ne:LATITUDE":38.33669,
    "ne:LONGITUDE":126.386642,
    "ne:LS_MATCH":1,
    "ne:LS_NAME":"Pyongsan",
    "ne:MAX_AREAKM":18.0,
    "ne:MAX_AREAMI":7.0,
    "ne:MAX_BBXMAX":126.441667,
    "ne:MAX_BBXMIN":126.375,
    "ne:MAX_BBYMAX":38.358333,
    "ne:MAX_BBYMIN":38.308333,
    "ne:MAX_NATSCA":20.0,
    "ne:MAX_PERKM":29.0,
    "ne:MAX_PERMI":18.0,
    "ne:MAX_POP10":66260,
    "ne:MAX_POP20":66260,
    "ne:MAX_POP300":0,
    "ne:MAX_POP310":0,
    "ne:MAX_POP50":0,
    "ne:MEAN_BBXC":126.403241,
    "ne:MEAN_BBYC":38.334414,
    "ne:MEGACITY":0,
    "ne:MIN_AREAKM":18.0,
    "ne:MIN_AREAMI":7.0,
    "ne:MIN_BBXMAX":126.441667,
    "ne:MIN_BBXMIN":126.375,
    "ne:MIN_BBYMAX":38.358333,
    "ne:MIN_BBYMIN":38.308333,
    "ne:MIN_PERKM":29.0,
    "ne:MIN_PERMI":18.0,
    "ne:NAME":"Pyongsan",
    "ne:NAMEASCII":"Pyongsan",
    "ne:NAMEDIFF":0,
    "ne:NATSCALE":20,
    "ne:POP1950":0,
    "ne:POP1955":0,
    "ne:POP1960":0,
    "ne:POP1965":0,
    "ne:POP1970":0,
    "ne:POP1975":0,
    "ne:POP1980":0,
    "ne:POP1985":0,
    "ne:POP1990":0,
    "ne:POP1995":0,
    "ne:POP2000":0,
    "ne:POP2005":0,
    "ne:POP2010":0,
    "ne:POP2015":0,
    "ne:POP2020":0,
    "ne:POP2025":0,
    "ne:POP2050":0,
    "ne:POP_MAX":66260,
    "ne:POP_MIN":66260,
    "ne:POP_OTHER":66113,
    "ne:RANK_MAX":8,
    "ne:RANK_MIN":8,
    "ne:SCALERANK":7,
    "ne:SOV0NAME":"Korea, North",
    "ne:SOV_A3":"PRK",
    "ne:UN_FID":0,
    "ne:UN_LAT":0.0,
    "ne:UN_LONG":0.0,
    "ne:WORLDCITY":0,
    "ne:min_zoom":6.7,
    "wof:name":"Pyongsan",
    "wof:placetype":"locality"
},
  "geometry": {"coordinates":[126.3866418041041,38.33668967595111],"type":"Point"}
}