{
  "type": "Feature",
  "properties": {
    "gn:admin1_code":"11.0",
    "gn:asciiname":"Samnyong-ni",
    "gn:country_code":"KP",
    "gn:dem":21,
    "gn:feature_class":"P",
    "gn:feature_code":"PPL",
    "gn:name":"Samnyong-ni",
    "gn:population":0,
    "gn:timezone":"Asia/Pyongyang",
    "iso:country":"KP",
    "name:und_x_variant":[
        "\uc0bc\ub8e1\ub9ac",
        "Samnyong-ni"
    ],
    "wof:name":"Samnyong-ni",
    "wof:placetype":"locality"
},
  "geometry": {"coordinates":[124.46611,40.03694],"type":"Point"}
}