{
  "type": "Feature",
  "properties": {
    "gn:admin1_code":"9.0",
    "gn:asciiname":"Yonson",
    "gn:country_code":"KP",
    "gn:dem":331,
    "gn:feature_class":"P",
    "gn:feature_code":"PPL",
    "gn:name":"Y\u014fnson",
    "gn:population":0,
    "gn:timezone":"Asia/Pyongyang",
    "iso:country":"KP",
    "name:kor_x_preferred":[
        "\uc5f0\uc190"
    ],
    "name:und_x_variant":[
        "Y\u014fnson"
    ],
    "wof:name":"Yonson",
    "wof:placetype":"locality"
},
  "geometry": {"coordinates":[127.69693999999998,38.59167],"type":"Point"}
}