{
  "type": "Feature",
  "properties": {
    "gn:admin1_code":"7.0",
    "gn:asciiname":"Taedong-ni",
    "gn:country_code":"KP",
    "gn:dem":19,
    "gn:feature_class":"P",
    "gn:feature_code":"PPL",
    "gn:name":"Taedong-ni",
    "gn:population":0,
    "gn:timezone":"Asia/Pyongyang",
    "iso:country":"KP",
    "wof:name":"Taedong-ni",
    "wof:placetype":"locality"
},
  "geometry": {"coordinates":[125.72139,38.67583],"type":"Point"}
}