{
  "type": "Feature",
  "properties": {
    "gn:admin1_code":"11.0",
    "gn:asciiname":"Hwanggump'yong-ni",
    "gn:country_code":"KP",
    "gn:dem":5,
    "gn:feature_class":"P",
    "gn:feature_code":"PPL",
    "gn:name":"Hwangg\u016dmp\u2019y\u014fng-ni",
    "gn:population":0,
    "gn:timezone":"Asia/Pyongyang",
    "iso:country":"KP",
    "name:und_x_variant":[
        "\ud669\uae08\ud3c9\ub9ac",
        "Hwangg\u016dmp\u2019y\u014fng-ni"
    ],
    "wof:name":"Hwanggump'yong-ni",
    "wof:placetype":"locality"
},
  "geometry": {"coordinates":[124.31056,39.95333],"type":"Point"}
}