{
  "type": "Feature",
  "properties": {
    "gn:admin1_code":"9.0",
    "gn:asciiname":"Ch'uktong-ni",
    "gn:country_code":"KP",
    "gn:dem":151,
    "gn:feature_class":"P",
    "gn:feature_code":"PPL",
    "gn:name":"Ch\u2019uktong-ni",
    "gn:population":0,
    "gn:timezone":"Asia/Pyongyang",
    "iso:country":"KP",
    "name:eng_x_preferred":[
        "Ch'uktong"
    ],
    "name:eng_x_variant":[
        "Ch'uktong-ni"
    ],
    "name:kor_x_preferred":[
        "\ucd95\ub3d9\ub9ac"
    ],
    "name:und_x_variant":[
        "Ch\u2019uktong-ni"
    ],
    "wof:name":"Ch'uktong",
    "wof:placetype":"locality"
},
  "geometry": {"coordinates":[126.89389,38.40694],"type":"Point"}
}