{
  "type": "Feature",
  "properties": {
    "gn:admin1_code":"6.0",
    "gn:admin2_code":"K\u016dmch\u2019\u014fn-gun",
    "gn:asciiname":"Uttorang",
    "gn:country_code":"KP",
    "gn:dem":139,
    "gn:feature_class":"P",
    "gn:feature_code":"PPL",
    "gn:name":"Uttorang",
    "gn:population":0,
    "gn:timezone":"Asia/Pyongyang",
    "iso:country":"KP",
    "wof:name":"Uttorang",
    "wof:placetype":"locality"
},
  "geometry": {"coordinates":[126.63472,38.20111],"type":"Point"}
}