{
  "type": "Feature",
  "properties": {
    "gn:admin1_code":"7.0",
    "gn:asciiname":"Hao-ri",
    "gn:country_code":"KP",
    "gn:dem":241,
    "gn:feature_class":"P",
    "gn:feature_code":"PPL",
    "gn:name":"Ha\u014f-ri",
    "gn:population":0,
    "gn:timezone":"Asia/Pyongyang",
    "iso:country":"KP",
    "wof:name":"Hao-ri",
    "wof:placetype":"locality"
},
  "geometry": {"coordinates":[126.22833,38.50972],"type":"Point"}
}