{
  "type": "Feature",
  "properties": {
    "gn:admin1_code":"11.0",
    "gn:asciiname":"Soju-dong",
    "gn:cc2":"KP",
    "gn:country_code":"KP",
    "gn:dem":26,
    "gn:feature_class":"P",
    "gn:feature_code":"PPL",
    "gn:name":"S\u014fju-dong",
    "gn:population":0,
    "gn:timezone":"Asia/Pyongyang",
    "iso:country":"KP",
    "name:kor_x_preferred":[
        "\uc11c\uc8fc\ub3d9"
    ],
    "name:kor_x_variant":[
        "S\u014fju-dong"
    ],
    "name:und_x_variant":[
        "S\u014fju-ri"
    ],
    "wof:name":"Soju-dong",
    "wof:placetype":"locality"
},
  "geometry": {"coordinates":[125.19138999999998,39.69556],"type":"Point"}
}