{
  "type": "Feature",
  "properties": {
    "gn:admin1_code":"6.0",
    "gn:asciiname":"Kyongch'on",
    "gn:country_code":"KP",
    "gn:dem":26,
    "gn:feature_class":"P",
    "gn:feature_code":"PPL",
    "gn:name":"Ky\u014fngch\u2019on",
    "gn:population":0,
    "gn:timezone":"Asia/Pyongyang",
    "iso:country":"KP",
    "name:und_x_variant":[
        "\uacbd\ucd0c",
        "Ky\u014fngch\u2019on"
    ],
    "wof:name":"Kyongch'on",
    "wof:placetype":"locality"
},
  "geometry": {"coordinates":[125.16306000000002,38.52028],"type":"Point"}
}