{
  "type": "Feature",
  "properties": {
    "gn:admin1_code":"7.0",
    "gn:asciiname":"Sangch'u",
    "gn:country_code":"KP",
    "gn:dem":16,
    "gn:feature_class":"P",
    "gn:feature_code":"PPL",
    "gn:name":"Sangch\u2019u",
    "gn:population":0,
    "gn:timezone":"Asia/Pyongyang",
    "iso:country":"KP",
    "wof:name":"Sangch'u",
    "wof:placetype":"locality"
},
  "geometry": {"coordinates":[125.73917,38.45083],"type":"Point"}
}