{
  "type": "Feature",
  "properties": {
    "gn:admin1_code":"9.0",
    "gn:asciiname":"Sangsago-ri",
    "gn:country_code":"KP",
    "gn:dem":5,
    "gn:feature_class":"P",
    "gn:feature_code":"PPL",
    "gn:name":"Sangsago-ri",
    "gn:population":0,
    "gn:timezone":"Asia/Pyongyang",
    "iso:country":"KP",
    "name:und_x_variant":[
        "\uc0c1\uc0ac\uace0\ub9ac"
    ],
    "wof:name":"Sangsago-ri",
    "wof:placetype":"locality"
},
  "geometry": {"coordinates":[127.51111000000002,39.11583],"type":"Point"}
}