{
  "type": "Feature",
  "properties": {
    "gn:admin1_code":"1.0",
    "gn:asciiname":"Haenam",
    "gn:country_code":"KP",
    "gn:dem":465,
    "gn:feature_class":"P",
    "gn:feature_code":"PPL",
    "gn:name":"Haenam",
    "gn:population":0,
    "gn:timezone":"Asia/Pyongyang",
    "iso:country":"KP",
    "name:kor_x_preferred":[
        "\ud574\ub0a8"
    ],
    "name:kor_x_variant":[
        "\ud574\ub0a8\uace8"
    ],
    "name:und_x_variant":[
        "Haenam-gol",
        "Haenam"
    ],
    "wof:name":"Haenam",
    "wof:placetype":"locality"
},
  "geometry": {"coordinates":[126.52171,40.91727],"type":"Point"}
}