{
  "type": "Feature",
  "properties": {
    "gn:admin1_code":"6.0",
    "gn:asciiname":"Kyohang-dong",
    "gn:cc2":"KP",
    "gn:country_code":"KP",
    "gn:dem":22,
    "gn:feature_class":"P",
    "gn:feature_code":"PPL",
    "gn:name":"Kyohang-dong",
    "gn:population":0,
    "gn:timezone":"Asia/Pyongyang",
    "iso:country":"KP",
    "name:und_x_variant":[
        "Saengyang-dong",
        "Kyohang-dong"
    ],
    "wof:name":"Kyohang-dong",
    "wof:placetype":"locality"
},
  "geometry": {"coordinates":[125.88278,37.92944],"type":"Point"}
}