{
  "type": "Feature",
  "properties": {
    "gn:admin1_code":"9.0",
    "gn:asciiname":"Kaeya-ri",
    "gn:country_code":"KP",
    "gn:dem":250,
    "gn:feature_class":"P",
    "gn:feature_code":"PPL",
    "gn:name":"Kaeya-ri",
    "gn:population":0,
    "gn:timezone":"Asia/Pyongyang",
    "iso:country":"KP",
    "name:und_x_variant":[
        "\uac1c\uc57c\ub9ac",
        "Gaeya-ri",
        "Kaeya-ri"
    ],
    "wof:name":"Kaeya-ri",
    "wof:placetype":"locality"
},
  "geometry": {"coordinates":[127.62472,38.36778],"type":"Point"}
}