{
  "type": "Feature",
  "properties": {
    "gn:admin1_code":"15.0",
    "gn:admin2_code":"Mund\u014fk-kun",
    "gn:asciiname":"Yongji-ri",
    "gn:country_code":"KP",
    "gn:dem":8,
    "gn:feature_class":"P",
    "gn:feature_code":"PPL",
    "gn:name":"Yongji-ri",
    "gn:population":0,
    "gn:timezone":"Asia/Pyongyang",
    "iso:country":"KP",
    "name:und_x_variant":[
        "Yongji-ni",
        "Yongji-ri"
    ],
    "wof:name":"Yongji-ri",
    "wof:placetype":"locality"
},
  "geometry": {"coordinates":[125.505,39.49583],"type":"Point"}
}