{
  "type": "Feature",
  "properties": {
    "gn:admin1_code":"6.0",
    "gn:asciiname":"Changhyol-li",
    "gn:cc2":"KP",
    "gn:country_code":"KP",
    "gn:dem":28,
    "gn:feature_class":"P",
    "gn:feature_code":"PPL",
    "gn:name":"Changhy\u014fl-li",
    "gn:population":0,
    "gn:timezone":"Asia/Pyongyang",
    "iso:country":"KP",
    "name:kor_x_preferred":[
        "\uc7a5\ud604\ub9ac"
    ],
    "name:und_x_variant":[
        "Changhy\u014fn-ni",
        "Changhy\u014fl-li"
    ],
    "wof:name":"Changhyol-li",
    "wof:placetype":"locality"
},
  "geometry": {"coordinates":[125.51443999999999,38.06667],"type":"Point"}
}