{
  "type": "Feature",
  "properties": {
    "gn:admin1_code":"9.0",
    "gn:admin2_code":"Ch\u2019\u014fnnae-gun",
    "gn:asciiname":"Munha-dong",
    "gn:country_code":"KP",
    "gn:dem":76,
    "gn:feature_class":"P",
    "gn:feature_code":"PPL",
    "gn:name":"Munha-dong",
    "gn:population":0,
    "gn:timezone":"Asia/Pyongyang",
    "iso:country":"KP",
    "name:und_x_variant":[
        "Munha-ri",
        "Munha-dong",
        "\ubb38\ud558\ub3d9"
    ],
    "wof:name":"Munha-dong",
    "wof:placetype":"locality"
},
  "geometry": {"coordinates":[127.25082999999999,39.26722],"type":"Point"}
}