{
  "type": "Feature",
  "properties": {
    "gn:admin1_code":"17.0",
    "gn:admin2_code":"\u016cnd\u014fk-kun",
    "gn:asciiname":"Paksong-dong",
    "gn:country_code":"KP",
    "gn:dem":190,
    "gn:feature_class":"P",
    "gn:feature_code":"PPL",
    "gn:name":"Paks\u014fng-dong",
    "gn:population":0,
    "gn:timezone":"Asia/Pyongyang",
    "iso:country":"KP",
    "name:und_x_variant":[
        "\ubc15\uc131\ub3d9",
        "Paks\u014fng-dong"
    ],
    "wof:name":"Paksong-dong",
    "wof:placetype":"locality"
},
  "geometry": {"coordinates":[130.39917,42.44778],"type":"Point"}
}