{
  "type": "Feature",
  "properties": {
    "gn:admin1_code":"0.0",
    "gn:asciiname":"Malmudom",
    "gn:cc2":"KP",
    "gn:country_code":"KP",
    "gn:dem":42,
    "gn:feature_class":"P",
    "gn:feature_code":"PPL",
    "gn:name":"Malmud\u014fm",
    "gn:population":0,
    "gn:timezone":"Asia/Pyongyang",
    "iso:country":"KP",
    "name:kor_x_preferred":[
        "\ub9d0\ubb34\ub364"
    ],
    "name:und_x_variant":[
        "Mabun",
        "Malmud\u014fm"
    ],
    "wof:name":"Malmudom",
    "wof:placetype":"locality"
},
  "geometry": {"coordinates":[125.36667,39.06667],"type":"Point"}
}