{
  "type": "Feature",
  "properties": {
    "gn:admin1_code":"6.0",
    "gn:asciiname":"Toam-ni",
    "gn:country_code":"KP",
    "gn:dem":76,
    "gn:feature_class":"P",
    "gn:feature_code":"PPL",
    "gn:name":"Toam-ni",
    "gn:population":0,
    "gn:timezone":"Asia/Pyongyang",
    "iso:country":"KP",
    "name:eng_x_preferred":[
        "Toam"
    ],
    "name:eng_x_variant":[
        "Toam-ni"
    ],
    "name:und_x_variant":[
        "\ub3c4\uc554\ub9ac",
        "Toam-ni"
    ],
    "wof:name":"Toam",
    "wof:placetype":"locality"
},
  "geometry": {"coordinates":[125.23333,38.24083],"type":"Point"}
}