{
  "type": "Feature",
  "properties": {
    "gn:admin1_code":"6.0",
    "gn:asciiname":"Nach'i-ri",
    "gn:country_code":"KP",
    "gn:dem":210,
    "gn:feature_class":"P",
    "gn:feature_code":"PPL",
    "gn:name":"Nach\u2019i-ri",
    "gn:population":0,
    "gn:timezone":"Asia/Pyongyang",
    "iso:country":"KP",
    "wof:name":"Nach'i-ri",
    "wof:placetype":"locality"
},
  "geometry": {"coordinates":[125.61528,38.16361],"type":"Point"}
}