{
  "type": "Feature",
  "properties": {
    "gn:admin1_code":"0.0",
    "gn:asciiname":"Youn'gyo",
    "gn:country_code":"KP",
    "gn:dem":175,
    "gn:feature_class":"P",
    "gn:feature_code":"PPL",
    "gn:name":"Y\u014fun\u2019gyo",
    "gn:population":0,
    "gn:timezone":"Asia/Pyongyang",
    "iso:country":"KP",
    "name:kor_x_preferred":[
        "\uc5ec\uc6b4\uad50"
    ],
    "name:und_x_variant":[
        "Y\u014fun-ni",
        "Y\u014fun\u2019gyo"
    ],
    "wof:name":"Youn'gyo",
    "wof:placetype":"locality"
},
  "geometry": {"coordinates":[126.51667,38.68333],"type":"Point"}
}