{
  "type": "Feature",
  "properties": {
    "gn:admin1_code":"6.0",
    "gn:asciiname":"Umbyon-dong",
    "gn:country_code":"KP",
    "gn:dem":111,
    "gn:feature_class":"P",
    "gn:feature_code":"PPL",
    "gn:name":"\u016cmby\u014fn-dong",
    "gn:population":0,
    "gn:timezone":"Asia/Pyongyang",
    "iso:country":"KP",
    "wof:name":"Umbyon-dong",
    "wof:placetype":"locality"
},
  "geometry": {"coordinates":[125.59611,38.11972],"type":"Point"}
}