{
  "type": "Feature",
  "properties": {
    "gn:admin1_code":"13.0",
    "gn:asciiname":"Sinjon-ni",
    "gn:country_code":"KP",
    "gn:dem":1603,
    "gn:feature_class":"P",
    "gn:feature_code":"PPL",
    "gn:name":"Sinj\u014fn-ni",
    "gn:population":0,
    "gn:timezone":"Asia/Pyongyang",
    "iso:country":"KP",
    "name:eng_x_preferred":[
        "Sinjon"
    ],
    "name:eng_x_variant":[
        "Sinjon-ni"
    ],
    "wof:name":"Sinjon",
    "wof:placetype":"locality"
},
  "geometry": {"coordinates":[128.55000000000001,41.16667],"type":"Point"}
}