{
  "type": "Feature",
  "properties": {
    "iso:country":"KP",
    "ne:ADM0CAP":0.0,
    "ne:ADM0NAME":"North Korea",
    "ne:ADM0_A3":"PRK",
    "ne:ADM1NAME":"Ryanggang",
    "ne:ADMIN1_COD":0,
    "ne:CAPALT":0,
    "ne:CHANGED":0,
    "ne:CHECKME":0,
    "ne:COMPARE":0,
    "ne:DIFFASCII":0,
    "ne:ELEVATION":0.0,
    "ne:FEATURECLA":"Populated place",
    "ne:GEONAMEID":-1,
    "ne:GEONAMESNO":"No GeoNames match due to small population, not in GeoNames, or poor NEV placement.",
    "ne:GN_POP":0,
    "ne:GTOPO30":0.0,
    "ne:ISO_A2":"KP",
    "ne:LABELRANK":6,
    "ne:LATITUDE":40.81752,
    "ne:LONGITUDE":128.155319,
    "ne:LS_MATCH":1,
    "ne:LS_NAME":"Kimhyonggwon",
    "ne:MAX_AREAKM":5.0,
    "ne:MAX_AREAMI":2.0,
    "ne:MAX_BBXMAX":128.175,
    "ne:MAX_BBXMIN":128.141667,
    "ne:MAX_BBYMAX":40.825,
    "ne:MAX_BBYMIN":40.808333,
    "ne:MAX_NATSCA":10.0,
    "ne:MAX_PERKM":10.0,
    "ne:MAX_PERMI":6.0,
    "ne:MAX_POP10":3839,
    "ne:MAX_POP20":0,
    "ne:MAX_POP300":0,
    "ne:MAX_POP310":0,
    "ne:MAX_POP50":0,
    "ne:MEAN_BBXC":128.156548,
    "ne:MEAN_BBYC":40.816071,
    "ne:MEGACITY":0,
    "ne:MIN_AREAKM":5.0,
    "ne:MIN_AREAMI":2.0,
    "ne:MIN_BBXMAX":128.175,
    "ne:MIN_BBXMIN":128.141667,
    "ne:MIN_BBYMAX":40.825,
    "ne:MIN_BBYMIN":40.808333,
    "ne:MIN_PERKM":10.0,
    "ne:MIN_PERMI":6.0,
    "ne:NAME":"Kimhyonggwon",
    "ne:NAMEASCII":"Kimhyonggwon",
    "ne:NAMEDIFF":0,
    "ne:NATSCALE":10,
    "ne:POP1950":0,
    "ne:POP1955":0,
    "ne:POP1960":0,
    "ne:POP1965":0,
    "ne:POP1970":0,
    "ne:POP1975":0,
    "ne:POP1980":0,
    "ne:POP1985":0,
    "ne:POP1990":0,
    "ne:POP1995":0,
    "ne:POP2000":0,
    "ne:POP2005":0,
    "ne:POP2010":0,
    "ne:POP2015":0,
    "ne:POP2020":0,
    "ne:POP2025":0,
    "ne:POP2050":0,
    "ne:POP_MAX":3839,
    "ne:POP_MIN":3839,
    "ne:POP_OTHER":3703,
    "ne:RANK_MAX":4,
    "ne:RANK_MIN":4,
    "ne:SCALERANK":8,
    "ne:SOV0NAME":"Korea, North",
    "ne:SOV_A3":"PRK",
    "ne:UN_FID":0,
    "ne:UN_LAT":0.0,
    "ne:UN_LONG":0.0,
    "ne:WORLDCITY":0,
    "ne:min_zoom":7.0,
    "wof:name":"Kimhyonggwon",
    "wof:placetype":"locality"
},
  "geometry": {"coordinates":[128.15531937572575,40.8175201609871],"type":"Point"}
}