{
  "type": "Feature",
  "properties": {
    "gn:admin1_code":"6.0",
    "gn:asciiname":"Pon'gye",
    "gn:country_code":"KP",
    "gn:dem":72,
    "gn:feature_class":"P",
    "gn:feature_code":"PPL",
    "gn:name":"P\u014fn\u2019gye",
    "gn:population":0,
    "gn:timezone":"Asia/Pyongyang",
    "iso:country":"KP",
    "wof:name":"Pon'gye",
    "wof:placetype":"locality"
},
  "geometry": {"coordinates":[125.67278,38.26722],"type":"Point"}
}