{
  "type": "Feature",
  "properties": {
    "gn:admin1_code":"11.0",
    "gn:asciiname":"Taebong-ni",
    "gn:country_code":"KP",
    "gn:dem":106,
    "gn:feature_class":"P",
    "gn:feature_code":"PPL",
    "gn:name":"Taebong-ni",
    "gn:population":0,
    "gn:timezone":"Asia/Pyongyang",
    "iso:country":"KP",
    "name:eng_x_preferred":[
        "Taebong"
    ],
    "name:eng_x_variant":[
        "Taebong-ni"
    ],
    "name:und_x_variant":[
        "\ub300\ubd09\ub9ac",
        "Taebong-ni"
    ],
    "wof:name":"Taebong",
    "wof:placetype":"locality"
},
  "geometry": {"coordinates":[124.75833,39.87222],"type":"Point"}
}