{
  "type": "Feature",
  "properties": {
    "gn:admin1_code":"15.0",
    "gn:asciiname":"Ching-ni",
    "gn:country_code":"KP",
    "gn:dem":892,
    "gn:feature_class":"P",
    "gn:feature_code":"PPL",
    "gn:name":"Ching-ni",
    "gn:population":0,
    "gn:timezone":"Asia/Pyongyang",
    "iso:country":"KP",
    "name:und_x_variant":[
        "\uc9c1\ub9ac",
        "Ching-ni"
    ],
    "wof:name":"Ching-ni",
    "wof:placetype":"locality"
},
  "geometry": {"coordinates":[126.88028,40.21833],"type":"Point"}
}