{
  "type": "Feature",
  "properties": {
    "gn:admin1_code":"3.0",
    "gn:asciiname":"Hanha-dong",
    "gn:country_code":"KP",
    "gn:dem":1083,
    "gn:feature_class":"P",
    "gn:feature_code":"PPL",
    "gn:name":"Hanha-dong",
    "gn:population":0,
    "gn:timezone":"Asia/Pyongyang",
    "iso:country":"KP",
    "name:kor_x_preferred":[
        "\ud55c\ud558\ub3d9"
    ],
    "name:kor_x_variant":[
        "Kalbat-ma\u016dl",
        "\uac08\ubc2d\ub9c8\uc744"
    ],
    "name:und_x_variant":[
        "\ud55c\ud558\ub9ac",
        "Hanha-ri",
        "Hanha-dong"
    ],
    "wof:name":"Hanha-dong",
    "wof:placetype":"locality"
},
  "geometry": {"coordinates":[127.10696000000002,40.46454],"type":"Point"}
}