{
  "type": "Feature",
  "properties": {
    "gn:admin1_code":"7.0",
    "gn:asciiname":"T'ogyo-dong",
    "gn:country_code":"KP",
    "gn:dem":32,
    "gn:feature_class":"P",
    "gn:feature_code":"PPL",
    "gn:name":"T\u2019ogyo-dong",
    "gn:population":0,
    "gn:timezone":"Asia/Pyongyang",
    "iso:country":"KP",
    "name:und_x_variant":[
        "Keito",
        "Dokyo-do",
        "T\u2019ogyo-dong"
    ],
    "wof:name":"T'ogyo-dong",
    "wof:placetype":"locality"
},
  "geometry": {"coordinates":[125.735,38.5575],"type":"Point"}
}