{
  "type": "Feature",
  "properties": {
    "gn:admin1_code":"7.0",
    "gn:admin2_code":"T\u2019osan-gun",
    "gn:asciiname":"Sonomi",
    "gn:country_code":"KP",
    "gn:dem":108,
    "gn:feature_class":"P",
    "gn:feature_code":"PPL",
    "gn:name":"S\u014fn\u014fmi",
    "gn:population":0,
    "gn:timezone":"Asia/Pyongyang",
    "iso:country":"KP",
    "wof:name":"Sonomi",
    "wof:placetype":"locality"
},
  "geometry": {"coordinates":[126.65194,38.23167],"type":"Point"}
}