{
  "type": "Feature",
  "properties": {
    "gn:admin1_code":"9.0",
    "gn:asciiname":"Pongdae-gol",
    "gn:cc2":"KP",
    "gn:country_code":"KP",
    "gn:dem":620,
    "gn:feature_class":"P",
    "gn:feature_code":"PPL",
    "gn:name":"Pongdae-gol",
    "gn:population":0,
    "gn:timezone":"Asia/Pyongyang",
    "iso:country":"KP",
    "name:und_x_variant":[
        "Pongdae-kol",
        "\ubd09\ub300\uace8",
        "Pongdae-gol"
    ],
    "wof:name":"Pongdae-gol",
    "wof:placetype":"locality"
},
  "geometry": {"coordinates":[127.51167,38.80278],"type":"Point"}
}