{
  "type": "Feature",
  "properties": {
    "gn:admin1_code":"7.0",
    "gn:asciiname":"Pirye-dong",
    "gn:country_code":"KP",
    "gn:dem":13,
    "gn:feature_class":"P",
    "gn:feature_code":"PPL",
    "gn:name":"Pirye-dong",
    "gn:population":0,
    "gn:timezone":"Asia/Pyongyang",
    "iso:country":"KP",
    "name:kor_x_preferred":[
        "\ube44\ub840\ub3d9"
    ],
    "wof:name":"Pirye-dong",
    "wof:placetype":"locality"
},
  "geometry": {"coordinates":[125.62528,38.68833],"type":"Point"}
}