{
  "type": "Feature",
  "properties": {
    "gn:admin1_code":"6.0",
    "gn:admin2_code":"Sinw\u014fn-gun",
    "gn:asciiname":"Yomt'oe-dong",
    "gn:country_code":"KP",
    "gn:dem":127,
    "gn:feature_class":"P",
    "gn:feature_code":"PPL",
    "gn:name":"Y\u014fmt\u2019oe-dong",
    "gn:population":0,
    "gn:timezone":"Asia/Pyongyang",
    "iso:country":"KP",
    "wof:name":"Yomt'oe-dong",
    "wof:placetype":"locality"
},
  "geometry": {"coordinates":[125.75806,38.12889000000001],"type":"Point"}
}