{
  "type": "Feature",
  "properties": {
    "gn:admin1_code":"6.0",
    "gn:asciiname":"Konch'on",
    "gn:country_code":"KP",
    "gn:dem":50,
    "gn:feature_class":"P",
    "gn:feature_code":"PPL",
    "gn:name":"K\u014fnch\u2019\u014fn",
    "gn:population":0,
    "gn:timezone":"Asia/Pyongyang",
    "iso:country":"KP",
    "name:kor_x_preferred":[
        "\uac74\ucc9c"
    ],
    "name:und_x_variant":[
        "K\u014fnch\u2019\u014fn"
    ],
    "wof:name":"Konch'on",
    "wof:placetype":"locality"
},
  "geometry": {"coordinates":[125.05972,38.43917],"type":"Point"}
}