{
  "type": "Feature",
  "properties": {
    "gn:admin1_code":"15.0",
    "gn:asciiname":"Hanjol-li",
    "gn:country_code":"KP",
    "gn:dem":18,
    "gn:feature_class":"P",
    "gn:feature_code":"PPL",
    "gn:name":"Hanj\u014fl-li",
    "gn:population":0,
    "gn:timezone":"Asia/Pyongyang",
    "iso:country":"KP",
    "name:kor_x_preferred":[
        "\ud558\uc804\ub9ac"
    ],
    "name:kor_x_variant":[
        "Hanj\u014fl-li"
    ],
    "name:und_x_variant":[
        "Hanj\u014fn-ni"
    ],
    "wof:name":"Hanjol-li",
    "wof:placetype":"locality"
},
  "geometry": {"coordinates":[125.5925,38.69611],"type":"Point"}
}