{
  "type": "Feature",
  "properties": {
    "gn:admin1_code":"7.0",
    "gn:asciiname":"Pusuhyon",
    "gn:country_code":"KP",
    "gn:dem":27,
    "gn:feature_class":"P",
    "gn:feature_code":"PPL",
    "gn:name":"Pusuhy\u014fn",
    "gn:population":0,
    "gn:timezone":"Asia/Pyongyang",
    "iso:country":"KP",
    "name:kor_x_preferred":[
        "\ubd80\uc218\ud604"
    ],
    "name:kor_x_variant":[
        "Pusuhy\u014fn"
    ],
    "wof:name":"Pusuhyon",
    "wof:placetype":"locality"
},
  "geometry": {"coordinates":[125.67222,38.67833],"type":"Point"}
}