{
  "type": "Feature",
  "properties": {
    "gn:admin1_code":"12.0",
    "gn:asciiname":"Kodun'go-ri",
    "gn:country_code":"KP",
    "gn:dem":50,
    "gn:feature_class":"P",
    "gn:feature_code":"PPL",
    "gn:name":"Kod\u016dn\u2019g\u014f-ri",
    "gn:population":0,
    "gn:timezone":"Asia/Pyongyang",
    "iso:country":"KP",
    "name:kor_x_preferred":[
        "\uace0\ub4e0\uac70\ub9ac"
    ],
    "name:und_x_variant":[
        "Kod\u016dn\u2019g\u014f-ri",
        "Godeungeori"
    ],
    "wof:name":"Kodun'go-ri",
    "wof:placetype":"locality"
},
  "geometry": {"coordinates":[125.88605,39.10482],"type":"Point"}
}