{
  "type": "Feature",
  "properties": {
    "gn:admin1_code":"6.0",
    "gn:asciiname":"Koch'i-dong",
    "gn:country_code":"KP",
    "gn:dem":124,
    "gn:feature_class":"P",
    "gn:feature_code":"PPL",
    "gn:name":"Koch\u2019i-dong",
    "gn:population":0,
    "gn:timezone":"Asia/Pyongyang",
    "iso:country":"KP",
    "wof:name":"Koch'i-dong",
    "wof:placetype":"locality"
},
  "geometry": {"coordinates":[126.10056000000002,38.15167],"type":"Point"}
}