{
  "type": "Feature",
  "properties": {
    "gn:admin1_code":"11.0",
    "gn:asciiname":"Hyoja-dong",
    "gn:country_code":"KP",
    "gn:dem":108,
    "gn:feature_class":"P",
    "gn:feature_code":"PPL",
    "gn:name":"Hyoja-dong",
    "gn:population":0,
    "gn:timezone":"Asia/Pyongyang",
    "iso:country":"KP",
    "name:jpn_x_preferred":[
        "\u5b5d\u5b50\u6d1e"
    ],
    "name:kor_x_preferred":[
        "\ud6a8\uc790\ub3d9"
    ],
    "name:msa_x_preferred":[
        "Hyoja-dong"
    ],
    "name:sco_x_preferred":[
        "Hyoja-dong"
    ],
    "name:tha_x_preferred":[
        "\u0e41\u0e02\u0e27\u0e07\u0e2e\u0e42\u0e22\u0e08\u0e32"
    ],
    "name:und_x_variant":[
        "Hyoja-ri"
    ],
    "name:vie_x_preferred":[
        "Hyoja-dong"
    ],
    "wof:name":"Hyoja-dong",
    "wof:placetype":"locality"
},
  "geometry": {"coordinates":[124.95083,39.78472],"type":"Point"}
}