{
  "type": "Feature",
  "properties": {
    "gn:admin1_code":"6.0",
    "gn:asciiname":"Kuryong",
    "gn:country_code":"KP",
    "gn:dem":40,
    "gn:feature_class":"P",
    "gn:feature_code":"PPL",
    "gn:name":"Kuryong",
    "gn:population":0,
    "gn:timezone":"Asia/Pyongyang",
    "iso:country":"KP",
    "name:und_x_variant":[
        "\uad6c\ub8e1",
        "Kuryong"
    ],
    "wof:name":"Kuryong",
    "wof:placetype":"locality"
},
  "geometry": {"coordinates":[125.14749999999999,38.51056],"type":"Point"}
}