{
  "type": "Feature",
  "properties": {
    "gn:admin1_code":"1.0",
    "gn:asciiname":"Ch'ongnyang-dong",
    "gn:country_code":"KP",
    "gn:dem":249,
    "gn:feature_class":"P",
    "gn:feature_code":"PPL",
    "gn:name":"Ch\u2019\u014fngnyang-dong",
    "gn:population":0,
    "gn:timezone":"Asia/Pyongyang",
    "iso:country":"KP",
    "name:und_x_variant":[
        "\uccad\ub7c9\ub3d9",
        "Ch\u2019\u014fngnyang-dong"
    ],
    "wof:name":"Ch'ongnyang-dong",
    "wof:placetype":"locality"
},
  "geometry": {"coordinates":[126.28417,40.23972],"type":"Point"}
}