{
  "type": "Feature",
  "properties": {
    "gn:admin1_code":"6.0",
    "gn:admin2_code":"P'anmun-gun",
    "gn:asciiname":"Aep'o-ri",
    "gn:country_code":"KP",
    "gn:dem":45,
    "gn:feature_class":"P",
    "gn:feature_code":"PPL",
    "gn:name":"Aep\u2019o-ri",
    "gn:population":0,
    "gn:timezone":"Asia/Pyongyang",
    "iso:country":"KP",
    "wof:name":"Aep'o-ri",
    "wof:placetype":"locality"
},
  "geometry": {"coordinates":[126.64806000000002,37.83639],"type":"Point"}
}