{
  "type": "Feature",
  "properties": {
    "gn:admin1_code":"3.0",
    "gn:asciiname":"Yongp'a",
    "gn:country_code":"KP",
    "gn:dem":579,
    "gn:feature_class":"P",
    "gn:feature_code":"PPL",
    "gn:name":"Y\u014fngp\u2019a",
    "gn:population":0,
    "gn:timezone":"Asia/Pyongyang",
    "iso:country":"KP",
    "name:kor_x_preferred":[
        "\uc601\ud30c"
    ],
    "name:kor_x_variant":[
        "Y\u014fngp\u2019a"
    ],
    "wof:name":"Yongp'a",
    "wof:placetype":"locality"
},
  "geometry": {"coordinates":[126.94889000000001,39.28472],"type":"Point"}
}