{
  "type": "Feature",
  "properties": {
    "gn:admin1_code":"18.0",
    "gn:asciiname":"Ch'anghwa-dong",
    "gn:country_code":"KP",
    "gn:dem":30,
    "gn:feature_class":"P",
    "gn:feature_code":"PPL",
    "gn:name":"Ch\u2019anghwa-dong",
    "gn:population":0,
    "gn:timezone":"Asia/Pyongyang",
    "iso:country":"KP",
    "name:und_x_variant":[
        "\ucc3d\ud654\ub3d9",
        "Ch\u2019anghwa-dong",
        "Changhwadong"
    ],
    "wof:name":"Ch'anghwa-dong",
    "wof:placetype":"locality"
},
  "geometry": {"coordinates":[130.31846000000002,42.2474],"type":"Point"}
}