{
  "type": "Feature",
  "properties": {
    "gn:admin1_code":"6.0",
    "gn:asciiname":"Palli-dong",
    "gn:country_code":"KP",
    "gn:dem":51,
    "gn:feature_class":"P",
    "gn:feature_code":"PPL",
    "gn:name":"Palli-dong",
    "gn:population":0,
    "gn:timezone":"Asia/Pyongyang",
    "iso:country":"KP",
    "name:und_x_variant":[
        "\ubc1c\ub9ac\ub3d9",
        "Palli-dong"
    ],
    "wof:name":"Palli-dong",
    "wof:placetype":"locality"
},
  "geometry": {"coordinates":[125.19167,38.25028],"type":"Point"}
}