{
  "type": "Feature",
  "properties": {
    "gn:admin1_code":"15.0",
    "gn:admin2_code":"Mund\u0171k-kun",
    "gn:asciiname":"Panmal",
    "gn:country_code":"KP",
    "gn:dem":10,
    "gn:feature_class":"P",
    "gn:feature_code":"PPL",
    "gn:name":"Panmal",
    "gn:population":0,
    "gn:timezone":"Asia/Pyongyang",
    "iso:country":"KP",
    "name:und_x_variant":[
        "Pan-ma\u016dl",
        "Pan-ni",
        "Panmal"
    ],
    "wof:name":"Panmal",
    "wof:placetype":"locality"
},
  "geometry": {"coordinates":[125.40083,39.50222],"type":"Point"}
}