{
  "type": "Feature",
  "properties": {
    "gn:admin1_code":"9.0",
    "gn:asciiname":"Ch'unsal-li",
    "gn:country_code":"KP",
    "gn:dem":40,
    "gn:feature_class":"P",
    "gn:feature_code":"PPL",
    "gn:name":"Ch\u2019unsal-li",
    "gn:population":0,
    "gn:timezone":"Asia/Pyongyang",
    "iso:country":"KP",
    "name:und_x_variant":[
        "Ch\u2019unsal-li",
        "\ucd98\uc0b0\ub9ac"
    ],
    "wof:name":"Ch'unsal-li",
    "wof:placetype":"locality"
},
  "geometry": {"coordinates":[127.44875999999999,39.11957],"type":"Point"}
}