{
  "type": "Feature",
  "properties": {
    "gn:admin1_code":"9.0",
    "gn:asciiname":"Oksuhyon",
    "gn:country_code":"KP",
    "gn:dem":600,
    "gn:feature_class":"P",
    "gn:feature_code":"PPL",
    "gn:name":"Oksuhy\u014fn",
    "gn:population":0,
    "gn:timezone":"Asia/Pyongyang",
    "iso:country":"KP",
    "name:kor_x_preferred":[
        "\uc625\uc218\ud604"
    ],
    "name:kor_x_variant":[
        "Oksuhy\u014fn"
    ],
    "wof:name":"Oksuhyon",
    "wof:placetype":"locality"
},
  "geometry": {"coordinates":[127.31917,38.80083],"type":"Point"}
}