{
  "type": "Feature",
  "properties": {
    "gn:admin1_code":"17.0",
    "gn:asciiname":"Tanbau",
    "gn:country_code":"KP",
    "gn:dem":468,
    "gn:feature_class":"P",
    "gn:feature_code":"PPL",
    "gn:name":"Tanbau",
    "gn:population":0,
    "gn:timezone":"Asia/Pyongyang",
    "iso:country":"KP",
    "name:und_x_variant":[
        "\ub2e8\ubc14\uc6b0",
        "Tanbau"
    ],
    "wof:name":"Tanbau",
    "wof:placetype":"locality"
},
  "geometry": {"coordinates":[129.34,41.35528],"type":"Point"}
}