{
  "type": "Feature",
  "properties": {
    "gn:admin1_code":"15.0",
    "gn:asciiname":"Hoe-gol",
    "gn:country_code":"KP",
    "gn:dem":454,
    "gn:feature_class":"P",
    "gn:feature_code":"PPL",
    "gn:name":"Hoe-gol",
    "gn:population":0,
    "gn:timezone":"Asia/Pyongyang",
    "iso:country":"KP",
    "name:und_x_variant":[
        "\ud68c\uace8",
        "Hoe-gol"
    ],
    "wof:name":"Hoe-gol",
    "wof:placetype":"locality"
},
  "geometry": {"coordinates":[126.47083000000001,39.91278],"type":"Point"}
}