{
  "type": "Feature",
  "properties": {
    "gn:admin1_code":"1.0",
    "gn:asciiname":"Kumch'ang-dong",
    "gn:country_code":"KP",
    "gn:dem":146,
    "gn:feature_class":"P",
    "gn:feature_code":"PPL",
    "gn:name":"K\u016dmch\u2019ang-dong",
    "gn:population":0,
    "gn:timezone":"Asia/Pyongyang",
    "iso:country":"KP",
    "name:und_x_variant":[
        "\uae08\ucc3d\ub3d9",
        "K\u016dmch\u2019ang-dong"
    ],
    "wof:name":"Kumch'ang-dong",
    "wof:placetype":"locality"
},
  "geometry": {"coordinates":[125.65555999999999,40.73278],"type":"Point"}
}