{
  "type": "Feature",
  "properties": {
    "gn:admin1_code":"9.0",
    "gn:asciiname":"Kuryong-ni",
    "gn:country_code":"KP",
    "gn:dem":569,
    "gn:feature_class":"P",
    "gn:feature_code":"PPL",
    "gn:name":"Kuryong-ni",
    "gn:population":0,
    "gn:timezone":"Asia/Pyongyang",
    "iso:country":"KP",
    "name:eng_x_preferred":[
        "Kuryong"
    ],
    "name:eng_x_variant":[
        "Kuryong-ni"
    ],
    "name:kor_x_preferred":[
        "\uad6c\ub8e1\ub9ac"
    ],
    "wof:name":"Kuryong",
    "wof:placetype":"locality"
},
  "geometry": {"coordinates":[127.21111000000001,38.91111],"type":"Point"}
}