{
  "type": "Feature",
  "properties": {
    "gn:admin1_code":"9.0",
    "gn:asciiname":"Wisan-gol",
    "gn:country_code":"KP",
    "gn:dem":744,
    "gn:feature_class":"P",
    "gn:feature_code":"PPL",
    "gn:name":"Wisan-gol",
    "gn:population":0,
    "gn:timezone":"Asia/Pyongyang",
    "iso:country":"KP",
    "name:und_x_variant":[
        "Wisan-kol",
        "\uc704\uc0b0\uace8",
        "Wisan-gol"
    ],
    "wof:name":"Wisan-gol",
    "wof:placetype":"locality"
},
  "geometry": {"coordinates":[127.56610999999999,38.86417],"type":"Point"}
}