{
  "type": "Feature",
  "properties": {
    "gn:admin1_code":"6.0",
    "gn:asciiname":"Sangsongson",
    "gn:country_code":"KP",
    "gn:dem":109,
    "gn:feature_class":"P",
    "gn:feature_code":"PPL",
    "gn:name":"Sangsongs\u014fn",
    "gn:population":0,
    "gn:timezone":"Asia/Pyongyang",
    "iso:country":"KP",
    "name:und_x_variant":[
        "\uc0c1\uc1a1\uc120",
        "Sangsongs\u014fn"
    ],
    "wof:name":"Sangsongson",
    "wof:placetype":"locality"
},
  "geometry": {"coordinates":[125.35861,38.22083],"type":"Point"}
}