{
  "type": "Feature",
  "properties": {
    "gn:admin1_code":"7.0",
    "gn:asciiname":"Wadae-dong",
    "gn:country_code":"KP",
    "gn:dem":113,
    "gn:feature_class":"P",
    "gn:feature_code":"PPL",
    "gn:name":"Wadae-dong",
    "gn:population":0,
    "gn:timezone":"Asia/Pyongyang",
    "iso:country":"KP",
    "wof:name":"Wadae-dong",
    "wof:placetype":"locality"
},
  "geometry": {"coordinates":[126.78471999999999,38.25417],"type":"Point"}
}