{
  "type": "Feature",
  "properties": {
    "gn:admin1_code":"7.0",
    "gn:asciiname":"Sangdongmak",
    "gn:country_code":"KP",
    "gn:dem":134,
    "gn:feature_class":"P",
    "gn:feature_code":"PPL",
    "gn:name":"Sangdongmak",
    "gn:population":0,
    "gn:timezone":"Asia/Pyongyang",
    "iso:country":"KP",
    "name:und_x_variant":[
        "Song-tongmak",
        "Sangdongmak"
    ],
    "wof:name":"Sangdongmak",
    "wof:placetype":"locality"
},
  "geometry": {"coordinates":[126.09389,38.30333],"type":"Point"}
}