{
  "type": "Feature",
  "properties": {
    "gn:admin1_code":"15.0",
    "gn:asciiname":"Kwiil-li",
    "gn:country_code":"KP",
    "gn:dem":296,
    "gn:feature_class":"P",
    "gn:feature_code":"PPL",
    "gn:name":"Kwiil-li",
    "gn:population":0,
    "gn:timezone":"Asia/Pyongyang",
    "iso:country":"KP",
    "name:kor_x_preferred":[
        "\uadc0\uc778\ub9ac"
    ],
    "wof:name":"Kwiil-li",
    "wof:placetype":"locality"
},
  "geometry": {"coordinates":[126.45667,39.10972],"type":"Point"}
}