{
  "type": "Feature",
  "properties": {
    "gn:admin1_code":"9.0",
    "gn:asciiname":"Chohyon-dong",
    "gn:cc2":"KP",
    "gn:country_code":"KP",
    "gn:dem":329,
    "gn:feature_class":"P",
    "gn:feature_code":"PPL",
    "gn:name":"Ch\u014fhy\u014fn-dong",
    "gn:population":0,
    "gn:timezone":"Asia/Pyongyang",
    "iso:country":"KP",
    "name:und_x_variant":[
        "Changp\u2019o-dong",
        "Ch\u014fhy\u014fn-dong"
    ],
    "wof:name":"Chohyon-dong",
    "wof:placetype":"locality"
},
  "geometry": {"coordinates":[126.96361,38.43417],"type":"Point"}
}