{
  "type": "Feature",
  "properties": {
    "gn:admin1_code":"6.0",
    "gn:asciiname":"Haech'anggol",
    "gn:country_code":"KP",
    "gn:dem":22,
    "gn:feature_class":"P",
    "gn:feature_code":"PPL",
    "gn:name":"Haech\u2019anggol",
    "gn:population":0,
    "gn:timezone":"Asia/Pyongyang",
    "iso:country":"KP",
    "name:kor_x_preferred":[
        "\ud574\ucc3d\uace8"
    ],
    "name:und_x_variant":[
        "Haech\u2019ang-dong",
        "Haech\u2019anggol"
    ],
    "wof:name":"Haech'anggol",
    "wof:placetype":"locality"
},
  "geometry": {"coordinates":[125.80194,37.97694],"type":"Point"}
}