{
  "type": "Feature",
  "properties": {
    "gn:admin1_code":"1.0",
    "gn:asciiname":"Maek-tong",
    "gn:country_code":"KP",
    "gn:dem":381,
    "gn:feature_class":"P",
    "gn:feature_code":"PPL",
    "gn:name":"Maek-tong",
    "gn:population":0,
    "gn:timezone":"Asia/Pyongyang",
    "iso:country":"KP",
    "name:und_x_variant":[
        "Maek-dong",
        "\ub9e5\ub3d9",
        "Maek-tong"
    ],
    "wof:name":"Maek-tong",
    "wof:placetype":"locality"
},
  "geometry": {"coordinates":[126.58833,41.0125],"type":"Point"}
}