{
  "type": "Feature",
  "properties": {
    "gn:admin1_code":"3.0",
    "gn:asciiname":"Tabo-ri",
    "gn:country_code":"KP",
    "gn:dem":167,
    "gn:feature_class":"P",
    "gn:feature_code":"PPL",
    "gn:name":"Tabo-ri",
    "gn:population":0,
    "gn:timezone":"Asia/Pyongyang",
    "iso:country":"KP",
    "name:und_x_variant":[
        "\ub2e4\ubcf4\ub9ac"
    ],
    "wof:name":"Tabo-ri",
    "wof:placetype":"locality"
},
  "geometry": {"coordinates":[128.54058999999998,40.28797],"type":"Point"}
}