{
  "type": "Feature",
  "properties": {
    "gn:admin1_code":"11.0",
    "gn:asciiname":"Tuung-gol",
    "gn:country_code":"KP",
    "gn:dem":17,
    "gn:feature_class":"P",
    "gn:feature_code":"PPL",
    "gn:name":"Tu\u016dng-gol",
    "gn:population":0,
    "gn:timezone":"Asia/Pyongyang",
    "iso:country":"KP",
    "name:und_x_variant":[
        "\ub450\uc751\uace8",
        "Tu\u016dng-gol"
    ],
    "wof:name":"Tuung-gol",
    "wof:placetype":"locality"
},
  "geometry": {"coordinates":[124.43111,39.99278],"type":"Point"}
}