{
  "type": "Feature",
  "properties": {
    "gn:admin1_code":"7.0",
    "gn:asciiname":"Pulch'i-gol",
    "gn:country_code":"KP",
    "gn:dem":80,
    "gn:feature_class":"P",
    "gn:feature_code":"PPL",
    "gn:name":"Pulch\u2019i-gol",
    "gn:population":0,
    "gn:timezone":"Asia/Pyongyang",
    "iso:country":"KP",
    "wof:name":"Pulch'i-gol",
    "wof:placetype":"locality"
},
  "geometry": {"coordinates":[126.01361,38.47444],"type":"Point"}
}