{
  "type": "Feature",
  "properties": {
    "gn:admin1_code":"15.0",
    "gn:asciiname":"Saejanggo-ri",
    "gn:cc2":"KP",
    "gn:country_code":"KP",
    "gn:dem":10,
    "gn:feature_class":"P",
    "gn:feature_code":"PPL",
    "gn:name":"Saejangg\u014f-ri",
    "gn:population":0,
    "gn:timezone":"Asia/Pyongyang",
    "iso:country":"KP",
    "name:und_x_variant":[
        "Sinjangga",
        "Saejangg\u014f-ri"
    ],
    "wof:name":"Saejanggo-ri",
    "wof:placetype":"locality"
},
  "geometry": {"coordinates":[125.49527999999999,38.8925],"type":"Point"}
}