{
  "type": "Feature",
  "properties": {
    "gn:admin1_code":"9.0",
    "gn:asciiname":"Pol-li",
    "gn:country_code":"KP",
    "gn:dem":518,
    "gn:feature_class":"P",
    "gn:feature_code":"PPL",
    "gn:name":"Pol-li",
    "gn:population":0,
    "gn:timezone":"Asia/Pyongyang",
    "iso:country":"KP",
    "name:und_x_variant":[
        "\ubcf8\ub9ac",
        "Pol-li"
    ],
    "wof:name":"Pol-li",
    "wof:placetype":"locality"
},
  "geometry": {"coordinates":[127.79277999999999,38.745],"type":"Point"}
}