{
  "type": "Feature",
  "properties": {
    "gn:admin1_code":"9.0",
    "gn:asciiname":"Ongjom-ni",
    "gn:country_code":"KP",
    "gn:dem":117,
    "gn:feature_class":"P",
    "gn:feature_code":"PPL",
    "gn:name":"Ongj\u014fm-ni",
    "gn:population":0,
    "gn:timezone":"Asia/Pyongyang",
    "iso:country":"KP",
    "name:und_x_variant":[
        "Ongj\u014fm-ni",
        "\uc639\uc810\ub9ac"
    ],
    "wof:name":"Ongjom-ni",
    "wof:placetype":"locality"
},
  "geometry": {"coordinates":[127.37595,39.0543],"type":"Point"}
}