{
  "type": "Feature",
  "properties": {
    "gn:admin1_code":"17.0",
    "gn:asciiname":"Chongsal-li",
    "gn:country_code":"KP",
    "gn:dem":121,
    "gn:feature_class":"P",
    "gn:feature_code":"PPLL",
    "gn:name":"Chongsal-li",
    "gn:population":0,
    "gn:timezone":"Asia/Pyongyang",
    "iso:country":"KP",
    "name:und_x_variant":[
        "Chongsan-ni",
        "Chongsan-dong",
        "\uc885\uc0b0\ub9ac",
        "Chongsal-li"
    ],
    "wof:name":"Chongsal-li",
    "wof:placetype":"locality"
},
  "geometry": {"coordinates":[130.10166999999998,42.5275],"type":"Point"}
}