{
  "type": "Feature",
  "properties": {
    "gn:admin1_code":"6.0",
    "gn:asciiname":"To-dong",
    "gn:country_code":"KP",
    "gn:dem":82,
    "gn:feature_class":"P",
    "gn:feature_code":"PPL",
    "gn:name":"To-dong",
    "gn:population":0,
    "gn:timezone":"Asia/Pyongyang",
    "iso:country":"KP",
    "name:kor_x_preferred":[
        "\ub3c4\ub3d9"
    ],
    "wof:name":"To-dong",
    "wof:placetype":"locality"
},
  "geometry": {"coordinates":[125.34999999999999,38.56667],"type":"Point"}
}