{
  "type": "Feature",
  "properties": {
    "gn:admin1_code":"11.0",
    "gn:asciiname":"Oryongp'o",
    "gn:country_code":"KP",
    "gn:dem":69,
    "gn:feature_class":"P",
    "gn:feature_code":"PPL",
    "gn:name":"\u014eryongp\u2019o",
    "gn:population":0,
    "gn:timezone":"Asia/Pyongyang",
    "iso:country":"KP",
    "name:und_x_variant":[
        "Gy\u014dry\u016bho",
        "Oyong",
        "\uc5b4\ub8e1\ud3ec",
        "\u014eryongp\u2019o"
    ],
    "wof:name":"Oryongp'o",
    "wof:placetype":"locality"
},
  "geometry": {"coordinates":[126.05500000000001,39.90167],"type":"Point"}
}