{
  "type": "Feature",
  "properties": {
    "gn:admin1_code":"7.0",
    "gn:asciiname":"Hwaya-ri",
    "gn:country_code":"KP",
    "gn:dem":147,
    "gn:feature_class":"P",
    "gn:feature_code":"PPL",
    "gn:name":"Hwaya-ri",
    "gn:population":0,
    "gn:timezone":"Asia/Pyongyang",
    "iso:country":"KP",
    "name:kor_x_preferred":[
        "\ud654\uc57c\ub9ac"
    ],
    "wof:name":"Hwaya-ri",
    "wof:placetype":"locality"
},
  "geometry": {"coordinates":[126.36667,38.53333],"type":"Point"}
}