{
  "type": "Feature",
  "properties": {
    "gn:admin1_code":"12.0",
    "gn:asciiname":"Toksugol",
    "gn:country_code":"KP",
    "gn:dem":47,
    "gn:feature_class":"P",
    "gn:feature_code":"PPL",
    "gn:name":"T\u014fksugol",
    "gn:population":0,
    "gn:timezone":"Asia/Pyongyang",
    "iso:country":"KP",
    "name:kor_x_preferred":[
        "T\u014fksugol"
    ],
    "name:kor_x_variant":[
        "\ub355\uc218\uace8"
    ],
    "name:und_x_variant":[
        "Deoksugol"
    ],
    "wof:name":"Toksugol",
    "wof:placetype":"locality"
},
  "geometry": {"coordinates":[125.81077999999999,39.09427],"type":"Point"}
}