{
  "type": "Feature",
  "properties": {
    "gn:admin1_code":"9.0",
    "gn:asciiname":"Ponghyol-li",
    "gn:country_code":"KP",
    "gn:dem":468,
    "gn:feature_class":"P",
    "gn:feature_code":"PPL",
    "gn:name":"Ponghy\u014fl-li",
    "gn:population":0,
    "gn:timezone":"Asia/Pyongyang",
    "iso:country":"KP",
    "name:und_x_variant":[
        "Ponghy\u014fn-ni",
        "\ubd09\ud604\ub9ac",
        "Ponghy\u014fl-li"
    ],
    "wof:name":"Ponghyol-li",
    "wof:placetype":"locality"
},
  "geometry": {"coordinates":[127.95583000000001,38.51194],"type":"Point"}
}