{
  "type": "Feature",
  "properties": {
    "gn:admin1_code":"3.0",
    "gn:admin2_code":"Puj\u014fn-gun",
    "gn:asciiname":"Sonsondong-ni",
    "gn:country_code":"KP",
    "gn:dem":1183,
    "gn:feature_class":"P",
    "gn:feature_code":"PPL",
    "gn:name":"S\u014fnsond\u014fng-ni",
    "gn:population":0,
    "gn:timezone":"Asia/Pyongyang",
    "iso:country":"KP",
    "name:eng_x_preferred":[
        "Sonsondong"
    ],
    "name:eng_x_variant":[
        "Sonsondong-ni"
    ],
    "name:kor_x_preferred":[
        "\uc120\uc190\ub355\ub9ac"
    ],
    "name:kor_x_variant":[
        "S\u014fnsond\u014fng-ni"
    ],
    "wof:name":"Sonsondong",
    "wof:placetype":"locality"
},
  "geometry": {"coordinates":[127.46333,40.97944],"type":"Point"}
}