{
  "type": "Feature",
  "properties": {
    "gn:admin1_code":"0.0",
    "gn:asciiname":"Ch'oryang-ni",
    "gn:country_code":"KP",
    "gn:dem":26,
    "gn:feature_class":"P",
    "gn:feature_code":"PPL",
    "gn:name":"Ch\u2019oryang-ni",
    "gn:population":0,
    "gn:timezone":"Asia/Pyongyang",
    "iso:country":"KP",
    "name:eng_x_preferred":[
        "Ch'oryang"
    ],
    "name:eng_x_variant":[
        "Ch'oryang-ni"
    ],
    "name:kor_x_preferred":[
        "\ucd08\ub7c9\ub9ac"
    ],
    "name:kor_x_variant":[
        "Ch\u2019oryang-ni"
    ],
    "wof:name":"Ch'oryang",
    "wof:placetype":"locality"
},
  "geometry": {"coordinates":[125.56056,39.7225],"type":"Point"}
}