{
  "type": "Feature",
  "properties": {
    "gn:admin1_code":"3.0",
    "gn:asciiname":"Kwansongjon",
    "gn:country_code":"KP",
    "gn:dem":18,
    "gn:feature_class":"P",
    "gn:feature_code":"PPL",
    "gn:name":"Kwans\u014fngj\u014fn",
    "gn:population":0,
    "gn:timezone":"Asia/Pyongyang",
    "iso:country":"KP",
    "name:und_x_variant":[
        "\uad00\uc131\uc804",
        "Kwans\u014fngj\u014fn"
    ],
    "wof:name":"Kwansongjon",
    "wof:placetype":"locality"
},
  "geometry": {"coordinates":[127.74444,39.90167],"type":"Point"}
}