{
  "type": "Feature",
  "properties": {
    "iso:country":"KP",
    "name:kor_x_preferred":[
        "\uc544\uc591\ub9ac"
    ],
    "name:unk_x_variant":[
        "Gay\u014d-ri"
    ],
    "qs:gn_country":"KP",
    "qs:gn_fcode":"PPL",
    "qs:gn_pop":16104,
    "qs:name":"Ayang-ni",
    "qs:name_adm0":"North Korea",
    "qs:name_adm1":"Hwanghae-namdo",
    "qs:photos":0,
    "qs:photos_1k":0,
    "qs:photos_9k":1,
    "qs:photos_9r":3,
    "qs:photos_all":98,
    "qs:photos_sr":0,
    "qs:placetype":"Town",
    "qs:pop_sr":"6",
    "qs:woe_adm0":23424865,
    "wof:name":"Ayang-ni",
    "wof:placetype":"locality",
    "wof:population":16104
},
  "geometry": {"coordinates":[125.78,38.24306],"type":"Point"}
}