{
  "type": "Feature",
  "properties": {
    "gn:admin1_code":"17.0",
    "gn:asciiname":"Yongch'ol-lodongjagu",
    "gn:country_code":"KP",
    "gn:dem":16,
    "gn:feature_class":"P",
    "gn:feature_code":"PPLL",
    "gn:name":"Yongch\u2019\u014fl-lodongjagu",
    "gn:population":0,
    "gn:timezone":"Asia/Pyongyang",
    "iso:country":"KP",
    "name:und_x_variant":[
        "Yongch\u2019\u014fn-ni",
        "Yongch\u2019\u014fl-li",
        "Yongch\u2019\u014fn-dong",
        "\ub8e1\ucc9c\ub85c\ub3d9\uc790\uad6c",
        "Yongch\u2019\u014fl-lodongjagu"
    ],
    "wof:name":"Yongch'ol-lodongjagu",
    "wof:placetype":"locality"
},
  "geometry": {"coordinates":[129.60333,41.56417],"type":"Point"}
}