{
  "type": "Feature",
  "properties": {
    "gn:admin1_code":"11.0",
    "gn:asciiname":"Myongsang-ni",
    "gn:country_code":"KP",
    "gn:dem":296,
    "gn:feature_class":"P",
    "gn:feature_code":"PPL",
    "gn:name":"My\u014fngsang-ni",
    "gn:population":0,
    "gn:timezone":"Asia/Pyongyang",
    "iso:country":"KP",
    "name:und_x_variant":[
        "My\u014fngsang-dong",
        "\uba85\uc0c1\ub9ac",
        "My\u014fngsang-ni"
    ],
    "wof:name":"Myongsang-ni",
    "wof:placetype":"locality"
},
  "geometry": {"coordinates":[125.11333,40.27667],"type":"Point"}
}