{
  "type": "Feature",
  "properties": {
    "gn:admin1_code":"7.0",
    "gn:asciiname":"Unp'a-up",
    "gn:country_code":"KP",
    "gn:dem":28,
    "gn:feature_class":"P",
    "gn:feature_code":"PPL",
    "gn:name":"\u016cnp\u2019a-\u016dp",
    "gn:population":0,
    "gn:timezone":"Asia/Pyongyang",
    "iso:country":"KP",
    "name:und_x_variant":[
        "Gimpa-ri",
        "Unp\u2019a",
        "Gimba-ri",
        "\u016cnp\u2019a-ri",
        "\u016cnp\u2019a-\u016dp"
    ],
    "wof:name":"Unp'a-up",
    "wof:placetype":"locality"
},
  "geometry": {"coordinates":[125.7925,38.40889],"type":"Point"}
}