{
  "type": "Feature",
  "properties": {
    "gn:admin1_code":"6.0",
    "gn:asciiname":"Ogul-li",
    "gn:country_code":"KP",
    "gn:dem":17,
    "gn:feature_class":"P",
    "gn:feature_code":"PPL",
    "gn:name":"Og\u016dl-li",
    "gn:population":0,
    "gn:timezone":"Asia/Pyongyang",
    "iso:country":"KP",
    "name:und_x_variant":[
        "\uc625\uc740\ub9ac",
        "Og\u016dn-ni",
        "Og\u016dl-li"
    ],
    "wof:name":"Ogul-li",
    "wof:placetype":"locality"
},
  "geometry": {"coordinates":[125.52443999999998,37.78083],"type":"Point"}
}