{
  "type": "Feature",
  "properties": {
    "gn:admin1_code":"3.0",
    "gn:asciiname":"Sinsong-ni",
    "gn:country_code":"KP",
    "gn:dem":874,
    "gn:feature_class":"P",
    "gn:feature_code":"PPL",
    "gn:name":"Sins\u014fng-ni",
    "gn:population":0,
    "gn:timezone":"Asia/Pyongyang",
    "iso:country":"KP",
    "name:und_x_variant":[
        "\ubb3c\ubc2d\uace8",
        "Sins\u014fng-ni"
    ],
    "wof:name":"Sinsong-ni",
    "wof:placetype":"locality"
},
  "geometry": {"coordinates":[128.57138999999998,40.88889],"type":"Point"}
}