{
  "type": "Feature",
  "properties": {
    "gn:admin1_code":"15.0",
    "gn:asciiname":"Paeksok-tong",
    "gn:country_code":"KP",
    "gn:dem":57,
    "gn:feature_class":"P",
    "gn:feature_code":"PPL",
    "gn:name":"Paeks\u014fk-tong",
    "gn:population":0,
    "gn:timezone":"Asia/Pyongyang",
    "iso:country":"KP",
    "name:eng_x_preferred":[
        "Paeksok"
    ],
    "name:eng_x_variant":[
        "Paeksok-tong"
    ],
    "wof:name":"Paeksok",
    "wof:placetype":"locality"
},
  "geometry": {"coordinates":[125.47111,39.13417],"type":"Point"}
}