{
  "type": "Feature",
  "properties": {
    "gn:admin1_code":"6.0",
    "gn:asciiname":"Ch'angbau-dong",
    "gn:country_code":"KP",
    "gn:dem":16,
    "gn:feature_class":"P",
    "gn:feature_code":"PPL",
    "gn:name":"Ch\u2019angbau-dong",
    "gn:population":0,
    "gn:timezone":"Asia/Pyongyang",
    "iso:country":"KP",
    "name:und_x_variant":[
        "Saugan-do",
        "\ucc3d\ubc14\uc6b0\ub3d9",
        "Ch\u2019angbau-dong"
    ],
    "wof:name":"Ch'angbau-dong",
    "wof:placetype":"locality"
},
  "geometry": {"coordinates":[124.69722,38.11722],"type":"Point"}
}