{
  "type": "Feature",
  "properties": {
    "gn:admin1_code":"7.0",
    "gn:asciiname":"Yogang-gol",
    "gn:country_code":"KP",
    "gn:dem":51,
    "gn:feature_class":"P",
    "gn:feature_code":"PPL",
    "gn:name":"Yogang-gol",
    "gn:population":0,
    "gn:timezone":"Asia/Pyongyang",
    "iso:country":"KP",
    "name:kor_x_preferred":[
        "\uc694\uac15\uace8"
    ],
    "name:und_x_variant":[
        "Yogang-kol",
        "Yogang-dong",
        "Yogang-gol"
    ],
    "wof:name":"Yogang-gol",
    "wof:placetype":"locality"
},
  "geometry": {"coordinates":[126.50639,38.29083],"type":"Point"}
}