{
  "type": "Feature",
  "properties": {
    "gn:admin1_code":"3.0",
    "gn:asciiname":"Mun-dong",
    "gn:country_code":"KP",
    "gn:dem":46,
    "gn:feature_class":"P",
    "gn:feature_code":"PPL",
    "gn:name":"Mun-dong",
    "gn:population":0,
    "gn:timezone":"Asia/Pyongyang",
    "iso:country":"KP",
    "name:und_x_variant":[
        "\ubb38\ub3d9"
    ],
    "wof:name":"Mun-dong",
    "wof:placetype":"locality"
},
  "geometry": {"coordinates":[128.55611000000002,40.19972],"type":"Point"}
}