{
  "type": "Feature",
  "properties": {
    "gn:admin1_code":"6.0",
    "gn:asciiname":"Changam-ni",
    "gn:country_code":"KP",
    "gn:dem":36,
    "gn:feature_class":"P",
    "gn:feature_code":"PPL",
    "gn:name":"Changam-ni",
    "gn:population":0,
    "gn:timezone":"Asia/Pyongyang",
    "iso:country":"KP",
    "name:kor_x_preferred":[
        "\uc7a5\uc554\ub9ac"
    ],
    "wof:name":"Changam-ni",
    "wof:placetype":"locality"
},
  "geometry": {"coordinates":[124.99388999999999,38.41833],"type":"Point"}
}