{
  "type": "Feature",
  "properties": {
    "gn:admin1_code":"6.0",
    "gn:asciiname":"Osal-li",
    "gn:country_code":"KP",
    "gn:dem":24,
    "gn:feature_class":"P",
    "gn:feature_code":"PPL",
    "gn:name":"Osal-li",
    "gn:population":0,
    "gn:timezone":"Asia/Pyongyang",
    "iso:country":"KP",
    "name:und_x_variant":[
        "\uc624\uc0b0\ub9ac",
        "Osan-ni",
        "Osal-li"
    ],
    "wof:name":"Osal-li",
    "wof:placetype":"locality"
},
  "geometry": {"coordinates":[125.55,37.89694],"type":"Point"}
}