{
  "type": "Feature",
  "properties": {
    "gn:admin1_code":"3.0",
    "gn:asciiname":"Songmul-li",
    "gn:country_code":"KP",
    "gn:dem":23,
    "gn:feature_class":"P",
    "gn:feature_code":"PPL",
    "gn:name":"Songmul-li",
    "gn:population":0,
    "gn:timezone":"Asia/Pyongyang",
    "iso:country":"KP",
    "name:und_x_variant":[
        "\uc1a1\ubb38\ub9ac",
        "Songmul-li"
    ],
    "wof:name":"Songmul-li",
    "wof:placetype":"locality"
},
  "geometry": {"coordinates":[127.46861,39.61778],"type":"Point"}
}