{
  "type": "Feature",
  "properties": {
    "gn:admin1_code":"9.0",
    "gn:asciiname":"Sangp'ung-dong",
    "gn:country_code":"KP",
    "gn:dem":443,
    "gn:feature_class":"P",
    "gn:feature_code":"PPL",
    "gn:name":"Sangp\u2019ung-dong",
    "gn:population":0,
    "gn:timezone":"Asia/Pyongyang",
    "iso:country":"KP",
    "name:und_x_variant":[
        "\uc0c1\ud48d\ub3d9",
        "Sangp\u2019ung-dong"
    ],
    "wof:name":"Sangp'ung-dong",
    "wof:placetype":"locality"
},
  "geometry": {"coordinates":[127.54472,38.3475],"type":"Point"}
}