{
  "type": "Feature",
  "properties": {
    "gn:admin1_code":"9.0",
    "gn:asciiname":"Chungsan",
    "gn:country_code":"KP",
    "gn:dem":475,
    "gn:feature_class":"P",
    "gn:feature_code":"PPL",
    "gn:name":"Chungsan",
    "gn:population":0,
    "gn:timezone":"Asia/Pyongyang",
    "iso:country":"KP",
    "name:und_x_variant":[
        "\uc911\uc0b0",
        "Chungsan"
    ],
    "wof:name":"Chungsan",
    "wof:placetype":"locality"
},
  "geometry": {"coordinates":[126.93722,38.7775],"type":"Point"}
}