{
  "type": "Feature",
  "properties": {
    "gn:admin1_code":"15.0",
    "gn:asciiname":"Kumch'ang-ni",
    "gn:country_code":"KP",
    "gn:dem":63,
    "gn:feature_class":"P",
    "gn:feature_code":"PPL",
    "gn:name":"K\u016dmch\u2019ang-ni",
    "gn:population":0,
    "gn:timezone":"Asia/Pyongyang",
    "iso:country":"KP",
    "name:kor_x_preferred":[
        "\uae08\ucc3d\ub9ac"
    ],
    "name:und_x_variant":[
        "K\u016dmch\u2019ang-ni"
    ],
    "wof:name":"Kumch'ang-ni",
    "wof:placetype":"locality"
},
  "geometry": {"coordinates":[126.07693999999999,39.38139],"type":"Point"}
}