{
  "type": "Feature",
  "properties": {
    "gn:admin1_code":"9.0",
    "gn:asciiname":"Namak-kol",
    "gn:country_code":"KP",
    "gn:dem":569,
    "gn:feature_class":"P",
    "gn:feature_code":"PPL",
    "gn:name":"Namak-kol",
    "gn:population":0,
    "gn:timezone":"Asia/Pyongyang",
    "iso:country":"KP",
    "name:und_x_variant":[
        "\ub0a8\uc545\uace8",
        "Namak-kol"
    ],
    "wof:name":"Namak-kol",
    "wof:placetype":"locality"
},
  "geometry": {"coordinates":[127.51917,38.57861],"type":"Point"}
}