{
  "type": "Feature",
  "properties": {
    "gn:admin1_code":"7.0",
    "gn:asciiname":"Chongbuk-tong",
    "gn:country_code":"KP",
    "gn:dem":80,
    "gn:feature_class":"P",
    "gn:feature_code":"PPL",
    "gn:name":"Ch\u014fngbuk-tong",
    "gn:population":0,
    "gn:timezone":"Asia/Pyongyang",
    "iso:country":"KP",
    "name:eng_x_preferred":[
        "Chongbuk"
    ],
    "name:eng_x_variant":[
        "Chongbuk-tong"
    ],
    "name:kor_x_preferred":[
        "\uc815\ubd81\ub3d9"
    ],
    "name:kor_x_variant":[
        "Ch\u014fngbuk-tong"
    ],
    "wof:name":"Chongbuk",
    "wof:placetype":"locality"
},
  "geometry": {"coordinates":[126.43861,38.38194],"type":"Point"}
}