{
  "type": "Feature",
  "properties": {
    "gn:admin1_code":"15.0",
    "gn:asciiname":"Changt'o-gol",
    "gn:country_code":"KP",
    "gn:dem":497,
    "gn:feature_class":"P",
    "gn:feature_code":"PPL",
    "gn:name":"Changt\u2019o-gol",
    "gn:population":0,
    "gn:timezone":"Asia/Pyongyang",
    "iso:country":"KP",
    "name:und_x_variant":[
        "\uc7a5\ud1a0\uace8",
        "Changt\u2019o-gol"
    ],
    "wof:name":"Changt'o-gol",
    "wof:placetype":"locality"
},
  "geometry": {"coordinates":[126.80389,39.90389],"type":"Point"}
}