{
  "type": "Feature",
  "properties": {
    "gn:admin1_code":"15.0",
    "gn:asciiname":"Changsang-ni",
    "gn:country_code":"KP",
    "gn:dem":398,
    "gn:feature_class":"P",
    "gn:feature_code":"PPL",
    "gn:name":"Changsang-ni",
    "gn:population":0,
    "gn:timezone":"Asia/Pyongyang",
    "iso:country":"KP",
    "name:eng_x_preferred":[
        "Changsang"
    ],
    "name:eng_x_variant":[
        "Changsang-ni"
    ],
    "name:kor_x_preferred":[
        "\uc7a5\uc0c1\ub9ac"
    ],
    "wof:name":"Changsang",
    "wof:placetype":"locality"
},
  "geometry": {"coordinates":[126.15611,39.82194],"type":"Point"}
}