{
  "type": "Feature",
  "properties": {
    "gn:admin1_code":"17.0",
    "gn:asciiname":"Yong-dong",
    "gn:country_code":"KP",
    "gn:dem":351,
    "gn:feature_class":"P",
    "gn:feature_code":"PPL",
    "gn:name":"Yong-dong",
    "gn:population":0,
    "gn:timezone":"Asia/Pyongyang",
    "iso:country":"KP",
    "name:und_x_variant":[
        "\uc6a9\ub3d9",
        "Yong-dong"
    ],
    "wof:name":"Yong-dong",
    "wof:placetype":"locality"
},
  "geometry": {"coordinates":[129.36444,41.10139],"type":"Point"}
}