{
  "type": "Feature",
  "properties": {
    "gn:admin1_code":"15.0",
    "gn:asciiname":"Namhae",
    "gn:country_code":"KP",
    "gn:dem":110,
    "gn:feature_class":"P",
    "gn:feature_code":"PPL",
    "gn:name":"Namhae",
    "gn:population":0,
    "gn:timezone":"Asia/Pyongyang",
    "iso:country":"KP",
    "name:kor_x_preferred":[
        "\ub0a8\ud574"
    ],
    "wof:name":"Namhae",
    "wof:placetype":"locality"
},
  "geometry": {"coordinates":[125.80249999999999,39.53056],"type":"Point"}
}