{
  "type": "Feature",
  "properties": {
    "gn:admin1_code":"11.0",
    "gn:asciiname":"Turyong-ni",
    "gn:country_code":"KP",
    "gn:dem":250,
    "gn:feature_class":"P",
    "gn:feature_code":"PPL",
    "gn:name":"Turyong-ni",
    "gn:population":0,
    "gn:timezone":"Asia/Pyongyang",
    "iso:country":"KP",
    "name:und_x_variant":[
        "Turyong-dong",
        "\ub450\ub8e1\ub9ac",
        "Turyong-ni"
    ],
    "wof:name":"Turyong-ni",
    "wof:placetype":"locality"
},
  "geometry": {"coordinates":[125.51582999999999,40.26722],"type":"Point"}
}