{
  "type": "Feature",
  "properties": {
    "gn:admin1_code":"6.0",
    "gn:asciiname":"Sangsanhyon",
    "gn:cc2":"KP",
    "gn:country_code":"KP",
    "gn:dem":22,
    "gn:feature_class":"P",
    "gn:feature_code":"PPL",
    "gn:name":"Sangsanhy\u014fn",
    "gn:population":0,
    "gn:timezone":"Asia/Pyongyang",
    "iso:country":"KP",
    "name:und_x_variant":[
        "Sangsanayon",
        "Sangsanhy\u014fn"
    ],
    "wof:name":"Sangsanhyon",
    "wof:placetype":"locality"
},
  "geometry": {"coordinates":[125.82306,38.01389],"type":"Point"}
}