{
  "type": "Feature",
  "properties": {
    "gn:admin1_code":"7.0",
    "gn:asciiname":"Sindae-ri",
    "gn:country_code":"KP",
    "gn:dem":152,
    "gn:feature_class":"P",
    "gn:feature_code":"PPL",
    "gn:name":"Sindae-ri",
    "gn:population":0,
    "gn:timezone":"Asia/Pyongyang",
    "iso:country":"KP",
    "wof:name":"Sindae-ri",
    "wof:placetype":"locality"
},
  "geometry": {"coordinates":[126.24583,38.69028],"type":"Point"}
}