{
  "type": "Feature",
  "properties": {
    "gn:admin1_code":"3.0",
    "gn:asciiname":"Sabup'yong",
    "gn:country_code":"KP",
    "gn:dem":291,
    "gn:feature_class":"P",
    "gn:feature_code":"PPL",
    "gn:name":"Sabup\u2019y\u014fng",
    "gn:population":0,
    "gn:timezone":"Asia/Pyongyang",
    "iso:country":"KP",
    "name:und_x_variant":[
        "\uc0ac\ubd80\ud3c9",
        "Sabup\u2019y\u014fng"
    ],
    "wof:name":"Sabup'yong",
    "wof:placetype":"locality"
},
  "geometry": {"coordinates":[128.03056000000001,40.33111],"type":"Point"}
}