{
  "type": "Feature",
  "properties": {
    "gn:admin1_code":"6.0",
    "gn:asciiname":"Paekt'ohyon",
    "gn:country_code":"KP",
    "gn:dem":22,
    "gn:feature_class":"P",
    "gn:feature_code":"PPL",
    "gn:name":"Paekt\u2019ohy\u014fn",
    "gn:population":0,
    "gn:timezone":"Asia/Pyongyang",
    "iso:country":"KP",
    "wof:name":"Paekt'ohyon",
    "wof:placetype":"locality"
},
  "geometry": {"coordinates":[125.77806,38.01389],"type":"Point"}
}