{
  "type": "Feature",
  "properties": {
    "gn:admin1_code":"7.0",
    "gn:asciiname":"Taehwa",
    "gn:country_code":"KP",
    "gn:dem":105,
    "gn:feature_class":"P",
    "gn:feature_code":"PPL",
    "gn:name":"Taehwa",
    "gn:population":0,
    "gn:timezone":"Asia/Pyongyang",
    "iso:country":"KP",
    "wof:name":"Taehwa",
    "wof:placetype":"locality"
},
  "geometry": {"coordinates":[126.07917,38.32972],"type":"Point"}
}