{
  "type": "Feature",
  "properties": {
    "gn:admin1_code":"15.0",
    "gn:asciiname":"Nami-ri",
    "gn:country_code":"KP",
    "gn:dem":9,
    "gn:feature_class":"P",
    "gn:feature_code":"PPL",
    "gn:name":"Nami-ri",
    "gn:population":0,
    "gn:timezone":"Asia/Pyongyang",
    "iso:country":"KP",
    "name:kor_x_preferred":[
        "\ub0a8\uc774\ub9ac"
    ],
    "name:und_x_variant":[
        "Nama-ri",
        "Nami-ri"
    ],
    "wof:name":"Nami-ri",
    "wof:placetype":"locality"
},
  "geometry": {"coordinates":[125.52722,39.56278],"type":"Point"}
}