{
  "type": "Feature",
  "properties": {
    "gn:admin1_code":"12.0",
    "gn:asciiname":"Hoegok-tong",
    "gn:country_code":"KP",
    "gn:dem":56,
    "gn:feature_class":"P",
    "gn:feature_code":"PPL",
    "gn:name":"Hoegok-tong",
    "gn:population":0,
    "gn:timezone":"Asia/Pyongyang",
    "iso:country":"KP",
    "name:kor_x_preferred":[
        "\ud68c\uace1\ub3d9"
    ],
    "name:und_x_variant":[
        "Hoegokdong"
    ],
    "wof:name":"Hoegok-tong",
    "wof:placetype":"locality"
},
  "geometry": {"coordinates":[125.901,39.11664],"type":"Point"}
}