{
  "type": "Feature",
  "properties": {
    "gn:admin1_code":"6.0",
    "gn:asciiname":"Sagundari",
    "gn:cc2":"KP",
    "gn:country_code":"KP",
    "gn:dem":46,
    "gn:feature_class":"P",
    "gn:feature_code":"PPL",
    "gn:name":"Sag\u016dndari",
    "gn:population":0,
    "gn:timezone":"Asia/Pyongyang",
    "iso:country":"KP",
    "name:kor_x_preferred":[
        "\uc0ac\uadfc\ub2e4\ub9ac"
    ],
    "name:kor_x_variant":[
        "Sag\u016dndari"
    ],
    "name:und_x_variant":[
        "Sag\u016dn\u2019gyo"
    ],
    "wof:name":"Sagundari",
    "wof:placetype":"locality"
},
  "geometry": {"coordinates":[125.19528,38.49167],"type":"Point"}
}