{
  "type": "Feature",
  "properties": {
    "gn:admin1_code":"7.0",
    "gn:asciiname":"Wondu",
    "gn:country_code":"KP",
    "gn:dem":145,
    "gn:feature_class":"P",
    "gn:feature_code":"PPL",
    "gn:name":"W\u014fndu",
    "gn:population":0,
    "gn:timezone":"Asia/Pyongyang",
    "iso:country":"KP",
    "name:kor_x_preferred":[
        "\uc6d0\ub450"
    ],
    "name:kor_x_variant":[
        "W\u014fndu"
    ],
    "wof:name":"Wondu",
    "wof:placetype":"locality"
},
  "geometry": {"coordinates":[126.42389,38.73361],"type":"Point"}
}