{
  "type": "Feature",
  "properties": {
    "gn:admin1_code":"12.0",
    "gn:asciiname":"Hagal-gol",
    "gn:country_code":"KP",
    "gn:dem":85,
    "gn:feature_class":"P",
    "gn:feature_code":"PPL",
    "gn:name":"Hagal-gol",
    "gn:population":0,
    "gn:timezone":"Asia/Pyongyang",
    "iso:country":"KP",
    "name:und_x_variant":[
        "\ud558\uac08\uace8",
        "Hagal-gol"
    ],
    "wof:name":"Hagal-gol",
    "wof:placetype":"locality"
},
  "geometry": {"coordinates":[125.935,38.82583],"type":"Point"}
}