{
  "type": "Feature",
  "properties": {
    "gn:admin1_code":"3.0",
    "gn:asciiname":"Sanso-ri",
    "gn:country_code":"KP",
    "gn:dem":4,
    "gn:feature_class":"P",
    "gn:feature_code":"PPL",
    "gn:name":"Sans\u014f-ri",
    "gn:population":0,
    "gn:timezone":"Asia/Pyongyang",
    "iso:country":"KP",
    "name:und_x_variant":[
        "\uc0b0\uc11c\ub9ac",
        "Sans\u014f-ri"
    ],
    "wof:name":"Sanso-ri",
    "wof:placetype":"locality"
},
  "geometry": {"coordinates":[128.06971999999999,40.04694],"type":"Point"}
}