{
  "type": "Feature",
  "properties": {
    "gn:admin1_code":"9.0",
    "gn:asciiname":"Taeam-ni",
    "gn:country_code":"KP",
    "gn:dem":483,
    "gn:feature_class":"P",
    "gn:feature_code":"PPL",
    "gn:name":"Taeam-ni",
    "gn:population":0,
    "gn:timezone":"Asia/Pyongyang",
    "iso:country":"KP",
    "name:und_x_variant":[
        "\ub300\uc554\ub9ac",
        "Taeam-ni"
    ],
    "wof:name":"Taeam-ni",
    "wof:placetype":"locality"
},
  "geometry": {"coordinates":[127.77361000000001,38.78694],"type":"Point"}
}