{
  "type": "Feature",
  "properties": {
    "gn:admin1_code":"6.0",
    "gn:asciiname":"Paekkot-tong",
    "gn:country_code":"KP",
    "gn:dem":13,
    "gn:feature_class":"P",
    "gn:feature_code":"PPL",
    "gn:name":"Paekkot-tong",
    "gn:population":0,
    "gn:timezone":"Asia/Pyongyang",
    "iso:country":"KP",
    "name:und_x_variant":[
        "\ubc30\uaf42\ub3d9",
        "Paekkot-tong"
    ],
    "wof:name":"Paekkot-tong",
    "wof:placetype":"locality"
},
  "geometry": {"coordinates":[125.63639000000001,37.93417],"type":"Point"}
}