{
  "type": "Feature",
  "properties": {
    "gn:admin1_code":"15.0",
    "gn:asciiname":"Chikcho-dong",
    "gn:country_code":"KP",
    "gn:dem":377,
    "gn:feature_class":"P",
    "gn:feature_code":"PPL",
    "gn:name":"Chikch\u014f-dong",
    "gn:population":0,
    "gn:timezone":"Asia/Pyongyang",
    "iso:country":"KP",
    "name:kor_x_preferred":[
        "\uc9c1\uc800\ub3d9"
    ],
    "name:kor_x_variant":[
        "Chikch\u014f-dong"
    ],
    "wof:name":"Chikcho-dong",
    "wof:placetype":"locality"
},
  "geometry": {"coordinates":[126.94278,39.15028],"type":"Point"}
}