{
  "type": "Feature",
  "properties": {
    "gn:admin1_code":"1.0",
    "gn:asciiname":"Hanunch'am",
    "gn:country_code":"KP",
    "gn:dem":816,
    "gn:feature_class":"P",
    "gn:feature_code":"PPL",
    "gn:name":"Hanunch\u2019am",
    "gn:population":0,
    "gn:timezone":"Asia/Pyongyang",
    "iso:country":"KP",
    "name:kor_x_preferred":[
        "Hanunch\u2019am"
    ],
    "name:und_x_variant":[
        "\ud55c\uc6b4\ucc38"
    ],
    "wof:name":"Hanunch'am",
    "wof:placetype":"locality"
},
  "geometry": {"coordinates":[126.89722,40.63167],"type":"Point"}
}