{
  "type": "Feature",
  "properties": {
    "gn:admin1_code":"1.0",
    "gn:asciiname":"Chung-dong",
    "gn:country_code":"KP",
    "gn:dem":576,
    "gn:feature_class":"P",
    "gn:feature_code":"PPL",
    "gn:name":"Chung-dong",
    "gn:population":0,
    "gn:timezone":"Asia/Pyongyang",
    "iso:country":"KP",
    "name:und_x_variant":[
        "\uc911\ub3d9",
        "Chung-dong"
    ],
    "wof:name":"Chung-dong",
    "wof:placetype":"locality"
},
  "geometry": {"coordinates":[126.00472000000001,40.63389],"type":"Point"}
}