{
  "type": "Feature",
  "properties": {
    "gn:admin1_code":"3.0",
    "gn:asciiname":"Korip",
    "gn:country_code":"KP",
    "gn:dem":224,
    "gn:feature_class":"P",
    "gn:feature_code":"PPL",
    "gn:name":"Korip",
    "gn:population":0,
    "gn:timezone":"Asia/Pyongyang",
    "iso:country":"KP",
    "name:und_x_variant":[
        "\uace0\ub9bd"
    ],
    "wof:name":"Korip",
    "wof:placetype":"locality"
},
  "geometry": {"coordinates":[128.27556999999999,40.45033],"type":"Point"}
}