{
  "type": "Feature",
  "properties": {
    "gn:admin1_code":"6.0",
    "gn:asciiname":"Pugok-tong",
    "gn:country_code":"KP",
    "gn:dem":95,
    "gn:feature_class":"P",
    "gn:feature_code":"PPL",
    "gn:name":"Pugok-tong",
    "gn:population":0,
    "gn:timezone":"Asia/Pyongyang",
    "iso:country":"KP",
    "name:eng_x_preferred":[
        "Pugok"
    ],
    "name:eng_x_variant":[
        "Pugok-tong"
    ],
    "wof:name":"Pugok",
    "wof:placetype":"locality"
},
  "geometry": {"coordinates":[125.58861,38.2675],"type":"Point"}
}