{
  "type": "Feature",
  "properties": {
    "gn:admin1_code":"13.0",
    "gn:asciiname":"An-gol",
    "gn:country_code":"KP",
    "gn:dem":514,
    "gn:feature_class":"P",
    "gn:feature_code":"PPL",
    "gn:name":"An-gol",
    "gn:population":0,
    "gn:timezone":"Asia/Pyongyang",
    "iso:country":"KP",
    "name:und_x_variant":[
        "\uc548\uace8",
        "An-gol"
    ],
    "wof:name":"An-gol",
    "wof:placetype":"locality"
},
  "geometry": {"coordinates":[128.57361,40.63056],"type":"Point"}
}