{
  "type": "Feature",
  "properties": {
    "gn:admin1_code":"6.0",
    "gn:asciiname":"Pusal-li",
    "gn:country_code":"KP",
    "gn:dem":78,
    "gn:feature_class":"P",
    "gn:feature_code":"PPL",
    "gn:name":"Pusal-li",
    "gn:population":0,
    "gn:timezone":"Asia/Pyongyang",
    "iso:country":"KP",
    "name:kor_x_preferred":[
        "\ubd80\uc0b0\ub9ac"
    ],
    "name:und_x_variant":[
        "Pusan-ni",
        "Pusal-li"
    ],
    "wof:name":"Pusal-li",
    "wof:placetype":"locality"
},
  "geometry": {"coordinates":[125.11972,38.33722],"type":"Point"}
}