{
  "type": "Feature",
  "properties": {
    "gn:admin1_code":"12.0",
    "gn:asciiname":"Pingjang-ni",
    "gn:cc2":"KP",
    "gn:country_code":"KP",
    "gn:dem":47,
    "gn:feature_class":"P",
    "gn:feature_code":"PPL",
    "gn:name":"Pingjang-ni",
    "gn:population":0,
    "gn:timezone":"Asia/Pyongyang",
    "iso:country":"KP",
    "name:und_x_variant":[
        "Hy\u014dsh\u014d",
        "Hy\u014dsh\u014d-ri",
        "\ube59\uc7a5\ub9ac",
        "Pingjang-ni"
    ],
    "wof:name":"Pingjang-ni",
    "wof:placetype":"locality"
},
  "geometry": {"coordinates":[125.86750000000001,38.83056],"type":"Point"}
}