{
  "type": "Feature",
  "properties": {
    "gn:admin1_code":"17.0",
    "gn:asciiname":"Hongch'on",
    "gn:country_code":"KP",
    "gn:dem":692,
    "gn:feature_class":"P",
    "gn:feature_code":"PPL",
    "gn:name":"Hongch\u2019on",
    "gn:population":0,
    "gn:timezone":"Asia/Pyongyang",
    "iso:country":"KP",
    "name:und_x_variant":[
        "\ud64d\ucd0c",
        "Hongch\u2019on"
    ],
    "wof:name":"Hongch'on",
    "wof:placetype":"locality"
},
  "geometry": {"coordinates":[129.00999999999999,40.85722],"type":"Point"}
}