{
  "type": "Feature",
  "properties": {
    "gn:admin1_code":"17.0",
    "gn:asciiname":"Yodong",
    "gn:country_code":"KP",
    "gn:dem":250,
    "gn:feature_class":"P",
    "gn:feature_code":"PPL",
    "gn:name":"Yodong",
    "gn:population":0,
    "gn:timezone":"Asia/Pyongyang",
    "iso:country":"KP",
    "name:und_x_variant":[
        "\uc694\ub3d9",
        "Yodong"
    ],
    "wof:name":"Yodong",
    "wof:placetype":"locality"
},
  "geometry": {"coordinates":[129.76889,42.41722],"type":"Point"}
}