{
  "type": "Feature",
  "properties": {
    "gn:admin1_code":"11.0",
    "gn:asciiname":"Kumgye-ri",
    "gn:country_code":"KP",
    "gn:dem":17,
    "gn:feature_class":"P",
    "gn:feature_code":"PPL",
    "gn:name":"K\u016dmgye-ri",
    "gn:population":0,
    "gn:timezone":"Asia/Pyongyang",
    "iso:country":"KP",
    "name:kor_x_preferred":[
        "\uae08\uacc4\ub9ac"
    ],
    "name:kor_x_variant":[
        "K\u016dmgye-ri"
    ],
    "name:und_x_variant":[
        "K\u016dmgye-dong"
    ],
    "wof:name":"Kumgye-ri",
    "wof:placetype":"locality"
},
  "geometry": {"coordinates":[125.45722000000001,39.65611],"type":"Point"}
}