{
  "type": "Feature",
  "properties": {
    "gn:admin1_code":"6.0",
    "gn:admin2_code":"P\u2019anmun-gun",
    "gn:asciiname":"Taejojong-ni",
    "gn:country_code":"KP",
    "gn:dem":27,
    "gn:feature_class":"P",
    "gn:feature_code":"PPL",
    "gn:name":"Taejoj\u014fng-ni",
    "gn:population":0,
    "gn:timezone":"Asia/Pyongyang",
    "iso:country":"KP",
    "name:und_x_variant":[
        "Taechoj\u014fng-ni",
        "Taejoj\u014fng-ni"
    ],
    "wof:name":"Taejojong-ni",
    "wof:placetype":"locality"
},
  "geometry": {"coordinates":[126.63943999999999,37.95],"type":"Point"}
}