{
  "type": "Feature",
  "properties": {
    "gn:admin1_code":"13.0",
    "gn:admin2_code":"Paegam-gun",
    "gn:asciiname":"Ch'ongbong-nodongjagu",
    "gn:country_code":"KP",
    "gn:dem":1093,
    "gn:feature_class":"P",
    "gn:feature_code":"PPL",
    "gn:name":"Ch\u2019\u014fngbong-nodongjagu",
    "gn:population":0,
    "gn:timezone":"Asia/Pyongyang",
    "iso:country":"KP",
    "name:kor_x_preferred":[
        "\uccad\ubd09\ub85c\ub3d9\uc790\uad6c"
    ],
    "name:und_x_variant":[
        "Ch\u2019\u014fngbong-nodongjagu",
        "Ch\u2019\u014fnbong-nodongjagu"
    ],
    "wof:name":"Ch'ongbong-nodongjagu",
    "wof:placetype":"locality"
},
  "geometry": {"coordinates":[128.75193999999999,41.78972],"type":"Point"}
}