{
  "type": "Feature",
  "properties": {
    "gn:admin1_code":"7.0",
    "gn:asciiname":"Saesulmak",
    "gn:country_code":"KP",
    "gn:dem":210,
    "gn:feature_class":"P",
    "gn:feature_code":"PPL",
    "gn:name":"Saesulmak",
    "gn:population":0,
    "gn:timezone":"Asia/Pyongyang",
    "iso:country":"KP",
    "wof:name":"Saesulmak",
    "wof:placetype":"locality"
},
  "geometry": {"coordinates":[126.18083,38.54667],"type":"Point"}
}