{
  "type": "Feature",
  "properties": {
    "gn:admin1_code":"7.0",
    "gn:asciiname":"Sin-ch'on",
    "gn:country_code":"KP",
    "gn:dem":28,
    "gn:feature_class":"P",
    "gn:feature_code":"PPL",
    "gn:name":"Sin-ch\u2019on",
    "gn:population":0,
    "gn:timezone":"Asia/Pyongyang",
    "iso:country":"KP",
    "name:kor_x_preferred":[
        "\uc2e0\ucd0c"
    ],
    "name:kor_x_variant":[
        "Sin-ch\u2019on"
    ],
    "wof:name":"Sin-ch'on",
    "wof:placetype":"locality"
},
  "geometry": {"coordinates":[125.51888999999998,38.60694],"type":"Point"}
}