{
  "type": "Feature",
  "properties": {
    "gn:admin1_code":"6.0",
    "gn:admin2_code":"Paech'\u014fn-gun",
    "gn:asciiname":"Kangho-ri",
    "gn:cc2":"KP",
    "gn:country_code":"KP",
    "gn:dem":15,
    "gn:feature_class":"P",
    "gn:feature_code":"PPL",
    "gn:name":"Kangho-ri",
    "gn:population":0,
    "gn:timezone":"Asia/Pyongyang",
    "iso:country":"KP",
    "name:kor_x_preferred":[
        "\uac15\ud638\ub9ac"
    ],
    "name:und_x_variant":[
        "Kangs\u014f-ri",
        "Kangho-ri"
    ],
    "wof:name":"Kangho-ri",
    "wof:placetype":"locality"
},
  "geometry": {"coordinates":[126.36444,37.97639],"type":"Point"}
}