{
  "type": "Feature",
  "properties": {
    "gn:admin1_code":"15.0",
    "gn:asciiname":"Naep'yong",
    "gn:country_code":"KP",
    "gn:dem":246,
    "gn:feature_class":"P",
    "gn:feature_code":"PPL",
    "gn:name":"Naep\u2019y\u014fng",
    "gn:population":0,
    "gn:timezone":"Asia/Pyongyang",
    "iso:country":"KP",
    "name:kor_x_preferred":[
        "\ub0b4\ud3c9"
    ],
    "name:kor_x_variant":[
        "Naep\u2019y\u014fng"
    ],
    "wof:name":"Naep'yong",
    "wof:placetype":"locality"
},
  "geometry": {"coordinates":[126.52306000000002,39.26111],"type":"Point"}
}