{
  "type": "Feature",
  "properties": {
    "gn:admin1_code":"11.0",
    "gn:asciiname":"T'obun-dong",
    "gn:country_code":"KP",
    "gn:dem":117,
    "gn:feature_class":"P",
    "gn:feature_code":"PPL",
    "gn:name":"T\u2019obun-dong",
    "gn:population":0,
    "gn:timezone":"Asia/Pyongyang",
    "iso:country":"KP",
    "name:und_x_variant":[
        "\ud1a0\ubd84\ub3d9",
        "T\u2019obun-dong"
    ],
    "wof:name":"T'obun-dong",
    "wof:placetype":"locality"
},
  "geometry": {"coordinates":[125.83833,40.06944],"type":"Point"}
}