{
  "type": "Feature",
  "properties": {
    "gn:admin1_code":"7.0",
    "gn:asciiname":"Kal-gol",
    "gn:country_code":"KP",
    "gn:dem":174,
    "gn:feature_class":"P",
    "gn:feature_code":"PPL",
    "gn:name":"Kal-gol",
    "gn:population":0,
    "gn:timezone":"Asia/Pyongyang",
    "iso:country":"KP",
    "name:kor_x_preferred":[
        "\uac08\uace8"
    ],
    "wof:name":"Kal-gol",
    "wof:placetype":"locality"
},
  "geometry": {"coordinates":[126.65111,38.77333],"type":"Point"}
}