{
  "type": "Feature",
  "properties": {
    "gn:admin1_code":"9.0",
    "gn:asciiname":"Honggosa-gol",
    "gn:country_code":"KP",
    "gn:dem":627,
    "gn:feature_class":"P",
    "gn:feature_code":"PPL",
    "gn:name":"Hongg\u014fsa-gol",
    "gn:population":0,
    "gn:timezone":"Asia/Pyongyang",
    "iso:country":"KP",
    "name:kor_x_preferred":[
        "\ud64d\uac70\uc0ac\uace8"
    ],
    "name:kor_x_variant":[
        "Hongg\u014fsa-gol"
    ],
    "wof:name":"Honggosa-gol",
    "wof:placetype":"locality"
},
  "geometry": {"coordinates":[127.18722,39.23278],"type":"Point"}
}