{
  "type": "Feature",
  "properties": {
    "gn:admin1_code":"13.0",
    "gn:asciiname":"Ibang-ni",
    "gn:country_code":"KP",
    "gn:dem":685,
    "gn:feature_class":"P",
    "gn:feature_code":"PPL",
    "gn:name":"Ibang-ni",
    "gn:population":0,
    "gn:timezone":"Asia/Pyongyang",
    "iso:country":"KP",
    "name:kor_x_preferred":[
        "\uc774\ubc29\ub9ac"
    ],
    "wof:name":"Ibang-ni",
    "wof:placetype":"locality"
},
  "geometry": {"coordinates":[127.91110999999999,41.41222],"type":"Point"}
}