{
  "type": "Feature",
  "properties": {
    "gn:admin1_code":"9.0",
    "gn:asciiname":"Harinwol-li",
    "gn:country_code":"KP",
    "gn:dem":258,
    "gn:feature_class":"P",
    "gn:feature_code":"PPL",
    "gn:name":"Harinw\u014fl-li",
    "gn:population":0,
    "gn:timezone":"Asia/Pyongyang",
    "iso:country":"KP",
    "name:und_x_variant":[
        "\ud558\ub9b0\uc6d0\ub9ac",
        "Harinw\u014fn-ni",
        "Harinw\u014fl-li"
    ],
    "wof:name":"Harinwol-li",
    "wof:placetype":"locality"
},
  "geometry": {"coordinates":[127.02583,38.76389],"type":"Point"}
}