{
  "type": "Feature",
  "properties": {
    "gn:admin1_code":"15.0",
    "gn:asciiname":"Ch'isong-dong",
    "gn:country_code":"KP",
    "gn:dem":116,
    "gn:feature_class":"P",
    "gn:feature_code":"PPL",
    "gn:name":"Ch\u2019is\u014fng-dong",
    "gn:population":0,
    "gn:timezone":"Asia/Pyongyang",
    "iso:country":"KP",
    "wof:name":"Ch'isong-dong",
    "wof:placetype":"locality"
},
  "geometry": {"coordinates":[125.75333000000001,39.28389],"type":"Point"}
}