{
  "type": "Feature",
  "properties": {
    "gn:admin1_code":"0.0",
    "gn:asciiname":"Sosong-dong",
    "gn:country_code":"KP",
    "gn:dem":20,
    "gn:feature_class":"P",
    "gn:feature_code":"PPL",
    "gn:name":"S\u014fsong-dong",
    "gn:population":0,
    "gn:timezone":"Asia/Pyongyang",
    "iso:country":"KP",
    "name:kor_x_preferred":[
        "\uc11c\uc1a1\ub3d9"
    ],
    "name:kor_x_variant":[
        "S\u014fsong-dong"
    ],
    "wof:name":"Sosong-dong",
    "wof:placetype":"locality"
},
  "geometry": {"coordinates":[125.61278,39.65389],"type":"Point"}
}