{
  "type": "Feature",
  "properties": {
    "gn:admin1_code":"6.0",
    "gn:admin2_code":"Paech\u2019\u014fn-gun",
    "gn:asciiname":"Tongbyo-ri",
    "gn:country_code":"KP",
    "gn:dem":9,
    "gn:feature_class":"P",
    "gn:feature_code":"PPL",
    "gn:name":"Tongby\u014f-ri",
    "gn:population":0,
    "gn:timezone":"Asia/Pyongyang",
    "iso:country":"KP",
    "name:und_x_variant":[
        "Tongby\u014flli",
        "Tongby\u014f-ri"
    ],
    "wof:name":"Tongbyo-ri",
    "wof:placetype":"locality"
},
  "geometry": {"coordinates":[126.30667,37.87222],"type":"Point"}
}