{
  "type": "Feature",
  "properties": {
    "gn:admin1_code":"6.0",
    "gn:asciiname":"Namsan-dong",
    "gn:country_code":"KP",
    "gn:dem":57,
    "gn:feature_class":"P",
    "gn:feature_code":"PPL",
    "gn:name":"Namsan-dong",
    "gn:population":0,
    "gn:timezone":"Asia/Pyongyang",
    "iso:country":"KP",
    "wof:name":"Namsan-dong",
    "wof:placetype":"locality"
},
  "geometry": {"coordinates":[125.70111,38.03556],"type":"Point"}
}