{
  "type": "Feature",
  "properties": {
    "gn:admin1_code":"12.0",
    "gn:admin2_code":"Sangw\u014fn-gun",
    "gn:asciiname":"Naeibam-ni",
    "gn:country_code":"KP",
    "gn:dem":168,
    "gn:feature_class":"P",
    "gn:feature_code":"PPL",
    "gn:name":"Naeibam-ni",
    "gn:population":0,
    "gn:timezone":"Asia/Pyongyang",
    "iso:country":"KP",
    "name:eng_x_preferred":[
        "Naeibam"
    ],
    "name:eng_x_variant":[
        "Naeibam-ni"
    ],
    "wof:name":"Naeibam",
    "wof:placetype":"locality"
},
  "geometry": {"coordinates":[126.12860999999999,38.81167],"type":"Point"}
}