{
  "type": "Feature",
  "properties": {
    "gn:admin1_code":"15.0",
    "gn:asciiname":"Pukch'ang-ni",
    "gn:country_code":"KP",
    "gn:dem":69,
    "gn:feature_class":"P",
    "gn:feature_code":"PPL",
    "gn:name":"Pukch\u2019ang-ni",
    "gn:population":0,
    "gn:timezone":"Asia/Pyongyang",
    "iso:country":"KP",
    "name:eng_x_preferred":[
        "Pukch'ang"
    ],
    "name:eng_x_variant":[
        "Pukch'ang-ni"
    ],
    "wof:name":"Pukch'ang",
    "wof:placetype":"locality"
},
  "geometry": {"coordinates":[125.70694,39.3025],"type":"Point"}
}