{
  "type": "Feature",
  "properties": {
    "gn:admin1_code":"12.0",
    "gn:asciiname":"Simbang-ni",
    "gn:cc2":"KP",
    "gn:country_code":"KP",
    "gn:dem":18,
    "gn:feature_class":"P",
    "gn:feature_code":"PPL",
    "gn:name":"Simbang-ni",
    "gn:population":0,
    "gn:timezone":"Asia/Pyongyang",
    "iso:country":"KP",
    "name:eng_x_preferred":[
        "Simbang"
    ],
    "name:eng_x_variant":[
        "Simbang-ni"
    ],
    "name:kor_x_preferred":[
        "\uc2ec\ubc29\ub9ac"
    ],
    "name:und_x_variant":[
        "Ch\u2019imbang-ni",
        "Simbang-ni",
        "Simbangni"
    ],
    "wof:name":"Simbang",
    "wof:placetype":"locality"
},
  "geometry": {"coordinates":[125.67833,38.87722],"type":"Point"}
}