{
  "type": "Feature",
  "properties": {
    "gn:admin1_code":"6.0",
    "gn:asciiname":"Ch'ilbong-ni",
    "gn:country_code":"KP",
    "gn:dem":39,
    "gn:feature_class":"P",
    "gn:feature_code":"PPL",
    "gn:name":"Ch\u2019ilbong-ni",
    "gn:population":0,
    "gn:timezone":"Asia/Pyongyang",
    "iso:country":"KP",
    "name:eng_x_preferred":[
        "Ch'ilbong"
    ],
    "name:eng_x_variant":[
        "Ch'ilbong-ni"
    ],
    "name:kor_x_preferred":[
        "\uce60\ubd09\ub9ac"
    ],
    "name:und_x_variant":[
        "Ch\u2019ilbong-ni"
    ],
    "wof:name":"Ch'ilbong",
    "wof:placetype":"locality"
},
  "geometry": {"coordinates":[125.89139,38.04861],"type":"Point"}
}