{
  "type": "Feature",
  "properties": {
    "gn:admin1_code":"3.0",
    "gn:asciiname":"Tasamp'o-ri",
    "gn:country_code":"KP",
    "gn:dem":50,
    "gn:feature_class":"P",
    "gn:feature_code":"PPL",
    "gn:name":"Tasamp\u2019o-ri",
    "gn:population":0,
    "gn:timezone":"Asia/Pyongyang",
    "iso:country":"KP",
    "name:kor_x_preferred":[
        "\ub2e4\uc0bc\ud3ec\ub9ac"
    ],
    "name:kor_x_variant":[
        "Tasamp\u2019o-ri"
    ],
    "wof:name":"Tasamp'o-ri",
    "wof:placetype":"locality"
},
  "geometry": {"coordinates":[127.16139,39.4825],"type":"Point"}
}