{
  "type": "Feature",
  "properties": {
    "gn:admin1_code":"13.0",
    "gn:asciiname":"Chinmokchong",
    "gn:country_code":"KP",
    "gn:dem":1130,
    "gn:feature_class":"P",
    "gn:feature_code":"PPL",
    "gn:name":"Chinmokch\u014fng",
    "gn:population":0,
    "gn:timezone":"Asia/Pyongyang",
    "iso:country":"KP",
    "name:und_x_variant":[
        "\uc9c4\ubaa9\uccad",
        "Chinmokch\u014fng"
    ],
    "wof:name":"Chinmokchong",
    "wof:placetype":"locality"
},
  "geometry": {"coordinates":[128.255,40.69889000000001],"type":"Point"}
}