{
  "type": "Feature",
  "properties": {
    "gn:admin1_code":"15.0",
    "gn:asciiname":"Namsa-ri",
    "gn:country_code":"KP",
    "gn:dem":21,
    "gn:feature_class":"P",
    "gn:feature_code":"PPL",
    "gn:name":"Namsa-ri",
    "gn:population":0,
    "gn:timezone":"Asia/Pyongyang",
    "iso:country":"KP",
    "name:kor_x_preferred":[
        "\ub0a8\uc0ac\ub9ac"
    ],
    "wof:name":"Namsa-ri",
    "wof:placetype":"locality"
},
  "geometry": {"coordinates":[125.49139,39.54528],"type":"Point"}
}