{
  "type": "Feature",
  "properties": {
    "gn:admin1_code":"1.0",
    "gn:asciiname":"Anp'ungji-dong",
    "gn:country_code":"KP",
    "gn:dem":300,
    "gn:feature_class":"P",
    "gn:feature_code":"PPL",
    "gn:name":"Anp\u2019ungji-dong",
    "gn:population":0,
    "gn:timezone":"Asia/Pyongyang",
    "iso:country":"KP",
    "name:und_x_variant":[
        "\uc548\ud48d\uc9c0\ub3d9",
        "Anp\u2019ungji-dong"
    ],
    "wof:name":"Anp'ungji-dong",
    "wof:placetype":"locality"
},
  "geometry": {"coordinates":[126.62944,41.00556],"type":"Point"}
}