{
  "type": "Feature",
  "properties": {
    "gn:admin1_code":"9.0",
    "gn:asciiname":"Sangnyong",
    "gn:country_code":"KP",
    "gn:dem":74,
    "gn:feature_class":"P",
    "gn:feature_code":"PPL",
    "gn:name":"Sangny\u014fng",
    "gn:population":0,
    "gn:timezone":"Asia/Pyongyang",
    "iso:country":"KP",
    "name:kor_x_preferred":[
        "\uc0c1\ub839"
    ],
    "name:und_x_variant":[
        "Sangny\u014fng"
    ],
    "wof:name":"Sangnyong",
    "wof:placetype":"locality"
},
  "geometry": {"coordinates":[126.90611,38.21444],"type":"Point"}
}