{
  "type": "Feature",
  "properties": {
    "gn:admin1_code":"15.0",
    "gn:asciiname":"Kojang-gol",
    "gn:country_code":"KP",
    "gn:dem":235,
    "gn:feature_class":"P",
    "gn:feature_code":"PPL",
    "gn:name":"Kojang-gol",
    "gn:population":0,
    "gn:timezone":"Asia/Pyongyang",
    "iso:country":"KP",
    "name:kor_x_preferred":[
        "\uace0\uc7a5\uace8"
    ],
    "wof:name":"Kojang-gol",
    "wof:placetype":"locality"
},
  "geometry": {"coordinates":[126.30583,39.38639000000001],"type":"Point"}
}