{
  "type": "Feature",
  "properties": {
    "gn:admin1_code":"6.0",
    "gn:asciiname":"Hasong-dong",
    "gn:country_code":"KP",
    "gn:dem":38,
    "gn:feature_class":"P",
    "gn:feature_code":"PPL",
    "gn:name":"Has\u014fng-dong",
    "gn:population":0,
    "gn:timezone":"Asia/Pyongyang",
    "iso:country":"KP",
    "name:kor_x_preferred":[
        "\ud558\uc131\ub3d9"
    ],
    "name:und_x_variant":[
        "Has\u014fng-dong"
    ],
    "wof:name":"Hasong-dong",
    "wof:placetype":"locality"
},
  "geometry": {"coordinates":[125.57611,38.32083],"type":"Point"}
}