{
  "type": "Feature",
  "properties": {
    "gn:admin1_code":"17.0",
    "gn:asciiname":"Hansonch'on",
    "gn:country_code":"KP",
    "gn:dem":131,
    "gn:feature_class":"P",
    "gn:feature_code":"PPL",
    "gn:name":"Hansonch\u2019on",
    "gn:population":0,
    "gn:timezone":"Asia/Pyongyang",
    "iso:country":"KP",
    "name:und_x_variant":[
        "\ud55c\uc120\ucd0c",
        "Hansonch\u2019on"
    ],
    "wof:name":"Hansonch'on",
    "wof:placetype":"locality"
},
  "geometry": {"coordinates":[129.10611,40.59722],"type":"Point"}
}