{
  "type": "Feature",
  "properties": {
    "gn:admin1_code":"15.0",
    "gn:asciiname":"Sondo-gol",
    "gn:country_code":"KP",
    "gn:dem":276,
    "gn:feature_class":"P",
    "gn:feature_code":"PPL",
    "gn:name":"S\u014fndo-gol",
    "gn:population":0,
    "gn:timezone":"Asia/Pyongyang",
    "iso:country":"KP",
    "name:kor_x_preferred":[
        "\uc120\ub3c4\uace8"
    ],
    "name:kor_x_variant":[
        "S\u014fndo-gol"
    ],
    "wof:name":"Sondo-gol",
    "wof:placetype":"locality"
},
  "geometry": {"coordinates":[126.41222,39.3625],"type":"Point"}
}