{
  "type": "Feature",
  "properties": {
    "gn:admin1_code":"0.0",
    "gn:asciiname":"Tojang-dong",
    "gn:country_code":"KP",
    "gn:dem":85,
    "gn:feature_class":"P",
    "gn:feature_code":"PPL",
    "gn:name":"Tojang-dong",
    "gn:population":0,
    "gn:timezone":"Asia/Pyongyang",
    "iso:country":"KP",
    "name:kor_x_preferred":[
        "\ub3c4\uc7a5\ub3d9"
    ],
    "wof:name":"Tojang-dong",
    "wof:placetype":"locality"
},
  "geometry": {"coordinates":[126.75,37.98333],"type":"Point"}
}