{
  "type": "Feature",
  "properties": {
    "gn:admin1_code":"9.0",
    "gn:admin2_code":"Kos\u014fng-gun",
    "gn:asciiname":"Changp'o-ri",
    "gn:country_code":"KP",
    "gn:dem":8,
    "gn:feature_class":"P",
    "gn:feature_code":"PPL",
    "gn:name":"Changp\u2019o-ri",
    "gn:population":0,
    "gn:timezone":"Asia/Pyongyang",
    "iso:country":"KP",
    "name:kor_x_preferred":[
        "\uc7a5\ud3ec\ub9ac"
    ],
    "name:und_x_variant":[
        "Changp\u2019o-ri"
    ],
    "wof:name":"Changp'o-ri",
    "wof:placetype":"locality"
},
  "geometry": {"coordinates":[128.3075,38.70889],"type":"Point"}
}