{
  "type": "Feature",
  "properties": {
    "gn:admin1_code":"6.0",
    "gn:asciiname":"Ma-dong",
    "gn:country_code":"KP",
    "gn:dem":14,
    "gn:feature_class":"P",
    "gn:feature_code":"PPL",
    "gn:name":"Ma-dong",
    "gn:population":0,
    "gn:timezone":"Asia/Pyongyang",
    "iso:country":"KP",
    "wof:name":"Ma-dong",
    "wof:placetype":"locality"
},
  "geometry": {"coordinates":[125.87667,37.95861],"type":"Point"}
}