{
  "type": "Feature",
  "properties": {
    "gn:admin1_code":"12.0",
    "gn:asciiname":"Munsan-dong",
    "gn:country_code":"KP",
    "gn:dem":36,
    "gn:feature_class":"P",
    "gn:feature_code":"PPL",
    "gn:name":"Munsan-dong",
    "gn:population":0,
    "gn:timezone":"Asia/Pyongyang",
    "iso:country":"KP",
    "name:kor_x_preferred":[
        "\ubb38\uc0b0\ub3d9"
    ],
    "name:und_x_variant":[
        "Munsandong"
    ],
    "wof:name":"Munsan-dong",
    "wof:placetype":"locality"
},
  "geometry": {"coordinates":[125.95889,39.12972],"type":"Point"}
}