{
  "type": "Feature",
  "properties": {
    "gn:admin1_code":"6.0",
    "gn:admin2_code":"1876380",
    "gn:asciiname":"T'an-dong",
    "gn:country_code":"KP",
    "gn:dem":11,
    "gn:feature_class":"P",
    "gn:feature_code":"PPL",
    "gn:name":"T\u2019an-dong",
    "gn:population":0,
    "gn:timezone":"Asia/Pyongyang",
    "iso:country":"KP",
    "name:kor_x_preferred":[
        "T\u2019an-dong"
    ],
    "wof:name":"T'an-dong",
    "wof:placetype":"locality"
},
  "geometry": {"coordinates":[126.44056,37.86917],"type":"Point"}
}