{
  "type": "Feature",
  "properties": {
    "gn:admin1_code":"17.0",
    "gn:asciiname":"Koch'am-ni",
    "gn:country_code":"KP",
    "gn:dem":296,
    "gn:feature_class":"P",
    "gn:feature_code":"PPLL",
    "gn:name":"Koch\u2019am-ni",
    "gn:population":0,
    "gn:timezone":"Asia/Pyongyang",
    "iso:country":"KP",
    "name:und_x_variant":[
        "Kotan",
        "Koch\u2019am-dong",
        "Koch\u2019an",
        "\uace0\ucc38\ub9ac",
        "Koch\u2019am-ni"
    ],
    "wof:name":"Koch'am-ni",
    "wof:placetype":"locality"
},
  "geometry": {"coordinates":[129.38388999999998,41.09278],"type":"Point"}
}