{
  "type": "Feature",
  "properties": {
    "gn:admin1_code":"6.0",
    "gn:asciiname":"Sangyonmyong-dong",
    "gn:country_code":"KP",
    "gn:dem":64,
    "gn:feature_class":"P",
    "gn:feature_code":"PPL",
    "gn:name":"Sangy\u014fnmy\u014fng-dong",
    "gn:population":0,
    "gn:timezone":"Asia/Pyongyang",
    "iso:country":"KP",
    "name:kor_x_preferred":[
        "\uc0c1\uc5f0\uba85\ub3d9"
    ],
    "name:kor_x_variant":[
        "Sangy\u014fnmy\u014fng-dong"
    ],
    "wof:name":"Sangyonmyong-dong",
    "wof:placetype":"locality"
},
  "geometry": {"coordinates":[125.21444,38.49056],"type":"Point"}
}