{
  "type": "Feature",
  "properties": {
    "gn:admin1_code":"17.0",
    "gn:asciiname":"Sam-ni",
    "gn:country_code":"KP",
    "gn:dem":249,
    "gn:feature_class":"P",
    "gn:feature_code":"PPL",
    "gn:name":"Sam-ni",
    "gn:population":0,
    "gn:timezone":"Asia/Pyongyang",
    "iso:country":"KP",
    "name:und_x_variant":[
        "\uc0bc\ub9ac",
        "Sam-ni"
    ],
    "wof:name":"Sam-ni",
    "wof:placetype":"locality"
},
  "geometry": {"coordinates":[129.86139,42.80778],"type":"Point"}
}