{
  "type": "Feature",
  "properties": {
    "gn:admin1_code":"6.0",
    "gn:asciiname":"Chuch'ol-li",
    "gn:country_code":"KP",
    "gn:dem":86,
    "gn:feature_class":"P",
    "gn:feature_code":"PPL",
    "gn:name":"Chuch\u2019ol-li",
    "gn:population":0,
    "gn:timezone":"Asia/Pyongyang",
    "iso:country":"KP",
    "name:kor_x_preferred":[
        "\uc8fc\ucd0c\ub9ac"
    ],
    "name:und_x_variant":[
        "Chu-ch\u2019on",
        "Chuch\u2019ol-li"
    ],
    "wof:name":"Chuch'ol-li",
    "wof:placetype":"locality"
},
  "geometry": {"coordinates":[125.05249999999999,38.35583],"type":"Point"}
}