{
  "type": "Feature",
  "properties": {
    "gn:admin1_code":"12.0",
    "gn:asciiname":"Naengsong-dong",
    "gn:country_code":"KP",
    "gn:dem":57,
    "gn:feature_class":"P",
    "gn:feature_code":"PPL",
    "gn:name":"Naengs\u014fng-dong",
    "gn:population":0,
    "gn:timezone":"Asia/Pyongyang",
    "iso:country":"KP",
    "name:und_x_variant":[
        "\ub0c9\uc131\ub3d9",
        "Naengs\u014fng-dong",
        "Naengseongdong"
    ],
    "wof:name":"Naengsong-dong",
    "wof:placetype":"locality"
},
  "geometry": {"coordinates":[125.97056000000001,38.9325],"type":"Point"}
}