{
  "type": "Feature",
  "properties": {
    "gn:admin1_code":"17.0",
    "gn:asciiname":"Ch'angch'on",
    "gn:country_code":"KP",
    "gn:dem":132,
    "gn:feature_class":"P",
    "gn:feature_code":"PPL",
    "gn:name":"Ch\u2019angch\u2019on",
    "gn:population":0,
    "gn:timezone":"Asia/Pyongyang",
    "iso:country":"KP",
    "name:und_x_variant":[
        "\ucc3d\ucd0c",
        "Ch\u2019angch\u2019on"
    ],
    "wof:name":"Ch'angch'on",
    "wof:placetype":"locality"
},
  "geometry": {"coordinates":[129.20861000000002,40.8725],"type":"Point"}
}