{
  "type": "Feature",
  "properties": {
    "gn:admin1_code":"11.0",
    "gn:asciiname":"Tongsal-li",
    "gn:country_code":"KP",
    "gn:dem":66,
    "gn:feature_class":"P",
    "gn:feature_code":"PPL",
    "gn:name":"Tongsal-li",
    "gn:population":0,
    "gn:timezone":"Asia/Pyongyang",
    "iso:country":"KP",
    "name:und_x_variant":[
        "Tongsan-ni",
        "Tongsal-li"
    ],
    "wof:name":"Tongsal-li",
    "wof:placetype":"locality"
},
  "geometry": {"coordinates":[125.34778,39.97306],"type":"Point"}
}