{
  "type": "Feature",
  "properties": {
    "gn:admin1_code":"18.0",
    "gn:asciiname":"Changno-dong",
    "gn:country_code":"KP",
    "gn:dem":63,
    "gn:feature_class":"P",
    "gn:feature_code":"PPL",
    "gn:name":"Changno-dong",
    "gn:population":0,
    "gn:timezone":"Asia/Pyongyang",
    "iso:country":"KP",
    "name:und_x_variant":[
        "\uc7a5\ub85c\ub3d9",
        "Changno-dong",
        "Jangnodong"
    ],
    "wof:name":"Changno-dong",
    "wof:placetype":"locality"
},
  "geometry": {"coordinates":[130.44499999999999,42.50944000000001],"type":"Point"}
}