{
  "type": "Feature",
  "properties": {
    "gn:admin1_code":"1.0",
    "gn:asciiname":"P'yongdang-dong",
    "gn:country_code":"KP",
    "gn:dem":444,
    "gn:feature_class":"P",
    "gn:feature_code":"PPL",
    "gn:name":"P\u2019y\u014fngdang-dong",
    "gn:population":0,
    "gn:timezone":"Asia/Pyongyang",
    "iso:country":"KP",
    "name:und_x_variant":[
        "\ud3c9\ub2f9\ub3d9",
        "P\u2019y\u014fngdang-dong"
    ],
    "wof:name":"P'yongdang-dong",
    "wof:placetype":"locality"
},
  "geometry": {"coordinates":[125.92610999999999,40.58222],"type":"Point"}
}