{
  "type": "Feature",
  "properties": {
    "gn:admin1_code":"3.0",
    "gn:asciiname":"Sin'gye-ri",
    "gn:country_code":"KP",
    "gn:dem":257,
    "gn:feature_class":"P",
    "gn:feature_code":"PPL",
    "gn:name":"Sin\u2019gye-ri",
    "gn:population":0,
    "gn:timezone":"Asia/Pyongyang",
    "iso:country":"KP",
    "name:und_x_variant":[
        "Sin\u2019ge-ri",
        "\uc2e0\uacc4\ub9ac",
        "Sin\u2019gye-ri"
    ],
    "wof:name":"Sin'gye-ri",
    "wof:placetype":"locality"
},
  "geometry": {"coordinates":[128.02361000000002,40.17944],"type":"Point"}
}