{
  "type": "Feature",
  "properties": {
    "gn:admin1_code":"3.0",
    "gn:asciiname":"Yongjol-li",
    "gn:country_code":"KP",
    "gn:dem":270,
    "gn:feature_class":"P",
    "gn:feature_code":"PPL",
    "gn:name":"Yongj\u014fl-li",
    "gn:population":0,
    "gn:timezone":"Asia/Pyongyang",
    "iso:country":"KP",
    "name:und_x_variant":[
        "\uc6a9\uc804\ub9ac",
        "Yongj\u014fl-li"
    ],
    "wof:name":"Yongjol-li",
    "wof:placetype":"locality"
},
  "geometry": {"coordinates":[127.82528000000001,40.17889],"type":"Point"}
}