{
  "type": "Feature",
  "properties": {
    "gn:admin1_code":"3.0",
    "gn:admin2_code":"K\u016dmya-gun",
    "gn:asciiname":"Yangjung-ni",
    "gn:country_code":"KP",
    "gn:dem":3,
    "gn:feature_class":"P",
    "gn:feature_code":"PPL",
    "gn:name":"Yangjung-ni",
    "gn:population":0,
    "gn:timezone":"Asia/Pyongyang",
    "iso:country":"KP",
    "name:eng_x_preferred":[
        "Yangjung"
    ],
    "name:eng_x_variant":[
        "Yangjung-ni"
    ],
    "wof:name":"Yangjung",
    "wof:placetype":"locality"
},
  "geometry": {"coordinates":[127.35944000000001,39.45056],"type":"Point"}
}