{
  "type": "Feature",
  "properties": {
    "gn:admin1_code":"6.0",
    "gn:asciiname":"Song-ch'on",
    "gn:country_code":"KP",
    "gn:dem":67,
    "gn:feature_class":"P",
    "gn:feature_code":"PPL",
    "gn:name":"S\u014fng-ch\u2019on",
    "gn:population":0,
    "gn:timezone":"Asia/Pyongyang",
    "iso:country":"KP",
    "wof:name":"Song-ch'on",
    "wof:placetype":"locality"
},
  "geometry": {"coordinates":[125.96889,38.07806],"type":"Point"}
}