{
  "type": "Feature",
  "properties": {
    "gn:admin1_code":"17.0",
    "gn:asciiname":"Namp'yong-dong",
    "gn:country_code":"KP",
    "gn:dem":1224,
    "gn:feature_class":"P",
    "gn:feature_code":"PPL",
    "gn:name":"Namp\u2019y\u014fng-dong",
    "gn:population":0,
    "gn:timezone":"Asia/Pyongyang",
    "iso:country":"KP",
    "name:und_x_variant":[
        "W\u014fnsu",
        "Namp\u2019y\u014fng-dong",
        "\ub0a8\ud3c9\ub3d9"
    ],
    "wof:name":"Namp'yong-dong",
    "wof:placetype":"locality"
},
  "geometry": {"coordinates":[129.07955999999999,41.37147],"type":"Point"}
}