{
  "type": "Feature",
  "properties": {
    "gn:admin1_code":"3.0",
    "gn:asciiname":"Pusang-ni",
    "gn:country_code":"KP",
    "gn:dem":43,
    "gn:feature_class":"P",
    "gn:feature_code":"PPL",
    "gn:name":"Pusang-ni",
    "gn:population":0,
    "gn:timezone":"Asia/Pyongyang",
    "iso:country":"KP",
    "name:und_x_variant":[
        "\ubd80\uc0c1\ub9ac",
        "Pusang-ni"
    ],
    "wof:name":"Pusang-ni",
    "wof:placetype":"locality"
},
  "geometry": {"coordinates":[127.89111,40.09917],"type":"Point"}
}