{
  "type": "Feature",
  "properties": {
    "gn:admin1_code":"12.0",
    "gn:asciiname":"Yongho-ri",
    "gn:country_code":"KP",
    "gn:dem":8,
    "gn:feature_class":"P",
    "gn:feature_code":"PPL",
    "gn:name":"Yongho-ri",
    "gn:population":0,
    "gn:timezone":"Asia/Pyongyang",
    "iso:country":"KP",
    "name:kor_x_preferred":[
        "\ub8e1\ud638\ub9ac"
    ],
    "name:kor_x_variant":[
        "\uc1a1\uc554\ub3d9"
    ],
    "name:und_x_variant":[
        "Songam-dong"
    ],
    "wof:name":"Yongho-ri",
    "wof:placetype":"locality"
},
  "geometry": {"coordinates":[125.64048,38.95005],"type":"Point"}
}