{
  "type": "Feature",
  "properties": {
    "gn:admin1_code":"9.0",
    "gn:asciiname":"Sang-ni",
    "gn:country_code":"KP",
    "gn:dem":63,
    "gn:feature_class":"P",
    "gn:feature_code":"PPL",
    "gn:name":"Sang-ni",
    "gn:population":0,
    "gn:timezone":"Asia/Pyongyang",
    "iso:country":"KP",
    "name:eng_x_preferred":[
        "Sang"
    ],
    "name:eng_x_variant":[
        "Sang-ni"
    ],
    "name:und_x_variant":[
        "\uc0c1\ub9ac"
    ],
    "wof:name":"Sang",
    "wof:placetype":"locality"
},
  "geometry": {"coordinates":[127.386,39.09594],"type":"Point"}
}