{
  "type": "Feature",
  "properties": {
    "gn:admin1_code":"6.0",
    "gn:asciiname":"Mujijae",
    "gn:cc2":"KP",
    "gn:country_code":"KP",
    "gn:dem":32,
    "gn:feature_class":"P",
    "gn:feature_code":"PPL",
    "gn:name":"Mujijae",
    "gn:population":0,
    "gn:timezone":"Asia/Pyongyang",
    "iso:country":"KP",
    "name:und_x_variant":[
        "Mujich\u2019i",
        "Mujijae"
    ],
    "wof:name":"Mujijae",
    "wof:placetype":"locality"
},
  "geometry": {"coordinates":[125.88417,38.02],"type":"Point"}
}