{
  "type": "Feature",
  "properties": {
    "gn:admin1_code":"15.0",
    "gn:asciiname":"Kiwajang-gol",
    "gn:country_code":"KP",
    "gn:dem":448,
    "gn:feature_class":"P",
    "gn:feature_code":"PPL",
    "gn:name":"Kiwajang-gol",
    "gn:population":0,
    "gn:timezone":"Asia/Pyongyang",
    "iso:country":"KP",
    "name:und_x_variant":[
        "\uae30\uc640\uc7a5\uace8",
        "Kiwajang-kol",
        "Kiwajang-gol"
    ],
    "wof:name":"Kiwajang-gol",
    "wof:placetype":"locality"
},
  "geometry": {"coordinates":[126.59999999999999,39.45611],"type":"Point"}
}