{
  "type": "Feature",
  "properties": {
    "gn:admin1_code":"11.0",
    "gn:asciiname":"Togam-ni",
    "gn:country_code":"KP",
    "gn:dem":7,
    "gn:feature_class":"P",
    "gn:feature_code":"PPL",
    "gn:name":"T\u014fgam-ni",
    "gn:population":0,
    "gn:timezone":"Asia/Pyongyang",
    "iso:country":"KP",
    "name:eng_x_preferred":[
        "Togam"
    ],
    "name:eng_x_variant":[
        "Togam-ni"
    ],
    "name:kor_x_preferred":[
        "\ub355\uc554\ub9ac"
    ],
    "name:kor_x_variant":[
        "T\u014fgam-ni"
    ],
    "name:und_x_variant":[
        "Toga-ri",
        "Toga-ma\u016dl"
    ],
    "wof:name":"Togam",
    "wof:placetype":"locality"
},
  "geometry": {"coordinates":[125.36333,39.57167],"type":"Point"}
}