{
  "type": "Feature",
  "properties": {
    "gn:admin1_code":"7.0",
    "gn:admin2_code":"S\u014fh\u016dng-gun",
    "gn:asciiname":"Hwagong-ni",
    "gn:cc2":"KP",
    "gn:country_code":"KP",
    "gn:dem":96,
    "gn:feature_class":"P",
    "gn:feature_code":"PPL",
    "gn:name":"Hwagong-ni",
    "gn:population":0,
    "gn:timezone":"Asia/Pyongyang",
    "iso:country":"KP",
    "name:eng_x_preferred":[
        "Hwagong"
    ],
    "name:eng_x_variant":[
        "Hwagong-ni"
    ],
    "name:kor_x_preferred":[
        "\ud654\uacf5\ub9ac"
    ],
    "name:und_x_variant":[
        "S\u014fh\u016dng",
        "Hwagong-hi",
        "Hwagong-ni",
        "Hwagong"
    ],
    "wof:name":"Hwagong",
    "wof:placetype":"locality"
},
  "geometry": {"coordinates":[126.16306,38.45556],"type":"Point"}
}