{
  "type": "Feature",
  "properties": {
    "gn:admin1_code":"11.0",
    "gn:asciiname":"Namsal-li",
    "gn:country_code":"KP",
    "gn:dem":25,
    "gn:feature_class":"P",
    "gn:feature_code":"PPL",
    "gn:name":"Namsal-li",
    "gn:population":0,
    "gn:timezone":"Asia/Pyongyang",
    "iso:country":"KP",
    "name:und_x_variant":[
        "\ub0a8\uc0b0\ub9ac",
        "Namsan-ni",
        "Namsal-li"
    ],
    "wof:name":"Namsal-li",
    "wof:placetype":"locality"
},
  "geometry": {"coordinates":[124.63806,39.8625],"type":"Point"}
}