{
  "type": "Feature",
  "properties": {
    "gn:admin1_code":"15.0",
    "gn:asciiname":"O-ri",
    "gn:country_code":"KP",
    "gn:dem":23,
    "gn:feature_class":"P",
    "gn:feature_code":"PPL",
    "gn:name":"O-ri",
    "gn:population":0,
    "gn:timezone":"Asia/Pyongyang",
    "iso:country":"KP",
    "wof:name":"O-ri",
    "wof:placetype":"locality"
},
  "geometry": {"coordinates":[125.55167,38.93222],"type":"Point"}
}