{
  "type": "Feature",
  "properties": {
    "gn:admin1_code":"6.0",
    "gn:admin2_code":"Changp\u2019ung-gun",
    "gn:asciiname":"Wonhyon-dong",
    "gn:country_code":"KP",
    "gn:dem":85,
    "gn:feature_class":"P",
    "gn:feature_code":"PPL",
    "gn:name":"W\u014fnhy\u014fn-dong",
    "gn:population":0,
    "gn:timezone":"Asia/Pyongyang",
    "iso:country":"KP",
    "name:und_x_variant":[
        "Inken-d\u014d",
        "Yu\u014fnhy\u014fn-dong",
        "Wonyondong",
        "W\u014fnhy\u014fn-dong"
    ],
    "wof:name":"Wonhyon-dong",
    "wof:placetype":"locality"
},
  "geometry": {"coordinates":[126.85583,38.21444],"type":"Point"}
}