{
  "type": "Feature",
  "properties": {
    "gn:admin1_code":"11.0",
    "gn:asciiname":"Sinan-dong",
    "gn:country_code":"KP",
    "gn:dem":238,
    "gn:feature_class":"P",
    "gn:feature_code":"PPL",
    "gn:name":"Sinan-dong",
    "gn:population":0,
    "gn:timezone":"Asia/Pyongyang",
    "iso:country":"KP",
    "name:und_x_variant":[
        "\uc2e0\uc548\ub3d9",
        "Sinan-dong"
    ],
    "wof:name":"Sinan-dong",
    "wof:placetype":"locality"
},
  "geometry": {"coordinates":[125.19138999999998,40.29611],"type":"Point"}
}