{
  "type": "Feature",
  "properties": {
    "gn:admin1_code":"9.0",
    "gn:asciiname":"Naedong-ni",
    "gn:country_code":"KP",
    "gn:dem":447,
    "gn:feature_class":"P",
    "gn:feature_code":"PPL",
    "gn:name":"Naedong-ni",
    "gn:population":0,
    "gn:timezone":"Asia/Pyongyang",
    "iso:country":"KP",
    "name:eng_x_preferred":[
        "Naedong"
    ],
    "name:eng_x_variant":[
        "Naedong-ni"
    ],
    "name:kor_x_preferred":[
        "\ub0b4\ub3d9\ub9ac"
    ],
    "wof:name":"Naedong",
    "wof:placetype":"locality"
},
  "geometry": {"coordinates":[127.15806000000001,39.04472],"type":"Point"}
}