{
  "type": "Feature",
  "properties": {
    "gn:admin1_code":"6.0",
    "gn:asciiname":"Kang-ch'on",
    "gn:country_code":"KP",
    "gn:dem":12,
    "gn:feature_class":"P",
    "gn:feature_code":"PPL",
    "gn:name":"Kang-ch\u2019on",
    "gn:population":0,
    "gn:timezone":"Asia/Pyongyang",
    "iso:country":"KP",
    "name:und_x_variant":[
        "\uac15\ucd0c",
        "Kang-ch\u2019on"
    ],
    "wof:name":"Kang-ch'on",
    "wof:placetype":"locality"
},
  "geometry": {"coordinates":[125.6725,37.89833],"type":"Point"}
}