{
  "type": "Feature",
  "properties": {
    "gn:admin1_code":"7.0",
    "gn:asciiname":"Chajak-kol",
    "gn:country_code":"KP",
    "gn:dem":116,
    "gn:feature_class":"P",
    "gn:feature_code":"PPL",
    "gn:name":"Chajak-kol",
    "gn:population":0,
    "gn:timezone":"Asia/Pyongyang",
    "iso:country":"KP",
    "name:und_x_variant":[
        "\uc790\uc791\uace8",
        "Chajak-kol"
    ],
    "wof:name":"Chajak-kol",
    "wof:placetype":"locality"
},
  "geometry": {"coordinates":[126.33750000000001,38.22917],"type":"Point"}
}