{
  "type": "Feature",
  "properties": {
    "gn:admin1_code":"11.0",
    "gn:asciiname":"Tapchungch'am",
    "gn:country_code":"KP",
    "gn:dem":116,
    "gn:feature_class":"P",
    "gn:feature_code":"PPL",
    "gn:name":"Tapchungch\u2019am",
    "gn:population":0,
    "gn:timezone":"Asia/Pyongyang",
    "iso:country":"KP",
    "wof:name":"Tapchungch'am",
    "wof:placetype":"locality"
},
  "geometry": {"coordinates":[126.08944,39.99194],"type":"Point"}
}