{
  "type": "Feature",
  "properties": {
    "gn:admin1_code":"6.0",
    "gn:admin2_code":"Kaep'ung-gun",
    "gn:asciiname":"Hugang",
    "gn:country_code":"KP",
    "gn:dem":18,
    "gn:feature_class":"P",
    "gn:feature_code":"PPL",
    "gn:name":"Hugang",
    "gn:population":0,
    "gn:timezone":"Asia/Pyongyang",
    "iso:country":"KP",
    "wof:name":"Hugang",
    "wof:placetype":"locality"
},
  "geometry": {"coordinates":[126.41916999999999,37.925],"type":"Point"}
}