{
  "type": "Feature",
  "properties": {
    "gn:admin1_code":"9.0",
    "gn:asciiname":"Sinch'ang-ni",
    "gn:country_code":"KP",
    "gn:dem":81,
    "gn:feature_class":"P",
    "gn:feature_code":"PPL",
    "gn:name":"Sinch\u2019ang-ni",
    "gn:population":0,
    "gn:timezone":"Asia/Pyongyang",
    "iso:country":"KP",
    "name:kor_x_preferred":[
        "\uc2e0\ucc3d\ub9ac"
    ],
    "name:kor_x_variant":[
        "Sinch\u2019ang-ni"
    ],
    "wof:name":"Sinch'ang-ni",
    "wof:placetype":"locality"
},
  "geometry": {"coordinates":[127.14,39.26861],"type":"Point"}
}