{
  "type": "Feature",
  "properties": {
    "gn:admin1_code":"17.0",
    "gn:asciiname":"Haesang-dong",
    "gn:country_code":"KP",
    "gn:dem":24,
    "gn:feature_class":"P",
    "gn:feature_code":"PPL",
    "gn:name":"Haesang-dong",
    "gn:population":0,
    "gn:timezone":"Asia/Pyongyang",
    "iso:country":"KP",
    "name:und_x_variant":[
        "\ud574\uc0c1\ub3d9",
        "Haesang-dong"
    ],
    "wof:name":"Haesang-dong",
    "wof:placetype":"locality"
},
  "geometry": {"coordinates":[129.97111000000001,42.01222],"type":"Point"}
}