{
  "type": "Feature",
  "properties": {
    "gn:admin1_code":"3.0",
    "gn:asciiname":"Tolgogae-gol",
    "gn:cc2":"KP",
    "gn:country_code":"KP",
    "gn:dem":16,
    "gn:feature_class":"P",
    "gn:feature_code":"PPL",
    "gn:name":"Tolgogae-gol",
    "gn:population":0,
    "gn:timezone":"Asia/Pyongyang",
    "iso:country":"KP",
    "name:und_x_variant":[
        "S\u014fngny\u014fng-dong",
        "\ub3cc\uace0\uac1c\uace8",
        "Tolgogae-gol"
    ],
    "wof:name":"Tolgogae-gol",
    "wof:placetype":"locality"
},
  "geometry": {"coordinates":[128.83972,40.42639000000001],"type":"Point"}
}