{
  "type": "Feature",
  "properties": {
    "gn:admin1_code":"3.0",
    "gn:asciiname":"Sinhungjang",
    "gn:country_code":"KP",
    "gn:dem":1415,
    "gn:feature_class":"P",
    "gn:feature_code":"PPL",
    "gn:name":"Sinh\u016dngjang",
    "gn:population":0,
    "gn:timezone":"Asia/Pyongyang",
    "iso:country":"KP",
    "name:und_x_variant":[
        "\uc2e0\ud765\uc7a5",
        "Sinh\u016dngjang"
    ],
    "wof:name":"Sinhungjang",
    "wof:placetype":"locality"
},
  "geometry": {"coordinates":[127.16083,40.34889],"type":"Point"}
}