{
  "type": "Feature",
  "properties": {
    "gn:country":"KP",
    "gn:fcode":"PPLL",
    "gn:population":8410,
    "iso:country":"KP",
    "name:und_x_variant":[
        "Ungsang-dong"
    ],
    "qs:name":"Ungsang-nodongjagu",
    "qs:photos_9r":0,
    "qs:photos_sr":0,
    "qs:pop_sr":"5",
    "wof:name":"Ungsang-nodongjagu",
    "wof:placetype":"locality",
    "wof:population":8410
},
  "geometry": {"coordinates":[130.46222,42.35778],"type":"Point"}
}