{
  "type": "Feature",
  "properties": {
    "gn:admin1_code":"3.0",
    "gn:asciiname":"Paengnam-ni",
    "gn:country_code":"KP",
    "gn:dem":23,
    "gn:feature_class":"P",
    "gn:feature_code":"PPL",
    "gn:name":"Paengnam-ni",
    "gn:population":0,
    "gn:timezone":"Asia/Pyongyang",
    "iso:country":"KP",
    "name:eng_x_preferred":[
        "Paengnam"
    ],
    "name:eng_x_variant":[
        "Paengnam-ni"
    ],
    "name:und_x_variant":[
        "\ubc31\ub0a8\ub9ac",
        "Paengnam-ni"
    ],
    "wof:name":"Paengnam",
    "wof:placetype":"locality"
},
  "geometry": {"coordinates":[127.31694,39.54417],"type":"Point"}
}