{
  "type": "Feature",
  "properties": {
    "gn:admin1_code":"1.0",
    "gn:asciiname":"Nojon-dong",
    "gn:country_code":"KP",
    "gn:dem":202,
    "gn:feature_class":"P",
    "gn:feature_code":"PPL",
    "gn:name":"Noj\u014fn-dong",
    "gn:population":0,
    "gn:timezone":"Asia/Pyongyang",
    "iso:country":"KP",
    "name:und_x_variant":[
        "\ub178\uc804\ub3d9",
        "Noj\u014fn-dong"
    ],
    "wof:name":"Nojon-dong",
    "wof:placetype":"locality"
},
  "geometry": {"coordinates":[125.80638999999999,40.84528],"type":"Point"}
}