{
  "type": "Feature",
  "properties": {
    "gn:country":"KP",
    "gn:fcode":"PPL",
    "gn:population":152425,
    "iso:country":"KP",
    "name:ace_x_preferred":[
        "Songrim"
    ],
    "name:bul_x_preferred":[
        "\u0421\u043e\u043d\u0440\u0438\u043c"
    ],
    "name:ceb_x_preferred":[
        "Songnim"
    ],
    "name:ces_x_preferred":[
        "Songnim"
    ],
    "name:deu_x_preferred":[
        "Songnim"
    ],
    "name:eng_x_preferred":[
        "Songrim"
    ],
    "name:epo_x_preferred":[
        "Songnim"
    ],
    "name:fas_x_preferred":[
        "\u0633\u0648\u0646\u06af\u0646\u06cc\u0645"
    ],
    "name:fin_x_preferred":[
        "Songrim"
    ],
    "name:fra_x_preferred":[
        "Songrim"
    ],
    "name:ita_x_preferred":[
        "Songrim"
    ],
    "name:jpn_x_preferred":[
        "\u677e\u6797\u5e02"
    ],
    "name:kor_x_preferred":[
        "\uc1a1\ub9bc\uc2dc"
    ],
    "name:mkd_x_preferred":[
        "\u0421\u043e\u043d\u0433\u043d\u0438\u043c"
    ],
    "name:nan_x_preferred":[
        "Songrim Chh\u012b"
    ],
    "name:nds_x_preferred":[
        "Songrim"
    ],
    "name:nld_x_preferred":[
        "Songrim"
    ],
    "name:nob_x_preferred":[
        "Songrim"
    ],
    "name:pol_x_preferred":[
        "Songnim"
    ],
    "name:ron_x_preferred":[
        "Songrim"
    ],
    "name:rus_x_preferred":[
        "\u0421\u043e\u043d\u043d\u0438\u043c"
    ],
    "name:swe_x_preferred":[
        "Songrim"
    ],
    "name:tgl_x_preferred":[
        "Songnim"
    ],
    "name:tur_x_preferred":[
        "Songnim"
    ],
    "name:und_x_variant":[
        "Kenjiho"
    ],
    "name:urd_x_preferred":[
        "\u0633\u0648\u0646\u06af\u0646\u0645"
    ],
    "name:vie_x_preferred":[
        "Songrim"
    ],
    "name:zho_x_preferred":[
        "\u677e\u6797\u5e02"
    ],
    "qs:name":"Songnim",
    "qs:photos_9r":0,
    "qs:photos_sr":0,
    "qs:pop_sr":"9",
    "wd:wordcount":119,
    "wof:name":"Songnim",
    "wof:placetype":"locality",
    "wof:population":152425
},
  "geometry": {"coordinates":[125.645,38.75417],"type":"Point"}
}