{
  "type": "Feature",
  "properties": {
    "gn:admin1_code":"1.0",
    "gn:asciiname":"Komul-li",
    "gn:country_code":"KP",
    "gn:dem":311,
    "gn:feature_class":"P",
    "gn:feature_code":"PPL",
    "gn:name":"K\u014fmul-li",
    "gn:population":0,
    "gn:timezone":"Asia/Pyongyang",
    "iso:country":"KP",
    "name:und_x_variant":[
        "\uac70\ubb38\ub9ac",
        "K\u014fmul-li"
    ],
    "wof:name":"Komul-li",
    "wof:placetype":"locality"
},
  "geometry": {"coordinates":[125.62139000000001,40.73583],"type":"Point"}
}