{
  "type": "Feature",
  "properties": {
    "gn:admin1_code":"17.0",
    "gn:asciiname":"Chuganch'on",
    "gn:country_code":"KP",
    "gn:dem":70,
    "gn:feature_class":"P",
    "gn:feature_code":"PPL",
    "gn:name":"Chuganch\u2019on",
    "gn:population":0,
    "gn:timezone":"Asia/Pyongyang",
    "iso:country":"KP",
    "name:und_x_variant":[
        "\uc8fc\uac04\ucd0c",
        "Chuganch\u2019on"
    ],
    "wof:name":"Chuganch'on",
    "wof:placetype":"locality"
},
  "geometry": {"coordinates":[129.30694,40.89639],"type":"Point"}
}