{
  "type": "Feature",
  "properties": {
    "gn:admin1_code":"12.0",
    "gn:asciiname":"Samga-ri",
    "gn:country_code":"KP",
    "gn:dem":5,
    "gn:feature_class":"P",
    "gn:feature_code":"PPL",
    "gn:name":"Samga-ri",
    "gn:population":0,
    "gn:timezone":"Asia/Pyongyang",
    "iso:country":"KP",
    "name:kor_x_preferred":[
        "\uc0bc\uac00\ub9ac"
    ],
    "name:und_x_variant":[
        "Samg\u014f-ri",
        "Samga-ri",
        "Samgari"
    ],
    "wof:name":"Samga-ri",
    "wof:placetype":"locality"
},
  "geometry": {"coordinates":[125.58708,38.87796],"type":"Point"}
}