{
  "type": "Feature",
  "properties": {
    "gn:admin1_code":"0.0",
    "gn:asciiname":"Sono-gol",
    "gn:cc2":"KP",
    "gn:country_code":"KP",
    "gn:dem":62,
    "gn:feature_class":"P",
    "gn:feature_code":"PPL",
    "gn:name":"Sono-gol",
    "gn:population":0,
    "gn:timezone":"Asia/Pyongyang",
    "iso:country":"KP",
    "name:kor_x_preferred":[
        "\uc18c\ub178\uace8"
    ],
    "name:und_x_variant":[
        "Sono-dong",
        "Sono-gol"
    ],
    "wof:name":"Sono-gol",
    "wof:placetype":"locality"
},
  "geometry": {"coordinates":[125.81667,38.88333],"type":"Point"}
}