{
  "type": "Feature",
  "properties": {
    "gn:admin1_code":"11.0",
    "gn:asciiname":"Ku-ri",
    "gn:country_code":"KP",
    "gn:dem":111,
    "gn:feature_class":"P",
    "gn:feature_code":"PPL",
    "gn:name":"Ku-ri",
    "gn:population":0,
    "gn:timezone":"Asia/Pyongyang",
    "iso:country":"KP",
    "name:und_x_variant":[
        "\uad6c\ub9ac",
        "Ku-ri"
    ],
    "wof:name":"Ku-ri",
    "wof:placetype":"locality"
},
  "geometry": {"coordinates":[125.85111000000001,40.0625],"type":"Point"}
}