{
  "type": "Feature",
  "properties": {
    "gn:admin1_code":"15.0",
    "gn:asciiname":"Yusong",
    "gn:country_code":"KP",
    "gn:dem":24,
    "gn:feature_class":"P",
    "gn:feature_code":"PPL",
    "gn:name":"Yus\u014fng",
    "gn:population":0,
    "gn:timezone":"Asia/Pyongyang",
    "iso:country":"KP",
    "name:kor_x_preferred":[
        "\uc720\uc131"
    ],
    "name:kor_x_variant":[
        "Yus\u014fng"
    ],
    "wof:name":"Yusong",
    "wof:placetype":"locality"
},
  "geometry": {"coordinates":[125.69194,39.68444],"type":"Point"}
}