{
  "type": "Feature",
  "properties": {
    "gn:admin1_code":"13.0",
    "gn:asciiname":"Sorhang-ni",
    "gn:country_code":"KP",
    "gn:dem":1203,
    "gn:feature_class":"P",
    "gn:feature_code":"PPL",
    "gn:name":"S\u014frhang-ni",
    "gn:population":0,
    "gn:timezone":"Asia/Pyongyang",
    "iso:country":"KP",
    "name:und_x_variant":[
        "\uc124\ud559\ub9ac",
        "S\u014frhang-ni"
    ],
    "wof:name":"Sorhang-ni",
    "wof:placetype":"locality"
},
  "geometry": {"coordinates":[128.12943999999999,40.84278],"type":"Point"}
}