{
  "type": "Feature",
  "properties": {
    "gn:admin1_code":"13.0",
    "gn:asciiname":"Sokp'yong-ni",
    "gn:country_code":"KP",
    "gn:dem":630,
    "gn:feature_class":"P",
    "gn:feature_code":"PPL",
    "gn:name":"S\u014fkp\u2019y\u014fng-ni",
    "gn:population":0,
    "gn:timezone":"Asia/Pyongyang",
    "iso:country":"KP",
    "name:eng_x_preferred":[
        "Sokp'yong"
    ],
    "name:eng_x_variant":[
        "Sokp'yong-ni"
    ],
    "wof:name":"Sokp'yong",
    "wof:placetype":"locality"
},
  "geometry": {"coordinates":[127.72417,41.27444],"type":"Point"}
}