{
  "type": "Feature",
  "properties": {
    "gn:admin1_code":"7.0",
    "gn:asciiname":"Kumnung-ni",
    "gn:country_code":"KP",
    "gn:dem":142,
    "gn:feature_class":"P",
    "gn:feature_code":"PPL",
    "gn:name":"K\u016dmn\u016dng-ni",
    "gn:population":0,
    "gn:timezone":"Asia/Pyongyang",
    "iso:country":"KP",
    "name:und_x_variant":[
        "\uae08\ub989\ub9ac",
        "K\u016dmn\u016dng-ni"
    ],
    "wof:name":"Kumnung-ni",
    "wof:placetype":"locality"
},
  "geometry": {"coordinates":[126.13583,38.39111],"type":"Point"}
}