{
  "type": "Feature",
  "properties": {
    "gn:admin1_code":"0.0",
    "gn:asciiname":"Ch'uksanp'o",
    "gn:country_code":"KP",
    "gn:dem":933,
    "gn:feature_class":"P",
    "gn:feature_code":"PPL",
    "gn:name":"Ch\u2019\u016dksanp\u2019o",
    "gn:population":0,
    "gn:timezone":"Asia/Pyongyang",
    "iso:country":"KP",
    "name:kor_x_preferred":[
        "\uce21\uc0b0\ud3ec"
    ],
    "name:und_x_variant":[
        "Ch\u2019\u016dksanp\u2019o"
    ],
    "wof:name":"Ch'uksanp'o",
    "wof:placetype":"locality"
},
  "geometry": {"coordinates":[127.96666999999999,40.48333],"type":"Point"}
}