{
  "type": "Feature",
  "properties": {
    "gn:admin1_code":"9.0",
    "gn:asciiname":"Such'ol-li",
    "gn:country_code":"KP",
    "gn:dem":11,
    "gn:feature_class":"P",
    "gn:feature_code":"PPL",
    "gn:name":"Such\u2019\u014fl-li",
    "gn:population":0,
    "gn:timezone":"Asia/Pyongyang",
    "iso:country":"KP",
    "name:und_x_variant":[
        "Such\u2019\u014fn-ni",
        "Such\u2019\u014fl-li"
    ],
    "wof:name":"Such'ol-li",
    "wof:placetype":"locality"
},
  "geometry": {"coordinates":[127.81806,39.00222],"type":"Point"}
}