{
  "type": "Feature",
  "properties": {
    "gn:admin1_code":"15.0",
    "gn:asciiname":"Sang-kol",
    "gn:country_code":"KP",
    "gn:dem":133,
    "gn:feature_class":"P",
    "gn:feature_code":"PPL",
    "gn:name":"Sang-kol",
    "gn:population":0,
    "gn:timezone":"Asia/Pyongyang",
    "iso:country":"KP",
    "wof:name":"Sang-kol",
    "wof:placetype":"locality"
},
  "geometry": {"coordinates":[126.13806,39.33444],"type":"Point"}
}