{
  "type": "Feature",
  "properties": {
    "gn:admin1_code":"1.0",
    "gn:asciiname":"Wai-dong",
    "gn:country_code":"KP",
    "gn:dem":255,
    "gn:feature_class":"P",
    "gn:feature_code":"PPL",
    "gn:name":"Wai-dong",
    "gn:population":0,
    "gn:timezone":"Asia/Pyongyang",
    "iso:country":"KP",
    "name:und_x_variant":[
        "\uc640\uc774\ub3d9",
        "Wai-dong"
    ],
    "wof:name":"Wai-dong",
    "wof:placetype":"locality"
},
  "geometry": {"coordinates":[125.81471999999999,40.68111],"type":"Point"}
}