{
  "type": "Feature",
  "properties": {
    "gn:admin1_code":"17.0",
    "gn:asciiname":"Sat'an-dong",
    "gn:country_code":"KP",
    "gn:dem":145,
    "gn:feature_class":"P",
    "gn:feature_code":"PPL",
    "gn:name":"Sat\u2019an-dong",
    "gn:population":0,
    "gn:timezone":"Asia/Pyongyang",
    "iso:country":"KP",
    "name:und_x_variant":[
        "\uc0ac\ud0c4\ub3d9",
        "Sat\u2019an-dong"
    ],
    "wof:name":"Sat'an-dong",
    "wof:placetype":"locality"
},
  "geometry": {"coordinates":[130.13971999999998,42.48194],"type":"Point"}
}