{
  "type": "Feature",
  "properties": {
    "gn:admin1_code":"6.0",
    "gn:asciiname":"Sangokhyon",
    "gn:country_code":"KP",
    "gn:dem":74,
    "gn:feature_class":"P",
    "gn:feature_code":"PPL",
    "gn:name":"Sangokhy\u014fn",
    "gn:population":0,
    "gn:timezone":"Asia/Pyongyang",
    "iso:country":"KP",
    "name:kor_x_preferred":[
        "\uc0c1\uc625\ud604"
    ],
    "name:kor_x_variant":[
        "Sangokhy\u014fn"
    ],
    "wof:name":"Sangokhyon",
    "wof:placetype":"locality"
},
  "geometry": {"coordinates":[125.175,38.36722],"type":"Point"}
}