{
  "type": "Feature",
  "properties": {
    "gn:admin1_code":"7.0",
    "gn:asciiname":"Songjon-dong",
    "gn:country_code":"KP",
    "gn:dem":184,
    "gn:feature_class":"P",
    "gn:feature_code":"PPL",
    "gn:name":"Songj\u014fn-dong",
    "gn:population":0,
    "gn:timezone":"Asia/Pyongyang",
    "iso:country":"KP",
    "wof:name":"Songjon-dong",
    "wof:placetype":"locality"
},
  "geometry": {"coordinates":[126.18167,38.53778],"type":"Point"}
}