{
  "type": "Feature",
  "properties": {
    "gn:admin1_code":"6.0",
    "gn:admin2_code":"Changp\u2019ung-gun",
    "gn:asciiname":"Man-ch'on",
    "gn:country_code":"KP",
    "gn:dem":65,
    "gn:feature_class":"P",
    "gn:feature_code":"PPL",
    "gn:name":"Man-ch\u2019on",
    "gn:population":0,
    "gn:timezone":"Asia/Pyongyang",
    "iso:country":"KP",
    "name:und_x_variant":[
        "Manson",
        "Man-ch\u2019on"
    ],
    "wof:name":"Man-ch'on",
    "wof:placetype":"locality"
},
  "geometry": {"coordinates":[126.72638999999999,38.03389],"type":"Point"}
}