{
  "type": "Feature",
  "properties": {
    "gn:admin1_code":"7.0",
    "gn:asciiname":"Su-gol",
    "gn:cc2":"KP",
    "gn:country_code":"KP",
    "gn:dem":88,
    "gn:feature_class":"P",
    "gn:feature_code":"PPL",
    "gn:name":"Su-gol",
    "gn:population":0,
    "gn:timezone":"Asia/Pyongyang",
    "iso:country":"KP",
    "name:und_x_variant":[
        "Su-kol",
        "Su-gol"
    ],
    "wof:name":"Su-gol",
    "wof:placetype":"locality"
},
  "geometry": {"coordinates":[126.78972,38.30583],"type":"Point"}
}