{
  "type": "Feature",
  "properties": {
    "gn:admin1_code":"6.0",
    "gn:asciiname":"Changnim-dong",
    "gn:country_code":"KP",
    "gn:dem":26,
    "gn:feature_class":"P",
    "gn:feature_code":"PPL",
    "gn:name":"Changnim-dong",
    "gn:population":0,
    "gn:timezone":"Asia/Pyongyang",
    "iso:country":"KP",
    "name:kor_x_preferred":[
        "\uc7a5\ub9bc\ub3d9"
    ],
    "wof:name":"Changnim-dong",
    "wof:placetype":"locality"
},
  "geometry": {"coordinates":[125.53,38.32833],"type":"Point"}
}