{
  "type": "Feature",
  "properties": {
    "gn:admin1_code":"15.0",
    "gn:asciiname":"Sanggongsam-ni",
    "gn:country_code":"KP",
    "gn:dem":11,
    "gn:feature_class":"P",
    "gn:feature_code":"PPL",
    "gn:name":"Sanggongsam-ni",
    "gn:population":0,
    "gn:timezone":"Asia/Pyongyang",
    "iso:country":"KP",
    "name:kor_x_preferred":[
        "\uc0c1\uacf5\uc0bc\ub9ac"
    ],
    "wof:name":"Sanggongsam-ni",
    "wof:placetype":"locality"
},
  "geometry": {"coordinates":[125.42556,39.5025],"type":"Point"}
}