{
  "type": "Feature",
  "properties": {
    "gn:admin1_code":"11.0",
    "gn:asciiname":"Changhung-dong",
    "gn:country_code":"KP",
    "gn:dem":195,
    "gn:feature_class":"P",
    "gn:feature_code":"PPL",
    "gn:name":"Changh\u016dng-dong",
    "gn:population":0,
    "gn:timezone":"Asia/Pyongyang",
    "iso:country":"KP",
    "name:und_x_variant":[
        "\uc7a5\ud765\ub3d9",
        "Changh\u016dng-dong"
    ],
    "wof:name":"Changhung-dong",
    "wof:placetype":"locality"
},
  "geometry": {"coordinates":[125.19972,40.18222],"type":"Point"}
}