{
  "type": "Feature",
  "properties": {
    "gn:admin1_code":"7.0",
    "gn:asciiname":"Maksil-tong",
    "gn:country_code":"KP",
    "gn:dem":107,
    "gn:feature_class":"P",
    "gn:feature_code":"PPL",
    "gn:name":"Maksil-tong",
    "gn:population":0,
    "gn:timezone":"Asia/Pyongyang",
    "iso:country":"KP",
    "name:kor_x_preferred":[
        "\ub9c9\uc2e4\ub3d9"
    ],
    "wof:name":"Maksil-tong",
    "wof:placetype":"locality"
},
  "geometry": {"coordinates":[126.46528000000001,38.68833],"type":"Point"}
}