{
  "type": "Feature",
  "properties": {
    "gn:admin1_code":"7.0",
    "gn:admin2_code":"Y\u014fnsan-gun",
    "gn:asciiname":"Siriwol-li",
    "gn:cc2":"KP",
    "gn:country_code":"KP",
    "gn:dem":130,
    "gn:feature_class":"P",
    "gn:feature_code":"PPL",
    "gn:name":"Siriw\u014fl-li",
    "gn:population":0,
    "gn:timezone":"Asia/Pyongyang",
    "iso:country":"KP",
    "name:kor_x_preferred":[
        "Siriw\u014fl-li"
    ],
    "name:und_x_variant":[
        "Chaeriw\u014fn-ni",
        "Sij\u014fnw\u014fn-ni",
        "Siriw\u014fn-ni"
    ],
    "wof:name":"Siriwol-li",
    "wof:placetype":"locality"
},
  "geometry": {"coordinates":[126.29333,38.81472],"type":"Point"}
}