{
  "type": "Feature",
  "properties": {
    "gn:admin1_code":"17.0",
    "gn:asciiname":"Saenggiryong-nodongjagu",
    "gn:cc2":"KP",
    "gn:country_code":"KP",
    "gn:dem":63,
    "gn:feature_class":"P",
    "gn:feature_code":"PPL",
    "gn:name":"Saenggiry\u014fng-nodongjagu",
    "gn:population":0,
    "gn:timezone":"Asia/Pyongyang",
    "iso:country":"KP",
    "name:und_x_variant":[
        "Saenggiry\u014fng",
        "\uc0dd\uae30\ub839\ub85c\ub3d9\uc790\uad6c",
        "Saenggiry\u014fng-nodongjagu"
    ],
    "wof:name":"Saenggiryong-nodongjagu",
    "wof:placetype":"locality"
},
  "geometry": {"coordinates":[129.61667,41.64],"type":"Point"}
}