{
  "type": "Feature",
  "properties": {
    "gn:admin1_code":"3.0",
    "gn:asciiname":"Oibang",
    "gn:country_code":"KP",
    "gn:dem":372,
    "gn:feature_class":"P",
    "gn:feature_code":"PPL",
    "gn:name":"\u014eibang",
    "gn:population":0,
    "gn:timezone":"Asia/Pyongyang",
    "iso:country":"KP",
    "name:und_x_variant":[
        "\u014eibang",
        "\uc5b4\uc774\ubc29"
    ],
    "wof:name":"Oibang",
    "wof:placetype":"locality"
},
  "geometry": {"coordinates":[128.3349,40.31116],"type":"Point"}
}