{
  "type": "Feature",
  "properties": {
    "gn:admin1_code":"17.0",
    "gn:asciiname":"Kusodang",
    "gn:country_code":"KP",
    "gn:dem":106,
    "gn:feature_class":"P",
    "gn:feature_code":"PPL",
    "gn:name":"Kus\u014fdang",
    "gn:population":0,
    "gn:timezone":"Asia/Pyongyang",
    "iso:country":"KP",
    "name:und_x_variant":[
        "\uad6c\uc11c\ub2f9",
        "Kus\u014fdang"
    ],
    "wof:name":"Kusodang",
    "wof:placetype":"locality"
},
  "geometry": {"coordinates":[130.08028000000002,42.53528],"type":"Point"}
}