{
  "type": "Feature",
  "properties": {
    "gn:admin1_code":"6.0",
    "gn:asciiname":"Nakch'ol-li",
    "gn:country_code":"KP",
    "gn:dem":32,
    "gn:feature_class":"P",
    "gn:feature_code":"PPL",
    "gn:name":"Nakch\u2019\u014fl-li",
    "gn:population":0,
    "gn:timezone":"Asia/Pyongyang",
    "iso:country":"KP",
    "name:und_x_variant":[
        "Nakch\u2019\u014fn-ni",
        "Nakch\u2019\u014fl-li"
    ],
    "wof:name":"Nakch'ol-li",
    "wof:placetype":"locality"
},
  "geometry": {"coordinates":[125.20332999999999,38.53722],"type":"Point"}
}