{
  "type": "Feature",
  "properties": {
    "gn:admin1_code":"11.0",
    "gn:asciiname":"Paksang-dong",
    "gn:country_code":"KP",
    "gn:dem":190,
    "gn:feature_class":"P",
    "gn:feature_code":"PPL",
    "gn:name":"Paksang-dong",
    "gn:population":0,
    "gn:timezone":"Asia/Pyongyang",
    "iso:country":"KP",
    "name:und_x_variant":[
        "\ubc15\uc0c1\ub3d9",
        "Paksan-dong",
        "Paksang-dong"
    ],
    "wof:name":"Paksang-dong",
    "wof:placetype":"locality"
},
  "geometry": {"coordinates":[125.90639,40.14361],"type":"Point"}
}