{
  "type": "Feature",
  "properties": {
    "gn:admin1_code":"7.0",
    "gn:asciiname":"Chunggogae",
    "gn:country_code":"KP",
    "gn:dem":324,
    "gn:feature_class":"P",
    "gn:feature_code":"PPL",
    "gn:name":"Chunggogae",
    "gn:population":0,
    "gn:timezone":"Asia/Pyongyang",
    "iso:country":"KP",
    "wof:name":"Chunggogae",
    "wof:placetype":"locality"
},
  "geometry": {"coordinates":[125.97083000000001,38.18278],"type":"Point"}
}