{
  "type": "Feature",
  "properties": {
    "gn:admin1_code":"3.0",
    "gn:asciiname":"Hwanam-ni",
    "gn:country_code":"KP",
    "gn:dem":330,
    "gn:feature_class":"P",
    "gn:feature_code":"PPL",
    "gn:name":"Hwanam-ni",
    "gn:population":0,
    "gn:timezone":"Asia/Pyongyang",
    "iso:country":"KP",
    "name:eng_x_preferred":[
        "Hwanam"
    ],
    "name:eng_x_variant":[
        "Hwanam-ni"
    ],
    "name:kor_x_preferred":[
        "\ud654\ub0a8\ub9ac"
    ],
    "wof:name":"Hwanam",
    "wof:placetype":"locality"
},
  "geometry": {"coordinates":[126.99278,39.275],"type":"Point"}
}