{
  "type": "Feature",
  "properties": {
    "gn:admin1_code":"6.0",
    "gn:asciiname":"Hagwol-li",
    "gn:country_code":"KP",
    "gn:dem":12,
    "gn:feature_class":"P",
    "gn:feature_code":"PPL",
    "gn:name":"Hagw\u014fl-li",
    "gn:population":0,
    "gn:timezone":"Asia/Pyongyang",
    "iso:country":"KP",
    "name:kor_x_preferred":[
        "\ud559\uc6d4\ub9ac"
    ],
    "name:kor_x_variant":[
        "Hagw\u014fl-li"
    ],
    "wof:name":"Hagwol-li",
    "wof:placetype":"locality"
},
  "geometry": {"coordinates":[125.51555999999999,38.6425],"type":"Point"}
}