{
  "type": "Feature",
  "properties": {
    "gn:admin1_code":"13.0",
    "gn:asciiname":"Taehung-ni",
    "gn:country_code":"KP",
    "gn:dem":773,
    "gn:feature_class":"P",
    "gn:feature_code":"PPL",
    "gn:name":"Taeh\u016dng-ni",
    "gn:population":0,
    "gn:timezone":"Asia/Pyongyang",
    "iso:country":"KP",
    "name:eng_x_preferred":[
        "Taehung"
    ],
    "name:eng_x_variant":[
        "Taehung-ni"
    ],
    "name:kor_x_preferred":[
        "\ub300\ud765\ub9ac"
    ],
    "name:und_x_variant":[
        "Taeh\u016dng-ni"
    ],
    "wof:name":"Taehung",
    "wof:placetype":"locality"
},
  "geometry": {"coordinates":[128.21449999999999,41.39906],"type":"Point"}
}