{
  "type": "Feature",
  "properties": {
    "gn:admin1_code":"1.0",
    "gn:asciiname":"Kubo-dong",
    "gn:country_code":"KP",
    "gn:dem":333,
    "gn:feature_class":"P",
    "gn:feature_code":"PPL",
    "gn:name":"Kubo-dong",
    "gn:population":0,
    "gn:timezone":"Asia/Pyongyang",
    "iso:country":"KP",
    "name:und_x_variant":[
        "\uad6c\ubcf4\ub3d9",
        "Kubo-dong"
    ],
    "wof:name":"Kubo-dong",
    "wof:placetype":"locality"
},
  "geometry": {"coordinates":[126.46972,41.18278],"type":"Point"}
}