{
  "type": "Feature",
  "properties": {
    "gn:admin1_code":"9.0",
    "gn:asciiname":"Kon'gi-gol",
    "gn:country_code":"KP",
    "gn:dem":345,
    "gn:feature_class":"P",
    "gn:feature_code":"PPL",
    "gn:name":"K\u014fn\u2019gi-gol",
    "gn:population":0,
    "gn:timezone":"Asia/Pyongyang",
    "iso:country":"KP",
    "wof:name":"Kon'gi-gol",
    "wof:placetype":"locality"
},
  "geometry": {"coordinates":[127.86499999999999,38.56306],"type":"Point"}
}