{
  "type": "Feature",
  "properties": {
    "gn:admin1_code":"3.0",
    "gn:asciiname":"Nojokpau",
    "gn:country_code":"KP",
    "gn:dem":361,
    "gn:feature_class":"P",
    "gn:feature_code":"PPL",
    "gn:name":"Noj\u014fkpau",
    "gn:population":0,
    "gn:timezone":"Asia/Pyongyang",
    "iso:country":"KP",
    "name:und_x_variant":[
        "Noj\u014fkpawi",
        "Noj\u014fkam",
        "\ub178\uc801\ubc14\uc6b0",
        "Noj\u014fkpau"
    ],
    "wof:name":"Nojokpau",
    "wof:placetype":"locality"
},
  "geometry": {"coordinates":[127.18832999999999,39.93333],"type":"Point"}
}