{
  "type": "Feature",
  "properties": {
    "gn:admin1_code":"7.0",
    "gn:admin2_code":"T'osan-gun",
    "gn:asciiname":"Soech'igol",
    "gn:country_code":"KP",
    "gn:dem":253,
    "gn:feature_class":"P",
    "gn:feature_code":"PPL",
    "gn:name":"Soech\u2019igol",
    "gn:population":0,
    "gn:timezone":"Asia/Pyongyang",
    "iso:country":"KP",
    "name:kor_x_preferred":[
        "\uc1e0\uce58\uace8"
    ],
    "name:und_x_variant":[
        "K\u016dmch\u2019i-ri",
        "Soech\u2019igol"
    ],
    "wof:name":"Soech'igol",
    "wof:placetype":"locality"
},
  "geometry": {"coordinates":[126.73917,38.21333],"type":"Point"}
}