{
  "type": "Feature",
  "properties": {
    "gn:admin1_code":"6.0",
    "gn:asciiname":"Kagung-ni",
    "gn:country_code":"KP",
    "gn:dem":119,
    "gn:feature_class":"P",
    "gn:feature_code":"PPL",
    "gn:name":"Kagung-ni",
    "gn:population":0,
    "gn:timezone":"Asia/Pyongyang",
    "iso:country":"KP",
    "wof:name":"Kagung-ni",
    "wof:placetype":"locality"
},
  "geometry": {"coordinates":[125.73193999999999,38.20528],"type":"Point"}
}