{
  "type": "Feature",
  "properties": {
    "gn:admin1_code":"6.0",
    "gn:asciiname":"Soyang",
    "gn:country_code":"KP",
    "gn:dem":4,
    "gn:feature_class":"P",
    "gn:feature_code":"PPL",
    "gn:name":"Soyang",
    "gn:population":0,
    "gn:timezone":"Asia/Pyongyang",
    "iso:country":"KP",
    "name:bih_x_preferred":[
        "\u0938\u094b\u092f\u093e\u0919"
    ],
    "name:ceb_x_preferred":[
        "Soyang"
    ],
    "name:mai_x_preferred":[
        "\u0938\u094b\u092f\u093e\u0919"
    ],
    "name:msa_x_preferred":[
        "Soyang"
    ],
    "name:nep_x_preferred":[
        "\u0938\u094b\u092f\u093e\u0919"
    ],
    "name:new_x_preferred":[
        "\u0938\u094b\u092f\u093e\u0919\u0917"
    ],
    "name:nld_x_preferred":[
        "Soyang"
    ],
    "name:pol_x_preferred":[
        "Soyang"
    ],
    "wof:name":"Soyang",
    "wof:placetype":"locality"
},
  "geometry": {"coordinates":[125.54222,38.46472],"type":"Point"}
}