{
  "type": "Feature",
  "properties": {
    "gn:admin1_code":"6.0",
    "gn:asciiname":"Nodongmal",
    "gn:cc2":"KP",
    "gn:country_code":"KP",
    "gn:dem":48,
    "gn:feature_class":"P",
    "gn:feature_code":"PPL",
    "gn:name":"Nodongmal",
    "gn:population":0,
    "gn:timezone":"Asia/Pyongyang",
    "iso:country":"KP",
    "name:und_x_variant":[
        "Nondong-mol",
        "Nondon-mol",
        "Nodongmal"
    ],
    "wof:name":"Nodongmal",
    "wof:placetype":"locality"
},
  "geometry": {"coordinates":[126.05249999999999,37.995],"type":"Point"}
}