{
  "type": "Feature",
  "properties": {
    "gn:admin1_code":"15.0",
    "gn:asciiname":"Sinongjom",
    "gn:country_code":"KP",
    "gn:dem":43,
    "gn:feature_class":"P",
    "gn:feature_code":"PPL",
    "gn:name":"Sinongj\u014fm",
    "gn:population":0,
    "gn:timezone":"Asia/Pyongyang",
    "iso:country":"KP",
    "wof:name":"Sinongjom",
    "wof:placetype":"locality"
},
  "geometry": {"coordinates":[125.62389,39.13722],"type":"Point"}
}