{
  "type": "Feature",
  "properties": {
    "gn:admin1_code":"15.0",
    "gn:admin2_code":"T\u014fkch\u2019\u014fn-gun",
    "gn:asciiname":"Mat'al-li",
    "gn:country_code":"KP",
    "gn:dem":332,
    "gn:feature_class":"P",
    "gn:feature_code":"PPL",
    "gn:name":"Mat\u2019al-li",
    "gn:population":0,
    "gn:timezone":"Asia/Pyongyang",
    "iso:country":"KP",
    "name:und_x_variant":[
        "Mat\u2019an-ni",
        "Mat\u2019al-li"
    ],
    "wof:name":"Mat'al-li",
    "wof:placetype":"locality"
},
  "geometry": {"coordinates":[126.44306,39.76472],"type":"Point"}
}