{
  "type": "Feature",
  "properties": {
    "gn:admin1_code":"1.0",
    "gn:asciiname":"Ch'ilp'yong",
    "gn:country_code":"KP",
    "gn:dem":646,
    "gn:feature_class":"P",
    "gn:feature_code":"PPL",
    "gn:name":"Ch\u2019ilp\u2019y\u014fng",
    "gn:population":0,
    "gn:timezone":"Asia/Pyongyang",
    "iso:country":"KP",
    "name:und_x_variant":[
        "\uce60\ud3c9",
        "Ch\u2019ilp\u2019y\u014fng"
    ],
    "wof:name":"Ch'ilp'yong",
    "wof:placetype":"locality"
},
  "geometry": {"coordinates":[126.93361000000002,41.17889],"type":"Point"}
}