{
  "type": "Feature",
  "properties": {
    "gn:admin1_code":"13.0",
    "gn:asciiname":"Sangnyuk-tong",
    "gn:cc2":"KP",
    "gn:country_code":"KP",
    "gn:dem":736,
    "gn:feature_class":"P",
    "gn:feature_code":"PPL",
    "gn:name":"Sangnyuk-tong",
    "gn:population":0,
    "gn:timezone":"Asia/Pyongyang",
    "iso:country":"KP",
    "name:und_x_variant":[
        "Sangyuk-tong",
        "Sangnyuk-tong"
    ],
    "wof:name":"Sangnyuk-tong",
    "wof:placetype":"locality"
},
  "geometry": {"coordinates":[128.94917000000001,42.02861],"type":"Point"}
}