{
  "type": "Feature",
  "properties": {
    "gn:admin1_code":"0.0",
    "gn:asciiname":"Namyangdongan-gol",
    "gn:country_code":"KP",
    "gn:dem":9,
    "gn:feature_class":"P",
    "gn:feature_code":"PPL",
    "gn:name":"Namyangdongan-gol",
    "gn:population":0,
    "gn:timezone":"Asia/Pyongyang",
    "iso:country":"KP",
    "name:kor_x_preferred":[
        "\ub0a8\uc591\ub3d9\uc548\uace8"
    ],
    "name:und_x_variant":[
        "Namyangdongnae-dong",
        "Namyangdongan-gol"
    ],
    "wof:name":"Namyangdongan-gol",
    "wof:placetype":"locality"
},
  "geometry": {"coordinates":[125.21666999999999,39.63333],"type":"Point"}
}