{
  "type": "Feature",
  "properties": {
    "gn:admin1_code":"13.0",
    "gn:admin2_code":"2041726",
    "gn:asciiname":"Toyon-dong",
    "gn:country_code":"KP",
    "gn:dem":1302,
    "gn:feature_class":"P",
    "gn:feature_code":"PPL",
    "gn:name":"Toy\u014fn-dong",
    "gn:population":0,
    "gn:timezone":"Asia/Pyongyang",
    "iso:country":"KP",
    "wof:name":"Toyon-dong",
    "wof:placetype":"locality"
},
  "geometry": {"coordinates":[127.92167000000001,40.87194],"type":"Point"}
}