{
  "type": "Feature",
  "properties": {
    "gn:admin1_code":"12.0",
    "gn:asciiname":"Nut'i-gol",
    "gn:country_code":"KP",
    "gn:dem":91,
    "gn:feature_class":"P",
    "gn:feature_code":"PPL",
    "gn:name":"N\u016dt\u2019i-gol",
    "gn:population":0,
    "gn:timezone":"Asia/Pyongyang",
    "iso:country":"KP",
    "name:und_x_variant":[
        "\ub290\ud2f0\uace8",
        "N\u016dt\u2019i-gol"
    ],
    "wof:name":"Nut'i-gol",
    "wof:placetype":"locality"
},
  "geometry": {"coordinates":[125.92917,38.82194000000001],"type":"Point"}
}