{
  "type": "Feature",
  "properties": {
    "gn:admin1_code":"15.0",
    "gn:asciiname":"Sosang-ni",
    "gn:country_code":"KP",
    "gn:dem":218,
    "gn:feature_class":"P",
    "gn:feature_code":"PPL",
    "gn:name":"Sosang-ni",
    "gn:population":0,
    "gn:timezone":"Asia/Pyongyang",
    "iso:country":"KP",
    "name:kor_x_preferred":[
        "\uc18c\uc0c1\ub9ac"
    ],
    "wof:name":"Sosang-ni",
    "wof:placetype":"locality"
},
  "geometry": {"coordinates":[126.42833,39.44861],"type":"Point"}
}