{
  "type": "Feature",
  "properties": {
    "gn:admin1_code":"3.0",
    "gn:admin2_code":"Puj\u014fn-gun",
    "gn:asciiname":"Norumong-ni",
    "gn:country_code":"KP",
    "gn:dem":955,
    "gn:feature_class":"P",
    "gn:feature_code":"PPL",
    "gn:name":"Norumong-ni",
    "gn:population":0,
    "gn:timezone":"Asia/Pyongyang",
    "iso:country":"KP",
    "name:eng_x_preferred":[
        "Norumong"
    ],
    "name:eng_x_variant":[
        "Norumong-ni"
    ],
    "name:kor_x_preferred":[
        "\ub178\ub8e8\ubaa9\ub9ac"
    ],
    "wof:name":"Norumong",
    "wof:placetype":"locality"
},
  "geometry": {"coordinates":[127.49083,40.98194],"type":"Point"}
}