{
  "type": "Feature",
  "properties": {
    "gn:admin1_code":"11.0",
    "gn:asciiname":"Chuum-dong",
    "gn:country_code":"KP",
    "gn:dem":100,
    "gn:feature_class":"P",
    "gn:feature_code":"PPL",
    "gn:name":"Chu\u016dm-dong",
    "gn:population":0,
    "gn:timezone":"Asia/Pyongyang",
    "iso:country":"KP",
    "name:und_x_variant":[
        "\uc8fc\uc74c\ub3d9",
        "Chu\u016dm-dong"
    ],
    "wof:name":"Chuum-dong",
    "wof:placetype":"locality"
},
  "geometry": {"coordinates":[124.75972,40.06167],"type":"Point"}
}