{
  "type": "Feature",
  "properties": {
    "gn:admin1_code":"11.0",
    "gn:asciiname":"Omong-ni",
    "gn:country_code":"KP",
    "gn:dem":39,
    "gn:feature_class":"P",
    "gn:feature_code":"PPL",
    "gn:name":"Omong-ni",
    "gn:population":0,
    "gn:timezone":"Asia/Pyongyang",
    "iso:country":"KP",
    "name:eng_x_preferred":[
        "Omong"
    ],
    "name:eng_x_variant":[
        "Omong-ni"
    ],
    "name:kor_x_preferred":[
        "\uc624\ubaa9\ub9ac"
    ],
    "wof:name":"Omong",
    "wof:placetype":"locality"
},
  "geometry": {"coordinates":[124.8725,39.84972],"type":"Point"}
}