{
  "type": "Feature",
  "properties": {
    "gn:admin1_code":"15.0",
    "gn:asciiname":"Unp'oriki-ri",
    "gn:country_code":"KP",
    "gn:dem":34,
    "gn:feature_class":"P",
    "gn:feature_code":"PPL",
    "gn:name":"Unp\u2019oriki-ri",
    "gn:population":0,
    "gn:timezone":"Asia/Pyongyang",
    "iso:country":"KP",
    "wof:name":"Unp'oriki-ri",
    "wof:placetype":"locality"
},
  "geometry": {"coordinates":[125.42861000000001,39.04278],"type":"Point"}
}