{
  "type": "Feature",
  "properties": {
    "gn:admin1_code":"6.0",
    "gn:asciiname":"Kungsi-ri",
    "gn:country_code":"KP",
    "gn:dem":14,
    "gn:feature_class":"P",
    "gn:feature_code":"PPL",
    "gn:name":"Kungsi-ri",
    "gn:population":0,
    "gn:timezone":"Asia/Pyongyang",
    "iso:country":"KP",
    "name:kor_x_preferred":[
        "\uad81\uc2dc\ub9ac"
    ],
    "wof:name":"Kungsi-ri",
    "wof:placetype":"locality"
},
  "geometry": {"coordinates":[126.06028000000001,37.87361],"type":"Point"}
}