{
  "type": "Feature",
  "properties": {
    "gn:admin1_code":"3.0",
    "gn:asciiname":"Hungch'ol-li",
    "gn:country_code":"KP",
    "gn:dem":87,
    "gn:feature_class":"P",
    "gn:feature_code":"PPL",
    "gn:name":"H\u016dngch\u2019\u014fl-li",
    "gn:population":0,
    "gn:timezone":"Asia/Pyongyang",
    "iso:country":"KP",
    "name:und_x_variant":[
        "\ud765\ucc9c\ub9ac",
        "H\u016dngch\u2019\u014fl-li"
    ],
    "wof:name":"Hungch'ol-li",
    "wof:placetype":"locality"
},
  "geometry": {"coordinates":[127.26778,39.735],"type":"Point"}
}