{
  "type": "Feature",
  "properties": {
    "gn:admin1_code":"7.0",
    "gn:asciiname":"Sinch'ol-li",
    "gn:country_code":"KP",
    "gn:dem":80,
    "gn:feature_class":"P",
    "gn:feature_code":"PPL",
    "gn:name":"Sinch\u2019ol-li",
    "gn:population":0,
    "gn:timezone":"Asia/Pyongyang",
    "iso:country":"KP",
    "name:und_x_variant":[
        "Sinch\u2019on-ni",
        "Sinch\u2019ol-li"
    ],
    "wof:name":"Sinch'ol-li",
    "wof:placetype":"locality"
},
  "geometry": {"coordinates":[126.06999999999999,38.39722],"type":"Point"}
}