{
  "type": "Feature",
  "properties": {
    "gn:admin1_code":"7.0",
    "gn:asciiname":"Sap'yong",
    "gn:country_code":"KP",
    "gn:dem":196,
    "gn:feature_class":"P",
    "gn:feature_code":"PPL",
    "gn:name":"Sap\u2019y\u014fng",
    "gn:population":0,
    "gn:timezone":"Asia/Pyongyang",
    "iso:country":"KP",
    "name:kor_x_preferred":[
        "\uc0ac\ud3c9"
    ],
    "name:kor_x_variant":[
        "Sap\u2019y\u014fng"
    ],
    "wof:name":"Sap'yong",
    "wof:placetype":"locality"
},
  "geometry": {"coordinates":[126.815,38.90722],"type":"Point"}
}