{
  "type": "Feature",
  "properties": {
    "gn:admin1_code":"17.0",
    "gn:admin2_code":"\u016cnd\u014fk-kun",
    "gn:asciiname":"Pulgundunji",
    "gn:country_code":"KP",
    "gn:dem":157,
    "gn:feature_class":"P",
    "gn:feature_code":"PPL",
    "gn:name":"Pulg\u016dndunji",
    "gn:population":0,
    "gn:timezone":"Asia/Pyongyang",
    "iso:country":"KP",
    "name:und_x_variant":[
        "\ubd89\uc740\ub454\uc9c0",
        "Pulg\u016dndunji"
    ],
    "wof:name":"Pulgundunji",
    "wof:placetype":"locality"
},
  "geometry": {"coordinates":[130.22916999999998,42.48889000000001],"type":"Point"}
}