{
  "type": "Feature",
  "properties": {
    "gn:admin1_code":"3.0",
    "gn:asciiname":"Tojinp'o",
    "gn:country_code":"KP",
    "gn:dem":73,
    "gn:feature_class":"P",
    "gn:feature_code":"PPL",
    "gn:name":"Tojinp\u2019o",
    "gn:population":0,
    "gn:timezone":"Asia/Pyongyang",
    "iso:country":"KP",
    "name:und_x_variant":[
        "Tojinp\u2019o",
        "\ub3c4\uc9c4\ud3ec"
    ],
    "wof:name":"Tojinp'o",
    "wof:placetype":"locality"
},
  "geometry": {"coordinates":[128.2225,40.17583],"type":"Point"}
}