{
  "type": "Feature",
  "properties": {
    "gn:admin1_code":"6.0",
    "gn:asciiname":"Naedong-maul",
    "gn:country_code":"KP",
    "gn:dem":25,
    "gn:feature_class":"P",
    "gn:feature_code":"PPL",
    "gn:name":"Naedong-ma\u016dl",
    "gn:population":0,
    "gn:timezone":"Asia/Pyongyang",
    "iso:country":"KP",
    "name:kor_x_preferred":[
        "Naedong-ma\u016dl"
    ],
    "name:kor_x_variant":[
        "\ub0b4\ub3d9\ub9c8\uc744",
        "\ub0b4\ub3d9"
    ],
    "name:und_x_variant":[
        "Nae-dong"
    ],
    "wof:name":"Naedong-maul",
    "wof:placetype":"locality"
},
  "geometry": {"coordinates":[125.61924,38.35327],"type":"Point"}
}