{
  "type": "Feature",
  "properties": {
    "gn:admin1_code":"0.0",
    "gn:asciiname":"Tolji-dong",
    "gn:country_code":"KP",
    "gn:dem":56,
    "gn:feature_class":"P",
    "gn:feature_code":"PPL",
    "gn:name":"Tolji-dong",
    "gn:population":0,
    "gn:timezone":"Asia/Pyongyang",
    "iso:country":"KP",
    "name:kor_x_preferred":[
        "\ub3cc\uc9c0\ub3d9"
    ],
    "name:und_x_variant":[
        "Tolchi-dong"
    ],
    "wof:name":"Tolji-dong",
    "wof:placetype":"locality"
},
  "geometry": {"coordinates":[125.98333,38.08333],"type":"Point"}
}