{
  "type": "Feature",
  "properties": {
    "gn:admin1_code":"3.0",
    "gn:asciiname":"Hungni-ch'on",
    "gn:country_code":"KP",
    "gn:dem":316,
    "gn:feature_class":"P",
    "gn:feature_code":"PPL",
    "gn:name":"H\u016dngni-ch\u2019on",
    "gn:population":0,
    "gn:timezone":"Asia/Pyongyang",
    "iso:country":"KP",
    "name:und_x_variant":[
        "H\u016dngni-ch\u2019on",
        "\ud765\ub9ac\ucd0c"
    ],
    "wof:name":"Hungni-ch'on",
    "wof:placetype":"locality"
},
  "geometry": {"coordinates":[128.22859,40.47382],"type":"Point"}
}