{
  "type": "Feature",
  "properties": {
    "gn:admin1_code":"7.0",
    "gn:asciiname":"Yup'al-li",
    "gn:country_code":"KP",
    "gn:dem":129,
    "gn:feature_class":"P",
    "gn:feature_code":"PPL",
    "gn:name":"Yup\u2019al-li",
    "gn:population":0,
    "gn:timezone":"Asia/Pyongyang",
    "iso:country":"KP",
    "name:und_x_variant":[
        "Yup\u2019an-ni",
        "Yup\u2019al-li"
    ],
    "wof:name":"Yup'al-li",
    "wof:placetype":"locality"
},
  "geometry": {"coordinates":[126.095,38.36778],"type":"Point"}
}