{
  "type": "Feature",
  "properties": {
    "gn:admin1_code":"6.0",
    "gn:asciiname":"Sogu-dong",
    "gn:country_code":"KP",
    "gn:dem":59,
    "gn:feature_class":"P",
    "gn:feature_code":"PPL",
    "gn:name":"S\u014fgu-dong",
    "gn:population":0,
    "gn:timezone":"Asia/Pyongyang",
    "iso:country":"KP",
    "wof:name":"Sogu-dong",
    "wof:placetype":"locality"
},
  "geometry": {"coordinates":[125.16028,38.18083],"type":"Point"}
}