{
  "type": "Feature",
  "properties": {
    "gn:admin1_code":"3.0",
    "gn:asciiname":"Yangjich'on",
    "gn:country_code":"KP",
    "gn:dem":11,
    "gn:feature_class":"P",
    "gn:feature_code":"PPL",
    "gn:name":"Yangjich\u2019on",
    "gn:population":0,
    "gn:timezone":"Asia/Pyongyang",
    "iso:country":"KP",
    "name:und_x_variant":[
        "\uc591\uc9c0\ucd0c",
        "Yangjich\u2019on"
    ],
    "wof:name":"Yangjich'on",
    "wof:placetype":"locality"
},
  "geometry": {"coordinates":[129.14111,40.56472],"type":"Point"}
}