{
  "type": "Feature",
  "properties": {
    "gn:admin1_code":"1.0",
    "gn:asciiname":"Songsang-ni",
    "gn:country_code":"KP",
    "gn:dem":340,
    "gn:feature_class":"P",
    "gn:feature_code":"PPL",
    "gn:name":"Songsang-ni",
    "gn:population":0,
    "gn:timezone":"Asia/Pyongyang",
    "iso:country":"KP",
    "name:und_x_variant":[
        "\uc1a1\uc0c1\ub9ac",
        "Songsan-ni",
        "Songsang-ni"
    ],
    "wof:name":"Songsang-ni",
    "wof:placetype":"locality"
},
  "geometry": {"coordinates":[125.55389,40.63694],"type":"Point"}
}