{
  "type": "Feature",
  "properties": {
    "gn:admin1_code":"6.0",
    "gn:asciiname":"Chesallisaet'o",
    "gn:country_code":"KP",
    "gn:dem":18,
    "gn:feature_class":"P",
    "gn:feature_code":"PPL",
    "gn:name":"Chesallisaet\u2019\u014f",
    "gn:population":0,
    "gn:timezone":"Asia/Pyongyang",
    "iso:country":"KP",
    "wof:name":"Chesallisaet'o",
    "wof:placetype":"locality"
},
  "geometry": {"coordinates":[125.90833000000001,37.88028],"type":"Point"}
}