{
  "type": "Feature",
  "properties": {
    "gn:admin1_code":"3.0",
    "gn:asciiname":"Songjong",
    "gn:country_code":"KP",
    "gn:dem":522,
    "gn:feature_class":"P",
    "gn:feature_code":"PPL",
    "gn:name":"Songj\u014fng",
    "gn:population":0,
    "gn:timezone":"Asia/Pyongyang",
    "iso:country":"KP",
    "name:und_x_variant":[
        "\uc131\uc815",
        "Songj\u014fng"
    ],
    "wof:name":"Songjong",
    "wof:placetype":"locality"
},
  "geometry": {"coordinates":[128.56111000000001,40.62194],"type":"Point"}
}