{
  "type": "Feature",
  "properties": {
    "gn:admin1_code":"13.0",
    "gn:asciiname":"Tunji-dong",
    "gn:country_code":"KP",
    "gn:dem":841,
    "gn:feature_class":"P",
    "gn:feature_code":"PPL",
    "gn:name":"Tunji-dong",
    "gn:population":0,
    "gn:timezone":"Asia/Pyongyang",
    "iso:country":"KP",
    "name:kor_x_preferred":[
        "\ub454\uc9c0\ub3d9"
    ],
    "wof:name":"Tunji-dong",
    "wof:placetype":"locality"
},
  "geometry": {"coordinates":[128.37031999999999,41.38249],"type":"Point"}
}