{
  "type": "Feature",
  "properties": {
    "gn:admin1_code":"17.0",
    "gn:asciiname":"Tongsu-gol",
    "gn:country_code":"KP",
    "gn:dem":482,
    "gn:feature_class":"P",
    "gn:feature_code":"PPL",
    "gn:name":"Tongsu-gol",
    "gn:population":0,
    "gn:timezone":"Asia/Pyongyang",
    "iso:country":"KP",
    "name:und_x_variant":[
        "Tongsu-kol",
        "\ub3d9\uc218\uace8",
        "Tongsu-gol"
    ],
    "wof:name":"Tongsu-gol",
    "wof:placetype":"locality"
},
  "geometry": {"coordinates":[129.46056000000002,41.80167],"type":"Point"}
}