{
  "type": "Feature",
  "properties": {
    "gn:admin1_code":"0.0",
    "gn:asciiname":"Sosong-ni",
    "gn:country_code":"KP",
    "gn:dem":14,
    "gn:feature_class":"P",
    "gn:feature_code":"PPL",
    "gn:name":"S\u014fs\u014fng-ni",
    "gn:population":0,
    "gn:timezone":"Asia/Pyongyang",
    "iso:country":"KP",
    "name:eng_x_preferred":[
        "Sosong"
    ],
    "name:eng_x_variant":[
        "Sosong-ni"
    ],
    "name:kor_x_preferred":[
        "\uc11c\uc131\ub9ac"
    ],
    "name:kor_x_variant":[
        "S\u014fs\u014fng-ni"
    ],
    "wof:name":"Sosong",
    "wof:placetype":"locality"
},
  "geometry": {"coordinates":[125.58306,39.57056],"type":"Point"}
}