{
  "type": "Feature",
  "properties": {
    "gn:admin1_code":"17.0",
    "gn:admin2_code":"2038910",
    "gn:asciiname":"Kalp'yong",
    "gn:country_code":"KP",
    "gn:dem":675,
    "gn:feature_class":"P",
    "gn:feature_code":"PPL",
    "gn:name":"Kalp\u2019y\u014fng",
    "gn:population":0,
    "gn:timezone":"Asia/Pyongyang",
    "iso:country":"KP",
    "name:kor_x_preferred":[
        "\uac08\ud3c9"
    ],
    "name:und_x_variant":[
        "Kalp\u2019y\u014fng"
    ],
    "wof:name":"Kalp'yong",
    "wof:placetype":"locality"
},
  "geometry": {"coordinates":[128.91435000000001,41.97542],"type":"Point"}
}