{
  "type": "Feature",
  "properties": {
    "gn:admin1_code":"11.0",
    "gn:asciiname":"Yonp'yong-dong",
    "gn:country_code":"KP",
    "gn:dem":180,
    "gn:feature_class":"P",
    "gn:feature_code":"PPL",
    "gn:name":"Y\u014fnp\u2019y\u014fng-dong",
    "gn:population":0,
    "gn:timezone":"Asia/Pyongyang",
    "iso:country":"KP",
    "wof:name":"Yonp'yong-dong",
    "wof:placetype":"locality"
},
  "geometry": {"coordinates":[125.02110999999999,40.41556],"type":"Point"}
}