{
  "type": "Feature",
  "properties": {
    "gn:admin1_code":"6.0",
    "gn:asciiname":"Sunmang-ni",
    "gn:country_code":"KP",
    "gn:dem":89,
    "gn:feature_class":"P",
    "gn:feature_code":"PPL",
    "gn:name":"Sunmang-ni",
    "gn:population":0,
    "gn:timezone":"Asia/Pyongyang",
    "iso:country":"KP",
    "name:kor_x_preferred":[
        "\uc21c\ub9dd\ub9ac"
    ],
    "wof:name":"Sunmang-ni",
    "wof:placetype":"locality"
},
  "geometry": {"coordinates":[125.28333000000001,38.25],"type":"Point"}
}