{
  "type": "Feature",
  "properties": {
    "gn:admin1_code":"11.0",
    "gn:asciiname":"Hadal-li",
    "gn:country_code":"KP",
    "gn:dem":35,
    "gn:feature_class":"P",
    "gn:feature_code":"PPL",
    "gn:name":"Hadal-li",
    "gn:population":0,
    "gn:timezone":"Asia/Pyongyang",
    "iso:country":"KP",
    "name:kor_x_preferred":[
        "\ud558\ub2e8\ub9ac"
    ],
    "name:und_x_variant":[
        "Hadan",
        "Hadal-li"
    ],
    "wof:name":"Hadal-li",
    "wof:placetype":"locality"
},
  "geometry": {"coordinates":[125.17889,39.67056],"type":"Point"}
}