{
  "type": "Feature",
  "properties": {
    "gn:admin1_code":"7.0",
    "gn:asciiname":"Kayang-ni",
    "gn:country_code":"KP",
    "gn:dem":5,
    "gn:feature_class":"P",
    "gn:feature_code":"PPL",
    "gn:name":"Kayang-ni",
    "gn:population":0,
    "gn:timezone":"Asia/Pyongyang",
    "iso:country":"KP",
    "name:eng_x_preferred":[
        "Kayang"
    ],
    "name:eng_x_variant":[
        "Kayang-ni"
    ],
    "name:kor_x_preferred":[
        "\uac00\uc591\ub9ac"
    ],
    "wof:name":"Kayang",
    "wof:placetype":"locality"
},
  "geometry": {"coordinates":[125.58917,38.51444],"type":"Point"}
}