{
  "type": "Feature",
  "properties": {
    "gn:admin1_code":"11.0",
    "gn:asciiname":"Chungbong-dong",
    "gn:country_code":"KP",
    "gn:dem":162,
    "gn:feature_class":"P",
    "gn:feature_code":"PPL",
    "gn:name":"Ch\u016dngbong-dong",
    "gn:population":0,
    "gn:timezone":"Asia/Pyongyang",
    "iso:country":"KP",
    "name:und_x_variant":[
        "\uc99d\ubd09\ub3d9",
        "Ch\u016dngbong-dong"
    ],
    "wof:name":"Chungbong-dong",
    "wof:placetype":"locality"
},
  "geometry": {"coordinates":[125.66333,40.10028],"type":"Point"}
}