{
  "type": "Feature",
  "properties": {
    "gn:admin1_code":"9.0",
    "gn:asciiname":"Sa-dong",
    "gn:country_code":"KP",
    "gn:dem":577,
    "gn:feature_class":"P",
    "gn:feature_code":"PPL",
    "gn:name":"Sa-dong",
    "gn:population":0,
    "gn:timezone":"Asia/Pyongyang",
    "iso:country":"KP",
    "name:und_x_variant":[
        "\uc0ac\ub3d9",
        "Sa-dong"
    ],
    "wof:name":"Sa-dong",
    "wof:placetype":"locality"
},
  "geometry": {"coordinates":[127.69944,38.72722],"type":"Point"}
}