{
  "type": "Feature",
  "properties": {
    "gn:admin1_code":"11.0",
    "gn:asciiname":"Yongsal-li",
    "gn:country_code":"KP",
    "gn:dem":38,
    "gn:feature_class":"P",
    "gn:feature_code":"PPL",
    "gn:name":"Yongsal-li",
    "gn:population":0,
    "gn:timezone":"Asia/Pyongyang",
    "iso:country":"KP",
    "name:kor_x_preferred":[
        "\uc6a9\uc0b0\ub9ac"
    ],
    "name:und_x_variant":[
        "Yongsang-ni",
        "Yongsal-li"
    ],
    "wof:name":"Yongsal-li",
    "wof:placetype":"locality"
},
  "geometry": {"coordinates":[125.09556000000001,39.73258],"type":"Point"}
}