{
  "type": "Feature",
  "properties": {
    "gn:admin1_code":"6.0",
    "gn:asciiname":"Taegammol",
    "gn:cc2":"KP",
    "gn:country_code":"KP",
    "gn:dem":39,
    "gn:feature_class":"P",
    "gn:feature_code":"PPL",
    "gn:name":"Taegammol",
    "gn:population":0,
    "gn:timezone":"Asia/Pyongyang",
    "iso:country":"KP",
    "name:und_x_variant":[
        "Taegang-ma\u016dl",
        "Taegangch\u2019on",
        "Taegang-dong",
        "Taegammol"
    ],
    "wof:name":"Taegammol",
    "wof:placetype":"locality"
},
  "geometry": {"coordinates":[125.9375,37.98611],"type":"Point"}
}