{
  "type": "Feature",
  "properties": {
    "gn:admin1_code":"15.0",
    "gn:asciiname":"Yangmak-tong",
    "gn:country_code":"KP",
    "gn:dem":70,
    "gn:feature_class":"P",
    "gn:feature_code":"PPL",
    "gn:name":"Yangmak-tong",
    "gn:population":0,
    "gn:timezone":"Asia/Pyongyang",
    "iso:country":"KP",
    "name:eng_x_preferred":[
        "Yangmak"
    ],
    "name:eng_x_variant":[
        "Yangmak-tong"
    ],
    "name:und_x_variant":[
        "\uc591\ub9c9\ub3d9",
        "Yangmak-tong"
    ],
    "wof:name":"Yangmak",
    "wof:placetype":"locality"
},
  "geometry": {"coordinates":[125.36,38.89278],"type":"Point"}
}