{
  "type": "Feature",
  "properties": {
    "gn:admin1_code":"7.0",
    "gn:asciiname":"Hap'yong",
    "gn:country_code":"KP",
    "gn:dem":66,
    "gn:feature_class":"P",
    "gn:feature_code":"PPL",
    "gn:name":"Hap\u2019y\u014fng",
    "gn:population":0,
    "gn:timezone":"Asia/Pyongyang",
    "iso:country":"KP",
    "wof:name":"Hap'yong",
    "wof:placetype":"locality"
},
  "geometry": {"coordinates":[126.03722,38.44111],"type":"Point"}
}