{
  "type": "Feature",
  "properties": {
    "gn:admin1_code":"6.0",
    "gn:asciiname":"Kumbong-ni",
    "gn:country_code":"KP",
    "gn:dem":14,
    "gn:feature_class":"P",
    "gn:feature_code":"PPL",
    "gn:name":"K\u016dmbong-ni",
    "gn:population":0,
    "gn:timezone":"Asia/Pyongyang",
    "iso:country":"KP",
    "name:kor_x_preferred":[
        "\uae08\ubd09\ub9ac"
    ],
    "name:und_x_variant":[
        "K\u016dmbong-ni"
    ],
    "wof:name":"Kumbong-ni",
    "wof:placetype":"locality"
},
  "geometry": {"coordinates":[125.28888999999999,38.63278],"type":"Point"}
}