{
  "type": "Feature",
  "properties": {
    "gn:admin1_code":"3.0",
    "gn:asciiname":"Cholp'a-gol",
    "gn:country_code":"KP",
    "gn:dem":696,
    "gn:feature_class":"P",
    "gn:feature_code":"PPL",
    "gn:name":"Ch\u014flp\u2019a-gol",
    "gn:population":0,
    "gn:timezone":"Asia/Pyongyang",
    "iso:country":"KP",
    "name:und_x_variant":[
        "\uc808\ud30c\uace8",
        "Ch\u014flp\u2019a-gol"
    ],
    "wof:name":"Cholp'a-gol",
    "wof:placetype":"locality"
},
  "geometry": {"coordinates":[128.66083,40.56972],"type":"Point"}
}