{
  "type": "Feature",
  "properties": {
    "gn:admin1_code":"3.0",
    "gn:asciiname":"Tongho-ri",
    "gn:country_code":"KP",
    "gn:dem":6,
    "gn:feature_class":"P",
    "gn:feature_code":"PPL",
    "gn:name":"Tongho-ri",
    "gn:population":0,
    "gn:timezone":"Asia/Pyongyang",
    "iso:country":"KP",
    "name:und_x_variant":[
        "\ub3d9\ud638\ub9ac",
        "Tongho-ri"
    ],
    "wof:name":"Tongho-ri",
    "wof:placetype":"locality"
},
  "geometry": {"coordinates":[128.08500000000001,40.04611],"type":"Point"}
}