{
  "type": "Feature",
  "properties": {
    "gn:admin1_code":"9.0",
    "gn:asciiname":"Wau-ri",
    "gn:cc2":"KP",
    "gn:country_code":"KP",
    "gn:dem":13,
    "gn:feature_class":"P",
    "gn:feature_code":"PPL",
    "gn:name":"Wau-ri",
    "gn:population":0,
    "gn:timezone":"Asia/Pyongyang",
    "iso:country":"KP",
    "name:und_x_variant":[
        "Wau-dong",
        "Wau-ri",
        "\uc640\uc6b0\ub3d9"
    ],
    "wof:name":"Wau-ri",
    "wof:placetype":"locality"
},
  "geometry": {"coordinates":[127.41194,39.15722],"type":"Point"}
}