{
  "type": "Feature",
  "properties": {
    "gn:admin1_code":"6.0",
    "gn:asciiname":"Yusul-li",
    "gn:country_code":"KP",
    "gn:dem":15,
    "gn:feature_class":"P",
    "gn:feature_code":"PPL",
    "gn:name":"Yusul-li",
    "gn:population":0,
    "gn:timezone":"Asia/Pyongyang",
    "iso:country":"KP",
    "wof:name":"Yusul-li",
    "wof:placetype":"locality"
},
  "geometry": {"coordinates":[125.49472,38.46722000000001],"type":"Point"}
}