{
  "type": "Feature",
  "properties": {
    "gn:admin1_code":"11.0",
    "gn:asciiname":"Munp'o-dong",
    "gn:country_code":"KP",
    "gn:dem":260,
    "gn:feature_class":"P",
    "gn:feature_code":"PPL",
    "gn:name":"Munp\u2019o-dong",
    "gn:population":0,
    "gn:timezone":"Asia/Pyongyang",
    "iso:country":"KP",
    "name:und_x_variant":[
        "\ubb38\ud3ec\ub3d9",
        "Munp\u2019o-dong"
    ],
    "wof:name":"Munp'o-dong",
    "wof:placetype":"locality"
},
  "geometry": {"coordinates":[125.89028,40.15861],"type":"Point"}
}