{
  "type": "Feature",
  "properties": {
    "gn:admin1_code":"9.0",
    "gn:asciiname":"Changyol-li",
    "gn:country_code":"KP",
    "gn:dem":661,
    "gn:feature_class":"P",
    "gn:feature_code":"PPL",
    "gn:name":"Changy\u014fl-li",
    "gn:population":0,
    "gn:timezone":"Asia/Pyongyang",
    "iso:country":"KP",
    "name:und_x_variant":[
        "Changy\u014fnni-Nambohy\u014fn",
        "Changy\u014fn-ni",
        "\uc7a5\uc5f0\ub9ac",
        "Changy\u014fl-li"
    ],
    "wof:name":"Changyol-li",
    "wof:placetype":"locality"
},
  "geometry": {"coordinates":[128.05417,38.61694],"type":"Point"}
}