{
  "type": "Feature",
  "properties": {
    "gn:admin1_code":"6.0",
    "gn:asciiname":"Paenung-gol",
    "gn:country_code":"KP",
    "gn:dem":223,
    "gn:feature_class":"P",
    "gn:feature_code":"PPL",
    "gn:name":"Paen\u016dng-gol",
    "gn:population":0,
    "gn:timezone":"Asia/Pyongyang",
    "iso:country":"KP",
    "name:und_x_variant":[
        "Paen\u016dng-kol",
        "Paen\u016dng-gol"
    ],
    "wof:name":"Paenung-gol",
    "wof:placetype":"locality"
},
  "geometry": {"coordinates":[126.60028,38.12111],"type":"Point"}
}