{
  "type": "Feature",
  "properties": {
    "gn:admin1_code":"6.0",
    "gn:admin2_code":"Kaep'ung-gun",
    "gn:asciiname":"Chol-gol",
    "gn:country_code":"KP",
    "gn:dem":21,
    "gn:feature_class":"P",
    "gn:feature_code":"PPL",
    "gn:name":"Ch\u014fl-gol",
    "gn:population":0,
    "gn:timezone":"Asia/Pyongyang",
    "iso:country":"KP",
    "name:und_x_variant":[
        "Sa-dong",
        "Ch\u014fl-kol",
        "Ch\u014fl-gol"
    ],
    "wof:name":"Chol-gol",
    "wof:placetype":"locality"
},
  "geometry": {"coordinates":[126.50806,37.82167000000001],"type":"Point"}
}