{
  "type": "Feature",
  "properties": {
    "gn:admin1_code":"17.0",
    "gn:asciiname":"Sin'gol-li",
    "gn:country_code":"KP",
    "gn:dem":33,
    "gn:feature_class":"P",
    "gn:feature_code":"PPL",
    "gn:name":"Sin\u2019g\u014fl-li",
    "gn:population":0,
    "gn:timezone":"Asia/Pyongyang",
    "iso:country":"KP",
    "name:und_x_variant":[
        "Sin\u2019g\u014fn-dong",
        "Sin\u2019gan-dong",
        "Sin\u2019g\u014fn-ni",
        "\uc2e0\uac74\ub9ac",
        "Sin\u2019g\u014fl-li"
    ],
    "wof:name":"Sin'gol-li",
    "wof:placetype":"locality"
},
  "geometry": {"coordinates":[130.29166999999998,42.67611],"type":"Point"}
}