{
  "type": "Feature",
  "properties": {
    "gn:admin1_code":"6.0",
    "gn:asciiname":"Chogaedemi",
    "gn:country_code":"KP",
    "gn:dem":31,
    "gn:feature_class":"P",
    "gn:feature_code":"PPL",
    "gn:name":"Chogaedemi",
    "gn:population":0,
    "gn:timezone":"Asia/Pyongyang",
    "iso:country":"KP",
    "name:und_x_variant":[
        "Chogaed\u014fmi",
        "\uc870\uac1c\ub380\uc774",
        "Chogaed\u014fmi-gol"
    ],
    "wof:name":"Chogaedemi",
    "wof:placetype":"locality"
},
  "geometry": {"coordinates":[125.18333,38.11583],"type":"Point"}
}