{
  "type": "Feature",
  "properties": {
    "gn:admin1_code":"7.0",
    "gn:asciiname":"Sohak-tong",
    "gn:country_code":"KP",
    "gn:dem":74,
    "gn:feature_class":"P",
    "gn:feature_code":"PPL",
    "gn:name":"Sohak-tong",
    "gn:population":0,
    "gn:timezone":"Asia/Pyongyang",
    "iso:country":"KP",
    "name:und_x_variant":[
        "\uc18c\ud559\ub3d9",
        "Sohak-tong"
    ],
    "wof:name":"Sohak-tong",
    "wof:placetype":"locality"
},
  "geometry": {"coordinates":[126.51278000000001,38.20139],"type":"Point"}
}