{
  "type": "Feature",
  "properties": {
    "gn:admin1_code":"7.0",
    "gn:asciiname":"Oejong-ni",
    "gn:country_code":"KP",
    "gn:dem":19,
    "gn:feature_class":"P",
    "gn:feature_code":"PPL",
    "gn:name":"Oejong-ni",
    "gn:population":0,
    "gn:timezone":"Asia/Pyongyang",
    "iso:country":"KP",
    "name:eng_x_preferred":[
        "Oejong"
    ],
    "name:eng_x_variant":[
        "Oejong-ni"
    ],
    "name:kor_x_preferred":[
        "\uc678\uc885\ub9ac"
    ],
    "wof:name":"Oejong",
    "wof:placetype":"locality"
},
  "geometry": {"coordinates":[125.64167,38.68139],"type":"Point"}
}