{
  "type": "Feature",
  "properties": {
    "gn:admin1_code":"6.0",
    "gn:admin2_code":"Paech'\u014fn-gun",
    "gn:asciiname":"Ch'ujong-ni",
    "gn:country_code":"KP",
    "gn:dem":15,
    "gn:feature_class":"P",
    "gn:feature_code":"PPL",
    "gn:name":"Ch\u2019uj\u014fng-ni",
    "gn:population":0,
    "gn:timezone":"Asia/Pyongyang",
    "iso:country":"KP",
    "name:eng_x_preferred":[
        "Ch'ujong"
    ],
    "name:eng_x_variant":[
        "Ch'ujong-ni"
    ],
    "name:kor_x_preferred":[
        "\ucd94\uc815\ub9ac"
    ],
    "name:und_x_variant":[
        "Ch\u2019uj\u014fng-ni"
    ],
    "wof:name":"Ch'ujong",
    "wof:placetype":"locality"
},
  "geometry": {"coordinates":[126.23,37.885],"type":"Point"}
}