{
  "type": "Feature",
  "properties": {
    "gn:admin1_code":"7.0",
    "gn:asciiname":"Saenmal",
    "gn:country_code":"KP",
    "gn:dem":104,
    "gn:feature_class":"P",
    "gn:feature_code":"PPL",
    "gn:name":"Saenmal",
    "gn:population":0,
    "gn:timezone":"Asia/Pyongyang",
    "iso:country":"KP",
    "wof:name":"Saenmal",
    "wof:placetype":"locality"
},
  "geometry": {"coordinates":[126.01000000000001,38.27167],"type":"Point"}
}