{
  "type": "Feature",
  "properties": {
    "gn:admin1_code":"11.0",
    "gn:asciiname":"Sindukch'am",
    "gn:country_code":"KP",
    "gn:dem":123,
    "gn:feature_class":"P",
    "gn:feature_code":"PPL",
    "gn:name":"Sind\u016dkch\u2019am",
    "gn:population":0,
    "gn:timezone":"Asia/Pyongyang",
    "iso:country":"KP",
    "name:und_x_variant":[
        "\uc2e0\ub4dd\ucc38",
        "Sind\u016dkch\u2019am"
    ],
    "wof:name":"Sindukch'am",
    "wof:placetype":"locality"
},
  "geometry": {"coordinates":[125.50917,40.08028],"type":"Point"}
}