{
  "type": "Feature",
  "properties": {
    "gn:admin1_code":"15.0",
    "gn:asciiname":"Nalgun-dong",
    "gn:country_code":"KP",
    "gn:dem":225,
    "gn:feature_class":"P",
    "gn:feature_code":"PPL",
    "gn:name":"Nalg\u016dn-dong",
    "gn:population":0,
    "gn:timezone":"Asia/Pyongyang",
    "iso:country":"KP",
    "name:kor_x_preferred":[
        "\ub0a1\uc740\ub3d9"
    ],
    "name:kor_x_variant":[
        "Nalg\u016dn-dong"
    ],
    "wof:name":"Nalgun-dong",
    "wof:placetype":"locality"
},
  "geometry": {"coordinates":[126.44777999999999,39.08556],"type":"Point"}
}