{
  "type": "Feature",
  "properties": {
    "gn:admin1_code":"6.0",
    "gn:asciiname":"Araesonggol",
    "gn:country_code":"KP",
    "gn:dem":19,
    "gn:feature_class":"P",
    "gn:feature_code":"PPL",
    "gn:name":"Araes\u014fnggol",
    "gn:population":0,
    "gn:timezone":"Asia/Pyongyang",
    "iso:country":"KP",
    "name:kor_x_preferred":[
        "\uc544\ub798\uc131\uace8"
    ],
    "name:und_x_variant":[
        "Hasong-dong",
        "Araes\u014fnggol"
    ],
    "wof:name":"Araesonggol",
    "wof:placetype":"locality"
},
  "geometry": {"coordinates":[125.88361,37.95583],"type":"Point"}
}