{
  "type": "Feature",
  "properties": {
    "gn:admin1_code":"15.0",
    "gn:asciiname":"Oryu-dong",
    "gn:country_code":"KP",
    "gn:dem":34,
    "gn:feature_class":"P",
    "gn:feature_code":"PPL",
    "gn:name":"Oryu-dong",
    "gn:population":0,
    "gn:timezone":"Asia/Pyongyang",
    "iso:country":"KP",
    "name:kor_x_preferred":[
        "\uc624\ub958\ub3d9"
    ],
    "name:und_x_variant":[
        "Oryu-ri",
        "Oryu-dong",
        "Oryudong"
    ],
    "wof:name":"Oryu-dong",
    "wof:placetype":"locality"
},
  "geometry": {"coordinates":[125.64187,39.02237],"type":"Point"}
}