{
  "type": "Feature",
  "properties": {
    "gn:admin1_code":"12.0",
    "gn:asciiname":"Ogya-dong",
    "gn:country_code":"KP",
    "gn:dem":39,
    "gn:feature_class":"P",
    "gn:feature_code":"PPL",
    "gn:name":"Ogya-dong",
    "gn:population":0,
    "gn:timezone":"Asia/Pyongyang",
    "iso:country":"KP",
    "name:und_x_variant":[
        "\uc625\uc57c\ub3d9",
        "Ogya-dong"
    ],
    "wof:name":"Ogya-dong",
    "wof:placetype":"locality"
},
  "geometry": {"coordinates":[125.82861,38.86889],"type":"Point"}
}