{
  "type": "Feature",
  "properties": {
    "gn:admin1_code":"0.0",
    "gn:asciiname":"P'ooejin-ni",
    "gn:country_code":"KP",
    "gn:dem":-9999,
    "gn:feature_class":"P",
    "gn:feature_code":"PPL",
    "gn:name":"P\u2019ooejin-ni",
    "gn:population":0,
    "gn:timezone":"Asia/Pyongyang",
    "iso:country":"KP",
    "name:eng_x_preferred":[
        "P'ooejin"
    ],
    "name:eng_x_variant":[
        "P'ooejin-ni"
    ],
    "name:und_x_variant":[
        "Hogaishin-ri",
        "P\u2019ooejin-ni"
    ],
    "wof:name":"P'ooejin",
    "wof:placetype":"locality"
},
  "geometry": {"coordinates":[128.36667,38.61667],"type":"Point"}
}