{
  "type": "Feature",
  "properties": {
    "gn:admin1_code":"1.0",
    "gn:asciiname":"Sonam-ni",
    "gn:country_code":"KP",
    "gn:dem":461,
    "gn:feature_class":"P",
    "gn:feature_code":"PPL",
    "gn:name":"Sonam-ni",
    "gn:population":0,
    "gn:timezone":"Asia/Pyongyang",
    "iso:country":"KP",
    "name:und_x_variant":[
        "\uc18c\ub0a8\ub9ac",
        "Sonam-ni"
    ],
    "wof:name":"Sonam-ni",
    "wof:placetype":"locality"
},
  "geometry": {"coordinates":[126.8075,41.47361],"type":"Point"}
}