{
  "type": "Feature",
  "properties": {
    "gn:admin1_code":"15.0",
    "gn:asciiname":"Unbong-ni",
    "gn:country_code":"KP",
    "gn:dem":366,
    "gn:feature_class":"P",
    "gn:feature_code":"PPL",
    "gn:name":"Unbong-ni",
    "gn:population":0,
    "gn:timezone":"Asia/Pyongyang",
    "iso:country":"KP",
    "name:und_x_variant":[
        "\uc6b4\ubd09\ub9ac",
        "Unbong-ni"
    ],
    "wof:name":"Unbong-ni",
    "wof:placetype":"locality"
},
  "geometry": {"coordinates":[126.66,39.44861],"type":"Point"}
}