{
  "type": "Feature",
  "properties": {
    "gn:admin1_code":"3.0",
    "gn:admin2_code":"K\u016dmya-gun",
    "gn:asciiname":"Yangsang-ni",
    "gn:country_code":"KP",
    "gn:dem":2,
    "gn:feature_class":"P",
    "gn:feature_code":"PPL",
    "gn:name":"Yangsang-ni",
    "gn:population":0,
    "gn:timezone":"Asia/Pyongyang",
    "iso:country":"KP",
    "name:eng_x_preferred":[
        "Yangsang"
    ],
    "name:eng_x_variant":[
        "Yangsang-ni"
    ],
    "wof:name":"Yangsang",
    "wof:placetype":"locality"
},
  "geometry": {"coordinates":[127.3425,39.45111],"type":"Point"}
}