{
  "type": "Feature",
  "properties": {
    "gn:admin1_code":"12.0",
    "gn:asciiname":"Sungni",
    "gn:country_code":"KP",
    "gn:dem":24,
    "gn:feature_class":"P",
    "gn:feature_code":"PPL",
    "gn:name":"S\u016dngni",
    "gn:population":0,
    "gn:timezone":"Asia/Pyongyang",
    "iso:country":"KP",
    "name:und_x_variant":[
        "\uc2b9\ub9ac",
        "S\u016dngni",
        "Seungni"
    ],
    "wof:name":"Sungni",
    "wof:placetype":"locality"
},
  "geometry": {"coordinates":[125.70611,38.96556],"type":"Point"}
}