{
  "type": "Feature",
  "properties": {
    "gn:admin1_code":"11.0",
    "gn:asciiname":"Nae-gol",
    "gn:country_code":"KP",
    "gn:dem":29,
    "gn:feature_class":"P",
    "gn:feature_code":"PPL",
    "gn:name":"Nae-gol",
    "gn:population":0,
    "gn:timezone":"Asia/Pyongyang",
    "iso:country":"KP",
    "name:und_x_variant":[
        "Nae-kol",
        "\ub0b4\uace8",
        "Nae-gol"
    ],
    "wof:name":"Nae-gol",
    "wof:placetype":"locality"
},
  "geometry": {"coordinates":[124.68333,40.29778],"type":"Point"}
}