{
  "type": "Feature",
  "properties": {
    "gn:admin1_code":"15.0",
    "gn:asciiname":"Yongho-ri",
    "gn:country_code":"KP",
    "gn:dem":51,
    "gn:feature_class":"P",
    "gn:feature_code":"PPL",
    "gn:name":"Yongho-ri",
    "gn:population":0,
    "gn:timezone":"Asia/Pyongyang",
    "iso:country":"KP",
    "name:kor_x_preferred":[
        "\uc6a9\ud638\ub9ac"
    ],
    "wof:name":"Yongho-ri",
    "wof:placetype":"locality"
},
  "geometry": {"coordinates":[125.65306,39.55361],"type":"Point"}
}