{
  "type": "Feature",
  "properties": {
    "gn:admin1_code":"11.0",
    "gn:asciiname":"Kaemijungji",
    "gn:country_code":"KP",
    "gn:dem":130,
    "gn:feature_class":"P",
    "gn:feature_code":"PPL",
    "gn:name":"Kaemijungji",
    "gn:population":0,
    "gn:timezone":"Asia/Pyongyang",
    "iso:country":"KP",
    "name:und_x_variant":[
        "Chinjungji",
        "Kaemijungji"
    ],
    "wof:name":"Kaemijungji",
    "wof:placetype":"locality"
},
  "geometry": {"coordinates":[124.90000000000001,39.58333],"type":"Point"}
}