{
  "type": "Feature",
  "properties": {
    "gn:admin1_code":"1.0",
    "gn:asciiname":"Yoch'am",
    "gn:country_code":"KP",
    "gn:dem":357,
    "gn:feature_class":"P",
    "gn:feature_code":"PPL",
    "gn:name":"Yoch\u2019am",
    "gn:population":0,
    "gn:timezone":"Asia/Pyongyang",
    "iso:country":"KP",
    "name:und_x_variant":[
        "\uc694\ucc38",
        "Yoch\u2019am"
    ],
    "wof:name":"Yoch'am",
    "wof:placetype":"locality"
},
  "geometry": {"coordinates":[126.27306000000002,40.33417],"type":"Point"}
}