{
  "type": "Feature",
  "properties": {
    "gn:admin1_code":"11.0",
    "gn:asciiname":"Inp'ung-ni",
    "gn:country_code":"KP",
    "gn:dem":77,
    "gn:feature_class":"P",
    "gn:feature_code":"PPL",
    "gn:name":"Inp\u2019ung-ni",
    "gn:population":0,
    "gn:timezone":"Asia/Pyongyang",
    "iso:country":"KP",
    "name:kor_x_preferred":[
        "Inp\u2019ung-ni"
    ],
    "name:kor_x_variant":[
        "\uc778\ud48d\ub9ac"
    ],
    "wof:name":"Inp'ung-ni",
    "wof:placetype":"locality"
},
  "geometry": {"coordinates":[124.84,39.92694],"type":"Point"}
}