{
  "type": "Feature",
  "properties": {
    "gn:admin1_code":"6.0",
    "gn:asciiname":"Haejang",
    "gn:country_code":"KP",
    "gn:dem":19,
    "gn:feature_class":"P",
    "gn:feature_code":"PPL",
    "gn:name":"Haejang",
    "gn:population":0,
    "gn:timezone":"Asia/Pyongyang",
    "iso:country":"KP",
    "name:und_x_variant":[
        "\ud574\uc7a5",
        "Haejang"
    ],
    "wof:name":"Haejang",
    "wof:placetype":"locality"
},
  "geometry": {"coordinates":[125.29277999999999,37.74556],"type":"Point"}
}