{
  "type": "Feature",
  "properties": {
    "gn:admin1_code":"1.0",
    "gn:asciiname":"Masang-dong",
    "gn:country_code":"KP",
    "gn:dem":404,
    "gn:feature_class":"P",
    "gn:feature_code":"PPL",
    "gn:name":"Masang-dong",
    "gn:population":0,
    "gn:timezone":"Asia/Pyongyang",
    "iso:country":"KP",
    "name:und_x_variant":[
        "\ub9c8\uc0c1\ub3d9",
        "Masang-dong"
    ],
    "wof:name":"Masang-dong",
    "wof:placetype":"locality"
},
  "geometry": {"coordinates":[126.45083,40.96111],"type":"Point"}
}