{
  "type": "Feature",
  "properties": {
    "gn:admin1_code":"9.0",
    "gn:asciiname":"Sadong-ni",
    "gn:country_code":"KP",
    "gn:dem":284,
    "gn:feature_class":"P",
    "gn:feature_code":"PPL",
    "gn:name":"Sadong-ni",
    "gn:population":0,
    "gn:timezone":"Asia/Pyongyang",
    "iso:country":"KP",
    "wof:name":"Sadong-ni",
    "wof:placetype":"locality"
},
  "geometry": {"coordinates":[127.0575,38.72611],"type":"Point"}
}