{
  "type": "Feature",
  "properties": {
    "gn:admin1_code":"11.0",
    "gn:asciiname":"Sangdan",
    "gn:country_code":"KP",
    "gn:dem":264,
    "gn:feature_class":"P",
    "gn:feature_code":"PPL",
    "gn:name":"Sangdan",
    "gn:population":0,
    "gn:timezone":"Asia/Pyongyang",
    "iso:country":"KP",
    "name:kor_x_preferred":[
        "\uc0c1\ub2e8"
    ],
    "wof:name":"Sangdan",
    "wof:placetype":"locality"
},
  "geometry": {"coordinates":[125.32861,39.81361],"type":"Point"}
}