{
  "type": "Feature",
  "properties": {
    "gn:admin1_code":"7.0",
    "gn:asciiname":"P'anch'il-li",
    "gn:country_code":"KP",
    "gn:dem":32,
    "gn:feature_class":"P",
    "gn:feature_code":"PPL",
    "gn:name":"P\u2019anch\u2019il-li",
    "gn:population":0,
    "gn:timezone":"Asia/Pyongyang",
    "iso:country":"KP",
    "name:kor_x_preferred":[
        "\ud310\uce60\ub9ac"
    ],
    "name:kor_x_variant":[
        "P\u2019anch\u2019il-li"
    ],
    "wof:name":"P'anch'il-li",
    "wof:placetype":"locality"
},
  "geometry": {"coordinates":[125.50444,38.51528],"type":"Point"}
}