{
  "type": "Feature",
  "properties": {
    "gn:admin1_code":"13.0",
    "gn:asciiname":"Sinch'ang-ni",
    "gn:country_code":"KP",
    "gn:dem":998,
    "gn:feature_class":"P",
    "gn:feature_code":"PPL",
    "gn:name":"Sinch\u2019ang-ni",
    "gn:population":0,
    "gn:timezone":"Asia/Pyongyang",
    "iso:country":"KP",
    "name:und_x_variant":[
        "\uc2e0\ucc3d\ub9ac",
        "Sinch\u2019ang-ni"
    ],
    "wof:name":"Sinch'ang-ni",
    "wof:placetype":"locality"
},
  "geometry": {"coordinates":[128.34999999999999,40.88611],"type":"Point"}
}