{
  "type": "Feature",
  "properties": {
    "gn:admin1_code":"6.0",
    "gn:admin2_code":"P\u2019anmun-gun",
    "gn:asciiname":"Yongdum-dong",
    "gn:country_code":"KP",
    "gn:dem":37,
    "gn:feature_class":"P",
    "gn:feature_code":"PPL",
    "gn:name":"Yongdum-dong",
    "gn:population":0,
    "gn:timezone":"Asia/Pyongyang",
    "iso:country":"KP",
    "name:und_x_variant":[
        "Yongdun-dong",
        "Yongdum-dong"
    ],
    "wof:name":"Yongdum-dong",
    "wof:placetype":"locality"
},
  "geometry": {"coordinates":[126.61833,37.98611],"type":"Point"}
}