{
  "type": "Feature",
  "properties": {
    "gn:admin1_code":"11.0",
    "gn:asciiname":"Ryongch'u-dong-saman",
    "gn:country_code":"KP",
    "gn:dem":62,
    "gn:feature_class":"P",
    "gn:feature_code":"PPL",
    "gn:name":"Ryongch\u2019u-dong-saman",
    "gn:population":0,
    "gn:timezone":"Asia/Pyongyang",
    "iso:country":"KP",
    "name:kor_x_preferred":[
        "\ub8e1\ucd94\ub3d9\uc0ac\ub9cc"
    ],
    "name:und_x_variant":[
        "Ryongch\u2019u-dong-saman",
        "Yongch\u2019udong-Saman"
    ],
    "wof:name":"Ryongch'u-dong-saman",
    "wof:placetype":"locality"
},
  "geometry": {"coordinates":[125.66028,39.78917],"type":"Point"}
}