{
  "type": "Feature",
  "properties": {
    "gn:admin1_code":"3.0",
    "gn:asciiname":"Maehang-dong",
    "gn:country_code":"KP",
    "gn:dem":247,
    "gn:feature_class":"P",
    "gn:feature_code":"PPL",
    "gn:name":"Maehang-dong",
    "gn:population":0,
    "gn:timezone":"Asia/Pyongyang",
    "iso:country":"KP",
    "name:und_x_variant":[
        "\ub9e4\ud56d\ub3d9",
        "Maehang-dong"
    ],
    "wof:name":"Maehang-dong",
    "wof:placetype":"locality"
},
  "geometry": {"coordinates":[126.8425,39.68972],"type":"Point"}
}