{
  "type": "Feature",
  "properties": {
    "gn:admin1_code":"6.0",
    "gn:asciiname":"Malchon",
    "gn:country_code":"KP",
    "gn:dem":38,
    "gn:feature_class":"P",
    "gn:feature_code":"PPL",
    "gn:name":"Malch\u014fn",
    "gn:population":0,
    "gn:timezone":"Asia/Pyongyang",
    "iso:country":"KP",
    "name:und_x_variant":[
        "\ub9d0\uc804",
        "Malch\u014fn"
    ],
    "wof:name":"Malchon",
    "wof:placetype":"locality"
},
  "geometry": {"coordinates":[125.18083,38.66278],"type":"Point"}
}