{
  "type": "Feature",
  "properties": {
    "gn:admin1_code":"6.0",
    "gn:asciiname":"Chin-dong",
    "gn:country_code":"KP",
    "gn:dem":20,
    "gn:feature_class":"P",
    "gn:feature_code":"PPL",
    "gn:name":"Chin-dong",
    "gn:population":0,
    "gn:timezone":"Asia/Pyongyang",
    "iso:country":"KP",
    "name:kor_x_preferred":[
        "\uc9c4\ub3d9"
    ],
    "wof:name":"Chin-dong",
    "wof:placetype":"locality"
},
  "geometry": {"coordinates":[125.91306000000002,37.77917],"type":"Point"}
}