{
  "type": "Feature",
  "properties": {
    "gn:admin1_code":"15.0",
    "gn:asciiname":"Kugo-dong",
    "gn:country_code":"KP",
    "gn:dem":41,
    "gn:feature_class":"P",
    "gn:feature_code":"PPL",
    "gn:name":"Kugo-dong",
    "gn:population":0,
    "gn:timezone":"Asia/Pyongyang",
    "iso:country":"KP",
    "wof:name":"Kugo-dong",
    "wof:placetype":"locality"
},
  "geometry": {"coordinates":[125.99694,39.24556],"type":"Point"}
}