{
  "type": "Feature",
  "properties": {
    "gn:admin1_code":"17.0",
    "gn:asciiname":"T'o-gol",
    "gn:country_code":"KP",
    "gn:dem":226,
    "gn:feature_class":"P",
    "gn:feature_code":"PPL",
    "gn:name":"T\u2019\u014f-gol",
    "gn:population":0,
    "gn:timezone":"Asia/Pyongyang",
    "iso:country":"KP",
    "name:und_x_variant":[
        "T\u2019o-kol",
        "\ud130\uace8",
        "T\u2019\u014f-gol"
    ],
    "wof:name":"T'o-gol",
    "wof:placetype":"locality"
},
  "geometry": {"coordinates":[129.42861000000002,41.04917],"type":"Point"}
}