{
  "type": "Feature",
  "properties": {
    "gn:admin1_code":"7.0",
    "gn:asciiname":"Koryong-dong",
    "gn:country_code":"KP",
    "gn:dem":367,
    "gn:feature_class":"P",
    "gn:feature_code":"PPL",
    "gn:name":"Kory\u014fng-dong",
    "gn:population":0,
    "gn:timezone":"Asia/Pyongyang",
    "iso:country":"KP",
    "name:kor_x_preferred":[
        "\uace0\ub839\ub3d9"
    ],
    "name:kor_x_variant":[
        "Kory\u014fng-dong"
    ],
    "wof:name":"Koryong-dong",
    "wof:placetype":"locality"
},
  "geometry": {"coordinates":[126.93111,39.02972000000001],"type":"Point"}
}