{
  "type": "Feature",
  "properties": {
    "gn:admin1_code":"6.0",
    "gn:asciiname":"Pakchi",
    "gn:country_code":"KP",
    "gn:dem":3,
    "gn:feature_class":"P",
    "gn:feature_code":"PPL",
    "gn:name":"Pakchi",
    "gn:population":0,
    "gn:timezone":"Asia/Pyongyang",
    "iso:country":"KP",
    "wof:name":"Pakchi",
    "wof:placetype":"locality"
},
  "geometry": {"coordinates":[125.66472,38.48528],"type":"Point"}
}