{
  "type": "Feature",
  "properties": {
    "gn:admin1_code":"7.0",
    "gn:asciiname":"Kich'ang-dong",
    "gn:country_code":"KP",
    "gn:dem":51,
    "gn:feature_class":"P",
    "gn:feature_code":"PPL",
    "gn:name":"Kich\u2019ang-dong",
    "gn:population":0,
    "gn:timezone":"Asia/Pyongyang",
    "iso:country":"KP",
    "name:und_x_variant":[
        "\uae30\ucc3d\ub3d9",
        "Kich\u2019ang-dong"
    ],
    "wof:name":"Kich'ang-dong",
    "wof:placetype":"locality"
},
  "geometry": {"coordinates":[126.53082999999999,38.2325],"type":"Point"}
}