{
  "type": "Feature",
  "properties": {
    "gn:admin1_code":"7.0",
    "gn:asciiname":"Kodae-dong",
    "gn:country_code":"KP",
    "gn:dem":168,
    "gn:feature_class":"P",
    "gn:feature_code":"PPL",
    "gn:name":"Kodae-dong",
    "gn:population":0,
    "gn:timezone":"Asia/Pyongyang",
    "iso:country":"KP",
    "name:kor_x_preferred":[
        "\uace0\ub300\ub3d9"
    ],
    "wof:name":"Kodae-dong",
    "wof:placetype":"locality"
},
  "geometry": {"coordinates":[126.47638999999999,38.74056],"type":"Point"}
}