{
  "type": "Feature",
  "properties": {
    "gn:admin1_code":"11.0",
    "gn:asciiname":"Kuam-dong",
    "gn:country_code":"KP",
    "gn:dem":9,
    "gn:feature_class":"P",
    "gn:feature_code":"PPL",
    "gn:name":"Kuam-dong",
    "gn:population":0,
    "gn:timezone":"Asia/Pyongyang",
    "iso:country":"KP",
    "name:kor_x_preferred":[
        "\uad6c\uc554\ub3d9"
    ],
    "wof:name":"Kuam-dong",
    "wof:placetype":"locality"
},
  "geometry": {"coordinates":[125.28888999999999,39.535],"type":"Point"}
}