{
  "type": "Feature",
  "properties": {
    "gn:admin1_code":"3.0",
    "gn:asciiname":"Hanong-ni",
    "gn:country_code":"KP",
    "gn:dem":151,
    "gn:feature_class":"P",
    "gn:feature_code":"PPL",
    "gn:name":"Hanong-ni",
    "gn:population":0,
    "gn:timezone":"Asia/Pyongyang",
    "iso:country":"KP",
    "name:und_x_variant":[
        "\ud558\ub18d\ub9ac"
    ],
    "wof:name":"Hanong-ni",
    "wof:placetype":"locality"
},
  "geometry": {"coordinates":[128.78083000000001,40.60222],"type":"Point"}
}