{
  "type": "Feature",
  "properties": {
    "gn:admin1_code":"11.0",
    "gn:asciiname":"To-dong",
    "gn:country_code":"KP",
    "gn:dem":138,
    "gn:feature_class":"P",
    "gn:feature_code":"PPL",
    "gn:name":"To-dong",
    "gn:population":0,
    "gn:timezone":"Asia/Pyongyang",
    "iso:country":"KP",
    "name:und_x_variant":[
        "\ub3c4\ub3d9",
        "To-dong"
    ],
    "wof:name":"To-dong",
    "wof:placetype":"locality"
},
  "geometry": {"coordinates":[125.85972,40.11972],"type":"Point"}
}