{
  "type": "Feature",
  "properties": {
    "gn:admin1_code":"18.0",
    "gn:admin2_code":"Najins\u014fnbong-si",
    "gn:asciiname":"Yongsu-ri",
    "gn:country_code":"KP",
    "gn:dem":4,
    "gn:feature_class":"P",
    "gn:feature_code":"PPL",
    "gn:name":"Yongsu-ri",
    "gn:population":0,
    "gn:timezone":"Asia/Pyongyang",
    "iso:country":"KP",
    "name:und_x_variant":[
        "Yongsu-dong",
        "\uc6a9\uc218\ub9ac",
        "Yongsu-ri",
        "Yongsuri"
    ],
    "wof:name":"Yongsu-ri",
    "wof:placetype":"locality"
},
  "geometry": {"coordinates":[130.35611,42.32722],"type":"Point"}
}