{
  "type": "Feature",
  "properties": {
    "gn:admin1_code":"11.0",
    "gn:asciiname":"Yangmul-gol",
    "gn:country_code":"KP",
    "gn:dem":129,
    "gn:feature_class":"P",
    "gn:feature_code":"PPL",
    "gn:name":"Yangmul-gol",
    "gn:population":0,
    "gn:timezone":"Asia/Pyongyang",
    "iso:country":"KP",
    "wof:name":"Yangmul-gol",
    "wof:placetype":"locality"
},
  "geometry": {"coordinates":[126.10361,39.93167],"type":"Point"}
}