{
  "type": "Feature",
  "properties": {
    "gn:admin1_code":"6.0",
    "gn:asciiname":"Sinp'ung-dong",
    "gn:country_code":"KP",
    "gn:dem":15,
    "gn:feature_class":"P",
    "gn:feature_code":"PPL",
    "gn:name":"Sinp\u2019ung-dong",
    "gn:population":0,
    "gn:timezone":"Asia/Pyongyang",
    "iso:country":"KP",
    "name:und_x_variant":[
        "\uc2e0\ud48d\ub3d9",
        "Sinp\u2019ung-dong"
    ],
    "wof:name":"Sinp'ung-dong",
    "wof:placetype":"locality"
},
  "geometry": {"coordinates":[125.3275,38.66083],"type":"Point"}
}