{
  "type": "Feature",
  "properties": {
    "gn:admin1_code":"11.0",
    "gn:asciiname":"Ch'ongsal-li",
    "gn:country_code":"KP",
    "gn:dem":16,
    "gn:feature_class":"P",
    "gn:feature_code":"PPL",
    "gn:name":"Ch\u2019\u014fngsal-li",
    "gn:population":0,
    "gn:timezone":"Asia/Pyongyang",
    "iso:country":"KP",
    "name:kor_x_preferred":[
        "\uccad\uc0b0\ub9ac"
    ],
    "name:kor_x_variant":[
        "Ch\u2019\u014fngsal-li"
    ],
    "name:und_x_variant":[
        "Ch\u2019\u014fngsan-ni"
    ],
    "wof:name":"Ch'ongsal-li",
    "wof:placetype":"locality"
},
  "geometry": {"coordinates":[125.50333000000001,39.60167],"type":"Point"}
}