{
  "type": "Feature",
  "properties": {
    "gn:admin1_code":"12.0",
    "gn:asciiname":"Tonggong-ni",
    "gn:country_code":"KP",
    "gn:dem":6,
    "gn:feature_class":"P",
    "gn:feature_code":"PPL",
    "gn:name":"Tonggong-ni",
    "gn:population":0,
    "gn:timezone":"Asia/Pyongyang",
    "iso:country":"KP",
    "name:eng_x_preferred":[
        "Tonggong"
    ],
    "name:eng_x_variant":[
        "Tonggong-ni"
    ],
    "name:kor_x_preferred":[
        "\ub3d9\uacf5\ub9ac"
    ],
    "name:und_x_variant":[
        "Donggongni"
    ],
    "wof:name":"Tonggong",
    "wof:placetype":"locality"
},
  "geometry": {"coordinates":[125.59389,38.87778],"type":"Point"}
}