{
  "type": "Feature",
  "properties": {
    "gn:admin1_code":"3.0",
    "gn:asciiname":"Chaktong-ni",
    "gn:country_code":"KP",
    "gn:dem":15,
    "gn:feature_class":"P",
    "gn:feature_code":"PPL",
    "gn:name":"Chaktong-ni",
    "gn:population":0,
    "gn:timezone":"Asia/Pyongyang",
    "iso:country":"KP",
    "name:und_x_variant":[
        "\uc791\ub3d9\ub9ac",
        "Chaktong-ni"
    ],
    "wof:name":"Chaktong-ni",
    "wof:placetype":"locality"
},
  "geometry": {"coordinates":[127.34305999999999,39.52778],"type":"Point"}
}