{
  "type": "Feature",
  "properties": {
    "gn:admin1_code":"1.0",
    "gn:asciiname":"Samhung-ni",
    "gn:country_code":"KP",
    "gn:dem":1117,
    "gn:feature_class":"P",
    "gn:feature_code":"PPL",
    "gn:name":"Samh\u016dng-ni",
    "gn:population":0,
    "gn:timezone":"Asia/Pyongyang",
    "iso:country":"KP",
    "name:kor_x_preferred":[
        "\uc0bc\ud765\ub9ac"
    ],
    "name:kor_x_variant":[
        "Samh\u016dng-ni"
    ],
    "wof:name":"Samhung-ni",
    "wof:placetype":"locality"
},
  "geometry": {"coordinates":[127.16722,40.66639],"type":"Point"}
}