{
  "type": "Feature",
  "properties": {
    "gn:admin1_code":"9.0",
    "gn:asciiname":"Samoktongni Chik-tong",
    "gn:country_code":"KP",
    "gn:dem":619,
    "gn:feature_class":"P",
    "gn:feature_code":"PPL",
    "gn:name":"Sam\u014fktongni Chik-tong",
    "gn:population":0,
    "gn:timezone":"Asia/Pyongyang",
    "iso:country":"KP",
    "name:und_x_variant":[
        "\uc0bc\uc5b5\ub3d9\ub9ac\uc9c1\ub3d9",
        "Sam\u014fktongni Chik-tong"
    ],
    "wof:name":"Samoktongni Chik-tong",
    "wof:placetype":"locality"
},
  "geometry": {"coordinates":[128.05250000000001,38.5675],"type":"Point"}
}