{
  "type": "Feature",
  "properties": {
    "gn:admin1_code":"6.0",
    "gn:admin2_code":"Changp\u2019ung-gun",
    "gn:asciiname":"Sin-ch'on",
    "gn:country_code":"KP",
    "gn:dem":104,
    "gn:feature_class":"P",
    "gn:feature_code":"PPL",
    "gn:name":"Sin-ch\u2019on",
    "gn:population":0,
    "gn:timezone":"Asia/Pyongyang",
    "iso:country":"KP",
    "wof:name":"Sin-ch'on",
    "wof:placetype":"locality"
},
  "geometry": {"coordinates":[126.71611,38.06583],"type":"Point"}
}