{
  "type": "Feature",
  "properties": {
    "gn:admin1_code":"15.0",
    "gn:asciiname":"Chikha",
    "gn:country_code":"KP",
    "gn:dem":318,
    "gn:feature_class":"P",
    "gn:feature_code":"PPL",
    "gn:name":"Chikha",
    "gn:population":0,
    "gn:timezone":"Asia/Pyongyang",
    "iso:country":"KP",
    "name:und_x_variant":[
        "\uc9c1\ud558",
        "Chikha"
    ],
    "wof:name":"Chikha",
    "wof:placetype":"locality"
},
  "geometry": {"coordinates":[126.63083,39.825],"type":"Point"}
}