{
  "type": "Feature",
  "properties": {
    "iso:country":"KP",
    "name:unk_x_variant":[
        "Kyungwan"
    ],
    "qs:gn_country":"KP",
    "qs:gn_fcode":"PPL",
    "qs:gn_pop":12650,
    "qs:name":"Kyongwon",
    "qs:name_adm0":"North Korea",
    "qs:name_adm1":"Hamgyong-bukto",
    "qs:photos":0,
    "qs:photos_1k":0,
    "qs:photos_9k":0,
    "qs:photos_9r":0,
    "qs:photos_all":0,
    "qs:photos_sr":0,
    "qs:placetype":"Town",
    "qs:pop_sr":"6",
    "qs:woe_adm0":23424865,
    "wd:wordcount":39,
    "wof:name":"Kyongwon",
    "wof:placetype":"locality",
    "wof:population":12650
},
  "geometry": {"coordinates":[130.15278000000001,42.81361],"type":"Point"}
}