{
  "type": "Feature",
  "properties": {
    "gn:admin1_code":"11.0",
    "gn:asciiname":"Oedo-ri",
    "gn:country_code":"KP",
    "gn:dem":13,
    "gn:feature_class":"P",
    "gn:feature_code":"PPL",
    "gn:name":"Oedo-ri",
    "gn:population":0,
    "gn:timezone":"Asia/Pyongyang",
    "iso:country":"KP",
    "name:kor_x_preferred":[
        "\uc678\ub450\ub9ac"
    ],
    "wof:name":"Oedo-ri",
    "wof:placetype":"locality"
},
  "geometry": {"coordinates":[125.21666999999999,39.64694],"type":"Point"}
}