{
  "type": "Feature",
  "properties": {
    "gn:admin1_code":"11.0",
    "gn:asciiname":"Tong-dong",
    "gn:country_code":"KP",
    "gn:dem":8,
    "gn:feature_class":"P",
    "gn:feature_code":"PPL",
    "gn:name":"Tong-dong",
    "gn:population":0,
    "gn:timezone":"Asia/Pyongyang",
    "iso:country":"KP",
    "name:kor_x_preferred":[
        "\ub2f9\uace8"
    ],
    "name:und_x_variant":[
        "\ub3d9\ub3d9",
        "Tong-dong",
        "Tanggol"
    ],
    "wof:name":"Tong-dong",
    "wof:placetype":"locality"
},
  "geometry": {"coordinates":[124.78982999999999,39.75198],"type":"Point"}
}