{
  "type": "Feature",
  "properties": {
    "gn:admin1_code":"1.0",
    "gn:asciiname":"T'osong-ni",
    "gn:country_code":"KP",
    "gn:dem":346,
    "gn:feature_class":"P",
    "gn:feature_code":"PPL",
    "gn:name":"T\u2019os\u014fng-ni",
    "gn:population":0,
    "gn:timezone":"Asia/Pyongyang",
    "iso:country":"KP",
    "name:und_x_variant":[
        "T\u2019os\u014fng-dong",
        "\ud1a0\uc131\ub9ac",
        "T\u2019os\u014fng-ni"
    ],
    "wof:name":"T'osong-ni",
    "wof:placetype":"locality"
},
  "geometry": {"coordinates":[126.70305999999999,41.68028],"type":"Point"}
}