{
  "type": "Feature",
  "properties": {
    "gn:admin1_code":"13.0",
    "gn:asciiname":"Amhung-ni",
    "gn:country_code":"KP",
    "gn:dem":882,
    "gn:feature_class":"P",
    "gn:feature_code":"PPL",
    "gn:name":"Amh\u016dng-ni",
    "gn:population":0,
    "gn:timezone":"Asia/Pyongyang",
    "iso:country":"KP",
    "name:und_x_variant":[
        "\uc554\ud765\ub9ac",
        "Amh\u016dng-ni"
    ],
    "wof:name":"Amhung-ni",
    "wof:placetype":"locality"
},
  "geometry": {"coordinates":[128.28916999999998,40.96806],"type":"Point"}
}