{
  "type": "Feature",
  "properties": {
    "gn:admin1_code":"15.0",
    "gn:asciiname":"Pulgun-dong",
    "gn:cc2":"KP",
    "gn:country_code":"KP",
    "gn:dem":15,
    "gn:feature_class":"P",
    "gn:feature_code":"PPL",
    "gn:name":"Pulg\u016dn-dong",
    "gn:population":0,
    "gn:timezone":"Asia/Pyongyang",
    "iso:country":"KP",
    "name:kor_x_preferred":[
        "\ubd88\uadfc\ub3d9"
    ],
    "name:und_x_variant":[
        "Chok-tong",
        "Pulg\u016dn-dong"
    ],
    "wof:name":"Pulgun-dong",
    "wof:placetype":"locality"
},
  "geometry": {"coordinates":[125.39028,39.17806],"type":"Point"}
}