{
  "type": "Feature",
  "properties": {
    "gn:admin1_code":"6.0",
    "gn:asciiname":"Yongha",
    "gn:country_code":"KP",
    "gn:dem":49,
    "gn:feature_class":"P",
    "gn:feature_code":"PPL",
    "gn:name":"Y\u014fngha",
    "gn:population":0,
    "gn:timezone":"Asia/Pyongyang",
    "iso:country":"KP",
    "wof:name":"Yongha",
    "wof:placetype":"locality"
},
  "geometry": {"coordinates":[125.67055999999999,38.29333],"type":"Point"}
}