{
  "type": "Feature",
  "properties": {
    "gn:admin1_code":"0.0",
    "gn:asciiname":"Yongch'ol-li",
    "gn:country_code":"KP",
    "gn:dem":243,
    "gn:feature_class":"P",
    "gn:feature_code":"PPL",
    "gn:name":"Yongch\u2019\u014fl-li",
    "gn:population":0,
    "gn:timezone":"Asia/Pyongyang",
    "iso:country":"KP",
    "name:kor_x_preferred":[
        "\uc6a9\ucc9c\ub9ac"
    ],
    "name:und_x_variant":[
        "Yongch\u2019\u014fl-li",
        "Yongch\u2019\u014fn-ni"
    ],
    "wof:name":"Yongch'ol-li",
    "wof:placetype":"locality"
},
  "geometry": {"coordinates":[126.86667,39.68333],"type":"Point"}
}