{
  "type": "Feature",
  "properties": {
    "gn:admin1_code":"6.0",
    "gn:asciiname":"Sanggan-dong",
    "gn:country_code":"KP",
    "gn:dem":64,
    "gn:feature_class":"P",
    "gn:feature_code":"PPL",
    "gn:name":"Sanggan-dong",
    "gn:population":0,
    "gn:timezone":"Asia/Pyongyang",
    "iso:country":"KP",
    "wof:name":"Sanggan-dong",
    "wof:placetype":"locality"
},
  "geometry": {"coordinates":[125.52722,38.29778],"type":"Point"}
}