{
  "type": "Feature",
  "properties": {
    "gn:admin1_code":"7.0",
    "gn:asciiname":"Yangdok-tong",
    "gn:country_code":"KP",
    "gn:dem":176,
    "gn:feature_class":"P",
    "gn:feature_code":"PPL",
    "gn:name":"Yangd\u014fk-tong",
    "gn:population":0,
    "gn:timezone":"Asia/Pyongyang",
    "iso:country":"KP",
    "name:eng_x_preferred":[
        "Yangdok"
    ],
    "name:eng_x_variant":[
        "Yangdok-tong"
    ],
    "wof:name":"Yangdok",
    "wof:placetype":"locality"
},
  "geometry": {"coordinates":[126.26889,38.48667],"type":"Point"}
}