{
  "type": "Feature",
  "properties": {
    "gn:admin1_code":"6.0",
    "gn:asciiname":"Masal-li",
    "gn:country_code":"KP",
    "gn:dem":59,
    "gn:feature_class":"P",
    "gn:feature_code":"PPL",
    "gn:name":"Masal-li",
    "gn:population":0,
    "gn:timezone":"Asia/Pyongyang",
    "iso:country":"KP",
    "name:kor_x_preferred":[
        "\ub9c8\uc0b0\ub9ac"
    ],
    "name:und_x_variant":[
        "Masan-ni",
        "Masal-li"
    ],
    "wof:name":"Masal-li",
    "wof:placetype":"locality"
},
  "geometry": {"coordinates":[125.19499999999999,38.33722],"type":"Point"}
}