{
  "type": "Feature",
  "properties": {
    "gn:admin1_code":"7.0",
    "gn:asciiname":"Pongdang-dong",
    "gn:country_code":"KP",
    "gn:dem":221,
    "gn:feature_class":"P",
    "gn:feature_code":"PPL",
    "gn:name":"Pongdang-dong",
    "gn:population":0,
    "gn:timezone":"Asia/Pyongyang",
    "iso:country":"KP",
    "wof:name":"Pongdang-dong",
    "wof:placetype":"locality"
},
  "geometry": {"coordinates":[126.16249999999999,38.5875],"type":"Point"}
}