{
  "type": "Feature",
  "properties": {
    "gn:admin1_code":"7.0",
    "gn:asciiname":"Un'gok-tong",
    "gn:country_code":"KP",
    "gn:dem":146,
    "gn:feature_class":"P",
    "gn:feature_code":"PPL",
    "gn:name":"Un\u2019gok-tong",
    "gn:population":0,
    "gn:timezone":"Asia/Pyongyang",
    "iso:country":"KP",
    "name:eng_x_preferred":[
        "Un'gok"
    ],
    "name:eng_x_variant":[
        "Un'gok-tong"
    ],
    "name:und_x_variant":[
        "Ungok-tong",
        "Un\u2019gok-tong"
    ],
    "wof:name":"Un'gok",
    "wof:placetype":"locality"
},
  "geometry": {"coordinates":[126.12333,38.40667],"type":"Point"}
}