{
  "type": "Feature",
  "properties": {
    "gn:admin1_code":"6.0",
    "gn:admin2_code":"Changp\u2019ung-gun",
    "gn:asciiname":"Tumu-dong",
    "gn:country_code":"KP",
    "gn:dem":269,
    "gn:feature_class":"P",
    "gn:feature_code":"PPL",
    "gn:name":"Tumu-dong",
    "gn:population":0,
    "gn:timezone":"Asia/Pyongyang",
    "iso:country":"KP",
    "wof:name":"Tumu-dong",
    "wof:placetype":"locality"
},
  "geometry": {"coordinates":[126.62833000000001,38.10194],"type":"Point"}
}