{
  "type": "Feature",
  "properties": {
    "gn:admin1_code":"15.0",
    "gn:admin2_code":"1871865",
    "gn:asciiname":"Yongdang-ni",
    "gn:country_code":"KP",
    "gn:dem":12,
    "gn:feature_class":"P",
    "gn:feature_code":"PPL",
    "gn:name":"Yongdang-ni",
    "gn:population":0,
    "gn:timezone":"Asia/Pyongyang",
    "iso:country":"KP",
    "wof:name":"Yongdang-ni",
    "wof:placetype":"locality"
},
  "geometry": {"coordinates":[125.54389,39.29389000000001],"type":"Point"}
}