{
  "type": "Feature",
  "properties": {
    "gn:admin1_code":"12.0",
    "gn:asciiname":"Chaksom",
    "gn:country_code":"KP",
    "gn:dem":11,
    "gn:feature_class":"P",
    "gn:feature_code":"PPL",
    "gn:name":"Chaks\u014fm",
    "gn:population":0,
    "gn:timezone":"Asia/Pyongyang",
    "iso:country":"KP",
    "name:kor_x_preferred":[
        "\uc791\uc12c"
    ],
    "name:und_x_variant":[
        "Chakto",
        "Chaks\u014fm",
        "Jakseom"
    ],
    "wof:name":"Chaksom",
    "wof:placetype":"locality"
},
  "geometry": {"coordinates":[125.6862,38.92412],"type":"Point"}
}