{
  "type": "Feature",
  "properties": {
    "gn:admin1_code":"9.0",
    "gn:admin2_code":"Munch\u2019\u014fn-si",
    "gn:asciiname":"Munch'ang-ni",
    "gn:country_code":"KP",
    "gn:dem":25,
    "gn:feature_class":"P",
    "gn:feature_code":"PPL",
    "gn:name":"Munch\u2019ang-ni",
    "gn:population":0,
    "gn:timezone":"Asia/Pyongyang",
    "iso:country":"KP",
    "name:und_x_variant":[
        "Munyang-ni",
        "Munch\u2019ang-ni",
        "\ubb38\ucc3d\ub9ac"
    ],
    "wof:name":"Munch'ang-ni",
    "wof:placetype":"locality"
},
  "geometry": {"coordinates":[127.28139,39.30222],"type":"Point"}
}