{
  "type": "Feature",
  "properties": {
    "gn:admin1_code":"9.0",
    "gn:asciiname":"Twik-kol",
    "gn:country_code":"KP",
    "gn:dem":192,
    "gn:feature_class":"P",
    "gn:feature_code":"PPL",
    "gn:name":"Twik-kol",
    "gn:population":0,
    "gn:timezone":"Asia/Pyongyang",
    "iso:country":"KP",
    "wof:name":"Twik-kol",
    "wof:placetype":"locality"
},
  "geometry": {"coordinates":[126.93306,38.66361],"type":"Point"}
}