{
  "type": "Feature",
  "properties": {
    "gn:admin1_code":"15.0",
    "gn:asciiname":"Yonghung-ni",
    "gn:cc2":"KP",
    "gn:country_code":"KP",
    "gn:dem":48,
    "gn:feature_class":"P",
    "gn:feature_code":"PPL",
    "gn:name":"Yongh\u016dng-ni",
    "gn:population":0,
    "gn:timezone":"Asia/Pyongyang",
    "iso:country":"KP",
    "name:kor_x_preferred":[
        "\uc6a9\ud765\ub9ac"
    ],
    "name:und_x_variant":[
        "Yonghung",
        "Yongh\u016dng-ni"
    ],
    "wof:name":"Yonghung-ni",
    "wof:placetype":"locality"
},
  "geometry": {"coordinates":[125.76416999999999,39.65],"type":"Point"}
}