{
  "type": "Feature",
  "properties": {
    "gn:admin1_code":"11.0",
    "gn:asciiname":"Omp'ung-dong",
    "gn:country_code":"KP",
    "gn:dem":219,
    "gn:feature_class":"P",
    "gn:feature_code":"PPL",
    "gn:name":"\u014emp\u2019ung-dong",
    "gn:population":0,
    "gn:timezone":"Asia/Pyongyang",
    "iso:country":"KP",
    "name:und_x_variant":[
        "\uc5c4\ud48d\ub3d9",
        "\u014emp\u2019ung-dong"
    ],
    "wof:name":"Omp'ung-dong",
    "wof:placetype":"locality"
},
  "geometry": {"coordinates":[125.24250000000001,40.25028],"type":"Point"}
}