{
  "type": "Feature",
  "properties": {
    "gn:admin1_code":"6.0",
    "gn:asciiname":"Hwangguk-tong",
    "gn:country_code":"KP",
    "gn:dem":104,
    "gn:feature_class":"P",
    "gn:feature_code":"PPL",
    "gn:name":"Hwangguk-tong",
    "gn:population":0,
    "gn:timezone":"Asia/Pyongyang",
    "iso:country":"KP",
    "wof:name":"Hwangguk-tong",
    "wof:placetype":"locality"
},
  "geometry": {"coordinates":[124.96666999999999,38.15],"type":"Point"}
}