{
  "type": "Feature",
  "properties": {
    "gn:admin1_code":"6.0",
    "gn:asciiname":"Yojok-tong",
    "gn:country_code":"KP",
    "gn:dem":40,
    "gn:feature_class":"P",
    "gn:feature_code":"PPL",
    "gn:name":"Y\u014fj\u014fk-tong",
    "gn:population":0,
    "gn:timezone":"Asia/Pyongyang",
    "iso:country":"KP",
    "name:eng_x_preferred":[
        "Yojok"
    ],
    "name:eng_x_variant":[
        "Yojok-tong"
    ],
    "name:kor_x_preferred":[
        "\uc5ec\uc801\ub3d9"
    ],
    "name:kor_x_variant":[
        "Y\u014fj\u014fk-tong"
    ],
    "wof:name":"Yojok",
    "wof:placetype":"locality"
},
  "geometry": {"coordinates":[125.12333,38.25361],"type":"Point"}
}