{
  "type": "Feature",
  "properties": {
    "gn:admin1_code":"1.0",
    "gn:asciiname":"Hoeyang-dong",
    "gn:country_code":"KP",
    "gn:dem":352,
    "gn:feature_class":"P",
    "gn:feature_code":"PPL",
    "gn:name":"Hoeyang-dong",
    "gn:population":0,
    "gn:timezone":"Asia/Pyongyang",
    "iso:country":"KP",
    "name:und_x_variant":[
        "\ud68c\uc591\ub3d9",
        "Hoeyang-dong"
    ],
    "wof:name":"Hoeyang-dong",
    "wof:placetype":"locality"
},
  "geometry": {"coordinates":[126.68056,41.46083],"type":"Point"}
}