{
  "type": "Feature",
  "properties": {
    "gn:admin1_code":"15.0",
    "gn:asciiname":"Chagundarigonno",
    "gn:country_code":"KP",
    "gn:dem":21,
    "gn:feature_class":"P",
    "gn:feature_code":"PPL",
    "gn:name":"Chag\u016dndarig\u014fnn\u014f",
    "gn:population":0,
    "gn:timezone":"Asia/Pyongyang",
    "iso:country":"KP",
    "name:und_x_variant":[
        "Sogyow\u014fl",
        "Chag\u016dndarig\u014fnn\u014f"
    ],
    "wof:name":"Chagundarigonno",
    "wof:placetype":"locality"
},
  "geometry": {"coordinates":[125.43138999999999,39.21528],"type":"Point"}
}