{
  "type": "Feature",
  "properties": {
    "gn:admin1_code":"11.0",
    "gn:asciiname":"Yongyol-li",
    "gn:country_code":"KP",
    "gn:dem":11,
    "gn:feature_class":"P",
    "gn:feature_code":"PPL",
    "gn:name":"Yongy\u014fl-li",
    "gn:population":0,
    "gn:timezone":"Asia/Pyongyang",
    "iso:country":"KP",
    "name:und_x_variant":[
        "Yongy\u014fn-dong",
        "Yongy\u014fn-ni",
        "\ub8e1\uc5f0\ub9ac",
        "Yongy\u014fl-li"
    ],
    "wof:name":"Yongyol-li",
    "wof:placetype":"locality"
},
  "geometry": {"coordinates":[124.41388999999999,39.97583],"type":"Point"}
}