{
  "type": "Feature",
  "properties": {
    "gn:admin1_code":"17.0",
    "gn:asciiname":"Myongsudok",
    "gn:country_code":"KP",
    "gn:dem":442,
    "gn:feature_class":"P",
    "gn:feature_code":"PPL",
    "gn:name":"My\u014fngsud\u014fk",
    "gn:population":0,
    "gn:timezone":"Asia/Pyongyang",
    "iso:country":"KP",
    "name:und_x_variant":[
        "\uba85\uc218\ub355",
        "My\u014fngsud\u014fk"
    ],
    "wof:name":"Myongsudok",
    "wof:placetype":"locality"
},
  "geometry": {"coordinates":[129.92056000000002,42.69472],"type":"Point"}
}