{
  "type": "Feature",
  "properties": {
    "gn:admin1_code":"1.0",
    "gn:asciiname":"Munmyong-dong",
    "gn:country_code":"KP",
    "gn:dem":379,
    "gn:feature_class":"P",
    "gn:feature_code":"PPL",
    "gn:name":"Munmy\u014fng-dong",
    "gn:population":0,
    "gn:timezone":"Asia/Pyongyang",
    "iso:country":"KP",
    "name:und_x_variant":[
        "\ubb38\uba85\ub3d9",
        "Munmy\u014fng-dong"
    ],
    "wof:name":"Munmyong-dong",
    "wof:placetype":"locality"
},
  "geometry": {"coordinates":[126.25639,40.81361],"type":"Point"}
}