{
  "type": "Feature",
  "properties": {
    "gn:admin1_code":"6.0",
    "gn:admin2_code":"Kaep'ung-gun",
    "gn:asciiname":"Araebol",
    "gn:country_code":"KP",
    "gn:dem":23,
    "gn:feature_class":"P",
    "gn:feature_code":"PPL",
    "gn:name":"Araeb\u014fl",
    "gn:population":0,
    "gn:timezone":"Asia/Pyongyang",
    "iso:country":"KP",
    "wof:name":"Araebol",
    "wof:placetype":"locality"
},
  "geometry": {"coordinates":[126.46222,37.94194],"type":"Point"}
}