{
  "type": "Feature",
  "properties": {
    "gn:admin1_code":"6.0",
    "gn:admin2_code":"Paech'\u014fn-gun",
    "gn:asciiname":"Honghyol-li",
    "gn:cc2":"KP",
    "gn:country_code":"KP",
    "gn:dem":15,
    "gn:feature_class":"P",
    "gn:feature_code":"PPL",
    "gn:name":"Honghy\u014fl-li",
    "gn:population":0,
    "gn:timezone":"Asia/Pyongyang",
    "iso:country":"KP",
    "name:kor_x_preferred":[
        "\ud64d\ud604\ub9ac"
    ],
    "name:und_x_variant":[
        "Honghy\u014fnjang",
        "Honghy\u014fn-ni",
        "Honghy\u014fl-li"
    ],
    "wof:name":"Honghyol-li",
    "wof:placetype":"locality"
},
  "geometry": {"coordinates":[126.27333,37.96639],"type":"Point"}
}