{
  "type": "Feature",
  "properties": {
    "gn:admin1_code":"3.0",
    "gn:asciiname":"Songhung-ni",
    "gn:country_code":"KP",
    "gn:dem":38,
    "gn:feature_class":"P",
    "gn:feature_code":"PPL",
    "gn:name":"S\u014fngh\u016dng-ni",
    "gn:population":0,
    "gn:timezone":"Asia/Pyongyang",
    "iso:country":"KP",
    "name:und_x_variant":[
        "\uc131\ud765\ub9ac",
        "S\u014fngh\u016dng-ni"
    ],
    "wof:name":"Songhung-ni",
    "wof:placetype":"locality"
},
  "geometry": {"coordinates":[127.43361000000002,39.54278],"type":"Point"}
}