{
  "type": "Feature",
  "properties": {
    "gn:admin1_code":"12.0",
    "gn:asciiname":"Chonch'ol-li",
    "gn:country_code":"KP",
    "gn:dem":39,
    "gn:feature_class":"P",
    "gn:feature_code":"PPL",
    "gn:name":"Ch\u014fnch\u2019ol-li",
    "gn:population":0,
    "gn:timezone":"Asia/Pyongyang",
    "iso:country":"KP",
    "name:kor_x_preferred":[
        "\uc804\ucd0c\ub9ac"
    ],
    "name:und_x_variant":[
        "Ch\u014fnch\u2019on-ni",
        "Ch\u014fnch\u2019ol-li",
        "Jeoncholli"
    ],
    "wof:name":"Chonch'ol-li",
    "wof:placetype":"locality"
},
  "geometry": {"coordinates":[125.64444,39.04778],"type":"Point"}
}