{
  "type": "Feature",
  "properties": {
    "gn:admin1_code":"3.0",
    "gn:asciiname":"Sinjung-ni",
    "gn:country_code":"KP",
    "gn:dem":60,
    "gn:feature_class":"P",
    "gn:feature_code":"PPL",
    "gn:name":"Sinjung-ni",
    "gn:population":0,
    "gn:timezone":"Asia/Pyongyang",
    "iso:country":"KP",
    "name:und_x_variant":[
        "\uc2e0\uc911\ub9ac",
        "Sinjung-ni"
    ],
    "wof:name":"Sinjung-ni",
    "wof:placetype":"locality"
},
  "geometry": {"coordinates":[127.54167,40.04056],"type":"Point"}
}