{
  "type": "Feature",
  "properties": {
    "gn:admin1_code":"15.0",
    "gn:asciiname":"Ryongp'o-dong",
    "gn:country_code":"KP",
    "gn:dem":175,
    "gn:feature_class":"P",
    "gn:feature_code":"PPL",
    "gn:name":"Ryongp\u2019o-dong",
    "gn:population":0,
    "gn:timezone":"Asia/Pyongyang",
    "iso:country":"KP",
    "name:kor_x_preferred":[
        "\ub8e1\ud3ec\ub3d9"
    ],
    "name:und_x_variant":[
        "Ryongp\u2019o-dong",
        "Yongp\u2019o-dong"
    ],
    "wof:name":"Ryongp'o-dong",
    "wof:placetype":"locality"
},
  "geometry": {"coordinates":[126.3925,39.61361],"type":"Point"}
}