{
  "type": "Feature",
  "properties": {
    "gn:admin1_code":"15.0",
    "gn:asciiname":"Ryongp'och'am",
    "gn:country_code":"KP",
    "gn:dem":23,
    "gn:feature_class":"P",
    "gn:feature_code":"PPL",
    "gn:name":"Ryongp\u2019och\u2019am",
    "gn:population":0,
    "gn:timezone":"Asia/Pyongyang",
    "iso:country":"KP",
    "name:kor_x_preferred":[
        "\ub8e1\ud3ec\ucc38"
    ],
    "name:und_x_variant":[
        "Ryongp\u2019och\u2019am",
        "Yongp\u2019och\u2019am"
    ],
    "wof:name":"Ryongp'och'am",
    "wof:placetype":"locality"
},
  "geometry": {"coordinates":[125.84472,39.70222],"type":"Point"}
}