{
  "type": "Feature",
  "properties": {
    "gn:admin1_code":"6.0",
    "gn:asciiname":"Tarangmol",
    "gn:country_code":"KP",
    "gn:dem":23,
    "gn:feature_class":"P",
    "gn:feature_code":"PPL",
    "gn:name":"Tarangmol",
    "gn:population":0,
    "gn:timezone":"Asia/Pyongyang",
    "iso:country":"KP",
    "wof:name":"Tarangmol",
    "wof:placetype":"locality"
},
  "geometry": {"coordinates":[126.12778,37.95306],"type":"Point"}
}