{
  "type": "Feature",
  "properties": {
    "gn:admin1_code":"3.0",
    "gn:asciiname":"Pumil-li",
    "gn:country_code":"KP",
    "gn:dem":14,
    "gn:feature_class":"P",
    "gn:feature_code":"PPL",
    "gn:name":"Pumil-li",
    "gn:population":0,
    "gn:timezone":"Asia/Pyongyang",
    "iso:country":"KP",
    "name:und_x_variant":[
        "\ubd80\ubbfc\ub9ac",
        "Pumil-li"
    ],
    "wof:name":"Pumil-li",
    "wof:placetype":"locality"
},
  "geometry": {"coordinates":[127.85666999999999,39.97111],"type":"Point"}
}