{
  "type": "Feature",
  "properties": {
    "gn:admin1_code":"17.0",
    "gn:asciiname":"Uch'onsangp'yong",
    "gn:country_code":"KP",
    "gn:dem":374,
    "gn:feature_class":"P",
    "gn:feature_code":"PPL",
    "gn:name":"Uch\u2019onsangp\u2019y\u014fng",
    "gn:population":0,
    "gn:timezone":"Asia/Pyongyang",
    "iso:country":"KP",
    "name:und_x_variant":[
        "\uc6b0\ucd0c\uc0c1\ud3c9",
        "Uch\u2019onsangp\u2019y\u014fng"
    ],
    "wof:name":"Uch'onsangp'yong",
    "wof:placetype":"locality"
},
  "geometry": {"coordinates":[129.86389,42.40306],"type":"Point"}
}