{
  "type": "Feature",
  "properties": {
    "gn:admin1_code":"15.0",
    "gn:asciiname":"Kyedong-ni",
    "gn:country_code":"KP",
    "gn:dem":66,
    "gn:feature_class":"P",
    "gn:feature_code":"PPL",
    "gn:name":"Kyedong-ni",
    "gn:population":0,
    "gn:timezone":"Asia/Pyongyang",
    "iso:country":"KP",
    "name:eng_x_preferred":[
        "Kyedong"
    ],
    "name:eng_x_variant":[
        "Kyedong-ni"
    ],
    "wof:name":"Kyedong",
    "wof:placetype":"locality"
},
  "geometry": {"coordinates":[125.95222,39.31611],"type":"Point"}
}