{
  "type": "Feature",
  "properties": {
    "gn:admin1_code":"1.0",
    "gn:asciiname":"Paeksal-li",
    "gn:country_code":"KP",
    "gn:dem":345,
    "gn:feature_class":"P",
    "gn:feature_code":"PPL",
    "gn:name":"Paeksal-li",
    "gn:population":0,
    "gn:timezone":"Asia/Pyongyang",
    "iso:country":"KP",
    "name:kor_x_preferred":[
        "\ubc31\uc0b0\ub9ac"
    ],
    "name:und_x_variant":[
        "Paeksan-ni",
        "Paeksan-dong",
        "Paeksal-li"
    ],
    "wof:name":"Paeksal-li",
    "wof:placetype":"locality"
},
  "geometry": {"coordinates":[126.51348,40.36317],"type":"Point"}
}