{
  "type": "Feature",
  "properties": {
    "gn:admin1_code":"0.0",
    "gn:asciiname":"P'osang-ni",
    "gn:country_code":"KP",
    "gn:dem":440,
    "gn:feature_class":"P",
    "gn:feature_code":"PPL",
    "gn:name":"P\u2019osang-ni",
    "gn:population":0,
    "gn:timezone":"Asia/Pyongyang",
    "iso:country":"KP",
    "name:eng_x_preferred":[
        "P'osang"
    ],
    "name:eng_x_variant":[
        "P'osang-ni"
    ],
    "name:und_x_variant":[
        "P\u2019osam-dong",
        "P\u2019osam-ni",
        "P\u2019osang-ni"
    ],
    "wof:name":"P'osang",
    "wof:placetype":"locality"
},
  "geometry": {"coordinates":[127.23372999999999,41.49776],"type":"Point"}
}