{
  "type": "Feature",
  "properties": {
    "gn:admin1_code":"15.0",
    "gn:admin2_code":"S\u014fngch\u2019\u014fn-gun",
    "gn:asciiname":"Kohwang-dong",
    "gn:country_code":"KP",
    "gn:dem":84,
    "gn:feature_class":"P",
    "gn:feature_code":"PPL",
    "gn:name":"Kohwang-dong",
    "gn:population":0,
    "gn:timezone":"Asia/Pyongyang",
    "iso:country":"KP",
    "wof:name":"Kohwang-dong",
    "wof:placetype":"locality"
},
  "geometry": {"coordinates":[126.12027999999999,39.21056],"type":"Point"}
}