{
  "type": "Feature",
  "properties": {
    "gn:admin1_code":"7.0",
    "gn:admin2_code":"Y\u014fnsan-gun",
    "gn:asciiname":"Odu",
    "gn:country_code":"KP",
    "gn:dem":87,
    "gn:feature_class":"P",
    "gn:feature_code":"PPL",
    "gn:name":"Odu",
    "gn:population":0,
    "gn:timezone":"Asia/Pyongyang",
    "iso:country":"KP",
    "name:ceb_x_preferred":[
        "Odu"
    ],
    "name:swe_x_preferred":[
        "Odu"
    ],
    "wof:name":"Odu",
    "wof:placetype":"locality"
},
  "geometry": {"coordinates":[126.25444,38.95806],"type":"Point"}
}