{
  "type": "Feature",
  "properties": {
    "gn:admin1_code":"6.0",
    "gn:asciiname":"Ch'imgyo",
    "gn:country_code":"KP",
    "gn:dem":91,
    "gn:feature_class":"P",
    "gn:feature_code":"PPL",
    "gn:name":"Ch\u2019imgyo",
    "gn:population":0,
    "gn:timezone":"Asia/Pyongyang",
    "iso:country":"KP",
    "name:kor_x_preferred":[
        "\uce68\uad50"
    ],
    "name:kor_x_variant":[
        "Ch\u2019imgyo"
    ],
    "wof:name":"Ch'imgyo",
    "wof:placetype":"locality"
},
  "geometry": {"coordinates":[125.27443999999998,38.28889],"type":"Point"}
}