{
  "type": "Feature",
  "properties": {
    "gn:admin1_code":"0.0",
    "gn:asciiname":"Sodok",
    "gn:cc2":"KP",
    "gn:country_code":"KP",
    "gn:dem":1420,
    "gn:feature_class":"P",
    "gn:feature_code":"PPL",
    "gn:name":"Sod\u014fk",
    "gn:population":0,
    "gn:timezone":"Asia/Pyongyang",
    "iso:country":"KP",
    "name:kor_x_preferred":[
        "\uc18c\ub355"
    ],
    "name:und_x_variant":[
        "Chag\u016dnd\u014fk",
        "Sod\u014fk"
    ],
    "wof:name":"Sodok",
    "wof:placetype":"locality"
},
  "geometry": {"coordinates":[127.38333,40.48333],"type":"Point"}
}