{
  "type": "Feature",
  "properties": {
    "gn:admin1_code":"1.0",
    "gn:asciiname":"Sagi-dong",
    "gn:country_code":"KP",
    "gn:dem":681,
    "gn:feature_class":"P",
    "gn:feature_code":"PPL",
    "gn:name":"Sagi-dong",
    "gn:population":0,
    "gn:timezone":"Asia/Pyongyang",
    "iso:country":"KP",
    "name:kor_x_preferred":[
        "\uc0ac\uae30\ub3d9"
    ],
    "wof:name":"Sagi-dong",
    "wof:placetype":"locality"
},
  "geometry": {"coordinates":[125.79139000000001,40.23833],"type":"Point"}
}