{
  "type": "Feature",
  "properties": {
    "gn:admin1_code":"13.0",
    "gn:asciiname":"Hajigyong-ni",
    "gn:country_code":"KP",
    "gn:dem":1081,
    "gn:feature_class":"P",
    "gn:feature_code":"PPL",
    "gn:name":"Hajigy\u014fng-ni",
    "gn:population":0,
    "gn:timezone":"Asia/Pyongyang",
    "iso:country":"KP",
    "name:eng_x_preferred":[
        "Hajigyong"
    ],
    "name:eng_x_variant":[
        "Hajigyong-ni"
    ],
    "wof:name":"Hajigyong",
    "wof:placetype":"locality"
},
  "geometry": {"coordinates":[128.255,40.79333],"type":"Point"}
}