{
  "type": "Feature",
  "properties": {
    "gn:admin1_code":"15.0",
    "gn:asciiname":"Kosong-ni",
    "gn:country_code":"KP",
    "gn:dem":31,
    "gn:feature_class":"P",
    "gn:feature_code":"PPL",
    "gn:name":"Kos\u014fng-ni",
    "gn:population":0,
    "gn:timezone":"Asia/Pyongyang",
    "iso:country":"KP",
    "name:kor_x_preferred":[
        "\uace0\uc131\ub9ac"
    ],
    "name:kor_x_variant":[
        "Kos\u014fng-ni"
    ],
    "wof:name":"Kosong-ni",
    "wof:placetype":"locality"
},
  "geometry": {"coordinates":[125.68111,39.62222],"type":"Point"}
}