{
  "type": "Feature",
  "properties": {
    "gn:admin1_code":"17.0",
    "gn:asciiname":"Tagal-tong",
    "gn:country_code":"KP",
    "gn:dem":251,
    "gn:feature_class":"P",
    "gn:feature_code":"PPL",
    "gn:name":"Tagal-tong",
    "gn:population":0,
    "gn:timezone":"Asia/Pyongyang",
    "iso:country":"KP",
    "name:eng_x_preferred":[
        "Tagal"
    ],
    "name:eng_x_variant":[
        "Tagal-tong"
    ],
    "name:und_x_variant":[
        "\ub2e4\uac08\ub3d9",
        "Tagal-tong"
    ],
    "wof:name":"Tagal",
    "wof:placetype":"locality"
},
  "geometry": {"coordinates":[129.77055999999999,41.99056],"type":"Point"}
}