{
  "type": "Feature",
  "properties": {
    "gn:admin1_code":"11.0",
    "gn:asciiname":"Kan-dong",
    "gn:country_code":"KP",
    "gn:dem":33,
    "gn:feature_class":"P",
    "gn:feature_code":"PPL",
    "gn:name":"Kan-dong",
    "gn:population":0,
    "gn:timezone":"Asia/Pyongyang",
    "iso:country":"KP",
    "name:kor_x_preferred":[
        "\uac04\ub3d9"
    ],
    "wof:name":"Kan-dong",
    "wof:placetype":"locality"
},
  "geometry": {"coordinates":[125.02097000000001,39.71842],"type":"Point"}
}