{
  "type": "Feature",
  "properties": {
    "gn:admin1_code":"7.0",
    "gn:asciiname":"Kwanjok-tong",
    "gn:country_code":"KP",
    "gn:dem":369,
    "gn:feature_class":"P",
    "gn:feature_code":"PPL",
    "gn:name":"Kwanj\u014fk-tong",
    "gn:population":0,
    "gn:timezone":"Asia/Pyongyang",
    "iso:country":"KP",
    "name:kor_x_preferred":[
        "\uad00\uc801\ub3d9"
    ],
    "name:kor_x_variant":[
        "Kwanj\u014fk-tong"
    ],
    "wof:name":"Kwanjok-tong",
    "wof:placetype":"locality"
},
  "geometry": {"coordinates":[126.77611,38.88028],"type":"Point"}
}