{
  "type": "Feature",
  "properties": {
    "gn:admin1_code":"15.0",
    "gn:asciiname":"No-dong",
    "gn:country_code":"KP",
    "gn:dem":23,
    "gn:feature_class":"P",
    "gn:feature_code":"PPL",
    "gn:name":"No-dong",
    "gn:population":0,
    "gn:timezone":"Asia/Pyongyang",
    "iso:country":"KP",
    "name:kor_x_preferred":[
        "\ub178\ub3d9"
    ],
    "wof:name":"No-dong",
    "wof:placetype":"locality"
},
  "geometry": {"coordinates":[125.53972,38.74917],"type":"Point"}
}