{
  "type": "Feature",
  "properties": {
    "gn:admin1_code":"7.0",
    "gn:asciiname":"Hanp'o-ri",
    "gn:country_code":"KP",
    "gn:dem":29,
    "gn:feature_class":"P",
    "gn:feature_code":"PPL",
    "gn:name":"Hanp\u2019o-ri",
    "gn:population":0,
    "gn:timezone":"Asia/Pyongyang",
    "iso:country":"KP",
    "name:und_x_variant":[
        "Kampo-ri",
        "\ud55c\ud3ec\ub9ac",
        "Hanp\u2019o-ri"
    ],
    "wof:name":"Hanp'o-ri",
    "wof:placetype":"locality"
},
  "geometry": {"coordinates":[126.44917,38.23139000000001],"type":"Point"}
}