{
  "type": "Feature",
  "properties": {
    "gn:admin1_code":"6.0",
    "gn:asciiname":"Yangsu-dong",
    "gn:country_code":"KP",
    "gn:dem":120,
    "gn:feature_class":"P",
    "gn:feature_code":"PPL",
    "gn:name":"Yangsu-dong",
    "gn:population":0,
    "gn:timezone":"Asia/Pyongyang",
    "iso:country":"KP",
    "name:und_x_variant":[
        "Yusu-dong",
        "Yangsu-dong"
    ],
    "wof:name":"Yangsu-dong",
    "wof:placetype":"locality"
},
  "geometry": {"coordinates":[125.37972000000001,38.54694],"type":"Point"}
}