{
  "type": "Feature",
  "properties": {
    "gn:admin1_code":"7.0",
    "gn:asciiname":"T'orong-gol",
    "gn:country_code":"KP",
    "gn:dem":181,
    "gn:feature_class":"P",
    "gn:feature_code":"PPL",
    "gn:name":"T\u2019orong-gol",
    "gn:population":0,
    "gn:timezone":"Asia/Pyongyang",
    "iso:country":"KP",
    "name:kor_x_preferred":[
        "\ud1a0\ub871\uace8"
    ],
    "name:kor_x_variant":[
        "T\u2019orong-gol"
    ],
    "wof:name":"T'orong-gol",
    "wof:placetype":"locality"
},
  "geometry": {"coordinates":[126.29889,38.59222000000001],"type":"Point"}
}