{
  "type": "Feature",
  "properties": {
    "gn:admin1_code":"0.0",
    "gn:asciiname":"Hasonggwal-li",
    "gn:country_code":"KP",
    "gn:dem":336,
    "gn:feature_class":"P",
    "gn:feature_code":"PPL",
    "gn:name":"Hasonggwal-li",
    "gn:population":0,
    "gn:timezone":"Asia/Pyongyang",
    "iso:country":"KP",
    "name:kor_x_preferred":[
        "\ud558\uc1a1\uad00\ub9ac"
    ],
    "name:und_x_variant":[
        "Hasonggwan-ni"
    ],
    "wof:name":"Hasonggwal-li",
    "wof:placetype":"locality"
},
  "geometry": {"coordinates":[127.42083,38.48278],"type":"Point"}
}