{
  "type": "Feature",
  "properties": {
    "gn:admin1_code":"1.0",
    "gn:asciiname":"Koum-dong",
    "gn:country_code":"KP",
    "gn:dem":186,
    "gn:feature_class":"P",
    "gn:feature_code":"PPL",
    "gn:name":"Ko\u016dm-dong",
    "gn:population":0,
    "gn:timezone":"Asia/Pyongyang",
    "iso:country":"KP",
    "name:und_x_variant":[
        "\uace0\uc74c\ub3d9",
        "Ko\u016dm-dong"
    ],
    "wof:name":"Koum-dong",
    "wof:placetype":"locality"
},
  "geometry": {"coordinates":[126.14278,40.12528],"type":"Point"}
}