{
  "type": "Feature",
  "properties": {
    "gn:admin1_code":"6.0",
    "gn:asciiname":"Yongjong-ni",
    "gn:country_code":"KP",
    "gn:dem":37,
    "gn:feature_class":"P",
    "gn:feature_code":"PPL",
    "gn:name":"Y\u014fngj\u014fng-ni",
    "gn:population":0,
    "gn:timezone":"Asia/Pyongyang",
    "iso:country":"KP",
    "name:kor_x_preferred":[
        "\uc601\uc815\ub9ac"
    ],
    "name:und_x_variant":[
        "Y\u014fngj\u014fng-ni"
    ],
    "wof:name":"Yongjong-ni",
    "wof:placetype":"locality"
},
  "geometry": {"coordinates":[126.03694,38.08417],"type":"Point"}
}