{
  "type": "Feature",
  "properties": {
    "gn:admin1_code":"17.0",
    "gn:asciiname":"Sangsinjon",
    "gn:country_code":"KP",
    "gn:dem":185,
    "gn:feature_class":"P",
    "gn:feature_code":"PPL",
    "gn:name":"Sangsinj\u014fn",
    "gn:population":0,
    "gn:timezone":"Asia/Pyongyang",
    "iso:country":"KP",
    "name:und_x_variant":[
        "\uc0c1\uc2e0\uc804",
        "Sangsinj\u014fn"
    ],
    "wof:name":"Sangsinjon",
    "wof:placetype":"locality"
},
  "geometry": {"coordinates":[129.75056000000001,42.64333],"type":"Point"}
}