{
  "type": "Feature",
  "properties": {
    "gn:admin1_code":"6.0",
    "gn:admin2_code":"Kaes\u0171ng-si",
    "gn:asciiname":"Kwakchang-ni",
    "gn:country_code":"KP",
    "gn:dem":55,
    "gn:feature_class":"P",
    "gn:feature_code":"PPL",
    "gn:name":"Kwakchang-ni",
    "gn:population":0,
    "gn:timezone":"Asia/Pyongyang",
    "iso:country":"KP",
    "name:eng_x_preferred":[
        "Kwakchang"
    ],
    "name:eng_x_variant":[
        "Kwakchang-ni"
    ],
    "wof:name":"Kwakchang",
    "wof:placetype":"locality"
},
  "geometry": {"coordinates":[126.55583,37.96],"type":"Point"}
}