{
  "type": "Feature",
  "properties": {
    "gn:admin1_code":"11.0",
    "gn:asciiname":"Muksi-dong",
    "gn:country_code":"KP",
    "gn:dem":57,
    "gn:feature_class":"P",
    "gn:feature_code":"PPL",
    "gn:name":"Muksi-dong",
    "gn:population":0,
    "gn:timezone":"Asia/Pyongyang",
    "iso:country":"KP",
    "name:und_x_variant":[
        "Muksi-ri",
        "Muksi-dong"
    ],
    "wof:name":"Muksi-dong",
    "wof:placetype":"locality"
},
  "geometry": {"coordinates":[125.92583,39.83],"type":"Point"}
}