{
  "type": "Feature",
  "properties": {
    "gn:admin1_code":"18.0",
    "gn:asciiname":"Sinhungch'on",
    "gn:country_code":"KP",
    "gn:dem":15,
    "gn:feature_class":"P",
    "gn:feature_code":"PPL",
    "gn:name":"Sinh\u016dngch\u2019\u014fn",
    "gn:population":0,
    "gn:timezone":"Asia/Pyongyang",
    "iso:country":"KP",
    "name:und_x_variant":[
        "Sinhoe-dong",
        "Sinhoe-ri",
        "\uc2e0\ud765\ucc9c",
        "Sinh\u016dngch\u2019\u014fn",
        "Sinheungcheon"
    ],
    "wof:name":"Sinhungch'on",
    "wof:placetype":"locality"
},
  "geometry": {"coordinates":[130.52638999999999,42.47528],"type":"Point"}
}