{
  "type": "Feature",
  "properties": {
    "gn:admin1_code":"3.0",
    "gn:admin2_code":"Tanch'\u014fn-si",
    "gn:asciiname":"Kumsan-dong",
    "gn:country_code":"KP",
    "gn:dem":506,
    "gn:feature_class":"P",
    "gn:feature_code":"PPL",
    "gn:name":"K\u016dmsan-dong",
    "gn:population":0,
    "gn:timezone":"Asia/Pyongyang",
    "iso:country":"KP",
    "name:und_x_variant":[
        "\uae08\uc0b0\ub3d9",
        "K\u016dmsan-dong"
    ],
    "wof:name":"Kumsan-dong",
    "wof:placetype":"locality"
},
  "geometry": {"coordinates":[128.83167,40.86694],"type":"Point"}
}