{
  "type": "Feature",
  "properties": {
    "gn:admin1_code":"15.0",
    "gn:asciiname":"Hyon'ga-gol",
    "gn:country_code":"KP",
    "gn:dem":13,
    "gn:feature_class":"P",
    "gn:feature_code":"PPL",
    "gn:name":"Hy\u014fn\u2019ga-gol",
    "gn:population":0,
    "gn:timezone":"Asia/Pyongyang",
    "iso:country":"KP",
    "name:und_x_variant":[
        "Hy\u014fnch\u2019on-dong",
        "Hy\u014fn\u2019ga-gol"
    ],
    "wof:name":"Hyon'ga-gol",
    "wof:placetype":"locality"
},
  "geometry": {"coordinates":[125.45278,39.23167],"type":"Point"}
}