{
  "type": "Feature",
  "properties": {
    "gn:admin1_code":"6.0",
    "gn:asciiname":"T'o-gol",
    "gn:country_code":"KP",
    "gn:dem":47,
    "gn:feature_class":"P",
    "gn:feature_code":"PPL",
    "gn:name":"T\u2019\u014f-gol",
    "gn:population":0,
    "gn:timezone":"Asia/Pyongyang",
    "iso:country":"KP",
    "name:kor_x_preferred":[
        "\ud130\uace8"
    ],
    "name:und_x_variant":[
        "T\u2019\u014f-gol"
    ],
    "wof:name":"T'o-gol",
    "wof:placetype":"locality"
},
  "geometry": {"coordinates":[125.4325,38.09833],"type":"Point"}
}