{
  "type": "Feature",
  "properties": {
    "gn:admin1_code":"17.0",
    "gn:asciiname":"Yongp'yong-ni",
    "gn:country_code":"KP",
    "gn:dem":3,
    "gn:feature_class":"P",
    "gn:feature_code":"PPLL",
    "gn:name":"Yongp\u2019y\u014fng-ni",
    "gn:population":0,
    "gn:timezone":"Asia/Pyongyang",
    "iso:country":"KP",
    "name:und_x_variant":[
        "Ry\u016dhy\u014f-d\u014f",
        "Yongp\u2019yong-do",
        "Ry\u016dhei-d\u014f",
        "Yongp\u2019y\u014fng-dong",
        "Ryuhy\u014f",
        "\ub8e1\ud3c9\ub9ac",
        "Yongp\u2019y\u014fng-ni"
    ],
    "wof:name":"Yongp'yong-ni",
    "wof:placetype":"locality"
},
  "geometry": {"coordinates":[129.7175,41.39917],"type":"Point"}
}