{
  "type": "Feature",
  "properties": {
    "gn:admin1_code":"3.0",
    "gn:asciiname":"Yonjong-ni",
    "gn:country_code":"KP",
    "gn:dem":61,
    "gn:feature_class":"P",
    "gn:feature_code":"PPL",
    "gn:name":"Y\u014fnj\u014fng-ni",
    "gn:population":0,
    "gn:timezone":"Asia/Pyongyang",
    "iso:country":"KP",
    "name:eng_x_preferred":[
        "Yonjong"
    ],
    "name:eng_x_variant":[
        "Yonjong-ni"
    ],
    "name:und_x_variant":[
        "\uc5f0\uc815\ub9ac",
        "Y\u014fnj\u014fng-ni"
    ],
    "wof:name":"Yonjong",
    "wof:placetype":"locality"
},
  "geometry": {"coordinates":[127.36861,39.83583],"type":"Point"}
}