{
  "type": "Feature",
  "properties": {
    "gn:admin1_code":"6.0",
    "gn:admin2_code":"P\u2019anmun-gun",
    "gn:asciiname":"Nu-ri",
    "gn:country_code":"KP",
    "gn:dem":11,
    "gn:feature_class":"P",
    "gn:feature_code":"PPL",
    "gn:name":"Nu-ri",
    "gn:population":0,
    "gn:timezone":"Asia/Pyongyang",
    "iso:country":"KP",
    "wof:name":"Nu-ri",
    "wof:placetype":"locality"
},
  "geometry": {"coordinates":[126.61139,37.79194],"type":"Point"}
}