{
  "type": "Feature",
  "properties": {
    "gn:admin1_code":"3.0",
    "gn:asciiname":"Majon",
    "gn:country_code":"KP",
    "gn:dem":134,
    "gn:feature_class":"P",
    "gn:feature_code":"PPL",
    "gn:name":"Maj\u014fn",
    "gn:population":0,
    "gn:timezone":"Asia/Pyongyang",
    "iso:country":"KP",
    "name:und_x_variant":[
        "\ub9c8\uc804",
        "Maj\u014fn"
    ],
    "wof:name":"Majon",
    "wof:placetype":"locality"
},
  "geometry": {"coordinates":[128.92417,40.6375],"type":"Point"}
}