{
  "type": "Feature",
  "properties": {
    "gn:admin1_code":"9.0",
    "gn:admin2_code":"Ch\u2019angdo-gun",
    "gn:asciiname":"Songgo-ri",
    "gn:country_code":"KP",
    "gn:dem":468,
    "gn:feature_class":"P",
    "gn:feature_code":"PPL",
    "gn:name":"Songg\u014f-ri",
    "gn:population":0,
    "gn:timezone":"Asia/Pyongyang",
    "iso:country":"KP",
    "wof:name":"Songgo-ri",
    "wof:placetype":"locality"
},
  "geometry": {"coordinates":[127.95860999999999,38.40639],"type":"Point"}
}