{
  "type": "Feature",
  "properties": {
    "gn:admin1_code":"11.0",
    "gn:asciiname":"Kumsong",
    "gn:country_code":"KP",
    "gn:dem":45,
    "gn:feature_class":"P",
    "gn:feature_code":"PPL",
    "gn:name":"K\u016dmsong",
    "gn:population":0,
    "gn:timezone":"Asia/Pyongyang",
    "iso:country":"KP",
    "name:kor_x_preferred":[
        "\uae08\uc1a1"
    ],
    "name:kor_x_variant":[
        "K\u016dmsong"
    ],
    "wof:name":"Kumsong",
    "wof:placetype":"locality"
},
  "geometry": {"coordinates":[125.26139000000001,39.71056],"type":"Point"}
}