{
  "type": "Feature",
  "properties": {
    "gn:admin1_code":"15.0",
    "gn:admin2_code":"Maengsan-gun",
    "gn:asciiname":"Kiun-dong",
    "gn:country_code":"KP",
    "gn:dem":291,
    "gn:feature_class":"P",
    "gn:feature_code":"PPL",
    "gn:name":"Ki\u016dn-dong",
    "gn:population":0,
    "gn:timezone":"Asia/Pyongyang",
    "iso:country":"KP",
    "wof:name":"Kiun-dong",
    "wof:placetype":"locality"
},
  "geometry": {"coordinates":[126.56444,39.78417],"type":"Point"}
}