{
  "type": "Feature",
  "properties": {
    "gn:admin1_code":"0.0",
    "gn:asciiname":"Ch'angnae-ri",
    "gn:country_code":"KP",
    "gn:dem":8,
    "gn:feature_class":"P",
    "gn:feature_code":"PPL",
    "gn:name":"Ch\u2019angnae-ri",
    "gn:population":0,
    "gn:timezone":"Asia/Pyongyang",
    "iso:country":"KP",
    "name:kor_x_preferred":[
        "\ucc3d\ub0b4\ub9ac"
    ],
    "name:und_x_variant":[
        "Ch\u2019angnae-ri"
    ],
    "wof:name":"Ch'angnae-ri",
    "wof:placetype":"locality"
},
  "geometry": {"coordinates":[126.66667,37.88333],"type":"Point"}
}