{
  "type": "Feature",
  "properties": {
    "gn:admin1_code":"12.0",
    "gn:asciiname":"Soido",
    "gn:country_code":"KP",
    "gn:dem":7,
    "gn:feature_class":"P",
    "gn:feature_code":"PPL",
    "gn:name":"Soido",
    "gn:population":0,
    "gn:timezone":"Asia/Pyongyang",
    "iso:country":"KP",
    "name:kor_x_preferred":[
        "\uc18c\uc774\ub3c4"
    ],
    "name:kor_x_variant":[
        "\uc18c\uc774\ub3c4\ub9ac"
    ],
    "name:und_x_variant":[
        "Soido-ri"
    ],
    "wof:name":"Soido",
    "wof:placetype":"locality"
},
  "geometry": {"coordinates":[125.62761999999999,38.91744],"type":"Point"}
}