{
  "type": "Feature",
  "properties": {
    "gn:admin1_code":"13.0",
    "gn:asciiname":"Ha-ch'on",
    "gn:country_code":"KP",
    "gn:dem":1121,
    "gn:feature_class":"P",
    "gn:feature_code":"PPL",
    "gn:name":"Ha-ch\u2019on",
    "gn:population":0,
    "gn:timezone":"Asia/Pyongyang",
    "iso:country":"KP",
    "name:und_x_variant":[
        "Kason",
        "Ha-ch\u2019on"
    ],
    "wof:name":"Ha-ch'on",
    "wof:placetype":"locality"
},
  "geometry": {"coordinates":[128.83638999999999,41.5725],"type":"Point"}
}