{
  "type": "Feature",
  "properties": {
    "gn:admin1_code":"3.0",
    "gn:asciiname":"Tokp'ung-dong",
    "gn:country_code":"KP",
    "gn:dem":7,
    "gn:feature_class":"P",
    "gn:feature_code":"PPL",
    "gn:name":"T\u014fkp\u2019ung-dong",
    "gn:population":0,
    "gn:timezone":"Asia/Pyongyang",
    "iso:country":"KP",
    "name:und_x_variant":[
        "P\u2019ungd\u014fng-ni",
        "T\u014fkp\u2019ung-ni",
        "T\u014fkp\u2019ung-dong"
    ],
    "wof:name":"Tokp'ung-dong",
    "wof:placetype":"locality"
},
  "geometry": {"coordinates":[127.55611,39.82944000000001],"type":"Point"}
}