{
  "type": "Feature",
  "properties": {
    "gn:admin1_code":"9.0",
    "gn:admin2_code":"P'y\u014fnggang-gun",
    "gn:asciiname":"Ch'ol-tong",
    "gn:country_code":"KP",
    "gn:dem":476,
    "gn:feature_class":"P",
    "gn:feature_code":"PPL",
    "gn:name":"Ch\u2019\u014fl-tong",
    "gn:population":0,
    "gn:timezone":"Asia/Pyongyang",
    "iso:country":"KP",
    "name:eng_x_preferred":[
        "Ch'ol"
    ],
    "name:eng_x_variant":[
        "Ch'ol-tong"
    ],
    "name:kor_x_preferred":[
        "\ucca0\ub3d9"
    ],
    "name:und_x_variant":[
        "Chuul Tong",
        "Tetsu-d\u014d",
        "Ch\u2019\u014fl-tong"
    ],
    "wof:name":"Ch'ol",
    "wof:placetype":"locality"
},
  "geometry": {"coordinates":[127.34833,38.48972],"type":"Point"}
}