{
  "type": "Feature",
  "properties": {
    "gn:admin1_code":"15.0",
    "gn:admin2_code":"P\u2019\u014fngw\u014fn-gun",
    "gn:asciiname":"Chogam-ni",
    "gn:country_code":"KP",
    "gn:dem":54,
    "gn:feature_class":"P",
    "gn:feature_code":"PPL",
    "gn:name":"Ch\u014fgam-ni",
    "gn:population":0,
    "gn:timezone":"Asia/Pyongyang",
    "iso:country":"KP",
    "wof:name":"Chogam-ni",
    "wof:placetype":"locality"
},
  "geometry": {"coordinates":[125.66417,39.28778],"type":"Point"}
}