{
  "type": "Feature",
  "properties": {
    "gn:admin1_code":"9.0",
    "gn:asciiname":"Kwangsok-tong",
    "gn:country_code":"KP",
    "gn:dem":104,
    "gn:feature_class":"P",
    "gn:feature_code":"PPL",
    "gn:name":"Kwangs\u014fk-tong",
    "gn:population":0,
    "gn:timezone":"Asia/Pyongyang",
    "iso:country":"KP",
    "name:und_x_variant":[
        "Kwangs\u014fk-tong",
        "\uad11\uc11d\ub3d9"
    ],
    "wof:name":"Kwangsok-tong",
    "wof:placetype":"locality"
},
  "geometry": {"coordinates":[127.43198999999998,39.14871],"type":"Point"}
}