{
  "type": "Feature",
  "properties": {
    "gn:admin1_code":"9.0",
    "gn:asciiname":"Tae-ri",
    "gn:country_code":"KP",
    "gn:dem":26,
    "gn:feature_class":"P",
    "gn:feature_code":"PPL",
    "gn:name":"Tae-ri",
    "gn:population":0,
    "gn:timezone":"Asia/Pyongyang",
    "iso:country":"KP",
    "wof:name":"Tae-ri",
    "wof:placetype":"locality"
},
  "geometry": {"coordinates":[127.88139,38.89278],"type":"Point"}
}