{
  "type": "Feature",
  "properties": {
    "gn:admin1_code":"6.0",
    "gn:asciiname":"Kamch'o-dong",
    "gn:country_code":"KP",
    "gn:dem":43,
    "gn:feature_class":"P",
    "gn:feature_code":"PPL",
    "gn:name":"Kamch\u2019o-dong",
    "gn:population":0,
    "gn:timezone":"Asia/Pyongyang",
    "iso:country":"KP",
    "name:kor_x_preferred":[
        "\uac10\ucd08\ub3d9"
    ],
    "name:kor_x_variant":[
        "Kamch\u2019o-dong"
    ],
    "wof:name":"Kamch'o-dong",
    "wof:placetype":"locality"
},
  "geometry": {"coordinates":[125.15222,38.29389000000001],"type":"Point"}
}