{
  "type": "Feature",
  "properties": {
    "gn:admin1_code":"13.0",
    "gn:asciiname":"Sunam",
    "gn:country_code":"KP",
    "gn:dem":1140,
    "gn:feature_class":"P",
    "gn:feature_code":"PPL",
    "gn:name":"Sunam",
    "gn:population":0,
    "gn:timezone":"Asia/Pyongyang",
    "iso:country":"KP",
    "wof:name":"Sunam",
    "wof:placetype":"locality"
},
  "geometry": {"coordinates":[128.54917,41.29028],"type":"Point"}
}