{
  "type": "Feature",
  "properties": {
    "gn:admin1_code":"13.0",
    "gn:asciiname":"Sunam",
    "gn:country_code":"KP",
    "gn:dem":1140,
    "gn:feature_class":"P",
    "gn:feature_code":"PPL",
    "gn:name":"Sunam",
    "gn:population":0,
    "gn:timezone":"Asia/Pyongyang",
    "iso:country":"KP",
    "name:ben_x_preferred":[
        "\u09b8\u09c1\u09a8\u09be\u09ae"
    ],
    "name:bpy_x_preferred":[
        "\u09b8\u09c1\u09a8\u09be\u09ae"
    ],
    "name:ceb_x_preferred":[
        "Sun\u0101m"
    ],
    "name:hin_x_preferred":[
        "\u0938\u0941\u0928\u093e\u092e"
    ],
    "name:ita_x_preferred":[
        "Sunam"
    ],
    "name:msa_x_preferred":[
        "Sunam"
    ],
    "name:nld_x_preferred":[
        "Sunam"
    ],
    "name:ori_x_preferred":[
        "\u0b38\u0b41\u0b28\u0b3e\u0b2e"
    ],
    "name:pan_x_preferred":[
        "\u0a38\u0a41\u0a28\u0a3e\u0a2e"
    ],
    "name:pnb_x_preferred":[
        "\u0633\u064f\u0646\u0627\u0645"
    ],
    "name:por_x_preferred":[
        "Sunam"
    ],
    "name:spa_x_preferred":[
        "Sunam"
    ],
    "name:swe_x_preferred":[
        "Sun\u0101m"
    ],
    "name:urd_x_preferred":[
        "\u0633\u0646\u0627\u0645"
    ],
    "name:vie_x_preferred":[
        "Sunam"
    ],
    "name:zho_x_preferred":[
        "\u82cf\u7eb3\u59c6"
    ],
    "wof:name":"Sunam",
    "wof:placetype":"locality"
},
  "geometry": {"coordinates":[128.54917,41.29028],"type":"Point"}
}