{
  "type": "Feature",
  "properties": {
    "gn:admin1_code":"17.0",
    "gn:asciiname":"Soch'on",
    "gn:country_code":"KP",
    "gn:dem":38,
    "gn:feature_class":"P",
    "gn:feature_code":"PPL",
    "gn:name":"Soch\u2019on",
    "gn:population":0,
    "gn:timezone":"Asia/Pyongyang",
    "iso:country":"KP",
    "name:und_x_variant":[
        "\uc11c\ucd0c",
        "Soch\u2019on"
    ],
    "wof:name":"Soch'on",
    "wof:placetype":"locality"
},
  "geometry": {"coordinates":[129.40388999999999,40.80806],"type":"Point"}
}