{
  "type": "Feature",
  "properties": {
    "gn:admin1_code":"6.0",
    "gn:asciiname":"Ch'osan-dong",
    "gn:country_code":"KP",
    "gn:dem":28,
    "gn:feature_class":"P",
    "gn:feature_code":"PPL",
    "gn:name":"Ch\u2019osan-dong",
    "gn:population":0,
    "gn:timezone":"Asia/Pyongyang",
    "iso:country":"KP",
    "name:kor_x_preferred":[
        "\ucd08\uc0b0\ub3d9"
    ],
    "name:und_x_variant":[
        "Ch\u2019osan-dong"
    ],
    "wof:name":"Ch'osan-dong",
    "wof:placetype":"locality"
},
  "geometry": {"coordinates":[125.435,38.43028],"type":"Point"}
}