{
  "type": "Feature",
  "properties": {
    "gn:admin1_code":"6.0",
    "gn:asciiname":"Yongho-ri",
    "gn:country_code":"KP",
    "gn:dem":67,
    "gn:feature_class":"P",
    "gn:feature_code":"PPL",
    "gn:name":"Yongho-ri",
    "gn:population":0,
    "gn:timezone":"Asia/Pyongyang",
    "iso:country":"KP",
    "name:kor_x_preferred":[
        "\uc6a9\ud638\ub9ac"
    ],
    "wof:name":"Yongho-ri",
    "wof:placetype":"locality"
},
  "geometry": {"coordinates":[125.14194000000001,38.33889],"type":"Point"}
}