{
  "type": "Feature",
  "properties": {
    "gn:admin1_code":"15.0",
    "gn:admin2_code":"P\u2019\u014fngw\u014fn-gun",
    "gn:asciiname":"Kosari-gol",
    "gn:country_code":"KP",
    "gn:dem":95,
    "gn:feature_class":"P",
    "gn:feature_code":"PPL",
    "gn:name":"Kosari-gol",
    "gn:population":0,
    "gn:timezone":"Asia/Pyongyang",
    "iso:country":"KP",
    "name:und_x_variant":[
        "Kosari-kol",
        "Kosari-gol"
    ],
    "wof:name":"Kosari-gol",
    "wof:placetype":"locality"
},
  "geometry": {"coordinates":[125.64361,39.3325],"type":"Point"}
}