{
  "type": "Feature",
  "properties": {
    "gn:admin1_code":"1.0",
    "gn:asciiname":"Yangp'o-dong",
    "gn:country_code":"KP",
    "gn:dem":306,
    "gn:feature_class":"P",
    "gn:feature_code":"PPL",
    "gn:name":"Yangp\u2019o-dong",
    "gn:population":0,
    "gn:timezone":"Asia/Pyongyang",
    "iso:country":"KP",
    "name:und_x_variant":[
        "\uc591\ud3ec\ub3d9",
        "Yangp\u2019o-dong"
    ],
    "wof:name":"Yangp'o-dong",
    "wof:placetype":"locality"
},
  "geometry": {"coordinates":[126.29277999999999,41.00167],"type":"Point"}
}