{
  "type": "Feature",
  "properties": {
    "gn:admin1_code":"6.0",
    "gn:asciiname":"Kiril-li",
    "gn:cc2":"KP",
    "gn:country_code":"KP",
    "gn:dem":25,
    "gn:feature_class":"P",
    "gn:feature_code":"PPL",
    "gn:name":"Kiril-li",
    "gn:population":0,
    "gn:timezone":"Asia/Pyongyang",
    "iso:country":"KP",
    "name:kor_x_preferred":[
        "\uae30\ub9b0\ub9ac"
    ],
    "name:und_x_variant":[
        "Kirin-ni",
        "Kiril-li"
    ],
    "wof:name":"Kiril-li",
    "wof:placetype":"locality"
},
  "geometry": {"coordinates":[126.12667,37.92056],"type":"Point"}
}