{
  "type": "Feature",
  "properties": {
    "gn:admin1_code":"15.0",
    "gn:asciiname":"Sangnam",
    "gn:country_code":"KP",
    "gn:dem":858,
    "gn:feature_class":"P",
    "gn:feature_code":"PPL",
    "gn:name":"Sangnam",
    "gn:population":0,
    "gn:timezone":"Asia/Pyongyang",
    "iso:country":"KP",
    "name:kor_x_preferred":[
        "\uc0c1\ub0a8"
    ],
    "name:und_x_variant":[
        "\uc0c1\ub0a8\ub9ac",
        "Sangnam-ni",
        "Sangnam"
    ],
    "wof:name":"Sangnam",
    "wof:placetype":"locality"
},
  "geometry": {"coordinates":[126.96229,40.27791],"type":"Point"}
}