{
  "type": "Feature",
  "properties": {
    "gn:admin1_code":"3.0",
    "gn:asciiname":"Moraeanch'i",
    "gn:country_code":"KP",
    "gn:dem":6,
    "gn:feature_class":"P",
    "gn:feature_code":"PPL",
    "gn:name":"Moraeanch\u2019i",
    "gn:population":0,
    "gn:timezone":"Asia/Pyongyang",
    "iso:country":"KP",
    "name:und_x_variant":[
        "Saanch\u2019i",
        "\ubaa8\ub798\uc548\uce58",
        "Moraeanch\u2019i"
    ],
    "wof:name":"Moraeanch'i",
    "wof:placetype":"locality"
},
  "geometry": {"coordinates":[127.52778000000001,39.325],"type":"Point"}
}