{
  "type": "Feature",
  "properties": {
    "gn:admin1_code":"17.0",
    "gn:admin2_code":"\u016cnd\u014fk-kun",
    "gn:asciiname":"Namsokkyot",
    "gn:country_code":"KP",
    "gn:dem":165,
    "gn:feature_class":"P",
    "gn:feature_code":"PPL",
    "gn:name":"Nams\u014fkky\u014ft",
    "gn:population":0,
    "gn:timezone":"Asia/Pyongyang",
    "iso:country":"KP",
    "name:und_x_variant":[
        "\ub0a8\uc11d\uacc1",
        "Nams\u014fkpang",
        "Nams\u014fkky\u014ft"
    ],
    "wof:name":"Namsokkyot",
    "wof:placetype":"locality"
},
  "geometry": {"coordinates":[130.22193999999999,42.49028],"type":"Point"}
}