{
  "type": "Feature",
  "properties": {
    "gn:admin1_code":"6.0",
    "gn:asciiname":"P'imokch'on",
    "gn:country_code":"KP",
    "gn:dem":34,
    "gn:feature_class":"P",
    "gn:feature_code":"PPL",
    "gn:name":"P\u2019imokch\u2019on",
    "gn:population":0,
    "gn:timezone":"Asia/Pyongyang",
    "iso:country":"KP",
    "name:und_x_variant":[
        "\ud53c\ubaa9\ucd0c",
        "P\u2019imokch\u2019on"
    ],
    "wof:name":"P'imokch'on",
    "wof:placetype":"locality"
},
  "geometry": {"coordinates":[125.11722,38.52889],"type":"Point"}
}