{
  "type": "Feature",
  "properties": {
    "gn:admin1_code":"6.0",
    "gn:asciiname":"Huiyogogae",
    "gn:country_code":"KP",
    "gn:dem":130,
    "gn:feature_class":"P",
    "gn:feature_code":"PPL",
    "gn:name":"H\u016diy\u014fgogae",
    "gn:population":0,
    "gn:timezone":"Asia/Pyongyang",
    "iso:country":"KP",
    "name:kor_x_preferred":[
        "\ud76c\uc5ec\uace0\uac1c"
    ],
    "name:und_x_variant":[
        "H\u016diy\u014fgogae",
        "H\u016diy\u014fkogae"
    ],
    "wof:name":"Huiyogogae",
    "wof:placetype":"locality"
},
  "geometry": {"coordinates":[126.10028,38.15389],"type":"Point"}
}