{
  "type": "Feature",
  "properties": {
    "gn:admin1_code":"1.0",
    "gn:asciiname":"Songwon",
    "gn:country_code":"KP",
    "gn:dem":329,
    "gn:feature_class":"P",
    "gn:feature_code":"PPL",
    "gn:name":"Songw\u014fn",
    "gn:population":0,
    "gn:timezone":"Asia/Pyongyang",
    "iso:country":"KP",
    "name:und_x_variant":[
        "\uc1a1\uc6d0",
        "Songw\u014fn-\u016dp",
        "Songw\u014fn"
    ],
    "wof:name":"Songwon",
    "wof:placetype":"locality"
},
  "geometry": {"coordinates":[125.87860999999999,40.3775],"type":"Point"}
}