{
  "type": "Feature",
  "properties": {
    "gn:admin1_code":"17.0",
    "gn:asciiname":"Subukch'on",
    "gn:country_code":"KP",
    "gn:dem":26,
    "gn:feature_class":"P",
    "gn:feature_code":"PPL",
    "gn:name":"Subukch\u2019on",
    "gn:population":0,
    "gn:timezone":"Asia/Pyongyang",
    "iso:country":"KP",
    "name:und_x_variant":[
        "\uc218\ubd81\ucd0c",
        "Subukch\u2019on"
    ],
    "wof:name":"Subukch'on",
    "wof:placetype":"locality"
},
  "geometry": {"coordinates":[129.18333000000001,40.72444],"type":"Point"}
}