{
  "type": "Feature",
  "properties": {
    "gn:admin1_code":"6.0",
    "gn:asciiname":"Ongjom-dong",
    "gn:country_code":"KP",
    "gn:dem":31,
    "gn:feature_class":"P",
    "gn:feature_code":"PPL",
    "gn:name":"Ongj\u014fm-dong",
    "gn:population":0,
    "gn:timezone":"Asia/Pyongyang",
    "iso:country":"KP",
    "name:kor_x_preferred":[
        "\uc639\uc810\ub3d9"
    ],
    "name:kor_x_variant":[
        "Ongj\u014fm-dong"
    ],
    "wof:name":"Ongjom-dong",
    "wof:placetype":"locality"
},
  "geometry": {"coordinates":[125.07250000000001,37.92833],"type":"Point"}
}