{
  "type": "Feature",
  "properties": {
    "gn:admin1_code":"11.0",
    "gn:asciiname":"Chinhung-dong",
    "gn:country_code":"KP",
    "gn:dem":18,
    "gn:feature_class":"P",
    "gn:feature_code":"PPL",
    "gn:name":"Chinh\u016dng-dong",
    "gn:population":0,
    "gn:timezone":"Asia/Pyongyang",
    "iso:country":"KP",
    "name:und_x_variant":[
        "\uc9c4\ud765\ub3d9",
        "Chinh\u016dng-dong"
    ],
    "wof:name":"Chinhung-dong",
    "wof:placetype":"locality"
},
  "geometry": {"coordinates":[124.42806000000002,39.92667],"type":"Point"}
}