{
  "type": "Feature",
  "properties": {
    "gn:admin1_code":"9.0",
    "gn:asciiname":"Sangnyong-gol",
    "gn:country_code":"KP",
    "gn:dem":227,
    "gn:feature_class":"P",
    "gn:feature_code":"PPL",
    "gn:name":"Sangny\u014fng-gol",
    "gn:population":0,
    "gn:timezone":"Asia/Pyongyang",
    "iso:country":"KP",
    "name:und_x_variant":[
        "\uc0c1\ub155\uace8",
        "Sangny\u014fng-gol"
    ],
    "wof:name":"Sangnyong-gol",
    "wof:placetype":"locality"
},
  "geometry": {"coordinates":[127.78194000000001,38.39028],"type":"Point"}
}