{
  "type": "Feature",
  "properties": {
    "gn:admin1_code":"15.0",
    "gn:asciiname":"Hungnyong-dong",
    "gn:country_code":"KP",
    "gn:dem":278,
    "gn:feature_class":"P",
    "gn:feature_code":"PPL",
    "gn:name":"H\u016dngnyong-dong",
    "gn:population":0,
    "gn:timezone":"Asia/Pyongyang",
    "iso:country":"KP",
    "name:kor_x_preferred":[
        "\ud765\ub8e1\ub3d9"
    ],
    "name:kor_x_variant":[
        "H\u016dngnyong-dong"
    ],
    "wof:name":"Hungnyong-dong",
    "wof:placetype":"locality"
},
  "geometry": {"coordinates":[126.31528,39.20389],"type":"Point"}
}