{
  "type": "Feature",
  "properties": {
    "gn:admin1_code":"6.0",
    "gn:asciiname":"Wolgi",
    "gn:country_code":"KP",
    "gn:dem":73,
    "gn:feature_class":"P",
    "gn:feature_code":"PPL",
    "gn:name":"W\u014flgi",
    "gn:population":0,
    "gn:timezone":"Asia/Pyongyang",
    "iso:country":"KP",
    "wof:name":"Wolgi",
    "wof:placetype":"locality"
},
  "geometry": {"coordinates":[125.99527999999999,38.04278],"type":"Point"}
}