{
  "type": "Feature",
  "properties": {
    "gn:admin1_code":"9.0",
    "gn:asciiname":"Cholchae",
    "gn:country_code":"KP",
    "gn:dem":235,
    "gn:feature_class":"P",
    "gn:feature_code":"PPL",
    "gn:name":"Ch\u014flchae",
    "gn:population":0,
    "gn:timezone":"Asia/Pyongyang",
    "iso:country":"KP",
    "name:kor_x_preferred":[
        "\uc808\uc7ac"
    ],
    "name:kor_x_variant":[
        "Ch\u014flchae"
    ],
    "wof:name":"Cholchae",
    "wof:placetype":"locality"
},
  "geometry": {"coordinates":[127.14694,39.35139],"type":"Point"}
}