{
  "type": "Feature",
  "properties": {
    "gn:admin1_code":"6.0",
    "gn:admin2_code":"Changp\u2019ung-gun",
    "gn:asciiname":"Paekch'i",
    "gn:country_code":"KP",
    "gn:dem":196,
    "gn:feature_class":"P",
    "gn:feature_code":"PPL",
    "gn:name":"Paekch\u2019i",
    "gn:population":0,
    "gn:timezone":"Asia/Pyongyang",
    "iso:country":"KP",
    "wof:name":"Paekch'i",
    "wof:placetype":"locality"
},
  "geometry": {"coordinates":[126.65611,38.13083],"type":"Point"}
}