{
  "type": "Feature",
  "properties": {
    "gn:admin1_code":"11.0",
    "gn:asciiname":"Chasong-dong",
    "gn:country_code":"KP",
    "gn:dem":13,
    "gn:feature_class":"P",
    "gn:feature_code":"PPL",
    "gn:name":"Chas\u014fng-dong",
    "gn:population":0,
    "gn:timezone":"Asia/Pyongyang",
    "iso:country":"KP",
    "name:kor_x_preferred":[
        "\uc790\uc131\ub3d9"
    ],
    "name:kor_x_variant":[
        "Chas\u014fng-dong"
    ],
    "wof:name":"Chasong-dong",
    "wof:placetype":"locality"
},
  "geometry": {"coordinates":[125.28556,39.57861],"type":"Point"}
}