{
  "type": "Feature",
  "properties": {
    "gn:admin1_code":"15.0",
    "gn:asciiname":"Maebong-ni",
    "gn:country_code":"KP",
    "gn:dem":46,
    "gn:feature_class":"P",
    "gn:feature_code":"PPL",
    "gn:name":"Maebong-ni",
    "gn:population":0,
    "gn:timezone":"Asia/Pyongyang",
    "iso:country":"KP",
    "name:kor_x_preferred":[
        "\ub9e4\ubd09\ub9ac"
    ],
    "name:und_x_variant":[
        "Ungbong-ni",
        "Maebong-ni"
    ],
    "wof:name":"Maebong-ni",
    "wof:placetype":"locality"
},
  "geometry": {"coordinates":[125.58861,39.52528],"type":"Point"}
}