{
  "type": "Feature",
  "properties": {
    "gn:admin1_code":"7.0",
    "gn:asciiname":"Kok-tong",
    "gn:country_code":"KP",
    "gn:dem":91,
    "gn:feature_class":"P",
    "gn:feature_code":"PPL",
    "gn:name":"Kok-tong",
    "gn:population":0,
    "gn:timezone":"Asia/Pyongyang",
    "iso:country":"KP",
    "name:kor_x_preferred":[
        "\uace1\ub3d9"
    ],
    "wof:name":"Kok-tong",
    "wof:placetype":"locality"
},
  "geometry": {"coordinates":[126.46611,38.56056],"type":"Point"}
}