{
  "type": "Feature",
  "properties": {
    "gn:admin1_code":"3.0",
    "gn:asciiname":"Chongch'un-gol",
    "gn:country_code":"KP",
    "gn:dem":737,
    "gn:feature_class":"P",
    "gn:feature_code":"PPL",
    "gn:name":"Ch\u014fngch\u2019un-gol",
    "gn:population":0,
    "gn:timezone":"Asia/Pyongyang",
    "iso:country":"KP",
    "name:und_x_variant":[
        "\uc815\ucd98\uace8",
        "Ch\u014fngch\u2019un-gol"
    ],
    "wof:name":"Chongch'un-gol",
    "wof:placetype":"locality"
},
  "geometry": {"coordinates":[128.39361,40.52889],"type":"Point"}
}