{
  "type": "Feature",
  "properties": {
    "gn:admin1_code":"6.0",
    "gn:asciiname":"Kumip'o",
    "gn:country_code":"KP",
    "gn:dem":9,
    "gn:feature_class":"P",
    "gn:feature_code":"PPL",
    "gn:name":"Kumip\u2019o",
    "gn:population":0,
    "gn:timezone":"Asia/Pyongyang",
    "iso:country":"KP",
    "name:kor_x_preferred":[
        "Kumip\u2019o"
    ],
    "name:kor_x_variant":[
        "\uad6c\ubbf8\ud3ec"
    ],
    "name:und_x_variant":[
        "Ky\u016bbi-ri",
        "Ky\u016bmih\u014d",
        "Kumi-ri"
    ],
    "wof:name":"Kumip'o",
    "wof:placetype":"locality"
},
  "geometry": {"coordinates":[125.00528,38.06944],"type":"Point"}
}