{
  "type": "Feature",
  "properties": {
    "gn:admin1_code":"17.0",
    "gn:asciiname":"Samjang-nodongjagu",
    "gn:country_code":"KP",
    "gn:dem":554,
    "gn:feature_class":"P",
    "gn:feature_code":"PPL",
    "gn:name":"Samjang-nodongjagu",
    "gn:population":0,
    "gn:timezone":"Asia/Pyongyang",
    "iso:country":"KP",
    "name:kor_x_preferred":[
        "\uc0bc\uc7a5\ub178\ub3d9\uc790\uad6c"
    ],
    "wof:name":"Samjang-nodongjagu",
    "wof:placetype":"locality"
},
  "geometry": {"coordinates":[129.00226999999998,42.08652],"type":"Point"}
}