{
  "type": "Feature",
  "properties": {
    "gn:admin1_code":"9.0",
    "gn:asciiname":"Kijong-ni",
    "gn:country_code":"KP",
    "gn:dem":929,
    "gn:feature_class":"P",
    "gn:feature_code":"PPL",
    "gn:name":"Kij\u014fng-ni",
    "gn:population":0,
    "gn:timezone":"Asia/Pyongyang",
    "iso:country":"KP",
    "name:und_x_variant":[
        "\uae30\uc815\ub9ac",
        "Kij\u014fng-ni"
    ],
    "wof:name":"Kijong-ni",
    "wof:placetype":"locality"
},
  "geometry": {"coordinates":[127.5975,38.84528],"type":"Point"}
}