{
  "type": "Feature",
  "properties": {
    "gn:admin1_code":"3.0",
    "gn:asciiname":"Ch'unp'yong",
    "gn:country_code":"KP",
    "gn:dem":275,
    "gn:feature_class":"P",
    "gn:feature_code":"PPL",
    "gn:name":"Ch\u2019unp\u2019y\u014fng",
    "gn:population":0,
    "gn:timezone":"Asia/Pyongyang",
    "iso:country":"KP",
    "name:und_x_variant":[
        "Ch\u2019unp\u2019y\u014fng",
        "\ucd98\ud3c9"
    ],
    "wof:name":"Ch'unp'yong",
    "wof:placetype":"locality"
},
  "geometry": {"coordinates":[128.10748999999998,40.33583],"type":"Point"}
}