{
  "type": "Feature",
  "properties": {
    "gn:admin1_code":"11.0",
    "gn:asciiname":"Taeha-dong",
    "gn:cc2":"KP",
    "gn:country_code":"KP",
    "gn:dem":120,
    "gn:feature_class":"P",
    "gn:feature_code":"PPL",
    "gn:name":"Taeha-dong",
    "gn:population":0,
    "gn:timezone":"Asia/Pyongyang",
    "iso:country":"KP",
    "name:und_x_variant":[
        "\ub300\ud558\ub3d9",
        "Taeha-ri",
        "Taeha-dong"
    ],
    "wof:name":"Taeha-dong",
    "wof:placetype":"locality"
},
  "geometry": {"coordinates":[124.84166999999999,40.0725],"type":"Point"}
}