{
  "type": "Feature",
  "properties": {
    "gn:admin1_code":"15.0",
    "gn:asciiname":"Kap'yong-ni",
    "gn:country_code":"KP",
    "gn:dem":240,
    "gn:feature_class":"P",
    "gn:feature_code":"PPL",
    "gn:name":"Kap\u2019y\u014fng-ni",
    "gn:population":0,
    "gn:timezone":"Asia/Pyongyang",
    "iso:country":"KP",
    "name:eng_x_preferred":[
        "Kap'yong"
    ],
    "name:eng_x_variant":[
        "Kap'yong-ni"
    ],
    "name:kor_x_preferred":[
        "\uac00\ud3c9\ub9ac"
    ],
    "name:kor_x_variant":[
        "Kap\u2019y\u014fng-ni"
    ],
    "wof:name":"Kap'yong",
    "wof:placetype":"locality"
},
  "geometry": {"coordinates":[126.35306,39.20028],"type":"Point"}
}