{
  "type": "Feature",
  "properties": {
    "gn:admin1_code":"9.0",
    "gn:asciiname":"Sahop'o",
    "gn:country_code":"KP",
    "gn:dem":517,
    "gn:feature_class":"P",
    "gn:feature_code":"PPL",
    "gn:name":"Sahop\u2019o",
    "gn:population":0,
    "gn:timezone":"Asia/Pyongyang",
    "iso:country":"KP",
    "name:und_x_variant":[
        "\uc0ac\ud638\ud3ec",
        "Sahop\u2019o"
    ],
    "wof:name":"Sahop'o",
    "wof:placetype":"locality"
},
  "geometry": {"coordinates":[127.76555999999999,38.84694],"type":"Point"}
}