{
  "type": "Feature",
  "properties": {
    "gn:admin1_code":"7.0",
    "gn:admin2_code":"T\u2019san-gun",
    "gn:asciiname":"Kwanmul-li",
    "gn:country_code":"KP",
    "gn:dem":125,
    "gn:feature_class":"P",
    "gn:feature_code":"PPL",
    "gn:name":"Kwanmul-li",
    "gn:population":0,
    "gn:timezone":"Asia/Pyongyang",
    "iso:country":"KP",
    "name:und_x_variant":[
        "Kwanmun-ni",
        "Kwanmul-li"
    ],
    "wof:name":"Kwanmul-li",
    "wof:placetype":"locality"
},
  "geometry": {"coordinates":[126.69750000000001,38.2475],"type":"Point"}
}