{
  "type": "Feature",
  "properties": {
    "gn:admin1_code":"7.0",
    "gn:asciiname":"Soktal-li",
    "gn:cc2":"KP",
    "gn:country_code":"KP",
    "gn:dem":235,
    "gn:feature_class":"P",
    "gn:feature_code":"PPL",
    "gn:name":"S\u014fktal-li",
    "gn:population":0,
    "gn:timezone":"Asia/Pyongyang",
    "iso:country":"KP",
    "name:kor_x_preferred":[
        "\uc11d\ub2ec\ub9ac"
    ],
    "name:kor_x_variant":[
        "S\u014fktal-li"
    ],
    "name:und_x_variant":[
        "Sekitatsu",
        "Sekitatsu-ri"
    ],
    "wof:name":"Soktal-li",
    "wof:placetype":"locality"
},
  "geometry": {"coordinates":[126.44528,38.87361],"type":"Point"}
}