{
  "type": "Feature",
  "properties": {
    "gn:admin1_code":"15.0",
    "gn:asciiname":"Yanggong-ni",
    "gn:country_code":"KP",
    "gn:dem":38,
    "gn:feature_class":"P",
    "gn:feature_code":"PPL",
    "gn:name":"Yanggong-ni",
    "gn:population":0,
    "gn:timezone":"Asia/Pyongyang",
    "iso:country":"KP",
    "name:und_x_variant":[
        "\uc591\uace1\ub9ac",
        "Yanggong-ni"
    ],
    "wof:name":"Yanggong-ni",
    "wof:placetype":"locality"
},
  "geometry": {"coordinates":[125.37639,38.84694],"type":"Point"}
}