{
  "type": "Feature",
  "properties": {
    "gn:admin1_code":"1.0",
    "gn:asciiname":"Songp'a-ri",
    "gn:country_code":"KP",
    "gn:dem":170,
    "gn:feature_class":"P",
    "gn:feature_code":"PPL",
    "gn:name":"Songp\u2019a-ri",
    "gn:population":0,
    "gn:timezone":"Asia/Pyongyang",
    "iso:country":"KP",
    "name:und_x_variant":[
        "\uc1a1\ud30c\ub9ac",
        "Songp\u2019a-ri"
    ],
    "wof:name":"Songp'a-ri",
    "wof:placetype":"locality"
},
  "geometry": {"coordinates":[125.69083000000001,40.69417],"type":"Point"}
}