{
  "type": "Feature",
  "properties": {
    "gn:admin1_code":"15.0",
    "gn:asciiname":"Sonam-ni",
    "gn:country_code":"KP",
    "gn:dem":235,
    "gn:feature_class":"P",
    "gn:feature_code":"PPL",
    "gn:name":"Sonam-ni",
    "gn:population":0,
    "gn:timezone":"Asia/Pyongyang",
    "iso:country":"KP",
    "name:kor_x_preferred":[
        "\uc18c\ub0a8\ub9ac"
    ],
    "wof:name":"Sonam-ni",
    "wof:placetype":"locality"
},
  "geometry": {"coordinates":[126.39388999999998,39.05333],"type":"Point"}
}