{
  "type": "Feature",
  "properties": {
    "gn:admin1_code":"3.0",
    "gn:asciiname":"Pansong-ni",
    "gn:country_code":"KP",
    "gn:dem":325,
    "gn:feature_class":"P",
    "gn:feature_code":"PPL",
    "gn:name":"Pans\u014fng-ni",
    "gn:population":0,
    "gn:timezone":"Asia/Pyongyang",
    "iso:country":"KP",
    "name:und_x_variant":[
        "\ubc18\uc11d\ub9ac",
        "Pans\u014fng-ni"
    ],
    "wof:name":"Pansong-ni",
    "wof:placetype":"locality"
},
  "geometry": {"coordinates":[127.7525,40.29278],"type":"Point"}
}