{
  "type": "Feature",
  "properties": {
    "gn:admin1_code":"3.0",
    "gn:asciiname":"Sungji",
    "gn:country_code":"KP",
    "gn:dem":38,
    "gn:feature_class":"P",
    "gn:feature_code":"PPL",
    "gn:name":"Sungji",
    "gn:population":0,
    "gn:timezone":"Asia/Pyongyang",
    "iso:country":"KP",
    "name:und_x_variant":[
        "\uc2b9\uc9c0"
    ],
    "wof:name":"Sungji",
    "wof:placetype":"locality"
},
  "geometry": {"coordinates":[128.26389,40.16361],"type":"Point"}
}