{
  "type": "Feature",
  "properties": {
    "gn:admin1_code":"7.0",
    "gn:asciiname":"Changul-li",
    "gn:cc2":"KP",
    "gn:country_code":"KP",
    "gn:dem":114,
    "gn:feature_class":"P",
    "gn:feature_code":"PPL",
    "gn:name":"Changul-li",
    "gn:population":0,
    "gn:timezone":"Asia/Pyongyang",
    "iso:country":"KP",
    "name:kor_x_preferred":[
        "\uc7a5\uc6b4\ub9ac"
    ],
    "name:und_x_variant":[
        "Changun-ni",
        "Changul-li"
    ],
    "wof:name":"Changul-li",
    "wof:placetype":"locality"
},
  "geometry": {"coordinates":[126.08,38.62333],"type":"Point"}
}