{
  "type": "Feature",
  "properties": {
    "gn:admin1_code":"6.0",
    "gn:admin2_code":"Changp'ung-gun",
    "gn:asciiname":"Kuhwa-ri",
    "gn:country_code":"KP",
    "gn:dem":52,
    "gn:feature_class":"P",
    "gn:feature_code":"PPL",
    "gn:name":"Kuhwa-ri",
    "gn:population":0,
    "gn:timezone":"Asia/Pyongyang",
    "iso:country":"KP",
    "name:und_x_variant":[
        "Ky\u016bka-ri",
        "Kuhwa-ri"
    ],
    "wof:name":"Kuhwa-ri",
    "wof:placetype":"locality"
},
  "geometry": {"coordinates":[126.80306000000002,38.10611],"type":"Point"}
}