{
  "type": "Feature",
  "properties": {
    "gn:admin1_code":"7.0",
    "gn:asciiname":"Saem-gol",
    "gn:country_code":"KP",
    "gn:dem":71,
    "gn:feature_class":"P",
    "gn:feature_code":"PPL",
    "gn:name":"Saem-gol",
    "gn:population":0,
    "gn:timezone":"Asia/Pyongyang",
    "iso:country":"KP",
    "wof:name":"Saem-gol",
    "wof:placetype":"locality"
},
  "geometry": {"coordinates":[125.9725,38.40556],"type":"Point"}
}