{
  "type": "Feature",
  "properties": {
    "gn:admin1_code":"7.0",
    "gn:asciiname":"Somul",
    "gn:cc2":"KP",
    "gn:country_code":"KP",
    "gn:dem":22,
    "gn:feature_class":"P",
    "gn:feature_code":"PPL",
    "gn:name":"Somul",
    "gn:population":0,
    "gn:timezone":"Asia/Pyongyang",
    "iso:country":"KP",
    "name:und_x_variant":[
        "Somol",
        "Soj\u014fng",
        "Somul"
    ],
    "wof:name":"Somul",
    "wof:placetype":"locality"
},
  "geometry": {"coordinates":[125.67055999999999,38.75639],"type":"Point"}
}