{
  "type": "Feature",
  "properties": {
    "gn:admin1_code":"6.0",
    "gn:asciiname":"Songjung-ni",
    "gn:country_code":"KP",
    "gn:dem":50,
    "gn:feature_class":"P",
    "gn:feature_code":"PPL",
    "gn:name":"Songjung-ni",
    "gn:population":0,
    "gn:timezone":"Asia/Pyongyang",
    "iso:country":"KP",
    "name:kor_x_preferred":[
        "\uc1a1\uc8fd\ub9ac"
    ],
    "wof:name":"Songjung-ni",
    "wof:placetype":"locality"
},
  "geometry": {"coordinates":[125.19889000000001,38.26583],"type":"Point"}
}