{
  "type": "Feature",
  "properties": {
    "gn:admin1_code":"7.0",
    "gn:asciiname":"Kusok-tong",
    "gn:country_code":"KP",
    "gn:dem":105,
    "gn:feature_class":"P",
    "gn:feature_code":"PPL",
    "gn:name":"Kus\u014fk-tong",
    "gn:population":0,
    "gn:timezone":"Asia/Pyongyang",
    "iso:country":"KP",
    "name:eng_x_preferred":[
        "Kusok"
    ],
    "name:eng_x_variant":[
        "Kusok-tong"
    ],
    "wof:name":"Kusok",
    "wof:placetype":"locality"
},
  "geometry": {"coordinates":[126.14833,38.21806],"type":"Point"}
}