{
  "type": "Feature",
  "properties": {
    "gn:admin1_code":"7.0",
    "gn:asciiname":"Sat'ae",
    "gn:country_code":"KP",
    "gn:dem":225,
    "gn:feature_class":"P",
    "gn:feature_code":"PPL",
    "gn:name":"Sat\u2019ae",
    "gn:population":0,
    "gn:timezone":"Asia/Pyongyang",
    "iso:country":"KP",
    "wof:name":"Sat'ae",
    "wof:placetype":"locality"
},
  "geometry": {"coordinates":[126.25861,38.55806],"type":"Point"}
}