{
  "type": "Feature",
  "properties": {
    "gn:admin1_code":"1.0",
    "gn:asciiname":"Hyongha-ri",
    "gn:country_code":"KP",
    "gn:dem":235,
    "gn:feature_class":"P",
    "gn:feature_code":"PPL",
    "gn:name":"Hy\u014fngha-ri",
    "gn:population":0,
    "gn:timezone":"Asia/Pyongyang",
    "iso:country":"KP",
    "name:und_x_variant":[
        "\ud615\ud558\ub9ac",
        "Hy\u014fngha-ri"
    ],
    "wof:name":"Hyongha-ri",
    "wof:placetype":"locality"
},
  "geometry": {"coordinates":[125.59778,40.6425],"type":"Point"}
}