{
  "type": "Feature",
  "properties": {
    "gn:admin1_code":"12.0",
    "gn:asciiname":"Sosin-dong",
    "gn:country_code":"KP",
    "gn:dem":21,
    "gn:feature_class":"P",
    "gn:feature_code":"PPL",
    "gn:name":"Sosin-dong",
    "gn:population":0,
    "gn:timezone":"Asia/Pyongyang",
    "iso:country":"KP",
    "name:und_x_variant":[
        "Sosil-li",
        "\uc18c\uc2e0\ub9ac",
        "\uc18c\uc2e0\ub3d9",
        "Sosin-dong"
    ],
    "wof:name":"Sosin-dong",
    "wof:placetype":"locality"
},
  "geometry": {"coordinates":[125.80114,38.96784],"type":"Point"}
}