{
  "type": "Feature",
  "properties": {
    "gn:admin1_code":"11.0",
    "gn:asciiname":"Yadong-gol",
    "gn:country_code":"KP",
    "gn:dem":121,
    "gn:feature_class":"P",
    "gn:feature_code":"PPL",
    "gn:name":"Yadong-gol",
    "gn:population":0,
    "gn:timezone":"Asia/Pyongyang",
    "iso:country":"KP",
    "name:und_x_variant":[
        "\uc57c\ub3d9\uace8",
        "Yadong-gol"
    ],
    "wof:name":"Yadong-gol",
    "wof:placetype":"locality"
},
  "geometry": {"coordinates":[124.79167,40.11889],"type":"Point"}
}