{
  "type": "Feature",
  "properties": {
    "gn:admin1_code":"1.0",
    "gn:asciiname":"Paktal-gol",
    "gn:country_code":"KP",
    "gn:dem":273,
    "gn:feature_class":"P",
    "gn:feature_code":"PPL",
    "gn:name":"Paktal-gol",
    "gn:population":0,
    "gn:timezone":"Asia/Pyongyang",
    "iso:country":"KP",
    "name:und_x_variant":[
        "\ubc15\ub2ec\uace8",
        "Paktal-gol"
    ],
    "wof:name":"Paktal-gol",
    "wof:placetype":"locality"
},
  "geometry": {"coordinates":[126.52249999999999,40.27778],"type":"Point"}
}