{
  "type": "Feature",
  "properties": {
    "gn:admin1_code":"17.0",
    "gn:asciiname":"Sech'ol-li",
    "gn:country_code":"KP",
    "gn:dem":213,
    "gn:feature_class":"P",
    "gn:feature_code":"PPL",
    "gn:name":"Sech\u2019\u014fl-li",
    "gn:population":0,
    "gn:timezone":"Asia/Pyongyang",
    "iso:country":"KP",
    "name:und_x_variant":[
        "Sech\u2019\u014fn-dong",
        "Sech\u2019\u014fn-ni",
        "\uc138\ucc9c\ub9ac",
        "Sech\u2019\u014fl-li"
    ],
    "wof:name":"Sech'ol-li",
    "wof:placetype":"locality"
},
  "geometry": {"coordinates":[129.14056000000002,40.8675],"type":"Point"}
}