{
  "type": "Feature",
  "properties": {
    "gn:admin1_code":"9.0",
    "gn:asciiname":"Munbau-ri",
    "gn:cc2":"KP",
    "gn:country_code":"KP",
    "gn:dem":156,
    "gn:feature_class":"P",
    "gn:feature_code":"PPL",
    "gn:name":"Munbau-ri",
    "gn:population":0,
    "gn:timezone":"Asia/Pyongyang",
    "iso:country":"KP",
    "name:und_x_variant":[
        "Bungan-ri",
        "Munam-ni",
        "Munbawi-ri",
        "Munbau-ri"
    ],
    "wof:name":"Munbau-ri",
    "wof:placetype":"locality"
},
  "geometry": {"coordinates":[126.91806,38.66778],"type":"Point"}
}