{
  "type": "Feature",
  "properties": {
    "gn:admin1_code":"3.0",
    "gn:admin2_code":"K\u016dmya-gun",
    "gn:asciiname":"Sinhung-ni",
    "gn:country_code":"KP",
    "gn:dem":20,
    "gn:feature_class":"P",
    "gn:feature_code":"PPL",
    "gn:name":"Sinh\u016dng-ni",
    "gn:population":0,
    "gn:timezone":"Asia/Pyongyang",
    "iso:country":"KP",
    "name:und_x_variant":[
        "Sinh\u016dng-ni",
        "\uc2e0\ud765\ub9ac"
    ],
    "wof:name":"Sinhung-ni",
    "wof:placetype":"locality"
},
  "geometry": {"coordinates":[127.25943999999998,39.47833],"type":"Point"}
}