{
  "type": "Feature",
  "properties": {
    "gn:admin1_code":"11.0",
    "gn:asciiname":"Songsa-ri",
    "gn:country_code":"KP",
    "gn:dem":165,
    "gn:feature_class":"P",
    "gn:feature_code":"PPL",
    "gn:name":"Songsa-ri",
    "gn:population":0,
    "gn:timezone":"Asia/Pyongyang",
    "iso:country":"KP",
    "name:und_x_variant":[
        "Songsa-dong",
        "\uc1a14\ub9ac",
        "Songsa-ri"
    ],
    "wof:name":"Songsa-ri",
    "wof:placetype":"locality"
},
  "geometry": {"coordinates":[125.31638999999998,40.57639],"type":"Point"}
}