{
  "type": "Feature",
  "properties": {
    "gn:admin1_code":"3.0",
    "gn:asciiname":"Tokko-ch'on",
    "gn:country_code":"KP",
    "gn:dem":905,
    "gn:feature_class":"P",
    "gn:feature_code":"PPL",
    "gn:name":"T\u014fkk\u014f-ch\u2019on",
    "gn:population":0,
    "gn:timezone":"Asia/Pyongyang",
    "iso:country":"KP",
    "name:und_x_variant":[
        "\ub355\uac70\ucd0c",
        "T\u014fkk\u014f-ch\u2019on"
    ],
    "wof:name":"Tokko-ch'on",
    "wof:placetype":"locality"
},
  "geometry": {"coordinates":[128.64332999999999,40.59972],"type":"Point"}
}