{
  "type": "Feature",
  "properties": {
    "gn:admin1_code":"6.0",
    "gn:asciiname":"Sin'gi",
    "gn:country_code":"KP",
    "gn:dem":58,
    "gn:feature_class":"P",
    "gn:feature_code":"PPL",
    "gn:name":"Sin\u2019gi",
    "gn:population":0,
    "gn:timezone":"Asia/Pyongyang",
    "iso:country":"KP",
    "wof:name":"Sin'gi",
    "wof:placetype":"locality"
},
  "geometry": {"coordinates":[125.64749999999999,38.35111],"type":"Point"}
}