{
  "type": "Feature",
  "properties": {
    "gn:admin1_code":"7.0",
    "gn:asciiname":"Songp'il-tong",
    "gn:country_code":"KP",
    "gn:dem":200,
    "gn:feature_class":"P",
    "gn:feature_code":"PPL",
    "gn:name":"S\u014fngp\u2019il-tong",
    "gn:population":0,
    "gn:timezone":"Asia/Pyongyang",
    "iso:country":"KP",
    "name:kor_x_preferred":[
        "\uc131\ud544\ub3d9"
    ],
    "name:kor_x_variant":[
        "S\u014fngp\u2019il-tong"
    ],
    "wof:name":"Songp'il-tong",
    "wof:placetype":"locality"
},
  "geometry": {"coordinates":[126.55417,38.62222],"type":"Point"}
}