{
  "type": "Feature",
  "properties": {
    "gn:admin1_code":"0.0",
    "gn:asciiname":"Omyonbo",
    "gn:cc2":"KP",
    "gn:country_code":"KP",
    "gn:dem":725,
    "gn:feature_class":"P",
    "gn:feature_code":"PPL",
    "gn:name":"\u014emy\u014fnbo",
    "gn:population":0,
    "gn:timezone":"Asia/Pyongyang",
    "iso:country":"KP",
    "name:kor_x_preferred":[
        "\uc5b4\uba74\ubcf4"
    ],
    "name:und_x_variant":[
        "Gyomenho",
        "\u014emy\u014fnp\u2019o",
        "Gyomenpo",
        "Gyomempo",
        "\u014emy\u014fnbo"
    ],
    "wof:name":"Omyonbo",
    "wof:placetype":"locality"
},
  "geometry": {"coordinates":[127.61667,41.26667],"type":"Point"}
}