{
  "type": "Feature",
  "properties": {
    "gn:admin1_code":"11.0",
    "gn:asciiname":"Tongmukch'am",
    "gn:country_code":"KP",
    "gn:dem":36,
    "gn:feature_class":"P",
    "gn:feature_code":"PPL",
    "gn:name":"Tongmukch\u2019am",
    "gn:population":0,
    "gn:timezone":"Asia/Pyongyang",
    "iso:country":"KP",
    "name:kor_x_preferred":[
        "\ub3d9\ubb35\ucc38"
    ],
    "name:und_x_variant":[
        "Tongmukch\u2019am"
    ],
    "wof:name":"Tongmukch'am",
    "wof:placetype":"locality"
},
  "geometry": {"coordinates":[125.79194,39.71972],"type":"Point"}
}