{
  "type": "Feature",
  "properties": {
    "gn:admin1_code":"6.0",
    "gn:asciiname":"Igi-ch'on",
    "gn:country_code":"KP",
    "gn:dem":25,
    "gn:feature_class":"P",
    "gn:feature_code":"PPL",
    "gn:name":"Igi-ch\u2019on",
    "gn:population":0,
    "gn:timezone":"Asia/Pyongyang",
    "iso:country":"KP",
    "name:kor_x_preferred":[
        "\uc774\uae30\ucd0c"
    ],
    "name:und_x_variant":[
        "Igi-ch\u2019on"
    ],
    "wof:name":"Igi-ch'on",
    "wof:placetype":"locality"
},
  "geometry": {"coordinates":[125.42083,38.47861],"type":"Point"}
}