{
  "type": "Feature",
  "properties": {
    "gn:admin1_code":"15.0",
    "gn:asciiname":"Mun-gol",
    "gn:country_code":"KP",
    "gn:dem":508,
    "gn:feature_class":"P",
    "gn:feature_code":"PPL",
    "gn:name":"Mun-gol",
    "gn:population":0,
    "gn:timezone":"Asia/Pyongyang",
    "iso:country":"KP",
    "name:kor_x_preferred":[
        "\ubb38\uace8"
    ],
    "wof:name":"Mun-gol",
    "wof:placetype":"locality"
},
  "geometry": {"coordinates":[126.685,39.46278],"type":"Point"}
}