{
  "type": "Feature",
  "properties": {
    "gn:admin1_code":"3.0",
    "gn:asciiname":"Chich'on",
    "gn:country_code":"KP",
    "gn:dem":217,
    "gn:feature_class":"P",
    "gn:feature_code":"PPL",
    "gn:name":"Chich\u2019on",
    "gn:population":0,
    "gn:timezone":"Asia/Pyongyang",
    "iso:country":"KP",
    "name:und_x_variant":[
        "\uc9c0\ucd0c",
        "Chich\u2019on"
    ],
    "wof:name":"Chich'on",
    "wof:placetype":"locality"
},
  "geometry": {"coordinates":[127.61722,40.27639],"type":"Point"}
}