{
  "type": "Feature",
  "properties": {
    "gn:admin1_code":"7.0",
    "gn:asciiname":"Ch'onggye-ri",
    "gn:country_code":"KP",
    "gn:dem":31,
    "gn:feature_class":"P",
    "gn:feature_code":"PPL",
    "gn:name":"Ch\u2019\u014fnggye-ri",
    "gn:population":0,
    "gn:timezone":"Asia/Pyongyang",
    "iso:country":"KP",
    "name:kor_x_preferred":[
        "\uccad\uacc4\ub9ac"
    ],
    "name:und_x_variant":[
        "Sekeij\u014d",
        "Changae",
        "Ch\u2019\u014fnggyejang",
        "Chongkae",
        "Chonggye-jarg",
        "Ch\u2019\u014fnggye-ri"
    ],
    "wof:name":"Ch'onggye-ri",
    "wof:placetype":"locality"
},
  "geometry": {"coordinates":[125.93832999999999,38.46139],"type":"Point"}
}