{
  "type": "Feature",
  "properties": {
    "gn:admin1_code":"12.0",
    "gn:admin2_code":"Kangdong-gun",
    "gn:asciiname":"Chu-ch'on",
    "gn:country_code":"KP",
    "gn:dem":72,
    "gn:feature_class":"P",
    "gn:feature_code":"PPL",
    "gn:name":"Chu-ch\u2019on",
    "gn:population":0,
    "gn:timezone":"Asia/Pyongyang",
    "iso:country":"KP",
    "name:kor_x_preferred":[
        "\uc8fc\ucd0c"
    ],
    "name:und_x_variant":[
        "Chu-ch\u2019on",
        "Juchon"
    ],
    "wof:name":"Chu-ch'on",
    "wof:placetype":"locality"
},
  "geometry": {"coordinates":[126.2025,39.04278],"type":"Point"}
}