{
  "type": "Feature",
  "properties": {
    "gn:admin1_code":"15.0",
    "gn:asciiname":"Kubong-ni",
    "gn:cc2":"KP",
    "gn:country_code":"KP",
    "gn:dem":22,
    "gn:feature_class":"P",
    "gn:feature_code":"PPL",
    "gn:name":"Kubong-ni",
    "gn:population":0,
    "gn:timezone":"Asia/Pyongyang",
    "iso:country":"KP",
    "name:eng_x_preferred":[
        "Kubong"
    ],
    "name:eng_x_variant":[
        "Kubong-ni"
    ],
    "name:kor_x_preferred":[
        "\uad6c\ubd09\ub9ac"
    ],
    "name:und_x_variant":[
        "Kwibong-ni",
        "Kubong-ni"
    ],
    "wof:name":"Kubong",
    "wof:placetype":"locality"
},
  "geometry": {"coordinates":[125.67361,39.66167],"type":"Point"}
}