{
  "type": "Feature",
  "properties": {
    "gn:admin1_code":"17.0",
    "gn:admin2_code":"Ch'\u014fngam-guy\u014fk, Ch'\u014fngjin-si",
    "gn:asciiname":"Ssangp'o-dong",
    "gn:country_code":"KP",
    "gn:dem":21,
    "gn:feature_class":"P",
    "gn:feature_code":"PPL",
    "gn:name":"Ssangp\u2019o-dong",
    "gn:population":0,
    "gn:timezone":"Asia/Pyongyang",
    "iso:country":"KP",
    "name:und_x_variant":[
        "S\u014fho",
        "Ssangp\u2019o",
        "Soho-d\u014f",
        "\uc30d\ud3ec\ub3d9",
        "Ssangp\u2019o-dong"
    ],
    "wof:name":"Ssangp'o-dong",
    "wof:placetype":"locality"
},
  "geometry": {"coordinates":[129.97943999999998,41.94889000000001],"type":"Point"}
}