{
  "type": "Feature",
  "properties": {
    "gn:admin1_code":"0.0",
    "gn:asciiname":"Songsa-ri",
    "gn:country_code":"KP",
    "gn:dem":26,
    "gn:feature_class":"P",
    "gn:feature_code":"PPL",
    "gn:name":"Songsa-ri",
    "gn:population":0,
    "gn:timezone":"Asia/Pyongyang",
    "iso:country":"KP",
    "name:kor_x_preferred":[
        "\uc1a1\uc0ac\ub9ac"
    ],
    "wof:name":"Songsa-ri",
    "wof:placetype":"locality"
},
  "geometry": {"coordinates":[125.60972,39.73972],"type":"Point"}
}