{
  "type": "Feature",
  "properties": {
    "gn:admin1_code":"9.0",
    "gn:admin2_code":"Munch\u2019\u014fn-si",
    "gn:asciiname":"Pomokchong-ni",
    "gn:country_code":"KP",
    "gn:dem":31,
    "gn:feature_class":"P",
    "gn:feature_code":"PPL",
    "gn:name":"Pomokch\u014fng-ni",
    "gn:population":0,
    "gn:timezone":"Asia/Pyongyang",
    "iso:country":"KP",
    "wof:name":"Pomokchong-ni",
    "wof:placetype":"locality"
},
  "geometry": {"coordinates":[127.29667000000001,39.31722],"type":"Point"}
}