{
  "type": "Feature",
  "properties": {
    "gn:admin1_code":"11.0",
    "gn:asciiname":"Kouptong Chung-dong",
    "gn:country_code":"KP",
    "gn:dem":29,
    "gn:feature_class":"P",
    "gn:feature_code":"PPL",
    "gn:name":"Ko\u016dptong Chung-dong",
    "gn:population":0,
    "gn:timezone":"Asia/Pyongyang",
    "iso:country":"KP",
    "name:kor_x_preferred":[
        "Ko\u016dptong Chung-dong"
    ],
    "name:kor_x_variant":[
        "\uace0\uc74d\ub3d9\uc911\ub3d9"
    ],
    "wof:name":"Kouptong Chung-dong",
    "wof:placetype":"locality"
},
  "geometry": {"coordinates":[124.82722,39.76528],"type":"Point"}
}