{
  "type": "Feature",
  "properties": {
    "gn:admin1_code":"0.0",
    "gn:asciiname":"Pun-dong",
    "gn:country_code":"KP",
    "gn:dem":33,
    "gn:feature_class":"P",
    "gn:feature_code":"PPL",
    "gn:name":"Pun-dong",
    "gn:population":0,
    "gn:timezone":"Asia/Pyongyang",
    "iso:country":"KP",
    "name:kor_x_preferred":[
        "\ubd84\ub3d9"
    ],
    "wof:name":"Pun-dong",
    "wof:placetype":"locality"
},
  "geometry": {"coordinates":[125.36667,38.15],"type":"Point"}
}