{
  "type": "Feature",
  "properties": {
    "gn:admin1_code":"15.0",
    "gn:asciiname":"Ch'im-dong",
    "gn:country_code":"KP",
    "gn:dem":39,
    "gn:feature_class":"P",
    "gn:feature_code":"PPL",
    "gn:name":"Ch\u2019im-dong",
    "gn:population":0,
    "gn:timezone":"Asia/Pyongyang",
    "iso:country":"KP",
    "name:und_x_variant":[
        "Ch\u014fp-tong",
        "Ky\u014fk-tong",
        "Ch\u2019im-dong"
    ],
    "wof:name":"Ch'im-dong",
    "wof:placetype":"locality"
},
  "geometry": {"coordinates":[125.36667,39.08333],"type":"Point"}
}