{
  "type": "Feature",
  "properties": {
    "gn:admin1_code":"17.0",
    "gn:asciiname":"Ungp'yong-dong",
    "gn:country_code":"KP",
    "gn:dem":889,
    "gn:feature_class":"P",
    "gn:feature_code":"PPL",
    "gn:name":"Ungp\u2019y\u014fng-dong",
    "gn:population":0,
    "gn:timezone":"Asia/Pyongyang",
    "iso:country":"KP",
    "name:kor_x_preferred":[
        "\uc6c5\ud3c9\ub3d9"
    ],
    "name:und_x_variant":[
        "Ungp\u2019y\u014fng-dong",
        "Sangsosik-tong"
    ],
    "wof:name":"Ungp'yong-dong",
    "wof:placetype":"locality"
},
  "geometry": {"coordinates":[129.24638999999999,41.215],"type":"Point"}
}