{
  "type": "Feature",
  "properties": {
    "gn:admin1_code":"15.0",
    "gn:asciiname":"Sinbae-dong",
    "gn:country_code":"KP",
    "gn:dem":110,
    "gn:feature_class":"P",
    "gn:feature_code":"PPL",
    "gn:name":"Sinbae-dong",
    "gn:population":0,
    "gn:timezone":"Asia/Pyongyang",
    "iso:country":"KP",
    "wof:name":"Sinbae-dong",
    "wof:placetype":"locality"
},
  "geometry": {"coordinates":[125.82472,39.25778],"type":"Point"}
}