{
  "type": "Feature",
  "properties": {
    "gn:admin1_code":"3.0",
    "gn:asciiname":"K'un Kanun'gae",
    "gn:country_code":"KP",
    "gn:dem":603,
    "gn:feature_class":"P",
    "gn:feature_code":"PPL",
    "gn:name":"K\u2019\u016dn Kan\u016dn\u2019gae",
    "gn:population":0,
    "gn:timezone":"Asia/Pyongyang",
    "iso:country":"KP",
    "name:und_x_variant":[
        "\ud070\uac00\ub294\uac1c",
        "K\u2019\u016dn Kan\u016dn\u2019gae"
    ],
    "wof:name":"K'un Kanun'gae",
    "wof:placetype":"locality"
},
  "geometry": {"coordinates":[126.87444000000001,39.82306],"type":"Point"}
}