{
  "type": "Feature",
  "properties": {
    "gn:admin1_code":"0.0",
    "gn:asciiname":"Haengjong-dong",
    "gn:country_code":"KP",
    "gn:dem":91,
    "gn:feature_class":"P",
    "gn:feature_code":"PPL",
    "gn:name":"Haengj\u014fng-dong",
    "gn:population":0,
    "gn:timezone":"Asia/Pyongyang",
    "iso:country":"KP",
    "name:kor_x_preferred":[
        "\ud589\uc815\ub3d9"
    ],
    "name:und_x_variant":[
        "Haengj\u014fng-dong"
    ],
    "wof:name":"Haengjong-dong",
    "wof:placetype":"locality"
},
  "geometry": {"coordinates":[125.38333,38.55],"type":"Point"}
}