{
  "type": "Feature",
  "properties": {
    "gn:admin1_code":"6.0",
    "gn:asciiname":"Sojong-ni",
    "gn:country_code":"KP",
    "gn:dem":9,
    "gn:feature_class":"P",
    "gn:feature_code":"PPL",
    "gn:name":"S\u014fj\u014fng-ni",
    "gn:population":0,
    "gn:timezone":"Asia/Pyongyang",
    "iso:country":"KP",
    "wof:name":"Sojong-ni",
    "wof:placetype":"locality"
},
  "geometry": {"coordinates":[125.55916999999999,38.38639000000001],"type":"Point"}
}