{
  "type": "Feature",
  "properties": {
    "gn:admin1_code":"11.0",
    "gn:asciiname":"Kuryong",
    "gn:country_code":"KP",
    "gn:dem":85,
    "gn:feature_class":"P",
    "gn:feature_code":"PPL",
    "gn:name":"Kuryong",
    "gn:population":0,
    "gn:timezone":"Asia/Pyongyang",
    "iso:country":"KP",
    "wof:name":"Kuryong",
    "wof:placetype":"locality"
},
  "geometry": {"coordinates":[125.89194000000001,39.84111],"type":"Point"}
}