{
  "type": "Feature",
  "properties": {
    "gn:admin1_code":"11.0",
    "gn:asciiname":"Han-dong",
    "gn:country_code":"KP",
    "gn:dem":115,
    "gn:feature_class":"P",
    "gn:feature_code":"PPL",
    "gn:name":"Han-dong",
    "gn:population":0,
    "gn:timezone":"Asia/Pyongyang",
    "iso:country":"KP",
    "name:und_x_variant":[
        "\ud55c\ub3d9",
        "Han-dong"
    ],
    "wof:name":"Han-dong",
    "wof:placetype":"locality"
},
  "geometry": {"coordinates":[125.89194000000001,40.1175],"type":"Point"}
}