{
  "type": "Feature",
  "properties": {
    "gn:admin1_code":"7.0",
    "gn:asciiname":"Kimjewol-li",
    "gn:country_code":"KP",
    "gn:dem":5,
    "gn:feature_class":"P",
    "gn:feature_code":"PPL",
    "gn:name":"Kimjew\u014fl-li",
    "gn:population":0,
    "gn:timezone":"Asia/Pyongyang",
    "iso:country":"KP",
    "name:kor_x_preferred":[
        "\uae40\uc81c\uc6d0\ub9ac"
    ],
    "name:kor_x_variant":[
        "Kimjew\u014fl-li"
    ],
    "wof:name":"Kimjewol-li",
    "wof:placetype":"locality"
},
  "geometry": {"coordinates":[125.65694000000001,38.50917000000001],"type":"Point"}
}