{
  "type": "Feature",
  "properties": {
    "gn:admin1_code":"1.0",
    "gn:asciiname":"Kumdonggu",
    "gn:country_code":"KP",
    "gn:dem":372,
    "gn:feature_class":"P",
    "gn:feature_code":"PPL",
    "gn:name":"K\u016dmdonggu",
    "gn:population":0,
    "gn:timezone":"Asia/Pyongyang",
    "iso:country":"KP",
    "name:und_x_variant":[
        "\uae08\ub3d9\uad6c",
        "K\u016dmdonggu"
    ],
    "wof:name":"Kumdonggu",
    "wof:placetype":"locality"
},
  "geometry": {"coordinates":[127.04306,41.66056],"type":"Point"}
}