{
  "type": "Feature",
  "properties": {
    "gn:admin1_code":"6.0",
    "gn:asciiname":"Cho-ch'on",
    "gn:country_code":"KP",
    "gn:dem":9,
    "gn:feature_class":"P",
    "gn:feature_code":"PPL",
    "gn:name":"Cho-ch\u2019on",
    "gn:population":0,
    "gn:timezone":"Asia/Pyongyang",
    "iso:country":"KP",
    "name:und_x_variant":[
        "\uc870\ucd0c",
        "Cho-ch\u2019on"
    ],
    "wof:name":"Cho-ch'on",
    "wof:placetype":"locality"
},
  "geometry": {"coordinates":[125.54528000000001,37.86583],"type":"Point"}
}