{
  "type": "Feature",
  "properties": {
    "gn:admin1_code":"3.0",
    "gn:asciiname":"Mandong-ni",
    "gn:country_code":"KP",
    "gn:dem":488,
    "gn:feature_class":"P",
    "gn:feature_code":"PPL",
    "gn:name":"Mand\u014fng-ni",
    "gn:population":0,
    "gn:timezone":"Asia/Pyongyang",
    "iso:country":"KP",
    "name:und_x_variant":[
        "\ub9cc\ub355\ub9ac",
        "Mand\u014fng-ni"
    ],
    "wof:name":"Mandong-ni",
    "wof:placetype":"locality"
},
  "geometry": {"coordinates":[128.58611000000002,40.65278],"type":"Point"}
}