{
  "type": "Feature",
  "properties": {
    "gn:admin1_code":"3.0",
    "gn:asciiname":"Tok-kol",
    "gn:country_code":"KP",
    "gn:dem":203,
    "gn:feature_class":"P",
    "gn:feature_code":"PPL",
    "gn:name":"Tok-kol",
    "gn:population":0,
    "gn:timezone":"Asia/Pyongyang",
    "iso:country":"KP",
    "name:und_x_variant":[
        "Tok-tong",
        "Tok-kol",
        "\ub3c5\uace8"
    ],
    "wof:name":"Tok-kol",
    "wof:placetype":"locality"
},
  "geometry": {"coordinates":[128.18274,40.33586],"type":"Point"}
}