{
  "type": "Feature",
  "properties": {
    "gn:admin1_code":"3.0",
    "gn:asciiname":"Namosokch'on",
    "gn:country_code":"KP",
    "gn:dem":83,
    "gn:feature_class":"P",
    "gn:feature_code":"PPL",
    "gn:name":"Namos\u014fkch\u2019on",
    "gn:population":0,
    "gn:timezone":"Asia/Pyongyang",
    "iso:country":"KP",
    "name:und_x_variant":[
        "\ub0a8\uc624\uc11d\ucd0c",
        "Namos\u014fkch\u2019on"
    ],
    "wof:name":"Namosokch'on",
    "wof:placetype":"locality"
},
  "geometry": {"coordinates":[128.83194,40.54],"type":"Point"}
}