{
  "type": "Feature",
  "properties": {
    "gn:admin1_code":"3.0",
    "gn:asciiname":"Songjong-ni",
    "gn:country_code":"KP",
    "gn:dem":1119,
    "gn:feature_class":"P",
    "gn:feature_code":"PPL",
    "gn:name":"Songj\u014fng-ni",
    "gn:population":0,
    "gn:timezone":"Asia/Pyongyang",
    "iso:country":"KP",
    "name:und_x_variant":[
        "\uc1a1\uc815\ub9ac",
        "Songj\u014fng-ni"
    ],
    "wof:name":"Songjong-ni",
    "wof:placetype":"locality"
},
  "geometry": {"coordinates":[127.28,40.35806],"type":"Point"}
}