{
  "type": "Feature",
  "properties": {
    "gn:admin1_code":"12.0",
    "gn:asciiname":"Chungjangji-dong",
    "gn:country_code":"KP",
    "gn:dem":21,
    "gn:feature_class":"P",
    "gn:feature_code":"PPL",
    "gn:name":"Chungjangji-dong",
    "gn:population":0,
    "gn:timezone":"Asia/Pyongyang",
    "iso:country":"KP",
    "name:und_x_variant":[
        "\uc911\uc7a5\uc9c0\ub3d9",
        "Chungjangji-dong",
        "Jungjangjidong"
    ],
    "wof:name":"Chungjangji-dong",
    "wof:placetype":"locality"
},
  "geometry": {"coordinates":[125.82971999999999,38.98806],"type":"Point"}
}