{
  "type": "Feature",
  "properties": {
    "gn:admin1_code":"0.0",
    "gn:asciiname":"Togal-li",
    "gn:country_code":"KP",
    "gn:dem":20,
    "gn:feature_class":"P",
    "gn:feature_code":"PPL",
    "gn:name":"T\u014fgal-li",
    "gn:population":0,
    "gn:timezone":"Asia/Pyongyang",
    "iso:country":"KP",
    "name:kor_x_preferred":[
        "\ub354\uac04\ub9ac"
    ],
    "name:und_x_variant":[
        "T\u014fgal-li",
        "T\u014fgan-ni"
    ],
    "wof:name":"Togal-li",
    "wof:placetype":"locality"
},
  "geometry": {"coordinates":[125.03333000000001,38.55],"type":"Point"}
}