{
  "type": "Feature",
  "properties": {
    "gn:admin1_code":"6.0",
    "gn:asciiname":"Ch'ongch'ol-li",
    "gn:country_code":"KP",
    "gn:dem":19,
    "gn:feature_class":"P",
    "gn:feature_code":"PPL",
    "gn:name":"Ch\u2019\u014fngch\u2019\u014fl-li",
    "gn:population":0,
    "gn:timezone":"Asia/Pyongyang",
    "iso:country":"KP",
    "name:kor_x_preferred":[
        "\uccad\ucd0c\ub9ac"
    ],
    "name:und_x_variant":[
        "Ch\u2019\u014fngch\u2019\u014fn-ni",
        "Ch\u2019\u014fngch\u2019\u014fl-li"
    ],
    "wof:name":"Ch'ongch'ol-li",
    "wof:placetype":"locality"
},
  "geometry": {"coordinates":[125.66472,38.33361],"type":"Point"}
}