{
  "type": "Feature",
  "properties": {
    "gn:admin1_code":"6.0",
    "gn:asciiname":"Ta-dong",
    "gn:cc2":"KP",
    "gn:country_code":"KP",
    "gn:dem":29,
    "gn:feature_class":"P",
    "gn:feature_code":"PPL",
    "gn:name":"Ta-dong",
    "gn:population":0,
    "gn:timezone":"Asia/Pyongyang",
    "iso:country":"KP",
    "name:kor_x_preferred":[
        "\ub2e4\ub3d9"
    ],
    "name:und_x_variant":[
        "To-dong",
        "Ta-dong"
    ],
    "wof:name":"Ta-dong",
    "wof:placetype":"locality"
},
  "geometry": {"coordinates":[125.39167,38.45889],"type":"Point"}
}