{
  "type": "Feature",
  "properties": {
    "gn:admin1_code":"9.0",
    "gn:asciiname":"Yondong-ni",
    "gn:country_code":"KP",
    "gn:dem":36,
    "gn:feature_class":"P",
    "gn:feature_code":"PPL",
    "gn:name":"Y\u014fndong-ni",
    "gn:population":0,
    "gn:timezone":"Asia/Pyongyang",
    "iso:country":"KP",
    "name:und_x_variant":[
        "Y\u014fndong-ni",
        "\uc5f0\ub3d9\ub9ac"
    ],
    "wof:name":"Yondong-ni",
    "wof:placetype":"locality"
},
  "geometry": {"coordinates":[127.57417,39.14361],"type":"Point"}
}