{
  "type": "Feature",
  "properties": {
    "gn:admin1_code":"13.0",
    "gn:asciiname":"Hagwangsaeng",
    "gn:country_code":"KP",
    "gn:dem":745,
    "gn:feature_class":"P",
    "gn:feature_code":"PPL",
    "gn:name":"Hagwangsaeng",
    "gn:population":0,
    "gn:timezone":"Asia/Pyongyang",
    "iso:country":"KP",
    "name:kor_x_preferred":[
        "\ud558\uad11\uc0dd"
    ],
    "wof:name":"Hagwangsaeng",
    "wof:placetype":"locality"
},
  "geometry": {"coordinates":[128.15723,41.31424000000001],"type":"Point"}
}