{
  "type": "Feature",
  "properties": {
    "gn:admin1_code":"1.0",
    "gn:asciiname":"K'ungori",
    "gn:country_code":"KP",
    "gn:dem":749,
    "gn:feature_class":"P",
    "gn:feature_code":"PPL",
    "gn:name":"K\u2019\u016dng\u014fri",
    "gn:population":0,
    "gn:timezone":"Asia/Pyongyang",
    "iso:country":"KP",
    "name:und_x_variant":[
        "\uad70\uace8",
        "Kun-gol",
        "K\u2019\u016dng\u014fri",
        "\ud070\uac70\ub9ac"
    ],
    "wof:name":"K'ungori",
    "wof:placetype":"locality"
},
  "geometry": {"coordinates":[126.28706,40.55688],"type":"Point"}
}