{
  "type": "Feature",
  "properties": {
    "gn:admin1_code":"9.0",
    "gn:asciiname":"Hup'yong",
    "gn:country_code":"KP",
    "gn:dem":292,
    "gn:feature_class":"P",
    "gn:feature_code":"PPL",
    "gn:name":"Hup\u2019y\u014fng",
    "gn:population":0,
    "gn:timezone":"Asia/Pyongyang",
    "iso:country":"KP",
    "wof:name":"Hup'yong",
    "wof:placetype":"locality"
},
  "geometry": {"coordinates":[127.85833,38.42278],"type":"Point"}
}