{
  "type": "Feature",
  "properties": {
    "gn:admin1_code":"9.0",
    "gn:asciiname":"Kahang-ni",
    "gn:country_code":"KP",
    "gn:dem":259,
    "gn:feature_class":"P",
    "gn:feature_code":"PPL",
    "gn:name":"Kahang-ni",
    "gn:population":0,
    "gn:timezone":"Asia/Pyongyang",
    "iso:country":"KP",
    "name:und_x_variant":[
        "\uac00\ud559\ub9ac",
        "Kahang-ni"
    ],
    "wof:name":"Kahang-ni",
    "wof:placetype":"locality"
},
  "geometry": {"coordinates":[127.63388999999999,38.3825],"type":"Point"}
}