{
  "type": "Feature",
  "properties": {
    "gn:admin1_code":"7.0",
    "gn:asciiname":"Kundap",
    "gn:country_code":"KP",
    "gn:dem":153,
    "gn:feature_class":"P",
    "gn:feature_code":"PPL",
    "gn:name":"K\u016dndap",
    "gn:population":0,
    "gn:timezone":"Asia/Pyongyang",
    "iso:country":"KP",
    "name:kor_x_preferred":[
        "\uadfc\ub2f5"
    ],
    "name:kor_x_variant":[
        "K\u016dndap"
    ],
    "wof:name":"Kundap",
    "wof:placetype":"locality"
},
  "geometry": {"coordinates":[126.69693999999998,38.78389],"type":"Point"}
}