{
  "type": "Feature",
  "properties": {
    "gn:admin1_code":"9.0",
    "gn:asciiname":"Podulpak-kol",
    "gn:country_code":"KP",
    "gn:dem":599,
    "gn:feature_class":"P",
    "gn:feature_code":"PPL",
    "gn:name":"P\u014fd\u016dlpak-kol",
    "gn:population":0,
    "gn:timezone":"Asia/Pyongyang",
    "iso:country":"KP",
    "name:und_x_variant":[
        "P\u014fd\u016dlpat-kol",
        "\ubc84\ub4e4\ubc2d\uace8",
        "P\u014fd\u016dlpak-kol"
    ],
    "wof:name":"Podulpak-kol",
    "wof:placetype":"locality"
},
  "geometry": {"coordinates":[127.50611000000001,38.71111],"type":"Point"}
}