{
  "type": "Feature",
  "properties": {
    "gn:admin1_code":"12.0",
    "gn:asciiname":"San'gok-ch'on",
    "gn:country_code":"KP",
    "gn:dem":24,
    "gn:feature_class":"P",
    "gn:feature_code":"PPL",
    "gn:name":"San\u2019gok-ch\u2019on",
    "gn:population":0,
    "gn:timezone":"Asia/Pyongyang",
    "iso:country":"KP",
    "name:kor_x_preferred":[
        "\uc0b0\uace1\ucd0c"
    ],
    "name:und_x_variant":[
        "San\u2019gok-ch\u2019on",
        "Sangokchon"
    ],
    "wof:name":"San'gok-ch'on",
    "wof:placetype":"locality"
},
  "geometry": {"coordinates":[125.57277999999999,38.85944],"type":"Point"}
}