{
  "type": "Feature",
  "properties": {
    "gn:admin1_code":"7.0",
    "gn:asciiname":"Nojon-dong",
    "gn:country_code":"KP",
    "gn:dem":191,
    "gn:feature_class":"P",
    "gn:feature_code":"PPL",
    "gn:name":"Noj\u014fn-dong",
    "gn:population":0,
    "gn:timezone":"Asia/Pyongyang",
    "iso:country":"KP",
    "name:kor_x_preferred":[
        "\ub178\uc804\ub3d9"
    ],
    "name:kor_x_variant":[
        "Noj\u014fn-dong"
    ],
    "wof:name":"Nojon-dong",
    "wof:placetype":"locality"
},
  "geometry": {"coordinates":[126.73111000000002,38.99306],"type":"Point"}
}