{
  "type": "Feature",
  "properties": {
    "gn:admin1_code":"9.0",
    "gn:asciiname":"Kumdong-ni",
    "gn:country_code":"KP",
    "gn:dem":187,
    "gn:feature_class":"P",
    "gn:feature_code":"PPL",
    "gn:name":"K\u016dmd\u014fng-ni",
    "gn:population":0,
    "gn:timezone":"Asia/Pyongyang",
    "iso:country":"KP",
    "name:und_x_variant":[
        "K\u016dmd\u014fng-ni",
        "\uae08\ub355\ub9ac"
    ],
    "wof:name":"Kumdong-ni",
    "wof:placetype":"locality"
},
  "geometry": {"coordinates":[127.21056000000002,39.26083],"type":"Point"}
}