{
  "type": "Feature",
  "properties": {
    "gn:admin1_code":"11.0",
    "gn:asciiname":"Pan'gong-ni",
    "gn:country_code":"KP",
    "gn:dem":19,
    "gn:feature_class":"P",
    "gn:feature_code":"PPL",
    "gn:name":"Pan\u2019gong-ni",
    "gn:population":0,
    "gn:timezone":"Asia/Pyongyang",
    "iso:country":"KP",
    "name:und_x_variant":[
        "Pan\u2019gok-tong",
        "\ubc18\uace1\ub9ac",
        "Pan\u2019gong-ni"
    ],
    "wof:name":"Pan'gong-ni",
    "wof:placetype":"locality"
},
  "geometry": {"coordinates":[124.56111,39.93333],"type":"Point"}
}