{
  "type": "Feature",
  "properties": {
    "gn:admin1_code":"11.0",
    "gn:asciiname":"Chongha-dong",
    "gn:country_code":"KP",
    "gn:dem":86,
    "gn:feature_class":"P",
    "gn:feature_code":"PPL",
    "gn:name":"Ch\u014fngha-dong",
    "gn:population":0,
    "gn:timezone":"Asia/Pyongyang",
    "iso:country":"KP",
    "name:und_x_variant":[
        "\uc815\ud558\ub3d9",
        "Ch\u014fngha-dong"
    ],
    "wof:name":"Chongha-dong",
    "wof:placetype":"locality"
},
  "geometry": {"coordinates":[124.72667,40.02944],"type":"Point"}
}