{
  "type": "Feature",
  "properties": {
    "gn:admin1_code":"6.0",
    "gn:asciiname":"Pyoktang-ni",
    "gn:country_code":"KP",
    "gn:dem":51,
    "gn:feature_class":"P",
    "gn:feature_code":"PPL",
    "gn:name":"Py\u014fktang-ni",
    "gn:population":0,
    "gn:timezone":"Asia/Pyongyang",
    "iso:country":"KP",
    "wof:name":"Pyoktang-ni",
    "wof:placetype":"locality"
},
  "geometry": {"coordinates":[126.16278,37.91694],"type":"Point"}
}