{
  "type": "Feature",
  "properties": {
    "gn:admin1_code":"1.0",
    "gn:asciiname":"Changbaeng-nodongjagu",
    "gn:country_code":"KP",
    "gn:dem":581,
    "gn:feature_class":"P",
    "gn:feature_code":"PPL",
    "gn:name":"Changbaeng-nodongjagu",
    "gn:population":0,
    "gn:timezone":"Asia/Pyongyang",
    "iso:country":"KP",
    "name:und_x_variant":[
        "Changbaek-nodongjagu",
        "\uc7a5\ubc31\ub85c\ub3d9\uc790\uad6c",
        "Changbaeng-nodongjagu"
    ],
    "wof:name":"Changbaeng-nodongjagu",
    "wof:placetype":"locality"
},
  "geometry": {"coordinates":[126.92222,41.245],"type":"Point"}
}