{
  "type": "Feature",
  "properties": {
    "gn:admin1_code":"12.0",
    "gn:admin2_code":"Kangdong-gun",
    "gn:asciiname":"Saenggol",
    "gn:country_code":"KP",
    "gn:dem":130,
    "gn:feature_class":"P",
    "gn:feature_code":"PPL",
    "gn:name":"Saenggol",
    "gn:population":0,
    "gn:timezone":"Asia/Pyongyang",
    "iso:country":"KP",
    "name:kor_x_preferred":[
        "\uc0dd\uace8"
    ],
    "wof:name":"Saenggol",
    "wof:placetype":"locality"
},
  "geometry": {"coordinates":[126.22292,39.01498],"type":"Point"}
}