{
  "type": "Feature",
  "properties": {
    "gn:admin1_code":"11.0",
    "gn:asciiname":"Changbol",
    "gn:country_code":"KP",
    "gn:dem":7,
    "gn:feature_class":"P",
    "gn:feature_code":"PPL",
    "gn:name":"Changb\u014fl",
    "gn:population":0,
    "gn:timezone":"Asia/Pyongyang",
    "iso:country":"KP",
    "name:kor_x_preferred":[
        "\uc7a5\ubc8c"
    ],
    "name:kor_x_variant":[
        "Changb\u014fl"
    ],
    "wof:name":"Changbol",
    "wof:placetype":"locality"
},
  "geometry": {"coordinates":[125.2025,39.52694],"type":"Point"}
}