{
  "type": "Feature",
  "properties": {
    "gn:admin1_code":"15.0",
    "gn:asciiname":"Taegu-gol",
    "gn:country_code":"KP",
    "gn:dem":241,
    "gn:feature_class":"P",
    "gn:feature_code":"PPL",
    "gn:name":"Taegu-gol",
    "gn:population":0,
    "gn:timezone":"Asia/Pyongyang",
    "iso:country":"KP",
    "name:und_x_variant":[
        "\ub300\uad6c\uace8",
        "Taegu-gol"
    ],
    "wof:name":"Taegu-gol",
    "wof:placetype":"locality"
},
  "geometry": {"coordinates":[126.59972,39.23389],"type":"Point"}
}