{
  "type": "Feature",
  "properties": {
    "gn:admin1_code":"0.0",
    "gn:asciiname":"Yup'o-ri",
    "gn:country_code":"KP",
    "gn:dem":14,
    "gn:feature_class":"P",
    "gn:feature_code":"PPL",
    "gn:name":"Yup\u2019o-ri",
    "gn:population":0,
    "gn:timezone":"Asia/Pyongyang",
    "iso:country":"KP",
    "name:kor_x_preferred":[
        "\uc720\ud3ec\ub9ac"
    ],
    "name:und_x_variant":[
        "Yup\u2019o-ri"
    ],
    "wof:name":"Yup'o-ri",
    "wof:placetype":"locality"
},
  "geometry": {"coordinates":[125.08333,38.55],"type":"Point"}
}