{
  "type": "Feature",
  "properties": {
    "gn:admin1_code":"15.0",
    "gn:asciiname":"Kyejip-kol",
    "gn:country_code":"KP",
    "gn:dem":350,
    "gn:feature_class":"P",
    "gn:feature_code":"PPL",
    "gn:name":"Kyejip-kol",
    "gn:population":0,
    "gn:timezone":"Asia/Pyongyang",
    "iso:country":"KP",
    "name:kor_x_preferred":[
        "\uacc4\uc9d1\uace8"
    ],
    "wof:name":"Kyejip-kol",
    "wof:placetype":"locality"
},
  "geometry": {"coordinates":[126.47028,39.10611],"type":"Point"}
}