{
  "type": "Feature",
  "properties": {
    "gn:admin1_code":"0.0",
    "gn:asciiname":"Chunghungjang",
    "gn:cc2":"KP",
    "gn:country_code":"KP",
    "gn:dem":427,
    "gn:feature_class":"P",
    "gn:feature_code":"PPL",
    "gn:name":"Chungh\u016dngjang",
    "gn:population":0,
    "gn:timezone":"Asia/Pyongyang",
    "iso:country":"KP",
    "name:kor_x_preferred":[
        "\uc911\ud765\uc7a5"
    ],
    "name:und_x_variant":[
        "Samka",
        "Chinh\u016dng-ni",
        "Ch\u016bk\u014dsh\u014d",
        "Chungh\u016dngjang"
    ],
    "wof:name":"Chunghungjang",
    "wof:placetype":"locality"
},
  "geometry": {"coordinates":[127.28333000000001,40.18333],"type":"Point"}
}