{
  "type": "Feature",
  "properties": {
    "gn:admin1_code":"7.0",
    "gn:asciiname":"Kat'omi-ri",
    "gn:country_code":"KP",
    "gn:dem":34,
    "gn:feature_class":"P",
    "gn:feature_code":"PPL",
    "gn:name":"Kat\u2019omi-ri",
    "gn:population":0,
    "gn:timezone":"Asia/Pyongyang",
    "iso:country":"KP",
    "name:und_x_variant":[
        "\uac00\ud1a0\ubbf8\ub9ac",
        "Kat\u2019omi-ri"
    ],
    "wof:name":"Kat'omi-ri",
    "wof:placetype":"locality"
},
  "geometry": {"coordinates":[126.41861000000002,38.02306],"type":"Point"}
}