{
  "type": "Feature",
  "properties": {
    "gn:admin1_code":"12.0",
    "gn:asciiname":"Chungsan-dong",
    "gn:country_code":"KP",
    "gn:dem":30,
    "gn:feature_class":"P",
    "gn:feature_code":"PPL",
    "gn:name":"Chungsan-dong",
    "gn:population":0,
    "gn:timezone":"Asia/Pyongyang",
    "iso:country":"KP",
    "name:und_x_variant":[
        "\uc911\uc0b0\ub3d9",
        "Chungsan-dong",
        "Jungsandong"
    ],
    "wof:name":"Chungsan-dong",
    "wof:placetype":"locality"
},
  "geometry": {"coordinates":[125.78082999999999,39.00111],"type":"Point"}
}