{
  "type": "Feature",
  "properties": {
    "gn:admin1_code":"1.0",
    "gn:asciiname":"Sanggandae",
    "gn:country_code":"KP",
    "gn:dem":299,
    "gn:feature_class":"P",
    "gn:feature_code":"PPL",
    "gn:name":"Sanggandae",
    "gn:population":0,
    "gn:timezone":"Asia/Pyongyang",
    "iso:country":"KP",
    "name:und_x_variant":[
        "\uc0c1\uac04\ub300",
        "Sanggandae"
    ],
    "wof:name":"Sanggandae",
    "wof:placetype":"locality"
},
  "geometry": {"coordinates":[125.90194,40.32444],"type":"Point"}
}