{
  "type": "Feature",
  "properties": {
    "gn:admin1_code":"7.0",
    "gn:asciiname":"Tangsal-li",
    "gn:cc2":"KP",
    "gn:country_code":"KP",
    "gn:dem":19,
    "gn:feature_class":"P",
    "gn:feature_code":"PPL",
    "gn:name":"Tangsal-li",
    "gn:population":0,
    "gn:timezone":"Asia/Pyongyang",
    "iso:country":"KP",
    "name:und_x_variant":[
        "Tangsan-ni",
        "Tangsal-li"
    ],
    "wof:name":"Tangsal-li",
    "wof:placetype":"locality"
},
  "geometry": {"coordinates":[125.66833,38.76583],"type":"Point"}
}