{
  "type": "Feature",
  "properties": {
    "gn:admin1_code":"6.0",
    "gn:asciiname":"Kojal-li",
    "gn:cc2":"KP",
    "gn:country_code":"KP",
    "gn:dem":7,
    "gn:feature_class":"P",
    "gn:feature_code":"PPL",
    "gn:name":"Kojal-li",
    "gn:population":0,
    "gn:timezone":"Asia/Pyongyang",
    "iso:country":"KP",
    "name:kor_x_preferred":[
        "\uace0\uc794\ub9ac"
    ],
    "name:und_x_variant":[
        "Kyojal-li",
        "Kojan-ni",
        "Kojal-li"
    ],
    "wof:name":"Kojal-li",
    "wof:placetype":"locality"
},
  "geometry": {"coordinates":[125.64888999999999,38.4575],"type":"Point"}
}