{
  "type": "Feature",
  "properties": {
    "gn:admin1_code":"6.0",
    "gn:asciiname":"Tul-mal",
    "gn:country_code":"KP",
    "gn:dem":13,
    "gn:feature_class":"P",
    "gn:feature_code":"PPL",
    "gn:name":"T\u016dl-mal",
    "gn:population":0,
    "gn:timezone":"Asia/Pyongyang",
    "iso:country":"KP",
    "name:und_x_variant":[
        "\ub4e4\ub9d0",
        "T\u016dl-mal"
    ],
    "wof:name":"Tul-mal",
    "wof:placetype":"locality"
},
  "geometry": {"coordinates":[125.60889,37.93944000000001],"type":"Point"}
}