{
  "type": "Feature",
  "properties": {
    "gn:admin1_code":"13.0",
    "gn:asciiname":"Pangnyongdogi",
    "gn:country_code":"KP",
    "gn:dem":1214,
    "gn:feature_class":"P",
    "gn:feature_code":"PPL",
    "gn:name":"Pangnyongd\u014fgi",
    "gn:population":0,
    "gn:timezone":"Asia/Pyongyang",
    "iso:country":"KP",
    "name:und_x_variant":[
        "\uc7a5\ub3d9",
        "Pangnyongd\u014fgi"
    ],
    "wof:name":"Pangnyongdogi",
    "wof:placetype":"locality"
},
  "geometry": {"coordinates":[128.16638999999998,40.66222],"type":"Point"}
}