{
  "type": "Feature",
  "properties": {
    "gn:admin1_code":"3.0",
    "gn:asciiname":"Naedong-ni",
    "gn:country_code":"KP",
    "gn:dem":22,
    "gn:feature_class":"P",
    "gn:feature_code":"PPL",
    "gn:name":"Naedong-ni",
    "gn:population":0,
    "gn:timezone":"Asia/Pyongyang",
    "iso:country":"KP",
    "name:und_x_variant":[
        "\ub0b4\ub3d9\ub9ac",
        "Naedong-ni"
    ],
    "wof:name":"Naedong-ni",
    "wof:placetype":"locality"
},
  "geometry": {"coordinates":[127.45139,39.61778],"type":"Point"}
}