{
  "type": "Feature",
  "properties": {
    "gn:admin1_code":"7.0",
    "gn:asciiname":"Sangja-dong",
    "gn:country_code":"KP",
    "gn:dem":63,
    "gn:feature_class":"P",
    "gn:feature_code":"PPL",
    "gn:name":"Sangja-dong",
    "gn:population":0,
    "gn:timezone":"Asia/Pyongyang",
    "iso:country":"KP",
    "wof:name":"Sangja-dong",
    "wof:placetype":"locality"
},
  "geometry": {"coordinates":[125.82083,38.41722],"type":"Point"}
}