{
  "type": "Feature",
  "properties": {
    "gn:admin1_code":"15.0",
    "gn:asciiname":"Namyang-ni",
    "gn:cc2":"KP",
    "gn:country_code":"KP",
    "gn:dem":200,
    "gn:feature_class":"P",
    "gn:feature_code":"PPL",
    "gn:name":"Namyang-ni",
    "gn:population":0,
    "gn:timezone":"Asia/Pyongyang",
    "iso:country":"KP",
    "name:eng_x_preferred":[
        "Namyang"
    ],
    "name:eng_x_variant":[
        "Namyang-ni"
    ],
    "name:kor_x_preferred":[
        "\ub0a8\uc591\ub9ac"
    ],
    "name:und_x_variant":[
        "Nany\u014d-ri",
        "Namyang-ni"
    ],
    "wof:name":"Namyang",
    "wof:placetype":"locality"
},
  "geometry": {"coordinates":[125.72556,39.46639],"type":"Point"}
}