{
  "type": "Feature",
  "properties": {
    "gn:admin1_code":"9.0",
    "gn:asciiname":"Sangso-ri",
    "gn:country_code":"KP",
    "gn:dem":404,
    "gn:feature_class":"P",
    "gn:feature_code":"PPL",
    "gn:name":"Sangs\u014f-ri",
    "gn:population":0,
    "gn:timezone":"Asia/Pyongyang",
    "iso:country":"KP",
    "name:kor_x_preferred":[
        "\uc0c1\uc11c\ub9ac"
    ],
    "name:kor_x_variant":[
        "Sangs\u014f-ri"
    ],
    "wof:name":"Sangso-ri",
    "wof:placetype":"locality"
},
  "geometry": {"coordinates":[127.03610999999999,39.07528],"type":"Point"}
}