{
  "type": "Feature",
  "properties": {
    "gn:admin1_code":"3.0",
    "gn:asciiname":"Yonghung-dong",
    "gn:country_code":"KP",
    "gn:dem":1217,
    "gn:feature_class":"P",
    "gn:feature_code":"PPL",
    "gn:name":"Yongh\u016dng-dong",
    "gn:population":0,
    "gn:timezone":"Asia/Pyongyang",
    "iso:country":"KP",
    "name:kor_x_preferred":[
        "Yongh\u016dng-dong"
    ],
    "name:kor_x_variant":[
        "\ub8e1\ud765\ub3d9",
        "Py\u014frang-ma\u016dl",
        "\ubcbc\ub791\ub9c8\uc744"
    ],
    "name:und_x_variant":[
        "\uc6a9\ud765\ub9ac",
        "Yongh\u016dng-ni"
    ],
    "wof:name":"Yonghung-dong",
    "wof:placetype":"locality"
},
  "geometry": {"coordinates":[127.16652000000001,40.33312],"type":"Point"}
}