{
  "type": "Feature",
  "properties": {
    "gn:admin1_code":"11.0",
    "gn:asciiname":"Tunggot-tong",
    "gn:country_code":"KP",
    "gn:dem":16,
    "gn:feature_class":"P",
    "gn:feature_code":"PPL",
    "gn:name":"T\u016dnggot-tong",
    "gn:population":0,
    "gn:timezone":"Asia/Pyongyang",
    "iso:country":"KP",
    "name:und_x_variant":[
        "Tokan-d\u014d",
        "Got",
        "T\u016bnggwan-dong",
        "\ub4f1\uacf3\ub3d9",
        "T\u016dnggot",
        "T\u016dnggot-tong"
    ],
    "wof:name":"Tunggot-tong",
    "wof:placetype":"locality"
},
  "geometry": {"coordinates":[124.56910999999999,39.72845],"type":"Point"}
}