{
  "type": "Feature",
  "properties": {
    "gn:admin1_code":"6.0",
    "gn:admin2_code":"Changp\u2019ung-gun",
    "gn:asciiname":"Kach'ol-li",
    "gn:country_code":"KP",
    "gn:dem":126,
    "gn:feature_class":"P",
    "gn:feature_code":"PPL",
    "gn:name":"Kach\u2019ol-li",
    "gn:population":0,
    "gn:timezone":"Asia/Pyongyang",
    "iso:country":"KP",
    "wof:name":"Kach'ol-li",
    "wof:placetype":"locality"
},
  "geometry": {"coordinates":[126.88527999999999,38.1425],"type":"Point"}
}