{
  "type": "Feature",
  "properties": {
    "gn:admin1_code":"7.0",
    "gn:asciiname":"Mamyong-gol",
    "gn:country_code":"KP",
    "gn:dem":70,
    "gn:feature_class":"P",
    "gn:feature_code":"PPL",
    "gn:name":"Mamy\u014fng-gol",
    "gn:population":0,
    "gn:timezone":"Asia/Pyongyang",
    "iso:country":"KP",
    "name:und_x_variant":[
        "\ub9c8\uba85\uace8",
        "Mamy\u014fng-gol"
    ],
    "wof:name":"Mamyong-gol",
    "wof:placetype":"locality"
},
  "geometry": {"coordinates":[126.51778,38.21333],"type":"Point"}
}