{
  "type": "Feature",
  "properties": {
    "gn:admin1_code":"0.0",
    "gn:asciiname":"Yonggung-ni",
    "gn:country_code":"KP",
    "gn:dem":5,
    "gn:feature_class":"P",
    "gn:feature_code":"PPL",
    "gn:name":"Yonggung-ni",
    "gn:population":0,
    "gn:timezone":"Asia/Pyongyang",
    "iso:country":"KP",
    "name:kor_x_preferred":[
        "\uc6a9\uad81\ub9ac"
    ],
    "wof:name":"Yonggung-ni",
    "wof:placetype":"locality"
},
  "geometry": {"coordinates":[125.71666999999999,38.73333],"type":"Point"}
}