{
  "type": "Feature",
  "properties": {
    "gn:admin1_code":"1.0",
    "gn:asciiname":"Kubidulgi",
    "gn:country_code":"KP",
    "gn:dem":503,
    "gn:feature_class":"P",
    "gn:feature_code":"PPL",
    "gn:name":"Kubidulgi",
    "gn:population":0,
    "gn:timezone":"Asia/Pyongyang",
    "iso:country":"KP",
    "name:und_x_variant":[
        "\uad6c\ube44\ub458\uae30",
        "Kubidulgi"
    ],
    "wof:name":"Kubidulgi",
    "wof:placetype":"locality"
},
  "geometry": {"coordinates":[126.85389000000001,41.29972],"type":"Point"}
}