{
  "type": "Feature",
  "properties": {
    "gn:admin1_code":"12.0",
    "gn:asciiname":"Hwaho-ri",
    "gn:country_code":"KP",
    "gn:dem":10,
    "gn:feature_class":"P",
    "gn:feature_code":"PPL",
    "gn:name":"Hwaho-ri",
    "gn:population":0,
    "gn:timezone":"Asia/Pyongyang",
    "iso:country":"KP",
    "name:kor_x_preferred":[
        "\ud654\ud638\ub9ac"
    ],
    "name:und_x_variant":[
        "Hwahori"
    ],
    "wof:name":"Hwaho-ri",
    "wof:placetype":"locality"
},
  "geometry": {"coordinates":[125.56278,38.82889],"type":"Point"}
}