{
  "type": "Feature",
  "properties": {
    "gn:admin1_code":"1.0",
    "gn:asciiname":"Tumul-li",
    "gn:country_code":"KP",
    "gn:dem":457,
    "gn:feature_class":"P",
    "gn:feature_code":"PPL",
    "gn:name":"Tumul-li",
    "gn:population":0,
    "gn:timezone":"Asia/Pyongyang",
    "iso:country":"KP",
    "name:kor_x_preferred":[
        "\ub450\ubb38\ub9ac"
    ],
    "name:und_x_variant":[
        "Tumun-ni",
        "\ub450\ubb38\ub9ac",
        "Tumul-li"
    ],
    "wof:name":"Tumul-li",
    "wof:placetype":"locality"
},
  "geometry": {"coordinates":[126.55674,40.58783],"type":"Point"}
}