{
  "type": "Feature",
  "properties": {
    "gn:admin1_code":"7.0",
    "gn:asciiname":"Paegam-ni",
    "gn:country_code":"KP",
    "gn:dem":149,
    "gn:feature_class":"P",
    "gn:feature_code":"PPL",
    "gn:name":"Paegam-ni",
    "gn:population":0,
    "gn:timezone":"Asia/Pyongyang",
    "iso:country":"KP",
    "name:und_x_variant":[
        "Paegam-dong",
        "\ubc31\uc554\ub9ac",
        "Paegam-ni"
    ],
    "wof:name":"Paegam-ni",
    "wof:placetype":"locality"
},
  "geometry": {"coordinates":[126.14888999999999,38.48111],"type":"Point"}
}