{
  "type": "Feature",
  "properties": {
    "gn:admin1_code":"17.0",
    "gn:asciiname":"Ijin-dong",
    "gn:country_code":"KP",
    "gn:dem":21,
    "gn:feature_class":"P",
    "gn:feature_code":"PPLL",
    "gn:name":"Ijin-dong",
    "gn:population":0,
    "gn:timezone":"Asia/Pyongyang",
    "iso:country":"KP",
    "name:kor_x_preferred":[
        "\uc774\uc9c4\ub3d9"
    ],
    "name:und_x_variant":[
        "Richind\u014f",
        "Ijil-li",
        "Rishin-do",
        "Ijin-ni",
        "Rishin",
        "Ijin-dong",
        "\ub9ac\uc9c4\ub3d9"
    ],
    "wof:name":"Ijin-dong",
    "wof:placetype":"locality"
},
  "geometry": {"coordinates":[130.13611,42.08667],"type":"Point"}
}