{
  "type": "Feature",
  "properties": {
    "gn:admin1_code":"15.0",
    "gn:asciiname":"Taech'on",
    "gn:country_code":"KP",
    "gn:dem":199,
    "gn:feature_class":"P",
    "gn:feature_code":"PPL",
    "gn:name":"Taech\u2019on",
    "gn:population":0,
    "gn:timezone":"Asia/Pyongyang",
    "iso:country":"KP",
    "name:kor_x_preferred":[
        "\ub300\ucd0c"
    ],
    "name:kor_x_variant":[
        "Taech\u2019on"
    ],
    "wof:name":"Taech'on",
    "wof:placetype":"locality"
},
  "geometry": {"coordinates":[126.41889,39.05444],"type":"Point"}
}