{
  "type": "Feature",
  "properties": {
    "gn:admin1_code":"9.0",
    "gn:asciiname":"Chigap-tong",
    "gn:country_code":"KP",
    "gn:dem":492,
    "gn:feature_class":"P",
    "gn:feature_code":"PPL",
    "gn:name":"Chigap-tong",
    "gn:population":0,
    "gn:timezone":"Asia/Pyongyang",
    "iso:country":"KP",
    "wof:name":"Chigap-tong",
    "wof:placetype":"locality"
},
  "geometry": {"coordinates":[128.04499999999999,38.48889000000001],"type":"Point"}
}