{
  "type": "Feature",
  "properties": {
    "gn:admin1_code":"11.0",
    "gn:asciiname":"Tangjo-ri",
    "gn:country_code":"KP",
    "gn:dem":48,
    "gn:feature_class":"P",
    "gn:feature_code":"PPL",
    "gn:name":"Tangj\u014f-ri",
    "gn:population":0,
    "gn:timezone":"Asia/Pyongyang",
    "iso:country":"KP",
    "name:kor_x_preferred":[
        "\ub2f9\uc800\ub9ac"
    ],
    "name:und_x_variant":[
        "Tangj\u014f-ri"
    ],
    "wof:name":"Tangjo-ri",
    "wof:placetype":"locality"
},
  "geometry": {"coordinates":[125.48333,39.91667],"type":"Point"}
}