{
  "type": "Feature",
  "properties": {
    "gn:admin1_code":"6.0",
    "gn:asciiname":"Yangji-dong",
    "gn:country_code":"KP",
    "gn:dem":23,
    "gn:feature_class":"P",
    "gn:feature_code":"PPL",
    "gn:name":"Yangji-dong",
    "gn:population":0,
    "gn:timezone":"Asia/Pyongyang",
    "iso:country":"KP",
    "name:und_x_variant":[
        "\uc591\uc9c0\ub3d9",
        "Yangji-dong"
    ],
    "wof:name":"Yangji-dong",
    "wof:placetype":"locality"
},
  "geometry": {"coordinates":[125.13861,37.92444],"type":"Point"}
}