{
  "type": "Feature",
  "properties": {
    "gn:admin1_code":"7.0",
    "gn:asciiname":"Twira-dong",
    "gn:country_code":"KP",
    "gn:dem":82,
    "gn:feature_class":"P",
    "gn:feature_code":"PPL",
    "gn:name":"Twira-dong",
    "gn:population":0,
    "gn:timezone":"Asia/Pyongyang",
    "iso:country":"KP",
    "wof:name":"Twira-dong",
    "wof:placetype":"locality"
},
  "geometry": {"coordinates":[125.89639,38.42639000000001],"type":"Point"}
}