{
  "type": "Feature",
  "properties": {
    "gn:admin1_code":"7.0",
    "gn:asciiname":"Samnyong-ni",
    "gn:country_code":"KP",
    "gn:dem":50,
    "gn:feature_class":"P",
    "gn:feature_code":"PPL",
    "gn:name":"Samnyong-ni",
    "gn:population":0,
    "gn:timezone":"Asia/Pyongyang",
    "iso:country":"KP",
    "name:kor_x_preferred":[
        "\uc0bc\ub8e1\ub9ac"
    ],
    "wof:name":"Samnyong-ni",
    "wof:placetype":"locality"
},
  "geometry": {"coordinates":[126.39361,38.30861],"type":"Point"}
}