{
  "type": "Feature",
  "properties": {
    "gn:admin1_code":"11.0",
    "gn:asciiname":"Kojang-gol",
    "gn:country_code":"KP",
    "gn:dem":74,
    "gn:feature_class":"P",
    "gn:feature_code":"PPL",
    "gn:name":"Kojang-gol",
    "gn:population":0,
    "gn:timezone":"Asia/Pyongyang",
    "iso:country":"KP",
    "name:und_x_variant":[
        "\uace0\uc7a5\uace8",
        "Kojang-gol"
    ],
    "wof:name":"Kojang-gol",
    "wof:placetype":"locality"
},
  "geometry": {"coordinates":[124.57917,40.14417],"type":"Point"}
}