{
  "type": "Feature",
  "properties": {
    "gn:admin1_code":"17.0",
    "gn:asciiname":"Undok-tong",
    "gn:country_code":"KP",
    "gn:dem":126,
    "gn:feature_class":"P",
    "gn:feature_code":"PPL",
    "gn:name":"\u016cnd\u014fk-tong",
    "gn:population":0,
    "gn:timezone":"Asia/Pyongyang",
    "iso:country":"KP",
    "name:eng_x_preferred":[
        "Undok"
    ],
    "name:eng_x_variant":[
        "Undok-tong"
    ],
    "wof:name":"Undok",
    "wof:placetype":"locality"
},
  "geometry": {"coordinates":[129.64167,41.70778],"type":"Point"}
}