{
  "type": "Feature",
  "properties": {
    "gn:admin1_code":"6.0",
    "gn:asciiname":"Kan-ch'on",
    "gn:country_code":"KP",
    "gn:dem":18,
    "gn:feature_class":"P",
    "gn:feature_code":"PPL",
    "gn:name":"Kan-ch\u2019on",
    "gn:population":0,
    "gn:timezone":"Asia/Pyongyang",
    "iso:country":"KP",
    "name:kor_x_preferred":[
        "\uac04\ucd0c"
    ],
    "name:und_x_variant":[
        "Kan-ch\u2019on"
    ],
    "wof:name":"Kan-ch'on",
    "wof:placetype":"locality"
},
  "geometry": {"coordinates":[125.13833,38.65306],"type":"Point"}
}