{
  "type": "Feature",
  "properties": {
    "gn:admin1_code":"11.0",
    "gn:asciiname":"Tongch'ang",
    "gn:country_code":"KP",
    "gn:dem":81,
    "gn:feature_class":"P",
    "gn:feature_code":"PPL",
    "gn:name":"Tongch\u2019ang",
    "gn:population":0,
    "gn:timezone":"Asia/Pyongyang",
    "iso:country":"KP",
    "wof:name":"Tongch'ang",
    "wof:placetype":"locality"
},
  "geometry": {"coordinates":[125.34083,39.98417],"type":"Point"}
}