{
  "type": "Feature",
  "properties": {
    "gn:admin1_code":"17.0",
    "gn:asciiname":"Saebat'mok",
    "gn:country_code":"KP",
    "gn:dem":563,
    "gn:feature_class":"P",
    "gn:feature_code":"PPL",
    "gn:name":"Saebat\u2019mok",
    "gn:population":0,
    "gn:timezone":"Asia/Pyongyang",
    "iso:country":"KP",
    "name:und_x_variant":[
        "Saebanmok",
        "Saebat\u2019mok"
    ],
    "wof:name":"Saebat'mok",
    "wof:placetype":"locality"
},
  "geometry": {"coordinates":[129.68333000000001,40.91667],"type":"Point"}
}