{
  "type": "Feature",
  "properties": {
    "gn:admin1_code":"15.0",
    "gn:asciiname":"Umdal-mal",
    "gn:country_code":"KP",
    "gn:dem":230,
    "gn:feature_class":"P",
    "gn:feature_code":"PPL",
    "gn:name":"\u016cmdal-mal",
    "gn:population":0,
    "gn:timezone":"Asia/Pyongyang",
    "iso:country":"KP",
    "name:kor_x_preferred":[
        "\uc74c\ub2ec\ub9d0"
    ],
    "name:und_x_variant":[
        "\u016cmdal-mal",
        "Umdal-mal"
    ],
    "wof:name":"Umdal-mal",
    "wof:placetype":"locality"
},
  "geometry": {"coordinates":[126.44861000000002,39.72167],"type":"Point"}
}