{
  "type": "Feature",
  "properties": {
    "gn:admin1_code":"7.0",
    "gn:asciiname":"Haeyoul",
    "gn:country_code":"KP",
    "gn:dem":85,
    "gn:feature_class":"P",
    "gn:feature_code":"PPL",
    "gn:name":"Haey\u014ful",
    "gn:population":0,
    "gn:timezone":"Asia/Pyongyang",
    "iso:country":"KP",
    "name:kor_x_preferred":[
        "\ud574\uc5ec\uc6b8"
    ],
    "name:kor_x_variant":[
        "Haey\u014ful"
    ],
    "wof:name":"Haeyoul",
    "wof:placetype":"locality"
},
  "geometry": {"coordinates":[126.50861,38.48222],"type":"Point"}
}