{
  "type": "Feature",
  "properties": {
    "gn:admin1_code":"3.0",
    "gn:asciiname":"Chongdal-gol",
    "gn:country_code":"KP",
    "gn:dem":475,
    "gn:feature_class":"P",
    "gn:feature_code":"PPL",
    "gn:name":"Chongdal-gol",
    "gn:population":0,
    "gn:timezone":"Asia/Pyongyang",
    "iso:country":"KP",
    "name:kor_x_preferred":[
        "\uc885\ub2ec\uace8"
    ],
    "name:und_x_variant":[
        "Chongdal-kol",
        "Chongdal-gol"
    ],
    "wof:name":"Chongdal-gol",
    "wof:placetype":"locality"
},
  "geometry": {"coordinates":[127.11722,39.61361],"type":"Point"}
}