{
  "type": "Feature",
  "properties": {
    "gn:admin1_code":"6.0",
    "gn:admin2_code":"Kaep'ung-gun",
    "gn:asciiname":"Kunul-li",
    "gn:country_code":"KP",
    "gn:dem":18,
    "gn:feature_class":"P",
    "gn:feature_code":"PPL",
    "gn:name":"Kun\u016dl-li",
    "gn:population":0,
    "gn:timezone":"Asia/Pyongyang",
    "iso:country":"KP",
    "name:und_x_variant":[
        "Kun\u016dn-ni",
        "Ku\u016dn-ni",
        "Kun\u016dl-li"
    ],
    "wof:name":"Kunul-li",
    "wof:placetype":"locality"
},
  "geometry": {"coordinates":[126.42055999999999,37.91333],"type":"Point"}
}