{
  "type": "Feature",
  "properties": {
    "gn:admin1_code":"3.0",
    "gn:asciiname":"Pomja-ri",
    "gn:country_code":"KP",
    "gn:dem":25,
    "gn:feature_class":"P",
    "gn:feature_code":"PPL",
    "gn:name":"P\u014fmja-ri",
    "gn:population":0,
    "gn:timezone":"Asia/Pyongyang",
    "iso:country":"KP",
    "name:und_x_variant":[
        "\ubc94\uc790\ub9ac",
        "P\u014fmja-ri"
    ],
    "wof:name":"Pomja-ri",
    "wof:placetype":"locality"
},
  "geometry": {"coordinates":[127.77500000000001,39.88667],"type":"Point"}
}