{
  "type": "Feature",
  "properties": {
    "gn:admin1_code":"7.0",
    "gn:asciiname":"Sunyong-dong",
    "gn:country_code":"KP",
    "gn:dem":49,
    "gn:feature_class":"P",
    "gn:feature_code":"PPL",
    "gn:name":"Suny\u014fng-dong",
    "gn:population":0,
    "gn:timezone":"Asia/Pyongyang",
    "iso:country":"KP",
    "wof:name":"Sunyong-dong",
    "wof:placetype":"locality"
},
  "geometry": {"coordinates":[125.88361,38.48222],"type":"Point"}
}