{
  "type": "Feature",
  "properties": {
    "gn:admin1_code":"12.0",
    "gn:asciiname":"Ryokp'o-dong",
    "gn:country_code":"KP",
    "gn:dem":20,
    "gn:feature_class":"P",
    "gn:feature_code":"PPL",
    "gn:name":"Ry\u014fkp\u2019o-dong",
    "gn:population":0,
    "gn:timezone":"Asia/Pyongyang",
    "iso:country":"KP",
    "name:kor_x_preferred":[
        "\uc5ed\ud3ec\ub3d9"
    ],
    "name:und_x_variant":[
        "Rikiho",
        "Y\u014fkp\u2019o-ri",
        "Y\u014fkp\u2019o",
        "\ub825\ud3ec\ub3d9",
        "Y\u014fkp\u2019o-dong",
        "Ry\u014fkp\u2019o-dong",
        "Yeokpodong"
    ],
    "wof:name":"Ryokp'o-dong",
    "wof:placetype":"locality"
},
  "geometry": {"coordinates":[125.77912000000001,38.91842000000001],"type":"Point"}
}