{
  "type": "Feature",
  "properties": {
    "gn:admin1_code":"6.0",
    "gn:asciiname":"Sogogae",
    "gn:country_code":"KP",
    "gn:dem":63,
    "gn:feature_class":"P",
    "gn:feature_code":"PPL",
    "gn:name":"Sogogae",
    "gn:population":0,
    "gn:timezone":"Asia/Pyongyang",
    "iso:country":"KP",
    "wof:name":"Sogogae",
    "wof:placetype":"locality"
},
  "geometry": {"coordinates":[126.00194,38.01056],"type":"Point"}
}