{
  "type": "Feature",
  "properties": {
    "gn:admin1_code":"13.0",
    "gn:asciiname":"Sodu-ri",
    "gn:country_code":"KP",
    "gn:dem":1265,
    "gn:feature_class":"P",
    "gn:feature_code":"PPL",
    "gn:name":"S\u014fdu-ri",
    "gn:population":0,
    "gn:timezone":"Asia/Pyongyang",
    "iso:country":"KP",
    "name:und_x_variant":[
        "Nany\u014d-d\u014d",
        "Sodu",
        "Namyang-dong",
        "S\u014fdu-ri",
        "\uc11c\ub450\ub9ac"
    ],
    "wof:name":"Sodu-ri",
    "wof:placetype":"locality"
},
  "geometry": {"coordinates":[128.84259,41.44563],"type":"Point"}
}