{
  "type": "Feature",
  "properties": {
    "gn:admin1_code":"17.0",
    "gn:asciiname":"Namdongch'on",
    "gn:country_code":"KP",
    "gn:dem":8,
    "gn:feature_class":"P",
    "gn:feature_code":"PPL",
    "gn:name":"Namdongch\u2019on",
    "gn:population":0,
    "gn:timezone":"Asia/Pyongyang",
    "iso:country":"KP",
    "name:und_x_variant":[
        "Nant\u014dson",
        "Namkangouk",
        "\ub0a8\ub3d9\ucd0c",
        "Namdongch\u2019on"
    ],
    "wof:name":"Namdongch'on",
    "wof:placetype":"locality"
},
  "geometry": {"coordinates":[129.74111000000002,41.73333],"type":"Point"}
}