{
  "type": "Feature",
  "properties": {
    "gn:admin1_code":"13.0",
    "gn:asciiname":"Yongsong-gol",
    "gn:country_code":"KP",
    "gn:dem":918,
    "gn:feature_class":"P",
    "gn:feature_code":"PPL",
    "gn:name":"Y\u014fngs\u014fng-gol",
    "gn:population":0,
    "gn:timezone":"Asia/Pyongyang",
    "iso:country":"KP",
    "name:und_x_variant":[
        "\uadc0\ub77d\ub9ac",
        "Y\u014fngs\u014fng-gol"
    ],
    "wof:name":"Yongsong-gol",
    "wof:placetype":"locality"
},
  "geometry": {"coordinates":[128.30027999999999,40.90222],"type":"Point"}
}