{
  "type": "Feature",
  "properties": {
    "gn:admin1_code":"9.0",
    "gn:asciiname":"Kojingmong-ni",
    "gn:country_code":"KP",
    "gn:dem":291,
    "gn:feature_class":"P",
    "gn:feature_code":"PPL",
    "gn:name":"Kojingmong-ni",
    "gn:population":0,
    "gn:timezone":"Asia/Pyongyang",
    "iso:country":"KP",
    "name:eng_x_preferred":[
        "Kojingmong"
    ],
    "name:eng_x_variant":[
        "Kojingmong-ni"
    ],
    "name:und_x_variant":[
        "\uace0\uc9c1\ubaa9\ub9ac",
        "Kojingmong-ni"
    ],
    "wof:name":"Kojingmong",
    "wof:placetype":"locality"
},
  "geometry": {"coordinates":[127.63,38.42111],"type":"Point"}
}