{
  "type": "Feature",
  "properties": {
    "gn:admin1_code":"15.0",
    "gn:asciiname":"Sangp'al-li",
    "gn:country_code":"KP",
    "gn:dem":8,
    "gn:feature_class":"P",
    "gn:feature_code":"PPL",
    "gn:name":"Sangp\u2019al-li",
    "gn:population":0,
    "gn:timezone":"Asia/Pyongyang",
    "iso:country":"KP",
    "name:kor_x_preferred":[
        "\uc0c1\ud314\ub9ac"
    ],
    "name:kor_x_variant":[
        "Sangp\u2019al-li"
    ],
    "wof:name":"Sangp'al-li",
    "wof:placetype":"locality"
},
  "geometry": {"coordinates":[125.55889000000001,39.57306],"type":"Point"}
}