{
  "type": "Feature",
  "properties": {
    "gn:admin1_code":"1.0",
    "gn:asciiname":"Changt'o-dong",
    "gn:country_code":"KP",
    "gn:dem":410,
    "gn:feature_class":"P",
    "gn:feature_code":"PPL",
    "gn:name":"Changt\u2019o-dong",
    "gn:population":0,
    "gn:timezone":"Asia/Pyongyang",
    "iso:country":"KP",
    "name:und_x_variant":[
        "\uc7a5\ud1a0\ub3d9",
        "Changt\u2019o-dong"
    ],
    "wof:name":"Changt'o-dong",
    "wof:placetype":"locality"
},
  "geometry": {"coordinates":[126.36696999999999,40.94085],"type":"Point"}
}