{
  "type": "Feature",
  "properties": {
    "gn:admin1_code":"3.0",
    "gn:asciiname":"Sukkama-gol",
    "gn:country_code":"KP",
    "gn:dem":1121,
    "gn:feature_class":"P",
    "gn:feature_code":"PPL",
    "gn:name":"Sukkama-gol",
    "gn:population":0,
    "gn:timezone":"Asia/Pyongyang",
    "iso:country":"KP",
    "name:und_x_variant":[
        "Sukkama-kol",
        "\uc22f\uac00\ub9c8\uace8",
        "Sutkama-gol",
        "Sukkama-gol"
    ],
    "wof:name":"Sukkama-gol",
    "wof:placetype":"locality"
},
  "geometry": {"coordinates":[128.76639,40.7975],"type":"Point"}
}