{
  "type": "Feature",
  "properties": {
    "gn:admin1_code":"3.0",
    "gn:asciiname":"Taehung-dong",
    "gn:country_code":"KP",
    "gn:dem":27,
    "gn:feature_class":"P",
    "gn:feature_code":"PPL",
    "gn:name":"Taeh\u016dng-dong",
    "gn:population":0,
    "gn:timezone":"Asia/Pyongyang",
    "iso:country":"KP",
    "name:und_x_variant":[
        "\ub300\ud765\ub3d9",
        "Taeh\u016dng-dong"
    ],
    "wof:name":"Taehung-dong",
    "wof:placetype":"locality"
},
  "geometry": {"coordinates":[127.59278,39.905],"type":"Point"}
}