{
  "type": "Feature",
  "properties": {
    "gn:admin1_code":"7.0",
    "gn:asciiname":"Chaebong-dong",
    "gn:country_code":"KP",
    "gn:dem":127,
    "gn:feature_class":"P",
    "gn:feature_code":"PPL",
    "gn:name":"Chaebong-dong",
    "gn:population":0,
    "gn:timezone":"Asia/Pyongyang",
    "iso:country":"KP",
    "wof:name":"Chaebong-dong",
    "wof:placetype":"locality"
},
  "geometry": {"coordinates":[126.73417000000001,38.36528],"type":"Point"}
}