{
  "type": "Feature",
  "properties": {
    "gn:admin1_code":"6.0",
    "gn:asciiname":"Sanch'on",
    "gn:country_code":"KP",
    "gn:dem":151,
    "gn:feature_class":"P",
    "gn:feature_code":"PPL",
    "gn:name":"Sanch\u2019on",
    "gn:population":0,
    "gn:timezone":"Asia/Pyongyang",
    "iso:country":"KP",
    "name:kor_x_preferred":[
        "\uc0b0\ucd0c"
    ],
    "name:und_x_variant":[
        "Sanch\u2019on"
    ],
    "wof:name":"Sanch'on",
    "wof:placetype":"locality"
},
  "geometry": {"coordinates":[125.46056000000002,38.20972],"type":"Point"}
}