{
  "type": "Feature",
  "properties": {
    "gn:admin1_code":"1.0",
    "gn:asciiname":"Samga-dong",
    "gn:country_code":"KP",
    "gn:dem":621,
    "gn:feature_class":"P",
    "gn:feature_code":"PPL",
    "gn:name":"Samga-dong",
    "gn:population":0,
    "gn:timezone":"Asia/Pyongyang",
    "iso:country":"KP",
    "name:und_x_variant":[
        "\uc0bc\uac00\ub3d9",
        "Samga-dong"
    ],
    "wof:name":"Samga-dong",
    "wof:placetype":"locality"
},
  "geometry": {"coordinates":[126.57861,41.11472],"type":"Point"}
}