{
  "type": "Feature",
  "properties": {
    "gn:admin1_code":"11.0",
    "gn:asciiname":"In-gol",
    "gn:country_code":"KP",
    "gn:dem":28,
    "gn:feature_class":"P",
    "gn:feature_code":"PPL",
    "gn:name":"In-gol",
    "gn:population":0,
    "gn:timezone":"Asia/Pyongyang",
    "iso:country":"KP",
    "name:und_x_variant":[
        "\uc778\uace8",
        "In-gol"
    ],
    "wof:name":"In-gol",
    "wof:placetype":"locality"
},
  "geometry": {"coordinates":[124.61694,40.06528],"type":"Point"}
}