{
  "type": "Feature",
  "properties": {
    "gn:admin1_code":"7.0",
    "gn:asciiname":"Ihwa-dong",
    "gn:country_code":"KP",
    "gn:dem":330,
    "gn:feature_class":"P",
    "gn:feature_code":"PPL",
    "gn:name":"Ihwa-dong",
    "gn:population":0,
    "gn:timezone":"Asia/Pyongyang",
    "iso:country":"KP",
    "name:kor_x_preferred":[
        "\uc774\ud654\ub3d9"
    ],
    "name:sco_x_preferred":[
        "Ihwa-dong"
    ],
    "wof:name":"Ihwa-dong",
    "wof:placetype":"locality"
},
  "geometry": {"coordinates":[126.31222,38.53889],"type":"Point"}
}