{
  "type": "Feature",
  "properties": {
    "gn:admin1_code":"13.0",
    "gn:asciiname":"Insal-li",
    "gn:cc2":"KP",
    "gn:country_code":"KP",
    "gn:dem":637,
    "gn:feature_class":"P",
    "gn:feature_code":"PPL",
    "gn:name":"Insal-li",
    "gn:population":0,
    "gn:timezone":"Asia/Pyongyang",
    "iso:country":"KP",
    "name:kor_x_preferred":[
        "\uc778\uc0b0\ub9ac"
    ],
    "name:und_x_variant":[
        "Insan-ni",
        "Insal-li"
    ],
    "wof:name":"Insal-li",
    "wof:placetype":"locality"
},
  "geometry": {"coordinates":[127.98999999999999,41.41361],"type":"Point"}
}