{
  "type": "Feature",
  "properties": {
    "gn:admin1_code":"0.0",
    "gn:asciiname":"Unmu-dong",
    "gn:cc2":"KP",
    "gn:country_code":"KP",
    "gn:dem":864,
    "gn:feature_class":"P",
    "gn:feature_code":"PPL",
    "gn:name":"Unmu-dong",
    "gn:population":0,
    "gn:timezone":"Asia/Pyongyang",
    "iso:country":"KP",
    "name:kor_x_preferred":[
        "\uc6b4\ubb34\ub3d9"
    ],
    "name:und_x_variant":[
        "Unmu-gol",
        "Unmu-dong"
    ],
    "wof:name":"Unmu-dong",
    "wof:placetype":"locality"
},
  "geometry": {"coordinates":[127.88333,40.38333],"type":"Point"}
}