{
  "type": "Feature",
  "properties": {
    "gn:admin1_code":"13.0",
    "gn:asciiname":"Songil-li",
    "gn:cc2":"KP",
    "gn:country_code":"KP",
    "gn:dem":1152,
    "gn:feature_class":"P",
    "gn:feature_code":"PPL",
    "gn:name":"S\u014fngil-li",
    "gn:population":0,
    "gn:timezone":"Asia/Pyongyang",
    "iso:country":"KP",
    "name:kor_x_preferred":[
        "\uc131\uc778\ub9ac"
    ],
    "name:und_x_variant":[
        "S\u014fngjin-ni",
        "S\u014fngil-li"
    ],
    "wof:name":"Songil-li",
    "wof:placetype":"locality"
},
  "geometry": {"coordinates":[128.10777999999999,41.11361],"type":"Point"}
}