{
  "type": "Feature",
  "properties": {
    "gn:admin1_code":"6.0",
    "gn:asciiname":"Haejigae",
    "gn:cc2":"KP",
    "gn:country_code":"KP",
    "gn:dem":21,
    "gn:feature_class":"P",
    "gn:feature_code":"PPL",
    "gn:name":"Haejigae",
    "gn:population":0,
    "gn:timezone":"Asia/Pyongyang",
    "iso:country":"KP",
    "name:kor_x_preferred":[
        "\ud574\uc9c0\uac1c"
    ],
    "name:und_x_variant":[
        "Haejil-ch\u2019on",
        "Illakch\u2019on",
        "Haejigae"
    ],
    "wof:name":"Haejigae",
    "wof:placetype":"locality"
},
  "geometry": {"coordinates":[125.92194000000001,37.98083],"type":"Point"}
}