{
  "type": "Feature",
  "properties": {
    "gn:admin1_code":"13.0",
    "gn:asciiname":"T'aeyang-ni",
    "gn:country_code":"KP",
    "gn:dem":1127,
    "gn:feature_class":"P",
    "gn:feature_code":"PPL",
    "gn:name":"T\u2019aeyang-ni",
    "gn:population":0,
    "gn:timezone":"Asia/Pyongyang",
    "iso:country":"KP",
    "name:eng_x_preferred":[
        "T'aeyang"
    ],
    "name:eng_x_variant":[
        "T'aeyang-ni"
    ],
    "name:und_x_variant":[
        "T\u2019aeyang-dong",
        "T\u2019aeyang-ni"
    ],
    "wof:name":"T'aeyang",
    "wof:placetype":"locality"
},
  "geometry": {"coordinates":[127.67222,41.36194],"type":"Point"}
}