{
  "type": "Feature",
  "properties": {
    "gn:admin1_code":"7.0",
    "gn:asciiname":"Paksa-gol",
    "gn:country_code":"KP",
    "gn:dem":94,
    "gn:feature_class":"P",
    "gn:feature_code":"PPL",
    "gn:name":"Paksa-gol",
    "gn:population":0,
    "gn:timezone":"Asia/Pyongyang",
    "iso:country":"KP",
    "wof:name":"Paksa-gol",
    "wof:placetype":"locality"
},
  "geometry": {"coordinates":[125.92417,38.33944],"type":"Point"}
}