{
  "type": "Feature",
  "properties": {
    "gn:admin1_code":"11.0",
    "gn:asciiname":"Hach'ang",
    "gn:country_code":"KP",
    "gn:dem":205,
    "gn:feature_class":"P",
    "gn:feature_code":"PPL",
    "gn:name":"Hach\u2019ang",
    "gn:population":0,
    "gn:timezone":"Asia/Pyongyang",
    "iso:country":"KP",
    "name:und_x_variant":[
        "\ud558\ucc3d",
        "Hach\u2019ang"
    ],
    "wof:name":"Hach'ang",
    "wof:placetype":"locality"
},
  "geometry": {"coordinates":[125.55556,40.20917],"type":"Point"}
}