{
  "type": "Feature",
  "properties": {
    "gn:admin1_code":"15.0",
    "gn:asciiname":"Kumch'on",
    "gn:country_code":"KP",
    "gn:dem":66,
    "gn:feature_class":"P",
    "gn:feature_code":"PPL",
    "gn:name":"Kumch\u2019on",
    "gn:population":0,
    "gn:timezone":"Asia/Pyongyang",
    "iso:country":"KP",
    "wof:name":"Kumch'on",
    "wof:placetype":"locality"
},
  "geometry": {"coordinates":[125.74556,39.41806],"type":"Point"}
}