{
  "type": "Feature",
  "properties": {
    "gn:admin1_code":"13.0",
    "gn:asciiname":"Chigyong-ni",
    "gn:country_code":"KP",
    "gn:dem":865,
    "gn:feature_class":"P",
    "gn:feature_code":"PPL",
    "gn:name":"Chigy\u014fng-ni",
    "gn:population":0,
    "gn:timezone":"Asia/Pyongyang",
    "iso:country":"KP",
    "name:eng_x_preferred":[
        "Chigyong"
    ],
    "name:eng_x_variant":[
        "Chigyong-ni"
    ],
    "name:kor_x_preferred":[
        "\uc9c0\uacbd\ub9ac"
    ],
    "name:und_x_variant":[
        "Chigy\u014fng-ni"
    ],
    "wof:name":"Chigyong",
    "wof:placetype":"locality"
},
  "geometry": {"coordinates":[128.34138999999999,41.09],"type":"Point"}
}