{
  "type": "Feature",
  "properties": {
    "gn:admin1_code":"11.0",
    "gn:asciiname":"Taesong-ni",
    "gn:country_code":"KP",
    "gn:dem":26,
    "gn:feature_class":"P",
    "gn:feature_code":"PPL",
    "gn:name":"Taesong-ni",
    "gn:population":0,
    "gn:timezone":"Asia/Pyongyang",
    "iso:country":"KP",
    "name:eng_x_preferred":[
        "Taesong"
    ],
    "name:eng_x_variant":[
        "Taesong-ni"
    ],
    "name:kor_x_preferred":[
        "\ub300\uc1a1\ub9ac"
    ],
    "wof:name":"Taesong",
    "wof:placetype":"locality"
},
  "geometry": {"coordinates":[125.25111,39.71278],"type":"Point"}
}