{
  "type": "Feature",
  "properties": {
    "gn:admin1_code":"17.0",
    "gn:asciiname":"Musal-li",
    "gn:country_code":"KP",
    "gn:dem":545,
    "gn:feature_class":"P",
    "gn:feature_code":"PPLL",
    "gn:name":"Musal-li",
    "gn:population":0,
    "gn:timezone":"Asia/Pyongyang",
    "iso:country":"KP",
    "name:und_x_variant":[
        "Musan-dong",
        "Musan-ni",
        "\ubb34\uc0b0\ub9ac",
        "Musal-li"
    ],
    "wof:name":"Musal-li",
    "wof:placetype":"locality"
},
  "geometry": {"coordinates":[129.75221999999999,42.21167],"type":"Point"}
}