{
  "type": "Feature",
  "properties": {
    "gn:admin1_code":"1.0",
    "gn:asciiname":"Ch'ang-dong",
    "gn:country_code":"KP",
    "gn:dem":417,
    "gn:feature_class":"P",
    "gn:feature_code":"PPL",
    "gn:name":"Ch\u2019ang-dong",
    "gn:population":0,
    "gn:timezone":"Asia/Pyongyang",
    "iso:country":"KP",
    "name:und_x_variant":[
        "\ucc3d\ub3d9",
        "Ch\u2019ang-dong"
    ],
    "wof:name":"Ch'ang-dong",
    "wof:placetype":"locality"
},
  "geometry": {"coordinates":[125.95361,40.54667],"type":"Point"}
}