{
  "type": "Feature",
  "properties": {
    "gn:admin1_code":"3.0",
    "gn:asciiname":"Sokchaegung-gol",
    "gn:country_code":"KP",
    "gn:dem":46,
    "gn:feature_class":"P",
    "gn:feature_code":"PPL",
    "gn:name":"S\u014fkchaegung-gol",
    "gn:population":0,
    "gn:timezone":"Asia/Pyongyang",
    "iso:country":"KP",
    "name:kor_x_preferred":[
        "\uc11d\uc7ac\uad81\uace8"
    ],
    "name:kor_x_variant":[
        "S\u014fkchaegung-gol"
    ],
    "wof:name":"Sokchaegung-gol",
    "wof:placetype":"locality"
},
  "geometry": {"coordinates":[127.17749999999999,39.55],"type":"Point"}
}