{
  "type": "Feature",
  "properties": {
    "gn:admin1_code":"11.0",
    "gn:asciiname":"Mobong-ni",
    "gn:country_code":"KP",
    "gn:dem":47,
    "gn:feature_class":"P",
    "gn:feature_code":"PPL",
    "gn:name":"Mobong-ni",
    "gn:population":0,
    "gn:timezone":"Asia/Pyongyang",
    "iso:country":"KP",
    "name:eng_x_preferred":[
        "Mobong"
    ],
    "name:eng_x_variant":[
        "Mobong-ni"
    ],
    "name:und_x_variant":[
        "B\u014dh\u014d-ri",
        "\ubaa8\ubd09\ub9ac",
        "Mobong-ni"
    ],
    "wof:name":"Mobong",
    "wof:placetype":"locality"
},
  "geometry": {"coordinates":[124.58833,40.04222],"type":"Point"}
}