{
  "type": "Feature",
  "properties": {
    "gn:admin1_code":"3.0",
    "gn:asciiname":"Kil-li",
    "gn:country_code":"KP",
    "gn:dem":147,
    "gn:feature_class":"P",
    "gn:feature_code":"PPL",
    "gn:name":"Kil-li",
    "gn:population":0,
    "gn:timezone":"Asia/Pyongyang",
    "iso:country":"KP",
    "name:und_x_variant":[
        "\uae38\ub9ac",
        "Kil-li"
    ],
    "wof:name":"Kil-li",
    "wof:placetype":"locality"
},
  "geometry": {"coordinates":[127.57693999999999,40.22472],"type":"Point"}
}