{
  "type": "Feature",
  "properties": {
    "gn:admin1_code":"3.0",
    "gn:asciiname":"Kaenmal",
    "gn:country_code":"KP",
    "gn:dem":122,
    "gn:feature_class":"P",
    "gn:feature_code":"PPL",
    "gn:name":"Kaenmal",
    "gn:population":0,
    "gn:timezone":"Asia/Pyongyang",
    "iso:country":"KP",
    "name:kor_x_preferred":[
        "\uac2f\ub9d0"
    ],
    "name:und_x_variant":[
        "Ke-ma\u016dl",
        "Kae-ma\u016dl",
        "Kaenmal"
    ],
    "wof:name":"Kaenmal",
    "wof:placetype":"locality"
},
  "geometry": {"coordinates":[126.96666999999999,39.44444],"type":"Point"}
}