{
  "type": "Feature",
  "properties": {
    "gn:admin1_code":"1.0",
    "gn:asciiname":"Sinbang-ni",
    "gn:country_code":"KP",
    "gn:dem":776,
    "gn:feature_class":"P",
    "gn:feature_code":"PPL",
    "gn:name":"Sinbang-ni",
    "gn:population":0,
    "gn:timezone":"Asia/Pyongyang",
    "iso:country":"KP",
    "name:kor_x_preferred":[
        "\uc2e0\ubc29\ub9ac"
    ],
    "name:und_x_variant":[
        "Shimb\u014d-ri",
        "Sinhori",
        "Shinb\u014d-ri",
        "Sinbang-ni"
    ],
    "wof:name":"Sinbang-ni",
    "wof:placetype":"locality"
},
  "geometry": {"coordinates":[127.44302999999999,41.05572],"type":"Point"}
}