{
  "type": "Feature",
  "properties": {
    "gn:admin1_code":"11.0",
    "gn:asciiname":"Hakhyondong Ha-dong",
    "gn:country_code":"KP",
    "gn:dem":13,
    "gn:feature_class":"P",
    "gn:feature_code":"PPL",
    "gn:name":"Hakhy\u014fndong Ha-dong",
    "gn:population":0,
    "gn:timezone":"Asia/Pyongyang",
    "iso:country":"KP",
    "name:und_x_variant":[
        "\ud559\ud604\ub3d9\ud558\ub3d9",
        "Hakhy\u014fndong Ha-dong"
    ],
    "wof:name":"Hakhyondong Ha-dong",
    "wof:placetype":"locality"
},
  "geometry": {"coordinates":[124.77278,39.77778],"type":"Point"}
}