{
  "type": "Feature",
  "properties": {
    "gn:admin1_code":"7.0",
    "gn:asciiname":"Kudan",
    "gn:country_code":"KP",
    "gn:dem":479,
    "gn:feature_class":"P",
    "gn:feature_code":"PPL",
    "gn:name":"Kudan",
    "gn:population":0,
    "gn:timezone":"Asia/Pyongyang",
    "iso:country":"KP",
    "name:ceb_x_preferred":[
        "Kudan"
    ],
    "name:ita_x_preferred":[
        "Kudan"
    ],
    "name:spa_x_preferred":[
        "Kudan"
    ],
    "wof:name":"Kudan",
    "wof:placetype":"locality"
},
  "geometry": {"coordinates":[126.18111,38.57],"type":"Point"}
}