{
  "type": "Feature",
  "properties": {
    "gn:admin1_code":"12.0",
    "gn:asciiname":"Songp'a",
    "gn:country_code":"KP",
    "gn:dem":56,
    "gn:feature_class":"P",
    "gn:feature_code":"PPL",
    "gn:name":"Songp\u2019a",
    "gn:population":0,
    "gn:timezone":"Asia/Pyongyang",
    "iso:country":"KP",
    "name:kor_x_preferred":[
        "Songp\u2019a"
    ],
    "name:kor_x_variant":[
        "\uc1a1\ud30c"
    ],
    "name:und_x_variant":[
        "Songpa"
    ],
    "wof:name":"Songp'a",
    "wof:placetype":"locality"
},
  "geometry": {"coordinates":[125.90407,38.9067],"type":"Point"}
}