{
  "type": "Feature",
  "properties": {
    "gn:admin1_code":"6.0",
    "gn:asciiname":"Nongbau",
    "gn:cc2":"KP",
    "gn:country_code":"KP",
    "gn:dem":66,
    "gn:feature_class":"P",
    "gn:feature_code":"PPL",
    "gn:name":"Nongbau",
    "gn:population":0,
    "gn:timezone":"Asia/Pyongyang",
    "iso:country":"KP",
    "name:und_x_variant":[
        "Yongbawi",
        "Nongbau"
    ],
    "wof:name":"Nongbau",
    "wof:placetype":"locality"
},
  "geometry": {"coordinates":[125.43472,38.15056],"type":"Point"}
}