{
  "type": "Feature",
  "properties": {
    "gn:admin1_code":"6.0",
    "gn:asciiname":"Yongjo-dong",
    "gn:cc2":"KP",
    "gn:country_code":"KP",
    "gn:dem":29,
    "gn:feature_class":"P",
    "gn:feature_code":"PPL",
    "gn:name":"Yongjo-dong",
    "gn:population":0,
    "gn:timezone":"Asia/Pyongyang",
    "iso:country":"KP",
    "name:kor_x_preferred":[
        "\uc6a9\uc870\ub3d9"
    ],
    "name:und_x_variant":[
        "Yongso-dong",
        "Yongjo-dong"
    ],
    "wof:name":"Yongjo-dong",
    "wof:placetype":"locality"
},
  "geometry": {"coordinates":[125.03917,37.94972],"type":"Point"}
}