{
  "type": "Feature",
  "properties": {
    "gn:admin1_code":"1.0",
    "gn:asciiname":"Pogil-li",
    "gn:country_code":"KP",
    "gn:dem":357,
    "gn:feature_class":"P",
    "gn:feature_code":"PPL",
    "gn:name":"Pogil-li",
    "gn:population":0,
    "gn:timezone":"Asia/Pyongyang",
    "iso:country":"KP",
    "name:und_x_variant":[
        "\ubcf5\uc778\ub9ac",
        "Pogil-li"
    ],
    "wof:name":"Pogil-li",
    "wof:placetype":"locality"
},
  "geometry": {"coordinates":[126.26278000000001,40.79472],"type":"Point"}
}