{
  "type": "Feature",
  "properties": {
    "gn:admin1_code":"6.0",
    "gn:asciiname":"Sillung-dong",
    "gn:country_code":"KP",
    "gn:dem":88,
    "gn:feature_class":"P",
    "gn:feature_code":"PPL",
    "gn:name":"Sill\u016dng-dong",
    "gn:population":0,
    "gn:timezone":"Asia/Pyongyang",
    "iso:country":"KP",
    "name:kor_x_preferred":[
        "\uc2e0\ub989\ub3d9"
    ],
    "name:und_x_variant":[
        "Sill\u016dng-dong"
    ],
    "wof:name":"Sillung-dong",
    "wof:placetype":"locality"
},
  "geometry": {"coordinates":[126.14722,38.16472],"type":"Point"}
}