{
  "type": "Feature",
  "properties": {
    "gn:admin1_code":"7.0",
    "gn:asciiname":"Ch'ongye-ri",
    "gn:country_code":"KP",
    "gn:dem":69,
    "gn:feature_class":"P",
    "gn:feature_code":"PPL",
    "gn:name":"Ch\u2019\u014fngye-ri",
    "gn:population":0,
    "gn:timezone":"Asia/Pyongyang",
    "iso:country":"KP",
    "name:und_x_variant":[
        "H\u016dngsu-ri",
        "Ch\u2019\u014fngye-ri"
    ],
    "wof:name":"Ch'ongye-ri",
    "wof:placetype":"locality"
},
  "geometry": {"coordinates":[125.98806,38.47944],"type":"Point"}
}