{
  "type": "Feature",
  "properties": {
    "gn:admin1_code":"7.0",
    "gn:asciiname":"Sagimak",
    "gn:country_code":"KP",
    "gn:dem":253,
    "gn:feature_class":"P",
    "gn:feature_code":"PPL",
    "gn:name":"Sagimak",
    "gn:population":0,
    "gn:timezone":"Asia/Pyongyang",
    "iso:country":"KP",
    "name:kor_x_preferred":[
        "\uc0ac\uae30\ub9c9"
    ],
    "wof:name":"Sagimak",
    "wof:placetype":"locality"
},
  "geometry": {"coordinates":[126.70444000000001,38.56694],"type":"Point"}
}