{
  "type": "Feature",
  "properties": {
    "gn:admin1_code":"7.0",
    "gn:asciiname":"Haesu-ri",
    "gn:country_code":"KP",
    "gn:dem":63,
    "gn:feature_class":"P",
    "gn:feature_code":"PPL",
    "gn:name":"Haesu-ri",
    "gn:population":0,
    "gn:timezone":"Asia/Pyongyang",
    "iso:country":"KP",
    "name:kor_x_preferred":[
        "\ud574\uc218\ub9ac"
    ],
    "wof:name":"Haesu-ri",
    "wof:placetype":"locality"
},
  "geometry": {"coordinates":[126.33083000000001,38.255],"type":"Point"}
}