{
  "type": "Feature",
  "properties": {
    "gn:admin1_code":"11.0",
    "gn:asciiname":"Woryang-ni",
    "gn:cc2":"KP",
    "gn:country_code":"KP",
    "gn:dem":64,
    "gn:feature_class":"P",
    "gn:feature_code":"PPL",
    "gn:name":"W\u014fryang-ni",
    "gn:population":0,
    "gn:timezone":"Asia/Pyongyang",
    "iso:country":"KP",
    "name:eng_x_preferred":[
        "Woryang"
    ],
    "name:eng_x_variant":[
        "Woryang-ni"
    ],
    "name:und_x_variant":[
        "W\u014flyang-ni",
        "W\u014fryang-ni"
    ],
    "wof:name":"Woryang",
    "wof:placetype":"locality"
},
  "geometry": {"coordinates":[125.21805999999999,39.67056],"type":"Point"}
}