{
  "type": "Feature",
  "properties": {
    "gn:admin1_code":"6.0",
    "gn:asciiname":"Chibong-ni",
    "gn:country_code":"KP",
    "gn:dem":106,
    "gn:feature_class":"P",
    "gn:feature_code":"PPL",
    "gn:name":"Chibong-ni",
    "gn:population":0,
    "gn:timezone":"Asia/Pyongyang",
    "iso:country":"KP",
    "wof:name":"Chibong-ni",
    "wof:placetype":"locality"
},
  "geometry": {"coordinates":[125.56583000000001,38.29361],"type":"Point"}
}