{
  "type": "Feature",
  "properties": {
    "gn:admin1_code":"9.0",
    "gn:asciiname":"Changsung-ni",
    "gn:country_code":"KP",
    "gn:dem":478,
    "gn:feature_class":"P",
    "gn:feature_code":"PPL",
    "gn:name":"Changs\u016dng-ni",
    "gn:population":0,
    "gn:timezone":"Asia/Pyongyang",
    "iso:country":"KP",
    "name:und_x_variant":[
        "Ch\u014dj\u014d-ri",
        "Changs\u016dng-ni"
    ],
    "wof:name":"Changsung-ni",
    "wof:placetype":"locality"
},
  "geometry": {"coordinates":[128.19999999999999,38.38333],"type":"Point"}
}