{
  "type": "Feature",
  "properties": {
    "gn:admin1_code":"3.0",
    "gn:asciiname":"Hohang",
    "gn:country_code":"KP",
    "gn:dem":25,
    "gn:feature_class":"P",
    "gn:feature_code":"PPL",
    "gn:name":"H\u014fhang",
    "gn:population":0,
    "gn:timezone":"Asia/Pyongyang",
    "iso:country":"KP",
    "name:und_x_variant":[
        "\ud5c8\ud56d",
        "H\u014fhang"
    ],
    "wof:name":"Hohang",
    "wof:placetype":"locality"
},
  "geometry": {"coordinates":[128.73389,40.34972],"type":"Point"}
}