{
  "type": "Feature",
  "properties": {
    "gn:admin1_code":"7.0",
    "gn:asciiname":"Puyon-dong",
    "gn:country_code":"KP",
    "gn:dem":226,
    "gn:feature_class":"P",
    "gn:feature_code":"PPL",
    "gn:name":"Puy\u014fn-dong",
    "gn:population":0,
    "gn:timezone":"Asia/Pyongyang",
    "iso:country":"KP",
    "name:kor_x_preferred":[
        "\ubd80\uc5f0\ub3d9"
    ],
    "name:kor_x_variant":[
        "Puy\u014fn-dong"
    ],
    "wof:name":"Puyon-dong",
    "wof:placetype":"locality"
},
  "geometry": {"coordinates":[126.64888999999999,38.74556],"type":"Point"}
}