{
  "type": "Feature",
  "properties": {
    "gn:admin1_code":"17.0",
    "gn:asciiname":"Yup'o-dong",
    "gn:country_code":"KP",
    "gn:dem":200,
    "gn:feature_class":"P",
    "gn:feature_code":"PPL",
    "gn:name":"Yup\u2019o-dong",
    "gn:population":0,
    "gn:timezone":"Asia/Pyongyang",
    "iso:country":"KP",
    "name:und_x_variant":[
        "\uc720\ud3ec\ub3d9",
        "Yup\u2019o-dong"
    ],
    "wof:name":"Yup'o-dong",
    "wof:placetype":"locality"
},
  "geometry": {"coordinates":[129.48611,40.9175],"type":"Point"}
}