{
  "type": "Feature",
  "properties": {
    "gn:admin1_code":"1.0",
    "gn:asciiname":"Mak-tong",
    "gn:country_code":"KP",
    "gn:dem":507,
    "gn:feature_class":"P",
    "gn:feature_code":"PPL",
    "gn:name":"Mak-tong",
    "gn:population":0,
    "gn:timezone":"Asia/Pyongyang",
    "iso:country":"KP",
    "name:und_x_variant":[
        "\ub9c9\ub3d9",
        "Mak-tong"
    ],
    "wof:name":"Mak-tong",
    "wof:placetype":"locality"
},
  "geometry": {"coordinates":[125.98694,40.66389],"type":"Point"}
}