{
  "type": "Feature",
  "properties": {
    "gn:admin1_code":"3.0",
    "gn:asciiname":"Sungji",
    "gn:country_code":"KP",
    "gn:dem":12,
    "gn:feature_class":"P",
    "gn:feature_code":"PPL",
    "gn:name":"S\u016dngji",
    "gn:population":0,
    "gn:timezone":"Asia/Pyongyang",
    "iso:country":"KP",
    "name:und_x_variant":[
        "\uc2b9\uc9c0",
        "S\u016dngji"
    ],
    "wof:name":"Sungji",
    "wof:placetype":"locality"
},
  "geometry": {"coordinates":[127.39139,39.79722],"type":"Point"}
}