{
  "type": "Feature",
  "properties": {
    "gn:admin1_code":"11.0",
    "gn:asciiname":"Unsong-dong",
    "gn:country_code":"KP",
    "gn:dem":103,
    "gn:feature_class":"P",
    "gn:feature_code":"PPL",
    "gn:name":"Uns\u014fng-dong",
    "gn:population":0,
    "gn:timezone":"Asia/Pyongyang",
    "iso:country":"KP",
    "name:und_x_variant":[
        "\uc6b4\uc131\ub3d9",
        "Uns\u014fng-dong"
    ],
    "wof:name":"Unsong-dong",
    "wof:placetype":"locality"
},
  "geometry": {"coordinates":[125.73639,40.05278],"type":"Point"}
}