{
  "type": "Feature",
  "properties": {
    "gn:admin1_code":"15.0",
    "gn:asciiname":"Yongp'yong-ni",
    "gn:country_code":"KP",
    "gn:dem":260,
    "gn:feature_class":"P",
    "gn:feature_code":"PPL",
    "gn:name":"Yongp\u2019y\u014fng-ni",
    "gn:population":0,
    "gn:timezone":"Asia/Pyongyang",
    "iso:country":"KP",
    "name:und_x_variant":[
        "\ub8e1\ud3c9\ub9ac",
        "Yongp\u2019y\u014fng-ni"
    ],
    "wof:name":"Yongp'yong-ni",
    "wof:placetype":"locality"
},
  "geometry": {"coordinates":[126.84,39.15694000000001],"type":"Point"}
}