{
  "type": "Feature",
  "properties": {
    "gn:admin1_code":"3.0",
    "gn:asciiname":"Namsok-tong",
    "gn:country_code":"KP",
    "gn:dem":15,
    "gn:feature_class":"P",
    "gn:feature_code":"PPL",
    "gn:name":"Nams\u014fk-tong",
    "gn:population":0,
    "gn:timezone":"Asia/Pyongyang",
    "iso:country":"KP",
    "name:eng_x_preferred":[
        "Namsok"
    ],
    "name:eng_x_variant":[
        "Namsok-tong"
    ],
    "name:und_x_variant":[
        "\ub0a8\uc11d\ub3d9",
        "Nams\u014fk-tong"
    ],
    "wof:name":"Namsok",
    "wof:placetype":"locality"
},
  "geometry": {"coordinates":[127.30028,39.52361],"type":"Point"}
}