{
  "type": "Feature",
  "properties": {
    "gn:admin1_code":"9.0",
    "gn:admin2_code":"Ch\u2019\u014fnnae-gun",
    "gn:asciiname":"Munwang-ni",
    "gn:country_code":"KP",
    "gn:dem":20,
    "gn:feature_class":"P",
    "gn:feature_code":"PPL",
    "gn:name":"Munwang-ni",
    "gn:population":0,
    "gn:timezone":"Asia/Pyongyang",
    "iso:country":"KP",
    "name:und_x_variant":[
        "\ubb38\uc655\ub9ac"
    ],
    "wof:name":"Munwang-ni",
    "wof:placetype":"locality"
},
  "geometry": {"coordinates":[127.22163999999999,39.34143],"type":"Point"}
}