{
  "type": "Feature",
  "properties": {
    "gn:admin1_code":"12.0",
    "gn:admin2_code":"Kangdong-gun",
    "gn:asciiname":"Saemgol",
    "gn:country_code":"KP",
    "gn:dem":55,
    "gn:feature_class":"P",
    "gn:feature_code":"PPL",
    "gn:name":"Saemgol",
    "gn:population":0,
    "gn:timezone":"Asia/Pyongyang",
    "iso:country":"KP",
    "name:kor_x_preferred":[
        "\uc0d8\uace8"
    ],
    "wof:name":"Saemgol",
    "wof:placetype":"locality"
},
  "geometry": {"coordinates":[126.12417000000001,39.12528],"type":"Point"}
}