{
  "type": "Feature",
  "properties": {
    "gn:admin1_code":"15.0",
    "gn:asciiname":"Ch'on-dong",
    "gn:country_code":"KP",
    "gn:dem":363,
    "gn:feature_class":"P",
    "gn:feature_code":"PPL",
    "gn:name":"Ch\u2019on-dong",
    "gn:population":0,
    "gn:timezone":"Asia/Pyongyang",
    "iso:country":"KP",
    "name:kor_x_preferred":[
        "\ucd0c\ub3d9"
    ],
    "name:und_x_variant":[
        "Ch\u2019on-dong"
    ],
    "wof:name":"Ch'on-dong",
    "wof:placetype":"locality"
},
  "geometry": {"coordinates":[126.395,39.64944000000001],"type":"Point"}
}