{
  "type": "Feature",
  "properties": {
    "gn:admin1_code":"1.0",
    "gn:asciiname":"I-dong",
    "gn:country_code":"KP",
    "gn:dem":213,
    "gn:feature_class":"P",
    "gn:feature_code":"PPL",
    "gn:name":"I-dong",
    "gn:population":0,
    "gn:timezone":"Asia/Pyongyang",
    "iso:country":"KP",
    "name:und_x_variant":[
        "\uc774\ub3d9",
        "I-dong"
    ],
    "wof:name":"I-dong",
    "wof:placetype":"locality"
},
  "geometry": {"coordinates":[126.17111,40.18917],"type":"Point"}
}