{
  "type": "Feature",
  "properties": {
    "gn:admin1_code":"15.0",
    "gn:asciiname":"Chajak-tong",
    "gn:country_code":"KP",
    "gn:dem":552,
    "gn:feature_class":"P",
    "gn:feature_code":"PPL",
    "gn:name":"Chajak-tong",
    "gn:population":0,
    "gn:timezone":"Asia/Pyongyang",
    "iso:country":"KP",
    "name:eng_x_preferred":[
        "Chajak"
    ],
    "name:eng_x_variant":[
        "Chajak-tong"
    ],
    "name:und_x_variant":[
        "\uc790\uc791\ub3d9",
        "Chajak-tong"
    ],
    "wof:name":"Chajak",
    "wof:placetype":"locality"
},
  "geometry": {"coordinates":[126.64639,39.64528],"type":"Point"}
}