{
  "type": "Feature",
  "properties": {
    "gn:admin1_code":"6.0",
    "gn:asciiname":"Mangsokch'i",
    "gn:country_code":"KP",
    "gn:dem":8,
    "gn:feature_class":"P",
    "gn:feature_code":"PPL",
    "gn:name":"Mangs\u014fkch\u2019i",
    "gn:population":0,
    "gn:timezone":"Asia/Pyongyang",
    "iso:country":"KP",
    "wof:name":"Mangsokch'i",
    "wof:placetype":"locality"
},
  "geometry": {"coordinates":[126.24167,37.97917],"type":"Point"}
}