{
  "type": "Feature",
  "properties": {
    "gn:admin1_code":"6.0",
    "gn:asciiname":"Nuk-tong",
    "gn:country_code":"KP",
    "gn:dem":15,
    "gn:feature_class":"P",
    "gn:feature_code":"PPL",
    "gn:name":"N\u016dk-tong",
    "gn:population":0,
    "gn:timezone":"Asia/Pyongyang",
    "iso:country":"KP",
    "name:kor_x_preferred":[
        "\ub291\ub3d9"
    ],
    "name:kor_x_variant":[
        "N\u016dk-tong"
    ],
    "wof:name":"Nuk-tong",
    "wof:placetype":"locality"
},
  "geometry": {"coordinates":[125.44194,38.65667],"type":"Point"}
}