{
  "type": "Feature",
  "properties": {
    "gn:admin1_code":"1.0",
    "gn:asciiname":"Sangch'ongch'am",
    "gn:country_code":"KP",
    "gn:dem":235,
    "gn:feature_class":"P",
    "gn:feature_code":"PPL",
    "gn:name":"Sangch\u2019\u014fngch\u2019am",
    "gn:population":0,
    "gn:timezone":"Asia/Pyongyang",
    "iso:country":"KP",
    "name:und_x_variant":[
        "\uc0c1\uccad\ucc38",
        "Sangch\u2019\u014fngch\u2019am"
    ],
    "wof:name":"Sangch'ongch'am",
    "wof:placetype":"locality"
},
  "geometry": {"coordinates":[126.32056,40.20889],"type":"Point"}
}