{
  "type": "Feature",
  "properties": {
    "gn:admin1_code":"12.0",
    "gn:asciiname":"Soangol",
    "gn:country_code":"KP",
    "gn:dem":3,
    "gn:feature_class":"P",
    "gn:feature_code":"PPL",
    "gn:name":"Soangol",
    "gn:population":0,
    "gn:timezone":"Asia/Pyongyang",
    "iso:country":"KP",
    "name:kor_x_preferred":[
        "\uc18c\uc548\uace8"
    ],
    "name:und_x_variant":[
        "Sonae-dong",
        "Soangol"
    ],
    "wof:name":"Soangol",
    "wof:placetype":"locality"
},
  "geometry": {"coordinates":[125.59999999999999,38.93333],"type":"Point"}
}