{
  "type": "Feature",
  "properties": {
    "gn:admin1_code":"7.0",
    "gn:asciiname":"Kyejong-ni",
    "gn:country_code":"KP",
    "gn:dem":27,
    "gn:feature_class":"P",
    "gn:feature_code":"PPL",
    "gn:name":"Kyej\u014fng-ni",
    "gn:population":0,
    "gn:timezone":"Asia/Pyongyang",
    "iso:country":"KP",
    "name:eng_x_preferred":[
        "Kyejong"
    ],
    "name:eng_x_variant":[
        "Kyejong-ni"
    ],
    "name:und_x_variant":[
        "Kyej\u014fng-gol",
        "\uacc4\uc815\ub9ac",
        "Kyej\u014fng-ni"
    ],
    "wof:name":"Kyejong",
    "wof:placetype":"locality"
},
  "geometry": {"coordinates":[126.45305999999999,38.06694],"type":"Point"}
}