{
  "type": "Feature",
  "properties": {
    "gn:admin1_code":"7.0",
    "gn:asciiname":"Taryon-dong",
    "gn:country_code":"KP",
    "gn:dem":258,
    "gn:feature_class":"P",
    "gn:feature_code":"PPL",
    "gn:name":"Tary\u014fn-dong",
    "gn:population":0,
    "gn:timezone":"Asia/Pyongyang",
    "iso:country":"KP",
    "name:kor_x_preferred":[
        "\ub2ec\uc5f0\ub3d9"
    ],
    "name:kor_x_variant":[
        "Tary\u014fn-dong"
    ],
    "wof:name":"Taryon-dong",
    "wof:placetype":"locality"
},
  "geometry": {"coordinates":[126.47278,38.71],"type":"Point"}
}