{
  "type": "Feature",
  "properties": {
    "gn:admin1_code":"13.0",
    "gn:asciiname":"Koogu",
    "gn:cc2":"KP",
    "gn:country_code":"KP",
    "gn:dem":847,
    "gn:feature_class":"P",
    "gn:feature_code":"PPL",
    "gn:name":"Ko\u014fgu",
    "gn:population":0,
    "gn:timezone":"Asia/Pyongyang",
    "iso:country":"KP",
    "name:kor_x_preferred":[
        "\uace0\uc5b4\uad6c"
    ],
    "name:und_x_variant":[
        "Kook\u014d",
        "Ko\u014fgu"
    ],
    "wof:name":"Koogu",
    "wof:placetype":"locality"
},
  "geometry": {"coordinates":[128.23056,41.03611],"type":"Point"}
}