{
  "type": "Feature",
  "properties": {
    "gn:admin1_code":"15.0",
    "gn:asciiname":"Ryonghung",
    "gn:country_code":"KP",
    "gn:dem":132,
    "gn:feature_class":"P",
    "gn:feature_code":"PPL",
    "gn:name":"Ryongh\u016dng",
    "gn:population":0,
    "gn:timezone":"Asia/Pyongyang",
    "iso:country":"KP",
    "name:kor_x_preferred":[
        "\ub8e1\ud765"
    ],
    "name:und_x_variant":[
        "Ryongh\u016dng",
        "Yonghung"
    ],
    "wof:name":"Ryonghung",
    "wof:placetype":"locality"
},
  "geometry": {"coordinates":[126.30556,39.56417],"type":"Point"}
}