{
  "type": "Feature",
  "properties": {
    "gn:admin1_code":"17.0",
    "gn:asciiname":"Hago-ri",
    "gn:country_code":"KP",
    "gn:dem":92,
    "gn:feature_class":"P",
    "gn:feature_code":"PPL",
    "gn:name":"Hag\u014f-ri",
    "gn:population":0,
    "gn:timezone":"Asia/Pyongyang",
    "iso:country":"KP",
    "name:und_x_variant":[
        "\ud558\uac70\ub9ac",
        "Hag\u014f-ri"
    ],
    "wof:name":"Hago-ri",
    "wof:placetype":"locality"
},
  "geometry": {"coordinates":[129.62028000000001,41.61806],"type":"Point"}
}