{
  "type": "Feature",
  "properties": {
    "gn:admin1_code":"7.0",
    "gn:asciiname":"Kit'al-li",
    "gn:country_code":"KP",
    "gn:dem":60,
    "gn:feature_class":"P",
    "gn:feature_code":"PPL",
    "gn:name":"Kit\u2019al-li",
    "gn:population":0,
    "gn:timezone":"Asia/Pyongyang",
    "iso:country":"KP",
    "name:kor_x_preferred":[
        "\uae30\ud0c4\ub9ac"
    ],
    "name:kor_x_variant":[
        "Kit\u2019al-li"
    ],
    "name:und_x_variant":[
        "Kit\u2019an"
    ],
    "wof:name":"Kit'al-li",
    "wof:placetype":"locality"
},
  "geometry": {"coordinates":[126.49417,38.38889],"type":"Point"}
}