{
  "type": "Feature",
  "properties": {
    "gn:admin1_code":"11.0",
    "gn:asciiname":"Tongsang-dong",
    "gn:country_code":"KP",
    "gn:dem":6,
    "gn:feature_class":"P",
    "gn:feature_code":"PPL",
    "gn:name":"Tongsang-dong",
    "gn:population":0,
    "gn:timezone":"Asia/Pyongyang",
    "iso:country":"KP",
    "name:und_x_variant":[
        "\ub3d9\uc0c1\ub3d9",
        "Tongsang-dong"
    ],
    "wof:name":"Tongsang-dong",
    "wof:placetype":"locality"
},
  "geometry": {"coordinates":[124.41889,40.01167],"type":"Point"}
}