{
  "type": "Feature",
  "properties": {
    "gn:admin1_code":"1.0",
    "gn:asciiname":"Umulgol",
    "gn:country_code":"KP",
    "gn:dem":400,
    "gn:feature_class":"P",
    "gn:feature_code":"PPL",
    "gn:name":"Umulgol",
    "gn:population":0,
    "gn:timezone":"Asia/Pyongyang",
    "iso:country":"KP",
    "name:und_x_variant":[
        "\uccad\uacc4\ucc38",
        "Ch\u014fnggyech\u2019am",
        "Umulgol",
        "\uc6b0\ubb3c\uace8"
    ],
    "wof:name":"Umulgol",
    "wof:placetype":"locality"
},
  "geometry": {"coordinates":[126.45355000000001,40.26302],"type":"Point"}
}