{
  "type": "Feature",
  "properties": {
    "gn:admin1_code":"11.0",
    "gn:asciiname":"Kunsal-li",
    "gn:country_code":"KP",
    "gn:dem":64,
    "gn:feature_class":"P",
    "gn:feature_code":"PPL",
    "gn:name":"Kunsal-li",
    "gn:population":0,
    "gn:timezone":"Asia/Pyongyang",
    "iso:country":"KP",
    "name:kor_x_preferred":[
        "\uad70\uc0b0\ub9ac"
    ],
    "name:und_x_variant":[
        "Kunsan-ni",
        "Kunsan-dong",
        "Kunsal-li"
    ],
    "wof:name":"Kunsal-li",
    "wof:placetype":"locality"
},
  "geometry": {"coordinates":[125.06667,39.78861],"type":"Point"}
}