{
  "type": "Feature",
  "properties": {
    "gn:admin1_code":"0.0",
    "gn:asciiname":"Chuk-ch'on",
    "gn:country_code":"KP",
    "gn:dem":780,
    "gn:feature_class":"P",
    "gn:feature_code":"PPL",
    "gn:name":"Chuk-ch\u2019on",
    "gn:population":0,
    "gn:timezone":"Asia/Pyongyang",
    "iso:country":"KP",
    "name:kor_x_preferred":[
        "\uc8fd\ucd0c"
    ],
    "name:und_x_variant":[
        "Taegol",
        "Chuk-ch\u2019on"
    ],
    "wof:name":"Chuk-ch'on",
    "wof:placetype":"locality"
},
  "geometry": {"coordinates":[127.33333,38.91667],"type":"Point"}
}