{
  "type": "Feature",
  "properties": {
    "gn:admin1_code":"12.0",
    "gn:asciiname":"Tongha-dong",
    "gn:country_code":"KP",
    "gn:dem":21,
    "gn:feature_class":"P",
    "gn:feature_code":"PPL",
    "gn:name":"Tongha-dong",
    "gn:population":0,
    "gn:timezone":"Asia/Pyongyang",
    "iso:country":"KP",
    "name:und_x_variant":[
        "\ub3d9\ud558\ub3d9",
        "Tongha-dong",
        "Donghadong"
    ],
    "wof:name":"Tongha-dong",
    "wof:placetype":"locality"
},
  "geometry": {"coordinates":[125.71666999999999,38.86722],"type":"Point"}
}