{
  "type": "Feature",
  "properties": {
    "gn:admin1_code":"17.0",
    "gn:asciiname":"Oso",
    "gn:country_code":"KP",
    "gn:dem":734,
    "gn:feature_class":"P",
    "gn:feature_code":"PPL",
    "gn:name":"Oso",
    "gn:population":0,
    "gn:timezone":"Asia/Pyongyang",
    "iso:country":"KP",
    "name:ceb_x_preferred":[
        "Oso"
    ],
    "name:fra_x_preferred":[
        "Oso"
    ],
    "name:nld_x_preferred":[
        "Oso"
    ],
    "name:por_x_preferred":[
        "Oso"
    ],
    "name:sco_x_preferred":[
        "Oso"
    ],
    "name:spa_x_preferred":[
        "Oso"
    ],
    "name:swe_x_preferred":[
        "Oso"
    ],
    "name:und_x_variant":[
        "\uc624\uc18c",
        "O-dong"
    ],
    "wof:name":"Oso",
    "wof:placetype":"locality"
},
  "geometry": {"coordinates":[129.25556,42.02278],"type":"Point"}
}