{
  "type": "Feature",
  "properties": {
    "gn:admin1_code":"6.0",
    "gn:asciiname":"Muhak-tong",
    "gn:country_code":"KP",
    "gn:dem":20,
    "gn:feature_class":"P",
    "gn:feature_code":"PPL",
    "gn:name":"Muhak-tong",
    "gn:population":0,
    "gn:timezone":"Asia/Pyongyang",
    "iso:country":"KP",
    "name:eng_x_preferred":[
        "Muhak"
    ],
    "name:eng_x_variant":[
        "Muhak-tong"
    ],
    "wof:name":"Muhak",
    "wof:placetype":"locality"
},
  "geometry": {"coordinates":[126.01833000000001,37.93278],"type":"Point"}
}