{
  "type": "Feature",
  "properties": {
    "gn:admin1_code":"9.0",
    "gn:asciiname":"Sinp'ung-ni",
    "gn:country_code":"KP",
    "gn:dem":330,
    "gn:feature_class":"P",
    "gn:feature_code":"PPL",
    "gn:name":"Sinp\u2019ung-ni",
    "gn:population":0,
    "gn:timezone":"Asia/Pyongyang",
    "iso:country":"KP",
    "name:und_x_variant":[
        "\uc2e0\ud48d\ub9ac",
        "Sinp\u2019ung-ni"
    ],
    "wof:name":"Sinp'ung-ni",
    "wof:placetype":"locality"
},
  "geometry": {"coordinates":[127.55194,38.47583],"type":"Point"}
}