{
  "type": "Feature",
  "properties": {
    "gn:admin1_code":"1.0",
    "gn:asciiname":"Worunch'on-dong",
    "gn:country_code":"KP",
    "gn:dem":502,
    "gn:feature_class":"P",
    "gn:feature_code":"PPL",
    "gn:name":"W\u014fr\u016dnch\u2019\u014fn-dong",
    "gn:population":0,
    "gn:timezone":"Asia/Pyongyang",
    "iso:country":"KP",
    "name:und_x_variant":[
        "\uc6d4\uc740\ucc9c\ub3d9",
        "W\u014fr\u016dnch\u2019\u014fn-dong"
    ],
    "wof:name":"Worunch'on-dong",
    "wof:placetype":"locality"
},
  "geometry": {"coordinates":[125.67833,40.30611],"type":"Point"}
}