{
  "type": "Feature",
  "properties": {
    "gn:admin1_code":"7.0",
    "gn:asciiname":"Changdokpau",
    "gn:country_code":"KP",
    "gn:dem":39,
    "gn:feature_class":"P",
    "gn:feature_code":"PPL",
    "gn:name":"Changdokpau",
    "gn:population":0,
    "gn:timezone":"Asia/Pyongyang",
    "iso:country":"KP",
    "name:kor_x_preferred":[
        "\uc7a5\ub3c5\ubc14\uc6b0"
    ],
    "wof:name":"Changdokpau",
    "wof:placetype":"locality"
},
  "geometry": {"coordinates":[126.40278000000001,38.30194],"type":"Point"}
}