{
  "type": "Feature",
  "properties": {
    "gn:admin1_code":"0.0",
    "gn:asciiname":"Nou-mol",
    "gn:cc2":"KP",
    "gn:country_code":"KP",
    "gn:dem":9,
    "gn:feature_class":"P",
    "gn:feature_code":"PPL",
    "gn:name":"Nou-mol",
    "gn:population":0,
    "gn:timezone":"Asia/Pyongyang",
    "iso:country":"KP",
    "name:kor_x_preferred":[
        "\ub178\uc6b0\ubab0"
    ],
    "name:und_x_variant":[
        "Kusu-dong",
        "Nou-mol"
    ],
    "wof:name":"Nou-mol",
    "wof:placetype":"locality"
},
  "geometry": {"coordinates":[125.66667,38.73333],"type":"Point"}
}