{
  "type": "Feature",
  "properties": {
    "gn:admin1_code":"9.0",
    "gn:asciiname":"Tongp'o-ri",
    "gn:country_code":"KP",
    "gn:dem":76,
    "gn:feature_class":"P",
    "gn:feature_code":"PPL",
    "gn:name":"Tongp\u2019o-ri",
    "gn:population":0,
    "gn:timezone":"Asia/Pyongyang",
    "iso:country":"KP",
    "name:und_x_variant":[
        "Tongp\u2019o-ri",
        "\ub3d9\ud3ec\ub9ac"
    ],
    "wof:name":"Tongp'o-ri",
    "wof:placetype":"locality"
},
  "geometry": {"coordinates":[127.41361000000001,39.07],"type":"Point"}
}