{
  "type": "Feature",
  "properties": {
    "gn:admin1_code":"17.0",
    "gn:asciiname":"Hwap'yong",
    "gn:country_code":"KP",
    "gn:dem":17,
    "gn:feature_class":"P",
    "gn:feature_code":"PPL",
    "gn:name":"Hwap\u2019y\u014fng",
    "gn:population":0,
    "gn:timezone":"Asia/Pyongyang",
    "iso:country":"KP",
    "name:und_x_variant":[
        "\ud654\ud3c9",
        "Hwap\u2019y\u014fng"
    ],
    "wof:name":"Hwap'yong",
    "wof:placetype":"locality"
},
  "geometry": {"coordinates":[129.58472,41.46139],"type":"Point"}
}