{
  "type": "Feature",
  "properties": {
    "gn:admin1_code":"9.0",
    "gn:admin2_code":"1875980",
    "gn:asciiname":"Wonnam-ni",
    "gn:country_code":"KP",
    "gn:dem":260,
    "gn:feature_class":"P",
    "gn:feature_code":"PPL",
    "gn:name":"W\u014fnnam-ni",
    "gn:population":0,
    "gn:timezone":"Asia/Pyongyang",
    "iso:country":"KP",
    "name:eng_x_preferred":[
        "Wonnam"
    ],
    "name:eng_x_variant":[
        "Wonnam-ni"
    ],
    "wof:name":"Wonnam",
    "wof:placetype":"locality"
},
  "geometry": {"coordinates":[127.61360999999999,38.38389],"type":"Point"}
}