{
  "type": "Feature",
  "properties": {
    "gn:admin1_code":"17.0",
    "gn:asciiname":"Ibam",
    "gn:country_code":"KP",
    "gn:dem":148,
    "gn:feature_class":"P",
    "gn:feature_code":"PPL",
    "gn:name":"Ibam",
    "gn:population":0,
    "gn:timezone":"Asia/Pyongyang",
    "iso:country":"KP",
    "name:und_x_variant":[
        "\uc785\uc554",
        "Ibam"
    ],
    "wof:name":"Ibam",
    "wof:placetype":"locality"
},
  "geometry": {"coordinates":[130.07749999999999,42.59722],"type":"Point"}
}