{
  "type": "Feature",
  "properties": {
    "gn:admin1_code":"12.0",
    "gn:asciiname":"Taega-dong",
    "gn:country_code":"KP",
    "gn:dem":121,
    "gn:feature_class":"P",
    "gn:feature_code":"PPL",
    "gn:name":"Taega-dong",
    "gn:population":0,
    "gn:timezone":"Asia/Pyongyang",
    "iso:country":"KP",
    "name:kor_x_preferred":[
        "\ub300\uac00\ub3d9"
    ],
    "name:und_x_variant":[
        "Daegadong"
    ],
    "wof:name":"Taega-dong",
    "wof:placetype":"locality"
},
  "geometry": {"coordinates":[125.8489,39.13297],"type":"Point"}
}