{
  "type": "Feature",
  "properties": {
    "gn:admin1_code":"0.0",
    "gn:asciiname":"Tongsan",
    "gn:country_code":"KP",
    "gn:dem":148,
    "gn:feature_class":"P",
    "gn:feature_code":"PPL",
    "gn:name":"Tongsan",
    "gn:population":0,
    "gn:timezone":"Asia/Pyongyang",
    "iso:country":"KP",
    "wof:name":"Tongsan",
    "wof:placetype":"locality"
},
  "geometry": {"coordinates":[128.09999999999999,40.16667],"type":"Point"}
}