{
  "type": "Feature",
  "properties": {
    "gn:admin1_code":"17.0",
    "gn:asciiname":"Osang-ni",
    "gn:country_code":"KP",
    "gn:dem":124,
    "gn:feature_class":"P",
    "gn:feature_code":"PPLL",
    "gn:name":"Osang-ni",
    "gn:population":0,
    "gn:timezone":"Asia/Pyongyang",
    "iso:country":"KP",
    "name:eng_x_preferred":[
        "Osang"
    ],
    "name:eng_x_variant":[
        "Osang-ni"
    ],
    "name:und_x_variant":[
        "Osang-dong",
        "\uc624\uc0c1\ub9ac",
        "Osang-ni"
    ],
    "wof:name":"Osang",
    "wof:placetype":"locality"
},
  "geometry": {"coordinates":[129.54083,41.71639],"type":"Point"}
}