{
  "type": "Feature",
  "properties": {
    "gn:admin1_code":"6.0",
    "gn:asciiname":"Ogam-ni",
    "gn:country_code":"KP",
    "gn:dem":18,
    "gn:feature_class":"P",
    "gn:feature_code":"PPL",
    "gn:name":"Ogam-ni",
    "gn:population":0,
    "gn:timezone":"Asia/Pyongyang",
    "iso:country":"KP",
    "name:und_x_variant":[
        "\uc625\uc554\ub9ac",
        "Ogam-ni"
    ],
    "wof:name":"Ogam-ni",
    "wof:placetype":"locality"
},
  "geometry": {"coordinates":[125.32138999999999,38.04583],"type":"Point"}
}