{
  "type": "Feature",
  "properties": {
    "gn:admin1_code":"7.0",
    "gn:asciiname":"Kujong-ni",
    "gn:country_code":"KP",
    "gn:dem":188,
    "gn:feature_class":"P",
    "gn:feature_code":"PPL",
    "gn:name":"Kuj\u014fng-ni",
    "gn:population":0,
    "gn:timezone":"Asia/Pyongyang",
    "iso:country":"KP",
    "wof:name":"Kujong-ni",
    "wof:placetype":"locality"
},
  "geometry": {"coordinates":[126.28583,38.57583],"type":"Point"}
}