{
  "type": "Feature",
  "properties": {
    "gn:admin1_code":"6.0",
    "gn:asciiname":"T'apkogae",
    "gn:country_code":"KP",
    "gn:dem":48,
    "gn:feature_class":"P",
    "gn:feature_code":"PPL",
    "gn:name":"T\u2019apkogae",
    "gn:population":0,
    "gn:timezone":"Asia/Pyongyang",
    "iso:country":"KP",
    "name:und_x_variant":[
        "Sogye",
        "T\u2019apkogae"
    ],
    "wof:name":"T'apkogae",
    "wof:placetype":"locality"
},
  "geometry": {"coordinates":[126.13556,37.97917],"type":"Point"}
}