{
  "type": "Feature",
  "properties": {
    "gn:admin1_code":"13.0",
    "gn:asciiname":"Samp'o-ri",
    "gn:country_code":"KP",
    "gn:dem":1078,
    "gn:feature_class":"P",
    "gn:feature_code":"PPL",
    "gn:name":"Samp\u2019o-ri",
    "gn:population":0,
    "gn:timezone":"Asia/Pyongyang",
    "iso:country":"KP",
    "wof:name":"Samp'o-ri",
    "wof:placetype":"locality"
},
  "geometry": {"coordinates":[127.92944,41.24528],"type":"Point"}
}