{
  "type": "Feature",
  "properties": {
    "gn:admin1_code":"13.0",
    "gn:admin2_code":"Paegam-gun",
    "gn:asciiname":"Okch'ol-lodongjagu",
    "gn:country_code":"KP",
    "gn:dem":1103,
    "gn:feature_class":"P",
    "gn:feature_code":"PPL",
    "gn:name":"Okch\u2019\u014fl-lodongjagu",
    "gn:population":0,
    "gn:timezone":"Asia/Pyongyang",
    "iso:country":"KP",
    "name:kor_x_preferred":[
        "\uc625\ucc9c\ub85c\ub3d9\uc790\uad6c"
    ],
    "name:und_x_variant":[
        "Okch\u2019\u014fl-lodongjagu"
    ],
    "wof:name":"Okch'ol-lodongjagu",
    "wof:placetype":"locality"
},
  "geometry": {"coordinates":[128.80831000000001,41.81549],"type":"Point"}
}