{
  "type": "Feature",
  "properties": {
    "gn:admin1_code":"6.0",
    "gn:asciiname":"Myongch'ol-li",
    "gn:country_code":"KP",
    "gn:dem":29,
    "gn:feature_class":"P",
    "gn:feature_code":"PPL",
    "gn:name":"My\u014fngch\u2019\u014fl-li",
    "gn:population":0,
    "gn:timezone":"Asia/Pyongyang",
    "iso:country":"KP",
    "name:kor_x_preferred":[
        "\uba85\ucc9c\ub9ac"
    ],
    "name:kor_x_variant":[
        "My\u014fngch\u2019\u014fl-li"
    ],
    "name:und_x_variant":[
        "My\u014fngch\u2019\u014fn-ni"
    ],
    "wof:name":"Myongch'ol-li",
    "wof:placetype":"locality"
},
  "geometry": {"coordinates":[125.12222,38.26778],"type":"Point"}
}