{
  "type": "Feature",
  "properties": {
    "gn:admin1_code":"17.0",
    "gn:asciiname":"Sin'gi-dong",
    "gn:country_code":"KP",
    "gn:dem":305,
    "gn:feature_class":"P",
    "gn:feature_code":"PPL",
    "gn:name":"Sin\u2019gi-dong",
    "gn:population":0,
    "gn:timezone":"Asia/Pyongyang",
    "iso:country":"KP",
    "wof:name":"Sin'gi-dong",
    "wof:placetype":"locality"
},
  "geometry": {"coordinates":[129.84999999999999,42.06667],"type":"Point"}
}