{
  "type": "Feature",
  "properties": {
    "gn:admin1_code":"0.0",
    "gn:asciiname":"Hwangnyong-ni",
    "gn:country_code":"KP",
    "gn:dem":47,
    "gn:feature_class":"P",
    "gn:feature_code":"PPL",
    "gn:name":"Hwangnyong-ni",
    "gn:population":0,
    "gn:timezone":"Asia/Pyongyang",
    "iso:country":"KP",
    "name:kor_x_preferred":[
        "\ud669\ub8e1\ub9ac"
    ],
    "wof:name":"Hwangnyong-ni",
    "wof:placetype":"locality"
},
  "geometry": {"coordinates":[126.26667,38.11667],"type":"Point"}
}