{
  "type": "Feature",
  "properties": {
    "gn:admin1_code":"7.0",
    "gn:asciiname":"Naegun",
    "gn:country_code":"KP",
    "gn:dem":89,
    "gn:feature_class":"P",
    "gn:feature_code":"PPL",
    "gn:name":"Naeg\u016dn",
    "gn:population":0,
    "gn:timezone":"Asia/Pyongyang",
    "iso:country":"KP",
    "wof:name":"Naegun",
    "wof:placetype":"locality"
},
  "geometry": {"coordinates":[126.01861,38.32583],"type":"Point"}
}