{
  "type": "Feature",
  "properties": {
    "gn:admin1_code":"1.0",
    "gn:asciiname":"Sich'am",
    "gn:country_code":"KP",
    "gn:dem":396,
    "gn:feature_class":"P",
    "gn:feature_code":"PPL",
    "gn:name":"Sich\u2019am",
    "gn:population":0,
    "gn:timezone":"Asia/Pyongyang",
    "iso:country":"KP",
    "name:und_x_variant":[
        "\uc2e0\ucc38",
        "Sich\u2019am"
    ],
    "wof:name":"Sich'am",
    "wof:placetype":"locality"
},
  "geometry": {"coordinates":[126.65139000000001,40.265],"type":"Point"}
}