{
  "type": "Feature",
  "properties": {
    "gn:admin1_code":"6.0",
    "gn:asciiname":"Hangmyong-dong",
    "gn:country_code":"KP",
    "gn:dem":111,
    "gn:feature_class":"P",
    "gn:feature_code":"PPL",
    "gn:name":"Hangmy\u014fng-dong",
    "gn:population":0,
    "gn:timezone":"Asia/Pyongyang",
    "iso:country":"KP",
    "name:und_x_variant":[
        "\ud559\uba85\ub3d9",
        "Hangmy\u014fng-dong"
    ],
    "wof:name":"Hangmyong-dong",
    "wof:placetype":"locality"
},
  "geometry": {"coordinates":[125.38778000000001,38.22333],"type":"Point"}
}