{
  "type": "Feature",
  "properties": {
    "gn:admin1_code":"9.0",
    "gn:admin2_code":"1875980",
    "gn:asciiname":"Paegyang-ni",
    "gn:country_code":"KP",
    "gn:dem":320,
    "gn:feature_class":"P",
    "gn:feature_code":"PPL",
    "gn:name":"Paegyang-ni",
    "gn:population":0,
    "gn:timezone":"Asia/Pyongyang",
    "iso:country":"KP",
    "name:eng_x_preferred":[
        "Paegyang"
    ],
    "name:eng_x_variant":[
        "Paegyang-ni"
    ],
    "wof:name":"Paegyang",
    "wof:placetype":"locality"
},
  "geometry": {"coordinates":[127.54472,38.39944],"type":"Point"}
}