{
  "type": "Feature",
  "properties": {
    "gn:admin1_code":"12.0",
    "gn:admin2_code":"S\u016dngho-guy\u014fk",
    "gn:asciiname":"O-dong",
    "gn:country_code":"KP",
    "gn:dem":75,
    "gn:feature_class":"P",
    "gn:feature_code":"PPL",
    "gn:name":"O-dong",
    "gn:population":0,
    "gn:timezone":"Asia/Pyongyang",
    "iso:country":"KP",
    "wof:name":"O-dong",
    "wof:placetype":"locality"
},
  "geometry": {"coordinates":[126.03749999999999,39.06833],"type":"Point"}
}