{
  "type": "Feature",
  "properties": {
    "gn:admin1_code":"12.0",
    "gn:asciiname":"Namgung-maul",
    "gn:country_code":"KP",
    "gn:dem":53,
    "gn:feature_class":"P",
    "gn:feature_code":"PPL",
    "gn:name":"Namgung-ma\u016dl",
    "gn:population":0,
    "gn:timezone":"Asia/Pyongyang",
    "iso:country":"KP",
    "name:kor_x_preferred":[
        "Namgung-ma\u016dl"
    ],
    "name:kor_x_variant":[
        "\ub0a8\uad81\ub9c8\uc744",
        "\ub0a8\uad81\ub9ac",
        "\ub0a8\uc0b0\ubaa8\ub8e8"
    ],
    "name:und_x_variant":[
        "Namgungni-San\u016dm-dong",
        "Namgung-ni",
        "Namsanmoru",
        "Namgungmaeul"
    ],
    "wof:name":"Namgung-maul",
    "wof:placetype":"locality"
},
  "geometry": {"coordinates":[125.76497000000001,39.14622],"type":"Point"}
}