{
  "type": "Feature",
  "properties": {
    "gn:admin1_code":"6.0",
    "gn:asciiname":"Mokhui-dong",
    "gn:country_code":"KP",
    "gn:dem":124,
    "gn:feature_class":"P",
    "gn:feature_code":"PPL",
    "gn:name":"Mokh\u016di-dong",
    "gn:population":0,
    "gn:timezone":"Asia/Pyongyang",
    "iso:country":"KP",
    "wof:name":"Mokhui-dong",
    "wof:placetype":"locality"
},
  "geometry": {"coordinates":[125.01528,38.275],"type":"Point"}
}