{
  "type": "Feature",
  "properties": {
    "gn:admin1_code":"15.0",
    "gn:asciiname":"Kalch'ol-li",
    "gn:country_code":"KP",
    "gn:dem":18,
    "gn:feature_class":"P",
    "gn:feature_code":"PPL",
    "gn:name":"Kalch\u2019\u014fl-li",
    "gn:population":0,
    "gn:timezone":"Asia/Pyongyang",
    "iso:country":"KP",
    "name:und_x_variant":[
        "Kalch\u2019\u014fn-ni",
        "Kalch\u2019\u014fl-li"
    ],
    "wof:name":"Kalch'ol-li",
    "wof:placetype":"locality"
},
  "geometry": {"coordinates":[125.4175,38.79556],"type":"Point"}
}