{
  "type": "Feature",
  "properties": {
    "gn:admin1_code":"1.0",
    "gn:asciiname":"Changsong-ni",
    "gn:country_code":"KP",
    "gn:dem":349,
    "gn:feature_class":"P",
    "gn:feature_code":"PPL",
    "gn:name":"Changs\u014fng-ni",
    "gn:population":0,
    "gn:timezone":"Asia/Pyongyang",
    "iso:country":"KP",
    "name:und_x_variant":[
        "Ch\u014dj\u014d-d\u014d",
        "Changs\u014fng-dong",
        "Changs\u014fngdong-ch\u2019angp\u2019yong",
        "\uc7a5\uc131\ub9ac",
        "Changs\u014fng-ni"
    ],
    "wof:name":"Changsong-ni",
    "wof:placetype":"locality"
},
  "geometry": {"coordinates":[126.71639,41.73556],"type":"Point"}
}