{
  "type": "Feature",
  "properties": {
    "gn:admin1_code":"11.0",
    "gn:asciiname":"Tongdonghagong-ni",
    "gn:country_code":"KP",
    "gn:dem":62,
    "gn:feature_class":"P",
    "gn:feature_code":"PPL",
    "gn:name":"Tongdonghagong-ni",
    "gn:population":0,
    "gn:timezone":"Asia/Pyongyang",
    "iso:country":"KP",
    "name:eng_x_preferred":[
        "Tongdonghagong"
    ],
    "name:eng_x_variant":[
        "Tongdonghagong-ni"
    ],
    "name:und_x_variant":[
        "\ub3d9\ub3d9\ud558\uace1\ub9ac",
        "Tongdonghagong-ni"
    ],
    "wof:name":"Tongdonghagong",
    "wof:placetype":"locality"
},
  "geometry": {"coordinates":[124.64722,40.08111],"type":"Point"}
}