{
  "type": "Feature",
  "properties": {
    "gn:admin1_code":"15.0",
    "gn:asciiname":"Ch'ongyong-ni",
    "gn:country_code":"KP",
    "gn:dem":50,
    "gn:feature_class":"P",
    "gn:feature_code":"PPL",
    "gn:name":"Ch\u2019\u014fngyong-ni",
    "gn:population":0,
    "gn:timezone":"Asia/Pyongyang",
    "iso:country":"KP",
    "name:eng_x_preferred":[
        "Ch'ongyong"
    ],
    "name:eng_x_variant":[
        "Ch'ongyong-ni"
    ],
    "wof:name":"Ch'ongyong",
    "wof:placetype":"locality"
},
  "geometry": {"coordinates":[125.90361,39.31694],"type":"Point"}
}