{
  "type": "Feature",
  "properties": {
    "gn:admin1_code":"9.0",
    "gn:asciiname":"Sagijom-ni",
    "gn:country_code":"KP",
    "gn:dem":436,
    "gn:feature_class":"P",
    "gn:feature_code":"PPL",
    "gn:name":"Sagij\u014fm-ni",
    "gn:population":0,
    "gn:timezone":"Asia/Pyongyang",
    "iso:country":"KP",
    "name:und_x_variant":[
        "\uc0ac\uae30\uc810\ub9ac",
        "Sagij\u014fm-ni"
    ],
    "wof:name":"Sagijom-ni",
    "wof:placetype":"locality"
},
  "geometry": {"coordinates":[127.78943999999998,38.62139000000001],"type":"Point"}
}