{
  "type": "Feature",
  "properties": {
    "gn:admin1_code":"0.0",
    "gn:asciiname":"Sa-dong",
    "gn:country_code":"KP",
    "gn:dem":325,
    "gn:feature_class":"P",
    "gn:feature_code":"PPL",
    "gn:name":"Sa-dong",
    "gn:population":0,
    "gn:timezone":"Asia/Pyongyang",
    "iso:country":"KP",
    "name:kor_x_preferred":[
        "\uc0ac\ub3d9"
    ],
    "wof:name":"Sa-dong",
    "wof:placetype":"locality"
},
  "geometry": {"coordinates":[125.28333000000001,38.53333],"type":"Point"}
}