{
  "type": "Feature",
  "properties": {
    "gn:admin1_code":"7.0",
    "gn:asciiname":"Hwawol-li",
    "gn:country_code":"KP",
    "gn:dem":115,
    "gn:feature_class":"P",
    "gn:feature_code":"PPL",
    "gn:name":"Hwaw\u014fl-li",
    "gn:population":0,
    "gn:timezone":"Asia/Pyongyang",
    "iso:country":"KP",
    "wof:name":"Hwawol-li",
    "wof:placetype":"locality"
},
  "geometry": {"coordinates":[126.08750000000001,38.34556],"type":"Point"}
}