{
  "type": "Feature",
  "properties": {
    "gn:admin1_code":"17.0",
    "gn:asciiname":"Sosan-dong",
    "gn:country_code":"KP",
    "gn:dem":91,
    "gn:feature_class":"P",
    "gn:feature_code":"PPL",
    "gn:name":"Sosan-dong",
    "gn:population":0,
    "gn:timezone":"Asia/Pyongyang",
    "iso:country":"KP",
    "name:und_x_variant":[
        "\uc18c\uc0b0\ub3d9",
        "Sosan-dong"
    ],
    "wof:name":"Sosan-dong",
    "wof:placetype":"locality"
},
  "geometry": {"coordinates":[129.13722000000001,40.67444],"type":"Point"}
}