{
  "type": "Feature",
  "properties": {
    "gn:admin1_code":"13.0",
    "gn:asciiname":"Namyang-dong",
    "gn:country_code":"KP",
    "gn:dem":1095,
    "gn:feature_class":"P",
    "gn:feature_code":"PPL",
    "gn:name":"Namyang-dong",
    "gn:population":0,
    "gn:timezone":"Asia/Pyongyang",
    "iso:country":"KP",
    "wof:name":"Namyang-dong",
    "wof:placetype":"locality"
},
  "geometry": {"coordinates":[128.46556000000001,41.03306],"type":"Point"}
}