{
  "type": "Feature",
  "properties": {
    "gn:admin1_code":"9.0",
    "gn:admin2_code":"P\u2019y\u014fnggang-gun",
    "gn:asciiname":"Kalgungjong",
    "gn:country_code":"KP",
    "gn:dem":357,
    "gn:feature_class":"P",
    "gn:feature_code":"PPL",
    "gn:name":"Kalgungj\u014fng",
    "gn:population":0,
    "gn:timezone":"Asia/Pyongyang",
    "iso:country":"KP",
    "wof:name":"Kalgungjong",
    "wof:placetype":"locality"
},
  "geometry": {"coordinates":[127.31861000000001,38.45917],"type":"Point"}
}