{
  "type": "Feature",
  "properties": {
    "gn:admin1_code":"1.0",
    "gn:asciiname":"Ungdongch'am",
    "gn:country_code":"KP",
    "gn:dem":536,
    "gn:feature_class":"P",
    "gn:feature_code":"PPL",
    "gn:name":"\u016cngdongch\u2019am",
    "gn:population":0,
    "gn:timezone":"Asia/Pyongyang",
    "iso:country":"KP",
    "name:und_x_variant":[
        "\uc751\ub3d9\ucc38",
        "\u016cngdongch\u2019am"
    ],
    "wof:name":"Ungdongch'am",
    "wof:placetype":"locality"
},
  "geometry": {"coordinates":[126.15778,40.39278],"type":"Point"}
}