{
  "type": "Feature",
  "properties": {
    "gn:admin1_code":"7.0",
    "gn:admin2_code":"T\u2019osan-gun",
    "gn:asciiname":"Changyang-dong",
    "gn:country_code":"KP",
    "gn:dem":95,
    "gn:feature_class":"P",
    "gn:feature_code":"PPL",
    "gn:name":"Changyang-dong",
    "gn:population":0,
    "gn:timezone":"Asia/Pyongyang",
    "iso:country":"KP",
    "wof:name":"Changyang-dong",
    "wof:placetype":"locality"
},
  "geometry": {"coordinates":[126.81806,38.25],"type":"Point"}
}