{
  "type": "Feature",
  "properties": {
    "gn:admin1_code":"12.0",
    "gn:asciiname":"Sangsam-ni",
    "gn:country_code":"KP",
    "gn:dem":15,
    "gn:feature_class":"P",
    "gn:feature_code":"PPL",
    "gn:name":"Sangsam-ni",
    "gn:population":0,
    "gn:timezone":"Asia/Pyongyang",
    "iso:country":"KP",
    "name:kor_x_preferred":[
        "\uc0c1\uc0bc\ub9ac"
    ],
    "name:und_x_variant":[
        "Sangsamni"
    ],
    "wof:name":"Sangsam-ni",
    "wof:placetype":"locality"
},
  "geometry": {"coordinates":[125.66643000000001,38.86673],"type":"Point"}
}