{
  "type": "Feature",
  "properties": {
    "gn:admin1_code":"11.0",
    "gn:asciiname":"Changhang-dong",
    "gn:country_code":"KP",
    "gn:dem":68,
    "gn:feature_class":"P",
    "gn:feature_code":"PPL",
    "gn:name":"Changhang-dong",
    "gn:population":0,
    "gn:timezone":"Asia/Pyongyang",
    "iso:country":"KP",
    "name:kor_x_preferred":[
        "\uc7a5\ud56d\ub3d9"
    ],
    "wof:name":"Changhang-dong",
    "wof:placetype":"locality"
},
  "geometry": {"coordinates":[124.81722000000001,39.89333],"type":"Point"}
}