{
  "type": "Feature",
  "properties": {
    "gn:admin1_code":"0.0",
    "gn:asciiname":"Tura-dong",
    "gn:country_code":"KP",
    "gn:dem":500,
    "gn:feature_class":"P",
    "gn:feature_code":"PPL",
    "gn:name":"Tura-dong",
    "gn:population":0,
    "gn:timezone":"Asia/Pyongyang",
    "iso:country":"KP",
    "name:kor_x_preferred":[
        "\ub450\ub77c\ub3d9"
    ],
    "wof:name":"Tura-dong",
    "wof:placetype":"locality"
},
  "geometry": {"coordinates":[125.36667,38.51667],"type":"Point"}
}