{
  "type": "Feature",
  "properties": {
    "gn:admin1_code":"11.0",
    "gn:asciiname":"Namho-ri",
    "gn:cc2":"KP",
    "gn:country_code":"KP",
    "gn:dem":25,
    "gn:feature_class":"P",
    "gn:feature_code":"PPL",
    "gn:name":"Namho-ri",
    "gn:population":0,
    "gn:timezone":"Asia/Pyongyang",
    "iso:country":"KP",
    "name:kor_x_preferred":[
        "\ub0a8\ud638\ub9ac"
    ],
    "name:und_x_variant":[
        "Namho-dong",
        "Namho-ri"
    ],
    "wof:name":"Namho-ri",
    "wof:placetype":"locality"
},
  "geometry": {"coordinates":[125.21167,39.62056],"type":"Point"}
}