{
  "type": "Feature",
  "properties": {
    "gn:admin1_code":"11.0",
    "gn:asciiname":"Nunggong-ni",
    "gn:country_code":"KP",
    "gn:dem":179,
    "gn:feature_class":"P",
    "gn:feature_code":"PPL",
    "gn:name":"N\u016dnggong-ni",
    "gn:population":0,
    "gn:timezone":"Asia/Pyongyang",
    "iso:country":"KP",
    "name:eng_x_preferred":[
        "Nunggong"
    ],
    "name:eng_x_variant":[
        "Nunggong-ni"
    ],
    "name:und_x_variant":[
        "\ub2a5\uace1\ub9ac",
        "N\u016dnggong-ni"
    ],
    "wof:name":"Nunggong",
    "wof:placetype":"locality"
},
  "geometry": {"coordinates":[124.76278000000001,40.195],"type":"Point"}
}