{
  "type": "Feature",
  "properties": {
    "gn:admin1_code":"9.0",
    "gn:asciiname":"Yoam-dong",
    "gn:country_code":"KP",
    "gn:dem":71,
    "gn:feature_class":"P",
    "gn:feature_code":"PPL",
    "gn:name":"Y\u014fam-dong",
    "gn:population":0,
    "gn:timezone":"Asia/Pyongyang",
    "iso:country":"KP",
    "wof:name":"Yoam-dong",
    "wof:placetype":"locality"
},
  "geometry": {"coordinates":[127.78888999999999,39.02167],"type":"Point"}
}