{
  "type": "Feature",
  "properties": {
    "gn:admin1_code":"1.0",
    "gn:asciiname":"Yongma-dong",
    "gn:country_code":"KP",
    "gn:dem":886,
    "gn:feature_class":"P",
    "gn:feature_code":"PPL",
    "gn:name":"Yongma-dong",
    "gn:population":0,
    "gn:timezone":"Asia/Pyongyang",
    "iso:country":"KP",
    "name:kor_x_preferred":[
        "\ub8e1\ub9c8\ub3d9"
    ],
    "name:kor_x_variant":[
        "Yongmach\u2019am",
        "\uc6a9\ub9c8\ucc38"
    ],
    "name:und_x_variant":[
        "Yongma-dong"
    ],
    "wof:name":"Yongma-dong",
    "wof:placetype":"locality"
},
  "geometry": {"coordinates":[126.67506000000002,40.66278],"type":"Point"}
}