{
  "type": "Feature",
  "properties": {
    "gn:admin1_code":"1.0",
    "gn:asciiname":"Ha-dong",
    "gn:country_code":"KP",
    "gn:dem":295,
    "gn:feature_class":"P",
    "gn:feature_code":"PPL",
    "gn:name":"Ha-dong",
    "gn:population":0,
    "gn:timezone":"Asia/Pyongyang",
    "iso:country":"KP",
    "name:und_x_variant":[
        "\ud558\ub3d9",
        "Ha-dong"
    ],
    "wof:name":"Ha-dong",
    "wof:placetype":"locality"
},
  "geometry": {"coordinates":[126.59139,40.97944],"type":"Point"}
}