{
  "type": "Feature",
  "properties": {
    "gn:admin1_code":"0.0",
    "gn:asciiname":"Yonbong",
    "gn:country_code":"KP",
    "gn:dem":86,
    "gn:feature_class":"P",
    "gn:feature_code":"PPL",
    "gn:name":"Y\u014fnbong",
    "gn:population":0,
    "gn:timezone":"Asia/Pyongyang",
    "iso:country":"KP",
    "name:kor_x_preferred":[
        "\uc5f0\ubd09"
    ],
    "name:und_x_variant":[
        "Y\u014fnbong"
    ],
    "wof:name":"Yonbong",
    "wof:placetype":"locality"
},
  "geometry": {"coordinates":[125.73333,38.16667],"type":"Point"}
}