{
  "type": "Feature",
  "properties": {
    "gn:admin1_code":"15.0",
    "gn:admin2_code":"1871865",
    "gn:asciiname":"Wono-ri",
    "gn:country_code":"KP",
    "gn:dem":43,
    "gn:feature_class":"P",
    "gn:feature_code":"PPL",
    "gn:name":"W\u014fno-ri",
    "gn:population":0,
    "gn:timezone":"Asia/Pyongyang",
    "iso:country":"KP",
    "wof:name":"Wono-ri",
    "wof:placetype":"locality"
},
  "geometry": {"coordinates":[125.41139,39.25472],"type":"Point"}
}