{
  "type": "Feature",
  "properties": {
    "gn:admin1_code":"6.0",
    "gn:asciiname":"Kori-dong",
    "gn:country_code":"KP",
    "gn:dem":7,
    "gn:feature_class":"P",
    "gn:feature_code":"PPL",
    "gn:name":"K\u014fri-dong",
    "gn:population":0,
    "gn:timezone":"Asia/Pyongyang",
    "iso:country":"KP",
    "name:kor_x_preferred":[
        "\uac70\ub9ac\ub3d9"
    ],
    "name:kor_x_variant":[
        "K\u014fri-dong"
    ],
    "wof:name":"Kori-dong",
    "wof:placetype":"locality"
},
  "geometry": {"coordinates":[125.01528,37.95111],"type":"Point"}
}