{
  "type": "Feature",
  "properties": {
    "gn:admin1_code":"0.0",
    "gn:asciiname":"Sogumdok",
    "gn:cc2":"KP",
    "gn:country_code":"KP",
    "gn:dem":59,
    "gn:feature_class":"P",
    "gn:feature_code":"PPL",
    "gn:name":"Sog\u016dmd\u014fk",
    "gn:population":0,
    "gn:timezone":"Asia/Pyongyang",
    "iso:country":"KP",
    "name:kor_x_preferred":[
        "\uc18c\uae08\ub355"
    ],
    "name:und_x_variant":[
        "Sogimd\u014fk",
        "Sog\u016dmd\u014fk"
    ],
    "wof:name":"Sogumdok",
    "wof:placetype":"locality"
},
  "geometry": {"coordinates":[125.43333,37.75],"type":"Point"}
}