{
  "type": "Feature",
  "properties": {
    "gn:admin1_code":"15.0",
    "gn:asciiname":"Chungsokhwa-ri",
    "gn:country_code":"KP",
    "gn:dem":52,
    "gn:feature_class":"P",
    "gn:feature_code":"PPL",
    "gn:name":"Chungs\u014fkhwa-ri",
    "gn:population":0,
    "gn:timezone":"Asia/Pyongyang",
    "iso:country":"KP",
    "wof:name":"Chungsokhwa-ri",
    "wof:placetype":"locality"
},
  "geometry": {"coordinates":[125.58556000000002,39.1725],"type":"Point"}
}