{
  "type": "Feature",
  "properties": {
    "gn:admin1_code":"3.0",
    "gn:asciiname":"Ssanghung-ni",
    "gn:country_code":"KP",
    "gn:dem":17,
    "gn:feature_class":"P",
    "gn:feature_code":"PPL",
    "gn:name":"Ssangh\u016dng-ni",
    "gn:population":0,
    "gn:timezone":"Asia/Pyongyang",
    "iso:country":"KP",
    "name:und_x_variant":[
        "Sangpyong",
        "Sangp\u2019y\u014fng-ni",
        "\uc30d\ud765\ub9ac",
        "Ssangh\u016dng-ni"
    ],
    "wof:name":"Ssanghung-ni",
    "wof:placetype":"locality"
},
  "geometry": {"coordinates":[127.31833,39.53278],"type":"Point"}
}