{
  "type": "Feature",
  "properties": {
    "gn:admin1_code":"15.0",
    "gn:asciiname":"Kurigae",
    "gn:country_code":"KP",
    "gn:dem":6,
    "gn:feature_class":"P",
    "gn:feature_code":"PPL",
    "gn:name":"Kurigae",
    "gn:population":0,
    "gn:timezone":"Asia/Pyongyang",
    "iso:country":"KP",
    "name:kor_x_preferred":[
        "\uad6c\ub9ac\uac1c"
    ],
    "name:und_x_variant":[
        "Kurikae"
    ],
    "wof:name":"Kurigae",
    "wof:placetype":"locality"
},
  "geometry": {"coordinates":[125.38333,39.20083],"type":"Point"}
}