{
  "type": "Feature",
  "properties": {
    "gn:admin1_code":"6.0",
    "gn:asciiname":"Hagok",
    "gn:country_code":"KP",
    "gn:dem":35,
    "gn:feature_class":"P",
    "gn:feature_code":"PPL",
    "gn:name":"Hagok",
    "gn:population":0,
    "gn:timezone":"Asia/Pyongyang",
    "iso:country":"KP",
    "name:und_x_variant":[
        "\ud558\uace1",
        "Hagok"
    ],
    "wof:name":"Hagok",
    "wof:placetype":"locality"
},
  "geometry": {"coordinates":[125.12139000000001,38.51083],"type":"Point"}
}