{
  "type": "Feature",
  "properties": {
    "gn:admin1_code":"6.0",
    "gn:asciiname":"Chop'o-dong",
    "gn:country_code":"KP",
    "gn:dem":14,
    "gn:feature_class":"P",
    "gn:feature_code":"PPL",
    "gn:name":"Chop\u2019o-dong",
    "gn:population":0,
    "gn:timezone":"Asia/Pyongyang",
    "iso:country":"KP",
    "name:und_x_variant":[
        "Joho-d\u014d",
        "Chop\u2019o-dong"
    ],
    "wof:name":"Chop'o-dong",
    "wof:placetype":"locality"
},
  "geometry": {"coordinates":[126.38443999999998,38.13778],"type":"Point"}
}