{
  "type": "Feature",
  "properties": {
    "gn:admin1_code":"15.0",
    "gn:asciiname":"Ch'on'gi-ri",
    "gn:country_code":"KP",
    "gn:dem":235,
    "gn:feature_class":"P",
    "gn:feature_code":"PPL",
    "gn:name":"Ch\u2019\u014fn\u2019gi-ri",
    "gn:population":0,
    "gn:timezone":"Asia/Pyongyang",
    "iso:country":"KP",
    "name:kor_x_preferred":[
        "\ucc9c\uae30\ub9ac"
    ],
    "name:kor_x_variant":[
        "Ch\u2019\u014fn\u2019gi-ri"
    ],
    "wof:name":"Ch'on'gi-ri",
    "wof:placetype":"locality"
},
  "geometry": {"coordinates":[126.46889,39.25],"type":"Point"}
}