{
  "type": "Feature",
  "properties": {
    "gn:admin1_code":"11.0",
    "gn:asciiname":"Nammun-gol",
    "gn:country_code":"KP",
    "gn:dem":29,
    "gn:feature_class":"P",
    "gn:feature_code":"PPL",
    "gn:name":"Nammun-gol",
    "gn:population":0,
    "gn:timezone":"Asia/Pyongyang",
    "iso:country":"KP",
    "name:und_x_variant":[
        "\ub0a8\ubb38\uace8",
        "Nammun-gol"
    ],
    "wof:name":"Nammun-gol",
    "wof:placetype":"locality"
},
  "geometry": {"coordinates":[124.56638999999998,40.08889],"type":"Point"}
}