{
  "type": "Feature",
  "properties": {
    "gn:admin1_code":"1.0",
    "gn:asciiname":"Mason-gol",
    "gn:country_code":"KP",
    "gn:dem":417,
    "gn:feature_class":"P",
    "gn:feature_code":"PPL",
    "gn:name":"Mas\u014fn-gol",
    "gn:population":0,
    "gn:timezone":"Asia/Pyongyang",
    "iso:country":"KP",
    "name:und_x_variant":[
        "\ub9c8\uc120\uace8",
        "Mas\u014fn-gol"
    ],
    "wof:name":"Mason-gol",
    "wof:placetype":"locality"
},
  "geometry": {"coordinates":[126.44750000000001,40.61694],"type":"Point"}
}