{
  "type": "Feature",
  "properties": {
    "gn:admin1_code":"15.0",
    "gn:asciiname":"Ka-ri",
    "gn:country_code":"KP",
    "gn:dem":278,
    "gn:feature_class":"P",
    "gn:feature_code":"PPL",
    "gn:name":"Ka-ri",
    "gn:population":0,
    "gn:timezone":"Asia/Pyongyang",
    "iso:country":"KP",
    "name:kor_x_preferred":[
        "\uac00\ub9ac"
    ],
    "wof:name":"Ka-ri",
    "wof:placetype":"locality"
},
  "geometry": {"coordinates":[126.46528000000001,39.45833],"type":"Point"}
}