{
  "type": "Feature",
  "properties": {
    "gn:admin1_code":"1.0",
    "gn:asciiname":"Soyoksu-ri",
    "gn:country_code":"KP",
    "gn:dem":511,
    "gn:feature_class":"P",
    "gn:feature_code":"PPL",
    "gn:name":"Soy\u014fksu-ri",
    "gn:population":0,
    "gn:timezone":"Asia/Pyongyang",
    "iso:country":"KP",
    "name:und_x_variant":[
        "Soy\u014fksu-ri",
        "\uc18c\uc5ed\uc218\ub9ac"
    ],
    "wof:name":"Soyoksu-ri",
    "wof:placetype":"locality"
},
  "geometry": {"coordinates":[126.56278,41.28139],"type":"Point"}
}