{
  "type": "Feature",
  "properties": {
    "gn:admin1_code":"9.0",
    "gn:asciiname":"Kosari-gol",
    "gn:cc2":"KP",
    "gn:country_code":"KP",
    "gn:dem":463,
    "gn:feature_class":"P",
    "gn:feature_code":"PPL",
    "gn:name":"Kosari-gol",
    "gn:population":0,
    "gn:timezone":"Asia/Pyongyang",
    "iso:country":"KP",
    "name:und_x_variant":[
        "Kosari-kol",
        "\uace0\uc0ac\ub9ac\uace8",
        "Kosari-gol"
    ],
    "wof:name":"Kosari-gol",
    "wof:placetype":"locality"
},
  "geometry": {"coordinates":[127.57778,38.68917],"type":"Point"}
}