{
  "type": "Feature",
  "properties": {
    "gn:admin1_code":"9.0",
    "gn:asciiname":"Sanmak-kol",
    "gn:country_code":"KP",
    "gn:dem":489,
    "gn:feature_class":"P",
    "gn:feature_code":"PPL",
    "gn:name":"Sanmak-kol",
    "gn:population":0,
    "gn:timezone":"Asia/Pyongyang",
    "iso:country":"KP",
    "wof:name":"Sanmak-kol",
    "wof:placetype":"locality"
},
  "geometry": {"coordinates":[127.36694,38.52694],"type":"Point"}
}