{
  "type": "Feature",
  "properties": {
    "gn:admin1_code":"1.0",
    "gn:asciiname":"Chungduru",
    "gn:country_code":"KP",
    "gn:dem":351,
    "gn:feature_class":"P",
    "gn:feature_code":"PPL",
    "gn:name":"Chungd\u016dru",
    "gn:population":0,
    "gn:timezone":"Asia/Pyongyang",
    "iso:country":"KP",
    "name:und_x_variant":[
        "\uc911\ud3c9",
        "Chungp\u2019y\u014fng",
        "Chungd\u016dru",
        "\uc911\ub4dc\ub8e8",
        "Chungd\u016dl",
        "Chungp\u2019y\u014fnch\u2019am",
        "\uc911\ub4e4",
        "\uc911\ud3b8\ucc38"
    ],
    "wof:name":"Chungduru",
    "wof:placetype":"locality"
},
  "geometry": {"coordinates":[126.46216,40.27865],"type":"Point"}
}