{
  "type": "Feature",
  "properties": {
    "gn:admin1_code":"11.0",
    "gn:asciiname":"T'apsang-dong",
    "gn:country_code":"KP",
    "gn:dem":6,
    "gn:feature_class":"P",
    "gn:feature_code":"PPL",
    "gn:name":"T\u2019apsang-dong",
    "gn:population":0,
    "gn:timezone":"Asia/Pyongyang",
    "iso:country":"KP",
    "name:und_x_variant":[
        "\ud0d1\uc0c1\ub3d9",
        "T\u2019apsang-dong"
    ],
    "wof:name":"T'apsang-dong",
    "wof:placetype":"locality"
},
  "geometry": {"coordinates":[124.44583,40.08889],"type":"Point"}
}