{
  "type": "Feature",
  "properties": {
    "gn:admin1_code":"17.0",
    "gn:asciiname":"Hadae-dong",
    "gn:country_code":"KP",
    "gn:dem":91,
    "gn:feature_class":"P",
    "gn:feature_code":"PPL",
    "gn:name":"Hadae-dong",
    "gn:population":0,
    "gn:timezone":"Asia/Pyongyang",
    "iso:country":"KP",
    "name:und_x_variant":[
        "\ud558\ub300\ub3d9",
        "Hadae-dong"
    ],
    "wof:name":"Hadae-dong",
    "wof:placetype":"locality"
},
  "geometry": {"coordinates":[129.55027999999999,41.21389],"type":"Point"}
}