{
  "type": "Feature",
  "properties": {
    "gn:admin1_code":"12.0",
    "gn:asciiname":"Ut-tong",
    "gn:country_code":"KP",
    "gn:dem":27,
    "gn:feature_class":"P",
    "gn:feature_code":"PPL",
    "gn:name":"Ut-tong",
    "gn:population":0,
    "gn:timezone":"Asia/Pyongyang",
    "iso:country":"KP",
    "name:und_x_variant":[
        "Sang-dong",
        "\uc6c3\ub3d9",
        "Ut-tong",
        "Utdong"
    ],
    "wof:name":"Ut-tong",
    "wof:placetype":"locality"
},
  "geometry": {"coordinates":[125.79049999999999,38.91477],"type":"Point"}
}