{
  "type": "Feature",
  "properties": {
    "gn:admin1_code":"11.0",
    "gn:asciiname":"Munam-ni",
    "gn:country_code":"KP",
    "gn:dem":49,
    "gn:feature_class":"P",
    "gn:feature_code":"PPL",
    "gn:name":"Munam-ni",
    "gn:population":0,
    "gn:timezone":"Asia/Pyongyang",
    "iso:country":"KP",
    "name:und_x_variant":[
        "\ubb38\uc554\ub9ac",
        "Munam-ni"
    ],
    "wof:name":"Munam-ni",
    "wof:placetype":"locality"
},
  "geometry": {"coordinates":[124.72556000000002,40.10361],"type":"Point"}
}