{
  "type": "Feature",
  "properties": {
    "gn:admin1_code":"9.0",
    "gn:asciiname":"Chongjagol",
    "gn:country_code":"KP",
    "gn:dem":573,
    "gn:feature_class":"P",
    "gn:feature_code":"PPL",
    "gn:name":"Ch\u014fngjagol",
    "gn:population":0,
    "gn:timezone":"Asia/Pyongyang",
    "iso:country":"KP",
    "name:kor_x_preferred":[
        "\uc815\uc790\uace8"
    ],
    "name:und_x_variant":[
        "Ch\u014fngja-dong",
        "Ch\u014fngjakol",
        "Ch\u014fngjagol"
    ],
    "wof:name":"Chongjagol",
    "wof:placetype":"locality"
},
  "geometry": {"coordinates":[127.57917,38.81333],"type":"Point"}
}