{
  "type": "Feature",
  "properties": {
    "gn:admin1_code":"3.0",
    "gn:asciiname":"Un'gok-tong",
    "gn:country_code":"KP",
    "gn:dem":608,
    "gn:feature_class":"P",
    "gn:feature_code":"PPL",
    "gn:name":"Un\u2019gok-tong",
    "gn:population":0,
    "gn:timezone":"Asia/Pyongyang",
    "iso:country":"KP",
    "name:und_x_variant":[
        "Un\u2019gok-nodongjagu",
        "Un\u2019gok",
        "\uc6b4\uace1\ub3d9",
        "Un\u2019gong-nodongjagu",
        "Un\u2019gok-tong"
    ],
    "wof:name":"Un'gok-tong",
    "wof:placetype":"locality"
},
  "geometry": {"coordinates":[126.82583,39.38444000000001],"type":"Point"}
}