{
  "type": "Feature",
  "properties": {
    "gn:admin1_code":"7.0",
    "gn:asciiname":"Kwang-dong",
    "gn:country_code":"KP",
    "gn:dem":77,
    "gn:feature_class":"P",
    "gn:feature_code":"PPL",
    "gn:name":"Kwang-dong",
    "gn:population":0,
    "gn:timezone":"Asia/Pyongyang",
    "iso:country":"KP",
    "name:und_x_variant":[
        "\uad11\ub3d9",
        "Kwang-dong"
    ],
    "wof:name":"Kwang-dong",
    "wof:placetype":"locality"
},
  "geometry": {"coordinates":[126.55138999999998,38.16778],"type":"Point"}
}