{
  "type": "Feature",
  "properties": {
    "gn:admin1_code":"12.0",
    "gn:asciiname":"Paekch'on",
    "gn:country_code":"KP",
    "gn:dem":49,
    "gn:feature_class":"P",
    "gn:feature_code":"PPL",
    "gn:name":"Paekch\u2019on",
    "gn:population":0,
    "gn:timezone":"Asia/Pyongyang",
    "iso:country":"KP",
    "name:und_x_variant":[
        "\ubc31\ucd0c",
        "Paekch\u2019on"
    ],
    "wof:name":"Paekch'on",
    "wof:placetype":"locality"
},
  "geometry": {"coordinates":[125.80528,38.84167],"type":"Point"}
}