{
  "type": "Feature",
  "properties": {
    "gn:admin1_code":"6.0",
    "gn:asciiname":"Hadobong",
    "gn:country_code":"KP",
    "gn:dem":88,
    "gn:feature_class":"P",
    "gn:feature_code":"PPL",
    "gn:name":"Hadobong",
    "gn:population":0,
    "gn:timezone":"Asia/Pyongyang",
    "iso:country":"KP",
    "name:kor_x_preferred":[
        "\ud558\ub3c4\ubd09"
    ],
    "wof:name":"Hadobong",
    "wof:placetype":"locality"
},
  "geometry": {"coordinates":[125.31222,38.2725],"type":"Point"}
}