{
  "type": "Feature",
  "properties": {
    "gn:admin1_code":"11.0",
    "gn:asciiname":"Omt'aegok",
    "gn:country_code":"KP",
    "gn:dem":288,
    "gn:feature_class":"P",
    "gn:feature_code":"PPL",
    "gn:name":"\u014emt\u2019aegok",
    "gn:population":0,
    "gn:timezone":"Asia/Pyongyang",
    "iso:country":"KP",
    "name:kor_x_preferred":[
        "\u014emt\u2019aegok"
    ],
    "name:kor_x_variant":[
        "\uc5c4\ud0dc\uace1"
    ],
    "wof:name":"Omt'aegok",
    "wof:placetype":"locality"
},
  "geometry": {"coordinates":[125.05611,39.94972],"type":"Point"}
}