{
  "type": "Feature",
  "properties": {
    "gn:admin1_code":"3.0",
    "gn:asciiname":"Yongsu-gol",
    "gn:country_code":"KP",
    "gn:dem":1407,
    "gn:feature_class":"P",
    "gn:feature_code":"PPL",
    "gn:name":"Yongsu-gol",
    "gn:population":0,
    "gn:timezone":"Asia/Pyongyang",
    "iso:country":"KP",
    "name:und_x_variant":[
        "\uc6a9\uc218\uace8",
        "Yongsu-gol"
    ],
    "wof:name":"Yongsu-gol",
    "wof:placetype":"locality"
},
  "geometry": {"coordinates":[127.12300999999999,40.30885],"type":"Point"}
}