{
  "type": "Feature",
  "properties": {
    "gn:admin1_code":"6.0",
    "gn:asciiname":"Uyong-ni",
    "gn:country_code":"KP",
    "gn:dem":45,
    "gn:feature_class":"P",
    "gn:feature_code":"PPL",
    "gn:name":"Uy\u014fng-ni",
    "gn:population":0,
    "gn:timezone":"Asia/Pyongyang",
    "iso:country":"KP",
    "name:eng_x_preferred":[
        "Uyong"
    ],
    "name:eng_x_variant":[
        "Uyong-ni"
    ],
    "wof:name":"Uyong",
    "wof:placetype":"locality"
},
  "geometry": {"coordinates":[125.09972,38.50972],"type":"Point"}
}