{
  "type": "Feature",
  "properties": {
    "gn:admin1_code":"15.0",
    "gn:asciiname":"Igaegol",
    "gn:country_code":"KP",
    "gn:dem":401,
    "gn:feature_class":"P",
    "gn:feature_code":"PPL",
    "gn:name":"Igaegol",
    "gn:population":0,
    "gn:timezone":"Asia/Pyongyang",
    "iso:country":"KP",
    "name:kor_x_preferred":[
        "\uc774\uac1c\uace8"
    ],
    "wof:name":"Igaegol",
    "wof:placetype":"locality"
},
  "geometry": {"coordinates":[126.38167,39.70861],"type":"Point"}
}