{
  "type": "Feature",
  "properties": {
    "gn:admin1_code":"7.0",
    "gn:asciiname":"Yangji-dong",
    "gn:country_code":"KP",
    "gn:dem":153,
    "gn:feature_class":"P",
    "gn:feature_code":"PPL",
    "gn:name":"Yangji-dong",
    "gn:population":0,
    "gn:timezone":"Asia/Pyongyang",
    "iso:country":"KP",
    "name:kor_x_preferred":[
        "\uc591\uc9c0\ub3d9"
    ],
    "wof:name":"Yangji-dong",
    "wof:placetype":"locality"
},
  "geometry": {"coordinates":[126.62611,38.90778],"type":"Point"}
}