{
  "type": "Feature",
  "properties": {
    "gn:admin1_code":"6.0",
    "gn:asciiname":"Kumam-dong",
    "gn:country_code":"KP",
    "gn:dem":59,
    "gn:feature_class":"P",
    "gn:feature_code":"PPL",
    "gn:name":"K\u016dmam-dong",
    "gn:population":0,
    "gn:timezone":"Asia/Pyongyang",
    "iso:country":"KP",
    "name:kor_x_preferred":[
        "\uae08\uc548\ub3d9"
    ],
    "name:kor_x_variant":[
        "K\u016dmam-dong"
    ],
    "wof:name":"Kumam-dong",
    "wof:placetype":"locality"
},
  "geometry": {"coordinates":[125.36278,38.47861],"type":"Point"}
}