{
  "type": "Feature",
  "properties": {
    "gn:admin1_code":"7.0",
    "gn:admin2_code":"T\u2019osan-gun",
    "gn:asciiname":"Songt'al-li",
    "gn:country_code":"KP",
    "gn:dem":116,
    "gn:feature_class":"P",
    "gn:feature_code":"PPL",
    "gn:name":"Songt\u2019al-li",
    "gn:population":0,
    "gn:timezone":"Asia/Pyongyang",
    "iso:country":"KP",
    "name:und_x_variant":[
        "Songt\u2019an-ni",
        "Songt\u2019al-li"
    ],
    "wof:name":"Songt'al-li",
    "wof:placetype":"locality"
},
  "geometry": {"coordinates":[126.71111000000001,38.24556],"type":"Point"}
}