{
  "type": "Feature",
  "properties": {
    "gn:admin1_code":"6.0",
    "gn:asciiname":"Songjong-dong",
    "gn:country_code":"KP",
    "gn:dem":129,
    "gn:feature_class":"P",
    "gn:feature_code":"PPL",
    "gn:name":"Songj\u014fng-dong",
    "gn:population":0,
    "gn:timezone":"Asia/Pyongyang",
    "iso:country":"KP",
    "wof:name":"Songjong-dong",
    "wof:placetype":"locality"
},
  "geometry": {"coordinates":[125.68583,38.22528],"type":"Point"}
}