{
  "type": "Feature",
  "properties": {
    "gn:admin1_code":"11.0",
    "gn:asciiname":"Onp'ung-ni",
    "gn:country_code":"KP",
    "gn:dem":264,
    "gn:feature_class":"P",
    "gn:feature_code":"PPL",
    "gn:name":"Onp\u2019ung-ni",
    "gn:population":0,
    "gn:timezone":"Asia/Pyongyang",
    "iso:country":"KP",
    "wof:name":"Onp'ung-ni",
    "wof:placetype":"locality"
},
  "geometry": {"coordinates":[125.06861000000001,40.31833],"type":"Point"}
}