{
  "type": "Feature",
  "properties": {
    "gn:admin1_code":"6.0",
    "gn:asciiname":"T'agyong-ni",
    "gn:country_code":"KP",
    "gn:dem":51,
    "gn:feature_class":"P",
    "gn:feature_code":"PPL",
    "gn:name":"T\u2019agy\u014fng-ni",
    "gn:population":0,
    "gn:timezone":"Asia/Pyongyang",
    "iso:country":"KP",
    "name:kor_x_preferred":[
        "\ud0c0\uacbd\ub9ac"
    ],
    "name:und_x_variant":[
        "Takuei-ri",
        "Tekiei-ri",
        "Tangny\u014fng-ni",
        "T\u2019agy\u014fng-ni"
    ],
    "wof:name":"T'agyong-ni",
    "wof:placetype":"locality"
},
  "geometry": {"coordinates":[126.0325,38.07333],"type":"Point"}
}