{
  "type": "Feature",
  "properties": {
    "gn:admin1_code":"1.0",
    "gn:asciiname":"Hongdo-dong",
    "gn:country_code":"KP",
    "gn:dem":441,
    "gn:feature_class":"P",
    "gn:feature_code":"PPL",
    "gn:name":"Hongdo-dong",
    "gn:population":0,
    "gn:timezone":"Asia/Pyongyang",
    "iso:country":"KP",
    "name:und_x_variant":[
        "K\u014dt\u014d-d\u014d",
        "Koto-ri",
        "\ud64d\ub3c4\ub3d9",
        "Hongdo-dong"
    ],
    "wof:name":"Hongdo-dong",
    "wof:placetype":"locality"
},
  "geometry": {"coordinates":[126.33981,40.78794],"type":"Point"}
}