{
  "type": "Feature",
  "properties": {
    "gn:admin1_code":"1.0",
    "gn:asciiname":"Pusongdongoguch'am",
    "gn:country_code":"KP",
    "gn:dem":128,
    "gn:feature_class":"P",
    "gn:feature_code":"PPL",
    "gn:name":"Pus\u014fngdong\u014fguch\u2019am",
    "gn:population":0,
    "gn:timezone":"Asia/Pyongyang",
    "iso:country":"KP",
    "name:und_x_variant":[
        "\ubd80\uc131\ub3d9\uc5b4\uad6c\ucc38",
        "Pus\u014fngdong\u014fguch\u2019am"
    ],
    "wof:name":"Pusongdongoguch'am",
    "wof:placetype":"locality"
},
  "geometry": {"coordinates":[126.24583,40.09194],"type":"Point"}
}