{
  "type": "Feature",
  "properties": {
    "gn:admin1_code":"9.0",
    "gn:asciiname":"Suraktong-ni",
    "gn:country_code":"KP",
    "gn:dem":97,
    "gn:feature_class":"P",
    "gn:feature_code":"PPL",
    "gn:name":"Suraktong-ni",
    "gn:population":0,
    "gn:timezone":"Asia/Pyongyang",
    "iso:country":"KP",
    "name:und_x_variant":[
        "\uc218\ub77d\ub3d9\ub9ac"
    ],
    "wof:name":"Suraktong-ni",
    "wof:placetype":"locality"
},
  "geometry": {"coordinates":[127.43065,39.07909],"type":"Point"}
}