{
  "type": "Feature",
  "properties": {
    "gn:admin1_code":"15.0",
    "gn:asciiname":"Ungbong-dong",
    "gn:country_code":"KP",
    "gn:dem":85,
    "gn:feature_class":"P",
    "gn:feature_code":"PPL",
    "gn:name":"\u016cngbong-dong",
    "gn:population":0,
    "gn:timezone":"Asia/Pyongyang",
    "iso:country":"KP",
    "name:und_x_variant":[
        "\u016cngbong-ni",
        "\u016cngbong-dong"
    ],
    "wof:name":"Ungbong-dong",
    "wof:placetype":"locality"
},
  "geometry": {"coordinates":[125.82861,39.42611],"type":"Point"}
}