{
  "type": "Feature",
  "properties": {
    "gn:admin1_code":"17.0",
    "gn:asciiname":"Nongp'yong-dong",
    "gn:country_code":"KP",
    "gn:dem":58,
    "gn:feature_class":"P",
    "gn:feature_code":"PPL",
    "gn:name":"Nongp\u2019y\u014fng-dong",
    "gn:population":0,
    "gn:timezone":"Asia/Pyongyang",
    "iso:country":"KP",
    "name:und_x_variant":[
        "\ub18d\ud3c9\ub3d9",
        "Nongp\u2019y\u014fng-dong"
    ],
    "wof:name":"Nongp'yong-dong",
    "wof:placetype":"locality"
},
  "geometry": {"coordinates":[129.45472000000001,40.90444],"type":"Point"}
}