{
  "type": "Feature",
  "properties": {
    "gn:admin1_code":"6.0",
    "gn:asciiname":"Tongjong-ni",
    "gn:country_code":"KP",
    "gn:dem":15,
    "gn:feature_class":"P",
    "gn:feature_code":"PPL",
    "gn:name":"Tongj\u014fng-ni",
    "gn:population":0,
    "gn:timezone":"Asia/Pyongyang",
    "iso:country":"KP",
    "name:eng_x_preferred":[
        "Tongjong"
    ],
    "name:eng_x_variant":[
        "Tongjong-ni"
    ],
    "wof:name":"Tongjong",
    "wof:placetype":"locality"
},
  "geometry": {"coordinates":[126.22389,37.87639],"type":"Point"}
}