{
  "type": "Feature",
  "properties": {
    "gn:admin1_code":"1.0",
    "gn:asciiname":"Ansang-ni",
    "gn:country_code":"KP",
    "gn:dem":297,
    "gn:feature_class":"P",
    "gn:feature_code":"PPL",
    "gn:name":"Ansang-ni",
    "gn:population":0,
    "gn:timezone":"Asia/Pyongyang",
    "iso:country":"KP",
    "name:eng_x_preferred":[
        "Ansang"
    ],
    "name:eng_x_variant":[
        "Ansang-ni"
    ],
    "name:und_x_variant":[
        "\uc548\uc0c1\ub9ac",
        "Ansang-ni"
    ],
    "wof:name":"Ansang",
    "wof:placetype":"locality"
},
  "geometry": {"coordinates":[125.69694,40.57444],"type":"Point"}
}