{
  "type": "Feature",
  "properties": {
    "gn:admin1_code":"17.0",
    "gn:asciiname":"Songhang",
    "gn:country_code":"KP",
    "gn:dem":128,
    "gn:feature_class":"P",
    "gn:feature_code":"PPL",
    "gn:name":"Songhang",
    "gn:population":0,
    "gn:timezone":"Asia/Pyongyang",
    "iso:country":"KP",
    "name:und_x_variant":[
        "\uc1a1\ud56d",
        "Songhang"
    ],
    "wof:name":"Songhang",
    "wof:placetype":"locality"
},
  "geometry": {"coordinates":[130.26333,42.61389000000001],"type":"Point"}
}