{
  "type": "Feature",
  "properties": {
    "gn:admin1_code":"15.0",
    "gn:admin2_code":"Pukch\u2019ang-gun",
    "gn:asciiname":"P'oom-ni",
    "gn:country_code":"KP",
    "gn:dem":102,
    "gn:feature_class":"P",
    "gn:feature_code":"PPL",
    "gn:name":"P\u2019o\u014fm-ni",
    "gn:population":0,
    "gn:timezone":"Asia/Pyongyang",
    "iso:country":"KP",
    "wof:name":"P'oom-ni",
    "wof:placetype":"locality"
},
  "geometry": {"coordinates":[126.20944,39.5825],"type":"Point"}
}