{
  "type": "Feature",
  "properties": {
    "gn:admin1_code":"6.0",
    "gn:asciiname":"So-dong",
    "gn:country_code":"KP",
    "gn:dem":101,
    "gn:feature_class":"P",
    "gn:feature_code":"PPL",
    "gn:name":"So-dong",
    "gn:population":0,
    "gn:timezone":"Asia/Pyongyang",
    "iso:country":"KP",
    "wof:name":"So-dong",
    "wof:placetype":"locality"
},
  "geometry": {"coordinates":[125.89806000000002,38.23333],"type":"Point"}
}