{
  "type": "Feature",
  "properties": {
    "gn:admin1_code":"3.0",
    "gn:asciiname":"Unsung-ni",
    "gn:cc2":"KP",
    "gn:country_code":"KP",
    "gn:dem":346,
    "gn:feature_class":"P",
    "gn:feature_code":"PPL",
    "gn:name":"Uns\u016dng-ni",
    "gn:population":0,
    "gn:timezone":"Asia/Pyongyang",
    "iso:country":"KP",
    "name:und_x_variant":[
        "Sanguns\u016dng-ni",
        "Uns\u016dng-ni"
    ],
    "wof:name":"Unsung-ni",
    "wof:placetype":"locality"
},
  "geometry": {"coordinates":[128.83082999999999,40.62972],"type":"Point"}
}