{
  "type": "Feature",
  "properties": {
    "gn:admin1_code":"6.0",
    "gn:asciiname":"Hanong-dong",
    "gn:country_code":"KP",
    "gn:dem":12,
    "gn:feature_class":"P",
    "gn:feature_code":"PPL",
    "gn:name":"Hanong-dong",
    "gn:population":0,
    "gn:timezone":"Asia/Pyongyang",
    "iso:country":"KP",
    "name:kor_x_preferred":[
        "\ud558\ub18d\ub3d9"
    ],
    "wof:name":"Hanong-dong",
    "wof:placetype":"locality"
},
  "geometry": {"coordinates":[125.03055999999999,38.23639],"type":"Point"}
}