{
  "type": "Feature",
  "properties": {
    "gn:admin1_code":"3.0",
    "gn:asciiname":"Chwasang-ni",
    "gn:country_code":"KP",
    "gn:dem":51,
    "gn:feature_class":"P",
    "gn:feature_code":"PPL",
    "gn:name":"Chwasang-ni",
    "gn:population":0,
    "gn:timezone":"Asia/Pyongyang",
    "iso:country":"KP",
    "name:eng_x_preferred":[
        "Chwasang"
    ],
    "name:eng_x_variant":[
        "Chwasang-ni"
    ],
    "name:und_x_variant":[
        "\uc88c\uc0c1\ub9ac",
        "Chwasang-ni"
    ],
    "wof:name":"Chwasang",
    "wof:placetype":"locality"
},
  "geometry": {"coordinates":[128.00583,40.07861],"type":"Point"}
}