{
  "type": "Feature",
  "properties": {
    "gn:admin1_code":"9.0",
    "gn:asciiname":"Hajisong-ni",
    "gn:country_code":"KP",
    "gn:dem":282,
    "gn:feature_class":"P",
    "gn:feature_code":"PPL",
    "gn:name":"Hajis\u014fng-ni",
    "gn:population":0,
    "gn:timezone":"Asia/Pyongyang",
    "iso:country":"KP",
    "name:kor_x_preferred":[
        "\ud558\uc9c0\uc131\ub9ac"
    ],
    "name:und_x_variant":[
        "Hajis\u014fng-ni"
    ],
    "wof:name":"Hajisong-ni",
    "wof:placetype":"locality"
},
  "geometry": {"coordinates":[127.75,38.58333],"type":"Point"}
}