{
  "type": "Feature",
  "properties": {
    "gn:admin1_code":"1.0",
    "gn:asciiname":"Yangdong-ni",
    "gn:country_code":"KP",
    "gn:dem":674,
    "gn:feature_class":"P",
    "gn:feature_code":"PPL",
    "gn:name":"Yangd\u014fng-ni",
    "gn:population":0,
    "gn:timezone":"Asia/Pyongyang",
    "iso:country":"KP",
    "name:und_x_variant":[
        "\ub7c9\ub355\ub9ac",
        "Yangd\u014fng-ni"
    ],
    "wof:name":"Yangdong-ni",
    "wof:placetype":"locality"
},
  "geometry": {"coordinates":[126.69138999999998,41.23972],"type":"Point"}
}