{
  "type": "Feature",
  "properties": {
    "gn:admin1_code":"12.0",
    "gn:asciiname":"Huillak",
    "gn:country_code":"KP",
    "gn:dem":56,
    "gn:feature_class":"P",
    "gn:feature_code":"PPL",
    "gn:name":"Huillak",
    "gn:population":0,
    "gn:timezone":"Asia/Pyongyang",
    "iso:country":"KP",
    "name:kor_x_preferred":[
        "\ud6c4\uc77c\ub77d"
    ],
    "wof:name":"Huillak",
    "wof:placetype":"locality"
},
  "geometry": {"coordinates":[125.71389000000001,39.14222],"type":"Point"}
}