{
  "type": "Feature",
  "properties": {
    "gn:admin1_code":"6.0",
    "gn:admin2_code":"Paech\u2019\u014fn-gun",
    "gn:asciiname":"Orik-kol",
    "gn:country_code":"KP",
    "gn:dem":6,
    "gn:feature_class":"P",
    "gn:feature_code":"PPL",
    "gn:name":"Orik-kol",
    "gn:population":0,
    "gn:timezone":"Asia/Pyongyang",
    "iso:country":"KP",
    "wof:name":"Orik-kol",
    "wof:placetype":"locality"
},
  "geometry": {"coordinates":[126.38139,37.8875],"type":"Point"}
}