{
  "type": "Feature",
  "properties": {
    "gn:admin1_code":"13.0",
    "gn:asciiname":"Pallyonggi-ri",
    "gn:cc2":"KP",
    "gn:country_code":"KP",
    "gn:dem":958,
    "gn:feature_class":"P",
    "gn:feature_code":"PPL",
    "gn:name":"Pallyonggi-ri",
    "gn:population":0,
    "gn:timezone":"Asia/Pyongyang",
    "iso:country":"KP",
    "name:und_x_variant":[
        "Panyonggi-ri",
        "Pallyonggi-ri"
    ],
    "wof:name":"Pallyonggi-ri",
    "wof:placetype":"locality"
},
  "geometry": {"coordinates":[128.04471999999998,41.21278],"type":"Point"}
}