{
  "type": "Feature",
  "properties": {
    "gn:admin1_code":"6.0",
    "gn:asciiname":"Chinmi-dong",
    "gn:country_code":"KP",
    "gn:dem":10,
    "gn:feature_class":"P",
    "gn:feature_code":"PPL",
    "gn:name":"Chinmi-dong",
    "gn:population":0,
    "gn:timezone":"Asia/Pyongyang",
    "iso:country":"KP",
    "name:kor_x_preferred":[
        "\uc9c4\ubbf8\ub3d9"
    ],
    "wof:name":"Chinmi-dong",
    "wof:placetype":"locality"
},
  "geometry": {"coordinates":[126.0675,37.81861],"type":"Point"}
}