{
  "type": "Feature",
  "properties": {
    "gn:admin1_code":"11.0",
    "gn:asciiname":"Kwango-ri",
    "gn:country_code":"KP",
    "gn:dem":30,
    "gn:feature_class":"P",
    "gn:feature_code":"PPL",
    "gn:name":"Kwang\u014f-ri",
    "gn:population":0,
    "gn:timezone":"Asia/Pyongyang",
    "iso:country":"KP",
    "name:kor_x_preferred":[
        "\uad00\uac70\ub9ac"
    ],
    "name:kor_x_variant":[
        "Kwang\u014f-ri"
    ],
    "name:und_x_variant":[
        "Kwandong-ni"
    ],
    "wof:name":"Kwango-ri",
    "wof:placetype":"locality"
},
  "geometry": {"coordinates":[125.485,39.69833],"type":"Point"}
}