{
  "type": "Feature",
  "properties": {
    "gn:admin1_code":"6.0",
    "gn:asciiname":"Chonch'on-dong",
    "gn:country_code":"KP",
    "gn:dem":36,
    "gn:feature_class":"P",
    "gn:feature_code":"PPL",
    "gn:name":"Ch\u014fnch\u2019on-dong",
    "gn:population":0,
    "gn:timezone":"Asia/Pyongyang",
    "iso:country":"KP",
    "name:und_x_variant":[
        "\uc804\ucd0c\ub3d9",
        "Ch\u014fnch\u2019on-dong"
    ],
    "wof:name":"Chonch'on-dong",
    "wof:placetype":"locality"
},
  "geometry": {"coordinates":[125.48027999999999,37.87],"type":"Point"}
}