{
  "type": "Feature",
  "properties": {
    "gn:admin1_code":"1.0",
    "gn:asciiname":"Ssangnyong-ni",
    "gn:country_code":"KP",
    "gn:dem":382,
    "gn:feature_class":"P",
    "gn:feature_code":"PPL",
    "gn:name":"Ssangnyong-ni",
    "gn:population":0,
    "gn:timezone":"Asia/Pyongyang",
    "iso:country":"KP",
    "name:kor_x_preferred":[
        "\uc30d\ub8e1\ub9ac"
    ],
    "name:und_x_variant":[
        "\uc30d\ub8e1\ub9ac",
        "Ssangnyong-ni"
    ],
    "wof:name":"Ssangnyong-ni",
    "wof:placetype":"locality"
},
  "geometry": {"coordinates":[126.48166999999999,40.72056],"type":"Point"}
}