{
  "type": "Feature",
  "properties": {
    "gn:admin1_code":"3.0",
    "gn:asciiname":"P'ungt'aeng-ni",
    "gn:country_code":"KP",
    "gn:dem":158,
    "gn:feature_class":"P",
    "gn:feature_code":"PPL",
    "gn:name":"P\u2019ungt\u2019aeng-ni",
    "gn:population":0,
    "gn:timezone":"Asia/Pyongyang",
    "iso:country":"KP",
    "name:eng_x_preferred":[
        "P'ungt'aeng"
    ],
    "name:eng_x_variant":[
        "P'ungt'aeng-ni"
    ],
    "name:und_x_variant":[
        "\ud48d\ud0dd\ub9ac",
        "P\u2019ungt\u2019aeng-ni"
    ],
    "wof:name":"P'ungt'aeng",
    "wof:placetype":"locality"
},
  "geometry": {"coordinates":[127.83472,40.12278],"type":"Point"}
}