{
  "type": "Feature",
  "properties": {
    "gn:admin1_code":"1.0",
    "gn:asciiname":"Tangu-dong",
    "gn:country_code":"KP",
    "gn:dem":376,
    "gn:feature_class":"P",
    "gn:feature_code":"PPL",
    "gn:name":"Tangu-dong",
    "gn:population":0,
    "gn:timezone":"Asia/Pyongyang",
    "iso:country":"KP",
    "name:und_x_variant":[
        "\ub2f9\uc6b0\ub3d9",
        "Tangu-dong"
    ],
    "wof:name":"Tangu-dong",
    "wof:placetype":"locality"
},
  "geometry": {"coordinates":[126.64778,41.07111],"type":"Point"}
}