{
  "type": "Feature",
  "properties": {
    "gn:admin1_code":"7.0",
    "gn:asciiname":"Munan",
    "gn:country_code":"KP",
    "gn:dem":146,
    "gn:feature_class":"P",
    "gn:feature_code":"PPL",
    "gn:name":"Munan",
    "gn:population":0,
    "gn:timezone":"Asia/Pyongyang",
    "iso:country":"KP",
    "name:kor_x_preferred":[
        "\ubb38\uc548"
    ],
    "wof:name":"Munan",
    "wof:placetype":"locality"
},
  "geometry": {"coordinates":[126.32306,38.33389],"type":"Point"}
}