{
  "type": "Feature",
  "properties": {
    "gn:admin1_code":"12.0",
    "gn:asciiname":"Chuksan-dong",
    "gn:country_code":"KP",
    "gn:dem":10,
    "gn:feature_class":"P",
    "gn:feature_code":"PPL",
    "gn:name":"Chuksan-dong",
    "gn:population":0,
    "gn:timezone":"Asia/Pyongyang",
    "iso:country":"KP",
    "name:kor_x_preferred":[
        "\uc8fd\uc0b0\ub9ac"
    ],
    "name:kor_x_variant":[
        "\uc8fd\uc0b0\ub3d9"
    ],
    "name:und_x_variant":[
        "Chuksan-ni",
        "Chuksal-li",
        "Chuksan-dong",
        "Juksandong"
    ],
    "wof:name":"Chuksan-dong",
    "wof:placetype":"locality"
},
  "geometry": {"coordinates":[125.57962000000001,38.84425],"type":"Point"}
}