{
  "type": "Feature",
  "properties": {
    "gn:admin1_code":"12.0",
    "gn:admin2_code":"Sangw\u014fn-gun",
    "gn:asciiname":"Imok-tong",
    "gn:country_code":"KP",
    "gn:dem":51,
    "gn:feature_class":"P",
    "gn:feature_code":"PPL",
    "gn:name":"Imok-tong",
    "gn:population":0,
    "gn:timezone":"Asia/Pyongyang",
    "iso:country":"KP",
    "name:eng_x_preferred":[
        "Imok"
    ],
    "name:eng_x_variant":[
        "Imok-tong"
    ],
    "wof:name":"Imok",
    "wof:placetype":"locality"
},
  "geometry": {"coordinates":[126.01917,38.95278],"type":"Point"}
}