{
  "type": "Feature",
  "properties": {
    "gn:admin1_code":"9.0",
    "gn:asciiname":"Sin'gombul-li",
    "gn:country_code":"KP",
    "gn:dem":549,
    "gn:feature_class":"P",
    "gn:feature_code":"PPL",
    "gn:name":"Sin\u2019g\u014fmbul-li",
    "gn:population":0,
    "gn:timezone":"Asia/Pyongyang",
    "iso:country":"KP",
    "wof:name":"Sin'gombul-li",
    "wof:placetype":"locality"
},
  "geometry": {"coordinates":[127.32528000000001,38.56139],"type":"Point"}
}