{
  "type": "Feature",
  "properties": {
    "gn:admin1_code":"15.0",
    "gn:admin2_code":"Ch\u2019\u014fngnam-gu",
    "gn:asciiname":"Yangsong-ni",
    "gn:country_code":"KP",
    "gn:dem":13,
    "gn:feature_class":"P",
    "gn:feature_code":"PPL",
    "gn:name":"Yangs\u014fng-ni",
    "gn:population":0,
    "gn:timezone":"Asia/Pyongyang",
    "iso:country":"KP",
    "wof:name":"Yangsong-ni",
    "wof:placetype":"locality"
},
  "geometry": {"coordinates":[125.46722,39.47806],"type":"Point"}
}