{
  "type": "Feature",
  "properties": {
    "gn:admin1_code":"15.0",
    "gn:asciiname":"Taeal-li",
    "gn:country_code":"KP",
    "gn:dem":15,
    "gn:feature_class":"P",
    "gn:feature_code":"PPL",
    "gn:name":"Taeal-li",
    "gn:population":0,
    "gn:timezone":"Asia/Pyongyang",
    "iso:country":"KP",
    "name:kor_x_preferred":[
        "\ub300\uc548\ub9ac"
    ],
    "name:und_x_variant":[
        "Taean-ni",
        "Taeal-li"
    ],
    "wof:name":"Taeal-li",
    "wof:placetype":"locality"
},
  "geometry": {"coordinates":[125.55028,38.72667],"type":"Point"}
}