{
  "type": "Feature",
  "properties": {
    "gn:admin1_code":"6.0",
    "gn:asciiname":"Kukhwa-gol",
    "gn:country_code":"KP",
    "gn:dem":91,
    "gn:feature_class":"P",
    "gn:feature_code":"PPL",
    "gn:name":"Kukhwa-gol",
    "gn:population":0,
    "gn:timezone":"Asia/Pyongyang",
    "iso:country":"KP",
    "name:und_x_variant":[
        "Kukhwa-dong",
        "\uad6d\ud654\uace8",
        "Kukhwa-gol"
    ],
    "wof:name":"Kukhwa-gol",
    "wof:placetype":"locality"
},
  "geometry": {"coordinates":[125.39722,38.22806],"type":"Point"}
}