{
  "type": "Feature",
  "properties": {
    "gn:admin1_code":"0.0",
    "gn:asciiname":"Pol-dong",
    "gn:country_code":"KP",
    "gn:dem":424,
    "gn:feature_class":"P",
    "gn:feature_code":"PPL",
    "gn:name":"P\u014fl-dong",
    "gn:population":0,
    "gn:timezone":"Asia/Pyongyang",
    "iso:country":"KP",
    "name:kor_x_preferred":[
        "\ubc8c\ub3d9"
    ],
    "name:und_x_variant":[
        "P\u014fl-dong",
        "P\u014fl-tong"
    ],
    "wof:name":"Pol-dong",
    "wof:placetype":"locality"
},
  "geometry": {"coordinates":[126.66667,41.65],"type":"Point"}
}