{
  "type": "Feature",
  "properties": {
    "gn:admin1_code":"1.0",
    "gn:asciiname":"Mulbanga-gol",
    "gn:country_code":"KP",
    "gn:dem":350,
    "gn:feature_class":"P",
    "gn:feature_code":"PPL",
    "gn:name":"Mulbanga-gol",
    "gn:population":0,
    "gn:timezone":"Asia/Pyongyang",
    "iso:country":"KP",
    "name:und_x_variant":[
        "\ubb3c\ubc29\uc544\uace8"
    ],
    "wof:name":"Mulbanga-gol",
    "wof:placetype":"locality"
},
  "geometry": {"coordinates":[126.6024,40.97752],"type":"Point"}
}