{
  "type": "Feature",
  "properties": {
    "gn:admin1_code":"9.0",
    "gn:asciiname":"Ssuk-kol",
    "gn:country_code":"KP",
    "gn:dem":190,
    "gn:feature_class":"P",
    "gn:feature_code":"PPL",
    "gn:name":"Ssuk-kol",
    "gn:population":0,
    "gn:timezone":"Asia/Pyongyang",
    "iso:country":"KP",
    "wof:name":"Ssuk-kol",
    "wof:placetype":"locality"
},
  "geometry": {"coordinates":[127.08,38.32472],"type":"Point"}
}