{
  "type": "Feature",
  "properties": {
    "gn:admin1_code":"17.0",
    "gn:asciiname":"Yongsan-dong",
    "gn:country_code":"KP",
    "gn:dem":90,
    "gn:feature_class":"P",
    "gn:feature_code":"PPL",
    "gn:name":"Yongsan-dong",
    "gn:population":0,
    "gn:timezone":"Asia/Pyongyang",
    "iso:country":"KP",
    "name:ceb_x_preferred":[
        "Yongsan-dong"
    ],
    "name:kor_x_preferred":[
        "\uc6a9\uc0b0\ub3d9"
    ],
    "name:swe_x_preferred":[
        "Yongsan-dong"
    ],
    "name:und_x_variant":[
        "Yongsan-ni",
        "Yongsal-li",
        "\uc6a9\uc0b0\ub3d9",
        "Yongsan-dong"
    ],
    "name:zho_x_preferred":[
        "\u9f8d\u5c71\u6d1e"
    ],
    "wof:name":"Yongsan-dong",
    "wof:placetype":"locality"
},
  "geometry": {"coordinates":[129.51639,41.22083],"type":"Point"}
}