{
  "type": "Feature",
  "properties": {
    "gn:admin1_code":"3.0",
    "gn:asciiname":"Sin'gyong-ni",
    "gn:country_code":"KP",
    "gn:dem":19,
    "gn:feature_class":"P",
    "gn:feature_code":"PPL",
    "gn:name":"Sin\u2019gy\u014fng-ni",
    "gn:population":0,
    "gn:timezone":"Asia/Pyongyang",
    "iso:country":"KP",
    "name:und_x_variant":[
        "\uc2e0\uacbd\ub9ac",
        "Sin\u2019gy\u014fng-ni"
    ],
    "wof:name":"Sin'gyong-ni",
    "wof:placetype":"locality"
},
  "geometry": {"coordinates":[127.43805999999999,39.91861],"type":"Point"}
}