{
  "type": "Feature",
  "properties": {
    "gn:admin1_code":"6.0",
    "gn:admin2_code":"Kaep'ung-gun",
    "gn:asciiname":"Kan-dong",
    "gn:country_code":"KP",
    "gn:dem":51,
    "gn:feature_class":"P",
    "gn:feature_code":"PPL",
    "gn:name":"Kan-dong",
    "gn:population":0,
    "gn:timezone":"Asia/Pyongyang",
    "iso:country":"KP",
    "wof:name":"Kan-dong",
    "wof:placetype":"locality"
},
  "geometry": {"coordinates":[126.52333,37.94083],"type":"Point"}
}