{
  "type": "Feature",
  "properties": {
    "gn:admin1_code":"1.0",
    "gn:asciiname":"Namsang-ni",
    "gn:country_code":"KP",
    "gn:dem":241,
    "gn:feature_class":"P",
    "gn:feature_code":"PPL",
    "gn:name":"Namsang-ni",
    "gn:population":0,
    "gn:timezone":"Asia/Pyongyang",
    "iso:country":"KP",
    "name:eng_x_preferred":[
        "Namsang"
    ],
    "name:eng_x_variant":[
        "Namsang-ni"
    ],
    "wof:name":"Namsang",
    "wof:placetype":"locality"
},
  "geometry": {"coordinates":[125.97499999999999,40.86194],"type":"Point"}
}