{
  "type": "Feature",
  "properties": {
    "gn:admin1_code":"6.0",
    "gn:asciiname":"Poriam",
    "gn:country_code":"KP",
    "gn:dem":40,
    "gn:feature_class":"P",
    "gn:feature_code":"PPL",
    "gn:name":"P\u014friam",
    "gn:population":0,
    "gn:timezone":"Asia/Pyongyang",
    "iso:country":"KP",
    "name:und_x_variant":[
        "P\u014fram",
        "P\u014friam"
    ],
    "wof:name":"Poriam",
    "wof:placetype":"locality"
},
  "geometry": {"coordinates":[125.80110999999999,38.0575],"type":"Point"}
}