{
  "type": "Feature",
  "properties": {
    "gn:admin1_code":"7.0",
    "gn:asciiname":"Oech'u-dong",
    "gn:country_code":"KP",
    "gn:dem":301,
    "gn:feature_class":"P",
    "gn:feature_code":"PPL",
    "gn:name":"Oech\u2019u-dong",
    "gn:population":0,
    "gn:timezone":"Asia/Pyongyang",
    "iso:country":"KP",
    "name:kor_x_preferred":[
        "\uc678\ucd94\ub3d9"
    ],
    "name:kor_x_variant":[
        "Oech\u2019u-dong"
    ],
    "wof:name":"Oech'u-dong",
    "wof:placetype":"locality"
},
  "geometry": {"coordinates":[126.70222,39.00167],"type":"Point"}
}