{
  "type": "Feature",
  "properties": {
    "gn:admin1_code":"11.0",
    "gn:asciiname":"Tangmong-ni",
    "gn:country_code":"KP",
    "gn:dem":110,
    "gn:feature_class":"P",
    "gn:feature_code":"PPL",
    "gn:name":"Tangmong-ni",
    "gn:population":0,
    "gn:timezone":"Asia/Pyongyang",
    "iso:country":"KP",
    "name:und_x_variant":[
        "Tangmok-tong",
        "\ub2f9\ubaa9\ub9ac",
        "Tangmong-ni"
    ],
    "wof:name":"Tangmong-ni",
    "wof:placetype":"locality"
},
  "geometry": {"coordinates":[124.83861,40.29389000000001],"type":"Point"}
}