{
  "type": "Feature",
  "properties": {
    "gn:admin1_code":"9.0",
    "gn:asciiname":"Yangssangnyong",
    "gn:country_code":"KP",
    "gn:dem":568,
    "gn:feature_class":"P",
    "gn:feature_code":"PPL",
    "gn:name":"Yangssangny\u014fng",
    "gn:population":0,
    "gn:timezone":"Asia/Pyongyang",
    "iso:country":"KP",
    "wof:name":"Yangssangnyong",
    "wof:placetype":"locality"
},
  "geometry": {"coordinates":[127.43583,38.55667],"type":"Point"}
}