{
  "type": "Feature",
  "properties": {
    "gn:admin1_code":"17.0",
    "gn:asciiname":"Namnyanggae",
    "gn:country_code":"KP",
    "gn:dem":24,
    "gn:feature_class":"P",
    "gn:feature_code":"PPL",
    "gn:name":"Namnyanggae",
    "gn:population":0,
    "gn:timezone":"Asia/Pyongyang",
    "iso:country":"KP",
    "name:und_x_variant":[
        "Namnyangp\u2019o",
        "\ub0a8\ub7c9\uac1c",
        "Namnyanggae"
    ],
    "wof:name":"Namnyanggae",
    "wof:placetype":"locality"
},
  "geometry": {"coordinates":[129.16806,40.71417],"type":"Point"}
}