{
  "type": "Feature",
  "properties": {
    "gn:admin1_code":"9.0",
    "gn:asciiname":"Saemal",
    "gn:country_code":"KP",
    "gn:dem":479,
    "gn:feature_class":"P",
    "gn:feature_code":"PPL",
    "gn:name":"Saemal",
    "gn:population":0,
    "gn:timezone":"Asia/Pyongyang",
    "iso:country":"KP",
    "name:und_x_variant":[
        "\uc0c8\ub9d0",
        "Saemal"
    ],
    "wof:name":"Saemal",
    "wof:placetype":"locality"
},
  "geometry": {"coordinates":[127.74917000000001,38.64472],"type":"Point"}
}