{
  "type": "Feature",
  "properties": {
    "gn:admin1_code":"17.0",
    "gn:asciiname":"P'al-tong",
    "gn:country_code":"KP",
    "gn:dem":580,
    "gn:feature_class":"P",
    "gn:feature_code":"PPL",
    "gn:name":"P\u2019al-tong",
    "gn:population":0,
    "gn:timezone":"Asia/Pyongyang",
    "iso:country":"KP",
    "name:und_x_variant":[
        "\ud314\ub3d9",
        "P\u2019al-tong"
    ],
    "wof:name":"P'al-tong",
    "wof:placetype":"locality"
},
  "geometry": {"coordinates":[129.33944,42.17389],"type":"Point"}
}