{
  "type": "Feature",
  "properties": {
    "gn:admin1_code":"6.0",
    "gn:asciiname":"Ponghwang-ni",
    "gn:country_code":"KP",
    "gn:dem":11,
    "gn:feature_class":"P",
    "gn:feature_code":"PPL",
    "gn:name":"Ponghwang-ni",
    "gn:population":0,
    "gn:timezone":"Asia/Pyongyang",
    "iso:country":"KP",
    "name:eng_x_preferred":[
        "Ponghwang"
    ],
    "name:eng_x_variant":[
        "Ponghwang-ni"
    ],
    "wof:name":"Ponghwang",
    "wof:placetype":"locality"
},
  "geometry": {"coordinates":[126.02667,37.88167],"type":"Point"}
}