{
  "type": "Feature",
  "properties": {
    "gn:admin1_code":"6.0",
    "gn:asciiname":"Nuch'ol-li",
    "gn:country_code":"KP",
    "gn:dem":64,
    "gn:feature_class":"P",
    "gn:feature_code":"PPL",
    "gn:name":"Nuch\u2019\u014fl-li",
    "gn:population":0,
    "gn:timezone":"Asia/Pyongyang",
    "iso:country":"KP",
    "name:kor_x_preferred":[
        "\ub204\ucd0c\ub9ac"
    ],
    "name:und_x_variant":[
        "R\u014dsen-ri",
        "Nuch\u2019\u014fl-li"
    ],
    "wof:name":"Nuch'ol-li",
    "wof:placetype":"locality"
},
  "geometry": {"coordinates":[126.20417,38.125],"type":"Point"}
}