{
  "type": "Feature",
  "properties": {
    "gn:admin1_code":"9.0",
    "gn:asciiname":"Yangjich'on",
    "gn:country_code":"KP",
    "gn:dem":482,
    "gn:feature_class":"P",
    "gn:feature_code":"PPL",
    "gn:name":"Yangjich\u2019on",
    "gn:population":0,
    "gn:timezone":"Asia/Pyongyang",
    "iso:country":"KP",
    "name:kor_x_preferred":[
        "\uc591\uc9c0\ucc9c"
    ],
    "name:und_x_variant":[
        "Yangji-ri",
        "Yangjich\u2019on"
    ],
    "wof:name":"Yangjich'on",
    "wof:placetype":"locality"
},
  "geometry": {"coordinates":[127.14861000000001,39.20972],"type":"Point"}
}