{
  "type": "Feature",
  "properties": {
    "gn:admin1_code":"7.0",
    "gn:asciiname":"Chidae-dong",
    "gn:country_code":"KP",
    "gn:dem":30,
    "gn:feature_class":"P",
    "gn:feature_code":"PPL",
    "gn:name":"Chidae-dong",
    "gn:population":0,
    "gn:timezone":"Asia/Pyongyang",
    "iso:country":"KP",
    "name:kor_x_preferred":[
        "\uc9c0\ub300\ub3d9"
    ],
    "wof:name":"Chidae-dong",
    "wof:placetype":"locality"
},
  "geometry": {"coordinates":[126.46472,38.25556],"type":"Point"}
}