{
  "type": "Feature",
  "properties": {
    "gn:admin1_code":"7.0",
    "gn:asciiname":"Tojang",
    "gn:country_code":"KP",
    "gn:dem":27,
    "gn:feature_class":"P",
    "gn:feature_code":"PPL",
    "gn:name":"Tojang",
    "gn:population":0,
    "gn:timezone":"Asia/Pyongyang",
    "iso:country":"KP",
    "name:und_x_variant":[
        "\ub3c4\uc7a5",
        "Tojang"
    ],
    "wof:name":"Tojang",
    "wof:placetype":"locality"
},
  "geometry": {"coordinates":[125.73583000000001,38.81861],"type":"Point"}
}