{
  "type": "Feature",
  "properties": {
    "gn:admin1_code":"7.0",
    "gn:asciiname":"Sawol-li",
    "gn:country_code":"KP",
    "gn:dem":69,
    "gn:feature_class":"P",
    "gn:feature_code":"PPL",
    "gn:name":"Saw\u014fl-li",
    "gn:population":0,
    "gn:timezone":"Asia/Pyongyang",
    "iso:country":"KP",
    "wof:name":"Sawol-li",
    "wof:placetype":"locality"
},
  "geometry": {"coordinates":[125.76278000000001,38.53139],"type":"Point"}
}