{
  "type": "Feature",
  "properties": {
    "gn:admin1_code":"1.0",
    "gn:asciiname":"Saajae",
    "gn:country_code":"KP",
    "gn:dem":759,
    "gn:feature_class":"P",
    "gn:feature_code":"PPL",
    "gn:name":"Saajae",
    "gn:population":0,
    "gn:timezone":"Asia/Pyongyang",
    "iso:country":"KP",
    "name:kor_x_preferred":[
        "\uc0ac\uc544\uc7ac"
    ],
    "name:und_x_variant":[
        "Sanjae"
    ],
    "wof:name":"Saajae",
    "wof:placetype":"locality"
},
  "geometry": {"coordinates":[127.43847,41.07459],"type":"Point"}
}