{
  "type": "Feature",
  "properties": {
    "gn:admin1_code":"9.0",
    "gn:asciiname":"Changch'idong-ni",
    "gn:country_code":"KP",
    "gn:dem":687,
    "gn:feature_class":"P",
    "gn:feature_code":"PPL",
    "gn:name":"Changch\u2019idong-ni",
    "gn:population":0,
    "gn:timezone":"Asia/Pyongyang",
    "iso:country":"KP",
    "name:eng_x_preferred":[
        "Changch'idong"
    ],
    "name:eng_x_variant":[
        "Changch'idong-ni"
    ],
    "name:und_x_variant":[
        "\uc7a5\uce58\ub3d9\ub9ac",
        "Changch\u2019idong-ni"
    ],
    "wof:name":"Changch'idong",
    "wof:placetype":"locality"
},
  "geometry": {"coordinates":[127.93111,38.69778],"type":"Point"}
}