{
  "type": "Feature",
  "properties": {
    "gn:admin1_code":"11.0",
    "gn:asciiname":"Tok-tong",
    "gn:country_code":"KP",
    "gn:dem":101,
    "gn:feature_class":"P",
    "gn:feature_code":"PPL",
    "gn:name":"T\u014fk-tong",
    "gn:population":0,
    "gn:timezone":"Asia/Pyongyang",
    "iso:country":"KP",
    "name:eng_x_preferred":[
        "Tok"
    ],
    "name:eng_x_variant":[
        "Tok-tong"
    ],
    "name:kor_x_preferred":[
        "\ub355\ub3d9"
    ],
    "name:kor_x_variant":[
        "T\u014fk-tong"
    ],
    "wof:name":"Tok",
    "wof:placetype":"locality"
},
  "geometry": {"coordinates":[125.17471999999999,39.73556],"type":"Point"}
}