{
  "type": "Feature",
  "properties": {
    "gn:admin1_code":"7.0",
    "gn:asciiname":"Haebau",
    "gn:country_code":"KP",
    "gn:dem":82,
    "gn:feature_class":"P",
    "gn:feature_code":"PPL",
    "gn:name":"Haebau",
    "gn:population":0,
    "gn:timezone":"Asia/Pyongyang",
    "iso:country":"KP",
    "wof:name":"Haebau",
    "wof:placetype":"locality"
},
  "geometry": {"coordinates":[125.92389,38.33556],"type":"Point"}
}