{
  "type": "Feature",
  "properties": {
    "gn:admin1_code":"6.0",
    "gn:asciiname":"Changjaegol",
    "gn:country_code":"KP",
    "gn:dem":41,
    "gn:feature_class":"P",
    "gn:feature_code":"PPL",
    "gn:name":"Changjaegol",
    "gn:population":0,
    "gn:timezone":"Asia/Pyongyang",
    "iso:country":"KP",
    "name:kor_x_preferred":[
        "\uc7a5\uc7ac\uace8"
    ],
    "name:und_x_variant":[
        "Changjegol",
        "Changjaegol"
    ],
    "wof:name":"Changjaegol",
    "wof:placetype":"locality"
},
  "geometry": {"coordinates":[125.85417,38.03417],"type":"Point"}
}