{
  "type": "Feature",
  "properties": {
    "gn:admin1_code":"0.0",
    "gn:asciiname":"Won-gol",
    "gn:country_code":"KP",
    "gn:dem":27,
    "gn:feature_class":"P",
    "gn:feature_code":"PPL",
    "gn:name":"W\u014fn-gol",
    "gn:population":0,
    "gn:timezone":"Asia/Pyongyang",
    "iso:country":"KP",
    "name:kor_x_preferred":[
        "\uc6d0\uace8"
    ],
    "name:kor_x_variant":[
        "W\u014fn-gol"
    ],
    "wof:name":"Won-gol",
    "wof:placetype":"locality"
},
  "geometry": {"coordinates":[125.62194,39.70389],"type":"Point"}
}