{
  "type": "Feature",
  "properties": {
    "gn:admin1_code":"0.0",
    "gn:asciiname":"Taehyon",
    "gn:cc2":"KP",
    "gn:country_code":"KP",
    "gn:dem":30,
    "gn:feature_class":"P",
    "gn:feature_code":"PPL",
    "gn:name":"Taehy\u014fn",
    "gn:population":0,
    "gn:timezone":"Asia/Pyongyang",
    "iso:country":"KP",
    "name:kor_x_preferred":[
        "\ub300\ud604"
    ],
    "name:und_x_variant":[
        "Chukhy\u014fn",
        "Taehy\u014fn"
    ],
    "wof:name":"Taehyon",
    "wof:placetype":"locality"
},
  "geometry": {"coordinates":[125.28333000000001,39.01667],"type":"Point"}
}