{
  "type": "Feature",
  "properties": {
    "gn:admin1_code":"17.0",
    "gn:asciiname":"Haengnangch'on",
    "gn:country_code":"KP",
    "gn:dem":111,
    "gn:feature_class":"P",
    "gn:feature_code":"PPL",
    "gn:name":"Haengnangch\u2019on",
    "gn:population":0,
    "gn:timezone":"Asia/Pyongyang",
    "iso:country":"KP",
    "name:und_x_variant":[
        "\ud58f\ub791\ucd0c",
        "Haengnangch\u2019on"
    ],
    "wof:name":"Haengnangch'on",
    "wof:placetype":"locality"
},
  "geometry": {"coordinates":[129.33583000000002,40.94444],"type":"Point"}
}