{
  "type": "Feature",
  "properties": {
    "gn:admin1_code":"15.0",
    "gn:asciiname":"Ch'onggye-dong",
    "gn:country_code":"KP",
    "gn:dem":77,
    "gn:feature_class":"P",
    "gn:feature_code":"PPL",
    "gn:name":"Ch\u2019\u014fnggye-dong",
    "gn:population":0,
    "gn:timezone":"Asia/Pyongyang",
    "iso:country":"KP",
    "wof:name":"Ch'onggye-dong",
    "wof:placetype":"locality"
},
  "geometry": {"coordinates":[125.93472,39.31139],"type":"Point"}
}