{
  "type": "Feature",
  "properties": {
    "gn:admin1_code":"3.0",
    "gn:asciiname":"Chung-ni",
    "gn:country_code":"KP",
    "gn:dem":590,
    "gn:feature_class":"P",
    "gn:feature_code":"PPL",
    "gn:name":"Chung-ni",
    "gn:population":0,
    "gn:timezone":"Asia/Pyongyang",
    "iso:country":"KP",
    "name:und_x_variant":[
        "\uc81c\uc0c1\ub9ac",
        "Chung-ni"
    ],
    "wof:name":"Chung-ni",
    "wof:placetype":"locality"
},
  "geometry": {"coordinates":[128.29306,40.57028],"type":"Point"}
}