{
  "type": "Feature",
  "properties": {
    "gn:admin1_code":"17.0",
    "gn:asciiname":"Tokko-ri",
    "gn:country_code":"KP",
    "gn:dem":159,
    "gn:feature_class":"P",
    "gn:feature_code":"PPL",
    "gn:name":"T\u014fkk\u014f-ri",
    "gn:population":0,
    "gn:timezone":"Asia/Pyongyang",
    "iso:country":"KP",
    "name:und_x_variant":[
        "\ub355\uac70\ub9ac",
        "T\u014fkk\u014f-ri"
    ],
    "wof:name":"Tokko-ri",
    "wof:placetype":"locality"
},
  "geometry": {"coordinates":[129.49388999999999,41.32306],"type":"Point"}
}