{
  "type": "Feature",
  "properties": {
    "gn:admin1_code":"7.0",
    "gn:asciiname":"P'yongwol-li",
    "gn:country_code":"KP",
    "gn:dem":218,
    "gn:feature_class":"P",
    "gn:feature_code":"PPL",
    "gn:name":"P\u2019y\u014fngw\u014fl-li",
    "gn:population":0,
    "gn:timezone":"Asia/Pyongyang",
    "iso:country":"KP",
    "name:kor_x_preferred":[
        "\ud3c9\uc6d0\ub9ac"
    ],
    "name:kor_x_variant":[
        "P\u2019y\u014fngw\u014fl-li"
    ],
    "name:und_x_variant":[
        "Heiin-ri",
        "P\u2019yongwon-ni"
    ],
    "wof:name":"P'yongwol-li",
    "wof:placetype":"locality"
},
  "geometry": {"coordinates":[126.49028,38.76778],"type":"Point"}
}