{
  "type": "Feature",
  "properties": {
    "gn:admin1_code":"6.0",
    "gn:asciiname":"Pak-tong",
    "gn:country_code":"KP",
    "gn:dem":7,
    "gn:feature_class":"P",
    "gn:feature_code":"PPL",
    "gn:name":"Pak-tong",
    "gn:population":0,
    "gn:timezone":"Asia/Pyongyang",
    "iso:country":"KP",
    "name:kor_x_preferred":[
        "\ubc15\ub3d9"
    ],
    "wof:name":"Pak-tong",
    "wof:placetype":"locality"
},
  "geometry": {"coordinates":[125.69083999999999,38.43612],"type":"Point"}
}