{
  "type": "Feature",
  "properties": {
    "gn:admin1_code":"9.0",
    "gn:asciiname":"Saebattun",
    "gn:country_code":"KP",
    "gn:dem":381,
    "gn:feature_class":"P",
    "gn:feature_code":"PPL",
    "gn:name":"Saebattun",
    "gn:population":0,
    "gn:timezone":"Asia/Pyongyang",
    "iso:country":"KP",
    "name:kor_x_preferred":[
        "\uc0c8\ubc2d\ub454"
    ],
    "wof:name":"Saebattun",
    "wof:placetype":"locality"
},
  "geometry": {"coordinates":[127.11499999999999,39.05944],"type":"Point"}
}