{
  "type": "Feature",
  "properties": {
    "gn:admin1_code":"13.0",
    "gn:asciiname":"Nop'un'gori",
    "gn:country_code":"KP",
    "gn:dem":686,
    "gn:feature_class":"P",
    "gn:feature_code":"PPL",
    "gn:name":"Nop\u2019\u016dn\u2019g\u014fri",
    "gn:population":0,
    "gn:timezone":"Asia/Pyongyang",
    "iso:country":"KP",
    "wof:name":"Nop'un'gori",
    "wof:placetype":"locality"
},
  "geometry": {"coordinates":[128.03222,41.40833],"type":"Point"}
}