{
  "type": "Feature",
  "properties": {
    "gn:admin1_code":"15.0",
    "gn:asciiname":"Sokch'o-dong",
    "gn:country_code":"KP",
    "gn:dem":486,
    "gn:feature_class":"P",
    "gn:feature_code":"PPL",
    "gn:name":"Sokch\u2019o-dong",
    "gn:population":0,
    "gn:timezone":"Asia/Pyongyang",
    "iso:country":"KP",
    "name:und_x_variant":[
        "\uc18d\ucd08\ub3d9",
        "Sokch\u2019o-dong"
    ],
    "wof:name":"Sokch'o-dong",
    "wof:placetype":"locality"
},
  "geometry": {"coordinates":[126.74833,39.16472],"type":"Point"}
}