{
  "type": "Feature",
  "properties": {
    "gn:admin1_code":"0.0",
    "gn:asciiname":"Puldang-dong",
    "gn:country_code":"KP",
    "gn:dem":46,
    "gn:feature_class":"P",
    "gn:feature_code":"PPL",
    "gn:name":"Puldang-dong",
    "gn:population":0,
    "gn:timezone":"Asia/Pyongyang",
    "iso:country":"KP",
    "name:kor_x_preferred":[
        "\ubd88\ub2f9\ub3d9"
    ],
    "name:und_x_variant":[
        "Pultang-dong"
    ],
    "wof:name":"Puldang-dong",
    "wof:placetype":"locality"
},
  "geometry": {"coordinates":[125.75,38.83333],"type":"Point"}
}