{
  "type": "Feature",
  "properties": {
    "gn:admin1_code":"11.0",
    "gn:asciiname":"Haso-ri",
    "gn:country_code":"KP",
    "gn:dem":30,
    "gn:feature_class":"P",
    "gn:feature_code":"PPL",
    "gn:name":"Haso-ri",
    "gn:population":0,
    "gn:timezone":"Asia/Pyongyang",
    "iso:country":"KP",
    "name:kor_x_preferred":[
        "\ud558\uc18c\ub9ac"
    ],
    "wof:name":"Haso-ri",
    "wof:placetype":"locality"
},
  "geometry": {"coordinates":[124.91028,39.71478],"type":"Point"}
}