{
  "type": "Feature",
  "properties": {
    "gn:admin1_code":"7.0",
    "gn:asciiname":"Surak-tong",
    "gn:country_code":"KP",
    "gn:dem":16,
    "gn:feature_class":"P",
    "gn:feature_code":"PPL",
    "gn:name":"Surak-tong",
    "gn:population":0,
    "gn:timezone":"Asia/Pyongyang",
    "iso:country":"KP",
    "name:eng_x_preferred":[
        "Surak"
    ],
    "name:eng_x_variant":[
        "Surak-tong"
    ],
    "name:kor_x_preferred":[
        "\uc218\ub77d\ub3d9"
    ],
    "wof:name":"Surak",
    "wof:placetype":"locality"
},
  "geometry": {"coordinates":[125.53139,38.63417],"type":"Point"}
}