{
  "type": "Feature",
  "properties": {
    "gn:admin1_code":"13.0",
    "gn:asciiname":"Songam-ni",
    "gn:country_code":"KP",
    "gn:dem":868,
    "gn:feature_class":"P",
    "gn:feature_code":"PPL",
    "gn:name":"Songam-ni",
    "gn:population":0,
    "gn:timezone":"Asia/Pyongyang",
    "iso:country":"KP",
    "name:kor_x_preferred":[
        "\uc1a1\uc554\ub9ac"
    ],
    "wof:name":"Songam-ni",
    "wof:placetype":"locality"
},
  "geometry": {"coordinates":[128.30916999999999,41.35306],"type":"Point"}
}