{
  "type": "Feature",
  "properties": {
    "gn:admin1_code":"17.0",
    "gn:asciiname":"Pakch'ung-nodongjagu",
    "gn:country_code":"KP",
    "gn:dem":33,
    "gn:feature_class":"P",
    "gn:feature_code":"PPL",
    "gn:name":"Pakch\u2019ung-nodongjagu",
    "gn:population":0,
    "gn:timezone":"Asia/Pyongyang",
    "iso:country":"KP",
    "name:und_x_variant":[
        "Bokuch\u016b",
        "Pakchung-dong",
        "Bokuch\u016b-do",
        "Pakch\u2019ung",
        "Pakch\u2019ung-ni",
        "\ubc15\ucda9\ub85c\ub3d9\uc790\uad6c",
        "Pakch\u2019ung-nodongjagu"
    ],
    "wof:name":"Pakch'ung-nodongjagu",
    "wof:placetype":"locality"
},
  "geometry": {"coordinates":[129.62166999999999,41.66333],"type":"Point"}
}