{
  "type": "Feature",
  "properties": {
    "gn:admin1_code":"7.0",
    "gn:asciiname":"Orumdol",
    "gn:country_code":"KP",
    "gn:dem":177,
    "gn:feature_class":"P",
    "gn:feature_code":"PPL",
    "gn:name":"\u014er\u016dmdol",
    "gn:population":0,
    "gn:timezone":"Asia/Pyongyang",
    "iso:country":"KP",
    "name:kor_x_preferred":[
        "\uc5b4\ub984\ub3cc"
    ],
    "name:kor_x_variant":[
        "\u014er\u016dmdol"
    ],
    "wof:name":"Orumdol",
    "wof:placetype":"locality"
},
  "geometry": {"coordinates":[126.65472,38.57389000000001],"type":"Point"}
}