{
  "type": "Feature",
  "properties": {
    "gn:admin1_code":"7.0",
    "gn:asciiname":"Toksong-ni",
    "gn:country_code":"KP",
    "gn:dem":80,
    "gn:feature_class":"P",
    "gn:feature_code":"PPL",
    "gn:name":"T\u014fks\u014fng-ni",
    "gn:population":0,
    "gn:timezone":"Asia/Pyongyang",
    "iso:country":"KP",
    "name:eng_x_preferred":[
        "Toksong"
    ],
    "name:eng_x_variant":[
        "Toksong-ni"
    ],
    "wof:name":"Toksong",
    "wof:placetype":"locality"
},
  "geometry": {"coordinates":[125.99556,38.33111],"type":"Point"}
}