{
  "type": "Feature",
  "properties": {
    "gn:admin1_code":"3.0",
    "gn:admin2_code":"Tanch\u2019\u014fn-si",
    "gn:asciiname":"Sinhungdogi",
    "gn:country_code":"KP",
    "gn:dem":1417,
    "gn:feature_class":"P",
    "gn:feature_code":"PPL",
    "gn:name":"Sinh\u016dngd\u014fgi",
    "gn:population":0,
    "gn:timezone":"Asia/Pyongyang",
    "iso:country":"KP",
    "wof:name":"Sinhungdogi",
    "wof:placetype":"locality"
},
  "geometry": {"coordinates":[128.73832999999999,41.13556],"type":"Point"}
}