{
  "type": "Feature",
  "properties": {
    "gn:admin1_code":"11.0",
    "gn:asciiname":"Hakpong",
    "gn:country_code":"KP",
    "gn:dem":11,
    "gn:feature_class":"P",
    "gn:feature_code":"PPL",
    "gn:name":"Hakpong",
    "gn:population":0,
    "gn:timezone":"Asia/Pyongyang",
    "iso:country":"KP",
    "name:kor_x_preferred":[
        "\ud559\ubd09"
    ],
    "wof:name":"Hakpong",
    "wof:placetype":"locality"
},
  "geometry": {"coordinates":[124.55535,39.83989],"type":"Point"}
}