{
  "type": "Feature",
  "properties": {
    "gn:admin1_code":"13.0",
    "gn:asciiname":"Konjang-ni",
    "gn:country_code":"KP",
    "gn:dem":1057,
    "gn:feature_class":"P",
    "gn:feature_code":"PPL",
    "gn:name":"K\u014fnjang-ni",
    "gn:population":0,
    "gn:timezone":"Asia/Pyongyang",
    "iso:country":"KP",
    "wof:name":"Konjang-ni",
    "wof:placetype":"locality"
},
  "geometry": {"coordinates":[128.48861000000002,41.06917],"type":"Point"}
}