{
  "type": "Feature",
  "properties": {
    "gn:admin1_code":"6.0",
    "gn:admin2_code":"Paech'\u014fn-gun",
    "gn:asciiname":"Kumsong-ni",
    "gn:country_code":"KP",
    "gn:dem":25,
    "gn:feature_class":"P",
    "gn:feature_code":"PPL",
    "gn:name":"K\u016dms\u014fng-ni",
    "gn:population":0,
    "gn:timezone":"Asia/Pyongyang",
    "iso:country":"KP",
    "name:kor_x_preferred":[
        "\uae08\uc131\ub9ac"
    ],
    "name:und_x_variant":[
        "K\u016dms\u014fng-ni"
    ],
    "wof:name":"Kumsong-ni",
    "wof:placetype":"locality"
},
  "geometry": {"coordinates":[126.23305999999999,37.90611],"type":"Point"}
}