{
  "type": "Feature",
  "properties": {
    "gn:admin1_code":"15.0",
    "gn:asciiname":"Kumch'on",
    "gn:country_code":"KP",
    "gn:dem":45,
    "gn:feature_class":"P",
    "gn:feature_code":"PPL",
    "gn:name":"K\u016dmch\u2019on",
    "gn:population":0,
    "gn:timezone":"Asia/Pyongyang",
    "iso:country":"KP",
    "name:und_x_variant":[
        "K\u016dmch\u2019\u014fn-ni",
        "K\u016dmch\u2019on"
    ],
    "wof:name":"Kumch'on",
    "wof:placetype":"locality"
},
  "geometry": {"coordinates":[125.88611000000002,39.43917],"type":"Point"}
}