{
  "type": "Feature",
  "properties": {
    "gn:admin1_code":"3.0",
    "gn:asciiname":"Simp'o-ri",
    "gn:country_code":"KP",
    "gn:dem":1052,
    "gn:feature_class":"P",
    "gn:feature_code":"PPL",
    "gn:name":"Simp\u2019o-ri",
    "gn:population":0,
    "gn:timezone":"Asia/Pyongyang",
    "iso:country":"KP",
    "name:kor_x_preferred":[
        "\uc2ec\ud3ec\ub9ac"
    ],
    "name:kor_x_variant":[
        "Simp\u2019o-ri"
    ],
    "wof:name":"Simp'o-ri",
    "wof:placetype":"locality"
},
  "geometry": {"coordinates":[127.25639,40.59528],"type":"Point"}
}