{
  "type": "Feature",
  "properties": {
    "gn:admin1_code":"0.0",
    "gn:asciiname":"Ch'onghang-ni",
    "gn:country_code":"KP",
    "gn:dem":665,
    "gn:feature_class":"P",
    "gn:feature_code":"PPL",
    "gn:name":"Ch\u2019\u014fnghang-ni",
    "gn:population":0,
    "gn:timezone":"Asia/Pyongyang",
    "iso:country":"KP",
    "name:kor_x_preferred":[
        "\uccad\ud56d\ub9ac"
    ],
    "name:und_x_variant":[
        "Ch\u2019\u014fnghang-ni"
    ],
    "wof:name":"Ch'onghang-ni",
    "wof:placetype":"locality"
},
  "geometry": {"coordinates":[127.40000000000001,38.73333],"type":"Point"}
}