{
  "type": "Feature",
  "properties": {
    "gn:admin1_code":"11.0",
    "gn:asciiname":"Unha-ri",
    "gn:country_code":"KP",
    "gn:dem":36,
    "gn:feature_class":"P",
    "gn:feature_code":"PPL",
    "gn:name":"Unha-ri",
    "gn:population":0,
    "gn:timezone":"Asia/Pyongyang",
    "iso:country":"KP",
    "name:kor_x_preferred":[
        "\uc6b4\ud558\ub9ac"
    ],
    "wof:name":"Unha-ri",
    "wof:placetype":"locality"
},
  "geometry": {"coordinates":[125.42861000000001,39.61083],"type":"Point"}
}