{
  "type": "Feature",
  "properties": {
    "gn:admin1_code":"11.0",
    "gn:asciiname":"Kamch'o-ri",
    "gn:country_code":"KP",
    "gn:dem":38,
    "gn:feature_class":"P",
    "gn:feature_code":"PPL",
    "gn:name":"Kamch\u2019o-ri",
    "gn:population":0,
    "gn:timezone":"Asia/Pyongyang",
    "iso:country":"KP",
    "name:und_x_variant":[
        "\uac10\ucd08\ub9ac",
        "Kamch\u2019o-ri"
    ],
    "wof:name":"Kamch'o-ri",
    "wof:placetype":"locality"
},
  "geometry": {"coordinates":[124.61221999999999,40.04889],"type":"Point"}
}