{
  "type": "Feature",
  "properties": {
    "gn:admin1_code":"15.0",
    "gn:asciiname":"Powoll il-li",
    "gn:country_code":"KP",
    "gn:dem":7,
    "gn:feature_class":"P",
    "gn:feature_code":"PPL",
    "gn:name":"Powoll il-li",
    "gn:population":0,
    "gn:timezone":"Asia/Pyongyang",
    "iso:country":"KP",
    "name:kor_x_preferred":[
        "\ubcf4\uc6d0\ub9ac 2\ub9ac"
    ],
    "name:und_x_variant":[
        "Pow\u014fnni I-ri",
        "Powoll il-li"
    ],
    "wof:name":"Powoll il-li",
    "wof:placetype":"locality"
},
  "geometry": {"coordinates":[125.3925,39.42611],"type":"Point"}
}