{
  "type": "Feature",
  "properties": {
    "gn:admin1_code":"11.0",
    "gn:asciiname":"Kop'owon",
    "gn:country_code":"KP",
    "gn:dem":167,
    "gn:feature_class":"P",
    "gn:feature_code":"PPL",
    "gn:name":"Kop\u2019ow\u014fn",
    "gn:population":0,
    "gn:timezone":"Asia/Pyongyang",
    "iso:country":"KP",
    "name:und_x_variant":[
        "\uace0\ud3ec\uc6d0",
        "Kop\u2019ow\u014fn"
    ],
    "wof:name":"Kop'owon",
    "wof:placetype":"locality"
},
  "geometry": {"coordinates":[126.01000000000001,40.05083],"type":"Point"}
}