{
  "type": "Feature",
  "properties": {
    "gn:admin1_code":"15.0",
    "gn:asciiname":"Imsong-ni",
    "gn:country_code":"KP",
    "gn:dem":19,
    "gn:feature_class":"P",
    "gn:feature_code":"PPL",
    "gn:name":"Ims\u014fng-ni",
    "gn:population":0,
    "gn:timezone":"Asia/Pyongyang",
    "iso:country":"KP",
    "name:eng_x_preferred":[
        "Imsong"
    ],
    "name:eng_x_variant":[
        "Imsong-ni"
    ],
    "wof:name":"Imsong",
    "wof:placetype":"locality"
},
  "geometry": {"coordinates":[125.355,39.06472],"type":"Point"}
}