{
  "type": "Feature",
  "properties": {
    "gn:admin1_code":"7.0",
    "gn:asciiname":"Myongsong-dong",
    "gn:country_code":"KP",
    "gn:dem":58,
    "gn:feature_class":"P",
    "gn:feature_code":"PPL",
    "gn:name":"My\u014fngs\u014fng-dong",
    "gn:population":0,
    "gn:timezone":"Asia/Pyongyang",
    "iso:country":"KP",
    "wof:name":"Myongsong-dong",
    "wof:placetype":"locality"
},
  "geometry": {"coordinates":[125.87139000000001,38.36139],"type":"Point"}
}