{
  "type": "Feature",
  "properties": {
    "gn:admin1_code":"6.0",
    "gn:asciiname":"Yongjong-ni",
    "gn:country_code":"KP",
    "gn:dem":32,
    "gn:feature_class":"P",
    "gn:feature_code":"PPL",
    "gn:name":"Yongj\u014fng-ni",
    "gn:population":0,
    "gn:timezone":"Asia/Pyongyang",
    "iso:country":"KP",
    "name:eng_x_preferred":[
        "Yongjong"
    ],
    "name:eng_x_variant":[
        "Yongjong-ni"
    ],
    "wof:name":"Yongjong",
    "wof:placetype":"locality"
},
  "geometry": {"coordinates":[125.51027999999999,38.32389],"type":"Point"}
}