{
  "type": "Feature",
  "properties": {
    "gn:admin1_code":"6.0",
    "gn:asciiname":"Poch'on-dong",
    "gn:country_code":"KP",
    "gn:dem":68,
    "gn:feature_class":"P",
    "gn:feature_code":"PPL",
    "gn:name":"Poch\u2019\u014fn-dong",
    "gn:population":0,
    "gn:timezone":"Asia/Pyongyang",
    "iso:country":"KP",
    "wof:name":"Poch'on-dong",
    "wof:placetype":"locality"
},
  "geometry": {"coordinates":[125.26083,38.58944],"type":"Point"}
}