{
  "type": "Feature",
  "properties": {
    "gn:admin1_code":"11.0",
    "gn:asciiname":"Naesang",
    "gn:country_code":"KP",
    "gn:dem":110,
    "gn:feature_class":"P",
    "gn:feature_code":"PPL",
    "gn:name":"Naesang",
    "gn:population":0,
    "gn:timezone":"Asia/Pyongyang",
    "iso:country":"KP",
    "wof:name":"Naesang",
    "wof:placetype":"locality"
},
  "geometry": {"coordinates":[125.35056000000002,39.87806],"type":"Point"}
}