{
  "type": "Feature",
  "properties": {
    "gn:admin1_code":"9.0",
    "gn:asciiname":"Ch'uhyon",
    "gn:country_code":"KP",
    "gn:dem":350,
    "gn:feature_class":"P",
    "gn:feature_code":"PPL",
    "gn:name":"Ch\u2019uhy\u014fn",
    "gn:population":0,
    "gn:timezone":"Asia/Pyongyang",
    "iso:country":"KP",
    "name:kor_x_preferred":[
        "\ucd94\ud604"
    ],
    "name:und_x_variant":[
        "Ch\u2019uhy\u014fn"
    ],
    "wof:name":"Ch'uhyon",
    "wof:placetype":"locality"
},
  "geometry": {"coordinates":[127.24944000000001,38.64278],"type":"Point"}
}