{
  "type": "Feature",
  "properties": {
    "gn:admin1_code":"11.0",
    "gn:asciiname":"Noksan-gol",
    "gn:country_code":"KP",
    "gn:dem":29,
    "gn:feature_class":"P",
    "gn:feature_code":"PPL",
    "gn:name":"Noksan-gol",
    "gn:population":0,
    "gn:timezone":"Asia/Pyongyang",
    "iso:country":"KP",
    "name:kor_x_preferred":[
        "\ub179\uc0b0\uace8"
    ],
    "name:und_x_variant":[
        "Noksan-kol",
        "Noksan-dong",
        "Noksan-gol"
    ],
    "wof:name":"Noksan-gol",
    "wof:placetype":"locality"
},
  "geometry": {"coordinates":[124.86278,39.85861],"type":"Point"}
}