{
  "type": "Feature",
  "properties": {
    "gn:admin1_code":"11.0",
    "gn:asciiname":"Kuksogok",
    "gn:country_code":"KP",
    "gn:dem":53,
    "gn:feature_class":"P",
    "gn:feature_code":"PPL",
    "gn:name":"Kuks\u014fgok",
    "gn:population":0,
    "gn:timezone":"Asia/Pyongyang",
    "iso:country":"KP",
    "name:und_x_variant":[
        "\uad6d\uc11c\uace1",
        "Kuks\u014fgok"
    ],
    "wof:name":"Kuksogok",
    "wof:placetype":"locality"
},
  "geometry": {"coordinates":[124.64861000000001,40.25917000000001],"type":"Point"}
}