{
  "type": "Feature",
  "properties": {
    "gn:admin1_code":"7.0",
    "gn:asciiname":"Yonghu-dong",
    "gn:country_code":"KP",
    "gn:dem":156,
    "gn:feature_class":"P",
    "gn:feature_code":"PPL",
    "gn:name":"Yonghu-dong",
    "gn:population":0,
    "gn:timezone":"Asia/Pyongyang",
    "iso:country":"KP",
    "name:kor_x_preferred":[
        "\uc6a9\ud6c4\ub3d9"
    ],
    "wof:name":"Yonghu-dong",
    "wof:placetype":"locality"
},
  "geometry": {"coordinates":[126.70111,38.77861],"type":"Point"}
}