{
  "type": "Feature",
  "properties": {
    "gn:admin1_code":"6.0",
    "gn:asciiname":"Chegol",
    "gn:country_code":"KP",
    "gn:dem":125,
    "gn:feature_class":"P",
    "gn:feature_code":"PPL",
    "gn:name":"Chegol",
    "gn:population":0,
    "gn:timezone":"Asia/Pyongyang",
    "iso:country":"KP",
    "name:kor_x_preferred":[
        "\uc81c\uace8"
    ],
    "wof:name":"Chegol",
    "wof:placetype":"locality"
},
  "geometry": {"coordinates":[125.48860999999999,38.14778],"type":"Point"}
}