{
  "type": "Feature",
  "properties": {
    "gn:admin1_code":"15.0",
    "gn:asciiname":"Yongp'yongha-dong",
    "gn:country_code":"KP",
    "gn:dem":43,
    "gn:feature_class":"P",
    "gn:feature_code":"PPL",
    "gn:name":"Yongp\u2019y\u014fngha-dong",
    "gn:population":0,
    "gn:timezone":"Asia/Pyongyang",
    "iso:country":"KP",
    "name:und_x_variant":[
        "\uc6a9\ud3c9\ud558\ub3d9",
        "Yongp\u2019y\u014fngha-dong"
    ],
    "wof:name":"Yongp'yongha-dong",
    "wof:placetype":"locality"
},
  "geometry": {"coordinates":[125.27861,38.88389],"type":"Point"}
}