{
  "type": "Feature",
  "properties": {
    "gn:admin1_code":"15.0",
    "gn:admin2_code":"1871865",
    "gn:asciiname":"Hwarim-ni",
    "gn:country_code":"KP",
    "gn:dem":25,
    "gn:feature_class":"P",
    "gn:feature_code":"PPL",
    "gn:name":"Hwarim-ni",
    "gn:population":0,
    "gn:timezone":"Asia/Pyongyang",
    "iso:country":"KP",
    "name:eng_x_preferred":[
        "Hwarim"
    ],
    "name:eng_x_variant":[
        "Hwarim-ni"
    ],
    "wof:name":"Hwarim",
    "wof:placetype":"locality"
},
  "geometry": {"coordinates":[125.5825,39.32028],"type":"Point"}
}