{
  "type": "Feature",
  "properties": {
    "gn:admin1_code":"9.0",
    "gn:asciiname":"Araemal",
    "gn:country_code":"KP",
    "gn:dem":193,
    "gn:feature_class":"P",
    "gn:feature_code":"PPL",
    "gn:name":"Araemal",
    "gn:population":0,
    "gn:timezone":"Asia/Pyongyang",
    "iso:country":"KP",
    "wof:name":"Araemal",
    "wof:placetype":"locality"
},
  "geometry": {"coordinates":[127.16722,38.47139],"type":"Point"}
}