{
  "type": "Feature",
  "properties": {
    "gn:admin1_code":"7.0",
    "gn:asciiname":"Samsang-dong",
    "gn:country_code":"KP",
    "gn:dem":13,
    "gn:feature_class":"P",
    "gn:feature_code":"PPL",
    "gn:name":"Samsang-dong",
    "gn:population":0,
    "gn:timezone":"Asia/Pyongyang",
    "iso:country":"KP",
    "name:kor_x_preferred":[
        "\uc0bc\uc0c1\ub3d9"
    ],
    "wof:name":"Samsang-dong",
    "wof:placetype":"locality"
},
  "geometry": {"coordinates":[125.54333,38.53667],"type":"Point"}
}