{
  "type": "Feature",
  "properties": {
    "gn:admin1_code":"13.0",
    "gn:admin2_code":"Paegam-gun",
    "gn:asciiname":"Sangch'op'yong",
    "gn:country_code":"KP",
    "gn:dem":1570,
    "gn:feature_class":"P",
    "gn:feature_code":"PPL",
    "gn:name":"Sangch\u2019op\u2019y\u014fng",
    "gn:population":0,
    "gn:timezone":"Asia/Pyongyang",
    "iso:country":"KP",
    "wof:name":"Sangch'op'yong",
    "wof:placetype":"locality"
},
  "geometry": {"coordinates":[128.86000000000001,41.18361],"type":"Point"}
}