{
  "type": "Feature",
  "properties": {
    "gn:admin1_code":"15.0",
    "gn:asciiname":"Chungsan-dong",
    "gn:country_code":"KP",
    "gn:dem":63,
    "gn:feature_class":"P",
    "gn:feature_code":"PPL",
    "gn:name":"Ch\u016dngsan-dong",
    "gn:population":0,
    "gn:timezone":"Asia/Pyongyang",
    "iso:country":"KP",
    "name:und_x_variant":[
        "Ch\u016dngsan-ni",
        "Ch\u016dngsan-dong"
    ],
    "wof:name":"Chungsan-dong",
    "wof:placetype":"locality"
},
  "geometry": {"coordinates":[125.98333,39.46667],"type":"Point"}
}