{
  "type": "Feature",
  "properties": {
    "gn:admin1_code":"13.0",
    "gn:admin2_code":"2041726",
    "gn:asciiname":"Sosang-ni",
    "gn:country_code":"KP",
    "gn:dem":1101,
    "gn:feature_class":"P",
    "gn:feature_code":"PPL",
    "gn:name":"S\u014fsang-ni",
    "gn:population":0,
    "gn:timezone":"Asia/Pyongyang",
    "iso:country":"KP",
    "wof:name":"Sosang-ni",
    "wof:placetype":"locality"
},
  "geometry": {"coordinates":[127.91194,40.90778],"type":"Point"}
}