{
  "type": "Feature",
  "properties": {
    "gn:admin1_code":"17.0",
    "gn:asciiname":"Kwangha-dong",
    "gn:country_code":"KP",
    "gn:dem":628,
    "gn:feature_class":"P",
    "gn:feature_code":"PPL",
    "gn:name":"Kwangha-dong",
    "gn:population":0,
    "gn:timezone":"Asia/Pyongyang",
    "iso:country":"KP",
    "name:und_x_variant":[
        "\uad11\ud558\ub3d9",
        "Kwangha-dong"
    ],
    "wof:name":"Kwangha-dong",
    "wof:placetype":"locality"
},
  "geometry": {"coordinates":[129.39278000000002,41.41278],"type":"Point"}
}