{
  "type": "Feature",
  "properties": {
    "gn:admin1_code":"7.0",
    "gn:asciiname":"Misan-dong",
    "gn:country_code":"KP",
    "gn:dem":115,
    "gn:feature_class":"P",
    "gn:feature_code":"PPL",
    "gn:name":"Misan-dong",
    "gn:population":0,
    "gn:timezone":"Asia/Pyongyang",
    "iso:country":"KP",
    "name:kor_x_preferred":[
        "\ubbf8\uc0b0\ub3d9"
    ],
    "wof:name":"Misan-dong",
    "wof:placetype":"locality"
},
  "geometry": {"coordinates":[126.40306,38.54028],"type":"Point"}
}