{
  "type": "Feature",
  "properties": {
    "gn:admin1_code":"11.0",
    "gn:asciiname":"Chonggye-ri",
    "gn:country_code":"KP",
    "gn:dem":101,
    "gn:feature_class":"P",
    "gn:feature_code":"PPL",
    "gn:name":"Chonggye-ri",
    "gn:population":0,
    "gn:timezone":"Asia/Pyongyang",
    "iso:country":"KP",
    "name:und_x_variant":[
        "\uc885\uacc4\ub9ac",
        "Chonggye-ri"
    ],
    "wof:name":"Chonggye-ri",
    "wof:placetype":"locality"
},
  "geometry": {"coordinates":[124.69278,40.23194],"type":"Point"}
}