{
  "type": "Feature",
  "properties": {
    "gn:admin1_code":"15.0",
    "gn:asciiname":"Hangno-dong",
    "gn:country_code":"KP",
    "gn:dem":33,
    "gn:feature_class":"P",
    "gn:feature_code":"PPL",
    "gn:name":"Hangno-dong",
    "gn:population":0,
    "gn:timezone":"Asia/Pyongyang",
    "iso:country":"KP",
    "name:kor_x_preferred":[
        "\ud559\ub178\ub3d9"
    ],
    "name:und_x_variant":[
        "Hangnodong"
    ],
    "wof:name":"Hangno-dong",
    "wof:placetype":"locality"
},
  "geometry": {"coordinates":[125.59999999999999,39.07139],"type":"Point"}
}