{
  "type": "Feature",
  "properties": {
    "gn:admin1_code":"9.0",
    "gn:asciiname":"Haso-ri",
    "gn:country_code":"KP",
    "gn:dem":374,
    "gn:feature_class":"P",
    "gn:feature_code":"PPL",
    "gn:name":"Has\u014f-ri",
    "gn:population":0,
    "gn:timezone":"Asia/Pyongyang",
    "iso:country":"KP",
    "name:kor_x_preferred":[
        "\ud558\uc11c\ub9ac"
    ],
    "name:kor_x_variant":[
        "Has\u014f-ri"
    ],
    "wof:name":"Haso-ri",
    "wof:placetype":"locality"
},
  "geometry": {"coordinates":[127.01361,39.09889],"type":"Point"}
}