{
  "type": "Feature",
  "properties": {
    "gn:admin1_code":"0.0",
    "gn:asciiname":"Koje-dong",
    "gn:country_code":"KP",
    "gn:dem":61,
    "gn:feature_class":"P",
    "gn:feature_code":"PPL",
    "gn:name":"Koje-dong",
    "gn:population":0,
    "gn:timezone":"Asia/Pyongyang",
    "iso:country":"KP",
    "name:kor_x_preferred":[
        "\uace0\uc81c\ub3d9"
    ],
    "wof:name":"Koje-dong",
    "wof:placetype":"locality"
},
  "geometry": {"coordinates":[125.09999999999999,37.93333],"type":"Point"}
}