{
  "type": "Feature",
  "properties": {
    "gn:admin1_code":"9.0",
    "gn:admin2_code":"Ch\u2019\u014fnnae-gun",
    "gn:asciiname":"Sinch'ol-li",
    "gn:country_code":"KP",
    "gn:dem":29,
    "gn:feature_class":"P",
    "gn:feature_code":"PPL",
    "gn:name":"Sinch\u2019\u014fl-li",
    "gn:population":0,
    "gn:timezone":"Asia/Pyongyang",
    "iso:country":"KP",
    "name:kor_x_preferred":[
        "Sinch\u2019\u014fl-li"
    ],
    "name:und_x_variant":[
        "Sinch\u2019\u014fn-ni"
    ],
    "wof:name":"Sinch'ol-li",
    "wof:placetype":"locality"
},
  "geometry": {"coordinates":[127.32722,39.38278],"type":"Point"}
}