{
  "type": "Feature",
  "properties": {
    "gn:admin1_code":"0.0",
    "gn:asciiname":"Sisan-ni",
    "gn:cc2":"KP",
    "gn:country_code":"KP",
    "gn:dem":78,
    "gn:feature_class":"P",
    "gn:feature_code":"PPL",
    "gn:name":"Sisan-ni",
    "gn:population":0,
    "gn:timezone":"Asia/Pyongyang",
    "iso:country":"KP",
    "name:kor_x_preferred":[
        "\uc2dc\uc0b0\ub9ac"
    ],
    "name:und_x_variant":[
        "Sansan-ni",
        "Sisan-ni"
    ],
    "wof:name":"Sisan-ni",
    "wof:placetype":"locality"
},
  "geometry": {"coordinates":[125.73333,38.58333],"type":"Point"}
}