{
  "type": "Feature",
  "properties": {
    "gn:admin1_code":"11.0",
    "gn:asciiname":"Unam-ni",
    "gn:country_code":"KP",
    "gn:dem":122,
    "gn:feature_class":"P",
    "gn:feature_code":"PPL",
    "gn:name":"Unam-ni",
    "gn:population":0,
    "gn:timezone":"Asia/Pyongyang",
    "iso:country":"KP",
    "name:und_x_variant":[
        "\uc6b4\uc554\ub9ac",
        "Unam-ni"
    ],
    "wof:name":"Unam-ni",
    "wof:placetype":"locality"
},
  "geometry": {"coordinates":[124.70471999999999,39.7925],"type":"Point"}
}