{
  "type": "Feature",
  "properties": {
    "gn:admin1_code":"6.0",
    "gn:asciiname":"Saemol",
    "gn:cc2":"KP",
    "gn:country_code":"KP",
    "gn:dem":17,
    "gn:feature_class":"P",
    "gn:feature_code":"PPL",
    "gn:name":"Saemol",
    "gn:population":0,
    "gn:timezone":"Asia/Pyongyang",
    "iso:country":"KP",
    "name:kor_x_preferred":[
        "\uc0c8\ubab0"
    ],
    "name:und_x_variant":[
        "Kanch\u2019on",
        "Chae-mal",
        "Saemol"
    ],
    "wof:name":"Saemol",
    "wof:placetype":"locality"
},
  "geometry": {"coordinates":[125.925,37.93833],"type":"Point"}
}