{
  "type": "Feature",
  "properties": {
    "gn:admin1_code":"7.0",
    "gn:asciiname":"Yuik-tong",
    "gn:country_code":"KP",
    "gn:dem":55,
    "gn:feature_class":"P",
    "gn:feature_code":"PPL",
    "gn:name":"Yuik-tong",
    "gn:population":0,
    "gn:timezone":"Asia/Pyongyang",
    "iso:country":"KP",
    "name:kor_x_preferred":[
        "\uc720\uc775\ub3d9"
    ],
    "wof:name":"Yuik-tong",
    "wof:placetype":"locality"
},
  "geometry": {"coordinates":[126.52861,38.41972],"type":"Point"}
}