{
  "type": "Feature",
  "properties": {
    "gn:admin1_code":"13.0",
    "gn:asciiname":"Simp'odong-ni",
    "gn:country_code":"KP",
    "gn:dem":1451,
    "gn:feature_class":"P",
    "gn:feature_code":"PPL",
    "gn:name":"Simp\u2019odong-ni",
    "gn:population":0,
    "gn:timezone":"Asia/Pyongyang",
    "iso:country":"KP",
    "name:eng_x_preferred":[
        "Simp'odong"
    ],
    "name:eng_x_variant":[
        "Simp'odong-ni"
    ],
    "name:und_x_variant":[
        "Simp\u2019o-dong",
        "Simp\u2019odong-ni"
    ],
    "wof:name":"Simp'odong",
    "wof:placetype":"locality"
},
  "geometry": {"coordinates":[127.87333,41.17583],"type":"Point"}
}