{
  "type": "Feature",
  "properties": {
    "gn:admin1_code":"7.0",
    "gn:asciiname":"Se-gol",
    "gn:country_code":"KP",
    "gn:dem":123,
    "gn:feature_class":"P",
    "gn:feature_code":"PPL",
    "gn:name":"Se-gol",
    "gn:population":0,
    "gn:timezone":"Asia/Pyongyang",
    "iso:country":"KP",
    "wof:name":"Se-gol",
    "wof:placetype":"locality"
},
  "geometry": {"coordinates":[125.94417,38.21778],"type":"Point"}
}