{
  "type": "Feature",
  "properties": {
    "gn:admin1_code":"9.0",
    "gn:asciiname":"Hajongwol",
    "gn:country_code":"KP",
    "gn:dem":48,
    "gn:feature_class":"P",
    "gn:feature_code":"PPL",
    "gn:name":"Haj\u014fngw\u014fl",
    "gn:population":0,
    "gn:timezone":"Asia/Pyongyang",
    "iso:country":"KP",
    "name:kor_x_preferred":[
        "\ud558\uc815\uc6d4"
    ],
    "name:und_x_variant":[
        "Haj\u014fngw\u014fl"
    ],
    "wof:name":"Hajongwol",
    "wof:placetype":"locality"
},
  "geometry": {"coordinates":[128.29083,38.63083],"type":"Point"}
}