{
  "type": "Feature",
  "properties": {
    "gn:admin1_code":"0.0",
    "gn:asciiname":"O-ch'on",
    "gn:country_code":"KP",
    "gn:dem":70,
    "gn:feature_class":"P",
    "gn:feature_code":"PPL",
    "gn:name":"O-ch\u2019on",
    "gn:population":0,
    "gn:timezone":"Asia/Pyongyang",
    "iso:country":"KP",
    "name:kor_x_preferred":[
        "\uc624\ucd0c"
    ],
    "name:und_x_variant":[
        "O-ch\u2019on"
    ],
    "wof:name":"O-ch'on",
    "wof:placetype":"locality"
},
  "geometry": {"coordinates":[125.58333,37.96667],"type":"Point"}
}