{
  "type": "Feature",
  "properties": {
    "gn:admin1_code":"15.0",
    "gn:asciiname":"Hoe-dong",
    "gn:country_code":"KP",
    "gn:dem":496,
    "gn:feature_class":"P",
    "gn:feature_code":"PPL",
    "gn:name":"Hoe-dong",
    "gn:population":0,
    "gn:timezone":"Asia/Pyongyang",
    "iso:country":"KP",
    "name:und_x_variant":[
        "Hoe-gol",
        "Hoe-dong",
        "\ud68c\ub3d9"
    ],
    "wof:name":"Hoe-dong",
    "wof:placetype":"locality"
},
  "geometry": {"coordinates":[127.01622999999999,39.19501],"type":"Point"}
}