{
  "type": "Feature",
  "properties": {
    "gn:admin1_code":"6.0",
    "gn:asciiname":"Hyonam-ni",
    "gn:country_code":"KP",
    "gn:dem":8,
    "gn:feature_class":"P",
    "gn:feature_code":"PPL",
    "gn:name":"Hy\u014fnam-ni",
    "gn:population":0,
    "gn:timezone":"Asia/Pyongyang",
    "iso:country":"KP",
    "name:kor_x_preferred":[
        "\ud604\uc554\ub9ac"
    ],
    "name:und_x_variant":[
        "Hy\u014fnam-ni"
    ],
    "wof:name":"Hyonam-ni",
    "wof:placetype":"locality"
},
  "geometry": {"coordinates":[125.97778,37.9025],"type":"Point"}
}