{
  "type": "Feature",
  "properties": {
    "gn:admin1_code":"0.0",
    "gn:asciiname":"Paegam",
    "gn:cc2":"KP",
    "gn:country_code":"KP",
    "gn:dem":7,
    "gn:feature_class":"P",
    "gn:feature_code":"PPL",
    "gn:name":"Paegam",
    "gn:population":0,
    "gn:timezone":"Asia/Pyongyang",
    "iso:country":"KP",
    "name:kor_x_preferred":[
        "\ubc31\uc554"
    ],
    "name:und_x_variant":[
        "Paekam",
        "Paegam"
    ],
    "wof:name":"Paegam",
    "wof:placetype":"locality"
},
  "geometry": {"coordinates":[125.61667,37.85],"type":"Point"}
}