{
  "type": "Feature",
  "properties": {
    "gn:admin1_code":"9.0",
    "gn:asciiname":"Honggadok",
    "gn:country_code":"KP",
    "gn:dem":908,
    "gn:feature_class":"P",
    "gn:feature_code":"PPL",
    "gn:name":"Honggad\u014fk",
    "gn:population":0,
    "gn:timezone":"Asia/Pyongyang",
    "iso:country":"KP",
    "wof:name":"Honggadok",
    "wof:placetype":"locality"
},
  "geometry": {"coordinates":[127.92028000000001,38.6425],"type":"Point"}
}