{
  "type": "Feature",
  "properties": {
    "gn:admin1_code":"12.0",
    "gn:admin2_code":"Sangw\u014fn-gun",
    "gn:asciiname":"Taedong-ni",
    "gn:country_code":"KP",
    "gn:dem":64,
    "gn:feature_class":"P",
    "gn:feature_code":"PPL",
    "gn:name":"Taedong-ni",
    "gn:population":0,
    "gn:timezone":"Asia/Pyongyang",
    "iso:country":"KP",
    "name:eng_x_preferred":[
        "Taedong"
    ],
    "name:eng_x_variant":[
        "Taedong-ni"
    ],
    "wof:name":"Taedong",
    "wof:placetype":"locality"
},
  "geometry": {"coordinates":[126.00694,38.90972],"type":"Point"}
}