{
  "type": "Feature",
  "properties": {
    "gn:admin1_code":"0.0",
    "gn:asciiname":"Kum-ch'on",
    "gn:country_code":"KP",
    "gn:dem":20,
    "gn:feature_class":"P",
    "gn:feature_code":"PPL",
    "gn:name":"K\u016dm-ch\u2019on",
    "gn:population":0,
    "gn:timezone":"Asia/Pyongyang",
    "iso:country":"KP",
    "name:kor_x_preferred":[
        "\uae08\ucd0c"
    ],
    "name:und_x_variant":[
        "K\u016dm-ch\u2019on"
    ],
    "wof:name":"Kum-ch'on",
    "wof:placetype":"locality"
},
  "geometry": {"coordinates":[125.40000000000001,38.81667],"type":"Point"}
}