{
  "type": "Feature",
  "properties": {
    "gn:admin1_code":"6.0",
    "gn:asciiname":"Taruji",
    "gn:country_code":"KP",
    "gn:dem":10,
    "gn:feature_class":"P",
    "gn:feature_code":"PPL",
    "gn:name":"Taruji",
    "gn:population":0,
    "gn:timezone":"Asia/Pyongyang",
    "iso:country":"KP",
    "name:und_x_variant":[
        "\ub2ec\uc6b0\uc9c0",
        "Taruji"
    ],
    "wof:name":"Taruji",
    "wof:placetype":"locality"
},
  "geometry": {"coordinates":[125.03778,38.58972],"type":"Point"}
}