{
  "type": "Feature",
  "properties": {
    "gn:admin1_code":"15.0",
    "gn:asciiname":"Ch'anmul-li",
    "gn:country_code":"KP",
    "gn:dem":19,
    "gn:feature_class":"P",
    "gn:feature_code":"PPL",
    "gn:name":"Ch\u2019anmul-li",
    "gn:population":0,
    "gn:timezone":"Asia/Pyongyang",
    "iso:country":"KP",
    "name:und_x_variant":[
        "Naengj\u014fng-ni",
        "\ucc2c\ubb3c\ub9ac",
        "Ch\u2019anmul-li"
    ],
    "wof:name":"Ch'anmul-li",
    "wof:placetype":"locality"
},
  "geometry": {"coordinates":[125.27,38.72333],"type":"Point"}
}