{
  "type": "Feature",
  "properties": {
    "gn:admin1_code":"11.0",
    "gn:asciiname":"Kiril-li",
    "gn:country_code":"KP",
    "gn:dem":118,
    "gn:feature_class":"P",
    "gn:feature_code":"PPL",
    "gn:name":"Kiril-li",
    "gn:population":0,
    "gn:timezone":"Asia/Pyongyang",
    "iso:country":"KP",
    "name:und_x_variant":[
        "Kirin-ni",
        "Kiril-li"
    ],
    "wof:name":"Kiril-li",
    "wof:placetype":"locality"
},
  "geometry": {"coordinates":[125.38556,39.78222],"type":"Point"}
}