{
  "type": "Feature",
  "properties": {
    "gn:admin1_code":"3.0",
    "gn:asciiname":"Namandae-ri",
    "gn:country_code":"KP",
    "gn:dem":3,
    "gn:feature_class":"P",
    "gn:feature_code":"PPL",
    "gn:name":"Namandae-ri",
    "gn:population":0,
    "gn:timezone":"Asia/Pyongyang",
    "iso:country":"KP",
    "name:und_x_variant":[
        "\ub0a8\ub300\ub9ac"
    ],
    "wof:name":"Namandae-ri",
    "wof:placetype":"locality"
},
  "geometry": {"coordinates":[128.31023999999999,40.04178],"type":"Point"}
}