{
  "type": "Feature",
  "properties": {
    "gn:admin1_code":"9.0",
    "gn:asciiname":"Sunam-ni",
    "gn:country_code":"KP",
    "gn:dem":33,
    "gn:feature_class":"P",
    "gn:feature_code":"PPL",
    "gn:name":"Sunam-ni",
    "gn:population":0,
    "gn:timezone":"Asia/Pyongyang",
    "iso:country":"KP",
    "name:eng_x_preferred":[
        "Sunam"
    ],
    "name:eng_x_variant":[
        "Sunam-ni"
    ],
    "name:und_x_variant":[
        "\uc218\ub0a8\ub9ac",
        "Sunam-ni"
    ],
    "wof:name":"Sunam",
    "wof:placetype":"locality"
},
  "geometry": {"coordinates":[127.53639,38.98167],"type":"Point"}
}