{
  "type": "Feature",
  "properties": {
    "gn:admin1_code":"1.0",
    "gn:asciiname":"Kaphyon-dong",
    "gn:country_code":"KP",
    "gn:dem":143,
    "gn:feature_class":"P",
    "gn:feature_code":"PPL",
    "gn:name":"Kaphy\u014fn-dong",
    "gn:population":0,
    "gn:timezone":"Asia/Pyongyang",
    "iso:country":"KP",
    "name:und_x_variant":[
        "\uac11\ud604\ub3d9",
        "Kaphy\u014fn-dong"
    ],
    "wof:name":"Kaphyon-dong",
    "wof:placetype":"locality"
},
  "geometry": {"coordinates":[126.20222,40.07667],"type":"Point"}
}