{
  "type": "Feature",
  "properties": {
    "gn:admin1_code":"7.0",
    "gn:asciiname":"Murung-ni",
    "gn:country_code":"KP",
    "gn:dem":73,
    "gn:feature_class":"P",
    "gn:feature_code":"PPL",
    "gn:name":"Mur\u016dng-ni",
    "gn:population":0,
    "gn:timezone":"Asia/Pyongyang",
    "iso:country":"KP",
    "wof:name":"Murung-ni",
    "wof:placetype":"locality"
},
  "geometry": {"coordinates":[126.61972,38.29278],"type":"Point"}
}