{
  "type": "Feature",
  "properties": {
    "gn:admin1_code":"3.0",
    "gn:asciiname":"Kumsa-ri",
    "gn:country_code":"KP",
    "gn:dem":204,
    "gn:feature_class":"P",
    "gn:feature_code":"PPL",
    "gn:name":"K\u016dmsa-ri",
    "gn:population":0,
    "gn:timezone":"Asia/Pyongyang",
    "iso:country":"KP",
    "name:und_x_variant":[
        "\uae08\uc0ac\ub9ac",
        "K\u016dmsa-ri"
    ],
    "wof:name":"Kumsa-ri",
    "wof:placetype":"locality"
},
  "geometry": {"coordinates":[127.68389000000001,40.0925],"type":"Point"}
}