{
  "type": "Feature",
  "properties": {
    "gn:admin1_code":"6.0",
    "gn:asciiname":"Ipsok-tong",
    "gn:country_code":"KP",
    "gn:dem":14,
    "gn:feature_class":"P",
    "gn:feature_code":"PPL",
    "gn:name":"Ips\u014fk-tong",
    "gn:population":0,
    "gn:timezone":"Asia/Pyongyang",
    "iso:country":"KP",
    "name:eng_x_preferred":[
        "Ipsok"
    ],
    "name:eng_x_variant":[
        "Ipsok-tong"
    ],
    "name:kor_x_preferred":[
        "\uc785\uc11d\ub3d9"
    ],
    "name:kor_x_variant":[
        "Ips\u014fk-tong"
    ],
    "wof:name":"Ipsok",
    "wof:placetype":"locality"
},
  "geometry": {"coordinates":[125.52916999999999,38.65083],"type":"Point"}
}