{
  "type": "Feature",
  "properties": {
    "gn:admin1_code":"6.0",
    "gn:asciiname":"Muryon-dong",
    "gn:country_code":"KP",
    "gn:dem":84,
    "gn:feature_class":"P",
    "gn:feature_code":"PPL",
    "gn:name":"Mury\u014fn-dong",
    "gn:population":0,
    "gn:timezone":"Asia/Pyongyang",
    "iso:country":"KP",
    "name:und_x_variant":[
        "\ubb34\ub828\ub3d9"
    ],
    "wof:name":"Muryon-dong",
    "wof:placetype":"locality"
},
  "geometry": {"coordinates":[125.20833,38.19583],"type":"Point"}
}