{
  "type": "Feature",
  "properties": {
    "gn:admin1_code":"13.0",
    "gn:asciiname":"Chaso-ri",
    "gn:country_code":"KP",
    "gn:dem":726,
    "gn:feature_class":"P",
    "gn:feature_code":"PPL",
    "gn:name":"Chas\u014f-ri",
    "gn:population":0,
    "gn:timezone":"Asia/Pyongyang",
    "iso:country":"KP",
    "name:kor_x_preferred":[
        "\uc790\uc11c\ub9ac"
    ],
    "name:und_x_variant":[
        "Chas\u014f-ri"
    ],
    "wof:name":"Chaso-ri",
    "wof:placetype":"locality"
},
  "geometry": {"coordinates":[127.75349,41.33096],"type":"Point"}
}