{
  "type": "Feature",
  "properties": {
    "gn:admin1_code":"7.0",
    "gn:asciiname":"Muk-tong",
    "gn:country_code":"KP",
    "gn:dem":167,
    "gn:feature_class":"P",
    "gn:feature_code":"PPL",
    "gn:name":"Muk-tong",
    "gn:population":0,
    "gn:timezone":"Asia/Pyongyang",
    "iso:country":"KP",
    "wof:name":"Muk-tong",
    "wof:placetype":"locality"
},
  "geometry": {"coordinates":[126.19917,38.71556],"type":"Point"}
}