{
  "type": "Feature",
  "properties": {
    "gn:admin1_code":"0.0",
    "gn:asciiname":"Miryong-ni",
    "gn:cc2":"KP",
    "gn:country_code":"KP",
    "gn:dem":9,
    "gn:feature_class":"P",
    "gn:feature_code":"PPL",
    "gn:name":"Miry\u014fng-ni",
    "gn:population":0,
    "gn:timezone":"Asia/Pyongyang",
    "iso:country":"KP",
    "name:kor_x_preferred":[
        "\ubbf8\ub839\ub9ac"
    ],
    "name:und_x_variant":[
        "Mir\u016dng-ni",
        "Miry\u014fng-ni"
    ],
    "wof:name":"Miryong-ni",
    "wof:placetype":"locality"
},
  "geometry": {"coordinates":[125.65000000000001,39.65],"type":"Point"}
}