{
  "type": "Feature",
  "properties": {
    "gn:admin1_code":"7.0",
    "gn:asciiname":"Tongsinhung-ni",
    "gn:country_code":"KP",
    "gn:dem":4,
    "gn:feature_class":"P",
    "gn:feature_code":"PPL",
    "gn:name":"Tongsinh\u016dng-ni",
    "gn:population":0,
    "gn:timezone":"Asia/Pyongyang",
    "iso:country":"KP",
    "name:kor_x_preferred":[
        "\ub3c4\uc2e0\ud765\ub9ac"
    ],
    "name:kor_x_variant":[
        "Tongsinh\u016dng-ni"
    ],
    "wof:name":"Tongsinhung-ni",
    "wof:placetype":"locality"
},
  "geometry": {"coordinates":[125.6425,38.56389],"type":"Point"}
}