{
  "type": "Feature",
  "properties": {
    "gn:admin1_code":"7.0",
    "gn:asciiname":"Madung-gol",
    "gn:country_code":"KP",
    "gn:dem":303,
    "gn:feature_class":"P",
    "gn:feature_code":"PPL",
    "gn:name":"Mad\u016dng-gol",
    "gn:population":0,
    "gn:timezone":"Asia/Pyongyang",
    "iso:country":"KP",
    "name:kor_x_preferred":[
        "\ub9c8\ub4f1\uace8"
    ],
    "name:kor_x_variant":[
        "Mad\u016dng-gol"
    ],
    "wof:name":"Madung-gol",
    "wof:placetype":"locality"
},
  "geometry": {"coordinates":[126.79583,38.70667],"type":"Point"}
}