{
  "type": "Feature",
  "properties": {
    "gn:admin1_code":"6.0",
    "gn:admin2_code":"1876380",
    "gn:asciiname":"Yul-tong",
    "gn:country_code":"KP",
    "gn:dem":29,
    "gn:feature_class":"P",
    "gn:feature_code":"PPL",
    "gn:name":"Yul-tong",
    "gn:population":0,
    "gn:timezone":"Asia/Pyongyang",
    "iso:country":"KP",
    "wof:name":"Yul-tong",
    "wof:placetype":"locality"
},
  "geometry": {"coordinates":[126.52472,37.87528],"type":"Point"}
}