{
  "type": "Feature",
  "properties": {
    "gn:admin1_code":"1.0",
    "gn:asciiname":"Hyonmal",
    "gn:country_code":"KP",
    "gn:dem":383,
    "gn:feature_class":"P",
    "gn:feature_code":"PPL",
    "gn:name":"Hy\u014fnmal",
    "gn:population":0,
    "gn:timezone":"Asia/Pyongyang",
    "iso:country":"KP",
    "name:kor_x_preferred":[
        "\ud604\ub9d0"
    ],
    "name:und_x_variant":[
        "\ud604\ub9d0",
        "Hy\u014fnmal"
    ],
    "wof:name":"Hyonmal",
    "wof:placetype":"locality"
},
  "geometry": {"coordinates":[126.55249999999999,40.76028],"type":"Point"}
}