{
  "type": "Feature",
  "properties": {
    "gn:admin1_code":"0.0",
    "gn:asciiname":"Sokch'onp'o",
    "gn:country_code":"KP",
    "gn:dem":4,
    "gn:feature_class":"P",
    "gn:feature_code":"PPL",
    "gn:name":"S\u014fkch\u2019\u014fnp\u2019o",
    "gn:population":0,
    "gn:timezone":"Asia/Pyongyang",
    "iso:country":"KP",
    "name:kor_x_preferred":[
        "\uc11d\ucc9c\ud3ec"
    ],
    "name:und_x_variant":[
        "S\u014fkch\u2019\u014fnp\u2019o"
    ],
    "wof:name":"Sokch'onp'o",
    "wof:placetype":"locality"
},
  "geometry": {"coordinates":[125.73333,38.01667],"type":"Point"}
}