{
  "type": "Feature",
  "properties": {
    "gn:admin1_code":"1.0",
    "gn:asciiname":"Tongdae-dong",
    "gn:country_code":"KP",
    "gn:dem":384,
    "gn:feature_class":"P",
    "gn:feature_code":"PPL",
    "gn:name":"Tongdae-dong",
    "gn:population":0,
    "gn:timezone":"Asia/Pyongyang",
    "iso:country":"KP",
    "name:kor_x_preferred":[
        "\ub3d9\ub300\ub3d9"
    ],
    "name:und_x_variant":[
        "\ub3d9\ub300\ub3d9",
        "Tongdae-dong"
    ],
    "wof:name":"Tongdae-dong",
    "wof:placetype":"locality"
},
  "geometry": {"coordinates":[126.64407,40.93588],"type":"Point"}
}