{
  "type": "Feature",
  "properties": {
    "gn:admin1_code":"12.0",
    "gn:asciiname":"Noyon-gol",
    "gn:country_code":"KP",
    "gn:dem":108,
    "gn:feature_class":"P",
    "gn:feature_code":"PPL",
    "gn:name":"Noy\u014fn-gol",
    "gn:population":0,
    "gn:timezone":"Asia/Pyongyang",
    "iso:country":"KP",
    "name:und_x_variant":[
        "\ub178\uc5f0\uace8",
        "Noy\u014fn-gol"
    ],
    "wof:name":"Noyon-gol",
    "wof:placetype":"locality"
},
  "geometry": {"coordinates":[125.96278,38.78278],"type":"Point"}
}