{
  "type": "Feature",
  "properties": {
    "gn:admin1_code":"6.0",
    "gn:asciiname":"Hawol-li",
    "gn:country_code":"KP",
    "gn:dem":113,
    "gn:feature_class":"P",
    "gn:feature_code":"PPL",
    "gn:name":"Haw\u014fl-li",
    "gn:population":0,
    "gn:timezone":"Asia/Pyongyang",
    "iso:country":"KP",
    "name:und_x_variant":[
        "\ud558\uc6d4\ub9ac",
        "Haw\u014fl-tong",
        "Haw\u014fl-li"
    ],
    "wof:name":"Hawol-li",
    "wof:placetype":"locality"
},
  "geometry": {"coordinates":[125.01027999999999,38.31111],"type":"Point"}
}