{
  "type": "Feature",
  "properties": {
    "gn:admin1_code":"17.0",
    "gn:asciiname":"Sorang-dong",
    "gn:country_code":"KP",
    "gn:dem":213,
    "gn:feature_class":"P",
    "gn:feature_code":"PPL",
    "gn:name":"Sorang-dong",
    "gn:population":0,
    "gn:timezone":"Asia/Pyongyang",
    "iso:country":"KP",
    "name:und_x_variant":[
        "\uc18c\ub791\ub3d9",
        "Sorang-dong"
    ],
    "wof:name":"Sorang-dong",
    "wof:placetype":"locality"
},
  "geometry": {"coordinates":[130.20833000000002,42.50333],"type":"Point"}
}