{
  "type": "Feature",
  "properties": {
    "gn:admin1_code":"12.0",
    "gn:asciiname":"T'aegam-ni",
    "gn:country_code":"KP",
    "gn:dem":53,
    "gn:feature_class":"P",
    "gn:feature_code":"PPL",
    "gn:name":"T\u2019aegam-ni",
    "gn:population":0,
    "gn:timezone":"Asia/Pyongyang",
    "iso:country":"KP",
    "name:kor_x_preferred":[
        "\ud0dd\uc554\ub9ac"
    ],
    "name:und_x_variant":[
        "T\u2019aegam-ni",
        "Taegamni"
    ],
    "wof:name":"T'aegam-ni",
    "wof:placetype":"locality"
},
  "geometry": {"coordinates":[125.69583,39.25147],"type":"Point"}
}