{
  "type": "Feature",
  "properties": {
    "gn:admin1_code":"9.0",
    "gn:asciiname":"Kongsujol-li",
    "gn:country_code":"KP",
    "gn:dem":53,
    "gn:feature_class":"P",
    "gn:feature_code":"PPL",
    "gn:name":"Kongsuj\u014fl-li",
    "gn:population":0,
    "gn:timezone":"Asia/Pyongyang",
    "iso:country":"KP",
    "name:kor_x_preferred":[
        "\uacf5\uc218\uc804\ub9ac"
    ],
    "name:und_x_variant":[
        "K\u014dsuden",
        "Kosuden-ri",
        "Kongsuj\u014fn-ni",
        "Kongsuj\u014fl-li"
    ],
    "wof:name":"Kongsujol-li",
    "wof:placetype":"locality"
},
  "geometry": {"coordinates":[127.55,38.95],"type":"Point"}
}