{
  "type": "Feature",
  "properties": {
    "gn:admin1_code":"17.0",
    "gn:asciiname":"Chosin-dong",
    "gn:country_code":"KP",
    "gn:dem":185,
    "gn:feature_class":"P",
    "gn:feature_code":"PPL",
    "gn:name":"Chosin-dong",
    "gn:population":0,
    "gn:timezone":"Asia/Pyongyang",
    "iso:country":"KP",
    "name:und_x_variant":[
        "\uc870\uc2e0\ub3d9",
        "Chosin-dong"
    ],
    "wof:name":"Chosin-dong",
    "wof:placetype":"locality"
},
  "geometry": {"coordinates":[130.08917,42.43333],"type":"Point"}
}