{
  "type": "Feature",
  "properties": {
    "gn:admin1_code":"17.0",
    "gn:asciiname":"Ch'undong-ni",
    "gn:country_code":"KP",
    "gn:dem":15,
    "gn:feature_class":"P",
    "gn:feature_code":"PPL",
    "gn:name":"Ch\u2019undong-ni",
    "gn:population":0,
    "gn:timezone":"Asia/Pyongyang",
    "iso:country":"KP",
    "name:und_x_variant":[
        "Ch\u2019un-dong",
        "\ucd98\ub3d9\ub9ac",
        "Ch\u2019undong-ni"
    ],
    "wof:name":"Ch'undong-ni",
    "wof:placetype":"locality"
},
  "geometry": {"coordinates":[129.26611,40.71889],"type":"Point"}
}