{
  "type": "Feature",
  "properties": {
    "gn:admin1_code":"9.0",
    "gn:admin2_code":"Munch\u2019\u014fn-si",
    "gn:asciiname":"Nujinmegi",
    "gn:country_code":"KP",
    "gn:dem":18,
    "gn:feature_class":"P",
    "gn:feature_code":"PPL",
    "gn:name":"Nujinmegi",
    "gn:population":0,
    "gn:timezone":"Asia/Pyongyang",
    "iso:country":"KP",
    "wof:name":"Nujinmegi",
    "wof:placetype":"locality"
},
  "geometry": {"coordinates":[127.3875,39.34639],"type":"Point"}
}