{
  "type": "Feature",
  "properties": {
    "gn:admin1_code":"7.0",
    "gn:asciiname":"Hoesong-ni",
    "gn:country_code":"KP",
    "gn:dem":148,
    "gn:feature_class":"P",
    "gn:feature_code":"PPL",
    "gn:name":"Hoes\u014fng-ni",
    "gn:population":0,
    "gn:timezone":"Asia/Pyongyang",
    "iso:country":"KP",
    "wof:name":"Hoesong-ni",
    "wof:placetype":"locality"
},
  "geometry": {"coordinates":[126.23667,38.69417],"type":"Point"}
}