{
  "type": "Feature",
  "properties": {
    "gn:admin1_code":"9.0",
    "gn:asciiname":"Taehak-tong",
    "gn:country_code":"KP",
    "gn:dem":574,
    "gn:feature_class":"P",
    "gn:feature_code":"PPL",
    "gn:name":"Taehak-tong",
    "gn:population":0,
    "gn:timezone":"Asia/Pyongyang",
    "iso:country":"KP",
    "name:und_x_variant":[
        "\ub300\ud559\ub3d9",
        "Taehak-tong"
    ],
    "wof:name":"Taehak-tong",
    "wof:placetype":"locality"
},
  "geometry": {"coordinates":[127.69806,38.73389],"type":"Point"}
}