{
  "type": "Feature",
  "properties": {
    "gn:admin1_code":"1.0",
    "gn:asciiname":"Yongsang-ni",
    "gn:country_code":"KP",
    "gn:dem":1096,
    "gn:feature_class":"P",
    "gn:feature_code":"PPL",
    "gn:name":"Y\u014fngsang-ni",
    "gn:population":0,
    "gn:timezone":"Asia/Pyongyang",
    "iso:country":"KP",
    "name:eng_x_preferred":[
        "Yongsang"
    ],
    "name:eng_x_variant":[
        "Yongsang-ni"
    ],
    "name:kor_x_preferred":[
        "\uc601\uc0c1\ub9ac"
    ],
    "name:kor_x_variant":[
        "Y\u014fngsang-ni"
    ],
    "wof:name":"Yongsang",
    "wof:placetype":"locality"
},
  "geometry": {"coordinates":[127.00806,40.935],"type":"Point"}
}