{
  "type": "Feature",
  "properties": {
    "gn:admin1_code":"3.0",
    "gn:asciiname":"Yongamnijungch'on",
    "gn:country_code":"KP",
    "gn:dem":15,
    "gn:feature_class":"P",
    "gn:feature_code":"PPL",
    "gn:name":"Yongamnijungch\u2019on",
    "gn:population":0,
    "gn:timezone":"Asia/Pyongyang",
    "iso:country":"KP",
    "name:und_x_variant":[
        "\uc6a9\uc554\ub9ac\uc911\ucd0c",
        "Yonggangnijung-ch\u2019on",
        "Yongamnijungch\u2019on"
    ],
    "wof:name":"Yongamnijungch'on",
    "wof:placetype":"locality"
},
  "geometry": {"coordinates":[128.83806000000001,40.39083],"type":"Point"}
}