{
  "type": "Feature",
  "properties": {
    "gn:admin1_code":"9.0",
    "gn:asciiname":"Ch'oech'on",
    "gn:country_code":"KP",
    "gn:dem":433,
    "gn:feature_class":"P",
    "gn:feature_code":"PPL",
    "gn:name":"Ch\u2019oech\u2019on",
    "gn:population":0,
    "gn:timezone":"Asia/Pyongyang",
    "iso:country":"KP",
    "name:kor_x_preferred":[
        "\ucd5c\ucd0c"
    ],
    "name:kor_x_variant":[
        "Ch\u2019oech\u2019on"
    ],
    "wof:name":"Ch'oech'on",
    "wof:placetype":"locality"
},
  "geometry": {"coordinates":[127.06556,39.04278],"type":"Point"}
}