{
  "type": "Feature",
  "properties": {
    "gn:admin1_code":"17.0",
    "gn:asciiname":"Ssangnyong-ni",
    "gn:country_code":"KP",
    "gn:dem":109,
    "gn:feature_class":"P",
    "gn:feature_code":"PPL",
    "gn:name":"Ssangnyong-ni",
    "gn:population":0,
    "gn:timezone":"Asia/Pyongyang",
    "iso:country":"KP",
    "name:und_x_variant":[
        "Ssangnyong-dong",
        "\uc30d\ub8e1\ub9ac",
        "Ssangnyong-ni"
    ],
    "wof:name":"Ssangnyong-ni",
    "wof:placetype":"locality"
},
  "geometry": {"coordinates":[129.34443999999999,40.93667],"type":"Point"}
}