{
  "type": "Feature",
  "properties": {
    "gn:admin1_code":"12.0",
    "gn:asciiname":"Tunjon-maul",
    "gn:country_code":"KP",
    "gn:dem":8,
    "gn:feature_class":"P",
    "gn:feature_code":"PPL",
    "gn:name":"Tunj\u014fn-ma\u016dl",
    "gn:population":0,
    "gn:timezone":"Asia/Pyongyang",
    "iso:country":"KP",
    "name:kor_x_preferred":[
        "\ub454\uc804\ub9c8\uc744"
    ],
    "name:und_x_variant":[
        "Tunj\u014fnch\u2019on",
        "Tunj\u014fn-ma\u016dl",
        "Dunjeonmaeul"
    ],
    "wof:name":"Tunjon-maul",
    "wof:placetype":"locality"
},
  "geometry": {"coordinates":[125.73333,38.93333],"type":"Point"}
}