{
  "type": "Feature",
  "properties": {
    "gn:admin1_code":"0.0",
    "gn:asciiname":"Myong-dong",
    "gn:country_code":"KP",
    "gn:dem":1,
    "gn:feature_class":"P",
    "gn:feature_code":"PPL",
    "gn:name":"My\u014fng-dong",
    "gn:population":0,
    "gn:timezone":"Asia/Pyongyang",
    "iso:country":"KP",
    "name:kor_x_preferred":[
        "\uba85\ub3d9"
    ],
    "name:und_x_variant":[
        "My\u014fng-dong"
    ],
    "wof:name":"Myong-dong",
    "wof:placetype":"locality"
},
  "geometry": {"coordinates":[125.38333,37.76667],"type":"Point"}
}