{
  "type": "Feature",
  "properties": {
    "gn:admin1_code":"11.0",
    "gn:asciiname":"Hawol",
    "gn:country_code":"KP",
    "gn:dem":32,
    "gn:feature_class":"P",
    "gn:feature_code":"PPL",
    "gn:name":"Haw\u014fl",
    "gn:population":0,
    "gn:timezone":"Asia/Pyongyang",
    "iso:country":"KP",
    "name:kor_x_preferred":[
        "\ud558\uc6d4"
    ],
    "wof:name":"Hawol",
    "wof:placetype":"locality"
},
  "geometry": {"coordinates":[125.21666999999999,39.65444],"type":"Point"}
}