{
  "type": "Feature",
  "properties": {
    "gn:admin1_code":"0.0",
    "gn:asciiname":"Haengnim-dong",
    "gn:country_code":"KP",
    "gn:dem":87,
    "gn:feature_class":"P",
    "gn:feature_code":"PPL",
    "gn:name":"Haengnim-dong",
    "gn:population":0,
    "gn:timezone":"Asia/Pyongyang",
    "iso:country":"KP",
    "name:kor_x_preferred":[
        "\ud589\ub9bc\ub3d9"
    ],
    "wof:name":"Haengnim-dong",
    "wof:placetype":"locality"
},
  "geometry": {"coordinates":[125.36667,38.56667],"type":"Point"}
}