{
  "type": "Feature",
  "properties": {
    "gn:admin1_code":"11.0",
    "gn:asciiname":"Anp'yong-ni",
    "gn:country_code":"KP",
    "gn:dem":83,
    "gn:feature_class":"P",
    "gn:feature_code":"PPL",
    "gn:name":"Anp\u2019y\u014fng-ni",
    "gn:population":0,
    "gn:timezone":"Asia/Pyongyang",
    "iso:country":"KP",
    "name:kor_x_preferred":[
        "\uc548\ud3c9\ub9ac"
    ],
    "name:und_x_variant":[
        "Anp\u2019y\u014fng-ni"
    ],
    "wof:name":"Anp'yong-ni",
    "wof:placetype":"locality"
},
  "geometry": {"coordinates":[125.50194,39.94028],"type":"Point"}
}