{
  "type": "Feature",
  "properties": {
    "gn:admin1_code":"11.0",
    "gn:asciiname":"Chambong-ni",
    "gn:country_code":"KP",
    "gn:dem":26,
    "gn:feature_class":"P",
    "gn:feature_code":"PPL",
    "gn:name":"Chambong-ni",
    "gn:population":0,
    "gn:timezone":"Asia/Pyongyang",
    "iso:country":"KP",
    "name:und_x_variant":[
        "Chambong-dong",
        "\uc7a0\ubd09\ub9ac",
        "Chambong-ni"
    ],
    "wof:name":"Chambong-ni",
    "wof:placetype":"locality"
},
  "geometry": {"coordinates":[124.6925,39.88083],"type":"Point"}
}