{
  "type": "Feature",
  "properties": {
    "gn:admin1_code":"6.0",
    "gn:asciiname":"Sanghwa-dong",
    "gn:country_code":"KP",
    "gn:dem":78,
    "gn:feature_class":"P",
    "gn:feature_code":"PPL",
    "gn:name":"Sanghwa-dong",
    "gn:population":0,
    "gn:timezone":"Asia/Pyongyang",
    "iso:country":"KP",
    "name:kor_x_preferred":[
        "\uc0c1\ud654\ub3d9"
    ],
    "wof:name":"Sanghwa-dong",
    "wof:placetype":"locality"
},
  "geometry": {"coordinates":[125.11583,38.34194],"type":"Point"}
}