{
  "type": "Feature",
  "properties": {
    "gn:admin1_code":"9.0",
    "gn:asciiname":"Yonmok-kol",
    "gn:country_code":"KP",
    "gn:dem":481,
    "gn:feature_class":"P",
    "gn:feature_code":"PPL",
    "gn:name":"Y\u014fnmok-kol",
    "gn:population":0,
    "gn:timezone":"Asia/Pyongyang",
    "iso:country":"KP",
    "name:und_x_variant":[
        "\uc5f0\ubaa9\uace8",
        "Y\u014fnmok-kol"
    ],
    "wof:name":"Yonmok-kol",
    "wof:placetype":"locality"
},
  "geometry": {"coordinates":[127.52611,38.54667],"type":"Point"}
}