{
  "type": "Feature",
  "properties": {
    "gn:admin1_code":"6.0",
    "gn:asciiname":"Chungch'ong",
    "gn:country_code":"KP",
    "gn:dem":13,
    "gn:feature_class":"P",
    "gn:feature_code":"PPL",
    "gn:name":"Chungch\u2019\u014fng",
    "gn:population":0,
    "gn:timezone":"Asia/Pyongyang",
    "iso:country":"KP",
    "name:kor_x_preferred":[
        "\uc911\uccad"
    ],
    "name:und_x_variant":[
        "Chungch\u2019\u014fng"
    ],
    "wof:name":"Chungch'ong",
    "wof:placetype":"locality"
},
  "geometry": {"coordinates":[125.71639,38.33667],"type":"Point"}
}