{
  "type": "Feature",
  "properties": {
    "gn:admin1_code":"17.0",
    "gn:asciiname":"Pangwol-li",
    "gn:country_code":"KP",
    "gn:dem":463,
    "gn:feature_class":"P",
    "gn:feature_code":"PPLL",
    "gn:name":"Pangw\u014fl-li",
    "gn:population":0,
    "gn:timezone":"Asia/Pyongyang",
    "iso:country":"KP",
    "name:und_x_variant":[
        "\ubc29\uc6d0\ub9ac",
        "Pangw\u014fl-li"
    ],
    "wof:name":"Pangwol-li",
    "wof:placetype":"locality"
},
  "geometry": {"coordinates":[129.81416999999999,42.65528],"type":"Point"}
}