{
  "type": "Feature",
  "properties": {
    "gn:admin1_code":"15.0",
    "gn:asciiname":"Iryang-dong",
    "gn:country_code":"KP",
    "gn:dem":199,
    "gn:feature_class":"P",
    "gn:feature_code":"PPL",
    "gn:name":"Iryang-dong",
    "gn:population":0,
    "gn:timezone":"Asia/Pyongyang",
    "iso:country":"KP",
    "name:kor_x_preferred":[
        "\uc77c\uc591\ub3d9"
    ],
    "wof:name":"Iryang-dong",
    "wof:placetype":"locality"
},
  "geometry": {"coordinates":[126.53,39.70972],"type":"Point"}
}