{
  "type": "Feature",
  "properties": {
    "gn:admin1_code":"11.0",
    "gn:asciiname":"Maengma-dong",
    "gn:cc2":"KP",
    "gn:country_code":"KP",
    "gn:dem":88,
    "gn:feature_class":"P",
    "gn:feature_code":"PPL",
    "gn:name":"Maengma-dong",
    "gn:population":0,
    "gn:timezone":"Asia/Pyongyang",
    "iso:country":"KP",
    "name:kor_x_preferred":[
        "\ub9e5\ub9c8\ub3d9"
    ],
    "name:und_x_variant":[
        "Paengma-dong",
        "Maengma-dong"
    ],
    "wof:name":"Maengma-dong",
    "wof:placetype":"locality"
},
  "geometry": {"coordinates":[125.05722,39.75194000000001],"type":"Point"}
}