{
  "type": "Feature",
  "properties": {
    "gn:admin1_code":"6.0",
    "gn:asciiname":"Pun-gol",
    "gn:country_code":"KP",
    "gn:dem":78,
    "gn:feature_class":"P",
    "gn:feature_code":"PPL",
    "gn:name":"Pun-gol",
    "gn:population":0,
    "gn:timezone":"Asia/Pyongyang",
    "iso:country":"KP",
    "name:kor_x_preferred":[
        "\ubd84\uace8"
    ],
    "wof:name":"Pun-gol",
    "wof:placetype":"locality"
},
  "geometry": {"coordinates":[125.42610999999999,38.09028],"type":"Point"}
}