{
  "type": "Feature",
  "properties": {
    "gn:admin1_code":"6.0",
    "gn:asciiname":"Tohyol-li",
    "gn:cc2":"KP",
    "gn:country_code":"KP",
    "gn:dem":81,
    "gn:feature_class":"P",
    "gn:feature_code":"PPL",
    "gn:name":"Tohy\u014fl-li",
    "gn:population":0,
    "gn:timezone":"Asia/Pyongyang",
    "iso:country":"KP",
    "name:und_x_variant":[
        "Tohy\u014fn-ni",
        "Tohy\u014fl-li"
    ],
    "wof:name":"Tohyol-li",
    "wof:placetype":"locality"
},
  "geometry": {"coordinates":[125.52943999999999,38.1525],"type":"Point"}
}