{
  "type": "Feature",
  "properties": {
    "gn:admin1_code":"11.0",
    "gn:asciiname":"Simjok-kol",
    "gn:country_code":"KP",
    "gn:dem":165,
    "gn:feature_class":"P",
    "gn:feature_code":"PPL",
    "gn:name":"Simj\u014fk-kol",
    "gn:population":0,
    "gn:timezone":"Asia/Pyongyang",
    "iso:country":"KP",
    "name:und_x_variant":[
        "\uc2ec\uc801\uace8",
        "Simj\u014fk-kol"
    ],
    "wof:name":"Simjok-kol",
    "wof:placetype":"locality"
},
  "geometry": {"coordinates":[126.13722,39.89778],"type":"Point"}
}