{
  "type": "Feature",
  "properties": {
    "gn:admin1_code":"7.0",
    "gn:asciiname":"Sillang-ni",
    "gn:country_code":"KP",
    "gn:dem":232,
    "gn:feature_class":"P",
    "gn:feature_code":"PPL",
    "gn:name":"Sillang-ni",
    "gn:population":0,
    "gn:timezone":"Asia/Pyongyang",
    "iso:country":"KP",
    "name:eng_x_preferred":[
        "Sillang"
    ],
    "name:eng_x_variant":[
        "Sillang-ni"
    ],
    "name:kor_x_preferred":[
        "\uc2e0\ub77d\ub9ac"
    ],
    "wof:name":"Sillang",
    "wof:placetype":"locality"
},
  "geometry": {"coordinates":[126.35389000000001,38.8125],"type":"Point"}
}