{
  "type": "Feature",
  "properties": {
    "gn:admin1_code":"9.0",
    "gn:admin2_code":"1875980",
    "gn:asciiname":"Ponghwa-dong",
    "gn:country_code":"KP",
    "gn:dem":291,
    "gn:feature_class":"P",
    "gn:feature_code":"PPL",
    "gn:name":"Ponghwa-dong",
    "gn:population":0,
    "gn:timezone":"Asia/Pyongyang",
    "iso:country":"KP",
    "wof:name":"Ponghwa-dong",
    "wof:placetype":"locality"
},
  "geometry": {"coordinates":[127.6075,38.39806],"type":"Point"}
}