{
  "type": "Feature",
  "properties": {
    "gn:admin1_code":"13.0",
    "gn:asciiname":"Kugul-li",
    "gn:cc2":"KP",
    "gn:country_code":"KP",
    "gn:dem":954,
    "gn:feature_class":"P",
    "gn:feature_code":"PPL",
    "gn:name":"Kug\u016dl-li",
    "gn:population":0,
    "gn:timezone":"Asia/Pyongyang",
    "iso:country":"KP",
    "name:und_x_variant":[
        "Kug\u016dn-ni",
        "Kug\u016dl-li"
    ],
    "wof:name":"Kugul-li",
    "wof:placetype":"locality"
},
  "geometry": {"coordinates":[128.03,41.33139],"type":"Point"}
}