{
  "type": "Feature",
  "properties": {
    "gn:admin1_code":"6.0",
    "gn:asciiname":"Koewol-li",
    "gn:cc2":"KP",
    "gn:country_code":"KP",
    "gn:dem":109,
    "gn:feature_class":"P",
    "gn:feature_code":"PPL",
    "gn:name":"Koew\u014fl-li",
    "gn:population":0,
    "gn:timezone":"Asia/Pyongyang",
    "iso:country":"KP",
    "name:kor_x_preferred":[
        "Koew\u014fl-li"
    ],
    "name:und_x_variant":[
        "Koew\u014fn-ni",
        "\uad34\uc6d0\ub9ac"
    ],
    "wof:name":"Koewol-li",
    "wof:placetype":"locality"
},
  "geometry": {"coordinates":[125.31111,38.30833],"type":"Point"}
}