{
  "type": "Feature",
  "properties": {
    "gn:admin1_code":"6.0",
    "gn:asciiname":"P'uch'obau",
    "gn:country_code":"KP",
    "gn:dem":50,
    "gn:feature_class":"P",
    "gn:feature_code":"PPL",
    "gn:name":"P\u2019uch\u2019\u014fbau",
    "gn:population":0,
    "gn:timezone":"Asia/Pyongyang",
    "iso:country":"KP",
    "wof:name":"P'uch'obau",
    "wof:placetype":"locality"
},
  "geometry": {"coordinates":[126.15306,38.03139],"type":"Point"}
}