{
  "type": "Feature",
  "properties": {
    "gn:admin1_code":"11.0",
    "gn:asciiname":"Poch'ang-ni",
    "gn:country_code":"KP",
    "gn:dem":214,
    "gn:feature_class":"P",
    "gn:feature_code":"PPL",
    "gn:name":"Poch\u2019ang-ni",
    "gn:population":0,
    "gn:timezone":"Asia/Pyongyang",
    "iso:country":"KP",
    "name:eng_x_preferred":[
        "Poch'ang"
    ],
    "name:eng_x_variant":[
        "Poch'ang-ni"
    ],
    "name:und_x_variant":[
        "\ubcf4\ucc3d\ub9ac",
        "Poch\u2019ang-ni"
    ],
    "wof:name":"Poch'ang",
    "wof:placetype":"locality"
},
  "geometry": {"coordinates":[125.30110999999999,40.56278],"type":"Point"}
}