{
  "type": "Feature",
  "properties": {
    "gn:admin1_code":"11.0",
    "gn:asciiname":"Samal-lyong",
    "gn:country_code":"KP",
    "gn:dem":83,
    "gn:feature_class":"P",
    "gn:feature_code":"PPL",
    "gn:name":"Samal-ly\u014fng",
    "gn:population":0,
    "gn:timezone":"Asia/Pyongyang",
    "iso:country":"KP",
    "name:kor_x_preferred":[
        "\uc0ac\ub9cc\ub839"
    ],
    "name:und_x_variant":[
        "Samal-ly\u014fng",
        "Saman-ny\u014fng"
    ],
    "wof:name":"Samal-lyong",
    "wof:placetype":"locality"
},
  "geometry": {"coordinates":[125.64278,39.79],"type":"Point"}
}