{
  "type": "Feature",
  "properties": {
    "gn:admin1_code":"1.0",
    "gn:asciiname":"Tongbu-dong",
    "gn:country_code":"KP",
    "gn:dem":327,
    "gn:feature_class":"P",
    "gn:feature_code":"PPL",
    "gn:name":"Tongbu-dong",
    "gn:population":0,
    "gn:timezone":"Asia/Pyongyang",
    "iso:country":"KP",
    "name:kor_x_preferred":[
        "\ub3d9\ubd80\ub3d9"
    ],
    "name:und_x_variant":[
        "Tongbu-ri",
        "Tongbu-dong"
    ],
    "wof:name":"Tongbu-dong",
    "wof:placetype":"locality"
},
  "geometry": {"coordinates":[126.64671,40.98133],"type":"Point"}
}