{
  "type": "Feature",
  "properties": {
    "gn:gn_country":"KP",
    "gn:gn_fcode":"PPL",
    "gn:gn_pop":0,
    "iso:country":"KP",
    "qs_pg:aaroncc":"KP",
    "qs_pg:gn_country":"KP",
    "qs_pg:gn_fcode":"PPL",
    "qs_pg:gn_pop":0,
    "qs_pg:name":"\uad34\uc548\ub3d9",
    "qs_pg:name_adm0":"\ud55c\uad6d",
    "qs_pg:name_adm1":"\uacbd\uae30\ub3c4",
    "qs_pg:photos":9,
    "qs_pg:photos_1k":2,
    "qs_pg:photos_9k":1,
    "qs_pg:photos_9r":1,
    "qs_pg:photos_all":9,
    "qs_pg:photos_sr":1,
    "qs_pg:pop_sr":0,
    "qs_pg:qs_pg_placetype":"neighbourhood",
    "qs_pg:qs_pg_placetype_gp":"Suburb",
    "qs_pg:woe_adm0":23424868,
    "woe:adm0_id":23424868,
    "woe:name_adm0":"\ud55c\uad6d",
    "woe:name_adm1":"\uacbd\uae30\ub3c4",
    "woe:placetype":"Suburb",
    "wof:name":"\uad34\uc548\ub3d9",
    "wof:placetype":"neighbourhood"
},
  "geometry": {"coordinates":[126.11111,37.9175],"type":"Point"}
}