{
  "type": "Feature",
  "properties": {
    "gn:admin1_code":"3.0",
    "gn:asciiname":"Chongdong-ni",
    "gn:country_code":"KP",
    "gn:dem":90,
    "gn:feature_class":"P",
    "gn:feature_code":"PPL",
    "gn:name":"Ch\u014fngdong-ni",
    "gn:population":0,
    "gn:timezone":"Asia/Pyongyang",
    "iso:country":"KP",
    "name:und_x_variant":[
        "\uc815\ub3d9\ub9ac",
        "Ch\u014fngdong-ni"
    ],
    "wof:name":"Chongdong-ni",
    "wof:placetype":"locality"
},
  "geometry": {"coordinates":[127.255,39.615],"type":"Point"}
}