{
  "type": "Feature",
  "properties": {
    "gn:admin1_code":"15.0",
    "gn:asciiname":"Pugo-ri",
    "gn:country_code":"KP",
    "gn:dem":8,
    "gn:feature_class":"P",
    "gn:feature_code":"PPL",
    "gn:name":"Pugo-ri",
    "gn:population":0,
    "gn:timezone":"Asia/Pyongyang",
    "iso:country":"KP",
    "name:kor_x_preferred":[
        "\ubd81\uc624\ub9ac"
    ],
    "wof:name":"Pugo-ri",
    "wof:placetype":"locality"
},
  "geometry": {"coordinates":[125.37528,39.42278],"type":"Point"}
}