{
  "type": "Feature",
  "properties": {
    "gn:admin1_code":"15.0",
    "gn:asciiname":"Younjak",
    "gn:country_code":"KP",
    "gn:dem":251,
    "gn:feature_class":"P",
    "gn:feature_code":"PPL",
    "gn:name":"Y\u014funjak",
    "gn:population":0,
    "gn:timezone":"Asia/Pyongyang",
    "iso:country":"KP",
    "name:kor_x_preferred":[
        "\uc5ec\uc6b4\uc791"
    ],
    "name:kor_x_variant":[
        "Y\u014funjak"
    ],
    "wof:name":"Younjak",
    "wof:placetype":"locality"
},
  "geometry": {"coordinates":[126.41611,39.07583],"type":"Point"}
}