{
  "type": "Feature",
  "properties": {
    "gn:admin1_code":"9.0",
    "gn:admin2_code":"1875980",
    "gn:asciiname":"Sairwon",
    "gn:cc2":"KP",
    "gn:country_code":"KP",
    "gn:dem":329,
    "gn:feature_class":"P",
    "gn:feature_code":"PPL",
    "gn:name":"Sairw\u014fn",
    "gn:population":0,
    "gn:timezone":"Asia/Pyongyang",
    "iso:country":"KP",
    "name:und_x_variant":[
        "Saichiin",
        "Sirwon",
        "Sairw\u014fn"
    ],
    "wof:name":"Sairwon",
    "wof:placetype":"locality"
},
  "geometry": {"coordinates":[127.69611,38.4125],"type":"Point"}
}