{
  "type": "Feature",
  "properties": {
    "gn:admin1_code":"7.0",
    "gn:admin2_code":"T\u2019osan-gun",
    "gn:asciiname":"Pich'i-dong",
    "gn:country_code":"KP",
    "gn:dem":314,
    "gn:feature_class":"P",
    "gn:feature_code":"PPL",
    "gn:name":"Pich\u2019i-dong",
    "gn:population":0,
    "gn:timezone":"Asia/Pyongyang",
    "iso:country":"KP",
    "wof:name":"Pich'i-dong",
    "wof:placetype":"locality"
},
  "geometry": {"coordinates":[126.76389,38.20694],"type":"Point"}
}