{
  "type": "Feature",
  "properties": {
    "gn:admin1_code":"0.0",
    "gn:asciiname":"Ch'ahyon-dong",
    "gn:country_code":"KP",
    "gn:dem":37,
    "gn:feature_class":"P",
    "gn:feature_code":"PPL",
    "gn:name":"Ch\u2019ahy\u014fn-dong",
    "gn:population":0,
    "gn:timezone":"Asia/Pyongyang",
    "iso:country":"KP",
    "name:kor_x_preferred":[
        "\ucc28\ud604\ub3d9"
    ],
    "name:und_x_variant":[
        "Ch\u2019ahy\u014fn-dong"
    ],
    "wof:name":"Ch'ahyon-dong",
    "wof:placetype":"locality"
},
  "geometry": {"coordinates":[125.15000000000001,38.15],"type":"Point"}
}