{
  "type": "Feature",
  "properties": {
    "gn:admin1_code":"7.0",
    "gn:asciiname":"Tumu-ri",
    "gn:country_code":"KP",
    "gn:dem":258,
    "gn:feature_class":"P",
    "gn:feature_code":"PPL",
    "gn:name":"Tumu-ri",
    "gn:population":0,
    "gn:timezone":"Asia/Pyongyang",
    "iso:country":"KP",
    "name:kor_x_preferred":[
        "\ub450\ubb34\ub9ac"
    ],
    "wof:name":"Tumu-ri",
    "wof:placetype":"locality"
},
  "geometry": {"coordinates":[126.85138999999999,38.895],"type":"Point"}
}