{
  "type": "Feature",
  "properties": {
    "gn:admin1_code":"3.0",
    "gn:asciiname":"Ukkuok",
    "gn:country_code":"KP",
    "gn:dem":33,
    "gn:feature_class":"P",
    "gn:feature_code":"PPL",
    "gn:name":"Ukku\u014fk",
    "gn:population":0,
    "gn:timezone":"Asia/Pyongyang",
    "iso:country":"KP",
    "name:und_x_variant":[
        "\uc6c3\uad6c\uc5b5",
        "Ukku\u014fk"
    ],
    "wof:name":"Ukkuok",
    "wof:placetype":"locality"
},
  "geometry": {"coordinates":[127.40472,39.87389],"type":"Point"}
}