{
  "type": "Feature",
  "properties": {
    "gn:admin1_code":"1.0",
    "gn:asciiname":"Samgang-ni",
    "gn:country_code":"KP",
    "gn:dem":234,
    "gn:feature_class":"P",
    "gn:feature_code":"PPL",
    "gn:name":"Samgang-ni",
    "gn:population":0,
    "gn:timezone":"Asia/Pyongyang",
    "iso:country":"KP",
    "name:und_x_variant":[
        "Samgang-dong",
        "\uc0bc\uac15\ub9ac",
        "Samgang-ni"
    ],
    "wof:name":"Samgang-ni",
    "wof:placetype":"locality"
},
  "geometry": {"coordinates":[126.50333000000001,41.36528],"type":"Point"}
}