{
  "type": "Feature",
  "properties": {
    "gn:admin1_code":"17.0",
    "gn:asciiname":"Oryu-dong",
    "gn:country_code":"KP",
    "gn:dem":13,
    "gn:feature_class":"P",
    "gn:feature_code":"PPL",
    "gn:name":"Oryu-dong",
    "gn:population":0,
    "gn:timezone":"Asia/Pyongyang",
    "iso:country":"KP",
    "name:kor_x_preferred":[
        "\uc624\ub958\ub3d9"
    ],
    "name:msa_x_preferred":[
        "Oryu-dong"
    ],
    "name:sco_x_preferred":[
        "Oryu-dong"
    ],
    "name:und_x_variant":[
        "\uc624\ub958\ub3d9",
        "Oryu-dong"
    ],
    "name:vie_x_preferred":[
        "Oryu-dong"
    ],
    "wof:name":"Oryu-dong",
    "wof:placetype":"locality"
},
  "geometry": {"coordinates":[129.63193999999999,41.535],"type":"Point"}
}