{
  "type": "Feature",
  "properties": {
    "gn:admin1_code":"11.0",
    "gn:asciiname":"Susong-dong",
    "gn:country_code":"KP",
    "gn:dem":16,
    "gn:feature_class":"P",
    "gn:feature_code":"PPL",
    "gn:name":"Susong-dong",
    "gn:population":0,
    "gn:timezone":"Asia/Pyongyang",
    "iso:country":"KP",
    "name:und_x_variant":[
        "\uc218\uc1a1\ub3d9",
        "Susong-dong"
    ],
    "wof:name":"Susong-dong",
    "wof:placetype":"locality"
},
  "geometry": {"coordinates":[124.41972,39.98083],"type":"Point"}
}