{
  "type": "Feature",
  "properties": {
    "gn:admin1_code":"13.0",
    "gn:asciiname":"Sangunsal-li",
    "gn:cc2":"KP",
    "gn:country_code":"KP",
    "gn:dem":1097,
    "gn:feature_class":"P",
    "gn:feature_code":"PPL",
    "gn:name":"Sang\u016dnsal-li",
    "gn:population":0,
    "gn:timezone":"Asia/Pyongyang",
    "iso:country":"KP",
    "name:und_x_variant":[
        "Sang\u016dnsan-ni",
        "Sang\u016dnsal-li"
    ],
    "wof:name":"Sangunsal-li",
    "wof:placetype":"locality"
},
  "geometry": {"coordinates":[127.96666999999999,41.18833],"type":"Point"}
}