{
  "type": "Feature",
  "properties": {
    "gn:admin1_code":"3.0",
    "gn:asciiname":"P'ungdong-ni",
    "gn:country_code":"KP",
    "gn:dem":64,
    "gn:feature_class":"P",
    "gn:feature_code":"PPL",
    "gn:name":"P\u2019ungdong-ni",
    "gn:population":0,
    "gn:timezone":"Asia/Pyongyang",
    "iso:country":"KP",
    "name:und_x_variant":[
        "\ud48d\ub3d9\ub9ac",
        "P\u2019ungdong-ni"
    ],
    "wof:name":"P'ungdong-ni",
    "wof:placetype":"locality"
},
  "geometry": {"coordinates":[127.53667,40.03306],"type":"Point"}
}