{
  "type": "Feature",
  "properties": {
    "gn:admin1_code":"6.0",
    "gn:asciiname":"Toktong-ni",
    "gn:country_code":"KP",
    "gn:dem":14,
    "gn:feature_class":"P",
    "gn:feature_code":"PPL",
    "gn:name":"T\u014fktong-ni",
    "gn:population":0,
    "gn:timezone":"Asia/Pyongyang",
    "iso:country":"KP",
    "name:eng_x_preferred":[
        "Toktong"
    ],
    "name:eng_x_variant":[
        "Toktong-ni"
    ],
    "wof:name":"Toktong",
    "wof:placetype":"locality"
},
  "geometry": {"coordinates":[126.18694000000001,37.87361],"type":"Point"}
}