{
  "type": "Feature",
  "properties": {
    "gn:admin1_code":"7.0",
    "gn:asciiname":"Pukch'o-dong",
    "gn:country_code":"KP",
    "gn:dem":5,
    "gn:feature_class":"P",
    "gn:feature_code":"PPL",
    "gn:name":"Pukch\u2019o-dong",
    "gn:population":0,
    "gn:timezone":"Asia/Pyongyang",
    "iso:country":"KP",
    "name:kor_x_preferred":[
        "\ubd81\ucd08\ub3d9"
    ],
    "wof:name":"Pukch'o-dong",
    "wof:placetype":"locality"
},
  "geometry": {"coordinates":[125.66833,38.5775],"type":"Point"}
}