{
  "type": "Feature",
  "properties": {
    "gn:admin1_code":"1.0",
    "gn:asciiname":"Konggwi-dong",
    "gn:country_code":"KP",
    "gn:dem":319,
    "gn:feature_class":"P",
    "gn:feature_code":"PPL",
    "gn:name":"Konggwi-dong",
    "gn:population":0,
    "gn:timezone":"Asia/Pyongyang",
    "iso:country":"KP",
    "name:kor_x_preferred":[
        "\uacf5\uadc0\ub3d9"
    ],
    "name:und_x_variant":[
        "Konggwi-ri",
        "\uacf5\uadc0\ub3d9",
        "Konggwi-dong"
    ],
    "wof:name":"Konggwi-dong",
    "wof:placetype":"locality"
},
  "geometry": {"coordinates":[126.60953000000001,40.93387],"type":"Point"}
}