{
  "type": "Feature",
  "properties": {
    "gn:admin1_code":"9.0",
    "gn:asciiname":"Sinwol-li",
    "gn:country_code":"KP",
    "gn:dem":108,
    "gn:feature_class":"P",
    "gn:feature_code":"PPL",
    "gn:name":"Sinw\u014fl-li",
    "gn:population":0,
    "gn:timezone":"Asia/Pyongyang",
    "iso:country":"KP",
    "name:kor_x_preferred":[
        "\uc2e0\uc6d4\ub9ac"
    ],
    "name:kor_x_variant":[
        "Sinw\u014fl-li"
    ],
    "wof:name":"Sinwol-li",
    "wof:placetype":"locality"
},
  "geometry": {"coordinates":[127.45528,38.96944000000001],"type":"Point"}
}