{
  "type": "Feature",
  "properties": {
    "gn:admin1_code":"6.0",
    "gn:asciiname":"Munbak-tong",
    "gn:country_code":"KP",
    "gn:dem":62,
    "gn:feature_class":"P",
    "gn:feature_code":"PPL",
    "gn:name":"Munbak-tong",
    "gn:population":0,
    "gn:timezone":"Asia/Pyongyang",
    "iso:country":"KP",
    "name:eng_x_preferred":[
        "Munbak"
    ],
    "name:eng_x_variant":[
        "Munbak-tong"
    ],
    "name:kor_x_preferred":[
        "\ubb38\ubc15\ub3d9"
    ],
    "wof:name":"Munbak",
    "wof:placetype":"locality"
},
  "geometry": {"coordinates":[125.34444000000001,38.36472],"type":"Point"}
}