{
  "type": "Feature",
  "properties": {
    "gn:admin1_code":"12.0",
    "gn:admin2_code":"Sangw\u014fn-gun",
    "gn:asciiname":"Hangaeul",
    "gn:country_code":"KP",
    "gn:dem":92,
    "gn:feature_class":"P",
    "gn:feature_code":"PPL",
    "gn:name":"Hangaeul",
    "gn:population":0,
    "gn:timezone":"Asia/Pyongyang",
    "iso:country":"KP",
    "wof:name":"Hangaeul",
    "wof:placetype":"locality"
},
  "geometry": {"coordinates":[126.11333,38.83667],"type":"Point"}
}