{
  "type": "Feature",
  "properties": {
    "gn:admin1_code":"6.0",
    "gn:asciiname":"Ch'onnae-ri",
    "gn:country_code":"KP",
    "gn:dem":36,
    "gn:feature_class":"P",
    "gn:feature_code":"PPL",
    "gn:name":"Ch\u2019\u014fnnae-ri",
    "gn:population":0,
    "gn:timezone":"Asia/Pyongyang",
    "iso:country":"KP",
    "name:kor_x_preferred":[
        "\ucc98\ub0b4\ub9ac"
    ],
    "name:kor_x_variant":[
        "Ch\u2019\u014fnnae-ri"
    ],
    "wof:name":"Ch'onnae-ri",
    "wof:placetype":"locality"
},
  "geometry": {"coordinates":[125.37611,38.39556],"type":"Point"}
}