{
  "type": "Feature",
  "properties": {
    "gn:admin1_code":"7.0",
    "gn:asciiname":"Yo-gol",
    "gn:country_code":"KP",
    "gn:dem":78,
    "gn:feature_class":"P",
    "gn:feature_code":"PPL",
    "gn:name":"Yo-gol",
    "gn:population":0,
    "gn:timezone":"Asia/Pyongyang",
    "iso:country":"KP",
    "name:kor_x_preferred":[
        "\uc694\uace8"
    ],
    "wof:name":"Yo-gol",
    "wof:placetype":"locality"
},
  "geometry": {"coordinates":[126.59667,38.42917],"type":"Point"}
}