{
  "type": "Feature",
  "properties": {
    "gn:admin1_code":"6.0",
    "gn:asciiname":"Ham-ch'on",
    "gn:country_code":"KP",
    "gn:dem":79,
    "gn:feature_class":"P",
    "gn:feature_code":"PPL",
    "gn:name":"Ham-ch\u2019on",
    "gn:population":0,
    "gn:timezone":"Asia/Pyongyang",
    "iso:country":"KP",
    "name:kor_x_preferred":[
        "\ud568\ucd0c"
    ],
    "name:und_x_variant":[
        "Ham-ch\u2019on"
    ],
    "wof:name":"Ham-ch'on",
    "wof:placetype":"locality"
},
  "geometry": {"coordinates":[125.49167,38.03889],"type":"Point"}
}