{
  "type": "Feature",
  "properties": {
    "gn:admin1_code":"9.0",
    "gn:admin2_code":"Ch\u2019\u014fnnae-gun",
    "gn:asciiname":"Kagyong-ni",
    "gn:country_code":"KP",
    "gn:dem":4,
    "gn:feature_class":"P",
    "gn:feature_code":"PPL",
    "gn:name":"Kagy\u014fng-ni",
    "gn:population":0,
    "gn:timezone":"Asia/Pyongyang",
    "iso:country":"KP",
    "name:eng_x_preferred":[
        "Kagyong"
    ],
    "name:eng_x_variant":[
        "Kagyong-ni"
    ],
    "wof:name":"Kagyong",
    "wof:placetype":"locality"
},
  "geometry": {"coordinates":[127.26555999999999,39.39139],"type":"Point"}
}