{
  "type": "Feature",
  "properties": {
    "gn:admin1_code":"7.0",
    "gn:asciiname":"Kach'ol-li",
    "gn:country_code":"KP",
    "gn:dem":19,
    "gn:feature_class":"P",
    "gn:feature_code":"PPL",
    "gn:name":"Kach\u2019ol-li",
    "gn:population":0,
    "gn:timezone":"Asia/Pyongyang",
    "iso:country":"KP",
    "name:kor_x_preferred":[
        "\uac00\ucd0c\ub9ac"
    ],
    "name:und_x_variant":[
        "Kach\u2019on-ni",
        "Kach\u2019ol-li"
    ],
    "wof:name":"Kach'ol-li",
    "wof:placetype":"locality"
},
  "geometry": {"coordinates":[125.87472,38.47111],"type":"Point"}
}