{
  "type": "Feature",
  "properties": {
    "gn:admin1_code":"17.0",
    "gn:asciiname":"Cho-dong",
    "gn:country_code":"KP",
    "gn:dem":45,
    "gn:feature_class":"P",
    "gn:feature_code":"PPL",
    "gn:name":"Cho-dong",
    "gn:population":0,
    "gn:timezone":"Asia/Pyongyang",
    "iso:country":"KP",
    "name:und_x_variant":[
        "\uc870\ub3d9",
        "Cho-dong"
    ],
    "name:vie_x_preferred":[
        "Cho-dong"
    ],
    "wof:name":"Cho-dong",
    "wof:placetype":"locality"
},
  "geometry": {"coordinates":[129.45500000000001,40.85278],"type":"Point"}
}