{
  "type": "Feature",
  "properties": {
    "gn:admin1_code":"1.0",
    "gn:asciiname":"Yangjich'am",
    "gn:country_code":"KP",
    "gn:dem":420,
    "gn:feature_class":"P",
    "gn:feature_code":"PPL",
    "gn:name":"Yangjich\u2019am",
    "gn:population":0,
    "gn:timezone":"Asia/Pyongyang",
    "iso:country":"KP",
    "name:und_x_variant":[
        "\uc591\uc9c0\ucc38",
        "Yangji-ri",
        "Yangjich\u2019am"
    ],
    "wof:name":"Yangjich'am",
    "wof:placetype":"locality"
},
  "geometry": {"coordinates":[126.23333,40.365],"type":"Point"}
}