{
  "type": "Feature",
  "properties": {
    "gn:admin1_code":"11.0",
    "gn:asciiname":"Yongsang-ni",
    "gn:country_code":"KP",
    "gn:dem":284,
    "gn:feature_class":"P",
    "gn:feature_code":"PPL",
    "gn:name":"Yongsang-ni",
    "gn:population":0,
    "gn:timezone":"Asia/Pyongyang",
    "iso:country":"KP",
    "name:und_x_variant":[
        "\uc6a9\uc0c1\ub9ac",
        "Yongsang-ni"
    ],
    "wof:name":"Yongsang-ni",
    "wof:placetype":"locality"
},
  "geometry": {"coordinates":[125.47638999999999,40.54972],"type":"Point"}
}