{
  "type": "Feature",
  "properties": {
    "gn:admin1_code":"17.0",
    "gn:asciiname":"Suhwak-tong",
    "gn:cc2":"KP",
    "gn:country_code":"KP",
    "gn:dem":1032,
    "gn:feature_class":"P",
    "gn:feature_code":"PPL",
    "gn:name":"Suhwak-tong",
    "gn:population":0,
    "gn:timezone":"Asia/Pyongyang",
    "iso:country":"KP",
    "name:eng_x_preferred":[
        "Suhwak"
    ],
    "name:eng_x_variant":[
        "Suhwak-tong"
    ],
    "name:und_x_variant":[
        "Sudae-dong",
        "Suhwak-tong"
    ],
    "wof:name":"Suhwak",
    "wof:placetype":"locality"
},
  "geometry": {"coordinates":[129.03333000000001,41.16667],"type":"Point"}
}