{
  "type": "Feature",
  "properties": {
    "gn:admin1_code":"1.0",
    "gn:asciiname":"Songwon-up",
    "gn:country_code":"KP",
    "gn:dem":371,
    "gn:feature_class":"P",
    "gn:feature_code":"PPL",
    "gn:name":"Songw\u014fn-\u016dp",
    "gn:population":0,
    "gn:timezone":"Asia/Pyongyang",
    "iso:country":"KP",
    "name:und_x_variant":[
        "Meibun",
        "My\u014fngmun-ni",
        "Meibun-d\u014f",
        "My\u014fngmun-dong",
        "Myonmunton",
        "\uc1a1\uc6d0",
        "Songw\u014fn-\u016dp",
        "Songw\u014fn",
        "\uc1a1\uc6d0\uc74d"
    ],
    "wof:name":"Songwon-up",
    "wof:placetype":"locality"
},
  "geometry": {"coordinates":[126.30833,40.37278],"type":"Point"}
}