{
  "type": "Feature",
  "properties": {
    "gn:admin1_code":"7.0",
    "gn:asciiname":"Non-gol",
    "gn:country_code":"KP",
    "gn:dem":184,
    "gn:feature_class":"P",
    "gn:feature_code":"PPL",
    "gn:name":"Non-gol",
    "gn:population":0,
    "gn:timezone":"Asia/Pyongyang",
    "iso:country":"KP",
    "wof:name":"Non-gol",
    "wof:placetype":"locality"
},
  "geometry": {"coordinates":[126.20917,38.325],"type":"Point"}
}