{
  "type": "Feature",
  "properties": {
    "gn:admin1_code":"17.0",
    "gn:asciiname":"Sunam",
    "gn:country_code":"KP",
    "gn:dem":-9999,
    "gn:feature_class":"P",
    "gn:feature_code":"PPL",
    "gn:name":"Sunam",
    "gn:population":0,
    "gn:timezone":"Asia/Pyongyang",
    "iso:country":"KP",
    "wof:name":"Sunam",
    "wof:placetype":"locality"
},
  "geometry": {"coordinates":[129.59999999999999,40.68333],"type":"Point"}
}