{
  "type": "Feature",
  "properties": {
    "gn:admin1_code":"11.0",
    "gn:asciiname":"Sil-li",
    "gn:country_code":"KP",
    "gn:dem":220,
    "gn:feature_class":"P",
    "gn:feature_code":"PPL",
    "gn:name":"Sil-li",
    "gn:population":0,
    "gn:timezone":"Asia/Pyongyang",
    "iso:country":"KP",
    "name:und_x_variant":[
        "\uc2e0\ub9ac",
        "Sil-li"
    ],
    "wof:name":"Sil-li",
    "wof:placetype":"locality"
},
  "geometry": {"coordinates":[125.38139,40.60806],"type":"Point"}
}