{
  "type": "Feature",
  "properties": {
    "gn:admin1_code":"12.0",
    "gn:admin2_code":"Kangdong-gun",
    "gn:asciiname":"Pangme",
    "gn:country_code":"KP",
    "gn:dem":56,
    "gn:feature_class":"P",
    "gn:feature_code":"PPL",
    "gn:name":"Pangme",
    "gn:population":0,
    "gn:timezone":"Asia/Pyongyang",
    "iso:country":"KP",
    "name:kor_x_preferred":[
        "\ubc15\uba54"
    ],
    "name:und_x_variant":[
        "Bangme"
    ],
    "wof:name":"Pangme",
    "wof:placetype":"locality"
},
  "geometry": {"coordinates":[126.19528,39.01992],"type":"Point"}
}