{
  "type": "Feature",
  "properties": {
    "gn:admin1_code":"17.0",
    "gn:asciiname":"Puk-kol",
    "gn:country_code":"KP",
    "gn:dem":926,
    "gn:feature_class":"P",
    "gn:feature_code":"PPL",
    "gn:name":"Puk-kol",
    "gn:population":0,
    "gn:timezone":"Asia/Pyongyang",
    "iso:country":"KP",
    "name:und_x_variant":[
        "Pukkok",
        "\ubd81\uace8",
        "Puk-kol"
    ],
    "wof:name":"Puk-kol",
    "wof:placetype":"locality"
},
  "geometry": {"coordinates":[129.32721999999998,41.43472],"type":"Point"}
}