{
  "type": "Feature",
  "properties": {
    "gn:admin1_code":"12.0",
    "gn:asciiname":"Sokhae-dong",
    "gn:country_code":"KP",
    "gn:dem":17,
    "gn:feature_class":"P",
    "gn:feature_code":"PPL",
    "gn:name":"S\u014fkhae-dong",
    "gn:population":0,
    "gn:timezone":"Asia/Pyongyang",
    "iso:country":"KP",
    "name:kor_x_preferred":[
        "\uc11d\ud574\ub3d9"
    ],
    "name:und_x_variant":[
        "S\u014fkhae-dong",
        "Seokhaedong"
    ],
    "wof:name":"Sokhae-dong",
    "wof:placetype":"locality"
},
  "geometry": {"coordinates":[125.66325999999999,38.90626],"type":"Point"}
}