{
  "type": "Feature",
  "properties": {
    "gn:admin1_code":"7.0",
    "gn:asciiname":"Kumhang-ni",
    "gn:country_code":"KP",
    "gn:dem":141,
    "gn:feature_class":"P",
    "gn:feature_code":"PPL",
    "gn:name":"K\u016dmhang-ni",
    "gn:population":0,
    "gn:timezone":"Asia/Pyongyang",
    "iso:country":"KP",
    "name:kor_x_preferred":[
        "\uae08\ud559\ub9ac"
    ],
    "name:kor_x_variant":[
        "K\u016dmhang-ni"
    ],
    "wof:name":"Kumhang-ni",
    "wof:placetype":"locality"
},
  "geometry": {"coordinates":[126.33444,38.8575],"type":"Point"}
}