{
  "type": "Feature",
  "properties": {
    "gn:admin1_code":"6.0",
    "gn:asciiname":"Ch'anghu-dong",
    "gn:country_code":"KP",
    "gn:dem":41,
    "gn:feature_class":"P",
    "gn:feature_code":"PPL",
    "gn:name":"Ch\u2019anghu-dong",
    "gn:population":0,
    "gn:timezone":"Asia/Pyongyang",
    "iso:country":"KP",
    "name:kor_x_preferred":[
        "\ucc3d\ud6c4\ub3d9"
    ],
    "name:und_x_variant":[
        "Ch\u2019anghu-dong"
    ],
    "wof:name":"Ch'anghu-dong",
    "wof:placetype":"locality"
},
  "geometry": {"coordinates":[125.47833,38.08722],"type":"Point"}
}