{
  "type": "Feature",
  "properties": {
    "gn:admin1_code":"7.0",
    "gn:asciiname":"Muwang-dong",
    "gn:country_code":"KP",
    "gn:dem":127,
    "gn:feature_class":"P",
    "gn:feature_code":"PPL",
    "gn:name":"Muwang-dong",
    "gn:population":0,
    "gn:timezone":"Asia/Pyongyang",
    "iso:country":"KP",
    "name:kor_x_preferred":[
        "\ubb34\uc655\ub3d9"
    ],
    "wof:name":"Muwang-dong",
    "wof:placetype":"locality"
},
  "geometry": {"coordinates":[126.70139,38.86528],"type":"Point"}
}