{
  "type": "Feature",
  "properties": {
    "gn:admin1_code":"6.0",
    "gn:asciiname":"Pol-mal",
    "gn:country_code":"KP",
    "gn:dem":43,
    "gn:feature_class":"P",
    "gn:feature_code":"PPL",
    "gn:name":"P\u014fl-mal",
    "gn:population":0,
    "gn:timezone":"Asia/Pyongyang",
    "iso:country":"KP",
    "wof:name":"Pol-mal",
    "wof:placetype":"locality"
},
  "geometry": {"coordinates":[126.25167,38.13083],"type":"Point"}
}