{
  "type": "Feature",
  "properties": {
    "gn:admin1_code":"6.0",
    "gn:asciiname":"Hagalsan",
    "gn:country_code":"KP",
    "gn:dem":7,
    "gn:feature_class":"P",
    "gn:feature_code":"PPL",
    "gn:name":"Hagalsan",
    "gn:population":0,
    "gn:timezone":"Asia/Pyongyang",
    "iso:country":"KP",
    "name:kor_x_preferred":[
        "\ud558\uac08\uc0b0"
    ],
    "wof:name":"Hagalsan",
    "wof:placetype":"locality"
},
  "geometry": {"coordinates":[126.12917,37.85028],"type":"Point"}
}