{
  "type": "Feature",
  "properties": {
    "gn:admin1_code":"6.0",
    "gn:asciiname":"Songjong",
    "gn:country_code":"KP",
    "gn:dem":41,
    "gn:feature_class":"P",
    "gn:feature_code":"PPL",
    "gn:name":"Songj\u014fng",
    "gn:population":0,
    "gn:timezone":"Asia/Pyongyang",
    "iso:country":"KP",
    "name:und_x_variant":[
        "\uc1a1\uc815",
        "Songj\u014fng"
    ],
    "wof:name":"Songjong",
    "wof:placetype":"locality"
},
  "geometry": {"coordinates":[125.46167,37.98194],"type":"Point"}
}