{
  "type": "Feature",
  "properties": {
    "gn:admin1_code":"3.0",
    "gn:asciiname":"Hosong-ni",
    "gn:country_code":"KP",
    "gn:dem":17,
    "gn:feature_class":"P",
    "gn:feature_code":"PPL",
    "gn:name":"H\u014fs\u014fng-ni",
    "gn:population":0,
    "gn:timezone":"Asia/Pyongyang",
    "iso:country":"KP",
    "name:eng_x_preferred":[
        "Hosong"
    ],
    "name:eng_x_variant":[
        "Hosong-ni"
    ],
    "name:und_x_variant":[
        "H\u014fs\u014fng-ni",
        "\ud5c8\uc131\ub9ac"
    ],
    "wof:name":"Hosong",
    "wof:placetype":"locality"
},
  "geometry": {"coordinates":[128.59598,40.28354],"type":"Point"}
}