{
  "type": "Feature",
  "properties": {
    "gn:admin1_code":"6.0",
    "gn:asciiname":"Imjong-dong",
    "gn:country_code":"KP",
    "gn:dem":36,
    "gn:feature_class":"P",
    "gn:feature_code":"PPL",
    "gn:name":"Imj\u014fng-dong",
    "gn:population":0,
    "gn:timezone":"Asia/Pyongyang",
    "iso:country":"KP",
    "name:kor_x_preferred":[
        "\uc784\uc815\ub3d9"
    ],
    "name:und_x_variant":[
        "Imj\u014fng-dong"
    ],
    "wof:name":"Imjong-dong",
    "wof:placetype":"locality"
},
  "geometry": {"coordinates":[125.52556,38.07694],"type":"Point"}
}