{
  "type": "Feature",
  "properties": {
    "gn:admin1_code":"7.0",
    "gn:asciiname":"Sogu-dong",
    "gn:country_code":"KP",
    "gn:dem":236,
    "gn:feature_class":"P",
    "gn:feature_code":"PPL",
    "gn:name":"Sogu-dong",
    "gn:population":0,
    "gn:timezone":"Asia/Pyongyang",
    "iso:country":"KP",
    "name:und_x_variant":[
        "Sagu-dong",
        "\uc18c\uad6c\ub3d9",
        "Sogu-dong"
    ],
    "wof:name":"Sogu-dong",
    "wof:placetype":"locality"
},
  "geometry": {"coordinates":[126.84806,39.07444],"type":"Point"}
}