{
  "type": "Feature",
  "properties": {
    "gn:admin1_code":"9.0",
    "gn:asciiname":"Hugumnal-li",
    "gn:cc2":"KP",
    "gn:country_code":"KP",
    "gn:dem":5,
    "gn:feature_class":"P",
    "gn:feature_code":"PPL",
    "gn:name":"Hug\u016dmnal-li",
    "gn:population":0,
    "gn:timezone":"Asia/Pyongyang",
    "iso:country":"KP",
    "name:und_x_variant":[
        "Hug\u016dmnan-ni",
        "Hug\u016dmnal-li"
    ],
    "wof:name":"Hugumnal-li",
    "wof:placetype":"locality"
},
  "geometry": {"coordinates":[127.94444,38.92306],"type":"Point"}
}