{
  "type": "Feature",
  "properties": {
    "gn:admin1_code":"15.0",
    "gn:asciiname":"So-dong",
    "gn:country_code":"KP",
    "gn:dem":11,
    "gn:feature_class":"P",
    "gn:feature_code":"PPL",
    "gn:name":"S\u014f-dong",
    "gn:population":0,
    "gn:timezone":"Asia/Pyongyang",
    "iso:country":"KP",
    "name:kor_x_preferred":[
        "\uc11c\ub3d9"
    ],
    "name:kor_x_variant":[
        "S\u014f-dong"
    ],
    "wof:name":"So-dong",
    "wof:placetype":"locality"
},
  "geometry": {"coordinates":[125.60056000000002,38.7225],"type":"Point"}
}