{
  "type": "Feature",
  "properties": {
    "gn:admin1_code":"17.0",
    "gn:admin2_code":"Musan-gun",
    "gn:asciiname":"Onch'ol-li",
    "gn:country_code":"KP",
    "gn:dem":915,
    "gn:feature_class":"P",
    "gn:feature_code":"PPL",
    "gn:name":"Onch\u2019\u014fl-li",
    "gn:population":0,
    "gn:timezone":"Asia/Pyongyang",
    "iso:country":"KP",
    "name:und_x_variant":[
        "Onch\u2019\u014fn-dong",
        "Onch\u2019\u014fn-ni",
        "Onsen-d\u014d",
        "\uc628\ucc9c\ub9ac",
        "Onch\u2019\u014fl-li"
    ],
    "wof:name":"Onch'ol-li",
    "wof:placetype":"locality"
},
  "geometry": {"coordinates":[129.3075,41.99639000000001],"type":"Point"}
}