{
  "type": "Feature",
  "properties": {
    "gn:admin1_code":"17.0",
    "gn:asciiname":"Yongjondongyongjon'gok",
    "gn:country_code":"KP",
    "gn:dem":48,
    "gn:feature_class":"P",
    "gn:feature_code":"PPL",
    "gn:name":"Yongj\u014fndongyongj\u014fn\u2019gok",
    "gn:population":0,
    "gn:timezone":"Asia/Pyongyang",
    "iso:country":"KP",
    "name:und_x_variant":[
        "\uc6a9\uc804\ub3d9\uc6a9\uc804\uace1",
        "Yongj\u014fndongyongj\u014fn\u2019gok"
    ],
    "wof:name":"Yongjondongyongjon'gok",
    "wof:placetype":"locality"
},
  "geometry": {"coordinates":[129.59583000000001,41.41333],"type":"Point"}
}