{
  "type": "Feature",
  "properties": {
    "gn:admin1_code":"13.0",
    "gn:asciiname":"Yangmul-li",
    "gn:country_code":"KP",
    "gn:dem":733,
    "gn:feature_class":"P",
    "gn:feature_code":"PPL",
    "gn:name":"Yangmul-li",
    "gn:population":0,
    "gn:timezone":"Asia/Pyongyang",
    "iso:country":"KP",
    "name:kor_x_preferred":[
        "\uc591\ubb38\ub9ac"
    ],
    "wof:name":"Yangmul-li",
    "wof:placetype":"locality"
},
  "geometry": {"coordinates":[128.16176000000002,41.25741],"type":"Point"}
}