{
  "type": "Feature",
  "properties": {
    "gn:admin1_code":"17.0",
    "gn:asciiname":"Ch'irhyang-ni",
    "gn:country_code":"KP",
    "gn:dem":427,
    "gn:feature_class":"P",
    "gn:feature_code":"PPL",
    "gn:name":"Ch\u2019irhyang-ni",
    "gn:population":0,
    "gn:timezone":"Asia/Pyongyang",
    "iso:country":"KP",
    "name:und_x_variant":[
        "Ch\u2019iryang-dong",
        "\uce60\ud5a5\ub9ac",
        "Ch\u2019irhyang-ni"
    ],
    "wof:name":"Ch'irhyang-ni",
    "wof:placetype":"locality"
},
  "geometry": {"coordinates":[129.47193999999999,41.36639],"type":"Point"}
}