{
  "type": "Feature",
  "properties": {
    "gn:admin1_code":"13.0",
    "gn:admin2_code":"2041726",
    "gn:asciiname":"Sodongp'o",
    "gn:country_code":"KP",
    "gn:dem":1180,
    "gn:feature_class":"P",
    "gn:feature_code":"PPL",
    "gn:name":"S\u014fdongp\u2019o",
    "gn:population":0,
    "gn:timezone":"Asia/Pyongyang",
    "iso:country":"KP",
    "wof:name":"Sodongp'o",
    "wof:placetype":"locality"
},
  "geometry": {"coordinates":[127.90555999999999,40.78917],"type":"Point"}
}