{
  "type": "Feature",
  "properties": {
    "gn:admin1_code":"7.0",
    "gn:asciiname":"Tohwa-dong",
    "gn:country_code":"KP",
    "gn:dem":158,
    "gn:feature_class":"P",
    "gn:feature_code":"PPL",
    "gn:name":"Tohwa-dong",
    "gn:population":0,
    "gn:timezone":"Asia/Pyongyang",
    "iso:country":"KP",
    "name:kor_x_preferred":[
        "\ub3c4\ud654\ub3d9"
    ],
    "wof:name":"Tohwa-dong",
    "wof:placetype":"locality"
},
  "geometry": {"coordinates":[126.76027999999999,38.87722],"type":"Point"}
}