{
  "type": "Feature",
  "properties": {
    "gn:admin1_code":"17.0",
    "gn:asciiname":"Oktang-dong",
    "gn:country_code":"KP",
    "gn:dem":258,
    "gn:feature_class":"P",
    "gn:feature_code":"PPL",
    "gn:name":"Oktang-dong",
    "gn:population":0,
    "gn:timezone":"Asia/Pyongyang",
    "iso:country":"KP",
    "name:und_x_variant":[
        "Odang-dong",
        "Oktang-dong"
    ],
    "wof:name":"Oktang-dong",
    "wof:placetype":"locality"
},
  "geometry": {"coordinates":[129.41721999999999,40.8675],"type":"Point"}
}