{
  "type": "Feature",
  "properties": {
    "gn:admin1_code":"17.0",
    "gn:asciiname":"Kuryong-dong",
    "gn:cc2":"KP",
    "gn:country_code":"KP",
    "gn:dem":869,
    "gn:feature_class":"P",
    "gn:feature_code":"PPL",
    "gn:name":"Kuryong-dong",
    "gn:population":0,
    "gn:timezone":"Asia/Pyongyang",
    "iso:country":"KP",
    "name:und_x_variant":[
        "Kuyong-dong",
        "Kuryong-dong"
    ],
    "wof:name":"Kuryong-dong",
    "wof:placetype":"locality"
},
  "geometry": {"coordinates":[129.27806000000001,41.28278],"type":"Point"}
}