{
  "type": "Feature",
  "properties": {
    "gn:admin1_code":"12.0",
    "gn:asciiname":"Im-ch'on",
    "gn:country_code":"KP",
    "gn:dem":39,
    "gn:feature_class":"P",
    "gn:feature_code":"PPL",
    "gn:name":"Im-ch\u2019on",
    "gn:population":0,
    "gn:timezone":"Asia/Pyongyang",
    "iso:country":"KP",
    "name:und_x_variant":[
        "\uc784\ucd0c",
        "Im-ch\u2019on",
        "Imchon"
    ],
    "wof:name":"Im-ch'on",
    "wof:placetype":"locality"
},
  "geometry": {"coordinates":[125.75628,38.95394],"type":"Point"}
}