{
  "type": "Feature",
  "properties": {
    "gn:admin1_code":"15.0",
    "gn:asciiname":"Hwado-ri",
    "gn:country_code":"KP",
    "gn:dem":15,
    "gn:feature_class":"P",
    "gn:feature_code":"PPL",
    "gn:name":"Hwado-ri",
    "gn:population":0,
    "gn:timezone":"Asia/Pyongyang",
    "iso:country":"KP",
    "name:und_x_variant":[
        "\ud654\ub3c4\ub9ac",
        "Hwado-ri"
    ],
    "wof:name":"Hwado-ri",
    "wof:placetype":"locality"
},
  "geometry": {"coordinates":[125.2375,38.82583],"type":"Point"}
}