{
  "type": "Feature",
  "properties": {
    "gn:admin1_code":"12.0",
    "gn:asciiname":"Chagunjunggol",
    "gn:country_code":"KP",
    "gn:dem":28,
    "gn:feature_class":"P",
    "gn:feature_code":"PPL",
    "gn:name":"Chag\u016dnjunggol",
    "gn:population":0,
    "gn:timezone":"Asia/Pyongyang",
    "iso:country":"KP",
    "name:kor_x_preferred":[
        "Chag\u016dnjunggol"
    ],
    "name:und_x_variant":[
        "Sojung-dong",
        "\uc791\uc740\uc911\uace8",
        "Jageunjunggol"
    ],
    "wof:name":"Chagunjunggol",
    "wof:placetype":"locality"
},
  "geometry": {"coordinates":[125.85778000000001,38.9575],"type":"Point"}
}