{
  "type": "Feature",
  "properties": {
    "gn:admin1_code":"17.0",
    "gn:asciiname":"Chungganch'on",
    "gn:country_code":"KP",
    "gn:dem":152,
    "gn:feature_class":"P",
    "gn:feature_code":"PPL",
    "gn:name":"Chungganch\u2019on",
    "gn:population":0,
    "gn:timezone":"Asia/Pyongyang",
    "iso:country":"KP",
    "name:und_x_variant":[
        "\uc911\uac04\ucd0c",
        "Chungganch\u2019on"
    ],
    "wof:name":"Chungganch'on",
    "wof:placetype":"locality"
},
  "geometry": {"coordinates":[129.3475,40.9725],"type":"Point"}
}