{
  "type": "Feature",
  "properties": {
    "gn:admin1_code":"12.0",
    "gn:asciiname":"Ch'wisong-dong",
    "gn:country_code":"KP",
    "gn:dem":13,
    "gn:feature_class":"P",
    "gn:feature_code":"PPL",
    "gn:name":"Ch\u2019wis\u014fng-dong",
    "gn:population":0,
    "gn:timezone":"Asia/Pyongyang",
    "iso:country":"KP",
    "name:kor_x_preferred":[
        "\ucde8\uc131\ub3d9"
    ],
    "name:und_x_variant":[
        "Ch\u2019wis\u014fng-dong",
        "Chwiseongdong"
    ],
    "wof:name":"Ch'wisong-dong",
    "wof:placetype":"locality"
},
  "geometry": {"coordinates":[125.64472000000001,38.88639000000001],"type":"Point"}
}