{
  "type": "Feature",
  "properties": {
    "gn:admin1_code":"11.0",
    "gn:asciiname":"Manhak-kol",
    "gn:country_code":"KP",
    "gn:dem":91,
    "gn:feature_class":"P",
    "gn:feature_code":"PPL",
    "gn:name":"Manhak-kol",
    "gn:population":0,
    "gn:timezone":"Asia/Pyongyang",
    "iso:country":"KP",
    "wof:name":"Manhak-kol",
    "wof:placetype":"locality"
},
  "geometry": {"coordinates":[125.98806,39.88083],"type":"Point"}
}