{
  "type": "Feature",
  "properties": {
    "gn:admin1_code":"6.0",
    "gn:asciiname":"Kwan-dong",
    "gn:country_code":"KP",
    "gn:dem":81,
    "gn:feature_class":"P",
    "gn:feature_code":"PPL",
    "gn:name":"Kwan-dong",
    "gn:population":0,
    "gn:timezone":"Asia/Pyongyang",
    "iso:country":"KP",
    "name:kor_x_preferred":[
        "\uad00\ub3d9"
    ],
    "wof:name":"Kwan-dong",
    "wof:placetype":"locality"
},
  "geometry": {"coordinates":[125.23999999999999,38.34861],"type":"Point"}
}