{
  "type": "Feature",
  "properties": {
    "gn:admin1_code":"11.0",
    "gn:asciiname":"Kusong-dong",
    "gn:country_code":"KP",
    "gn:dem":11,
    "gn:feature_class":"P",
    "gn:feature_code":"PPL",
    "gn:name":"Kus\u014fng-dong",
    "gn:population":0,
    "gn:timezone":"Asia/Pyongyang",
    "iso:country":"KP",
    "name:und_x_variant":[
        "\uad6c\uc131\ub3d9",
        "Kus\u014fng-dong"
    ],
    "wof:name":"Kusong-dong",
    "wof:placetype":"locality"
},
  "geometry": {"coordinates":[124.43472,39.9725],"type":"Point"}
}