{
  "type": "Feature",
  "properties": {
    "gn:admin1_code":"17.0",
    "gn:asciiname":"T'angsup'yong",
    "gn:country_code":"KP",
    "gn:dem":362,
    "gn:feature_class":"P",
    "gn:feature_code":"PPL",
    "gn:name":"T\u2019angsup\u2019y\u014fng",
    "gn:population":0,
    "gn:timezone":"Asia/Pyongyang",
    "iso:country":"KP",
    "name:und_x_variant":[
        "\ud0d5\uc218\ud3c9",
        "T\u2019angsup\u2019y\u014fng"
    ],
    "wof:name":"T'angsup'yong",
    "wof:placetype":"locality"
},
  "geometry": {"coordinates":[129.36583000000002,41.36028],"type":"Point"}
}