{
  "type": "Feature",
  "properties": {
    "gn:admin1_code":"0.0",
    "gn:asciiname":"Tongnim-ni",
    "gn:country_code":"KP",
    "gn:dem":76,
    "gn:feature_class":"P",
    "gn:feature_code":"PPL",
    "gn:name":"T\u014fngnim-ni",
    "gn:population":0,
    "gn:timezone":"Asia/Pyongyang",
    "iso:country":"KP",
    "name:kor_x_preferred":[
        "\ub355\ub9bc\ub9ac"
    ],
    "name:und_x_variant":[
        "T\u014fngnim-ni"
    ],
    "wof:name":"Tongnim-ni",
    "wof:placetype":"locality"
},
  "geometry": {"coordinates":[125.48333,39.85],"type":"Point"}
}