{
  "type": "Feature",
  "properties": {
    "gn:admin1_code":"11.0",
    "gn:asciiname":"Kangsol-li",
    "gn:country_code":"KP",
    "gn:dem":472,
    "gn:feature_class":"P",
    "gn:feature_code":"PPL",
    "gn:name":"Kangs\u014fl-li",
    "gn:population":0,
    "gn:timezone":"Asia/Pyongyang",
    "iso:country":"KP",
    "name:und_x_variant":[
        "\uac15\uc120\ub9ac",
        "Kangs\u014fl-li"
    ],
    "wof:name":"Kangsol-li",
    "wof:placetype":"locality"
},
  "geometry": {"coordinates":[125.44638999999999,40.47889],"type":"Point"}
}