{
  "type": "Feature",
  "properties": {
    "gn:admin1_code":"9.0",
    "gn:asciiname":"Ch'olbyong-ni",
    "gn:country_code":"KP",
    "gn:dem":481,
    "gn:feature_class":"P",
    "gn:feature_code":"PPL",
    "gn:name":"Ch\u2019\u014flby\u014fng-ni",
    "gn:population":0,
    "gn:timezone":"Asia/Pyongyang",
    "iso:country":"KP",
    "name:eng_x_preferred":[
        "Ch'olbyong"
    ],
    "name:eng_x_variant":[
        "Ch'olbyong-ni"
    ],
    "name:und_x_variant":[
        "Senbo-ri",
        "Ch\u014fmbang-ni",
        "Senh\u014d-ri",
        "Ch\u014fmby\u014fng-ni",
        "Semp\u014d-ri",
        "\ucca0\ubcbd\ub9ac",
        "Ch\u2019\u014flby\u014fng-ni"
    ],
    "wof:name":"Ch'olbyong",
    "wof:placetype":"locality"
},
  "geometry": {"coordinates":[127.90582999999999,38.42806],"type":"Point"}
}