{
  "type": "Feature",
  "properties": {
    "gn:admin1_code":"6.0",
    "gn:asciiname":"Pun-dong",
    "gn:country_code":"KP",
    "gn:dem":34,
    "gn:feature_class":"P",
    "gn:feature_code":"PPL",
    "gn:name":"Pun-dong",
    "gn:population":0,
    "gn:timezone":"Asia/Pyongyang",
    "iso:country":"KP",
    "name:und_x_variant":[
        "\ubd84\ub3d9",
        "Pun-dong"
    ],
    "wof:name":"Pun-dong",
    "wof:placetype":"locality"
},
  "geometry": {"coordinates":[125.23917,38.10778],"type":"Point"}
}