{
  "type": "Feature",
  "properties": {
    "gn:admin1_code":"11.0",
    "gn:asciiname":"Wangdang-dong",
    "gn:country_code":"KP",
    "gn:dem":219,
    "gn:feature_class":"P",
    "gn:feature_code":"PPL",
    "gn:name":"Wangdang-dong",
    "gn:population":0,
    "gn:timezone":"Asia/Pyongyang",
    "iso:country":"KP",
    "name:kor_x_preferred":[
        "\uc655\ub2f9\ub3d9"
    ],
    "name:und_x_variant":[
        "Wangdong-dong",
        "Wangdang-dong"
    ],
    "wof:name":"Wangdang-dong",
    "wof:placetype":"locality"
},
  "geometry": {"coordinates":[125.00611000000001,39.955],"type":"Point"}
}