{
  "type": "Feature",
  "properties": {
    "gn:admin1_code":"11.0",
    "gn:asciiname":"Kwangsong",
    "gn:country_code":"KP",
    "gn:dem":29,
    "gn:feature_class":"P",
    "gn:feature_code":"PPL",
    "gn:name":"Kwangs\u014fng",
    "gn:population":0,
    "gn:timezone":"Asia/Pyongyang",
    "iso:country":"KP",
    "name:kor_x_preferred":[
        "\uad11\uc131"
    ],
    "name:kor_x_variant":[
        "Kwangs\u014fng"
    ],
    "wof:name":"Kwangsong",
    "wof:placetype":"locality"
},
  "geometry": {"coordinates":[125.30278,39.64778],"type":"Point"}
}