{
  "type": "Feature",
  "properties": {
    "gn:admin1_code":"11.0",
    "gn:asciiname":"Sosu-dong",
    "gn:country_code":"KP",
    "gn:dem":53,
    "gn:feature_class":"P",
    "gn:feature_code":"PPL",
    "gn:name":"Sosu-dong",
    "gn:population":0,
    "gn:timezone":"Asia/Pyongyang",
    "iso:country":"KP",
    "name:und_x_variant":[
        "\uc18c\uc218\ub3d9",
        "Sosu-dong"
    ],
    "wof:name":"Sosu-dong",
    "wof:placetype":"locality"
},
  "geometry": {"coordinates":[124.59972,40.15917],"type":"Point"}
}