{
  "type": "Feature",
  "properties": {
    "gn:admin1_code":"17.0",
    "gn:asciiname":"Tangu-ch'on",
    "gn:country_code":"KP",
    "gn:dem":143,
    "gn:feature_class":"P",
    "gn:feature_code":"PPL",
    "gn:name":"Tangu-ch\u2019on",
    "gn:population":0,
    "gn:timezone":"Asia/Pyongyang",
    "iso:country":"KP",
    "name:und_x_variant":[
        "\ub2f9\uc6b0\ucd0c",
        "Tangu-ch\u2019on"
    ],
    "wof:name":"Tangu-ch'on",
    "wof:placetype":"locality"
},
  "geometry": {"coordinates":[129.53999999999999,41.6475],"type":"Point"}
}