{
  "type": "Feature",
  "properties": {
    "gn:admin1_code":"12.0",
    "gn:asciiname":"Ich'on",
    "gn:country_code":"KP",
    "gn:dem":44,
    "gn:feature_class":"P",
    "gn:feature_code":"PPL",
    "gn:name":"Ich\u2019on",
    "gn:population":0,
    "gn:timezone":"Asia/Pyongyang",
    "iso:country":"KP",
    "name:und_x_variant":[
        "\uc774\ucd0c",
        "Ich\u2019on"
    ],
    "wof:name":"Ich'on",
    "wof:placetype":"locality"
},
  "geometry": {"coordinates":[125.81471999999999,38.83889],"type":"Point"}
}