{
  "type": "Feature",
  "properties": {
    "gn:admin1_code":"15.0",
    "gn:asciiname":"Sogok",
    "gn:country_code":"KP",
    "gn:dem":359,
    "gn:feature_class":"P",
    "gn:feature_code":"PPL",
    "gn:name":"Sogok",
    "gn:population":0,
    "gn:timezone":"Asia/Pyongyang",
    "iso:country":"KP",
    "name:und_x_variant":[
        "\uc18c\uace1",
        "Sogok"
    ],
    "wof:name":"Sogok",
    "wof:placetype":"locality"
},
  "geometry": {"coordinates":[126.57971999999999,39.85861],"type":"Point"}
}