{
  "type": "Feature",
  "properties": {
    "gn:admin1_code":"7.0",
    "gn:asciiname":"Kadokchong",
    "gn:country_code":"KP",
    "gn:dem":181,
    "gn:feature_class":"P",
    "gn:feature_code":"PPL",
    "gn:name":"Kad\u014fkch\u014fng",
    "gn:population":0,
    "gn:timezone":"Asia/Pyongyang",
    "iso:country":"KP",
    "name:kor_x_preferred":[
        "\uac00\ub355\uc815"
    ],
    "name:kor_x_variant":[
        "Kad\u014fkch\u014fng"
    ],
    "wof:name":"Kadokchong",
    "wof:placetype":"locality"
},
  "geometry": {"coordinates":[126.30333,38.66722],"type":"Point"}
}