{
  "type": "Feature",
  "properties": {
    "gn:admin1_code":"11.0",
    "gn:asciiname":"Saengul-li",
    "gn:country_code":"KP",
    "gn:dem":183,
    "gn:feature_class":"P",
    "gn:feature_code":"PPL",
    "gn:name":"Saeng\u016dl-li",
    "gn:population":0,
    "gn:timezone":"Asia/Pyongyang",
    "iso:country":"KP",
    "name:und_x_variant":[
        "\uc0dd\uc740\ub9ac",
        "Saeng\u016dn-ni",
        "Saeng\u016dl-li"
    ],
    "wof:name":"Saengul-li",
    "wof:placetype":"locality"
},
  "geometry": {"coordinates":[124.91722,40.34556],"type":"Point"}
}