{
  "type": "Feature",
  "properties": {
    "gn:admin1_code":"9.0",
    "gn:admin2_code":"Ch\u2019\u014fnnae-gun",
    "gn:asciiname":"Sumunmegi",
    "gn:country_code":"KP",
    "gn:dem":19,
    "gn:feature_class":"P",
    "gn:feature_code":"PPL",
    "gn:name":"Sumunmegi",
    "gn:population":0,
    "gn:timezone":"Asia/Pyongyang",
    "iso:country":"KP",
    "name:und_x_variant":[
        "\uc218\ubb38\uba54\uae30"
    ],
    "wof:name":"Sumunmegi",
    "wof:placetype":"locality"
},
  "geometry": {"coordinates":[127.24778000000001,39.36917],"type":"Point"}
}