{
  "type": "Feature",
  "properties": {
    "gn:admin1_code":"3.0",
    "gn:asciiname":"Sang-ch'on",
    "gn:country_code":"KP",
    "gn:dem":32,
    "gn:feature_class":"P",
    "gn:feature_code":"PPL",
    "gn:name":"Sang-ch\u2019on",
    "gn:population":0,
    "gn:timezone":"Asia/Pyongyang",
    "iso:country":"KP",
    "name:und_x_variant":[
        "\uc0c1\ucd0c",
        "Sang-ch\u2019on"
    ],
    "wof:name":"Sang-ch'on",
    "wof:placetype":"locality"
},
  "geometry": {"coordinates":[128.82778000000002,40.48806],"type":"Point"}
}