{
  "type": "Feature",
  "properties": {
    "gn:admin1_code":"15.0",
    "gn:asciiname":"Taedok",
    "gn:country_code":"KP",
    "gn:dem":791,
    "gn:feature_class":"P",
    "gn:feature_code":"PPL",
    "gn:name":"Taed\u014fk",
    "gn:population":0,
    "gn:timezone":"Asia/Pyongyang",
    "iso:country":"KP",
    "name:und_x_variant":[
        "\ub300\ub355",
        "Taed\u014fk"
    ],
    "wof:name":"Taedok",
    "wof:placetype":"locality"
},
  "geometry": {"coordinates":[126.88861,40.00028],"type":"Point"}
}