{
  "type": "Feature",
  "properties": {
    "gn:admin1_code":"0.0",
    "gn:asciiname":"Kumsan",
    "gn:cc2":"KP",
    "gn:country_code":"KP",
    "gn:dem":45,
    "gn:feature_class":"P",
    "gn:feature_code":"PPL",
    "gn:name":"K\u016dmsan",
    "gn:population":0,
    "gn:timezone":"Asia/Pyongyang",
    "iso:country":"KP",
    "name:kor_x_preferred":[
        "\uae08\uc0b0"
    ],
    "name:und_x_variant":[
        "Kinsan",
        "K\u016dmsan"
    ],
    "wof:name":"Kumsan",
    "wof:placetype":"locality"
},
  "geometry": {"coordinates":[125.78333000000001,38.61667],"type":"Point"}
}