{
  "type": "Feature",
  "properties": {
    "gn:admin1_code":"3.0",
    "gn:asciiname":"Tonggumi",
    "gn:country_code":"KP",
    "gn:dem":19,
    "gn:feature_class":"P",
    "gn:feature_code":"PPL",
    "gn:name":"Tonggumi",
    "gn:population":0,
    "gn:timezone":"Asia/Pyongyang",
    "iso:country":"KP",
    "name:und_x_variant":[
        "\ub3d9\uad6c\ubbf8",
        "Tonggumi"
    ],
    "wof:name":"Tonggumi",
    "wof:placetype":"locality"
},
  "geometry": {"coordinates":[128.74250000000001,40.34306],"type":"Point"}
}