{
  "type": "Feature",
  "properties": {
    "gn:admin1_code":"7.0",
    "gn:asciiname":"Sinbong-dong",
    "gn:country_code":"KP",
    "gn:dem":263,
    "gn:feature_class":"P",
    "gn:feature_code":"PPL",
    "gn:name":"Sinbong-dong",
    "gn:population":0,
    "gn:timezone":"Asia/Pyongyang",
    "iso:country":"KP",
    "wof:name":"Sinbong-dong",
    "wof:placetype":"locality"
},
  "geometry": {"coordinates":[126.13943999999999,38.55361],"type":"Point"}
}