{
  "type": "Feature",
  "properties": {
    "gn:admin1_code":"3.0",
    "gn:asciiname":"Oe-ch'on",
    "gn:country_code":"KP",
    "gn:dem":45,
    "gn:feature_class":"P",
    "gn:feature_code":"PPL",
    "gn:name":"Oe-ch\u2019on",
    "gn:population":0,
    "gn:timezone":"Asia/Pyongyang",
    "iso:country":"KP",
    "name:und_x_variant":[
        "\uc678\ucd0c",
        "Oe-ch\u2019on"
    ],
    "wof:name":"Oe-ch'on",
    "wof:placetype":"locality"
},
  "geometry": {"coordinates":[128.9725,40.54528],"type":"Point"}
}