{
  "type": "Feature",
  "properties": {
    "gn:admin1_code":"9.0",
    "gn:admin2_code":"Munch\u2019\u014fn-si",
    "gn:asciiname":"Sokchol-li",
    "gn:country_code":"KP",
    "gn:dem":21,
    "gn:feature_class":"P",
    "gn:feature_code":"PPL",
    "gn:name":"S\u014fkch\u014fl-li",
    "gn:population":0,
    "gn:timezone":"Asia/Pyongyang",
    "iso:country":"KP",
    "name:und_x_variant":[
        "S\u014fkch\u014fn-ni",
        "S\u014fkch\u014fl-li"
    ],
    "wof:name":"Sokchol-li",
    "wof:placetype":"locality"
},
  "geometry": {"coordinates":[127.38,39.34806],"type":"Point"}
}