{
  "type": "Feature",
  "properties": {
    "gn:admin1_code":"1.0",
    "gn:asciiname":"P'ungha-dong",
    "gn:country_code":"KP",
    "gn:dem":264,
    "gn:feature_class":"P",
    "gn:feature_code":"PPL",
    "gn:name":"P\u2019ungha-dong",
    "gn:population":0,
    "gn:timezone":"Asia/Pyongyang",
    "iso:country":"KP",
    "name:und_x_variant":[
        "\ud48d\ud558\ub3d9",
        "P\u2019ungha-dong"
    ],
    "wof:name":"P'ungha-dong",
    "wof:placetype":"locality"
},
  "geometry": {"coordinates":[126.26194,40.97111],"type":"Point"}
}