{
  "type": "Feature",
  "properties": {
    "gn:admin1_code":"6.0",
    "gn:admin2_code":"Changp\u2019ung-gun",
    "gn:asciiname":"Nung-dong",
    "gn:country_code":"KP",
    "gn:dem":58,
    "gn:feature_class":"P",
    "gn:feature_code":"PPL",
    "gn:name":"N\u016dng-dong",
    "gn:population":0,
    "gn:timezone":"Asia/Pyongyang",
    "iso:country":"KP",
    "wof:name":"Nung-dong",
    "wof:placetype":"locality"
},
  "geometry": {"coordinates":[126.78943999999998,38.07861],"type":"Point"}
}