{
  "type": "Feature",
  "properties": {
    "gn:admin1_code":"3.0",
    "gn:asciiname":"Samdo-gol",
    "gn:country_code":"KP",
    "gn:dem":39,
    "gn:feature_class":"P",
    "gn:feature_code":"PPL",
    "gn:name":"Samdo-gol",
    "gn:population":0,
    "gn:timezone":"Asia/Pyongyang",
    "iso:country":"KP",
    "name:und_x_variant":[
        "\uc0bc\ub3c4\uace8",
        "Samdo-gol"
    ],
    "wof:name":"Samdo-gol",
    "wof:placetype":"locality"
},
  "geometry": {"coordinates":[127.60833,39.87611],"type":"Point"}
}