{
  "type": "Feature",
  "properties": {
    "gn:admin1_code":"6.0",
    "gn:asciiname":"Munhwa",
    "gn:cc2":"KP",
    "gn:country_code":"KP",
    "gn:dem":33,
    "gn:feature_class":"P",
    "gn:feature_code":"PPL",
    "gn:name":"Munhwa",
    "gn:population":0,
    "gn:timezone":"Asia/Pyongyang",
    "iso:country":"KP",
    "name:und_x_variant":[
        "Bunka",
        "Munhwa"
    ],
    "wof:name":"Munhwa",
    "wof:placetype":"locality"
},
  "geometry": {"coordinates":[125.41,38.40611],"type":"Point"}
}