{
  "type": "Feature",
  "properties": {
    "gn:admin1_code":"6.0",
    "gn:asciiname":"Oejon-ch'on",
    "gn:country_code":"KP",
    "gn:dem":22,
    "gn:feature_class":"P",
    "gn:feature_code":"PPL",
    "gn:name":"Oej\u014fn-ch\u2019on",
    "gn:population":0,
    "gn:timezone":"Asia/Pyongyang",
    "iso:country":"KP",
    "wof:name":"Oejon-ch'on",
    "wof:placetype":"locality"
},
  "geometry": {"coordinates":[125.12860999999999,38.64417],"type":"Point"}
}