{
  "type": "Feature",
  "properties": {
    "gn:admin1_code":"0.0",
    "gn:asciiname":"Unhung-ni",
    "gn:cc2":"KP",
    "gn:country_code":"KP",
    "gn:dem":19,
    "gn:feature_class":"P",
    "gn:feature_code":"PPL",
    "gn:name":"Unh\u016dng-ni",
    "gn:population":0,
    "gn:timezone":"Asia/Pyongyang",
    "iso:country":"KP",
    "name:eng_x_preferred":[
        "Unhung"
    ],
    "name:eng_x_variant":[
        "Unhung-ni"
    ],
    "name:kor_x_preferred":[
        "\uc6b4\ud765\ub9ac"
    ],
    "name:und_x_variant":[
        "Pon\u2019gungi-dong",
        "Unh\u016dng-dong",
        "Unh\u016dng-ni"
    ],
    "wof:name":"Unhung",
    "wof:placetype":"locality"
},
  "geometry": {"coordinates":[127.59999999999999,39.86667],"type":"Point"}
}