{
  "type": "Feature",
  "properties": {
    "gn:admin1_code":"13.0",
    "gn:asciiname":"Komuso",
    "gn:country_code":"KP",
    "gn:dem":580,
    "gn:feature_class":"P",
    "gn:feature_code":"PPL",
    "gn:name":"Komuso",
    "gn:population":0,
    "gn:timezone":"Asia/Pyongyang",
    "iso:country":"KP",
    "wof:name":"Komuso",
    "wof:placetype":"locality"
},
  "geometry": {"coordinates":[127.87582999999999,41.43389000000001],"type":"Point"}
}