{
  "type": "Feature",
  "properties": {
    "gn:admin1_code":"7.0",
    "gn:asciiname":"Choso-dong",
    "gn:country_code":"KP",
    "gn:dem":41,
    "gn:feature_class":"P",
    "gn:feature_code":"PPL",
    "gn:name":"Choso-dong",
    "gn:population":0,
    "gn:timezone":"Asia/Pyongyang",
    "iso:country":"KP",
    "name:und_x_variant":[
        "\uc870\uc18c\ub3d9",
        "Choso-dong"
    ],
    "wof:name":"Choso-dong",
    "wof:placetype":"locality"
},
  "geometry": {"coordinates":[125.83889000000001,38.79806],"type":"Point"}
}