{
  "type": "Feature",
  "properties": {
    "gn:admin1_code":"1.0",
    "gn:asciiname":"Such'aech'am",
    "gn:country_code":"KP",
    "gn:dem":222,
    "gn:feature_class":"P",
    "gn:feature_code":"PPL",
    "gn:name":"Such\u2019aech\u2019am",
    "gn:population":0,
    "gn:timezone":"Asia/Pyongyang",
    "iso:country":"KP",
    "name:und_x_variant":[
        "\uc218\ucc44\ucc38",
        "Such\u2019aech\u2019am"
    ],
    "wof:name":"Such'aech'am",
    "wof:placetype":"locality"
},
  "geometry": {"coordinates":[126.36111,40.12972],"type":"Point"}
}