{
  "type": "Feature",
  "properties": {
    "gn:admin1_code":"6.0",
    "gn:asciiname":"Changdul-li",
    "gn:country_code":"KP",
    "gn:dem":45,
    "gn:feature_class":"P",
    "gn:feature_code":"PPL",
    "gn:name":"Changdul-li",
    "gn:population":0,
    "gn:timezone":"Asia/Pyongyang",
    "iso:country":"KP",
    "name:und_x_variant":[
        "Tanch\u2019\u014fn-ni",
        "\uc7a5\ub454\ub9ac",
        "Changdun-ni",
        "Changdul-li"
    ],
    "wof:name":"Changdul-li",
    "wof:placetype":"locality"
},
  "geometry": {"coordinates":[125.44222000000001,37.9675],"type":"Point"}
}