{
  "type": "Feature",
  "properties": {
    "gn:admin1_code":"15.0",
    "gn:admin2_code":"Ch'\u014fngnam-gu",
    "gn:asciiname":"Ch'ongnam",
    "gn:country_code":"KP",
    "gn:dem":12,
    "gn:feature_class":"P",
    "gn:feature_code":"PPL",
    "gn:name":"Ch\u2019\u014fngnam",
    "gn:population":0,
    "gn:timezone":"Asia/Pyongyang",
    "iso:country":"KP",
    "name:und_x_variant":[
        "Anju-nodongjagu",
        "Ch\u2019\u014fngnam"
    ],
    "wof:name":"Ch'ongnam",
    "wof:placetype":"locality"
},
  "geometry": {"coordinates":[125.46111000000001,39.48778],"type":"Point"}
}