{
  "type": "Feature",
  "properties": {
    "gn:admin1_code":"3.0",
    "gn:asciiname":"Tokhwa-gol",
    "gn:country_code":"KP",
    "gn:dem":111,
    "gn:feature_class":"P",
    "gn:feature_code":"PPL",
    "gn:name":"Tokhwa-gol",
    "gn:population":0,
    "gn:timezone":"Asia/Pyongyang",
    "iso:country":"KP",
    "name:und_x_variant":[
        "Tokhwa-kol",
        "\ub355\ud654\uace8",
        "Tokhwa-gol"
    ],
    "wof:name":"Tokhwa-gol",
    "wof:placetype":"locality"
},
  "geometry": {"coordinates":[127.36278,39.565],"type":"Point"}
}