{
  "type": "Feature",
  "properties": {
    "gn:admin1_code":"0.0",
    "gn:asciiname":"Hungbong-ni",
    "gn:country_code":"KP",
    "gn:dem":31,
    "gn:feature_class":"P",
    "gn:feature_code":"PPL",
    "gn:name":"H\u016dngbong-ni",
    "gn:population":0,
    "gn:timezone":"Asia/Pyongyang",
    "iso:country":"KP",
    "name:kor_x_preferred":[
        "\ud765\ubd09\ub9ac"
    ],
    "name:und_x_variant":[
        "H\u016dngbong-ni"
    ],
    "wof:name":"Hungbong-ni",
    "wof:placetype":"locality"
},
  "geometry": {"coordinates":[127.43333,39.96667],"type":"Point"}
}