{
  "type": "Feature",
  "properties": {
    "gn:admin1_code":"15.0",
    "gn:asciiname":"Pangha",
    "gn:country_code":"KP",
    "gn:dem":254,
    "gn:feature_class":"P",
    "gn:feature_code":"PPL",
    "gn:name":"Pangha",
    "gn:population":0,
    "gn:timezone":"Asia/Pyongyang",
    "iso:country":"KP",
    "name:und_x_variant":[
        "\ubc29\ud558",
        "Pangha"
    ],
    "wof:name":"Pangha",
    "wof:placetype":"locality"
},
  "geometry": {"coordinates":[126.64610999999999,39.72694],"type":"Point"}
}