{
  "type": "Feature",
  "properties": {
    "gn:admin1_code":"6.0",
    "gn:asciiname":"Punt'o",
    "gn:country_code":"KP",
    "gn:dem":96,
    "gn:feature_class":"P",
    "gn:feature_code":"PPL",
    "gn:name":"Punt\u2019o",
    "gn:population":0,
    "gn:timezone":"Asia/Pyongyang",
    "iso:country":"KP",
    "name:kor_x_preferred":[
        "\ubd84\ud1a0"
    ],
    "name:und_x_variant":[
        "Punt\u2019o"
    ],
    "wof:name":"Punt'o",
    "wof:placetype":"locality"
},
  "geometry": {"coordinates":[125.47556000000002,38.05167],"type":"Point"}
}