{
  "type": "Feature",
  "properties": {
    "gn:admin1_code":"17.0",
    "gn:asciiname":"Tunjon-dong",
    "gn:country_code":"KP",
    "gn:dem":24,
    "gn:feature_class":"P",
    "gn:feature_code":"PPL",
    "gn:name":"Tunj\u014fn-dong",
    "gn:population":0,
    "gn:timezone":"Asia/Pyongyang",
    "iso:country":"KP",
    "name:und_x_variant":[
        "Tunj\u014fn-ni",
        "\ub454\uc804\ub3d9",
        "Tunj\u014fn-dong"
    ],
    "wof:name":"Tunjon-dong",
    "wof:placetype":"locality"
},
  "geometry": {"coordinates":[129.50278,40.84389],"type":"Point"}
}