{
  "type": "Feature",
  "properties": {
    "gn:admin1_code":"6.0",
    "gn:asciiname":"Oung-ni",
    "gn:country_code":"KP",
    "gn:dem":48,
    "gn:feature_class":"P",
    "gn:feature_code":"PPL",
    "gn:name":"O\u016dng-ni",
    "gn:population":0,
    "gn:timezone":"Asia/Pyongyang",
    "iso:country":"KP",
    "name:kor_x_preferred":[
        "\uc624\uc751\ub9ac"
    ],
    "name:kor_x_variant":[
        "O\u016dng-ni"
    ],
    "wof:name":"Oung-ni",
    "wof:placetype":"locality"
},
  "geometry": {"coordinates":[125.17861000000001,38.25944000000001],"type":"Point"}
}