{
  "type": "Feature",
  "properties": {
    "gn:admin1_code":"7.0",
    "gn:asciiname":"Worun-ch'on",
    "gn:country_code":"KP",
    "gn:dem":7,
    "gn:feature_class":"P",
    "gn:feature_code":"PPL",
    "gn:name":"W\u014frun-ch\u2019on",
    "gn:population":0,
    "gn:timezone":"Asia/Pyongyang",
    "iso:country":"KP",
    "name:kor_x_preferred":[
        "\uc6d4\uc6b4\ucd0c"
    ],
    "name:kor_x_variant":[
        "W\u014frun-ch\u2019on"
    ],
    "wof:name":"Worun-ch'on",
    "wof:placetype":"locality"
},
  "geometry": {"coordinates":[125.66861000000002,38.61389000000001],"type":"Point"}
}