{
  "type": "Feature",
  "properties": {
    "gn:admin1_code":"1.0",
    "gn:asciiname":"Todang-ch'on",
    "gn:country_code":"KP",
    "gn:dem":855,
    "gn:feature_class":"P",
    "gn:feature_code":"PPL",
    "gn:name":"Todang-ch\u2019on",
    "gn:population":0,
    "gn:timezone":"Asia/Pyongyang",
    "iso:country":"KP",
    "name:kor_x_preferred":[
        "\ub3c4\ub2f9\ucd0c"
    ],
    "name:und_x_variant":[
        "Todang-ch\u2019on"
    ],
    "wof:name":"Todang-ch'on",
    "wof:placetype":"locality"
},
  "geometry": {"coordinates":[127.33,41.01389],"type":"Point"}
}