{
  "type": "Feature",
  "properties": {
    "gn:admin1_code":"15.0",
    "gn:admin2_code":"Pukch\u2019ang-gun",
    "gn:asciiname":"Songjong-ni",
    "gn:country_code":"KP",
    "gn:dem":271,
    "gn:feature_class":"P",
    "gn:feature_code":"PPL",
    "gn:name":"Songj\u014fng-ni",
    "gn:population":0,
    "gn:timezone":"Asia/Pyongyang",
    "iso:country":"KP",
    "wof:name":"Songjong-ni",
    "wof:placetype":"locality"
},
  "geometry": {"coordinates":[126.29389,39.64944000000001],"type":"Point"}
}