{
  "type": "Feature",
  "properties": {
    "gn:admin1_code":"11.0",
    "gn:asciiname":"Wol-gol",
    "gn:country_code":"KP",
    "gn:dem":48,
    "gn:feature_class":"P",
    "gn:feature_code":"PPL",
    "gn:name":"W\u014fl-gol",
    "gn:population":0,
    "gn:timezone":"Asia/Pyongyang",
    "iso:country":"KP",
    "name:und_x_variant":[
        "\uc6d4\uace8",
        "W\u014fl-gol"
    ],
    "wof:name":"Wol-gol",
    "wof:placetype":"locality"
},
  "geometry": {"coordinates":[124.62056,40.07167000000001],"type":"Point"}
}