{
  "type": "Feature",
  "properties": {
    "gn:admin1_code":"7.0",
    "gn:asciiname":"Insan",
    "gn:country_code":"KP",
    "gn:dem":101,
    "gn:feature_class":"P",
    "gn:feature_code":"PPL",
    "gn:name":"Insan",
    "gn:population":0,
    "gn:timezone":"Asia/Pyongyang",
    "iso:country":"KP",
    "name:fas_x_preferred":[
        "\u0627\u0646\u0633\u0627\u0646"
    ],
    "name:new_x_preferred":[
        "\u0907\u0928\u094d\u0938\u093e\u0928"
    ],
    "name:pol_x_preferred":[
        "Insan"
    ],
    "name:und_x_variant":[
        "Mun\u2019gu-ri",
        "Rinzan",
        "\uc778\uc0b0",
        "Insan-up"
    ],
    "wof:name":"Insan",
    "wof:placetype":"locality"
},
  "geometry": {"coordinates":[126.12667,38.34194],"type":"Point"}
}