{
  "type": "Feature",
  "properties": {
    "gn:admin1_code":"9.0",
    "gn:asciiname":"Sagi-dong",
    "gn:country_code":"KP",
    "gn:dem":286,
    "gn:feature_class":"P",
    "gn:feature_code":"PPL",
    "gn:name":"Sagi-dong",
    "gn:population":0,
    "gn:timezone":"Asia/Pyongyang",
    "iso:country":"KP",
    "name:und_x_variant":[
        "\uc0ac\uae30\ub3d9",
        "Sagi-dong"
    ],
    "wof:name":"Sagi-dong",
    "wof:placetype":"locality"
},
  "geometry": {"coordinates":[127.51833000000001,38.9075],"type":"Point"}
}