{
  "type": "Feature",
  "properties": {
    "gn:admin1_code":"3.0",
    "gn:asciiname":"Changjip'o",
    "gn:country_code":"KP",
    "gn:dem":318,
    "gn:feature_class":"P",
    "gn:feature_code":"PPL",
    "gn:name":"Changjip\u2019o",
    "gn:population":0,
    "gn:timezone":"Asia/Pyongyang",
    "iso:country":"KP",
    "name:kor_x_preferred":[
        "\uc7a5\uc9c0\ud3ec"
    ],
    "name:kor_x_variant":[
        "Changjip\u2019o"
    ],
    "wof:name":"Changjip'o",
    "wof:placetype":"locality"
},
  "geometry": {"coordinates":[127.01639,39.72417],"type":"Point"}
}