{
  "type": "Feature",
  "properties": {
    "gn:admin1_code":"17.0",
    "gn:asciiname":"Yusu-dong",
    "gn:country_code":"KP",
    "gn:dem":133,
    "gn:feature_class":"P",
    "gn:feature_code":"PPL",
    "gn:name":"Yusu-dong",
    "gn:population":0,
    "gn:timezone":"Asia/Pyongyang",
    "iso:country":"KP",
    "name:und_x_variant":[
        "\uc720\uc218\ub3d9",
        "Yusu-dong"
    ],
    "wof:name":"Yusu-dong",
    "wof:placetype":"locality"
},
  "geometry": {"coordinates":[130.15443999999999,42.68917],"type":"Point"}
}