{
  "type": "Feature",
  "properties": {
    "gn:admin1_code":"3.0",
    "gn:asciiname":"Marho-ri",
    "gn:country_code":"KP",
    "gn:dem":4,
    "gn:feature_class":"P",
    "gn:feature_code":"PPL",
    "gn:name":"Marh\u014f-ri",
    "gn:population":0,
    "gn:timezone":"Asia/Pyongyang",
    "iso:country":"KP",
    "name:und_x_variant":[
        "\ub9d0\ud5c8\ub9ac",
        "Marh\u014f-ri"
    ],
    "wof:name":"Marho-ri",
    "wof:placetype":"locality"
},
  "geometry": {"coordinates":[127.52500000000001,39.42417],"type":"Point"}
}