{
  "type": "Feature",
  "properties": {
    "gn:admin1_code":"3.0",
    "gn:asciiname":"Wonbong-ni",
    "gn:country_code":"KP",
    "gn:dem":291,
    "gn:feature_class":"P",
    "gn:feature_code":"PPL",
    "gn:name":"W\u014fnbong-ni",
    "gn:population":0,
    "gn:timezone":"Asia/Pyongyang",
    "iso:country":"KP",
    "name:und_x_variant":[
        "\uc6d0\ubd09\ub9ac",
        "W\u014fnbong-ni"
    ],
    "wof:name":"Wonbong-ni",
    "wof:placetype":"locality"
},
  "geometry": {"coordinates":[127.64972,40.26972],"type":"Point"}
}