{
  "type": "Feature",
  "properties": {
    "gn:admin1_code":"3.0",
    "gn:asciiname":"Sinhung-ch'on",
    "gn:country_code":"KP",
    "gn:dem":117,
    "gn:feature_class":"P",
    "gn:feature_code":"PPL",
    "gn:name":"Sinh\u016dng-ch\u2019on",
    "gn:population":0,
    "gn:timezone":"Asia/Pyongyang",
    "iso:country":"KP",
    "name:und_x_variant":[
        "Sinh\u016dng-ch\u2019on",
        "\uc2e0\ud765\ucd0c"
    ],
    "wof:name":"Sinhung-ch'on",
    "wof:placetype":"locality"
},
  "geometry": {"coordinates":[128.20813000000001,40.25868],"type":"Point"}
}