{
  "type": "Feature",
  "properties": {
    "gn:admin1_code":"18.0",
    "gn:asciiname":"Kamaewon",
    "gn:country_code":"KP",
    "gn:dem":11,
    "gn:feature_class":"P",
    "gn:feature_code":"PPL",
    "gn:name":"Kamaew\u014fn",
    "gn:population":0,
    "gn:timezone":"Asia/Pyongyang",
    "iso:country":"KP",
    "name:und_x_variant":[
        "\uac00\ub9e4\uc6d0",
        "Kamaew\u014fn",
        "Gamaewon"
    ],
    "wof:name":"Kamaewon",
    "wof:placetype":"locality"
},
  "geometry": {"coordinates":[130.19238000000001,42.19224000000001],"type":"Point"}
}