{
  "type": "Feature",
  "properties": {
    "gn:admin1_code":"7.0",
    "gn:asciiname":"Sangwang-dong",
    "gn:country_code":"KP",
    "gn:dem":64,
    "gn:feature_class":"P",
    "gn:feature_code":"PPL",
    "gn:name":"Sangwang-dong",
    "gn:population":0,
    "gn:timezone":"Asia/Pyongyang",
    "iso:country":"KP",
    "name:und_x_variant":[
        "\uc0c1\uc655\ub3d9",
        "Sangwang-dong"
    ],
    "wof:name":"Sangwang-dong",
    "wof:placetype":"locality"
},
  "geometry": {"coordinates":[126.49806,38.12333],"type":"Point"}
}