{
  "type": "Feature",
  "properties": {
    "gn:admin1_code":"11.0",
    "gn:asciiname":"Kunmal",
    "gn:country_code":"KP",
    "gn:dem":20,
    "gn:feature_class":"P",
    "gn:feature_code":"PPL",
    "gn:name":"K\u016dnmal",
    "gn:population":0,
    "gn:timezone":"Asia/Pyongyang",
    "iso:country":"KP",
    "name:kor_x_preferred":[
        "\ud070\ub9d0"
    ],
    "name:kor_x_variant":[
        "K\u016dnmal"
    ],
    "wof:name":"Kunmal",
    "wof:placetype":"locality"
},
  "geometry": {"coordinates":[125.25667,39.65333],"type":"Point"}
}