{
  "type": "Feature",
  "properties": {
    "gn:admin1_code":"11.0",
    "gn:asciiname":"Chaegol-mal",
    "gn:country_code":"KP",
    "gn:dem":30,
    "gn:feature_class":"P",
    "gn:feature_code":"PPL",
    "gn:name":"Chaegol-mal",
    "gn:population":0,
    "gn:timezone":"Asia/Pyongyang",
    "iso:country":"KP",
    "wof:name":"Chaegol-mal",
    "wof:placetype":"locality"
},
  "geometry": {"coordinates":[125.4075,39.64361],"type":"Point"}
}