{
  "type": "Feature",
  "properties": {
    "gn:admin1_code":"15.0",
    "gn:asciiname":"Chisu-ri",
    "gn:country_code":"KP",
    "gn:dem":282,
    "gn:feature_class":"P",
    "gn:feature_code":"PPL",
    "gn:name":"Chisu-ri",
    "gn:population":0,
    "gn:timezone":"Asia/Pyongyang",
    "iso:country":"KP",
    "name:kor_x_preferred":[
        "\uc9c0\uc218\ub9ac"
    ],
    "wof:name":"Chisu-ri",
    "wof:placetype":"locality"
},
  "geometry": {"coordinates":[126.56,39.2675],"type":"Point"}
}