{
  "type": "Feature",
  "properties": {
    "gn:admin1_code":"3.0",
    "gn:asciiname":"Sangiang",
    "gn:country_code":"KP",
    "gn:dem":106,
    "gn:feature_class":"P",
    "gn:feature_code":"PPL",
    "gn:name":"Sangiang",
    "gn:population":0,
    "gn:timezone":"Asia/Pyongyang",
    "iso:country":"KP",
    "name:und_x_variant":[
        "\uc0c1\uae30\uc7a5"
    ],
    "wof:name":"Sangiang",
    "wof:placetype":"locality"
},
  "geometry": {"coordinates":[128.25583,40.21889],"type":"Point"}
}