{
  "type": "Feature",
  "properties": {
    "gn:admin1_code":"3.0",
    "gn:asciiname":"Sangiang",
    "gn:country_code":"KP",
    "gn:dem":106,
    "gn:feature_class":"P",
    "gn:feature_code":"PPL",
    "gn:name":"Sangiang",
    "gn:population":0,
    "gn:timezone":"Asia/Pyongyang",
    "iso:country":"KP",
    "name:ara_x_preferred":[
        "\u0633\u0627\u0646\u063a\u064a\u0627\u0646\u063a"
    ],
    "name:ceb_x_preferred":[
        "Pulau Sangiang"
    ],
    "name:deu_x_preferred":[
        "Sangiang"
    ],
    "name:fra_x_preferred":[
        "Sangiang"
    ],
    "name:hak_x_preferred":[
        "Sangiang"
    ],
    "name:ind_x_preferred":[
        "Pulau Sangiang"
    ],
    "name:ita_x_preferred":[
        "Sangiang"
    ],
    "name:nld_x_preferred":[
        "Sangiang"
    ],
    "name:swe_x_preferred":[
        "Pulau Sangiang"
    ],
    "name:und_x_variant":[
        "\uc0c1\uae30\uc7a5"
    ],
    "name:zho_x_preferred":[
        "\u6851\u5409\u6602\u5cf6"
    ],
    "wof:name":"Sangiang",
    "wof:placetype":"locality"
},
  "geometry": {"coordinates":[128.25583,40.21889],"type":"Point"}
}