{
  "type": "Feature",
  "properties": {
    "gn:admin1_code":"18.0",
    "gn:admin2_code":"S\u014fnbong-gun",
    "gn:asciiname":"Kalbat",
    "gn:country_code":"KP",
    "gn:dem":92,
    "gn:feature_class":"P",
    "gn:feature_code":"PPL",
    "gn:name":"Kalbat",
    "gn:population":0,
    "gn:timezone":"Asia/Pyongyang",
    "iso:country":"KP",
    "name:kor_x_preferred":[
        "\uac08\ubc2d"
    ],
    "name:und_x_variant":[
        "\uac08\ubc2d\uce58",
        "Kalch\u014fn",
        "Kalbatch\u2019i",
        "Kalbat",
        "Galbatchi",
        "Galbat"
    ],
    "wof:name":"Kalbat",
    "wof:placetype":"locality"
},
  "geometry": {"coordinates":[130.43668,42.44234],"type":"Point"}
}