{
  "type": "Feature",
  "properties": {
    "gn:admin1_code":"15.0",
    "gn:asciiname":"Kinjae",
    "gn:country_code":"KP",
    "gn:dem":143,
    "gn:feature_class":"P",
    "gn:feature_code":"PPL",
    "gn:name":"Kinjae",
    "gn:population":0,
    "gn:timezone":"Asia/Pyongyang",
    "iso:country":"KP",
    "name:kor_x_preferred":[
        "\uae34\uc7ac"
    ],
    "wof:name":"Kinjae",
    "wof:placetype":"locality"
},
  "geometry": {"coordinates":[126.20806,39.43639],"type":"Point"}
}