{
  "type": "Feature",
  "properties": {
    "gn:admin1_code":"17.0",
    "gn:asciiname":"Komamdok",
    "gn:country_code":"KP",
    "gn:dem":1149,
    "gn:feature_class":"P",
    "gn:feature_code":"PPL",
    "gn:name":"K\u014fmamd\u014fk",
    "gn:population":0,
    "gn:timezone":"Asia/Pyongyang",
    "iso:country":"KP",
    "wof:name":"Komamdok",
    "wof:placetype":"locality"
},
  "geometry": {"coordinates":[129.01667,40.83333],"type":"Point"}
}