{
  "type": "Feature",
  "properties": {
    "gn:admin1_code":"15.0",
    "gn:asciiname":"Tandunji",
    "gn:country_code":"KP",
    "gn:dem":341,
    "gn:feature_class":"P",
    "gn:feature_code":"PPL",
    "gn:name":"Tandunji",
    "gn:population":0,
    "gn:timezone":"Asia/Pyongyang",
    "iso:country":"KP",
    "name:kor_x_preferred":[
        "\ub2e8\ub454\uc9c0"
    ],
    "wof:name":"Tandunji",
    "wof:placetype":"locality"
},
  "geometry": {"coordinates":[126.57971999999999,39.37139000000001],"type":"Point"}
}