{
  "type": "Feature",
  "properties": {
    "gn:admin1_code":"7.0",
    "gn:asciiname":"Nolta-ri",
    "gn:country_code":"KP",
    "gn:dem":102,
    "gn:feature_class":"P",
    "gn:feature_code":"PPL",
    "gn:name":"N\u014flta-ri",
    "gn:population":0,
    "gn:timezone":"Asia/Pyongyang",
    "iso:country":"KP",
    "wof:name":"Nolta-ri",
    "wof:placetype":"locality"
},
  "geometry": {"coordinates":[125.92278,38.32167000000001],"type":"Point"}
}