{
  "type": "Feature",
  "properties": {
    "gn:admin1_code":"6.0",
    "gn:asciiname":"Chukch'ol-li",
    "gn:country_code":"KP",
    "gn:dem":23,
    "gn:feature_class":"P",
    "gn:feature_code":"PPL",
    "gn:name":"Chukch\u2019\u014fl-li",
    "gn:population":0,
    "gn:timezone":"Asia/Pyongyang",
    "iso:country":"KP",
    "name:und_x_variant":[
        "Chikusen-ri",
        "Chukch\u2019\u014fn-ni",
        "\uc8fd\ucc9c\ub9ac",
        "Chukch\u2019\u014fl-li"
    ],
    "wof:name":"Chukch'ol-li",
    "wof:placetype":"locality"
},
  "geometry": {"coordinates":[125.38527999999999,38.12889000000001],"type":"Point"}
}