{
  "type": "Feature",
  "properties": {
    "gn:admin1_code":"17.0",
    "gn:asciiname":"Kumwol-tong",
    "gn:country_code":"KP",
    "gn:dem":108,
    "gn:feature_class":"P",
    "gn:feature_code":"PPL",
    "gn:name":"K\u016dmw\u014fl-tong",
    "gn:population":0,
    "gn:timezone":"Asia/Pyongyang",
    "iso:country":"KP",
    "name:und_x_variant":[
        "\uae08\uc6d4\ub3d9",
        "K\u016dmw\u014fl-tong"
    ],
    "wof:name":"Kumwol-tong",
    "wof:placetype":"locality"
},
  "geometry": {"coordinates":[130.16721999999999,42.7125],"type":"Point"}
}