{
  "type": "Feature",
  "properties": {
    "gn:admin1_code":"17.0",
    "gn:asciiname":"Hwangch'uk-tong",
    "gn:country_code":"KP",
    "gn:dem":114,
    "gn:feature_class":"P",
    "gn:feature_code":"PPL",
    "gn:name":"Hwangch\u2019\u016dk-tong",
    "gn:population":0,
    "gn:timezone":"Asia/Pyongyang",
    "iso:country":"KP",
    "name:eng_x_preferred":[
        "Hwangch'uk"
    ],
    "name:eng_x_variant":[
        "Hwangch'uk-tong"
    ],
    "name:und_x_variant":[
        "\ud669\uce21\ub3d9",
        "Hwangch\u2019\u016dk-tong"
    ],
    "wof:name":"Hwangch'uk",
    "wof:placetype":"locality"
},
  "geometry": {"coordinates":[129.76222000000001,41.89861],"type":"Point"}
}