{
  "type": "Feature",
  "properties": {
    "gn:admin1_code":"15.0",
    "gn:asciiname":"Ryongban",
    "gn:country_code":"KP",
    "gn:dem":530,
    "gn:feature_class":"P",
    "gn:feature_code":"PPL",
    "gn:name":"Ryongban",
    "gn:population":0,
    "gn:timezone":"Asia/Pyongyang",
    "iso:country":"KP",
    "name:kor_x_preferred":[
        "\ub8e1\ubc18"
    ],
    "name:und_x_variant":[
        "Yongban"
    ],
    "wof:name":"Ryongban",
    "wof:placetype":"locality"
},
  "geometry": {"coordinates":[126.59139,39.52222],"type":"Point"}
}