{
  "type": "Feature",
  "properties": {
    "gn:admin1_code":"11.0",
    "gn:asciiname":"Tangbong",
    "gn:country_code":"KP",
    "gn:dem":4,
    "gn:feature_class":"P",
    "gn:feature_code":"PPL",
    "gn:name":"Tangbong",
    "gn:population":0,
    "gn:timezone":"Asia/Pyongyang",
    "iso:country":"KP",
    "name:kor_x_preferred":[
        "\ub2f9\ubd09"
    ],
    "wof:name":"Tangbong",
    "wof:placetype":"locality"
},
  "geometry": {"coordinates":[124.40111,39.8975],"type":"Point"}
}