{
  "type": "Feature",
  "properties": {
    "gn:admin1_code":"3.0",
    "gn:asciiname":"Pangnuptogi",
    "gn:country_code":"KP",
    "gn:dem":574,
    "gn:feature_class":"P",
    "gn:feature_code":"PPL",
    "gn:name":"Pangn\u016dpt\u014fgi",
    "gn:population":0,
    "gn:timezone":"Asia/Pyongyang",
    "iso:country":"KP",
    "name:und_x_variant":[
        "\ubc29\ub2aa\ub355\uc774",
        "Pangn\u016dpt\u014fgi"
    ],
    "wof:name":"Pangnuptogi",
    "wof:placetype":"locality"
},
  "geometry": {"coordinates":[128.68056000000001,40.62028],"type":"Point"}
}