{
  "type": "Feature",
  "properties": {
    "gn:admin1_code":"3.0",
    "gn:asciiname":"Harop'yong",
    "gn:country_code":"KP",
    "gn:dem":209,
    "gn:feature_class":"P",
    "gn:feature_code":"PPL",
    "gn:name":"Harop\u2019y\u014fng",
    "gn:population":0,
    "gn:timezone":"Asia/Pyongyang",
    "iso:country":"KP",
    "name:und_x_variant":[
        "Harop\u2019y\u014fng",
        "\ud558\ub85c\ud3c9"
    ],
    "wof:name":"Harop'yong",
    "wof:placetype":"locality"
},
  "geometry": {"coordinates":[128.28278,40.42278],"type":"Point"}
}