{
  "type": "Feature",
  "properties": {
    "gn:admin1_code":"7.0",
    "gn:asciiname":"Kukhwa-dong",
    "gn:country_code":"KP",
    "gn:dem":118,
    "gn:feature_class":"P",
    "gn:feature_code":"PPL",
    "gn:name":"Kukhwa-dong",
    "gn:population":0,
    "gn:timezone":"Asia/Pyongyang",
    "iso:country":"KP",
    "wof:name":"Kukhwa-dong",
    "wof:placetype":"locality"
},
  "geometry": {"coordinates":[125.97944,38.2975],"type":"Point"}
}