{
  "type": "Feature",
  "properties": {
    "gn:admin1_code":"1.0",
    "gn:asciiname":"Hwaryong-ni",
    "gn:country_code":"KP",
    "gn:dem":627,
    "gn:feature_class":"P",
    "gn:feature_code":"PPL",
    "gn:name":"Hwaryong-ni",
    "gn:population":0,
    "gn:timezone":"Asia/Pyongyang",
    "iso:country":"KP",
    "name:und_x_variant":[
        "\ud654\ub8e1\ub9ac",
        "Hwaryong-ni"
    ],
    "wof:name":"Hwaryong-ni",
    "wof:placetype":"locality"
},
  "geometry": {"coordinates":[126.27222,40.51124],"type":"Point"}
}