{
  "type": "Feature",
  "properties": {
    "gn:admin1_code":"11.0",
    "gn:asciiname":"Sam-gol",
    "gn:country_code":"KP",
    "gn:dem":18,
    "gn:feature_class":"P",
    "gn:feature_code":"PPL",
    "gn:name":"Sam-gol",
    "gn:population":0,
    "gn:timezone":"Asia/Pyongyang",
    "iso:country":"KP",
    "name:und_x_variant":[
        "\uc0bc\uace8",
        "Sam-gol"
    ],
    "wof:name":"Sam-gol",
    "wof:placetype":"locality"
},
  "geometry": {"coordinates":[124.48667,40.03667],"type":"Point"}
}