{
  "type": "Feature",
  "properties": {
    "gn:admin1_code":"0.0",
    "gn:asciiname":"Hakke",
    "gn:cc2":"KP",
    "gn:country_code":"KP",
    "gn:dem":8,
    "gn:feature_class":"P",
    "gn:feature_code":"PPL",
    "gn:name":"Hakke",
    "gn:population":0,
    "gn:timezone":"Asia/Pyongyang",
    "iso:country":"KP",
    "name:kor_x_preferred":[
        "\ud559\uac8c"
    ],
    "name:und_x_variant":[
        "Hakhy\u014fn",
        "Whakhy\u014fn",
        "Hakke"
    ],
    "wof:name":"Hakke",
    "wof:placetype":"locality"
},
  "geometry": {"coordinates":[125.96666999999999,37.83333],"type":"Point"}
}