{
  "type": "Feature",
  "properties": {
    "gn:admin1_code":"0.0",
    "gn:asciiname":"Tongjang",
    "gn:country_code":"KP",
    "gn:dem":255,
    "gn:feature_class":"P",
    "gn:feature_code":"PPL",
    "gn:name":"Tongjang",
    "gn:population":0,
    "gn:timezone":"Asia/Pyongyang",
    "iso:country":"KP",
    "name:kor_x_preferred":[
        "\ub3d9\uc7a5"
    ],
    "wof:name":"Tongjang",
    "wof:placetype":"locality"
},
  "geometry": {"coordinates":[125.86667,40.76667],"type":"Point"}
}