{
  "type": "Feature",
  "properties": {
    "gn:admin1_code":"11.0",
    "gn:asciiname":"Ch'ungmak-tong",
    "gn:country_code":"KP",
    "gn:dem":33,
    "gn:feature_class":"P",
    "gn:feature_code":"PPL",
    "gn:name":"Ch\u2019ungmak-tong",
    "gn:population":0,
    "gn:timezone":"Asia/Pyongyang",
    "iso:country":"KP",
    "name:kor_x_preferred":[
        "\ucda9\ub9c9\ub3d9"
    ],
    "name:und_x_variant":[
        "Ch\u2019ungmak-tong"
    ],
    "wof:name":"Ch'ungmak-tong",
    "wof:placetype":"locality"
},
  "geometry": {"coordinates":[125.60361,39.82722],"type":"Point"}
}