{
  "type": "Feature",
  "properties": {
    "gn:admin1_code":"11.0",
    "gn:asciiname":"Taesong-dong",
    "gn:country_code":"KP",
    "gn:dem":13,
    "gn:feature_class":"P",
    "gn:feature_code":"PPL",
    "gn:name":"Taes\u014fng-dong",
    "gn:population":0,
    "gn:timezone":"Asia/Pyongyang",
    "iso:country":"KP",
    "name:kor_x_preferred":[
        "\ub300\uc131\ub3d9"
    ],
    "name:kor_x_variant":[
        "Taes\u014fng-dong"
    ],
    "wof:name":"Taesong-dong",
    "wof:placetype":"locality"
},
  "geometry": {"coordinates":[125.25111,39.66611],"type":"Point"}
}