{
  "type": "Feature",
  "properties": {
    "gn:admin1_code":"12.0",
    "gn:asciiname":"Kul-gol",
    "gn:country_code":"KP",
    "gn:dem":138,
    "gn:feature_class":"P",
    "gn:feature_code":"PPL",
    "gn:name":"Kul-gol",
    "gn:population":0,
    "gn:timezone":"Asia/Pyongyang",
    "iso:country":"KP",
    "name:und_x_variant":[
        "\uad74\uace8",
        "Kul-gol"
    ],
    "wof:name":"Kul-gol",
    "wof:placetype":"locality"
},
  "geometry": {"coordinates":[125.96972,38.79806],"type":"Point"}
}