{
  "type": "Feature",
  "properties": {
    "gn:admin1_code":"1.0",
    "gn:asciiname":"T'ojom-dong",
    "gn:country_code":"KP",
    "gn:dem":326,
    "gn:feature_class":"P",
    "gn:feature_code":"PPL",
    "gn:name":"T\u2019oj\u014fm-dong",
    "gn:population":0,
    "gn:timezone":"Asia/Pyongyang",
    "iso:country":"KP",
    "name:und_x_variant":[
        "\ud1a0\uc810\ub3d9",
        "T\u2019oj\u014fm-dong"
    ],
    "wof:name":"T'ojom-dong",
    "wof:placetype":"locality"
},
  "geometry": {"coordinates":[126.64749999999999,41.03944],"type":"Point"}
}