{
  "type": "Feature",
  "properties": {
    "gn:admin1_code":"13.0",
    "gn:asciiname":"Songdong-ni",
    "gn:cc2":"KP",
    "gn:country_code":"KP",
    "gn:dem":624,
    "gn:feature_class":"P",
    "gn:feature_code":"PPL",
    "gn:name":"S\u014fngdong-ni",
    "gn:population":0,
    "gn:timezone":"Asia/Pyongyang",
    "iso:country":"KP",
    "name:und_x_variant":[
        "Tongdong-ni",
        "S\u014fngdong-ni"
    ],
    "wof:name":"Songdong-ni",
    "wof:placetype":"locality"
},
  "geometry": {"coordinates":[127.67389,41.25861],"type":"Point"}
}