{
  "type": "Feature",
  "properties": {
    "gn:admin1_code":"7.0",
    "gn:asciiname":"Saenggum-ni",
    "gn:country_code":"KP",
    "gn:dem":161,
    "gn:feature_class":"P",
    "gn:feature_code":"PPL",
    "gn:name":"Saengg\u016dm-ni",
    "gn:population":0,
    "gn:timezone":"Asia/Pyongyang",
    "iso:country":"KP",
    "name:eng_x_preferred":[
        "Saenggum"
    ],
    "name:eng_x_variant":[
        "Saenggum-ni"
    ],
    "name:kor_x_preferred":[
        "\uc0dd\uae08\ub9ac"
    ],
    "name:kor_x_variant":[
        "Saengg\u016dm-ni"
    ],
    "wof:name":"Saenggum",
    "wof:placetype":"locality"
},
  "geometry": {"coordinates":[126.33806,38.86167],"type":"Point"}
}