{
  "type": "Feature",
  "properties": {
    "gn:admin1_code":"6.0",
    "gn:admin2_code":"Changp\u2019ung-gun",
    "gn:asciiname":"Nurumok",
    "gn:country_code":"KP",
    "gn:dem":69,
    "gn:feature_class":"P",
    "gn:feature_code":"PPL",
    "gn:name":"Nur\u016dmok",
    "gn:population":0,
    "gn:timezone":"Asia/Pyongyang",
    "iso:country":"KP",
    "wof:name":"Nurumok",
    "wof:placetype":"locality"
},
  "geometry": {"coordinates":[126.82138999999999,38.11083],"type":"Point"}
}