{
  "type": "Feature",
  "properties": {
    "gn:admin1_code":"12.0",
    "gn:asciiname":"Sangsojong-dong",
    "gn:country_code":"KP",
    "gn:dem":24,
    "gn:feature_class":"P",
    "gn:feature_code":"PPL",
    "gn:name":"Sangs\u014fj\u014fng-dong",
    "gn:population":0,
    "gn:timezone":"Asia/Pyongyang",
    "iso:country":"KP",
    "name:kor_x_preferred":[
        "\uc0c1\uc11c\uc815\ub3d9"
    ],
    "name:und_x_variant":[
        "Sangs\u014fj\u014fng-dong",
        "Sangseojeongdong"
    ],
    "wof:name":"Sangsojong-dong",
    "wof:placetype":"locality"
},
  "geometry": {"coordinates":[125.71666999999999,39.08333],"type":"Point"}
}