{
  "type": "Feature",
  "properties": {
    "gn:admin1_code":"17.0",
    "gn:asciiname":"Kajanggok",
    "gn:country_code":"KP",
    "gn:dem":260,
    "gn:feature_class":"P",
    "gn:feature_code":"PPL",
    "gn:name":"Kajanggok",
    "gn:population":0,
    "gn:timezone":"Asia/Pyongyang",
    "iso:country":"KP",
    "name:und_x_variant":[
        "\uac00\uc7a5\uace1"
    ],
    "wof:name":"Kajanggok",
    "wof:placetype":"locality"
},
  "geometry": {"coordinates":[129.92193999999998,42.9075],"type":"Point"}
}