{
  "type": "Feature",
  "properties": {
    "gn:admin1_code":"3.0",
    "gn:asciiname":"Pongyang-ni",
    "gn:country_code":"KP",
    "gn:dem":52,
    "gn:feature_class":"P",
    "gn:feature_code":"PPL",
    "gn:name":"Pongyang-ni",
    "gn:population":0,
    "gn:timezone":"Asia/Pyongyang",
    "iso:country":"KP",
    "name:eng_x_preferred":[
        "Pongyang"
    ],
    "name:eng_x_variant":[
        "Pongyang-ni"
    ],
    "name:und_x_variant":[
        "\ubd09\uc591\ub9ac",
        "Pongyang-ni"
    ],
    "wof:name":"Pongyang",
    "wof:placetype":"locality"
},
  "geometry": {"coordinates":[128.86832999999999,40.47778],"type":"Point"}
}