{
  "type": "Feature",
  "properties": {
    "gn:admin1_code":"11.0",
    "gn:asciiname":"Yongp'o-dong",
    "gn:country_code":"KP",
    "gn:dem":22,
    "gn:feature_class":"P",
    "gn:feature_code":"PPL",
    "gn:name":"Yongp\u2019o-dong",
    "gn:population":0,
    "gn:timezone":"Asia/Pyongyang",
    "iso:country":"KP",
    "name:kor_x_preferred":[
        "\uc6a9\ud3ec\ub3d9"
    ],
    "name:kor_x_variant":[
        "Yongp\u2019o-dong"
    ],
    "wof:name":"Yongp'o-dong",
    "wof:placetype":"locality"
},
  "geometry": {"coordinates":[125.22360999999999,39.70056],"type":"Point"}
}