{
  "type": "Feature",
  "properties": {
    "gn:admin1_code":"11.0",
    "gn:asciiname":"Sanggam-ni",
    "gn:country_code":"KP",
    "gn:dem":65,
    "gn:feature_class":"P",
    "gn:feature_code":"PPL",
    "gn:name":"Sanggam-ni",
    "gn:population":0,
    "gn:timezone":"Asia/Pyongyang",
    "iso:country":"KP",
    "name:kor_x_preferred":[
        "\uc0c1\uc0bc\ub9ac"
    ],
    "wof:name":"Sanggam-ni",
    "wof:placetype":"locality"
},
  "geometry": {"coordinates":[125.45305999999999,39.75694],"type":"Point"}
}