{
  "type": "Feature",
  "properties": {
    "gn:admin1_code":"0.0",
    "gn:asciiname":"Ilbongdae-dong",
    "gn:country_code":"KP",
    "gn:dem":51,
    "gn:feature_class":"P",
    "gn:feature_code":"PPL",
    "gn:name":"Ilbongdae-dong",
    "gn:population":0,
    "gn:timezone":"Asia/Pyongyang",
    "iso:country":"KP",
    "name:kor_x_preferred":[
        "\uc77c\ubd09\ub300\ub3d9"
    ],
    "name:und_x_variant":[
        "Ilbongdong-Tae-dong"
    ],
    "wof:name":"Ilbongdae-dong",
    "wof:placetype":"locality"
},
  "geometry": {"coordinates":[124.98333,39.81667],"type":"Point"}
}