{
  "type": "Feature",
  "properties": {
    "gn:admin1_code":"12.0",
    "gn:admin2_code":"Sangw\u014fn-gun",
    "gn:asciiname":"Ch'obong-ni",
    "gn:country_code":"KP",
    "gn:dem":120,
    "gn:feature_class":"P",
    "gn:feature_code":"PPL",
    "gn:name":"Ch\u2019obong-ni",
    "gn:population":0,
    "gn:timezone":"Asia/Pyongyang",
    "iso:country":"KP",
    "name:eng_x_preferred":[
        "Ch'obong"
    ],
    "name:eng_x_variant":[
        "Ch'obong-ni"
    ],
    "wof:name":"Ch'obong",
    "wof:placetype":"locality"
},
  "geometry": {"coordinates":[126.0825,38.76194],"type":"Point"}
}