{
  "type": "Feature",
  "properties": {
    "gn:admin1_code":"11.0",
    "gn:asciiname":"Ch'auryong-gol",
    "gn:country_code":"KP",
    "gn:dem":118,
    "gn:feature_class":"P",
    "gn:feature_code":"PPL",
    "gn:name":"Ch\u2019aury\u014fng-gol",
    "gn:population":0,
    "gn:timezone":"Asia/Pyongyang",
    "iso:country":"KP",
    "name:kor_x_preferred":[
        "Ch\u2019aury\u014fng-gol"
    ],
    "name:kor_x_variant":[
        "\ucc28\uc6b0\ub839\uace8"
    ],
    "name:und_x_variant":[
        "Ch\u2019aury\u014fnggok"
    ],
    "wof:name":"Ch'auryong-gol",
    "wof:placetype":"locality"
},
  "geometry": {"coordinates":[124.84417000000001,39.94194],"type":"Point"}
}