{
  "type": "Feature",
  "properties": {
    "gn:admin1_code":"7.0",
    "gn:asciiname":"Kumulgae",
    "gn:country_code":"KP",
    "gn:dem":80,
    "gn:feature_class":"P",
    "gn:feature_code":"PPL",
    "gn:name":"Kumulgae",
    "gn:population":0,
    "gn:timezone":"Asia/Pyongyang",
    "iso:country":"KP",
    "name:kor_x_preferred":[
        "\uad6c\ubb3c\uac1c"
    ],
    "wof:name":"Kumulgae",
    "wof:placetype":"locality"
},
  "geometry": {"coordinates":[126.33167,38.36972],"type":"Point"}
}