{
  "type": "Feature",
  "properties": {
    "gn:admin1_code":"12.0",
    "gn:asciiname":"Ukkarae-gol",
    "gn:country_code":"KP",
    "gn:dem":34,
    "gn:feature_class":"P",
    "gn:feature_code":"PPL",
    "gn:name":"Ukkarae-gol",
    "gn:population":0,
    "gn:timezone":"Asia/Pyongyang",
    "iso:country":"KP",
    "name:und_x_variant":[
        "\uc6c3\uac00\ub798\uace8",
        "Ukkarae-gol"
    ],
    "wof:name":"Ukkarae-gol",
    "wof:placetype":"locality"
},
  "geometry": {"coordinates":[125.83389,38.93],"type":"Point"}
}