{
  "type": "Feature",
  "properties": {
    "gn:admin1_code":"7.0",
    "gn:asciiname":"Posal-li",
    "gn:country_code":"KP",
    "gn:dem":43,
    "gn:feature_class":"P",
    "gn:feature_code":"PPL",
    "gn:name":"Posal-li",
    "gn:population":0,
    "gn:timezone":"Asia/Pyongyang",
    "iso:country":"KP",
    "name:kor_x_preferred":[
        "\ubcf4\uc0b0\ub9ac"
    ],
    "wof:name":"Posal-li",
    "wof:placetype":"locality"
},
  "geometry": {"coordinates":[126.41861000000002,38.32833],"type":"Point"}
}