{
  "type": "Feature",
  "properties": {
    "gn:admin1_code":"15.0",
    "gn:asciiname":"Midongch'am",
    "gn:country_code":"KP",
    "gn:dem":70,
    "gn:feature_class":"P",
    "gn:feature_code":"PPL",
    "gn:name":"Midongch\u2019am",
    "gn:population":0,
    "gn:timezone":"Asia/Pyongyang",
    "iso:country":"KP",
    "name:kor_x_preferred":[
        "\ubbf8\ub3d9\ucc38"
    ],
    "name:und_x_variant":[
        "Midongch\u2019am"
    ],
    "wof:name":"Midongch'am",
    "wof:placetype":"locality"
},
  "geometry": {"coordinates":[125.92917,39.60111],"type":"Point"}
}