{
  "type": "Feature",
  "properties": {
    "gn:admin1_code":"11.0",
    "gn:asciiname":"Tonggyo-dong",
    "gn:country_code":"KP",
    "gn:dem":32,
    "gn:feature_class":"P",
    "gn:feature_code":"PPL",
    "gn:name":"Tonggyo-dong",
    "gn:population":0,
    "gn:timezone":"Asia/Pyongyang",
    "iso:country":"KP",
    "name:kor_x_preferred":[
        "\ub3d9\uad50\ub3d9"
    ],
    "wof:name":"Tonggyo-dong",
    "wof:placetype":"locality"
},
  "geometry": {"coordinates":[125.18000000000001,39.68722],"type":"Point"}
}