{
  "type": "Feature",
  "properties": {
    "gn:admin1_code":"15.0",
    "gn:asciiname":"Sinp'yong",
    "gn:country_code":"KP",
    "gn:dem":298,
    "gn:feature_class":"P",
    "gn:feature_code":"PPL",
    "gn:name":"Sinp\u2019y\u014fng",
    "gn:population":0,
    "gn:timezone":"Asia/Pyongyang",
    "iso:country":"KP",
    "name:und_x_variant":[
        "\uc2e0\ud3c9",
        "Sinp\u2019y\u014fng"
    ],
    "wof:name":"Sinp'yong",
    "wof:placetype":"locality"
},
  "geometry": {"coordinates":[126.54028,39.95083],"type":"Point"}
}