{
  "type": "Feature",
  "properties": {
    "gn:admin1_code":"3.0",
    "gn:asciiname":"Ha-dong",
    "gn:country_code":"KP",
    "gn:dem":137,
    "gn:feature_class":"P",
    "gn:feature_code":"PPL",
    "gn:name":"Ha-dong",
    "gn:population":0,
    "gn:timezone":"Asia/Pyongyang",
    "iso:country":"KP",
    "name:kor_x_preferred":[
        "\ud558\ub3d9"
    ],
    "wof:name":"Ha-dong",
    "wof:placetype":"locality"
},
  "geometry": {"coordinates":[127.04639,39.66472],"type":"Point"}
}