{
  "type": "Feature",
  "properties": {
    "gn:admin1_code":"6.0",
    "gn:asciiname":"Tolmo-gol",
    "gn:country_code":"KP",
    "gn:dem":23,
    "gn:feature_class":"P",
    "gn:feature_code":"PPL",
    "gn:name":"Tolmo-gol",
    "gn:population":0,
    "gn:timezone":"Asia/Pyongyang",
    "iso:country":"KP",
    "name:und_x_variant":[
        "\ub3cc\ubaa8\uace8",
        "Tolmo-gol"
    ],
    "wof:name":"Tolmo-gol",
    "wof:placetype":"locality"
},
  "geometry": {"coordinates":[125.60306,37.9475],"type":"Point"}
}