{
  "type": "Feature",
  "properties": {
    "gn:admin1_code":"3.0",
    "gn:asciiname":"Tam-dong",
    "gn:country_code":"KP",
    "gn:dem":157,
    "gn:feature_class":"P",
    "gn:feature_code":"PPL",
    "gn:name":"Tam-dong",
    "gn:population":0,
    "gn:timezone":"Asia/Pyongyang",
    "iso:country":"KP",
    "name:kor_x_preferred":[
        "\ub2f4\ub3d9"
    ],
    "wof:name":"Tam-dong",
    "wof:placetype":"locality"
},
  "geometry": {"coordinates":[126.90639,39.52472],"type":"Point"}
}