{
  "type": "Feature",
  "properties": {
    "gn:admin1_code":"11.0",
    "gn:asciiname":"Tongsang-ni",
    "gn:country_code":"KP",
    "gn:dem":35,
    "gn:feature_class":"P",
    "gn:feature_code":"PPL",
    "gn:name":"Tongsang-ni",
    "gn:population":0,
    "gn:timezone":"Asia/Pyongyang",
    "iso:country":"KP",
    "name:und_x_variant":[
        "\ub3d9\uc0c1\ub9ac",
        "Tongsang-ni"
    ],
    "wof:name":"Tongsang-ni",
    "wof:placetype":"locality"
},
  "geometry": {"coordinates":[124.62139000000001,39.97333],"type":"Point"}
}