{
  "type": "Feature",
  "properties": {
    "gn:admin1_code":"7.0",
    "gn:asciiname":"Surimi",
    "gn:country_code":"KP",
    "gn:dem":74,
    "gn:feature_class":"P",
    "gn:feature_code":"PPL",
    "gn:name":"Surimi",
    "gn:population":0,
    "gn:timezone":"Asia/Pyongyang",
    "iso:country":"KP",
    "name:und_x_variant":[
        "\uc218\ub9ac\ubbf8",
        "Surimi"
    ],
    "wof:name":"Surimi",
    "wof:placetype":"locality"
},
  "geometry": {"coordinates":[126.48999999999999,38.09583],"type":"Point"}
}