{
  "type": "Feature",
  "properties": {
    "gn:admin1_code":"7.0",
    "gn:asciiname":"Surimi",
    "gn:country_code":"KP",
    "gn:dem":74,
    "gn:feature_class":"P",
    "gn:feature_code":"PPL",
    "gn:name":"Surimi",
    "gn:population":0,
    "gn:timezone":"Asia/Pyongyang",
    "iso:country":"KP",
    "name:ara_x_preferred":[
        "\u0633\u0648\u0631\u064a\u0645\u064a"
    ],
    "name:cat_x_preferred":[
        "Surimi"
    ],
    "name:ces_x_preferred":[
        "Surimi"
    ],
    "name:dan_x_preferred":[
        "Surimi"
    ],
    "name:deu_x_preferred":[
        "Surimi"
    ],
    "name:epo_x_preferred":[
        "Surimi"
    ],
    "name:est_x_preferred":[
        "Surimi"
    ],
    "name:eus_x_preferred":[
        "Surimi"
    ],
    "name:fas_x_preferred":[
        "\u0633\u0648\u0631\u06cc\u0645\u06cc"
    ],
    "name:fin_x_preferred":[
        "Surimi"
    ],
    "name:fra_x_preferred":[
        "Surimi"
    ],
    "name:glg_x_preferred":[
        "Surimi"
    ],
    "name:ind_x_preferred":[
        "Surimi"
    ],
    "name:isl_x_preferred":[
        "Surimi"
    ],
    "name:ita_x_preferred":[
        "Surimi"
    ],
    "name:jav_x_preferred":[
        "Surimi"
    ],
    "name:jpn_x_preferred":[
        "\u9b5a\u8089\u7df4\u308a\u88fd\u54c1"
    ],
    "name:kor_x_preferred":[
        "\uace0\uae30\ud480"
    ],
    "name:lin_x_preferred":[
        "Surimi"
    ],
    "name:msa_x_preferred":[
        "Surimi"
    ],
    "name:nld_x_preferred":[
        "Surimi"
    ],
    "name:nor_x_preferred":[
        "Surimi"
    ],
    "name:pol_x_preferred":[
        "Surimi"
    ],
    "name:por_x_preferred":[
        "Surimi"
    ],
    "name:rus_x_preferred":[
        "\u0421\u0443\u0440\u0438\u043c\u0438"
    ],
    "name:scn_x_preferred":[
        "Surimi"
    ],
    "name:slk_x_preferred":[
        "Surimi"
    ],
    "name:spa_x_preferred":[
        "Surimi"
    ],
    "name:swe_x_preferred":[
        "Surimi"
    ],
    "name:tgl_x_preferred":[
        "Surimi"
    ],
    "name:tur_x_preferred":[
        "Surimi"
    ],
    "name:ukr_x_preferred":[
        "\u0421\u0443\u0440\u0456\u043c\u0456"
    ],
    "name:und_x_variant":[
        "\uc218\ub9ac\ubbf8",
        "Surimi"
    ],
    "name:vie_x_preferred":[
        "Surimi"
    ],
    "wof:name":"Surimi",
    "wof:placetype":"locality"
},
  "geometry": {"coordinates":[126.48999999999999,38.09583],"type":"Point"}
}