{
  "type": "Feature",
  "properties": {
    "gn:admin1_code":"1.0",
    "gn:asciiname":"Ongjang-dong",
    "gn:country_code":"KP",
    "gn:dem":388,
    "gn:feature_class":"P",
    "gn:feature_code":"PPL",
    "gn:name":"Ongjang-dong",
    "gn:population":0,
    "gn:timezone":"Asia/Pyongyang",
    "iso:country":"KP",
    "name:und_x_variant":[
        "\uc639\uc7a5\ub3d9",
        "Ongjang-dong"
    ],
    "wof:name":"Ongjang-dong",
    "wof:placetype":"locality"
},
  "geometry": {"coordinates":[125.77417,40.76389],"type":"Point"}
}