{
  "type": "Feature",
  "properties": {
    "gn:admin1_code":"15.0",
    "gn:admin2_code":"Pukch\u2019ang-gun",
    "gn:asciiname":"Togyol-li",
    "gn:country_code":"KP",
    "gn:dem":160,
    "gn:feature_class":"P",
    "gn:feature_code":"PPL",
    "gn:name":"T\u014fgy\u014fl-li",
    "gn:population":0,
    "gn:timezone":"Asia/Pyongyang",
    "iso:country":"KP",
    "name:und_x_variant":[
        "T\u014fgy\u014fn-ni",
        "T\u014fgy\u014fl-li"
    ],
    "wof:name":"Togyol-li",
    "wof:placetype":"locality"
},
  "geometry": {"coordinates":[126.28833,39.61611],"type":"Point"}
}