{
  "type": "Feature",
  "properties": {
    "gn:admin1_code":"7.0",
    "gn:asciiname":"Maryoul",
    "gn:country_code":"KP",
    "gn:dem":93,
    "gn:feature_class":"P",
    "gn:feature_code":"PPL",
    "gn:name":"Mary\u014ful",
    "gn:population":0,
    "gn:timezone":"Asia/Pyongyang",
    "iso:country":"KP",
    "name:kor_x_preferred":[
        "\ub9d0\uc5ec\uc6b8"
    ],
    "name:kor_x_variant":[
        "Mary\u014ful"
    ],
    "wof:name":"Maryoul",
    "wof:placetype":"locality"
},
  "geometry": {"coordinates":[126.30361000000001,38.38917],"type":"Point"}
}