{
  "type": "Feature",
  "properties": {
    "gn:admin1_code":"3.0",
    "gn:asciiname":"Araesoksok-kol",
    "gn:country_code":"KP",
    "gn:dem":471,
    "gn:feature_class":"P",
    "gn:feature_code":"PPL",
    "gn:name":"Araesoks\u014fk-kol",
    "gn:population":0,
    "gn:timezone":"Asia/Pyongyang",
    "iso:country":"KP",
    "name:und_x_variant":[
        "\uc544\ub798\uc18d\uc11d\uace8",
        "Araesoks\u014fk-kol"
    ],
    "wof:name":"Araesoksok-kol",
    "wof:placetype":"locality"
},
  "geometry": {"coordinates":[127.99917000000001,40.43333],"type":"Point"}
}