{
  "type": "Feature",
  "properties": {
    "gn:admin1_code":"17.0",
    "gn:admin2_code":"2038910",
    "gn:asciiname":"Kosam-dong",
    "gn:country_code":"KP",
    "gn:dem":660,
    "gn:feature_class":"P",
    "gn:feature_code":"PPL",
    "gn:name":"Kosam-dong",
    "gn:population":0,
    "gn:timezone":"Asia/Pyongyang",
    "iso:country":"KP",
    "wof:name":"Kosam-dong",
    "wof:placetype":"locality"
},
  "geometry": {"coordinates":[129.04972000000001,41.96028],"type":"Point"}
}