{
  "type": "Feature",
  "properties": {
    "gn:admin1_code":"17.0",
    "gn:asciiname":"An-gol",
    "gn:country_code":"KP",
    "gn:dem":15,
    "gn:feature_class":"P",
    "gn:feature_code":"PPL",
    "gn:name":"An-gol",
    "gn:population":0,
    "gn:timezone":"Asia/Pyongyang",
    "iso:country":"KP",
    "name:und_x_variant":[
        "An\u2019gok",
        "\uc548\uace8",
        "An-gol"
    ],
    "wof:name":"An-gol",
    "wof:placetype":"locality"
},
  "geometry": {"coordinates":[129.64750000000001,41.5725],"type":"Point"}
}