{
  "type": "Feature",
  "properties": {
    "gn:admin1_code":"15.0",
    "gn:admin2_code":"T\u014fkch\u2019\u014fn-si",
    "gn:asciiname":"T'ok-kol",
    "gn:country_code":"KP",
    "gn:dem":259,
    "gn:feature_class":"P",
    "gn:feature_code":"PPL",
    "gn:name":"T\u2019\u014fk-kol",
    "gn:population":0,
    "gn:timezone":"Asia/Pyongyang",
    "iso:country":"KP",
    "name:und_x_variant":[
        "T\u2019\u014f-gol",
        "T\u2019\u014fk-kol"
    ],
    "wof:name":"T'ok-kol",
    "wof:placetype":"locality"
},
  "geometry": {"coordinates":[126.14306000000001,39.71667],"type":"Point"}
}