{
  "type": "Feature",
  "properties": {
    "gn:admin1_code":"13.0",
    "gn:asciiname":"Nongsal-li",
    "gn:country_code":"KP",
    "gn:dem":937,
    "gn:feature_class":"P",
    "gn:feature_code":"PPL",
    "gn:name":"Nongsal-li",
    "gn:population":0,
    "gn:timezone":"Asia/Pyongyang",
    "iso:country":"KP",
    "wof:name":"Nongsal-li",
    "wof:placetype":"locality"
},
  "geometry": {"coordinates":[128.31222,41.60722],"type":"Point"}
}