{
  "type": "Feature",
  "properties": {
    "gn:admin1_code":"12.0",
    "gn:asciiname":"Chaesongwon",
    "gn:country_code":"KP",
    "gn:dem":13,
    "gn:feature_class":"P",
    "gn:feature_code":"PPL",
    "gn:name":"Chaesongw\u014fn",
    "gn:population":0,
    "gn:timezone":"Asia/Pyongyang",
    "iso:country":"KP",
    "name:kor_x_preferred":[
        "Chaesongw\u014fn"
    ],
    "name:kor_x_variant":[
        "\uc7ac\uc1a1\uc6d0"
    ],
    "name:und_x_variant":[
        "Jaesongwon"
    ],
    "wof:name":"Chaesongwon",
    "wof:placetype":"locality"
},
  "geometry": {"coordinates":[125.75,38.98333],"type":"Point"}
}