{
  "type": "Feature",
  "properties": {
    "gn:admin1_code":"3.0",
    "gn:asciiname":"Kaha-gol",
    "gn:country_code":"KP",
    "gn:dem":10,
    "gn:feature_class":"P",
    "gn:feature_code":"PPL",
    "gn:name":"Kaha-gol",
    "gn:population":0,
    "gn:timezone":"Asia/Pyongyang",
    "iso:country":"KP",
    "name:und_x_variant":[
        "\uac00\ud558\uace8"
    ],
    "wof:name":"Kaha-gol",
    "wof:placetype":"locality"
},
  "geometry": {"coordinates":[128.34788,40.12278],"type":"Point"}
}