{
  "type": "Feature",
  "properties": {
    "gn:admin1_code":"7.0",
    "gn:asciiname":"Chisa-dong",
    "gn:country_code":"KP",
    "gn:dem":189,
    "gn:feature_class":"P",
    "gn:feature_code":"PPL",
    "gn:name":"Chisa-dong",
    "gn:population":0,
    "gn:timezone":"Asia/Pyongyang",
    "iso:country":"KP",
    "name:kor_x_preferred":[
        "\uc9c0\uc0ac\ub3d9"
    ],
    "wof:name":"Chisa-dong",
    "wof:placetype":"locality"
},
  "geometry": {"coordinates":[126.54472,38.60611],"type":"Point"}
}