{
  "type": "Feature",
  "properties": {
    "gn:admin1_code":"15.0",
    "gn:asciiname":"Tongdangp'yong",
    "gn:country_code":"KP",
    "gn:dem":682,
    "gn:feature_class":"P",
    "gn:feature_code":"PPL",
    "gn:name":"Tongdangp\u2019y\u014fng",
    "gn:population":0,
    "gn:timezone":"Asia/Pyongyang",
    "iso:country":"KP",
    "name:und_x_variant":[
        "\ub3d9\ub2f9\ud3c9",
        "Tongdangp\u2019y\u014fng"
    ],
    "wof:name":"Tongdangp'yong",
    "wof:placetype":"locality"
},
  "geometry": {"coordinates":[126.93889,40.16583],"type":"Point"}
}