{
  "type": "Feature",
  "properties": {
    "gn:admin1_code":"15.0",
    "gn:asciiname":"Pugwon-dong",
    "gn:country_code":"KP",
    "gn:dem":73,
    "gn:feature_class":"P",
    "gn:feature_code":"PPL",
    "gn:name":"Pugw\u014fn-dong",
    "gn:population":0,
    "gn:timezone":"Asia/Pyongyang",
    "iso:country":"KP",
    "name:und_x_variant":[
        "W\u014fn-ni",
        "In-ri",
        "Hokuin",
        "Pugw\u014fn",
        "Pugw\u014fn-ni",
        "Pugw\u014fn-nodongjagu",
        "Pugw\u014fn-dong"
    ],
    "wof:name":"Pugwon-dong",
    "wof:placetype":"locality"
},
  "geometry": {"coordinates":[125.96028,39.77333],"type":"Point"}
}