{
  "type": "Feature",
  "properties": {
    "gn:admin1_code":"11.0",
    "gn:asciiname":"Chokho-dong",
    "gn:country_code":"KP",
    "gn:dem":169,
    "gn:feature_class":"P",
    "gn:feature_code":"PPL",
    "gn:name":"Chokho-dong",
    "gn:population":0,
    "gn:timezone":"Asia/Pyongyang",
    "iso:country":"KP",
    "name:kor_x_preferred":[
        "\uc871\ud638\ub3d9"
    ],
    "wof:name":"Chokho-dong",
    "wof:placetype":"locality"
},
  "geometry": {"coordinates":[125.97083000000001,39.84778],"type":"Point"}
}