{
  "type": "Feature",
  "properties": {
    "gn:admin1_code":"3.0",
    "gn:asciiname":"Songnyong-ni",
    "gn:country_code":"KP",
    "gn:dem":4,
    "gn:feature_class":"P",
    "gn:feature_code":"PPL",
    "gn:name":"Songny\u014fng-ni",
    "gn:population":0,
    "gn:timezone":"Asia/Pyongyang",
    "iso:country":"KP",
    "name:und_x_variant":[
        "Sh\u014frei-ri",
        "\uc1a1\ub839\ub9ac",
        "Songny\u014fng-ni"
    ],
    "wof:name":"Songnyong-ni",
    "wof:placetype":"locality"
},
  "geometry": {"coordinates":[128.01249999999999,40.05667],"type":"Point"}
}