{
  "type": "Feature",
  "properties": {
    "gn:admin1_code":"7.0",
    "gn:asciiname":"Simsan-dong",
    "gn:country_code":"KP",
    "gn:dem":135,
    "gn:feature_class":"P",
    "gn:feature_code":"PPL",
    "gn:name":"Simsan-dong",
    "gn:population":0,
    "gn:timezone":"Asia/Pyongyang",
    "iso:country":"KP",
    "wof:name":"Simsan-dong",
    "wof:placetype":"locality"
},
  "geometry": {"coordinates":[125.88361,38.425],"type":"Point"}
}