{
  "type": "Feature",
  "properties": {
    "gn:admin1_code":"11.0",
    "gn:asciiname":"Yangha-dong",
    "gn:country_code":"KP",
    "gn:dem":120,
    "gn:feature_class":"P",
    "gn:feature_code":"PPL",
    "gn:name":"Yangha-dong",
    "gn:population":0,
    "gn:timezone":"Asia/Pyongyang",
    "iso:country":"KP",
    "name:und_x_variant":[
        "Yangha-ri",
        "Yangha-dong"
    ],
    "wof:name":"Yangha-dong",
    "wof:placetype":"locality"
},
  "geometry": {"coordinates":[125.25611000000001,39.96889],"type":"Point"}
}