{
  "type": "Feature",
  "properties": {
    "gn:admin1_code":"11.0",
    "gn:asciiname":"Kwangsang-dong",
    "gn:country_code":"KP",
    "gn:dem":109,
    "gn:feature_class":"P",
    "gn:feature_code":"PPL",
    "gn:name":"Kwangsang-dong",
    "gn:population":0,
    "gn:timezone":"Asia/Pyongyang",
    "iso:country":"KP",
    "name:und_x_variant":[
        "\uad11\uc0c1\ub3d9",
        "Kwangsang-dong"
    ],
    "wof:name":"Kwangsang-dong",
    "wof:placetype":"locality"
},
  "geometry": {"coordinates":[124.68138999999999,39.98194],"type":"Point"}
}