{
  "type": "Feature",
  "properties": {
    "gn:admin1_code":"3.0",
    "gn:asciiname":"Yojung-ni",
    "gn:country_code":"KP",
    "gn:dem":118,
    "gn:feature_class":"P",
    "gn:feature_code":"PPL",
    "gn:name":"Yojung-ni",
    "gn:population":0,
    "gn:timezone":"Asia/Pyongyang",
    "iso:country":"KP",
    "name:und_x_variant":[
        "\uc694\uc911\ub9ac",
        "Yojung-ni"
    ],
    "wof:name":"Yojung-ni",
    "wof:placetype":"locality"
},
  "geometry": {"coordinates":[127.52722,40.19111],"type":"Point"}
}