{
  "type": "Feature",
  "properties": {
    "gn:admin1_code":"17.0",
    "gn:asciiname":"In'gol-tong",
    "gn:country_code":"KP",
    "gn:dem":8,
    "gn:feature_class":"P",
    "gn:feature_code":"PPL",
    "gn:name":"In\u2019gol-tong",
    "gn:population":0,
    "gn:timezone":"Asia/Pyongyang",
    "iso:country":"KP",
    "name:und_x_variant":[
        "Inkol-tong",
        "In\u2019gok-tong",
        "\uc778\uace8\ub3d9",
        "In\u2019gol-tong"
    ],
    "wof:name":"In'gol-tong",
    "wof:placetype":"locality"
},
  "geometry": {"coordinates":[129.77583000000001,41.80861],"type":"Point"}
}