{
  "type": "Feature",
  "properties": {
    "gn:admin1_code":"15.0",
    "gn:asciiname":"Yegye-gol",
    "gn:country_code":"KP",
    "gn:dem":22,
    "gn:feature_class":"P",
    "gn:feature_code":"PPL",
    "gn:name":"Yegye-gol",
    "gn:population":0,
    "gn:timezone":"Asia/Pyongyang",
    "iso:country":"KP",
    "name:und_x_variant":[
        "Yegye-ri",
        "Yegye-gol"
    ],
    "wof:name":"Yegye-gol",
    "wof:placetype":"locality"
},
  "geometry": {"coordinates":[125.46944000000001,39.17639000000001],"type":"Point"}
}