{
  "type": "Feature",
  "properties": {
    "gn:admin1_code":"9.0",
    "gn:admin2_code":"Ch\u2019angdo-gun",
    "gn:asciiname":"Nonam-ni",
    "gn:country_code":"KP",
    "gn:dem":359,
    "gn:feature_class":"P",
    "gn:feature_code":"PPL",
    "gn:name":"Nonam-ni",
    "gn:population":0,
    "gn:timezone":"Asia/Pyongyang",
    "iso:country":"KP",
    "wof:name":"Nonam-ni",
    "wof:placetype":"locality"
},
  "geometry": {"coordinates":[127.72972,38.46139],"type":"Point"}
}