{
  "type": "Feature",
  "properties": {
    "gn:admin1_code":"3.0",
    "gn:asciiname":"P'yong-ch'on",
    "gn:country_code":"KP",
    "gn:dem":24,
    "gn:feature_class":"P",
    "gn:feature_code":"PPL",
    "gn:name":"P\u2019y\u014fng-ch\u2019on",
    "gn:population":0,
    "gn:timezone":"Asia/Pyongyang",
    "iso:country":"KP",
    "name:und_x_variant":[
        "\ud3c9\ucd0c",
        "P\u2019y\u014fng-ch\u2019on"
    ],
    "wof:name":"P'yong-ch'on",
    "wof:placetype":"locality"
},
  "geometry": {"coordinates":[128.96861000000001,40.53333],"type":"Point"}
}