{
  "type": "Feature",
  "properties": {
    "gn:admin1_code":"6.0",
    "gn:asciiname":"Sangmyo-dong",
    "gn:country_code":"KP",
    "gn:dem":94,
    "gn:feature_class":"P",
    "gn:feature_code":"PPL",
    "gn:name":"Sangmyo-dong",
    "gn:population":0,
    "gn:timezone":"Asia/Pyongyang",
    "iso:country":"KP",
    "name:kor_x_preferred":[
        "\uc0c1\ubb18\ub3d9"
    ],
    "wof:name":"Sangmyo-dong",
    "wof:placetype":"locality"
},
  "geometry": {"coordinates":[125.325,38.43861],"type":"Point"}
}