{
  "type": "Feature",
  "properties": {
    "gn:admin1_code":"1.0",
    "gn:asciiname":"Yonjom-dong",
    "gn:country_code":"KP",
    "gn:dem":1097,
    "gn:feature_class":"P",
    "gn:feature_code":"PPL",
    "gn:name":"Y\u014fnj\u014fm-dong",
    "gn:population":0,
    "gn:timezone":"Asia/Pyongyang",
    "iso:country":"KP",
    "name:kor_x_preferred":[
        "\uc5f0\uc810\ub3d9"
    ],
    "name:kor_x_variant":[
        "Y\u014fnj\u014fm-dong"
    ],
    "wof:name":"Yonjom-dong",
    "wof:placetype":"locality"
},
  "geometry": {"coordinates":[127.01139000000001,40.94528],"type":"Point"}
}