{
  "type": "Feature",
  "properties": {
    "gn:admin1_code":"15.0",
    "gn:asciiname":"Kunyu-dong",
    "gn:country_code":"KP",
    "gn:dem":123,
    "gn:feature_class":"P",
    "gn:feature_code":"PPL",
    "gn:name":"Kunyu-dong",
    "gn:population":0,
    "gn:timezone":"Asia/Pyongyang",
    "iso:country":"KP",
    "wof:name":"Kunyu-dong",
    "wof:placetype":"locality"
},
  "geometry": {"coordinates":[125.84028000000001,39.26972],"type":"Point"}
}