{
  "type": "Feature",
  "properties": {
    "gn:admin1_code":"6.0",
    "gn:asciiname":"Sin'gok-tong",
    "gn:country_code":"KP",
    "gn:dem":24,
    "gn:feature_class":"P",
    "gn:feature_code":"PPL",
    "gn:name":"Sin\u2019gok-tong",
    "gn:population":0,
    "gn:timezone":"Asia/Pyongyang",
    "iso:country":"KP",
    "name:eng_x_preferred":[
        "Sin'gok"
    ],
    "name:eng_x_variant":[
        "Sin'gok-tong"
    ],
    "wof:name":"Sin'gok",
    "wof:placetype":"locality"
},
  "geometry": {"coordinates":[125.33056000000001,38.61056],"type":"Point"}
}