{
  "type": "Feature",
  "properties": {
    "gn:admin1_code":"7.0",
    "gn:asciiname":"Huam-dong",
    "gn:country_code":"KP",
    "gn:dem":107,
    "gn:feature_class":"P",
    "gn:feature_code":"PPL",
    "gn:name":"Huam-dong",
    "gn:population":0,
    "gn:timezone":"Asia/Pyongyang",
    "iso:country":"KP",
    "name:ceb_x_preferred":[
        "Huam-dong"
    ],
    "name:kor_x_preferred":[
        "\ud6c4\uc554\ub3d9"
    ],
    "name:swe_x_preferred":[
        "Huam-dong"
    ],
    "name:vie_x_preferred":[
        "Huam-dong"
    ],
    "name:zho_x_preferred":[
        "\u539a\u5ca9\u6d1e"
    ],
    "wof:name":"Huam-dong",
    "wof:placetype":"locality"
},
  "geometry": {"coordinates":[126.13667,38.45972],"type":"Point"}
}