{
  "type": "Feature",
  "properties": {
    "gn:admin1_code":"17.0",
    "gn:asciiname":"Homangnyong",
    "gn:country_code":"KP",
    "gn:dem":491,
    "gn:feature_class":"P",
    "gn:feature_code":"PPL",
    "gn:name":"Homangny\u014fng",
    "gn:population":0,
    "gn:timezone":"Asia/Pyongyang",
    "iso:country":"KP",
    "name:und_x_variant":[
        "\ud638\ub9dd\ub839",
        "Homangny\u014fng"
    ],
    "wof:name":"Homangnyong",
    "wof:placetype":"locality"
},
  "geometry": {"coordinates":[129.82917,42.66611],"type":"Point"}
}