{
  "type": "Feature",
  "properties": {
    "gn:admin1_code":"7.0",
    "gn:admin2_code":"Y\u014fnsan-gun",
    "gn:asciiname":"Yongdu-ri",
    "gn:country_code":"KP",
    "gn:dem":101,
    "gn:feature_class":"P",
    "gn:feature_code":"PPL",
    "gn:name":"Yongdu-ri",
    "gn:population":0,
    "gn:timezone":"Asia/Pyongyang",
    "iso:country":"KP",
    "wof:name":"Yongdu-ri",
    "wof:placetype":"locality"
},
  "geometry": {"coordinates":[126.27722,38.89222],"type":"Point"}
}