{
  "type": "Feature",
  "properties": {
    "gn:admin1_code":"6.0",
    "gn:admin2_code":"Ch'ongdan-gun",
    "gn:asciiname":"Hwasal-li",
    "gn:cc2":"KP",
    "gn:country_code":"KP",
    "gn:dem":37,
    "gn:feature_class":"P",
    "gn:feature_code":"PPL",
    "gn:name":"Hwasal-li",
    "gn:population":0,
    "gn:timezone":"Asia/Pyongyang",
    "iso:country":"KP",
    "name:kor_x_preferred":[
        "\ud654\uc0b0\ub9ac"
    ],
    "name:und_x_variant":[
        "Hwasan-ni",
        "Hwasal-li"
    ],
    "wof:name":"Hwasal-li",
    "wof:placetype":"locality"
},
  "geometry": {"coordinates":[125.88222,37.97417],"type":"Point"}
}