{
  "type": "Feature",
  "properties": {
    "gn:admin1_code":"7.0",
    "gn:asciiname":"Manbu-gol",
    "gn:country_code":"KP",
    "gn:dem":28,
    "gn:feature_class":"P",
    "gn:feature_code":"PPL",
    "gn:name":"Manbu-gol",
    "gn:population":0,
    "gn:timezone":"Asia/Pyongyang",
    "iso:country":"KP",
    "name:und_x_variant":[
        "\ub9cc\ubd80\uace8",
        "Manbu-gol"
    ],
    "wof:name":"Manbu-gol",
    "wof:placetype":"locality"
},
  "geometry": {"coordinates":[126.47750000000001,38.17778],"type":"Point"}
}