{
  "type": "Feature",
  "properties": {
    "gn:admin1_code":"7.0",
    "gn:asciiname":"Sahyol-li",
    "gn:country_code":"KP",
    "gn:dem":25,
    "gn:feature_class":"P",
    "gn:feature_code":"PPL",
    "gn:name":"Sahy\u014fl-li",
    "gn:population":0,
    "gn:timezone":"Asia/Pyongyang",
    "iso:country":"KP",
    "name:kor_x_preferred":[
        "\uc0ac\ud604\ub9ac"
    ],
    "name:kor_x_variant":[
        "Sahy\u014fl-li"
    ],
    "wof:name":"Sahyol-li",
    "wof:placetype":"locality"
},
  "geometry": {"coordinates":[125.53417,38.50444],"type":"Point"}
}