{
  "type": "Feature",
  "properties": {
    "gn:admin1_code":"7.0",
    "gn:asciiname":"Kalchae-ri",
    "gn:country_code":"KP",
    "gn:dem":129,
    "gn:feature_class":"P",
    "gn:feature_code":"PPL",
    "gn:name":"Kalchae-ri",
    "gn:population":0,
    "gn:timezone":"Asia/Pyongyang",
    "iso:country":"KP",
    "name:kor_x_preferred":[
        "\uac08\uc7ac\ub9ac"
    ],
    "wof:name":"Kalchae-ri",
    "wof:placetype":"locality"
},
  "geometry": {"coordinates":[126.42167000000001,38.71222],"type":"Point"}
}