{
  "type": "Feature",
  "properties": {
    "gn:admin1_code":"3.0",
    "gn:admin2_code":"Tanch'\u014fn-si",
    "gn:asciiname":"Madogijang",
    "gn:country_code":"KP",
    "gn:dem":931,
    "gn:feature_class":"P",
    "gn:feature_code":"PPL",
    "gn:name":"Mad\u014fgijang",
    "gn:population":0,
    "gn:timezone":"Asia/Pyongyang",
    "iso:country":"KP",
    "name:und_x_variant":[
        "\ub9c8\ub355\uc774\uc7a5",
        "Mad\u014fgijang"
    ],
    "wof:name":"Madogijang",
    "wof:placetype":"locality"
},
  "geometry": {"coordinates":[128.87056000000001,40.97889],"type":"Point"}
}