{
  "type": "Feature",
  "properties": {
    "gn:admin1_code":"6.0",
    "gn:asciiname":"Chungsaengwang",
    "gn:country_code":"KP",
    "gn:dem":100,
    "gn:feature_class":"P",
    "gn:feature_code":"PPL",
    "gn:name":"Chungsaengwang",
    "gn:population":0,
    "gn:timezone":"Asia/Pyongyang",
    "iso:country":"KP",
    "name:kor_x_preferred":[
        "\uc911\uc0dd\uc655"
    ],
    "wof:name":"Chungsaengwang",
    "wof:placetype":"locality"
},
  "geometry": {"coordinates":[125.11667,38.38333],"type":"Point"}
}