{
  "type": "Feature",
  "properties": {
    "gn:admin1_code":"17.0",
    "gn:asciiname":"Suso-dong",
    "gn:country_code":"KP",
    "gn:dem":19,
    "gn:feature_class":"P",
    "gn:feature_code":"PPL",
    "gn:name":"Sus\u014f-dong",
    "gn:population":0,
    "gn:timezone":"Asia/Pyongyang",
    "iso:country":"KP",
    "name:und_x_variant":[
        "\uc218\uc11c\ub3d9",
        "Sus\u014f-dong"
    ],
    "wof:name":"Suso-dong",
    "wof:placetype":"locality"
},
  "geometry": {"coordinates":[129.45221999999998,40.86194],"type":"Point"}
}