{
  "type": "Feature",
  "properties": {
    "gn:admin1_code":"7.0",
    "gn:asciiname":"Imun-dong",
    "gn:country_code":"KP",
    "gn:dem":146,
    "gn:feature_class":"P",
    "gn:feature_code":"PPL",
    "gn:name":"Imun-dong",
    "gn:population":0,
    "gn:timezone":"Asia/Pyongyang",
    "iso:country":"KP",
    "name:fas_x_preferred":[
        "\u0627\u06cc\u0645\u0648\u0646-\u062f\u0648\u0646\u06af"
    ],
    "name:kor_x_preferred":[
        "\uc774\ubb38\ub3d9"
    ],
    "name:msa_x_preferred":[
        "Imun-dong"
    ],
    "name:vie_x_preferred":[
        "Imun-dong"
    ],
    "wof:name":"Imun-dong",
    "wof:placetype":"locality"
},
  "geometry": {"coordinates":[126.21889,38.68556],"type":"Point"}
}