{
  "type": "Feature",
  "properties": {
    "gn:admin1_code":"3.0",
    "gn:asciiname":"Sanggokt'an",
    "gn:country_code":"KP",
    "gn:dem":273,
    "gn:feature_class":"P",
    "gn:feature_code":"PPL",
    "gn:name":"Sanggokt\u2019an",
    "gn:population":0,
    "gn:timezone":"Asia/Pyongyang",
    "iso:country":"KP",
    "name:und_x_variant":[
        "\uc0c1\uace1\ud0c4",
        "Sanggokt\u2019an"
    ],
    "wof:name":"Sanggokt'an",
    "wof:placetype":"locality"
},
  "geometry": {"coordinates":[126.84111,39.71917],"type":"Point"}
}