{
  "type": "Feature",
  "properties": {
    "gn:admin1_code":"6.0",
    "gn:asciiname":"Tolmol",
    "gn:country_code":"KP",
    "gn:dem":94,
    "gn:feature_class":"P",
    "gn:feature_code":"PPL",
    "gn:name":"Tolmol",
    "gn:population":0,
    "gn:timezone":"Asia/Pyongyang",
    "iso:country":"KP",
    "name:kor_x_preferred":[
        "\ub3cc\ubab0"
    ],
    "wof:name":"Tolmol",
    "wof:placetype":"locality"
},
  "geometry": {"coordinates":[126.08444,38.14528],"type":"Point"}
}