{
  "type": "Feature",
  "properties": {
    "gn:admin1_code":"17.0",
    "gn:asciiname":"Naewon-dong",
    "gn:cc2":"KP",
    "gn:country_code":"KP",
    "gn:dem":234,
    "gn:feature_class":"P",
    "gn:feature_code":"PPL",
    "gn:name":"Naew\u014fn-dong",
    "gn:population":0,
    "gn:timezone":"Asia/Pyongyang",
    "iso:country":"KP",
    "name:und_x_variant":[
        "Naew\u014fn-gol",
        "\ub0b4\uc6d0\ub3d9",
        "Naew\u014fn-dong"
    ],
    "wof:name":"Naewon-dong",
    "wof:placetype":"locality"
},
  "geometry": {"coordinates":[129.61028000000002,41.08167],"type":"Point"}
}