{
  "type": "Feature",
  "properties": {
    "gn:admin1_code":"6.0",
    "gn:asciiname":"Soksuam",
    "gn:country_code":"KP",
    "gn:dem":67,
    "gn:feature_class":"P",
    "gn:feature_code":"PPL",
    "gn:name":"S\u014fksuam",
    "gn:population":0,
    "gn:timezone":"Asia/Pyongyang",
    "iso:country":"KP",
    "name:kor_x_preferred":[
        "\uc11d\uc218\uc554"
    ],
    "name:und_x_variant":[
        "S\u014fksuam"
    ],
    "wof:name":"Soksuam",
    "wof:placetype":"locality"
},
  "geometry": {"coordinates":[125.39472000000001,38.06444000000001],"type":"Point"}
}