{
  "type": "Feature",
  "properties": {
    "gn:admin1_code":"7.0",
    "gn:asciiname":"Oduk-tong",
    "gn:country_code":"KP",
    "gn:dem":96,
    "gn:feature_class":"P",
    "gn:feature_code":"PPL",
    "gn:name":"\u014ed\u016dk-tong",
    "gn:population":0,
    "gn:timezone":"Asia/Pyongyang",
    "iso:country":"KP",
    "wof:name":"Oduk-tong",
    "wof:placetype":"locality"
},
  "geometry": {"coordinates":[126.09778,38.42111],"type":"Point"}
}