{
  "type": "Feature",
  "properties": {
    "gn:admin1_code":"9.0",
    "gn:asciiname":"Talban-ni",
    "gn:country_code":"KP",
    "gn:dem":479,
    "gn:feature_class":"P",
    "gn:feature_code":"PPL",
    "gn:name":"Talban-ni",
    "gn:population":0,
    "gn:timezone":"Asia/Pyongyang",
    "iso:country":"KP",
    "name:eng_x_preferred":[
        "Talban"
    ],
    "name:eng_x_variant":[
        "Talban-ni"
    ],
    "name:und_x_variant":[
        "\ub2ec\ubc2d\ub9ac",
        "Talban-ni"
    ],
    "wof:name":"Talban",
    "wof:placetype":"locality"
},
  "geometry": {"coordinates":[127.77028,38.79806],"type":"Point"}
}