{
  "type": "Feature",
  "properties": {
    "gn:admin1_code":"3.0",
    "gn:asciiname":"Sonaji",
    "gn:country_code":"KP",
    "gn:dem":317,
    "gn:feature_class":"P",
    "gn:feature_code":"PPL",
    "gn:name":"Sonaji",
    "gn:population":0,
    "gn:timezone":"Asia/Pyongyang",
    "iso:country":"KP",
    "name:und_x_variant":[
        "\uc190\uc544\uc9c0",
        "Sonaji"
    ],
    "wof:name":"Sonaji",
    "wof:placetype":"locality"
},
  "geometry": {"coordinates":[127.20667,39.96528],"type":"Point"}
}