{
  "type": "Feature",
  "properties": {
    "gn:admin1_code":"15.0",
    "gn:asciiname":"Yongch'on-dong",
    "gn:country_code":"KP",
    "gn:dem":75,
    "gn:feature_class":"P",
    "gn:feature_code":"PPL",
    "gn:name":"Yongch\u2019\u014fn-dong",
    "gn:population":0,
    "gn:timezone":"Asia/Pyongyang",
    "iso:country":"KP",
    "name:und_x_variant":[
        "Yongj\u014fng-dong",
        "Yongch\u2019\u014fn-dong"
    ],
    "wof:name":"Yongch'on-dong",
    "wof:placetype":"locality"
},
  "geometry": {"coordinates":[125.89861000000001,39.30528],"type":"Point"}
}