{
  "type": "Feature",
  "properties": {
    "gn:admin1_code":"3.0",
    "gn:asciiname":"Kusang-ni",
    "gn:country_code":"KP",
    "gn:dem":236,
    "gn:feature_class":"P",
    "gn:feature_code":"PPL",
    "gn:name":"Kusang-ni",
    "gn:population":0,
    "gn:timezone":"Asia/Pyongyang",
    "iso:country":"KP",
    "name:und_x_variant":[
        "\uad6c\uc0c1\ub9ac",
        "Kusang-ni"
    ],
    "wof:name":"Kusang-ni",
    "wof:placetype":"locality"
},
  "geometry": {"coordinates":[127.69806,40.10333],"type":"Point"}
}