{
  "type": "Feature",
  "properties": {
    "gn:admin1_code":"13.0",
    "gn:admin2_code":"Paegam-gun",
    "gn:asciiname":"Wonbong-nodongjagu",
    "gn:cc2":"KP",
    "gn:country_code":"KP",
    "gn:dem":928,
    "gn:feature_class":"P",
    "gn:feature_code":"PPL",
    "gn:name":"W\u014fnbong-nodongjagu",
    "gn:population":0,
    "gn:timezone":"Asia/Pyongyang",
    "iso:country":"KP",
    "name:kor_x_preferred":[
        "\uc6d0\ubd09\ub85c\ub3d9\uc790\uad6c"
    ],
    "name:und_x_variant":[
        "W\u014fnbong-ni",
        "W\u014fnbong",
        "W\u014fnbong-nodongjagu"
    ],
    "wof:name":"Wonbong-nodongjagu",
    "wof:placetype":"locality"
},
  "geometry": {"coordinates":[128.82721999999998,41.875],"type":"Point"}
}