{
  "type": "Feature",
  "properties": {
    "gn:admin1_code":"17.0",
    "gn:asciiname":"Un'gong-ni",
    "gn:country_code":"KP",
    "gn:dem":3,
    "gn:feature_class":"P",
    "gn:feature_code":"PPLL",
    "gn:name":"Un\u2019gong-ni",
    "gn:population":0,
    "gn:timezone":"Asia/Pyongyang",
    "iso:country":"KP",
    "name:eng_x_preferred":[
        "Un'gong"
    ],
    "name:eng_x_variant":[
        "Un'gong-ni"
    ],
    "name:und_x_variant":[
        "Un\u2019gok-tong",
        "\uc6b4\uace1\ub9ac",
        "Un\u2019gong-ni"
    ],
    "wof:name":"Un'gong",
    "wof:placetype":"locality"
},
  "geometry": {"coordinates":[129.65360999999999,41.4775],"type":"Point"}
}