{
  "type": "Feature",
  "properties": {
    "gn:admin1_code":"17.0",
    "gn:asciiname":"Tomak-tong",
    "gn:country_code":"KP",
    "gn:dem":341,
    "gn:feature_class":"P",
    "gn:feature_code":"PPL",
    "gn:name":"Tomak-tong",
    "gn:population":0,
    "gn:timezone":"Asia/Pyongyang",
    "iso:country":"KP",
    "name:und_x_variant":[
        "\ub3c4\ub9c9\ub3d9",
        "Tomak-tong"
    ],
    "wof:name":"Tomak-tong",
    "wof:placetype":"locality"
},
  "geometry": {"coordinates":[129.94083000000001,42.42],"type":"Point"}
}