{
  "type": "Feature",
  "properties": {
    "gn:admin1_code":"15.0",
    "gn:asciiname":"Tongsanmol",
    "gn:cc2":"KP",
    "gn:country_code":"KP",
    "gn:dem":44,
    "gn:feature_class":"P",
    "gn:feature_code":"PPL",
    "gn:name":"Tongsanmol",
    "gn:population":0,
    "gn:timezone":"Asia/Pyongyang",
    "iso:country":"KP",
    "name:und_x_variant":[
        "Tongsanch\u2019on",
        "\ub3d9\uc0b0\ubab0",
        "Tongsanmol"
    ],
    "wof:name":"Tongsanmol",
    "wof:placetype":"locality"
},
  "geometry": {"coordinates":[125.33083000000001,38.92972],"type":"Point"}
}