{
  "type": "Feature",
  "properties": {
    "gn:admin1_code":"7.0",
    "gn:asciiname":"Ch'uchil-li",
    "gn:country_code":"KP",
    "gn:dem":29,
    "gn:feature_class":"P",
    "gn:feature_code":"PPL",
    "gn:name":"Ch\u2019uchil-li",
    "gn:population":0,
    "gn:timezone":"Asia/Pyongyang",
    "iso:country":"KP",
    "wof:name":"Ch'uchil-li",
    "wof:placetype":"locality"
},
  "geometry": {"coordinates":[125.73860999999999,38.455],"type":"Point"}
}