{
  "type": "Feature",
  "properties": {
    "gn:admin1_code":"17.0",
    "gn:admin2_code":"Hwadae-gun",
    "gn:asciiname":"No-dong",
    "gn:country_code":"KP",
    "gn:dem":12,
    "gn:feature_class":"P",
    "gn:feature_code":"PPL",
    "gn:name":"No-dong",
    "gn:population":0,
    "gn:timezone":"Asia/Pyongyang",
    "iso:country":"KP",
    "name:und_x_variant":[
        "Ro-d\u014d",
        "\ub178\ub3d9",
        "No-dong"
    ],
    "wof:name":"No-dong",
    "wof:placetype":"locality"
},
  "geometry": {"coordinates":[129.65611000000001,40.85056],"type":"Point"}
}