{
  "type": "Feature",
  "properties": {
    "gn:admin1_code":"6.0",
    "gn:asciiname":"Hojaemal",
    "gn:country_code":"KP",
    "gn:dem":25,
    "gn:feature_class":"P",
    "gn:feature_code":"PPL",
    "gn:name":"H\u014fjaemal",
    "gn:population":0,
    "gn:timezone":"Asia/Pyongyang",
    "iso:country":"KP",
    "name:und_x_variant":[
        "\ud5c8\uc7ac\ub9d0",
        "H\u014fjaemal"
    ],
    "wof:name":"Hojaemal",
    "wof:placetype":"locality"
},
  "geometry": {"coordinates":[126.42638999999998,38.1525],"type":"Point"}
}