{
  "type": "Feature",
  "properties": {
    "gn:admin1_code":"13.0",
    "gn:asciiname":"Hoesal-li",
    "gn:country_code":"KP",
    "gn:dem":1278,
    "gn:feature_class":"P",
    "gn:feature_code":"PPL",
    "gn:name":"Hoesal-li",
    "gn:population":0,
    "gn:timezone":"Asia/Pyongyang",
    "iso:country":"KP",
    "wof:name":"Hoesal-li",
    "wof:placetype":"locality"
},
  "geometry": {"coordinates":[128.08082999999999,41.16417],"type":"Point"}
}