{
  "type": "Feature",
  "properties": {
    "gn:admin1_code":"6.0",
    "gn:asciiname":"Hwanghyon",
    "gn:country_code":"KP",
    "gn:dem":10,
    "gn:feature_class":"P",
    "gn:feature_code":"PPL",
    "gn:name":"Hwanghy\u014fn",
    "gn:population":0,
    "gn:timezone":"Asia/Pyongyang",
    "iso:country":"KP",
    "name:kor_x_preferred":[
        "\ud669\ud604"
    ],
    "name:und_x_variant":[
        "Hwanghy\u014fn"
    ],
    "wof:name":"Hwanghyon",
    "wof:placetype":"locality"
},
  "geometry": {"coordinates":[126.06638999999998,37.93972],"type":"Point"}
}