{
  "type": "Feature",
  "properties": {
    "gn:admin1_code":"12.0",
    "gn:asciiname":"Sanghanjong",
    "gn:country_code":"KP",
    "gn:dem":24,
    "gn:feature_class":"P",
    "gn:feature_code":"PPL",
    "gn:name":"Sanghanj\u014fng",
    "gn:population":0,
    "gn:timezone":"Asia/Pyongyang",
    "iso:country":"KP",
    "name:kor_x_preferred":[
        "\uc0c1\ud55c\uc815"
    ],
    "name:und_x_variant":[
        "Sanghanj\u014fng",
        "Sanghanjeong"
    ],
    "wof:name":"Sanghanjong",
    "wof:placetype":"locality"
},
  "geometry": {"coordinates":[125.67167000000001,38.89583],"type":"Point"}
}