{
  "type": "Feature",
  "properties": {
    "gn:admin1_code":"15.0",
    "gn:asciiname":"Tolmae",
    "gn:country_code":"KP",
    "gn:dem":414,
    "gn:feature_class":"P",
    "gn:feature_code":"PPL",
    "gn:name":"Tolmae",
    "gn:population":0,
    "gn:timezone":"Asia/Pyongyang",
    "iso:country":"KP",
    "name:und_x_variant":[
        "\ub3cc\ub9e4",
        "Tolmae"
    ],
    "wof:name":"Tolmae",
    "wof:placetype":"locality"
},
  "geometry": {"coordinates":[126.81917,39.22611],"type":"Point"}
}