{
  "type": "Feature",
  "properties": {
    "gn:admin1_code":"17.0",
    "gn:asciiname":"Tat'ap-kol",
    "gn:country_code":"KP",
    "gn:dem":269,
    "gn:feature_class":"P",
    "gn:feature_code":"PPL",
    "gn:name":"Tat\u2019ap-kol",
    "gn:population":0,
    "gn:timezone":"Asia/Pyongyang",
    "iso:country":"KP",
    "name:und_x_variant":[
        "\ub2e4\ud0d1\uace8",
        "Tat\u2019ap-kol"
    ],
    "wof:name":"Tat'ap-kol",
    "wof:placetype":"locality"
},
  "geometry": {"coordinates":[129.78278,42.58306],"type":"Point"}
}