{
  "type": "Feature",
  "properties": {
    "gn:admin1_code":"11.0",
    "gn:asciiname":"Puhung-ni",
    "gn:country_code":"KP",
    "gn:dem":254,
    "gn:feature_class":"P",
    "gn:feature_code":"PPL",
    "gn:name":"Puh\u016dng-ni",
    "gn:population":0,
    "gn:timezone":"Asia/Pyongyang",
    "iso:country":"KP",
    "name:eng_x_preferred":[
        "Puhung"
    ],
    "name:eng_x_variant":[
        "Puhung-ni"
    ],
    "name:und_x_variant":[
        "\ubd80\ud765\ub9ac",
        "Puh\u016dng-ni"
    ],
    "wof:name":"Puhung",
    "wof:placetype":"locality"
},
  "geometry": {"coordinates":[125.69333,40.21194],"type":"Point"}
}