{
  "type": "Feature",
  "properties": {
    "gn:admin1_code":"12.0",
    "gn:asciiname":"Tang-dong",
    "gn:country_code":"KP",
    "gn:dem":20,
    "gn:feature_class":"P",
    "gn:feature_code":"PPL",
    "gn:name":"Tang-dong",
    "gn:population":0,
    "gn:timezone":"Asia/Pyongyang",
    "iso:country":"KP",
    "name:kor_x_preferred":[
        "\ub2f9\ub3d9"
    ],
    "name:und_x_variant":[
        "Dangdong"
    ],
    "wof:name":"Tang-dong",
    "wof:placetype":"locality"
},
  "geometry": {"coordinates":[125.61917,38.86333],"type":"Point"}
}