{
  "type": "Feature",
  "properties": {
    "gn:admin1_code":"6.0",
    "gn:asciiname":"Chonbung-ni",
    "gn:country_code":"KP",
    "gn:dem":4,
    "gn:feature_class":"P",
    "gn:feature_code":"PPL",
    "gn:name":"Chonbung-ni",
    "gn:population":0,
    "gn:timezone":"Asia/Pyongyang",
    "iso:country":"KP",
    "name:eng_x_preferred":[
        "Chonbung"
    ],
    "name:eng_x_variant":[
        "Chonbung-ni"
    ],
    "wof:name":"Chonbung",
    "wof:placetype":"locality"
},
  "geometry": {"coordinates":[124.97528,38.45917],"type":"Point"}
}