{
  "type": "Feature",
  "properties": {
    "gn:admin1_code":"1.0",
    "gn:asciiname":"Saewon",
    "gn:country_code":"KP",
    "gn:dem":1076,
    "gn:feature_class":"P",
    "gn:feature_code":"PPL",
    "gn:name":"Saew\u014fn",
    "gn:population":0,
    "gn:timezone":"Asia/Pyongyang",
    "iso:country":"KP",
    "name:kor_x_preferred":[
        "\uc0c8\uc6d0"
    ],
    "name:kor_x_variant":[
        "Saew\u014fn"
    ],
    "wof:name":"Saewon",
    "wof:placetype":"locality"
},
  "geometry": {"coordinates":[127.02167,40.96222],"type":"Point"}
}