{
  "type": "Feature",
  "properties": {
    "gn:admin1_code":"11.0",
    "gn:asciiname":"Yangso-ri",
    "gn:country_code":"KP",
    "gn:dem":6,
    "gn:feature_class":"P",
    "gn:feature_code":"PPL",
    "gn:name":"Yangs\u014f-ri",
    "gn:population":0,
    "gn:timezone":"Asia/Pyongyang",
    "iso:country":"KP",
    "name:und_x_variant":[
        "\uc591\uc11c\ub9ac",
        "Yangs\u014f-ri"
    ],
    "wof:name":"Yangso-ri",
    "wof:placetype":"locality"
},
  "geometry": {"coordinates":[124.40917,40.01111],"type":"Point"}
}