{
  "type": "Feature",
  "properties": {
    "gn:admin1_code":"7.0",
    "gn:asciiname":"Sumok-tong",
    "gn:country_code":"KP",
    "gn:dem":170,
    "gn:feature_class":"P",
    "gn:feature_code":"PPL",
    "gn:name":"Sumok-tong",
    "gn:population":0,
    "gn:timezone":"Asia/Pyongyang",
    "iso:country":"KP",
    "name:kor_x_preferred":[
        "\uc218\ubaa9\ub3d9"
    ],
    "wof:name":"Sumok-tong",
    "wof:placetype":"locality"
},
  "geometry": {"coordinates":[126.30556,38.46722000000001],"type":"Point"}
}