{
  "type": "Feature",
  "properties": {
    "gn:admin1_code":"11.0",
    "gn:asciiname":"San-dong",
    "gn:country_code":"KP",
    "gn:dem":26,
    "gn:feature_class":"P",
    "gn:feature_code":"PPL",
    "gn:name":"San-dong",
    "gn:population":0,
    "gn:timezone":"Asia/Pyongyang",
    "iso:country":"KP",
    "name:kor_x_preferred":[
        "\uc0b0\ub3d9"
    ],
    "wof:name":"San-dong",
    "wof:placetype":"locality"
},
  "geometry": {"coordinates":[125.20806,39.65917],"type":"Point"}
}