{
  "type": "Feature",
  "properties": {
    "gn:admin1_code":"13.0",
    "gn:asciiname":"Samsang 3-dong",
    "gn:country_code":"KP",
    "gn:dem":771,
    "gn:feature_class":"P",
    "gn:feature_code":"PPL",
    "gn:name":"Samsang 3-dong",
    "gn:population":0,
    "gn:timezone":"Asia/Pyongyang",
    "iso:country":"KP",
    "wof:name":"Samsang 3-dong",
    "wof:placetype":"locality"
},
  "geometry": {"coordinates":[128.91943999999998,42.01028],"type":"Point"}
}