{
  "type": "Feature",
  "properties": {
    "gn:admin1_code":"11.0",
    "gn:asciiname":"Yonganch'am",
    "gn:country_code":"KP",
    "gn:dem":95,
    "gn:feature_class":"P",
    "gn:feature_code":"PPL",
    "gn:name":"Yonganch\u2019am",
    "gn:population":0,
    "gn:timezone":"Asia/Pyongyang",
    "iso:country":"KP",
    "name:und_x_variant":[
        "\uc6a9\uc548\ucc38",
        "Yonganch\u2019am"
    ],
    "wof:name":"Yonganch'am",
    "wof:placetype":"locality"
},
  "geometry": {"coordinates":[126.16194,40.00861],"type":"Point"}
}