{
  "type": "Feature",
  "properties": {
    "gn:admin1_code":"6.0",
    "gn:asciiname":"Chinhae-ri",
    "gn:country_code":"KP",
    "gn:dem":11,
    "gn:feature_class":"P",
    "gn:feature_code":"PPL",
    "gn:name":"Chinhae-ri",
    "gn:population":0,
    "gn:timezone":"Asia/Pyongyang",
    "iso:country":"KP",
    "name:kor_x_preferred":[
        "\uc9c4\ud574\ub9ac"
    ],
    "wof:name":"Chinhae-ri",
    "wof:placetype":"locality"
},
  "geometry": {"coordinates":[125.26278000000001,38.01417],"type":"Point"}
}