{
  "type": "Feature",
  "properties": {
    "gn:admin1_code":"7.0",
    "gn:asciiname":"Hahap-tong",
    "gn:country_code":"KP",
    "gn:dem":150,
    "gn:feature_class":"P",
    "gn:feature_code":"PPL",
    "gn:name":"Hahap-tong",
    "gn:population":0,
    "gn:timezone":"Asia/Pyongyang",
    "iso:country":"KP",
    "name:eng_x_preferred":[
        "Hahap"
    ],
    "name:eng_x_variant":[
        "Hahap-tong"
    ],
    "name:kor_x_preferred":[
        "\ud558\ud569\ub3d9"
    ],
    "wof:name":"Hahap",
    "wof:placetype":"locality"
},
  "geometry": {"coordinates":[126.36306,38.54472],"type":"Point"}
}