{
  "type": "Feature",
  "properties": {
    "gn:admin1_code":"7.0",
    "gn:asciiname":"Pangun-dong",
    "gn:country_code":"KP",
    "gn:dem":259,
    "gn:feature_class":"P",
    "gn:feature_code":"PPL",
    "gn:name":"Pang\u016dn-dong",
    "gn:population":0,
    "gn:timezone":"Asia/Pyongyang",
    "iso:country":"KP",
    "name:kor_x_preferred":[
        "\ubc29\uc740\ub3d9"
    ],
    "name:kor_x_variant":[
        "Pang\u016dn-dong"
    ],
    "wof:name":"Pangun-dong",
    "wof:placetype":"locality"
},
  "geometry": {"coordinates":[126.56667,38.93806],"type":"Point"}
}