{
  "type": "Feature",
  "properties": {
    "gn:admin1_code":"17.0",
    "gn:asciiname":"Tonggwan-ni",
    "gn:cc2":"KP",
    "gn:country_code":"KP",
    "gn:dem":141,
    "gn:feature_class":"P",
    "gn:feature_code":"PPL",
    "gn:name":"Tonggwan-ni",
    "gn:population":0,
    "gn:timezone":"Asia/Pyongyang",
    "iso:country":"KP",
    "name:und_x_variant":[
        "Tonggwan-dong",
        "Tonggwan-ni"
    ],
    "wof:name":"Tonggwan-ni",
    "wof:placetype":"locality"
},
  "geometry": {"coordinates":[129.82806000000002,42.82778],"type":"Point"}
}