{
  "type": "Feature",
  "properties": {
    "gn:admin1_code":"3.0",
    "gn:asciiname":"Tongsan",
    "gn:country_code":"KP",
    "gn:dem":191,
    "gn:feature_class":"P",
    "gn:feature_code":"PPL",
    "gn:name":"Tongsan",
    "gn:population":0,
    "gn:timezone":"Asia/Pyongyang",
    "iso:country":"KP",
    "name:und_x_variant":[
        "\ub3d9\uc0b0",
        "Tongsan"
    ],
    "wof:name":"Tongsan",
    "wof:placetype":"locality"
},
  "geometry": {"coordinates":[128.08917,40.17306],"type":"Point"}
}