{
  "type": "Feature",
  "properties": {
    "gn:admin1_code":"6.0",
    "gn:asciiname":"Samga",
    "gn:country_code":"KP",
    "gn:dem":105,
    "gn:feature_class":"P",
    "gn:feature_code":"PPL",
    "gn:name":"Samga",
    "gn:population":0,
    "gn:timezone":"Asia/Pyongyang",
    "iso:country":"KP",
    "name:ita_x_preferred":[
        "Samga"
    ],
    "name:und_x_variant":[
        "Sankai",
        "Seg\u014fri",
        "\uc0bc\uac00",
        "Samga"
    ],
    "wof:name":"Samga",
    "wof:placetype":"locality"
},
  "geometry": {"coordinates":[125.345,38.28667],"type":"Point"}
}