{
  "type": "Feature",
  "properties": {
    "gn:admin1_code":"6.0",
    "gn:asciiname":"Changhang-gol",
    "gn:country_code":"KP",
    "gn:dem":83,
    "gn:feature_class":"P",
    "gn:feature_code":"PPL",
    "gn:name":"Changhang-gol",
    "gn:population":0,
    "gn:timezone":"Asia/Pyongyang",
    "iso:country":"KP",
    "name:und_x_variant":[
        "Changhang-dong",
        "\uc7a5\ud56d\uace8",
        "Changhang-gol"
    ],
    "wof:name":"Changhang-gol",
    "wof:placetype":"locality"
},
  "geometry": {"coordinates":[125.33750000000001,38.2075],"type":"Point"}
}