{
  "type": "Feature",
  "properties": {
    "gn:admin1_code":"9.0",
    "gn:asciiname":"Tattong-gol",
    "gn:cc2":"KP",
    "gn:country_code":"KP",
    "gn:dem":225,
    "gn:feature_class":"P",
    "gn:feature_code":"PPL",
    "gn:name":"Tattong-gol",
    "gn:population":0,
    "gn:timezone":"Asia/Pyongyang",
    "iso:country":"KP",
    "name:und_x_variant":[
        "Tattongkol",
        "Tattong-gol"
    ],
    "wof:name":"Tattong-gol",
    "wof:placetype":"locality"
},
  "geometry": {"coordinates":[127.15528,38.4675],"type":"Point"}
}