{
  "type": "Feature",
  "properties": {
    "gn:admin1_code":"17.0",
    "gn:asciiname":"Sanga-dong",
    "gn:country_code":"KP",
    "gn:dem":265,
    "gn:feature_class":"P",
    "gn:feature_code":"PPL",
    "gn:name":"Sanga-dong",
    "gn:population":0,
    "gn:timezone":"Asia/Pyongyang",
    "iso:country":"KP",
    "name:und_x_variant":[
        "\uc0c1\uc544\ub3d9",
        "Sanga-dong"
    ],
    "wof:name":"Sanga-dong",
    "wof:placetype":"locality"
},
  "geometry": {"coordinates":[129.38083,41.21944000000001],"type":"Point"}
}