{
  "type": "Feature",
  "properties": {
    "gn:admin1_code":"17.0",
    "gn:asciiname":"An'gubi",
    "gn:country_code":"KP",
    "gn:dem":655,
    "gn:feature_class":"P",
    "gn:feature_code":"PPL",
    "gn:name":"An\u2019gubi",
    "gn:population":0,
    "gn:timezone":"Asia/Pyongyang",
    "iso:country":"KP",
    "name:und_x_variant":[
        "\uc548\uad6c\ube44",
        "An\u2019gubi"
    ],
    "wof:name":"An'gubi",
    "wof:placetype":"locality"
},
  "geometry": {"coordinates":[129.42750000000001,42.10667],"type":"Point"}
}