{
  "type": "Feature",
  "properties": {
    "gn:admin1_code":"12.0",
    "gn:asciiname":"Tongsal-li",
    "gn:country_code":"KP",
    "gn:dem":16,
    "gn:feature_class":"P",
    "gn:feature_code":"PPL",
    "gn:name":"Tongsal-li",
    "gn:population":0,
    "gn:timezone":"Asia/Pyongyang",
    "iso:country":"KP",
    "name:und_x_variant":[
        "\ub3d9\uc0b0\ub9ac",
        "Tongsal-li",
        "Dongsalli"
    ],
    "wof:name":"Tongsal-li",
    "wof:placetype":"locality"
},
  "geometry": {"coordinates":[125.73222,38.91306],"type":"Point"}
}