{
  "type": "Feature",
  "properties": {
    "gn:admin1_code":"1.0",
    "gn:asciiname":"Kulgoksaemt'o",
    "gn:country_code":"KP",
    "gn:dem":484,
    "gn:feature_class":"P",
    "gn:feature_code":"PPL",
    "gn:name":"Kulgoksaemt\u2019\u014f",
    "gn:population":0,
    "gn:timezone":"Asia/Pyongyang",
    "iso:country":"KP",
    "name:kor_x_preferred":[
        "\uad74\uace1\uc0d8\ud130"
    ],
    "name:kor_x_variant":[
        "\uad74\uace8"
    ],
    "name:und_x_variant":[
        "Kul-gol",
        "Kulgoksaemt\u2019\u014f"
    ],
    "wof:name":"Kulgoksaemt'o",
    "wof:placetype":"locality"
},
  "geometry": {"coordinates":[126.47607000000001,40.6528],"type":"Point"}
}