{
  "type": "Feature",
  "properties": {
    "gn:admin1_code":"1.0",
    "gn:asciiname":"Kwangsongdongdaedong-gol",
    "gn:country_code":"KP",
    "gn:dem":1018,
    "gn:feature_class":"P",
    "gn:feature_code":"PPL",
    "gn:name":"Kwangs\u014fngdongdaedong-gol",
    "gn:population":0,
    "gn:timezone":"Asia/Pyongyang",
    "iso:country":"KP",
    "name:und_x_variant":[
        "\uad11\uc131\ub3d9\ub300\ub3d9\uace8",
        "Kwangs\u014fngdongdaedong-gol"
    ],
    "wof:name":"Kwangsongdongdaedong-gol",
    "wof:placetype":"locality"
},
  "geometry": {"coordinates":[126.84972,40.35139],"type":"Point"}
}