{
  "type": "Feature",
  "properties": {
    "gn:admin1_code":"3.0",
    "gn:asciiname":"Pidal-li",
    "gn:country_code":"KP",
    "gn:dem":22,
    "gn:feature_class":"P",
    "gn:feature_code":"PPL",
    "gn:name":"Pidal-li",
    "gn:population":0,
    "gn:timezone":"Asia/Pyongyang",
    "iso:country":"KP",
    "name:und_x_variant":[
        "\ube44\ub2e8\ub9ac",
        "Pidal-li"
    ],
    "wof:name":"Pidal-li",
    "wof:placetype":"locality"
},
  "geometry": {"coordinates":[127.23972000000001,39.56],"type":"Point"}
}