{
  "type": "Feature",
  "properties": {
    "gn:admin1_code":"7.0",
    "gn:asciiname":"Sillyang-ni",
    "gn:country_code":"KP",
    "gn:dem":41,
    "gn:feature_class":"P",
    "gn:feature_code":"PPL",
    "gn:name":"Sillyang-ni",
    "gn:population":0,
    "gn:timezone":"Asia/Pyongyang",
    "iso:country":"KP",
    "name:kor_x_preferred":[
        "\uc2e0\ub7c9\ub9ac"
    ],
    "wof:name":"Sillyang-ni",
    "wof:placetype":"locality"
},
  "geometry": {"coordinates":[125.64833,38.71944000000001],"type":"Point"}
}