{
  "type": "Feature",
  "properties": {
    "gn:admin1_code":"3.0",
    "gn:asciiname":"Namsok",
    "gn:country_code":"KP",
    "gn:dem":53,
    "gn:feature_class":"P",
    "gn:feature_code":"PPL",
    "gn:name":"Nams\u014fk",
    "gn:population":0,
    "gn:timezone":"Asia/Pyongyang",
    "iso:country":"KP",
    "wof:name":"Namsok",
    "wof:placetype":"locality"
},
  "geometry": {"coordinates":[127.38943999999999,39.61],"type":"Point"}
}