{
  "type": "Feature",
  "properties": {
    "gn:admin1_code":"9.0",
    "gn:asciiname":"Umdalmal",
    "gn:country_code":"KP",
    "gn:dem":286,
    "gn:feature_class":"P",
    "gn:feature_code":"PPL",
    "gn:name":"\u016cmdalmal",
    "gn:population":0,
    "gn:timezone":"Asia/Pyongyang",
    "iso:country":"KP",
    "name:und_x_variant":[
        "\uc74c\ub2ec\ub9d0",
        "\u016cmdalmal"
    ],
    "wof:name":"Umdalmal",
    "wof:placetype":"locality"
},
  "geometry": {"coordinates":[127.08138999999998,38.95194],"type":"Point"}
}