{
  "type": "Feature",
  "properties": {
    "gn:admin1_code":"15.0",
    "gn:admin2_code":"S\u014fngch\u2019\u014fn-gun",
    "gn:asciiname":"Majol-li",
    "gn:country_code":"KP",
    "gn:dem":133,
    "gn:feature_class":"P",
    "gn:feature_code":"PPL",
    "gn:name":"Maj\u014fl-li",
    "gn:population":0,
    "gn:timezone":"Asia/Pyongyang",
    "iso:country":"KP",
    "wof:name":"Majol-li",
    "wof:placetype":"locality"
},
  "geometry": {"coordinates":[126.29555999999999,39.22611],"type":"Point"}
}