{
  "type": "Feature",
  "properties": {
    "gn:admin1_code":"6.0",
    "gn:asciiname":"Songhyon",
    "gn:country_code":"KP",
    "gn:dem":57,
    "gn:feature_class":"P",
    "gn:feature_code":"PPL",
    "gn:name":"Songhy\u014fn",
    "gn:population":0,
    "gn:timezone":"Asia/Pyongyang",
    "iso:country":"KP",
    "wof:name":"Songhyon",
    "wof:placetype":"locality"
},
  "geometry": {"coordinates":[126.29222,38.20444000000001],"type":"Point"}
}