{
  "type": "Feature",
  "properties": {
    "gn:admin1_code":"11.0",
    "gn:asciiname":"Soenoe-dong",
    "gn:country_code":"KP",
    "gn:dem":139,
    "gn:feature_class":"P",
    "gn:feature_code":"PPL",
    "gn:name":"Soenoe-dong",
    "gn:population":0,
    "gn:timezone":"Asia/Pyongyang",
    "iso:country":"KP",
    "name:und_x_variant":[
        "Soenoegol",
        "Sonoe-gol",
        "\uc1e0\ub1cc\ub3d9",
        "Sonae-gol",
        "Soenoe-dong"
    ],
    "wof:name":"Soenoe-dong",
    "wof:placetype":"locality"
},
  "geometry": {"coordinates":[125.49417,40.04861],"type":"Point"}
}