{
  "type": "Feature",
  "properties": {
    "gn:admin1_code":"12.0",
    "gn:asciiname":"Saeyoul",
    "gn:cc2":"KP",
    "gn:country_code":"KP",
    "gn:dem":20,
    "gn:feature_class":"P",
    "gn:feature_code":"PPL",
    "gn:name":"Saey\u014ful",
    "gn:population":0,
    "gn:timezone":"Asia/Pyongyang",
    "iso:country":"KP",
    "name:kor_x_preferred":[
        "\uc0c8\uc5ec\uc6b8"
    ],
    "name:und_x_variant":[
        "K\u016dmt\u2019an-ni",
        "Saey\u014fl",
        "K\u016dmt\u2019an",
        "Saey\u014ful"
    ],
    "wof:name":"Saeyoul",
    "wof:placetype":"locality"
},
  "geometry": {"coordinates":[125.89556,39.035],"type":"Point"}
}