{
  "type": "Feature",
  "properties": {
    "gn:admin1_code":"3.0",
    "gn:asciiname":"Chungp'yong-ni",
    "gn:country_code":"KP",
    "gn:dem":226,
    "gn:feature_class":"P",
    "gn:feature_code":"PPL",
    "gn:name":"Chungp\u2019y\u014fng-ni",
    "gn:population":0,
    "gn:timezone":"Asia/Pyongyang",
    "iso:country":"KP",
    "name:eng_x_preferred":[
        "Chungp'yong"
    ],
    "name:eng_x_variant":[
        "Chungp'yong-ni"
    ],
    "name:und_x_variant":[
        "Chungp\u2019y\u014fng-ni",
        "\uc911\ud3c9\ub9ac"
    ],
    "wof:name":"Chungp'yong",
    "wof:placetype":"locality"
},
  "geometry": {"coordinates":[128.35457,40.26629],"type":"Point"}
}