{
  "type": "Feature",
  "properties": {
    "gn:admin1_code":"17.0",
    "gn:asciiname":"Pugam",
    "gn:country_code":"KP",
    "gn:dem":887,
    "gn:feature_class":"P",
    "gn:feature_code":"PPL",
    "gn:name":"Pugam",
    "gn:population":0,
    "gn:timezone":"Asia/Pyongyang",
    "iso:country":"KP",
    "name:und_x_variant":[
        "\ubd81\uc554"
    ],
    "wof:name":"Pugam",
    "wof:placetype":"locality"
},
  "geometry": {"coordinates":[129.17941999999999,41.49853],"type":"Point"}
}