{
  "type": "Feature",
  "properties": {
    "gn:admin1_code":"6.0",
    "gn:asciiname":"Chomch'on-dong",
    "gn:country_code":"KP",
    "gn:dem":105,
    "gn:feature_class":"P",
    "gn:feature_code":"PPL",
    "gn:name":"Ch\u014fmch\u2019on-dong",
    "gn:population":0,
    "gn:timezone":"Asia/Pyongyang",
    "iso:country":"KP",
    "name:kor_x_preferred":[
        "\uc810\ucd0c\ub3d9"
    ],
    "name:und_x_variant":[
        "Ch\u014fmch\u2019on-dong"
    ],
    "wof:name":"Chomch'on-dong",
    "wof:placetype":"locality"
},
  "geometry": {"coordinates":[125.44528,38.22],"type":"Point"}
}