{
  "type": "Feature",
  "properties": {
    "gn:admin1_code":"15.0",
    "gn:asciiname":"Yaktae-gol",
    "gn:country_code":"KP",
    "gn:dem":272,
    "gn:feature_class":"P",
    "gn:feature_code":"PPL",
    "gn:name":"Yaktae-gol",
    "gn:population":0,
    "gn:timezone":"Asia/Pyongyang",
    "iso:country":"KP",
    "name:kor_x_preferred":[
        "\uc57d\ub300\uace8"
    ],
    "wof:name":"Yaktae-gol",
    "wof:placetype":"locality"
},
  "geometry": {"coordinates":[126.42471999999999,39.48722],"type":"Point"}
}