{
  "type": "Feature",
  "properties": {
    "gn:admin1_code":"12.0",
    "gn:asciiname":"Hwasong-dong",
    "gn:country_code":"KP",
    "gn:dem":42,
    "gn:feature_class":"P",
    "gn:feature_code":"PPL",
    "gn:name":"Hwas\u014fng-dong",
    "gn:population":0,
    "gn:timezone":"Asia/Pyongyang",
    "iso:country":"KP",
    "name:kor_x_preferred":[
        "Hwas\u014fng-dong"
    ],
    "name:kor_x_variant":[
        "\ud654\uc131\ub3d9"
    ],
    "wof:name":"Hwasong-dong",
    "wof:placetype":"locality"
},
  "geometry": {"coordinates":[125.78606000000001,39.10312],"type":"Point"}
}