{
  "type": "Feature",
  "properties": {
    "gn:admin1_code":"0.0",
    "gn:asciiname":"Chudo-ri",
    "gn:country_code":"KP",
    "gn:dem":11,
    "gn:feature_class":"P",
    "gn:feature_code":"PPL",
    "gn:name":"Chudo-ri",
    "gn:population":0,
    "gn:timezone":"Asia/Pyongyang",
    "iso:country":"KP",
    "name:kor_x_preferred":[
        "\uc8fc\ub3c4\ub9ac"
    ],
    "wof:name":"Chudo-ri",
    "wof:placetype":"locality"
},
  "geometry": {"coordinates":[125.58138999999998,39.69861],"type":"Point"}
}