{
  "type": "Feature",
  "properties": {
    "gn:admin1_code":"11.0",
    "gn:asciiname":"Konji-dong",
    "gn:country_code":"KP",
    "gn:dem":285,
    "gn:feature_class":"P",
    "gn:feature_code":"PPL",
    "gn:name":"Konji-dong",
    "gn:population":0,
    "gn:timezone":"Asia/Pyongyang",
    "iso:country":"KP",
    "name:und_x_variant":[
        "\uace4\uc9c0\ub3d9",
        "Konji-dong"
    ],
    "wof:name":"Konji-dong",
    "wof:placetype":"locality"
},
  "geometry": {"coordinates":[125.11694,40.10472],"type":"Point"}
}