{
  "type": "Feature",
  "properties": {
    "gn:admin1_code":"11.0",
    "gn:asciiname":"Sep'abal",
    "gn:country_code":"KP",
    "gn:dem":10,
    "gn:feature_class":"P",
    "gn:feature_code":"PPL",
    "gn:name":"Sep\u2019abal",
    "gn:population":0,
    "gn:timezone":"Asia/Pyongyang",
    "iso:country":"KP",
    "name:kor_x_preferred":[
        "Sep\u2019abal"
    ],
    "name:kor_x_variant":[
        "\uc138\ud30c\ubc1c"
    ],
    "wof:name":"Sep'abal",
    "wof:placetype":"locality"
},
  "geometry": {"coordinates":[124.82222,39.83694000000001],"type":"Point"}
}