{
  "type": "Feature",
  "properties": {
    "gn:admin1_code":"0.0",
    "gn:asciiname":"Kosok-tong",
    "gn:country_code":"KP",
    "gn:dem":47,
    "gn:feature_class":"P",
    "gn:feature_code":"PPL",
    "gn:name":"Kos\u014fk-tong",
    "gn:population":0,
    "gn:timezone":"Asia/Pyongyang",
    "iso:country":"KP",
    "name:eng_x_preferred":[
        "Kosok"
    ],
    "name:eng_x_variant":[
        "Kosok-tong"
    ],
    "name:kor_x_preferred":[
        "\uace0\uc11d\ub3d9"
    ],
    "name:und_x_variant":[
        "Kos\u014fk-tong"
    ],
    "wof:name":"Kosok",
    "wof:placetype":"locality"
},
  "geometry": {"coordinates":[125.78333000000001,38.06667],"type":"Point"}
}