{
  "type": "Feature",
  "properties": {
    "gn:admin1_code":"6.0",
    "gn:asciiname":"Chunghak",
    "gn:country_code":"KP",
    "gn:dem":125,
    "gn:feature_class":"P",
    "gn:feature_code":"PPL",
    "gn:name":"Chunghak",
    "gn:population":0,
    "gn:timezone":"Asia/Pyongyang",
    "iso:country":"KP",
    "name:kor_x_preferred":[
        "\uc911\ud559"
    ],
    "wof:name":"Chunghak",
    "wof:placetype":"locality"
},
  "geometry": {"coordinates":[125.70833,38.19667000000001],"type":"Point"}
}