{
  "type": "Feature",
  "properties": {
    "gn:admin1_code":"9.0",
    "gn:asciiname":"Chungdae",
    "gn:country_code":"KP",
    "gn:dem":487,
    "gn:feature_class":"P",
    "gn:feature_code":"PPL",
    "gn:name":"Chungdae",
    "gn:population":0,
    "gn:timezone":"Asia/Pyongyang",
    "iso:country":"KP",
    "wof:name":"Chungdae",
    "wof:placetype":"locality"
},
  "geometry": {"coordinates":[127.95528,38.51528],"type":"Point"}
}