{
  "type": "Feature",
  "properties": {
    "gn:admin1_code":"1.0",
    "gn:asciiname":"Oeso-ri",
    "gn:country_code":"KP",
    "gn:dem":342,
    "gn:feature_class":"P",
    "gn:feature_code":"PPL",
    "gn:name":"Oes\u014f-ri",
    "gn:population":0,
    "gn:timezone":"Asia/Pyongyang",
    "iso:country":"KP",
    "name:und_x_variant":[
        "\uc678\uc11c\ub9ac",
        "Oes\u014f-ri"
    ],
    "wof:name":"Oeso-ri",
    "wof:placetype":"locality"
},
  "geometry": {"coordinates":[126.54657,40.80581],"type":"Point"}
}