{
  "type": "Feature",
  "properties": {
    "gn:admin1_code":"12.0",
    "gn:admin2_code":"S\u016dngho-guy\u014fk",
    "gn:asciiname":"Mandalhyon",
    "gn:country_code":"KP",
    "gn:dem":33,
    "gn:feature_class":"P",
    "gn:feature_code":"PPL",
    "gn:name":"Mandalhy\u014fn",
    "gn:population":0,
    "gn:timezone":"Asia/Pyongyang",
    "iso:country":"KP",
    "wof:name":"Mandalhyon",
    "wof:placetype":"locality"
},
  "geometry": {"coordinates":[126.035,39.01556],"type":"Point"}
}