{
  "type": "Feature",
  "properties": {
    "gn:admin1_code":"11.0",
    "gn:asciiname":"Oryong-ni",
    "gn:country_code":"KP",
    "gn:dem":167,
    "gn:feature_class":"P",
    "gn:feature_code":"PPL",
    "gn:name":"Oryong-ni",
    "gn:population":0,
    "gn:timezone":"Asia/Pyongyang",
    "iso:country":"KP",
    "name:eng_x_preferred":[
        "Oryong"
    ],
    "name:eng_x_variant":[
        "Oryong-ni"
    ],
    "name:und_x_variant":[
        "\uc624\ub8e1\ub9ac",
        "Oryong-ni"
    ],
    "wof:name":"Oryong",
    "wof:placetype":"locality"
},
  "geometry": {"coordinates":[125.50417,40.56861],"type":"Point"}
}