{
  "type": "Feature",
  "properties": {
    "gn:admin1_code":"6.0",
    "gn:asciiname":"Unam-dong",
    "gn:country_code":"KP",
    "gn:dem":115,
    "gn:feature_class":"P",
    "gn:feature_code":"PPL",
    "gn:name":"Unam-dong",
    "gn:population":0,
    "gn:timezone":"Asia/Pyongyang",
    "iso:country":"KP",
    "wof:name":"Unam-dong",
    "wof:placetype":"locality"
},
  "geometry": {"coordinates":[125.07528000000001,38.33889],"type":"Point"}
}