{
  "type": "Feature",
  "properties": {
    "gn:admin1_code":"1.0",
    "gn:asciiname":"Turung-ni",
    "gn:country_code":"KP",
    "gn:dem":413,
    "gn:feature_class":"P",
    "gn:feature_code":"PPL",
    "gn:name":"Tur\u016dng-ni",
    "gn:population":0,
    "gn:timezone":"Asia/Pyongyang",
    "iso:country":"KP",
    "name:und_x_variant":[
        "\ub450\ub989\ub9ac",
        "Tur\u016dng-ni"
    ],
    "wof:name":"Turung-ni",
    "wof:placetype":"locality"
},
  "geometry": {"coordinates":[125.65000000000001,40.40389],"type":"Point"}
}