{
  "type": "Feature",
  "properties": {
    "gn:admin1_code":"12.0",
    "gn:asciiname":"Yongdangmal",
    "gn:country_code":"KP",
    "gn:dem":31,
    "gn:feature_class":"P",
    "gn:feature_code":"PPL",
    "gn:name":"Y\u014fngdangmal",
    "gn:population":0,
    "gn:timezone":"Asia/Pyongyang",
    "iso:country":"KP",
    "name:und_x_variant":[
        "Y\u014fngdang-ni",
        "\uc601\ub2f9\ub9d0",
        "Y\u014fngdangmal"
    ],
    "wof:name":"Yongdangmal",
    "wof:placetype":"locality"
},
  "geometry": {"coordinates":[125.72917,38.8625],"type":"Point"}
}