{
  "type": "Feature",
  "properties": {
    "gn:admin1_code":"6.0",
    "gn:asciiname":"Kosong-ni",
    "gn:country_code":"KP",
    "gn:dem":13,
    "gn:feature_class":"P",
    "gn:feature_code":"PPL",
    "gn:name":"Kosong-ni",
    "gn:population":0,
    "gn:timezone":"Asia/Pyongyang",
    "iso:country":"KP",
    "name:kor_x_preferred":[
        "\uace0\uc1a1\ub9ac"
    ],
    "wof:name":"Kosong-ni",
    "wof:placetype":"locality"
},
  "geometry": {"coordinates":[125.56807000000001,38.37039],"type":"Point"}
}