{
  "type": "Feature",
  "properties": {
    "gn:admin1_code":"3.0",
    "gn:asciiname":"Sunamch'on",
    "gn:country_code":"KP",
    "gn:dem":226,
    "gn:feature_class":"P",
    "gn:feature_code":"PPL",
    "gn:name":"Sunamch\u2019on",
    "gn:population":0,
    "gn:timezone":"Asia/Pyongyang",
    "iso:country":"KP",
    "name:und_x_variant":[
        "\uc218\ub0a8\ucd0c",
        "Sunamch\u2019on"
    ],
    "wof:name":"Sunamch'on",
    "wof:placetype":"locality"
},
  "geometry": {"coordinates":[128.81,40.5775],"type":"Point"}
}