{
  "type": "Feature",
  "properties": {
    "gn:admin1_code":"13.0",
    "gn:asciiname":"Simp'o-ri",
    "gn:country_code":"KP",
    "gn:dem":857,
    "gn:feature_class":"P",
    "gn:feature_code":"PPL",
    "gn:name":"Simp\u2019o-ri",
    "gn:population":0,
    "gn:timezone":"Asia/Pyongyang",
    "iso:country":"KP",
    "name:kor_x_preferred":[
        "\uc2ec\ud3ec\ub9ac"
    ],
    "name:und_x_variant":[
        "Shimpo-ri",
        "Simp\u2019o-ri"
    ],
    "wof:name":"Simp'o-ri",
    "wof:placetype":"locality"
},
  "geometry": {"coordinates":[128.37853999999999,41.36915],"type":"Point"}
}