{
  "type": "Feature",
  "properties": {
    "gn:admin1_code":"3.0",
    "gn:asciiname":"Ssango",
    "gn:country_code":"KP",
    "gn:dem":120,
    "gn:feature_class":"P",
    "gn:feature_code":"PPL",
    "gn:name":"Ssang\u014f",
    "gn:population":0,
    "gn:timezone":"Asia/Pyongyang",
    "iso:country":"KP",
    "name:und_x_variant":[
        "Ssang\u014f",
        "\uc30d\uac70"
    ],
    "wof:name":"Ssango",
    "wof:placetype":"locality"
},
  "geometry": {"coordinates":[128.21421000000001,40.23614],"type":"Point"}
}