{
  "type": "Feature",
  "properties": {
    "gn:admin1_code":"6.0",
    "gn:asciiname":"Muhak-tong",
    "gn:country_code":"KP",
    "gn:dem":100,
    "gn:feature_class":"P",
    "gn:feature_code":"PPL",
    "gn:name":"Muhak-tong",
    "gn:population":0,
    "gn:timezone":"Asia/Pyongyang",
    "iso:country":"KP",
    "name:kor_x_preferred":[
        "\ubb34\ud559\ub3d9"
    ],
    "wof:name":"Muhak-tong",
    "wof:placetype":"locality"
},
  "geometry": {"coordinates":[125.27833,38.41694],"type":"Point"}
}