{
  "type": "Feature",
  "properties": {
    "gn:admin1_code":"13.0",
    "gn:asciiname":"Kwandong-ni",
    "gn:country_code":"KP",
    "gn:dem":1287,
    "gn:feature_class":"P",
    "gn:feature_code":"PPL",
    "gn:name":"Kwandong-ni",
    "gn:population":0,
    "gn:timezone":"Asia/Pyongyang",
    "iso:country":"KP",
    "name:eng_x_preferred":[
        "Kwandong"
    ],
    "name:eng_x_variant":[
        "Kwandong-ni"
    ],
    "wof:name":"Kwandong",
    "wof:placetype":"locality"
},
  "geometry": {"coordinates":[127.97556,41.06944],"type":"Point"}
}