{
  "type": "Feature",
  "properties": {
    "gn:admin1_code":"6.0",
    "gn:asciiname":"Hongjuk-tong",
    "gn:country_code":"KP",
    "gn:dem":19,
    "gn:feature_class":"P",
    "gn:feature_code":"PPL",
    "gn:name":"Hongjuk-tong",
    "gn:population":0,
    "gn:timezone":"Asia/Pyongyang",
    "iso:country":"KP",
    "name:kor_x_preferred":[
        "\ud64d\uc8fd\ub3d9"
    ],
    "wof:name":"Hongjuk-tong",
    "wof:placetype":"locality"
},
  "geometry": {"coordinates":[125.07028,38.20944],"type":"Point"}
}