{
  "type": "Feature",
  "properties": {
    "gn:admin1_code":"9.0",
    "gn:asciiname":"Chijang-ni",
    "gn:country_code":"KP",
    "gn:dem":64,
    "gn:feature_class":"P",
    "gn:feature_code":"PPL",
    "gn:name":"Chijang-ni",
    "gn:population":0,
    "gn:timezone":"Asia/Pyongyang",
    "iso:country":"KP",
    "name:eng_x_preferred":[
        "Chijang"
    ],
    "name:eng_x_variant":[
        "Chijang-ni"
    ],
    "name:und_x_variant":[
        "\uc9c0\uc7a5\ub9ac",
        "Chijang-ni"
    ],
    "wof:name":"Chijang",
    "wof:placetype":"locality"
},
  "geometry": {"coordinates":[127.87111,38.8725],"type":"Point"}
}