{
  "type": "Feature",
  "properties": {
    "gn:admin1_code":"17.0",
    "gn:asciiname":"Chin-dong",
    "gn:country_code":"KP",
    "gn:dem":409,
    "gn:feature_class":"P",
    "gn:feature_code":"PPL",
    "gn:name":"Chin-dong",
    "gn:population":0,
    "gn:timezone":"Asia/Pyongyang",
    "iso:country":"KP",
    "name:und_x_variant":[
        "\uc9c4\ub3d9",
        "Chin-dong"
    ],
    "wof:name":"Chin-dong",
    "wof:placetype":"locality"
},
  "geometry": {"coordinates":[129.96638999999999,42.74417],"type":"Point"}
}