{
  "type": "Feature",
  "properties": {
    "gn:admin1_code":"15.0",
    "gn:admin2_code":"1869039",
    "gn:asciiname":"Tongdong-ni",
    "gn:country_code":"KP",
    "gn:dem":13,
    "gn:feature_class":"P",
    "gn:feature_code":"PPL",
    "gn:name":"Tongd\u014fng-ni",
    "gn:population":0,
    "gn:timezone":"Asia/Pyongyang",
    "iso:country":"KP",
    "wof:name":"Tongdong-ni",
    "wof:placetype":"locality"
},
  "geometry": {"coordinates":[125.6525,39.41528],"type":"Point"}
}