{
  "type": "Feature",
  "properties": {
    "gn:admin1_code":"12.0",
    "gn:admin2_code":"Kangdong-gun",
    "gn:asciiname":"Yuil",
    "gn:country_code":"KP",
    "gn:dem":67,
    "gn:feature_class":"P",
    "gn:feature_code":"PPL",
    "gn:name":"Yuil",
    "gn:population":0,
    "gn:timezone":"Asia/Pyongyang",
    "iso:country":"KP",
    "name:kor_x_preferred":[
        "\uc720\uc77c"
    ],
    "wof:name":"Yuil",
    "wof:placetype":"locality"
},
  "geometry": {"coordinates":[126.27074,38.95586],"type":"Point"}
}