{
  "type": "Feature",
  "properties": {
    "gn:admin1_code":"13.0",
    "gn:admin2_code":"Paegam-gun",
    "gn:asciiname":"Paeamsom",
    "gn:cc2":"KP",
    "gn:country_code":"KP",
    "gn:dem":806,
    "gn:feature_class":"P",
    "gn:feature_code":"PPL",
    "gn:name":"Paeams\u014fm",
    "gn:population":0,
    "gn:timezone":"Asia/Pyongyang",
    "iso:country":"KP",
    "name:und_x_variant":[
        "Sado",
        "Paems\u014fm",
        "Paeams\u014fm"
    ],
    "wof:name":"Paeamsom",
    "wof:placetype":"locality"
},
  "geometry": {"coordinates":[128.98056,41.15639],"type":"Point"}
}