{
  "type": "Feature",
  "properties": {
    "gn:admin1_code":"7.0",
    "gn:asciiname":"Samch'ol-li",
    "gn:country_code":"KP",
    "gn:dem":75,
    "gn:feature_class":"P",
    "gn:feature_code":"PPL",
    "gn:name":"Samch\u2019\u014fl-li",
    "gn:population":0,
    "gn:timezone":"Asia/Pyongyang",
    "iso:country":"KP",
    "name:und_x_variant":[
        "Samch\u2019\u014fn-ni",
        "\uc0bc\ucc9c\ub9ac",
        "Samch\u2019\u014fl-li"
    ],
    "wof:name":"Samch'ol-li",
    "wof:placetype":"locality"
},
  "geometry": {"coordinates":[126.06278,38.46333],"type":"Point"}
}