{
  "type": "Feature",
  "properties": {
    "gn:admin1_code":"0.0",
    "gn:asciiname":"Yongsang-ni",
    "gn:cc2":"KP",
    "gn:country_code":"KP",
    "gn:dem":47,
    "gn:feature_class":"P",
    "gn:feature_code":"PPL",
    "gn:name":"Yongsang-ni",
    "gn:population":0,
    "gn:timezone":"Asia/Pyongyang",
    "iso:country":"KP",
    "name:kor_x_preferred":[
        "\uc6a9\uc0c1\ub9ac"
    ],
    "name:und_x_variant":[
        "Yongsang-dong",
        "Yongsang-ni"
    ],
    "wof:name":"Yongsang-ni",
    "wof:placetype":"locality"
},
  "geometry": {"coordinates":[125.41667,39.93333],"type":"Point"}
}