{
  "type": "Feature",
  "properties": {
    "gn:admin1_code":"7.0",
    "gn:asciiname":"Ch'ongnyong-dong",
    "gn:country_code":"KP",
    "gn:dem":162,
    "gn:feature_class":"P",
    "gn:feature_code":"PPL",
    "gn:name":"Ch\u2019\u014fngnyong-dong",
    "gn:population":0,
    "gn:timezone":"Asia/Pyongyang",
    "iso:country":"KP",
    "name:kor_x_preferred":[
        "\uccad\ub8e1\ub3d9"
    ],
    "name:kor_x_variant":[
        "Ch\u2019\u014fngnyong-dong"
    ],
    "wof:name":"Ch'ongnyong-dong",
    "wof:placetype":"locality"
},
  "geometry": {"coordinates":[126.72111,38.79944],"type":"Point"}
}