{
  "type": "Feature",
  "properties": {
    "gn:admin1_code":"7.0",
    "gn:asciiname":"Sanggamt'o-dong",
    "gn:country_code":"KP",
    "gn:dem":132,
    "gn:feature_class":"P",
    "gn:feature_code":"PPL",
    "gn:name":"Sanggamt\u2019o-dong",
    "gn:population":0,
    "gn:timezone":"Asia/Pyongyang",
    "iso:country":"KP",
    "wof:name":"Sanggamt'o-dong",
    "wof:placetype":"locality"
},
  "geometry": {"coordinates":[125.94556,38.20944],"type":"Point"}
}