{
  "type": "Feature",
  "properties": {
    "gn:admin1_code":"0.0",
    "gn:asciiname":"Poung-ni",
    "gn:country_code":"KP",
    "gn:dem":47,
    "gn:feature_class":"P",
    "gn:feature_code":"PPL",
    "gn:name":"Po\u016dng-ni",
    "gn:population":0,
    "gn:timezone":"Asia/Pyongyang",
    "iso:country":"KP",
    "name:kor_x_preferred":[
        "\ubcf4\uc5c9\ub9ac"
    ],
    "name:und_x_variant":[
        "Po\u016dng-ni"
    ],
    "wof:name":"Poung-ni",
    "wof:placetype":"locality"
},
  "geometry": {"coordinates":[124.88333,39.88333],"type":"Point"}
}