{
  "type": "Feature",
  "properties": {
    "gn:admin1_code":"11.0",
    "gn:asciiname":"Sinso-ri",
    "gn:country_code":"KP",
    "gn:dem":6,
    "gn:feature_class":"P",
    "gn:feature_code":"PPL",
    "gn:name":"Sins\u014f-ri",
    "gn:population":0,
    "gn:timezone":"Asia/Pyongyang",
    "iso:country":"KP",
    "name:und_x_variant":[
        "\uc2e0\uc11c\ub9ac",
        "Sins\u014f-ri"
    ],
    "wof:name":"Sinso-ri",
    "wof:placetype":"locality"
},
  "geometry": {"coordinates":[124.32639,39.96889],"type":"Point"}
}