{
  "type": "Feature",
  "properties": {
    "gn:admin1_code":"12.0",
    "gn:asciiname":"Changgwang-ni",
    "gn:country_code":"KP",
    "gn:dem":8,
    "gn:feature_class":"P",
    "gn:feature_code":"PPL",
    "gn:name":"Changgwang-ni",
    "gn:population":0,
    "gn:timezone":"Asia/Pyongyang",
    "iso:country":"KP",
    "name:kor_x_preferred":[
        "\uc7a5\uad11\ub9ac"
    ],
    "name:und_x_variant":[
        "Janggwangni"
    ],
    "wof:name":"Changgwang-ni",
    "wof:placetype":"locality"
},
  "geometry": {"coordinates":[125.62306,38.97389],"type":"Point"}
}