{
  "type": "Feature",
  "properties": {
    "gn:admin1_code":"11.0",
    "gn:asciiname":"Tap-tong",
    "gn:country_code":"KP",
    "gn:dem":43,
    "gn:feature_class":"P",
    "gn:feature_code":"PPL",
    "gn:name":"Tap-tong",
    "gn:population":0,
    "gn:timezone":"Asia/Pyongyang",
    "iso:country":"KP",
    "name:kor_x_preferred":[
        "\ub2f5\ub3d9"
    ],
    "wof:name":"Tap-tong",
    "wof:placetype":"locality"
},
  "geometry": {"coordinates":[125.25360999999999,39.73917],"type":"Point"}
}