{
  "type": "Feature",
  "properties": {
    "gn:admin1_code":"11.0",
    "gn:asciiname":"Yongbung-ni",
    "gn:country_code":"KP",
    "gn:dem":10,
    "gn:feature_class":"P",
    "gn:feature_code":"PPL",
    "gn:name":"Yongbung-ni",
    "gn:population":0,
    "gn:timezone":"Asia/Pyongyang",
    "iso:country":"KP",
    "name:und_x_variant":[
        "\ub8e1\ubd81\ub9ac",
        "Yongbung-ni"
    ],
    "wof:name":"Yongbung-ni",
    "wof:placetype":"locality"
},
  "geometry": {"coordinates":[124.44750000000001,39.88472],"type":"Point"}
}