{
  "type": "Feature",
  "properties": {
    "gn:admin1_code":"15.0",
    "gn:admin2_code":"1869039",
    "gn:asciiname":"Sipsam-ni",
    "gn:country_code":"KP",
    "gn:dem":25,
    "gn:feature_class":"P",
    "gn:feature_code":"PPL",
    "gn:name":"Sipsam-ni",
    "gn:population":0,
    "gn:timezone":"Asia/Pyongyang",
    "iso:country":"KP",
    "name:eng_x_preferred":[
        "Sipsam"
    ],
    "name:eng_x_variant":[
        "Sipsam-ni"
    ],
    "wof:name":"Sipsam",
    "wof:placetype":"locality"
},
  "geometry": {"coordinates":[125.65306,39.43528],"type":"Point"}
}