{
  "type": "Feature",
  "properties": {
    "gn:admin1_code":"6.0",
    "gn:admin2_code":"P\u2019anmun-gun",
    "gn:asciiname":"Nulmong-ni",
    "gn:country_code":"KP",
    "gn:dem":32,
    "gn:feature_class":"P",
    "gn:feature_code":"PPL",
    "gn:name":"Nulmong-ni",
    "gn:population":0,
    "gn:timezone":"Asia/Pyongyang",
    "iso:country":"KP",
    "wof:name":"Nulmong-ni",
    "wof:placetype":"locality"
},
  "geometry": {"coordinates":[126.69972,37.98972],"type":"Point"}
}