{
  "type": "Feature",
  "properties": {
    "gn:admin1_code":"17.0",
    "gn:admin2_code":"My\u014fngch'\u014fn-gun",
    "gn:asciiname":"Kojin",
    "gn:country_code":"KP",
    "gn:dem":3,
    "gn:feature_class":"P",
    "gn:feature_code":"PPL",
    "gn:name":"Kojin",
    "gn:population":0,
    "gn:timezone":"Asia/Pyongyang",
    "iso:country":"KP",
    "name:und_x_variant":[
        "Koshin",
        "Kosin",
        "\uace0\uc9c4",
        "Kojin"
    ],
    "wof:name":"Kojin",
    "wof:placetype":"locality"
},
  "geometry": {"coordinates":[129.71833000000001,40.98611],"type":"Point"}
}