{
  "type": "Feature",
  "properties": {
    "gn:admin1_code":"11.0",
    "gn:asciiname":"Songha-ri",
    "gn:country_code":"KP",
    "gn:dem":343,
    "gn:feature_class":"P",
    "gn:feature_code":"PPL",
    "gn:name":"S\u014fngha-ri",
    "gn:population":0,
    "gn:timezone":"Asia/Pyongyang",
    "iso:country":"KP",
    "name:und_x_variant":[
        "\uc131\ud558\ub9ac",
        "S\u014fngha-ri"
    ],
    "wof:name":"Songha-ri",
    "wof:placetype":"locality"
},
  "geometry": {"coordinates":[125.23639,40.51028],"type":"Point"}
}