{
  "type": "Feature",
  "properties": {
    "gn:admin1_code":"6.0",
    "gn:asciiname":"Sansu-dong",
    "gn:country_code":"KP",
    "gn:dem":46,
    "gn:feature_class":"P",
    "gn:feature_code":"PPL",
    "gn:name":"Sansu-dong",
    "gn:population":0,
    "gn:timezone":"Asia/Pyongyang",
    "iso:country":"KP",
    "name:und_x_variant":[
        "\uc0b0\uc218\ub3d9",
        "Sansu-dong"
    ],
    "wof:name":"Sansu-dong",
    "wof:placetype":"locality"
},
  "geometry": {"coordinates":[125.31917,38.58972],"type":"Point"}
}