{
  "type": "Feature",
  "properties": {
    "gn:admin1_code":"15.0",
    "gn:asciiname":"Tungnyong-ni",
    "gn:country_code":"KP",
    "gn:dem":82,
    "gn:feature_class":"P",
    "gn:feature_code":"PPL",
    "gn:name":"T\u016dngnyong-ni",
    "gn:population":0,
    "gn:timezone":"Asia/Pyongyang",
    "iso:country":"KP",
    "name:eng_x_preferred":[
        "Tungnyong"
    ],
    "name:eng_x_variant":[
        "Tungnyong-ni"
    ],
    "wof:name":"Tungnyong",
    "wof:placetype":"locality"
},
  "geometry": {"coordinates":[125.77361000000001,39.46806],"type":"Point"}
}