{
  "type": "Feature",
  "properties": {
    "gn:admin1_code":"11.0",
    "gn:asciiname":"Sorim-ni",
    "gn:country_code":"KP",
    "gn:dem":105,
    "gn:feature_class":"P",
    "gn:feature_code":"PPL",
    "gn:name":"S\u014frim-ni",
    "gn:population":0,
    "gn:timezone":"Asia/Pyongyang",
    "iso:country":"KP",
    "name:und_x_variant":[
        "S\u014frim-dong",
        "\uc11c\ub9bc\ub9ac",
        "S\u014frim-ni"
    ],
    "wof:name":"Sorim-ni",
    "wof:placetype":"locality"
},
  "geometry": {"coordinates":[124.65833000000001,39.905],"type":"Point"}
}