{
  "type": "Feature",
  "properties": {
    "gn:admin1_code":"17.0",
    "gn:asciiname":"Wonsu-gol",
    "gn:country_code":"KP",
    "gn:dem":85,
    "gn:feature_class":"P",
    "gn:feature_code":"PPL",
    "gn:name":"W\u014fnsu-gol",
    "gn:population":0,
    "gn:timezone":"Asia/Pyongyang",
    "iso:country":"KP",
    "name:und_x_variant":[
        "\uc6d0\uc218\uace8",
        "W\u014fnsu-gol"
    ],
    "wof:name":"Wonsu-gol",
    "wof:placetype":"locality"
},
  "geometry": {"coordinates":[130.28443999999999,42.50778],"type":"Point"}
}