{
  "type": "Feature",
  "properties": {
    "gn:admin1_code":"17.0",
    "gn:asciiname":"P'yongch'on",
    "gn:country_code":"KP",
    "gn:dem":23,
    "gn:feature_class":"P",
    "gn:feature_code":"PPL",
    "gn:name":"P\u2019yongch\u2019on",
    "gn:population":0,
    "gn:timezone":"Asia/Pyongyang",
    "iso:country":"KP",
    "name:und_x_variant":[
        "\ud3c9\ucd0c",
        "P\u2019yongch\u2019on"
    ],
    "wof:name":"P'yongch'on",
    "wof:placetype":"locality"
},
  "geometry": {"coordinates":[129.19972000000001,40.75222],"type":"Point"}
}