{
  "type": "Feature",
  "properties": {
    "gn:admin1_code":"7.0",
    "gn:asciiname":"Kwano-ri",
    "gn:country_code":"KP",
    "gn:dem":60,
    "gn:feature_class":"P",
    "gn:feature_code":"PPL",
    "gn:name":"Kwano-ri",
    "gn:population":0,
    "gn:timezone":"Asia/Pyongyang",
    "iso:country":"KP",
    "name:kor_x_preferred":[
        "\uad00\uc624\ub9ac"
    ],
    "name:und_x_variant":[
        "Kango-ri",
        "Kwano-ri"
    ],
    "wof:name":"Kwano-ri",
    "wof:placetype":"locality"
},
  "geometry": {"coordinates":[126.37361,38.365],"type":"Point"}
}