{
  "type": "Feature",
  "properties": {
    "gn:admin1_code":"9.0",
    "gn:asciiname":"Sinjang-ni",
    "gn:country_code":"KP",
    "gn:dem":10,
    "gn:feature_class":"P",
    "gn:feature_code":"PPL",
    "gn:name":"Sinjang-ni",
    "gn:population":0,
    "gn:timezone":"Asia/Pyongyang",
    "iso:country":"KP",
    "wof:name":"Sinjang-ni",
    "wof:placetype":"locality"
},
  "geometry": {"coordinates":[127.74444,39.06167],"type":"Point"}
}