{
  "type": "Feature",
  "properties": {
    "gn:admin1_code":"13.0",
    "gn:asciiname":"Pandong-ni",
    "gn:country_code":"KP",
    "gn:dem":1146,
    "gn:feature_class":"P",
    "gn:feature_code":"PPL",
    "gn:name":"Pand\u014fng-ni",
    "gn:population":0,
    "gn:timezone":"Asia/Pyongyang",
    "iso:country":"KP",
    "name:und_x_variant":[
        "\ubc18\ub355\ub9ac",
        "Pand\u014fng-ni"
    ],
    "wof:name":"Pandong-ni",
    "wof:placetype":"locality"
},
  "geometry": {"coordinates":[128.28556,40.79778],"type":"Point"}
}