{
  "type": "Feature",
  "properties": {
    "gn:admin1_code":"3.0",
    "gn:asciiname":"So-ri",
    "gn:country_code":"KP",
    "gn:dem":48,
    "gn:feature_class":"P",
    "gn:feature_code":"PPL",
    "gn:name":"S\u014f-ri",
    "gn:population":0,
    "gn:timezone":"Asia/Pyongyang",
    "iso:country":"KP",
    "name:und_x_variant":[
        "S\u014f-ri",
        "\uc11c\ub9ac"
    ],
    "wof:name":"So-ri",
    "wof:placetype":"locality"
},
  "geometry": {"coordinates":[128.30000999999999,40.24368],"type":"Point"}
}