{
  "type": "Feature",
  "properties": {
    "gn:admin1_code":"17.0",
    "gn:asciiname":"Yongso-gol",
    "gn:country_code":"KP",
    "gn:dem":650,
    "gn:feature_class":"P",
    "gn:feature_code":"PPL",
    "gn:name":"Yongso-gol",
    "gn:population":0,
    "gn:timezone":"Asia/Pyongyang",
    "iso:country":"KP",
    "name:und_x_variant":[
        "\uc6a9\uc18c\uace8",
        "Yongso-gol"
    ],
    "wof:name":"Yongso-gol",
    "wof:placetype":"locality"
},
  "geometry": {"coordinates":[129.41,41.38944],"type":"Point"}
}