{
  "type": "Feature",
  "properties": {
    "gn:admin1_code":"9.0",
    "gn:asciiname":"K'unnujunnae",
    "gn:country_code":"KP",
    "gn:dem":731,
    "gn:feature_class":"P",
    "gn:feature_code":"PPL",
    "gn:name":"K\u2019\u016dnn\u016dj\u016dnnae",
    "gn:population":0,
    "gn:timezone":"Asia/Pyongyang",
    "iso:country":"KP",
    "name:und_x_variant":[
        "\ud070\ub2a6\uc740\ub0b4",
        "K\u2019\u016dnn\u016dj\u016dnnae"
    ],
    "wof:name":"K'unnujunnae",
    "wof:placetype":"locality"
},
  "geometry": {"coordinates":[127.64472000000001,38.85611],"type":"Point"}
}