{
  "type": "Feature",
  "properties": {
    "gn:admin1_code":"17.0",
    "gn:admin2_code":"Hwadae-gun",
    "gn:asciiname":"Musudal-li",
    "gn:country_code":"KP",
    "gn:dem":4,
    "gn:feature_class":"P",
    "gn:feature_code":"PPL",
    "gn:name":"Musudal-li",
    "gn:population":0,
    "gn:timezone":"Asia/Pyongyang",
    "iso:country":"KP",
    "name:und_x_variant":[
        "Musudan-ni",
        "\ubb34\uc218\ub2ec\ub9ac",
        "Musudal-li"
    ],
    "wof:name":"Musudal-li",
    "wof:placetype":"locality"
},
  "geometry": {"coordinates":[129.66693999999998,40.85028],"type":"Point"}
}