{
  "type": "Feature",
  "properties": {
    "gn:admin1_code":"6.0",
    "gn:asciiname":"Mangdok-tong",
    "gn:country_code":"KP",
    "gn:dem":126,
    "gn:feature_class":"P",
    "gn:feature_code":"PPL",
    "gn:name":"Mangd\u014fk-tong",
    "gn:population":0,
    "gn:timezone":"Asia/Pyongyang",
    "iso:country":"KP",
    "name:kor_x_preferred":[
        "\ub9dd\ub355\ub3d9"
    ],
    "name:kor_x_variant":[
        "Mangd\u014fk-tong"
    ],
    "wof:name":"Mangdok-tong",
    "wof:placetype":"locality"
},
  "geometry": {"coordinates":[125.39778,38.55806],"type":"Point"}
}