{
  "type": "Feature",
  "properties": {
    "gn:admin1_code":"6.0",
    "gn:asciiname":"Saet'o",
    "gn:country_code":"KP",
    "gn:dem":52,
    "gn:feature_class":"P",
    "gn:feature_code":"PPL",
    "gn:name":"Saet\u2019\u014f",
    "gn:population":0,
    "gn:timezone":"Asia/Pyongyang",
    "iso:country":"KP",
    "name:kor_x_preferred":[
        "\uc0c8\ud130"
    ],
    "name:kor_x_variant":[
        "Saet\u2019\u014f"
    ],
    "name:und_x_variant":[
        "Sin\u2019gi"
    ],
    "wof:name":"Saet'o",
    "wof:placetype":"locality"
},
  "geometry": {"coordinates":[125.3875,38.39972],"type":"Point"}
}