{
  "type": "Feature",
  "properties": {
    "gn:admin1_code":"11.0",
    "gn:asciiname":"Sosu-ri",
    "gn:country_code":"KP",
    "gn:dem":258,
    "gn:feature_class":"P",
    "gn:feature_code":"PPL",
    "gn:name":"Sosu-ri",
    "gn:population":0,
    "gn:timezone":"Asia/Pyongyang",
    "iso:country":"KP",
    "name:und_x_variant":[
        "\uc18c\uc218\ub9ac",
        "Sosu-ri"
    ],
    "wof:name":"Sosu-ri",
    "wof:placetype":"locality"
},
  "geometry": {"coordinates":[124.98193999999999,40.27639],"type":"Point"}
}