{
  "type": "Feature",
  "properties": {
    "gn:admin1_code":"11.0",
    "gn:asciiname":"Chikp'ung-dong",
    "gn:country_code":"KP",
    "gn:dem":316,
    "gn:feature_class":"P",
    "gn:feature_code":"PPL",
    "gn:name":"Chikp\u2019ung-dong",
    "gn:population":0,
    "gn:timezone":"Asia/Pyongyang",
    "iso:country":"KP",
    "name:und_x_variant":[
        "\uc9c1\ud48d\ub3d9",
        "Chikp\u2019ung-dong"
    ],
    "wof:name":"Chikp'ung-dong",
    "wof:placetype":"locality"
},
  "geometry": {"coordinates":[125.32639,40.21361],"type":"Point"}
}