{
  "type": "Feature",
  "properties": {
    "gn:admin1_code":"11.0",
    "gn:asciiname":"Naejuch'am",
    "gn:country_code":"KP",
    "gn:dem":109,
    "gn:feature_class":"P",
    "gn:feature_code":"PPL",
    "gn:name":"Naejuch\u2019am",
    "gn:population":0,
    "gn:timezone":"Asia/Pyongyang",
    "iso:country":"KP",
    "name:und_x_variant":[
        "\ub0b4\uc8fc\ucc38",
        "Naejuch\u2019am"
    ],
    "wof:name":"Naejuch'am",
    "wof:placetype":"locality"
},
  "geometry": {"coordinates":[126.19750000000001,40.02528],"type":"Point"}
}