{
  "type": "Feature",
  "properties": {
    "gn:admin1_code":"3.0",
    "gn:asciiname":"Iha-ri",
    "gn:country_code":"KP",
    "gn:dem":318,
    "gn:feature_class":"P",
    "gn:feature_code":"PPL",
    "gn:name":"Iha-ri",
    "gn:population":0,
    "gn:timezone":"Asia/Pyongyang",
    "iso:country":"KP",
    "name:und_x_variant":[
        "\uc774\ud558\ub9ac",
        "Iha-ri"
    ],
    "wof:name":"Iha-ri",
    "wof:placetype":"locality"
},
  "geometry": {"coordinates":[128.91806,40.69806],"type":"Point"}
}