{
  "type": "Feature",
  "properties": {
    "gn:admin1_code":"13.0",
    "gn:admin2_code":"2041726",
    "gn:asciiname":"Tok-ch'on",
    "gn:country_code":"KP",
    "gn:dem":1286,
    "gn:feature_class":"P",
    "gn:feature_code":"PPL",
    "gn:name":"T\u014fk-ch\u2019on",
    "gn:population":0,
    "gn:timezone":"Asia/Pyongyang",
    "iso:country":"KP",
    "wof:name":"Tok-ch'on",
    "wof:placetype":"locality"
},
  "geometry": {"coordinates":[128.05778000000001,40.84833],"type":"Point"}
}