{
  "type": "Feature",
  "properties": {
    "gn:admin1_code":"0.0",
    "gn:asciiname":"Sinhung-dong",
    "gn:cc2":"KP",
    "gn:country_code":"KP",
    "gn:dem":902,
    "gn:feature_class":"P",
    "gn:feature_code":"PPL",
    "gn:name":"Sinh\u016dng-dong",
    "gn:population":0,
    "gn:timezone":"Asia/Pyongyang",
    "iso:country":"KP",
    "name:kor_x_preferred":[
        "\uc2e0\ud765\ub3d9"
    ],
    "name:und_x_variant":[
        "Sinby\u014fk-tong",
        "Sinh\u016dng-dong"
    ],
    "wof:name":"Sinhung-dong",
    "wof:placetype":"locality"
},
  "geometry": {"coordinates":[127.03333000000001,41.21667],"type":"Point"}
}