{
  "type": "Feature",
  "properties": {
    "gn:admin1_code":"3.0",
    "gn:admin2_code":"K\u016dmya-gun",
    "gn:asciiname":"Insong-ni",
    "gn:country_code":"KP",
    "gn:dem":2,
    "gn:feature_class":"P",
    "gn:feature_code":"PPL",
    "gn:name":"Ins\u014fng-ni",
    "gn:population":0,
    "gn:timezone":"Asia/Pyongyang",
    "iso:country":"KP",
    "name:eng_x_preferred":[
        "Insong"
    ],
    "name:eng_x_variant":[
        "Insong-ni"
    ],
    "wof:name":"Insong",
    "wof:placetype":"locality"
},
  "geometry": {"coordinates":[127.37139000000001,39.45333],"type":"Point"}
}