{
  "type": "Feature",
  "properties": {
    "gn:admin1_code":"7.0",
    "gn:asciiname":"Yu-dong",
    "gn:country_code":"KP",
    "gn:dem":103,
    "gn:feature_class":"P",
    "gn:feature_code":"PPL",
    "gn:name":"Yu-dong",
    "gn:population":0,
    "gn:timezone":"Asia/Pyongyang",
    "iso:country":"KP",
    "wof:name":"Yu-dong",
    "wof:placetype":"locality"
},
  "geometry": {"coordinates":[126.06638999999998,38.30917],"type":"Point"}
}