{
  "type": "Feature",
  "properties": {
    "gn:admin1_code":"1.0",
    "gn:asciiname":"Oguch'am",
    "gn:country_code":"KP",
    "gn:dem":133,
    "gn:feature_class":"P",
    "gn:feature_code":"PPL",
    "gn:name":"\u014eguch\u2019am",
    "gn:population":0,
    "gn:timezone":"Asia/Pyongyang",
    "iso:country":"KP",
    "name:und_x_variant":[
        "\uc5b4\uad6c\ucc38",
        "\u014eguch\u2019am"
    ],
    "wof:name":"Oguch'am",
    "wof:placetype":"locality"
},
  "geometry": {"coordinates":[126.27833,40.12722],"type":"Point"}
}