{
  "type": "Feature",
  "properties": {
    "gn:admin1_code":"3.0",
    "gn:asciiname":"Sinhung-dong",
    "gn:country_code":"KP",
    "gn:dem":469,
    "gn:feature_class":"P",
    "gn:feature_code":"PPL",
    "gn:name":"Sinh\u016dng-dong",
    "gn:population":0,
    "gn:timezone":"Asia/Pyongyang",
    "iso:country":"KP",
    "wof:name":"Sinhung-dong",
    "wof:placetype":"locality"
},
  "geometry": {"coordinates":[128.4375,40.29583],"type":"Point"}
}