{
  "type": "Feature",
  "properties": {
    "gn:admin1_code":"6.0",
    "gn:asciiname":"Ch'odo-ri",
    "gn:country_code":"KP",
    "gn:dem":134,
    "gn:feature_class":"P",
    "gn:feature_code":"PPL",
    "gn:name":"Ch\u2019odo-ri",
    "gn:population":0,
    "gn:timezone":"Asia/Pyongyang",
    "iso:country":"KP",
    "name:und_x_variant":[
        "\ucd08\ub3c4\ub9ac",
        "Ch\u2019odo-ri"
    ],
    "wof:name":"Ch'odo-ri",
    "wof:placetype":"locality"
},
  "geometry": {"coordinates":[124.87333,38.53028],"type":"Point"}
}