{
  "type": "Feature",
  "properties": {
    "gn:admin1_code":"0.0",
    "gn:asciiname":"Ch'osal-li",
    "gn:country_code":"KP",
    "gn:dem":17,
    "gn:feature_class":"P",
    "gn:feature_code":"PPL",
    "gn:name":"Ch\u2019osal-li",
    "gn:population":0,
    "gn:timezone":"Asia/Pyongyang",
    "iso:country":"KP",
    "name:kor_x_preferred":[
        "\ucd08\uc0b0\ub9ac"
    ],
    "name:und_x_variant":[
        "Ch\u2019osal-li",
        "Ch\u2019osan-ni"
    ],
    "wof:name":"Ch'osal-li",
    "wof:placetype":"locality"
},
  "geometry": {"coordinates":[125.36667,38.85],"type":"Point"}
}