{
  "type": "Feature",
  "properties": {
    "gn:admin1_code":"12.0",
    "gn:asciiname":"Oryong-dong",
    "gn:country_code":"KP",
    "gn:dem":42,
    "gn:feature_class":"P",
    "gn:feature_code":"PPL",
    "gn:name":"Oryong-dong",
    "gn:population":0,
    "gn:timezone":"Asia/Pyongyang",
    "iso:country":"KP",
    "name:kor_x_preferred":[
        "\uc624\ub8e1\ub3d9"
    ],
    "name:kor_x_variant":[
        "\uc138\ub3d9\ub124"
    ],
    "name:und_x_variant":[
        "Sedongne",
        "Oryongdong"
    ],
    "wof:name":"Oryong-dong",
    "wof:placetype":"locality"
},
  "geometry": {"coordinates":[125.77364,39.17667],"type":"Point"}
}