{
  "type": "Feature",
  "properties": {
    "gn:admin1_code":"17.0",
    "gn:asciiname":"P'ungsok-tong",
    "gn:country_code":"KP",
    "gn:dem":773,
    "gn:feature_class":"P",
    "gn:feature_code":"PPL",
    "gn:name":"P\u2019ungs\u014fk-tong",
    "gn:population":0,
    "gn:timezone":"Asia/Pyongyang",
    "iso:country":"KP",
    "wof:name":"P'ungsok-tong",
    "wof:placetype":"locality"
},
  "geometry": {"coordinates":[129.34999999999999,42.31667],"type":"Point"}
}