{
  "type": "Feature",
  "properties": {
    "gn:admin1_code":"3.0",
    "gn:asciiname":"Hanam-ni",
    "gn:country_code":"KP",
    "gn:dem":12,
    "gn:feature_class":"P",
    "gn:feature_code":"PPL",
    "gn:name":"Hanam-ni",
    "gn:population":0,
    "gn:timezone":"Asia/Pyongyang",
    "iso:country":"KP",
    "name:eng_x_preferred":[
        "Hanam"
    ],
    "name:eng_x_variant":[
        "Hanam-ni"
    ],
    "name:und_x_variant":[
        "\ud558\ub0a8\ub9ac",
        "Hanam-ni"
    ],
    "wof:name":"Hanam",
    "wof:placetype":"locality"
},
  "geometry": {"coordinates":[127.48528,39.62111],"type":"Point"}
}