{
  "type": "Feature",
  "properties": {
    "gn:admin1_code":"3.0",
    "gn:asciiname":"Yonp'o-ri",
    "gn:country_code":"KP",
    "gn:dem":2,
    "gn:feature_class":"P",
    "gn:feature_code":"PPL",
    "gn:name":"Y\u014fnp\u2019o-ri",
    "gn:population":0,
    "gn:timezone":"Asia/Pyongyang",
    "iso:country":"KP",
    "name:und_x_variant":[
        "Rempo",
        "Y\u014fngp\u2019o",
        "Renho",
        "Y\u014fnp\u014f-ri",
        "Y\u014fnp\u2019o",
        "\ub828\ud3ec\ub9ac",
        "Y\u014fnp\u2019o-ri"
    ],
    "wof:name":"Yonp'o-ri",
    "wof:placetype":"locality"
},
  "geometry": {"coordinates":[127.51806000000001,39.79278],"type":"Point"}
}