{
  "type": "Feature",
  "properties": {
    "gn:admin1_code":"6.0",
    "gn:asciiname":"Tonggong-ni",
    "gn:country_code":"KP",
    "gn:dem":26,
    "gn:feature_class":"P",
    "gn:feature_code":"PPL",
    "gn:name":"Tonggong-ni",
    "gn:population":0,
    "gn:timezone":"Asia/Pyongyang",
    "iso:country":"KP",
    "name:eng_x_preferred":[
        "Tonggong"
    ],
    "name:eng_x_variant":[
        "Tonggong-ni"
    ],
    "name:und_x_variant":[
        "\ub3d9\uace1\ub9ac",
        "Tonggong-ni"
    ],
    "wof:name":"Tonggong",
    "wof:placetype":"locality"
},
  "geometry": {"coordinates":[125.19194,38.55306],"type":"Point"}
}