{
  "type": "Feature",
  "properties": {
    "gn:admin1_code":"3.0",
    "gn:asciiname":"Changho-ri",
    "gn:country_code":"KP",
    "gn:dem":5,
    "gn:feature_class":"P",
    "gn:feature_code":"PPL",
    "gn:name":"Changho-ri",
    "gn:population":0,
    "gn:timezone":"Asia/Pyongyang",
    "iso:country":"KP",
    "name:und_x_variant":[
        "\uc7a5\ud638\ub9ac"
    ],
    "wof:name":"Changho-ri",
    "wof:placetype":"locality"
},
  "geometry": {"coordinates":[128.43693999999999,40.11111],"type":"Point"}
}