{
  "type": "Feature",
  "properties": {
    "gn:admin1_code":"11.0",
    "gn:asciiname":"Sodang-ni",
    "gn:country_code":"KP",
    "gn:dem":123,
    "gn:feature_class":"P",
    "gn:feature_code":"PPL",
    "gn:name":"S\u014fdang-ni",
    "gn:population":0,
    "gn:timezone":"Asia/Pyongyang",
    "iso:country":"KP",
    "name:eng_x_preferred":[
        "Sodang"
    ],
    "name:eng_x_variant":[
        "Sodang-ni"
    ],
    "wof:name":"Sodang",
    "wof:placetype":"locality"
},
  "geometry": {"coordinates":[124.87694,40.41167],"type":"Point"}
}