{
  "type": "Feature",
  "properties": {
    "gn:admin1_code":"3.0",
    "gn:asciiname":"Araessuk-kol",
    "gn:country_code":"KP",
    "gn:dem":19,
    "gn:feature_class":"P",
    "gn:feature_code":"PPL",
    "gn:name":"Araessuk-kol",
    "gn:population":0,
    "gn:timezone":"Asia/Pyongyang",
    "iso:country":"KP",
    "name:und_x_variant":[
        "\uc544\ub7ab\uc22b\uace8",
        "Araessuk-kol"
    ],
    "wof:name":"Araessuk-kol",
    "wof:placetype":"locality"
},
  "geometry": {"coordinates":[127.67667,39.8575],"type":"Point"}
}