{
  "type": "Feature",
  "properties": {
    "gn:admin1_code":"11.0",
    "gn:asciiname":"Hong-dong",
    "gn:country_code":"KP",
    "gn:dem":236,
    "gn:feature_class":"P",
    "gn:feature_code":"PPL",
    "gn:name":"Hong-dong",
    "gn:population":0,
    "gn:timezone":"Asia/Pyongyang",
    "iso:country":"KP",
    "name:und_x_variant":[
        "\ud64d\ub3d9",
        "Hong-dong"
    ],
    "wof:name":"Hong-dong",
    "wof:placetype":"locality"
},
  "geometry": {"coordinates":[125.21138999999999,40.25944000000001],"type":"Point"}
}