{
  "type": "Feature",
  "properties": {
    "gn:admin1_code":"11.0",
    "gn:asciiname":"Taehungdongnamsori",
    "gn:country_code":"KP",
    "gn:dem":7,
    "gn:feature_class":"P",
    "gn:feature_code":"PPL",
    "gn:name":"Taeh\u016dngdongnamsori",
    "gn:population":0,
    "gn:timezone":"Asia/Pyongyang",
    "iso:country":"KP",
    "name:kor_x_preferred":[
        "\ub300\ud765\ub3d9\ub0a8\uc18c\ub9ac"
    ],
    "name:kor_x_variant":[
        "Taeh\u016dngdongnamsori"
    ],
    "wof:name":"Taehungdongnamsori",
    "wof:placetype":"locality"
},
  "geometry": {"coordinates":[125.38139,39.56333],"type":"Point"}
}