{
  "type": "Feature",
  "properties": {
    "gn:admin1_code":"11.0",
    "gn:asciiname":"Kump'ung-dong",
    "gn:country_code":"KP",
    "gn:dem":273,
    "gn:feature_class":"P",
    "gn:feature_code":"PPL",
    "gn:name":"K\u016dmp\u2019ung-dong",
    "gn:population":0,
    "gn:timezone":"Asia/Pyongyang",
    "iso:country":"KP",
    "name:und_x_variant":[
        "\uae08\ud48d\ub3d9",
        "K\u016dmp\u2019ung-dong"
    ],
    "wof:name":"Kump'ung-dong",
    "wof:placetype":"locality"
},
  "geometry": {"coordinates":[125.29583,40.22611],"type":"Point"}
}