{
  "type": "Feature",
  "properties": {
    "gn:admin1_code":"7.0",
    "gn:asciiname":"Hoehwa-dong",
    "gn:country_code":"KP",
    "gn:dem":126,
    "gn:feature_class":"P",
    "gn:feature_code":"PPL",
    "gn:name":"Hoehwa-dong",
    "gn:population":0,
    "gn:timezone":"Asia/Pyongyang",
    "iso:country":"KP",
    "wof:name":"Hoehwa-dong",
    "wof:placetype":"locality"
},
  "geometry": {"coordinates":[126.20193999999999,38.43306],"type":"Point"}
}