{
  "type": "Feature",
  "properties": {
    "gn:admin1_code":"11.0",
    "gn:asciiname":"Tongjong-ni",
    "gn:country_code":"KP",
    "gn:dem":18,
    "gn:feature_class":"P",
    "gn:feature_code":"PPL",
    "gn:name":"Tongj\u014fng-ni",
    "gn:population":0,
    "gn:timezone":"Asia/Pyongyang",
    "iso:country":"KP",
    "name:und_x_variant":[
        "\ub3d9\uc815\ub9ac",
        "Tongj\u014fng-ni"
    ],
    "wof:name":"Tongjong-ni",
    "wof:placetype":"locality"
},
  "geometry": {"coordinates":[124.52306000000002,39.855],"type":"Point"}
}