{
  "type": "Feature",
  "properties": {
    "gn:admin1_code":"17.0",
    "gn:asciiname":"Sinch'am",
    "gn:country_code":"KP",
    "gn:dem":653,
    "gn:feature_class":"P",
    "gn:feature_code":"PPL",
    "gn:name":"Sinch\u2019am",
    "gn:population":0,
    "gn:timezone":"Asia/Pyongyang",
    "iso:country":"KP",
    "name:und_x_variant":[
        "Shinchon",
        "Shintan",
        "\uc2e0\ucc38",
        "Sinch\u2019am"
    ],
    "wof:name":"Sinch'am",
    "wof:placetype":"locality"
},
  "geometry": {"coordinates":[129.41917000000001,42.11583],"type":"Point"}
}