{
  "type": "Feature",
  "properties": {
    "gn:admin1_code":"3.0",
    "gn:asciiname":"Munch'ol-li",
    "gn:country_code":"KP",
    "gn:dem":1164,
    "gn:feature_class":"P",
    "gn:feature_code":"PPL",
    "gn:name":"Munch\u2019\u014fl-li",
    "gn:population":0,
    "gn:timezone":"Asia/Pyongyang",
    "iso:country":"KP",
    "name:und_x_variant":[
        "\ubb38\ucc9c\ub9ac",
        "Munch\u2019\u014fn-ni",
        "Munch\u2019\u014fl-li"
    ],
    "wof:name":"Munch'ol-li",
    "wof:placetype":"locality"
},
  "geometry": {"coordinates":[127.20139,40.4425],"type":"Point"}
}