{
  "type": "Feature",
  "properties": {
    "gn:admin1_code":"6.0",
    "gn:asciiname":"Andumu",
    "gn:country_code":"KP",
    "gn:dem":28,
    "gn:feature_class":"P",
    "gn:feature_code":"PPL",
    "gn:name":"Andumu",
    "gn:population":0,
    "gn:timezone":"Asia/Pyongyang",
    "iso:country":"KP",
    "name:und_x_variant":[
        "Andu-ri",
        "\uc548\ub450\ubb34",
        "Andumu"
    ],
    "wof:name":"Andumu",
    "wof:placetype":"locality"
},
  "geometry": {"coordinates":[125.25333000000001,37.92],"type":"Point"}
}