{
  "type": "Feature",
  "properties": {
    "gn:admin1_code":"3.0",
    "gn:asciiname":"Chinjanggae",
    "gn:country_code":"KP",
    "gn:dem":337,
    "gn:feature_class":"P",
    "gn:feature_code":"PPL",
    "gn:name":"Chinjanggae",
    "gn:population":0,
    "gn:timezone":"Asia/Pyongyang",
    "iso:country":"KP",
    "name:kor_x_preferred":[
        "\uc9c4\uc7a5\uac1c"
    ],
    "wof:name":"Chinjanggae",
    "wof:placetype":"locality"
},
  "geometry": {"coordinates":[127.05194,39.68194],"type":"Point"}
}