{
  "type": "Feature",
  "properties": {
    "gn:admin1_code":"6.0",
    "gn:asciiname":"Kamch'on-dong",
    "gn:country_code":"KP",
    "gn:dem":96,
    "gn:feature_class":"P",
    "gn:feature_code":"PPL",
    "gn:name":"Kamch\u2019\u014fn-dong",
    "gn:population":0,
    "gn:timezone":"Asia/Pyongyang",
    "iso:country":"KP",
    "name:kor_x_preferred":[
        "\uac10\ucc9c\ub3d9"
    ],
    "name:und_x_variant":[
        "Kamch\u2019\u014fn-dong"
    ],
    "wof:name":"Kamch'on-dong",
    "wof:placetype":"locality"
},
  "geometry": {"coordinates":[125.425,38.22083],"type":"Point"}
}