{
  "type": "Feature",
  "properties": {
    "gn:admin1_code":"6.0",
    "gn:asciiname":"Chang-dong",
    "gn:country_code":"KP",
    "gn:dem":54,
    "gn:feature_class":"P",
    "gn:feature_code":"PPL",
    "gn:name":"Chang-dong",
    "gn:population":0,
    "gn:timezone":"Asia/Pyongyang",
    "iso:country":"KP",
    "wof:name":"Chang-dong",
    "wof:placetype":"locality"
},
  "geometry": {"coordinates":[125.80833,38.22722],"type":"Point"}
}