{
  "type": "Feature",
  "properties": {
    "gn:admin1_code":"3.0",
    "gn:asciiname":"T'anbu-gol",
    "gn:country_code":"KP",
    "gn:dem":532,
    "gn:feature_class":"P",
    "gn:feature_code":"PPL",
    "gn:name":"T\u2019anbu-gol",
    "gn:population":0,
    "gn:timezone":"Asia/Pyongyang",
    "iso:country":"KP",
    "name:und_x_variant":[
        "\ud0c4\ubd80\uace8",
        "T\u2019anbu-gol"
    ],
    "wof:name":"T'anbu-gol",
    "wof:placetype":"locality"
},
  "geometry": {"coordinates":[127.82028,40.29833],"type":"Point"}
}