{
  "type": "Feature",
  "properties": {
    "gn:admin1_code":"3.0",
    "gn:asciiname":"Miruktangmal",
    "gn:country_code":"KP",
    "gn:dem":15,
    "gn:feature_class":"P",
    "gn:feature_code":"PPL",
    "gn:name":"Mir\u016dktangmal",
    "gn:population":0,
    "gn:timezone":"Asia/Pyongyang",
    "iso:country":"KP",
    "name:und_x_variant":[
        "\ubbf8\ub975\ub2f9\ub9d0",
        "Mir\u016dktangmal"
    ],
    "wof:name":"Miruktangmal",
    "wof:placetype":"locality"
},
  "geometry": {"coordinates":[127.21138999999999,39.55417],"type":"Point"}
}