{
  "type": "Feature",
  "properties": {
    "gn:admin1_code":"1.0",
    "gn:asciiname":"Munak-tong",
    "gn:country_code":"KP",
    "gn:dem":252,
    "gn:feature_class":"P",
    "gn:feature_code":"PPL",
    "gn:name":"Munak-tong",
    "gn:population":0,
    "gn:timezone":"Asia/Pyongyang",
    "iso:country":"KP",
    "name:und_x_variant":[
        "Munan-dong",
        "Munang-ni",
        "\ubb38\uc545\ub3d9",
        "Munak-tong"
    ],
    "wof:name":"Munak-tong",
    "wof:placetype":"locality"
},
  "geometry": {"coordinates":[126.3325,41.20194],"type":"Point"}
}