{
  "type": "Feature",
  "properties": {
    "gn:admin1_code":"3.0",
    "gn:asciiname":"P'ungdung-ni",
    "gn:country_code":"KP",
    "gn:dem":14,
    "gn:feature_class":"P",
    "gn:feature_code":"PPL",
    "gn:name":"P\u2019ungd\u016dng-ni",
    "gn:population":0,
    "gn:timezone":"Asia/Pyongyang",
    "iso:country":"KP",
    "name:eng_x_preferred":[
        "P'ungdung"
    ],
    "name:eng_x_variant":[
        "P'ungdung-ni"
    ],
    "name:und_x_variant":[
        "\ud48d\ub4f1\ub9ac",
        "P\u2019ungd\u016dng-ni"
    ],
    "wof:name":"P'ungdung",
    "wof:placetype":"locality"
},
  "geometry": {"coordinates":[127.28167000000001,39.53583],"type":"Point"}
}