{
  "type": "Feature",
  "properties": {
    "gn:admin1_code":"7.0",
    "gn:asciiname":"Kadong-ni",
    "gn:country_code":"KP",
    "gn:dem":87,
    "gn:feature_class":"P",
    "gn:feature_code":"PPL",
    "gn:name":"Kad\u014fng-ni",
    "gn:population":0,
    "gn:timezone":"Asia/Pyongyang",
    "iso:country":"KP",
    "wof:name":"Kadong-ni",
    "wof:placetype":"locality"
},
  "geometry": {"coordinates":[126.54000000000001,38.17806],"type":"Point"}
}