{
  "type": "Feature",
  "properties": {
    "gn:admin1_code":"3.0",
    "gn:asciiname":"Aeng-gol",
    "gn:country_code":"KP",
    "gn:dem":322,
    "gn:feature_class":"P",
    "gn:feature_code":"PPL",
    "gn:name":"Aeng-gol",
    "gn:population":0,
    "gn:timezone":"Asia/Pyongyang",
    "iso:country":"KP",
    "name:und_x_variant":[
        "\uc575\uace8",
        "Aeng-gol"
    ],
    "wof:name":"Aeng-gol",
    "wof:placetype":"locality"
},
  "geometry": {"coordinates":[127.26528,39.87667],"type":"Point"}
}