{
  "type": "Feature",
  "properties": {
    "gn:admin1_code":"7.0",
    "gn:asciiname":"Taeo-ri",
    "gn:country_code":"KP",
    "gn:dem":58,
    "gn:feature_class":"P",
    "gn:feature_code":"PPL",
    "gn:name":"Taeo-ri",
    "gn:population":0,
    "gn:timezone":"Asia/Pyongyang",
    "iso:country":"KP",
    "name:kor_x_preferred":[
        "\ub300\uc624\ub9ac"
    ],
    "wof:name":"Taeo-ri",
    "wof:placetype":"locality"
},
  "geometry": {"coordinates":[126.59721999999999,38.28139],"type":"Point"}
}