{
  "type": "Feature",
  "properties": {
    "gn:admin1_code":"6.0",
    "gn:asciiname":"An'gok",
    "gn:country_code":"KP",
    "gn:dem":79,
    "gn:feature_class":"P",
    "gn:feature_code":"PPL",
    "gn:name":"An\u2019gok",
    "gn:population":0,
    "gn:timezone":"Asia/Pyongyang",
    "iso:country":"KP",
    "name:kor_x_preferred":[
        "\uc548\uace1"
    ],
    "name:kor_x_variant":[
        "An\u2019gok"
    ],
    "wof:name":"An'gok",
    "wof:placetype":"locality"
},
  "geometry": {"coordinates":[125.3725,38.29972],"type":"Point"}
}