{
  "type": "Feature",
  "properties": {
    "gn:admin1_code":"15.0",
    "gn:admin2_code":"P\u2019\u014fngw\u014fn-gun",
    "gn:asciiname":"Kukhwa-dong",
    "gn:country_code":"KP",
    "gn:dem":17,
    "gn:feature_class":"P",
    "gn:feature_code":"PPL",
    "gn:name":"Kukhwa-dong",
    "gn:population":0,
    "gn:timezone":"Asia/Pyongyang",
    "iso:country":"KP",
    "wof:name":"Kukhwa-dong",
    "wof:placetype":"locality"
},
  "geometry": {"coordinates":[125.56944,39.31556],"type":"Point"}
}