{
  "type": "Feature",
  "properties": {
    "gn:admin1_code":"15.0",
    "gn:asciiname":"Ch'ogi-dong",
    "gn:country_code":"KP",
    "gn:dem":253,
    "gn:feature_class":"P",
    "gn:feature_code":"PPL",
    "gn:name":"Ch\u2019\u014fgi-dong",
    "gn:population":0,
    "gn:timezone":"Asia/Pyongyang",
    "iso:country":"KP",
    "name:kor_x_preferred":[
        "\ucc99\uc774\ub3d9"
    ],
    "name:kor_x_variant":[
        "Ch\u2019\u014fgi-dong"
    ],
    "wof:name":"Ch'ogi-dong",
    "wof:placetype":"locality"
},
  "geometry": {"coordinates":[126.58750000000001,39.23167],"type":"Point"}
}