{
  "type": "Feature",
  "properties": {
    "gn:admin1_code":"18.0",
    "gn:asciiname":"Sahoe-ri",
    "gn:cc2":"KP",
    "gn:country_code":"KP",
    "gn:dem":24,
    "gn:feature_class":"P",
    "gn:feature_code":"PPL",
    "gn:name":"Sahoe-ri",
    "gn:population":0,
    "gn:timezone":"Asia/Pyongyang",
    "iso:country":"KP",
    "name:und_x_variant":[
        "Shikai",
        "Sahoe",
        "\uc0ac\ud68c\ub9ac",
        "Sahoe-ri"
    ],
    "wof:name":"Sahoe-ri",
    "wof:placetype":"locality"
},
  "geometry": {"coordinates":[130.51389,42.46083],"type":"Point"}
}