{
  "type": "Feature",
  "properties": {
    "gn:admin1_code":"7.0",
    "gn:asciiname":"Sach'ongmal",
    "gn:country_code":"KP",
    "gn:dem":74,
    "gn:feature_class":"P",
    "gn:feature_code":"PPL",
    "gn:name":"Sach\u2019\u014fngmal",
    "gn:population":0,
    "gn:timezone":"Asia/Pyongyang",
    "iso:country":"KP",
    "wof:name":"Sach'ongmal",
    "wof:placetype":"locality"
},
  "geometry": {"coordinates":[126.72889000000001,38.3025],"type":"Point"}
}