{
  "type": "Feature",
  "properties": {
    "gn:admin1_code":"6.0",
    "gn:asciiname":"Uiyo-dong",
    "gn:country_code":"KP",
    "gn:dem":11,
    "gn:feature_class":"P",
    "gn:feature_code":"PPL",
    "gn:name":"\u016ciyo-dong",
    "gn:population":0,
    "gn:timezone":"Asia/Pyongyang",
    "iso:country":"KP",
    "name:kor_x_preferred":[
        "\uc758\uc694\ub3d9"
    ],
    "name:kor_x_variant":[
        "\u016ciyo-dong"
    ],
    "wof:name":"Uiyo-dong",
    "wof:placetype":"locality"
},
  "geometry": {"coordinates":[125.52694,38.65528],"type":"Point"}
}