{
  "type": "Feature",
  "properties": {
    "gn:admin1_code":"0.0",
    "gn:asciiname":"P'ungso-ri",
    "gn:country_code":"KP",
    "gn:dem":658,
    "gn:feature_class":"P",
    "gn:feature_code":"PPL",
    "gn:name":"P\u2019ungs\u014f-ri",
    "gn:population":0,
    "gn:timezone":"Asia/Pyongyang",
    "iso:country":"KP",
    "name:kor_x_preferred":[
        "\ud48d\uc11c\ub9ac"
    ],
    "name:und_x_variant":[
        "P\u2019ungs\u014f-ri"
    ],
    "wof:name":"P'ungso-ri",
    "wof:placetype":"locality"
},
  "geometry": {"coordinates":[127.16667,39.91667],"type":"Point"}
}