{
  "type": "Feature",
  "properties": {
    "gn:admin1_code":"15.0",
    "gn:asciiname":"K'umnyo-dong",
    "gn:country_code":"KP",
    "gn:dem":584,
    "gn:feature_class":"P",
    "gn:feature_code":"PPL",
    "gn:name":"K\u2019\u016dmny\u014f-dong",
    "gn:population":0,
    "gn:timezone":"Asia/Pyongyang",
    "iso:country":"KP",
    "name:und_x_variant":[
        "\uae08\ub824\ub3d9",
        "K\u2019\u016dmny\u014f-dong"
    ],
    "wof:name":"K'umnyo-dong",
    "wof:placetype":"locality"
},
  "geometry": {"coordinates":[126.95583000000001,40.055],"type":"Point"}
}