{
  "type": "Feature",
  "properties": {
    "gn:admin1_code":"6.0",
    "gn:admin2_code":"Paech'\u014fn-gun",
    "gn:asciiname":"Kobang-dong",
    "gn:country_code":"KP",
    "gn:dem":18,
    "gn:feature_class":"P",
    "gn:feature_code":"PPL",
    "gn:name":"Kobang-dong",
    "gn:population":0,
    "gn:timezone":"Asia/Pyongyang",
    "iso:country":"KP",
    "name:kor_x_preferred":[
        "\uace0\ubc29\ub3d9"
    ],
    "wof:name":"Kobang-dong",
    "wof:placetype":"locality"
},
  "geometry": {"coordinates":[126.35333,37.88889],"type":"Point"}
}