{
  "type": "Feature",
  "properties": {
    "gn:admin1_code":"6.0",
    "gn:asciiname":"Yongyang-ni",
    "gn:country_code":"KP",
    "gn:dem":24,
    "gn:feature_class":"P",
    "gn:feature_code":"PPL",
    "gn:name":"Y\u014fngyang-ni",
    "gn:population":0,
    "gn:timezone":"Asia/Pyongyang",
    "iso:country":"KP",
    "wof:name":"Yongyang-ni",
    "wof:placetype":"locality"
},
  "geometry": {"coordinates":[125.77611,38.02444000000001],"type":"Point"}
}