{
  "type": "Feature",
  "properties": {
    "gn:admin1_code":"12.0",
    "gn:asciiname":"Tongp'o-dong",
    "gn:country_code":"KP",
    "gn:dem":55,
    "gn:feature_class":"P",
    "gn:feature_code":"PPL",
    "gn:name":"Tongp\u2019o-dong",
    "gn:population":0,
    "gn:timezone":"Asia/Pyongyang",
    "iso:country":"KP",
    "name:kor_x_preferred":[
        "\ub3d9\ud3ec\ub3d9"
    ],
    "name:und_x_variant":[
        "Dong Poli",
        "Tongpo-ni",
        "T\u014dho",
        "Tongp\u2019o-ri",
        "T\u014dho-ri",
        "Tongp\u2019o-dong",
        "Dongpodong"
    ],
    "wof:name":"Tongp'o-dong",
    "wof:placetype":"locality"
},
  "geometry": {"coordinates":[125.74583,39.08583],"type":"Point"}
}