{
  "type": "Feature",
  "properties": {
    "gn:admin1_code":"6.0",
    "gn:asciiname":"Sinnoksan",
    "gn:country_code":"KP",
    "gn:dem":20,
    "gn:feature_class":"P",
    "gn:feature_code":"PPL",
    "gn:name":"Sinnoksan",
    "gn:population":0,
    "gn:timezone":"Asia/Pyongyang",
    "iso:country":"KP",
    "name:und_x_variant":[
        "\uc2e0\ub179\uc0b0",
        "Sinnoksan"
    ],
    "wof:name":"Sinnoksan",
    "wof:placetype":"locality"
},
  "geometry": {"coordinates":[125.61750000000001,37.95444000000001],"type":"Point"}
}