{
  "type": "Feature",
  "properties": {
    "gn:admin1_code":"3.0",
    "gn:asciiname":"Pyon'ga-dong",
    "gn:country_code":"KP",
    "gn:dem":702,
    "gn:feature_class":"P",
    "gn:feature_code":"PPL",
    "gn:name":"Py\u014fn\u2019ga-dong",
    "gn:population":0,
    "gn:timezone":"Asia/Pyongyang",
    "iso:country":"KP",
    "name:und_x_variant":[
        "\ubcc0\uac00\ub3d9",
        "Py\u014fn\u2019ga-dong"
    ],
    "wof:name":"Pyon'ga-dong",
    "wof:placetype":"locality"
},
  "geometry": {"coordinates":[128.53389000000001,40.57611],"type":"Point"}
}