{
  "type": "Feature",
  "properties": {
    "gn:admin1_code":"17.0",
    "gn:asciiname":"Iso",
    "gn:country_code":"KP",
    "gn:dem":480,
    "gn:feature_class":"P",
    "gn:feature_code":"PPL",
    "gn:name":"Iso",
    "gn:population":0,
    "gn:timezone":"Asia/Pyongyang",
    "iso:country":"KP",
    "wof:name":"Iso",
    "wof:placetype":"locality"
},
  "geometry": {"coordinates":[129.21943999999999,42.20194],"type":"Point"}
}