{
  "type": "Feature",
  "properties": {
    "gn:admin1_code":"6.0",
    "gn:asciiname":"Un'gol-tong",
    "gn:country_code":"KP",
    "gn:dem":18,
    "gn:feature_class":"P",
    "gn:feature_code":"PPL",
    "gn:name":"Un\u2019gol-tong",
    "gn:population":0,
    "gn:timezone":"Asia/Pyongyang",
    "iso:country":"KP",
    "name:kor_x_preferred":[
        "\uc6b4\uace8\ub3d9"
    ],
    "name:kor_x_variant":[
        "Un\u2019gol-tong"
    ],
    "name:und_x_variant":[
        "Un\u2019gok-tong"
    ],
    "wof:name":"Un'gol-tong",
    "wof:placetype":"locality"
},
  "geometry": {"coordinates":[125.47083000000001,38.60139],"type":"Point"}
}