{
  "type": "Feature",
  "properties": {
    "gn:admin1_code":"11.0",
    "gn:asciiname":"Pup'yong-dong",
    "gn:country_code":"KP",
    "gn:dem":163,
    "gn:feature_class":"P",
    "gn:feature_code":"PPL",
    "gn:name":"Pup\u2019y\u014fng-dong",
    "gn:population":0,
    "gn:timezone":"Asia/Pyongyang",
    "iso:country":"KP",
    "name:und_x_variant":[
        "\ubd80\ud3c9\ub3d9",
        "Pup\u2019y\u014fng-dong"
    ],
    "wof:name":"Pup'yong-dong",
    "wof:placetype":"locality"
},
  "geometry": {"coordinates":[125.935,40.11944],"type":"Point"}
}