{
  "type": "Feature",
  "properties": {
    "gn:admin1_code":"9.0",
    "gn:asciiname":"Maegye",
    "gn:country_code":"KP",
    "gn:dem":370,
    "gn:feature_class":"P",
    "gn:feature_code":"PPL",
    "gn:name":"Maegye",
    "gn:population":0,
    "gn:timezone":"Asia/Pyongyang",
    "iso:country":"KP",
    "wof:name":"Maegye",
    "wof:placetype":"locality"
},
  "geometry": {"coordinates":[127.18472,38.42667],"type":"Point"}
}