{
  "type": "Feature",
  "properties": {
    "gn:admin1_code":"3.0",
    "gn:admin2_code":"Kow\u014fn-gun",
    "gn:asciiname":"Kumsu-ri",
    "gn:country_code":"KP",
    "gn:dem":26,
    "gn:feature_class":"P",
    "gn:feature_code":"PPL",
    "gn:name":"K\u016dmsu-ri",
    "gn:population":0,
    "gn:timezone":"Asia/Pyongyang",
    "iso:country":"KP",
    "name:und_x_variant":[
        "K\u016dmsu-ri",
        "\uae08\uc218\ub9ac"
    ],
    "wof:name":"Kumsu-ri",
    "wof:placetype":"locality"
},
  "geometry": {"coordinates":[127.20613,39.46628],"type":"Point"}
}