{
  "type": "Feature",
  "properties": {
    "gn:admin1_code":"9.0",
    "gn:asciiname":"Nung-ni",
    "gn:country_code":"KP",
    "gn:dem":79,
    "gn:feature_class":"P",
    "gn:feature_code":"PPL",
    "gn:name":"N\u016dng-ni",
    "gn:population":0,
    "gn:timezone":"Asia/Pyongyang",
    "iso:country":"KP",
    "name:und_x_variant":[
        "N\u016dng-ni",
        "\ub2a5\ub9ac"
    ],
    "wof:name":"Nung-ni",
    "wof:placetype":"locality"
},
  "geometry": {"coordinates":[127.38939000000001,39.11061],"type":"Point"}
}