{
  "type": "Feature",
  "properties": {
    "gn:admin1_code":"11.0",
    "gn:asciiname":"Hangnim-dong",
    "gn:country_code":"KP",
    "gn:dem":54,
    "gn:feature_class":"P",
    "gn:feature_code":"PPL",
    "gn:name":"Hangnim-dong",
    "gn:population":0,
    "gn:timezone":"Asia/Pyongyang",
    "iso:country":"KP",
    "name:kor_x_preferred":[
        "\ud56d\ub9bc\ub3d9"
    ],
    "wof:name":"Hangnim-dong",
    "wof:placetype":"locality"
},
  "geometry": {"coordinates":[125.43277999999999,39.85167],"type":"Point"}
}