{
  "type": "Feature",
  "properties": {
    "gn:admin1_code":"3.0",
    "gn:asciiname":"Ch'o-ri",
    "gn:country_code":"KP",
    "gn:dem":154,
    "gn:feature_class":"P",
    "gn:feature_code":"PPL",
    "gn:name":"Ch\u2019o-ri",
    "gn:population":0,
    "gn:timezone":"Asia/Pyongyang",
    "iso:country":"KP",
    "name:und_x_variant":[
        "Ch\u2019o-ri",
        "\ucd08\ub9ac"
    ],
    "wof:name":"Ch'o-ri",
    "wof:placetype":"locality"
},
  "geometry": {"coordinates":[128.26213999999999,40.22776],"type":"Point"}
}