{
  "type": "Feature",
  "properties": {
    "gn:admin1_code":"3.0",
    "gn:asciiname":"Nosong",
    "gn:country_code":"KP",
    "gn:dem":658,
    "gn:feature_class":"P",
    "gn:feature_code":"PPL",
    "gn:name":"Nosong",
    "gn:population":0,
    "gn:timezone":"Asia/Pyongyang",
    "iso:country":"KP",
    "name:und_x_variant":[
        "\ub178\uc1a1",
        "Nosong"
    ],
    "wof:name":"Nosong",
    "wof:placetype":"locality"
},
  "geometry": {"coordinates":[128.02778000000001,40.25639],"type":"Point"}
}