{
  "type": "Feature",
  "properties": {
    "gn:admin1_code":"0.0",
    "gn:asciiname":"Samp'o-ch'on",
    "gn:country_code":"KP",
    "gn:dem":1392,
    "gn:feature_class":"P",
    "gn:feature_code":"PPL",
    "gn:name":"Samp\u2019o-ch\u2019on",
    "gn:population":0,
    "gn:timezone":"Asia/Pyongyang",
    "iso:country":"KP",
    "name:kor_x_preferred":[
        "\uc0bc\ud3ec\ucd0c"
    ],
    "name:und_x_variant":[
        "Samp\u2019o-ch\u2019on"
    ],
    "wof:name":"Samp'o-ch'on",
    "wof:placetype":"locality"
},
  "geometry": {"coordinates":[128.05000000000001,40.65],"type":"Point"}
}