{
  "type": "Feature",
  "properties": {
    "gn:admin1_code":"7.0",
    "gn:asciiname":"Songu-dong",
    "gn:country_code":"KP",
    "gn:dem":187,
    "gn:feature_class":"P",
    "gn:feature_code":"PPL",
    "gn:name":"S\u014fngu-dong",
    "gn:population":0,
    "gn:timezone":"Asia/Pyongyang",
    "iso:country":"KP",
    "name:kor_x_preferred":[
        "\uc131\uc6b0\ub3d9"
    ],
    "name:kor_x_variant":[
        "S\u014fngu-dong"
    ],
    "wof:name":"Songu-dong",
    "wof:placetype":"locality"
},
  "geometry": {"coordinates":[126.6375,38.52056],"type":"Point"}
}