{
  "type": "Feature",
  "properties": {
    "gn:admin1_code":"6.0",
    "gn:asciiname":"Sangdobong",
    "gn:country_code":"KP",
    "gn:dem":99,
    "gn:feature_class":"P",
    "gn:feature_code":"PPL",
    "gn:name":"Sangdobong",
    "gn:population":0,
    "gn:timezone":"Asia/Pyongyang",
    "iso:country":"KP",
    "name:kor_x_preferred":[
        "\uc0c1\ub3c4\ubd09"
    ],
    "wof:name":"Sangdobong",
    "wof:placetype":"locality"
},
  "geometry": {"coordinates":[125.31056,38.26833],"type":"Point"}
}