{
  "type": "Feature",
  "properties": {
    "gn:admin1_code":"3.0",
    "gn:asciiname":"Hunggyong-ni",
    "gn:country_code":"KP",
    "gn:dem":117,
    "gn:feature_class":"P",
    "gn:feature_code":"PPL",
    "gn:name":"H\u016dnggy\u014fng-ni",
    "gn:population":0,
    "gn:timezone":"Asia/Pyongyang",
    "iso:country":"KP",
    "name:eng_x_preferred":[
        "Hunggyong"
    ],
    "name:eng_x_variant":[
        "Hunggyong-ni"
    ],
    "name:und_x_variant":[
        "\ud765\uacbd\ub9ac",
        "H\u016dnggy\u014fng-ni"
    ],
    "wof:name":"Hunggyong",
    "wof:placetype":"locality"
},
  "geometry": {"coordinates":[127.55249999999999,40.18139],"type":"Point"}
}