{
  "type": "Feature",
  "properties": {
    "gn:admin1_code":"15.0",
    "gn:asciiname":"K'un'garae-gol",
    "gn:country_code":"KP",
    "gn:dem":908,
    "gn:feature_class":"P",
    "gn:feature_code":"PPL",
    "gn:name":"K\u2019un\u2019garae-gol",
    "gn:population":0,
    "gn:timezone":"Asia/Pyongyang",
    "iso:country":"KP",
    "name:und_x_variant":[
        "\ud070\uac00\ub798\uace8",
        "K\u2019un\u2019garae-gol"
    ],
    "wof:name":"K'un'garae-gol",
    "wof:placetype":"locality"
},
  "geometry": {"coordinates":[126.91388999999999,39.89472],"type":"Point"}
}