{
  "type": "Feature",
  "properties": {
    "gn:admin1_code":"1.0",
    "gn:asciiname":"Uijin-dong",
    "gn:country_code":"KP",
    "gn:dem":296,
    "gn:feature_class":"P",
    "gn:feature_code":"PPLA3",
    "gn:name":"\u016cijin-dong",
    "gn:population":0,
    "gn:timezone":"Asia/Pyongyang",
    "iso:country":"KP",
    "name:kor_x_preferred":[
        "\u016cijin-dong"
    ],
    "name:kor_x_variant":[
        "\uc758\uc9c4\ub3d9",
        "\u016cijil-li",
        "\uc758\uc9c4\ub9ac"
    ],
    "name:und_x_variant":[
        "\u016cijin-ni"
    ],
    "wof:name":"Uijin-dong",
    "wof:placetype":"locality"
},
  "geometry": {"coordinates":[126.49584,40.97518],"type":"Point"}
}