{
  "type": "Feature",
  "properties": {
    "gn:admin1_code":"9.0",
    "gn:asciiname":"Yonmu-dong",
    "gn:country_code":"KP",
    "gn:dem":400,
    "gn:feature_class":"P",
    "gn:feature_code":"PPL",
    "gn:name":"Y\u014fnmu-dong",
    "gn:population":0,
    "gn:timezone":"Asia/Pyongyang",
    "iso:country":"KP",
    "name:und_x_variant":[
        "\uc5f0\ubb34\ub3d9",
        "Y\u014fnmu-dong"
    ],
    "wof:name":"Yonmu-dong",
    "wof:placetype":"locality"
},
  "geometry": {"coordinates":[126.98917,38.8675],"type":"Point"}
}