{
  "type": "Feature",
  "properties": {
    "gn:admin1_code":"11.0",
    "gn:asciiname":"Yangji-dong",
    "gn:country_code":"KP",
    "gn:dem":78,
    "gn:feature_class":"P",
    "gn:feature_code":"PPL",
    "gn:name":"Yangji-dong",
    "gn:population":0,
    "gn:timezone":"Asia/Pyongyang",
    "iso:country":"KP",
    "wof:name":"Yangji-dong",
    "wof:placetype":"locality"
},
  "geometry": {"coordinates":[125.80972,39.78222],"type":"Point"}
}