{
  "type": "Feature",
  "properties": {
    "gn:admin1_code":"6.0",
    "gn:asciiname":"Changjakkol",
    "gn:country_code":"KP",
    "gn:dem":17,
    "gn:feature_class":"P",
    "gn:feature_code":"PPL",
    "gn:name":"Changjakkol",
    "gn:population":0,
    "gn:timezone":"Asia/Pyongyang",
    "iso:country":"KP",
    "name:kor_x_preferred":[
        "\uc7a5\uc791\uace8"
    ],
    "name:und_x_variant":[
        "Changjagol",
        "Changjakkol"
    ],
    "wof:name":"Changjakkol",
    "wof:placetype":"locality"
},
  "geometry": {"coordinates":[126.28222,37.90361],"type":"Point"}
}