{
  "type": "Feature",
  "properties": {
    "gn:admin1_code":"15.0",
    "gn:admin2_code":"Kaech\u2019\u014fn-si",
    "gn:asciiname":"Naenjongcha'm",
    "gn:country_code":"KP",
    "gn:dem":145,
    "gn:feature_class":"P",
    "gn:feature_code":"PPL",
    "gn:name":"Naenj\u014fngcha\u2019m",
    "gn:population":0,
    "gn:timezone":"Asia/Pyongyang",
    "iso:country":"KP",
    "wof:name":"Naenjongcha'm",
    "wof:placetype":"locality"
},
  "geometry": {"coordinates":[126.02500000000001,39.56667],"type":"Point"}
}