{
  "type": "Feature",
  "properties": {
    "gn:admin1_code":"1.0",
    "gn:asciiname":"Hungju-dong",
    "gn:country_code":"KP",
    "gn:dem":297,
    "gn:feature_class":"P",
    "gn:feature_code":"PPLA3",
    "gn:name":"H\u016dngju-dong",
    "gn:population":0,
    "gn:timezone":"Asia/Pyongyang",
    "iso:country":"KP",
    "name:und_x_variant":[
        "H\u016dngju-ri",
        "\ud765\uc8fc\ub3d9",
        "H\u016dngju-dong"
    ],
    "wof:name":"Hungju-dong",
    "wof:placetype":"locality"
},
  "geometry": {"coordinates":[126.54756,40.99629],"type":"Point"}
}