{
  "type": "Feature",
  "properties": {
    "gn:admin1_code":"9.0",
    "gn:asciiname":"Hayongul-li",
    "gn:cc2":"KP",
    "gn:country_code":"KP",
    "gn:dem":65,
    "gn:feature_class":"P",
    "gn:feature_code":"PPL",
    "gn:name":"Hayongul-li",
    "gn:population":0,
    "gn:timezone":"Asia/Pyongyang",
    "iso:country":"KP",
    "name:und_x_variant":[
        "Ha-yongun-ni",
        "Hayongul-li",
        "\ud558\uc6a9\uc6b4\ub9ac"
    ],
    "wof:name":"Hayongul-li",
    "wof:placetype":"locality"
},
  "geometry": {"coordinates":[127.4675,39.03833],"type":"Point"}
}