{
  "type": "Feature",
  "properties": {
    "gn:admin1_code":"7.0",
    "gn:admin2_code":"Y\u014fnsan-gun",
    "gn:asciiname":"Ham-ch'on",
    "gn:country_code":"KP",
    "gn:dem":166,
    "gn:feature_class":"P",
    "gn:feature_code":"PPL",
    "gn:name":"Ham-ch\u2019on",
    "gn:population":0,
    "gn:timezone":"Asia/Pyongyang",
    "iso:country":"KP",
    "wof:name":"Ham-ch'on",
    "wof:placetype":"locality"
},
  "geometry": {"coordinates":[126.27056,38.82694],"type":"Point"}
}