{
  "type": "Feature",
  "properties": {
    "gn:admin1_code":"13.0",
    "gn:asciiname":"Kubo-ri",
    "gn:country_code":"KP",
    "gn:dem":825,
    "gn:feature_class":"P",
    "gn:feature_code":"PPL",
    "gn:name":"Kubo-ri",
    "gn:population":0,
    "gn:timezone":"Asia/Pyongyang",
    "iso:country":"KP",
    "name:kor_x_preferred":[
        "\uad6c\ubcf4\ub9ac"
    ],
    "wof:name":"Kubo-ri",
    "wof:placetype":"locality"
},
  "geometry": {"coordinates":[128.27860999999999,41.22056],"type":"Point"}
}