{
  "type": "Feature",
  "properties": {
    "gn:admin1_code":"12.0",
    "gn:asciiname":"Kangsom",
    "gn:country_code":"KP",
    "gn:dem":6,
    "gn:feature_class":"P",
    "gn:feature_code":"PPL",
    "gn:name":"Kangs\u014fm",
    "gn:population":0,
    "gn:timezone":"Asia/Pyongyang",
    "iso:country":"KP",
    "name:kor_x_preferred":[
        "Kangs\u014fm"
    ],
    "name:kor_x_variant":[
        "\uac15\uc12c"
    ],
    "name:und_x_variant":[
        "Gangseom"
    ],
    "wof:name":"Kangsom",
    "wof:placetype":"locality"
},
  "geometry": {"coordinates":[125.61667,38.93333],"type":"Point"}
}