{
  "type": "Feature",
  "properties": {
    "gn:admin1_code":"9.0",
    "gn:asciiname":"Sinsong-ni",
    "gn:country_code":"KP",
    "gn:dem":271,
    "gn:feature_class":"P",
    "gn:feature_code":"PPL",
    "gn:name":"Sins\u014fng-ni",
    "gn:population":0,
    "gn:timezone":"Asia/Pyongyang",
    "iso:country":"KP",
    "name:eng_x_preferred":[
        "Sinsong"
    ],
    "name:eng_x_variant":[
        "Sinsong-ni"
    ],
    "name:und_x_variant":[
        "\uc2e0\uc131\ub9ac",
        "Sins\u014fng-ni"
    ],
    "wof:name":"Sinsong",
    "wof:placetype":"locality"
},
  "geometry": {"coordinates":[127.75472000000001,38.55167],"type":"Point"}
}