{
  "type": "Feature",
  "properties": {
    "gn:admin1_code":"7.0",
    "gn:asciiname":"Pudae-dong",
    "gn:country_code":"KP",
    "gn:dem":97,
    "gn:feature_class":"P",
    "gn:feature_code":"PPL",
    "gn:name":"Pudae-dong",
    "gn:population":0,
    "gn:timezone":"Asia/Pyongyang",
    "iso:country":"KP",
    "wof:name":"Pudae-dong",
    "wof:placetype":"locality"
},
  "geometry": {"coordinates":[126.64139,38.35917],"type":"Point"}
}