{
  "type": "Feature",
  "properties": {
    "gn:admin1_code":"11.0",
    "gn:admin2_code":"Kujang-gun",
    "gn:asciiname":"Kaehwa-ri",
    "gn:cc2":"KP",
    "gn:country_code":"KP",
    "gn:dem":287,
    "gn:feature_class":"P",
    "gn:feature_code":"PPL",
    "gn:name":"Kaehwa-ri",
    "gn:population":0,
    "gn:timezone":"Asia/Pyongyang",
    "iso:country":"KP",
    "name:kor_x_preferred":[
        "\uac1c\ud654\ub9ac"
    ],
    "name:und_x_variant":[
        "Kaehwa-dong",
        "Kaehwa-ri"
    ],
    "wof:name":"Kaehwa-ri",
    "wof:placetype":"locality"
},
  "geometry": {"coordinates":[126.33667,39.89444],"type":"Point"}
}