{
  "type": "Feature",
  "properties": {
    "gn:admin1_code":"15.0",
    "gn:asciiname":"Konnunsam-gol",
    "gn:country_code":"KP",
    "gn:dem":24,
    "gn:feature_class":"P",
    "gn:feature_code":"PPL",
    "gn:name":"K\u014fnn\u016dnsam-gol",
    "gn:population":0,
    "gn:timezone":"Asia/Pyongyang",
    "iso:country":"KP",
    "name:und_x_variant":[
        "W\u014flsam-dong",
        "K\u014fnn\u016dnsam-kol",
        "K\u014fnn\u014fnsam-gol",
        "K\u014fnn\u016dnsam-gol"
    ],
    "wof:name":"Konnunsam-gol",
    "wof:placetype":"locality"
},
  "geometry": {"coordinates":[125.46138999999999,39.19278],"type":"Point"}
}