{
  "type": "Feature",
  "properties": {
    "gn:admin1_code":"15.0",
    "gn:asciiname":"Ssangp'o",
    "gn:country_code":"KP",
    "gn:dem":350,
    "gn:feature_class":"P",
    "gn:feature_code":"PPL",
    "gn:name":"Ssangp\u2019o",
    "gn:population":0,
    "gn:timezone":"Asia/Pyongyang",
    "iso:country":"KP",
    "name:und_x_variant":[
        "\uc30d\ud3ec",
        "Ssangp\u2019o"
    ],
    "wof:name":"Ssangp'o",
    "wof:placetype":"locality"
},
  "geometry": {"coordinates":[126.79833000000001,39.18444],"type":"Point"}
}