{
  "type": "Feature",
  "properties": {
    "gn:admin1_code":"15.0",
    "gn:asciiname":"Kajung-ni",
    "gn:country_code":"KP",
    "gn:dem":10,
    "gn:feature_class":"P",
    "gn:feature_code":"PPL",
    "gn:name":"Kaj\u016dng-ni",
    "gn:population":0,
    "gn:timezone":"Asia/Pyongyang",
    "iso:country":"KP",
    "name:und_x_variant":[
        "\uac00\uc99d\ub9ac",
        "Kaj\u016dng-ni"
    ],
    "wof:name":"Kajung-ni",
    "wof:placetype":"locality"
},
  "geometry": {"coordinates":[125.38556,38.76722],"type":"Point"}
}