{
  "type": "Feature",
  "properties": {
    "gn:admin1_code":"17.0",
    "gn:asciiname":"Samgae",
    "gn:country_code":"KP",
    "gn:dem":648,
    "gn:feature_class":"P",
    "gn:feature_code":"PPL",
    "gn:name":"Samgae",
    "gn:population":0,
    "gn:timezone":"Asia/Pyongyang",
    "iso:country":"KP",
    "name:und_x_variant":[
        "\uc0bc\uac1c"
    ],
    "wof:name":"Samgae",
    "wof:placetype":"locality"
},
  "geometry": {"coordinates":[129.18073000000001,42.03002],"type":"Point"}
}