{
  "type": "Feature",
  "properties": {
    "gn:admin1_code":"1.0",
    "gn:asciiname":"Sangjang-dong",
    "gn:country_code":"KP",
    "gn:dem":370,
    "gn:feature_class":"P",
    "gn:feature_code":"PPL",
    "gn:name":"Sangjang-dong",
    "gn:population":0,
    "gn:timezone":"Asia/Pyongyang",
    "iso:country":"KP",
    "name:und_x_variant":[
        "\uc0c1\uc7a5\ub3d9",
        "Sangjang-dong"
    ],
    "wof:name":"Sangjang-dong",
    "wof:placetype":"locality"
},
  "geometry": {"coordinates":[127.06583000000001,41.69889000000001],"type":"Point"}
}