{
  "type": "Feature",
  "properties": {
    "gn:admin1_code":"3.0",
    "gn:asciiname":"Ssangsang-ni",
    "gn:country_code":"KP",
    "gn:dem":142,
    "gn:feature_class":"P",
    "gn:feature_code":"PPL",
    "gn:name":"Ssangsang-ni",
    "gn:population":0,
    "gn:timezone":"Asia/Pyongyang",
    "iso:country":"KP",
    "name:und_x_variant":[
        "\uc30d\uc0c1\ub9ac"
    ],
    "wof:name":"Ssangsang-ni",
    "wof:placetype":"locality"
},
  "geometry": {"coordinates":[128.68952999999999,40.47347],"type":"Point"}
}