{
  "type": "Feature",
  "properties": {
    "gn:admin1_code":"17.0",
    "gn:asciiname":"Il-tong",
    "gn:cc2":"KP",
    "gn:country_code":"KP",
    "gn:dem":717,
    "gn:feature_class":"P",
    "gn:feature_code":"PPL",
    "gn:name":"Il-tong",
    "gn:population":0,
    "gn:timezone":"Asia/Pyongyang",
    "iso:country":"KP",
    "name:eng_x_preferred":[
        "Il"
    ],
    "name:eng_x_variant":[
        "Il-tong"
    ],
    "name:und_x_variant":[
        "II-dong",
        "Il-tong"
    ],
    "wof:name":"Il",
    "wof:placetype":"locality"
},
  "geometry": {"coordinates":[129.24360999999999,42.045],"type":"Point"}
}