{
  "type": "Feature",
  "properties": {
    "gn:admin1_code":"3.0",
    "gn:asciiname":"Ip'al-li",
    "gn:country_code":"KP",
    "gn:dem":1362,
    "gn:feature_class":"P",
    "gn:feature_code":"PPL",
    "gn:name":"Ip\u2019al-li",
    "gn:population":0,
    "gn:timezone":"Asia/Pyongyang",
    "iso:country":"KP",
    "name:kor_x_preferred":[
        "\uc774\ud314\ub9ac"
    ],
    "name:kor_x_variant":[
        "Ip\u2019al-li"
    ],
    "wof:name":"Ip'al-li",
    "wof:placetype":"locality"
},
  "geometry": {"coordinates":[127.71528000000001,40.52778],"type":"Point"}
}