{
  "type": "Feature",
  "properties": {
    "gn:admin1_code":"9.0",
    "gn:asciiname":"Wont'ong-ni",
    "gn:country_code":"KP",
    "gn:dem":76,
    "gn:feature_class":"P",
    "gn:feature_code":"PPL",
    "gn:name":"W\u014fnt\u2019ong-ni",
    "gn:population":0,
    "gn:timezone":"Asia/Pyongyang",
    "iso:country":"KP",
    "name:kor_x_preferred":[
        "\uc6d0\ud1b5\ub9ac"
    ],
    "name:und_x_variant":[
        "W\u014fnt\u2019ong-ni"
    ],
    "wof:name":"Wont'ong-ni",
    "wof:placetype":"locality"
},
  "geometry": {"coordinates":[127.73139,38.98611],"type":"Point"}
}