{
  "type": "Feature",
  "properties": {
    "gn:admin1_code":"1.0",
    "gn:asciiname":"P'yong-dong",
    "gn:country_code":"KP",
    "gn:dem":267,
    "gn:feature_class":"P",
    "gn:feature_code":"PPL",
    "gn:name":"P\u2019y\u014fng-dong",
    "gn:population":0,
    "gn:timezone":"Asia/Pyongyang",
    "iso:country":"KP",
    "name:und_x_variant":[
        "\ud3c9\ub3d9",
        "P\u2019y\u014fng-dong"
    ],
    "wof:name":"P'yong-dong",
    "wof:placetype":"locality"
},
  "geometry": {"coordinates":[125.83167,40.69611],"type":"Point"}
}