{
  "type": "Feature",
  "properties": {
    "gn:admin1_code":"11.0",
    "gn:asciiname":"Mansu-dong",
    "gn:country_code":"KP",
    "gn:dem":50,
    "gn:feature_class":"P",
    "gn:feature_code":"PPL",
    "gn:name":"Mansu-dong",
    "gn:population":0,
    "gn:timezone":"Asia/Pyongyang",
    "iso:country":"KP",
    "name:kor_x_preferred":[
        "\ub9cc\uc218\ub3d9"
    ],
    "wof:name":"Mansu-dong",
    "wof:placetype":"locality"
},
  "geometry": {"coordinates":[124.81278,39.87361],"type":"Point"}
}