{
  "type": "Feature",
  "properties": {
    "gn:admin1_code":"11.0",
    "gn:asciiname":"Sokkyo-ri",
    "gn:country_code":"KP",
    "gn:dem":34,
    "gn:feature_class":"P",
    "gn:feature_code":"PPL",
    "gn:name":"S\u014fkkyo-ri",
    "gn:population":0,
    "gn:timezone":"Asia/Pyongyang",
    "iso:country":"KP",
    "name:und_x_variant":[
        "\uc11d\uad50\ub9ac",
        "S\u014fkkyo-ri"
    ],
    "wof:name":"Sokkyo-ri",
    "wof:placetype":"locality"
},
  "geometry": {"coordinates":[124.62778,40.07083],"type":"Point"}
}