{
  "type": "Feature",
  "properties": {
    "gn:admin1_code":"3.0",
    "gn:asciiname":"Pangha-ri",
    "gn:country_code":"KP",
    "gn:dem":24,
    "gn:feature_class":"P",
    "gn:feature_code":"PPL",
    "gn:name":"Pangha-ri",
    "gn:population":0,
    "gn:timezone":"Asia/Pyongyang",
    "iso:country":"KP",
    "name:und_x_variant":[
        "\ubc29\ud558\ub9ac",
        "Pangha-ri"
    ],
    "wof:name":"Pangha-ri",
    "wof:placetype":"locality"
},
  "geometry": {"coordinates":[127.99111000000001,40.04056],"type":"Point"}
}