{
  "type": "Feature",
  "properties": {
    "gn:admin1_code":"0.0",
    "gn:asciiname":"K'ungol",
    "gn:country_code":"KP",
    "gn:dem":1364,
    "gn:feature_class":"P",
    "gn:feature_code":"PPL",
    "gn:name":"K\u2019\u016dngol",
    "gn:population":0,
    "gn:timezone":"Asia/Pyongyang",
    "iso:country":"KP",
    "name:kor_x_preferred":[
        "\ud070\uace8"
    ],
    "name:und_x_variant":[
        "K\u2019\u016dngol"
    ],
    "wof:name":"K'ungol",
    "wof:placetype":"locality"
},
  "geometry": {"coordinates":[127.16667,41.11667],"type":"Point"}
}