{
  "type": "Feature",
  "properties": {
    "gn:admin1_code":"1.0",
    "gn:asciiname":"P'yongch'am",
    "gn:country_code":"KP",
    "gn:dem":620,
    "gn:feature_class":"P",
    "gn:feature_code":"PPL",
    "gn:name":"P\u2019y\u014fngch\u2019am",
    "gn:population":0,
    "gn:timezone":"Asia/Pyongyang",
    "iso:country":"KP",
    "name:kor_x_preferred":[
        "\ud3c9\ucc38"
    ],
    "name:und_x_variant":[
        "\ud3c9\ucc38",
        "P\u2019y\u014fngch\u2019am"
    ],
    "wof:name":"P'yongch'am",
    "wof:placetype":"locality"
},
  "geometry": {"coordinates":[126.66611,40.56944],"type":"Point"}
}