{
  "type": "Feature",
  "properties": {
    "gn:admin1_code":"1.0",
    "gn:asciiname":"Yodae-ri",
    "gn:country_code":"KP",
    "gn:dem":437,
    "gn:feature_class":"P",
    "gn:feature_code":"PPL",
    "gn:name":"Yodae-ri",
    "gn:population":0,
    "gn:timezone":"Asia/Pyongyang",
    "iso:country":"KP",
    "name:und_x_variant":[
        "\uc694\ub300\ub9ac",
        "Yodae-ri"
    ],
    "wof:name":"Yodae-ri",
    "wof:placetype":"locality"
},
  "geometry": {"coordinates":[125.96193999999998,40.54667],"type":"Point"}
}