{
  "type": "Feature",
  "properties": {
    "gn:admin1_code":"11.0",
    "gn:asciiname":"Songch'on-dong",
    "gn:country_code":"KP",
    "gn:dem":78,
    "gn:feature_class":"P",
    "gn:feature_code":"PPL",
    "gn:name":"Songch\u2019\u014fn-dong",
    "gn:population":0,
    "gn:timezone":"Asia/Pyongyang",
    "iso:country":"KP",
    "name:kor_x_preferred":[
        "\uc1a1\ucc9c\ub3d9"
    ],
    "name:und_x_variant":[
        "Songch\u2019\u014fn-dong"
    ],
    "wof:name":"Songch'on-dong",
    "wof:placetype":"locality"
},
  "geometry": {"coordinates":[125.60306,39.92556],"type":"Point"}
}