{
  "type": "Feature",
  "properties": {
    "gn:admin1_code":"11.0",
    "gn:asciiname":"Sokkye-dong",
    "gn:country_code":"KP",
    "gn:dem":27,
    "gn:feature_class":"P",
    "gn:feature_code":"PPL",
    "gn:name":"S\u014fkkye-dong",
    "gn:population":0,
    "gn:timezone":"Asia/Pyongyang",
    "iso:country":"KP",
    "name:und_x_variant":[
        "\uc11d\uacc4\ub3d9",
        "S\u014fkkye-dong"
    ],
    "wof:name":"Sokkye-dong",
    "wof:placetype":"locality"
},
  "geometry": {"coordinates":[124.60028,40.2475],"type":"Point"}
}