{
  "type": "Feature",
  "properties": {
    "gn:admin1_code":"7.0",
    "gn:asciiname":"Hagamu-dong",
    "gn:country_code":"KP",
    "gn:dem":5,
    "gn:feature_class":"P",
    "gn:feature_code":"PPL",
    "gn:name":"Hagamu-dong",
    "gn:population":0,
    "gn:timezone":"Asia/Pyongyang",
    "iso:country":"KP",
    "name:kor_x_preferred":[
        "\ud558\uac00\ubb34\ub3d9"
    ],
    "wof:name":"Hagamu-dong",
    "wof:placetype":"locality"
},
  "geometry": {"coordinates":[125.59778,38.56417],"type":"Point"}
}