{
  "type": "Feature",
  "properties": {
    "gn:admin1_code":"9.0",
    "gn:asciiname":"Ch'ikpat",
    "gn:country_code":"KP",
    "gn:dem":345,
    "gn:feature_class":"P",
    "gn:feature_code":"PPL",
    "gn:name":"Ch\u2019ikpat",
    "gn:population":0,
    "gn:timezone":"Asia/Pyongyang",
    "iso:country":"KP",
    "name:kor_x_preferred":[
        "\uce59\ubc2d"
    ],
    "name:und_x_variant":[
        "Ch\u2019ikpat"
    ],
    "wof:name":"Ch'ikpat",
    "wof:placetype":"locality"
},
  "geometry": {"coordinates":[128.13471999999999,38.70389],"type":"Point"}
}