{
  "type": "Feature",
  "properties": {
    "gn:admin1_code":"15.0",
    "gn:asciiname":"P'ot'an",
    "gn:country_code":"KP",
    "gn:dem":133,
    "gn:feature_class":"P",
    "gn:feature_code":"PPL",
    "gn:name":"P\u2019ot\u2019an",
    "gn:population":0,
    "gn:timezone":"Asia/Pyongyang",
    "iso:country":"KP",
    "name:kor_x_preferred":[
        "\ud3ec\ud0c4"
    ],
    "name:kor_x_variant":[
        "P\u2019ot\u2019an"
    ],
    "wof:name":"P'ot'an",
    "wof:placetype":"locality"
},
  "geometry": {"coordinates":[126.39749999999999,39.29611],"type":"Point"}
}