{
  "type": "Feature",
  "properties": {
    "gn:admin1_code":"6.0",
    "gn:asciiname":"Ch'uam-dong",
    "gn:country_code":"KP",
    "gn:dem":61,
    "gn:feature_class":"P",
    "gn:feature_code":"PPL",
    "gn:name":"Ch\u2019uam-dong",
    "gn:population":0,
    "gn:timezone":"Asia/Pyongyang",
    "iso:country":"KP",
    "name:kor_x_preferred":[
        "\ucd94\uc554\ub3d9"
    ],
    "name:und_x_variant":[
        "Ch\u2019uam-dong"
    ],
    "wof:name":"Ch'uam-dong",
    "wof:placetype":"locality"
},
  "geometry": {"coordinates":[124.97583,38.26972],"type":"Point"}
}