{
  "type": "Feature",
  "properties": {
    "gn:admin1_code":"17.0",
    "gn:asciiname":"Ojibau",
    "gn:country_code":"KP",
    "gn:dem":235,
    "gn:feature_class":"P",
    "gn:feature_code":"PPL",
    "gn:name":"Ojibau",
    "gn:population":0,
    "gn:timezone":"Asia/Pyongyang",
    "iso:country":"KP",
    "wof:name":"Ojibau",
    "wof:placetype":"locality"
},
  "geometry": {"coordinates":[129.90000000000001,42.93333],"type":"Point"}
}