{
  "type": "Feature",
  "properties": {
    "gn:admin1_code":"9.0",
    "gn:asciiname":"Naech'u-dong",
    "gn:country_code":"KP",
    "gn:dem":333,
    "gn:feature_class":"P",
    "gn:feature_code":"PPL",
    "gn:name":"Naech\u2019u-dong",
    "gn:population":0,
    "gn:timezone":"Asia/Pyongyang",
    "iso:country":"KP",
    "name:kor_x_preferred":[
        "\ub0b4\ucd94\ub3d9"
    ],
    "name:kor_x_variant":[
        "Naech\u2019u-dong"
    ],
    "wof:name":"Naech'u-dong",
    "wof:placetype":"locality"
},
  "geometry": {"coordinates":[126.86667,38.70083],"type":"Point"}
}