{
  "type": "Feature",
  "properties": {
    "gn:admin1_code":"11.0",
    "gn:asciiname":"Ponghu-ri",
    "gn:country_code":"KP",
    "gn:dem":194,
    "gn:feature_class":"P",
    "gn:feature_code":"PPL",
    "gn:name":"Ponghu-ri",
    "gn:population":0,
    "gn:timezone":"Asia/Pyongyang",
    "iso:country":"KP",
    "name:kor_x_preferred":[
        "\ubd09\ud6c4\ub9ac"
    ],
    "wof:name":"Ponghu-ri",
    "wof:placetype":"locality"
},
  "geometry": {"coordinates":[125.43333,39.95],"type":"Point"}
}