{
  "type": "Feature",
  "properties": {
    "gn:admin1_code":"12.0",
    "gn:admin2_code":"Sangw\u014fn-gun",
    "gn:asciiname":"Naesongsan",
    "gn:country_code":"KP",
    "gn:dem":114,
    "gn:feature_class":"P",
    "gn:feature_code":"PPL",
    "gn:name":"Naes\u014fngsan",
    "gn:population":0,
    "gn:timezone":"Asia/Pyongyang",
    "iso:country":"KP",
    "wof:name":"Naesongsan",
    "wof:placetype":"locality"
},
  "geometry": {"coordinates":[126.01806000000001,38.82778],"type":"Point"}
}