{
  "type": "Feature",
  "properties": {
    "gn:admin1_code":"15.0",
    "gn:asciiname":"Pyorok",
    "gn:country_code":"KP",
    "gn:dem":13,
    "gn:feature_class":"P",
    "gn:feature_code":"PPL",
    "gn:name":"Py\u014frok",
    "gn:population":0,
    "gn:timezone":"Asia/Pyongyang",
    "iso:country":"KP",
    "name:und_x_variant":[
        "\ubcc4\uc625",
        "Py\u014frok"
    ],
    "wof:name":"Pyorok",
    "wof:placetype":"locality"
},
  "geometry": {"coordinates":[125.20166999999999,38.81139],"type":"Point"}
}