{
  "type": "Feature",
  "properties": {
    "gn:admin1_code":"3.0",
    "gn:asciiname":"Uiho-ri",
    "gn:country_code":"KP",
    "gn:dem":5,
    "gn:feature_class":"P",
    "gn:feature_code":"PPL",
    "gn:name":"\u016ciho-ri",
    "gn:population":0,
    "gn:timezone":"Asia/Pyongyang",
    "iso:country":"KP",
    "name:und_x_variant":[
        "Giko-ri",
        "\u016ciho-ri",
        "\uc758\ud638\ub9ac"
    ],
    "wof:name":"Uiho-ri",
    "wof:placetype":"locality"
},
  "geometry": {"coordinates":[128.33626000000001,40.08363],"type":"Point"}
}