{
  "type": "Feature",
  "properties": {
    "gn:admin1_code":"3.0",
    "gn:asciiname":"Chunghung-ch'on",
    "gn:country_code":"KP",
    "gn:dem":301,
    "gn:feature_class":"P",
    "gn:feature_code":"PPL",
    "gn:name":"Chungh\u016dng-ch\u2019on",
    "gn:population":0,
    "gn:timezone":"Asia/Pyongyang",
    "iso:country":"KP",
    "name:und_x_variant":[
        "Chungh\u016dng-ch\u2019on",
        "\uc911\ud765\ucd0c"
    ],
    "wof:name":"Chunghung-ch'on",
    "wof:placetype":"locality"
},
  "geometry": {"coordinates":[128.26853,40.47944],"type":"Point"}
}