{
  "type": "Feature",
  "properties": {
    "gn:admin1_code":"6.0",
    "gn:asciiname":"Songbang-mal",
    "gn:country_code":"KP",
    "gn:dem":15,
    "gn:feature_class":"P",
    "gn:feature_code":"PPL",
    "gn:name":"Songbang-mal",
    "gn:population":0,
    "gn:timezone":"Asia/Pyongyang",
    "iso:country":"KP",
    "name:und_x_variant":[
        "\uc1a1\ubc29\ub9d0",
        "Songbang-ch\u2019on",
        "Songbang-mal"
    ],
    "wof:name":"Songbang-mal",
    "wof:placetype":"locality"
},
  "geometry": {"coordinates":[125.62222,37.97389],"type":"Point"}
}