{
  "type": "Feature",
  "properties": {
    "gn:admin1_code":"9.0",
    "gn:asciiname":"Anmal",
    "gn:country_code":"KP",
    "gn:dem":396,
    "gn:feature_class":"P",
    "gn:feature_code":"PPL",
    "gn:name":"Anmal",
    "gn:population":0,
    "gn:timezone":"Asia/Pyongyang",
    "iso:country":"KP",
    "name:kor_x_preferred":[
        "\uc548\ub9d0"
    ],
    "wof:name":"Anmal",
    "wof:placetype":"locality"
},
  "geometry": {"coordinates":[127.12139000000001,39.04583],"type":"Point"}
}