{
  "type": "Feature",
  "properties": {
    "gn:admin1_code":"3.0",
    "gn:asciiname":"Sangsap'yong",
    "gn:country_code":"KP",
    "gn:dem":234,
    "gn:feature_class":"P",
    "gn:feature_code":"PPL",
    "gn:name":"Sangsap\u2019y\u014fng",
    "gn:population":0,
    "gn:timezone":"Asia/Pyongyang",
    "iso:country":"KP",
    "name:und_x_variant":[
        "\uc0c1\uc0ac\ud3c9",
        "Sangsap\u2019y\u014fng"
    ],
    "wof:name":"Sangsap'yong",
    "wof:placetype":"locality"
},
  "geometry": {"coordinates":[128.06806,40.32861],"type":"Point"}
}