{
  "type": "Feature",
  "properties": {
    "gn:admin1_code":"11.0",
    "gn:asciiname":"Tae-ri",
    "gn:country_code":"KP",
    "gn:dem":242,
    "gn:feature_class":"P",
    "gn:feature_code":"PPL",
    "gn:name":"Tae-ri",
    "gn:population":0,
    "gn:timezone":"Asia/Pyongyang",
    "iso:country":"KP",
    "name:kor_x_preferred":[
        "\ub300\ub9ac"
    ],
    "wof:name":"Tae-ri",
    "wof:placetype":"locality"
},
  "geometry": {"coordinates":[124.82693999999999,40.3375],"type":"Point"}
}