{
  "type": "Feature",
  "properties": {
    "gn:admin1_code":"6.0",
    "gn:asciiname":"Ukkaam",
    "gn:country_code":"KP",
    "gn:dem":54,
    "gn:feature_class":"P",
    "gn:feature_code":"PPL",
    "gn:name":"Ukkaam",
    "gn:population":0,
    "gn:timezone":"Asia/Pyongyang",
    "iso:country":"KP",
    "wof:name":"Ukkaam",
    "wof:placetype":"locality"
},
  "geometry": {"coordinates":[126.02943999999999,37.97333],"type":"Point"}
}