{
  "type": "Feature",
  "properties": {
    "gn:admin1_code":"17.0",
    "gn:asciiname":"P'osangdongson-dong",
    "gn:country_code":"KP",
    "gn:dem":178,
    "gn:feature_class":"P",
    "gn:feature_code":"PPL",
    "gn:name":"P\u2019osangdongs\u014fn-dong",
    "gn:population":0,
    "gn:timezone":"Asia/Pyongyang",
    "iso:country":"KP",
    "name:und_x_variant":[
        "P\u2019ojungdong-S\u014fng-dong",
        "\ud3ec\uc0c1\ub3d9\uc120\ub3d9",
        "P\u2019osangdongs\u014fn-dong"
    ],
    "wof:name":"P'osangdongson-dong",
    "wof:placetype":"locality"
},
  "geometry": {"coordinates":[129.66388999999998,41.01667],"type":"Point"}
}