{
  "type": "Feature",
  "properties": {
    "gn:admin1_code":"6.0",
    "gn:asciiname":"Pak-ch'on",
    "gn:country_code":"KP",
    "gn:dem":18,
    "gn:feature_class":"P",
    "gn:feature_code":"PPL",
    "gn:name":"Pak-ch\u2019on",
    "gn:population":0,
    "gn:timezone":"Asia/Pyongyang",
    "iso:country":"KP",
    "name:und_x_variant":[
        "\ubc15\ucd0c",
        "Pak-ch\u2019on"
    ],
    "wof:name":"Pak-ch'on",
    "wof:placetype":"locality"
},
  "geometry": {"coordinates":[125.375,37.93111],"type":"Point"}
}