{
  "type": "Feature",
  "properties": {
    "gn:admin1_code":"7.0",
    "gn:asciiname":"Taedang-dong",
    "gn:country_code":"KP",
    "gn:dem":9,
    "gn:feature_class":"P",
    "gn:feature_code":"PPL",
    "gn:name":"Taedang-dong",
    "gn:population":0,
    "gn:timezone":"Asia/Pyongyang",
    "iso:country":"KP",
    "name:kor_x_preferred":[
        "\ub300\ub2f9\ub3d9"
    ],
    "wof:name":"Taedang-dong",
    "wof:placetype":"locality"
},
  "geometry": {"coordinates":[125.68556,38.52972000000001],"type":"Point"}
}