{
  "type": "Feature",
  "properties": {
    "gn:admin1_code":"3.0",
    "gn:asciiname":"Nung-dong",
    "gn:country_code":"KP",
    "gn:dem":162,
    "gn:feature_class":"P",
    "gn:feature_code":"PPL",
    "gn:name":"N\u016dng-dong",
    "gn:population":0,
    "gn:timezone":"Asia/Pyongyang",
    "iso:country":"KP",
    "name:und_x_variant":[
        "N\u016dng-dong",
        "\ub2a5\ub3d9"
    ],
    "wof:name":"Nung-dong",
    "wof:placetype":"locality"
},
  "geometry": {"coordinates":[128.19158000000002,40.3215],"type":"Point"}
}