{
  "type": "Feature",
  "properties": {
    "gn:admin1_code":"7.0",
    "gn:asciiname":"Nolbundol",
    "gn:country_code":"KP",
    "gn:dem":142,
    "gn:feature_class":"P",
    "gn:feature_code":"PPL",
    "gn:name":"N\u014flb\u016dndol",
    "gn:population":0,
    "gn:timezone":"Asia/Pyongyang",
    "iso:country":"KP",
    "name:kor_x_preferred":[
        "\ub113\uc740\ub3cc"
    ],
    "name:kor_x_variant":[
        "N\u014flb\u016dndol"
    ],
    "name:und_x_variant":[
        "N\u014flb\u016dltol",
        "N\u014flb\u016dtol",
        "Kwangs\u014fk"
    ],
    "wof:name":"Nolbundol",
    "wof:placetype":"locality"
},
  "geometry": {"coordinates":[126.69944,38.81722],"type":"Point"}
}