{
  "type": "Feature",
  "properties": {
    "gn:admin1_code":"6.0",
    "gn:asciiname":"Wonsinch'on",
    "gn:country_code":"KP",
    "gn:dem":19,
    "gn:feature_class":"P",
    "gn:feature_code":"PPL",
    "gn:name":"W\u014fnsinch\u2019on",
    "gn:population":0,
    "gn:timezone":"Asia/Pyongyang",
    "iso:country":"KP",
    "wof:name":"Wonsinch'on",
    "wof:placetype":"locality"
},
  "geometry": {"coordinates":[125.35805999999999,38.61806],"type":"Point"}
}