{
  "type": "Feature",
  "properties": {
    "gn:admin1_code":"1.0",
    "gn:asciiname":"Yoro-gol",
    "gn:country_code":"KP",
    "gn:dem":540,
    "gn:feature_class":"P",
    "gn:feature_code":"PPL",
    "gn:name":"Y\u014fr\u014f-gol",
    "gn:population":0,
    "gn:timezone":"Asia/Pyongyang",
    "iso:country":"KP",
    "name:und_x_variant":[
        "\uc5f4\uc5b4\uace8",
        "Y\u014fr\u014f-gol"
    ],
    "wof:name":"Yoro-gol",
    "wof:placetype":"locality"
},
  "geometry": {"coordinates":[126.79555999999999,41.45222],"type":"Point"}
}