{
  "type": "Feature",
  "properties": {
    "gn:admin1_code":"17.0",
    "gn:asciiname":"Yongp'yong-dong",
    "gn:country_code":"KP",
    "gn:dem":155,
    "gn:feature_class":"P",
    "gn:feature_code":"PPL",
    "gn:name":"Yongp\u2019y\u014fng-dong",
    "gn:population":0,
    "gn:timezone":"Asia/Pyongyang",
    "iso:country":"KP",
    "wof:name":"Yongp'yong-dong",
    "wof:placetype":"locality"
},
  "geometry": {"coordinates":[130.13333,42.55],"type":"Point"}
}