{
  "type": "Feature",
  "properties": {
    "gn:admin1_code":"12.0",
    "gn:asciiname":"Polmal",
    "gn:country_code":"KP",
    "gn:dem":55,
    "gn:feature_class":"P",
    "gn:feature_code":"PPL",
    "gn:name":"P\u014flmal",
    "gn:population":0,
    "gn:timezone":"Asia/Pyongyang",
    "iso:country":"KP",
    "name:und_x_variant":[
        "Ya-ri",
        "\ubc8c\ub9d0",
        "P\u014flmal"
    ],
    "wof:name":"Polmal",
    "wof:placetype":"locality"
},
  "geometry": {"coordinates":[125.94306,38.88667],"type":"Point"}
}