{
  "type": "Feature",
  "properties": {
    "gn:admin1_code":"11.0",
    "gn:asciiname":"Songu-dong",
    "gn:country_code":"KP",
    "gn:dem":93,
    "gn:feature_class":"P",
    "gn:feature_code":"PPL",
    "gn:name":"Songu-dong",
    "gn:population":0,
    "gn:timezone":"Asia/Pyongyang",
    "iso:country":"KP",
    "name:kor_x_preferred":[
        "\uc1a1\uc6b0\ub3d9"
    ],
    "wof:name":"Songu-dong",
    "wof:placetype":"locality"
},
  "geometry": {"coordinates":[124.92333000000001,39.90806],"type":"Point"}
}