{
  "type": "Feature",
  "properties": {
    "gn:admin1_code":"9.0",
    "gn:admin2_code":"Kos\u0171ng-gun",
    "gn:asciiname":"Songbung-ni",
    "gn:country_code":"KP",
    "gn:dem":20,
    "gn:feature_class":"P",
    "gn:feature_code":"PPL",
    "gn:name":"S\u014fngbung-ni",
    "gn:population":0,
    "gn:timezone":"Asia/Pyongyang",
    "iso:country":"KP",
    "name:kor_x_preferred":[
        "\uc131\ubd81\ub9ac"
    ],
    "name:und_x_variant":[
        "S\u014fngbung-ni"
    ],
    "wof:name":"Songbung-ni",
    "wof:placetype":"locality"
},
  "geometry": {"coordinates":[128.18961999999999,38.71884],"type":"Point"}
}