{
  "type": "Feature",
  "properties": {
    "gn:admin1_code":"11.0",
    "gn:asciiname":"Hajang-ni",
    "gn:country_code":"KP",
    "gn:dem":111,
    "gn:feature_class":"P",
    "gn:feature_code":"PPL",
    "gn:name":"Hajang-ni",
    "gn:population":0,
    "gn:timezone":"Asia/Pyongyang",
    "iso:country":"KP",
    "name:eng_x_preferred":[
        "Hajang"
    ],
    "name:eng_x_variant":[
        "Hajang-ni"
    ],
    "name:und_x_variant":[
        "Sangjang-dong",
        "Hajang-ni"
    ],
    "wof:name":"Hajang",
    "wof:placetype":"locality"
},
  "geometry": {"coordinates":[125.88667,39.96944],"type":"Point"}
}