{
  "type": "Feature",
  "properties": {
    "gn:admin1_code":"15.0",
    "gn:admin2_code":"S\u014fngch\u2019\u014fn-gun",
    "gn:asciiname":"Paeksok-tong",
    "gn:country_code":"KP",
    "gn:dem":183,
    "gn:feature_class":"P",
    "gn:feature_code":"PPL",
    "gn:name":"Paeks\u014fk-tong",
    "gn:population":0,
    "gn:timezone":"Asia/Pyongyang",
    "iso:country":"KP",
    "wof:name":"Paeksok-tong",
    "wof:placetype":"locality"
},
  "geometry": {"coordinates":[126.26306,39.1775],"type":"Point"}
}