{
  "type": "Feature",
  "properties": {
    "gn:admin1_code":"3.0",
    "gn:asciiname":"Chung-gol",
    "gn:cc2":"KP",
    "gn:country_code":"KP",
    "gn:dem":393,
    "gn:feature_class":"P",
    "gn:feature_code":"PPL",
    "gn:name":"Chung-gol",
    "gn:population":0,
    "gn:timezone":"Asia/Pyongyang",
    "iso:country":"KP",
    "name:und_x_variant":[
        "Chung-kol",
        "\uc911\uace8",
        "Chung-gol"
    ],
    "wof:name":"Chung-gol",
    "wof:placetype":"locality"
},
  "geometry": {"coordinates":[128.58444,40.66278],"type":"Point"}
}