{
  "type": "Feature",
  "properties": {
    "gn:admin1_code":"11.0",
    "gn:asciiname":"Yonmang-ni",
    "gn:cc2":"KP",
    "gn:country_code":"KP",
    "gn:dem":227,
    "gn:feature_class":"P",
    "gn:feature_code":"PPL",
    "gn:name":"Y\u014fnmang-ni",
    "gn:population":0,
    "gn:timezone":"Asia/Pyongyang",
    "iso:country":"KP",
    "name:und_x_variant":[
        "\uc5f0\ub9c9\ub9ac",
        "Y\u014fnmang-ni"
    ],
    "wof:name":"Yonmang-ni",
    "wof:placetype":"locality"
},
  "geometry": {"coordinates":[124.8725,40.24278],"type":"Point"}
}