{
  "type": "Feature",
  "properties": {
    "gn:admin1_code":"6.0",
    "gn:asciiname":"Susal-li",
    "gn:country_code":"KP",
    "gn:dem":43,
    "gn:feature_class":"P",
    "gn:feature_code":"PPL",
    "gn:name":"Susal-li",
    "gn:population":0,
    "gn:timezone":"Asia/Pyongyang",
    "iso:country":"KP",
    "name:und_x_variant":[
        "\uc218\uc0b0\ub9ac",
        "Susal-li"
    ],
    "wof:name":"Susal-li",
    "wof:placetype":"locality"
},
  "geometry": {"coordinates":[125.04472,38.50861],"type":"Point"}
}