{
  "type": "Feature",
  "properties": {
    "gn:admin1_code":"11.0",
    "gn:asciiname":"Taesam-ni",
    "gn:country_code":"KP",
    "gn:dem":37,
    "gn:feature_class":"P",
    "gn:feature_code":"PPL",
    "gn:name":"Taesam-ni",
    "gn:population":0,
    "gn:timezone":"Asia/Pyongyang",
    "iso:country":"KP",
    "name:kor_x_preferred":[
        "\ub300\uc0bc\ub9ac"
    ],
    "wof:name":"Taesam-ni",
    "wof:placetype":"locality"
},
  "geometry": {"coordinates":[125.50528,39.725],"type":"Point"}
}