{
  "type": "Feature",
  "properties": {
    "gn:admin1_code":"12.0",
    "gn:asciiname":"Ch'onghang-ni",
    "gn:country_code":"KP",
    "gn:dem":35,
    "gn:feature_class":"P",
    "gn:feature_code":"PPL",
    "gn:name":"Ch\u2019onghang-ni",
    "gn:population":0,
    "gn:timezone":"Asia/Pyongyang",
    "iso:country":"KP",
    "name:und_x_variant":[
        "\ucd1d\ud559\ub9ac",
        "Ch\u2019onghang-ni"
    ],
    "wof:name":"Ch'onghang-ni",
    "wof:placetype":"locality"
},
  "geometry": {"coordinates":[125.81028000000001,38.86278],"type":"Point"}
}