{
  "type": "Feature",
  "properties": {
    "gn:admin1_code":"0.0",
    "gn:asciiname":"Panhop'yong",
    "gn:country_code":"KP",
    "gn:dem":6,
    "gn:feature_class":"P",
    "gn:feature_code":"PPL",
    "gn:name":"Panhop\u2019y\u014fng",
    "gn:population":0,
    "gn:timezone":"Asia/Pyongyang",
    "iso:country":"KP",
    "name:kor_x_preferred":[
        "\ubc18\ud638\ud3c9"
    ],
    "name:und_x_variant":[
        "Panhop\u2019y\u014fng"
    ],
    "wof:name":"Panhop'yong",
    "wof:placetype":"locality"
},
  "geometry": {"coordinates":[125.58333,38.05],"type":"Point"}
}