{
  "type": "Feature",
  "properties": {
    "gn:admin1_code":"18.0",
    "gn:asciiname":"Chong-ch'on",
    "gn:country_code":"KP",
    "gn:dem":109,
    "gn:feature_class":"P",
    "gn:feature_code":"PPL",
    "gn:name":"Ch\u014fng-ch\u2019on",
    "gn:population":0,
    "gn:timezone":"Asia/Pyongyang",
    "iso:country":"KP",
    "name:und_x_variant":[
        "\uc815\ucd0c",
        "Ch\u014fng-ch\u2019on",
        "Jeongchon"
    ],
    "wof:name":"Chong-ch'on",
    "wof:placetype":"locality"
},
  "geometry": {"coordinates":[130.10361,42.19806],"type":"Point"}
}