{
  "type": "Feature",
  "properties": {
    "gn:admin1_code":"17.0",
    "gn:asciiname":"Sokhyol-li",
    "gn:country_code":"KP",
    "gn:dem":80,
    "gn:feature_class":"P",
    "gn:feature_code":"PPL",
    "gn:name":"S\u014fkhy\u014fl-li",
    "gn:population":0,
    "gn:timezone":"Asia/Pyongyang",
    "iso:country":"KP",
    "name:und_x_variant":[
        "S\u014fkhy\u014fn-ni",
        "\uc11d\ud604\ub9ac",
        "S\u014fkhy\u014fl-li"
    ],
    "wof:name":"Sokhyol-li",
    "wof:placetype":"locality"
},
  "geometry": {"coordinates":[129.42694,40.87528],"type":"Point"}
}