{
  "type": "Feature",
  "properties": {
    "gn:admin1_code":"9.0",
    "gn:asciiname":"Chiktong-ni",
    "gn:country_code":"KP",
    "gn:dem":301,
    "gn:feature_class":"P",
    "gn:feature_code":"PPL",
    "gn:name":"Chiktong-ni",
    "gn:population":0,
    "gn:timezone":"Asia/Pyongyang",
    "iso:country":"KP",
    "wof:name":"Chiktong-ni",
    "wof:placetype":"locality"
},
  "geometry": {"coordinates":[127.12111000000002,38.53611],"type":"Point"}
}