{
  "type": "Feature",
  "properties": {
    "gn:admin1_code":"3.0",
    "gn:asciiname":"Ch'oha-ri",
    "gn:country_code":"KP",
    "gn:dem":66,
    "gn:feature_class":"P",
    "gn:feature_code":"PPL",
    "gn:name":"Ch\u2019oha-ri",
    "gn:population":0,
    "gn:timezone":"Asia/Pyongyang",
    "iso:country":"KP",
    "name:und_x_variant":[
        "\ucd08\ud558\ub9ac",
        "Ch\u2019oha-ri"
    ],
    "wof:name":"Ch'oha-ri",
    "wof:placetype":"locality"
},
  "geometry": {"coordinates":[127.2075,39.58889],"type":"Point"}
}