{
  "type": "Feature",
  "properties": {
    "gn:admin1_code":"15.0",
    "gn:admin2_code":"1871865",
    "gn:asciiname":"Wolchong-ni",
    "gn:country_code":"KP",
    "gn:dem":35,
    "gn:feature_class":"P",
    "gn:feature_code":"PPL",
    "gn:name":"W\u014flch\u014fng-ni",
    "gn:population":0,
    "gn:timezone":"Asia/Pyongyang",
    "iso:country":"KP",
    "name:eng_x_preferred":[
        "Wolchong"
    ],
    "name:eng_x_variant":[
        "Wolchong-ni"
    ],
    "wof:name":"Wolchong",
    "wof:placetype":"locality"
},
  "geometry": {"coordinates":[125.57971999999999,39.27472],"type":"Point"}
}