{
  "type": "Feature",
  "properties": {
    "gn:admin1_code":"3.0",
    "gn:admin2_code":"Tanch'\u014fn-si",
    "gn:asciiname":"Ponsan-dong",
    "gn:country_code":"KP",
    "gn:dem":796,
    "gn:feature_class":"P",
    "gn:feature_code":"PPL",
    "gn:name":"Ponsan-dong",
    "gn:population":0,
    "gn:timezone":"Asia/Pyongyang",
    "iso:country":"KP",
    "name:und_x_variant":[
        "\ubcf8\uc0b0\ub3d9",
        "Ponsan-dong"
    ],
    "wof:name":"Ponsan-dong",
    "wof:placetype":"locality"
},
  "geometry": {"coordinates":[128.78111000000001,40.92],"type":"Point"}
}