{
  "type": "Feature",
  "properties": {
    "gn:admin1_code":"3.0",
    "gn:asciiname":"P'ungyang-ni",
    "gn:country_code":"KP",
    "gn:dem":33,
    "gn:feature_class":"P",
    "gn:feature_code":"PPL",
    "gn:name":"P\u2019ungyang-ni",
    "gn:population":0,
    "gn:timezone":"Asia/Pyongyang",
    "iso:country":"KP",
    "name:eng_x_preferred":[
        "P'ungyang"
    ],
    "name:eng_x_variant":[
        "P'ungyang-ni"
    ],
    "name:und_x_variant":[
        "\ud48d\uc591\ub9ac",
        "P\u2019ungyang-ni"
    ],
    "wof:name":"P'ungyang",
    "wof:placetype":"locality"
},
  "geometry": {"coordinates":[127.2625,39.55111],"type":"Point"}
}