{
  "type": "Feature",
  "properties": {
    "gn:admin1_code":"3.0",
    "gn:asciiname":"Taech'on",
    "gn:country_code":"KP",
    "gn:dem":60,
    "gn:feature_class":"P",
    "gn:feature_code":"PPL",
    "gn:name":"Taech\u2019on",
    "gn:population":0,
    "gn:timezone":"Asia/Pyongyang",
    "iso:country":"KP",
    "name:und_x_variant":[
        "\ub300\ucd0c",
        "Taech\u2019on"
    ],
    "wof:name":"Taech'on",
    "wof:placetype":"locality"
},
  "geometry": {"coordinates":[127.26472,39.67806],"type":"Point"}
}