{
  "type": "Feature",
  "properties": {
    "gn:admin1_code":"7.0",
    "gn:asciiname":"Wolge",
    "gn:country_code":"KP",
    "gn:dem":172,
    "gn:feature_class":"P",
    "gn:feature_code":"PPL",
    "gn:name":"W\u014flge",
    "gn:population":0,
    "gn:timezone":"Asia/Pyongyang",
    "iso:country":"KP",
    "name:kor_x_preferred":[
        "\uc6d4\uac8c"
    ],
    "name:kor_x_variant":[
        "W\u014flge"
    ],
    "wof:name":"Wolge",
    "wof:placetype":"locality"
},
  "geometry": {"coordinates":[126.70389,38.85417],"type":"Point"}
}