{
  "type": "Feature",
  "properties": {
    "gn:admin1_code":"12.0",
    "gn:asciiname":"Seryon-dong",
    "gn:country_code":"KP",
    "gn:dem":27,
    "gn:feature_class":"P",
    "gn:feature_code":"PPL",
    "gn:name":"Sery\u014fn-dong",
    "gn:population":0,
    "gn:timezone":"Asia/Pyongyang",
    "iso:country":"KP",
    "name:und_x_variant":[
        "\uc138\ub828\ub3d9",
        "Sery\u014fn-dong"
    ],
    "wof:name":"Seryon-dong",
    "wof:placetype":"locality"
},
  "geometry": {"coordinates":[125.80361000000001,38.85389],"type":"Point"}
}