{
  "type": "Feature",
  "properties": {
    "gn:admin1_code":"17.0",
    "gn:asciiname":"Togyeso",
    "gn:country_code":"KP",
    "gn:dem":162,
    "gn:feature_class":"P",
    "gn:feature_code":"PPL",
    "gn:name":"Togyeso",
    "gn:population":0,
    "gn:timezone":"Asia/Pyongyang",
    "iso:country":"KP",
    "name:und_x_variant":[
        "Toriso",
        "\ub3c4\uacc4\uc18c",
        "Togyeso"
    ],
    "wof:name":"Togyeso",
    "wof:placetype":"locality"
},
  "geometry": {"coordinates":[129.14694,40.84111],"type":"Point"}
}