{
  "type": "Feature",
  "properties": {
    "gn:admin1_code":"15.0",
    "gn:admin2_code":"Pukch\u2019ang-gun",
    "gn:asciiname":"Ch'angnyong-dong",
    "gn:country_code":"KP",
    "gn:dem":178,
    "gn:feature_class":"P",
    "gn:feature_code":"PPL",
    "gn:name":"Ch\u2019angnyong-dong",
    "gn:population":0,
    "gn:timezone":"Asia/Pyongyang",
    "iso:country":"KP",
    "wof:name":"Ch'angnyong-dong",
    "wof:placetype":"locality"
},
  "geometry": {"coordinates":[126.26972000000001,39.53139],"type":"Point"}
}