{
  "type": "Feature",
  "properties": {
    "gn:admin1_code":"9.0",
    "gn:asciiname":"Kuryong-ni",
    "gn:country_code":"KP",
    "gn:dem":183,
    "gn:feature_class":"P",
    "gn:feature_code":"PPL",
    "gn:name":"Kuryong-ni",
    "gn:population":0,
    "gn:timezone":"Asia/Pyongyang",
    "iso:country":"KP",
    "name:eng_x_preferred":[
        "Kuryong"
    ],
    "name:eng_x_variant":[
        "Kuryong-ni"
    ],
    "wof:name":"Kuryong",
    "wof:placetype":"locality"
},
  "geometry": {"coordinates":[126.96083,38.62778],"type":"Point"}
}