{
  "type": "Feature",
  "properties": {
    "gn:admin1_code":"9.0",
    "gn:asciiname":"Marich'on",
    "gn:country_code":"KP",
    "gn:dem":429,
    "gn:feature_class":"P",
    "gn:feature_code":"PPL",
    "gn:name":"Marich\u2019on",
    "gn:population":0,
    "gn:timezone":"Asia/Pyongyang",
    "iso:country":"KP",
    "wof:name":"Marich'on",
    "wof:placetype":"locality"
},
  "geometry": {"coordinates":[127.90667000000001,38.57611],"type":"Point"}
}