{
  "type": "Feature",
  "properties": {
    "gn:admin1_code":"6.0",
    "gn:asciiname":"Kama-maul",
    "gn:country_code":"KP",
    "gn:dem":104,
    "gn:feature_class":"P",
    "gn:feature_code":"PPL",
    "gn:name":"Kama-ma\u016dl",
    "gn:population":0,
    "gn:timezone":"Asia/Pyongyang",
    "iso:country":"KP",
    "name:kor_x_preferred":[
        "\uac00\ub9c8\ub9c8\uc744"
    ],
    "name:und_x_variant":[
        "Kama-ma\u016dl",
        "Kamal"
    ],
    "wof:name":"Kama-maul",
    "wof:placetype":"locality"
},
  "geometry": {"coordinates":[125.41833,38.31222],"type":"Point"}
}