{
  "type": "Feature",
  "properties": {
    "gn:admin1_code":"11.0",
    "gn:asciiname":"Tokhung-ni",
    "gn:country_code":"KP",
    "gn:dem":458,
    "gn:feature_class":"P",
    "gn:feature_code":"PPL",
    "gn:name":"T\u014fkh\u016dng-ni",
    "gn:population":0,
    "gn:timezone":"Asia/Pyongyang",
    "iso:country":"KP",
    "name:und_x_variant":[
        "\ub355\ud765\ub9ac",
        "T\u014fkh\u016dng-ni"
    ],
    "wof:name":"Tokhung-ni",
    "wof:placetype":"locality"
},
  "geometry": {"coordinates":[125.29056,40.47083],"type":"Point"}
}