{
  "type": "Feature",
  "properties": {
    "gn:admin1_code":"3.0",
    "gn:asciiname":"Twikkae",
    "gn:country_code":"KP",
    "gn:dem":1116,
    "gn:feature_class":"P",
    "gn:feature_code":"PPL",
    "gn:name":"Twikkae",
    "gn:population":0,
    "gn:timezone":"Asia/Pyongyang",
    "iso:country":"KP",
    "name:und_x_variant":[
        "\ub4b7\uac1c",
        "Twikkae"
    ],
    "wof:name":"Twikkae",
    "wof:placetype":"locality"
},
  "geometry": {"coordinates":[127.2625,40.44389],"type":"Point"}
}