{
  "type": "Feature",
  "properties": {
    "gn:admin1_code":"12.0",
    "gn:asciiname":"Soijung-dong",
    "gn:country_code":"KP",
    "gn:dem":8,
    "gn:feature_class":"P",
    "gn:feature_code":"PPL",
    "gn:name":"Soijung-dong",
    "gn:population":0,
    "gn:timezone":"Asia/Pyongyang",
    "iso:country":"KP",
    "name:kor_x_preferred":[
        "\uc18c\uc774\uc911\ub3d9"
    ],
    "name:und_x_variant":[
        "Soijungdong"
    ],
    "wof:name":"Soijung-dong",
    "wof:placetype":"locality"
},
  "geometry": {"coordinates":[125.62806999999999,38.92658],"type":"Point"}
}