{
  "type": "Feature",
  "properties": {
    "gn:admin1_code":"17.0",
    "gn:asciiname":"Yongho",
    "gn:country_code":"KP",
    "gn:dem":50,
    "gn:feature_class":"P",
    "gn:feature_code":"PPL",
    "gn:name":"Yongho",
    "gn:population":0,
    "gn:timezone":"Asia/Pyongyang",
    "iso:country":"KP",
    "name:und_x_variant":[
        "\uc6a9\ud638",
        "Yongho"
    ],
    "wof:name":"Yongho",
    "wof:placetype":"locality"
},
  "geometry": {"coordinates":[129.29028,40.87389],"type":"Point"}
}