{
  "type": "Feature",
  "properties": {
    "gn:admin1_code":"11.0",
    "gn:asciiname":"Sop'yong-ni",
    "gn:country_code":"KP",
    "gn:dem":144,
    "gn:feature_class":"P",
    "gn:feature_code":"PPL",
    "gn:name":"S\u014fp\u2019y\u014fng-ni",
    "gn:population":0,
    "gn:timezone":"Asia/Pyongyang",
    "iso:country":"KP",
    "name:und_x_variant":[
        "\uc11c\ud3c9\ub9ac",
        "S\u014fp\u2019y\u014fng-ni"
    ],
    "wof:name":"Sop'yong-ni",
    "wof:placetype":"locality"
},
  "geometry": {"coordinates":[124.87917,40.16111],"type":"Point"}
}