{
  "type": "Feature",
  "properties": {
    "gn:admin1_code":"3.0",
    "gn:asciiname":"Nungdong-ni",
    "gn:country_code":"KP",
    "gn:dem":54,
    "gn:feature_class":"P",
    "gn:feature_code":"PPL",
    "gn:name":"N\u016dngdong-ni",
    "gn:population":0,
    "gn:timezone":"Asia/Pyongyang",
    "iso:country":"KP",
    "name:eng_x_preferred":[
        "Nungdong"
    ],
    "name:eng_x_variant":[
        "Nungdong-ni"
    ],
    "name:und_x_variant":[
        "\ub2a5\ub3d9\ub9ac",
        "N\u016dngdong-ni"
    ],
    "wof:name":"Nungdong",
    "wof:placetype":"locality"
},
  "geometry": {"coordinates":[127.45083,39.52417],"type":"Point"}
}