{
  "type": "Feature",
  "properties": {
    "gn:admin1_code":"17.0",
    "gn:admin2_code":"2038910",
    "gn:asciiname":"Sangnop'yong",
    "gn:country_code":"KP",
    "gn:dem":721,
    "gn:feature_class":"P",
    "gn:feature_code":"PPL",
    "gn:name":"Sangnop\u2019y\u014fng",
    "gn:population":0,
    "gn:timezone":"Asia/Pyongyang",
    "iso:country":"KP",
    "wof:name":"Sangnop'yong",
    "wof:placetype":"locality"
},
  "geometry": {"coordinates":[128.88722000000001,41.93278],"type":"Point"}
}