{
  "type": "Feature",
  "properties": {
    "gn:admin1_code":"11.0",
    "gn:asciiname":"Sambong-ni",
    "gn:country_code":"KP",
    "gn:dem":35,
    "gn:feature_class":"P",
    "gn:feature_code":"PPL",
    "gn:name":"Sambong-ni",
    "gn:population":0,
    "gn:timezone":"Asia/Pyongyang",
    "iso:country":"KP",
    "name:kor_x_preferred":[
        "\uc0bc\ubd09\ub9ac"
    ],
    "wof:name":"Sambong-ni",
    "wof:placetype":"locality"
},
  "geometry": {"coordinates":[125.69278,39.70722],"type":"Point"}
}