{
  "type": "Feature",
  "properties": {
    "gn:admin1_code":"1.0",
    "gn:asciiname":"Chokp'o-dong",
    "gn:country_code":"KP",
    "gn:dem":578,
    "gn:feature_class":"P",
    "gn:feature_code":"PPL",
    "gn:name":"Ch\u014fkp\u2019o-dong",
    "gn:population":0,
    "gn:timezone":"Asia/Pyongyang",
    "iso:country":"KP",
    "name:kor_x_preferred":[
        "Ch\u014fkp\u2019o-dong"
    ],
    "name:kor_x_variant":[
        "\uc801\ud3ec\ub3d9"
    ],
    "name:und_x_variant":[
        "\uc801\ud3ec\ub3d9",
        "Ch\u014fkp\u2019o-dong"
    ],
    "wof:name":"Chokp'o-dong",
    "wof:placetype":"locality"
},
  "geometry": {"coordinates":[126.74214000000001,40.84539],"type":"Point"}
}