{
  "type": "Feature",
  "properties": {
    "gn:admin1_code":"11.0",
    "gn:asciiname":"Toryong-ni",
    "gn:country_code":"KP",
    "gn:dem":223,
    "gn:feature_class":"P",
    "gn:feature_code":"PPL",
    "gn:name":"Tory\u014fng-ni",
    "gn:population":0,
    "gn:timezone":"Asia/Pyongyang",
    "iso:country":"KP",
    "name:eng_x_preferred":[
        "Toryong"
    ],
    "name:eng_x_variant":[
        "Toryong-ni"
    ],
    "name:und_x_variant":[
        "Tory\u014fng-dong",
        "\ub3c4\ub839\ub9ac",
        "Tory\u014fng-ni"
    ],
    "wof:name":"Toryong",
    "wof:placetype":"locality"
},
  "geometry": {"coordinates":[124.84667,40.34583],"type":"Point"}
}