{
  "type": "Feature",
  "properties": {
    "gn:admin1_code":"7.0",
    "gn:asciiname":"Pultang-dong",
    "gn:country_code":"KP",
    "gn:dem":109,
    "gn:feature_class":"P",
    "gn:feature_code":"PPL",
    "gn:name":"Pultang-dong",
    "gn:population":0,
    "gn:timezone":"Asia/Pyongyang",
    "iso:country":"KP",
    "wof:name":"Pultang-dong",
    "wof:placetype":"locality"
},
  "geometry": {"coordinates":[126.05333,38.47333],"type":"Point"}
}