{
  "type": "Feature",
  "properties": {
    "gn:admin1_code":"9.0",
    "gn:asciiname":"Uthoegye",
    "gn:country_code":"KP",
    "gn:dem":175,
    "gn:feature_class":"P",
    "gn:feature_code":"PPL",
    "gn:name":"Uthoegye",
    "gn:population":0,
    "gn:timezone":"Asia/Pyongyang",
    "iso:country":"KP",
    "wof:name":"Uthoegye",
    "wof:placetype":"locality"
},
  "geometry": {"coordinates":[126.97472,38.2675],"type":"Point"}
}