{
  "type": "Feature",
  "properties": {
    "gn:admin1_code":"15.0",
    "gn:asciiname":"Namch'ang",
    "gn:country_code":"KP",
    "gn:dem":267,
    "gn:feature_class":"P",
    "gn:feature_code":"PPL",
    "gn:name":"Namch\u2019ang",
    "gn:population":0,
    "gn:timezone":"Asia/Pyongyang",
    "iso:country":"KP",
    "name:kor_x_preferred":[
        "\ub0a8\ucc3d"
    ],
    "name:und_x_variant":[
        "Namch\u2019ang"
    ],
    "wof:name":"Namch'ang",
    "wof:placetype":"locality"
},
  "geometry": {"coordinates":[126.41361000000001,39.70972],"type":"Point"}
}