{
  "type": "Feature",
  "properties": {
    "gn:admin1_code":"6.0",
    "gn:asciiname":"Aech'ol-li",
    "gn:country_code":"KP",
    "gn:dem":105,
    "gn:feature_class":"P",
    "gn:feature_code":"PPL",
    "gn:name":"Aech\u2019\u014fl-li",
    "gn:population":0,
    "gn:timezone":"Asia/Pyongyang",
    "iso:country":"KP",
    "name:kor_x_preferred":[
        "\uc560\ucc9c\ub9ac"
    ],
    "name:und_x_variant":[
        "Aech\u2019\u014fn-ni",
        "Aech\u2019\u014fl-li"
    ],
    "wof:name":"Aech'ol-li",
    "wof:placetype":"locality"
},
  "geometry": {"coordinates":[125.33028,38.27889],"type":"Point"}
}