{
  "type": "Feature",
  "properties": {
    "gn:admin1_code":"11.0",
    "gn:asciiname":"Sinch'ang-gol",
    "gn:country_code":"KP",
    "gn:dem":19,
    "gn:feature_class":"P",
    "gn:feature_code":"PPL",
    "gn:name":"Sinch\u2019ang-gol",
    "gn:population":0,
    "gn:timezone":"Asia/Pyongyang",
    "iso:country":"KP",
    "name:kor_x_preferred":[
        "\uc2e0\ucc3d\uace8"
    ],
    "name:kor_x_variant":[
        "Sinch\u2019ang-gol"
    ],
    "name:und_x_variant":[
        "Sinch\u2019ang-dong"
    ],
    "wof:name":"Sinch'ang-gol",
    "wof:placetype":"locality"
},
  "geometry": {"coordinates":[125.26167,39.61472],"type":"Point"}
}