{
  "type": "Feature",
  "properties": {
    "gn:admin1_code":"0.0",
    "gn:asciiname":"Yonghyol-li",
    "gn:country_code":"KP",
    "gn:dem":129,
    "gn:feature_class":"P",
    "gn:feature_code":"PPL",
    "gn:name":"Yonghy\u014fl-li",
    "gn:population":0,
    "gn:timezone":"Asia/Pyongyang",
    "iso:country":"KP",
    "name:kor_x_preferred":[
        "\uc6a9\ud604\ub9ac"
    ],
    "name:und_x_variant":[
        "Yonghy\u014fl-li",
        "Yonghy\u014fn-ni"
    ],
    "wof:name":"Yonghyol-li",
    "wof:placetype":"locality"
},
  "geometry": {"coordinates":[126.33333,38.68333],"type":"Point"}
}