{
  "type": "Feature",
  "properties": {
    "gn:admin1_code":"3.0",
    "gn:asciiname":"Puksu-ri",
    "gn:country_code":"KP",
    "gn:dem":1259,
    "gn:feature_class":"P",
    "gn:feature_code":"PPL",
    "gn:name":"Puksu-ri",
    "gn:population":0,
    "gn:timezone":"Asia/Pyongyang",
    "iso:country":"KP",
    "name:kor_x_preferred":[
        "\ubd81\uc218\ub9ac"
    ],
    "wof:name":"Puksu-ri",
    "wof:placetype":"locality"
},
  "geometry": {"coordinates":[127.07167,40.54333],"type":"Point"}
}