{
  "type": "Feature",
  "properties": {
    "gn:admin1_code":"6.0",
    "gn:asciiname":"Sinjong-dong",
    "gn:country_code":"KP",
    "gn:dem":13,
    "gn:feature_class":"P",
    "gn:feature_code":"PPL",
    "gn:name":"Sinj\u014fng-dong",
    "gn:population":0,
    "gn:timezone":"Asia/Pyongyang",
    "iso:country":"KP",
    "name:und_x_variant":[
        "\uc2e0\uc815\ub3d9",
        "Sinj\u014fng-dong"
    ],
    "wof:name":"Sinjong-dong",
    "wof:placetype":"locality"
},
  "geometry": {"coordinates":[124.98556000000001,38.63222],"type":"Point"}
}