{
  "type": "Feature",
  "properties": {
    "gn:admin1_code":"6.0",
    "gn:admin2_code":"Paech\u2019\u014fn-gun",
    "gn:asciiname":"Munsal-li",
    "gn:country_code":"KP",
    "gn:dem":19,
    "gn:feature_class":"P",
    "gn:feature_code":"PPL",
    "gn:name":"Munsal-li",
    "gn:population":0,
    "gn:timezone":"Asia/Pyongyang",
    "iso:country":"KP",
    "name:und_x_variant":[
        "Munsa-ri",
        "Munsan-ni",
        "Munsal-li"
    ],
    "wof:name":"Munsal-li",
    "wof:placetype":"locality"
},
  "geometry": {"coordinates":[126.36667,37.89889],"type":"Point"}
}