{
  "type": "Feature",
  "properties": {
    "gn:admin1_code":"11.0",
    "gn:asciiname":"Unhung-ni",
    "gn:cc2":"KP",
    "gn:country_code":"KP",
    "gn:dem":40,
    "gn:feature_class":"P",
    "gn:feature_code":"PPL",
    "gn:name":"\u016cnh\u016dng-ni",
    "gn:population":0,
    "gn:timezone":"Asia/Pyongyang",
    "iso:country":"KP",
    "name:und_x_variant":[
        "Unhung-hi",
        "\u016cnh\u016dng-ni"
    ],
    "wof:name":"Unhung-ni",
    "wof:placetype":"locality"
},
  "geometry": {"coordinates":[125.49333,39.88167],"type":"Point"}
}