{
  "type": "Feature",
  "properties": {
    "gn:admin1_code":"0.0",
    "gn:asciiname":"Unhung-ni",
    "gn:country_code":"KP",
    "gn:dem":29,
    "gn:feature_class":"P",
    "gn:feature_code":"PPL",
    "gn:name":"Unh\u016dng-ni",
    "gn:population":0,
    "gn:timezone":"Asia/Pyongyang",
    "iso:country":"KP",
    "name:kor_x_preferred":[
        "\uc6b4\ud765\ub9ac"
    ],
    "name:und_x_variant":[
        "Unh\u016dng-ni"
    ],
    "wof:name":"Unhung-ni",
    "wof:placetype":"locality"
},
  "geometry": {"coordinates":[125.81667,39.66667],"type":"Point"}
}