{
  "type": "Feature",
  "properties": {
    "gn:admin1_code":"7.0",
    "gn:asciiname":"Ungdam-ni",
    "gn:country_code":"KP",
    "gn:dem":330,
    "gn:feature_class":"P",
    "gn:feature_code":"PPL",
    "gn:name":"Ungdam-ni",
    "gn:population":0,
    "gn:timezone":"Asia/Pyongyang",
    "iso:country":"KP",
    "name:und_x_variant":[
        "\uc6c5\ub2f4\ub9ac",
        "Ungdam-ni"
    ],
    "wof:name":"Ungdam-ni",
    "wof:placetype":"locality"
},
  "geometry": {"coordinates":[126.66777999999999,39.07722],"type":"Point"}
}