{
  "type": "Feature",
  "properties": {
    "gn:admin1_code":"3.0",
    "gn:asciiname":"Subuk-ch'on",
    "gn:country_code":"KP",
    "gn:dem":265,
    "gn:feature_class":"P",
    "gn:feature_code":"PPL",
    "gn:name":"Subuk-ch\u2019on",
    "gn:population":0,
    "gn:timezone":"Asia/Pyongyang",
    "iso:country":"KP",
    "name:und_x_variant":[
        "Subuk-ch\u2019on",
        "\uc218\ubd81\ucd0c"
    ],
    "wof:name":"Subuk-ch'on",
    "wof:placetype":"locality"
},
  "geometry": {"coordinates":[128.58111,40.44673],"type":"Point"}
}