{
  "type": "Feature",
  "properties": {
    "gn:admin1_code":"3.0",
    "gn:asciiname":"Sangjukchol-li",
    "gn:country_code":"KP",
    "gn:dem":371,
    "gn:feature_class":"P",
    "gn:feature_code":"PPL",
    "gn:name":"Sangjukch\u014fl-li",
    "gn:population":0,
    "gn:timezone":"Asia/Pyongyang",
    "iso:country":"KP",
    "name:kor_x_preferred":[
        "\uc0c1\uc8fd\uc804\ub9ac"
    ],
    "name:kor_x_variant":[
        "Sangjukch\u014fl-li"
    ],
    "wof:name":"Sangjukchol-li",
    "wof:placetype":"locality"
},
  "geometry": {"coordinates":[126.97917,39.34583],"type":"Point"}
}