{
  "type": "Feature",
  "properties": {
    "gn:admin1_code":"6.0",
    "gn:asciiname":"Sangyang-dong",
    "gn:country_code":"KP",
    "gn:dem":153,
    "gn:feature_class":"P",
    "gn:feature_code":"PPL",
    "gn:name":"Sangyang-dong",
    "gn:population":0,
    "gn:timezone":"Asia/Pyongyang",
    "iso:country":"KP",
    "wof:name":"Sangyang-dong",
    "wof:placetype":"locality"
},
  "geometry": {"coordinates":[125.80972,38.12611],"type":"Point"}
}