{
  "type": "Feature",
  "properties": {
    "gn:admin1_code":"9.0",
    "gn:admin2_code":"1875980",
    "gn:asciiname":"Chwap'ae-ri",
    "gn:country_code":"KP",
    "gn:dem":412,
    "gn:feature_class":"P",
    "gn:feature_code":"PPL",
    "gn:name":"Chwap\u2019ae-ri",
    "gn:population":0,
    "gn:timezone":"Asia/Pyongyang",
    "iso:country":"KP",
    "name:kor_x_preferred":[
        "\uc88c\ud328\ub9ac"
    ],
    "name:und_x_variant":[
        "Chwap\u2019ae-ri"
    ],
    "wof:name":"Chwap'ae-ri",
    "wof:placetype":"locality"
},
  "geometry": {"coordinates":[127.73639,38.4125],"type":"Point"}
}