{
  "type": "Feature",
  "properties": {
    "gn:admin1_code":"6.0",
    "gn:asciiname":"Hang-dong",
    "gn:country_code":"KP",
    "gn:dem":152,
    "gn:feature_class":"P",
    "gn:feature_code":"PPL",
    "gn:name":"Hang-dong",
    "gn:population":0,
    "gn:timezone":"Asia/Pyongyang",
    "iso:country":"KP",
    "name:kor_x_preferred":[
        "\ud56d\ub3d9"
    ],
    "name:msa_x_preferred":[
        "Hang-dong"
    ],
    "name:sco_x_preferred":[
        "Hang-dong"
    ],
    "name:vie_x_preferred":[
        "Hang-dong"
    ],
    "wof:name":"Hang-dong",
    "wof:placetype":"locality"
},
  "geometry": {"coordinates":[125.48806,38.17139],"type":"Point"}
}