{
  "type": "Feature",
  "properties": {
    "gn:admin1_code":"1.0",
    "gn:asciiname":"Hwagol-li",
    "gn:country_code":"KP",
    "gn:dem":465,
    "gn:feature_class":"P",
    "gn:feature_code":"PPL",
    "gn:name":"Hwag\u014fl-li",
    "gn:population":0,
    "gn:timezone":"Asia/Pyongyang",
    "iso:country":"KP",
    "name:und_x_variant":[
        "\ud654\uac74\ub9ac",
        "Hwag\u014fn-ni",
        "Hwag\u014fl-li"
    ],
    "wof:name":"Hwagol-li",
    "wof:placetype":"locality"
},
  "geometry": {"coordinates":[125.94917,40.70917],"type":"Point"}
}