{
  "type": "Feature",
  "properties": {
    "gn:admin1_code":"12.0",
    "gn:asciiname":"Sanuch'on",
    "gn:country_code":"KP",
    "gn:dem":53,
    "gn:feature_class":"P",
    "gn:feature_code":"PPL",
    "gn:name":"Sanuch\u2019\u014fn",
    "gn:population":0,
    "gn:timezone":"Asia/Pyongyang",
    "iso:country":"KP",
    "name:kor_x_preferred":[
        "Sanuch\u2019on"
    ],
    "name:kor_x_variant":[
        "\uc0b0\uc6b0\ucc9c"
    ],
    "name:und_x_variant":[
        "Sanuch\u2019\u014fn",
        "Sanucheon"
    ],
    "wof:name":"Sanuch'on",
    "wof:placetype":"locality"
},
  "geometry": {"coordinates":[125.81263,39.14594],"type":"Point"}
}