{
  "type": "Feature",
  "properties": {
    "gn:admin1_code":"0.0",
    "gn:asciiname":"Kujin",
    "gn:country_code":"KP",
    "gn:dem":22,
    "gn:feature_class":"P",
    "gn:feature_code":"PPL",
    "gn:name":"Kujin",
    "gn:population":0,
    "gn:timezone":"Asia/Pyongyang",
    "iso:country":"KP",
    "name:kor_x_preferred":[
        "\uad6c\uc9c4"
    ],
    "wof:name":"Kujin",
    "wof:placetype":"locality"
},
  "geometry": {"coordinates":[125.56889,39.70944],"type":"Point"}
}