{
  "type": "Feature",
  "properties": {
    "gn:admin1_code":"17.0",
    "gn:asciiname":"Sangnyongsan",
    "gn:country_code":"KP",
    "gn:dem":119,
    "gn:feature_class":"P",
    "gn:feature_code":"PPL",
    "gn:name":"Sangnyongsan",
    "gn:population":0,
    "gn:timezone":"Asia/Pyongyang",
    "iso:country":"KP",
    "wof:name":"Sangnyongsan",
    "wof:placetype":"locality"
},
  "geometry": {"coordinates":[129.63333,41.26667],"type":"Point"}
}