{
  "type": "Feature",
  "properties": {
    "gn:admin1_code":"11.0",
    "gn:asciiname":"Yongch'ang-ni",
    "gn:country_code":"KP",
    "gn:dem":186,
    "gn:feature_class":"P",
    "gn:feature_code":"PPL",
    "gn:name":"Yongch\u2019ang-ni",
    "gn:population":0,
    "gn:timezone":"Asia/Pyongyang",
    "iso:country":"KP",
    "name:eng_x_preferred":[
        "Yongch'ang"
    ],
    "name:eng_x_variant":[
        "Yongch'ang-ni"
    ],
    "name:und_x_variant":[
        "Yongch\u2019ang-dong",
        "\ub8e1\ucc3d\ub9ac",
        "Yongch\u2019ang-ni"
    ],
    "wof:name":"Yongch'ang",
    "wof:placetype":"locality"
},
  "geometry": {"coordinates":[125.26778,40.17917],"type":"Point"}
}