{
  "type": "Feature",
  "properties": {
    "gn:admin1_code":"9.0",
    "gn:asciiname":"Unmoksanae",
    "gn:country_code":"KP",
    "gn:dem":303,
    "gn:feature_class":"P",
    "gn:feature_code":"PPL",
    "gn:name":"Unm\u014fksanae",
    "gn:population":0,
    "gn:timezone":"Asia/Pyongyang",
    "iso:country":"KP",
    "wof:name":"Unmoksanae",
    "wof:placetype":"locality"
},
  "geometry": {"coordinates":[127.84222,38.53083],"type":"Point"}
}