{
  "type": "Feature",
  "properties": {
    "gn:admin1_code":"12.0",
    "gn:asciiname":"Taemo-dong",
    "gn:country_code":"KP",
    "gn:dem":36,
    "gn:feature_class":"P",
    "gn:feature_code":"PPL",
    "gn:name":"Taemo-dong",
    "gn:population":0,
    "gn:timezone":"Asia/Pyongyang",
    "iso:country":"KP",
    "name:und_x_variant":[
        "\ub300\ubaa8\ub3d9",
        "Taemo-dong"
    ],
    "wof:name":"Taemo-dong",
    "wof:placetype":"locality"
},
  "geometry": {"coordinates":[125.93277999999999,38.96861],"type":"Point"}
}