{
  "type": "Feature",
  "properties": {
    "gn:admin1_code":"6.0",
    "gn:asciiname":"Kuhak-tong",
    "gn:country_code":"KP",
    "gn:dem":111,
    "gn:feature_class":"P",
    "gn:feature_code":"PPL",
    "gn:name":"Kuhak-tong",
    "gn:population":0,
    "gn:timezone":"Asia/Pyongyang",
    "iso:country":"KP",
    "name:eng_x_preferred":[
        "Kuhak"
    ],
    "name:eng_x_variant":[
        "Kuhak-tong"
    ],
    "name:und_x_variant":[
        "\uad6c\ud559\ub3d9",
        "Kuhak-tong"
    ],
    "wof:name":"Kuhak",
    "wof:placetype":"locality"
},
  "geometry": {"coordinates":[126.29917,38.09917],"type":"Point"}
}