{
  "type": "Feature",
  "properties": {
    "gn:admin1_code":"12.0",
    "gn:asciiname":"Soenaktari",
    "gn:country_code":"KP",
    "gn:dem":37,
    "gn:feature_class":"P",
    "gn:feature_code":"PPL",
    "gn:name":"Soenaktari",
    "gn:population":0,
    "gn:timezone":"Asia/Pyongyang",
    "iso:country":"KP",
    "name:und_x_variant":[
        "\uc1e0\ub099\ub2e4\ub9ac",
        "Soenaktari",
        "Soenakdali"
    ],
    "wof:name":"Soenaktari",
    "wof:placetype":"locality"
},
  "geometry": {"coordinates":[125.74778000000001,38.88917],"type":"Point"}
}