{
  "type": "Feature",
  "properties": {
    "gn:admin1_code":"6.0",
    "gn:asciiname":"Orijong",
    "gn:country_code":"KP",
    "gn:dem":60,
    "gn:feature_class":"P",
    "gn:feature_code":"PPL",
    "gn:name":"Orij\u014fng",
    "gn:population":0,
    "gn:timezone":"Asia/Pyongyang",
    "iso:country":"KP",
    "name:und_x_variant":[
        "\uc624\ub9ac\uc815",
        "Orij\u014fng"
    ],
    "wof:name":"Orijong",
    "wof:placetype":"locality"
},
  "geometry": {"coordinates":[125.125,38.15083],"type":"Point"}
}