{
  "type": "Feature",
  "properties": {
    "gn:admin1_code":"11.0",
    "gn:asciiname":"Tokp'yong-dong",
    "gn:country_code":"KP",
    "gn:dem":120,
    "gn:feature_class":"P",
    "gn:feature_code":"PPL",
    "gn:name":"T\u014fkp\u2019y\u014fng-dong",
    "gn:population":0,
    "gn:timezone":"Asia/Pyongyang",
    "iso:country":"KP",
    "name:kor_x_preferred":[
        "\ub355\ud3c9\ub3d9"
    ],
    "name:und_x_variant":[
        "T\u014fkp\u2019y\u014fng-dong"
    ],
    "wof:name":"Tokp'yong-dong",
    "wof:placetype":"locality"
},
  "geometry": {"coordinates":[125.44056,40.00167],"type":"Point"}
}