{
  "type": "Feature",
  "properties": {
    "gn:admin1_code":"3.0",
    "gn:asciiname":"Konjagae",
    "gn:country_code":"KP",
    "gn:dem":1147,
    "gn:feature_class":"P",
    "gn:feature_code":"PPL",
    "gn:name":"K\u014fnjagae",
    "gn:population":0,
    "gn:timezone":"Asia/Pyongyang",
    "iso:country":"KP",
    "name:und_x_variant":[
        "\uac74\uc790\uac1c",
        "K\u014fnjagae"
    ],
    "wof:name":"Konjagae",
    "wof:placetype":"locality"
},
  "geometry": {"coordinates":[127.28361,40.31194],"type":"Point"}
}