{
  "type": "Feature",
  "properties": {
    "gn:admin1_code":"6.0",
    "gn:asciiname":"Sindae",
    "gn:country_code":"KP",
    "gn:dem":95,
    "gn:feature_class":"P",
    "gn:feature_code":"PPL",
    "gn:name":"Sindae",
    "gn:population":0,
    "gn:timezone":"Asia/Pyongyang",
    "iso:country":"KP",
    "wof:name":"Sindae",
    "wof:placetype":"locality"
},
  "geometry": {"coordinates":[125.71472,38.16444],"type":"Point"}
}