{
  "type": "Feature",
  "properties": {
    "gn:admin1_code":"3.0",
    "gn:asciiname":"Ogu-ch'on",
    "gn:country_code":"KP",
    "gn:dem":109,
    "gn:feature_class":"P",
    "gn:feature_code":"PPL",
    "gn:name":"\u014egu-ch\u2019on",
    "gn:population":0,
    "gn:timezone":"Asia/Pyongyang",
    "iso:country":"KP",
    "name:und_x_variant":[
        "\uc5b4\uad6c\ucd0c",
        "\u014egu-ch\u2019on"
    ],
    "wof:name":"Ogu-ch'on",
    "wof:placetype":"locality"
},
  "geometry": {"coordinates":[128.72278,40.37972],"type":"Point"}
}