{
  "type": "Feature",
  "properties": {
    "gn:admin1_code":"6.0",
    "gn:asciiname":"Chungp'o",
    "gn:country_code":"KP",
    "gn:dem":36,
    "gn:feature_class":"P",
    "gn:feature_code":"PPL",
    "gn:name":"Chungp\u2019o",
    "gn:population":0,
    "gn:timezone":"Asia/Pyongyang",
    "iso:country":"KP",
    "name:kor_x_preferred":[
        "\uc911\ud3ec"
    ],
    "name:und_x_variant":[
        "Chungp\u2019o"
    ],
    "wof:name":"Chungp'o",
    "wof:placetype":"locality"
},
  "geometry": {"coordinates":[125.58667,38.32556],"type":"Point"}
}