{
  "type": "Feature",
  "properties": {
    "gn:admin1_code":"17.0",
    "gn:asciiname":"P'arhyang-dong",
    "gn:country_code":"KP",
    "gn:dem":39,
    "gn:feature_class":"P",
    "gn:feature_code":"PPL",
    "gn:name":"P\u2019arhyang-dong",
    "gn:population":0,
    "gn:timezone":"Asia/Pyongyang",
    "iso:country":"KP",
    "name:und_x_variant":[
        "\ud314\ud5a5\ub3d9",
        "P\u2019arhyang-dong"
    ],
    "wof:name":"P'arhyang-dong",
    "wof:placetype":"locality"
},
  "geometry": {"coordinates":[129.57388999999998,41.59417],"type":"Point"}
}