{
  "type": "Feature",
  "properties": {
    "gn:admin1_code":"3.0",
    "gn:asciiname":"Chunghung-ni",
    "gn:country_code":"KP",
    "gn:dem":8,
    "gn:feature_class":"P",
    "gn:feature_code":"PPL",
    "gn:name":"Chungh\u016dng-ni",
    "gn:population":0,
    "gn:timezone":"Asia/Pyongyang",
    "iso:country":"KP",
    "name:eng_x_preferred":[
        "Chunghung"
    ],
    "name:eng_x_variant":[
        "Chunghung-ni"
    ],
    "name:und_x_variant":[
        "\uc911\ud765\ub9ac",
        "Chungh\u016dng-ni"
    ],
    "wof:name":"Chunghung",
    "wof:placetype":"locality"
},
  "geometry": {"coordinates":[127.455,39.82],"type":"Point"}
}