{
  "type": "Feature",
  "properties": {
    "gn:admin1_code":"15.0",
    "gn:asciiname":"Taehyon-dong",
    "gn:country_code":"KP",
    "gn:dem":263,
    "gn:feature_class":"P",
    "gn:feature_code":"PPL",
    "gn:name":"Taehy\u014fn-dong",
    "gn:population":0,
    "gn:timezone":"Asia/Pyongyang",
    "iso:country":"KP",
    "name:kor_x_preferred":[
        "\ub300\ud604\ub3d9"
    ],
    "name:kor_x_variant":[
        "Taehy\u014fn-dong"
    ],
    "wof:name":"Taehyon-dong",
    "wof:placetype":"locality"
},
  "geometry": {"coordinates":[126.48721999999999,39.05167],"type":"Point"}
}