{
  "type": "Feature",
  "properties": {
    "gn:admin1_code":"11.0",
    "gn:asciiname":"Songoe-ri",
    "gn:country_code":"KP",
    "gn:dem":60,
    "gn:feature_class":"P",
    "gn:feature_code":"PPL",
    "gn:name":"S\u014fngoe-ri",
    "gn:population":0,
    "gn:timezone":"Asia/Pyongyang",
    "iso:country":"KP",
    "name:kor_x_preferred":[
        "\uc131\uc678\ub9ac"
    ],
    "name:und_x_variant":[
        "S\u014fngoe-ri"
    ],
    "wof:name":"Songoe-ri",
    "wof:placetype":"locality"
},
  "geometry": {"coordinates":[124.83056000000001,39.80222],"type":"Point"}
}