{
  "type": "Feature",
  "properties": {
    "gn:admin1_code":"17.0",
    "gn:asciiname":"Tunam-ni",
    "gn:country_code":"KP",
    "gn:dem":23,
    "gn:feature_class":"P",
    "gn:feature_code":"PPLL",
    "gn:name":"Tunam-ni",
    "gn:population":0,
    "gn:timezone":"Asia/Pyongyang",
    "iso:country":"KP",
    "name:und_x_variant":[
        "Tunam-dong",
        "Tonan-d\u014f",
        "\ub450\ub0a8\ub9ac",
        "Tunam-ni"
    ],
    "wof:name":"Tunam-ni",
    "wof:placetype":"locality"
},
  "geometry": {"coordinates":[129.59888999999998,41.46528],"type":"Point"}
}