{
  "type": "Feature",
  "properties": {
    "gn:admin1_code":"3.0",
    "gn:asciiname":"Taehuksong-ni",
    "gn:country_code":"KP",
    "gn:dem":9,
    "gn:feature_class":"P",
    "gn:feature_code":"PPL",
    "gn:name":"Taeh\u016dks\u014fng-ni",
    "gn:population":0,
    "gn:timezone":"Asia/Pyongyang",
    "iso:country":"KP",
    "name:eng_x_preferred":[
        "Taehuksong"
    ],
    "name:eng_x_variant":[
        "Taehuksong-ni"
    ],
    "name:und_x_variant":[
        "\ub300\ud751\uc11d\ub9ac",
        "Taeh\u016dks\u014fng-ni"
    ],
    "wof:name":"Taehuksong",
    "wof:placetype":"locality"
},
  "geometry": {"coordinates":[127.30500000000001,39.51278],"type":"Point"}
}