{
  "type": "Feature",
  "properties": {
    "gn:admin1_code":"1.0",
    "gn:admin2_code":"Yongnim-gun",
    "gn:asciiname":"Unhakch'am",
    "gn:country_code":"KP",
    "gn:dem":1120,
    "gn:feature_class":"P",
    "gn:feature_code":"PPL",
    "gn:name":"Unhakch\u2019am",
    "gn:population":0,
    "gn:timezone":"Asia/Pyongyang",
    "iso:country":"KP",
    "name:kor_x_preferred":[
        "\uc6b4\ud559\ucc38"
    ],
    "name:und_x_variant":[
        "Unhakch\u2019am"
    ],
    "wof:name":"Unhakch'am",
    "wof:placetype":"locality"
},
  "geometry": {"coordinates":[126.80667,40.37222],"type":"Point"}
}