{
  "type": "Feature",
  "properties": {
    "gn:admin1_code":"13.0",
    "gn:asciiname":"Taejang-dong",
    "gn:country_code":"KP",
    "gn:dem":1343,
    "gn:feature_class":"P",
    "gn:feature_code":"PPL",
    "gn:name":"Taejang-dong",
    "gn:population":0,
    "gn:timezone":"Asia/Pyongyang",
    "iso:country":"KP",
    "name:kor_x_preferred":[
        "\ub300\uc7a5\ub3d9"
    ],
    "wof:name":"Taejang-dong",
    "wof:placetype":"locality"
},
  "geometry": {"coordinates":[127.86667,41.26667],"type":"Point"}
}