{
  "type": "Feature",
  "properties": {
    "gn:admin1_code":"0.0",
    "gn:asciiname":"Ukkamsu",
    "gn:country_code":"KP",
    "gn:dem":37,
    "gn:feature_class":"P",
    "gn:feature_code":"PPL",
    "gn:name":"Ukkamsu",
    "gn:population":0,
    "gn:timezone":"Asia/Pyongyang",
    "iso:country":"KP",
    "name:kor_x_preferred":[
        "\uc6c3\uac10\uc218"
    ],
    "wof:name":"Ukkamsu",
    "wof:placetype":"locality"
},
  "geometry": {"coordinates":[125.91667,38.06667],"type":"Point"}
}