{
  "type": "Feature",
  "properties": {
    "gn:country":"KP",
    "gn:fcode":"PPL",
    "gn:population":13440,
    "iso:country":"KP",
    "name:eng_x_preferred":[
        "Yonggang"
    ],
    "name:eng_x_variant":[
        "Yonggang-\u016dp"
    ],
    "name:und_x_variant":[
        "Chinji-ri"
    ],
    "qs:name":"Yonggang-\u016dp",
    "qs:photos_9r":0,
    "qs:photos_sr":0,
    "qs:pop_sr":"6",
    "wof:name":"Yonggang",
    "wof:placetype":"locality",
    "wof:population":13440
},
  "geometry": {"coordinates":[125.42444,38.85611],"type":"Point"}
}