{
  "type": "Feature",
  "properties": {
    "gn:admin1_code":"17.0",
    "gn:asciiname":"Sap'yong",
    "gn:country_code":"KP",
    "gn:dem":56,
    "gn:feature_class":"P",
    "gn:feature_code":"PPL",
    "gn:name":"Sap\u2019y\u014fng",
    "gn:population":0,
    "gn:timezone":"Asia/Pyongyang",
    "iso:country":"KP",
    "name:und_x_variant":[
        "\uc0ac\ud3c9",
        "Sap\u2019y\u014fng"
    ],
    "wof:name":"Sap'yong",
    "wof:placetype":"locality"
},
  "geometry": {"coordinates":[129.565,41.62028],"type":"Point"}
}