{
  "type": "Feature",
  "properties": {
    "gn:admin1_code":"3.0",
    "gn:asciiname":"Ch'ongyang-ch'on",
    "gn:country_code":"KP",
    "gn:dem":174,
    "gn:feature_class":"P",
    "gn:feature_code":"PPL",
    "gn:name":"Ch\u2019\u014fngyang-ch\u2019on",
    "gn:population":0,
    "gn:timezone":"Asia/Pyongyang",
    "iso:country":"KP",
    "name:und_x_variant":[
        "Ch\u2019\u014fngyang-ch\u2019on",
        "\uccad\uc591\ucd0c"
    ],
    "wof:name":"Ch'ongyang-ch'on",
    "wof:placetype":"locality"
},
  "geometry": {"coordinates":[128.16636,40.25567],"type":"Point"}
}