{
  "type": "Feature",
  "properties": {
    "gn:admin1_code":"9.0",
    "gn:asciiname":"Songdul",
    "gn:country_code":"KP",
    "gn:dem":502,
    "gn:feature_class":"P",
    "gn:feature_code":"PPL",
    "gn:name":"S\u014fngd\u016dl",
    "gn:population":0,
    "gn:timezone":"Asia/Pyongyang",
    "iso:country":"KP",
    "name:kor_x_preferred":[
        "\uc131\ub4e4"
    ],
    "name:kor_x_variant":[
        "S\u014fngd\u016dl"
    ],
    "name:und_x_variant":[
        "S\u014fngp\u2019y\u014fng",
        "S\u014fngt\u016dl",
        "S\u014fngp\u2019y\u014fng-ni"
    ],
    "wof:name":"Songdul",
    "wof:placetype":"locality"
},
  "geometry": {"coordinates":[127.29333,38.76667],"type":"Point"}
}