{
  "type": "Feature",
  "properties": {
    "gn:admin1_code":"11.0",
    "gn:asciiname":"Masang-ni",
    "gn:country_code":"KP",
    "gn:dem":256,
    "gn:feature_class":"P",
    "gn:feature_code":"PPL",
    "gn:name":"Masang-ni",
    "gn:population":0,
    "gn:timezone":"Asia/Pyongyang",
    "iso:country":"KP",
    "name:eng_x_preferred":[
        "Masang"
    ],
    "name:eng_x_variant":[
        "Masang-ni"
    ],
    "name:kor_x_preferred":[
        "\ub9c8\uc0c1\ub9ac"
    ],
    "wof:name":"Masang",
    "wof:placetype":"locality"
},
  "geometry": {"coordinates":[124.95917,40.15833],"type":"Point"}
}