{
  "type": "Feature",
  "properties": {
    "gn:admin1_code":"1.0",
    "gn:asciiname":"Kyemyong-gol",
    "gn:country_code":"KP",
    "gn:dem":556,
    "gn:feature_class":"P",
    "gn:feature_code":"PPL",
    "gn:name":"Kyemy\u014fng-gol",
    "gn:population":0,
    "gn:timezone":"Asia/Pyongyang",
    "iso:country":"KP",
    "name:kor_x_preferred":[
        "\uacc4\uba85\uace8"
    ],
    "name:und_x_variant":[
        "Kyemy\u014fng-dong",
        "Kyemy\u014fng-kol",
        "Kyemy\u014fn-gol",
        "Keimei-d\u014d",
        "\uacc4\uba85\uace8",
        "Kyemy\u014fng-gol"
    ],
    "wof:name":"Kyemyong-gol",
    "wof:placetype":"locality"
},
  "geometry": {"coordinates":[126.66333,40.50083],"type":"Point"}
}