{
  "type": "Feature",
  "properties": {
    "gn:admin1_code":"12.0",
    "gn:asciiname":"Kuksugol",
    "gn:country_code":"KP",
    "gn:dem":47,
    "gn:feature_class":"P",
    "gn:feature_code":"PPL",
    "gn:name":"Kuksugol",
    "gn:population":0,
    "gn:timezone":"Asia/Pyongyang",
    "iso:country":"KP",
    "name:und_x_variant":[
        "Kuksu-dong",
        "\uad6d\uc218\uace8",
        "Kuksugol",
        "Guksugol"
    ],
    "wof:name":"Kuksugol",
    "wof:placetype":"locality"
},
  "geometry": {"coordinates":[125.89451,38.90122],"type":"Point"}
}