{
  "type": "Feature",
  "properties": {
    "gn:admin1_code":"12.0",
    "gn:admin2_code":"Sams\u014fk-kuy\u014fk",
    "gn:asciiname":"Sang-ni",
    "gn:country_code":"KP",
    "gn:dem":25,
    "gn:feature_class":"P",
    "gn:feature_code":"PPL",
    "gn:name":"Sang-ni",
    "gn:population":0,
    "gn:timezone":"Asia/Pyongyang",
    "iso:country":"KP",
    "name:kor_x_preferred":[
        "\uc0c1\ub9ac"
    ],
    "name:und_x_variant":[
        "Sangni"
    ],
    "wof:name":"Sang-ni",
    "wof:placetype":"locality"
},
  "geometry": {"coordinates":[126.00749999999999,39.09972],"type":"Point"}
}