{
  "type": "Feature",
  "properties": {
    "gn:admin1_code":"3.0",
    "gn:asciiname":"Sungdong-ni",
    "gn:country_code":"KP",
    "gn:dem":461,
    "gn:feature_class":"P",
    "gn:feature_code":"PPL",
    "gn:name":"S\u016dngdong-ni",
    "gn:population":0,
    "gn:timezone":"Asia/Pyongyang",
    "iso:country":"KP",
    "name:und_x_variant":[
        "S\u016dngdong-ni",
        "\uc2b9\ub3d9\ub9ac"
    ],
    "wof:name":"Sungdong-ni",
    "wof:placetype":"locality"
},
  "geometry": {"coordinates":[128.15303,40.39948],"type":"Point"}
}