{
  "type": "Feature",
  "properties": {
    "gn:admin1_code":"17.0",
    "gn:admin2_code":"2038910",
    "gn:asciiname":"Huin-dong",
    "gn:country_code":"KP",
    "gn:dem":617,
    "gn:feature_class":"P",
    "gn:feature_code":"PPL",
    "gn:name":"Huin-dong",
    "gn:population":0,
    "gn:timezone":"Asia/Pyongyang",
    "iso:country":"KP",
    "name:kor_x_preferred":[
        "\ud6c4\uc778\ub3d9"
    ],
    "wof:name":"Huin-dong",
    "wof:placetype":"locality"
},
  "geometry": {"coordinates":[128.96111000000002,41.99028],"type":"Point"}
}