{
  "type": "Feature",
  "properties": {
    "gn:admin1_code":"13.0",
    "gn:asciiname":"Hwangch'ol-gol",
    "gn:country_code":"KP",
    "gn:dem":1143,
    "gn:feature_class":"P",
    "gn:feature_code":"PPL",
    "gn:name":"Hwangch\u2019\u014fl-gol",
    "gn:population":0,
    "gn:timezone":"Asia/Pyongyang",
    "iso:country":"KP",
    "wof:name":"Hwangch'ol-gol",
    "wof:placetype":"locality"
},
  "geometry": {"coordinates":[128.78693999999999,41.07306],"type":"Point"}
}