{
  "type": "Feature",
  "properties": {
    "gn:admin1_code":"1.0",
    "gn:asciiname":"Worhajang",
    "gn:country_code":"KP",
    "gn:dem":1049,
    "gn:feature_class":"P",
    "gn:feature_code":"PPL",
    "gn:name":"W\u014frhajang",
    "gn:population":0,
    "gn:timezone":"Asia/Pyongyang",
    "iso:country":"KP",
    "name:und_x_variant":[
        "\uc6d4\ud558\uc7a5",
        "W\u014frhajang"
    ],
    "wof:name":"Worhajang",
    "wof:placetype":"locality"
},
  "geometry": {"coordinates":[127.11972,41.02222],"type":"Point"}
}