{
  "type": "Feature",
  "properties": {
    "gn:admin1_code":"7.0",
    "gn:asciiname":"Worun-dong",
    "gn:country_code":"KP",
    "gn:dem":182,
    "gn:feature_class":"P",
    "gn:feature_code":"PPL",
    "gn:name":"W\u014fr\u016dn-dong",
    "gn:population":0,
    "gn:timezone":"Asia/Pyongyang",
    "iso:country":"KP",
    "name:kor_x_preferred":[
        "\uc6d4\uc740\ub3d9"
    ],
    "name:kor_x_variant":[
        "W\u014fr\u016dn-dong"
    ],
    "wof:name":"Worun-dong",
    "wof:placetype":"locality"
},
  "geometry": {"coordinates":[126.37888999999998,38.4375],"type":"Point"}
}