{
  "type": "Feature",
  "properties": {
    "gn:admin1_code":"1.0",
    "gn:asciiname":"Hakkyo-dong",
    "gn:country_code":"KP",
    "gn:dem":252,
    "gn:feature_class":"P",
    "gn:feature_code":"PPL",
    "gn:name":"Hakkyo-dong",
    "gn:population":0,
    "gn:timezone":"Asia/Pyongyang",
    "iso:country":"KP",
    "name:und_x_variant":[
        "\ud559\uad50\ub3d9",
        "Hakkyo-dong"
    ],
    "wof:name":"Hakkyo-dong",
    "wof:placetype":"locality"
},
  "geometry": {"coordinates":[126.55722,41.35861],"type":"Point"}
}