{
  "type": "Feature",
  "properties": {
    "gn:admin1_code":"6.0",
    "gn:asciiname":"Taehung-ni",
    "gn:country_code":"KP",
    "gn:dem":3,
    "gn:feature_class":"P",
    "gn:feature_code":"PPL",
    "gn:name":"Taeh\u016dng-ni",
    "gn:population":0,
    "gn:timezone":"Asia/Pyongyang",
    "iso:country":"KP",
    "name:kor_x_preferred":[
        "\ub300\ud765\ub9ac"
    ],
    "name:kor_x_variant":[
        "Taeh\u016dng-ni"
    ],
    "name:und_x_variant":[
        "Kimjew\u014fn-ni",
        "Kimjew\u014fl-li"
    ],
    "wof:name":"Taehung-ni",
    "wof:placetype":"locality"
},
  "geometry": {"coordinates":[125.63333,38.51667],"type":"Point"}
}