{
  "type": "Feature",
  "properties": {
    "gn:admin1_code":"6.0",
    "gn:admin2_code":"P'anmun-gun",
    "gn:asciiname":"Chuk-tong",
    "gn:country_code":"KP",
    "gn:dem":52,
    "gn:feature_class":"P",
    "gn:feature_code":"PPL",
    "gn:name":"Chuk-tong",
    "gn:population":0,
    "gn:timezone":"Asia/Pyongyang",
    "iso:country":"KP",
    "name:eng_x_preferred":[
        "Chuk"
    ],
    "name:eng_x_variant":[
        "Chuk-tong"
    ],
    "wof:name":"Chuk",
    "wof:placetype":"locality"
},
  "geometry": {"coordinates":[126.61111,37.89361],"type":"Point"}
}