{
  "type": "Feature",
  "properties": {
    "gn:admin1_code":"1.0",
    "gn:asciiname":"Nungdae-dong",
    "gn:country_code":"KP",
    "gn:dem":374,
    "gn:feature_class":"P",
    "gn:feature_code":"PPL",
    "gn:name":"N\u016dngdae-dong",
    "gn:population":0,
    "gn:timezone":"Asia/Pyongyang",
    "iso:country":"KP",
    "name:und_x_variant":[
        "\ub2a5\ub300\ub3d9",
        "N\u016dngdae-dong"
    ],
    "wof:name":"Nungdae-dong",
    "wof:placetype":"locality"
},
  "geometry": {"coordinates":[125.99222,40.31278],"type":"Point"}
}