{
  "type": "Feature",
  "properties": {
    "gn:admin1_code":"1.0",
    "gn:asciiname":"Ch'angp'yong-ni",
    "gn:country_code":"KP",
    "gn:dem":448,
    "gn:feature_class":"P",
    "gn:feature_code":"PPL",
    "gn:name":"Ch\u2019angp\u2019y\u014fng-ni",
    "gn:population":0,
    "gn:timezone":"Asia/Pyongyang",
    "iso:country":"KP",
    "name:und_x_variant":[
        "Toksandong-Ch\u2019angp\u2019y\u014fng-ni",
        "\ucc3d\ud3c9\ub9ac",
        "Ch\u2019angp\u2019y\u014fng-ni"
    ],
    "wof:name":"Ch'angp'yong-ni",
    "wof:placetype":"locality"
},
  "geometry": {"coordinates":[126.35641,40.80949],"type":"Point"}
}