{
  "type": "Feature",
  "properties": {
    "gn:admin1_code":"1.0",
    "gn:asciiname":"Malgundami",
    "gn:country_code":"KP",
    "gn:dem":382,
    "gn:feature_class":"P",
    "gn:feature_code":"PPL",
    "gn:name":"Malg\u016dndami",
    "gn:population":0,
    "gn:timezone":"Asia/Pyongyang",
    "iso:country":"KP",
    "name:und_x_variant":[
        "\uccad\ub2f4\ucc38",
        "Ch\u2019\u014fngdamch\u2019am",
        "Malg\u016dndami",
        "\ub9d1\uc740\ub2f4\uc774"
    ],
    "wof:name":"Malgundami",
    "wof:placetype":"locality"
},
  "geometry": {"coordinates":[126.49437,40.35825],"type":"Point"}
}