{
  "type": "Feature",
  "properties": {
    "gn:admin1_code":"3.0",
    "gn:asciiname":"Yongso-ri",
    "gn:country_code":"KP",
    "gn:dem":400,
    "gn:feature_class":"P",
    "gn:feature_code":"PPL",
    "gn:name":"Yongs\u014f-ri",
    "gn:population":0,
    "gn:timezone":"Asia/Pyongyang",
    "iso:country":"KP",
    "name:und_x_variant":[
        "\uc6a9\uc11c\ub9ac",
        "Yongs\u014f-ri"
    ],
    "wof:name":"Yongso-ri",
    "wof:placetype":"locality"
},
  "geometry": {"coordinates":[127.98999999999999,40.20889],"type":"Point"}
}