{
  "type": "Feature",
  "properties": {
    "gn:admin1_code":"1.0",
    "gn:asciiname":"Yangch'un-dong",
    "gn:country_code":"KP",
    "gn:dem":529,
    "gn:feature_class":"P",
    "gn:feature_code":"PPL",
    "gn:name":"Yangch\u2019un-dong",
    "gn:population":0,
    "gn:timezone":"Asia/Pyongyang",
    "iso:country":"KP",
    "name:und_x_variant":[
        "\uc591\ucd98\ub3d9",
        "Yangch\u2019un-dong"
    ],
    "wof:name":"Yangch'un-dong",
    "wof:placetype":"locality"
},
  "geometry": {"coordinates":[125.97556000000002,40.72472],"type":"Point"}
}