{
  "type": "Feature",
  "properties": {
    "gn:admin1_code":"6.0",
    "gn:asciiname":"Tang-gol",
    "gn:country_code":"KP",
    "gn:dem":9,
    "gn:feature_class":"P",
    "gn:feature_code":"PPL",
    "gn:name":"Tang-gol",
    "gn:population":0,
    "gn:timezone":"Asia/Pyongyang",
    "iso:country":"KP",
    "name:und_x_variant":[
        "Tang-dong",
        "\ub2f9\uace8",
        "Tang-gol"
    ],
    "wof:name":"Tang-gol",
    "wof:placetype":"locality"
},
  "geometry": {"coordinates":[125.20471999999999,37.96583],"type":"Point"}
}