{
  "type": "Feature",
  "properties": {
    "gn:admin1_code":"1.0",
    "gn:asciiname":"Ch'och'och'am",
    "gn:country_code":"KP",
    "gn:dem":208,
    "gn:feature_class":"P",
    "gn:feature_code":"PPL",
    "gn:name":"Ch\u2019och\u2019och\u2019am",
    "gn:population":0,
    "gn:timezone":"Asia/Pyongyang",
    "iso:country":"KP",
    "name:und_x_variant":[
        "\ucd08\ucd08\ucc38",
        "Ch\u2019och\u2019och\u2019am"
    ],
    "wof:name":"Ch'och'och'am",
    "wof:placetype":"locality"
},
  "geometry": {"coordinates":[126.32222,40.23861],"type":"Point"}
}