{
  "type": "Feature",
  "properties": {
    "gn:admin1_code":"11.0",
    "gn:asciiname":"Nallang-dong",
    "gn:country_code":"KP",
    "gn:dem":53,
    "gn:feature_class":"P",
    "gn:feature_code":"PPL",
    "gn:name":"Nallang-dong",
    "gn:population":0,
    "gn:timezone":"Asia/Pyongyang",
    "iso:country":"KP",
    "name:kor_x_preferred":[
        "\ub09c\ub791\ub3d9"
    ],
    "wof:name":"Nallang-dong",
    "wof:placetype":"locality"
},
  "geometry": {"coordinates":[124.75139,39.84],"type":"Point"}
}