{
  "type": "Feature",
  "properties": {
    "gn:admin1_code":"11.0",
    "gn:asciiname":"Kwanhyon-dong",
    "gn:country_code":"KP",
    "gn:dem":71,
    "gn:feature_class":"P",
    "gn:feature_code":"PPL",
    "gn:name":"Kwanhy\u014fn-dong",
    "gn:population":0,
    "gn:timezone":"Asia/Pyongyang",
    "iso:country":"KP",
    "name:kor_x_preferred":[
        "Kwanhy\u014fn-dong"
    ],
    "name:kor_x_variant":[
        "\uad00\ud604\ub3d9"
    ],
    "wof:name":"Kwanhyon-dong",
    "wof:placetype":"locality"
},
  "geometry": {"coordinates":[124.88639000000001,39.78722],"type":"Point"}
}