{
  "type": "Feature",
  "properties": {
    "gn:admin1_code":"7.0",
    "gn:asciiname":"Pomal-li",
    "gn:country_code":"KP",
    "gn:dem":107,
    "gn:feature_class":"P",
    "gn:feature_code":"PPL",
    "gn:name":"P\u014fmal-li",
    "gn:population":0,
    "gn:timezone":"Asia/Pyongyang",
    "iso:country":"KP",
    "name:kor_x_preferred":[
        "\ubc94\uc548\ub9ac"
    ],
    "name:kor_x_variant":[
        "P\u014fmal-li"
    ],
    "name:und_x_variant":[
        "P\u014fman-ni"
    ],
    "wof:name":"Pomal-li",
    "wof:placetype":"locality"
},
  "geometry": {"coordinates":[126.32639,38.31528],"type":"Point"}
}