{
  "type": "Feature",
  "properties": {
    "gn:admin1_code":"9.0",
    "gn:asciiname":"Hoejol-li",
    "gn:country_code":"KP",
    "gn:dem":653,
    "gn:feature_class":"P",
    "gn:feature_code":"PPL",
    "gn:name":"Hoej\u014fl-li",
    "gn:population":0,
    "gn:timezone":"Asia/Pyongyang",
    "iso:country":"KP",
    "name:kor_x_preferred":[
        "\ud68c\uc804\ub9ac"
    ],
    "name:kor_x_variant":[
        "Hoej\u014fl-li"
    ],
    "name:und_x_variant":[
        "Hoejon-ni"
    ],
    "wof:name":"Hoejol-li",
    "wof:placetype":"locality"
},
  "geometry": {"coordinates":[127.23667,38.81],"type":"Point"}
}