{
  "type": "Feature",
  "properties": {
    "gn:admin1_code":"15.0",
    "gn:asciiname":"Talsang-ni",
    "gn:country_code":"KP",
    "gn:dem":14,
    "gn:feature_class":"P",
    "gn:feature_code":"PPL",
    "gn:name":"Talsang-ni",
    "gn:population":0,
    "gn:timezone":"Asia/Pyongyang",
    "iso:country":"KP",
    "name:eng_x_preferred":[
        "Talsang"
    ],
    "name:eng_x_variant":[
        "Talsang-ni"
    ],
    "name:und_x_variant":[
        "\ub2ec\uc0c1\ub9ac",
        "Talsang-ni"
    ],
    "wof:name":"Talsang",
    "wof:placetype":"locality"
},
  "geometry": {"coordinates":[125.27639000000001,38.98556],"type":"Point"}
}