{
  "type": "Feature",
  "properties": {
    "gn:admin1_code":"15.0",
    "gn:asciiname":"Namch'ol-li",
    "gn:country_code":"KP",
    "gn:dem":177,
    "gn:feature_class":"P",
    "gn:feature_code":"PPL",
    "gn:name":"Namch\u2019\u014fl-li",
    "gn:population":0,
    "gn:timezone":"Asia/Pyongyang",
    "iso:country":"KP",
    "name:kor_x_preferred":[
        "\ub0a8\ucc9c\ub9ac"
    ],
    "name:kor_x_variant":[
        "Namch\u2019\u014fl-li"
    ],
    "name:und_x_variant":[
        "Namch\u2019\u014fn-ni"
    ],
    "wof:name":"Namch'ol-li",
    "wof:placetype":"locality"
},
  "geometry": {"coordinates":[126.32583,39.495],"type":"Point"}
}