{
  "type": "Feature",
  "properties": {
    "gn:admin1_code":"7.0",
    "gn:asciiname":"Tap-tong",
    "gn:country_code":"KP",
    "gn:dem":56,
    "gn:feature_class":"P",
    "gn:feature_code":"PPL",
    "gn:name":"Tap-tong",
    "gn:population":0,
    "gn:timezone":"Asia/Pyongyang",
    "iso:country":"KP",
    "name:eng_x_preferred":[
        "Tap"
    ],
    "name:eng_x_variant":[
        "Tap-tong"
    ],
    "name:und_x_variant":[
        "\ub2f5\ub3d9",
        "Tap-tong"
    ],
    "wof:name":"Tap",
    "wof:placetype":"locality"
},
  "geometry": {"coordinates":[125.855,38.80056],"type":"Point"}
}