{
  "type": "Feature",
  "properties": {
    "gn:admin1_code":"7.0",
    "gn:asciiname":"Ch'onam-ni",
    "gn:country_code":"KP",
    "gn:dem":110,
    "gn:feature_class":"P",
    "gn:feature_code":"PPL",
    "gn:name":"Ch\u2019\u014fnam-ni",
    "gn:population":0,
    "gn:timezone":"Asia/Pyongyang",
    "iso:country":"KP",
    "name:eng_x_preferred":[
        "Ch'onam"
    ],
    "name:eng_x_variant":[
        "Ch'onam-ni"
    ],
    "name:kor_x_preferred":[
        "\ucc9c\uc554\ub9ac"
    ],
    "name:kor_x_variant":[
        "Ch\u2019\u014fnam-ni"
    ],
    "wof:name":"Ch'onam",
    "wof:placetype":"locality"
},
  "geometry": {"coordinates":[126.43583,38.68167],"type":"Point"}
}