{
  "type": "Feature",
  "properties": {
    "gn:admin1_code":"7.0",
    "gn:asciiname":"Naengjong-ni",
    "gn:country_code":"KP",
    "gn:dem":99,
    "gn:feature_class":"P",
    "gn:feature_code":"PPL",
    "gn:name":"Naengj\u014fng-ni",
    "gn:population":0,
    "gn:timezone":"Asia/Pyongyang",
    "iso:country":"KP",
    "wof:name":"Naengjong-ni",
    "wof:placetype":"locality"
},
  "geometry": {"coordinates":[126.73694,38.33944],"type":"Point"}
}