{
  "type": "Feature",
  "properties": {
    "gn:admin1_code":"6.0",
    "gn:asciiname":"Sokkyo-ri",
    "gn:country_code":"KP",
    "gn:dem":19,
    "gn:feature_class":"P",
    "gn:feature_code":"PPL",
    "gn:name":"S\u014fkkyo-ri",
    "gn:population":0,
    "gn:timezone":"Asia/Pyongyang",
    "iso:country":"KP",
    "name:kor_x_preferred":[
        "S\u014fkkyo-ri"
    ],
    "name:kor_x_variant":[
        "\uc11d\uad50\ub9ac"
    ],
    "wof:name":"Sokkyo-ri",
    "wof:placetype":"locality"
},
  "geometry": {"coordinates":[124.95389,38.21167],"type":"Point"}
}