{
  "type": "Feature",
  "properties": {
    "gn:admin1_code":"1.0",
    "gn:asciiname":"Upsal-li",
    "gn:country_code":"KP",
    "gn:dem":1021,
    "gn:feature_class":"P",
    "gn:feature_code":"PPL",
    "gn:name":"\u016cpsal-li",
    "gn:population":0,
    "gn:timezone":"Asia/Pyongyang",
    "iso:country":"KP",
    "name:kor_x_preferred":[
        "\uc74d\uc0b0\ub9ac"
    ],
    "name:kor_x_variant":[
        "\u016cpsal-li"
    ],
    "wof:name":"Upsal-li",
    "wof:placetype":"locality"
},
  "geometry": {"coordinates":[127.14722,40.91611],"type":"Point"}
}