{
  "type": "Feature",
  "properties": {
    "gn:admin1_code":"6.0",
    "gn:asciiname":"Musal-li",
    "gn:country_code":"KP",
    "gn:dem":34,
    "gn:feature_class":"P",
    "gn:feature_code":"PPL",
    "gn:name":"Musal-li",
    "gn:population":0,
    "gn:timezone":"Asia/Pyongyang",
    "iso:country":"KP",
    "name:und_x_variant":[
        "\ubb34\uc0b0\ub9ac"
    ],
    "wof:name":"Musal-li",
    "wof:placetype":"locality"
},
  "geometry": {"coordinates":[125.29277999999999,38.14806],"type":"Point"}
}