{
  "type": "Feature",
  "properties": {
    "gn:admin1_code":"15.0",
    "gn:asciiname":"Hadok-kol",
    "gn:country_code":"KP",
    "gn:dem":384,
    "gn:feature_class":"P",
    "gn:feature_code":"PPL",
    "gn:name":"Hadok-kol",
    "gn:population":0,
    "gn:timezone":"Asia/Pyongyang",
    "iso:country":"KP",
    "name:und_x_variant":[
        "\ud558\ub3d7\uace8",
        "Hadot-kol",
        "Hadok-kol"
    ],
    "wof:name":"Hadok-kol",
    "wof:placetype":"locality"
},
  "geometry": {"coordinates":[126.8125,39.26361],"type":"Point"}
}