{
  "type": "Feature",
  "properties": {
    "gn:admin1_code":"17.0",
    "gn:asciiname":"P'an'gyoch'on",
    "gn:country_code":"KP",
    "gn:dem":133,
    "gn:feature_class":"P",
    "gn:feature_code":"PPL",
    "gn:name":"P\u2019an\u2019gyoch\u2019on",
    "gn:population":0,
    "gn:timezone":"Asia/Pyongyang",
    "iso:country":"KP",
    "name:und_x_variant":[
        "\ud310\uad50\ucd0c",
        "P\u2019an\u2019gyoch\u2019on"
    ],
    "wof:name":"P'an'gyoch'on",
    "wof:placetype":"locality"
},
  "geometry": {"coordinates":[130.05222000000001,42.90889],"type":"Point"}
}