{
  "type": "Feature",
  "properties": {
    "gn:admin1_code":"12.0",
    "gn:asciiname":"Sonnae-dong",
    "gn:country_code":"KP",
    "gn:dem":21,
    "gn:feature_class":"P",
    "gn:feature_code":"PPL",
    "gn:name":"S\u014fnnae-dong",
    "gn:population":0,
    "gn:timezone":"Asia/Pyongyang",
    "iso:country":"KP",
    "name:kor_x_preferred":[
        "\uc120\ub0b4\ub3d9"
    ],
    "name:und_x_variant":[
        "S\u014fnnae-dong",
        "Seonnaedong"
    ],
    "wof:name":"Sonnae-dong",
    "wof:placetype":"locality"
},
  "geometry": {"coordinates":[125.69435,39.02291],"type":"Point"}
}