{
  "type": "Feature",
  "properties": {
    "gn:admin1_code":"15.0",
    "gn:asciiname":"Chung-dong",
    "gn:country_code":"KP",
    "gn:dem":328,
    "gn:feature_class":"P",
    "gn:feature_code":"PPL",
    "gn:name":"Chung-dong",
    "gn:population":0,
    "gn:timezone":"Asia/Pyongyang",
    "iso:country":"KP",
    "name:kor_x_preferred":[
        "\uc911\ub3d9"
    ],
    "wof:name":"Chung-dong",
    "wof:placetype":"locality"
},
  "geometry": {"coordinates":[126.47806,39.50028],"type":"Point"}
}