{
  "type": "Feature",
  "properties": {
    "gn:admin1_code":"17.0",
    "gn:asciiname":"Yongyon-dong",
    "gn:country_code":"KP",
    "gn:dem":387,
    "gn:feature_class":"P",
    "gn:feature_code":"PPL",
    "gn:name":"Yongy\u014fn-dong",
    "gn:population":0,
    "gn:timezone":"Asia/Pyongyang",
    "iso:country":"KP",
    "name:und_x_variant":[
        "\uc6a9\uc5f0\ub3d9",
        "Yongy\u014fn-dong"
    ],
    "wof:name":"Yongyon-dong",
    "wof:placetype":"locality"
},
  "geometry": {"coordinates":[129.08082999999999,40.81389],"type":"Point"}
}