{
  "type": "Feature",
  "properties": {
    "gn:admin1_code":"13.0",
    "gn:asciiname":"Yongp'o-rodongjagu",
    "gn:country_code":"KP",
    "gn:dem":1184,
    "gn:feature_class":"P",
    "gn:feature_code":"PPL",
    "gn:name":"Yongp\u2019o-rodongjagu",
    "gn:population":0,
    "gn:timezone":"Asia/Pyongyang",
    "iso:country":"KP",
    "name:und_x_variant":[
        "Yongp\u2019o-ri",
        "Yongp\u2019o-rodongjagu"
    ],
    "wof:name":"Yongp'o-rodongjagu",
    "wof:placetype":"locality"
},
  "geometry": {"coordinates":[128.53806,41.24278],"type":"Point"}
}