{
  "type": "Feature",
  "properties": {
    "gn:admin1_code":"15.0",
    "gn:asciiname":"Ch'ang-ni",
    "gn:country_code":"KP",
    "gn:dem":549,
    "gn:feature_class":"P",
    "gn:feature_code":"PPL",
    "gn:name":"Ch\u2019ang-ni",
    "gn:population":0,
    "gn:timezone":"Asia/Pyongyang",
    "iso:country":"KP",
    "name:und_x_variant":[
        "\ucc3d\ub9ac",
        "Ch\u2019ang-ni"
    ],
    "wof:name":"Ch'ang-ni",
    "wof:placetype":"locality"
},
  "geometry": {"coordinates":[126.91611,40.03444],"type":"Point"}
}