{
  "type": "Feature",
  "properties": {
    "gn:admin1_code":"0.0",
    "gn:asciiname":"Sosong",
    "gn:country_code":"KP",
    "gn:dem":19,
    "gn:feature_class":"P",
    "gn:feature_code":"PPL",
    "gn:name":"S\u014fsong",
    "gn:population":0,
    "gn:timezone":"Asia/Pyongyang",
    "iso:country":"KP",
    "name:kor_x_preferred":[
        "\uc11c\uc1a1"
    ],
    "name:und_x_variant":[
        "S\u014fsong"
    ],
    "wof:name":"Sosong",
    "wof:placetype":"locality"
},
  "geometry": {"coordinates":[124.51667,39.88333],"type":"Point"}
}