{
  "type": "Feature",
  "properties": {
    "gn:admin1_code":"13.0",
    "gn:asciiname":"Yongch'ol-li",
    "gn:country_code":"KP",
    "gn:dem":1001,
    "gn:feature_class":"P",
    "gn:feature_code":"PPL",
    "gn:name":"Yongch\u2019\u014fl-li",
    "gn:population":0,
    "gn:timezone":"Asia/Pyongyang",
    "iso:country":"KP",
    "wof:name":"Yongch'ol-li",
    "wof:placetype":"locality"
},
  "geometry": {"coordinates":[128.45417,41.32111],"type":"Point"}
}