{
  "type": "Feature",
  "properties": {
    "gn:admin1_code":"1.0",
    "gn:asciiname":"So-gol",
    "gn:country_code":"KP",
    "gn:dem":500,
    "gn:feature_class":"P",
    "gn:feature_code":"PPL",
    "gn:name":"So-gol",
    "gn:population":0,
    "gn:timezone":"Asia/Pyongyang",
    "iso:country":"KP",
    "name:kor_x_preferred":[
        "\uc18c\uace8"
    ],
    "name:kor_x_variant":[
        "\uc18c\ub3d9"
    ],
    "name:und_x_variant":[
        "\uc18c\ub3d9",
        "So-dong",
        "So-gol",
        "\uc18c\uace8"
    ],
    "wof:name":"So-gol",
    "wof:placetype":"locality"
},
  "geometry": {"coordinates":[126.47750000000001,40.58333],"type":"Point"}
}