{
  "type": "Feature",
  "properties": {
    "gn:admin1_code":"17.0",
    "gn:asciiname":"Sech'on-dong",
    "gn:country_code":"KP",
    "gn:dem":480,
    "gn:feature_class":"P",
    "gn:feature_code":"PPLL",
    "gn:name":"Sech\u2019\u014fn-dong",
    "gn:population":0,
    "gn:timezone":"Asia/Pyongyang",
    "iso:country":"KP",
    "name:und_x_variant":[
        "Sech\u2019\u014fn-nodongjagu",
        "\uc138\ucc9c\ub3d9",
        "Sech\u2019\u014fl-lodongjagu",
        "Sech\u2019\u014fn-dong"
    ],
    "wof:name":"Sech'on-dong",
    "wof:placetype":"locality"
},
  "geometry": {"coordinates":[129.84333000000001,42.595],"type":"Point"}
}