{
  "type": "Feature",
  "properties": {
    "gn:admin1_code":"12.0",
    "gn:asciiname":"Chong-dong",
    "gn:country_code":"KP",
    "gn:dem":55,
    "gn:feature_class":"P",
    "gn:feature_code":"PPL",
    "gn:name":"Ch\u014fng-dong",
    "gn:population":0,
    "gn:timezone":"Asia/Pyongyang",
    "iso:country":"KP",
    "name:kor_x_preferred":[
        "\uc815\ub3d9"
    ],
    "name:und_x_variant":[
        "Ch\u014fng-dong",
        "Jeongdong"
    ],
    "wof:name":"Chong-dong",
    "wof:placetype":"locality"
},
  "geometry": {"coordinates":[125.93617,39.10406],"type":"Point"}
}