{
  "type": "Feature",
  "properties": {
    "gn:admin1_code":"12.0",
    "gn:asciiname":"Taech'ang-gol",
    "gn:country_code":"KP",
    "gn:dem":56,
    "gn:feature_class":"P",
    "gn:feature_code":"PPL",
    "gn:name":"Taech\u2019ang-gol",
    "gn:population":0,
    "gn:timezone":"Asia/Pyongyang",
    "iso:country":"KP",
    "name:und_x_variant":[
        "Taech\u2019ang-dong",
        "\ub300\ucc3d\uace8",
        "Taech\u2019ang-gol"
    ],
    "wof:name":"Taech'ang-gol",
    "wof:placetype":"locality"
},
  "geometry": {"coordinates":[125.86111,38.86028],"type":"Point"}
}