{
  "type": "Feature",
  "properties": {
    "gn:admin1_code":"3.0",
    "gn:asciiname":"Undae-dong",
    "gn:country_code":"KP",
    "gn:dem":37,
    "gn:feature_class":"P",
    "gn:feature_code":"PPL",
    "gn:name":"Undae-dong",
    "gn:population":0,
    "gn:timezone":"Asia/Pyongyang",
    "iso:country":"KP",
    "name:und_x_variant":[
        "\uc6b4\ub300\ub3d9",
        "Undae-dong"
    ],
    "wof:name":"Undae-dong",
    "wof:placetype":"locality"
},
  "geometry": {"coordinates":[127.42028000000001,39.9625],"type":"Point"}
}