{
  "type": "Feature",
  "properties": {
    "gn:admin1_code":"11.0",
    "gn:asciiname":"Soam-dong",
    "gn:country_code":"KP",
    "gn:dem":30,
    "gn:feature_class":"P",
    "gn:feature_code":"PPL",
    "gn:name":"Soam-dong",
    "gn:population":0,
    "gn:timezone":"Asia/Pyongyang",
    "iso:country":"KP",
    "name:kor_x_preferred":[
        "\uc18c\uc554\ub3d9"
    ],
    "wof:name":"Soam-dong",
    "wof:placetype":"locality"
},
  "geometry": {"coordinates":[125.22889000000001,39.73889000000001],"type":"Point"}
}