{
  "type": "Feature",
  "properties": {
    "gn:admin1_code":"6.0",
    "gn:asciiname":"Ami-ri",
    "gn:country_code":"KP",
    "gn:dem":9,
    "gn:feature_class":"P",
    "gn:feature_code":"PPL",
    "gn:name":"Ami-ri",
    "gn:population":0,
    "gn:timezone":"Asia/Pyongyang",
    "iso:country":"KP",
    "name:und_x_variant":[
        "\uc544\ubbf8\ub9ac",
        "Ami-ri"
    ],
    "wof:name":"Ami-ri",
    "wof:placetype":"locality"
},
  "geometry": {"coordinates":[125.48027999999999,37.78028],"type":"Point"}
}