{
  "type": "Feature",
  "properties": {
    "gn:admin1_code":"9.0",
    "gn:asciiname":"Imnam-ni",
    "gn:country_code":"KP",
    "gn:dem":362,
    "gn:feature_class":"P",
    "gn:feature_code":"PPL",
    "gn:name":"Imnam-ni",
    "gn:population":0,
    "gn:timezone":"Asia/Pyongyang",
    "iso:country":"KP",
    "name:und_x_variant":[
        "\uc784\ub0a8\ub9ac",
        "Imnam-ni"
    ],
    "wof:name":"Imnam-ni",
    "wof:placetype":"locality"
},
  "geometry": {"coordinates":[127.78749999999999,38.44861],"type":"Point"}
}