{
  "type": "Feature",
  "properties": {
    "gn:admin1_code":"6.0",
    "gn:asciiname":"Namgye",
    "gn:country_code":"KP",
    "gn:dem":104,
    "gn:feature_class":"P",
    "gn:feature_code":"PPL",
    "gn:name":"Namgye",
    "gn:population":0,
    "gn:timezone":"Asia/Pyongyang",
    "iso:country":"KP",
    "wof:name":"Namgye",
    "wof:placetype":"locality"
},
  "geometry": {"coordinates":[125.60917000000001,38.23917],"type":"Point"}
}