{
  "type": "Feature",
  "properties": {
    "gn:admin1_code":"3.0",
    "gn:asciiname":"Hodo-ri",
    "gn:country_code":"KP",
    "gn:dem":21,
    "gn:feature_class":"P",
    "gn:feature_code":"PPL",
    "gn:name":"Hodo-ri",
    "gn:population":0,
    "gn:timezone":"Asia/Pyongyang",
    "iso:country":"KP",
    "name:kor_x_preferred":[
        "\ud638\ub3c4\ub9ac"
    ],
    "wof:name":"Hodo-ri",
    "wof:placetype":"locality"
},
  "geometry": {"coordinates":[127.53361,39.34583],"type":"Point"}
}