{
  "type": "Feature",
  "properties": {
    "gn:admin1_code":"15.0",
    "gn:asciiname":"Ch'ongp'ung-ni",
    "gn:country_code":"KP",
    "gn:dem":11,
    "gn:feature_class":"P",
    "gn:feature_code":"PPL",
    "gn:name":"Ch\u2019\u014fngp\u2019ung-ni",
    "gn:population":0,
    "gn:timezone":"Asia/Pyongyang",
    "iso:country":"KP",
    "name:eng_x_preferred":[
        "Ch'ongp'ung"
    ],
    "name:eng_x_variant":[
        "Ch'ongp'ung-ni"
    ],
    "name:kor_x_preferred":[
        "\uccad\ud48d\ub9ac"
    ],
    "name:kor_x_variant":[
        "Ch\u2019\u014fngp\u2019ung-ni"
    ],
    "wof:name":"Ch'ongp'ung",
    "wof:placetype":"locality"
},
  "geometry": {"coordinates":[125.39167,39.46556],"type":"Point"}
}