{
  "type": "Feature",
  "properties": {
    "gn:admin1_code":"7.0",
    "gn:asciiname":"Yulsa-dong",
    "gn:country_code":"KP",
    "gn:dem":142,
    "gn:feature_class":"P",
    "gn:feature_code":"PPL",
    "gn:name":"Yulsa-dong",
    "gn:population":0,
    "gn:timezone":"Asia/Pyongyang",
    "iso:country":"KP",
    "wof:name":"Yulsa-dong",
    "wof:placetype":"locality"
},
  "geometry": {"coordinates":[126.11360999999999,38.41222],"type":"Point"}
}