{
  "type": "Feature",
  "properties": {
    "gn:admin1_code":"3.0",
    "gn:asciiname":"Yonji",
    "gn:country_code":"KP",
    "gn:dem":11,
    "gn:feature_class":"P",
    "gn:feature_code":"PPL",
    "gn:name":"Y\u014fnji",
    "gn:population":0,
    "gn:timezone":"Asia/Pyongyang",
    "iso:country":"KP",
    "name:und_x_variant":[
        "\uc5f0\uc9c0",
        "Y\u014fnji"
    ],
    "wof:name":"Yonji",
    "wof:placetype":"locality"
},
  "geometry": {"coordinates":[128.69888999999998,40.34083],"type":"Point"}
}