{
  "type": "Feature",
  "properties": {
    "gn:admin1_code":"6.0",
    "gn:asciiname":"Chu-dong",
    "gn:country_code":"KP",
    "gn:dem":54,
    "gn:feature_class":"P",
    "gn:feature_code":"PPL",
    "gn:name":"Chu-dong",
    "gn:population":0,
    "gn:timezone":"Asia/Pyongyang",
    "iso:country":"KP",
    "name:kor_x_preferred":[
        "\uc8fc\ub3d9"
    ],
    "wof:name":"Chu-dong",
    "wof:placetype":"locality"
},
  "geometry": {"coordinates":[125.43138999999999,38.13028],"type":"Point"}
}