{
  "type": "Feature",
  "properties": {
    "gn:admin1_code":"18.0",
    "gn:asciiname":"Ukkol",
    "gn:country_code":"KP",
    "gn:dem":32,
    "gn:feature_class":"P",
    "gn:feature_code":"PPL",
    "gn:name":"Ukkol",
    "gn:population":0,
    "gn:timezone":"Asia/Pyongyang",
    "iso:country":"KP",
    "name:und_x_variant":[
        "\uc6c3\uace8",
        "Ukkol",
        "Utgol"
    ],
    "wof:name":"Ukkol",
    "wof:placetype":"locality"
},
  "geometry": {"coordinates":[130.50221999999999,42.55694],"type":"Point"}
}