{
  "type": "Feature",
  "properties": {
    "gn:admin1_code":"6.0",
    "gn:admin2_code":"Paech\u2019\u014fn-gun",
    "gn:asciiname":"Paech'ononch'on",
    "gn:country_code":"KP",
    "gn:dem":8,
    "gn:feature_class":"P",
    "gn:feature_code":"PPL",
    "gn:name":"Paech\u2019\u014fnonch\u2019\u014fn",
    "gn:population":0,
    "gn:timezone":"Asia/Pyongyang",
    "iso:country":"KP",
    "wof:name":"Paech'ononch'on",
    "wof:placetype":"locality"
},
  "geometry": {"coordinates":[126.29889,37.98222],"type":"Point"}
}