{
  "type": "Feature",
  "properties": {
    "gn:admin1_code":"9.0",
    "gn:asciiname":"Chungnim-ni",
    "gn:cc2":"KP",
    "gn:country_code":"KP",
    "gn:dem":333,
    "gn:feature_class":"P",
    "gn:feature_code":"PPL",
    "gn:name":"Chungnim-ni",
    "gn:population":0,
    "gn:timezone":"Asia/Pyongyang",
    "iso:country":"KP",
    "name:kor_x_preferred":[
        "\uc911\ub9bc\ub9ac"
    ],
    "name:und_x_variant":[
        "Chuksan-ni",
        "Chungnim-ni"
    ],
    "wof:name":"Chungnim-ni",
    "wof:placetype":"locality"
},
  "geometry": {"coordinates":[127.25388999999998,38.54472],"type":"Point"}
}