{
  "type": "Feature",
  "properties": {
    "gn:admin1_code":"9.0",
    "gn:asciiname":"Origol",
    "gn:country_code":"KP",
    "gn:dem":147,
    "gn:feature_class":"P",
    "gn:feature_code":"PPL",
    "gn:name":"Origol",
    "gn:population":0,
    "gn:timezone":"Asia/Pyongyang",
    "iso:country":"KP",
    "name:kor_x_preferred":[
        "\uc624\ub9ac\uace8"
    ],
    "name:und_x_variant":[
        "Orikol"
    ],
    "wof:name":"Origol",
    "wof:placetype":"locality"
},
  "geometry": {"coordinates":[127.07889,38.30361],"type":"Point"}
}