{
  "type": "Feature",
  "properties": {
    "gn:admin1_code":"15.0",
    "gn:asciiname":"T'ap-tong",
    "gn:country_code":"KP",
    "gn:dem":305,
    "gn:feature_class":"P",
    "gn:feature_code":"PPL",
    "gn:name":"T\u2019ap-tong",
    "gn:population":0,
    "gn:timezone":"Asia/Pyongyang",
    "iso:country":"KP",
    "name:eng_x_preferred":[
        "T'ap"
    ],
    "name:eng_x_variant":[
        "T'ap-tong"
    ],
    "name:kor_x_preferred":[
        "\ud0d1\ub3d9"
    ],
    "name:und_x_variant":[
        "T\u2019ap-tong"
    ],
    "wof:name":"T'ap",
    "wof:placetype":"locality"
},
  "geometry": {"coordinates":[126.62778,39.40722],"type":"Point"}
}