{
  "type": "Feature",
  "properties": {
    "gn:admin1_code":"7.0",
    "gn:asciiname":"Ssungmul",
    "gn:country_code":"KP",
    "gn:dem":28,
    "gn:feature_class":"P",
    "gn:feature_code":"PPL",
    "gn:name":"Ssungmul",
    "gn:population":0,
    "gn:timezone":"Asia/Pyongyang",
    "iso:country":"KP",
    "name:und_x_variant":[
        "\uc479\ubb3c",
        "Ssungmul"
    ],
    "wof:name":"Ssungmul",
    "wof:placetype":"locality"
},
  "geometry": {"coordinates":[125.83806,38.76778],"type":"Point"}
}