{
  "type": "Feature",
  "properties": {
    "gn:admin1_code":"15.0",
    "gn:admin2_code":"sukch\u2019\u014fn-gun",
    "gn:asciiname":"Haebin-ni",
    "gn:country_code":"KP",
    "gn:dem":13,
    "gn:feature_class":"P",
    "gn:feature_code":"PPL",
    "gn:name":"Haebin-ni",
    "gn:population":0,
    "gn:timezone":"Asia/Pyongyang",
    "iso:country":"KP",
    "wof:name":"Haebin-ni",
    "wof:placetype":"locality"
},
  "geometry": {"coordinates":[125.48556000000001,39.37389],"type":"Point"}
}