{
  "type": "Feature",
  "properties": {
    "gn:admin1_code":"3.0",
    "gn:asciiname":"Chagun-dong",
    "gn:country_code":"KP",
    "gn:dem":177,
    "gn:feature_class":"P",
    "gn:feature_code":"PPL",
    "gn:name":"Chag\u016dn-dong",
    "gn:population":0,
    "gn:timezone":"Asia/Pyongyang",
    "iso:country":"KP",
    "name:und_x_variant":[
        "Chag\u016dn-dong",
        "\uc791\uc740\ub3d9"
    ],
    "wof:name":"Chagun-dong",
    "wof:placetype":"locality"
},
  "geometry": {"coordinates":[128.19593999999998,40.21247],"type":"Point"}
}