{
  "type": "Feature",
  "properties": {
    "gn:admin1_code":"7.0",
    "gn:asciiname":"Kamdang-ni",
    "gn:country_code":"KP",
    "gn:dem":117,
    "gn:feature_class":"P",
    "gn:feature_code":"PPL",
    "gn:name":"Kamdang-ni",
    "gn:population":0,
    "gn:timezone":"Asia/Pyongyang",
    "iso:country":"KP",
    "wof:name":"Kamdang-ni",
    "wof:placetype":"locality"
},
  "geometry": {"coordinates":[126.06806,38.35],"type":"Point"}
}