{
  "type": "Feature",
  "properties": {
    "gn:admin1_code":"15.0",
    "gn:asciiname":"Inhung-ni",
    "gn:country_code":"KP",
    "gn:dem":8,
    "gn:feature_class":"P",
    "gn:feature_code":"PPL",
    "gn:name":"Inh\u016dng-ni",
    "gn:population":0,
    "gn:timezone":"Asia/Pyongyang",
    "iso:country":"KP",
    "name:kor_x_preferred":[
        "\uc778\ud765\ub9ac"
    ],
    "name:kor_x_variant":[
        "Inh\u016dng-ni"
    ],
    "wof:name":"Inhung-ni",
    "wof:placetype":"locality"
},
  "geometry": {"coordinates":[125.46278,39.52194],"type":"Point"}
}