{
  "type": "Feature",
  "properties": {
    "gn:admin1_code":"6.0",
    "gn:asciiname":"Kumch'ol-li",
    "gn:country_code":"KP",
    "gn:dem":21,
    "gn:feature_class":"P",
    "gn:feature_code":"PPL",
    "gn:name":"K\u016dmch\u2019\u014fl-li",
    "gn:population":0,
    "gn:timezone":"Asia/Pyongyang",
    "iso:country":"KP",
    "name:kor_x_preferred":[
        "\uae08\ucc9c\ub9ac"
    ],
    "name:und_x_variant":[
        "K\u016dmch\u2019\u014fn-ni",
        "K\u016dmch\u2019\u014fl-li"
    ],
    "wof:name":"Kumch'ol-li",
    "wof:placetype":"locality"
},
  "geometry": {"coordinates":[126.05694,37.94167],"type":"Point"}
}