{
  "type": "Feature",
  "properties": {
    "gn:admin1_code":"6.0",
    "gn:asciiname":"Saeganjinae",
    "gn:country_code":"KP",
    "gn:dem":34,
    "gn:feature_class":"P",
    "gn:feature_code":"PPL",
    "gn:name":"Saeganjinae",
    "gn:population":0,
    "gn:timezone":"Asia/Pyongyang",
    "iso:country":"KP",
    "name:kor_x_preferred":[
        "\uc0c8\uac04\uc9c0\ub0b4"
    ],
    "wof:name":"Saeganjinae",
    "wof:placetype":"locality"
},
  "geometry": {"coordinates":[125.39361,38.38778],"type":"Point"}
}