{
  "type": "Feature",
  "properties": {
    "gn:admin1_code":"17.0",
    "gn:asciiname":"Kaewol-li",
    "gn:country_code":"KP",
    "gn:dem":363,
    "gn:feature_class":"P",
    "gn:feature_code":"PPL",
    "gn:name":"Kaew\u014fl-li",
    "gn:population":0,
    "gn:timezone":"Asia/Pyongyang",
    "iso:country":"KP",
    "name:und_x_variant":[
        "\uac1c\uc6d0\ub9ac",
        "Kaew\u014fn-ni",
        "Kaew\u014fl-li"
    ],
    "wof:name":"Kaewol-li",
    "wof:placetype":"locality"
},
  "geometry": {"coordinates":[129.83082999999999,42.57722],"type":"Point"}
}