{
  "type": "Feature",
  "properties": {
    "gn:admin1_code":"0.0",
    "gn:asciiname":"Namhyon",
    "gn:country_code":"KP",
    "gn:dem":21,
    "gn:feature_class":"P",
    "gn:feature_code":"PPL",
    "gn:name":"Namhy\u014fn",
    "gn:population":0,
    "gn:timezone":"Asia/Pyongyang",
    "iso:country":"KP",
    "name:kor_x_preferred":[
        "\ub0a8\ud604"
    ],
    "name:und_x_variant":[
        "Namhy\u014fn"
    ],
    "wof:name":"Namhyon",
    "wof:placetype":"locality"
},
  "geometry": {"coordinates":[124.54395,39.85777],"type":"Point"}
}