{
  "type": "Feature",
  "properties": {
    "gn:admin1_code":"11.0",
    "gn:asciiname":"Chik-tong",
    "gn:country_code":"KP",
    "gn:dem":348,
    "gn:feature_class":"P",
    "gn:feature_code":"PPL",
    "gn:name":"Chik-tong",
    "gn:population":0,
    "gn:timezone":"Asia/Pyongyang",
    "iso:country":"KP",
    "name:und_x_variant":[
        "\uc9c1\ub3d9",
        "Chik-tong"
    ],
    "wof:name":"Chik-tong",
    "wof:placetype":"locality"
},
  "geometry": {"coordinates":[125.62333,40.17],"type":"Point"}
}