{
  "type": "Feature",
  "properties": {
    "gn:admin1_code":"7.0",
    "gn:asciiname":"Yangsa-ri",
    "gn:country_code":"KP",
    "gn:dem":127,
    "gn:feature_class":"P",
    "gn:feature_code":"PPL",
    "gn:name":"Yangsa-ri",
    "gn:population":0,
    "gn:timezone":"Asia/Pyongyang",
    "iso:country":"KP",
    "name:und_x_variant":[
        "\ub7c9\uc0ac\ub9ac",
        "Yangsa-ri"
    ],
    "wof:name":"Yangsa-ri",
    "wof:placetype":"locality"
},
  "geometry": {"coordinates":[126.28028,38.43667],"type":"Point"}
}