{
  "type": "Feature",
  "properties": {
    "gn:admin1_code":"12.0",
    "gn:asciiname":"Mujinjang-maul",
    "gn:country_code":"KP",
    "gn:dem":61,
    "gn:feature_class":"P",
    "gn:feature_code":"PPL",
    "gn:name":"Mujinjang-ma\u016dl",
    "gn:population":0,
    "gn:timezone":"Asia/Pyongyang",
    "iso:country":"KP",
    "name:kor_x_preferred":[
        "Mujinjang-ma\u016dl"
    ],
    "name:kor_x_variant":[
        "\ubb34\uc9c4\uc7a5\ub9c8\uc744",
        "\ubb34\uc9c4\uc7a5\ub9ac",
        "\ubb34\uc9c4\uc7a5"
    ],
    "name:und_x_variant":[
        "Boshinj\u014d",
        "Mujinjang",
        "Boshindo",
        "Mujin-ni",
        "Mujinjang-ni",
        "Mujinjangmaeul"
    ],
    "wof:name":"Mujinjang-maul",
    "wof:placetype":"locality"
},
  "geometry": {"coordinates":[125.90278000000001,38.89944000000001],"type":"Point"}
}