{
  "type": "Feature",
  "properties": {
    "gn:admin1_code":"9.0",
    "gn:asciiname":"Ch'uam-ni",
    "gn:country_code":"KP",
    "gn:dem":306,
    "gn:feature_class":"P",
    "gn:feature_code":"PPL",
    "gn:name":"Ch\u2019uam-ni",
    "gn:population":0,
    "gn:timezone":"Asia/Pyongyang",
    "iso:country":"KP",
    "name:eng_x_preferred":[
        "Ch'uam"
    ],
    "name:eng_x_variant":[
        "Ch'uam-ni"
    ],
    "name:und_x_variant":[
        "Ch\u2019wiam-ni",
        "\ucd94\uc554\ub9ac",
        "Ch\u2019uam-ni"
    ],
    "wof:name":"Ch'uam",
    "wof:placetype":"locality"
},
  "geometry": {"coordinates":[127.07666999999999,38.95167],"type":"Point"}
}