{
  "type": "Feature",
  "properties": {
    "gn:admin1_code":"1.0",
    "gn:asciiname":"Huich'on",
    "gn:country_code":"KP",
    "gn:dem":139,
    "gn:feature_class":"P",
    "gn:feature_code":"PPL",
    "gn:name":"H\u016dich\u2019\u014fn",
    "gn:population":0,
    "gn:timezone":"Asia/Pyongyang",
    "iso:country":"KP",
    "name:bul_x_preferred":[
        "\u0425\u044a\u0439\u0447\u0445\u044a\u043d"
    ],
    "name:ces_x_preferred":[
        "Hui\u010dchon"
    ],
    "name:deu_x_preferred":[
        "H\u016dich\u2019\u014fn"
    ],
    "name:fas_x_preferred":[
        "\u0647\u0648\u0627\u06cc\u0686\u0648\u0646"
    ],
    "name:fin_x_preferred":[
        "Huicheon"
    ],
    "name:fra_x_preferred":[
        "Huichon"
    ],
    "name:hun_x_preferred":[
        "Hicshon"
    ],
    "name:ita_x_preferred":[
        "H\u016dich'\u014fn"
    ],
    "name:jpn_x_preferred":[
        "\u7199\u5ddd\u5e02"
    ],
    "name:kor_x_preferred":[
        "\ud76c\ucc9c"
    ],
    "name:kor_x_variant":[
        "\ud76c\ucc9c\uc2dc"
    ],
    "name:nld_x_preferred":[
        "Huichon"
    ],
    "name:nor_x_preferred":[
        "Huichon"
    ],
    "name:pol_x_preferred":[
        "H\u016dich'\u014fn"
    ],
    "name:rus_x_preferred":[
        "\u0425\u0438\u0447\u0445\u043e\u043d"
    ],
    "name:swe_x_preferred":[
        "Huichon"
    ],
    "name:tur_x_preferred":[
        "Huich'on"
    ],
    "name:und_x_variant":[
        "Kisen",
        "Hich\u014fn",
        "H\u016dich\u2019\u014fn-\u016dp",
        "Hwi-tsch-h\u00f6n"
    ],
    "name:urd_x_preferred":[
        "\u06c1\u0648\u06cc\u0686\u0648\u0646"
    ],
    "name:vie_x_preferred":[
        "Huichon"
    ],
    "name:zho_x_preferred":[
        "\u7199\u5ddd\u5e02"
    ],
    "wof:name":"Huich'on",
    "wof:placetype":"locality"
},
  "geometry": {"coordinates":[126.27472,40.17139],"type":"Point"}
}