{
  "type": "Feature",
  "properties": {
    "gn:admin1_code":"1.0",
    "gn:asciiname":"Huich'on",
    "gn:country_code":"KP",
    "gn:dem":139,
    "gn:feature_class":"P",
    "gn:feature_code":"PPL",
    "gn:name":"H\u016dich\u2019\u014fn",
    "gn:population":0,
    "gn:timezone":"Asia/Pyongyang",
    "iso:country":"KP",
    "name:kor_x_preferred":[
        "\ud76c\ucc9c"
    ],
    "name:und_x_variant":[
        "Kisen",
        "Hich\u014fn",
        "H\u016dich\u2019\u014fn-\u016dp",
        "Hwi-tsch-h\u00f6n",
        "H\u016dich\u2019\u014fn"
    ],
    "wof:name":"Huich'on",
    "wof:placetype":"locality"
},
  "geometry": {"coordinates":[126.27472,40.17139],"type":"Point"}
}