{
  "type": "Feature",
  "properties": {
    "gn:admin1_code":"3.0",
    "gn:asciiname":"Chaehang-ch'on",
    "gn:country_code":"KP",
    "gn:dem":18,
    "gn:feature_class":"P",
    "gn:feature_code":"PPL",
    "gn:name":"Chaehang-ch\u2019on",
    "gn:population":0,
    "gn:timezone":"Asia/Pyongyang",
    "iso:country":"KP",
    "name:und_x_variant":[
        "Chaehang-ch\u2019on",
        "\uc7ac\ud56d\ucd0c"
    ],
    "wof:name":"Chaehang-ch'on",
    "wof:placetype":"locality"
},
  "geometry": {"coordinates":[128.61694,40.22278],"type":"Point"}
}