{
  "type": "Feature",
  "properties": {
    "gn:admin1_code":"15.0",
    "gn:asciiname":"Munsam-ni",
    "gn:country_code":"KP",
    "gn:dem":98,
    "gn:feature_class":"P",
    "gn:feature_code":"PPL",
    "gn:name":"Munsam-ni",
    "gn:population":0,
    "gn:timezone":"Asia/Pyongyang",
    "iso:country":"KP",
    "name:eng_x_preferred":[
        "Munsam"
    ],
    "name:eng_x_variant":[
        "Munsam-ni"
    ],
    "name:und_x_variant":[
        "Munam-ni",
        "Munsam-ni"
    ],
    "wof:name":"Munsam",
    "wof:placetype":"locality"
},
  "geometry": {"coordinates":[125.72417,39.2925],"type":"Point"}
}