{
  "type": "Feature",
  "properties": {
    "gn:admin1_code":"3.0",
    "gn:admin2_code":"K\u016dmya-gun",
    "gn:asciiname":"Chungang-ni",
    "gn:cc2":"KP",
    "gn:country_code":"KP",
    "gn:dem":13,
    "gn:feature_class":"P",
    "gn:feature_code":"PPL",
    "gn:name":"Chungang-ni",
    "gn:population":0,
    "gn:timezone":"Asia/Pyongyang",
    "iso:country":"KP",
    "name:und_x_variant":[
        "Chungyang-ni",
        "\uc911\uc559\ub9ac",
        "Chungang-ni"
    ],
    "wof:name":"Chungang-ni",
    "wof:placetype":"locality"
},
  "geometry": {"coordinates":[127.295,39.50056],"type":"Point"}
}