{
  "type": "Feature",
  "properties": {
    "gn:admin1_code":"6.0",
    "gn:asciiname":"Ch'am-ch'on",
    "gn:country_code":"KP",
    "gn:dem":31,
    "gn:feature_class":"P",
    "gn:feature_code":"PPL",
    "gn:name":"Ch\u2019am-ch\u2019on",
    "gn:population":0,
    "gn:timezone":"Asia/Pyongyang",
    "iso:country":"KP",
    "name:kor_x_preferred":[
        "\ucc38\ucd0c"
    ],
    "name:und_x_variant":[
        "Ch\u2019am-ch\u2019on"
    ],
    "wof:name":"Ch'am-ch'on",
    "wof:placetype":"locality"
},
  "geometry": {"coordinates":[124.92055999999999,38.26889],"type":"Point"}
}