{
  "type": "Feature",
  "properties": {
    "gn:admin1_code":"17.0",
    "gn:asciiname":"Puam-dong",
    "gn:country_code":"KP",
    "gn:dem":139,
    "gn:feature_class":"P",
    "gn:feature_code":"PPL",
    "gn:name":"Puam-dong",
    "gn:population":0,
    "gn:timezone":"Asia/Pyongyang",
    "iso:country":"KP",
    "name:und_x_variant":[
        "\ubd80\uc554\ub3d9",
        "Puam-dong"
    ],
    "wof:name":"Puam-dong",
    "wof:placetype":"locality"
},
  "geometry": {"coordinates":[129.49528000000001,41.19861],"type":"Point"}
}