{
  "type": "Feature",
  "properties": {
    "gn:admin1_code":"11.0",
    "gn:asciiname":"Choch'on",
    "gn:country_code":"KP",
    "gn:dem":93,
    "gn:feature_class":"P",
    "gn:feature_code":"PPL",
    "gn:name":"Choch\u2019on",
    "gn:population":0,
    "gn:timezone":"Asia/Pyongyang",
    "iso:country":"KP",
    "wof:name":"Choch'on",
    "wof:placetype":"locality"
},
  "geometry": {"coordinates":[125.87083,39.89722],"type":"Point"}
}