{
  "type": "Feature",
  "properties": {
    "gn:admin1_code":"17.0",
    "gn:asciiname":"Chaedogi",
    "gn:country_code":"KP",
    "gn:dem":322,
    "gn:feature_class":"P",
    "gn:feature_code":"PPL",
    "gn:name":"Chaed\u014fgi",
    "gn:population":0,
    "gn:timezone":"Asia/Pyongyang",
    "iso:country":"KP",
    "name:und_x_variant":[
        "\uc7ac\ub355\uc774",
        "Chaed\u014fgi"
    ],
    "wof:name":"Chaedogi",
    "wof:placetype":"locality"
},
  "geometry": {"coordinates":[129.41833,41.15056],"type":"Point"}
}