{
  "type": "Feature",
  "properties": {
    "gn:admin1_code":"9.0",
    "gn:asciiname":"Ch'ubang-ni",
    "gn:country_code":"KP",
    "gn:dem":399,
    "gn:feature_class":"P",
    "gn:feature_code":"PPL",
    "gn:name":"Ch\u2019ubang-ni",
    "gn:population":0,
    "gn:timezone":"Asia/Pyongyang",
    "iso:country":"KP",
    "name:und_x_variant":[
        "\ucd94\ubc29\ub9ac",
        "Ch\u2019ubang-ni"
    ],
    "wof:name":"Ch'ubang-ni",
    "wof:placetype":"locality"
},
  "geometry": {"coordinates":[127.71693999999999,38.6575],"type":"Point"}
}