{
  "type": "Feature",
  "properties": {
    "gn:admin1_code":"6.0",
    "gn:asciiname":"Anhyol-li",
    "gn:cc2":"KP",
    "gn:country_code":"KP",
    "gn:dem":89,
    "gn:feature_class":"P",
    "gn:feature_code":"PPL",
    "gn:name":"Anhy\u014fl-li",
    "gn:population":0,
    "gn:timezone":"Asia/Pyongyang",
    "iso:country":"KP",
    "name:kor_x_preferred":[
        "\uc548\ud604\ub9ac"
    ],
    "name:und_x_variant":[
        "Anhy\u014fn-ni",
        "Anhy\u014fl-li"
    ],
    "wof:name":"Anhyol-li",
    "wof:placetype":"locality"
},
  "geometry": {"coordinates":[125.43694000000001,38.00806],"type":"Point"}
}