{
  "type": "Feature",
  "properties": {
    "gn:admin1_code":"6.0",
    "gn:asciiname":"Namnon-dong",
    "gn:country_code":"KP",
    "gn:dem":10,
    "gn:feature_class":"P",
    "gn:feature_code":"PPL",
    "gn:name":"Namnon-dong",
    "gn:population":0,
    "gn:timezone":"Asia/Pyongyang",
    "iso:country":"KP",
    "name:und_x_variant":[
        "Namdap-tong",
        "\ub0a8\ub17c\ub3d9",
        "Namnon-dong"
    ],
    "wof:name":"Namnon-dong",
    "wof:placetype":"locality"
},
  "geometry": {"coordinates":[125.36861,37.91806],"type":"Point"}
}