{
  "type": "Feature",
  "properties": {
    "gn:admin1_code":"15.0",
    "gn:admin2_code":"T\u014fkch\u2019\u014fn-gun",
    "gn:asciiname":"Nojang-dong",
    "gn:country_code":"KP",
    "gn:dem":244,
    "gn:feature_class":"P",
    "gn:feature_code":"PPL",
    "gn:name":"Nojang-dong",
    "gn:population":0,
    "gn:timezone":"Asia/Pyongyang",
    "iso:country":"KP",
    "name:und_x_variant":[
        "Najang-dong",
        "Nojang-dong"
    ],
    "wof:name":"Nojang-dong",
    "wof:placetype":"locality"
},
  "geometry": {"coordinates":[126.32528000000001,39.87389],"type":"Point"}
}