{
  "type": "Feature",
  "properties": {
    "gn:admin1_code":"7.0",
    "gn:asciiname":"Yont'an",
    "gn:country_code":"KP",
    "gn:dem":111,
    "gn:feature_class":"P",
    "gn:feature_code":"PPL",
    "gn:name":"Y\u014fnt\u2019an",
    "gn:population":0,
    "gn:timezone":"Asia/Pyongyang",
    "iso:country":"KP",
    "name:kor_x_preferred":[
        "\uc5f0\ud0c4"
    ],
    "name:und_x_variant":[
        "Chelblyoul",
        "Cheblyo\u016dl",
        "Chebiy\u014ful",
        "Y\u014fnt\u2019an"
    ],
    "wof:name":"Yont'an",
    "wof:placetype":"locality"
},
  "geometry": {"coordinates":[126.09860999999999,38.62194],"type":"Point"}
}