{
  "type": "Feature",
  "properties": {
    "gn:admin1_code":"15.0",
    "gn:asciiname":"Sokchong-ni",
    "gn:country_code":"KP",
    "gn:dem":62,
    "gn:feature_class":"P",
    "gn:feature_code":"PPL",
    "gn:name":"S\u014fkch\u014fng-ni",
    "gn:population":0,
    "gn:timezone":"Asia/Pyongyang",
    "iso:country":"KP",
    "name:eng_x_preferred":[
        "Sokchong"
    ],
    "name:eng_x_variant":[
        "Sokchong-ni"
    ],
    "wof:name":"Sokchong",
    "wof:placetype":"locality"
},
  "geometry": {"coordinates":[125.96832999999999,39.28583],"type":"Point"}
}