{
  "type": "Feature",
  "properties": {
    "gn:admin1_code":"3.0",
    "gn:asciiname":"Kuch'ang-ni",
    "gn:country_code":"KP",
    "gn:dem":281,
    "gn:feature_class":"P",
    "gn:feature_code":"PPL",
    "gn:name":"Kuch\u2019ang-ni",
    "gn:population":0,
    "gn:timezone":"Asia/Pyongyang",
    "iso:country":"KP",
    "name:und_x_variant":[
        "\uad6c\ucc3d\ub9ac",
        "Kuch\u2019ang-ni"
    ],
    "wof:name":"Kuch'ang-ni",
    "wof:placetype":"locality"
},
  "geometry": {"coordinates":[127.71167,40.29083],"type":"Point"}
}