{
  "type": "Feature",
  "properties": {
    "gn:admin1_code":"7.0",
    "gn:asciiname":"Kanch'on",
    "gn:country_code":"KP",
    "gn:dem":137,
    "gn:feature_class":"P",
    "gn:feature_code":"PPL",
    "gn:name":"Kanch\u2019on",
    "gn:population":0,
    "gn:timezone":"Asia/Pyongyang",
    "iso:country":"KP",
    "wof:name":"Kanch'on",
    "wof:placetype":"locality"
},
  "geometry": {"coordinates":[126.25833,38.47194],"type":"Point"}
}