{
  "type": "Feature",
  "properties": {
    "gn:admin1_code":"11.0",
    "gn:asciiname":"Sinyol-li",
    "gn:country_code":"KP",
    "gn:dem":352,
    "gn:feature_class":"P",
    "gn:feature_code":"PPL",
    "gn:name":"Siny\u014fl-li",
    "gn:population":0,
    "gn:timezone":"Asia/Pyongyang",
    "iso:country":"KP",
    "name:und_x_variant":[
        "\uc2e0\uc5f0\ub9ac",
        "Siny\u014fl-li"
    ],
    "wof:name":"Sinyol-li",
    "wof:placetype":"locality"
},
  "geometry": {"coordinates":[125.58278,40.55611],"type":"Point"}
}