{
  "type": "Feature",
  "properties": {
    "gn:admin1_code":"7.0",
    "gn:asciiname":"Sangsan-dong",
    "gn:country_code":"KP",
    "gn:dem":20,
    "gn:feature_class":"P",
    "gn:feature_code":"PPL",
    "gn:name":"Sangsan-dong",
    "gn:population":0,
    "gn:timezone":"Asia/Pyongyang",
    "iso:country":"KP",
    "wof:name":"Sangsan-dong",
    "wof:placetype":"locality"
},
  "geometry": {"coordinates":[125.65806000000001,38.76917],"type":"Point"}
}