{
  "type": "Feature",
  "properties": {
    "gn:admin1_code":"15.0",
    "gn:asciiname":"Changan-dong",
    "gn:country_code":"KP",
    "gn:dem":489,
    "gn:feature_class":"P",
    "gn:feature_code":"PPL",
    "gn:name":"Changan-dong",
    "gn:population":0,
    "gn:timezone":"Asia/Pyongyang",
    "iso:country":"KP",
    "name:und_x_variant":[
        "\uc7a5\uc548\ub3d9",
        "Changan-dong"
    ],
    "wof:name":"Changan-dong",
    "wof:placetype":"locality"
},
  "geometry": {"coordinates":[126.63056,39.50583],"type":"Point"}
}