{
  "type": "Feature",
  "properties": {
    "gn:admin1_code":"1.0",
    "gn:asciiname":"Tarhung-ni",
    "gn:country_code":"KP",
    "gn:dem":265,
    "gn:feature_class":"P",
    "gn:feature_code":"PPL",
    "gn:name":"Tarh\u016dng-ni",
    "gn:population":0,
    "gn:timezone":"Asia/Pyongyang",
    "iso:country":"KP",
    "name:und_x_variant":[
        "\ub2ec\ud765\ub9ac",
        "Tarh\u016dng-ni"
    ],
    "wof:name":"Tarhung-ni",
    "wof:placetype":"locality"
},
  "geometry": {"coordinates":[125.58333,40.6875],"type":"Point"}
}