{
  "type": "Feature",
  "properties": {
    "gn:admin1_code":"3.0",
    "gn:asciiname":"Tok-kol",
    "gn:country_code":"KP",
    "gn:dem":718,
    "gn:feature_class":"P",
    "gn:feature_code":"PPL",
    "gn:name":"T\u014fk-kol",
    "gn:population":0,
    "gn:timezone":"Asia/Pyongyang",
    "iso:country":"KP",
    "name:und_x_variant":[
        "\ub355\uace8",
        "T\u014fk-kol"
    ],
    "wof:name":"Tok-kol",
    "wof:placetype":"locality"
},
  "geometry": {"coordinates":[128.46943999999999,40.72611],"type":"Point"}
}