{
  "type": "Feature",
  "properties": {
    "gn:admin1_code":"15.0",
    "gn:asciiname":"Yongbung-ni",
    "gn:country_code":"KP",
    "gn:dem":8,
    "gn:feature_class":"P",
    "gn:feature_code":"PPL",
    "gn:name":"Yongbung-ni",
    "gn:population":0,
    "gn:timezone":"Asia/Pyongyang",
    "iso:country":"KP",
    "name:kor_x_preferred":[
        "\ub8e1\ubd81\ub9ac"
    ],
    "wof:name":"Yongbung-ni",
    "wof:placetype":"locality"
},
  "geometry": {"coordinates":[125.455,39.51389],"type":"Point"}
}