{
  "type": "Feature",
  "properties": {
    "gn:admin1_code":"11.0",
    "gn:asciiname":"Yongyon-burak",
    "gn:country_code":"KP",
    "gn:dem":14,
    "gn:feature_class":"P",
    "gn:feature_code":"PPL",
    "gn:name":"Yongy\u014fn-burak",
    "gn:population":0,
    "gn:timezone":"Asia/Pyongyang",
    "iso:country":"KP",
    "name:kor_x_preferred":[
        "\uc6a9\uc5f0"
    ],
    "name:kor_x_variant":[
        "Yongy\u014fn",
        "Yongy\u014fn-burak",
        "\ub8e1\uc5f0\ubd80\ub77d",
        "Yongs\u014f-burak",
        "\ub8e1\uc11c\ubd80\ub77d"
    ],
    "wof:name":"Yongyon-burak",
    "wof:placetype":"locality"
},
  "geometry": {"coordinates":[124.93079,39.667],"type":"Point"}
}