{
  "type": "Feature",
  "properties": {
    "gn:admin1_code":"6.0",
    "gn:asciiname":"Omsojae",
    "gn:country_code":"KP",
    "gn:dem":13,
    "gn:feature_class":"P",
    "gn:feature_code":"PPL",
    "gn:name":"Oms\u014fjae",
    "gn:population":0,
    "gn:timezone":"Asia/Pyongyang",
    "iso:country":"KP",
    "name:und_x_variant":[
        "\uc5c4\uc11c\uc7ac",
        "Oms\u014fjae"
    ],
    "wof:name":"Omsojae",
    "wof:placetype":"locality"
},
  "geometry": {"coordinates":[125.52278,37.86722],"type":"Point"}
}