{
  "type": "Feature",
  "properties": {
    "gn:admin1_code":"12.0",
    "gn:asciiname":"Anhung-ni",
    "gn:country_code":"KP",
    "gn:dem":31,
    "gn:feature_class":"P",
    "gn:feature_code":"PPL",
    "gn:name":"Anh\u016dng-ni",
    "gn:population":0,
    "gn:timezone":"Asia/Pyongyang",
    "iso:country":"KP",
    "name:kor_x_preferred":[
        "\uc548\ud765\ub9ac"
    ],
    "name:und_x_variant":[
        "Anh\u016dng-ni"
    ],
    "wof:name":"Anhung-ni",
    "wof:placetype":"locality"
},
  "geometry": {"coordinates":[125.70917,39.18361],"type":"Point"}
}