{
  "type": "Feature",
  "properties": {
    "gn:admin1_code":"0.0",
    "gn:asciiname":"Saen-maul",
    "gn:country_code":"KP",
    "gn:dem":96,
    "gn:feature_class":"P",
    "gn:feature_code":"PPL",
    "gn:name":"Saen-ma\u016dl",
    "gn:population":0,
    "gn:timezone":"Asia/Pyongyang",
    "iso:country":"KP",
    "name:kor_x_preferred":[
        "\uc0db\ub9c8\uc744"
    ],
    "name:und_x_variant":[
        "Kan-dong",
        "Saet-ma\u016dl",
        "Saen-ma\u016dl"
    ],
    "wof:name":"Saen-maul",
    "wof:placetype":"locality"
},
  "geometry": {"coordinates":[124.90000000000001,39.76667],"type":"Point"}
}