{
  "type": "Feature",
  "properties": {
    "gn:admin1_code":"3.0",
    "gn:asciiname":"Tajon-li",
    "gn:country_code":"KP",
    "gn:dem":71,
    "gn:feature_class":"P",
    "gn:feature_code":"PPL",
    "gn:name":"Taj\u014fn-li",
    "gn:population":0,
    "gn:timezone":"Asia/Pyongyang",
    "iso:country":"KP",
    "name:und_x_variant":[
        "Taden-ri",
        "Taj\u014fn-li",
        "\ub2e4\uc804\ub9ac",
        "Taj\u014fn-ni"
    ],
    "wof:name":"Tajon-li",
    "wof:placetype":"locality"
},
  "geometry": {"coordinates":[128.11277999999999,40.10566],"type":"Point"}
}