{
  "type": "Feature",
  "properties": {
    "gn:admin1_code":"18.0",
    "gn:asciiname":"Hongsangp'o",
    "gn:country_code":"KP",
    "gn:dem":41,
    "gn:feature_class":"P",
    "gn:feature_code":"PPL",
    "gn:name":"Hongsangp\u2019o",
    "gn:population":0,
    "gn:timezone":"Asia/Pyongyang",
    "iso:country":"KP",
    "name:und_x_variant":[
        "\ud64d\uc0c1\ud3ec",
        "Hongsangp\u2019o",
        "Hongsangpo"
    ],
    "wof:name":"Hongsangp'o",
    "wof:placetype":"locality"
},
  "geometry": {"coordinates":[130.61917,42.33333],"type":"Point"}
}