{
  "type": "Feature",
  "properties": {
    "gn:admin1_code":"7.0",
    "gn:asciiname":"Sinjang-dong",
    "gn:country_code":"KP",
    "gn:dem":72,
    "gn:feature_class":"P",
    "gn:feature_code":"PPL",
    "gn:name":"Sinjang-dong",
    "gn:population":0,
    "gn:timezone":"Asia/Pyongyang",
    "iso:country":"KP",
    "wof:name":"Sinjang-dong",
    "wof:placetype":"locality"
},
  "geometry": {"coordinates":[125.9675,38.48083],"type":"Point"}
}