{
  "type": "Feature",
  "properties": {
    "gn:admin1_code":"1.0",
    "gn:asciiname":"Pultang-gol",
    "gn:country_code":"KP",
    "gn:dem":813,
    "gn:feature_class":"P",
    "gn:feature_code":"PPL",
    "gn:name":"Pultang-gol",
    "gn:population":0,
    "gn:timezone":"Asia/Pyongyang",
    "iso:country":"KP",
    "name:und_x_variant":[
        "\ubd88\ub2f9\uace8",
        "Pultang-gol"
    ],
    "wof:name":"Pultang-gol",
    "wof:placetype":"locality"
},
  "geometry": {"coordinates":[126.84806,40.39083],"type":"Point"}
}