{
  "type": "Feature",
  "properties": {
    "gn:admin1_code":"15.0",
    "gn:asciiname":"Unsan-nodongjagu",
    "gn:cc2":"KP",
    "gn:country_code":"KP",
    "gn:dem":80,
    "gn:feature_class":"P",
    "gn:feature_code":"PPL",
    "gn:name":"\u016cnsan-nodongjagu",
    "gn:population":0,
    "gn:timezone":"Asia/Pyongyang",
    "iso:country":"KP",
    "name:und_x_variant":[
        "Insan",
        "W\u014fnsan-ni",
        "\u016cnsan-nodongjagu"
    ],
    "wof:name":"Unsan-nodongjagu",
    "wof:placetype":"locality"
},
  "geometry": {"coordinates":[126.07138999999999,39.38194],"type":"Point"}
}