{
  "type": "Feature",
  "properties": {
    "gn:admin1_code":"7.0",
    "gn:asciiname":"Sojae-gol",
    "gn:country_code":"KP",
    "gn:dem":48,
    "gn:feature_class":"P",
    "gn:feature_code":"PPL",
    "gn:name":"Sojae-gol",
    "gn:population":0,
    "gn:timezone":"Asia/Pyongyang",
    "iso:country":"KP",
    "name:kor_x_preferred":[
        "\uc18c\uc7ac\uace8"
    ],
    "wof:name":"Sojae-gol",
    "wof:placetype":"locality"
},
  "geometry": {"coordinates":[126.39583,38.32667],"type":"Point"}
}