{
  "type": "Feature",
  "properties": {
    "gn:admin1_code":"3.0",
    "gn:asciiname":"Songdong-ni",
    "gn:country_code":"KP",
    "gn:dem":17,
    "gn:feature_class":"P",
    "gn:feature_code":"PPL",
    "gn:name":"S\u014fngdong-ni",
    "gn:population":0,
    "gn:timezone":"Asia/Pyongyang",
    "iso:country":"KP",
    "name:und_x_variant":[
        "\uc131\ub3d9\ub9ac",
        "S\u014fngdong-ni"
    ],
    "wof:name":"Songdong-ni",
    "wof:placetype":"locality"
},
  "geometry": {"coordinates":[127.75167,39.91194],"type":"Point"}
}