{
  "type": "Feature",
  "properties": {
    "gn:admin1_code":"7.0",
    "gn:asciiname":"Hwang-gol",
    "gn:country_code":"KP",
    "gn:dem":539,
    "gn:feature_class":"P",
    "gn:feature_code":"PPL",
    "gn:name":"Hwang-gol",
    "gn:population":0,
    "gn:timezone":"Asia/Pyongyang",
    "iso:country":"KP",
    "name:kor_x_preferred":[
        "\ud669\uace8"
    ],
    "name:und_x_variant":[
        "Hwang-kol",
        "Hwang-gol"
    ],
    "wof:name":"Hwang-gol",
    "wof:placetype":"locality"
},
  "geometry": {"coordinates":[126.58917,39.12917],"type":"Point"}
}