{
  "type": "Feature",
  "properties": {
    "gn:admin1_code":"3.0",
    "gn:asciiname":"Hungbong-ni",
    "gn:country_code":"KP",
    "gn:dem":108,
    "gn:feature_class":"P",
    "gn:feature_code":"PPL",
    "gn:name":"H\u016dngbong-ni",
    "gn:population":0,
    "gn:timezone":"Asia/Pyongyang",
    "iso:country":"KP",
    "name:eng_x_preferred":[
        "Hungbong"
    ],
    "name:eng_x_variant":[
        "Hungbong-ni"
    ],
    "name:und_x_variant":[
        "\ud765\ubcf5\ub9ac",
        "H\u016dngbong-ni"
    ],
    "wof:name":"Hungbong",
    "wof:placetype":"locality"
},
  "geometry": {"coordinates":[127.53972,40.16778],"type":"Point"}
}