{
  "type": "Feature",
  "properties": {
    "gn:admin1_code":"15.0",
    "gn:asciiname":"Songdang",
    "gn:country_code":"KP",
    "gn:dem":46,
    "gn:feature_class":"P",
    "gn:feature_code":"PPL",
    "gn:name":"Songdang",
    "gn:population":0,
    "gn:timezone":"Asia/Pyongyang",
    "iso:country":"KP",
    "name:kor_x_preferred":[
        "\uc1a1\ub2f9"
    ],
    "wof:name":"Songdang",
    "wof:placetype":"locality"
},
  "geometry": {"coordinates":[125.85138999999999,39.68722],"type":"Point"}
}