{
  "type": "Feature",
  "properties": {
    "gn:admin1_code":"12.0",
    "gn:admin2_code":"Sangw\u014fn-gun",
    "gn:asciiname":"Yo-gol",
    "gn:cc2":"KP",
    "gn:country_code":"KP",
    "gn:dem":139,
    "gn:feature_class":"P",
    "gn:feature_code":"PPL",
    "gn:name":"Yo-gol",
    "gn:population":0,
    "gn:timezone":"Asia/Pyongyang",
    "iso:country":"KP",
    "name:und_x_variant":[
        "Yo-kol",
        "Yo-gol"
    ],
    "wof:name":"Yo-gol",
    "wof:placetype":"locality"
},
  "geometry": {"coordinates":[126.08556000000002,38.89917],"type":"Point"}
}