{
  "type": "Feature",
  "properties": {
    "gn:admin1_code":"7.0",
    "gn:asciiname":"Sinch'on",
    "gn:country_code":"KP",
    "gn:dem":14,
    "gn:feature_class":"P",
    "gn:feature_code":"PPL",
    "gn:name":"Sinch\u2019on",
    "gn:population":0,
    "gn:timezone":"Asia/Pyongyang",
    "iso:country":"KP",
    "name:kor_x_preferred":[
        "\uc2e0\ucd0c"
    ],
    "name:kor_x_variant":[
        "Sinch\u2019on"
    ],
    "wof:name":"Sinch'on",
    "wof:placetype":"locality"
},
  "geometry": {"coordinates":[125.63028,38.65083],"type":"Point"}
}