{
  "type": "Feature",
  "properties": {
    "gn:admin1_code":"11.0",
    "gn:asciiname":"Yongsong-ni",
    "gn:country_code":"KP",
    "gn:dem":110,
    "gn:feature_class":"P",
    "gn:feature_code":"PPL",
    "gn:name":"Yongs\u014fng-ni",
    "gn:population":0,
    "gn:timezone":"Asia/Pyongyang",
    "iso:country":"KP",
    "name:eng_x_preferred":[
        "Yongsong"
    ],
    "name:eng_x_variant":[
        "Yongsong-ni"
    ],
    "name:und_x_variant":[
        "Yongs\u014fng-dong",
        "Yongs\u014fng-ni"
    ],
    "wof:name":"Yongsong",
    "wof:placetype":"locality"
},
  "geometry": {"coordinates":[125.74472,39.90639],"type":"Point"}
}