{
  "type": "Feature",
  "properties": {
    "gn:admin1_code":"6.0",
    "gn:asciiname":"Najang-dong",
    "gn:country_code":"KP",
    "gn:dem":62,
    "gn:feature_class":"P",
    "gn:feature_code":"PPL",
    "gn:name":"Najang-dong",
    "gn:population":0,
    "gn:timezone":"Asia/Pyongyang",
    "iso:country":"KP",
    "name:und_x_variant":[
        "\ub098\uc7a5\ub3d9",
        "Najang-dong"
    ],
    "wof:name":"Najang-dong",
    "wof:placetype":"locality"
},
  "geometry": {"coordinates":[125.19499999999999,38.20028],"type":"Point"}
}