{
  "type": "Feature",
  "properties": {
    "gn:admin1_code":"7.0",
    "gn:asciiname":"Tokchok-kol",
    "gn:country_code":"KP",
    "gn:dem":138,
    "gn:feature_class":"P",
    "gn:feature_code":"PPL",
    "gn:name":"T\u014fkch\u014fk-kol",
    "gn:population":0,
    "gn:timezone":"Asia/Pyongyang",
    "iso:country":"KP",
    "name:und_x_variant":[
        "\ub355\uc801\uace8",
        "T\u014fkch\u014fk-kol"
    ],
    "wof:name":"Tokchok-kol",
    "wof:placetype":"locality"
},
  "geometry": {"coordinates":[126.55444,38.135],"type":"Point"}
}