{
  "type": "Feature",
  "properties": {
    "gn:admin1_code":"9.0",
    "gn:asciiname":"Sogal-li",
    "gn:cc2":"KP",
    "gn:country_code":"KP",
    "gn:dem":213,
    "gn:feature_class":"P",
    "gn:feature_code":"PPL",
    "gn:name":"S\u014fgal-li",
    "gn:population":0,
    "gn:timezone":"Asia/Pyongyang",
    "iso:country":"KP",
    "name:und_x_variant":[
        "S\u014fgan-ni",
        "S\u014fgal-li"
    ],
    "wof:name":"Sogal-li",
    "wof:placetype":"locality"
},
  "geometry": {"coordinates":[126.94222000000001,38.47528],"type":"Point"}
}