{
  "type": "Feature",
  "properties": {
    "gn:admin1_code":"17.0",
    "gn:asciiname":"Komunsu-dong",
    "gn:country_code":"KP",
    "gn:dem":287,
    "gn:feature_class":"P",
    "gn:feature_code":"PPL",
    "gn:name":"K\u014fmunsu-dong",
    "gn:population":0,
    "gn:timezone":"Asia/Pyongyang",
    "iso:country":"KP",
    "name:und_x_variant":[
        "\uac70\ubb38\uc218\ub3d9",
        "K\u014fmunsu-dong"
    ],
    "wof:name":"Komunsu-dong",
    "wof:placetype":"locality"
},
  "geometry": {"coordinates":[129.89444,42.51917],"type":"Point"}
}