{
  "type": "Feature",
  "properties": {
    "gn:admin1_code":"0.0",
    "gn:asciiname":"Yangji",
    "gn:country_code":"KP",
    "gn:dem":76,
    "gn:feature_class":"P",
    "gn:feature_code":"PPL",
    "gn:name":"Yangji",
    "gn:population":0,
    "gn:timezone":"Asia/Pyongyang",
    "iso:country":"KP",
    "name:kor_x_preferred":[
        "\uc591\uc9c0"
    ],
    "wof:name":"Yangji",
    "wof:placetype":"locality"
},
  "geometry": {"coordinates":[125.18333,39.63333],"type":"Point"}
}