{
  "type": "Feature",
  "properties": {
    "gn:admin1_code":"3.0",
    "gn:asciiname":"Kwanghung-ni",
    "gn:country_code":"KP",
    "gn:dem":32,
    "gn:feature_class":"P",
    "gn:feature_code":"PPL",
    "gn:name":"Kwangh\u016dng-ni",
    "gn:population":0,
    "gn:timezone":"Asia/Pyongyang",
    "iso:country":"KP",
    "name:und_x_variant":[
        "\uad11\ud765\ub9ac",
        "Kwangh\u016dng-ni"
    ],
    "wof:name":"Kwanghung-ni",
    "wof:placetype":"locality"
},
  "geometry": {"coordinates":[127.3725,39.81333],"type":"Point"}
}