{
  "type": "Feature",
  "properties": {
    "gn:admin1_code":"13.0",
    "gn:admin2_code":"2041726",
    "gn:asciiname":"Maehyang-dong",
    "gn:country_code":"KP",
    "gn:dem":1100,
    "gn:feature_class":"P",
    "gn:feature_code":"PPL",
    "gn:name":"Maehyang-dong",
    "gn:population":0,
    "gn:timezone":"Asia/Pyongyang",
    "iso:country":"KP",
    "wof:name":"Maehyang-dong",
    "wof:placetype":"locality"
},
  "geometry": {"coordinates":[127.94638999999999,40.82167000000001],"type":"Point"}
}