{
  "type": "Feature",
  "properties": {
    "gn:admin1_code":"15.0",
    "gn:asciiname":"Sangnamch'ang",
    "gn:country_code":"KP",
    "gn:dem":372,
    "gn:feature_class":"P",
    "gn:feature_code":"PPL",
    "gn:name":"Sangnamch\u2019ang",
    "gn:population":0,
    "gn:timezone":"Asia/Pyongyang",
    "iso:country":"KP",
    "name:kor_x_preferred":[
        "\uc0c1\ub0a8\ucc3d"
    ],
    "name:und_x_variant":[
        "Sangnamch\u2019ang"
    ],
    "wof:name":"Sangnamch'ang",
    "wof:placetype":"locality"
},
  "geometry": {"coordinates":[126.52639000000001,39.54083],"type":"Point"}
}