{
  "type": "Feature",
  "properties": {
    "gn:admin1_code":"0.0",
    "gn:asciiname":"Pusan-dong",
    "gn:country_code":"KP",
    "gn:dem":49,
    "gn:feature_class":"P",
    "gn:feature_code":"PPL",
    "gn:name":"Pusan-dong",
    "gn:population":0,
    "gn:timezone":"Asia/Pyongyang",
    "iso:country":"KP",
    "name:kor_x_preferred":[
        "\ubd80\uc0b0\ub3d9"
    ],
    "wof:name":"Pusan-dong",
    "wof:placetype":"locality"
},
  "geometry": {"coordinates":[124.84999999999999,38.16667],"type":"Point"}
}