{
  "type": "Feature",
  "properties": {
    "gn:admin1_code":"7.0",
    "gn:asciiname":"P'ung-dong",
    "gn:country_code":"KP",
    "gn:dem":145,
    "gn:feature_class":"P",
    "gn:feature_code":"PPL",
    "gn:name":"P\u2019ung-dong",
    "gn:population":0,
    "gn:timezone":"Asia/Pyongyang",
    "iso:country":"KP",
    "name:kor_x_preferred":[
        "\ud48d\ub3d9"
    ],
    "name:und_x_variant":[
        "P\u2019ung-dong"
    ],
    "wof:name":"P'ung-dong",
    "wof:placetype":"locality"
},
  "geometry": {"coordinates":[126.01416999999999,38.22528],"type":"Point"}
}