{
  "type": "Feature",
  "properties": {
    "gn:admin1_code":"3.0",
    "gn:asciiname":"Yongsong-ni",
    "gn:country_code":"KP",
    "gn:dem":30,
    "gn:feature_class":"P",
    "gn:feature_code":"PPL",
    "gn:name":"Yongs\u014fng-ni",
    "gn:population":0,
    "gn:timezone":"Asia/Pyongyang",
    "iso:country":"KP",
    "name:und_x_variant":[
        "\uc6a9\uc11d\ub9ac",
        "Yongs\u014fng-ni"
    ],
    "wof:name":"Yongsong-ni",
    "wof:placetype":"locality"
},
  "geometry": {"coordinates":[127.31556,39.74194],"type":"Point"}
}