{
  "type": "Feature",
  "properties": {
    "gn:admin1_code":"12.0",
    "gn:asciiname":"P'yongch'on",
    "gn:country_code":"KP",
    "gn:dem":13,
    "gn:feature_class":"P",
    "gn:feature_code":"PPL",
    "gn:name":"P\u2019y\u014fngch\u2019\u014fn",
    "gn:population":0,
    "gn:timezone":"Asia/Pyongyang",
    "iso:country":"KP",
    "name:kor_x_preferred":[
        "\ud3c9\ucc9c"
    ],
    "name:und_x_variant":[
        "P\u2019y\u014fngch\u2019\u014fn",
        "Pyeongcheon"
    ],
    "wof:name":"P'yongch'on",
    "wof:placetype":"locality"
},
  "geometry": {"coordinates":[125.71528000000001,38.99306],"type":"Point"}
}