{
  "type": "Feature",
  "properties": {
    "gn:admin1_code":"12.0",
    "gn:asciiname":"P'yongch'on",
    "gn:country_code":"KP",
    "gn:dem":13,
    "gn:feature_class":"P",
    "gn:feature_code":"PPL",
    "gn:name":"P\u2019y\u014fngch\u2019\u014fn",
    "gn:population":0,
    "gn:timezone":"Asia/Pyongyang",
    "iso:country":"KP",
    "name:ceb_x_preferred":[
        "P'y\u014fngch'\u014fn-guy\u014fk"
    ],
    "name:deu_x_preferred":[
        "P\u2019y\u014fngch\u2019\u014fn-guy\u014fk"
    ],
    "name:epo_x_preferred":[
        "P'y\u014fngch'\u014fn-guy\u014fk"
    ],
    "name:fas_x_preferred":[
        "\u067e\u06cc\u0648\u0646\u06af\u0686\u0648\u0646-\u06af\u0648\u06cc\u0648\u06a9"
    ],
    "name:jpn_x_preferred":[
        "\u5e73\u5ddd\u533a\u57df"
    ],
    "name:kor_x_preferred":[
        "\ud3c9\ucc9c"
    ],
    "name:kor_x_variant":[
        "\ud3c9\ucc9c\uad6c\uc5ed"
    ],
    "name:nor_x_preferred":[
        "Pyongchon"
    ],
    "name:pol_x_preferred":[
        "P'y\u014fngch'\u014fn"
    ],
    "name:por_x_preferred":[
        "P'y\u014fngch'\u014fn-guy\u014fk"
    ],
    "name:sco_x_preferred":[
        "Pyongchon-guyok"
    ],
    "name:swe_x_preferred":[
        "P'y\u014fngch'\u014fn-guy\u014fk"
    ],
    "name:und_x_variant":[
        "P\u2019y\u014fngch\u2019\u014fn",
        "Pyeongcheon"
    ],
    "name:vie_x_preferred":[
        "Pyongchon"
    ],
    "name:zho_x_preferred":[
        "\u5e73\u5ddd\u5340\u57df"
    ],
    "wof:name":"P'yongch'on",
    "wof:placetype":"locality"
},
  "geometry": {"coordinates":[125.71528000000001,38.99306],"type":"Point"}
}