{
  "type": "Feature",
  "properties": {
    "gn:admin1_code":"17.0",
    "gn:asciiname":"Horyejungp'yong",
    "gn:country_code":"KP",
    "gn:dem":218,
    "gn:feature_class":"P",
    "gn:feature_code":"PPL",
    "gn:name":"Horyejungp\u2019y\u014fng",
    "gn:population":0,
    "gn:timezone":"Asia/Pyongyang",
    "iso:country":"KP",
    "wof:name":"Horyejungp'yong",
    "wof:placetype":"locality"
},
  "geometry": {"coordinates":[129.71666999999999,41.25],"type":"Point"}
}