{
  "type": "Feature",
  "properties": {
    "gn:admin1_code":"11.0",
    "gn:asciiname":"Pihyon-dong",
    "gn:country_code":"KP",
    "gn:dem":94,
    "gn:feature_class":"P",
    "gn:feature_code":"PPL",
    "gn:name":"Pihy\u014fn-dong",
    "gn:population":0,
    "gn:timezone":"Asia/Pyongyang",
    "iso:country":"KP",
    "name:kor_x_preferred":[
        "Pihy\u014fn-dong"
    ],
    "name:kor_x_variant":[
        "\ube44\ud604\ub3d9"
    ],
    "wof:name":"Pihyon-dong",
    "wof:placetype":"locality"
},
  "geometry": {"coordinates":[124.90944,39.8225],"type":"Point"}
}