{
  "type": "Feature",
  "properties": {
    "gn:admin1_code":"17.0",
    "gn:admin2_code":"My\u014fngch'\u014fn-gun",
    "gn:asciiname":"Mae-dong",
    "gn:country_code":"KP",
    "gn:dem":80,
    "gn:feature_class":"P",
    "gn:feature_code":"PPL",
    "gn:name":"Mae-dong",
    "gn:population":0,
    "gn:timezone":"Asia/Pyongyang",
    "iso:country":"KP",
    "name:und_x_variant":[
        "Mae-gol",
        "Mae-kol",
        "\ub9e4\ub3d9",
        "Mae-dong"
    ],
    "wof:name":"Mae-dong",
    "wof:placetype":"locality"
},
  "geometry": {"coordinates":[129.64944,40.99917],"type":"Point"}
}