{
  "type": "Feature",
  "properties": {
    "gn:admin1_code":"3.0",
    "gn:asciiname":"Sangdongsal-li",
    "gn:country_code":"KP",
    "gn:dem":222,
    "gn:feature_class":"P",
    "gn:feature_code":"PPL",
    "gn:name":"Sangdongsal-li",
    "gn:population":0,
    "gn:timezone":"Asia/Pyongyang",
    "iso:country":"KP",
    "name:und_x_variant":[
        "\uc0c1\ub3d9\uc0b0\ub9ac",
        "Sangdongsan-ni",
        "Sangdongsal-li"
    ],
    "wof:name":"Sangdongsal-li",
    "wof:placetype":"locality"
},
  "geometry": {"coordinates":[126.80333,39.53889],"type":"Point"}
}