{
  "type": "Feature",
  "properties": {
    "gn:admin1_code":"13.0",
    "gn:asciiname":"Koamp'osang-ni",
    "gn:country_code":"KP",
    "gn:dem":969,
    "gn:feature_class":"P",
    "gn:feature_code":"PPL",
    "gn:name":"Koamp\u2019osang-ni",
    "gn:population":0,
    "gn:timezone":"Asia/Pyongyang",
    "iso:country":"KP",
    "wof:name":"Koamp'osang-ni",
    "wof:placetype":"locality"
},
  "geometry": {"coordinates":[127.95999999999999,41.2375],"type":"Point"}
}