{
  "type": "Feature",
  "properties": {
    "gn:admin1_code":"0.0",
    "gn:asciiname":"P'ungsang-ni",
    "gn:country_code":"KP",
    "gn:dem":62,
    "gn:feature_class":"P",
    "gn:feature_code":"PPL",
    "gn:name":"P\u2019ungsang-ni",
    "gn:population":0,
    "gn:timezone":"Asia/Pyongyang",
    "iso:country":"KP",
    "name:eng_x_preferred":[
        "P'ungsang"
    ],
    "name:eng_x_variant":[
        "P'ungsang-ni"
    ],
    "name:kor_x_preferred":[
        "\ud48d\uc0c1\ub9ac"
    ],
    "name:und_x_variant":[
        "P\u2019ungsang-ni"
    ],
    "wof:name":"P'ungsang",
    "wof:placetype":"locality"
},
  "geometry": {"coordinates":[127.46666999999999,40.08333],"type":"Point"}
}