{
  "type": "Feature",
  "properties": {
    "gn:admin1_code":"1.0",
    "gn:asciiname":"Munmyong-maul",
    "gn:country_code":"KP",
    "gn:dem":372,
    "gn:feature_class":"P",
    "gn:feature_code":"PPL",
    "gn:name":"Munmy\u014fng-ma\u016dl",
    "gn:population":0,
    "gn:timezone":"Asia/Pyongyang",
    "iso:country":"KP",
    "name:und_x_variant":[
        "\ubb38\uba85\ub3d9",
        "Munmy\u014fng-dong",
        "Munmy\u014fng-ma\u016dl",
        "\ubb38\uba85\ub9c8\uc744"
    ],
    "wof:name":"Munmyong-maul",
    "wof:placetype":"locality"
},
  "geometry": {"coordinates":[126.2535,40.81235],"type":"Point"}
}