{
  "type": "Feature",
  "properties": {
    "gn:admin1_code":"6.0",
    "gn:asciiname":"Kkach'i-gol",
    "gn:country_code":"KP",
    "gn:dem":49,
    "gn:feature_class":"P",
    "gn:feature_code":"PPL",
    "gn:name":"Kkach\u2019i-gol",
    "gn:population":0,
    "gn:timezone":"Asia/Pyongyang",
    "iso:country":"KP",
    "name:kor_x_preferred":[
        "\uae4c\uce58\uace8"
    ],
    "name:und_x_variant":[
        "Kkach\u2019i-gol"
    ],
    "wof:name":"Kkach'i-gol",
    "wof:placetype":"locality"
},
  "geometry": {"coordinates":[126.155,37.98111],"type":"Point"}
}