{
  "type": "Feature",
  "properties": {
    "gn:admin1_code":"3.0",
    "gn:asciiname":"Sangjung-ni",
    "gn:country_code":"KP",
    "gn:dem":19,
    "gn:feature_class":"P",
    "gn:feature_code":"PPL",
    "gn:name":"Sangjung-ni",
    "gn:population":0,
    "gn:timezone":"Asia/Pyongyang",
    "iso:country":"KP",
    "name:eng_x_preferred":[
        "Sangjung"
    ],
    "name:eng_x_variant":[
        "Sangjung-ni"
    ],
    "name:und_x_variant":[
        "\uc0c1\uc911\ub9ac",
        "Sangjung-ni"
    ],
    "wof:name":"Sangjung",
    "wof:placetype":"locality"
},
  "geometry": {"coordinates":[127.46778,39.96528],"type":"Point"}
}