{
  "type": "Feature",
  "properties": {
    "gn:admin1_code":"9.0",
    "gn:asciiname":"Toryong-gol",
    "gn:country_code":"KP",
    "gn:dem":504,
    "gn:feature_class":"P",
    "gn:feature_code":"PPL",
    "gn:name":"Tory\u014fng-gol",
    "gn:population":0,
    "gn:timezone":"Asia/Pyongyang",
    "iso:country":"KP",
    "name:und_x_variant":[
        "\ub3c4\ub839\uace8",
        "Tory\u014fng-gol"
    ],
    "wof:name":"Toryong-gol",
    "wof:placetype":"locality"
},
  "geometry": {"coordinates":[127.57222,38.75167],"type":"Point"}
}