{
  "type": "Feature",
  "properties": {
    "gn:admin1_code":"6.0",
    "gn:asciiname":"Tonggok-tong",
    "gn:country_code":"KP",
    "gn:dem":81,
    "gn:feature_class":"P",
    "gn:feature_code":"PPL",
    "gn:name":"Tonggok-tong",
    "gn:population":0,
    "gn:timezone":"Asia/Pyongyang",
    "iso:country":"KP",
    "name:eng_x_preferred":[
        "Tonggok"
    ],
    "name:eng_x_variant":[
        "Tonggok-tong"
    ],
    "name:und_x_variant":[
        "\ub3d9\uace1\ub3d9",
        "Tonggok-tong"
    ],
    "wof:name":"Tonggok",
    "wof:placetype":"locality"
},
  "geometry": {"coordinates":[125.35472,37.95917],"type":"Point"}
}