{
  "type": "Feature",
  "properties": {
    "gn:admin1_code":"0.0",
    "gn:asciiname":"Sambong-ni",
    "gn:country_code":"KP",
    "gn:dem":95,
    "gn:feature_class":"P",
    "gn:feature_code":"PPL",
    "gn:name":"Sambong-ni",
    "gn:population":0,
    "gn:timezone":"Asia/Pyongyang",
    "iso:country":"KP",
    "name:eng_x_preferred":[
        "Sambong"
    ],
    "name:eng_x_variant":[
        "Sambong-ni"
    ],
    "name:kor_x_preferred":[
        "\uc0bc\ubd09\ub9ac"
    ],
    "wof:name":"Sambong",
    "wof:placetype":"locality"
},
  "geometry": {"coordinates":[126.01667,38.13333],"type":"Point"}
}