{
  "type": "Feature",
  "properties": {
    "gn:admin1_code":"18.0",
    "gn:asciiname":"Konch'i-dong",
    "gn:country_code":"KP",
    "gn:dem":189,
    "gn:feature_class":"P",
    "gn:feature_code":"PPL",
    "gn:name":"K\u014fnch\u2019i-dong",
    "gn:population":0,
    "gn:timezone":"Asia/Pyongyang",
    "iso:country":"KP",
    "name:kor_x_preferred":[
        "\uac74\uce58\ub3d9"
    ],
    "name:und_x_variant":[
        "K\u014fnch\u2019i-dong",
        "Geonchidong"
    ],
    "wof:name":"Konch'i-dong",
    "wof:placetype":"locality"
},
  "geometry": {"coordinates":[130.09999999999999,42.26667],"type":"Point"}
}