{
  "type": "Feature",
  "properties": {
    "gn:admin1_code":"0.0",
    "gn:asciiname":"Ungbong-dong",
    "gn:country_code":"KP",
    "gn:dem":117,
    "gn:feature_class":"P",
    "gn:feature_code":"PPL",
    "gn:name":"Ungbong-dong",
    "gn:population":0,
    "gn:timezone":"Asia/Pyongyang",
    "iso:country":"KP",
    "name:kor_x_preferred":[
        "\uc6c5\ubd09\ub3d9"
    ],
    "wof:name":"Ungbong-dong",
    "wof:placetype":"locality"
},
  "geometry": {"coordinates":[125.51667,39.76667],"type":"Point"}
}