{
  "type": "Feature",
  "properties": {
    "gn:admin1_code":"11.0",
    "gn:asciiname":"Yonsang-dong",
    "gn:country_code":"KP",
    "gn:dem":28,
    "gn:feature_class":"P",
    "gn:feature_code":"PPL",
    "gn:name":"Y\u014fnsang-dong",
    "gn:population":0,
    "gn:timezone":"Asia/Pyongyang",
    "iso:country":"KP",
    "name:und_x_variant":[
        "\ub828\uc0c1\ub3d9",
        "Y\u014fnsang-dong"
    ],
    "wof:name":"Yonsang-dong",
    "wof:placetype":"locality"
},
  "geometry": {"coordinates":[124.42944,40.07917],"type":"Point"}
}