{
  "type": "Feature",
  "properties": {
    "gn:admin1_code":"12.0",
    "gn:asciiname":"Sinp'yong-ni",
    "gn:country_code":"KP",
    "gn:dem":28,
    "gn:feature_class":"P",
    "gn:feature_code":"PPL",
    "gn:name":"Sinp\u2019y\u014fng-ni",
    "gn:population":0,
    "gn:timezone":"Asia/Pyongyang",
    "iso:country":"KP",
    "name:kor_x_preferred":[
        "\uc2e0\ud3c9\ub9ac"
    ],
    "name:und_x_variant":[
        "Sinp\u2019y\u014fng-ni",
        "Sinpyeongni"
    ],
    "wof:name":"Sinp'yong-ni",
    "wof:placetype":"locality"
},
  "geometry": {"coordinates":[125.66667,39.23333],"type":"Point"}
}