{
  "type": "Feature",
  "properties": {
    "gn:admin1_code":"9.0",
    "gn:asciiname":"Songch'on-dong",
    "gn:country_code":"KP",
    "gn:dem":85,
    "gn:feature_class":"P",
    "gn:feature_code":"PPL",
    "gn:name":"Songch\u2019\u014fn-dong",
    "gn:population":0,
    "gn:timezone":"Asia/Pyongyang",
    "iso:country":"KP",
    "name:und_x_variant":[
        "Sh\u014dch\u016b-ri",
        "Songjung-ni",
        "Songch\u2019\u014fn-ni",
        "Songch\u2019\u014fn-dong",
        "\uc1a1\ucd0c\ub3d9"
    ],
    "wof:name":"Songch'on-dong",
    "wof:placetype":"locality"
},
  "geometry": {"coordinates":[127.39643,39.19214],"type":"Point"}
}