{
  "type": "Feature",
  "properties": {
    "gn:admin1_code":"6.0",
    "gn:asciiname":"Chadal-li",
    "gn:country_code":"KP",
    "gn:dem":24,
    "gn:feature_class":"P",
    "gn:feature_code":"PPL",
    "gn:name":"Chadal-li",
    "gn:population":0,
    "gn:timezone":"Asia/Pyongyang",
    "iso:country":"KP",
    "name:kor_x_preferred":[
        "\uc790\ub2e8\ub9ac"
    ],
    "wof:name":"Chadal-li",
    "wof:placetype":"locality"
},
  "geometry": {"coordinates":[126.13972,37.87778],"type":"Point"}
}