{
  "type": "Feature",
  "properties": {
    "gn:admin1_code":"11.0",
    "gn:asciiname":"Yongsong-ni",
    "gn:country_code":"KP",
    "gn:dem":26,
    "gn:feature_class":"P",
    "gn:feature_code":"PPL",
    "gn:name":"Yongsong-ni",
    "gn:population":0,
    "gn:timezone":"Asia/Pyongyang",
    "iso:country":"KP",
    "name:und_x_variant":[
        "\ub8e1\uc1a1\ub9ac",
        "Yongsong-ni"
    ],
    "wof:name":"Yongsong-ni",
    "wof:placetype":"locality"
},
  "geometry": {"coordinates":[124.42583,39.98722],"type":"Point"}
}