{
  "type": "Feature",
  "properties": {
    "gn:admin1_code":"6.0",
    "gn:asciiname":"Chungnong-dong",
    "gn:country_code":"KP",
    "gn:dem":72,
    "gn:feature_class":"P",
    "gn:feature_code":"PPL",
    "gn:name":"Chungnong-dong",
    "gn:population":0,
    "gn:timezone":"Asia/Pyongyang",
    "iso:country":"KP",
    "name:kor_x_preferred":[
        "\uc911\ub18d\ub3d9"
    ],
    "wof:name":"Chungnong-dong",
    "wof:placetype":"locality"
},
  "geometry": {"coordinates":[125.02083,38.39944000000001],"type":"Point"}
}