{
  "type": "Feature",
  "properties": {
    "gn:admin1_code":"6.0",
    "gn:admin2_code":"P\u2019anmun-gun",
    "gn:asciiname":"Saenung-gol",
    "gn:country_code":"KP",
    "gn:dem":23,
    "gn:feature_class":"P",
    "gn:feature_code":"PPL",
    "gn:name":"Saen\u016dng-gol",
    "gn:population":0,
    "gn:timezone":"Asia/Pyongyang",
    "iso:country":"KP",
    "name:und_x_variant":[
        "Sillung-dong",
        "Saen\u016dng-dong",
        "Saen\u016dng-gol"
    ],
    "wof:name":"Saenung-gol",
    "wof:placetype":"locality"
},
  "geometry": {"coordinates":[126.52388999999999,37.81917],"type":"Point"}
}