{
  "type": "Feature",
  "properties": {
    "gn:admin1_code":"15.0",
    "gn:asciiname":"Mongemul",
    "gn:country_code":"KP",
    "gn:dem":699,
    "gn:feature_class":"P",
    "gn:feature_code":"PPL",
    "gn:name":"M\u014fngemul",
    "gn:population":0,
    "gn:timezone":"Asia/Pyongyang",
    "iso:country":"KP",
    "name:und_x_variant":[
        "\uba4d\uc5d0\ubb3c",
        "M\u014fngemul"
    ],
    "wof:name":"Mongemul",
    "wof:placetype":"locality"
},
  "geometry": {"coordinates":[126.69499999999999,39.76417],"type":"Point"}
}