{
  "type": "Feature",
  "properties": {
    "gn:admin1_code":"12.0",
    "gn:asciiname":"Chaktarigol",
    "gn:country_code":"KP",
    "gn:dem":73,
    "gn:feature_class":"P",
    "gn:feature_code":"PPL",
    "gn:name":"Chaktarigol",
    "gn:population":0,
    "gn:timezone":"Asia/Pyongyang",
    "iso:country":"KP",
    "name:kor_x_preferred":[
        "\uc791\ub2e4\ub9ac\uace8"
    ],
    "name:und_x_variant":[
        "Jakdarigol"
    ],
    "wof:name":"Chaktarigol",
    "wof:placetype":"locality"
},
  "geometry": {"coordinates":[125.87333,39.09722],"type":"Point"}
}