{
  "type": "Feature",
  "properties": {
    "gn:admin1_code":"15.0",
    "gn:asciiname":"Insan",
    "gn:country_code":"KP",
    "gn:dem":200,
    "gn:feature_class":"P",
    "gn:feature_code":"PPL",
    "gn:name":"Insan",
    "gn:population":0,
    "gn:timezone":"Asia/Pyongyang",
    "iso:country":"KP",
    "name:fas_x_preferred":[
        "\u0627\u0646\u0633\u0627\u0646"
    ],
    "name:kor_x_preferred":[
        "\uc778\uc0b0"
    ],
    "name:new_x_preferred":[
        "\u0907\u0928\u094d\u0938\u093e\u0928"
    ],
    "name:pol_x_preferred":[
        "Insan"
    ],
    "wof:name":"Insan",
    "wof:placetype":"locality"
},
  "geometry": {"coordinates":[126.53917,39.25472],"type":"Point"}
}