{
  "type": "Feature",
  "properties": {
    "gn:admin1_code":"12.0",
    "gn:asciiname":"Man'gyongdae-ri",
    "gn:country_code":"KP",
    "gn:dem":3,
    "gn:feature_class":"P",
    "gn:feature_code":"PPL",
    "gn:name":"Man\u2019gy\u014fngdae-ri",
    "gn:population":0,
    "gn:timezone":"Asia/Pyongyang",
    "iso:country":"KP",
    "name:ces_x_preferred":[
        "Mangj\u014fngd\u00e4guj\u014fk"
    ],
    "name:deu_x_preferred":[
        "Mangy\u014fngdae-guy\u014fk"
    ],
    "name:epo_x_preferred":[
        "Man'gy\u014fngdae-guy\u014fk"
    ],
    "name:fas_x_preferred":[
        "\u0645\u0627\u0646\u06af\u06cc\u0648\u0646\u06af\u062f\u0627\u0626\u0647-\u06af\u0648\u06cc\u0648\u06a9"
    ],
    "name:heb_x_preferred":[
        "\u05de\u05e0\u05d2\u05d9\u05d5\u05e0\u05d3\u05d4"
    ],
    "name:ita_x_preferred":[
        "Mangyongdae-guyok"
    ],
    "name:jpn_x_preferred":[
        "\u4e07\u666f\u53f0\u533a\u57df"
    ],
    "name:kor_x_preferred":[
        "\ub9cc\uacbd\ub300\uad6c\uc5ed"
    ],
    "name:nor_x_preferred":[
        "Mangyongdae"
    ],
    "name:pol_x_preferred":[
        "Man'gy\u014fngdae"
    ],
    "name:por_x_preferred":[
        "Man'gy\u014fngdae-guy\u014fk"
    ],
    "name:rus_x_preferred":[
        "\u041c\u0430\u043d\u0433\u0451\u043d\u0434\u044d-\u0433\u0443\u0451\u043a"
    ],
    "name:sco_x_preferred":[
        "Mangyongdae-guyok"
    ],
    "name:tha_x_preferred":[
        "\u0e40\u0e02\u0e15\u0e21\u0e31\u0e19\u0e01\u0e22\u0e47\u0e2d\u0e07\u0e41\u0e14"
    ],
    "name:und_x_variant":[
        "Man\u2019gy\u014fngdae",
        "Mangyondae",
        "Mankeidai",
        "Man\u2019gy\u014fngdae-ri"
    ],
    "name:vie_x_preferred":[
        "Mangyongdae"
    ],
    "name:zho_x_preferred":[
        "\u4e07\u666f\u53f0\u533a\u57df"
    ],
    "wof:name":"Man'gyongdae-ri",
    "wof:placetype":"locality"
},
  "geometry": {"coordinates":[125.66667,38.98333],"type":"Point"}
}