{
  "type": "Feature",
  "properties": {
    "gn:admin1_code":"12.0",
    "gn:asciiname":"Man'gyongdae-ri",
    "gn:country_code":"KP",
    "gn:dem":3,
    "gn:feature_class":"P",
    "gn:feature_code":"PPL",
    "gn:name":"Man\u2019gy\u014fngdae-ri",
    "gn:population":0,
    "gn:timezone":"Asia/Pyongyang",
    "iso:country":"KP",
    "name:und_x_variant":[
        "Man\u2019gy\u014fngdae",
        "Mangyondae",
        "Mankeidai",
        "Man\u2019gy\u014fngdae-ri"
    ],
    "wof:name":"Man'gyongdae-ri",
    "wof:placetype":"locality"
},
  "geometry": {"coordinates":[125.66667,38.98333],"type":"Point"}
}