{
  "type": "Feature",
  "properties": {
    "gn:admin1_code":"0.0",
    "gn:asciiname":"Songhung-dong",
    "gn:cc2":"KP",
    "gn:country_code":"KP",
    "gn:dem":78,
    "gn:feature_class":"P",
    "gn:feature_code":"PPL",
    "gn:name":"Songh\u016dng-dong",
    "gn:population":0,
    "gn:timezone":"Asia/Pyongyang",
    "iso:country":"KP",
    "name:kor_x_preferred":[
        "\uc1a1\ud765\ub3d9"
    ],
    "name:und_x_variant":[
        "Songh\u016dng-ni",
        "Songh\u016dng-dong"
    ],
    "wof:name":"Songhung-dong",
    "wof:placetype":"locality"
},
  "geometry": {"coordinates":[127.41667,39.16667],"type":"Point"}
}