{
  "type": "Feature",
  "properties": {
    "gn:admin1_code":"6.0",
    "gn:admin2_code":"P'anmun-gun",
    "gn:asciiname":"Hwagong-ni",
    "gn:country_code":"KP",
    "gn:dem":42,
    "gn:feature_class":"P",
    "gn:feature_code":"PPL",
    "gn:name":"Hwagong-ni",
    "gn:population":0,
    "gn:timezone":"Asia/Pyongyang",
    "iso:country":"KP",
    "name:eng_x_preferred":[
        "Hwagong"
    ],
    "name:eng_x_variant":[
        "Hwagong-ni"
    ],
    "name:und_x_variant":[
        "Hwagong-nodongjagu",
        "Hwagong-ni"
    ],
    "wof:name":"Hwagong",
    "wof:placetype":"locality"
},
  "geometry": {"coordinates":[126.58528,37.84472],"type":"Point"}
}