{
  "type": "Feature",
  "properties": {
    "gn:admin1_code":"1.0",
    "gn:asciiname":"Sangbuji-dong",
    "gn:country_code":"KP",
    "gn:dem":397,
    "gn:feature_class":"P",
    "gn:feature_code":"PPL",
    "gn:name":"Sangbuji-dong",
    "gn:population":0,
    "gn:timezone":"Asia/Pyongyang",
    "iso:country":"KP",
    "name:kor_x_preferred":[
        "\uc0c1\ubd80\uc9c0\ub3d9"
    ],
    "wof:name":"Sangbuji-dong",
    "wof:placetype":"locality"
},
  "geometry": {"coordinates":[126.58216000000002,40.87394000000001],"type":"Point"}
}