{
  "type": "Feature",
  "properties": {
    "gn:admin1_code":"1.0",
    "gn:asciiname":"Osu-ri",
    "gn:country_code":"KP",
    "gn:dem":791,
    "gn:feature_class":"P",
    "gn:feature_code":"PPL",
    "gn:name":"Osu-ri",
    "gn:population":0,
    "gn:timezone":"Asia/Pyongyang",
    "iso:country":"KP",
    "name:und_x_variant":[
        "\uc624\uc218\ub9ac",
        "Osu-ri"
    ],
    "wof:name":"Osu-ri",
    "wof:placetype":"locality"
},
  "geometry": {"coordinates":[127.01778,41.69972],"type":"Point"}
}