{
  "type": "Feature",
  "properties": {
    "gn:admin1_code":"3.0",
    "gn:asciiname":"Chungbong-ni",
    "gn:country_code":"KP",
    "gn:dem":35,
    "gn:feature_class":"P",
    "gn:feature_code":"PPL",
    "gn:name":"Chungbong-ni",
    "gn:population":0,
    "gn:timezone":"Asia/Pyongyang",
    "iso:country":"KP",
    "name:und_x_variant":[
        "\uc911\ubd09\ub9ac",
        "Chungbong-ni"
    ],
    "wof:name":"Chungbong-ni",
    "wof:placetype":"locality"
},
  "geometry": {"coordinates":[127.39306000000001,39.87778],"type":"Point"}
}