{
  "type": "Feature",
  "properties": {
    "gn:admin1_code":"17.0",
    "gn:asciiname":"Chungsan-dong",
    "gn:country_code":"KP",
    "gn:dem":38,
    "gn:feature_class":"P",
    "gn:feature_code":"PPL",
    "gn:name":"Chungsan-dong",
    "gn:population":0,
    "gn:timezone":"Asia/Pyongyang",
    "iso:country":"KP",
    "name:und_x_variant":[
        "\uc911\uc0b0\ub3d9",
        "Chungsan-dong"
    ],
    "wof:name":"Chungsan-dong",
    "wof:placetype":"locality"
},
  "geometry": {"coordinates":[129.59138999999999,41.30694],"type":"Point"}
}