{
  "type": "Feature",
  "properties": {
    "gn:admin1_code":"3.0",
    "gn:asciiname":"Tokswalgwi",
    "gn:country_code":"KP",
    "gn:dem":186,
    "gn:feature_class":"P",
    "gn:feature_code":"PPL",
    "gn:name":"T\u014fkswalgwi",
    "gn:population":0,
    "gn:timezone":"Asia/Pyongyang",
    "iso:country":"KP",
    "name:und_x_variant":[
        "T\u014fkswalgwi",
        "\ub355\uc0b4\uadc0"
    ],
    "wof:name":"Tokswalgwi",
    "wof:placetype":"locality"
},
  "geometry": {"coordinates":[128.25691,40.3925],"type":"Point"}
}