{
  "type": "Feature",
  "properties": {
    "gn:admin1_code":"17.0",
    "gn:asciiname":"Ch'il-tong",
    "gn:country_code":"KP",
    "gn:dem":547,
    "gn:feature_class":"P",
    "gn:feature_code":"PPL",
    "gn:name":"Ch\u2019il-tong",
    "gn:population":0,
    "gn:timezone":"Asia/Pyongyang",
    "iso:country":"KP",
    "name:eng_x_preferred":[
        "Ch'il"
    ],
    "name:eng_x_variant":[
        "Ch'il-tong"
    ],
    "name:und_x_variant":[
        "\uce60\ub3d9",
        "Ch\u2019il-tong"
    ],
    "wof:name":"Ch'il",
    "wof:placetype":"locality"
},
  "geometry": {"coordinates":[129.32028,42.18306],"type":"Point"}
}