{
  "type": "Feature",
  "properties": {
    "gn:admin1_code":"15.0",
    "gn:asciiname":"Ryong-dong",
    "gn:country_code":"KP",
    "gn:dem":63,
    "gn:feature_class":"P",
    "gn:feature_code":"PPL",
    "gn:name":"Ryong-dong",
    "gn:population":0,
    "gn:timezone":"Asia/Pyongyang",
    "iso:country":"KP",
    "name:kor_x_preferred":[
        "\ub8e1\ub3d9"
    ],
    "name:und_x_variant":[
        "Yong-dong"
    ],
    "wof:name":"Ryong-dong",
    "wof:placetype":"locality"
},
  "geometry": {"coordinates":[125.94861000000002,39.63806],"type":"Point"}
}