{
  "type": "Feature",
  "properties": {
    "gn:admin1_code":"0.0",
    "gn:asciiname":"Kwangp'yong-dong",
    "gn:country_code":"KP",
    "gn:dem":20,
    "gn:feature_class":"P",
    "gn:feature_code":"PPL",
    "gn:name":"Kwangp\u2019y\u014fng-dong",
    "gn:population":0,
    "gn:timezone":"Asia/Pyongyang",
    "iso:country":"KP",
    "name:kor_x_preferred":[
        "\uad11\ud3c9\ub3d9"
    ],
    "name:und_x_variant":[
        "Kwangp\u2019y\u014fng-dong"
    ],
    "wof:name":"Kwangp'yong-dong",
    "wof:placetype":"locality"
},
  "geometry": {"coordinates":[125.11667,38.03333],"type":"Point"}
}