{
  "type": "Feature",
  "properties": {
    "gn:admin1_code":"15.0",
    "gn:asciiname":"Samyol-li",
    "gn:country_code":"KP",
    "gn:dem":175,
    "gn:feature_class":"P",
    "gn:feature_code":"PPL",
    "gn:name":"Samy\u014fl-li",
    "gn:population":0,
    "gn:timezone":"Asia/Pyongyang",
    "iso:country":"KP",
    "name:kor_x_preferred":[
        "\uc0bc\uc5f0\ub9ac"
    ],
    "name:und_x_variant":[
        "Samy\u014fl-li",
        "Samy\u014fn-ni"
    ],
    "wof:name":"Samyol-li",
    "wof:placetype":"locality"
},
  "geometry": {"coordinates":[126.36888999999999,39.76361],"type":"Point"}
}