{
  "type": "Feature",
  "properties": {
    "gn:admin1_code":"1.0",
    "gn:asciiname":"Namsang-ni",
    "gn:country_code":"KP",
    "gn:dem":191,
    "gn:feature_class":"P",
    "gn:feature_code":"PPL",
    "gn:name":"Namsang-ni",
    "gn:population":0,
    "gn:timezone":"Asia/Pyongyang",
    "iso:country":"KP",
    "name:und_x_variant":[
        "Namsan-dong",
        "\ub0a8\uc0c1\ub9ac",
        "Namsang-ni"
    ],
    "wof:name":"Namsang-ni",
    "wof:placetype":"locality"
},
  "geometry": {"coordinates":[126.11167,41.00972],"type":"Point"}
}