{
  "type": "Feature",
  "properties": {
    "gn:admin1_code":"11.0",
    "gn:asciiname":"Tolmari",
    "gn:country_code":"KP",
    "gn:dem":11,
    "gn:feature_class":"P",
    "gn:feature_code":"PPL",
    "gn:name":"Tolmari",
    "gn:population":0,
    "gn:timezone":"Asia/Pyongyang",
    "iso:country":"KP",
    "name:und_x_variant":[
        "Sandong-dong",
        "Tolmari"
    ],
    "wof:name":"Tolmari",
    "wof:placetype":"locality"
},
  "geometry": {"coordinates":[124.88333,39.73333],"type":"Point"}
}