{
  "type": "Feature",
  "properties": {
    "gn:admin1_code":"3.0",
    "gn:admin2_code":"Tanch'\u014fn-si",
    "gn:asciiname":"Chich'ojang",
    "gn:country_code":"KP",
    "gn:dem":1221,
    "gn:feature_class":"P",
    "gn:feature_code":"PPL",
    "gn:name":"Chich\u2019ojang",
    "gn:population":0,
    "gn:timezone":"Asia/Pyongyang",
    "iso:country":"KP",
    "name:und_x_variant":[
        "\uc9c0\ucd08\uc7a5",
        "Chich\u2019ojang"
    ],
    "wof:name":"Chich'ojang",
    "wof:placetype":"locality"
},
  "geometry": {"coordinates":[128.80444,40.99056],"type":"Point"}
}