{
  "type": "Feature",
  "properties": {
    "gn:admin1_code":"11.0",
    "gn:asciiname":"Sokpang-dong",
    "gn:country_code":"KP",
    "gn:dem":131,
    "gn:feature_class":"P",
    "gn:feature_code":"PPL",
    "gn:name":"S\u014fkpang-dong",
    "gn:population":0,
    "gn:timezone":"Asia/Pyongyang",
    "iso:country":"KP",
    "name:und_x_variant":[
        "\uc11d\ubc29\ub3d9",
        "S\u014fkpang-dong"
    ],
    "wof:name":"Sokpang-dong",
    "wof:placetype":"locality"
},
  "geometry": {"coordinates":[125.92028000000001,40.11861],"type":"Point"}
}