{
  "type": "Feature",
  "properties": {
    "gn:admin1_code":"1.0",
    "gn:asciiname":"Wolsung-ni",
    "gn:country_code":"KP",
    "gn:dem":344,
    "gn:feature_class":"P",
    "gn:feature_code":"PPL",
    "gn:name":"W\u014flsung-ni",
    "gn:population":0,
    "gn:timezone":"Asia/Pyongyang",
    "iso:country":"KP",
    "name:eng_x_preferred":[
        "Wolsung"
    ],
    "name:eng_x_variant":[
        "Wolsung-ni"
    ],
    "name:und_x_variant":[
        "\uc6d4\uc22d\ub9ac",
        "W\u014flsung-ni"
    ],
    "wof:name":"Wolsung",
    "wof:placetype":"locality"
},
  "geometry": {"coordinates":[125.73139,40.35139],"type":"Point"}
}