{
  "type": "Feature",
  "properties": {
    "gn:admin1_code":"3.0",
    "gn:asciiname":"Chiktong-nyong",
    "gn:country_code":"KP",
    "gn:dem":1098,
    "gn:feature_class":"P",
    "gn:feature_code":"PPL",
    "gn:name":"Chiktong-ny\u014fng",
    "gn:population":0,
    "gn:timezone":"Asia/Pyongyang",
    "iso:country":"KP",
    "name:und_x_variant":[
        "\uc9c1\ub3d9\ub839",
        "Chiktong-ny\u014fng"
    ],
    "wof:name":"Chiktong-nyong",
    "wof:placetype":"locality"
},
  "geometry": {"coordinates":[128.29861,40.61111],"type":"Point"}
}