{
  "type": "Feature",
  "properties": {
    "gn:admin1_code":"1.0",
    "gn:asciiname":"Wagal-li",
    "gn:country_code":"KP",
    "gn:dem":1126,
    "gn:feature_class":"P",
    "gn:feature_code":"PPL",
    "gn:name":"Wagal-li",
    "gn:population":0,
    "gn:timezone":"Asia/Pyongyang",
    "iso:country":"KP",
    "name:kor_x_preferred":[
        "\uc640\uac08\ub9ac"
    ],
    "wof:name":"Wagal-li",
    "wof:placetype":"locality"
},
  "geometry": {"coordinates":[127.11333,40.68056],"type":"Point"}
}