{
  "type": "Feature",
  "properties": {
    "gn:admin1_code":"17.0",
    "gn:asciiname":"Tongsang",
    "gn:country_code":"KP",
    "gn:dem":33,
    "gn:feature_class":"P",
    "gn:feature_code":"PPL",
    "gn:name":"Tongsang",
    "gn:population":0,
    "gn:timezone":"Asia/Pyongyang",
    "iso:country":"KP",
    "name:und_x_variant":[
        "\ub3d9\uc0c1",
        "Tongsang"
    ],
    "wof:name":"Tongsang",
    "wof:placetype":"locality"
},
  "geometry": {"coordinates":[130.20361,42.84639],"type":"Point"}
}