{
  "type": "Feature",
  "properties": {
    "gn:admin1_code":"6.0",
    "gn:asciiname":"Pongch'on-up",
    "gn:country_code":"KP",
    "gn:dem":57,
    "gn:feature_class":"P",
    "gn:feature_code":"PPL",
    "gn:name":"Pongch\u2019\u014fn-\u016dp",
    "gn:population":0,
    "gn:timezone":"Asia/Pyongyang",
    "iso:country":"KP",
    "name:und_x_variant":[
        "P\u2019y\u014fngch\u2019\u014fn-\u016dp",
        "Pongch\u2019\u014fn",
        "Onsei-ri",
        "Onj\u014fng-ni",
        "P\u2019y\u014fngch\u2019\u014fn",
        "Pongch\u2019\u014fn-\u016dp"
    ],
    "wof:name":"Pongch'on-up",
    "wof:placetype":"locality"
},
  "geometry": {"coordinates":[126.20471999999999,38.12389],"type":"Point"}
}