{
  "type": "Feature",
  "properties": {
    "gn:admin1_code":"17.0",
    "gn:asciiname":"Yongyangch'on",
    "gn:country_code":"KP",
    "gn:dem":63,
    "gn:feature_class":"P",
    "gn:feature_code":"PPL",
    "gn:name":"Y\u014fngyangch\u2019on",
    "gn:population":0,
    "gn:timezone":"Asia/Pyongyang",
    "iso:country":"KP",
    "name:und_x_variant":[
        "Eiy\u014d-son",
        "\uc601\uc591\ucd0c",
        "Y\u014fngyangch\u2019on"
    ],
    "wof:name":"Yongyangch'on",
    "wof:placetype":"locality"
},
  "geometry": {"coordinates":[129.19138999999998,40.82833],"type":"Point"}
}