{
  "type": "Feature",
  "properties": {
    "gn:admin1_code":"7.0",
    "gn:asciiname":"Yuch'on-dong",
    "gn:country_code":"KP",
    "gn:dem":98,
    "gn:feature_class":"P",
    "gn:feature_code":"PPL",
    "gn:name":"Yuch\u2019\u014fn-dong",
    "gn:population":0,
    "gn:timezone":"Asia/Pyongyang",
    "iso:country":"KP",
    "name:kor_x_preferred":[
        "\uc720\ucc9c\ub3d9"
    ],
    "name:kor_x_variant":[
        "Yuch\u2019\u014fn-dong"
    ],
    "wof:name":"Yuch'on-dong",
    "wof:placetype":"locality"
},
  "geometry": {"coordinates":[126.57333,38.52111],"type":"Point"}
}