{
  "type": "Feature",
  "properties": {
    "gn:admin1_code":"3.0",
    "gn:asciiname":"Subang-dong",
    "gn:country_code":"KP",
    "gn:dem":523,
    "gn:feature_class":"P",
    "gn:feature_code":"PPL",
    "gn:name":"Subang-dong",
    "gn:population":0,
    "gn:timezone":"Asia/Pyongyang",
    "iso:country":"KP",
    "name:und_x_variant":[
        "\uc218\ubc29\ub3d9",
        "Subang-dong"
    ],
    "wof:name":"Subang-dong",
    "wof:placetype":"locality"
},
  "geometry": {"coordinates":[126.69944,39.65667],"type":"Point"}
}