{
  "type": "Feature",
  "properties": {
    "gn:admin1_code":"3.0",
    "gn:asciiname":"Changjae-ri",
    "gn:country_code":"KP",
    "gn:dem":34,
    "gn:feature_class":"P",
    "gn:feature_code":"PPL",
    "gn:name":"Changjae-ri",
    "gn:population":0,
    "gn:timezone":"Asia/Pyongyang",
    "iso:country":"KP",
    "name:und_x_variant":[
        "\uc7a5\uc7ac\ub9ac",
        "Changjae-ri"
    ],
    "wof:name":"Changjae-ri",
    "wof:placetype":"locality"
},
  "geometry": {"coordinates":[127.37639,39.53472],"type":"Point"}
}