{
  "type": "Feature",
  "properties": {
    "gn:admin1_code":"17.0",
    "gn:asciiname":"P'alchin",
    "gn:country_code":"KP",
    "gn:dem":21,
    "gn:feature_class":"P",
    "gn:feature_code":"PPL",
    "gn:name":"P\u2019alchin",
    "gn:population":0,
    "gn:timezone":"Asia/Pyongyang",
    "iso:country":"KP",
    "name:und_x_variant":[
        "\ud314\uc9c4",
        "P\u2019alchin"
    ],
    "wof:name":"P'alchin",
    "wof:placetype":"locality"
},
  "geometry": {"coordinates":[130.06721999999999,42.07639],"type":"Point"}
}