{
  "type": "Feature",
  "properties": {
    "gn:admin1_code":"11.0",
    "gn:asciiname":"Won-mal",
    "gn:country_code":"KP",
    "gn:dem":88,
    "gn:feature_class":"P",
    "gn:feature_code":"PPL",
    "gn:name":"W\u014fn-mal",
    "gn:population":0,
    "gn:timezone":"Asia/Pyongyang",
    "iso:country":"KP",
    "wof:name":"Won-mal",
    "wof:placetype":"locality"
},
  "geometry": {"coordinates":[126.0975,39.94722],"type":"Point"}
}