{
  "type": "Feature",
  "properties": {
    "gn:admin1_code":"11.0",
    "gn:asciiname":"Ch'ongsong-ni",
    "gn:country_code":"KP",
    "gn:dem":18,
    "gn:feature_class":"P",
    "gn:feature_code":"PPL",
    "gn:name":"Ch\u2019ongsong-ni",
    "gn:population":0,
    "gn:timezone":"Asia/Pyongyang",
    "iso:country":"KP",
    "name:und_x_variant":[
        "Moksadae-dong",
        "Moksadae-ri",
        "Ch\u2019ongsong-ni"
    ],
    "wof:name":"Ch'ongsong-ni",
    "wof:placetype":"locality"
},
  "geometry": {"coordinates":[124.7775,39.78333],"type":"Point"}
}