{
  "type": "Feature",
  "properties": {
    "gn:admin1_code":"7.0",
    "gn:asciiname":"Nolbau-gol",
    "gn:country_code":"KP",
    "gn:dem":154,
    "gn:feature_class":"P",
    "gn:feature_code":"PPL",
    "gn:name":"N\u014flbau-gol",
    "gn:population":0,
    "gn:timezone":"Asia/Pyongyang",
    "iso:country":"KP",
    "wof:name":"Nolbau-gol",
    "wof:placetype":"locality"
},
  "geometry": {"coordinates":[125.90389,38.32139],"type":"Point"}
}