{
  "type": "Feature",
  "properties": {
    "gn:admin1_code":"17.0",
    "gn:asciiname":"Toksan",
    "gn:country_code":"KP",
    "gn:dem":27,
    "gn:feature_class":"P",
    "gn:feature_code":"PPL",
    "gn:name":"T\u014fksan",
    "gn:population":0,
    "gn:timezone":"Asia/Pyongyang",
    "iso:country":"KP",
    "name:und_x_variant":[
        "\ub355\uc0b0",
        "T\u014fksan"
    ],
    "wof:name":"Toksan",
    "wof:placetype":"locality"
},
  "geometry": {"coordinates":[129.57832999999999,41.57639],"type":"Point"}
}