{
  "type": "Feature",
  "properties": {
    "gn:admin1_code":"12.0",
    "gn:asciiname":"Soksang-dong",
    "gn:country_code":"KP",
    "gn:dem":105,
    "gn:feature_class":"P",
    "gn:feature_code":"PPL",
    "gn:name":"S\u014fksang-dong",
    "gn:population":0,
    "gn:timezone":"Asia/Pyongyang",
    "iso:country":"KP",
    "name:kor_x_preferred":[
        "\uc11d\uc0c1\ub3d9"
    ],
    "name:und_x_variant":[
        "S\u014fksang-dong",
        "Seoksangdong"
    ],
    "wof:name":"Soksang-dong",
    "wof:placetype":"locality"
},
  "geometry": {"coordinates":[125.8475,39.21167],"type":"Point"}
}