{
  "type": "Feature",
  "properties": {
    "gn:admin1_code":"7.0",
    "gn:asciiname":"Paegyang-dong",
    "gn:country_code":"KP",
    "gn:dem":139,
    "gn:feature_class":"P",
    "gn:feature_code":"PPL",
    "gn:name":"Paegyang-dong",
    "gn:population":0,
    "gn:timezone":"Asia/Pyongyang",
    "iso:country":"KP",
    "name:kor_x_preferred":[
        "\ubc31\uc591\ub3d9"
    ],
    "wof:name":"Paegyang-dong",
    "wof:placetype":"locality"
},
  "geometry": {"coordinates":[126.31610999999999,38.45278],"type":"Point"}
}