{
  "type": "Feature",
  "properties": {
    "gn:admin1_code":"9.0",
    "gn:asciiname":"Kaech'ol-li",
    "gn:country_code":"KP",
    "gn:dem":163,
    "gn:feature_class":"P",
    "gn:feature_code":"PPL",
    "gn:name":"Kaech\u2019\u014fl-li",
    "gn:population":0,
    "gn:timezone":"Asia/Pyongyang",
    "iso:country":"KP",
    "name:kor_x_preferred":[
        "\uac1c\ucc9c\ub9ac"
    ],
    "name:und_x_variant":[
        "Kaech\u2019\u014fn-ni",
        "Kaech\u2019\u014fl-li"
    ],
    "wof:name":"Kaech'ol-li",
    "wof:placetype":"locality"
},
  "geometry": {"coordinates":[126.88056,38.51333],"type":"Point"}
}