{
  "type": "Feature",
  "properties": {
    "gn:admin1_code":"6.0",
    "gn:asciiname":"Parunbong",
    "gn:country_code":"KP",
    "gn:dem":49,
    "gn:feature_class":"P",
    "gn:feature_code":"PPL",
    "gn:name":"Par\u016dnbong",
    "gn:population":0,
    "gn:timezone":"Asia/Pyongyang",
    "iso:country":"KP",
    "name:und_x_variant":[
        "\ubc1c\uc740\ubd09",
        "Par\u016dnbong"
    ],
    "wof:name":"Parunbong",
    "wof:placetype":"locality"
},
  "geometry": {"coordinates":[125.12944,37.9475],"type":"Point"}
}