{
  "type": "Feature",
  "properties": {
    "gn:admin1_code":"12.0",
    "gn:asciiname":"Munbal-li",
    "gn:country_code":"KP",
    "gn:dem":10,
    "gn:feature_class":"P",
    "gn:feature_code":"PPL",
    "gn:name":"Munbal-li",
    "gn:population":0,
    "gn:timezone":"Asia/Pyongyang",
    "iso:country":"KP",
    "name:kor_x_preferred":[
        "\ubb38\ubc1c\ub9ac"
    ],
    "name:und_x_variant":[
        "Munballi"
    ],
    "wof:name":"Munbal-li",
    "wof:placetype":"locality"
},
  "geometry": {"coordinates":[125.6579,38.97334],"type":"Point"}
}