{
  "type": "Feature",
  "properties": {
    "gn:admin1_code":"7.0",
    "gn:asciiname":"Sain'gwan",
    "gn:country_code":"KP",
    "gn:dem":112,
    "gn:feature_class":"P",
    "gn:feature_code":"PPL",
    "gn:name":"Sain\u2019gwan",
    "gn:population":0,
    "gn:timezone":"Asia/Pyongyang",
    "iso:country":"KP",
    "name:kor_x_preferred":[
        "\uc0ac\uc778\uad00"
    ],
    "name:und_x_variant":[
        "Sain\u2019gwan"
    ],
    "wof:name":"Sain'gwan",
    "wof:placetype":"locality"
},
  "geometry": {"coordinates":[125.79472,38.57583],"type":"Point"}
}