{
  "type": "Feature",
  "properties": {
    "gn:admin1_code":"11.0",
    "gn:asciiname":"Ch'ang-gol",
    "gn:country_code":"KP",
    "gn:dem":69,
    "gn:feature_class":"P",
    "gn:feature_code":"PPL",
    "gn:name":"Ch\u2019ang-gol",
    "gn:population":0,
    "gn:timezone":"Asia/Pyongyang",
    "iso:country":"KP",
    "name:und_x_variant":[
        "\ucc3d\uace8",
        "Ch\u2019ang-gol"
    ],
    "wof:name":"Ch'ang-gol",
    "wof:placetype":"locality"
},
  "geometry": {"coordinates":[124.58472,40.0825],"type":"Point"}
}