{
  "type": "Feature",
  "properties": {
    "gn:admin1_code":"17.0",
    "gn:asciiname":"Changsadukch'on",
    "gn:country_code":"KP",
    "gn:dem":141,
    "gn:feature_class":"P",
    "gn:feature_code":"PPL",
    "gn:name":"Changsad\u016dkch\u2019on",
    "gn:population":0,
    "gn:timezone":"Asia/Pyongyang",
    "iso:country":"KP",
    "name:und_x_variant":[
        "Changsad\u014fkch\u2019on",
        "\uc7a5\uc0ac\ub4dd\ucd0c",
        "Changsad\u016dk",
        "Changsad\u016dkch\u2019on"
    ],
    "wof:name":"Changsadukch'on",
    "wof:placetype":"locality"
},
  "geometry": {"coordinates":[130.06583000000001,42.92667],"type":"Point"}
}