{
  "type": "Feature",
  "properties": {
    "gn:admin1_code":"6.0",
    "gn:asciiname":"Kujong-dong",
    "gn:country_code":"KP",
    "gn:dem":8,
    "gn:feature_class":"P",
    "gn:feature_code":"PPL",
    "gn:name":"Kuj\u014fng-dong",
    "gn:population":0,
    "gn:timezone":"Asia/Pyongyang",
    "iso:country":"KP",
    "name:kor_x_preferred":[
        "\uad6c\uc815\ub3d9"
    ],
    "name:und_x_variant":[
        "Kuj\u014fng-dong"
    ],
    "wof:name":"Kujong-dong",
    "wof:placetype":"locality"
},
  "geometry": {"coordinates":[125.63472,38.04111],"type":"Point"}
}