{
  "type": "Feature",
  "properties": {
    "gn:admin1_code":"3.0",
    "gn:asciiname":"Sinsang-ni",
    "gn:country_code":"KP",
    "gn:dem":51,
    "gn:feature_class":"P",
    "gn:feature_code":"PPL",
    "gn:name":"Sinsang-ni",
    "gn:population":0,
    "gn:timezone":"Asia/Pyongyang",
    "iso:country":"KP",
    "name:und_x_variant":[
        "\uc2e0\uc0c1\ub9ac"
    ],
    "wof:name":"Sinsang-ni",
    "wof:placetype":"locality"
},
  "geometry": {"coordinates":[128.37549999999999,40.20234],"type":"Point"}
}