{
  "type": "Feature",
  "properties": {
    "gn:admin1_code":"13.0",
    "gn:asciiname":"Hagarim",
    "gn:country_code":"KP",
    "gn:dem":837,
    "gn:feature_class":"P",
    "gn:feature_code":"PPL",
    "gn:name":"Hagarim",
    "gn:population":0,
    "gn:timezone":"Asia/Pyongyang",
    "iso:country":"KP",
    "name:kor_x_preferred":[
        "\ud558\uac00\ub9bc"
    ],
    "wof:name":"Hagarim",
    "wof:placetype":"locality"
},
  "geometry": {"coordinates":[128.23556000000002,41.03139],"type":"Point"}
}