{
  "type": "Feature",
  "properties": {
    "gn:admin1_code":"1.0",
    "gn:asciiname":"Hwajol-li",
    "gn:cc2":"KP",
    "gn:country_code":"KP",
    "gn:dem":359,
    "gn:feature_class":"P",
    "gn:feature_code":"PPL",
    "gn:name":"Hwaj\u014fl-li",
    "gn:population":0,
    "gn:timezone":"Asia/Pyongyang",
    "iso:country":"KP",
    "name:und_x_variant":[
        "Hwaj\u014fn-ni",
        "Hwaj\u014fn-dong",
        "\ud654\uc804\ub9ac",
        "Hwaj\u014fl-li"
    ],
    "wof:name":"Hwajol-li",
    "wof:placetype":"locality"
},
  "geometry": {"coordinates":[126.62389,41.48944],"type":"Point"}
}