{
  "type": "Feature",
  "properties": {
    "gn:admin1_code":"17.0",
    "gn:asciiname":"Samp'och'on",
    "gn:country_code":"KP",
    "gn:dem":273,
    "gn:feature_class":"P",
    "gn:feature_code":"PPL",
    "gn:name":"Samp\u2019och\u2019on",
    "gn:population":0,
    "gn:timezone":"Asia/Pyongyang",
    "iso:country":"KP",
    "name:und_x_variant":[
        "\uc0bc\ud3ec\ucd0c",
        "Samp\u2019och\u2019on"
    ],
    "wof:name":"Samp'och'on",
    "wof:placetype":"locality"
},
  "geometry": {"coordinates":[129.07639,40.65861],"type":"Point"}
}