{
  "type": "Feature",
  "properties": {
    "gn:admin1_code":"3.0",
    "gn:asciiname":"Kiamniha-ch'on",
    "gn:country_code":"KP",
    "gn:dem":17,
    "gn:feature_class":"P",
    "gn:feature_code":"PPL",
    "gn:name":"Kiamniha-ch\u2019on",
    "gn:population":0,
    "gn:timezone":"Asia/Pyongyang",
    "iso:country":"KP",
    "name:und_x_variant":[
        "Kigan-ri-Kason",
        "\uae30\uc554\ub9ac\ud558\ucd0c",
        "Kiamniha-ch\u2019on"
    ],
    "wof:name":"Kiamniha-ch'on",
    "wof:placetype":"locality"
},
  "geometry": {"coordinates":[128.80582999999999,40.36417],"type":"Point"}
}