{
  "type": "Feature",
  "properties": {
    "gn:admin1_code":"3.0",
    "gn:asciiname":"Songjong-ni",
    "gn:country_code":"KP",
    "gn:dem":3,
    "gn:feature_class":"P",
    "gn:feature_code":"PPL",
    "gn:name":"Songj\u014fng-ni",
    "gn:population":0,
    "gn:timezone":"Asia/Pyongyang",
    "iso:country":"KP",
    "name:und_x_variant":[
        "Sh\u014dtan-ri",
        "Songdon-ni",
        "Songdan-ni",
        "Songj\u014fng-ni",
        "\uc1a1\uc815\ub9ac"
    ],
    "wof:name":"Songjong-ni",
    "wof:placetype":"locality"
},
  "geometry": {"coordinates":[128.61968999999999,40.30584],"type":"Point"}
}