{
  "type": "Feature",
  "properties": {
    "gn:admin1_code":"9.0",
    "gn:asciiname":"Hoeu",
    "gn:country_code":"KP",
    "gn:dem":275,
    "gn:feature_class":"P",
    "gn:feature_code":"PPL",
    "gn:name":"Hoeu",
    "gn:population":0,
    "gn:timezone":"Asia/Pyongyang",
    "iso:country":"KP",
    "name:kor_x_preferred":[
        "\ud68c\uc6b0"
    ],
    "wof:name":"Hoeu",
    "wof:placetype":"locality"
},
  "geometry": {"coordinates":[127.51667,38.31667],"type":"Point"}
}