{
  "type": "Feature",
  "properties": {
    "gn:admin1_code":"6.0",
    "gn:admin2_code":"Kaes\u014fng-si",
    "gn:asciiname":"Yorum-ni",
    "gn:country_code":"KP",
    "gn:dem":84,
    "gn:feature_class":"P",
    "gn:feature_code":"PPL",
    "gn:name":"Y\u014fr\u016dm-ni",
    "gn:population":0,
    "gn:timezone":"Asia/Pyongyang",
    "iso:country":"KP",
    "wof:name":"Yorum-ni",
    "wof:placetype":"locality"
},
  "geometry": {"coordinates":[126.52278,37.97889],"type":"Point"}
}