{
  "type": "Feature",
  "properties": {
    "gn:admin1_code":"7.0",
    "gn:asciiname":"Umuran",
    "gn:country_code":"KP",
    "gn:dem":210,
    "gn:feature_class":"P",
    "gn:feature_code":"PPL",
    "gn:name":"Umuran",
    "gn:population":0,
    "gn:timezone":"Asia/Pyongyang",
    "iso:country":"KP",
    "name:kor_x_preferred":[
        "\uc6b0\ubb3c\uc548"
    ],
    "wof:name":"Umuran",
    "wof:placetype":"locality"
},
  "geometry": {"coordinates":[126.57361000000002,38.67056],"type":"Point"}
}