{
  "type": "Feature",
  "properties": {
    "gn:admin1_code":"7.0",
    "gn:asciiname":"Kulmol",
    "gn:country_code":"KP",
    "gn:dem":232,
    "gn:feature_class":"P",
    "gn:feature_code":"PPL",
    "gn:name":"Kulmol",
    "gn:population":0,
    "gn:timezone":"Asia/Pyongyang",
    "iso:country":"KP",
    "wof:name":"Kulmol",
    "wof:placetype":"locality"
},
  "geometry": {"coordinates":[126.17167000000001,38.29528],"type":"Point"}
}