{
  "type": "Feature",
  "properties": {
    "gn:admin1_code":"17.0",
    "gn:asciiname":"Todok-tong",
    "gn:country_code":"KP",
    "gn:dem":40,
    "gn:feature_class":"P",
    "gn:feature_code":"PPL",
    "gn:name":"Tod\u014fk-tong",
    "gn:population":0,
    "gn:timezone":"Asia/Pyongyang",
    "iso:country":"KP",
    "name:eng_x_preferred":[
        "Todok"
    ],
    "name:eng_x_variant":[
        "Todok-tong"
    ],
    "name:und_x_variant":[
        "\ub3c4\ub355\ub3d9",
        "Tod\u014fk-tong"
    ],
    "wof:name":"Todok",
    "wof:placetype":"locality"
},
  "geometry": {"coordinates":[130.19139000000001,42.80722],"type":"Point"}
}