{
  "type": "Feature",
  "properties": {
    "gn:admin1_code":"17.0",
    "gn:asciiname":"Sonamsok-tong",
    "gn:country_code":"KP",
    "gn:dem":668,
    "gn:feature_class":"P",
    "gn:feature_code":"PPL",
    "gn:name":"Sonams\u014fk-tong",
    "gn:population":0,
    "gn:timezone":"Asia/Pyongyang",
    "iso:country":"KP",
    "name:und_x_variant":[
        "Sonams\u014fk-tong",
        "\uc11c\ub0a8\uc11d\ub3d9"
    ],
    "wof:name":"Sonamsok-tong",
    "wof:placetype":"locality"
},
  "geometry": {"coordinates":[129.26561000000001,41.34394],"type":"Point"}
}