{
  "type": "Feature",
  "properties": {
    "gn:admin1_code":"1.0",
    "gn:asciiname":"Kipun'gae",
    "gn:country_code":"KP",
    "gn:dem":394,
    "gn:feature_class":"P",
    "gn:feature_code":"PPL",
    "gn:name":"Kip\u016dn\u2019gae",
    "gn:population":0,
    "gn:timezone":"Asia/Pyongyang",
    "iso:country":"KP",
    "name:kor_x_preferred":[
        "Kip\u016dn\u2019gae"
    ],
    "name:kor_x_variant":[
        "\uae4a\uc740\uac1c"
    ],
    "wof:name":"Kipun'gae",
    "wof:placetype":"locality"
},
  "geometry": {"coordinates":[126.55652000000001,40.80645],"type":"Point"}
}