{
  "type": "Feature",
  "properties": {
    "gn:admin1_code":"0.0",
    "gn:asciiname":"Sajamori",
    "gn:cc2":"KP",
    "gn:country_code":"KP",
    "gn:dem":8,
    "gn:feature_class":"P",
    "gn:feature_code":"PPL",
    "gn:name":"Sajam\u014fri",
    "gn:population":0,
    "gn:timezone":"Asia/Pyongyang",
    "iso:country":"KP",
    "name:kor_x_preferred":[
        "\uc0ac\uc790\uba38\ub9ac"
    ],
    "name:und_x_variant":[
        "Sadu",
        "Sajam\u014fri"
    ],
    "wof:name":"Sajamori",
    "wof:placetype":"locality"
},
  "geometry": {"coordinates":[125.68333,38.71667],"type":"Point"}
}