{
  "type": "Feature",
  "properties": {
    "gn:admin1_code":"7.0",
    "gn:asciiname":"Okhyol-li",
    "gn:country_code":"KP",
    "gn:dem":124,
    "gn:feature_class":"P",
    "gn:feature_code":"PPL",
    "gn:name":"Okhy\u014fl-li",
    "gn:population":0,
    "gn:timezone":"Asia/Pyongyang",
    "iso:country":"KP",
    "name:kor_x_preferred":[
        "\uc625\ud604\ub9ac"
    ],
    "name:kor_x_variant":[
        "Okhy\u014fl-li"
    ],
    "wof:name":"Okhyol-li",
    "wof:placetype":"locality"
},
  "geometry": {"coordinates":[126.33750000000001,38.67639000000001],"type":"Point"}
}