{
  "type": "Feature",
  "properties": {
    "gn:admin1_code":"3.0",
    "gn:asciiname":"Odaep'yong",
    "gn:country_code":"KP",
    "gn:dem":249,
    "gn:feature_class":"P",
    "gn:feature_code":"PPL",
    "gn:name":"\u014edaep\u2019y\u014fng",
    "gn:population":0,
    "gn:timezone":"Asia/Pyongyang",
    "iso:country":"KP",
    "name:und_x_variant":[
        "\u014edaep\u2019y\u014fng",
        "\uc624\ub300\ud3c9"
    ],
    "wof:name":"Odaep'yong",
    "wof:placetype":"locality"
},
  "geometry": {"coordinates":[128.15998999999999,40.17505],"type":"Point"}
}