{
  "type": "Feature",
  "properties": {
    "gn:admin1_code":"11.0",
    "gn:asciiname":"Kajwadongsangch'am",
    "gn:country_code":"KP",
    "gn:dem":162,
    "gn:feature_class":"P",
    "gn:feature_code":"PPL",
    "gn:name":"Kajwadongsangch\u2019am",
    "gn:population":0,
    "gn:timezone":"Asia/Pyongyang",
    "iso:country":"KP",
    "name:und_x_variant":[
        "\uac00\uc88c\ub3d9\uc0c1\ucc38",
        "Kajwadongsangch\u2019am"
    ],
    "wof:name":"Kajwadongsangch'am",
    "wof:placetype":"locality"
},
  "geometry": {"coordinates":[126.02528,40.01167],"type":"Point"}
}