{
  "type": "Feature",
  "properties": {
    "gn:admin1_code":"13.0",
    "gn:admin2_code":"Paegam-gun",
    "gn:asciiname":"Hagyongp'yong",
    "gn:country_code":"KP",
    "gn:dem":910,
    "gn:feature_class":"P",
    "gn:feature_code":"PPL",
    "gn:name":"Hagy\u014fngp\u2019y\u014fng",
    "gn:population":0,
    "gn:timezone":"Asia/Pyongyang",
    "iso:country":"KP",
    "name:kor_x_preferred":[
        "\ud558\uacbd\ud3c9"
    ],
    "name:und_x_variant":[
        "Hagy\u014fngp\u2019y\u014fng"
    ],
    "wof:name":"Hagyongp'yong",
    "wof:placetype":"locality"
},
  "geometry": {"coordinates":[128.84361000000001,41.7825],"type":"Point"}
}