{
  "type": "Feature",
  "properties": {
    "gn:admin1_code":"0.0",
    "gn:asciiname":"Songha-ri",
    "gn:country_code":"KP",
    "gn:dem":39,
    "gn:feature_class":"P",
    "gn:feature_code":"PPL",
    "gn:name":"Songha-ri",
    "gn:population":0,
    "gn:timezone":"Asia/Pyongyang",
    "iso:country":"KP",
    "name:kor_x_preferred":[
        "\uc1a1\ud558\ub9ac"
    ],
    "wof:name":"Songha-ri",
    "wof:placetype":"locality"
},
  "geometry": {"coordinates":[125.45,39.88333],"type":"Point"}
}