{
  "type": "Feature",
  "properties": {
    "gn:admin1_code":"3.0",
    "gn:asciiname":"Moraeso",
    "gn:country_code":"KP",
    "gn:dem":1024,
    "gn:feature_class":"P",
    "gn:feature_code":"PPL",
    "gn:name":"Moraeso",
    "gn:population":0,
    "gn:timezone":"Asia/Pyongyang",
    "iso:country":"KP",
    "name:kor_x_preferred":[
        "\ubaa8\ub798\uc18c"
    ],
    "wof:name":"Moraeso",
    "wof:placetype":"locality"
},
  "geometry": {"coordinates":[127.25667,40.69722],"type":"Point"}
}