{
  "type": "Feature",
  "properties": {
    "gn:admin1_code":"7.0",
    "gn:asciiname":"Naejangha",
    "gn:country_code":"KP",
    "gn:dem":4,
    "gn:feature_class":"P",
    "gn:feature_code":"PPL",
    "gn:name":"Naejangha",
    "gn:population":0,
    "gn:timezone":"Asia/Pyongyang",
    "iso:country":"KP",
    "name:kor_x_preferred":[
        "\ub0b4\uc7a5\ud558"
    ],
    "wof:name":"Naejangha",
    "wof:placetype":"locality"
},
  "geometry": {"coordinates":[125.67083,38.505],"type":"Point"}
}