{
  "type": "Feature",
  "properties": {
    "gn:admin1_code":"7.0",
    "gn:asciiname":"Chayang-dong",
    "gn:country_code":"KP",
    "gn:dem":32,
    "gn:feature_class":"P",
    "gn:feature_code":"PPL",
    "gn:name":"Chayang-dong",
    "gn:population":0,
    "gn:timezone":"Asia/Pyongyang",
    "iso:country":"KP",
    "name:und_x_variant":[
        "\uc790\uc591\ub3d9",
        "Chayang-dong"
    ],
    "wof:name":"Chayang-dong",
    "wof:placetype":"locality"
},
  "geometry": {"coordinates":[126.5175,38.25],"type":"Point"}
}