{
  "type": "Feature",
  "properties": {
    "gn:admin1_code":"15.0",
    "gn:asciiname":"Kahung-ni",
    "gn:country_code":"KP",
    "gn:dem":61,
    "gn:feature_class":"P",
    "gn:feature_code":"PPL",
    "gn:name":"Kah\u016dng-ni",
    "gn:population":0,
    "gn:timezone":"Asia/Pyongyang",
    "iso:country":"KP",
    "name:eng_x_preferred":[
        "Kahung"
    ],
    "name:eng_x_variant":[
        "Kahung-ni"
    ],
    "name:und_x_variant":[
        "\uac00\ud765\ub9ac",
        "Kah\u016dng-ni"
    ],
    "wof:name":"Kahung",
    "wof:placetype":"locality"
},
  "geometry": {"coordinates":[125.35805999999999,38.97194],"type":"Point"}
}