{
  "type": "Feature",
  "properties": {
    "gn:admin1_code":"1.0",
    "gn:asciiname":"Songgyoch'am",
    "gn:country_code":"KP",
    "gn:dem":186,
    "gn:feature_class":"P",
    "gn:feature_code":"PPL",
    "gn:name":"S\u014fnggyoch\u2019am",
    "gn:population":0,
    "gn:timezone":"Asia/Pyongyang",
    "iso:country":"KP",
    "name:und_x_variant":[
        "\uc131\uad50\ucc38",
        "S\u014fnggyoch\u2019am"
    ],
    "wof:name":"Songgyoch'am",
    "wof:placetype":"locality"
},
  "geometry": {"coordinates":[126.30722,40.10917],"type":"Point"}
}