{
  "type": "Feature",
  "properties": {
    "gn:admin1_code":"3.0",
    "gn:asciiname":"Songbung-ni",
    "gn:country_code":"KP",
    "gn:dem":32,
    "gn:feature_class":"P",
    "gn:feature_code":"PPL",
    "gn:name":"S\u014fngbung-ni",
    "gn:population":0,
    "gn:timezone":"Asia/Pyongyang",
    "iso:country":"KP",
    "name:und_x_variant":[
        "\uc131\ubd81\ub9ac",
        "S\u014fngbung-ni"
    ],
    "wof:name":"Songbung-ni",
    "wof:placetype":"locality"
},
  "geometry": {"coordinates":[127.21333,39.53722],"type":"Point"}
}