{
  "type": "Feature",
  "properties": {
    "gn:admin1_code":"12.0",
    "gn:admin2_code":"Kangdong-gun",
    "gn:asciiname":"Munwang-dong",
    "gn:country_code":"KP",
    "gn:dem":80,
    "gn:feature_class":"P",
    "gn:feature_code":"PPL",
    "gn:name":"Munwang-dong",
    "gn:population":0,
    "gn:timezone":"Asia/Pyongyang",
    "iso:country":"KP",
    "name:kor_x_preferred":[
        "\ubb38\uc655\ub3d9"
    ],
    "name:und_x_variant":[
        "Munwang-ni",
        "Munwangdong"
    ],
    "wof:name":"Munwang-dong",
    "wof:placetype":"locality"
},
  "geometry": {"coordinates":[126.05392000000001,39.17837],"type":"Point"}
}