{
  "type": "Feature",
  "properties": {
    "gn:admin1_code":"9.0",
    "gn:asciiname":"Yok-kol",
    "gn:country_code":"KP",
    "gn:dem":358,
    "gn:feature_class":"P",
    "gn:feature_code":"PPL",
    "gn:name":"Yok-kol",
    "gn:population":0,
    "gn:timezone":"Asia/Pyongyang",
    "iso:country":"KP",
    "name:kor_x_preferred":[
        "\uc6a7\uace8"
    ],
    "wof:name":"Yok-kol",
    "wof:placetype":"locality"
},
  "geometry": {"coordinates":[126.82444,38.63722],"type":"Point"}
}