{
  "type": "Feature",
  "properties": {
    "gn:admin1_code":"6.0",
    "gn:asciiname":"Tongch'ongsok",
    "gn:country_code":"KP",
    "gn:dem":12,
    "gn:feature_class":"P",
    "gn:feature_code":"PPL",
    "gn:name":"Tongch\u2019\u014fngs\u014fk",
    "gn:population":0,
    "gn:timezone":"Asia/Pyongyang",
    "iso:country":"KP",
    "name:kor_x_preferred":[
        "\ub3d9\uccad\uc11d"
    ],
    "name:kor_x_variant":[
        "Tongch\u2019\u014fngs\u014fk"
    ],
    "name:und_x_variant":[
        "Ry\u016bgan-ri",
        "T\u014dseiseki",
        "Yongam-ni"
    ],
    "wof:name":"Tongch'ongsok",
    "wof:placetype":"locality"
},
  "geometry": {"coordinates":[125.06944,37.97722],"type":"Point"}
}