{
  "type": "Feature",
  "properties": {
    "gn:admin1_code":"11.0",
    "gn:asciiname":"Tongjak-kol",
    "gn:country_code":"KP",
    "gn:dem":104,
    "gn:feature_class":"P",
    "gn:feature_code":"PPL",
    "gn:name":"Tongjak-kol",
    "gn:population":0,
    "gn:timezone":"Asia/Pyongyang",
    "iso:country":"KP",
    "name:und_x_variant":[
        "\ub3d9\uc791\uace8",
        "Tongjak-kol"
    ],
    "wof:name":"Tongjak-kol",
    "wof:placetype":"locality"
},
  "geometry": {"coordinates":[124.65222,40.1425],"type":"Point"}
}