{
  "type": "Feature",
  "properties": {
    "gn:admin1_code":"12.0",
    "gn:asciiname":"Munam-ni",
    "gn:country_code":"KP",
    "gn:dem":17,
    "gn:feature_class":"P",
    "gn:feature_code":"PPL",
    "gn:name":"Munam-ni",
    "gn:population":0,
    "gn:timezone":"Asia/Pyongyang",
    "iso:country":"KP",
    "name:kor_x_preferred":[
        "\ubb38\uc554\ub9ac"
    ],
    "name:und_x_variant":[
        "Munamni"
    ],
    "wof:name":"Munam-ni",
    "wof:placetype":"locality"
},
  "geometry": {"coordinates":[125.61417,38.86917],"type":"Point"}
}