{
  "type": "Feature",
  "properties": {
    "gn:admin1_code":"6.0",
    "gn:asciiname":"Songch'on-dong",
    "gn:country_code":"KP",
    "gn:dem":70,
    "gn:feature_class":"P",
    "gn:feature_code":"PPL",
    "gn:name":"Songch\u2019on-dong",
    "gn:population":0,
    "gn:timezone":"Asia/Pyongyang",
    "iso:country":"KP",
    "wof:name":"Songch'on-dong",
    "wof:placetype":"locality"
},
  "geometry": {"coordinates":[125.57722,38.10278],"type":"Point"}
}