{
  "type": "Feature",
  "properties": {
    "gn:admin1_code":"13.0",
    "gn:asciiname":"Saduk-ch'on",
    "gn:country_code":"KP",
    "gn:dem":1195,
    "gn:feature_class":"P",
    "gn:feature_code":"PPL",
    "gn:name":"Sad\u016dk-ch\u2019on",
    "gn:population":0,
    "gn:timezone":"Asia/Pyongyang",
    "iso:country":"KP",
    "name:und_x_variant":[
        "\uc0ac\ub4dd\ucd0c",
        "Sad\u016dk-ch\u2019on"
    ],
    "wof:name":"Saduk-ch'on",
    "wof:placetype":"locality"
},
  "geometry": {"coordinates":[128.20917,40.64167],"type":"Point"}
}