{
  "type": "Feature",
  "properties": {
    "gn:admin1_code":"3.0",
    "gn:asciiname":"Ogujang-ni",
    "gn:country_code":"KP",
    "gn:dem":689,
    "gn:feature_class":"P",
    "gn:feature_code":"PPL",
    "gn:name":"\u014egujang-ni",
    "gn:population":0,
    "gn:timezone":"Asia/Pyongyang",
    "iso:country":"KP",
    "name:und_x_variant":[
        "\uc5b4\uad6c\uc7a5\ub9ac",
        "\u014egujang-ni"
    ],
    "wof:name":"Ogujang-ni",
    "wof:placetype":"locality"
},
  "geometry": {"coordinates":[128.52028000000001,40.86222],"type":"Point"}
}