{
  "type": "Feature",
  "properties": {
    "gn:admin1_code":"6.0",
    "gn:asciiname":"Hao-dong",
    "gn:country_code":"KP",
    "gn:dem":106,
    "gn:feature_class":"P",
    "gn:feature_code":"PPL",
    "gn:name":"Ha\u014f-dong",
    "gn:population":0,
    "gn:timezone":"Asia/Pyongyang",
    "iso:country":"KP",
    "name:kor_x_preferred":[
        "\ud558\uc5b4\ub3d9"
    ],
    "name:und_x_variant":[
        "Ha\u014f-dong"
    ],
    "wof:name":"Hao-dong",
    "wof:placetype":"locality"
},
  "geometry": {"coordinates":[125.67806000000002,38.24472],"type":"Point"}
}