{
  "type": "Feature",
  "properties": {
    "gn:admin1_code":"15.0",
    "gn:admin2_code":"T\u014fkch\u2019\u014fn-si",
    "gn:asciiname":"Chagun-gol",
    "gn:country_code":"KP",
    "gn:dem":271,
    "gn:feature_class":"P",
    "gn:feature_code":"PPL",
    "gn:name":"Chag\u016dn-gol",
    "gn:population":0,
    "gn:timezone":"Asia/Pyongyang",
    "iso:country":"KP",
    "wof:name":"Chagun-gol",
    "wof:placetype":"locality"
},
  "geometry": {"coordinates":[126.19944,39.71167],"type":"Point"}
}