{
  "type": "Feature",
  "properties": {
    "gn:admin1_code":"6.0",
    "gn:asciiname":"Kusok-tong",
    "gn:country_code":"KP",
    "gn:dem":82,
    "gn:feature_class":"P",
    "gn:feature_code":"PPL",
    "gn:name":"Kus\u014fk-tong",
    "gn:population":0,
    "gn:timezone":"Asia/Pyongyang",
    "iso:country":"KP",
    "name:und_x_variant":[
        "\uad6c\uc11d\ub3d9",
        "Kus\u014fk-tong"
    ],
    "wof:name":"Kusok-tong",
    "wof:placetype":"locality"
},
  "geometry": {"coordinates":[125.12333,38.15472000000001],"type":"Point"}
}