{
  "type": "Feature",
  "properties": {
    "gn:admin1_code":"7.0",
    "gn:asciiname":"Chongdong-ni",
    "gn:country_code":"KP",
    "gn:dem":29,
    "gn:feature_class":"P",
    "gn:feature_code":"PPL",
    "gn:name":"Ch\u014fngdong-ni",
    "gn:population":0,
    "gn:timezone":"Asia/Pyongyang",
    "iso:country":"KP",
    "name:eng_x_preferred":[
        "Chongdong"
    ],
    "name:eng_x_variant":[
        "Chongdong-ni"
    ],
    "name:kor_x_preferred":[
        "\uc815\ub3d9\ub9ac"
    ],
    "name:kor_x_variant":[
        "Ch\u014fngdong-ni"
    ],
    "wof:name":"Chongdong",
    "wof:placetype":"locality"
},
  "geometry": {"coordinates":[125.50722,38.61333],"type":"Point"}
}