{
  "type": "Feature",
  "properties": {
    "gn:admin1_code":"3.0",
    "gn:admin2_code":"Kow\u014fn-gun",
    "gn:asciiname":"Hada-ri",
    "gn:country_code":"KP",
    "gn:dem":18,
    "gn:feature_class":"P",
    "gn:feature_code":"PPL",
    "gn:name":"Hada-ri",
    "gn:population":0,
    "gn:timezone":"Asia/Pyongyang",
    "iso:country":"KP",
    "name:und_x_variant":[
        "\ud558\ub2e4\ub9ac"
    ],
    "wof:name":"Hada-ri",
    "wof:placetype":"locality"
},
  "geometry": {"coordinates":[127.21666999999999,39.42028],"type":"Point"}
}