{
  "type": "Feature",
  "properties": {
    "gn:admin1_code":"1.0",
    "gn:asciiname":"Kujungyong-ni",
    "gn:cc2":"KP",
    "gn:country_code":"KP",
    "gn:dem":313,
    "gn:feature_class":"P",
    "gn:feature_code":"PPL",
    "gn:name":"Kujungy\u014fng-ni",
    "gn:population":0,
    "gn:timezone":"Asia/Pyongyang",
    "iso:country":"KP",
    "name:und_x_variant":[
        "Kujungy\u014fng",
        "\uad6c\uc911\uc601\ub9ac",
        "Kujungy\u014fng-ni"
    ],
    "wof:name":"Kujungyong-ni",
    "wof:placetype":"locality"
},
  "geometry": {"coordinates":[126.60472,41.38472],"type":"Point"}
}