{
  "type": "Feature",
  "properties": {
    "gn:admin1_code":"7.0",
    "gn:asciiname":"Nuro-ri",
    "gn:country_code":"KP",
    "gn:dem":60,
    "gn:feature_class":"P",
    "gn:feature_code":"PPL",
    "gn:name":"N\u016dro-ri",
    "gn:population":0,
    "gn:timezone":"Asia/Pyongyang",
    "iso:country":"KP",
    "name:kor_x_preferred":[
        "\ub290\ub85c\ub9ac"
    ],
    "name:kor_x_variant":[
        "N\u016dro-ri"
    ],
    "wof:name":"Nuro-ri",
    "wof:placetype":"locality"
},
  "geometry": {"coordinates":[126.50888999999999,38.465],"type":"Point"}
}