{
  "type": "Feature",
  "properties": {
    "gn:admin1_code":"15.0",
    "gn:asciiname":"Ch'onggye",
    "gn:country_code":"KP",
    "gn:dem":275,
    "gn:feature_class":"P",
    "gn:feature_code":"PPL",
    "gn:name":"Ch\u2019\u014fnggye",
    "gn:population":0,
    "gn:timezone":"Asia/Pyongyang",
    "iso:country":"KP",
    "name:kor_x_preferred":[
        "\uccad\uacc4"
    ],
    "name:kor_x_variant":[
        "Ch\u2019\u014fnggye"
    ],
    "wof:name":"Ch'onggye",
    "wof:placetype":"locality"
},
  "geometry": {"coordinates":[126.41249999999999,38.95889],"type":"Point"}
}