{
  "type": "Feature",
  "properties": {
    "gn:admin1_code":"3.0",
    "gn:asciiname":"P'ungdong-ni",
    "gn:country_code":"KP",
    "gn:dem":38,
    "gn:feature_class":"P",
    "gn:feature_code":"PPL",
    "gn:name":"P\u2019ungdong-ni",
    "gn:population":0,
    "gn:timezone":"Asia/Pyongyang",
    "iso:country":"KP",
    "name:eng_x_preferred":[
        "P'ungdong"
    ],
    "name:eng_x_variant":[
        "P'ungdong-ni"
    ],
    "name:und_x_variant":[
        "\ud48d\ub3d9\ub9ac",
        "P\u2019ungdong-ni"
    ],
    "wof:name":"P'ungdong",
    "wof:placetype":"locality"
},
  "geometry": {"coordinates":[127.56222,39.96722],"type":"Point"}
}