{
  "type": "Feature",
  "properties": {
    "gn:admin1_code":"1.0",
    "gn:asciiname":"Pujangch'am",
    "gn:country_code":"KP",
    "gn:dem":499,
    "gn:feature_class":"P",
    "gn:feature_code":"PPL",
    "gn:name":"Pujangch\u2019am",
    "gn:population":0,
    "gn:timezone":"Asia/Pyongyang",
    "iso:country":"KP",
    "name:und_x_variant":[
        "\ubd80\uc7a5\ucc38",
        "Pujangch\u2019am"
    ],
    "wof:name":"Pujangch'am",
    "wof:placetype":"locality"
},
  "geometry": {"coordinates":[126.66278,40.23167],"type":"Point"}
}