{
  "type": "Feature",
  "properties": {
    "gn:admin1_code":"7.0",
    "gn:asciiname":"T'ak-kol",
    "gn:country_code":"KP",
    "gn:dem":331,
    "gn:feature_class":"P",
    "gn:feature_code":"PPL",
    "gn:name":"T\u2019ak-kol",
    "gn:population":0,
    "gn:timezone":"Asia/Pyongyang",
    "iso:country":"KP",
    "wof:name":"T'ak-kol",
    "wof:placetype":"locality"
},
  "geometry": {"coordinates":[126.15389,38.52194],"type":"Point"}
}