{
  "type": "Feature",
  "properties": {
    "gn:admin1_code":"17.0",
    "gn:asciiname":"Hagaek-tong",
    "gn:country_code":"KP",
    "gn:dem":188,
    "gn:feature_class":"P",
    "gn:feature_code":"PPL",
    "gn:name":"Hagaek-tong",
    "gn:population":0,
    "gn:timezone":"Asia/Pyongyang",
    "iso:country":"KP",
    "name:und_x_variant":[
        "\ud558\uac1d\ub3d9",
        "Hagaek-tong"
    ],
    "wof:name":"Hagaek-tong",
    "wof:placetype":"locality"
},
  "geometry": {"coordinates":[129.76471999999998,42.62917],"type":"Point"}
}