{
  "type": "Feature",
  "properties": {
    "gn:admin1_code":"17.0",
    "gn:asciiname":"Iman-dong",
    "gn:country_code":"KP",
    "gn:dem":359,
    "gn:feature_class":"P",
    "gn:feature_code":"PPL",
    "gn:name":"Iman-dong",
    "gn:population":0,
    "gn:timezone":"Asia/Pyongyang",
    "iso:country":"KP",
    "name:und_x_variant":[
        "\uc774\ub9cc\ub3d9",
        "Uman-dong",
        "Iman-dong"
    ],
    "wof:name":"Iman-dong",
    "wof:placetype":"locality"
},
  "geometry": {"coordinates":[129.96916999999999,42.44333],"type":"Point"}
}