{
  "type": "Feature",
  "properties": {
    "gn:admin1_code":"9.0",
    "gn:asciiname":"Paekchong-ni",
    "gn:country_code":"KP",
    "gn:dem":18,
    "gn:feature_class":"P",
    "gn:feature_code":"PPL",
    "gn:name":"Paekchong-ni",
    "gn:population":0,
    "gn:timezone":"Asia/Pyongyang",
    "iso:country":"KP",
    "name:und_x_variant":[
        "\ubc31\uc885\ub9ac",
        "Paekchong-ni"
    ],
    "wof:name":"Paekchong-ni",
    "wof:placetype":"locality"
},
  "geometry": {"coordinates":[127.86944,38.95306],"type":"Point"}
}