{
  "type": "Feature",
  "properties": {
    "gn:admin1_code":"7.0",
    "gn:asciiname":"Silla-dong",
    "gn:country_code":"KP",
    "gn:dem":267,
    "gn:feature_class":"P",
    "gn:feature_code":"PPL",
    "gn:name":"Silla-dong",
    "gn:population":0,
    "gn:timezone":"Asia/Pyongyang",
    "iso:country":"KP",
    "name:kor_x_preferred":[
        "\uc2e0\ub77c\ub3d9"
    ],
    "wof:name":"Silla-dong",
    "wof:placetype":"locality"
},
  "geometry": {"coordinates":[126.40389,38.87083],"type":"Point"}
}