{
  "type": "Feature",
  "properties": {
    "gn:admin1_code":"17.0",
    "gn:asciiname":"Chungp'yong-dong",
    "gn:country_code":"KP",
    "gn:dem":306,
    "gn:feature_class":"P",
    "gn:feature_code":"PPL",
    "gn:name":"Chungp\u2019y\u014fng-dong",
    "gn:population":0,
    "gn:timezone":"Asia/Pyongyang",
    "iso:country":"KP",
    "name:und_x_variant":[
        "\uc911\ud3c9\ub3d9",
        "Chungp\u2019y\u014fng-dong"
    ],
    "wof:name":"Chungp'yong-dong",
    "wof:placetype":"locality"
},
  "geometry": {"coordinates":[130.02167,42.36806],"type":"Point"}
}