{
  "type": "Feature",
  "properties": {
    "gn:admin1_code":"9.0",
    "gn:asciiname":"Paeyang-ni",
    "gn:country_code":"KP",
    "gn:dem":21,
    "gn:feature_class":"P",
    "gn:feature_code":"PPL",
    "gn:name":"Paeyang-ni",
    "gn:population":0,
    "gn:timezone":"Asia/Pyongyang",
    "iso:country":"KP",
    "name:und_x_variant":[
        "\ubc30\uc591\ub9ac"
    ],
    "wof:name":"Paeyang-ni",
    "wof:placetype":"locality"
},
  "geometry": {"coordinates":[127.4622,39.09753],"type":"Point"}
}