{
  "type": "Feature",
  "properties": {
    "gn:admin1_code":"7.0",
    "gn:asciiname":"Ho-gol",
    "gn:country_code":"KP",
    "gn:dem":78,
    "gn:feature_class":"P",
    "gn:feature_code":"PPL",
    "gn:name":"Ho-gol",
    "gn:population":0,
    "gn:timezone":"Asia/Pyongyang",
    "iso:country":"KP",
    "wof:name":"Ho-gol",
    "wof:placetype":"locality"
},
  "geometry": {"coordinates":[125.93611,38.34333],"type":"Point"}
}