{
  "type": "Feature",
  "properties": {
    "gn:admin1_code":"6.0",
    "gn:asciiname":"Nondang-mal",
    "gn:country_code":"KP",
    "gn:dem":23,
    "gn:feature_class":"P",
    "gn:feature_code":"PPL",
    "gn:name":"Nondang-mal",
    "gn:population":0,
    "gn:timezone":"Asia/Pyongyang",
    "iso:country":"KP",
    "name:und_x_variant":[
        "Nondangma\u016dl",
        "Taptangch\u2019on",
        "\ub17c\ub2f9\ub9d0",
        "Taptang-mal",
        "Nondang-mal"
    ],
    "wof:name":"Nondang-mal",
    "wof:placetype":"locality"
},
  "geometry": {"coordinates":[125.19556,37.98833],"type":"Point"}
}