{
  "type": "Feature",
  "properties": {
    "gn:admin1_code":"1.0",
    "gn:asciiname":"Namp'o-dong",
    "gn:country_code":"KP",
    "gn:dem":379,
    "gn:feature_class":"P",
    "gn:feature_code":"PPL",
    "gn:name":"Namp\u2019o-dong",
    "gn:population":0,
    "gn:timezone":"Asia/Pyongyang",
    "iso:country":"KP",
    "name:und_x_variant":[
        "\ub0a8\ud3ec\ub3d9",
        "Namp\u2019o-dong"
    ],
    "wof:name":"Namp'o-dong",
    "wof:placetype":"locality"
},
  "geometry": {"coordinates":[126.69917,41.4875],"type":"Point"}
}