{
  "type": "Feature",
  "properties": {
    "gn:admin1_code":"6.0",
    "gn:asciiname":"Komun-dong",
    "gn:country_code":"KP",
    "gn:dem":33,
    "gn:feature_class":"P",
    "gn:feature_code":"PPL",
    "gn:name":"K\u014fmun-dong",
    "gn:population":0,
    "gn:timezone":"Asia/Pyongyang",
    "iso:country":"KP",
    "wof:name":"Komun-dong",
    "wof:placetype":"locality"
},
  "geometry": {"coordinates":[125.29528000000001,37.93361],"type":"Point"}
}