{
  "type": "Feature",
  "properties": {
    "gn:admin1_code":"3.0",
    "gn:asciiname":"Pingin-ch'on",
    "gn:country_code":"KP",
    "gn:dem":30,
    "gn:feature_class":"P",
    "gn:feature_code":"PPL",
    "gn:name":"Pingin-ch\u2019on",
    "gn:population":0,
    "gn:timezone":"Asia/Pyongyang",
    "iso:country":"KP",
    "name:und_x_variant":[
        "Pingin-ch\u2019on",
        "\ube59\uc778\ucd0c"
    ],
    "wof:name":"Pingin-ch'on",
    "wof:placetype":"locality"
},
  "geometry": {"coordinates":[128.48917,40.19333],"type":"Point"}
}