{
  "type": "Feature",
  "properties": {
    "gn:admin1_code":"1.0",
    "gn:asciiname":"Kalbat-kol",
    "gn:country_code":"KP",
    "gn:dem":347,
    "gn:feature_class":"P",
    "gn:feature_code":"PPL",
    "gn:name":"Kalbat-kol",
    "gn:population":0,
    "gn:timezone":"Asia/Pyongyang",
    "iso:country":"KP",
    "name:und_x_variant":[
        "\uac08\ubc2d\uace8",
        "Kalbat-kol"
    ],
    "wof:name":"Kalbat-kol",
    "wof:placetype":"locality"
},
  "geometry": {"coordinates":[126.66722,41.485],"type":"Point"}
}