{
  "type": "Feature",
  "properties": {
    "gn:admin1_code":"17.0",
    "gn:asciiname":"Tongjin",
    "gn:country_code":"KP",
    "gn:dem":65,
    "gn:feature_class":"P",
    "gn:feature_code":"PPL",
    "gn:name":"Tongjin",
    "gn:population":0,
    "gn:timezone":"Asia/Pyongyang",
    "iso:country":"KP",
    "name:und_x_variant":[
        "\ub3d9\uc9c4",
        "Tongjin"
    ],
    "wof:name":"Tongjin",
    "wof:placetype":"locality"
},
  "geometry": {"coordinates":[129.19193999999999,40.63806],"type":"Point"}
}