{
  "type": "Feature",
  "properties": {
    "gn:admin1_code":"6.0",
    "gn:asciiname":"Kumch'ol-li",
    "gn:country_code":"KP",
    "gn:dem":75,
    "gn:feature_class":"P",
    "gn:feature_code":"PPL",
    "gn:name":"K\u016dmch\u2019\u014fl-li",
    "gn:population":0,
    "gn:timezone":"Asia/Pyongyang",
    "iso:country":"KP",
    "name:kor_x_preferred":[
        "\uae08\ucc9c\ub9ac"
    ],
    "name:kor_x_variant":[
        "K\u016dmch\u2019\u014fl-li"
    ],
    "name:und_x_variant":[
        "K\u016dmch\u2019\u014fn-ni"
    ],
    "wof:name":"Kumch'ol-li",
    "wof:placetype":"locality"
},
  "geometry": {"coordinates":[125.27083,38.36444],"type":"Point"}
}