{
  "type": "Feature",
  "properties": {
    "gn:admin1_code":"6.0",
    "gn:asciiname":"Kumjong-dong",
    "gn:country_code":"KP",
    "gn:dem":68,
    "gn:feature_class":"P",
    "gn:feature_code":"PPL",
    "gn:name":"K\u016dmj\u014fng-dong",
    "gn:population":0,
    "gn:timezone":"Asia/Pyongyang",
    "iso:country":"KP",
    "name:kor_x_preferred":[
        "\uae08\uc815\ub3d9"
    ],
    "name:und_x_variant":[
        "K\u016dmj\u014fng-dong"
    ],
    "wof:name":"Kumjong-dong",
    "wof:placetype":"locality"
},
  "geometry": {"coordinates":[125.43639,38.10333],"type":"Point"}
}