{
  "type": "Feature",
  "properties": {
    "gn:admin1_code":"3.0",
    "gn:asciiname":"K'unbaenamu-gol",
    "gn:country_code":"KP",
    "gn:dem":354,
    "gn:feature_class":"P",
    "gn:feature_code":"PPL",
    "gn:name":"K\u2019\u016dnbaenamu-gol",
    "gn:population":0,
    "gn:timezone":"Asia/Pyongyang",
    "iso:country":"KP",
    "name:und_x_variant":[
        "\ud070\ubc30\ub098\ubb34\uace8",
        "K\u2019\u016dnbaenamu-gol"
    ],
    "wof:name":"K'unbaenamu-gol",
    "wof:placetype":"locality"
},
  "geometry": {"coordinates":[127.77417,40.2925],"type":"Point"}
}