{
  "type": "Feature",
  "properties": {
    "gn:admin1_code":"6.0",
    "gn:asciiname":"Ori-gol",
    "gn:country_code":"KP",
    "gn:dem":62,
    "gn:feature_class":"P",
    "gn:feature_code":"PPL",
    "gn:name":"Ori-gol",
    "gn:population":0,
    "gn:timezone":"Asia/Pyongyang",
    "iso:country":"KP",
    "wof:name":"Ori-gol",
    "wof:placetype":"locality"
},
  "geometry": {"coordinates":[126.08583,38.02083],"type":"Point"}
}