{
  "type": "Feature",
  "properties": {
    "gn:admin1_code":"11.0",
    "gn:asciiname":"Chung-ni",
    "gn:country_code":"KP",
    "gn:dem":88,
    "gn:feature_class":"P",
    "gn:feature_code":"PPL",
    "gn:name":"Chung-ni",
    "gn:population":0,
    "gn:timezone":"Asia/Pyongyang",
    "iso:country":"KP",
    "name:eng_x_preferred":[
        "Chung"
    ],
    "name:eng_x_variant":[
        "Chung-ni"
    ],
    "name:und_x_variant":[
        "\uc911\ub9ac",
        "Chung-ni"
    ],
    "wof:name":"Chung",
    "wof:placetype":"locality"
},
  "geometry": {"coordinates":[124.73611,40.15444],"type":"Point"}
}