{
  "type": "Feature",
  "properties": {
    "gn:admin1_code":"17.0",
    "gn:asciiname":"Yanghyon-dong",
    "gn:country_code":"KP",
    "gn:dem":399,
    "gn:feature_class":"P",
    "gn:feature_code":"PPL",
    "gn:name":"Yanghy\u014fn-dong",
    "gn:population":0,
    "gn:timezone":"Asia/Pyongyang",
    "iso:country":"KP",
    "name:und_x_variant":[
        "\uc591\ud604\ub3d9",
        "Yanghy\u014fn-dong"
    ],
    "wof:name":"Yanghyon-dong",
    "wof:placetype":"locality"
},
  "geometry": {"coordinates":[129.66388999999998,42.20306],"type":"Point"}
}