{
  "type": "Feature",
  "properties": {
    "gn:admin1_code":"11.0",
    "gn:asciiname":"Tohung-gol",
    "gn:country_code":"KP",
    "gn:dem":169,
    "gn:feature_class":"P",
    "gn:feature_code":"PPL",
    "gn:name":"Toh\u016dng-gol",
    "gn:population":0,
    "gn:timezone":"Asia/Pyongyang",
    "iso:country":"KP",
    "name:und_x_variant":[
        "Toh\u016dng-gol",
        "Toh\u016dng-dong"
    ],
    "wof:name":"Tohung-gol",
    "wof:placetype":"locality"
},
  "geometry": {"coordinates":[126.01389,39.97889],"type":"Point"}
}