{
  "type": "Feature",
  "properties": {
    "gn:admin1_code":"17.0",
    "gn:asciiname":"Ongnarugaek-kol",
    "gn:country_code":"KP",
    "gn:dem":351,
    "gn:feature_class":"P",
    "gn:feature_code":"PPL",
    "gn:name":"Ongnarugaek-kol",
    "gn:population":0,
    "gn:timezone":"Asia/Pyongyang",
    "iso:country":"KP",
    "name:und_x_variant":[
        "Ongoarukaek-kol",
        "\uc625\ub098\ub8e8\uac2f\uace8",
        "Ongnarukaek-kol",
        "Ongnarugaek-kol"
    ],
    "wof:name":"Ongnarugaek-kol",
    "wof:placetype":"locality"
},
  "geometry": {"coordinates":[129.87916999999999,42.42639000000001],"type":"Point"}
}