{
  "type": "Feature",
  "properties": {
    "gn:admin1_code":"15.0",
    "gn:asciiname":"Unnam-ni",
    "gn:country_code":"KP",
    "gn:dem":55,
    "gn:feature_class":"P",
    "gn:feature_code":"PPL",
    "gn:name":"Unnam-ni",
    "gn:population":0,
    "gn:timezone":"Asia/Pyongyang",
    "iso:country":"KP",
    "name:eng_x_preferred":[
        "Unnam"
    ],
    "name:eng_x_variant":[
        "Unnam-ni"
    ],
    "name:und_x_variant":[
        "\uc6b4\ub0a8\ub9ac",
        "Unnam-ni"
    ],
    "wof:name":"Unnam",
    "wof:placetype":"locality"
},
  "geometry": {"coordinates":[125.37472,38.99778],"type":"Point"}
}