{
  "type": "Feature",
  "properties": {
    "gn:admin1_code":"11.0",
    "gn:asciiname":"Okchon",
    "gn:country_code":"KP",
    "gn:dem":44,
    "gn:feature_class":"P",
    "gn:feature_code":"PPL",
    "gn:name":"Okch\u014fn",
    "gn:population":0,
    "gn:timezone":"Asia/Pyongyang",
    "iso:country":"KP",
    "name:kor_x_preferred":[
        "\uc625\ucc9c"
    ],
    "name:und_x_variant":[
        "Okch\u014fn"
    ],
    "wof:name":"Okchon",
    "wof:placetype":"locality"
},
  "geometry": {"coordinates":[124.52834,39.93812],"type":"Point"}
}