{
  "type": "Feature",
  "properties": {
    "gn:admin1_code":"1.0",
    "gn:asciiname":"Sinmal-tong",
    "gn:country_code":"KP",
    "gn:dem":256,
    "gn:feature_class":"P",
    "gn:feature_code":"PPL",
    "gn:name":"Sinmal-tong",
    "gn:population":0,
    "gn:timezone":"Asia/Pyongyang",
    "iso:country":"KP",
    "name:und_x_variant":[
        "\uc2e0\ub9d0\ub3d9",
        "Sinmal-tong"
    ],
    "wof:name":"Sinmal-tong",
    "wof:placetype":"locality"
},
  "geometry": {"coordinates":[126.38111000000001,41.04444],"type":"Point"}
}