{
  "type": "Feature",
  "properties": {
    "gn:admin1_code":"7.0",
    "gn:asciiname":"Sogyang-ni",
    "gn:country_code":"KP",
    "gn:dem":8,
    "gn:feature_class":"P",
    "gn:feature_code":"PPL",
    "gn:name":"S\u014fgyang-ni",
    "gn:population":0,
    "gn:timezone":"Asia/Pyongyang",
    "iso:country":"KP",
    "name:eng_x_preferred":[
        "Sogyang"
    ],
    "name:eng_x_variant":[
        "Sogyang-ni"
    ],
    "name:kor_x_preferred":[
        "\uc11d\uc591\ub9ac"
    ],
    "name:kor_x_variant":[
        "S\u014fgyang-ni"
    ],
    "wof:name":"Sogyang",
    "wof:placetype":"locality"
},
  "geometry": {"coordinates":[125.56332999999999,38.58917],"type":"Point"}
}