{
  "type": "Feature",
  "properties": {
    "gn:admin1_code":"17.0",
    "gn:asciiname":"Kanjin-dong",
    "gn:country_code":"KP",
    "gn:dem":3,
    "gn:feature_class":"P",
    "gn:feature_code":"PPL",
    "gn:name":"Kanjin-dong",
    "gn:population":0,
    "gn:timezone":"Asia/Pyongyang",
    "iso:country":"KP",
    "name:und_x_variant":[
        "\uac04\uc9c4\ub3d9",
        "Kanjin-dong"
    ],
    "wof:name":"Kanjin-dong",
    "wof:placetype":"locality"
},
  "geometry": {"coordinates":[130.15583000000001,42.10611],"type":"Point"}
}