{
  "type": "Feature",
  "properties": {
    "gn:admin1_code":"7.0",
    "gn:asciiname":"Hanch'on",
    "gn:country_code":"KP",
    "gn:dem":7,
    "gn:feature_class":"P",
    "gn:feature_code":"PPL",
    "gn:name":"Hanch\u2019on",
    "gn:population":0,
    "gn:timezone":"Asia/Pyongyang",
    "iso:country":"KP",
    "name:kor_x_preferred":[
        "\ud55c\ucd0c"
    ],
    "name:kor_x_variant":[
        "Hanch\u2019on"
    ],
    "wof:name":"Hanch'on",
    "wof:placetype":"locality"
},
  "geometry": {"coordinates":[125.68111,38.62167],"type":"Point"}
}