{
  "type": "Feature",
  "properties": {
    "gn:admin1_code":"6.0",
    "gn:asciiname":"Samjong-dong",
    "gn:cc2":"KP",
    "gn:country_code":"KP",
    "gn:dem":9,
    "gn:feature_class":"P",
    "gn:feature_code":"PPL",
    "gn:name":"Samj\u014fng-dong",
    "gn:population":0,
    "gn:timezone":"Asia/Pyongyang",
    "iso:country":"KP",
    "name:und_x_variant":[
        "Nanj\u014fn-dong",
        "Samj\u014fng-dong"
    ],
    "wof:name":"Samjong-dong",
    "wof:placetype":"locality"
},
  "geometry": {"coordinates":[125.97833,37.89444],"type":"Point"}
}