{
  "type": "Feature",
  "properties": {
    "gn:admin1_code":"9.0",
    "gn:asciiname":"Songbung-ni",
    "gn:country_code":"KP",
    "gn:dem":183,
    "gn:feature_class":"P",
    "gn:feature_code":"PPL",
    "gn:name":"S\u014fngbung-ni",
    "gn:population":0,
    "gn:timezone":"Asia/Pyongyang",
    "iso:country":"KP",
    "name:kor_x_preferred":[
        "\uc131\ubd81\ub9ac"
    ],
    "name:kor_x_variant":[
        "S\u014fngbung-ni"
    ],
    "wof:name":"Songbung-ni",
    "wof:placetype":"locality"
},
  "geometry": {"coordinates":[127.43944,38.87528],"type":"Point"}
}