{
  "type": "Feature",
  "properties": {
    "gn:admin1_code":"7.0",
    "gn:asciiname":"Ch'oe-dong",
    "gn:country_code":"KP",
    "gn:dem":138,
    "gn:feature_class":"P",
    "gn:feature_code":"PPL",
    "gn:name":"Ch\u2019oe-dong",
    "gn:population":0,
    "gn:timezone":"Asia/Pyongyang",
    "iso:country":"KP",
    "wof:name":"Ch'oe-dong",
    "wof:placetype":"locality"
},
  "geometry": {"coordinates":[126.22389,38.68361],"type":"Point"}
}