{
  "type": "Feature",
  "properties": {
    "gn:admin1_code":"15.0",
    "gn:asciiname":"Pisokko-ri",
    "gn:country_code":"KP",
    "gn:dem":17,
    "gn:feature_class":"P",
    "gn:feature_code":"PPL",
    "gn:name":"Pis\u014fkk\u014f-ri",
    "gn:population":0,
    "gn:timezone":"Asia/Pyongyang",
    "iso:country":"KP",
    "name:und_x_variant":[
        "Pisokkol",
        "Pis\u014fkka",
        "\ube44\uc11d\uac70\ub9ac",
        "Pis\u014fkk\u014f-ri"
    ],
    "wof:name":"Pisokko-ri",
    "wof:placetype":"locality"
},
  "geometry": {"coordinates":[125.29389,38.95167],"type":"Point"}
}