{
  "type": "Feature",
  "properties": {
    "gn:admin1_code":"3.0",
    "gn:asciiname":"Yondong-ni",
    "gn:country_code":"KP",
    "gn:dem":23,
    "gn:feature_class":"P",
    "gn:feature_code":"PPL",
    "gn:name":"Y\u014fndong-ni",
    "gn:population":0,
    "gn:timezone":"Asia/Pyongyang",
    "iso:country":"KP",
    "name:eng_x_preferred":[
        "Yondong"
    ],
    "name:eng_x_variant":[
        "Yondong-ni"
    ],
    "name:und_x_variant":[
        "\uc5f0\ub3d9\ub9ac",
        "Y\u014fndong-ni"
    ],
    "wof:name":"Yondong",
    "wof:placetype":"locality"
},
  "geometry": {"coordinates":[127.49167,39.52417],"type":"Point"}
}