{
  "type": "Feature",
  "properties": {
    "gn:admin1_code":"9.0",
    "gn:asciiname":"Changal-li",
    "gn:country_code":"KP",
    "gn:dem":280,
    "gn:feature_class":"P",
    "gn:feature_code":"PPL",
    "gn:name":"Changal-li",
    "gn:population":0,
    "gn:timezone":"Asia/Pyongyang",
    "iso:country":"KP",
    "name:und_x_variant":[
        "Changan-ni",
        "\uc7a5\uc548\ub9ac",
        "Changal-li"
    ],
    "wof:name":"Changal-li",
    "wof:placetype":"locality"
},
  "geometry": {"coordinates":[127.07193999999998,38.92361],"type":"Point"}
}