{
  "type": "Feature",
  "properties": {
    "gn:admin1_code":"1.0",
    "gn:asciiname":"Sangyang-dong",
    "gn:country_code":"KP",
    "gn:dem":160,
    "gn:feature_class":"P",
    "gn:feature_code":"PPL",
    "gn:name":"Sangyang-dong",
    "gn:population":0,
    "gn:timezone":"Asia/Pyongyang",
    "iso:country":"KP",
    "name:und_x_variant":[
        "\uc0c1\uc591\ub3d9",
        "Sangyang-dong"
    ],
    "wof:name":"Sangyang-dong",
    "wof:placetype":"locality"
},
  "geometry": {"coordinates":[125.84111,40.84139],"type":"Point"}
}