{
  "type": "Feature",
  "properties": {
    "gn:admin1_code":"3.0",
    "gn:asciiname":"P'ojil-li",
    "gn:country_code":"KP",
    "gn:dem":6,
    "gn:feature_class":"P",
    "gn:feature_code":"PPL",
    "gn:name":"P\u2019ojil-li",
    "gn:population":0,
    "gn:timezone":"Asia/Pyongyang",
    "iso:country":"KP",
    "name:und_x_variant":[
        "Hoshin-ri",
        "P\u2019ojin-ni",
        "P\u2019ojil-li",
        "\ud3ec\uc9c4\ub9ac"
    ],
    "wof:name":"P'ojil-li",
    "wof:placetype":"locality"
},
  "geometry": {"coordinates":[128.60639,40.18778],"type":"Point"}
}