{
  "type": "Feature",
  "properties": {
    "gn:admin1_code":"12.0",
    "gn:admin2_code":"Kangdong-gun",
    "gn:asciiname":"Munhung-ni",
    "gn:country_code":"KP",
    "gn:dem":23,
    "gn:feature_class":"P",
    "gn:feature_code":"PPL",
    "gn:name":"Munh\u016dng-ni",
    "gn:population":0,
    "gn:timezone":"Asia/Pyongyang",
    "iso:country":"KP",
    "name:eng_x_preferred":[
        "Munhung"
    ],
    "name:eng_x_variant":[
        "Munhung-ni"
    ],
    "name:kor_x_preferred":[
        "\ubb38\ud765\ub9ac"
    ],
    "name:und_x_variant":[
        "Munh\u016dng-ni",
        "Munheung-ri"
    ],
    "wof:name":"Munhung",
    "wof:placetype":"locality"
},
  "geometry": {"coordinates":[126.0651,39.15777],"type":"Point"}
}