{
  "type": "Feature",
  "properties": {
    "gn:admin1_code":"3.0",
    "gn:admin2_code":"Kow\u014fn-gun",
    "gn:asciiname":"Ha-ch'on",
    "gn:country_code":"KP",
    "gn:dem":72,
    "gn:feature_class":"P",
    "gn:feature_code":"PPL",
    "gn:name":"Ha-ch\u2019on",
    "gn:population":0,
    "gn:timezone":"Asia/Pyongyang",
    "iso:country":"KP",
    "name:und_x_variant":[
        "Ha-ch\u2019on",
        "\ud558\ucd0c"
    ],
    "wof:name":"Ha-ch'on",
    "wof:placetype":"locality"
},
  "geometry": {"coordinates":[127.20056,39.47944],"type":"Point"}
}