{
  "type": "Feature",
  "properties": {
    "gn:admin1_code":"17.0",
    "gn:asciiname":"Hagomun",
    "gn:country_code":"KP",
    "gn:dem":33,
    "gn:feature_class":"P",
    "gn:feature_code":"PPL",
    "gn:name":"Hag\u014fmun",
    "gn:population":0,
    "gn:timezone":"Asia/Pyongyang",
    "iso:country":"KP",
    "name:und_x_variant":[
        "\ud558\uac70\ubb38",
        "Hag\u014fmun"
    ],
    "wof:name":"Hagomun",
    "wof:placetype":"locality"
},
  "geometry": {"coordinates":[129.62388999999999,41.25944000000001],"type":"Point"}
}