{
  "type": "Feature",
  "properties": {
    "gn:admin1_code":"11.0",
    "gn:asciiname":"Paengma-nodongjagu",
    "gn:country_code":"KP",
    "gn:dem":45,
    "gn:feature_class":"P",
    "gn:feature_code":"PPL",
    "gn:name":"Paengma-nodongjagu",
    "gn:population":0,
    "gn:timezone":"Asia/Pyongyang",
    "iso:country":"KP",
    "name:und_x_variant":[
        "Hakuba",
        "Paengma",
        "Paekwa",
        "\ubc31\ub9c8\ub85c\ub3d9\uc790\uad6c",
        "Paengma-ri",
        "Paengma-nodongjagu"
    ],
    "wof:name":"Paengma-nodongjagu",
    "wof:placetype":"locality"
},
  "geometry": {"coordinates":[124.57138999999999,40.07583],"type":"Point"}
}