{
  "type": "Feature",
  "properties": {
    "gn:admin1_code":"7.0",
    "gn:asciiname":"Chaegung-dong",
    "gn:country_code":"KP",
    "gn:dem":475,
    "gn:feature_class":"P",
    "gn:feature_code":"PPL",
    "gn:name":"Chaegung-dong",
    "gn:population":0,
    "gn:timezone":"Asia/Pyongyang",
    "iso:country":"KP",
    "name:kor_x_preferred":[
        "\uc7ac\uad81\ub3d9"
    ],
    "wof:name":"Chaegung-dong",
    "wof:placetype":"locality"
},
  "geometry": {"coordinates":[126.94028,39.04],"type":"Point"}
}