{
  "type": "Feature",
  "properties": {
    "gn:admin1_code":"7.0",
    "gn:asciiname":"Ton-gol",
    "gn:country_code":"KP",
    "gn:dem":164,
    "gn:feature_class":"P",
    "gn:feature_code":"PPL",
    "gn:name":"Ton-gol",
    "gn:population":0,
    "gn:timezone":"Asia/Pyongyang",
    "iso:country":"KP",
    "wof:name":"Ton-gol",
    "wof:placetype":"locality"
},
  "geometry": {"coordinates":[126.20667,38.31861],"type":"Point"}
}