{
  "type": "Feature",
  "properties": {
    "gn:admin1_code":"6.0",
    "gn:asciiname":"Puk-tong",
    "gn:country_code":"KP",
    "gn:dem":7,
    "gn:feature_class":"P",
    "gn:feature_code":"PPL",
    "gn:name":"Puk-tong",
    "gn:population":0,
    "gn:timezone":"Asia/Pyongyang",
    "iso:country":"KP",
    "wof:name":"Puk-tong",
    "wof:placetype":"locality"
},
  "geometry": {"coordinates":[125.50221999999999,38.38278],"type":"Point"}
}