{
  "type": "Feature",
  "properties": {
    "gn:admin1_code":"6.0",
    "gn:asciiname":"Chadan",
    "gn:country_code":"KP",
    "gn:dem":96,
    "gn:feature_class":"P",
    "gn:feature_code":"PPL",
    "gn:name":"Chadan",
    "gn:population":0,
    "gn:timezone":"Asia/Pyongyang",
    "iso:country":"KP",
    "name:ceb_x_preferred":[
        "Chadan"
    ],
    "name:deu_x_preferred":[
        "Chadan"
    ],
    "name:kor_x_preferred":[
        "\uc790\ub2e8"
    ],
    "wof:name":"Chadan",
    "wof:placetype":"locality"
},
  "geometry": {"coordinates":[125.90306,38.11667],"type":"Point"}
}