{
  "type": "Feature",
  "properties": {
    "gn:admin1_code":"6.0",
    "gn:asciiname":"No-dong",
    "gn:country_code":"KP",
    "gn:dem":103,
    "gn:feature_class":"P",
    "gn:feature_code":"PPL",
    "gn:name":"No-dong",
    "gn:population":0,
    "gn:timezone":"Asia/Pyongyang",
    "iso:country":"KP",
    "wof:name":"No-dong",
    "wof:placetype":"locality"
},
  "geometry": {"coordinates":[125.53111,38.14139],"type":"Point"}
}