{
  "type": "Feature",
  "properties": {
    "gn:admin1_code":"3.0",
    "gn:asciiname":"Kamjang-kol",
    "gn:country_code":"KP",
    "gn:dem":918,
    "gn:feature_class":"P",
    "gn:feature_code":"PPL",
    "gn:name":"Kamjang-kol",
    "gn:population":0,
    "gn:timezone":"Asia/Pyongyang",
    "iso:country":"KP",
    "wof:name":"Kamjang-kol",
    "wof:placetype":"locality"
},
  "geometry": {"coordinates":[128.38917000000001,40.57139],"type":"Point"}
}