{
  "type": "Feature",
  "properties": {
    "gn:admin1_code":"7.0",
    "gn:asciiname":"Urung-dong",
    "gn:country_code":"KP",
    "gn:dem":84,
    "gn:feature_class":"P",
    "gn:feature_code":"PPL",
    "gn:name":"Ur\u016dng-dong",
    "gn:population":0,
    "gn:timezone":"Asia/Pyongyang",
    "iso:country":"KP",
    "name:kor_x_preferred":[
        "\uc6b0\ub989\ub3d9"
    ],
    "name:kor_x_variant":[
        "Ur\u016dng-dong"
    ],
    "wof:name":"Urung-dong",
    "wof:placetype":"locality"
},
  "geometry": {"coordinates":[126.56332999999999,38.52333],"type":"Point"}
}