{
  "type": "Feature",
  "properties": {
    "gn:admin1_code":"11.0",
    "gn:asciiname":"Paengnyol-li",
    "gn:country_code":"KP",
    "gn:dem":174,
    "gn:feature_class":"P",
    "gn:feature_code":"PPL",
    "gn:name":"Paengny\u014fl-li",
    "gn:population":0,
    "gn:timezone":"Asia/Pyongyang",
    "iso:country":"KP",
    "name:und_x_variant":[
        "\ubc31\ub828\ub9ac",
        "Paengny\u014fn-ni",
        "Paengny\u014fl-li"
    ],
    "wof:name":"Paengnyol-li",
    "wof:placetype":"locality"
},
  "geometry": {"coordinates":[124.93389000000001,40.29667],"type":"Point"}
}