{
  "type": "Feature",
  "properties": {
    "gn:admin1_code":"6.0",
    "gn:asciiname":"Yomt'an-dong",
    "gn:country_code":"KP",
    "gn:dem":72,
    "gn:feature_class":"P",
    "gn:feature_code":"PPL",
    "gn:name":"Y\u014fmt\u2019an-dong",
    "gn:population":0,
    "gn:timezone":"Asia/Pyongyang",
    "iso:country":"KP",
    "name:und_x_variant":[
        "\uc5fc\ud0c4\ub3d9",
        "Y\u014fmt\u2019an-dong"
    ],
    "wof:name":"Yomt'an-dong",
    "wof:placetype":"locality"
},
  "geometry": {"coordinates":[125.27694,38.20361],"type":"Point"}
}