{
  "type": "Feature",
  "properties": {
    "gn:admin1_code":"0.0",
    "gn:asciiname":"Happ'o-ri",
    "gn:country_code":"KP",
    "gn:dem":1586,
    "gn:feature_class":"P",
    "gn:feature_code":"PPL",
    "gn:name":"Happ\u2019o-ri",
    "gn:population":0,
    "gn:timezone":"Asia/Pyongyang",
    "iso:country":"KP",
    "name:kor_x_preferred":[
        "\ud569\ud3ec\ub9ac"
    ],
    "name:und_x_variant":[
        "Happ\u2019o-ri"
    ],
    "wof:name":"Happ'o-ri",
    "wof:placetype":"locality"
},
  "geometry": {"coordinates":[127.83333,40.65],"type":"Point"}
}