{
  "type": "Feature",
  "properties": {
    "gn:admin1_code":"11.0",
    "gn:asciiname":"Hasam-ni",
    "gn:country_code":"KP",
    "gn:dem":63,
    "gn:feature_class":"P",
    "gn:feature_code":"PPL",
    "gn:name":"Hasam-ni",
    "gn:population":0,
    "gn:timezone":"Asia/Pyongyang",
    "iso:country":"KP",
    "name:eng_x_preferred":[
        "Hasam"
    ],
    "name:eng_x_variant":[
        "Hasam-ni"
    ],
    "name:und_x_variant":[
        "\ud558\uc0bc\ub9ac",
        "Hasam-ni"
    ],
    "wof:name":"Hasam",
    "wof:placetype":"locality"
},
  "geometry": {"coordinates":[124.74583,40.12861],"type":"Point"}
}