{
  "type": "Feature",
  "properties": {
    "gn:admin1_code":"6.0",
    "gn:admin2_code":"Changp\u2019ung-gun",
    "gn:asciiname":"Araedoe-gol",
    "gn:country_code":"KP",
    "gn:dem":154,
    "gn:feature_class":"P",
    "gn:feature_code":"PPL",
    "gn:name":"Araedoe-gol",
    "gn:population":0,
    "gn:timezone":"Asia/Pyongyang",
    "iso:country":"KP",
    "name:und_x_variant":[
        "Araetoe-kol",
        "Araedoe-gol"
    ],
    "wof:name":"Araedoe-gol",
    "wof:placetype":"locality"
},
  "geometry": {"coordinates":[126.68611,38.17222],"type":"Point"}
}