{
  "type": "Feature",
  "properties": {
    "gn:admin1_code":"3.0",
    "gn:asciiname":"Won'go-dong",
    "gn:country_code":"KP",
    "gn:dem":173,
    "gn:feature_class":"P",
    "gn:feature_code":"PPL",
    "gn:name":"W\u014fn\u2019g\u014f-dong",
    "gn:population":0,
    "gn:timezone":"Asia/Pyongyang",
    "iso:country":"KP",
    "name:kor_x_preferred":[
        "\uc6d0\uac70\ub3d9"
    ],
    "name:kor_x_variant":[
        "W\u014fn\u2019g\u014f-dong"
    ],
    "name:und_x_variant":[
        "Inkyo-ri"
    ],
    "wof:name":"Won'go-dong",
    "wof:placetype":"locality"
},
  "geometry": {"coordinates":[126.99194,39.41111],"type":"Point"}
}