{
  "type": "Feature",
  "properties": {
    "gn:admin1_code":"6.0",
    "gn:asciiname":"Kwangsandong-maul",
    "gn:country_code":"KP",
    "gn:dem":22,
    "gn:feature_class":"P",
    "gn:feature_code":"PPL",
    "gn:name":"Kwangsandong-ma\u016dl",
    "gn:population":0,
    "gn:timezone":"Asia/Pyongyang",
    "iso:country":"KP",
    "name:kor_x_preferred":[
        "Kwangsandong-ma\u016dl"
    ],
    "name:kor_x_variant":[
        "\uad11\uc0b0\ub9c8\uc744",
        "\uad11\uc0b0",
        "\uad11\uc0b0\ub3d9"
    ],
    "name:und_x_variant":[
        "Kwangsan",
        "Kwangsan-dong"
    ],
    "wof:name":"Kwangsandong-maul",
    "wof:placetype":"locality"
},
  "geometry": {"coordinates":[125.62260000000001,38.4188],"type":"Point"}
}