{
  "type": "Feature",
  "properties": {
    "gn:admin1_code":"15.0",
    "gn:asciiname":"Ma-dong",
    "gn:country_code":"KP",
    "gn:dem":255,
    "gn:feature_class":"P",
    "gn:feature_code":"PPL",
    "gn:name":"Ma-dong",
    "gn:population":0,
    "gn:timezone":"Asia/Pyongyang",
    "iso:country":"KP",
    "name:und_x_variant":[
        "\ub9c8\ub3d9",
        "Ma-dong"
    ],
    "wof:name":"Ma-dong",
    "wof:placetype":"locality"
},
  "geometry": {"coordinates":[126.60417,39.82611],"type":"Point"}
}