{
  "type": "Feature",
  "properties": {
    "gn:admin1_code":"0.0",
    "gn:asciiname":"Wolp'o-ri",
    "gn:country_code":"KP",
    "gn:dem":152,
    "gn:feature_class":"P",
    "gn:feature_code":"PPL",
    "gn:name":"W\u014flp\u2019o-ri",
    "gn:population":0,
    "gn:timezone":"Asia/Pyongyang",
    "iso:country":"KP",
    "name:kor_x_preferred":[
        "\uc6d4\ud3ec\ub9ac"
    ],
    "name:und_x_variant":[
        "W\u014flp\u2019o-ri"
    ],
    "wof:name":"Wolp'o-ri",
    "wof:placetype":"locality"
},
  "geometry": {"coordinates":[126.23333,39.48333],"type":"Point"}
}