{
  "type": "Feature",
  "properties": {
    "gn:admin1_code":"9.0",
    "gn:asciiname":"Ch'onch'i",
    "gn:country_code":"KP",
    "gn:dem":322,
    "gn:feature_class":"P",
    "gn:feature_code":"PPL",
    "gn:name":"Ch\u2019onch\u2019i",
    "gn:population":0,
    "gn:timezone":"Asia/Pyongyang",
    "iso:country":"KP",
    "name:kor_x_preferred":[
        "\ucd0c\uce58"
    ],
    "name:und_x_variant":[
        "Ch\u2019onch-i",
        "Ch\u2019onch\u2019i"
    ],
    "wof:name":"Ch'onch'i",
    "wof:placetype":"locality"
},
  "geometry": {"coordinates":[127.33861,39.00917000000001],"type":"Point"}
}