{
  "type": "Feature",
  "properties": {
    "gn:admin1_code":"7.0",
    "gn:asciiname":"Choksong-ni",
    "gn:country_code":"KP",
    "gn:dem":76,
    "gn:feature_class":"P",
    "gn:feature_code":"PPL",
    "gn:name":"Ch\u014fks\u014fng-ni",
    "gn:population":0,
    "gn:timezone":"Asia/Pyongyang",
    "iso:country":"KP",
    "name:eng_x_preferred":[
        "Choksong"
    ],
    "name:eng_x_variant":[
        "Choksong-ni"
    ],
    "name:kor_x_preferred":[
        "\uc801\uc131\ub9ac"
    ],
    "name:und_x_variant":[
        "Ch\u014fks\u014fng-ni"
    ],
    "wof:name":"Choksong",
    "wof:placetype":"locality"
},
  "geometry": {"coordinates":[125.9325,38.36],"type":"Point"}
}