{
  "type": "Feature",
  "properties": {
    "gn:admin1_code":"1.0",
    "gn:asciiname":"Ch'onggye-ri",
    "gn:country_code":"KP",
    "gn:dem":251,
    "gn:feature_class":"P",
    "gn:feature_code":"PPL",
    "gn:name":"Ch\u2019\u014fnggye-ri",
    "gn:population":0,
    "gn:timezone":"Asia/Pyongyang",
    "iso:country":"KP",
    "name:und_x_variant":[
        "\uccad\uacc4\ub9ac",
        "Ch\u2019\u014fngge-ri",
        "Ch\u2019\u014fnggye-ri"
    ],
    "wof:name":"Ch'onggye-ri",
    "wof:placetype":"locality"
},
  "geometry": {"coordinates":[125.51416999999999,40.62972],"type":"Point"}
}