{
  "type": "Feature",
  "properties": {
    "gn:admin1_code":"17.0",
    "gn:asciiname":"Yangho-dong",
    "gn:country_code":"KP",
    "gn:dem":20,
    "gn:feature_class":"P",
    "gn:feature_code":"PPL",
    "gn:name":"Yangho-dong",
    "gn:population":0,
    "gn:timezone":"Asia/Pyongyang",
    "iso:country":"KP",
    "name:und_x_variant":[
        "Yangha-ch\u2019on",
        "\uc591\ud638\ub3d9",
        "Yangho-dong"
    ],
    "wof:name":"Yangho-dong",
    "wof:placetype":"locality"
},
  "geometry": {"coordinates":[129.18278000000001,40.71972],"type":"Point"}
}