{
  "type": "Feature",
  "properties": {
    "gn:admin1_code":"3.0",
    "gn:admin2_code":"K\u016dmya-gun",
    "gn:asciiname":"Sangsejung-ni",
    "gn:country_code":"KP",
    "gn:dem":7,
    "gn:feature_class":"P",
    "gn:feature_code":"PPL",
    "gn:name":"Sangsejung-ni",
    "gn:population":0,
    "gn:timezone":"Asia/Pyongyang",
    "iso:country":"KP",
    "name:und_x_variant":[
        "\uc0c1\uc138\uc8fd\ub9ac"
    ],
    "wof:name":"Sangsejung-ni",
    "wof:placetype":"locality"
},
  "geometry": {"coordinates":[127.34090999999999,39.50145],"type":"Point"}
}