{
  "type": "Feature",
  "properties": {
    "gn:admin1_code":"15.0",
    "gn:asciiname":"Namsa-dong",
    "gn:country_code":"KP",
    "gn:dem":21,
    "gn:feature_class":"P",
    "gn:feature_code":"PPL",
    "gn:name":"Namsa-dong",
    "gn:population":0,
    "gn:timezone":"Asia/Pyongyang",
    "iso:country":"KP",
    "wof:name":"Namsa-dong",
    "wof:placetype":"locality"
},
  "geometry": {"coordinates":[125.49250000000001,39.0475],"type":"Point"}
}