{
  "type": "Feature",
  "properties": {
    "gn:admin1_code":"1.0",
    "gn:asciiname":"Ch'angp'yong",
    "gn:country_code":"KP",
    "gn:dem":300,
    "gn:feature_class":"P",
    "gn:feature_code":"PPL",
    "gn:name":"Ch\u2019angp\u2019yong",
    "gn:population":0,
    "gn:timezone":"Asia/Pyongyang",
    "iso:country":"KP",
    "name:und_x_variant":[
        "\ucc3d\ud3c9",
        "Ch\u2019angp\u2019yong"
    ],
    "wof:name":"Ch'angp'yong",
    "wof:placetype":"locality"
},
  "geometry": {"coordinates":[126.60417,41.38806],"type":"Point"}
}