{
  "type": "Feature",
  "properties": {
    "gn:admin1_code":"11.0",
    "gn:asciiname":"Wonbop",
    "gn:country_code":"KP",
    "gn:dem":54,
    "gn:feature_class":"P",
    "gn:feature_code":"PPL",
    "gn:name":"W\u014fnb\u014fp",
    "gn:population":0,
    "gn:timezone":"Asia/Pyongyang",
    "iso:country":"KP",
    "name:und_x_variant":[
        "\uc6d0\ubc95",
        "W\u014fnb\u014fp"
    ],
    "wof:name":"Wonbop",
    "wof:placetype":"locality"
},
  "geometry": {"coordinates":[124.50888999999999,39.97667],"type":"Point"}
}