{
  "type": "Feature",
  "properties": {
    "gn:admin1_code":"6.0",
    "gn:asciiname":"An-gol",
    "gn:country_code":"KP",
    "gn:dem":12,
    "gn:feature_class":"P",
    "gn:feature_code":"PPL",
    "gn:name":"An-gol",
    "gn:population":0,
    "gn:timezone":"Asia/Pyongyang",
    "iso:country":"KP",
    "name:und_x_variant":[
        "\uc548\uace8",
        "An-gol"
    ],
    "wof:name":"An-gol",
    "wof:placetype":"locality"
},
  "geometry": {"coordinates":[125.24527999999999,38.04611],"type":"Point"}
}