{
  "type": "Feature",
  "properties": {
    "gn:admin1_code":"15.0",
    "gn:asciiname":"Chinjang-ni",
    "gn:country_code":"KP",
    "gn:dem":626,
    "gn:feature_class":"P",
    "gn:feature_code":"PPL",
    "gn:name":"Chinjang-ni",
    "gn:population":0,
    "gn:timezone":"Asia/Pyongyang",
    "iso:country":"KP",
    "name:eng_x_preferred":[
        "Chinjang"
    ],
    "name:eng_x_variant":[
        "Chinjang-ni"
    ],
    "name:und_x_variant":[
        "\uc9c4\uc791\ub9ac",
        "Chinjang-ni"
    ],
    "wof:name":"Chinjang",
    "wof:placetype":"locality"
},
  "geometry": {"coordinates":[127.01667,39.91667],"type":"Point"}
}