{
  "type": "Feature",
  "properties": {
    "gn:admin1_code":"1.0",
    "gn:asciiname":"Chonsanum-dong",
    "gn:country_code":"KP",
    "gn:dem":198,
    "gn:feature_class":"P",
    "gn:feature_code":"PPL",
    "gn:name":"Ch\u014fnsan\u016dm-dong",
    "gn:population":0,
    "gn:timezone":"Asia/Pyongyang",
    "iso:country":"KP",
    "name:und_x_variant":[
        "\uc804\uc0b0\uc74c\ub3d9",
        "Ch\u014fnsan\u016dm-dong"
    ],
    "wof:name":"Chonsanum-dong",
    "wof:placetype":"locality"
},
  "geometry": {"coordinates":[126.14583,41.0325],"type":"Point"}
}