{
  "type": "Feature",
  "properties": {
    "gn:admin1_code":"17.0",
    "gn:asciiname":"Taep'ijin",
    "gn:country_code":"KP",
    "gn:dem":10,
    "gn:feature_class":"P",
    "gn:feature_code":"PPL",
    "gn:name":"Taep\u2019ijin",
    "gn:population":0,
    "gn:timezone":"Asia/Pyongyang",
    "iso:country":"KP",
    "name:und_x_variant":[
        "\ub300\ud53c\uc9c4",
        "Taep\u2019ijin"
    ],
    "wof:name":"Taep'ijin",
    "wof:placetype":"locality"
},
  "geometry": {"coordinates":[130.1875,42.12444],"type":"Point"}
}