{
  "type": "Feature",
  "properties": {
    "gn:admin1_code":"17.0",
    "gn:asciiname":"Kumulmok",
    "gn:cc2":"KP",
    "gn:country_code":"KP",
    "gn:dem":214,
    "gn:feature_class":"P",
    "gn:feature_code":"PPL",
    "gn:name":"K\u016dmulmok",
    "gn:population":0,
    "gn:timezone":"Asia/Pyongyang",
    "iso:country":"KP",
    "name:und_x_variant":[
        "Manghang",
        "\uadf8\ubb3c\ubaa9",
        "K\u016dmulmok"
    ],
    "wof:name":"Kumulmok",
    "wof:placetype":"locality"
},
  "geometry": {"coordinates":[129.54556000000002,41.41806],"type":"Point"}
}