{
  "type": "Feature",
  "properties": {
    "gn:admin1_code":"3.0",
    "gn:asciiname":"Suraenomi",
    "gn:country_code":"KP",
    "gn:dem":365,
    "gn:feature_class":"P",
    "gn:feature_code":"PPL",
    "gn:name":"Suraen\u014fmi",
    "gn:population":0,
    "gn:timezone":"Asia/Pyongyang",
    "iso:country":"KP",
    "name:und_x_variant":[
        "\uc218\ub798\ub118\uc774",
        "Suraen\u014fmi"
    ],
    "wof:name":"Suraenomi",
    "wof:placetype":"locality"
},
  "geometry": {"coordinates":[127.80083,40.315],"type":"Point"}
}