{
  "type": "Feature",
  "properties": {
    "gn:admin1_code":"13.0",
    "gn:asciiname":"Pyorhak-kol",
    "gn:country_code":"KP",
    "gn:dem":1195,
    "gn:feature_class":"P",
    "gn:feature_code":"PPL",
    "gn:name":"Py\u014frhak-kol",
    "gn:population":0,
    "gn:timezone":"Asia/Pyongyang",
    "iso:country":"KP",
    "wof:name":"Pyorhak-kol",
    "wof:placetype":"locality"
},
  "geometry": {"coordinates":[128.55528000000001,41.0475],"type":"Point"}
}