{
  "type": "Feature",
  "properties": {
    "gn:admin1_code":"9.0",
    "gn:asciiname":"Nuptunji",
    "gn:country_code":"KP",
    "gn:dem":55,
    "gn:feature_class":"P",
    "gn:feature_code":"PPL",
    "gn:name":"N\u016dptunji",
    "gn:population":0,
    "gn:timezone":"Asia/Pyongyang",
    "iso:country":"KP",
    "name:und_x_variant":[
        "N\u016dptunji",
        "\ub2a1\ub454\uc9c0"
    ],
    "wof:name":"Nuptunji",
    "wof:placetype":"locality"
},
  "geometry": {"coordinates":[127.36964999999999,39.11253],"type":"Point"}
}