{
  "type": "Feature",
  "properties": {
    "gn:admin1_code":"3.0",
    "gn:asciiname":"P'yongjol-li",
    "gn:country_code":"KP",
    "gn:dem":494,
    "gn:feature_class":"P",
    "gn:feature_code":"PPL",
    "gn:name":"P\u2019y\u014fngj\u014fl-li",
    "gn:population":0,
    "gn:timezone":"Asia/Pyongyang",
    "iso:country":"KP",
    "name:kor_x_preferred":[
        "\ud3c9\uc804\ub9ac"
    ],
    "name:kor_x_variant":[
        "P\u2019y\u014fngj\u014fl-li"
    ],
    "wof:name":"P'yongjol-li",
    "wof:placetype":"locality"
},
  "geometry": {"coordinates":[126.91056,39.74028],"type":"Point"}
}