{
  "type": "Feature",
  "properties": {
    "gn:admin1_code":"7.0",
    "gn:asciiname":"Chindae-dong",
    "gn:country_code":"KP",
    "gn:dem":46,
    "gn:feature_class":"P",
    "gn:feature_code":"PPL",
    "gn:name":"Chindae-dong",
    "gn:population":0,
    "gn:timezone":"Asia/Pyongyang",
    "iso:country":"KP",
    "name:und_x_variant":[
        "\uc9c4\ub300\ub3d9",
        "Chindae-dong"
    ],
    "wof:name":"Chindae-dong",
    "wof:placetype":"locality"
},
  "geometry": {"coordinates":[126.48027999999999,38.11528],"type":"Point"}
}