{
  "type": "Feature",
  "properties": {
    "gn:admin1_code":"1.0",
    "gn:asciiname":"Sap'yongch'am",
    "gn:country_code":"KP",
    "gn:dem":568,
    "gn:feature_class":"P",
    "gn:feature_code":"PPL",
    "gn:name":"Sap\u2019y\u014fngch\u2019am",
    "gn:population":0,
    "gn:timezone":"Asia/Pyongyang",
    "iso:country":"KP",
    "name:und_x_variant":[
        "\uc0ac\ud3c9\ucc38",
        "Sap\u2019y\u014fngch\u2019am"
    ],
    "wof:name":"Sap'yongch'am",
    "wof:placetype":"locality"
},
  "geometry": {"coordinates":[126.37917,40.46167],"type":"Point"}
}