{
  "type": "Feature",
  "properties": {
    "gn:admin1_code":"13.0",
    "gn:asciiname":"Myongdangdegi",
    "gn:country_code":"KP",
    "gn:dem":1212,
    "gn:feature_class":"P",
    "gn:feature_code":"PPL",
    "gn:name":"My\u014fngdangdegi",
    "gn:population":0,
    "gn:timezone":"Asia/Pyongyang",
    "iso:country":"KP",
    "name:und_x_variant":[
        "\uba85\ub2f9\ub371\uc774",
        "My\u014fngdangdegi"
    ],
    "wof:name":"Myongdangdegi",
    "wof:placetype":"locality"
},
  "geometry": {"coordinates":[128.36528000000001,40.89917],"type":"Point"}
}