{
  "type": "Feature",
  "properties": {
    "gn:admin1_code":"13.0",
    "gn:asciiname":"Sogu-ri",
    "gn:country_code":"KP",
    "gn:dem":877,
    "gn:feature_class":"P",
    "gn:feature_code":"PPL",
    "gn:name":"S\u014fgu-ri",
    "gn:population":0,
    "gn:timezone":"Asia/Pyongyang",
    "iso:country":"KP",
    "name:und_x_variant":[
        "\uc11d\uc6b0\ub9ac",
        "S\u014fgu-ri"
    ],
    "wof:name":"Sogu-ri",
    "wof:placetype":"locality"
},
  "geometry": {"coordinates":[128.19361000000001,40.99361],"type":"Point"}
}