{
  "type": "Feature",
  "properties": {
    "gn:admin1_code":"3.0",
    "gn:asciiname":"Tobi",
    "gn:country_code":"KP",
    "gn:dem":96,
    "gn:feature_class":"P",
    "gn:feature_code":"PPL",
    "gn:name":"Tobi",
    "gn:population":0,
    "gn:timezone":"Asia/Pyongyang",
    "iso:country":"KP",
    "name:ceb_x_preferred":[
        "Tobi"
    ],
    "name:deu_x_preferred":[
        "Tobi"
    ],
    "name:fra_x_preferred":[
        "Tobi"
    ],
    "name:heb_x_preferred":[
        "\u05d8\u05d5\u05d1\u05d9"
    ],
    "name:ita_x_preferred":[
        "Tobi"
    ],
    "name:jpn_x_preferred":[
        "\u30c8\u30d3"
    ],
    "name:nld_x_preferred":[
        "Tobi"
    ],
    "name:pol_x_preferred":[
        "Tobi"
    ],
    "name:por_x_preferred":[
        "Tobi"
    ],
    "name:swe_x_preferred":[
        "Tobi"
    ],
    "name:und_x_variant":[
        "\ub3c4\ube44"
    ],
    "name:zho_x_preferred":[
        "\u9cf6"
    ],
    "wof:name":"Tobi",
    "wof:placetype":"locality"
},
  "geometry": {"coordinates":[128.23471999999998,40.14833],"type":"Point"}
}