{
  "type": "Feature",
  "properties": {
    "gn:admin1_code":"6.0",
    "gn:asciiname":"Sinnae-dong",
    "gn:country_code":"KP",
    "gn:dem":10,
    "gn:feature_class":"P",
    "gn:feature_code":"PPL",
    "gn:name":"Sinnae-dong",
    "gn:population":0,
    "gn:timezone":"Asia/Pyongyang",
    "iso:country":"KP",
    "name:kor_x_preferred":[
        "\uc2e0\ub0b4\ub3d9"
    ],
    "name:msa_x_preferred":[
        "Sinnae-dong"
    ],
    "name:tha_x_preferred":[
        "\u0e41\u0e02\u0e27\u0e07\u0e0a\u0e34\u0e19\u0e41\u0e19"
    ],
    "name:vie_x_preferred":[
        "Sinnae-dong"
    ],
    "wof:name":"Sinnae-dong",
    "wof:placetype":"locality"
},
  "geometry": {"coordinates":[126.0625,37.93139],"type":"Point"}
}