{
  "type": "Feature",
  "properties": {
    "gn:admin1_code":"15.0",
    "gn:admin2_code":"1869039",
    "gn:asciiname":"Kwandong-ni",
    "gn:country_code":"KP",
    "gn:dem":27,
    "gn:feature_class":"P",
    "gn:feature_code":"PPL",
    "gn:name":"Kwand\u014fng-ni",
    "gn:population":0,
    "gn:timezone":"Asia/Pyongyang",
    "iso:country":"KP",
    "name:eng_x_preferred":[
        "Kwandong"
    ],
    "name:eng_x_variant":[
        "Kwandong-ni"
    ],
    "wof:name":"Kwandong",
    "wof:placetype":"locality"
},
  "geometry": {"coordinates":[125.64417,39.42083],"type":"Point"}
}