{
  "type": "Feature",
  "properties": {
    "gn:admin1_code":"0.0",
    "gn:asciiname":"Kajimak-tong",
    "gn:country_code":"KP",
    "gn:dem":570,
    "gn:feature_class":"P",
    "gn:feature_code":"PPL",
    "gn:name":"Kajimak-tong",
    "gn:population":0,
    "gn:timezone":"Asia/Pyongyang",
    "iso:country":"KP",
    "name:kor_x_preferred":[
        "\uac00\uc9c0\ub9c9\ub3d9"
    ],
    "wof:name":"Kajimak-tong",
    "wof:placetype":"locality"
},
  "geometry": {"coordinates":[125.59999999999999,40.31667],"type":"Point"}
}