{
  "type": "Feature",
  "properties": {
    "gn:admin1_code":"15.0",
    "gn:asciiname":"Suhang-dong",
    "gn:country_code":"KP",
    "gn:dem":1099,
    "gn:feature_class":"P",
    "gn:feature_code":"PPL",
    "gn:name":"Suhang-dong",
    "gn:population":0,
    "gn:timezone":"Asia/Pyongyang",
    "iso:country":"KP",
    "name:und_x_variant":[
        "\uc218\ud56d\ub3d9",
        "Suhang-dong"
    ],
    "wof:name":"Suhang-dong",
    "wof:placetype":"locality"
},
  "geometry": {"coordinates":[126.97806,40.18833],"type":"Point"}
}