{
  "type": "Feature",
  "properties": {
    "gn:admin1_code":"3.0",
    "gn:admin2_code":"Tanch'\u014fn-si",
    "gn:asciiname":"Sodunji",
    "gn:country_code":"KP",
    "gn:dem":709,
    "gn:feature_class":"P",
    "gn:feature_code":"PPL",
    "gn:name":"Sodunji",
    "gn:population":0,
    "gn:timezone":"Asia/Pyongyang",
    "iso:country":"KP",
    "name:und_x_variant":[
        "\uc18c\ub454\uc9c0",
        "Sodunji"
    ],
    "wof:name":"Sodunji",
    "wof:placetype":"locality"
},
  "geometry": {"coordinates":[128.82277999999999,40.95333],"type":"Point"}
}