{
  "type": "Feature",
  "properties": {
    "gn:admin1_code":"13.0",
    "gn:asciiname":"Majol-li",
    "gn:country_code":"KP",
    "gn:dem":831,
    "gn:feature_class":"P",
    "gn:feature_code":"PPL",
    "gn:name":"Maj\u014fl-li",
    "gn:population":0,
    "gn:timezone":"Asia/Pyongyang",
    "iso:country":"KP",
    "name:kor_x_preferred":[
        "\ub9c8\uc804\ub9ac"
    ],
    "name:und_x_variant":[
        "Maj\u014fl-li"
    ],
    "wof:name":"Majol-li",
    "wof:placetype":"locality"
},
  "geometry": {"coordinates":[128.25676000000001,41.34586],"type":"Point"}
}