{
  "type": "Feature",
  "properties": {
    "gn:admin1_code":"9.0",
    "gn:admin2_code":"P'y\u014fnggang-gun",
    "gn:asciiname":"Isudong-ni",
    "gn:cc2":"KP",
    "gn:country_code":"KP",
    "gn:dem":341,
    "gn:feature_class":"P",
    "gn:feature_code":"PPL",
    "gn:name":"Isud\u014fng-ni",
    "gn:population":0,
    "gn:timezone":"Asia/Pyongyang",
    "iso:country":"KP",
    "name:kor_x_preferred":[
        "\uc774\uc218\ub355\ub9ac"
    ],
    "name:und_x_variant":[
        "Yisud\u014fng-ni",
        "Isud\u014fng-ni"
    ],
    "wof:name":"Isudong-ni",
    "wof:placetype":"locality"
},
  "geometry": {"coordinates":[127.33306,38.43556],"type":"Point"}
}