{
  "type": "Feature",
  "properties": {
    "gn:admin1_code":"17.0",
    "gn:asciiname":"Sonbau-gol",
    "gn:country_code":"KP",
    "gn:dem":470,
    "gn:feature_class":"P",
    "gn:feature_code":"PPL",
    "gn:name":"S\u014fnbau-gol",
    "gn:population":0,
    "gn:timezone":"Asia/Pyongyang",
    "iso:country":"KP",
    "name:und_x_variant":[
        "S\u014fnbawi-gol",
        "S\u014fnam-dong",
        "\uc120\ubc14\uc6b0\uace8",
        "S\u014fnbau-gol"
    ],
    "wof:name":"Sonbau-gol",
    "wof:placetype":"locality"
},
  "geometry": {"coordinates":[129.13917000000001,40.94167],"type":"Point"}
}