{
  "type": "Feature",
  "properties": {
    "gn:admin1_code":"11.0",
    "gn:asciiname":"Ihyon'gyo",
    "gn:country_code":"KP",
    "gn:dem":36,
    "gn:feature_class":"P",
    "gn:feature_code":"PPL",
    "gn:name":"Ihy\u014fn\u2019gyo",
    "gn:population":0,
    "gn:timezone":"Asia/Pyongyang",
    "iso:country":"KP",
    "name:kor_x_preferred":[
        "\uc774\ud604\uad50"
    ],
    "name:kor_x_variant":[
        "Ihy\u014fn\u2019gyo"
    ],
    "wof:name":"Ihyon'gyo",
    "wof:placetype":"locality"
},
  "geometry": {"coordinates":[125.27417,39.68222],"type":"Point"}
}