{
  "type": "Feature",
  "properties": {
    "gn:admin1_code":"3.0",
    "gn:asciiname":"Chungsang-ni",
    "gn:country_code":"KP",
    "gn:dem":24,
    "gn:feature_class":"P",
    "gn:feature_code":"PPL",
    "gn:name":"Chungsang-ni",
    "gn:population":0,
    "gn:timezone":"Asia/Pyongyang",
    "iso:country":"KP",
    "name:und_x_variant":[
        "\uc911\uc0c1\ub9ac",
        "Chungsang-ni"
    ],
    "wof:name":"Chungsang-ni",
    "wof:placetype":"locality"
},
  "geometry": {"coordinates":[127.44028,39.60194],"type":"Point"}
}