{
  "type": "Feature",
  "properties": {
    "gn:admin1_code":"3.0",
    "gn:asciiname":"Suregi",
    "gn:country_code":"KP",
    "gn:dem":198,
    "gn:feature_class":"P",
    "gn:feature_code":"PPL",
    "gn:name":"Suregi",
    "gn:population":0,
    "gn:timezone":"Asia/Pyongyang",
    "iso:country":"KP",
    "name:und_x_variant":[
        "\uc218\ub808\uae30",
        "Suregi"
    ],
    "wof:name":"Suregi",
    "wof:placetype":"locality"
},
  "geometry": {"coordinates":[127.33556000000002,39.90306],"type":"Point"}
}