{
  "type": "Feature",
  "properties": {
    "gn:admin1_code":"3.0",
    "gn:asciiname":"Kodok-ch'on",
    "gn:country_code":"KP",
    "gn:dem":276,
    "gn:feature_class":"P",
    "gn:feature_code":"PPL",
    "gn:name":"Kod\u014fk-ch\u2019on",
    "gn:population":0,
    "gn:timezone":"Asia/Pyongyang",
    "iso:country":"KP",
    "name:und_x_variant":[
        "Kod\u014fk-ch\u2019on",
        "\uace0\ub355\ucd0c"
    ],
    "wof:name":"Kodok-ch'on",
    "wof:placetype":"locality"
},
  "geometry": {"coordinates":[128.57312999999999,40.44658],"type":"Point"}
}