{
  "type": "Feature",
  "properties": {
    "gn:admin1_code":"12.0",
    "gn:admin2_code":"S\u016dngho-guy\u014fk",
    "gn:asciiname":"Hungnyong-ni",
    "gn:country_code":"KP",
    "gn:dem":73,
    "gn:feature_class":"P",
    "gn:feature_code":"PPL",
    "gn:name":"H\u016dngnyong-ni",
    "gn:population":0,
    "gn:timezone":"Asia/Pyongyang",
    "iso:country":"KP",
    "wof:name":"Hungnyong-ni",
    "wof:placetype":"locality"
},
  "geometry": {"coordinates":[126.03333000000001,39.06833],"type":"Point"}
}