{
  "type": "Feature",
  "properties": {
    "gn:admin1_code":"11.0",
    "gn:asciiname":"Tongmogi",
    "gn:country_code":"KP",
    "gn:dem":18,
    "gn:feature_class":"P",
    "gn:feature_code":"PPL",
    "gn:name":"Tongmogi",
    "gn:population":0,
    "gn:timezone":"Asia/Pyongyang",
    "iso:country":"KP",
    "name:kor_x_preferred":[
        "\ub3d9\ubaa9\uc774"
    ],
    "wof:name":"Tongmogi",
    "wof:placetype":"locality"
},
  "geometry": {"coordinates":[125.37667,39.60917],"type":"Point"}
}