{
  "type": "Feature",
  "properties": {
    "gn:admin1_code":"3.0",
    "gn:asciiname":"Chossi-dong",
    "gn:country_code":"KP",
    "gn:dem":13,
    "gn:feature_class":"P",
    "gn:feature_code":"PPL",
    "gn:name":"Chossi-dong",
    "gn:population":0,
    "gn:timezone":"Asia/Pyongyang",
    "iso:country":"KP",
    "name:und_x_variant":[
        "\uc870\uc528\ub3d9",
        "Chossi-dong"
    ],
    "wof:name":"Chossi-dong",
    "wof:placetype":"locality"
},
  "geometry": {"coordinates":[128.82639,40.41083],"type":"Point"}
}