{
  "type": "Feature",
  "properties": {
    "gn:admin1_code":"12.0",
    "gn:asciiname":"Wonhung-ni",
    "gn:country_code":"KP",
    "gn:dem":23,
    "gn:feature_class":"P",
    "gn:feature_code":"PPL",
    "gn:name":"W\u014fnh\u016dng-ni",
    "gn:population":0,
    "gn:timezone":"Asia/Pyongyang",
    "iso:country":"KP",
    "name:kor_x_preferred":[
        "\uc6d0\ud765\ub9ac"
    ],
    "name:und_x_variant":[
        "Kunh\u016dng-ni",
        "W\u014fnh\u016dng-ni",
        "Wonheungni"
    ],
    "wof:name":"Wonhung-ni",
    "wof:placetype":"locality"
},
  "geometry": {"coordinates":[125.97803999999999,39.11853],"type":"Point"}
}