{
  "type": "Feature",
  "properties": {
    "gn:admin1_code":"11.0",
    "gn:asciiname":"P'osang-ni",
    "gn:country_code":"KP",
    "gn:dem":201,
    "gn:feature_class":"P",
    "gn:feature_code":"PPL",
    "gn:name":"P\u2019osang-ni",
    "gn:population":0,
    "gn:timezone":"Asia/Pyongyang",
    "iso:country":"KP",
    "name:und_x_variant":[
        "\ud3ec\uc0c1\ub9ac",
        "P\u2019osang-ni"
    ],
    "wof:name":"P'osang-ni",
    "wof:placetype":"locality"
},
  "geometry": {"coordinates":[125.44750000000001,40.63889],"type":"Point"}
}