{
  "type": "Feature",
  "properties": {
    "gn:admin1_code":"17.0",
    "gn:asciiname":"Namidongch'op'yong",
    "gn:country_code":"KP",
    "gn:dem":346,
    "gn:feature_class":"P",
    "gn:feature_code":"PPL",
    "gn:name":"Namidongch\u2019op\u2019y\u014fng",
    "gn:population":0,
    "gn:timezone":"Asia/Pyongyang",
    "iso:country":"KP",
    "wof:name":"Namidongch'op'yong",
    "wof:placetype":"locality"
},
  "geometry": {"coordinates":[129.37611000000001,40.90694000000001],"type":"Point"}
}