{
  "type": "Feature",
  "properties": {
    "gn:admin1_code":"1.0",
    "gn:asciiname":"Yongt'al-li",
    "gn:country_code":"KP",
    "gn:dem":226,
    "gn:feature_class":"P",
    "gn:feature_code":"PPL",
    "gn:name":"Yongt\u2019al-li",
    "gn:population":0,
    "gn:timezone":"Asia/Pyongyang",
    "iso:country":"KP",
    "name:und_x_variant":[
        "Yongt\u2019an-dong",
        "Yongt\u2019an-ni",
        "\ub8e1\ud0c4\ub9ac",
        "Yongt\u2019al-li"
    ],
    "wof:name":"Yongt'al-li",
    "wof:placetype":"locality"
},
  "geometry": {"coordinates":[126.16139,40.89],"type":"Point"}
}