{
  "type": "Feature",
  "properties": {
    "gn:admin1_code":"6.0",
    "gn:asciiname":"Sangsokkyo",
    "gn:country_code":"KP",
    "gn:dem":94,
    "gn:feature_class":"P",
    "gn:feature_code":"PPL",
    "gn:name":"Sangs\u014fkkyo",
    "gn:population":0,
    "gn:timezone":"Asia/Pyongyang",
    "iso:country":"KP",
    "name:kor_x_preferred":[
        "\uc0c1\uc11d\uad50"
    ],
    "name:kor_x_variant":[
        "Sangs\u014fkkyo"
    ],
    "wof:name":"Sangsokkyo",
    "wof:placetype":"locality"
},
  "geometry": {"coordinates":[125.28806000000002,38.28083],"type":"Point"}
}