{
  "type": "Feature",
  "properties": {
    "gn:admin1_code":"12.0",
    "gn:asciiname":"Che-dong",
    "gn:country_code":"KP",
    "gn:dem":31,
    "gn:feature_class":"P",
    "gn:feature_code":"PPL",
    "gn:name":"Che-dong",
    "gn:population":0,
    "gn:timezone":"Asia/Pyongyang",
    "iso:country":"KP",
    "name:und_x_variant":[
        "\uc81c\ub3d9",
        "Che-dong",
        "Jedong"
    ],
    "wof:name":"Che-dong",
    "wof:placetype":"locality"
},
  "geometry": {"coordinates":[125.74778000000001,38.94528],"type":"Point"}
}