{
  "type": "Feature",
  "properties": {
    "gn:admin1_code":"15.0",
    "gn:asciiname":"Soha-ri",
    "gn:country_code":"KP",
    "gn:dem":235,
    "gn:feature_class":"P",
    "gn:feature_code":"PPL",
    "gn:name":"Soha-ri",
    "gn:population":0,
    "gn:timezone":"Asia/Pyongyang",
    "iso:country":"KP",
    "name:kor_x_preferred":[
        "\uc18c\ud558\ub9ac"
    ],
    "wof:name":"Soha-ri",
    "wof:placetype":"locality"
},
  "geometry": {"coordinates":[126.53778,39.64833],"type":"Point"}
}