{
  "type": "Feature",
  "properties": {
    "gn:admin1_code":"0.0",
    "gn:asciiname":"Milchol-li",
    "gn:country_code":"KP",
    "gn:dem":152,
    "gn:feature_class":"P",
    "gn:feature_code":"PPL",
    "gn:name":"Milch\u014fl-li",
    "gn:population":0,
    "gn:timezone":"Asia/Pyongyang",
    "iso:country":"KP",
    "name:kor_x_preferred":[
        "\ubc00\ucc9c\ub9ac"
    ],
    "name:und_x_variant":[
        "Milch\u014fl-li",
        "Milch\u014fn-ni"
    ],
    "wof:name":"Milchol-li",
    "wof:placetype":"locality"
},
  "geometry": {"coordinates":[126.23333,39.48333],"type":"Point"}
}