{
  "type": "Feature",
  "properties": {
    "gn:admin1_code":"7.0",
    "gn:asciiname":"Nondulgori",
    "gn:country_code":"KP",
    "gn:dem":150,
    "gn:feature_class":"P",
    "gn:feature_code":"PPL",
    "gn:name":"Nond\u016dlg\u014fri",
    "gn:population":0,
    "gn:timezone":"Asia/Pyongyang",
    "iso:country":"KP",
    "name:kor_x_preferred":[
        "\ub17c\ub4e4\uac70\ub9ac"
    ],
    "name:kor_x_variant":[
        "Nond\u016dlg\u014fri"
    ],
    "wof:name":"Nondulgori",
    "wof:placetype":"locality"
},
  "geometry": {"coordinates":[126.58,38.56444000000001],"type":"Point"}
}