{
  "type": "Feature",
  "properties": {
    "gn:admin1_code":"17.0",
    "gn:asciiname":"Puhungbau",
    "gn:country_code":"KP",
    "gn:dem":872,
    "gn:feature_class":"P",
    "gn:feature_code":"PPL",
    "gn:name":"Puh\u016dngbau",
    "gn:population":0,
    "gn:timezone":"Asia/Pyongyang",
    "iso:country":"KP",
    "name:und_x_variant":[
        "\ubd80\ud765\ubc14\uc6b0",
        "Puh\u016dngbau"
    ],
    "wof:name":"Puhungbau",
    "wof:placetype":"locality"
},
  "geometry": {"coordinates":[129.30944,42.13639000000001],"type":"Point"}
}