{
  "type": "Feature",
  "properties": {
    "gn:admin1_code":"11.0",
    "gn:asciiname":"Sin-gol",
    "gn:country_code":"KP",
    "gn:dem":28,
    "gn:feature_class":"P",
    "gn:feature_code":"PPL",
    "gn:name":"Sin-gol",
    "gn:population":0,
    "gn:timezone":"Asia/Pyongyang",
    "iso:country":"KP",
    "name:und_x_variant":[
        "\uc2e0\uace8",
        "Sin-gol"
    ],
    "wof:name":"Sin-gol",
    "wof:placetype":"locality"
},
  "geometry": {"coordinates":[124.545,40.08639],"type":"Point"}
}