{
  "type": "Feature",
  "properties": {
    "gn:admin1_code":"1.0",
    "gn:asciiname":"Sangsong-dong",
    "gn:country_code":"KP",
    "gn:dem":240,
    "gn:feature_class":"P",
    "gn:feature_code":"PPL",
    "gn:name":"Sangs\u014fng-dong",
    "gn:population":0,
    "gn:timezone":"Asia/Pyongyang",
    "iso:country":"KP",
    "name:und_x_variant":[
        "\uc0c1\uc131\ub3d9",
        "Sangs\u014fng-dong"
    ],
    "wof:name":"Sangsong-dong",
    "wof:placetype":"locality"
},
  "geometry": {"coordinates":[126.12888999999998,41.01833],"type":"Point"}
}