{
  "type": "Feature",
  "properties": {
    "gn:country":"KP",
    "gn:fcode":"PPL",
    "gn:population":19995,
    "iso:country":"KP",
    "name:deu_x_preferred":[
        "Anak"
    ],
    "name:fra_x_preferred":[
        "Anak"
    ],
    "name:heb_x_preferred":[
        "\u05e2\u05e0\u05e7#\u05d4\u05e2\u05e0\u05e7\u05d9\u05dd \u05d1\u05de\u05e7\u05e8\u05d0"
    ],
    "name:ind_x_preferred":[
        "Enak"
    ],
    "name:kor_x_preferred":[
        "\uc548\uc545"
    ],
    "name:nld_x_preferred":[
        "Enak"
    ],
    "name:por_x_preferred":[
        "Enaque"
    ],
    "name:und_x_variant":[
        "Nangaku"
    ],
    "qs_pg:aaroncc":"KP",
    "qs_pg:gn_country":"KP",
    "qs_pg:gn_fcode":"PPL",
    "qs_pg:gn_pop":19995,
    "qs_pg:name":"Anak",
    "qs_pg:photos_9r":0,
    "qs_pg:photos_sr":0,
    "qs_pg:pop_sr":6,
    "qs_pg:qs_pg_placetype":"locality",
    "wof:name":"Anak",
    "wof:placetype":"locality",
    "wof:population":19995
},
  "geometry": {"coordinates":[125.49417,38.51083],"type":"Point"}
}