{
  "type": "Feature",
  "properties": {
    "gn:gn_country":"KP",
    "gn:gn_fcode":"PPL",
    "gn:gn_pop":19995,
    "gn:population":19995,
    "iso:country":"KP",
    "name:kor_x_preferred":[
        "\uc548\uc545"
    ],
    "name:unk_x_variant":[
        "Nangaku"
    ],
    "qs_pg:aaroncc":"KP",
    "qs_pg:gn_country":"KP",
    "qs_pg:gn_fcode":"PPL",
    "qs_pg:gn_pop":19995,
    "qs_pg:name":"Anak",
    "qs_pg:photos_9r":0,
    "qs_pg:photos_sr":0,
    "qs_pg:pop_sr":6,
    "qs_pg:qs_pg_placetype":"locality",
    "wof:name":"Anak",
    "wof:placetype":"locality",
    "wof:population":19995
},
  "geometry": {"coordinates":[125.49417,38.51083],"type":"Point"}
}