{
  "type": "Feature",
  "properties": {
    "gn:admin1_code":"11.0",
    "gn:asciiname":"Taemaeng-ni",
    "gn:country_code":"KP",
    "gn:dem":107,
    "gn:feature_class":"P",
    "gn:feature_code":"PPL",
    "gn:name":"Taemaeng-ni",
    "gn:population":0,
    "gn:timezone":"Asia/Pyongyang",
    "iso:country":"KP",
    "wof:name":"Taemaeng-ni",
    "wof:placetype":"locality"
},
  "geometry": {"coordinates":[125.22111,39.97778],"type":"Point"}
}