{
  "type": "Feature",
  "properties": {
    "gn:admin1_code":"17.0",
    "gn:admin2_code":"2038910",
    "gn:asciiname":"Tonae",
    "gn:country_code":"KP",
    "gn:dem":623,
    "gn:feature_class":"P",
    "gn:feature_code":"PPL",
    "gn:name":"Tonae",
    "gn:population":0,
    "gn:timezone":"Asia/Pyongyang",
    "iso:country":"KP",
    "wof:name":"Tonae",
    "wof:placetype":"locality"
},
  "geometry": {"coordinates":[129.09028000000001,41.97889],"type":"Point"}
}