{
  "type": "Feature",
  "properties": {
    "gn:admin1_code":"11.0",
    "gn:asciiname":"Kalsal-li",
    "gn:country_code":"KP",
    "gn:dem":33,
    "gn:feature_class":"P",
    "gn:feature_code":"PPL",
    "gn:name":"Kalsal-li",
    "gn:population":0,
    "gn:timezone":"Asia/Pyongyang",
    "iso:country":"KP",
    "name:und_x_variant":[
        "\uac08\uc0b0\ub9ac",
        "Kalsan-ni",
        "Kalsal-li"
    ],
    "wof:name":"Kalsal-li",
    "wof:placetype":"locality"
},
  "geometry": {"coordinates":[124.54889,40.03167],"type":"Point"}
}