{
  "type": "Feature",
  "properties": {
    "gn:admin1_code":"7.0",
    "gn:asciiname":"Munam-dong",
    "gn:country_code":"KP",
    "gn:dem":56,
    "gn:feature_class":"P",
    "gn:feature_code":"PPL",
    "gn:name":"Munam-dong",
    "gn:population":0,
    "gn:timezone":"Asia/Pyongyang",
    "iso:country":"KP",
    "name:kor_x_preferred":[
        "\ubb38\uc554\ub3d9"
    ],
    "wof:name":"Munam-dong",
    "wof:placetype":"locality"
},
  "geometry": {"coordinates":[126.58722,38.31167],"type":"Point"}
}