{
  "type": "Feature",
  "properties": {
    "gn:admin1_code":"12.0",
    "gn:asciiname":"Sinjong-ni",
    "gn:country_code":"KP",
    "gn:dem":11,
    "gn:feature_class":"P",
    "gn:feature_code":"PPL",
    "gn:name":"Sinj\u014fng-ni",
    "gn:population":0,
    "gn:timezone":"Asia/Pyongyang",
    "iso:country":"KP",
    "name:kor_x_preferred":[
        "\uc2e0\uc815\ub9ac"
    ],
    "name:und_x_variant":[
        "Sinj\u014fng-ni",
        "Sinjeongni"
    ],
    "wof:name":"Sinjong-ni",
    "wof:placetype":"locality"
},
  "geometry": {"coordinates":[125.63325,38.83488],"type":"Point"}
}