{
  "type": "Feature",
  "properties": {
    "gn:admin1_code":"11.0",
    "gn:asciiname":"Yongung-ni",
    "gn:country_code":"KP",
    "gn:dem":166,
    "gn:feature_class":"P",
    "gn:feature_code":"PPL",
    "gn:name":"Y\u014fngung-ni",
    "gn:population":0,
    "gn:timezone":"Asia/Pyongyang",
    "iso:country":"KP",
    "name:eng_x_preferred":[
        "Yongung"
    ],
    "name:eng_x_variant":[
        "Yongung-ni"
    ],
    "name:und_x_variant":[
        "\uc601\uc6c5\ub9ac",
        "Y\u014fngung-ni"
    ],
    "wof:name":"Yongung",
    "wof:placetype":"locality"
},
  "geometry": {"coordinates":[125.93361,40.15528],"type":"Point"}
}