{
  "type": "Feature",
  "properties": {
    "gn:admin1_code":"13.0",
    "gn:asciiname":"Chihadok",
    "gn:country_code":"KP",
    "gn:dem":663,
    "gn:feature_class":"P",
    "gn:feature_code":"PPL",
    "gn:name":"Chihad\u014fk",
    "gn:population":0,
    "gn:timezone":"Asia/Pyongyang",
    "iso:country":"KP",
    "name:kor_x_preferred":[
        "\uc9c0\ud558\ub355"
    ],
    "name:und_x_variant":[
        "Chihad\u014fk",
        "Chiyad\u014fng-ni"
    ],
    "wof:name":"Chihadok",
    "wof:placetype":"locality"
},
  "geometry": {"coordinates":[127.60639,41.27472],"type":"Point"}
}