{
  "type": "Feature",
  "properties": {
    "gn:admin1_code":"9.0",
    "gn:admin2_code":"1875980",
    "gn:asciiname":"Araet'apkori",
    "gn:country_code":"KP",
    "gn:dem":349,
    "gn:feature_class":"P",
    "gn:feature_code":"PPL",
    "gn:name":"Araet\u2019apk\u014fri",
    "gn:population":0,
    "gn:timezone":"Asia/Pyongyang",
    "iso:country":"KP",
    "wof:name":"Araet'apkori",
    "wof:placetype":"locality"
},
  "geometry": {"coordinates":[127.52443999999998,38.45722],"type":"Point"}
}