{
  "type": "Feature",
  "properties": {
    "gn:admin1_code":"11.0",
    "gn:asciiname":"Wonhwadongdong-gol",
    "gn:country_code":"KP",
    "gn:dem":18,
    "gn:feature_class":"P",
    "gn:feature_code":"PPL",
    "gn:name":"W\u014fnhwadongdong-gol",
    "gn:population":0,
    "gn:timezone":"Asia/Pyongyang",
    "iso:country":"KP",
    "name:und_x_variant":[
        "\uc6d0\ud654\ub3d9\ub3d9\uace8",
        "W\u014fnhwadongdong-gol"
    ],
    "wof:name":"Wonhwadongdong-gol",
    "wof:placetype":"locality"
},
  "geometry": {"coordinates":[124.54806000000001,40.20972],"type":"Point"}
}