{
  "type": "Feature",
  "properties": {
    "gn:admin1_code":"9.0",
    "gn:asciiname":"Sadong-ni",
    "gn:country_code":"KP",
    "gn:dem":432,
    "gn:feature_class":"P",
    "gn:feature_code":"PPL",
    "gn:name":"Sadong-ni",
    "gn:population":0,
    "gn:timezone":"Asia/Pyongyang",
    "iso:country":"KP",
    "name:und_x_variant":[
        "\uc0ac\ub3d9\ub9ac",
        "Sadong-ni"
    ],
    "wof:name":"Sadong-ni",
    "wof:placetype":"locality"
},
  "geometry": {"coordinates":[127.82250000000001,38.64056],"type":"Point"}
}