{
  "type": "Feature",
  "properties": {
    "gn:admin1_code":"1.0",
    "gn:asciiname":"Tonggakchang",
    "gn:country_code":"KP",
    "gn:dem":372,
    "gn:feature_class":"P",
    "gn:feature_code":"PPL",
    "gn:name":"Tonggakchang",
    "gn:population":0,
    "gn:timezone":"Asia/Pyongyang",
    "iso:country":"KP",
    "name:und_x_variant":[
        "\ub3d9\uace1\uc7a5",
        "Tonggakchang"
    ],
    "wof:name":"Tonggakchang",
    "wof:placetype":"locality"
},
  "geometry": {"coordinates":[126.59972,41.32278],"type":"Point"}
}