{
  "type": "Feature",
  "properties": {
    "gn:admin1_code":"18.0",
    "gn:asciiname":"Ihonok",
    "gn:country_code":"KP",
    "gn:dem":14,
    "gn:feature_class":"P",
    "gn:feature_code":"PPL",
    "gn:name":"Ih\u014fnok",
    "gn:population":0,
    "gn:timezone":"Asia/Pyongyang",
    "iso:country":"KP",
    "name:und_x_variant":[
        "\uc774\ud5cc\uc625",
        "Ih\u014fnok",
        "Iheonok"
    ],
    "wof:name":"Ihonok",
    "wof:placetype":"locality"
},
  "geometry": {"coordinates":[130.50611000000001,42.60583],"type":"Point"}
}