{
  "type": "Feature",
  "properties": {
    "gn:admin1_code":"15.0",
    "gn:admin2_code":"T\u014fkch\u2019\u014fn-si",
    "gn:asciiname":"Malguri",
    "gn:country_code":"KP",
    "gn:dem":260,
    "gn:feature_class":"P",
    "gn:feature_code":"PPL",
    "gn:name":"Malguri",
    "gn:population":0,
    "gn:timezone":"Asia/Pyongyang",
    "iso:country":"KP",
    "wof:name":"Malguri",
    "wof:placetype":"locality"
},
  "geometry": {"coordinates":[126.12528,39.64417],"type":"Point"}
}