{
  "type": "Feature",
  "properties": {
    "gn:admin1_code":"6.0",
    "gn:asciiname":"Chedo-ri",
    "gn:cc2":"KP",
    "gn:country_code":"KP",
    "gn:dem":16,
    "gn:feature_class":"P",
    "gn:feature_code":"PPL",
    "gn:name":"Chedo-ri",
    "gn:population":0,
    "gn:timezone":"Asia/Pyongyang",
    "iso:country":"KP",
    "name:und_x_variant":[
        "Chot\u014d-ri",
        "Ch\u014fdo-ri",
        "\uc81c\ub3c4\ub9ac",
        "Chedo-ri"
    ],
    "wof:name":"Chedo-ri",
    "wof:placetype":"locality"
},
  "geometry": {"coordinates":[125.39,38.68083],"type":"Point"}
}