{
  "type": "Feature",
  "properties": {
    "gn:admin1_code":"6.0",
    "gn:asciiname":"Soksong-ni",
    "gn:country_code":"KP",
    "gn:dem":46,
    "gn:feature_class":"P",
    "gn:feature_code":"PPL",
    "gn:name":"S\u014fks\u014fng-ni",
    "gn:population":0,
    "gn:timezone":"Asia/Pyongyang",
    "iso:country":"KP",
    "name:eng_x_preferred":[
        "Soksong"
    ],
    "name:eng_x_variant":[
        "Soksong-ni"
    ],
    "name:kor_x_preferred":[
        "\uc11d\uc131\ub9ac"
    ],
    "name:kor_x_variant":[
        "S\u014fks\u014fng-ni"
    ],
    "wof:name":"Soksong",
    "wof:placetype":"locality"
},
  "geometry": {"coordinates":[125.38194,38.48611],"type":"Point"}
}