{
  "type": "Feature",
  "properties": {
    "gn:admin1_code":"7.0",
    "gn:asciiname":"P'oumjang",
    "gn:country_code":"KP",
    "gn:dem":86,
    "gn:feature_class":"P",
    "gn:feature_code":"PPL",
    "gn:name":"P\u2019o\u016dmjang",
    "gn:population":0,
    "gn:timezone":"Asia/Pyongyang",
    "iso:country":"KP",
    "name:kor_x_preferred":[
        "\ud3ec\uc74c\uc7a5"
    ],
    "name:kor_x_variant":[
        "P\u2019o\u016dmjang"
    ],
    "name:und_x_variant":[
        "Sambung-ni"
    ],
    "wof:name":"P'oumjang",
    "wof:placetype":"locality"
},
  "geometry": {"coordinates":[126.46111000000001,38.65583],"type":"Point"}
}