{
  "type": "Feature",
  "properties": {
    "gn:admin1_code":"11.0",
    "gn:asciiname":"Sosang-ni",
    "gn:country_code":"KP",
    "gn:dem":145,
    "gn:feature_class":"P",
    "gn:feature_code":"PPL",
    "gn:name":"Sosang-ni",
    "gn:population":0,
    "gn:timezone":"Asia/Pyongyang",
    "iso:country":"KP",
    "name:kor_x_preferred":[
        "\uc18c\uc0c1\ub9ac"
    ],
    "wof:name":"Sosang-ni",
    "wof:placetype":"locality"
},
  "geometry": {"coordinates":[125.08722,39.87056],"type":"Point"}
}