{
  "type": "Feature",
  "properties": {
    "gn:admin1_code":"6.0",
    "gn:asciiname":"Songch'ol-li",
    "gn:country_code":"KP",
    "gn:dem":13,
    "gn:feature_class":"P",
    "gn:feature_code":"PPL",
    "gn:name":"Songch\u2019\u014fl-li",
    "gn:population":0,
    "gn:timezone":"Asia/Pyongyang",
    "iso:country":"KP",
    "name:und_x_variant":[
        "Songch\u2019\u014fn-ni",
        "Songch\u2019\u014fl-li"
    ],
    "wof:name":"Songch'ol-li",
    "wof:placetype":"locality"
},
  "geometry": {"coordinates":[126.1425,37.86583],"type":"Point"}
}