{
  "type": "Feature",
  "properties": {
    "gn:admin1_code":"9.0",
    "gn:asciiname":"Sudok-tong",
    "gn:country_code":"KP",
    "gn:dem":534,
    "gn:feature_class":"P",
    "gn:feature_code":"PPL",
    "gn:name":"Sud\u014fk-tong",
    "gn:population":0,
    "gn:timezone":"Asia/Pyongyang",
    "iso:country":"KP",
    "name:und_x_variant":[
        "\uc218\ub355\ub3d9",
        "Sud\u014fk-tong"
    ],
    "wof:name":"Sudok-tong",
    "wof:placetype":"locality"
},
  "geometry": {"coordinates":[127.51361,38.62083],"type":"Point"}
}