{
  "type": "Feature",
  "properties": {
    "gn:admin1_code":"18.0",
    "gn:asciiname":"Chakso-dong",
    "gn:country_code":"KP",
    "gn:dem":20,
    "gn:feature_class":"P",
    "gn:feature_code":"PPL",
    "gn:name":"Chakso-dong",
    "gn:population":0,
    "gn:timezone":"Asia/Pyongyang",
    "iso:country":"KP",
    "name:und_x_variant":[
        "\uc791\uc18c\ub3d9",
        "Chakso-dong",
        "Jaksodong"
    ],
    "wof:name":"Chakso-dong",
    "wof:placetype":"locality"
},
  "geometry": {"coordinates":[130.20111,42.21389],"type":"Point"}
}