{
  "type": "Feature",
  "properties": {
    "gn:admin1_code":"3.0",
    "gn:asciiname":"Sangsinp'ung-ni",
    "gn:country_code":"KP",
    "gn:dem":27,
    "gn:feature_class":"P",
    "gn:feature_code":"PPL",
    "gn:name":"Sangsinp\u2019ung-ni",
    "gn:population":0,
    "gn:timezone":"Asia/Pyongyang",
    "iso:country":"KP",
    "name:und_x_variant":[
        "\uc0c1\uc2e0\ud48d\ub9ac",
        "Sinp\u2019ung-ni",
        "Sangsinp\u2019ung-ni"
    ],
    "wof:name":"Sangsinp'ung-ni",
    "wof:placetype":"locality"
},
  "geometry": {"coordinates":[127.60389000000001,39.98222],"type":"Point"}
}