{
  "type": "Feature",
  "properties": {
    "gn:admin1_code":"7.0",
    "gn:asciiname":"Tok-tong",
    "gn:country_code":"KP",
    "gn:dem":106,
    "gn:feature_class":"P",
    "gn:feature_code":"PPL",
    "gn:name":"T\u014fk-tong",
    "gn:population":0,
    "gn:timezone":"Asia/Pyongyang",
    "iso:country":"KP",
    "wof:name":"Tok-tong",
    "wof:placetype":"locality"
},
  "geometry": {"coordinates":[126.66583,38.39111],"type":"Point"}
}