{
  "type": "Feature",
  "properties": {
    "gn:admin1_code":"17.0",
    "gn:asciiname":"Kumsong-ni",
    "gn:country_code":"KP",
    "gn:dem":199,
    "gn:feature_class":"P",
    "gn:feature_code":"PPL",
    "gn:name":"K\u016dmsong-ni",
    "gn:population":0,
    "gn:timezone":"Asia/Pyongyang",
    "iso:country":"KP",
    "name:eng_x_preferred":[
        "Kumsong"
    ],
    "name:eng_x_variant":[
        "Kumsong-ni"
    ],
    "name:und_x_variant":[
        "K\u016dmsong-dong",
        "\uae08\uc1a1\ub9ac",
        "K\u016dmsong-ni"
    ],
    "wof:name":"Kumsong",
    "wof:placetype":"locality"
},
  "geometry": {"coordinates":[129.35111000000001,41.02028],"type":"Point"}
}