{
  "type": "Feature",
  "properties": {
    "gn:admin1_code":"0.0",
    "gn:asciiname":"Unhak-tong",
    "gn:country_code":"KP",
    "gn:dem":118,
    "gn:feature_class":"P",
    "gn:feature_code":"PPL",
    "gn:name":"Unhak-tong",
    "gn:population":0,
    "gn:timezone":"Asia/Pyongyang",
    "iso:country":"KP",
    "name:kor_x_preferred":[
        "\uc6b4\ud559\ub3d9"
    ],
    "wof:name":"Unhak-tong",
    "wof:placetype":"locality"
},
  "geometry": {"coordinates":[125.43333,39.61667],"type":"Point"}
}