{
  "type": "Feature",
  "properties": {
    "gn:admin1_code":"3.0",
    "gn:asciiname":"Kando",
    "gn:country_code":"KP",
    "gn:dem":96,
    "gn:feature_class":"P",
    "gn:feature_code":"PPL",
    "gn:name":"Kando",
    "gn:population":0,
    "gn:timezone":"Asia/Pyongyang",
    "iso:country":"KP",
    "name:und_x_variant":[
        "\uac04\ub3c4"
    ],
    "wof:name":"Kando",
    "wof:placetype":"locality"
},
  "geometry": {"coordinates":[128.20533999999998,40.24522],"type":"Point"}
}