{
  "type": "Feature",
  "properties": {
    "gn:admin1_code":"12.0",
    "gn:admin2_code":"S\u016dngho-guy\u014fk",
    "gn:asciiname":"T'ogyo",
    "gn:country_code":"KP",
    "gn:dem":60,
    "gn:feature_class":"P",
    "gn:feature_code":"PPL",
    "gn:name":"T\u2019ogyo",
    "gn:population":0,
    "gn:timezone":"Asia/Pyongyang",
    "iso:country":"KP",
    "wof:name":"T'ogyo",
    "wof:placetype":"locality"
},
  "geometry": {"coordinates":[126.09111,39.01222],"type":"Point"}
}