{
  "type": "Feature",
  "properties": {
    "gn:admin1_code":"11.0",
    "gn:asciiname":"Tongdang-dong",
    "gn:country_code":"KP",
    "gn:dem":10,
    "gn:feature_class":"P",
    "gn:feature_code":"PPL",
    "gn:name":"Tongdang-dong",
    "gn:population":0,
    "gn:timezone":"Asia/Pyongyang",
    "iso:country":"KP",
    "name:und_x_variant":[
        "\ub3d9\ub2f9\ub3d9",
        "Tongdang-dong"
    ],
    "wof:name":"Tongdang-dong",
    "wof:placetype":"locality"
},
  "geometry": {"coordinates":[124.52972,39.91722],"type":"Point"}
}