{
  "type": "Feature",
  "properties": {
    "gn:admin1_code":"6.0",
    "gn:asciiname":"Chonsan",
    "gn:country_code":"KP",
    "gn:dem":44,
    "gn:feature_class":"P",
    "gn:feature_code":"PPL",
    "gn:name":"Ch\u014fnsan",
    "gn:population":0,
    "gn:timezone":"Asia/Pyongyang",
    "iso:country":"KP",
    "name:kor_x_preferred":[
        "\uc804\uc0b0"
    ],
    "name:kor_x_variant":[
        "Ch\u014fnsan"
    ],
    "wof:name":"Chonsan",
    "wof:placetype":"locality"
},
  "geometry": {"coordinates":[125.37111000000002,38.45389],"type":"Point"}
}