{
  "type": "Feature",
  "properties": {
    "gn:admin1_code":"13.0",
    "gn:asciiname":"Tanjil-li",
    "gn:cc2":"KP",
    "gn:country_code":"KP",
    "gn:dem":1078,
    "gn:feature_class":"P",
    "gn:feature_code":"PPL",
    "gn:name":"Tanjil-li",
    "gn:population":0,
    "gn:timezone":"Asia/Pyongyang",
    "iso:country":"KP",
    "name:kor_x_preferred":[
        "\ub2e8\uc9c4\ub9ac"
    ],
    "name:und_x_variant":[
        "Tanjin-ni",
        "Tanjil-li"
    ],
    "wof:name":"Tanjil-li",
    "wof:placetype":"locality"
},
  "geometry": {"coordinates":[128.13556,41.01833],"type":"Point"}
}