{
  "type": "Feature",
  "properties": {
    "gn:admin1_code":"17.0",
    "gn:asciiname":"Tukki",
    "gn:country_code":"KP",
    "gn:dem":903,
    "gn:feature_class":"P",
    "gn:feature_code":"PPL",
    "gn:name":"T\u016dkki",
    "gn:population":0,
    "gn:timezone":"Asia/Pyongyang",
    "iso:country":"KP",
    "name:und_x_variant":[
        "\ub4dd\uae30",
        "T\u016dkki"
    ],
    "wof:name":"Tukki",
    "wof:placetype":"locality"
},
  "geometry": {"coordinates":[129.30722,41.46611],"type":"Point"}
}