{
  "type": "Feature",
  "properties": {
    "gn:admin1_code":"15.0",
    "gn:asciiname":"Ch'angdong-ni",
    "gn:country_code":"KP",
    "gn:dem":8,
    "gn:feature_class":"P",
    "gn:feature_code":"PPL",
    "gn:name":"Ch\u2019angdong-ni",
    "gn:population":0,
    "gn:timezone":"Asia/Pyongyang",
    "iso:country":"KP",
    "name:kor_x_preferred":[
        "\ucc3d\ub3d9\ub9ac"
    ],
    "name:kor_x_variant":[
        "Ch\u2019angdong-ni"
    ],
    "wof:name":"Ch'angdong-ni",
    "wof:placetype":"locality"
},
  "geometry": {"coordinates":[125.39583,39.42444],"type":"Point"}
}