{
  "type": "Feature",
  "properties": {
    "gn:admin1_code":"0.0",
    "gn:asciiname":"Kogae-dong",
    "gn:country_code":"KP",
    "gn:dem":1360,
    "gn:feature_class":"P",
    "gn:feature_code":"PPL",
    "gn:name":"Kogae-dong",
    "gn:population":0,
    "gn:timezone":"Asia/Pyongyang",
    "iso:country":"KP",
    "name:kor_x_preferred":[
        "\uace0\uac1c\ub3d9"
    ],
    "wof:name":"Kogae-dong",
    "wof:placetype":"locality"
},
  "geometry": {"coordinates":[127.18333,40.65],"type":"Point"}
}