{
  "type": "Feature",
  "properties": {
    "gn:admin1_code":"15.0",
    "gn:asciiname":"Ch'oryosan",
    "gn:country_code":"KP",
    "gn:dem":19,
    "gn:feature_class":"P",
    "gn:feature_code":"PPL",
    "gn:name":"Ch\u2019oryosan",
    "gn:population":0,
    "gn:timezone":"Asia/Pyongyang",
    "iso:country":"KP",
    "name:und_x_variant":[
        "\ucd08\ub8cc\uc0b0",
        "Ch\u2019oryosan"
    ],
    "wof:name":"Ch'oryosan",
    "wof:placetype":"locality"
},
  "geometry": {"coordinates":[125.30056,38.98306],"type":"Point"}
}