{
  "type": "Feature",
  "properties": {
    "gn:admin1_code":"11.0",
    "gn:asciiname":"Songhyon",
    "gn:country_code":"KP",
    "gn:dem":25,
    "gn:feature_class":"P",
    "gn:feature_code":"PPL",
    "gn:name":"Songhy\u014fn",
    "gn:population":0,
    "gn:timezone":"Asia/Pyongyang",
    "iso:country":"KP",
    "name:kor_x_preferred":[
        "\uc1a1\ud604"
    ],
    "name:kor_x_variant":[
        "Songhy\u014fn"
    ],
    "wof:name":"Songhyon",
    "wof:placetype":"locality"
},
  "geometry": {"coordinates":[125.10389000000001,39.66694],"type":"Point"}
}