{
  "type": "Feature",
  "properties": {
    "gn:admin1_code":"3.0",
    "gn:asciiname":"Suhung-ni",
    "gn:country_code":"KP",
    "gn:dem":21,
    "gn:feature_class":"P",
    "gn:feature_code":"PPL",
    "gn:name":"Suh\u016dng-ni",
    "gn:population":0,
    "gn:timezone":"Asia/Pyongyang",
    "iso:country":"KP",
    "name:und_x_variant":[
        "\uc218\ud765\ub9ac",
        "Suh\u016dng-ni"
    ],
    "wof:name":"Suhung-ni",
    "wof:placetype":"locality"
},
  "geometry": {"coordinates":[127.44917,39.87806],"type":"Point"}
}