{
  "type": "Feature",
  "properties": {
    "gn:admin1_code":"1.0",
    "gn:asciiname":"Chisin-dong",
    "gn:cc2":"KP",
    "gn:country_code":"KP",
    "gn:dem":172,
    "gn:feature_class":"P",
    "gn:feature_code":"PPL",
    "gn:name":"Chisin-dong",
    "gn:population":0,
    "gn:timezone":"Asia/Pyongyang",
    "iso:country":"KP",
    "name:kor_x_preferred":[
        "\uc9c0\uc2e0\ub3d9"
    ],
    "name:und_x_variant":[
        "Chisin-ni",
        "Chisin-dong"
    ],
    "wof:name":"Chisin-dong",
    "wof:placetype":"locality"
},
  "geometry": {"coordinates":[126.24139,40.21361],"type":"Point"}
}