{
  "type": "Feature",
  "properties": {
    "gn:admin1_code":"9.0",
    "gn:admin2_code":"Sep\u2019o-gun",
    "gn:asciiname":"Sambang-ni",
    "gn:country_code":"KP",
    "gn:dem":358,
    "gn:feature_class":"P",
    "gn:feature_code":"PPL",
    "gn:name":"Sambang-ni",
    "gn:population":0,
    "gn:timezone":"Asia/Pyongyang",
    "iso:country":"KP",
    "name:eng_x_preferred":[
        "Sambang"
    ],
    "name:eng_x_variant":[
        "Sambang-ni"
    ],
    "name:und_x_variant":[
        "Samb\u014d-ri",
        "Sampori",
        "Sambang-ni"
    ],
    "wof:name":"Sambang",
    "wof:placetype":"locality"
},
  "geometry": {"coordinates":[127.37444000000001,38.73944],"type":"Point"}
}