{
  "type": "Feature",
  "properties": {
    "gn:admin1_code":"3.0",
    "gn:asciiname":"Tongdong-ni",
    "gn:country_code":"KP",
    "gn:dem":157,
    "gn:feature_class":"P",
    "gn:feature_code":"PPL",
    "gn:name":"Tongd\u014fng-ni",
    "gn:population":0,
    "gn:timezone":"Asia/Pyongyang",
    "iso:country":"KP",
    "name:eng_x_preferred":[
        "Tongdong"
    ],
    "name:eng_x_variant":[
        "Tongdong-ni"
    ],
    "name:und_x_variant":[
        "\ub3d9\ub355\ub9ac",
        "Tongd\u014fng-ni"
    ],
    "wof:name":"Tongdong",
    "wof:placetype":"locality"
},
  "geometry": {"coordinates":[127.54083,40.22611],"type":"Point"}
}