{
  "type": "Feature",
  "properties": {
    "gn:admin1_code":"11.0",
    "gn:asciiname":"Songdong-ni",
    "gn:country_code":"KP",
    "gn:dem":20,
    "gn:feature_class":"P",
    "gn:feature_code":"PPL",
    "gn:name":"S\u014fngdong-ni",
    "gn:population":0,
    "gn:timezone":"Asia/Pyongyang",
    "iso:country":"KP",
    "name:eng_x_preferred":[
        "Songdong"
    ],
    "name:eng_x_variant":[
        "Songdong-ni"
    ],
    "name:und_x_variant":[
        "S\u014fngdong-dong",
        "S\u014fng-dong",
        "\uc131\ub3d9\ub9ac",
        "S\u014fngdong-ni"
    ],
    "wof:name":"Songdong",
    "wof:placetype":"locality"
},
  "geometry": {"coordinates":[124.56833,39.97083],"type":"Point"}
}