{
  "type": "Feature",
  "properties": {
    "gn:admin1_code":"7.0",
    "gn:asciiname":"Sirungsan",
    "gn:country_code":"KP",
    "gn:dem":133,
    "gn:feature_class":"P",
    "gn:feature_code":"PPL",
    "gn:name":"Sir\u016dngsan",
    "gn:population":0,
    "gn:timezone":"Asia/Pyongyang",
    "iso:country":"KP",
    "name:kor_x_preferred":[
        "\uc2e4\uc751\uc0b0"
    ],
    "name:kor_x_variant":[
        "Sir\u016dngsan"
    ],
    "name:und_x_variant":[
        "Sur\u016dngsan"
    ],
    "wof:name":"Sirungsan",
    "wof:placetype":"locality"
},
  "geometry": {"coordinates":[126.42778,38.7275],"type":"Point"}
}