{
  "type": "Feature",
  "properties": {
    "gn:admin1_code":"0.0",
    "gn:asciiname":"Puhaji",
    "gn:country_code":"KP",
    "gn:dem":143,
    "gn:feature_class":"P",
    "gn:feature_code":"PPL",
    "gn:name":"Puhaji",
    "gn:population":0,
    "gn:timezone":"Asia/Pyongyang",
    "iso:country":"KP",
    "name:kor_x_preferred":[
        "\ubd80\ud558\uc9c0"
    ],
    "wof:name":"Puhaji",
    "wof:placetype":"locality"
},
  "geometry": {"coordinates":[125.73333,38.15],"type":"Point"}
}