{
  "type": "Feature",
  "properties": {
    "gn:admin1_code":"6.0",
    "gn:asciiname":"Mansu-dong",
    "gn:country_code":"KP",
    "gn:dem":8,
    "gn:feature_class":"P",
    "gn:feature_code":"PPL",
    "gn:name":"Mansu-dong",
    "gn:population":0,
    "gn:timezone":"Asia/Pyongyang",
    "iso:country":"KP",
    "name:und_x_variant":[
        "\ub9cc\uc218\ub3d9",
        "Mansu-dong"
    ],
    "wof:name":"Mansu-dong",
    "wof:placetype":"locality"
},
  "geometry": {"coordinates":[125.28471999999999,38.085],"type":"Point"}
}