{
  "type": "Feature",
  "properties": {
    "gn:admin1_code":"1.0",
    "gn:asciiname":"Chaeyang-dong",
    "gn:country_code":"KP",
    "gn:dem":478,
    "gn:feature_class":"P",
    "gn:feature_code":"PPL",
    "gn:name":"Chaeyang-dong",
    "gn:population":0,
    "gn:timezone":"Asia/Pyongyang",
    "iso:country":"KP",
    "name:und_x_variant":[
        "\uc7ac\uc591\ub3d9",
        "Chaeyang-dong"
    ],
    "wof:name":"Chaeyang-dong",
    "wof:placetype":"locality"
},
  "geometry": {"coordinates":[126.68339,40.37689],"type":"Point"}
}