{
  "type": "Feature",
  "properties": {
    "gn:admin1_code":"9.0",
    "gn:asciiname":"Kodun-gol",
    "gn:country_code":"KP",
    "gn:dem":745,
    "gn:feature_class":"P",
    "gn:feature_code":"PPL",
    "gn:name":"Kod\u016dn-gol",
    "gn:population":0,
    "gn:timezone":"Asia/Pyongyang",
    "iso:country":"KP",
    "name:und_x_variant":[
        "\uace7\uc740\uace8",
        "Kod\u016dn-gol"
    ],
    "wof:name":"Kodun-gol",
    "wof:placetype":"locality"
},
  "geometry": {"coordinates":[127.57056,38.84417],"type":"Point"}
}