{
  "type": "Feature",
  "properties": {
    "gn:admin1_code":"11.0",
    "gn:asciiname":"Sinhung-dong",
    "gn:country_code":"KP",
    "gn:dem":11,
    "gn:feature_class":"P",
    "gn:feature_code":"PPL",
    "gn:name":"Sinh\u016dng-dong",
    "gn:population":0,
    "gn:timezone":"Asia/Pyongyang",
    "iso:country":"KP",
    "name:und_x_variant":[
        "\uc2e0\ud765\ub3d9",
        "Sinh\u016dng-dong"
    ],
    "wof:name":"Sinhung-dong",
    "wof:placetype":"locality"
},
  "geometry": {"coordinates":[124.33138999999998,39.91944],"type":"Point"}
}