{
  "type": "Feature",
  "properties": {
    "gn:admin1_code":"11.0",
    "gn:asciiname":"Tamang",
    "gn:country_code":"KP",
    "gn:dem":34,
    "gn:feature_class":"P",
    "gn:feature_code":"PPL",
    "gn:name":"Tamang",
    "gn:population":0,
    "gn:timezone":"Asia/Pyongyang",
    "iso:country":"KP",
    "name:und_x_variant":[
        "\ub2e4\ub9dd",
        "Tamang"
    ],
    "wof:name":"Tamang",
    "wof:placetype":"locality"
},
  "geometry": {"coordinates":[124.63703999999998,39.64097],"type":"Point"}
}