{
  "type": "Feature",
  "properties": {
    "gn:admin1_code":"3.0",
    "gn:admin2_code":"Tanch\u2019\u014fn-si",
    "gn:asciiname":"Tongp'a",
    "gn:country_code":"KP",
    "gn:dem":1461,
    "gn:feature_class":"P",
    "gn:feature_code":"PPL",
    "gn:name":"Tongp\u2019a",
    "gn:population":0,
    "gn:timezone":"Asia/Pyongyang",
    "iso:country":"KP",
    "wof:name":"Tongp'a",
    "wof:placetype":"locality"
},
  "geometry": {"coordinates":[128.77860999999999,41.0475],"type":"Point"}
}