{
  "type": "Feature",
  "properties": {
    "gn:admin1_code":"6.0",
    "gn:asciiname":"Wol-tong",
    "gn:country_code":"KP",
    "gn:dem":11,
    "gn:feature_class":"P",
    "gn:feature_code":"PPL",
    "gn:name":"W\u014fl-tong",
    "gn:population":0,
    "gn:timezone":"Asia/Pyongyang",
    "iso:country":"KP",
    "name:eng_x_preferred":[
        "Wol"
    ],
    "name:eng_x_variant":[
        "Wol-tong"
    ],
    "name:und_x_variant":[
        "\uc6d4\ub3d9",
        "W\u014fl-tong"
    ],
    "wof:name":"Wol",
    "wof:placetype":"locality"
},
  "geometry": {"coordinates":[125.27056,38.08778],"type":"Point"}
}