{
  "type": "Feature",
  "properties": {
    "gn:admin1_code":"13.0",
    "gn:asciiname":"Sihwa-ri",
    "gn:country_code":"KP",
    "gn:dem":1003,
    "gn:feature_class":"P",
    "gn:feature_code":"PPL",
    "gn:name":"Sihwa-ri",
    "gn:population":0,
    "gn:timezone":"Asia/Pyongyang",
    "iso:country":"KP",
    "name:kor_x_preferred":[
        "\uc2dc\ud654\ub9ac"
    ],
    "wof:name":"Sihwa-ri",
    "wof:placetype":"locality"
},
  "geometry": {"coordinates":[128.1875,41.08451],"type":"Point"}
}