{
  "type": "Feature",
  "properties": {
    "gn:admin1_code":"6.0",
    "gn:admin2_code":"Changp\u2019ung-gun",
    "gn:asciiname":"Oksan-gol",
    "gn:country_code":"KP",
    "gn:dem":216,
    "gn:feature_class":"P",
    "gn:feature_code":"PPL",
    "gn:name":"Oksan-gol",
    "gn:population":0,
    "gn:timezone":"Asia/Pyongyang",
    "iso:country":"KP",
    "wof:name":"Oksan-gol",
    "wof:placetype":"locality"
},
  "geometry": {"coordinates":[126.63472,38.1225],"type":"Point"}
}