{
  "type": "Feature",
  "properties": {
    "gn:admin1_code":"17.0",
    "gn:asciiname":"Haryegumi",
    "gn:country_code":"KP",
    "gn:dem":163,
    "gn:feature_class":"P",
    "gn:feature_code":"PPL",
    "gn:name":"Haryegumi",
    "gn:population":0,
    "gn:timezone":"Asia/Pyongyang",
    "iso:country":"KP",
    "name:und_x_variant":[
        "Ha-yegumi",
        "\ud558\ub840\uad6c\ubbf8",
        "Haryegumi"
    ],
    "wof:name":"Haryegumi",
    "wof:placetype":"locality"
},
  "geometry": {"coordinates":[129.42027999999999,41.215],"type":"Point"}
}