{
  "type": "Feature",
  "properties": {
    "gn:admin1_code":"15.0",
    "gn:asciiname":"Chusal-li",
    "gn:cc2":"KP",
    "gn:country_code":"KP",
    "gn:dem":23,
    "gn:feature_class":"P",
    "gn:feature_code":"PPL",
    "gn:name":"Chusal-li",
    "gn:population":0,
    "gn:timezone":"Asia/Pyongyang",
    "iso:country":"KP",
    "name:und_x_variant":[
        "Chusan-ni",
        "Chusal-li"
    ],
    "wof:name":"Chusal-li",
    "wof:placetype":"locality"
},
  "geometry": {"coordinates":[125.45833,38.82639],"type":"Point"}
}