{
  "type": "Feature",
  "properties": {
    "gn:admin1_code":"9.0",
    "gn:asciiname":"Sillung-dong",
    "gn:country_code":"KP",
    "gn:dem":262,
    "gn:feature_class":"P",
    "gn:feature_code":"PPL",
    "gn:name":"Sill\u016dng-dong",
    "gn:population":0,
    "gn:timezone":"Asia/Pyongyang",
    "iso:country":"KP",
    "wof:name":"Sillung-dong",
    "wof:placetype":"locality"
},
  "geometry": {"coordinates":[126.91110999999999,38.26389],"type":"Point"}
}