{
  "type": "Feature",
  "properties": {
    "gn:admin1_code":"15.0",
    "gn:asciiname":"Songsam-ni",
    "gn:country_code":"KP",
    "gn:dem":50,
    "gn:feature_class":"P",
    "gn:feature_code":"PPL",
    "gn:name":"S\u014fngsam-ni",
    "gn:population":0,
    "gn:timezone":"Asia/Pyongyang",
    "iso:country":"KP",
    "name:eng_x_preferred":[
        "Songsam"
    ],
    "name:eng_x_variant":[
        "Songsam-ni"
    ],
    "wof:name":"Songsam",
    "wof:placetype":"locality"
},
  "geometry": {"coordinates":[125.48778,39.1025],"type":"Point"}
}