{
  "type": "Feature",
  "properties": {
    "gn:admin1_code":"15.0",
    "gn:admin2_code":"Y\u014fngw\u014fn-gun",
    "gn:asciiname":"Mun'gong-ni",
    "gn:country_code":"KP",
    "gn:dem":215,
    "gn:feature_class":"P",
    "gn:feature_code":"PPL",
    "gn:name":"Mun\u2019gong-ni",
    "gn:population":0,
    "gn:timezone":"Asia/Pyongyang",
    "iso:country":"KP",
    "name:eng_x_preferred":[
        "Mun'gong"
    ],
    "name:eng_x_variant":[
        "Mun'gong-ni"
    ],
    "wof:name":"Mun'gong",
    "wof:placetype":"locality"
},
  "geometry": {"coordinates":[126.56667,39.8225],"type":"Point"}
}