{
  "type": "Feature",
  "properties": {
    "gn:admin1_code":"12.0",
    "gn:asciiname":"Negwi-bong",
    "gn:country_code":"KP",
    "gn:dem":272,
    "gn:feature_class":"P",
    "gn:feature_code":"PPL",
    "gn:name":"Negwi-bong",
    "gn:population":0,
    "gn:timezone":"Asia/Pyongyang",
    "iso:country":"KP",
    "name:kor_x_preferred":[
        "\ub124\uadc0\ubd09"
    ],
    "name:und_x_variant":[
        "Negwibong"
    ],
    "wof:name":"Negwi-bong",
    "wof:placetype":"locality"
},
  "geometry": {"coordinates":[125.854,39.16845],"type":"Point"}
}