{
  "type": "Feature",
  "properties": {
    "gn:admin1_code":"15.0",
    "gn:asciiname":"Changbaeng-ni",
    "gn:country_code":"KP",
    "gn:dem":22,
    "gn:feature_class":"P",
    "gn:feature_code":"PPL",
    "gn:name":"Changbaeng-ni",
    "gn:population":0,
    "gn:timezone":"Asia/Pyongyang",
    "iso:country":"KP",
    "name:eng_x_preferred":[
        "Changbaeng"
    ],
    "name:eng_x_variant":[
        "Changbaeng-ni"
    ],
    "name:kor_x_preferred":[
        "\uc7a5\ubc31\ub9ac"
    ],
    "wof:name":"Changbaeng",
    "wof:placetype":"locality"
},
  "geometry": {"coordinates":[125.60194,39.53333],"type":"Point"}
}