{
  "type": "Feature",
  "properties": {
    "gn:admin1_code":"17.0",
    "gn:asciiname":"Changhang",
    "gn:country_code":"KP",
    "gn:dem":20,
    "gn:feature_class":"P",
    "gn:feature_code":"PPL",
    "gn:name":"Changhang",
    "gn:population":0,
    "gn:timezone":"Asia/Pyongyang",
    "iso:country":"KP",
    "name:und_x_variant":[
        "\uc7a5\ud56d",
        "Changhang"
    ],
    "wof:name":"Changhang",
    "wof:placetype":"locality"
},
  "geometry": {"coordinates":[129.56943999999999,40.84611],"type":"Point"}
}