{
  "type": "Feature",
  "properties": {
    "gn:admin1_code":"6.0",
    "gn:asciiname":"Sangnyul-tong",
    "gn:country_code":"KP",
    "gn:dem":46,
    "gn:feature_class":"P",
    "gn:feature_code":"PPL",
    "gn:name":"Sangnyul-tong",
    "gn:population":0,
    "gn:timezone":"Asia/Pyongyang",
    "iso:country":"KP",
    "name:kor_x_preferred":[
        "\uc0c1\ub960\ub3d9"
    ],
    "wof:name":"Sangnyul-tong",
    "wof:placetype":"locality"
},
  "geometry": {"coordinates":[125.11917,38.29778],"type":"Point"}
}