{
  "type": "Feature",
  "properties": {
    "gn:admin1_code":"11.0",
    "gn:asciiname":"Ch'u-dong",
    "gn:country_code":"KP",
    "gn:dem":100,
    "gn:feature_class":"P",
    "gn:feature_code":"PPL",
    "gn:name":"Ch\u2019u-dong",
    "gn:population":0,
    "gn:timezone":"Asia/Pyongyang",
    "iso:country":"KP",
    "name:und_x_variant":[
        "\ucd94\ub3d9",
        "Ch\u2019u-dong"
    ],
    "wof:name":"Ch'u-dong",
    "wof:placetype":"locality"
},
  "geometry": {"coordinates":[124.7525,40.05222],"type":"Point"}
}