{
  "type": "Feature",
  "properties": {
    "gn:admin1_code":"3.0",
    "gn:asciiname":"K'unjonggae",
    "gn:country_code":"KP",
    "gn:dem":115,
    "gn:feature_class":"P",
    "gn:feature_code":"PPL",
    "gn:name":"K\u2019\u016dnjonggae",
    "gn:population":0,
    "gn:timezone":"Asia/Pyongyang",
    "iso:country":"KP",
    "name:und_x_variant":[
        "\ud070\uc885\uac1c",
        "K\u2019\u016dnjonggae"
    ],
    "wof:name":"K'unjonggae",
    "wof:placetype":"locality"
},
  "geometry": {"coordinates":[128.87388999999999,40.50722],"type":"Point"}
}