{
  "type": "Feature",
  "properties": {
    "gn:country":"KP",
    "gn:fcode":"PPL",
    "gn:population":53330,
    "iso:country":"KP",
    "name:cat_x_preferred":[
        "Chaeryong"
    ],
    "name:ceb_x_preferred":[
        "Chaery\u014fng-gun"
    ],
    "name:cym_x_preferred":[
        "Sir Chaeryong"
    ],
    "name:deu_x_preferred":[
        "Chaery\u014fng-kun"
    ],
    "name:eng_x_preferred":[
        "Chaery\u014fng"
    ],
    "name:eng_x_variant":[
        "Chaery\u014fng-\u016dp",
        "Chaeryong County"
    ],
    "name:jpn_x_preferred":[
        "\u8f09\u5be7\u90e1"
    ],
    "name:kor_x_preferred":[
        "\uc7ac\ub839\uc74d"
    ],
    "name:kor_x_variant":[
        "\uc7ac\ub839\uad70"
    ],
    "name:nan_x_preferred":[
        "Chaery\u014fng K\u016bn"
    ],
    "name:nob_x_preferred":[
        "Chaeryong"
    ],
    "name:pol_x_preferred":[
        "Chaery\u014fng"
    ],
    "name:swe_x_preferred":[
        "Chaery\u014fng-gun"
    ],
    "name:und_x_variant":[
        "Sainei-men"
    ],
    "name:vie_x_preferred":[
        "Chaeryong"
    ],
    "name:zho_x_preferred":[
        "\u8f09\u5be7\u90e1"
    ],
    "qs:name":"Chaery\u014fng-\u016dp",
    "qs:photos_9r":0,
    "qs:photos_sr":0,
    "qs:pop_sr":"8",
    "wd:wordcount":220,
    "wof:name":"Chaery\u014fng",
    "wof:placetype":"locality",
    "wof:population":53330
},
  "geometry": {"coordinates":[125.61556,38.39917],"type":"Point"}
}