{
  "type": "Feature",
  "properties": {
    "gn:admin1_code":"0.0",
    "gn:asciiname":"Hyonhung-ni",
    "gn:country_code":"KP",
    "gn:dem":-9999,
    "gn:feature_class":"P",
    "gn:feature_code":"PPL",
    "gn:name":"Hy\u014fnh\u016dng-ni",
    "gn:population":0,
    "gn:timezone":"Asia/Pyongyang",
    "iso:country":"KP",
    "name:kor_x_preferred":[
        "\ud604\ud765\ub9ac"
    ],
    "name:und_x_variant":[
        "Hy\u014fnh\u016dng-ni"
    ],
    "wof:name":"Hyonhung-ni",
    "wof:placetype":"locality"
},
  "geometry": {"coordinates":[125.23333,39.48333],"type":"Point"}
}