{
  "type": "Feature",
  "properties": {
    "gn:admin1_code":"9.0",
    "gn:asciiname":"Konja-ri",
    "gn:country_code":"KP",
    "gn:dem":620,
    "gn:feature_class":"P",
    "gn:feature_code":"PPL",
    "gn:name":"K\u014fnja-ri",
    "gn:population":0,
    "gn:timezone":"Asia/Pyongyang",
    "iso:country":"KP",
    "name:kor_x_preferred":[
        "\uac74\uc790\ub9ac"
    ],
    "name:kor_x_variant":[
        "K\u014fnja-ri"
    ],
    "wof:name":"Konja-ri",
    "wof:placetype":"locality"
},
  "geometry": {"coordinates":[127.215,38.93889],"type":"Point"}
}