{
  "type": "Feature",
  "properties": {
    "gn:admin1_code":"15.0",
    "gn:asciiname":"Simjil-li",
    "gn:country_code":"KP",
    "gn:dem":135,
    "gn:feature_class":"P",
    "gn:feature_code":"PPL",
    "gn:name":"Simjil-li",
    "gn:population":0,
    "gn:timezone":"Asia/Pyongyang",
    "iso:country":"KP",
    "name:kor_x_preferred":[
        "\uc2ec\uc9c4\ub9ac"
    ],
    "name:und_x_variant":[
        "Simjin-ni",
        "Simjil-li"
    ],
    "wof:name":"Simjil-li",
    "wof:placetype":"locality"
},
  "geometry": {"coordinates":[126.44417,38.9275],"type":"Point"}
}