{
  "type": "Feature",
  "properties": {
    "gn:admin1_code":"7.0",
    "gn:asciiname":"Karam-dong",
    "gn:country_code":"KP",
    "gn:dem":209,
    "gn:feature_class":"P",
    "gn:feature_code":"PPL",
    "gn:name":"Karam-dong",
    "gn:population":0,
    "gn:timezone":"Asia/Pyongyang",
    "iso:country":"KP",
    "wof:name":"Karam-dong",
    "wof:placetype":"locality"
},
  "geometry": {"coordinates":[126.675,38.49222],"type":"Point"}
}