{
  "type": "Feature",
  "properties": {
    "gn:admin1_code":"3.0",
    "gn:asciiname":"Unsang-ni",
    "gn:country_code":"KP",
    "gn:dem":50,
    "gn:feature_class":"P",
    "gn:feature_code":"PPL",
    "gn:name":"Unsang-ni",
    "gn:population":0,
    "gn:timezone":"Asia/Pyongyang",
    "iso:country":"KP",
    "name:eng_x_preferred":[
        "Unsang"
    ],
    "name:eng_x_variant":[
        "Unsang-ni"
    ],
    "name:und_x_variant":[
        "Usang-ni",
        "\uc6b4\uc0c1\ub9ac",
        "Unsang-ni"
    ],
    "wof:name":"Unsang",
    "wof:placetype":"locality"
},
  "geometry": {"coordinates":[128.05082999999999,40.07056],"type":"Point"}
}