{
  "type": "Feature",
  "properties": {
    "gn:country":"KP",
    "gn:fcode":"PPL",
    "gn:population":0,
    "iso:country":"KP",
    "name:eng_x_preferred":[
        "Pil-dong"
    ],
    "name:kor_x_preferred":[
        "\ud544\ub3d9"
    ],
    "qs_pg:aaroncc":"KP",
    "qs_pg:gn_country":"KP",
    "qs_pg:gn_fcode":"PPL",
    "qs_pg:gn_pop":0,
    "qs_pg:name":"\ud544\ub3d9",
    "qs_pg:name_adm0":"\ud55c\uad6d",
    "qs_pg:name_adm1":"\uc11c\uc6b8",
    "qs_pg:photos":3346,
    "qs_pg:photos_1k":678,
    "qs_pg:photos_9k":15,
    "qs_pg:photos_9r":11,
    "qs_pg:photos_all":3346,
    "qs_pg:photos_sr":20,
    "qs_pg:pop_sr":0,
    "qs_pg:qs_pg_placetype":"neighbourhood",
    "qs_pg:qs_pg_placetype_gp":"Suburb",
    "qs_pg:woe_adm0":23424868,
    "woe:adm0_id":23424868,
    "woe:name_adm0":"\ud55c\uad6d",
    "woe:name_adm1":"\uc11c\uc6b8",
    "woe:placetype":"Suburb",
    "wof:name":"Pil-dong",
    "wof:placetype":"neighbourhood"
},
  "geometry": {"coordinates":[126.46389000000001,38.32],"type":"Point"}
}