{
  "type": "Feature",
  "properties": {
    "gn:admin1_code":"17.0",
    "gn:asciiname":"Kyehwa-dong",
    "gn:country_code":"KP",
    "gn:dem":139,
    "gn:feature_class":"P",
    "gn:feature_code":"PPL",
    "gn:name":"Kyehwa-dong",
    "gn:population":0,
    "gn:timezone":"Asia/Pyongyang",
    "iso:country":"KP",
    "name:und_x_variant":[
        "\uacc4\ud654\ub3d9",
        "Kyehwa-dong"
    ],
    "wof:name":"Kyehwa-dong",
    "wof:placetype":"locality"
},
  "geometry": {"coordinates":[129.75888999999998,41.90806],"type":"Point"}
}