{
  "type": "Feature",
  "properties": {
    "gn:admin1_code":"15.0",
    "gn:asciiname":"Tonggye-ri",
    "gn:country_code":"KP",
    "gn:dem":45,
    "gn:feature_class":"P",
    "gn:feature_code":"PPL",
    "gn:name":"Tonggye-ri",
    "gn:population":0,
    "gn:timezone":"Asia/Pyongyang",
    "iso:country":"KP",
    "name:kor_x_preferred":[
        "\ub3d9\uacc4\ub9ac"
    ],
    "wof:name":"Tonggye-ri",
    "wof:placetype":"locality"
},
  "geometry": {"coordinates":[125.63943999999999,39.54972],"type":"Point"}
}