{
  "type": "Feature",
  "properties": {
    "gn:admin1_code":"3.0",
    "gn:asciiname":"Chikso-ri",
    "gn:country_code":"KP",
    "gn:dem":25,
    "gn:feature_class":"P",
    "gn:feature_code":"PPL",
    "gn:name":"Chiks\u014f-ri",
    "gn:population":0,
    "gn:timezone":"Asia/Pyongyang",
    "iso:country":"KP",
    "name:und_x_variant":[
        "\uc9c1\uc11c\ub9ac",
        "Chiks\u014f-ri"
    ],
    "wof:name":"Chikso-ri",
    "wof:placetype":"locality"
},
  "geometry": {"coordinates":[127.32861,39.55472],"type":"Point"}
}