{
  "type": "Feature",
  "properties": {
    "gn:admin1_code":"15.0",
    "gn:asciiname":"Mulmogi-dong",
    "gn:country_code":"KP",
    "gn:dem":1424,
    "gn:feature_class":"P",
    "gn:feature_code":"PPL",
    "gn:name":"Mulmogi-dong",
    "gn:population":0,
    "gn:timezone":"Asia/Pyongyang",
    "iso:country":"KP",
    "name:und_x_variant":[
        "\ubb3c\ubaa9\uc774\ub3d9",
        "Mulmogi-dong"
    ],
    "wof:name":"Mulmogi-dong",
    "wof:placetype":"locality"
},
  "geometry": {"coordinates":[127.00888999999999,40.16556],"type":"Point"}
}