{
  "type": "Feature",
  "properties": {
    "gn:admin1_code":"6.0",
    "gn:admin2_code":"Ch\u2019ongdan-gun",
    "gn:asciiname":"Yongp'o-ri",
    "gn:country_code":"KP",
    "gn:dem":22,
    "gn:feature_class":"P",
    "gn:feature_code":"PPL",
    "gn:name":"Yongp\u2019o-ri",
    "gn:population":0,
    "gn:timezone":"Asia/Pyongyang",
    "iso:country":"KP",
    "wof:name":"Yongp'o-ri",
    "wof:placetype":"locality"
},
  "geometry": {"coordinates":[125.92917,37.93778],"type":"Point"}
}