{
  "type": "Feature",
  "properties": {
    "gn:admin1_code":"3.0",
    "gn:asciiname":"Irak",
    "gn:country_code":"KP",
    "gn:dem":565,
    "gn:feature_class":"P",
    "gn:feature_code":"PPL",
    "gn:name":"Irak",
    "gn:population":0,
    "gn:timezone":"Asia/Pyongyang",
    "iso:country":"KP",
    "name:und_x_variant":[
        "\uc774\ub77d",
        "Irak"
    ],
    "wof:name":"Irak",
    "wof:placetype":"locality"
},
  "geometry": {"coordinates":[128.31,40.53917],"type":"Point"}
}