{
  "type": "Feature",
  "properties": {
    "gn:admin1_code":"6.0",
    "gn:asciiname":"Yangon'on",
    "gn:country_code":"KP",
    "gn:dem":80,
    "gn:feature_class":"P",
    "gn:feature_code":"PPL",
    "gn:name":"Yangon\u2019on",
    "gn:population":0,
    "gn:timezone":"Asia/Pyongyang",
    "iso:country":"KP",
    "name:kor_x_preferred":[
        "\uc591\uc628\uc628"
    ],
    "name:und_x_variant":[
        "Yangon\u2019on"
    ],
    "wof:name":"Yangon'on",
    "wof:placetype":"locality"
},
  "geometry": {"coordinates":[126.12833000000001,38.14611],"type":"Point"}
}