{
  "type": "Feature",
  "properties": {
    "gn:admin1_code":"6.0",
    "gn:asciiname":"Songdomol",
    "gn:cc2":"KP",
    "gn:country_code":"KP",
    "gn:dem":16,
    "gn:feature_class":"P",
    "gn:feature_code":"PPL",
    "gn:name":"Songdomol",
    "gn:population":0,
    "gn:timezone":"Asia/Pyongyang",
    "iso:country":"KP",
    "name:und_x_variant":[
        "Songhy\u014fn-ch\u2019on",
        "Songdomol"
    ],
    "wof:name":"Songdomol",
    "wof:placetype":"locality"
},
  "geometry": {"coordinates":[125.94917,37.9725],"type":"Point"}
}