{
  "type": "Feature",
  "properties": {
    "gn:admin1_code":"13.0",
    "gn:admin2_code":"2041726",
    "gn:asciiname":"Nohung-ni",
    "gn:country_code":"KP",
    "gn:dem":1119,
    "gn:feature_class":"P",
    "gn:feature_code":"PPL",
    "gn:name":"Noh\u016dng-ni",
    "gn:population":0,
    "gn:timezone":"Asia/Pyongyang",
    "iso:country":"KP",
    "name:eng_x_preferred":[
        "Nohung"
    ],
    "name:eng_x_variant":[
        "Nohung-ni"
    ],
    "wof:name":"Nohung",
    "wof:placetype":"locality"
},
  "geometry": {"coordinates":[127.95361,40.80972],"type":"Point"}
}