{
  "type": "Feature",
  "properties": {
    "gn:admin1_code":"3.0",
    "gn:asciiname":"Sangil-li",
    "gn:country_code":"KP",
    "gn:dem":394,
    "gn:feature_class":"P",
    "gn:feature_code":"PPL",
    "gn:name":"Sangil-li",
    "gn:population":0,
    "gn:timezone":"Asia/Pyongyang",
    "iso:country":"KP",
    "name:und_x_variant":[
        "San-il-li",
        "\uc0c1\uc77c\ub9ac",
        "Sangil-li"
    ],
    "wof:name":"Sangil-li",
    "wof:placetype":"locality"
},
  "geometry": {"coordinates":[128.12941999999998,40.50166],"type":"Point"}
}