{
  "type": "Feature",
  "properties": {
    "gn:admin1_code":"17.0",
    "gn:asciiname":"Samch'on-dong",
    "gn:country_code":"KP",
    "gn:dem":603,
    "gn:feature_class":"P",
    "gn:feature_code":"PPL",
    "gn:name":"Samch\u2019\u014fn-dong",
    "gn:population":0,
    "gn:timezone":"Asia/Pyongyang",
    "iso:country":"KP",
    "name:kor_x_preferred":[
        "\uc0bc\ucc9c\ub3d9"
    ],
    "name:und_x_variant":[
        "Samch\u2019\u014fn-dong"
    ],
    "wof:name":"Samch'on-dong",
    "wof:placetype":"locality"
},
  "geometry": {"coordinates":[129.08231000000001,42.12359],"type":"Point"}
}