{
  "type": "Feature",
  "properties": {
    "gn:admin1_code":"11.0",
    "gn:asciiname":"Ch'onsal-li",
    "gn:country_code":"KP",
    "gn:dem":181,
    "gn:feature_class":"P",
    "gn:feature_code":"PPL",
    "gn:name":"Ch\u2019\u014fnsal-li",
    "gn:population":0,
    "gn:timezone":"Asia/Pyongyang",
    "iso:country":"KP",
    "name:und_x_variant":[
        "Ch\u2019\u014fnma-dong",
        "\ucc9c\uc0b0\ub9ac",
        "Ch\u2019\u014fnsan-ni",
        "Ch\u2019\u014fnsal-li"
    ],
    "wof:name":"Ch'onsal-li",
    "wof:placetype":"locality"
},
  "geometry": {"coordinates":[124.90778,40.17722],"type":"Point"}
}