{
  "type": "Feature",
  "properties": {
    "gn:admin1_code":"6.0",
    "gn:asciiname":"Changsirang",
    "gn:country_code":"KP",
    "gn:dem":178,
    "gn:feature_class":"P",
    "gn:feature_code":"PPL",
    "gn:name":"Changsirang",
    "gn:population":0,
    "gn:timezone":"Asia/Pyongyang",
    "iso:country":"KP",
    "wof:name":"Changsirang",
    "wof:placetype":"locality"
},
  "geometry": {"coordinates":[126.59721999999999,38.10944],"type":"Point"}
}