{
  "type": "Feature",
  "properties": {
    "gn:admin1_code":"17.0",
    "gn:asciiname":"Kuok-tong",
    "gn:country_code":"KP",
    "gn:dem":94,
    "gn:feature_class":"P",
    "gn:feature_code":"PPL",
    "gn:name":"Ku\u014fk-tong",
    "gn:population":0,
    "gn:timezone":"Asia/Pyongyang",
    "iso:country":"KP",
    "name:eng_x_preferred":[
        "Kuok"
    ],
    "name:eng_x_variant":[
        "Kuok-tong"
    ],
    "name:und_x_variant":[
        "\uad6c\uc5b5\ub3d9",
        "Ku\u014fk-tong"
    ],
    "wof:name":"Kuok",
    "wof:placetype":"locality"
},
  "geometry": {"coordinates":[129.93333000000001,42.98917],"type":"Point"}
}