{
  "type": "Feature",
  "properties": {
    "gn:admin1_code":"9.0",
    "gn:asciiname":"Hoenamuko-ri",
    "gn:country_code":"KP",
    "gn:dem":366,
    "gn:feature_class":"P",
    "gn:feature_code":"PPL",
    "gn:name":"Hoenamuk\u014f-ri",
    "gn:population":0,
    "gn:timezone":"Asia/Pyongyang",
    "iso:country":"KP",
    "wof:name":"Hoenamuko-ri",
    "wof:placetype":"locality"
},
  "geometry": {"coordinates":[127.09889,38.68472],"type":"Point"}
}