{
  "type": "Feature",
  "properties": {
    "gn:admin1_code":"1.0",
    "gn:asciiname":"Chup'yong-dong",
    "gn:country_code":"KP",
    "gn:dem":128,
    "gn:feature_class":"P",
    "gn:feature_code":"PPL",
    "gn:name":"Chup\u2019y\u014fng-dong",
    "gn:population":0,
    "gn:timezone":"Asia/Pyongyang",
    "iso:country":"KP",
    "name:und_x_variant":[
        "\uc8fc\ud3c9\ub3d9",
        "Chup\u2019y\u014fng-dong"
    ],
    "wof:name":"Chup'yong-dong",
    "wof:placetype":"locality"
},
  "geometry": {"coordinates":[125.63943999999999,40.74611],"type":"Point"}
}