{
  "type": "Feature",
  "properties": {
    "gn:admin1_code":"15.0",
    "gn:asciiname":"Panyang-ni",
    "gn:country_code":"KP",
    "gn:dem":143,
    "gn:feature_class":"P",
    "gn:feature_code":"PPL",
    "gn:name":"Panyang-ni",
    "gn:population":0,
    "gn:timezone":"Asia/Pyongyang",
    "iso:country":"KP",
    "name:eng_x_preferred":[
        "Panyang"
    ],
    "name:eng_x_variant":[
        "Panyang-ni"
    ],
    "wof:name":"Panyang",
    "wof:placetype":"locality"
},
  "geometry": {"coordinates":[125.735,39.31556],"type":"Point"}
}