{
  "type": "Feature",
  "properties": {
    "gn:admin1_code":"7.0",
    "gn:asciiname":"Hoedong-ni",
    "gn:country_code":"KP",
    "gn:dem":102,
    "gn:feature_class":"P",
    "gn:feature_code":"PPL",
    "gn:name":"Hoedong-ni",
    "gn:population":0,
    "gn:timezone":"Asia/Pyongyang",
    "iso:country":"KP",
    "name:kor_x_preferred":[
        "\ud68c\ub3d9\ub9ac"
    ],
    "wof:name":"Hoedong-ni",
    "wof:placetype":"locality"
},
  "geometry": {"coordinates":[126.55833,38.50472],"type":"Point"}
}