{
  "type": "Feature",
  "properties": {
    "gn:admin1_code":"1.0",
    "gn:asciiname":"Namsang-dong",
    "gn:country_code":"KP",
    "gn:dem":319,
    "gn:feature_class":"P",
    "gn:feature_code":"PPL",
    "gn:name":"Namsang-dong",
    "gn:population":0,
    "gn:timezone":"Asia/Pyongyang",
    "iso:country":"KP",
    "name:und_x_variant":[
        "\ub0a8\uc0c1\ub3d9",
        "Namsamdong",
        "Namsang-dong"
    ],
    "wof:name":"Namsang-dong",
    "wof:placetype":"locality"
},
  "geometry": {"coordinates":[125.84694,40.67556],"type":"Point"}
}