{
  "type": "Feature",
  "properties": {
    "gn:admin1_code":"15.0",
    "gn:admin2_code":"Pukch\u2019ang-gun",
    "gn:asciiname":"Sang-ni",
    "gn:country_code":"KP",
    "gn:dem":127,
    "gn:feature_class":"P",
    "gn:feature_code":"PPL",
    "gn:name":"Sang-ni",
    "gn:population":0,
    "gn:timezone":"Asia/Pyongyang",
    "iso:country":"KP",
    "name:eng_x_preferred":[
        "Sang"
    ],
    "name:eng_x_variant":[
        "Sang-ni"
    ],
    "wof:name":"Sang",
    "wof:placetype":"locality"
},
  "geometry": {"coordinates":[126.18917,39.58778],"type":"Point"}
}