{
  "type": "Feature",
  "properties": {
    "gn:admin1_code":"7.0",
    "gn:asciiname":"Utchollung",
    "gn:country_code":"KP",
    "gn:dem":39,
    "gn:feature_class":"P",
    "gn:feature_code":"PPL",
    "gn:name":"Utch\u014fll\u016dng",
    "gn:population":0,
    "gn:timezone":"Asia/Pyongyang",
    "iso:country":"KP",
    "name:kor_x_preferred":[
        "\uc6c3\uc804\ub989"
    ],
    "name:kor_x_variant":[
        "Utch\u014fll\u016dng"
    ],
    "wof:name":"Utchollung",
    "wof:placetype":"locality"
},
  "geometry": {"coordinates":[126.53333000000001,38.29139],"type":"Point"}
}