{
  "type": "Feature",
  "properties": {
    "gn:admin1_code":"7.0",
    "gn:asciiname":"Yongban-dong",
    "gn:country_code":"KP",
    "gn:dem":240,
    "gn:feature_class":"P",
    "gn:feature_code":"PPL",
    "gn:name":"Yongban-dong",
    "gn:population":0,
    "gn:timezone":"Asia/Pyongyang",
    "iso:country":"KP",
    "name:kor_x_preferred":[
        "\uc6a9\ubc18\ub3d9"
    ],
    "wof:name":"Yongban-dong",
    "wof:placetype":"locality"
},
  "geometry": {"coordinates":[126.64361,38.62667],"type":"Point"}
}