{
  "type": "Feature",
  "properties": {
    "gn:admin1_code":"15.0",
    "gn:asciiname":"Handul",
    "gn:cc2":"KP",
    "gn:country_code":"KP",
    "gn:dem":48,
    "gn:feature_class":"P",
    "gn:feature_code":"PPL",
    "gn:name":"Hand\u016dl",
    "gn:population":0,
    "gn:timezone":"Asia/Pyongyang",
    "iso:country":"KP",
    "name:kor_x_preferred":[
        "\ud55c\ub4e4"
    ],
    "name:und_x_variant":[
        "Hant\u016dl",
        "Hanya",
        "Hand\u016dl"
    ],
    "wof:name":"Handul",
    "wof:placetype":"locality"
},
  "geometry": {"coordinates":[126.02361000000001,39.29139],"type":"Point"}
}