{
  "type": "Feature",
  "properties": {
    "gn:admin1_code":"15.0",
    "gn:asciiname":"Paegun-dong",
    "gn:country_code":"KP",
    "gn:dem":61,
    "gn:feature_class":"P",
    "gn:feature_code":"PPL",
    "gn:name":"Paegun-dong",
    "gn:population":0,
    "gn:timezone":"Asia/Pyongyang",
    "iso:country":"KP",
    "wof:name":"Paegun-dong",
    "wof:placetype":"locality"
},
  "geometry": {"coordinates":[125.50333000000001,39.17722],"type":"Point"}
}