{
  "type": "Feature",
  "properties": {
    "gn:admin1_code":"6.0",
    "gn:asciiname":"Saet'o",
    "gn:country_code":"KP",
    "gn:dem":160,
    "gn:feature_class":"P",
    "gn:feature_code":"PPL",
    "gn:name":"Saet\u2019\u014f",
    "gn:population":0,
    "gn:timezone":"Asia/Pyongyang",
    "iso:country":"KP",
    "wof:name":"Saet'o",
    "wof:placetype":"locality"
},
  "geometry": {"coordinates":[125.66611,38.21056],"type":"Point"}
}