{
  "type": "Feature",
  "properties": {
    "gn:admin1_code":"9.0",
    "gn:asciiname":"Pongsal-li",
    "gn:country_code":"KP",
    "gn:dem":15,
    "gn:feature_class":"P",
    "gn:feature_code":"PPL",
    "gn:name":"Pongsal-li",
    "gn:population":0,
    "gn:timezone":"Asia/Pyongyang",
    "iso:country":"KP",
    "name:und_x_variant":[
        "Pongsan-ni",
        "Pongsal-li",
        "\ubd09\uc0b0\ub9ac"
    ],
    "wof:name":"Pongsal-li",
    "wof:placetype":"locality"
},
  "geometry": {"coordinates":[127.47762,39.10582],"type":"Point"}
}