{
  "type": "Feature",
  "properties": {
    "gn:admin1_code":"9.0",
    "gn:asciiname":"Yongyol-li",
    "gn:country_code":"KP",
    "gn:dem":66,
    "gn:feature_class":"P",
    "gn:feature_code":"PPL",
    "gn:name":"Yongy\u014fl-li",
    "gn:population":0,
    "gn:timezone":"Asia/Pyongyang",
    "iso:country":"KP",
    "wof:name":"Yongyol-li",
    "wof:placetype":"locality"
},
  "geometry": {"coordinates":[127.72499999999999,39.03222],"type":"Point"}
}