{
  "type": "Feature",
  "properties": {
    "gn:admin1_code":"9.0",
    "gn:asciiname":"Chungoji-ri",
    "gn:country_code":"KP",
    "gn:dem":41,
    "gn:feature_class":"P",
    "gn:feature_code":"PPL",
    "gn:name":"Chung\u014fji-ri",
    "gn:population":0,
    "gn:timezone":"Asia/Pyongyang",
    "iso:country":"KP",
    "name:kor_x_preferred":[
        "\uc911\uc5b4\uc9c0\ub9ac"
    ],
    "name:kor_x_variant":[
        "Chung\u014fji-ri"
    ],
    "wof:name":"Chungoji-ri",
    "wof:placetype":"locality"
},
  "geometry": {"coordinates":[127.49444,38.985],"type":"Point"}
}