{
  "type": "Feature",
  "properties": {
    "gn:admin1_code":"9.0",
    "gn:asciiname":"Kungnae-dong",
    "gn:country_code":"KP",
    "gn:dem":272,
    "gn:feature_class":"P",
    "gn:feature_code":"PPL",
    "gn:name":"Kungnae-dong",
    "gn:population":0,
    "gn:timezone":"Asia/Pyongyang",
    "iso:country":"KP",
    "name:kor_x_preferred":[
        "\uad81\ub0b4\ub3d9"
    ],
    "wof:name":"Kungnae-dong",
    "wof:placetype":"locality"
},
  "geometry": {"coordinates":[126.70833,38.6475],"type":"Point"}
}