{
  "type": "Feature",
  "properties": {
    "gn:admin1_code":"7.0",
    "gn:asciiname":"Chungo-dong",
    "gn:country_code":"KP",
    "gn:dem":243,
    "gn:feature_class":"P",
    "gn:feature_code":"PPL",
    "gn:name":"Chungo-dong",
    "gn:population":0,
    "gn:timezone":"Asia/Pyongyang",
    "iso:country":"KP",
    "wof:name":"Chungo-dong",
    "wof:placetype":"locality"
},
  "geometry": {"coordinates":[126.15667000000001,38.54972],"type":"Point"}
}