{
  "type": "Feature",
  "properties": {
    "gn:admin1_code":"6.0",
    "gn:asciiname":"Wolsal-li",
    "gn:country_code":"KP",
    "gn:dem":93,
    "gn:feature_class":"P",
    "gn:feature_code":"PPL",
    "gn:name":"W\u014flsal-li",
    "gn:population":0,
    "gn:timezone":"Asia/Pyongyang",
    "iso:country":"KP",
    "name:kor_x_preferred":[
        "\uc6d4\uc0b0\ub9ac"
    ],
    "name:kor_x_variant":[
        "W\u014flsal-li"
    ],
    "wof:name":"Wolsal-li",
    "wof:placetype":"locality"
},
  "geometry": {"coordinates":[125.24583,38.40583],"type":"Point"}
}