{
  "type": "Feature",
  "properties": {
    "gn:admin1_code":"6.0",
    "gn:asciiname":"Mojilmol",
    "gn:cc2":"KP",
    "gn:country_code":"KP",
    "gn:dem":9,
    "gn:feature_class":"P",
    "gn:feature_code":"PPL",
    "gn:name":"Mojilmol",
    "gn:population":0,
    "gn:timezone":"Asia/Pyongyang",
    "iso:country":"KP",
    "name:und_x_variant":[
        "Uch\u2019on",
        "Mol-mal",
        "Mojilmol"
    ],
    "wof:name":"Mojilmol",
    "wof:placetype":"locality"
},
  "geometry": {"coordinates":[125.96917000000001,37.96778],"type":"Point"}
}