{
  "type": "Feature",
  "properties": {
    "gn:admin1_code":"3.0",
    "gn:asciiname":"Youn-dong",
    "gn:country_code":"KP",
    "gn:dem":1335,
    "gn:feature_class":"P",
    "gn:feature_code":"PPL",
    "gn:name":"Y\u014fun-dong",
    "gn:population":0,
    "gn:timezone":"Asia/Pyongyang",
    "iso:country":"KP",
    "wof:name":"Youn-dong",
    "wof:placetype":"locality"
},
  "geometry": {"coordinates":[128.71666999999999,40.93333],"type":"Point"}
}