{
  "type": "Feature",
  "properties": {
    "gn:admin1_code":"0.0",
    "gn:asciiname":"Yongbong",
    "gn:country_code":"KP",
    "gn:dem":8,
    "gn:feature_class":"P",
    "gn:feature_code":"PPL",
    "gn:name":"Y\u014fngbong",
    "gn:population":0,
    "gn:timezone":"Asia/Pyongyang",
    "iso:country":"KP",
    "name:kor_x_preferred":[
        "Y\u014fngbong"
    ],
    "name:kor_x_variant":[
        "\uc601\ubd09"
    ],
    "wof:name":"Yongbong",
    "wof:placetype":"locality"
},
  "geometry": {"coordinates":[124.68333,39.76667],"type":"Point"}
}