{
  "type": "Feature",
  "properties": {
    "gn:admin1_code":"6.0",
    "gn:asciiname":"Changgumoe",
    "gn:country_code":"KP",
    "gn:dem":64,
    "gn:feature_class":"P",
    "gn:feature_code":"PPL",
    "gn:name":"Changgumoe",
    "gn:population":0,
    "gn:timezone":"Asia/Pyongyang",
    "iso:country":"KP",
    "name:kor_x_preferred":[
        "\uc7a5\uad6c\ubafc"
    ],
    "wof:name":"Changgumoe",
    "wof:placetype":"locality"
},
  "geometry": {"coordinates":[125.13028,38.34639],"type":"Point"}
}