{
  "type": "Feature",
  "properties": {
    "gn:admin1_code":"6.0",
    "gn:asciiname":"Worun-dong",
    "gn:country_code":"KP",
    "gn:dem":34,
    "gn:feature_class":"P",
    "gn:feature_code":"PPL",
    "gn:name":"W\u014fr\u016dn-dong",
    "gn:population":0,
    "gn:timezone":"Asia/Pyongyang",
    "iso:country":"KP",
    "wof:name":"Worun-dong",
    "wof:placetype":"locality"
},
  "geometry": {"coordinates":[125.56556,38.01389],"type":"Point"}
}