{
  "type": "Feature",
  "properties": {
    "gn:admin1_code":"0.0",
    "gn:asciiname":"Hwaram-ni",
    "gn:cc2":"KP",
    "gn:country_code":"KP",
    "gn:dem":140,
    "gn:feature_class":"P",
    "gn:feature_code":"PPL",
    "gn:name":"Hwaram-ni",
    "gn:population":0,
    "gn:timezone":"Asia/Pyongyang",
    "iso:country":"KP",
    "name:eng_x_preferred":[
        "Hwaram"
    ],
    "name:eng_x_variant":[
        "Hwaram-ni"
    ],
    "name:kor_x_preferred":[
        "\ud654\ub78c\ub9ac"
    ],
    "name:und_x_variant":[
        "Chich\u2019iram-i",
        "Hwaram-dong",
        "Tudurami",
        "Kotsugan-d\u014d",
        "Hwaram-ni"
    ],
    "wof:name":"Hwaram",
    "wof:placetype":"locality"
},
  "geometry": {"coordinates":[126.33333,38.45],"type":"Point"}
}