{
  "type": "Feature",
  "properties": {
    "gn:admin1_code":"0.0",
    "gn:asciiname":"Hwanggaegol",
    "gn:country_code":"KP",
    "gn:dem":866,
    "gn:feature_class":"P",
    "gn:feature_code":"PPL",
    "gn:name":"Hwanggaegol",
    "gn:population":0,
    "gn:timezone":"Asia/Pyongyang",
    "iso:country":"KP",
    "name:kor_x_preferred":[
        "\ud669\uac1c\uace8"
    ],
    "name:und_x_variant":[
        "Hwangp\u2019o-dong",
        "Hwanggaegol"
    ],
    "wof:name":"Hwanggaegol",
    "wof:placetype":"locality"
},
  "geometry": {"coordinates":[126.84999999999999,40.95],"type":"Point"}
}