{
  "type": "Feature",
  "properties": {
    "gn:admin1_code":"6.0",
    "gn:admin2_code":"1876380",
    "gn:asciiname":"Osal-li",
    "gn:country_code":"KP",
    "gn:dem":53,
    "gn:feature_class":"P",
    "gn:feature_code":"PPL",
    "gn:name":"Osal-li",
    "gn:population":0,
    "gn:timezone":"Asia/Pyongyang",
    "iso:country":"KP",
    "wof:name":"Osal-li",
    "wof:placetype":"locality"
},
  "geometry": {"coordinates":[126.54806000000001,37.93],"type":"Point"}
}