{
  "type": "Feature",
  "properties": {
    "gn:admin1_code":"9.0",
    "gn:asciiname":"Habukchom-ni",
    "gn:country_code":"KP",
    "gn:dem":410,
    "gn:feature_class":"P",
    "gn:feature_code":"PPL",
    "gn:name":"Habukch\u014fm-ni",
    "gn:population":0,
    "gn:timezone":"Asia/Pyongyang",
    "iso:country":"KP",
    "name:eng_x_preferred":[
        "Habukchom"
    ],
    "name:eng_x_variant":[
        "Habukchom-ni"
    ],
    "name:und_x_variant":[
        "\ud558\ubd81\uc810\ub9ac",
        "Habukch\u014fm-ni"
    ],
    "wof:name":"Habukchom",
    "wof:placetype":"locality"
},
  "geometry": {"coordinates":[127.98999999999999,38.54417],"type":"Point"}
}