{
  "type": "Feature",
  "properties": {
    "gn:admin1_code":"3.0",
    "gn:asciiname":"Sinhung-ni",
    "gn:country_code":"KP",
    "gn:dem":12,
    "gn:feature_class":"P",
    "gn:feature_code":"PPL",
    "gn:name":"Sinh\u016dng-ni",
    "gn:population":0,
    "gn:timezone":"Asia/Pyongyang",
    "iso:country":"KP",
    "name:eng_x_preferred":[
        "Sinhung"
    ],
    "name:eng_x_variant":[
        "Sinhung-ni"
    ],
    "name:und_x_variant":[
        "\uc2e0\ud765\ub9ac",
        "Sinh\u016dng-ni"
    ],
    "wof:name":"Sinhung",
    "wof:placetype":"locality"
},
  "geometry": {"coordinates":[127.47778,39.91944],"type":"Point"}
}