{
  "type": "Feature",
  "properties": {
    "gn:admin1_code":"9.0",
    "gn:asciiname":"Paehwa-ri",
    "gn:country_code":"KP",
    "gn:dem":9,
    "gn:feature_class":"P",
    "gn:feature_code":"PPL",
    "gn:name":"Paehwa-ri",
    "gn:population":0,
    "gn:timezone":"Asia/Pyongyang",
    "iso:country":"KP",
    "name:und_x_variant":[
        "\ubc30\ud654\ub9ac"
    ],
    "wof:name":"Paehwa-ri",
    "wof:placetype":"locality"
},
  "geometry": {"coordinates":[127.47918,39.08657],"type":"Point"}
}