{
  "type": "Feature",
  "properties": {
    "gn:admin1_code":"17.0",
    "gn:asciiname":"Chongsuam",
    "gn:country_code":"KP",
    "gn:dem":343,
    "gn:feature_class":"P",
    "gn:feature_code":"PPL",
    "gn:name":"Ch\u014fngsuam",
    "gn:population":0,
    "gn:timezone":"Asia/Pyongyang",
    "iso:country":"KP",
    "name:und_x_variant":[
        "\uc815\uc218\uc554",
        "Ch\u014fngsuam"
    ],
    "wof:name":"Chongsuam",
    "wof:placetype":"locality"
},
  "geometry": {"coordinates":[129.47721999999999,41.46139],"type":"Point"}
}