{
  "type": "Feature",
  "properties": {
    "gn:admin1_code":"11.0",
    "gn:asciiname":"Masong-ni",
    "gn:country_code":"KP",
    "gn:dem":47,
    "gn:feature_class":"P",
    "gn:feature_code":"PPL",
    "gn:name":"Mas\u014fng-ni",
    "gn:population":0,
    "gn:timezone":"Asia/Pyongyang",
    "iso:country":"KP",
    "name:eng_x_preferred":[
        "Masong"
    ],
    "name:eng_x_variant":[
        "Masong-ni"
    ],
    "name:und_x_variant":[
        "Mas\u014fng-dong",
        "\ub9c8\uc131\ub9ac",
        "Mas\u014fng-ni"
    ],
    "wof:name":"Masong",
    "wof:placetype":"locality"
},
  "geometry": {"coordinates":[124.75139,39.81444],"type":"Point"}
}