{
  "type": "Feature",
  "properties": {
    "gn:admin1_code":"11.0",
    "gn:asciiname":"Hadal-li",
    "gn:country_code":"KP",
    "gn:dem":54,
    "gn:feature_class":"P",
    "gn:feature_code":"PPL",
    "gn:name":"Hadal-li",
    "gn:population":0,
    "gn:timezone":"Asia/Pyongyang",
    "iso:country":"KP",
    "name:und_x_variant":[
        "\ud558\ub2e8\ub9ac",
        "Hadan-ni",
        "Hadal-li"
    ],
    "wof:name":"Hadal-li",
    "wof:placetype":"locality"
},
  "geometry": {"coordinates":[124.61056000000001,40.08722],"type":"Point"}
}