{
  "type": "Feature",
  "properties": {
    "gn:admin1_code":"17.0",
    "gn:asciiname":"Mulbanga",
    "gn:country_code":"KP",
    "gn:dem":369,
    "gn:feature_class":"P",
    "gn:feature_code":"PPL",
    "gn:name":"Mulbanga",
    "gn:population":0,
    "gn:timezone":"Asia/Pyongyang",
    "iso:country":"KP",
    "name:und_x_variant":[
        "\ubb3c\ubc29\uc544",
        "Mulbanga"
    ],
    "wof:name":"Mulbanga",
    "wof:placetype":"locality"
},
  "geometry": {"coordinates":[129.48417000000001,41.68028],"type":"Point"}
}