{
  "type": "Feature",
  "properties": {
    "gn:admin1_code":"13.0",
    "gn:asciiname":"Top'yong-ni",
    "gn:country_code":"KP",
    "gn:dem":545,
    "gn:feature_class":"P",
    "gn:feature_code":"PPL",
    "gn:name":"Top\u2019y\u014fng-ni",
    "gn:population":0,
    "gn:timezone":"Asia/Shanghai",
    "iso:country":"KP",
    "name:kor_x_preferred":[
        "\ub3c4\ud3c9\ub9ac"
    ],
    "name:und_x_variant":[
        "Top\u2019y\u014fng-ni"
    ],
    "wof:name":"Top'yong-ni",
    "wof:placetype":"locality"
},
  "geometry": {"coordinates":[127.67956,41.41553],"type":"Point"}
}