{
  "type": "Feature",
  "properties": {
    "gn:admin1_code":"11.0",
    "gn:asciiname":"Paekhung-ni",
    "gn:country_code":"KP",
    "gn:dem":123,
    "gn:feature_class":"P",
    "gn:feature_code":"PPL",
    "gn:name":"Paekh\u016dng-ni",
    "gn:population":0,
    "gn:timezone":"Asia/Pyongyang",
    "iso:country":"KP",
    "name:eng_x_preferred":[
        "Paekhung"
    ],
    "name:eng_x_variant":[
        "Paekhung-ni"
    ],
    "name:kor_x_preferred":[
        "\ubc31\ud765\ub9ac"
    ],
    "name:und_x_variant":[
        "Paekh\u016dng-ni"
    ],
    "wof:name":"Paekhung",
    "wof:placetype":"locality"
},
  "geometry": {"coordinates":[125.37194,39.83389],"type":"Point"}
}