{
  "type": "Feature",
  "properties": {
    "gn:admin1_code":"9.0",
    "gn:asciiname":"Yanggae-gol",
    "gn:country_code":"KP",
    "gn:dem":489,
    "gn:feature_class":"P",
    "gn:feature_code":"PPL",
    "gn:name":"Yanggae-gol",
    "gn:population":0,
    "gn:timezone":"Asia/Pyongyang",
    "iso:country":"KP",
    "name:und_x_variant":[
        "\uc591\uac1c\uace8",
        "Yanggae-gol"
    ],
    "wof:name":"Yanggae-gol",
    "wof:placetype":"locality"
},
  "geometry": {"coordinates":[127.74917000000001,38.63028],"type":"Point"}
}