{
  "type": "Feature",
  "properties": {
    "gn:admin1_code":"6.0",
    "gn:asciiname":"Sin'gyo-dong",
    "gn:country_code":"KP",
    "gn:dem":25,
    "gn:feature_class":"P",
    "gn:feature_code":"PPL",
    "gn:name":"Sin\u2019gyo-dong",
    "gn:population":0,
    "gn:timezone":"Asia/Pyongyang",
    "iso:country":"KP",
    "name:und_x_variant":[
        "\uc2e0\uad50\ub3d9",
        "Sin\u2019gyo-dong"
    ],
    "wof:name":"Sin'gyo-dong",
    "wof:placetype":"locality"
},
  "geometry": {"coordinates":[125.64943999999998,37.93306],"type":"Point"}
}