{
  "type": "Feature",
  "properties": {
    "gn:admin1_code":"3.0",
    "gn:asciiname":"Sap'oil-tong",
    "gn:country_code":"KP",
    "gn:dem":12,
    "gn:feature_class":"P",
    "gn:feature_code":"PPL",
    "gn:name":"Sap\u2019oil-tong",
    "gn:population":0,
    "gn:timezone":"Asia/Pyongyang",
    "iso:country":"KP",
    "name:und_x_variant":[
        "Sap\u2019o-ri",
        "\uc0ac\ud3ec\uc77c\ub3d9",
        "Sap\u2019o-dong",
        "Sap\u2019oil-tong"
    ],
    "wof:name":"Sap'oil-tong",
    "wof:placetype":"locality"
},
  "geometry": {"coordinates":[127.54194,39.8925],"type":"Point"}
}