{
  "type": "Feature",
  "properties": {
    "gn:admin1_code":"9.0",
    "gn:asciiname":"Oul-li",
    "gn:country_code":"KP",
    "gn:dem":70,
    "gn:feature_class":"P",
    "gn:feature_code":"PPL",
    "gn:name":"\u014e\u016dl-li",
    "gn:population":0,
    "gn:timezone":"Asia/Pyongyang",
    "iso:country":"KP",
    "name:kor_x_preferred":[
        "\uc5b4\uc740\ub9ac"
    ],
    "name:kor_x_variant":[
        "\u014e\u016dl-li"
    ],
    "name:und_x_variant":[
        "\u014e\u016dn-ni"
    ],
    "wof:name":"Oul-li",
    "wof:placetype":"locality"
},
  "geometry": {"coordinates":[127.14,39.29583],"type":"Point"}
}