{
  "type": "Feature",
  "properties": {
    "gn:admin1_code":"7.0",
    "gn:asciiname":"Sinya-dong",
    "gn:country_code":"KP",
    "gn:dem":353,
    "gn:feature_class":"P",
    "gn:feature_code":"PPL",
    "gn:name":"Sinya-dong",
    "gn:population":0,
    "gn:timezone":"Asia/Pyongyang",
    "iso:country":"KP",
    "name:kor_x_preferred":[
        "\uc2e0\uc57c\ub3d9"
    ],
    "wof:name":"Sinya-dong",
    "wof:placetype":"locality"
},
  "geometry": {"coordinates":[126.58360999999999,38.92778],"type":"Point"}
}