{
  "type": "Feature",
  "properties": {
    "gn:admin1_code":"9.0",
    "gn:asciiname":"Sangp'yong-ni",
    "gn:country_code":"KP",
    "gn:dem":122,
    "gn:feature_class":"P",
    "gn:feature_code":"PPL",
    "gn:name":"Sangp\u2019y\u014fng-ni",
    "gn:population":0,
    "gn:timezone":"Asia/Pyongyang",
    "iso:country":"KP",
    "name:eng_x_preferred":[
        "Sangp'yong"
    ],
    "name:eng_x_variant":[
        "Sangp'yong-ni"
    ],
    "name:kor_x_preferred":[
        "\uc0c1\ud3c9\ub9ac"
    ],
    "name:kor_x_variant":[
        "Sangp\u2019y\u014fng-ni"
    ],
    "wof:name":"Sangp'yong",
    "wof:placetype":"locality"
},
  "geometry": {"coordinates":[127.12611,39.23028],"type":"Point"}
}