{
  "type": "Feature",
  "properties": {
    "gn:admin1_code":"1.0",
    "gn:asciiname":"Ch'angcham",
    "gn:country_code":"KP",
    "gn:dem":567,
    "gn:feature_class":"P",
    "gn:feature_code":"PPL",
    "gn:name":"Ch\u2019angcham",
    "gn:population":0,
    "gn:timezone":"Asia/Pyongyang",
    "iso:country":"KP",
    "name:und_x_variant":[
        "\ucc3d\ucc38",
        "Ch\u2019angcham"
    ],
    "wof:name":"Ch'angcham",
    "wof:placetype":"locality"
},
  "geometry": {"coordinates":[126.41806,40.5425],"type":"Point"}
}