{
  "type": "Feature",
  "properties": {
    "gn:admin1_code":"7.0",
    "gn:asciiname":"Suip-tong",
    "gn:country_code":"KP",
    "gn:dem":243,
    "gn:feature_class":"P",
    "gn:feature_code":"PPL",
    "gn:name":"Suip-tong",
    "gn:population":0,
    "gn:timezone":"Asia/Pyongyang",
    "iso:country":"KP",
    "name:kor_x_preferred":[
        "\uc218\uc785\ub3d9"
    ],
    "wof:name":"Suip-tong",
    "wof:placetype":"locality"
},
  "geometry": {"coordinates":[126.68917,38.72889],"type":"Point"}
}