{
  "type": "Feature",
  "properties": {
    "gn:admin1_code":"17.0",
    "gn:asciiname":"Hagumsaeng-dong",
    "gn:country_code":"KP",
    "gn:dem":213,
    "gn:feature_class":"P",
    "gn:feature_code":"PPL",
    "gn:name":"Hag\u016dmsaeng-dong",
    "gn:population":0,
    "gn:timezone":"Asia/Pyongyang",
    "iso:country":"KP",
    "name:und_x_variant":[
        "\ud558\uae08\uc0dd\ub3d9",
        "Hag\u016dmsaeng-dong"
    ],
    "wof:name":"Hagumsaeng-dong",
    "wof:placetype":"locality"
},
  "geometry": {"coordinates":[129.74694,42.48028],"type":"Point"}
}