{
  "type": "Feature",
  "properties": {
    "gn:admin1_code":"11.0",
    "gn:asciiname":"T'apchung-dong",
    "gn:country_code":"KP",
    "gn:dem":13,
    "gn:feature_class":"P",
    "gn:feature_code":"PPL",
    "gn:name":"T\u2019apchung-dong",
    "gn:population":0,
    "gn:timezone":"Asia/Pyongyang",
    "iso:country":"KP",
    "name:und_x_variant":[
        "T\u014dch\u016b-d\u014d",
        "\ud0d1\uc911\ub3d9",
        "T\u2019apchung-dong"
    ],
    "wof:name":"T'apchung-dong",
    "wof:placetype":"locality"
},
  "geometry": {"coordinates":[124.45222,40.08],"type":"Point"}
}