{
  "type": "Feature",
  "properties": {
    "gn:admin1_code":"15.0",
    "gn:admin2_code":"S\u014fngch\u2019\u014fn-gun",
    "gn:asciiname":"Yongam-ni",
    "gn:country_code":"KP",
    "gn:dem":57,
    "gn:feature_class":"P",
    "gn:feature_code":"PPL",
    "gn:name":"Yongam-ni",
    "gn:population":0,
    "gn:timezone":"Asia/Pyongyang",
    "iso:country":"KP",
    "name:eng_x_preferred":[
        "Yongam"
    ],
    "name:eng_x_variant":[
        "Yongam-ni"
    ],
    "wof:name":"Yongam",
    "wof:placetype":"locality"
},
  "geometry": {"coordinates":[126.14167,39.24694],"type":"Point"}
}