{
  "type": "Feature",
  "properties": {
    "gn:admin1_code":"9.0",
    "gn:asciiname":"Yongch'ol-li",
    "gn:country_code":"KP",
    "gn:dem":205,
    "gn:feature_class":"P",
    "gn:feature_code":"PPL",
    "gn:name":"Yongch\u2019\u014fl-li",
    "gn:population":0,
    "gn:timezone":"Asia/Pyongyang",
    "iso:country":"KP",
    "name:und_x_variant":[
        "Yongch\u2019\u014fn-ni",
        "Yongch\u2019\u014fl-li"
    ],
    "wof:name":"Yongch'ol-li",
    "wof:placetype":"locality"
},
  "geometry": {"coordinates":[126.95389,38.69444],"type":"Point"}
}