{
  "type": "Feature",
  "properties": {
    "gn:admin1_code":"3.0",
    "gn:asciiname":"Wonsang-ni",
    "gn:country_code":"KP",
    "gn:dem":202,
    "gn:feature_class":"P",
    "gn:feature_code":"PPL",
    "gn:name":"W\u014fnsang-ni",
    "gn:population":0,
    "gn:timezone":"Asia/Pyongyang",
    "iso:country":"KP",
    "name:und_x_variant":[
        "\uc6d0\uc0c1\ub9ac",
        "W\u014fnsang-ni"
    ],
    "wof:name":"Wonsang-ni",
    "wof:placetype":"locality"
},
  "geometry": {"coordinates":[127.88500000000001,40.1575],"type":"Point"}
}