{
  "type": "Feature",
  "properties": {
    "gn:admin1_code":"0.0",
    "gn:asciiname":"Haong-dong",
    "gn:country_code":"KP",
    "gn:dem":309,
    "gn:feature_class":"P",
    "gn:feature_code":"PPL",
    "gn:name":"Haong-dong",
    "gn:population":0,
    "gn:timezone":"Asia/Pyongyang",
    "iso:country":"KP",
    "name:kor_x_preferred":[
        "\ud558\uc639\ub3d9"
    ],
    "wof:name":"Haong-dong",
    "wof:placetype":"locality"
},
  "geometry": {"coordinates":[127.21666999999999,38.65],"type":"Point"}
}