{
  "type": "Feature",
  "properties": {
    "gn:admin1_code":"17.0",
    "gn:asciiname":"Puyun",
    "gn:country_code":"KP",
    "gn:dem":38,
    "gn:feature_class":"P",
    "gn:feature_code":"PPL",
    "gn:name":"Puyun",
    "gn:population":0,
    "gn:timezone":"Asia/Pyongyang",
    "iso:country":"KP",
    "name:und_x_variant":[
        "\ubd80\uc724",
        "Puyun"
    ],
    "wof:name":"Puyun",
    "wof:placetype":"locality"
},
  "geometry": {"coordinates":[129.59999999999999,41.24528],"type":"Point"}
}