{
  "type": "Feature",
  "properties": {
    "gn:admin1_code":"1.0",
    "gn:asciiname":"Saengdongch'am",
    "gn:country_code":"KP",
    "gn:dem":674,
    "gn:feature_class":"P",
    "gn:feature_code":"PPL",
    "gn:name":"Saengdongch\u2019am",
    "gn:population":0,
    "gn:timezone":"Asia/Pyongyang",
    "iso:country":"KP",
    "name:kor_x_preferred":[
        "Sas\u016draegol-ma\u016dl"
    ],
    "name:kor_x_variant":[
        "\uc0ac\uc2a4\ub798\uace8\ub9c8\uc744",
        "Saengdongch\u2019am",
        "\uc0dd\ub3d9\ucc38"
    ],
    "name:und_x_variant":[
        "\uc0dd\ub3d9\ucc38",
        "Saengdongch\u2019am"
    ],
    "wof:name":"Saengdongch'am",
    "wof:placetype":"locality"
},
  "geometry": {"coordinates":[126.63384000000001,40.72095],"type":"Point"}
}