{
  "type": "Feature",
  "properties": {
    "gn:admin1_code":"1.0",
    "gn:asciiname":"Kokchanggogae",
    "gn:country_code":"KP",
    "gn:dem":1242,
    "gn:feature_class":"P",
    "gn:feature_code":"PPL",
    "gn:name":"Kokchanggogae",
    "gn:population":0,
    "gn:timezone":"Asia/Pyongyang",
    "iso:country":"KP",
    "name:kor_x_preferred":[
        "\uace1\uc7a5\uace0\uac1c"
    ],
    "wof:name":"Kokchanggogae",
    "wof:placetype":"locality"
},
  "geometry": {"coordinates":[127.61972,40.53222],"type":"Point"}
}