{
  "type": "Feature",
  "properties": {
    "gn:admin1_code":"9.0",
    "gn:admin2_code":"Munch\u2019\u014fn-si",
    "gn:asciiname":"Yangji-dong",
    "gn:country_code":"KP",
    "gn:dem":11,
    "gn:feature_class":"P",
    "gn:feature_code":"PPL",
    "gn:name":"Yangji-dong",
    "gn:population":0,
    "gn:timezone":"Asia/Pyongyang",
    "iso:country":"KP",
    "name:und_x_variant":[
        "Y\u014dchi-do",
        "Yangji-dong",
        "\uc591\uc9c0\ub3d9"
    ],
    "wof:name":"Yangji-dong",
    "wof:placetype":"locality"
},
  "geometry": {"coordinates":[127.34166999999999,39.25722],"type":"Point"}
}