{
  "type": "Feature",
  "properties": {
    "gn:admin1_code":"7.0",
    "gn:asciiname":"Kumhwa",
    "gn:country_code":"KP",
    "gn:dem":10,
    "gn:feature_class":"P",
    "gn:feature_code":"PPL",
    "gn:name":"K\u016dmhwa",
    "gn:population":0,
    "gn:timezone":"Asia/Pyongyang",
    "iso:country":"KP",
    "name:kor_x_preferred":[
        "\uae08\ud654"
    ],
    "name:kor_x_variant":[
        "K\u016dmhwa"
    ],
    "wof:name":"Kumhwa",
    "wof:placetype":"locality"
},
  "geometry": {"coordinates":[125.68556,38.59806],"type":"Point"}
}