{
  "type": "Feature",
  "properties": {
    "gn:admin1_code":"6.0",
    "gn:asciiname":"Changt'ong-ni",
    "gn:country_code":"KP",
    "gn:dem":50,
    "gn:feature_class":"P",
    "gn:feature_code":"PPL",
    "gn:name":"Changt\u2019ong-ni",
    "gn:population":0,
    "gn:timezone":"Asia/Pyongyang",
    "iso:country":"KP",
    "name:und_x_variant":[
        "\uc7a5\ud1b5\ub9ac",
        "Changt\u2019ong-ni"
    ],
    "wof:name":"Changt'ong-ni",
    "wof:placetype":"locality"
},
  "geometry": {"coordinates":[125.25111,38.59278],"type":"Point"}
}