{
  "type": "Feature",
  "properties": {
    "gn:admin1_code":"6.0",
    "gn:asciiname":"Sadanggami",
    "gn:cc2":"KP",
    "gn:country_code":"KP",
    "gn:dem":9,
    "gn:feature_class":"P",
    "gn:feature_code":"PPL",
    "gn:name":"Sadanggami",
    "gn:population":0,
    "gn:timezone":"Asia/Pyongyang",
    "iso:country":"KP",
    "name:und_x_variant":[
        "Sadangg\u014f-ri",
        "Sadanggami"
    ],
    "wof:name":"Sadanggami",
    "wof:placetype":"locality"
},
  "geometry": {"coordinates":[126.27278,37.86278],"type":"Point"}
}