{
  "type": "Feature",
  "properties": {
    "gn:admin1_code":"3.0",
    "gn:asciiname":"Sangsungji",
    "gn:country_code":"KP",
    "gn:dem":377,
    "gn:feature_class":"P",
    "gn:feature_code":"PPL",
    "gn:name":"Sangs\u016dngji",
    "gn:population":0,
    "gn:timezone":"Asia/Pyongyang",
    "iso:country":"KP",
    "name:und_x_variant":[
        "Sangs\u016dngji",
        "\uc0c1\uc2b9\uc9c0"
    ],
    "wof:name":"Sangsungji",
    "wof:placetype":"locality"
},
  "geometry": {"coordinates":[128.16763,40.39631],"type":"Point"}
}