{
  "type": "Feature",
  "properties": {
    "gn:admin1_code":"11.0",
    "gn:asciiname":"Ogya-dong",
    "gn:cc2":"KP",
    "gn:country_code":"KP",
    "gn:dem":37,
    "gn:feature_class":"P",
    "gn:feature_code":"PPL",
    "gn:name":"Ogya-dong",
    "gn:population":0,
    "gn:timezone":"Asia/Pyongyang",
    "iso:country":"KP",
    "name:kor_x_preferred":[
        "\uc625\uc57c\ub3d9"
    ],
    "name:und_x_variant":[
        "Ogya-ri",
        "Ogya-dong"
    ],
    "wof:name":"Ogya-dong",
    "wof:placetype":"locality"
},
  "geometry": {"coordinates":[125.38722,39.64806],"type":"Point"}
}