{
  "type": "Feature",
  "properties": {
    "gn:admin1_code":"11.0",
    "gn:asciiname":"Naech'am-ni",
    "gn:country_code":"KP",
    "gn:dem":171,
    "gn:feature_class":"P",
    "gn:feature_code":"PPL",
    "gn:name":"Naech\u2019am-ni",
    "gn:population":0,
    "gn:timezone":"Asia/Pyongyang",
    "iso:country":"KP",
    "name:eng_x_preferred":[
        "Naech'am"
    ],
    "name:eng_x_variant":[
        "Naech'am-ni"
    ],
    "name:und_x_variant":[
        "\ub0b4\ucc38\ub9ac",
        "Naech\u2019am-ni"
    ],
    "wof:name":"Naech'am",
    "wof:placetype":"locality"
},
  "geometry": {"coordinates":[125.61083000000001,40.1225],"type":"Point"}
}