{
  "type": "Feature",
  "properties": {
    "gn:admin1_code":"9.0",
    "gn:asciiname":"Ogu-dong",
    "gn:country_code":"KP",
    "gn:dem":470,
    "gn:feature_class":"P",
    "gn:feature_code":"PPL",
    "gn:name":"\u014egu-dong",
    "gn:population":0,
    "gn:timezone":"Asia/Pyongyang",
    "iso:country":"KP",
    "wof:name":"Ogu-dong",
    "wof:placetype":"locality"
},
  "geometry": {"coordinates":[128.03888999999998,38.60333],"type":"Point"}
}