{
  "type": "Feature",
  "properties": {
    "gn:admin1_code":"0.0",
    "gn:asciiname":"Puam-ni",
    "gn:country_code":"KP",
    "gn:dem":19,
    "gn:feature_class":"P",
    "gn:feature_code":"PPL",
    "gn:name":"Puam-ni",
    "gn:population":0,
    "gn:timezone":"Asia/Pyongyang",
    "iso:country":"KP",
    "name:kor_x_preferred":[
        "\ubd80\uc554\ub9ac"
    ],
    "wof:name":"Puam-ni",
    "wof:placetype":"locality"
},
  "geometry": {"coordinates":[125.51667,37.91667],"type":"Point"}
}