{
  "type": "Feature",
  "properties": {
    "gn:admin1_code":"15.0",
    "gn:admin2_code":"Ch\u2019\u014fngnam-gu",
    "gn:asciiname":"Inp'ung-ni",
    "gn:country_code":"KP",
    "gn:dem":10,
    "gn:feature_class":"P",
    "gn:feature_code":"PPL",
    "gn:name":"Inp\u2019ung-ni",
    "gn:population":0,
    "gn:timezone":"Asia/Pyongyang",
    "iso:country":"KP",
    "wof:name":"Inp'ung-ni",
    "wof:placetype":"locality"
},
  "geometry": {"coordinates":[125.44556,39.48417],"type":"Point"}
}