{
  "type": "Feature",
  "properties": {
    "gn:admin1_code":"6.0",
    "gn:asciiname":"Kyongt'an",
    "gn:country_code":"KP",
    "gn:dem":18,
    "gn:feature_class":"P",
    "gn:feature_code":"PPL",
    "gn:name":"Ky\u014fngt\u2019an",
    "gn:population":0,
    "gn:timezone":"Asia/Pyongyang",
    "iso:country":"KP",
    "name:und_x_variant":[
        "\uacbd\ud0c4",
        "Ky\u014fngt\u2019an"
    ],
    "wof:name":"Kyongt'an",
    "wof:placetype":"locality"
},
  "geometry": {"coordinates":[124.72111,38.13583],"type":"Point"}
}