{
  "type": "Feature",
  "properties": {
    "gn:admin1_code":"3.0",
    "gn:admin2_code":"K\u016dmya-gun",
    "gn:asciiname":"Hyongt'al-li",
    "gn:country_code":"KP",
    "gn:dem":42,
    "gn:feature_class":"P",
    "gn:feature_code":"PPL",
    "gn:name":"Hy\u014fngt\u2019al-li",
    "gn:population":0,
    "gn:timezone":"Asia/Pyongyang",
    "iso:country":"KP",
    "name:kor_x_preferred":[
        "Hy\u014fngt\u2019al-li"
    ],
    "name:und_x_variant":[
        "Hy\u014fngt\u2019an-ni",
        "Hy\u014fngnan-ni",
        "\ud615\ud0c4\ub9ac"
    ],
    "wof:name":"Hyongt'al-li",
    "wof:placetype":"locality"
},
  "geometry": {"coordinates":[127.19861000000002,39.49972],"type":"Point"}
}