{
  "type": "Feature",
  "properties": {
    "gn:admin1_code":"1.0",
    "gn:asciiname":"Yup'yong",
    "gn:country_code":"KP",
    "gn:dem":544,
    "gn:feature_class":"P",
    "gn:feature_code":"PPL",
    "gn:name":"Yup\u2019y\u014fng",
    "gn:population":0,
    "gn:timezone":"Asia/Pyongyang",
    "iso:country":"KP",
    "name:und_x_variant":[
        "\uc720\ud3c9",
        "Yup\u2019y\u014fng"
    ],
    "wof:name":"Yup'yong",
    "wof:placetype":"locality"
},
  "geometry": {"coordinates":[126.90833000000001,41.27389],"type":"Point"}
}