{
  "type": "Feature",
  "properties": {
    "gn:admin1_code":"13.0",
    "gn:asciiname":"Hungsong-dong",
    "gn:country_code":"KP",
    "gn:dem":1353,
    "gn:feature_class":"P",
    "gn:feature_code":"PPL",
    "gn:name":"H\u016dngs\u014fng-dong",
    "gn:population":0,
    "gn:timezone":"Asia/Pyongyang",
    "iso:country":"KP",
    "wof:name":"Hungsong-dong",
    "wof:placetype":"locality"
},
  "geometry": {"coordinates":[128.41666999999998,41.63333],"type":"Point"}
}