{
  "type": "Feature",
  "properties": {
    "gn:admin1_code":"6.0",
    "gn:asciiname":"Ussabong",
    "gn:country_code":"KP",
    "gn:dem":168,
    "gn:feature_class":"P",
    "gn:feature_code":"PPL",
    "gn:name":"Ussabong",
    "gn:population":0,
    "gn:timezone":"Asia/Pyongyang",
    "iso:country":"KP",
    "wof:name":"Ussabong",
    "wof:placetype":"locality"
},
  "geometry": {"coordinates":[126.08750000000001,38.13889],"type":"Point"}
}