{
  "type": "Feature",
  "properties": {
    "gn:admin1_code":"9.0",
    "gn:asciiname":"Hagujol-tong",
    "gn:country_code":"KP",
    "gn:dem":296,
    "gn:feature_class":"P",
    "gn:feature_code":"PPL",
    "gn:name":"Haguj\u014fl-tong",
    "gn:population":0,
    "gn:timezone":"Asia/Pyongyang",
    "iso:country":"KP",
    "name:und_x_variant":[
        "\ud558\uad6c\uc808\ub3d9",
        "Haguj\u014fl-tong"
    ],
    "wof:name":"Hagujol-tong",
    "wof:placetype":"locality"
},
  "geometry": {"coordinates":[127.55,38.91],"type":"Point"}
}