{
  "type": "Feature",
  "properties": {
    "gn:admin1_code":"0.0",
    "gn:asciiname":"Soam",
    "gn:country_code":"KP",
    "gn:dem":38,
    "gn:feature_class":"P",
    "gn:feature_code":"PPL",
    "gn:name":"S\u014fam",
    "gn:population":0,
    "gn:timezone":"Asia/Pyongyang",
    "iso:country":"KP",
    "name:kor_x_preferred":[
        "\uc11c\uc554"
    ],
    "name:und_x_variant":[
        "S\u014fam"
    ],
    "wof:name":"Soam",
    "wof:placetype":"locality"
},
  "geometry": {"coordinates":[125.71666999999999,38.83333],"type":"Point"}
}