{
  "type": "Feature",
  "properties": {
    "gn:admin1_code":"11.0",
    "gn:asciiname":"Sangdan-maul",
    "gn:country_code":"KP",
    "gn:dem":15,
    "gn:feature_class":"P",
    "gn:feature_code":"PPL",
    "gn:name":"Sangdan-ma\u016dl",
    "gn:population":0,
    "gn:timezone":"Asia/Pyongyang",
    "iso:country":"KP",
    "name:kor_x_preferred":[
        "\uc0c1\ub2e8\ub9ac"
    ],
    "name:kor_x_variant":[
        "Sangdan-ma\u016dl",
        "\uc0c1\ub2e8\ub9c8\uc744"
    ],
    "name:und_x_variant":[
        "Sangdan",
        "Sangdan-ni",
        "Sangdal-li"
    ],
    "wof:name":"Sangdan-maul",
    "wof:placetype":"locality"
},
  "geometry": {"coordinates":[125.0081,39.65857000000001],"type":"Point"}
}