{
  "type": "Feature",
  "properties": {
    "gn:admin1_code":"11.0",
    "gn:asciiname":"Chuui-ri",
    "gn:country_code":"KP",
    "gn:dem":3,
    "gn:feature_class":"P",
    "gn:feature_code":"PPL",
    "gn:name":"Chu\u016di-ri",
    "gn:population":0,
    "gn:timezone":"Asia/Pyongyang",
    "iso:country":"KP",
    "name:und_x_variant":[
        "Chu\u016di-dong",
        "\uc8fc\uc758\ub9ac",
        "Chu\u016di-ri"
    ],
    "wof:name":"Chuui-ri",
    "wof:placetype":"locality"
},
  "geometry": {"coordinates":[124.53471999999999,39.85472],"type":"Point"}
}