{
  "type": "Feature",
  "properties": {
    "gn:admin1_code":"3.0",
    "gn:asciiname":"Sanggot'al",
    "gn:country_code":"KP",
    "gn:dem":81,
    "gn:feature_class":"P",
    "gn:feature_code":"PPL",
    "gn:name":"Sanggot\u2019al",
    "gn:population":0,
    "gn:timezone":"Asia/Pyongyang",
    "iso:country":"KP",
    "name:und_x_variant":[
        "Sanggot\u2019an",
        "\uc0c1\uace0\ud0c8",
        "Sanggot\u2019al"
    ],
    "wof:name":"Sanggot'al",
    "wof:placetype":"locality"
},
  "geometry": {"coordinates":[127.82167,39.92222],"type":"Point"}
}