{
  "type": "Feature",
  "properties": {
    "gn:admin1_code":"17.0",
    "gn:asciiname":"Yongjin-dong",
    "gn:country_code":"KP",
    "gn:dem":32,
    "gn:feature_class":"P",
    "gn:feature_code":"PPL",
    "gn:name":"Y\u014fngjin-dong",
    "gn:population":0,
    "gn:timezone":"Asia/Pyongyang",
    "iso:country":"KP",
    "name:und_x_variant":[
        "\uc601\uc9c4\ub3d9",
        "Y\u014fngjin-dong"
    ],
    "wof:name":"Yongjin-dong",
    "wof:placetype":"locality"
},
  "geometry": {"coordinates":[130.13193999999999,42.10611],"type":"Point"}
}