{
  "type": "Feature",
  "properties": {
    "gn:admin1_code":"0.0",
    "gn:asciiname":"Sangjae-dong",
    "gn:country_code":"KP",
    "gn:dem":1266,
    "gn:feature_class":"P",
    "gn:feature_code":"PPL",
    "gn:name":"Sangjae-dong",
    "gn:population":0,
    "gn:timezone":"Asia/Pyongyang",
    "iso:country":"KP",
    "name:kor_x_preferred":[
        "\uc0c1\uc7ac\ub3d9"
    ],
    "wof:name":"Sangjae-dong",
    "wof:placetype":"locality"
},
  "geometry": {"coordinates":[127.34999999999999,40.25],"type":"Point"}
}