{
  "type": "Feature",
  "properties": {
    "gn:admin1_code":"3.0",
    "gn:asciiname":"Nongdok",
    "gn:country_code":"KP",
    "gn:dem":98,
    "gn:feature_class":"P",
    "gn:feature_code":"PPL",
    "gn:name":"Nongd\u014fk",
    "gn:population":0,
    "gn:timezone":"Asia/Pyongyang",
    "iso:country":"KP",
    "name:und_x_variant":[
        "\ub18d\ub355",
        "Nongd\u014fk"
    ],
    "wof:name":"Nongdok",
    "wof:placetype":"locality"
},
  "geometry": {"coordinates":[128.98832999999999,40.5975],"type":"Point"}
}