{
  "type": "Feature",
  "properties": {
    "gn:admin1_code":"11.0",
    "gn:asciiname":"Kanghung-ni",
    "gn:country_code":"KP",
    "gn:dem":254,
    "gn:feature_class":"P",
    "gn:feature_code":"PPL",
    "gn:name":"Kangh\u016dng-ni",
    "gn:population":0,
    "gn:timezone":"Asia/Pyongyang",
    "iso:country":"KP",
    "name:und_x_variant":[
        "\uac15\ud765\ub9ac",
        "Kangh\u016dng-ni"
    ],
    "wof:name":"Kanghung-ni",
    "wof:placetype":"locality"
},
  "geometry": {"coordinates":[125.38278,40.59611],"type":"Point"}
}