{
  "type": "Feature",
  "properties": {
    "gn:admin1_code":"7.0",
    "gn:asciiname":"Sangsokka-dong",
    "gn:country_code":"KP",
    "gn:dem":95,
    "gn:feature_class":"P",
    "gn:feature_code":"PPL",
    "gn:name":"Sangs\u014fkka-dong",
    "gn:population":0,
    "gn:timezone":"Asia/Pyongyang",
    "iso:country":"KP",
    "wof:name":"Sangsokka-dong",
    "wof:placetype":"locality"
},
  "geometry": {"coordinates":[126.59721999999999,38.17028],"type":"Point"}
}