{
  "type": "Feature",
  "properties": {
    "gn:admin1_code":"17.0",
    "gn:asciiname":"Hwasok-tong",
    "gn:country_code":"KP",
    "gn:dem":740,
    "gn:feature_class":"P",
    "gn:feature_code":"PPL",
    "gn:name":"Hwas\u014fk-tong",
    "gn:population":0,
    "gn:timezone":"Asia/Pyongyang",
    "iso:country":"KP",
    "wof:name":"Hwasok-tong",
    "wof:placetype":"locality"
},
  "geometry": {"coordinates":[129.01889,41.14806],"type":"Point"}
}