{
  "type": "Feature",
  "properties": {
    "gn:admin1_code":"12.0",
    "gn:admin2_code":"Kangdong-gun",
    "gn:asciiname":"Puksian",
    "gn:country_code":"KP",
    "gn:dem":76,
    "gn:feature_class":"P",
    "gn:feature_code":"PPL",
    "gn:name":"Puksian",
    "gn:population":0,
    "gn:timezone":"Asia/Pyongyang",
    "iso:country":"KP",
    "name:kor_x_preferred":[
        "\ubd81\uc2dc\uc548"
    ],
    "name:und_x_variant":[
        "Buksian"
    ],
    "wof:name":"Puksian",
    "wof:placetype":"locality"
},
  "geometry": {"coordinates":[126.25444,39.02778],"type":"Point"}
}