{
  "type": "Feature",
  "properties": {
    "gn:admin1_code":"11.0",
    "gn:asciiname":"Naeong-ni",
    "gn:country_code":"KP",
    "gn:dem":110,
    "gn:feature_class":"P",
    "gn:feature_code":"PPL",
    "gn:name":"Naeong-ni",
    "gn:population":0,
    "gn:timezone":"Asia/Pyongyang",
    "iso:country":"KP",
    "wof:name":"Naeong-ni",
    "wof:placetype":"locality"
},
  "geometry": {"coordinates":[124.80278,40.28139],"type":"Point"}
}