{
  "type": "Feature",
  "properties": {
    "gn:admin1_code":"11.0",
    "gn:asciiname":"Soha-ri",
    "gn:country_code":"KP",
    "gn:dem":36,
    "gn:feature_class":"P",
    "gn:feature_code":"PPL",
    "gn:name":"S\u014fha-ri",
    "gn:population":0,
    "gn:timezone":"Asia/Pyongyang",
    "iso:country":"KP",
    "name:und_x_variant":[
        "\uc11c\ud558\ub9ac",
        "S\u014fha-ri"
    ],
    "wof:name":"Soha-ri",
    "wof:placetype":"locality"
},
  "geometry": {"coordinates":[124.65889,40.07139],"type":"Point"}
}