{
  "type": "Feature",
  "properties": {
    "gn:admin1_code":"17.0",
    "gn:asciiname":"Odungch'on",
    "gn:country_code":"KP",
    "gn:dem":417,
    "gn:feature_class":"P",
    "gn:feature_code":"PPL",
    "gn:name":"Od\u016dngch\u2019on",
    "gn:population":0,
    "gn:timezone":"Asia/Pyongyang",
    "iso:country":"KP",
    "name:und_x_variant":[
        "\uc624\ub4f1\ucd0c",
        "Od\u016dngch\u2019on"
    ],
    "wof:name":"Odungch'on",
    "wof:placetype":"locality"
},
  "geometry": {"coordinates":[129.15693999999999,40.9525],"type":"Point"}
}