{
  "type": "Feature",
  "properties": {
    "gn:admin1_code":"11.0",
    "gn:asciiname":"Samp'omal",
    "gn:country_code":"KP",
    "gn:dem":114,
    "gn:feature_class":"P",
    "gn:feature_code":"PPL",
    "gn:name":"Samp\u2019omal",
    "gn:population":0,
    "gn:timezone":"Asia/Pyongyang",
    "iso:country":"KP",
    "name:und_x_variant":[
        "\uc0bc\ud3ec\ub9d0",
        "Samp\u2019omal"
    ],
    "wof:name":"Samp'omal",
    "wof:placetype":"locality"
},
  "geometry": {"coordinates":[125.53082999999999,40.04778],"type":"Point"}
}