{
  "type": "Feature",
  "properties": {
    "gn:admin1_code":"15.0",
    "gn:asciiname":"An-gol",
    "gn:country_code":"KP",
    "gn:dem":19,
    "gn:feature_class":"P",
    "gn:feature_code":"PPL",
    "gn:name":"An-gol",
    "gn:population":0,
    "gn:timezone":"Asia/Pyongyang",
    "iso:country":"KP",
    "name:und_x_variant":[
        "An-dong",
        "\uc548\uace8",
        "An-gol"
    ],
    "wof:name":"An-gol",
    "wof:placetype":"locality"
},
  "geometry": {"coordinates":[125.27278,38.91472],"type":"Point"}
}