{
  "type": "Feature",
  "properties": {
    "gn:admin1_code":"15.0",
    "gn:asciiname":"Kyosang-ni",
    "gn:country_code":"KP",
    "gn:dem":285,
    "gn:feature_class":"P",
    "gn:feature_code":"PPL",
    "gn:name":"Kyosang-ni",
    "gn:population":0,
    "gn:timezone":"Asia/Pyongyang",
    "iso:country":"KP",
    "name:eng_x_preferred":[
        "Kyosang"
    ],
    "name:eng_x_variant":[
        "Kyosang-ni"
    ],
    "name:und_x_variant":[
        "\uad50\uc0c1\ub9ac",
        "Kyosang-ni"
    ],
    "wof:name":"Kyosang",
    "wof:placetype":"locality"
},
  "geometry": {"coordinates":[126.44361000000001,39.84667],"type":"Point"}
}