{
  "type": "Feature",
  "properties": {
    "gn:admin1_code":"9.0",
    "gn:admin2_code":"Ch\u2019angdo-gun",
    "gn:asciiname":"Masach'on",
    "gn:country_code":"KP",
    "gn:dem":234,
    "gn:feature_class":"P",
    "gn:feature_code":"PPL",
    "gn:name":"Masach\u2019\u014fn",
    "gn:population":0,
    "gn:timezone":"Asia/Pyongyang",
    "iso:country":"KP",
    "name:und_x_variant":[
        "Bashisen",
        "Taejon-ni",
        "Mashisen",
        "Masach\u2019\u014fn"
    ],
    "wof:name":"Masach'on",
    "wof:placetype":"locality"
},
  "geometry": {"coordinates":[127.78333000000001,38.45083],"type":"Point"}
}