{
  "type": "Feature",
  "properties": {
    "gn:admin1_code":"15.0",
    "gn:asciiname":"Sinsong-ni",
    "gn:country_code":"KP",
    "gn:dem":57,
    "gn:feature_class":"P",
    "gn:feature_code":"PPL",
    "gn:name":"Sinsong-ni",
    "gn:population":0,
    "gn:timezone":"Asia/Pyongyang",
    "iso:country":"KP",
    "name:eng_x_preferred":[
        "Sinsong"
    ],
    "name:eng_x_variant":[
        "Sinsong-ni"
    ],
    "wof:name":"Sinsong",
    "wof:placetype":"locality"
},
  "geometry": {"coordinates":[125.41611,39.23306],"type":"Point"}
}