{
  "type": "Feature",
  "properties": {
    "gn:admin1_code":"3.0",
    "gn:asciiname":"Yongjol-li",
    "gn:country_code":"KP",
    "gn:dem":66,
    "gn:feature_class":"P",
    "gn:feature_code":"PPL",
    "gn:name":"Yongjol-li",
    "gn:population":0,
    "gn:timezone":"Asia/Pyongyang",
    "iso:country":"KP",
    "name:kor_x_preferred":[
        "\uc601\uc804\ub9ac"
    ],
    "name:und_x_variant":[
        "Yongjon-ni"
    ],
    "wof:name":"Yongjol-li",
    "wof:placetype":"locality"
},
  "geometry": {"coordinates":[127.37194,39.89],"type":"Point"}
}