{
  "type": "Feature",
  "properties": {
    "gn:admin1_code":"11.0",
    "gn:asciiname":"Ch'ondae-ri",
    "gn:country_code":"KP",
    "gn:dem":22,
    "gn:feature_class":"P",
    "gn:feature_code":"PPL",
    "gn:name":"Ch\u2019\u014fndae-ri",
    "gn:population":0,
    "gn:timezone":"Asia/Pyongyang",
    "iso:country":"KP",
    "name:kor_x_preferred":[
        "\ucc9c\ub300\ub9ac"
    ],
    "name:kor_x_variant":[
        "Ch\u2019\u014fndae-ri"
    ],
    "name:und_x_variant":[
        "Ch\u2019\u014fndae-dong"
    ],
    "wof:name":"Ch'ondae-ri",
    "wof:placetype":"locality"
},
  "geometry": {"coordinates":[125.12417000000001,39.5975],"type":"Point"}
}