{
  "type": "Feature",
  "properties": {
    "gn:admin1_code":"1.0",
    "gn:asciiname":"Kaewol-li",
    "gn:country_code":"KP",
    "gn:dem":283,
    "gn:feature_class":"P",
    "gn:feature_code":"PPL",
    "gn:name":"Kaew\u014fl-li",
    "gn:population":0,
    "gn:timezone":"Asia/Pyongyang",
    "iso:country":"KP",
    "name:und_x_variant":[
        "Kaew\u014fn-dong",
        "Kaew\u014fn-ni",
        "\uac1c\uc6d0\ub9ac",
        "Kaew\u014fl-li"
    ],
    "wof:name":"Kaewol-li",
    "wof:placetype":"locality"
},
  "geometry": {"coordinates":[126.15139000000001,40.84833],"type":"Point"}
}