{
  "type": "Feature",
  "properties": {
    "gn:admin1_code":"17.0",
    "gn:asciiname":"Tari-gol",
    "gn:country_code":"KP",
    "gn:dem":358,
    "gn:feature_class":"P",
    "gn:feature_code":"PPL",
    "gn:name":"Tari-gol",
    "gn:population":0,
    "gn:timezone":"Asia/Pyongyang",
    "iso:country":"KP",
    "name:und_x_variant":[
        "\ub2e4\ub9ac\uace8",
        "Tari-gol"
    ],
    "wof:name":"Tari-gol",
    "wof:placetype":"locality"
},
  "geometry": {"coordinates":[129.35693999999998,41.06583],"type":"Point"}
}