{
  "type": "Feature",
  "properties": {
    "gn:admin1_code":"15.0",
    "gn:admin2_code":"1869039",
    "gn:asciiname":"I-ri",
    "gn:country_code":"KP",
    "gn:dem":13,
    "gn:feature_class":"P",
    "gn:feature_code":"PPL",
    "gn:name":"I-ri",
    "gn:population":0,
    "gn:timezone":"Asia/Pyongyang",
    "iso:country":"KP",
    "wof:name":"I-ri",
    "wof:placetype":"locality"
},
  "geometry": {"coordinates":[125.535,39.39361],"type":"Point"}
}