{
  "type": "Feature",
  "properties": {
    "gn:admin1_code":"11.0",
    "gn:asciiname":"Sogot-burak",
    "gn:country_code":"KP",
    "gn:dem":15,
    "gn:feature_class":"P",
    "gn:feature_code":"PPL",
    "gn:name":"Sogot-burak",
    "gn:population":0,
    "gn:timezone":"Asia/Pyongyang",
    "iso:country":"KP",
    "name:kor_x_preferred":[
        "\uc18c\uacf3"
    ],
    "name:kor_x_variant":[
        "\uc18c\uacf6\ubd80\ub77d",
        "\uc18c\uacf3\uac1c",
        "\uc18c\uad6c\uc9c0"
    ],
    "name:und_x_variant":[
        "Sogotkae",
        "Sogwan",
        "Sogokkae",
        "Sogot-burak",
        "Soguji",
        "Sogot"
    ],
    "wof:name":"Sogot-burak",
    "wof:placetype":"locality"
},
  "geometry": {"coordinates":[124.81043,39.72723],"type":"Point"}
}