{
  "type": "Feature",
  "properties": {
    "gn:admin1_code":"17.0",
    "gn:asciiname":"Hoe-dong",
    "gn:country_code":"KP",
    "gn:dem":672,
    "gn:feature_class":"P",
    "gn:feature_code":"PPL",
    "gn:name":"Hoe-dong",
    "gn:population":0,
    "gn:timezone":"Asia/Pyongyang",
    "iso:country":"KP",
    "name:und_x_variant":[
        "\ud68c\ub3d9"
    ],
    "wof:name":"Hoe-dong",
    "wof:placetype":"locality"
},
  "geometry": {"coordinates":[129.29917,41.35444],"type":"Point"}
}