{
  "type": "Feature",
  "properties": {
    "gn:admin1_code":"3.0",
    "gn:asciiname":"Manch'ul-li",
    "gn:country_code":"KP",
    "gn:dem":4,
    "gn:feature_class":"P",
    "gn:feature_code":"PPL",
    "gn:name":"Manch\u2019ul-li",
    "gn:population":0,
    "gn:timezone":"Asia/Pyongyang",
    "iso:country":"KP",
    "name:und_x_variant":[
        "Manch\u2019un-ni",
        "Manch\u2019ul-li",
        "\ub9cc\ucd98\ub9ac"
    ],
    "wof:name":"Manch'ul-li",
    "wof:placetype":"locality"
},
  "geometry": {"coordinates":[128.49222,40.14028],"type":"Point"}
}