{
  "type": "Feature",
  "properties": {
    "gn:admin1_code":"17.0",
    "gn:asciiname":"Yongp'o-dong",
    "gn:country_code":"KP",
    "gn:dem":19,
    "gn:feature_class":"P",
    "gn:feature_code":"PPL",
    "gn:name":"Yongp\u2019o-dong",
    "gn:population":0,
    "gn:timezone":"Asia/Pyongyang",
    "iso:country":"KP",
    "name:und_x_variant":[
        "\uc6a9\ud3ec\ub3d9",
        "Yongp\u2019o-dong"
    ],
    "wof:name":"Yongp'o-dong",
    "wof:placetype":"locality"
},
  "geometry": {"coordinates":[129.32917,40.74722],"type":"Point"}
}