{
  "type": "Feature",
  "properties": {
    "gn:admin1_code":"11.0",
    "gn:asciiname":"Munbong-ni",
    "gn:country_code":"KP",
    "gn:dem":8,
    "gn:feature_class":"P",
    "gn:feature_code":"PPL",
    "gn:name":"Munbong-ni",
    "gn:population":0,
    "gn:timezone":"Asia/Pyongyang",
    "iso:country":"KP",
    "name:und_x_variant":[
        "Munbong-dong",
        "\ubb38\ubd09\ub9ac",
        "Munbong-ni"
    ],
    "wof:name":"Munbong-ni",
    "wof:placetype":"locality"
},
  "geometry": {"coordinates":[124.62306,39.82056],"type":"Point"}
}