{
  "type": "Feature",
  "properties": {
    "gn:admin1_code":"9.0",
    "gn:asciiname":"Sinch'ong-ni",
    "gn:country_code":"KP",
    "gn:dem":63,
    "gn:feature_class":"P",
    "gn:feature_code":"PPL",
    "gn:name":"Sinch\u2019\u014fng-ni",
    "gn:population":0,
    "gn:timezone":"Asia/Pyongyang",
    "iso:country":"KP",
    "name:eng_x_preferred":[
        "Sinch'ong"
    ],
    "name:eng_x_variant":[
        "Sinch'ong-ni"
    ],
    "name:kor_x_preferred":[
        "\uc2e0\uccad\ub9ac"
    ],
    "name:kor_x_variant":[
        "Sinch\u2019\u014fng-ni"
    ],
    "wof:name":"Sinch'ong",
    "wof:placetype":"locality"
},
  "geometry": {"coordinates":[127.41278,39.00083],"type":"Point"}
}