{
  "type": "Feature",
  "properties": {
    "gn:admin1_code":"15.0",
    "gn:asciiname":"Sang-dong",
    "gn:country_code":"KP",
    "gn:dem":307,
    "gn:feature_class":"P",
    "gn:feature_code":"PPL",
    "gn:name":"Sang-dong",
    "gn:population":0,
    "gn:timezone":"Asia/Pyongyang",
    "iso:country":"KP",
    "name:kor_x_preferred":[
        "\uc0c1\ub3d9"
    ],
    "wof:name":"Sang-dong",
    "wof:placetype":"locality"
},
  "geometry": {"coordinates":[126.62027999999999,38.99556],"type":"Point"}
}