{
  "type": "Feature",
  "properties": {
    "gn:admin1_code":"6.0",
    "gn:admin2_code":"Kaep'ung-gun",
    "gn:asciiname":"Hanmul-gol",
    "gn:country_code":"KP",
    "gn:dem":20,
    "gn:feature_class":"P",
    "gn:feature_code":"PPL",
    "gn:name":"Hanmul-gol",
    "gn:population":0,
    "gn:timezone":"Asia/Pyongyang",
    "iso:country":"KP",
    "name:und_x_variant":[
        "K\u2019\u016dnumul-gol",
        "Hanmul-gol"
    ],
    "wof:name":"Hanmul-gol",
    "wof:placetype":"locality"
},
  "geometry": {"coordinates":[126.44333,37.9625],"type":"Point"}
}