{
  "type": "Feature",
  "properties": {
    "gn:admin1_code":"6.0",
    "gn:asciiname":"Soep'al-dong",
    "gn:country_code":"KP",
    "gn:dem":44,
    "gn:feature_class":"P",
    "gn:feature_code":"PPL",
    "gn:name":"Soep\u2019al-dong",
    "gn:population":0,
    "gn:timezone":"Asia/Pyongyang",
    "iso:country":"KP",
    "wof:name":"Soep'al-dong",
    "wof:placetype":"locality"
},
  "geometry": {"coordinates":[125.29194,37.93694],"type":"Point"}
}