{
  "type": "Feature",
  "properties": {
    "gn:admin1_code":"1.0",
    "gn:asciiname":"P'imok-tong",
    "gn:country_code":"KP",
    "gn:dem":411,
    "gn:feature_class":"P",
    "gn:feature_code":"PPL",
    "gn:name":"P\u2019imok-tong",
    "gn:population":0,
    "gn:timezone":"Asia/Pyongyang",
    "iso:country":"KP",
    "name:und_x_variant":[
        "\ud53c\ubaa9\ub3d9",
        "P\u2019imok-tong"
    ],
    "wof:name":"P'imok-tong",
    "wof:placetype":"locality"
},
  "geometry": {"coordinates":[126.62027999999999,41.59306],"type":"Point"}
}