{
  "type": "Feature",
  "properties": {
    "gn:admin1_code":"9.0",
    "gn:asciiname":"Wangnoso",
    "gn:country_code":"KP",
    "gn:dem":567,
    "gn:feature_class":"P",
    "gn:feature_code":"PPL",
    "gn:name":"Wangnoso",
    "gn:population":0,
    "gn:timezone":"Asia/Pyongyang",
    "iso:country":"KP",
    "name:kor_x_preferred":[
        "\uc655\ub85c\uc18c"
    ],
    "wof:name":"Wangnoso",
    "wof:placetype":"locality"
},
  "geometry": {"coordinates":[127.21278,38.90861],"type":"Point"}
}