{
  "type": "Feature",
  "properties": {
    "gn:admin1_code":"9.0",
    "gn:asciiname":"Kunnamnihomok",
    "gn:country_code":"KP",
    "gn:dem":596,
    "gn:feature_class":"P",
    "gn:feature_code":"PPL",
    "gn:name":"K\u016dnnamnih\u014fmok",
    "gn:population":0,
    "gn:timezone":"Asia/Pyongyang",
    "iso:country":"KP",
    "name:kor_x_preferred":[
        "\uadfc\ub0a8\ub9ac\ud5c8\ubaa9"
    ],
    "name:und_x_variant":[
        "K\u016dnnamnih\u014fmok"
    ],
    "wof:name":"Kunnamnihomok",
    "wof:placetype":"locality"
},
  "geometry": {"coordinates":[127.33306,38.63972],"type":"Point"}
}