{
  "type": "Feature",
  "properties": {
    "gn:admin1_code":"11.0",
    "gn:asciiname":"Chuktae-dong",
    "gn:country_code":"KP",
    "gn:dem":265,
    "gn:feature_class":"P",
    "gn:feature_code":"PPL",
    "gn:name":"Chuktae-dong",
    "gn:population":0,
    "gn:timezone":"Asia/Pyongyang",
    "iso:country":"KP",
    "name:und_x_variant":[
        "\uc8fd\ub300\ub3d9",
        "Chuktae-dong"
    ],
    "wof:name":"Chuktae-dong",
    "wof:placetype":"locality"
},
  "geometry": {"coordinates":[125.74388999999999,40.12972],"type":"Point"}
}