{
  "type": "Feature",
  "properties": {
    "gn:admin1_code":"7.0",
    "gn:asciiname":"Sangnam-dong",
    "gn:country_code":"KP",
    "gn:dem":329,
    "gn:feature_class":"P",
    "gn:feature_code":"PPL",
    "gn:name":"Sangnam-dong",
    "gn:population":0,
    "gn:timezone":"Asia/Pyongyang",
    "iso:country":"KP",
    "name:und_x_variant":[
        "\uc0c1\ub0a8\ub3d9",
        "Sangnam-dong"
    ],
    "wof:name":"Sangnam-dong",
    "wof:placetype":"locality"
},
  "geometry": {"coordinates":[126.77583,39.09],"type":"Point"}
}