{
  "type": "Feature",
  "properties": {
    "gn:admin1_code":"17.0",
    "gn:asciiname":"T'owol-li",
    "gn:country_code":"KP",
    "gn:dem":10,
    "gn:feature_class":"P",
    "gn:feature_code":"PPL",
    "gn:name":"T\u2019ow\u014fl-li",
    "gn:population":0,
    "gn:timezone":"Asia/Pyongyang",
    "iso:country":"KP",
    "name:und_x_variant":[
        "T\u2019odam-ni",
        "T\u2019ow\u014fn-dong",
        "\ud1a0\uc6d0\ub9ac",
        "T\u2019ow\u014fl-li"
    ],
    "wof:name":"T'owol-li",
    "wof:placetype":"locality"
},
  "geometry": {"coordinates":[129.54333,40.84028],"type":"Point"}
}