{
  "type": "Feature",
  "properties": {
    "gn:admin1_code":"17.0",
    "gn:asciiname":"Chaegungch'on",
    "gn:country_code":"KP",
    "gn:dem":60,
    "gn:feature_class":"P",
    "gn:feature_code":"PPL",
    "gn:name":"Chaegungch\u2019on",
    "gn:population":0,
    "gn:timezone":"Asia/Pyongyang",
    "iso:country":"KP",
    "name:und_x_variant":[
        "Zaig\u016b-son",
        "Zaiky\u016bson",
        "\uc7ac\uad81\ucd0c",
        "Chaegungch\u2019on"
    ],
    "wof:name":"Chaegungch'on",
    "wof:placetype":"locality"
},
  "geometry": {"coordinates":[129.14667,40.61028],"type":"Point"}
}