{
  "type": "Feature",
  "properties": {
    "gn:admin1_code":"12.0",
    "gn:asciiname":"Pangch'uk-tong",
    "gn:country_code":"KP",
    "gn:dem":36,
    "gn:feature_class":"P",
    "gn:feature_code":"PPL",
    "gn:name":"Pangch\u2019uk-tong",
    "gn:population":0,
    "gn:timezone":"Asia/Pyongyang",
    "iso:country":"KP",
    "name:kor_x_preferred":[
        "Pangch\u2019ukkol"
    ],
    "name:kor_x_variant":[
        "\ubc29\ucd95\ub3d9"
    ],
    "name:und_x_variant":[
        "Pangch\u2019uk-tong",
        "\ubc29\ucd95\uace8",
        "Bangchukdong"
    ],
    "wof:name":"Pangch'uk-tong",
    "wof:placetype":"locality"
},
  "geometry": {"coordinates":[125.84056,38.91051],"type":"Point"}
}