{
  "type": "Feature",
  "properties": {
    "gn:admin1_code":"3.0",
    "gn:asciiname":"Tach'ol-li",
    "gn:country_code":"KP",
    "gn:dem":44,
    "gn:feature_class":"P",
    "gn:feature_code":"PPL",
    "gn:name":"Tach\u2019\u014fl-li",
    "gn:population":0,
    "gn:timezone":"Asia/Pyongyang",
    "iso:country":"KP",
    "name:kor_x_preferred":[
        "\ub2e4\ucc9c\ub9ac"
    ],
    "name:kor_x_variant":[
        "Tach\u2019\u014fl-li"
    ],
    "name:und_x_variant":[
        "Tach\u2019\u014fn-ni",
        "Tanch\u2019\u014fn-ni"
    ],
    "wof:name":"Tach'ol-li",
    "wof:placetype":"locality"
},
  "geometry": {"coordinates":[127.15971999999999,39.48222],"type":"Point"}
}