{
  "type": "Feature",
  "properties": {
    "gn:admin1_code":"15.0",
    "gn:asciiname":"Songsang-ni",
    "gn:country_code":"KP",
    "gn:dem":131,
    "gn:feature_class":"P",
    "gn:feature_code":"PPL",
    "gn:name":"Songsang-ni",
    "gn:population":0,
    "gn:timezone":"Asia/Pyongyang",
    "iso:country":"KP",
    "name:kor_x_preferred":[
        "\uc1a1\uc0c1\ub9ac"
    ],
    "wof:name":"Songsang-ni",
    "wof:placetype":"locality"
},
  "geometry": {"coordinates":[126.11139,39.43194],"type":"Point"}
}