{
  "type": "Feature",
  "properties": {
    "gn:admin1_code":"11.0",
    "gn:asciiname":"Taemul-li",
    "gn:country_code":"KP",
    "gn:dem":70,
    "gn:feature_class":"P",
    "gn:feature_code":"PPL",
    "gn:name":"Taemul-li",
    "gn:population":0,
    "gn:timezone":"Asia/Pyongyang",
    "iso:country":"KP",
    "name:und_x_variant":[
        "Taemun-dong",
        "\ub300\ubb38\ub9ac",
        "Taemun-ni",
        "Taemul-li"
    ],
    "wof:name":"Taemul-li",
    "wof:placetype":"locality"
},
  "geometry": {"coordinates":[124.65694000000001,40.16472],"type":"Point"}
}