{
  "type": "Feature",
  "properties": {
    "gn:admin1_code":"1.0",
    "gn:asciiname":"Samnang-ni",
    "gn:country_code":"KP",
    "gn:dem":446,
    "gn:feature_class":"P",
    "gn:feature_code":"PPL",
    "gn:name":"Samnang-ni",
    "gn:population":0,
    "gn:timezone":"Asia/Pyongyang",
    "iso:country":"KP",
    "name:eng_x_preferred":[
        "Samnang"
    ],
    "name:eng_x_variant":[
        "Samnang-ni"
    ],
    "name:und_x_variant":[
        "Sanrakud\u014d",
        "Samnak-tong",
        "Sangaku-d\u014d",
        "\uc0bc\ub77d\ub9ac",
        "Samnang-ni"
    ],
    "wof:name":"Samnang",
    "wof:placetype":"locality"
},
  "geometry": {"coordinates":[126.14972,40.69667],"type":"Point"}
}