{
  "type": "Feature",
  "properties": {
    "gn:admin1_code":"0.0",
    "gn:asciiname":"Ipsong-ni",
    "gn:country_code":"KP",
    "gn:dem":40,
    "gn:feature_class":"P",
    "gn:feature_code":"PPL",
    "gn:name":"Ips\u014fng-ni",
    "gn:population":0,
    "gn:timezone":"Asia/Pyongyang",
    "iso:country":"KP",
    "name:kor_x_preferred":[
        "\uc785\uc131\ub9ac"
    ],
    "name:und_x_variant":[
        "Ips\u014fng-ni"
    ],
    "wof:name":"Ipsong-ni",
    "wof:placetype":"locality"
},
  "geometry": {"coordinates":[124.73333,40.31667],"type":"Point"}
}