{
  "type": "Feature",
  "properties": {
    "gn:admin1_code":"9.0",
    "gn:asciiname":"Yongsan-dong",
    "gn:country_code":"KP",
    "gn:dem":711,
    "gn:feature_class":"P",
    "gn:feature_code":"PPL",
    "gn:name":"Yongsan-dong",
    "gn:population":0,
    "gn:timezone":"Asia/Pyongyang",
    "iso:country":"KP",
    "name:ceb_x_preferred":[
        "Yongsan-dong"
    ],
    "name:kor_x_preferred":[
        "\ub8e1\uc0b0\ub3d9"
    ],
    "name:kor_x_variant":[
        "\uc6a9\uc0b0\ub3d9"
    ],
    "name:swe_x_preferred":[
        "Yongsan-dong"
    ],
    "name:und_x_variant":[
        "Yongson-gol",
        "Yongsan-gol"
    ],
    "name:zho_x_preferred":[
        "\u9f8d\u5c71\u6d1e"
    ],
    "wof:name":"Yongsan-dong",
    "wof:placetype":"locality"
},
  "geometry": {"coordinates":[128.12138999999999,38.43444],"type":"Point"}
}