{
  "type": "Feature",
  "properties": {
    "gn:admin1_code":"15.0",
    "gn:admin2_code":"S\u014fngch\u2019\u014fn-gun",
    "gn:asciiname":"Hwasong-ni",
    "gn:country_code":"KP",
    "gn:dem":42,
    "gn:feature_class":"P",
    "gn:feature_code":"PPL",
    "gn:name":"Hwas\u014fng-ni",
    "gn:population":0,
    "gn:timezone":"Asia/Pyongyang",
    "iso:country":"KP",
    "name:eng_x_preferred":[
        "Hwasong"
    ],
    "name:eng_x_variant":[
        "Hwasong-ni"
    ],
    "wof:name":"Hwasong",
    "wof:placetype":"locality"
},
  "geometry": {"coordinates":[126.06639,39.24556],"type":"Point"}
}