{
  "type": "Feature",
  "properties": {
    "gn:admin1_code":"11.0",
    "gn:asciiname":"Idop'o",
    "gn:country_code":"KP",
    "gn:dem":6,
    "gn:feature_class":"P",
    "gn:feature_code":"PPL",
    "gn:name":"Idop\u2019o",
    "gn:population":0,
    "gn:timezone":"Asia/Pyongyang",
    "iso:country":"KP",
    "name:und_x_variant":[
        "Jit\u014dh\u014d",
        "\uc774\ub3c4\ud3ec",
        "Idop\u2019o"
    ],
    "wof:name":"Idop'o",
    "wof:placetype":"locality"
},
  "geometry": {"coordinates":[124.4575,39.84194],"type":"Point"}
}