{
  "type": "Feature",
  "properties": {
    "gn:admin1_code":"3.0",
    "gn:asciiname":"Kaeamsom",
    "gn:country_code":"KP",
    "gn:dem":228,
    "gn:feature_class":"P",
    "gn:feature_code":"PPL",
    "gn:name":"Kaeams\u014fm",
    "gn:population":0,
    "gn:timezone":"Asia/Pyongyang",
    "iso:country":"KP",
    "name:und_x_variant":[
        "Chindo",
        "Kaedams\u014fm",
        "Kayams\u014fm",
        "Kaeams\u014fm",
        "\uac1c\uc554\uc12c"
    ],
    "wof:name":"Kaeamsom",
    "wof:placetype":"locality"
},
  "geometry": {"coordinates":[128.23053999999999,40.38786],"type":"Point"}
}