{
  "type": "Feature",
  "properties": {
    "gn:admin1_code":"6.0",
    "gn:asciiname":"Sat'ae-gol",
    "gn:country_code":"KP",
    "gn:dem":129,
    "gn:feature_class":"P",
    "gn:feature_code":"PPL",
    "gn:name":"Sat\u2019ae-gol",
    "gn:population":0,
    "gn:timezone":"Asia/Pyongyang",
    "iso:country":"KP",
    "wof:name":"Sat'ae-gol",
    "wof:placetype":"locality"
},
  "geometry": {"coordinates":[125.48333,38.14167],"type":"Point"}
}