{
  "type": "Feature",
  "properties": {
    "gn:admin1_code":"3.0",
    "gn:asciiname":"Yongsujae",
    "gn:country_code":"KP",
    "gn:dem":9,
    "gn:feature_class":"P",
    "gn:feature_code":"PPL",
    "gn:name":"Yongsujae",
    "gn:population":0,
    "gn:timezone":"Asia/Pyongyang",
    "iso:country":"KP",
    "name:und_x_variant":[
        "\uc6a9\uc218\uc7ac",
        "Yongsujae"
    ],
    "wof:name":"Yongsujae",
    "wof:placetype":"locality"
},
  "geometry": {"coordinates":[127.43694000000001,39.83028],"type":"Point"}
}