{
  "type": "Feature",
  "properties": {
    "gn:admin1_code":"12.0",
    "gn:asciiname":"K'unoryu-ri",
    "gn:country_code":"KP",
    "gn:dem":37,
    "gn:feature_class":"P",
    "gn:feature_code":"PPL",
    "gn:name":"K\u2019\u016dnoryu-ri",
    "gn:population":0,
    "gn:timezone":"Asia/Pyongyang",
    "iso:country":"KP",
    "name:und_x_variant":[
        "\ud070\uc624\ub958\ub9ac",
        "K\u2019\u016dnoryu-ri",
        "Keunoryuri"
    ],
    "wof:name":"K'unoryu-ri",
    "wof:placetype":"locality"
},
  "geometry": {"coordinates":[125.89388999999998,38.99694],"type":"Point"}
}