{
  "type": "Feature",
  "properties": {
    "gn:admin1_code":"7.0",
    "gn:asciiname":"Chajang-ni",
    "gn:country_code":"KP",
    "gn:dem":221,
    "gn:feature_class":"P",
    "gn:feature_code":"PPL",
    "gn:name":"Chajang-ni",
    "gn:population":0,
    "gn:timezone":"Asia/Pyongyang",
    "iso:country":"KP",
    "name:kor_x_preferred":[
        "\uc790\uc7a5\ub9ac"
    ],
    "wof:name":"Chajang-ni",
    "wof:placetype":"locality"
},
  "geometry": {"coordinates":[126.25472000000001,38.55889000000001],"type":"Point"}
}