{
  "type": "Feature",
  "properties": {
    "gn:admin1_code":"6.0",
    "gn:asciiname":"Chaegung-ni",
    "gn:country_code":"KP",
    "gn:dem":93,
    "gn:feature_class":"P",
    "gn:feature_code":"PPL",
    "gn:name":"Chaegung-ni",
    "gn:population":0,
    "gn:timezone":"Asia/Pyongyang",
    "iso:country":"KP",
    "name:kor_x_preferred":[
        "\uc7ac\uad81\ub9ac"
    ],
    "wof:name":"Chaegung-ni",
    "wof:placetype":"locality"
},
  "geometry": {"coordinates":[126.11388999999998,37.99944],"type":"Point"}
}