{
  "type": "Feature",
  "properties": {
    "gn:admin1_code":"6.0",
    "gn:asciiname":"P'ung-dong",
    "gn:country_code":"KP",
    "gn:dem":27,
    "gn:feature_class":"P",
    "gn:feature_code":"PPL",
    "gn:name":"P\u2019ung-dong",
    "gn:population":0,
    "gn:timezone":"Asia/Pyongyang",
    "iso:country":"KP",
    "name:und_x_variant":[
        "\ud48d\ub3d9",
        "P\u2019ung-dong"
    ],
    "wof:name":"P'ung-dong",
    "wof:placetype":"locality"
},
  "geometry": {"coordinates":[125.22667,38.00028],"type":"Point"}
}