{
  "type": "Feature",
  "properties": {
    "gn:admin1_code":"6.0",
    "gn:asciiname":"Sowol-li",
    "gn:cc2":"KP",
    "gn:country_code":"KP",
    "gn:dem":19,
    "gn:feature_class":"P",
    "gn:feature_code":"PPL",
    "gn:name":"S\u014fw\u014fl-li",
    "gn:population":0,
    "gn:timezone":"Asia/Pyongyang",
    "iso:country":"KP",
    "name:und_x_variant":[
        "S\u014fw\u014fn-ni",
        "S\u014fw\u014fl-li"
    ],
    "wof:name":"Sowol-li",
    "wof:placetype":"locality"
},
  "geometry": {"coordinates":[125.59611,38.05611],"type":"Point"}
}