{
  "type": "Feature",
  "properties": {
    "gn:admin1_code":"3.0",
    "gn:asciiname":"Hagyongdul-li",
    "gn:country_code":"KP",
    "gn:dem":155,
    "gn:feature_class":"P",
    "gn:feature_code":"PPL",
    "gn:name":"Hagy\u014fngdul-li",
    "gn:population":0,
    "gn:timezone":"Asia/Pyongyang",
    "iso:country":"KP",
    "name:kor_x_preferred":[
        "\ud558\uacbd\ub454\ub9ac"
    ],
    "name:kor_x_variant":[
        "Hagy\u014fngdul-li"
    ],
    "wof:name":"Hagyongdul-li",
    "wof:placetype":"locality"
},
  "geometry": {"coordinates":[127.01167,39.37778],"type":"Point"}
}