{
  "type": "Feature",
  "properties": {
    "gn:admin1_code":"0.0",
    "gn:asciiname":"Sudong-ni",
    "gn:country_code":"KP",
    "gn:dem":193,
    "gn:feature_class":"P",
    "gn:feature_code":"PPL",
    "gn:name":"Sud\u014fng-ni",
    "gn:population":0,
    "gn:timezone":"Asia/Pyongyang",
    "iso:country":"KP",
    "name:eng_x_preferred":[
        "Sudong"
    ],
    "name:eng_x_variant":[
        "Sudong-ni"
    ],
    "name:kor_x_preferred":[
        "\uc218\ub355\ub9ac"
    ],
    "name:und_x_variant":[
        "Sud\u014fng-ni"
    ],
    "wof:name":"Sudong",
    "wof:placetype":"locality"
},
  "geometry": {"coordinates":[126.25,39.25],"type":"Point"}
}