{
  "type": "Feature",
  "properties": {
    "gn:admin1_code":"9.0",
    "gn:asciiname":"Oemasan-dong",
    "gn:country_code":"KP",
    "gn:dem":376,
    "gn:feature_class":"P",
    "gn:feature_code":"PPL",
    "gn:name":"Oemasan-dong",
    "gn:population":0,
    "gn:timezone":"Asia/Pyongyang",
    "iso:country":"KP",
    "name:und_x_variant":[
        "\uc678\ub9c8\uc0b0\ub3d9",
        "Oemasan-dong"
    ],
    "wof:name":"Oemasan-dong",
    "wof:placetype":"locality"
},
  "geometry": {"coordinates":[127.58,38.71],"type":"Point"}
}