{
  "type": "Feature",
  "properties": {
    "gn:admin1_code":"9.0",
    "gn:asciiname":"Nodong-ni",
    "gn:country_code":"KP",
    "gn:dem":519,
    "gn:feature_class":"P",
    "gn:feature_code":"PPL",
    "gn:name":"Nodong-ni",
    "gn:population":0,
    "gn:timezone":"Asia/Pyongyang",
    "iso:country":"KP",
    "name:und_x_variant":[
        "\ub178\ub3d9\ub9ac",
        "Nodong-ni"
    ],
    "wof:name":"Nodong-ni",
    "wof:placetype":"locality"
},
  "geometry": {"coordinates":[127.73361,38.64944000000001],"type":"Point"}
}