{
  "type": "Feature",
  "properties": {
    "gn:admin1_code":"3.0",
    "gn:asciiname":"Komunyoul",
    "gn:country_code":"KP",
    "gn:dem":48,
    "gn:feature_class":"P",
    "gn:feature_code":"PPL",
    "gn:name":"K\u014fmuny\u014ful",
    "gn:population":0,
    "gn:timezone":"Asia/Pyongyang",
    "iso:country":"KP",
    "name:kor_x_preferred":[
        "\uac70\ubb38\uc5ec\uc6b8"
    ],
    "name:kor_x_variant":[
        "K\u014fmuny\u014ful"
    ],
    "wof:name":"Komunyoul",
    "wof:placetype":"locality"
},
  "geometry": {"coordinates":[127.16222,39.56778],"type":"Point"}
}