{
  "type": "Feature",
  "properties": {
    "gn:admin1_code":"3.0",
    "gn:asciiname":"Koraegukki",
    "gn:country_code":"KP",
    "gn:dem":64,
    "gn:feature_class":"P",
    "gn:feature_code":"PPL",
    "gn:name":"Koraegukki",
    "gn:population":0,
    "gn:timezone":"Asia/Pyongyang",
    "iso:country":"KP",
    "name:kor_x_preferred":[
        "\uace0\ub798\uad6d\uae30"
    ],
    "wof:name":"Koraegukki",
    "wof:placetype":"locality"
},
  "geometry": {"coordinates":[127.11194,39.45333],"type":"Point"}
}