{
  "type": "Feature",
  "properties": {
    "gn:admin1_code":"3.0",
    "gn:asciiname":"Ponghwangdok",
    "gn:country_code":"KP",
    "gn:dem":1429,
    "gn:feature_class":"P",
    "gn:feature_code":"PPL",
    "gn:name":"Ponghwangd\u014fk",
    "gn:population":0,
    "gn:timezone":"Asia/Pyongyang",
    "iso:country":"KP",
    "wof:name":"Ponghwangdok",
    "wof:placetype":"locality"
},
  "geometry": {"coordinates":[128.81666999999999,41.13333],"type":"Point"}
}