{
  "type": "Feature",
  "properties": {
    "gn:admin1_code":"6.0",
    "gn:asciiname":"Kwasal-li",
    "gn:country_code":"KP",
    "gn:dem":91,
    "gn:feature_class":"P",
    "gn:feature_code":"PPL",
    "gn:name":"Kwasal-li",
    "gn:population":0,
    "gn:timezone":"Asia/Pyongyang",
    "iso:country":"KP",
    "name:und_x_variant":[
        "\u016cig\u014f-ri",
        "Kwansan-ni",
        "\uacfc\uc0b0\ub9ac",
        "Kwasal-li"
    ],
    "wof:name":"Kwasal-li",
    "wof:placetype":"locality"
},
  "geometry": {"coordinates":[125.3425,38.10583],"type":"Point"}
}