{
  "type": "Feature",
  "properties": {
    "gn:admin1_code":"11.0",
    "gn:asciiname":"Songjang-ni",
    "gn:country_code":"KP",
    "gn:dem":174,
    "gn:feature_class":"P",
    "gn:feature_code":"PPL",
    "gn:name":"Songjang-ni",
    "gn:population":0,
    "gn:timezone":"Asia/Pyongyang",
    "iso:country":"KP",
    "name:eng_x_preferred":[
        "Songjang"
    ],
    "name:eng_x_variant":[
        "Songjang-ni"
    ],
    "name:und_x_variant":[
        "\uc1a1\uc7a5\ub9ac",
        "Songjang-ni"
    ],
    "wof:name":"Songjang",
    "wof:placetype":"locality"
},
  "geometry": {"coordinates":[125.34472,40.57167],"type":"Point"}
}