{
  "type": "Feature",
  "properties": {
    "gn:admin1_code":"15.0",
    "gn:asciiname":"Nodong-ni",
    "gn:country_code":"KP",
    "gn:dem":50,
    "gn:feature_class":"P",
    "gn:feature_code":"PPL",
    "gn:name":"Nodong-ni",
    "gn:population":0,
    "gn:timezone":"Asia/Pyongyang",
    "iso:country":"KP",
    "name:eng_x_preferred":[
        "Nodong"
    ],
    "name:eng_x_variant":[
        "Nodong-ni"
    ],
    "wof:name":"Nodong",
    "wof:placetype":"locality"
},
  "geometry": {"coordinates":[126.03778,39.31111],"type":"Point"}
}