{
  "type": "Feature",
  "properties": {
    "gn:admin1_code":"0.0",
    "gn:asciiname":"Onch'ae-ri",
    "gn:country_code":"KP",
    "gn:dem":5,
    "gn:feature_class":"P",
    "gn:feature_code":"PPL",
    "gn:name":"Onch\u2019ae-ri",
    "gn:population":0,
    "gn:timezone":"Asia/Pyongyang",
    "iso:country":"KP",
    "name:kor_x_preferred":[
        "\uc628\ucc44\ub9ac"
    ],
    "name:und_x_variant":[
        "Onch\u2019ae-ri"
    ],
    "wof:name":"Onch'ae-ri",
    "wof:placetype":"locality"
},
  "geometry": {"coordinates":[125.71666999999999,38.43333],"type":"Point"}
}