{
  "type": "Feature",
  "properties": {
    "gn:admin1_code":"17.0",
    "gn:asciiname":"Iman",
    "gn:country_code":"KP",
    "gn:dem":411,
    "gn:feature_class":"P",
    "gn:feature_code":"PPL",
    "gn:name":"Iman",
    "gn:population":0,
    "gn:timezone":"Asia/Pyongyang",
    "iso:country":"KP",
    "name:und_x_variant":[
        "\uc774\ub9cc",
        "Iman"
    ],
    "wof:name":"Iman",
    "wof:placetype":"locality"
},
  "geometry": {"coordinates":[129.40889000000001,41.31833],"type":"Point"}
}