{
  "type": "Feature",
  "properties": {
    "gn:admin1_code":"17.0",
    "gn:asciiname":"Iman",
    "gn:country_code":"KP",
    "gn:dem":411,
    "gn:feature_class":"P",
    "gn:feature_code":"PPL",
    "gn:name":"Iman",
    "gn:population":0,
    "gn:timezone":"Asia/Pyongyang",
    "iso:country":"KP",
    "name:ara_x_preferred":[
        "\u0625\u064a\u0645\u0627\u0646"
    ],
    "name:aze_x_preferred":[
        "\u0130man"
    ],
    "name:ceb_x_preferred":[
        "Iman"
    ],
    "name:ces_x_preferred":[
        "Iman"
    ],
    "name:deu_x_preferred":[
        "Iman"
    ],
    "name:fra_x_preferred":[
        "Iman"
    ],
    "name:heb_x_preferred":[
        "\u05d0\u05d9\u05de\u05df"
    ],
    "name:ita_x_preferred":[
        "Iman"
    ],
    "name:jpn_x_preferred":[
        "\u30a4\u30de\u30f3"
    ],
    "name:nld_x_preferred":[
        "Iman"
    ],
    "name:por_x_preferred":[
        "Im\u00e3"
    ],
    "name:rus_x_preferred":[
        "\u0418\u043c\u0430\u043d"
    ],
    "name:spa_x_preferred":[
        "Im\u00e1n"
    ],
    "name:tat_x_preferred":[
        "\u0418\u043c\u0430\u043d"
    ],
    "name:und_x_variant":[
        "\uc774\ub9cc",
        "Iman"
    ],
    "wof:name":"Iman",
    "wof:placetype":"locality"
},
  "geometry": {"coordinates":[129.40889000000001,41.31833],"type":"Point"}
}