{
  "type": "Feature",
  "properties": {
    "gn:admin1_code":"3.0",
    "gn:asciiname":"Sinsan",
    "gn:cc2":"KP",
    "gn:country_code":"KP",
    "gn:dem":11,
    "gn:feature_class":"P",
    "gn:feature_code":"PPL",
    "gn:name":"Sinsan",
    "gn:population":0,
    "gn:timezone":"Asia/Pyongyang",
    "iso:country":"KP",
    "name:und_x_variant":[
        "Sinsa",
        "\uc2e0\uc0b0",
        "Sinsan"
    ],
    "wof:name":"Sinsan",
    "wof:placetype":"locality"
},
  "geometry": {"coordinates":[127.39388999999998,39.63444000000001],"type":"Point"}
}