{
  "type": "Feature",
  "properties": {
    "gn:admin1_code":"11.0",
    "gn:asciiname":"Tokchung",
    "gn:country_code":"KP",
    "gn:dem":99,
    "gn:feature_class":"P",
    "gn:feature_code":"PPL",
    "gn:name":"T\u014fkchung",
    "gn:population":0,
    "gn:timezone":"Asia/Pyongyang",
    "iso:country":"KP",
    "wof:name":"Tokchung",
    "wof:placetype":"locality"
},
  "geometry": {"coordinates":[125.36722,39.89389],"type":"Point"}
}