{
  "type": "Feature",
  "properties": {
    "gn:admin1_code":"6.0",
    "gn:asciiname":"Hasasan",
    "gn:country_code":"KP",
    "gn:dem":31,
    "gn:feature_class":"P",
    "gn:feature_code":"PPL",
    "gn:name":"Hasasan",
    "gn:population":0,
    "gn:timezone":"Asia/Pyongyang",
    "iso:country":"KP",
    "name:kor_x_preferred":[
        "\ud558\uc0ac\uc0b0"
    ],
    "wof:name":"Hasasan",
    "wof:placetype":"locality"
},
  "geometry": {"coordinates":[125.18333,38.4925],"type":"Point"}
}