{
  "type": "Feature",
  "properties": {
    "gn:admin1_code":"6.0",
    "gn:asciiname":"Samp'o-dong",
    "gn:country_code":"KP",
    "gn:dem":131,
    "gn:feature_class":"P",
    "gn:feature_code":"PPL",
    "gn:name":"Samp\u2019o-dong",
    "gn:population":0,
    "gn:timezone":"Asia/Pyongyang",
    "iso:country":"KP",
    "name:und_x_variant":[
        "\uc0bc\ud3ec\ub3d9",
        "Samp\u2019o-dong"
    ],
    "wof:name":"Samp'o-dong",
    "wof:placetype":"locality"
},
  "geometry": {"coordinates":[126.53306000000001,38.04222],"type":"Point"}
}