{
  "type": "Feature",
  "properties": {
    "gn:admin1_code":"3.0",
    "gn:asciiname":"Unsung-ni",
    "gn:country_code":"KP",
    "gn:dem":86,
    "gn:feature_class":"P",
    "gn:feature_code":"PPL",
    "gn:name":"Uns\u016dng-ni",
    "gn:population":0,
    "gn:timezone":"Asia/Pyongyang",
    "iso:country":"KP",
    "name:und_x_variant":[
        "Hauns\u016dng-ni",
        "\uc6b4\uc2b9\ub9ac",
        "Uns\u016dng-ni"
    ],
    "wof:name":"Unsung-ni",
    "wof:placetype":"locality"
},
  "geometry": {"coordinates":[128.81888999999998,40.59194],"type":"Point"}
}