{
  "type": "Feature",
  "properties": {
    "gn:admin1_code":"15.0",
    "gn:asciiname":"Puksong-ni",
    "gn:country_code":"KP",
    "gn:dem":37,
    "gn:feature_class":"P",
    "gn:feature_code":"PPL",
    "gn:name":"Puksong-ni",
    "gn:population":0,
    "gn:timezone":"Asia/Pyongyang",
    "iso:country":"KP",
    "wof:name":"Puksong-ni",
    "wof:placetype":"locality"
},
  "geometry": {"coordinates":[125.72028,39.63778],"type":"Point"}
}