{
  "type": "Feature",
  "properties": {
    "gn:admin1_code":"3.0",
    "gn:asciiname":"Kudan-dong",
    "gn:country_code":"KP",
    "gn:dem":424,
    "gn:feature_class":"P",
    "gn:feature_code":"PPL",
    "gn:name":"Kudan-dong",
    "gn:population":0,
    "gn:timezone":"Asia/Pyongyang",
    "iso:country":"KP",
    "name:kor_x_preferred":[
        "\uad6c\ub2e8\ub3d9"
    ],
    "wof:name":"Kudan-dong",
    "wof:placetype":"locality"
},
  "geometry": {"coordinates":[127.10889,39.76056],"type":"Point"}
}