{
  "type": "Feature",
  "properties": {
    "gn:admin1_code":"11.0",
    "gn:asciiname":"T'angno-dong",
    "gn:country_code":"KP",
    "gn:dem":185,
    "gn:feature_class":"P",
    "gn:feature_code":"PPL",
    "gn:name":"T\u2019angno-dong",
    "gn:population":0,
    "gn:timezone":"Asia/Pyongyang",
    "iso:country":"KP",
    "name:und_x_variant":[
        "\ud0d5\ub85c\ub3d9",
        "T\u2019angno-dong"
    ],
    "wof:name":"T'angno-dong",
    "wof:placetype":"locality"
},
  "geometry": {"coordinates":[125.06361,40.3575],"type":"Point"}
}