{
  "type": "Feature",
  "properties": {
    "gn:admin1_code":"12.0",
    "gn:asciiname":"Chongam-ni",
    "gn:country_code":"KP",
    "gn:dem":14,
    "gn:feature_class":"P",
    "gn:feature_code":"PPL",
    "gn:name":"Ch\u014fngam-ni",
    "gn:population":0,
    "gn:timezone":"Asia/Pyongyang",
    "iso:country":"KP",
    "name:kor_x_preferred":[
        "\uc815\uc554\ub9ac"
    ],
    "name:und_x_variant":[
        "Ch\u014fngam-ni",
        "Jeongamni"
    ],
    "wof:name":"Chongam-ni",
    "wof:placetype":"locality"
},
  "geometry": {"coordinates":[125.6075,38.87222],"type":"Point"}
}