{
  "type": "Feature",
  "properties": {
    "gn:admin1_code":"17.0",
    "gn:asciiname":"Oksan-dong",
    "gn:country_code":"KP",
    "gn:dem":360,
    "gn:feature_class":"P",
    "gn:feature_code":"PPL",
    "gn:name":"Oksan-dong",
    "gn:population":0,
    "gn:timezone":"Asia/Pyongyang",
    "iso:country":"KP",
    "name:und_x_variant":[
        "\uc625\uc0b0\ub3d9",
        "Oksan-dong"
    ],
    "wof:name":"Oksan-dong",
    "wof:placetype":"locality"
},
  "geometry": {"coordinates":[129.93194,42.41278],"type":"Point"}
}