{
  "type": "Feature",
  "properties": {
    "gn:admin1_code":"3.0",
    "gn:asciiname":"Han-ch'on",
    "gn:country_code":"KP",
    "gn:dem":98,
    "gn:feature_class":"P",
    "gn:feature_code":"PPL",
    "gn:name":"Han-ch\u2019on",
    "gn:population":0,
    "gn:timezone":"Asia/Pyongyang",
    "iso:country":"KP",
    "name:und_x_variant":[
        "Han-ch\u2019on",
        "\ud55c\ucd0c"
    ],
    "wof:name":"Han-ch'on",
    "wof:placetype":"locality"
},
  "geometry": {"coordinates":[128.22576999999998,40.29799000000001],"type":"Point"}
}