{
  "type": "Feature",
  "properties": {
    "gn:admin1_code":"9.0",
    "gn:admin2_code":"P\u2019y\u014fnggang-gun",
    "gn:asciiname":"Hyongjaedari",
    "gn:country_code":"KP",
    "gn:dem":352,
    "gn:feature_class":"P",
    "gn:feature_code":"PPL",
    "gn:name":"Hy\u014fngjaedari",
    "gn:population":0,
    "gn:timezone":"Asia/Pyongyang",
    "iso:country":"KP",
    "wof:name":"Hyongjaedari",
    "wof:placetype":"locality"
},
  "geometry": {"coordinates":[127.22417,38.44278],"type":"Point"}
}