{
  "type": "Feature",
  "properties": {
    "gn:admin1_code":"7.0",
    "gn:asciiname":"Kwangt'al-li",
    "gn:country_code":"KP",
    "gn:dem":17,
    "gn:feature_class":"P",
    "gn:feature_code":"PPL",
    "gn:name":"Kwangt\u2019al-li",
    "gn:population":0,
    "gn:timezone":"Asia/Pyongyang",
    "iso:country":"KP",
    "name:und_x_variant":[
        "Kwangt\u2019an-ni",
        "Kwangt\u2019al-li"
    ],
    "wof:name":"Kwangt'al-li",
    "wof:placetype":"locality"
},
  "geometry": {"coordinates":[125.72417,38.37083],"type":"Point"}
}