{
  "type": "Feature",
  "properties": {
    "gn:admin1_code":"11.0",
    "gn:asciiname":"Ch'osang-ni",
    "gn:country_code":"KP",
    "gn:dem":154,
    "gn:feature_class":"P",
    "gn:feature_code":"PPL",
    "gn:name":"Ch\u2019osang-ni",
    "gn:population":0,
    "gn:timezone":"Asia/Pyongyang",
    "iso:country":"KP",
    "name:eng_x_preferred":[
        "Ch'osang"
    ],
    "name:eng_x_variant":[
        "Ch'osang-ni"
    ],
    "name:und_x_variant":[
        "\ucd08\uc0c1\ub9ac",
        "Ch\u2019osang-ni"
    ],
    "wof:name":"Ch'osang",
    "wof:placetype":"locality"
},
  "geometry": {"coordinates":[125.75861,40.07417],"type":"Point"}
}