{
  "type": "Feature",
  "properties": {
    "gn:admin1_code":"17.0",
    "gn:admin2_code":"Ch'\u014fngam-guy\u014fk, Ch'\u014fngjin-si",
    "gn:asciiname":"Sangsagu-dong",
    "gn:country_code":"KP",
    "gn:dem":38,
    "gn:feature_class":"P",
    "gn:feature_code":"PPL",
    "gn:name":"Sangsagu-dong",
    "gn:population":0,
    "gn:timezone":"Asia/Pyongyang",
    "iso:country":"KP",
    "name:und_x_variant":[
        "\uc0c1\uc0ac\uad6c\ub3d9",
        "Sangsagu-dong"
    ],
    "wof:name":"Sangsagu-dong",
    "wof:placetype":"locality"
},
  "geometry": {"coordinates":[129.90943999999999,41.99417],"type":"Point"}
}