{
  "type": "Feature",
  "properties": {
    "gn:admin1_code":"15.0",
    "gn:asciiname":"T'ongdong-ni",
    "gn:country_code":"KP",
    "gn:dem":288,
    "gn:feature_class":"P",
    "gn:feature_code":"PPL",
    "gn:name":"T\u2019ongdong-ni",
    "gn:population":0,
    "gn:timezone":"Asia/Pyongyang",
    "iso:country":"KP",
    "name:eng_x_preferred":[
        "T'ongdong"
    ],
    "name:eng_x_variant":[
        "T'ongdong-ni"
    ],
    "name:kor_x_preferred":[
        "\ud1b5\ub3d9\ub9ac"
    ],
    "name:kor_x_variant":[
        "T\u2019ongdong-ni"
    ],
    "wof:name":"T'ongdong",
    "wof:placetype":"locality"
},
  "geometry": {"coordinates":[126.94777999999999,39.14],"type":"Point"}
}