{
  "type": "Feature",
  "properties": {
    "gn:admin1_code":"6.0",
    "gn:asciiname":"Murung-ni",
    "gn:cc2":"KP",
    "gn:country_code":"KP",
    "gn:dem":14,
    "gn:feature_class":"P",
    "gn:feature_code":"PPL",
    "gn:name":"Mur\u016dng-ni",
    "gn:population":0,
    "gn:timezone":"Asia/Pyongyang",
    "iso:country":"KP",
    "name:und_x_variant":[
        "Mun\u016dng-ni",
        "Mur\u016dng-ni"
    ],
    "wof:name":"Murung-ni",
    "wof:placetype":"locality"
},
  "geometry": {"coordinates":[126.14028,37.79056],"type":"Point"}
}