{
  "type": "Feature",
  "properties": {
    "gn:admin1_code":"11.0",
    "gn:asciiname":"Ch'ungdal",
    "gn:country_code":"KP",
    "gn:dem":65,
    "gn:feature_class":"P",
    "gn:feature_code":"PPL",
    "gn:name":"Ch\u2019ungdal",
    "gn:population":0,
    "gn:timezone":"Asia/Pyongyang",
    "iso:country":"KP",
    "name:und_x_variant":[
        "Ch-ungda",
        "Ch\u2019ungdal"
    ],
    "wof:name":"Ch'ungdal",
    "wof:placetype":"locality"
},
  "geometry": {"coordinates":[125.23111000000002,39.79806],"type":"Point"}
}