{
  "type": "Feature",
  "properties": {
    "gn:admin1_code":"3.0",
    "gn:asciiname":"Sant'aegae",
    "gn:country_code":"KP",
    "gn:dem":825,
    "gn:feature_class":"P",
    "gn:feature_code":"PPL",
    "gn:name":"Sant\u2019aegae",
    "gn:population":0,
    "gn:timezone":"Asia/Pyongyang",
    "iso:country":"KP",
    "name:kor_x_preferred":[
        "\uc0b0\ud0dc\uac1c"
    ],
    "name:kor_x_variant":[
        "Sant\u2019aegae"
    ],
    "wof:name":"Sant'aegae",
    "wof:placetype":"locality"
},
  "geometry": {"coordinates":[126.96417,39.75167],"type":"Point"}
}