{
  "type": "Feature",
  "properties": {
    "gn:admin1_code":"6.0",
    "gn:asciiname":"Tongbakkok",
    "gn:country_code":"KP",
    "gn:dem":102,
    "gn:feature_class":"P",
    "gn:feature_code":"PPL",
    "gn:name":"Tongbakkok",
    "gn:population":0,
    "gn:timezone":"Asia/Pyongyang",
    "iso:country":"KP",
    "wof:name":"Tongbakkok",
    "wof:placetype":"locality"
},
  "geometry": {"coordinates":[125.73860999999999,38.24917],"type":"Point"}
}