{
  "type": "Feature",
  "properties": {
    "gn:admin1_code":"6.0",
    "gn:asciiname":"Tangch'on",
    "gn:country_code":"KP",
    "gn:dem":101,
    "gn:feature_class":"P",
    "gn:feature_code":"PPL",
    "gn:name":"Tangch\u2019on",
    "gn:population":0,
    "gn:timezone":"Asia/Pyongyang",
    "iso:country":"KP",
    "wof:name":"Tangch'on",
    "wof:placetype":"locality"
},
  "geometry": {"coordinates":[125.09278,38.36889],"type":"Point"}
}