{
  "type": "Feature",
  "properties": {
    "gn:admin1_code":"6.0",
    "gn:asciiname":"Popsok-tong",
    "gn:country_code":"KP",
    "gn:dem":11,
    "gn:feature_class":"P",
    "gn:feature_code":"PPL",
    "gn:name":"P\u014fps\u014fk-tong",
    "gn:population":0,
    "gn:timezone":"Asia/Pyongyang",
    "iso:country":"KP",
    "name:eng_x_preferred":[
        "Popsok"
    ],
    "name:eng_x_variant":[
        "Popsok-tong"
    ],
    "name:und_x_variant":[
        "\ubc95\uc11d\ub3d9",
        "P\u014fps\u014fk-tong"
    ],
    "wof:name":"Popsok",
    "wof:placetype":"locality"
},
  "geometry": {"coordinates":[125.16500000000001,37.9625],"type":"Point"}
}