{
  "type": "Feature",
  "properties": {
    "gn:admin1_code":"17.0",
    "gn:asciiname":"Toksanch'on",
    "gn:country_code":"KP",
    "gn:dem":217,
    "gn:feature_class":"P",
    "gn:feature_code":"PPL",
    "gn:name":"Toksanch\u2019on",
    "gn:population":0,
    "gn:timezone":"Asia/Pyongyang",
    "iso:country":"KP",
    "name:und_x_variant":[
        "\ub3c5\uc0b0\ucd0c",
        "Toksanch\u2019on"
    ],
    "wof:name":"Toksanch'on",
    "wof:placetype":"locality"
},
  "geometry": {"coordinates":[129.07417000000001,40.77694],"type":"Point"}
}