{
  "type": "Feature",
  "properties": {
    "gn:admin1_code":"9.0",
    "gn:admin2_code":"Munch\u2019\u014fn-si",
    "gn:asciiname":"Taesong-ni",
    "gn:country_code":"KP",
    "gn:dem":60,
    "gn:feature_class":"P",
    "gn:feature_code":"PPL",
    "gn:name":"Taes\u014fng-ni",
    "gn:population":0,
    "gn:timezone":"Asia/Pyongyang",
    "iso:country":"KP",
    "name:eng_x_preferred":[
        "Taesong"
    ],
    "name:eng_x_variant":[
        "Taesong-ni"
    ],
    "wof:name":"Taesong",
    "wof:placetype":"locality"
},
  "geometry": {"coordinates":[127.285,39.33056],"type":"Point"}
}