{
  "type": "Feature",
  "properties": {
    "gn:admin1_code":"7.0",
    "gn:asciiname":"Sugut'o",
    "gn:country_code":"KP",
    "gn:dem":94,
    "gn:feature_class":"P",
    "gn:feature_code":"PPL",
    "gn:name":"Sugut\u2019\u014f",
    "gn:population":0,
    "gn:timezone":"Asia/Pyongyang",
    "iso:country":"KP",
    "name:kor_x_preferred":[
        "\uc218\uad6c\ud130"
    ],
    "name:kor_x_variant":[
        "Sugut\u2019\u014f"
    ],
    "wof:name":"Sugut'o",
    "wof:placetype":"locality"
},
  "geometry": {"coordinates":[126.53861000000001,38.54333],"type":"Point"}
}