{
  "type": "Feature",
  "properties": {
    "gn:admin1_code":"7.0",
    "gn:asciiname":"Tuhwach'on",
    "gn:country_code":"KP",
    "gn:dem":122,
    "gn:feature_class":"P",
    "gn:feature_code":"PPL",
    "gn:name":"Tuhwach\u2019on",
    "gn:population":0,
    "gn:timezone":"Asia/Pyongyang",
    "iso:country":"KP",
    "wof:name":"Tuhwach'on",
    "wof:placetype":"locality"
},
  "geometry": {"coordinates":[126.10833,38.61],"type":"Point"}
}