{
  "type": "Feature",
  "properties": {
    "gn:admin1_code":"9.0",
    "gn:asciiname":"Nodong-ni",
    "gn:country_code":"KP",
    "gn:dem":529,
    "gn:feature_class":"P",
    "gn:feature_code":"PPL",
    "gn:name":"Nodong-ni",
    "gn:population":0,
    "gn:timezone":"Asia/Pyongyang",
    "iso:country":"KP",
    "name:kor_x_preferred":[
        "\ub178\ub3d9\ub9ac"
    ],
    "wof:name":"Nodong-ni",
    "wof:placetype":"locality"
},
  "geometry": {"coordinates":[127.15722,39.14389],"type":"Point"}
}