{
  "type": "Feature",
  "properties": {
    "gn:admin1_code":"13.0",
    "gn:asciiname":"Wolt'al-lodongjagu",
    "gn:country_code":"KP",
    "gn:dem":587,
    "gn:feature_class":"P",
    "gn:feature_code":"PPL",
    "gn:name":"W\u014flt\u2019al-lodongjagu",
    "gn:population":0,
    "gn:timezone":"Asia/Pyongyang",
    "iso:country":"KP",
    "name:und_x_variant":[
        "W\u014flt\u2019an-dong",
        "W\u014flt\u2019al-li",
        "\uc6d4\ud0c4\ub85c\ub3d9\uc790\uad6c",
        "W\u014flt\u2019al-lodongjagu"
    ],
    "wof:name":"Wolt'al-lodongjagu",
    "wof:placetype":"locality"
},
  "geometry": {"coordinates":[127.06194000000001,41.40722],"type":"Point"}
}