{
  "type": "Feature",
  "properties": {
    "gn:admin1_code":"0.0",
    "gn:asciiname":"Mirim-i-ri",
    "gn:country_code":"KP",
    "gn:dem":15,
    "gn:feature_class":"P",
    "gn:feature_code":"PPL",
    "gn:name":"Mirim-i-ri",
    "gn:population":0,
    "gn:timezone":"Asia/Pyongyang",
    "iso:country":"KP",
    "name:kor_x_preferred":[
        "\ubbf8\ub9bc2\ub9ac"
    ],
    "name:und_x_variant":[
        "Mirim-2-ri",
        "Mirim-i-ri"
    ],
    "wof:name":"Mirim-i-ri",
    "wof:placetype":"locality"
},
  "geometry": {"coordinates":[125.86667,39.03333],"type":"Point"}
}