{
  "type": "Feature",
  "properties": {
    "gn:admin1_code":"6.0",
    "gn:asciiname":"Songch'on-dong",
    "gn:country_code":"KP",
    "gn:dem":58,
    "gn:feature_class":"P",
    "gn:feature_code":"PPL",
    "gn:name":"Songch\u2019\u014fn-dong",
    "gn:population":0,
    "gn:timezone":"Asia/Pyongyang",
    "iso:country":"KP",
    "name:kor_x_preferred":[
        "\uc1a1\uc804\ub3d9"
    ],
    "name:kor_x_variant":[
        "Songch\u2019\u014fn-dong"
    ],
    "wof:name":"Songch'on-dong",
    "wof:placetype":"locality"
},
  "geometry": {"coordinates":[125.1925,38.26167],"type":"Point"}
}