{
  "type": "Feature",
  "properties": {
    "gn:admin1_code":"15.0",
    "gn:admin2_code":"1871865",
    "gn:asciiname":"Yongsal-li",
    "gn:country_code":"KP",
    "gn:dem":48,
    "gn:feature_class":"P",
    "gn:feature_code":"PPL",
    "gn:name":"Yongsal-li",
    "gn:population":0,
    "gn:timezone":"Asia/Pyongyang",
    "iso:country":"KP",
    "wof:name":"Yongsal-li",
    "wof:placetype":"locality"
},
  "geometry": {"coordinates":[125.63417,39.25528],"type":"Point"}
}