{
  "type": "Feature",
  "properties": {
    "gn:admin1_code":"12.0",
    "gn:admin2_code":"Sangw\u014fn-gun",
    "gn:asciiname":"Ppael-gol",
    "gn:cc2":"KP",
    "gn:country_code":"KP",
    "gn:dem":94,
    "gn:feature_class":"P",
    "gn:feature_code":"PPL",
    "gn:name":"Ppael-gol",
    "gn:population":0,
    "gn:timezone":"Asia/Pyongyang",
    "iso:country":"KP",
    "name:und_x_variant":[
        "Ppael-kol",
        "Ppael-gol"
    ],
    "wof:name":"Ppael-gol",
    "wof:placetype":"locality"
},
  "geometry": {"coordinates":[126.12361,38.86694],"type":"Point"}
}