{
  "type": "Feature",
  "properties": {
    "gn:admin1_code":"15.0",
    "gn:asciiname":"Somanmal",
    "gn:country_code":"KP",
    "gn:dem":403,
    "gn:feature_class":"P",
    "gn:feature_code":"PPL",
    "gn:name":"S\u014fmanmal",
    "gn:population":0,
    "gn:timezone":"Asia/Pyongyang",
    "iso:country":"KP",
    "name:und_x_variant":[
        "S\u014fmanma\u016dp",
        "\uc12c\uc548\ub9d0",
        "S\u014fmam-ma\u016dl",
        "S\u014fmanmal"
    ],
    "wof:name":"Somanmal",
    "wof:placetype":"locality"
},
  "geometry": {"coordinates":[126.64417,39.47806],"type":"Point"}
}