{
  "type": "Feature",
  "properties": {
    "gn:admin1_code":"15.0",
    "gn:asciiname":"Kwanp'yong-ni",
    "gn:country_code":"KP",
    "gn:dem":587,
    "gn:feature_class":"P",
    "gn:feature_code":"PPL",
    "gn:name":"Kwanp\u2019y\u014fng-ni",
    "gn:population":0,
    "gn:timezone":"Asia/Pyongyang",
    "iso:country":"KP",
    "name:eng_x_preferred":[
        "Kwanp'yong"
    ],
    "name:eng_x_variant":[
        "Kwanp'yong-ni"
    ],
    "name:und_x_variant":[
        "\uad00\ud3c9\ub9ac",
        "Kwanp\u2019y\u014fng-ni"
    ],
    "wof:name":"Kwanp'yong",
    "wof:placetype":"locality"
},
  "geometry": {"coordinates":[126.93778,40.09444],"type":"Point"}
}