{
  "type": "Feature",
  "properties": {
    "gn:admin1_code":"1.0",
    "gn:asciiname":"Sojunggang",
    "gn:country_code":"KP",
    "gn:dem":861,
    "gn:feature_class":"P",
    "gn:feature_code":"PPL",
    "gn:name":"Sojunggang",
    "gn:population":0,
    "gn:timezone":"Asia/Pyongyang",
    "iso:country":"KP",
    "name:und_x_variant":[
        "\uc18c\uc911\uac15",
        "Sojunggang"
    ],
    "wof:name":"Sojunggang",
    "wof:placetype":"locality"
},
  "geometry": {"coordinates":[127.00611000000001,41.63444000000001],"type":"Point"}
}