{
  "type": "Feature",
  "properties": {
    "gn:admin1_code":"12.0",
    "gn:admin2_code":"Sangw\u014fn-gun",
    "gn:asciiname":"Chom-gol",
    "gn:cc2":"KP",
    "gn:country_code":"KP",
    "gn:dem":258,
    "gn:feature_class":"P",
    "gn:feature_code":"PPL",
    "gn:name":"Ch\u014fm-gol",
    "gn:population":0,
    "gn:timezone":"Asia/Pyongyang",
    "iso:country":"KP",
    "name:und_x_variant":[
        "Ch\u014fm-kol",
        "Ch\u014fm-gol"
    ],
    "wof:name":"Chom-gol",
    "wof:placetype":"locality"
},
  "geometry": {"coordinates":[126.18361000000002,38.7775],"type":"Point"}
}