{
  "type": "Feature",
  "properties": {
    "gn:admin1_code":"0.0",
    "gn:asciiname":"Chinp'yong",
    "gn:country_code":"KP",
    "gn:dem":465,
    "gn:feature_class":"P",
    "gn:feature_code":"PPL",
    "gn:name":"Chinp\u2019y\u014fng",
    "gn:population":0,
    "gn:timezone":"Asia/Pyongyang",
    "iso:country":"KP",
    "name:kor_x_preferred":[
        "\uc9c4\ud3c9"
    ],
    "name:und_x_variant":[
        "Chinp\u2019y\u014fng"
    ],
    "wof:name":"Chinp'yong",
    "wof:placetype":"locality"
},
  "geometry": {"coordinates":[126.84206,41.64694],"type":"Point"}
}