{
  "type": "Feature",
  "properties": {
    "gn:admin1_code":"7.0",
    "gn:asciiname":"Worun-dong",
    "gn:country_code":"KP",
    "gn:dem":130,
    "gn:feature_class":"P",
    "gn:feature_code":"PPL",
    "gn:name":"W\u014fr\u016dn-dong",
    "gn:population":0,
    "gn:timezone":"Asia/Pyongyang",
    "iso:country":"KP",
    "wof:name":"Worun-dong",
    "wof:placetype":"locality"
},
  "geometry": {"coordinates":[126.21306,38.40389],"type":"Point"}
}