{
  "type": "Feature",
  "properties": {
    "gn:admin1_code":"7.0",
    "gn:asciiname":"Kal-gol",
    "gn:country_code":"KP",
    "gn:dem":312,
    "gn:feature_class":"P",
    "gn:feature_code":"PPL",
    "gn:name":"Kal-gol",
    "gn:population":0,
    "gn:timezone":"Asia/Pyongyang",
    "iso:country":"KP",
    "name:kor_x_preferred":[
        "\uac08\uace8"
    ],
    "name:und_x_variant":[
        "Kal-kol",
        "Kal-gol"
    ],
    "wof:name":"Kal-gol",
    "wof:placetype":"locality"
},
  "geometry": {"coordinates":[126.73361,38.67],"type":"Point"}
}