{
  "type": "Feature",
  "properties": {
    "gn:admin1_code":"6.0",
    "gn:admin2_code":"P'anmun-gun",
    "gn:asciiname":"Hant'o",
    "gn:country_code":"KP",
    "gn:dem":29,
    "gn:feature_class":"P",
    "gn:feature_code":"PPL",
    "gn:name":"Hant\u2019\u014f",
    "gn:population":0,
    "gn:timezone":"Asia/Pyongyang",
    "iso:country":"KP",
    "name:kor_x_preferred":[
        "Hant\u2019\u014f"
    ],
    "name:kor_x_variant":[
        "\ud55c\ud130"
    ],
    "name:und_x_variant":[
        "Han\u2019gi",
        "Hando"
    ],
    "wof:name":"Hant'o",
    "wof:placetype":"locality"
},
  "geometry": {"coordinates":[126.60193999999998,37.78333],"type":"Point"}
}