{
  "type": "Feature",
  "properties": {
    "gn:admin1_code":"6.0",
    "gn:asciiname":"Chayang",
    "gn:country_code":"KP",
    "gn:dem":55,
    "gn:feature_class":"P",
    "gn:feature_code":"PPL",
    "gn:name":"Chayang",
    "gn:population":0,
    "gn:timezone":"Asia/Pyongyang",
    "iso:country":"KP",
    "name:und_x_variant":[
        "\uc790\uc591",
        "Chayang-ni",
        "Chayang"
    ],
    "wof:name":"Chayang",
    "wof:placetype":"locality"
},
  "geometry": {"coordinates":[125.49028,37.99778],"type":"Point"}
}