{
  "type": "Feature",
  "properties": {
    "gn:admin1_code":"13.0",
    "gn:asciiname":"Uihwa-ri",
    "gn:country_code":"KP",
    "gn:dem":784,
    "gn:feature_class":"P",
    "gn:feature_code":"PPL",
    "gn:name":"\u016cihwa-ri",
    "gn:population":0,
    "gn:timezone":"Asia/Pyongyang",
    "iso:country":"KP",
    "wof:name":"Uihwa-ri",
    "wof:placetype":"locality"
},
  "geometry": {"coordinates":[128.29583,41.50389000000001],"type":"Point"}
}