{
  "type": "Feature",
  "properties": {
    "gn:admin1_code":"15.0",
    "gn:asciiname":"Kusong-dong",
    "gn:country_code":"KP",
    "gn:dem":8,
    "gn:feature_class":"P",
    "gn:feature_code":"PPL",
    "gn:name":"Kusong-dong",
    "gn:population":0,
    "gn:timezone":"Asia/Pyongyang",
    "iso:country":"KP",
    "name:kor_x_preferred":[
        "\uad6c\uc1a1\ub3d9"
    ],
    "wof:name":"Kusong-dong",
    "wof:placetype":"locality"
},
  "geometry": {"coordinates":[125.53444,38.72944],"type":"Point"}
}