{
  "type": "Feature",
  "properties": {
    "gn:admin1_code":"3.0",
    "gn:asciiname":"Tangbong-ni",
    "gn:country_code":"KP",
    "gn:dem":193,
    "gn:feature_class":"P",
    "gn:feature_code":"PPL",
    "gn:name":"Tangbong-ni",
    "gn:population":0,
    "gn:timezone":"Asia/Pyongyang",
    "iso:country":"KP",
    "name:und_x_variant":[
        "\ub2f9\ubcf5\ub9ac",
        "Tangbong-ni"
    ],
    "wof:name":"Tangbong-ni",
    "wof:placetype":"locality"
},
  "geometry": {"coordinates":[127.57889,40.26861],"type":"Point"}
}