{
  "type": "Feature",
  "properties": {
    "gn:admin1_code":"15.0",
    "gn:asciiname":"Ansang-ni",
    "gn:cc2":"KP",
    "gn:country_code":"KP",
    "gn:dem":181,
    "gn:feature_class":"P",
    "gn:feature_code":"PPL",
    "gn:name":"Ansang-ni",
    "gn:population":0,
    "gn:timezone":"Asia/Pyongyang",
    "iso:country":"KP",
    "name:eng_x_preferred":[
        "Ansang"
    ],
    "name:eng_x_variant":[
        "Ansang-ni"
    ],
    "name:kor_x_preferred":[
        "\uc548\uc0c1\ub9ac"
    ],
    "name:und_x_variant":[
        "Ansan-dong",
        "Ansang-ni"
    ],
    "wof:name":"Ansang",
    "wof:placetype":"locality"
},
  "geometry": {"coordinates":[126.33167,39.515],"type":"Point"}
}