{
  "type": "Feature",
  "properties": {
    "gn:admin1_code":"15.0",
    "gn:asciiname":"Sach'on-dong",
    "gn:country_code":"KP",
    "gn:dem":323,
    "gn:feature_class":"P",
    "gn:feature_code":"PPL",
    "gn:name":"Sach\u2019\u014fn-dong",
    "gn:population":0,
    "gn:timezone":"Asia/Pyongyang",
    "iso:country":"KP",
    "name:und_x_variant":[
        "\uc0ac\ucc9c\ub3d9",
        "Sach\u2019\u014fn-dong"
    ],
    "wof:name":"Sach'on-dong",
    "wof:placetype":"locality"
},
  "geometry": {"coordinates":[126.69194,39.17722],"type":"Point"}
}