{
  "type": "Feature",
  "properties": {
    "gn:admin1_code":"15.0",
    "gn:admin2_code":"Kaech\u2019\u014fn-si",
    "gn:asciiname":"Yasach'am",
    "gn:country_code":"KP",
    "gn:dem":89,
    "gn:feature_class":"P",
    "gn:feature_code":"PPL",
    "gn:name":"Yasach\u2019am",
    "gn:population":0,
    "gn:timezone":"Asia/Pyongyang",
    "iso:country":"KP",
    "wof:name":"Yasach'am",
    "wof:placetype":"locality"
},
  "geometry": {"coordinates":[126.05583,39.57028],"type":"Point"}
}