{
  "type": "Feature",
  "properties": {
    "gn:admin1_code":"6.0",
    "gn:asciiname":"Paekchong-ni",
    "gn:country_code":"KP",
    "gn:dem":72,
    "gn:feature_class":"P",
    "gn:feature_code":"PPL",
    "gn:name":"Paekch\u014fng-ni",
    "gn:population":0,
    "gn:timezone":"Asia/Pyongyang",
    "iso:country":"KP",
    "name:und_x_variant":[
        "\ubc31\uc815\ub9ac",
        "Paekch\u014fng-ni"
    ],
    "wof:name":"Paekchong-ni",
    "wof:placetype":"locality"
},
  "geometry": {"coordinates":[125.32611,38.19167],"type":"Point"}
}