{
  "type": "Feature",
  "properties": {
    "gn:admin1_code":"6.0",
    "gn:asciiname":"Yach'on",
    "gn:country_code":"KP",
    "gn:dem":22,
    "gn:feature_class":"P",
    "gn:feature_code":"PPL",
    "gn:name":"Yach\u2019on",
    "gn:population":0,
    "gn:timezone":"Asia/Pyongyang",
    "iso:country":"KP",
    "name:kor_x_preferred":[
        "Yach\u2019on"
    ],
    "name:kor_x_variant":[
        "\uc57c\ucd0c"
    ],
    "wof:name":"Yach'on",
    "wof:placetype":"locality"
},
  "geometry": {"coordinates":[125.01000000000001,38.0975],"type":"Point"}
}