{
  "type": "Feature",
  "properties": {
    "gn:admin1_code":"6.0",
    "gn:asciiname":"Namsusan",
    "gn:country_code":"KP",
    "gn:dem":44,
    "gn:feature_class":"P",
    "gn:feature_code":"PPL",
    "gn:name":"Namsusan",
    "gn:population":0,
    "gn:timezone":"Asia/Pyongyang",
    "iso:country":"KP",
    "name:kor_x_preferred":[
        "\ub0a8\uc218\uc0b0"
    ],
    "wof:name":"Namsusan",
    "wof:placetype":"locality"
},
  "geometry": {"coordinates":[126.24666999999999,38.1625],"type":"Point"}
}