{
  "type": "Feature",
  "properties": {
    "gn:admin1_code":"3.0",
    "gn:asciiname":"Yongsong-ni",
    "gn:country_code":"KP",
    "gn:dem":3,
    "gn:feature_class":"P",
    "gn:feature_code":"PPL",
    "gn:name":"Yongs\u014fng-ni",
    "gn:population":0,
    "gn:timezone":"Asia/Pyongyang",
    "iso:country":"KP",
    "name:und_x_variant":[
        "Ry\u016bj\u014d-ri",
        "Ry\u016bj\u014d",
        "Yongsang-ni",
        "Yongs\u014fng-ni"
    ],
    "wof:name":"Yongsong-ni",
    "wof:placetype":"locality"
},
  "geometry": {"coordinates":[127.53222,39.78417],"type":"Point"}
}