{
  "type": "Feature",
  "properties": {
    "gn:admin1_code":"3.0",
    "gn:asciiname":"Nunggu-ri",
    "gn:country_code":"KP",
    "gn:dem":959,
    "gn:feature_class":"P",
    "gn:feature_code":"PPL",
    "gn:name":"N\u016dnggu-ri",
    "gn:population":0,
    "gn:timezone":"Asia/Pyongyang",
    "iso:country":"KP",
    "name:kor_x_preferred":[
        "\ub2a5\uad6c\ub9ac"
    ],
    "name:kor_x_variant":[
        "N\u016dnggu-ri"
    ],
    "name:und_x_variant":[
        "Ry\u014dk\u014d-ri"
    ],
    "wof:name":"Nunggu-ri",
    "wof:placetype":"locality"
},
  "geometry": {"coordinates":[127.56139,40.98944],"type":"Point"}
}