{
  "type": "Feature",
  "properties": {
    "gn:admin1_code":"15.0",
    "gn:asciiname":"Sokch'i-ri",
    "gn:country_code":"KP",
    "gn:dem":11,
    "gn:feature_class":"P",
    "gn:feature_code":"PPL",
    "gn:name":"S\u014fkch\u2019i-ri",
    "gn:population":0,
    "gn:timezone":"Asia/Pyongyang",
    "iso:country":"KP",
    "name:und_x_variant":[
        "\uc11d\uce58\ub9ac",
        "S\u014fkch\u2019i-ri"
    ],
    "wof:name":"Sokch'i-ri",
    "wof:placetype":"locality"
},
  "geometry": {"coordinates":[125.21361,38.94083],"type":"Point"}
}