{
  "type": "Feature",
  "properties": {
    "gn:admin1_code":"9.0",
    "gn:asciiname":"T'oet'al-li",
    "gn:country_code":"KP",
    "gn:dem":83,
    "gn:feature_class":"P",
    "gn:feature_code":"PPL",
    "gn:name":"T\u2019oet\u2019al-li",
    "gn:population":0,
    "gn:timezone":"Asia/Pyongyang",
    "iso:country":"KP",
    "name:und_x_variant":[
        "T\u2019oet\u2019an-ni",
        "T\u2019oet\u2019al-li"
    ],
    "wof:name":"T'oet'al-li",
    "wof:placetype":"locality"
},
  "geometry": {"coordinates":[126.88611000000002,38.36333],"type":"Point"}
}