{
  "type": "Feature",
  "properties": {
    "gn:admin1_code":"6.0",
    "gn:asciiname":"Put'o-ri",
    "gn:country_code":"KP",
    "gn:dem":19,
    "gn:feature_class":"P",
    "gn:feature_code":"PPL",
    "gn:name":"Put\u2019o-ri",
    "gn:population":0,
    "gn:timezone":"Asia/Pyongyang",
    "iso:country":"KP",
    "name:und_x_variant":[
        "Pusa-ri",
        "Put\u2019o-ri"
    ],
    "wof:name":"Put'o-ri",
    "wof:placetype":"locality"
},
  "geometry": {"coordinates":[126.02916999999999,37.90056],"type":"Point"}
}