{
  "type": "Feature",
  "properties": {
    "gn:admin1_code":"7.0",
    "gn:asciiname":"Han'gu-dong",
    "gn:country_code":"KP",
    "gn:dem":79,
    "gn:feature_class":"P",
    "gn:feature_code":"PPL",
    "gn:name":"Han\u2019gu-dong",
    "gn:population":0,
    "gn:timezone":"Asia/Pyongyang",
    "iso:country":"KP",
    "wof:name":"Han'gu-dong",
    "wof:placetype":"locality"
},
  "geometry": {"coordinates":[126.00417,38.35],"type":"Point"}
}