{
  "type": "Feature",
  "properties": {
    "gn:admin1_code":"0.0",
    "gn:asciiname":"Ch'ongnyon-dong",
    "gn:country_code":"KP",
    "gn:dem":238,
    "gn:feature_class":"P",
    "gn:feature_code":"PPL",
    "gn:name":"Ch\u2019\u014fngny\u014fn-dong",
    "gn:population":0,
    "gn:timezone":"Asia/Pyongyang",
    "iso:country":"KP",
    "wof:name":"Ch'ongnyon-dong",
    "wof:placetype":"locality"
},
  "geometry": {"coordinates":[125.09999999999999,38.18333],"type":"Point"}
}