{
  "type": "Feature",
  "properties": {
    "gn:admin1_code":"12.0",
    "gn:admin2_code":"Kangdong-gun",
    "gn:asciiname":"Cheryong-ni",
    "gn:country_code":"KP",
    "gn:dem":96,
    "gn:feature_class":"P",
    "gn:feature_code":"PPL",
    "gn:name":"Chery\u014fng-ni",
    "gn:population":0,
    "gn:timezone":"Asia/Pyongyang",
    "iso:country":"KP",
    "name:kor_x_preferred":[
        "\uc81c\ub839\ub9ac"
    ],
    "name:und_x_variant":[
        "Chery\u014fng-ni",
        "Jeryeongni"
    ],
    "wof:name":"Cheryong-ni",
    "wof:placetype":"locality"
},
  "geometry": {"coordinates":[126.11417,39.02694],"type":"Point"}
}