{
  "type": "Feature",
  "properties": {
    "gn:admin1_code":"3.0",
    "gn:asciiname":"Chisong-ni",
    "gn:country_code":"KP",
    "gn:dem":15,
    "gn:feature_class":"P",
    "gn:feature_code":"PPL",
    "gn:name":"Chis\u014fng-ni",
    "gn:population":0,
    "gn:timezone":"Asia/Pyongyang",
    "iso:country":"KP",
    "name:und_x_variant":[
        "\uc9c0\uc11d\ub9ac",
        "Chis\u014fng-ni"
    ],
    "wof:name":"Chisong-ni",
    "wof:placetype":"locality"
},
  "geometry": {"coordinates":[127.45361,39.91389],"type":"Point"}
}