{
  "type": "Feature",
  "properties": {
    "gn:admin1_code":"0.0",
    "gn:asciiname":"Kwangsong-dong",
    "gn:country_code":"KP",
    "gn:dem":491,
    "gn:feature_class":"P",
    "gn:feature_code":"PPL",
    "gn:name":"Kwangs\u014fng-dong",
    "gn:population":0,
    "gn:timezone":"Asia/Pyongyang",
    "iso:country":"KP",
    "name:kor_x_preferred":[
        "\uad11\uc131\ub3d9"
    ],
    "name:und_x_variant":[
        "Kwangs\u014fng-dong"
    ],
    "wof:name":"Kwangsong-dong",
    "wof:placetype":"locality"
},
  "geometry": {"coordinates":[125.15000000000001,40.33333],"type":"Point"}
}