{
  "type": "Feature",
  "properties": {
    "gn:admin1_code":"15.0",
    "gn:asciiname":"Sinhwa-ri",
    "gn:country_code":"KP",
    "gn:dem":77,
    "gn:feature_class":"P",
    "gn:feature_code":"PPL",
    "gn:name":"Sinhwa-ri",
    "gn:population":0,
    "gn:timezone":"Asia/Pyongyang",
    "iso:country":"KP",
    "wof:name":"Sinhwa-ri",
    "wof:placetype":"locality"
},
  "geometry": {"coordinates":[125.715,39.30306],"type":"Point"}
}