{
  "type": "Feature",
  "properties": {
    "gn:admin1_code":"3.0",
    "gn:asciiname":"Mun-ch'on",
    "gn:country_code":"KP",
    "gn:dem":17,
    "gn:feature_class":"P",
    "gn:feature_code":"PPL",
    "gn:name":"Mun-ch\u2019on",
    "gn:population":0,
    "gn:timezone":"Asia/Pyongyang",
    "iso:country":"KP",
    "name:und_x_variant":[
        "Mun-ch\u2019on",
        "\ubb38\ucd0c"
    ],
    "wof:name":"Mun-ch'on",
    "wof:placetype":"locality"
},
  "geometry": {"coordinates":[128.18167,40.03917],"type":"Point"}
}