{
  "type": "Feature",
  "properties": {
    "gn:admin1_code":"7.0",
    "gn:asciiname":"Tunung-gol",
    "gn:country_code":"KP",
    "gn:dem":44,
    "gn:feature_class":"P",
    "gn:feature_code":"PPL",
    "gn:name":"Tun\u016dng-gol",
    "gn:population":0,
    "gn:timezone":"Asia/Pyongyang",
    "iso:country":"KP",
    "name:und_x_variant":[
        "\ub450\ub2a5\uace8",
        "Tun\u016dng-gol"
    ],
    "wof:name":"Tunung-gol",
    "wof:placetype":"locality"
},
  "geometry": {"coordinates":[125.88,38.76333],"type":"Point"}
}