{
  "type": "Feature",
  "properties": {
    "gn:admin1_code":"11.0",
    "gn:asciiname":"Puksinhyol-li",
    "gn:cc2":"KP",
    "gn:country_code":"KP",
    "gn:dem":90,
    "gn:feature_class":"P",
    "gn:feature_code":"PPL",
    "gn:name":"Puksinhy\u014fl-li",
    "gn:population":0,
    "gn:timezone":"Asia/Pyongyang",
    "iso:country":"KP",
    "name:und_x_variant":[
        "Puksinhy\u014fn-ni",
        "\ubd81\uc2e0\ud604\ub9ac",
        "Puksinhy\u014fl-li"
    ],
    "wof:name":"Puksinhyol-li",
    "wof:placetype":"locality"
},
  "geometry": {"coordinates":[126.13249999999999,39.98917],"type":"Point"}
}