{
  "type": "Feature",
  "properties": {
    "iso:country":"KP",
    "name:eng_x_colloquial":[
        "Sanhthng-dong",
        "Sanhtng-dong",
        "Sanhung-dong"
    ],
    "name:eng_x_preferred":[
        "Sanh\u00feng-dong"
    ],
    "name:unk_x_variant":[
        "Sanh\u00feng-dong"
    ],
    "qs:gn_adm0_cc":"KP",
    "qs:gn_local":1871859,
    "qs:gn_nam_loc":"Pyongyang",
    "qs:gn_namadm1":"15",
    "qs:local_max":3808,
    "qs:local_sum":10152,
    "qs:localhoods":11,
    "qs:name":"Sanh\u00feng-dong",
    "qs:name_adm0":"North Korea",
    "qs:name_adm1":"P\u00b4yongyang-si",
    "qs:name_local":"Pyongyang",
    "qs:photo_max":10,
    "qs:photo_sum":14,
    "qs:placetype":"Suburb",
    "qs:quad_count":3,
    "qs:woe_adm0":23424865,
    "qs:woe_adm1":20070115,
    "qs:woe_adm2":0,
    "qs:woe_lau":0,
    "qs:woe_local":1079132,
    "qs:woe_ver":"7.10.0",
    "wof:lang":[
        "eng"
    ],
    "wof:name":"Sanh\u00feng-dong",
    "wof:placetype":"neighbourhood"
},
  "geometry": {"coordinates":[125.73651099999999,39.046921],"type":"Point"}
}