{
  "type": "Feature",
  "properties": {
    "gn:admin1_code":"6.0",
    "gn:asciiname":"Sach'on",
    "gn:country_code":"KP",
    "gn:dem":59,
    "gn:feature_class":"P",
    "gn:feature_code":"PPL",
    "gn:name":"Sach\u2019\u014fn",
    "gn:population":0,
    "gn:timezone":"Asia/Pyongyang",
    "iso:country":"KP",
    "name:kor_x_preferred":[
        "\uc0ac\ucc9c"
    ],
    "name:kor_x_variant":[
        "Sach\u2019\u014fn"
    ],
    "wof:name":"Sach'on",
    "wof:placetype":"locality"
},
  "geometry": {"coordinates":[125.27417,38.34028],"type":"Point"}
}