{
  "type": "Feature",
  "properties": {
    "gn:admin1_code":"9.0",
    "gn:admin2_code":"Munch\u2019\u014fn-si",
    "gn:asciiname":"Yugumi-ri",
    "gn:country_code":"KP",
    "gn:dem":8,
    "gn:feature_class":"P",
    "gn:feature_code":"PPL",
    "gn:name":"Yugumi-ri",
    "gn:population":0,
    "gn:timezone":"Asia/Pyongyang",
    "iso:country":"KP",
    "wof:name":"Yugumi-ri",
    "wof:placetype":"locality"
},
  "geometry": {"coordinates":[127.40806000000001,39.35889],"type":"Point"}
}