{
  "type": "Feature",
  "properties": {
    "gn:admin1_code":"17.0",
    "gn:asciiname":"Yugwan-dong",
    "gn:country_code":"KP",
    "gn:dem":26,
    "gn:feature_class":"P",
    "gn:feature_code":"PPL",
    "gn:name":"Yugwan-dong",
    "gn:population":0,
    "gn:timezone":"Asia/Pyongyang",
    "iso:country":"KP",
    "name:und_x_variant":[
        "\uc720\uad00\ub3d9",
        "Yugwan-dong"
    ],
    "wof:name":"Yugwan-dong",
    "wof:placetype":"locality"
},
  "geometry": {"coordinates":[129.75667000000001,41.84556],"type":"Point"}
}