{
  "type": "Feature",
  "properties": {
    "gn:admin1_code":"17.0",
    "gn:asciiname":"Soman",
    "gn:country_code":"KP",
    "gn:dem":199,
    "gn:feature_class":"P",
    "gn:feature_code":"PPL",
    "gn:name":"S\u014fman",
    "gn:population":0,
    "gn:timezone":"Asia/Pyongyang",
    "iso:country":"KP",
    "name:und_x_variant":[
        "\uc12c\uc548",
        "S\u014fman"
    ],
    "wof:name":"Soman",
    "wof:placetype":"locality"
},
  "geometry": {"coordinates":[129.35138999999998,41.02111],"type":"Point"}
}