{
  "type": "Feature",
  "properties": {
    "gn:admin1_code":"7.0",
    "gn:asciiname":"Wangdaejong",
    "gn:country_code":"KP",
    "gn:dem":17,
    "gn:feature_class":"P",
    "gn:feature_code":"PPL",
    "gn:name":"Wangdaej\u014fng",
    "gn:population":0,
    "gn:timezone":"Asia/Pyongyang",
    "iso:country":"KP",
    "name:und_x_variant":[
        "\uc655\ub300\uc815",
        "Wangdaej\u014fng"
    ],
    "wof:name":"Wangdaejong",
    "wof:placetype":"locality"
},
  "geometry": {"coordinates":[125.7625,38.79333],"type":"Point"}
}