{
  "type": "Feature",
  "properties": {
    "gn:admin1_code":"6.0",
    "gn:asciiname":"Sanji-gol",
    "gn:country_code":"KP",
    "gn:dem":47,
    "gn:feature_class":"P",
    "gn:feature_code":"PPL",
    "gn:name":"Sanji-gol",
    "gn:population":0,
    "gn:timezone":"Asia/Pyongyang",
    "iso:country":"KP",
    "name:und_x_variant":[
        "\uc0b0\uc9c0\uace8",
        "Sanji-gol"
    ],
    "wof:name":"Sanji-gol",
    "wof:placetype":"locality"
},
  "geometry": {"coordinates":[125.5575,37.83278],"type":"Point"}
}