{
  "type": "Feature",
  "properties": {
    "gn:admin1_code":"9.0",
    "gn:asciiname":"T'osong",
    "gn:country_code":"KP",
    "gn:dem":570,
    "gn:feature_class":"P",
    "gn:feature_code":"PPL",
    "gn:name":"T\u2019os\u014fng",
    "gn:population":0,
    "gn:timezone":"Asia/Pyongyang",
    "iso:country":"KP",
    "wof:name":"T'osong",
    "wof:placetype":"locality"
},
  "geometry": {"coordinates":[127.36056000000001,38.62861],"type":"Point"}
}