{
  "type": "Feature",
  "properties": {
    "gn:admin1_code":"15.0",
    "gn:asciiname":"Ch'onbang-gol",
    "gn:country_code":"KP",
    "gn:dem":764,
    "gn:feature_class":"P",
    "gn:feature_code":"PPL",
    "gn:name":"Ch\u2019\u014fnbang-gol",
    "gn:population":0,
    "gn:timezone":"Asia/Pyongyang",
    "iso:country":"KP",
    "name:und_x_variant":[
        "\ucc9c\ubc29\uace8",
        "Ch\u2019\u014fnbang-gol"
    ],
    "wof:name":"Ch'onbang-gol",
    "wof:placetype":"locality"
},
  "geometry": {"coordinates":[126.95332999999999,40.09722],"type":"Point"}
}