{
  "type": "Feature",
  "properties": {
    "gn:admin1_code":"15.0",
    "gn:asciiname":"Won-dong",
    "gn:country_code":"KP",
    "gn:dem":540,
    "gn:feature_class":"P",
    "gn:feature_code":"PPL",
    "gn:name":"W\u014fn-dong",
    "gn:population":0,
    "gn:timezone":"Asia/Pyongyang",
    "iso:country":"KP",
    "name:und_x_variant":[
        "\uc6d0\ub3d9",
        "W\u014fn-dong"
    ],
    "wof:name":"Won-dong",
    "wof:placetype":"locality"
},
  "geometry": {"coordinates":[126.72750000000001,39.38667],"type":"Point"}
}