{
  "type": "Feature",
  "properties": {
    "gn:admin1_code":"0.0",
    "gn:asciiname":"Tubaeng-ni",
    "gn:country_code":"KP",
    "gn:dem":6,
    "gn:feature_class":"P",
    "gn:feature_code":"PPL",
    "gn:name":"Tubaeng-ni",
    "gn:population":0,
    "gn:timezone":"Asia/Pyongyang",
    "iso:country":"KP",
    "name:kor_x_preferred":[
        "\ub450\ubc45\ub9ac"
    ],
    "wof:name":"Tubaeng-ni",
    "wof:placetype":"locality"
},
  "geometry": {"coordinates":[128.05000000000001,38.85],"type":"Point"}
}