{
  "type": "Feature",
  "properties": {
    "gn:admin1_code":"15.0",
    "gn:asciiname":"Hwasim-ni",
    "gn:country_code":"KP",
    "gn:dem":108,
    "gn:feature_class":"P",
    "gn:feature_code":"PPL",
    "gn:name":"Hwasim-ni",
    "gn:population":0,
    "gn:timezone":"Asia/Pyongyang",
    "iso:country":"KP",
    "name:eng_x_preferred":[
        "Hwasim"
    ],
    "name:eng_x_variant":[
        "Hwasim-ni"
    ],
    "name:kor_x_preferred":[
        "\ud654\uc2ec\ub9ac"
    ],
    "wof:name":"Hwasim",
    "wof:placetype":"locality"
},
  "geometry": {"coordinates":[126.46028,38.92833],"type":"Point"}
}