{
  "type": "Feature",
  "properties": {
    "gn:admin1_code":"0.0",
    "gn:asciiname":"Hasam-ni",
    "gn:country_code":"KP",
    "gn:dem":16,
    "gn:feature_class":"P",
    "gn:feature_code":"PPL",
    "gn:name":"Hasam-ni",
    "gn:population":0,
    "gn:timezone":"Asia/Pyongyang",
    "iso:country":"KP",
    "name:eng_x_preferred":[
        "Hasam"
    ],
    "name:eng_x_variant":[
        "Hasam-ni"
    ],
    "name:kor_x_preferred":[
        "\ud558\uc0bc\ub9ac"
    ],
    "wof:name":"Hasam",
    "wof:placetype":"locality"
},
  "geometry": {"coordinates":[125.63333,38.05],"type":"Point"}
}