{
  "type": "Feature",
  "properties": {
    "gn:admin1_code":"12.0",
    "gn:asciiname":"Sojiyong",
    "gn:country_code":"KP",
    "gn:dem":94,
    "gn:feature_class":"P",
    "gn:feature_code":"PPL",
    "gn:name":"S\u014fjiy\u014fng",
    "gn:population":0,
    "gn:timezone":"Asia/Pyongyang",
    "iso:country":"KP",
    "name:kor_x_preferred":[
        "\uc11c\uc9c0\uc601"
    ],
    "name:und_x_variant":[
        "S\u014fjiy\u014fng",
        "Seojiyeong"
    ],
    "wof:name":"Sojiyong",
    "wof:placetype":"locality"
},
  "geometry": {"coordinates":[125.91278,39.11167],"type":"Point"}
}