{
  "type": "Feature",
  "properties": {
    "gn:admin1_code":"17.0",
    "gn:asciiname":"Yuson-dong",
    "gn:country_code":"KP",
    "gn:dem":241,
    "gn:feature_class":"P",
    "gn:feature_code":"PPLL",
    "gn:name":"Yus\u014fn-dong",
    "gn:population":0,
    "gn:timezone":"Asia/Pyongyang",
    "iso:country":"KP",
    "name:und_x_variant":[
        "Y\u016dsen-d\u014f",
        "Yus\u014fl-li",
        "Yus\u014fn-nodongjagu",
        "Yus\u014fn",
        "Yus\u014fn-ni",
        "\uc720\uc120\ub3d9",
        "Yus\u014fl-lodongjagu",
        "Yus\u014fn-dong"
    ],
    "wof:name":"Yuson-dong",
    "wof:placetype":"locality"
},
  "geometry": {"coordinates":[129.64332999999999,42.42111],"type":"Point"}
}