{
  "type": "Feature",
  "properties": {
    "gn:admin1_code":"3.0",
    "gn:asciiname":"Ich'on",
    "gn:country_code":"KP",
    "gn:dem":87,
    "gn:feature_class":"P",
    "gn:feature_code":"PPL",
    "gn:name":"Ich\u2019on",
    "gn:population":0,
    "gn:timezone":"Asia/Pyongyang",
    "iso:country":"KP",
    "name:kor_x_preferred":[
        "\uc774\ucd0c"
    ],
    "name:kor_x_variant":[
        "Ich\u2019on"
    ],
    "wof:name":"Ich'on",
    "wof:placetype":"locality"
},
  "geometry": {"coordinates":[127.15306,39.51278],"type":"Point"}
}