{
  "type": "Feature",
  "properties": {
    "gn:admin1_code":"7.0",
    "gn:asciiname":"Sangnyong-ni",
    "gn:country_code":"KP",
    "gn:dem":73,
    "gn:feature_class":"P",
    "gn:feature_code":"PPL",
    "gn:name":"Sangny\u014fng-ni",
    "gn:population":0,
    "gn:timezone":"Asia/Pyongyang",
    "iso:country":"KP",
    "name:eng_x_preferred":[
        "Sangnyong"
    ],
    "name:eng_x_variant":[
        "Sangnyong-ni"
    ],
    "name:und_x_variant":[
        "\uc0c1\ub839\ub9ac",
        "Sangny\u014fng-ni"
    ],
    "wof:name":"Sangnyong",
    "wof:placetype":"locality"
},
  "geometry": {"coordinates":[126.36972,38.22944],"type":"Point"}
}