{
  "type": "Feature",
  "properties": {
    "gn:admin1_code":"17.0",
    "gn:asciiname":"Pang-dong",
    "gn:country_code":"KP",
    "gn:dem":17,
    "gn:feature_class":"P",
    "gn:feature_code":"PPL",
    "gn:name":"Pang-dong",
    "gn:population":0,
    "gn:timezone":"Asia/Pyongyang",
    "iso:country":"KP",
    "name:und_x_variant":[
        "\ubc29\ub3d9",
        "Pang-dong"
    ],
    "wof:name":"Pang-dong",
    "wof:placetype":"locality"
},
  "geometry": {"coordinates":[129.32611,40.76056],"type":"Point"}
}