{
  "type": "Feature",
  "properties": {
    "gn:admin1_code":"11.0",
    "gn:asciiname":"Unjung-dong",
    "gn:country_code":"KP",
    "gn:dem":228,
    "gn:feature_class":"P",
    "gn:feature_code":"PPL",
    "gn:name":"Unjung-dong",
    "gn:population":0,
    "gn:timezone":"Asia/Pyongyang",
    "iso:country":"KP",
    "name:und_x_variant":[
        "\uc6b4\uc911\ub3d9",
        "Unjung-dong"
    ],
    "wof:name":"Unjung-dong",
    "wof:placetype":"locality"
},
  "geometry": {"coordinates":[125.17083,40.22861],"type":"Point"}
}