{
  "type": "Feature",
  "properties": {
    "gn:admin1_code":"3.0",
    "gn:admin2_code":"Kow\u014fn-gun",
    "gn:asciiname":"Chungsabung-ni",
    "gn:country_code":"KP",
    "gn:dem":12,
    "gn:feature_class":"P",
    "gn:feature_code":"PPL",
    "gn:name":"Chungsabung-ni",
    "gn:population":0,
    "gn:timezone":"Asia/Pyongyang",
    "iso:country":"KP",
    "wof:name":"Chungsabung-ni",
    "wof:placetype":"locality"
},
  "geometry": {"coordinates":[127.27443999999998,39.46639],"type":"Point"}
}