{
  "type": "Feature",
  "properties": {
    "gn:admin1_code":"9.0",
    "gn:admin2_code":"Munch\u2019\u014fn-si",
    "gn:asciiname":"Hoeam-ni",
    "gn:country_code":"KP",
    "gn:dem":21,
    "gn:feature_class":"P",
    "gn:feature_code":"PPL",
    "gn:name":"Hoeam-ni",
    "gn:population":0,
    "gn:timezone":"Asia/Pyongyang",
    "iso:country":"KP",
    "name:und_x_variant":[
        "\ud68c\uc554\ub9ac"
    ],
    "wof:name":"Hoeam-ni",
    "wof:placetype":"locality"
},
  "geometry": {"coordinates":[127.31889,39.30139000000001],"type":"Point"}
}