{
  "type": "Feature",
  "properties": {
    "gn:admin1_code":"15.0",
    "gn:asciiname":"Sunghwa-dong",
    "gn:country_code":"KP",
    "gn:dem":279,
    "gn:feature_class":"P",
    "gn:feature_code":"PPL",
    "gn:name":"S\u016dnghwa-dong",
    "gn:population":0,
    "gn:timezone":"Asia/Pyongyang",
    "iso:country":"KP",
    "name:kor_x_preferred":[
        "\uc2b9\ud654\ub3d9"
    ],
    "name:kor_x_variant":[
        "S\u016dnghwa-dong"
    ],
    "wof:name":"Sunghwa-dong",
    "wof:placetype":"locality"
},
  "geometry": {"coordinates":[126.40000000000001,39.18083],"type":"Point"}
}