{
  "type": "Feature",
  "properties": {
    "gn:admin1_code":"0.0",
    "gn:asciiname":"Toldari",
    "gn:cc2":"KP",
    "gn:country_code":"KP",
    "gn:dem":6,
    "gn:feature_class":"P",
    "gn:feature_code":"PPL",
    "gn:name":"Toldari",
    "gn:population":0,
    "gn:timezone":"Asia/Pyongyang",
    "iso:country":"KP",
    "name:kor_x_preferred":[
        "\ub3cc\ub2e4\ub9ac"
    ],
    "name:und_x_variant":[
        "S\u014fkkyo",
        "Toldari"
    ],
    "wof:name":"Toldari",
    "wof:placetype":"locality"
},
  "geometry": {"coordinates":[125.56667,39.61667],"type":"Point"}
}