{
  "type": "Feature",
  "properties": {
    "gn:admin1_code":"9.0",
    "gn:asciiname":"Kwaegungjong",
    "gn:country_code":"KP",
    "gn:dem":567,
    "gn:feature_class":"P",
    "gn:feature_code":"PPL",
    "gn:name":"Kwaegungj\u014fng",
    "gn:population":0,
    "gn:timezone":"Asia/Pyongyang",
    "iso:country":"KP",
    "name:und_x_variant":[
        "\uad18\uad81\uc815",
        "Kwaegungj\u014fng"
    ],
    "wof:name":"Kwaegungjong",
    "wof:placetype":"locality"
},
  "geometry": {"coordinates":[128.05111000000002,38.61278],"type":"Point"}
}