{
  "type": "Feature",
  "properties": {
    "gn:admin1_code":"6.0",
    "gn:asciiname":"Piryong-dong",
    "gn:country_code":"KP",
    "gn:dem":13,
    "gn:feature_class":"P",
    "gn:feature_code":"PPL",
    "gn:name":"Piryong-dong",
    "gn:population":0,
    "gn:timezone":"Asia/Pyongyang",
    "iso:country":"KP",
    "wof:name":"Piryong-dong",
    "wof:placetype":"locality"
},
  "geometry": {"coordinates":[125.67222,38.03083],"type":"Point"}
}