{
  "type": "Feature",
  "properties": {
    "gn:admin1_code":"12.0",
    "gn:asciiname":"Taeryonghung-dong",
    "gn:country_code":"KP",
    "gn:dem":30,
    "gn:feature_class":"P",
    "gn:feature_code":"PPL",
    "gn:name":"Taeryongh\u016dng-dong",
    "gn:population":0,
    "gn:timezone":"Asia/Pyongyang",
    "iso:country":"KP",
    "name:und_x_variant":[
        "\ub300\ub8e1\ud765\ub3d9",
        "Taeryongh\u016dng-dong",
        "Daeryongheungdong"
    ],
    "wof:name":"Taeryonghung-dong",
    "wof:placetype":"locality"
},
  "geometry": {"coordinates":[125.72389,38.87333],"type":"Point"}
}