{
  "type": "Feature",
  "properties": {
    "gn:admin1_code":"0.0",
    "gn:asciiname":"Inhung-ni",
    "gn:country_code":"KP",
    "gn:dem":432,
    "gn:feature_class":"P",
    "gn:feature_code":"PPL",
    "gn:name":"Inh\u016dng-ni",
    "gn:population":0,
    "gn:timezone":"Asia/Pyongyang",
    "iso:country":"KP",
    "name:eng_x_preferred":[
        "Inhung"
    ],
    "name:eng_x_variant":[
        "Inhung-ni"
    ],
    "name:kor_x_preferred":[
        "\uc778\ud765\ub9ac"
    ],
    "name:und_x_variant":[
        "Inh\u016dng-ni"
    ],
    "wof:name":"Inhung",
    "wof:placetype":"locality"
},
  "geometry": {"coordinates":[126.55,39.55],"type":"Point"}
}