{
  "type": "Feature",
  "properties": {
    "gn:admin1_code":"11.0",
    "gn:asciiname":"Kol-maul",
    "gn:country_code":"KP",
    "gn:dem":16,
    "gn:feature_class":"P",
    "gn:feature_code":"PPL",
    "gn:name":"Kol-ma\u016dl",
    "gn:population":0,
    "gn:timezone":"Asia/Pyongyang",
    "iso:country":"KP",
    "name:kor_x_preferred":[
        "\uace1\ub3d9"
    ],
    "name:kor_x_variant":[
        "Kol-ma\u016dl",
        "\uace8\ub9c8\uc744"
    ],
    "name:und_x_variant":[
        "Kol-tong",
        "Kok-tong"
    ],
    "wof:name":"Kol-maul",
    "wof:placetype":"locality"
},
  "geometry": {"coordinates":[124.86261,39.7265],"type":"Point"}
}