{
  "type": "Feature",
  "properties": {
    "gn:admin1_code":"15.0",
    "gn:asciiname":"Taep'yongnae-ri",
    "gn:country_code":"KP",
    "gn:dem":58,
    "gn:feature_class":"P",
    "gn:feature_code":"PPL",
    "gn:name":"Taep\u2019y\u014fngnae-ri",
    "gn:population":0,
    "gn:timezone":"Asia/Pyongyang",
    "iso:country":"KP",
    "wof:name":"Taep'yongnae-ri",
    "wof:placetype":"locality"
},
  "geometry": {"coordinates":[125.57389000000001,38.98111],"type":"Point"}
}