{
  "type": "Feature",
  "properties": {
    "gn:admin1_code":"9.0",
    "gn:asciiname":"Pakkat'o",
    "gn:country_code":"KP",
    "gn:dem":459,
    "gn:feature_class":"P",
    "gn:feature_code":"PPL",
    "gn:name":"Pakkat\u2019\u014f",
    "gn:population":0,
    "gn:timezone":"Asia/Pyongyang",
    "iso:country":"KP",
    "name:und_x_variant":[
        "\ubc15\uac00\ud130",
        "Pakka\u2019\u014f",
        "Pakkat\u2019\u014f"
    ],
    "wof:name":"Pakkat'o",
    "wof:placetype":"locality"
},
  "geometry": {"coordinates":[127.03111,38.90611],"type":"Point"}
}