{
  "type": "Feature",
  "properties": {
    "gn:admin1_code":"11.0",
    "gn:asciiname":"Songp'yong-dong",
    "gn:country_code":"KP",
    "gn:dem":149,
    "gn:feature_class":"P",
    "gn:feature_code":"PPL",
    "gn:name":"Songp\u2019y\u014fng-dong",
    "gn:population":0,
    "gn:timezone":"Asia/Pyongyang",
    "iso:country":"KP",
    "name:und_x_variant":[
        "\uc1a1\ud3c9\ub3d9",
        "Songp\u2019y\u014fng-dong"
    ],
    "wof:name":"Songp'yong-dong",
    "wof:placetype":"locality"
},
  "geometry": {"coordinates":[125.94028,40.11194],"type":"Point"}
}