{
  "type": "Feature",
  "properties": {
    "gn:admin1_code":"17.0",
    "gn:asciiname":"Tongsosura-ri",
    "gn:country_code":"KP",
    "gn:dem":6,
    "gn:feature_class":"P",
    "gn:feature_code":"PPLL",
    "gn:name":"Tongs\u014fsura-ri",
    "gn:population":0,
    "gn:timezone":"Asia/Pyongyang",
    "iso:country":"KP",
    "name:und_x_variant":[
        "Chag\u016dns\u014fsura",
        "Sos\u014fsura",
        "Sh\u014f-seisuira",
        "\ub3d9\uc11c\uc218\ub77c\ub9ac",
        "Tongs\u014fsura-ri"
    ],
    "wof:name":"Tongsosura-ri",
    "wof:placetype":"locality"
},
  "geometry": {"coordinates":[129.87,41.81611],"type":"Point"}
}