{
  "type": "Feature",
  "properties": {
    "gn:admin1_code":"6.0",
    "gn:asciiname":"Kin'gotchi",
    "gn:country_code":"KP",
    "gn:dem":13,
    "gn:feature_class":"P",
    "gn:feature_code":"PPL",
    "gn:name":"Kin\u2019gotchi",
    "gn:population":0,
    "gn:timezone":"Asia/Pyongyang",
    "iso:country":"KP",
    "name:und_x_variant":[
        "\uae34\uacf3\uc9c0",
        "Kin\u2019gotchi"
    ],
    "wof:name":"Kin'gotchi",
    "wof:placetype":"locality"
},
  "geometry": {"coordinates":[125.68444,37.92806],"type":"Point"}
}