{
  "type": "Feature",
  "properties": {
    "gn:admin1_code":"12.0",
    "gn:admin2_code":"Sunan-guy\u014fk",
    "gn:asciiname":"Pusim-ni",
    "gn:country_code":"KP",
    "gn:dem":71,
    "gn:feature_class":"P",
    "gn:feature_code":"PPL",
    "gn:name":"Pusim-ni",
    "gn:population":0,
    "gn:timezone":"Asia/Pyongyang",
    "iso:country":"KP",
    "name:eng_x_preferred":[
        "Pusim"
    ],
    "name:eng_x_variant":[
        "Pusim-ni"
    ],
    "wof:name":"Pusim",
    "wof:placetype":"locality"
},
  "geometry": {"coordinates":[125.69389,39.26806],"type":"Point"}
}