{
  "type": "Feature",
  "properties": {
    "gn:admin1_code":"17.0",
    "gn:asciiname":"Norumegich'on",
    "gn:country_code":"KP",
    "gn:dem":549,
    "gn:feature_class":"P",
    "gn:feature_code":"PPL",
    "gn:name":"Norumegich\u2019on",
    "gn:population":0,
    "gn:timezone":"Asia/Pyongyang",
    "iso:country":"KP",
    "name:und_x_variant":[
        "Norumogi",
        "Norumok",
        "Norumegich\u2019on",
        "\ub178\ub8e8\uba54\uae30\ucd0c",
        "Nolgumok",
        "\ub180\uad6c\ubaa9",
        "\ub178\ub8e8\ubaa9"
    ],
    "wof:name":"Norumegich'on",
    "wof:placetype":"locality"
},
  "geometry": {"coordinates":[129.12556000000001,42.09197],"type":"Point"}
}