{
  "type": "Feature",
  "properties": {
    "gn:admin1_code":"9.0",
    "gn:asciiname":"Songt'al-li",
    "gn:country_code":"KP",
    "gn:dem":12,
    "gn:feature_class":"P",
    "gn:feature_code":"PPL",
    "gn:name":"Songt\u2019al-li",
    "gn:population":0,
    "gn:timezone":"Asia/Pyongyang",
    "iso:country":"KP",
    "name:kor_x_preferred":[
        "\uc1a1\ud0c4\ub9ac"
    ],
    "name:und_x_variant":[
        "Songt\u2019an-ni",
        "Songt\u2019al-li"
    ],
    "wof:name":"Songt'al-li",
    "wof:placetype":"locality"
},
  "geometry": {"coordinates":[128.27888999999999,38.65083],"type":"Point"}
}