{
  "type": "Feature",
  "properties": {
    "gn:admin1_code":"1.0",
    "gn:asciiname":"Myongdae-ri",
    "gn:country_code":"KP",
    "gn:dem":282,
    "gn:feature_class":"P",
    "gn:feature_code":"PPL",
    "gn:name":"My\u014fngdae-ri",
    "gn:population":0,
    "gn:timezone":"Asia/Pyongyang",
    "iso:country":"KP",
    "name:kor_x_preferred":[
        "\uba85\ub300\ub9ac"
    ],
    "name:und_x_variant":[
        "My\u014fngdae-dong",
        "My\u014fngdae-ri"
    ],
    "wof:name":"Myongdae-ri",
    "wof:placetype":"locality"
},
  "geometry": {"coordinates":[126.21116000000001,40.28374],"type":"Point"}
}