{
  "type": "Feature",
  "properties": {
    "gn:admin1_code":"17.0",
    "gn:asciiname":"Samhyang-ni",
    "gn:country_code":"KP",
    "gn:dem":265,
    "gn:feature_class":"P",
    "gn:feature_code":"PPL",
    "gn:name":"Samhyang-ni",
    "gn:population":0,
    "gn:timezone":"Asia/Pyongyang",
    "iso:country":"KP",
    "name:und_x_variant":[
        "\uc0bc\ud5a5\ub9ac",
        "Samhyang-ni"
    ],
    "wof:name":"Samhyang-ni",
    "wof:placetype":"locality"
},
  "geometry": {"coordinates":[129.50111000000001,41.39083],"type":"Point"}
}