{
  "type": "Feature",
  "properties": {
    "gn:admin1_code":"6.0",
    "gn:asciiname":"Kwansal-li",
    "gn:cc2":"KP",
    "gn:country_code":"KP",
    "gn:dem":25,
    "gn:feature_class":"P",
    "gn:feature_code":"PPL",
    "gn:name":"Kwansal-li",
    "gn:population":0,
    "gn:timezone":"Asia/Pyongyang",
    "iso:country":"KP",
    "name:und_x_variant":[
        "Kwansan-ni",
        "Kwansal-li"
    ],
    "wof:name":"Kwansal-li",
    "wof:placetype":"locality"
},
  "geometry": {"coordinates":[125.19361000000001,38.58694000000001],"type":"Point"}
}