{
  "type": "Feature",
  "properties": {
    "gn:admin1_code":"13.0",
    "gn:asciiname":"Chop'ung-ni",
    "gn:country_code":"KP",
    "gn:dem":1330,
    "gn:feature_class":"P",
    "gn:feature_code":"PPL",
    "gn:name":"Ch\u014fp\u2019ung-ni",
    "gn:population":0,
    "gn:timezone":"Asia/Pyongyang",
    "iso:country":"KP",
    "name:eng_x_preferred":[
        "Chop'ung"
    ],
    "name:eng_x_variant":[
        "Chop'ung-ni"
    ],
    "wof:name":"Chop'ung",
    "wof:placetype":"locality"
},
  "geometry": {"coordinates":[127.63056,41.34167],"type":"Point"}
}