{
  "type": "Feature",
  "properties": {
    "gn:admin1_code":"11.0",
    "gn:asciiname":"Yongso",
    "gn:country_code":"KP",
    "gn:dem":31,
    "gn:feature_class":"P",
    "gn:feature_code":"PPL",
    "gn:name":"Y\u014fngs\u014f",
    "gn:population":0,
    "gn:timezone":"Asia/Pyongyang",
    "iso:country":"KP",
    "name:kor_x_preferred":[
        "\uc601\uc11c"
    ],
    "name:kor_x_variant":[
        "Y\u014fngs\u014f"
    ],
    "wof:name":"Yongso",
    "wof:placetype":"locality"
},
  "geometry": {"coordinates":[124.93142,39.71797],"type":"Point"}
}