{
  "type": "Feature",
  "properties": {
    "gn:admin1_code":"3.0",
    "gn:asciiname":"Sinha-ri",
    "gn:country_code":"KP",
    "gn:dem":12,
    "gn:feature_class":"P",
    "gn:feature_code":"PPL",
    "gn:name":"Sinha-ri",
    "gn:population":0,
    "gn:timezone":"Asia/Pyongyang",
    "iso:country":"KP",
    "name:und_x_variant":[
        "\uc2e0\ud558\ub9ac",
        "Sinha-ri"
    ],
    "wof:name":"Sinha-ri",
    "wof:placetype":"locality"
},
  "geometry": {"coordinates":[127.42028000000001,39.63417000000001],"type":"Point"}
}