{
  "type": "Feature",
  "properties": {
    "gn:admin1_code":"1.0",
    "gn:asciiname":"Hakp'yongch'am",
    "gn:country_code":"KP",
    "gn:dem":930,
    "gn:feature_class":"P",
    "gn:feature_code":"PPL",
    "gn:name":"Hakp\u2019y\u014fngch\u2019am",
    "gn:population":0,
    "gn:timezone":"Asia/Pyongyang",
    "iso:country":"KP",
    "name:und_x_variant":[
        "\ud559\ud3c9\ucc38",
        "Hakp\u2019y\u014fngch\u2019am"
    ],
    "wof:name":"Hakp'yongch'am",
    "wof:placetype":"locality"
},
  "geometry": {"coordinates":[126.82556,40.37083],"type":"Point"}
}