{
  "type": "Feature",
  "properties": {
    "gn:admin1_code":"1.0",
    "gn:asciiname":"Chongch'oltok",
    "gn:country_code":"KP",
    "gn:dem":847,
    "gn:feature_class":"P",
    "gn:feature_code":"PPL",
    "gn:name":"Ch\u014fngch\u2019\u014flt\u014fk",
    "gn:population":0,
    "gn:timezone":"Asia/Pyongyang",
    "iso:country":"KP",
    "name:und_x_variant":[
        "\uc815\ucca0\ub355",
        "Ch\u014fngch\u2019\u014flt\u014fk"
    ],
    "wof:name":"Chongch'oltok",
    "wof:placetype":"locality"
},
  "geometry": {"coordinates":[126.93971999999999,41.68167],"type":"Point"}
}