{
  "type": "Feature",
  "properties": {
    "gn:admin1_code":"9.0",
    "gn:admin2_code":"P\u2019y\u014fnggang-gun",
    "gn:asciiname":"Sangbong-ni",
    "gn:country_code":"KP",
    "gn:dem":419,
    "gn:feature_class":"P",
    "gn:feature_code":"PPL",
    "gn:name":"Sangbong-ni",
    "gn:population":0,
    "gn:timezone":"Asia/Pyongyang",
    "iso:country":"KP",
    "wof:name":"Sangbong-ni",
    "wof:placetype":"locality"
},
  "geometry": {"coordinates":[127.26582999999999,38.47306],"type":"Point"}
}