{
  "type": "Feature",
  "properties": {
    "gn:admin1_code":"17.0",
    "gn:asciiname":"Ssangnyongjin",
    "gn:country_code":"KP",
    "gn:dem":5,
    "gn:feature_class":"P",
    "gn:feature_code":"PPL",
    "gn:name":"Ssangnyongjin",
    "gn:population":0,
    "gn:timezone":"Asia/Pyongyang",
    "iso:country":"KP",
    "name:und_x_variant":[
        "S\u014dry\u016bshin",
        "\uc30d\ub8e1\uc9c4"
    ],
    "wof:name":"Ssangnyongjin",
    "wof:placetype":"locality"
},
  "geometry": {"coordinates":[129.18556000000001,40.61944],"type":"Point"}
}