{
  "type": "Feature",
  "properties": {
    "gn:admin1_code":"6.0",
    "gn:asciiname":"K'un-mal",
    "gn:country_code":"KP",
    "gn:dem":40,
    "gn:feature_class":"P",
    "gn:feature_code":"PPL",
    "gn:name":"K\u2019\u016dn-mal",
    "gn:population":0,
    "gn:timezone":"Asia/Pyongyang",
    "iso:country":"KP",
    "name:kor_x_preferred":[
        "\ud070\ub9d0"
    ],
    "name:und_x_variant":[
        "K\u2019\u016dn-mol",
        "K\u2019\u016dn-mal"
    ],
    "wof:name":"K'un-mal",
    "wof:placetype":"locality"
},
  "geometry": {"coordinates":[126.03667,37.97111],"type":"Point"}
}