{
  "type": "Feature",
  "properties": {
    "gn:admin1_code":"0.0",
    "gn:asciiname":"Chaejol-li",
    "gn:country_code":"KP",
    "gn:dem":143,
    "gn:feature_class":"P",
    "gn:feature_code":"PPL",
    "gn:name":"Chaej\u014fl-li",
    "gn:population":0,
    "gn:timezone":"Asia/Pyongyang",
    "iso:country":"KP",
    "name:kor_x_preferred":[
        "\uc7ac\uc804\ub9ac"
    ],
    "name:und_x_variant":[
        "Chaej\u014fl-li",
        "Chaej\u014fn-ni"
    ],
    "wof:name":"Chaejol-li",
    "wof:placetype":"locality"
},
  "geometry": {"coordinates":[125.75,39.53333],"type":"Point"}
}