{
  "type": "Feature",
  "properties": {
    "gn:admin1_code":"3.0",
    "gn:asciiname":"Uk-kol",
    "gn:country_code":"KP",
    "gn:dem":271,
    "gn:feature_class":"P",
    "gn:feature_code":"PPL",
    "gn:name":"Uk-kol",
    "gn:population":0,
    "gn:timezone":"Asia/Pyongyang",
    "iso:country":"KP",
    "name:und_x_variant":[
        "\uc6c3\uace8",
        "Uk-kol"
    ],
    "wof:name":"Uk-kol",
    "wof:placetype":"locality"
},
  "geometry": {"coordinates":[127.97972,40.13167],"type":"Point"}
}