{
  "type": "Feature",
  "properties": {
    "gn:admin1_code":"12.0",
    "gn:asciiname":"Mangyongdae-dong",
    "gn:country_code":"KP",
    "gn:dem":53,
    "gn:feature_class":"P",
    "gn:feature_code":"PPL",
    "gn:name":"Mangy\u014fngdae-dong",
    "gn:population":0,
    "gn:timezone":"Asia/Pyongyang",
    "iso:country":"KP",
    "wof:name":"Mangyongdae-dong",
    "wof:placetype":"locality"
},
  "geometry": {"coordinates":[125.69,39.02444000000001],"type":"Point"}
}