{
  "type": "Feature",
  "properties": {
    "gn:admin1_code":"17.0",
    "gn:admin2_code":"Ch'\u014fngam-guy\u014fk, Ch'\u014fngjin-si",
    "gn:asciiname":"Anssaakp'o-dong",
    "gn:country_code":"KP",
    "gn:dem":9,
    "gn:feature_class":"P",
    "gn:feature_code":"PPL",
    "gn:name":"Anssaakp\u2019o-dong",
    "gn:population":0,
    "gn:timezone":"Asia/Pyongyang",
    "iso:country":"KP",
    "name:und_x_variant":[
        "Anssangp\u2019o-dong",
        "\uc548\uc2f8\uc545\ud3ec\ub3d9",
        "Anssaakp\u2019o-dong"
    ],
    "wof:name":"Anssaakp'o-dong",
    "wof:placetype":"locality"
},
  "geometry": {"coordinates":[129.95778000000001,41.96194000000001],"type":"Point"}
}