{
  "type": "Feature",
  "properties": {
    "gn:admin1_code":"0.0",
    "gn:asciiname":"Suunjang",
    "gn:cc2":"KP",
    "gn:country_code":"KP",
    "gn:dem":1085,
    "gn:feature_class":"P",
    "gn:feature_code":"PPL",
    "gn:name":"Suunjang",
    "gn:population":0,
    "gn:timezone":"Asia/Pyongyang",
    "iso:country":"KP",
    "name:kor_x_preferred":[
        "\uc218\uc6b4\uc7a5"
    ],
    "name:und_x_variant":[
        "Hwangchoryong",
        "Suiuns\u014d",
        "Suunjang"
    ],
    "wof:name":"Suunjang",
    "wof:placetype":"locality"
},
  "geometry": {"coordinates":[127.33333,40.23333],"type":"Point"}
}