{
  "type": "Feature",
  "properties": {
    "gn:admin1_code":"11.0",
    "gn:asciiname":"Waya-dong",
    "gn:country_code":"KP",
    "gn:dem":66,
    "gn:feature_class":"P",
    "gn:feature_code":"PPL",
    "gn:name":"Waya-dong",
    "gn:population":0,
    "gn:timezone":"Asia/Pyongyang",
    "iso:country":"KP",
    "name:kor_x_preferred":[
        "\uc640\uc57c\ub3d9"
    ],
    "wof:name":"Waya-dong",
    "wof:placetype":"locality"
},
  "geometry": {"coordinates":[125.67278,39.80861],"type":"Point"}
}