{
  "type": "Feature",
  "properties": {
    "gn:admin1_code":"17.0",
    "gn:asciiname":"Hwaam",
    "gn:country_code":"KP",
    "gn:dem":132,
    "gn:feature_class":"P",
    "gn:feature_code":"PPL",
    "gn:name":"Hwaam",
    "gn:population":0,
    "gn:timezone":"Asia/Pyongyang",
    "iso:country":"KP",
    "name:und_x_variant":[
        "\ud654\uc554",
        "Hwaam"
    ],
    "wof:name":"Hwaam",
    "wof:placetype":"locality"
},
  "geometry": {"coordinates":[129.52916999999999,41.59056],"type":"Point"}
}