{
  "type": "Feature",
  "properties": {
    "gn:admin1_code":"17.0",
    "gn:asciiname":"Chukki-dong",
    "gn:country_code":"KP",
    "gn:dem":183,
    "gn:feature_class":"P",
    "gn:feature_code":"PPL",
    "gn:name":"Chukki-dong",
    "gn:population":0,
    "gn:timezone":"Asia/Pyongyang",
    "iso:country":"KP",
    "name:und_x_variant":[
        "\uc8fd\uae30\ub3d9",
        "Chukki-dong"
    ],
    "wof:name":"Chukki-dong",
    "wof:placetype":"locality"
},
  "geometry": {"coordinates":[129.78528,42.72],"type":"Point"}
}