{
  "type": "Feature",
  "properties": {
    "gn:admin1_code":"3.0",
    "gn:asciiname":"Tonae-ri",
    "gn:country_code":"KP",
    "gn:dem":1080,
    "gn:feature_class":"P",
    "gn:feature_code":"PPL",
    "gn:name":"Tonae-ri",
    "gn:population":0,
    "gn:timezone":"Asia/Pyongyang",
    "iso:country":"KP",
    "name:und_x_variant":[
        "\ub3c4\ub0b4\ub9ac",
        "Tonae-ri"
    ],
    "wof:name":"Tonae-ri",
    "wof:placetype":"locality"
},
  "geometry": {"coordinates":[127.25028,40.37167],"type":"Point"}
}