{
  "type": "Feature",
  "properties": {
    "gn:admin1_code":"15.0",
    "gn:asciiname":"Chunghung-ni",
    "gn:country_code":"KP",
    "gn:dem":21,
    "gn:feature_class":"P",
    "gn:feature_code":"PPL",
    "gn:name":"Chungh\u016dng-ni",
    "gn:population":0,
    "gn:timezone":"Asia/Pyongyang",
    "iso:country":"KP",
    "name:eng_x_preferred":[
        "Chunghung"
    ],
    "name:eng_x_variant":[
        "Chunghung-ni"
    ],
    "wof:name":"Chunghung",
    "wof:placetype":"locality"
},
  "geometry": {"coordinates":[125.30972,39.11583],"type":"Point"}
}