{
  "type": "Feature",
  "properties": {
    "gn:admin1_code":"1.0",
    "gn:asciiname":"Ch'ubu-ri",
    "gn:country_code":"KP",
    "gn:dem":215,
    "gn:feature_class":"P",
    "gn:feature_code":"PPL",
    "gn:name":"Ch\u2019ubu-ri",
    "gn:population":0,
    "gn:timezone":"Asia/Pyongyang",
    "iso:country":"KP",
    "name:und_x_variant":[
        "\ucd94\ubd80\ub9ac",
        "Ch\u2019ubu-ri"
    ],
    "wof:name":"Ch'ubu-ri",
    "wof:placetype":"locality"
},
  "geometry": {"coordinates":[125.77028,40.5925],"type":"Point"}
}