{
  "type": "Feature",
  "properties": {
    "gn:admin1_code":"11.0",
    "gn:asciiname":"Komjang-gol",
    "gn:country_code":"KP",
    "gn:dem":23,
    "gn:feature_class":"P",
    "gn:feature_code":"PPL",
    "gn:name":"K\u014fmjang-gol",
    "gn:population":0,
    "gn:timezone":"Asia/Pyongyang",
    "iso:country":"KP",
    "name:und_x_variant":[
        "\uac80\uc7a5\uace8",
        "K\u014fmjang-gol"
    ],
    "wof:name":"Komjang-gol",
    "wof:placetype":"locality"
},
  "geometry": {"coordinates":[124.47917,40.02972000000001],"type":"Point"}
}