{
  "type": "Feature",
  "properties": {
    "gn:admin1_code":"1.0",
    "gn:asciiname":"Sahach'am",
    "gn:country_code":"KP",
    "gn:dem":404,
    "gn:feature_class":"P",
    "gn:feature_code":"PPL",
    "gn:name":"Sahach\u2019am",
    "gn:population":0,
    "gn:timezone":"Asia/Pyongyang",
    "iso:country":"KP",
    "name:und_x_variant":[
        "\uc0ac\ud558\ucc38",
        "Sahach\u2019am"
    ],
    "wof:name":"Sahach'am",
    "wof:placetype":"locality"
},
  "geometry": {"coordinates":[126.53556,40.80917],"type":"Point"}
}