{
  "type": "Feature",
  "properties": {
    "gn:admin1_code":"15.0",
    "gn:asciiname":"K'unji",
    "gn:country_code":"KP",
    "gn:dem":520,
    "gn:feature_class":"P",
    "gn:feature_code":"PPL",
    "gn:name":"K\u2019\u016dnji",
    "gn:population":0,
    "gn:timezone":"Asia/Pyongyang",
    "iso:country":"KP",
    "name:kor_x_preferred":[
        "\ud070\uc9c0"
    ],
    "name:kor_x_variant":[
        "K\u2019\u016dnji"
    ],
    "wof:name":"K'unji",
    "wof:placetype":"locality"
},
  "geometry": {"coordinates":[126.50611000000001,39.45528],"type":"Point"}
}