{
  "type": "Feature",
  "properties": {
    "gn:admin1_code":"0.0",
    "gn:asciiname":"Toktal-li",
    "gn:cc2":"KP",
    "gn:country_code":"KP",
    "gn:dem":41,
    "gn:feature_class":"P",
    "gn:feature_code":"PPL",
    "gn:name":"T\u014fktal-li",
    "gn:population":0,
    "gn:timezone":"Asia/Pyongyang",
    "iso:country":"KP",
    "name:kor_x_preferred":[
        "\ub355\ub2ec\ub9ac"
    ],
    "name:und_x_variant":[
        "Togy\u014fn-ni",
        "T\u014fktal-li"
    ],
    "wof:name":"Toktal-li",
    "wof:placetype":"locality"
},
  "geometry": {"coordinates":[125.98333,38.05],"type":"Point"}
}