{
  "type": "Feature",
  "properties": {
    "gn:admin1_code":"1.0",
    "gn:asciiname":"Usang-ni",
    "gn:country_code":"KP",
    "gn:dem":268,
    "gn:feature_class":"P",
    "gn:feature_code":"PPL",
    "gn:name":"Usang-ni",
    "gn:population":0,
    "gn:timezone":"Asia/Pyongyang",
    "iso:country":"KP",
    "name:und_x_variant":[
        "Usang-dong",
        "\uc6b0\uc0c1\ub9ac",
        "Usang-ni"
    ],
    "wof:name":"Usang-ni",
    "wof:placetype":"locality"
},
  "geometry": {"coordinates":[125.55389,40.65333],"type":"Point"}
}