{
  "type": "Feature",
  "properties": {
    "gn:admin1_code":"6.0",
    "gn:asciiname":"Kugosa-dong",
    "gn:country_code":"KP",
    "gn:dem":171,
    "gn:feature_class":"P",
    "gn:feature_code":"PPL",
    "gn:name":"Kugosa-dong",
    "gn:population":0,
    "gn:timezone":"Asia/Pyongyang",
    "iso:country":"KP",
    "wof:name":"Kugosa-dong",
    "wof:placetype":"locality"
},
  "geometry": {"coordinates":[126.13806,38.18611],"type":"Point"}
}