{
  "type": "Feature",
  "properties": {
    "gn:admin1_code":"6.0",
    "gn:asciiname":"Huihyon-dong",
    "gn:cc2":"KP",
    "gn:country_code":"KP",
    "gn:dem":30,
    "gn:feature_class":"P",
    "gn:feature_code":"PPL",
    "gn:name":"H\u016dihy\u014fn-dong",
    "gn:population":0,
    "gn:timezone":"Asia/Pyongyang",
    "iso:country":"KP",
    "name:kor_x_preferred":[
        "\ud76c\ud604\ub3d9"
    ],
    "name:und_x_variant":[
        "Kihy\u014fn-dong",
        "H\u016dihy\u014fn-dong"
    ],
    "wof:name":"Huihyon-dong",
    "wof:placetype":"locality"
},
  "geometry": {"coordinates":[125.84139,37.9825],"type":"Point"}
}