{
  "type": "Feature",
  "properties": {
    "gn:admin1_code":"6.0",
    "gn:asciiname":"Soch'on",
    "gn:country_code":"KP",
    "gn:dem":87,
    "gn:feature_class":"P",
    "gn:feature_code":"PPL",
    "gn:name":"S\u014fch\u2019on",
    "gn:population":0,
    "gn:timezone":"Asia/Pyongyang",
    "iso:country":"KP",
    "name:kor_x_preferred":[
        "\uc11c\ucd0c"
    ],
    "name:kor_x_variant":[
        "S\u014fch\u2019on"
    ],
    "wof:name":"Soch'on",
    "wof:placetype":"locality"
},
  "geometry": {"coordinates":[125.16110999999999,38.32889],"type":"Point"}
}