{
  "type": "Feature",
  "properties": {
    "gn:admin1_code":"3.0",
    "gn:asciiname":"Yondae-ri",
    "gn:country_code":"KP",
    "gn:dem":15,
    "gn:feature_class":"P",
    "gn:feature_code":"PPL",
    "gn:name":"Y\u014fndae-ri",
    "gn:population":0,
    "gn:timezone":"Asia/Pyongyang",
    "iso:country":"KP",
    "name:und_x_variant":[
        "\ub828\ub300\ub9ac",
        "Y\u014fndae-ri"
    ],
    "wof:name":"Yondae-ri",
    "wof:placetype":"locality"
},
  "geometry": {"coordinates":[128.84,40.47333],"type":"Point"}
}