{
  "type": "Feature",
  "properties": {
    "gn:admin1_code":"15.0",
    "gn:asciiname":"Sinbak-ch'on",
    "gn:country_code":"KP",
    "gn:dem":255,
    "gn:feature_class":"P",
    "gn:feature_code":"PPL",
    "gn:name":"Sinbak-ch\u2019on",
    "gn:population":0,
    "gn:timezone":"Asia/Pyongyang",
    "iso:country":"KP",
    "name:kor_x_preferred":[
        "\uc2e0\ubc15\ucd0c"
    ],
    "name:und_x_variant":[
        "Sinbak-ch\u2019on"
    ],
    "wof:name":"Sinbak-ch'on",
    "wof:placetype":"locality"
},
  "geometry": {"coordinates":[126.57417,39.42389],"type":"Point"}
}