{
  "type": "Feature",
  "properties": {
    "gn:gn_country":"KP",
    "gn:gn_fcode":"PPL",
    "gn:gn_pop":50081,
    "gn:population":50081,
    "iso:country":"KP",
    "name:unk_x_variant":[
        "Gish\u016b"
    ],
    "qs_pg:aaroncc":"KP",
    "qs_pg:gn_country":"KP",
    "qs_pg:gn_fcode":"PPL",
    "qs_pg:gn_pop":50081,
    "qs_pg:name":"\u016ciju",
    "qs_pg:photos_9r":0,
    "qs_pg:photos_sr":0,
    "qs_pg:pop_sr":8,
    "qs_pg:qs_pg_placetype":"locality",
    "wof:name":"\u016ciju",
    "wof:placetype":"locality",
    "wof:population":50081
},
  "geometry": {"coordinates":[124.53167000000001,40.19944],"type":"Point"}
}