{
  "type": "Feature",
  "properties": {
    "gn:admin1_code":"12.0",
    "gn:asciiname":"P'an'gyo-ri",
    "gn:country_code":"KP",
    "gn:dem":66,
    "gn:feature_class":"P",
    "gn:feature_code":"PPL",
    "gn:name":"P\u2019an\u2019gyo-ri",
    "gn:population":0,
    "gn:timezone":"Asia/Pyongyang",
    "iso:country":"KP",
    "name:kor_x_preferred":[
        "\ud310\uad50\ub9ac"
    ],
    "name:und_x_variant":[
        "P\u2019an\u2019gyo-dong",
        "P\u2019an\u2019gyo-ri",
        "Pangyori"
    ],
    "wof:name":"P'an'gyo-ri",
    "wof:placetype":"locality"
},
  "geometry": {"coordinates":[125.81671,39.10651],"type":"Point"}
}