{
  "type": "Feature",
  "properties": {
    "gn:admin1_code":"3.0",
    "gn:asciiname":"Chindul",
    "gn:country_code":"KP",
    "gn:dem":163,
    "gn:feature_class":"P",
    "gn:feature_code":"PPL",
    "gn:name":"Chind\u016dl",
    "gn:population":0,
    "gn:timezone":"Asia/Pyongyang",
    "iso:country":"KP",
    "name:und_x_variant":[
        "Chintul",
        "Chind\u016dl"
    ],
    "wof:name":"Chindul",
    "wof:placetype":"locality"
},
  "geometry": {"coordinates":[127.23888999999998,39.83111],"type":"Point"}
}