{
  "type": "Feature",
  "properties": {
    "gn:admin1_code":"17.0",
    "gn:asciiname":"Ch'ilban-dong",
    "gn:country_code":"KP",
    "gn:dem":42,
    "gn:feature_class":"P",
    "gn:feature_code":"PPL",
    "gn:name":"Ch\u2019ilban-dong",
    "gn:population":0,
    "gn:timezone":"Asia/Pyongyang",
    "iso:country":"KP",
    "name:und_x_variant":[
        "\uce60\ubc18\ub3d9",
        "Ch\u2019ilban-dong"
    ],
    "wof:name":"Ch'ilban-dong",
    "wof:placetype":"locality"
},
  "geometry": {"coordinates":[129.60471999999999,41.46472],"type":"Point"}
}