{
  "type": "Feature",
  "properties": {
    "gn:admin1_code":"3.0",
    "gn:asciiname":"Hungbong-ni",
    "gn:country_code":"KP",
    "gn:dem":81,
    "gn:feature_class":"P",
    "gn:feature_code":"PPL",
    "gn:name":"H\u016dngbong-ni",
    "gn:population":0,
    "gn:timezone":"Asia/Pyongyang",
    "iso:country":"KP",
    "name:und_x_variant":[
        "Hungbong",
        "\ud765\ubd09\ub9ac",
        "H\u016dngbong-ni"
    ],
    "wof:name":"Hungbong-ni",
    "wof:placetype":"locality"
},
  "geometry": {"coordinates":[127.60778000000001,40.02528],"type":"Point"}
}