{
  "type": "Feature",
  "properties": {
    "gn:admin1_code":"6.0",
    "gn:asciiname":"Yongam-ni",
    "gn:country_code":"KP",
    "gn:dem":77,
    "gn:feature_class":"P",
    "gn:feature_code":"PPL",
    "gn:name":"Yongam-ni",
    "gn:population":0,
    "gn:timezone":"Asia/Pyongyang",
    "iso:country":"KP",
    "name:eng_x_preferred":[
        "Yongam"
    ],
    "name:eng_x_variant":[
        "Yongam-ni"
    ],
    "name:kor_x_preferred":[
        "\ub8e1\uc554\ub9ac"
    ],
    "wof:name":"Yongam",
    "wof:placetype":"locality"
},
  "geometry": {"coordinates":[125.22750000000001,38.35806],"type":"Point"}
}