{
  "type": "Feature",
  "properties": {
    "gn:admin1_code":"17.0",
    "gn:asciiname":"Saebattogi",
    "gn:country_code":"KP",
    "gn:dem":541,
    "gn:feature_class":"P",
    "gn:feature_code":"PPL",
    "gn:name":"Saebatt\u014fgi",
    "gn:population":0,
    "gn:timezone":"Asia/Pyongyang",
    "iso:country":"KP",
    "wof:name":"Saebattogi",
    "wof:placetype":"locality"
},
  "geometry": {"coordinates":[129.22471999999999,41.02056],"type":"Point"}
}