{
  "type": "Feature",
  "properties": {
    "gn:admin1_code":"6.0",
    "gn:asciiname":"Koam-ch'on",
    "gn:country_code":"KP",
    "gn:dem":31,
    "gn:feature_class":"P",
    "gn:feature_code":"PPL",
    "gn:name":"Koam-ch\u2019on",
    "gn:population":0,
    "gn:timezone":"Asia/Pyongyang",
    "iso:country":"KP",
    "name:kor_x_preferred":[
        "\uace0\uc554\ucd0c"
    ],
    "name:und_x_variant":[
        "Koam-ch\u2019on"
    ],
    "wof:name":"Koam-ch'on",
    "wof:placetype":"locality"
},
  "geometry": {"coordinates":[125.40167,38.38556],"type":"Point"}
}