{
  "type": "Feature",
  "properties": {
    "gn:admin1_code":"13.0",
    "gn:asciiname":"Chung-ni",
    "gn:country_code":"KP",
    "gn:dem":937,
    "gn:feature_class":"P",
    "gn:feature_code":"PPL",
    "gn:name":"Chung-ni",
    "gn:population":0,
    "gn:timezone":"Asia/Pyongyang",
    "iso:country":"KP",
    "name:eng_x_preferred":[
        "Chung"
    ],
    "name:eng_x_variant":[
        "Chung-ni"
    ],
    "name:kor_x_preferred":[
        "\uc911\ub9ac"
    ],
    "wof:name":"Chung",
    "wof:placetype":"locality"
},
  "geometry": {"coordinates":[128.34388999999999,41.24111],"type":"Point"}
}