{
  "type": "Feature",
  "properties": {
    "gn:admin1_code":"6.0",
    "gn:asciiname":"Wonch'ol-li",
    "gn:country_code":"KP",
    "gn:dem":26,
    "gn:feature_class":"P",
    "gn:feature_code":"PPL",
    "gn:name":"W\u014fnch\u2019ol-li",
    "gn:population":0,
    "gn:timezone":"Asia/Pyongyang",
    "iso:country":"KP",
    "name:und_x_variant":[
        "W\u014fnch\u2019on-ni",
        "W\u014fnch\u2019ol-li"
    ],
    "wof:name":"Wonch'ol-li",
    "wof:placetype":"locality"
},
  "geometry": {"coordinates":[125.13833,38.10722],"type":"Point"}
}