{
  "type": "Feature",
  "properties": {
    "gn:admin1_code":"11.0",
    "gn:asciiname":"Unp'ung-ni",
    "gn:country_code":"KP",
    "gn:dem":159,
    "gn:feature_class":"P",
    "gn:feature_code":"PPL",
    "gn:name":"Unp\u2019ung-ni",
    "gn:population":0,
    "gn:timezone":"Asia/Pyongyang",
    "iso:country":"KP",
    "name:eng_x_preferred":[
        "Unp'ung"
    ],
    "name:eng_x_variant":[
        "Unp'ung-ni"
    ],
    "wof:name":"Unp'ung",
    "wof:placetype":"locality"
},
  "geometry": {"coordinates":[125.1375,39.93583],"type":"Point"}
}