{
  "type": "Feature",
  "properties": {
    "gn:admin1_code":"0.0",
    "gn:asciiname":"Hoemong-ni",
    "gn:country_code":"KP",
    "gn:dem":413,
    "gn:feature_class":"P",
    "gn:feature_code":"PPL",
    "gn:name":"Hoemong-ni",
    "gn:population":0,
    "gn:timezone":"Asia/Pyongyang",
    "iso:country":"KP",
    "name:eng_x_preferred":[
        "Hoemong"
    ],
    "name:eng_x_variant":[
        "Hoemong-ni"
    ],
    "name:kor_x_preferred":[
        "\ud68c\ubaa9\ub9ac"
    ],
    "wof:name":"Hoemong",
    "wof:placetype":"locality"
},
  "geometry": {"coordinates":[126.00011000000001,40.3304],"type":"Point"}
}