{
  "type": "Feature",
  "properties": {
    "gn:admin1_code":"6.0",
    "gn:asciiname":"Soppat",
    "gn:country_code":"KP",
    "gn:dem":61,
    "gn:feature_class":"P",
    "gn:feature_code":"PPL",
    "gn:name":"S\u014fppat",
    "gn:population":0,
    "gn:timezone":"Asia/Pyongyang",
    "iso:country":"KP",
    "name:kor_x_preferred":[
        "\uc12f\ubc2d"
    ],
    "name:und_x_variant":[
        "S\u014fppat"
    ],
    "wof:name":"Soppat",
    "wof:placetype":"locality"
},
  "geometry": {"coordinates":[126.28610999999999,38.07889],"type":"Point"}
}