{
  "type": "Feature",
  "properties": {
    "gn:admin1_code":"6.0",
    "gn:asciiname":"Changjae-dong",
    "gn:country_code":"KP",
    "gn:dem":70,
    "gn:feature_class":"P",
    "gn:feature_code":"PPL",
    "gn:name":"Changjae-dong",
    "gn:population":0,
    "gn:timezone":"Asia/Pyongyang",
    "iso:country":"KP",
    "name:kor_x_preferred":[
        "\uc7a5\uc7ac\ub3d9"
    ],
    "wof:name":"Changjae-dong",
    "wof:placetype":"locality"
},
  "geometry": {"coordinates":[126.17610999999999,38.18083],"type":"Point"}
}