{
  "type": "Feature",
  "properties": {
    "gn:admin1_code":"6.0",
    "gn:asciiname":"Polgogae",
    "gn:country_code":"KP",
    "gn:dem":143,
    "gn:feature_class":"P",
    "gn:feature_code":"PPL",
    "gn:name":"P\u014flgogae",
    "gn:population":0,
    "gn:timezone":"Asia/Pyongyang",
    "iso:country":"KP",
    "name:und_x_variant":[
        "\ubc8c\uace0\uac1c",
        "P\u014flgogae"
    ],
    "wof:name":"Polgogae",
    "wof:placetype":"locality"
},
  "geometry": {"coordinates":[126.53389,38.0575],"type":"Point"}
}