{
  "type": "Feature",
  "properties": {
    "gn:admin1_code":"6.0",
    "gn:asciiname":"Hadae-ch'on",
    "gn:country_code":"KP",
    "gn:dem":16,
    "gn:feature_class":"P",
    "gn:feature_code":"PPL",
    "gn:name":"Hadae-ch\u2019on",
    "gn:population":0,
    "gn:timezone":"Asia/Pyongyang",
    "iso:country":"KP",
    "name:kor_x_preferred":[
        "\ud558\ub300\ucd0c"
    ],
    "name:und_x_variant":[
        "Hadae-ch\u2019on"
    ],
    "wof:name":"Hadae-ch'on",
    "wof:placetype":"locality"
},
  "geometry": {"coordinates":[125.14221999999999,38.54111],"type":"Point"}
}