{
  "type": "Feature",
  "properties": {
    "gn:admin1_code":"3.0",
    "gn:asciiname":"An'gi-ri",
    "gn:country_code":"KP",
    "gn:dem":871,
    "gn:feature_class":"P",
    "gn:feature_code":"PPL",
    "gn:name":"An\u2019gi-ri",
    "gn:population":0,
    "gn:timezone":"Asia/Pyongyang",
    "iso:country":"KP",
    "name:kor_x_preferred":[
        "\uc548\uae30\ub9ac"
    ],
    "name:und_x_variant":[
        "An\u2019gi-ri"
    ],
    "wof:name":"An'gi-ri",
    "wof:placetype":"locality"
},
  "geometry": {"coordinates":[127.57642,41.01752000000001],"type":"Point"}
}