{
  "type": "Feature",
  "properties": {
    "gn:admin1_code":"3.0",
    "gn:asciiname":"Hungnam-ni",
    "gn:country_code":"KP",
    "gn:dem":80,
    "gn:feature_class":"P",
    "gn:feature_code":"PPL",
    "gn:name":"H\u016dngnam-ni",
    "gn:population":0,
    "gn:timezone":"Asia/Pyongyang",
    "iso:country":"KP",
    "name:und_x_variant":[
        "\ud765\ub0a8\ub9ac",
        "H\u016dngnam-ni"
    ],
    "wof:name":"Hungnam-ni",
    "wof:placetype":"locality"
},
  "geometry": {"coordinates":[127.505,40.06722],"type":"Point"}
}