{
  "type": "Feature",
  "properties": {
    "gn:admin1_code":"1.0",
    "gn:asciiname":"Muson-dong",
    "gn:country_code":"KP",
    "gn:dem":551,
    "gn:feature_class":"P",
    "gn:feature_code":"PPL",
    "gn:name":"Mus\u014fn-dong",
    "gn:population":0,
    "gn:timezone":"Asia/Pyongyang",
    "iso:country":"KP",
    "name:und_x_variant":[
        "\ubb34\uc120\ub3d9",
        "Mus\u014fn-dong"
    ],
    "wof:name":"Muson-dong",
    "wof:placetype":"locality"
},
  "geometry": {"coordinates":[126.61972,41.26611],"type":"Point"}
}