{
  "type": "Feature",
  "properties": {
    "gn:admin1_code":"15.0",
    "gn:asciiname":"Yongyon-dong",
    "gn:country_code":"KP",
    "gn:dem":326,
    "gn:feature_class":"P",
    "gn:feature_code":"PPL",
    "gn:name":"Yongy\u014fn-dong",
    "gn:population":0,
    "gn:timezone":"Asia/Pyongyang",
    "iso:country":"KP",
    "name:kor_x_preferred":[
        "\uc6a9\uc5f0\ub3d9"
    ],
    "name:und_x_variant":[
        "Yongy\u014fn-dong"
    ],
    "wof:name":"Yongyon-dong",
    "wof:placetype":"locality"
},
  "geometry": {"coordinates":[126.65139000000001,39.41889000000001],"type":"Point"}
}