{
  "type": "Feature",
  "properties": {
    "gn:admin1_code":"3.0",
    "gn:asciiname":"Kojung-gol",
    "gn:country_code":"KP",
    "gn:dem":340,
    "gn:feature_class":"P",
    "gn:feature_code":"PPL",
    "gn:name":"K\u014fjung-gol",
    "gn:population":0,
    "gn:timezone":"Asia/Pyongyang",
    "iso:country":"KP",
    "name:kor_x_preferred":[
        "\uac70\uc911\uace8"
    ],
    "name:kor_x_variant":[
        "K\u014fjung-gol"
    ],
    "name:und_x_variant":[
        "K\u014fjung-kol"
    ],
    "wof:name":"Kojung-gol",
    "wof:placetype":"locality"
},
  "geometry": {"coordinates":[126.98860999999999,39.28972],"type":"Point"}
}