{
  "type": "Feature",
  "properties": {
    "gn:admin1_code":"17.0",
    "gn:asciiname":"Soch'on-dong",
    "gn:country_code":"KP",
    "gn:dem":233,
    "gn:feature_class":"P",
    "gn:feature_code":"PPL",
    "gn:name":"S\u014fch\u2019on-dong",
    "gn:population":0,
    "gn:timezone":"Asia/Pyongyang",
    "iso:country":"KP",
    "name:und_x_variant":[
        "\uc11c\ucd0c\ub3d9",
        "S\u014fch\u2019on-dong"
    ],
    "wof:name":"Soch'on-dong",
    "wof:placetype":"locality"
},
  "geometry": {"coordinates":[129.70278000000002,42.42111],"type":"Point"}
}