{
  "type": "Feature",
  "properties": {
    "gn:admin1_code":"3.0",
    "gn:asciiname":"Inhwa-ri",
    "gn:country_code":"KP",
    "gn:dem":176,
    "gn:feature_class":"P",
    "gn:feature_code":"PPL",
    "gn:name":"Inhwa-ri",
    "gn:population":0,
    "gn:timezone":"Asia/Pyongyang",
    "iso:country":"KP",
    "name:kor_x_preferred":[
        "\uc778\ud654\ub9ac"
    ],
    "name:und_x_variant":[
        "Inha-ri",
        "Inhwa-ri"
    ],
    "wof:name":"Inhwa-ri",
    "wof:placetype":"locality"
},
  "geometry": {"coordinates":[127.0275,39.66],"type":"Point"}
}