{
  "type": "Feature",
  "properties": {
    "gn:admin1_code":"1.0",
    "gn:asciiname":"T'ogolch'ang",
    "gn:country_code":"KP",
    "gn:dem":481,
    "gn:feature_class":"P",
    "gn:feature_code":"PPL",
    "gn:name":"T\u2019ogolch\u2019ang",
    "gn:population":0,
    "gn:timezone":"Asia/Pyongyang",
    "iso:country":"KP",
    "name:und_x_variant":[
        "\ud1a0\uace8\ucc3d",
        "T\u2019ogolch\u2019ang"
    ],
    "wof:name":"T'ogolch'ang",
    "wof:placetype":"locality"
},
  "geometry": {"coordinates":[126.97221999999999,41.71667],"type":"Point"}
}