{
  "type": "Feature",
  "properties": {
    "gn:admin1_code":"11.0",
    "gn:asciiname":"Yujong",
    "gn:country_code":"KP",
    "gn:dem":7,
    "gn:feature_class":"P",
    "gn:feature_code":"PPL",
    "gn:name":"Yuj\u014fng",
    "gn:population":0,
    "gn:timezone":"Asia/Pyongyang",
    "iso:country":"KP",
    "name:und_x_variant":[
        "\uc720\uc815",
        "Yuj\u014fng"
    ],
    "wof:name":"Yujong",
    "wof:placetype":"locality"
},
  "geometry": {"coordinates":[124.38611000000002,39.92806],"type":"Point"}
}