{
  "type": "Feature",
  "properties": {
    "gn:admin1_code":"15.0",
    "gn:asciiname":"Sangch'on-dong",
    "gn:country_code":"KP",
    "gn:dem":94,
    "gn:feature_class":"P",
    "gn:feature_code":"PPL",
    "gn:name":"Sangch\u2019\u014fn-dong",
    "gn:population":0,
    "gn:timezone":"Asia/Pyongyang",
    "iso:country":"KP",
    "name:kor_x_preferred":[
        "\uc0c1\ucc9c\ub3d9"
    ],
    "name:und_x_variant":[
        "Sangch\u2019\u014fn-dong"
    ],
    "wof:name":"Sangch'on-dong",
    "wof:placetype":"locality"
},
  "geometry": {"coordinates":[126.14722,39.42361],"type":"Point"}
}