{
  "type": "Feature",
  "properties": {
    "gn:admin1_code":"17.0",
    "gn:asciiname":"Changp'o",
    "gn:country_code":"KP",
    "gn:dem":254,
    "gn:feature_class":"P",
    "gn:feature_code":"PPL",
    "gn:name":"Changp\u2019o",
    "gn:population":0,
    "gn:timezone":"Asia/Pyongyang",
    "iso:country":"KP",
    "name:und_x_variant":[
        "\uc7a5\ud3ec",
        "Changp\u2019o"
    ],
    "wof:name":"Changp'o",
    "wof:placetype":"locality"
},
  "geometry": {"coordinates":[129.94417000000001,42.78194000000001],"type":"Point"}
}