{
  "type": "Feature",
  "properties": {
    "gn:admin1_code":"7.0",
    "gn:asciiname":"P'yonghwa-ri",
    "gn:country_code":"KP",
    "gn:dem":109,
    "gn:feature_class":"P",
    "gn:feature_code":"PPL",
    "gn:name":"P\u2019y\u014fnghwa-ri",
    "gn:population":0,
    "gn:timezone":"Asia/Pyongyang",
    "iso:country":"KP",
    "name:und_x_variant":[
        "\ud3c9\ud654\ub9ac",
        "P\u2019y\u014fnghwa-ri"
    ],
    "wof:name":"P'yonghwa-ri",
    "wof:placetype":"locality"
},
  "geometry": {"coordinates":[126.12917,38.32417],"type":"Point"}
}