{
  "type": "Feature",
  "properties": {
    "gn:admin1_code":"3.0",
    "gn:asciiname":"P'yongp'o",
    "gn:country_code":"KP",
    "gn:dem":78,
    "gn:feature_class":"P",
    "gn:feature_code":"PPL",
    "gn:name":"P\u2019y\u014fngp\u2019o",
    "gn:population":0,
    "gn:timezone":"Asia/Pyongyang",
    "iso:country":"KP",
    "name:und_x_variant":[
        "Sopo-ri",
        "Saiho-ri",
        "P\u2019y\u014fngp\u2019o",
        "\ud3c9\ud3ec"
    ],
    "wof:name":"P'yongp'o",
    "wof:placetype":"locality"
},
  "geometry": {"coordinates":[128.12497999999999,40.11755],"type":"Point"}
}