{
  "type": "Feature",
  "properties": {
    "gn:admin1_code":"1.0",
    "gn:asciiname":"Naehung-dong",
    "gn:country_code":"KP",
    "gn:dem":215,
    "gn:feature_class":"P",
    "gn:feature_code":"PPL",
    "gn:name":"Naeh\u016dng-dong",
    "gn:population":0,
    "gn:timezone":"Asia/Pyongyang",
    "iso:country":"KP",
    "name:und_x_variant":[
        "\ub0b4\ud765\ub3d9",
        "Naeh\u016dng-dong"
    ],
    "wof:name":"Naehung-dong",
    "wof:placetype":"locality"
},
  "geometry": {"coordinates":[125.74056000000002,40.52833],"type":"Point"}
}