{
  "type": "Feature",
  "properties": {
    "gn:admin1_code":"17.0",
    "gn:asciiname":"An'gyo",
    "gn:country_code":"KP",
    "gn:dem":4,
    "gn:feature_class":"P",
    "gn:feature_code":"PPL",
    "gn:name":"An\u2019gyo",
    "gn:population":0,
    "gn:timezone":"Asia/Pyongyang",
    "iso:country":"KP",
    "name:und_x_variant":[
        "\uc548\uad50",
        "An\u2019gyo"
    ],
    "wof:name":"An'gyo",
    "wof:placetype":"locality"
},
  "geometry": {"coordinates":[129.73083,41.37167],"type":"Point"}
}