{
  "type": "Feature",
  "properties": {
    "gn:admin1_code":"17.0",
    "gn:asciiname":"Sogu-dong",
    "gn:country_code":"KP",
    "gn:dem":171,
    "gn:feature_class":"P",
    "gn:feature_code":"PPL",
    "gn:name":"S\u014fgu-dong",
    "gn:population":0,
    "gn:timezone":"Asia/Pyongyang",
    "iso:country":"KP",
    "name:und_x_variant":[
        "\uc11d\uc6b0\ub3d9",
        "S\u014fgu-dong"
    ],
    "wof:name":"Sogu-dong",
    "wof:placetype":"locality"
},
  "geometry": {"coordinates":[129.47861,41.16611],"type":"Point"}
}