{
  "type": "Feature",
  "properties": {
    "gn:admin1_code":"7.0",
    "gn:asciiname":"Hongmyo-ri",
    "gn:country_code":"KP",
    "gn:dem":94,
    "gn:feature_class":"P",
    "gn:feature_code":"PPL",
    "gn:name":"Hongmyo-ri",
    "gn:population":0,
    "gn:timezone":"Asia/Pyongyang",
    "iso:country":"KP",
    "name:kor_x_preferred":[
        "\ud64d\ubb18\ub9ac"
    ],
    "wof:name":"Hongmyo-ri",
    "wof:placetype":"locality"
},
  "geometry": {"coordinates":[126.77611,38.30861],"type":"Point"}
}