{
  "type": "Feature",
  "properties": {
    "gn:admin1_code":"15.0",
    "gn:admin2_code":"S\u014fngch'\u014fn-gun",
    "gn:asciiname":"Amp'o-ri",
    "gn:country_code":"KP",
    "gn:dem":78,
    "gn:feature_class":"P",
    "gn:feature_code":"PPL",
    "gn:name":"Amp\u2019o-ri",
    "gn:population":0,
    "gn:timezone":"Asia/Pyongyang",
    "iso:country":"KP",
    "name:kor_x_preferred":[
        "\uc554\ud3ec\ub9ac"
    ],
    "name:und_x_variant":[
        "Amp\u2019o-ri"
    ],
    "wof:name":"Amp'o-ri",
    "wof:placetype":"locality"
},
  "geometry": {"coordinates":[126.24778000000001,39.23583],"type":"Point"}
}