{
  "type": "Feature",
  "properties": {
    "gn:admin1_code":"6.0",
    "gn:asciiname":"Yongam-dong",
    "gn:country_code":"KP",
    "gn:dem":13,
    "gn:feature_class":"P",
    "gn:feature_code":"PPL",
    "gn:name":"Yongam-dong",
    "gn:population":0,
    "gn:timezone":"Asia/Pyongyang",
    "iso:country":"KP",
    "name:kor_x_preferred":[
        "\uc6a9\uc554\ub3d9"
    ],
    "wof:name":"Yongam-dong",
    "wof:placetype":"locality"
},
  "geometry": {"coordinates":[125.47360999999999,38.67139],"type":"Point"}
}