{
  "type": "Feature",
  "properties": {
    "gn:admin1_code":"3.0",
    "gn:asciiname":"Hojung-ni",
    "gn:country_code":"KP",
    "gn:dem":21,
    "gn:feature_class":"P",
    "gn:feature_code":"PPL",
    "gn:name":"Hojung-ni",
    "gn:population":0,
    "gn:timezone":"Asia/Pyongyang",
    "iso:country":"KP",
    "name:und_x_variant":[
        "\ud638\uc911\ub9ac",
        "Hojung-ni"
    ],
    "wof:name":"Hojung-ni",
    "wof:placetype":"locality"
},
  "geometry": {"coordinates":[127.41333,39.73611],"type":"Point"}
}