{
  "type": "Feature",
  "properties": {
    "gn:admin1_code":"15.0",
    "gn:admin2_code":"Mund\u014fk-kun",
    "gn:asciiname":"T'ogyo-ri",
    "gn:country_code":"KP",
    "gn:dem":69,
    "gn:feature_class":"P",
    "gn:feature_code":"PPL",
    "gn:name":"T\u2019ogyo-ri",
    "gn:population":0,
    "gn:timezone":"Asia/Pyongyang",
    "iso:country":"KP",
    "wof:name":"T'ogyo-ri",
    "wof:placetype":"locality"
},
  "geometry": {"coordinates":[125.61221999999999,39.49056],"type":"Point"}
}