{
  "type": "Feature",
  "properties": {
    "gn:admin1_code":"9.0",
    "gn:asciiname":"Pongbau",
    "gn:country_code":"KP",
    "gn:dem":201,
    "gn:feature_class":"P",
    "gn:feature_code":"PPL",
    "gn:name":"Pongbau",
    "gn:population":0,
    "gn:timezone":"Asia/Pyongyang",
    "iso:country":"KP",
    "name:und_x_variant":[
        "Pongam",
        "Pongbawi",
        "\ubd09\ubc14\uc6b0",
        "P\u014flbau",
        "Pongbau"
    ],
    "wof:name":"Pongbau",
    "wof:placetype":"locality"
},
  "geometry": {"coordinates":[127.03417,38.78917],"type":"Point"}
}