{
  "type": "Feature",
  "properties": {
    "gn:admin1_code":"11.0",
    "gn:asciiname":"Unhung-dong",
    "gn:country_code":"KP",
    "gn:dem":25,
    "gn:feature_class":"P",
    "gn:feature_code":"PPL",
    "gn:name":"Unh\u016dng-dong",
    "gn:population":0,
    "gn:timezone":"Asia/Pyongyang",
    "iso:country":"KP",
    "name:kor_x_preferred":[
        "\uc6b4\ud765\ub3d9"
    ],
    "name:kor_x_variant":[
        "Unh\u016dng-dong"
    ],
    "wof:name":"Unhung-dong",
    "wof:placetype":"locality"
},
  "geometry": {"coordinates":[125.39139,39.60556],"type":"Point"}
}