{
  "type": "Feature",
  "properties": {
    "gn:admin1_code":"9.0",
    "gn:asciiname":"Sagul-li",
    "gn:country_code":"KP",
    "gn:dem":719,
    "gn:feature_class":"P",
    "gn:feature_code":"PPL",
    "gn:name":"Sag\u016dl-li",
    "gn:population":0,
    "gn:timezone":"Asia/Pyongyang",
    "iso:country":"KP",
    "name:und_x_variant":[
        "\uc0ac\uadfc\ub9ac",
        "Sag\u016dl-li"
    ],
    "wof:name":"Sagul-li",
    "wof:placetype":"locality"
},
  "geometry": {"coordinates":[127.53943999999998,38.88722],"type":"Point"}
}