{
  "type": "Feature",
  "properties": {
    "gn:admin1_code":"1.0",
    "gn:asciiname":"Paekse-ri",
    "gn:country_code":"KP",
    "gn:dem":274,
    "gn:feature_class":"P",
    "gn:feature_code":"PPL",
    "gn:name":"Paekse-ri",
    "gn:population":0,
    "gn:timezone":"Asia/Pyongyang",
    "iso:country":"KP",
    "name:und_x_variant":[
        "\ubc31\uc138\ub9ac",
        "Paekse-ri"
    ],
    "wof:name":"Paekse-ri",
    "wof:placetype":"locality"
},
  "geometry": {"coordinates":[125.6675,40.49667],"type":"Point"}
}