{
  "type": "Feature",
  "properties": {
    "gn:admin1_code":"6.0",
    "gn:asciiname":"Hyu-dong",
    "gn:country_code":"KP",
    "gn:dem":6,
    "gn:feature_class":"P",
    "gn:feature_code":"PPL",
    "gn:name":"Hyu-dong",
    "gn:population":0,
    "gn:timezone":"Asia/Pyongyang",
    "iso:country":"KP",
    "name:kor_x_preferred":[
        "\ud734\ub3d9"
    ],
    "wof:name":"Hyu-dong",
    "wof:placetype":"locality"
},
  "geometry": {"coordinates":[125.02722,37.94389],"type":"Point"}
}