{
  "type": "Feature",
  "properties": {
    "gn:admin1_code":"15.0",
    "gn:asciiname":"Ko-dong",
    "gn:country_code":"KP",
    "gn:dem":151,
    "gn:feature_class":"P",
    "gn:feature_code":"PPL",
    "gn:name":"Ko-dong",
    "gn:population":0,
    "gn:timezone":"Asia/Pyongyang",
    "iso:country":"KP",
    "name:kor_x_preferred":[
        "\uace0\ub3d9"
    ],
    "wof:name":"Ko-dong",
    "wof:placetype":"locality"
},
  "geometry": {"coordinates":[126.19110999999999,39.39556],"type":"Point"}
}