{
  "type": "Feature",
  "properties": {
    "gn:admin1_code":"12.0",
    "gn:asciiname":"Changgae-dong",
    "gn:country_code":"KP",
    "gn:dem":58,
    "gn:feature_class":"P",
    "gn:feature_code":"PPL",
    "gn:name":"Changgae-dong",
    "gn:population":0,
    "gn:timezone":"Asia/Pyongyang",
    "iso:country":"KP",
    "name:kor_x_preferred":[
        "\uc7a5\uac1c\ub3d9"
    ],
    "name:und_x_variant":[
        "Janggaedong"
    ],
    "wof:name":"Changgae-dong",
    "wof:placetype":"locality"
},
  "geometry": {"coordinates":[125.77736000000002,39.17814],"type":"Point"}
}