{
  "type": "Feature",
  "properties": {
    "gn:admin1_code":"11.0",
    "gn:asciiname":"P'yongji-ri",
    "gn:country_code":"KP",
    "gn:dem":103,
    "gn:feature_class":"P",
    "gn:feature_code":"PPL",
    "gn:name":"P\u2019y\u014fngji-ri",
    "gn:population":0,
    "gn:timezone":"Asia/Pyongyang",
    "iso:country":"KP",
    "name:kor_x_preferred":[
        "P\u2019y\u014fngji-ri"
    ],
    "name:kor_x_variant":[
        "\ud3c9\uc9c0\ub9ac"
    ],
    "wof:name":"P'yongji-ri",
    "wof:placetype":"locality"
},
  "geometry": {"coordinates":[125.07250000000001,39.83583],"type":"Point"}
}