{
  "type": "Feature",
  "properties": {
    "gn:admin1_code":"18.0",
    "gn:admin2_code":"S\u014fnbong-gun",
    "gn:asciiname":"Wolp'o",
    "gn:country_code":"KP",
    "gn:dem":33,
    "gn:feature_class":"P",
    "gn:feature_code":"PPL",
    "gn:name":"W\u014flp\u2019o",
    "gn:population":0,
    "gn:timezone":"Asia/Pyongyang",
    "iso:country":"KP",
    "name:und_x_variant":[
        "\uc6d4\ud3ec",
        "W\u014flp\u2019o",
        "Wolpo"
    ],
    "wof:name":"Wolp'o",
    "wof:placetype":"locality"
},
  "geometry": {"coordinates":[130.47957,42.35464],"type":"Point"}
}