{
  "type": "Feature",
  "properties": {
    "gn:admin1_code":"6.0",
    "gn:asciiname":"Tobong-ni",
    "gn:country_code":"KP",
    "gn:dem":112,
    "gn:feature_class":"P",
    "gn:feature_code":"PPL",
    "gn:name":"Tobong-ni",
    "gn:population":0,
    "gn:timezone":"Asia/Pyongyang",
    "iso:country":"KP",
    "name:kor_x_preferred":[
        "\ub3c4\ubd09\ub9ac"
    ],
    "wof:name":"Tobong-ni",
    "wof:placetype":"locality"
},
  "geometry": {"coordinates":[125.32111,38.27417],"type":"Point"}
}