{
  "type": "Feature",
  "properties": {
    "gn:admin1_code":"11.0",
    "gn:asciiname":"Hoemong-ni",
    "gn:country_code":"KP",
    "gn:dem":43,
    "gn:feature_class":"P",
    "gn:feature_code":"PPL",
    "gn:name":"Hoemong-ni",
    "gn:population":0,
    "gn:timezone":"Asia/Pyongyang",
    "iso:country":"KP",
    "name:eng_x_preferred":[
        "Hoemong"
    ],
    "name:eng_x_variant":[
        "Hoemong-ni"
    ],
    "name:und_x_variant":[
        "\ud68c\ubaa9\ub9ac",
        "Hoemong-ni"
    ],
    "wof:name":"Hoemong",
    "wof:placetype":"locality"
},
  "geometry": {"coordinates":[124.64861000000001,39.87722],"type":"Point"}
}