{
  "type": "Feature",
  "properties": {
    "gn:admin1_code":"12.0",
    "gn:asciiname":"Araekkumsumul",
    "gn:country_code":"KP",
    "gn:dem":18,
    "gn:feature_class":"P",
    "gn:feature_code":"PPL",
    "gn:name":"Araekk\u016dmsumul",
    "gn:population":0,
    "gn:timezone":"Asia/Pyongyang",
    "iso:country":"KP",
    "name:und_x_variant":[
        "Hag\u016dmsuj\u014fng",
        "\uc544\ub7ab\uae08\uc218\ubb3c",
        "Araekk\u016dmsumul",
        "Araetgeumsumul"
    ],
    "wof:name":"Araekkumsumul",
    "wof:placetype":"locality"
},
  "geometry": {"coordinates":[125.74250000000001,38.88056],"type":"Point"}
}