{
  "type": "Feature",
  "properties": {
    "gn:admin1_code":"6.0",
    "gn:admin2_code":"Ongjin-gun",
    "gn:asciiname":"Yongch'ol-li",
    "gn:country_code":"KP",
    "gn:dem":14,
    "gn:feature_class":"P",
    "gn:feature_code":"PPL",
    "gn:name":"Yongch\u2019\u014fl-li",
    "gn:population":0,
    "gn:timezone":"Asia/Pyongyang",
    "iso:country":"KP",
    "name:und_x_variant":[
        "Yongch\u2019\u014fn-dong",
        "Yongch\u2019\u014fn-ni",
        "\ub8e1\ucc9c\ub9ac",
        "Yongch\u2019\u014fl-li"
    ],
    "wof:name":"Yongch'ol-li",
    "wof:placetype":"locality"
},
  "geometry": {"coordinates":[125.11499999999999,37.96028],"type":"Point"}
}