{
  "type": "Feature",
  "properties": {
    "gn:admin1_code":"6.0",
    "gn:asciiname":"Sanhangp'o",
    "gn:country_code":"KP",
    "gn:dem":14,
    "gn:feature_class":"P",
    "gn:feature_code":"PPL",
    "gn:name":"Sanhangp\u2019o",
    "gn:population":0,
    "gn:timezone":"Asia/Pyongyang",
    "iso:country":"KP",
    "name:kor_x_preferred":[
        "\uc0b0\ud56d\ud3ec"
    ],
    "name:kor_x_variant":[
        "Sanhangp\u2019o"
    ],
    "name:und_x_variant":[
        "San\u2019gongp\u2019o"
    ],
    "wof:name":"Sanhangp'o",
    "wof:placetype":"locality"
},
  "geometry": {"coordinates":[125.06278,37.98389],"type":"Point"}
}