{
  "type": "Feature",
  "properties": {
    "gn:admin1_code":"9.0",
    "gn:asciiname":"Sindong-ni",
    "gn:country_code":"KP",
    "gn:dem":604,
    "gn:feature_class":"P",
    "gn:feature_code":"PPL",
    "gn:name":"Sindong-ni",
    "gn:population":0,
    "gn:timezone":"Asia/Pyongyang",
    "iso:country":"KP",
    "name:eng_x_preferred":[
        "Sindong"
    ],
    "name:eng_x_variant":[
        "Sindong-ni"
    ],
    "name:kor_x_preferred":[
        "\uc2e0\ub3d9\ub9ac"
    ],
    "wof:name":"Sindong",
    "wof:placetype":"locality"
},
  "geometry": {"coordinates":[127.2175,38.82],"type":"Point"}
}