{
  "type": "Feature",
  "properties": {
    "gn:admin1_code":"1.0",
    "gn:asciiname":"P'inamuk-kol",
    "gn:country_code":"KP",
    "gn:dem":191,
    "gn:feature_class":"P",
    "gn:feature_code":"PPL",
    "gn:name":"P\u2019inamuk-kol",
    "gn:population":0,
    "gn:timezone":"Asia/Pyongyang",
    "iso:country":"KP",
    "name:und_x_variant":[
        "\ud53c\ub098\ubb47\uace8",
        "P\u2019inamuk-kol"
    ],
    "wof:name":"P'inamuk-kol",
    "wof:placetype":"locality"
},
  "geometry": {"coordinates":[125.68722,40.82],"type":"Point"}
}