{
  "type": "Feature",
  "properties": {
    "gn:admin1_code":"3.0",
    "gn:asciiname":"Kuok-ch'on",
    "gn:country_code":"KP",
    "gn:dem":38,
    "gn:feature_class":"P",
    "gn:feature_code":"PPL",
    "gn:name":"Ku\u014fk-ch\u2019on",
    "gn:population":0,
    "gn:timezone":"Asia/Pyongyang",
    "iso:country":"KP",
    "name:und_x_variant":[
        "\uad6c\uc5b5\ucd0c",
        "Ku\u014fk-ch\u2019on"
    ],
    "wof:name":"Kuok-ch'on",
    "wof:placetype":"locality"
},
  "geometry": {"coordinates":[128.83667,40.52778],"type":"Point"}
}