{
  "type": "Feature",
  "properties": {
    "gn:admin1_code":"11.0",
    "gn:asciiname":"Samnyong-dong",
    "gn:country_code":"KP",
    "gn:dem":7,
    "gn:feature_class":"P",
    "gn:feature_code":"PPL",
    "gn:name":"Samnyong-dong",
    "gn:population":0,
    "gn:timezone":"Asia/Pyongyang",
    "iso:country":"KP",
    "name:und_x_variant":[
        "\uc0bc\ub8e1\ub3d9",
        "Samnyong-dong"
    ],
    "wof:name":"Samnyong-dong",
    "wof:placetype":"locality"
},
  "geometry": {"coordinates":[124.45,39.88694],"type":"Point"}
}