{
  "type": "Feature",
  "properties": {
    "gn:admin1_code":"6.0",
    "gn:admin2_code":"1876380",
    "gn:asciiname":"Ongnyon-gol",
    "gn:country_code":"KP",
    "gn:dem":33,
    "gn:feature_class":"P",
    "gn:feature_code":"PPL",
    "gn:name":"Ongny\u014fn-gol",
    "gn:population":0,
    "gn:timezone":"Asia/Pyongyang",
    "iso:country":"KP",
    "name:und_x_variant":[
        "Ongny\u014fn-dong",
        "Ongny\u014fn-gol"
    ],
    "wof:name":"Ongnyon-gol",
    "wof:placetype":"locality"
},
  "geometry": {"coordinates":[126.50388999999998,37.93278],"type":"Point"}
}