{
  "type": "Feature",
  "properties": {
    "gn:admin1_code":"9.0",
    "gn:asciiname":"Sangsulbi",
    "gn:country_code":"KP",
    "gn:dem":519,
    "gn:feature_class":"P",
    "gn:feature_code":"PPL",
    "gn:name":"Sangsulbi",
    "gn:population":0,
    "gn:timezone":"Asia/Pyongyang",
    "iso:country":"KP",
    "name:kor_x_preferred":[
        "\uc0c1\uc220\ube44"
    ],
    "wof:name":"Sangsulbi",
    "wof:placetype":"locality"
},
  "geometry": {"coordinates":[127.45944,38.76917],"type":"Point"}
}