{
  "type": "Feature",
  "properties": {
    "gn:admin1_code":"1.0",
    "gn:asciiname":"Sosudongp'yong-dong",
    "gn:country_code":"KP",
    "gn:dem":471,
    "gn:feature_class":"P",
    "gn:feature_code":"PPL",
    "gn:name":"Sosudongp\u2019y\u014fng-dong",
    "gn:population":0,
    "gn:timezone":"Asia/Pyongyang",
    "iso:country":"KP",
    "name:und_x_variant":[
        "\uc18c\uc218\ub3d9\ud3c9\ub3d9",
        "Sosudongp\u2019y\u014fng-dong"
    ],
    "wof:name":"Sosudongp'yong-dong",
    "wof:placetype":"locality"
},
  "geometry": {"coordinates":[125.98917,40.61639],"type":"Point"}
}