{
  "type": "Feature",
  "properties": {
    "gn:admin1_code":"7.0",
    "gn:asciiname":"Rak-ch'on",
    "gn:country_code":"KP",
    "gn:dem":73,
    "gn:feature_class":"P",
    "gn:feature_code":"PPL",
    "gn:name":"Rak-ch\u2019on",
    "gn:population":0,
    "gn:timezone":"Asia/Pyongyang",
    "iso:country":"KP",
    "name:kor_x_preferred":[
        "\ub77d\ucd0c"
    ],
    "name:und_x_variant":[
        "Rak-ch\u2019on",
        "Nak-ch\u2019on"
    ],
    "wof:name":"Rak-ch'on",
    "wof:placetype":"locality"
},
  "geometry": {"coordinates":[125.82722,38.53083],"type":"Point"}
}