{
  "type": "Feature",
  "properties": {
    "gn:admin1_code":"7.0",
    "gn:asciiname":"Mangjol-li",
    "gn:country_code":"KP",
    "gn:dem":156,
    "gn:feature_class":"P",
    "gn:feature_code":"PPL",
    "gn:name":"Mangj\u014fl-li",
    "gn:population":0,
    "gn:timezone":"Asia/Pyongyang",
    "iso:country":"KP",
    "wof:name":"Mangjol-li",
    "wof:placetype":"locality"
},
  "geometry": {"coordinates":[126.035,38.55611],"type":"Point"}
}