{
  "type": "Feature",
  "properties": {
    "gn:admin1_code":"9.0",
    "gn:asciiname":"Chandiji",
    "gn:country_code":"KP",
    "gn:dem":545,
    "gn:feature_class":"P",
    "gn:feature_code":"PPL",
    "gn:name":"Chandiji",
    "gn:population":0,
    "gn:timezone":"Asia/Pyongyang",
    "iso:country":"KP",
    "name:kor_x_preferred":[
        "\uc794\ub514\uc9c0"
    ],
    "wof:name":"Chandiji",
    "wof:placetype":"locality"
},
  "geometry": {"coordinates":[127.30916999999999,38.78222],"type":"Point"}
}