{
  "type": "Feature",
  "properties": {
    "gn:admin1_code":"9.0",
    "gn:asciiname":"Songjong-gol",
    "gn:country_code":"KP",
    "gn:dem":360,
    "gn:feature_class":"P",
    "gn:feature_code":"PPL",
    "gn:name":"Songj\u014fng-gol",
    "gn:population":0,
    "gn:timezone":"Asia/Pyongyang",
    "iso:country":"KP",
    "name:kor_x_preferred":[
        "\uc1a1\uc815\uace8"
    ],
    "name:kor_x_variant":[
        "Songj\u014fng-gol"
    ],
    "name:und_x_variant":[
        "Songj\u014fng-kol"
    ],
    "wof:name":"Songjong-gol",
    "wof:placetype":"locality"
},
  "geometry": {"coordinates":[127.08417,39.01889],"type":"Point"}
}