{
  "type": "Feature",
  "properties": {
    "gn:admin1_code":"15.0",
    "gn:asciiname":"Ullimch'am",
    "gn:country_code":"KP",
    "gn:dem":20,
    "gn:feature_class":"P",
    "gn:feature_code":"PPL",
    "gn:name":"Ullimch\u2019am",
    "gn:population":0,
    "gn:timezone":"Asia/Pyongyang",
    "iso:country":"KP",
    "name:kor_x_preferred":[
        "\uc6b4\ub9bc\ucc38"
    ],
    "name:und_x_variant":[
        "Ullimch\u2019am"
    ],
    "wof:name":"Ullimch'am",
    "wof:placetype":"locality"
},
  "geometry": {"coordinates":[125.82222,39.68972],"type":"Point"}
}