{
  "type": "Feature",
  "properties": {
    "gn:admin1_code":"7.0",
    "gn:asciiname":"Sollanmol",
    "gn:country_code":"KP",
    "gn:dem":57,
    "gn:feature_class":"P",
    "gn:feature_code":"PPL",
    "gn:name":"Sollanmol",
    "gn:population":0,
    "gn:timezone":"Asia/Pyongyang",
    "iso:country":"KP",
    "wof:name":"Sollanmol",
    "wof:placetype":"locality"
},
  "geometry": {"coordinates":[125.76333,38.38528],"type":"Point"}
}