{
  "type": "Feature",
  "properties": {
    "gn:admin1_code":"11.0",
    "gn:asciiname":"Pongch'on-gol",
    "gn:country_code":"KP",
    "gn:dem":215,
    "gn:feature_class":"P",
    "gn:feature_code":"PPL",
    "gn:name":"Pongch\u2019\u014fn-gol",
    "gn:population":0,
    "gn:timezone":"Asia/Pyongyang",
    "iso:country":"KP",
    "wof:name":"Pongch'on-gol",
    "wof:placetype":"locality"
},
  "geometry": {"coordinates":[126.12860999999999,39.86556],"type":"Point"}
}