{
  "type": "Feature",
  "properties": {
    "gn:admin1_code":"3.0",
    "gn:asciiname":"Chiil-li",
    "gn:country_code":"KP",
    "gn:dem":37,
    "gn:feature_class":"P",
    "gn:feature_code":"PPL",
    "gn:name":"Chiil-li",
    "gn:population":0,
    "gn:timezone":"Asia/Pyongyang",
    "iso:country":"KP",
    "name:und_x_variant":[
        "Chijin-ri",
        "Chiin-ni",
        "\uc9c0\uc778\ub9ac",
        "Chiil-li"
    ],
    "wof:name":"Chiil-li",
    "wof:placetype":"locality"
},
  "geometry": {"coordinates":[127.34417000000001,39.5475],"type":"Point"}
}