{
  "type": "Feature",
  "properties": {
    "gn:admin1_code":"15.0",
    "gn:asciiname":"In'gyong-dong",
    "gn:country_code":"KP",
    "gn:dem":240,
    "gn:feature_class":"P",
    "gn:feature_code":"PPL",
    "gn:name":"In\u2019gy\u014fng-dong",
    "gn:population":0,
    "gn:timezone":"Asia/Pyongyang",
    "iso:country":"KP",
    "name:und_x_variant":[
        "\uc778\uacbd\ub3d9",
        "In\u2019gy\u014fng-dong"
    ],
    "wof:name":"In'gyong-dong",
    "wof:placetype":"locality"
},
  "geometry": {"coordinates":[126.84417000000001,39.12167],"type":"Point"}
}