{
  "type": "Feature",
  "properties": {
    "gn:admin1_code":"15.0",
    "gn:asciiname":"Kiwadae",
    "gn:country_code":"KP",
    "gn:dem":322,
    "gn:feature_class":"P",
    "gn:feature_code":"PPL",
    "gn:name":"Kiwadae",
    "gn:population":0,
    "gn:timezone":"Asia/Pyongyang",
    "iso:country":"KP",
    "name:und_x_variant":[
        "\uae30\uc640\ub300",
        "Kiwadae"
    ],
    "wof:name":"Kiwadae",
    "wof:placetype":"locality"
},
  "geometry": {"coordinates":[126.65889,39.965],"type":"Point"}
}