{
  "type": "Feature",
  "properties": {
    "gn:admin1_code":"6.0",
    "gn:admin2_code":"1876380",
    "gn:asciiname":"Paemi-dong",
    "gn:country_code":"KP",
    "gn:dem":17,
    "gn:feature_class":"P",
    "gn:feature_code":"PPL",
    "gn:name":"Paemi-dong",
    "gn:population":0,
    "gn:timezone":"Asia/Pyongyang",
    "iso:country":"KP",
    "wof:name":"Paemi-dong",
    "wof:placetype":"locality"
},
  "geometry": {"coordinates":[126.40917,37.88194],"type":"Point"}
}