{
  "type": "Feature",
  "properties": {
    "gn:admin1_code":"17.0",
    "gn:asciiname":"Paengnong-ni",
    "gn:country_code":"KP",
    "gn:dem":110,
    "gn:feature_class":"P",
    "gn:feature_code":"PPLL",
    "gn:name":"Paengnong-ni",
    "gn:population":0,
    "gn:timezone":"Asia/Pyongyang",
    "iso:country":"KP",
    "name:eng_x_preferred":[
        "Paengnong"
    ],
    "name:eng_x_variant":[
        "Paengnong-ni"
    ],
    "name:und_x_variant":[
        "Paengnok-tong",
        "\ubc31\ub85d\ub9ac",
        "Paengnong-ni"
    ],
    "wof:name":"Paengnong",
    "wof:placetype":"locality"
},
  "geometry": {"coordinates":[129.50833,41.21083],"type":"Point"}
}