{
  "type": "Feature",
  "properties": {
    "gn:admin1_code":"9.0",
    "gn:asciiname":"Pulgunbau",
    "gn:country_code":"KP",
    "gn:dem":123,
    "gn:feature_class":"P",
    "gn:feature_code":"PPL",
    "gn:name":"Pulg\u016dnbau",
    "gn:population":0,
    "gn:timezone":"Asia/Pyongyang",
    "iso:country":"KP",
    "wof:name":"Pulgunbau",
    "wof:placetype":"locality"
},
  "geometry": {"coordinates":[126.97056000000001,38.33056],"type":"Point"}
}