{
  "type": "Feature",
  "properties": {
    "gn:admin1_code":"17.0",
    "gn:asciiname":"Won-dong",
    "gn:country_code":"KP",
    "gn:dem":517,
    "gn:feature_class":"P",
    "gn:feature_code":"PPL",
    "gn:name":"W\u014fn-dong",
    "gn:population":0,
    "gn:timezone":"Asia/Pyongyang",
    "iso:country":"KP",
    "name:und_x_variant":[
        "\uc6d0\ub3d9",
        "W\u014fn-dong"
    ],
    "wof:name":"Won-dong",
    "wof:placetype":"locality"
},
  "geometry": {"coordinates":[129.85556,42.60611],"type":"Point"}
}