{
  "type": "Feature",
  "properties": {
    "gn:admin1_code":"7.0",
    "gn:asciiname":"Songjae-ri",
    "gn:country_code":"KP",
    "gn:dem":8,
    "gn:feature_class":"P",
    "gn:feature_code":"PPL",
    "gn:name":"S\u014fngjae-ri",
    "gn:population":0,
    "gn:timezone":"Asia/Pyongyang",
    "iso:country":"KP",
    "name:kor_x_preferred":[
        "\uc131\uc7ac\ub9ac"
    ],
    "name:kor_x_variant":[
        "S\u014fngjae-ri"
    ],
    "wof:name":"Songjae-ri",
    "wof:placetype":"locality"
},
  "geometry": {"coordinates":[125.66500000000001,38.70972],"type":"Point"}
}