{
  "type": "Feature",
  "properties": {
    "gn:admin1_code":"17.0",
    "gn:asciiname":"Hwangsokch'on",
    "gn:country_code":"KP",
    "gn:dem":68,
    "gn:feature_class":"P",
    "gn:feature_code":"PPL",
    "gn:name":"Hwangsokch\u2019on",
    "gn:population":0,
    "gn:timezone":"Asia/Pyongyang",
    "iso:country":"KP",
    "name:und_x_variant":[
        "\ud669\uc11d\ucd0c",
        "Hwangsokch\u2019on"
    ],
    "wof:name":"Hwangsokch'on",
    "wof:placetype":"locality"
},
  "geometry": {"coordinates":[129.12333000000001,40.59333],"type":"Point"}
}