{
  "type": "Feature",
  "properties": {
    "gn:admin1_code":"3.0",
    "gn:asciiname":"Changdong-ni",
    "gn:country_code":"KP",
    "gn:dem":78,
    "gn:feature_class":"P",
    "gn:feature_code":"PPL",
    "gn:name":"Changdong-ni",
    "gn:population":0,
    "gn:timezone":"Asia/Pyongyang",
    "iso:country":"KP",
    "name:und_x_variant":[
        "\uc7a5\ub3d9\ub9ac",
        "Changdong-ni"
    ],
    "wof:name":"Changdong-ni",
    "wof:placetype":"locality"
},
  "geometry": {"coordinates":[127.55056,40.06444000000001],"type":"Point"}
}