{
  "type": "Feature",
  "properties": {
    "gn:admin1_code":"3.0",
    "gn:admin2_code":"K\u016dmya-gun",
    "gn:asciiname":"Tusal-li",
    "gn:country_code":"KP",
    "gn:dem":9,
    "gn:feature_class":"P",
    "gn:feature_code":"PPL",
    "gn:name":"Tusal-li",
    "gn:population":0,
    "gn:timezone":"Asia/Pyongyang",
    "iso:country":"KP",
    "wof:name":"Tusal-li",
    "wof:placetype":"locality"
},
  "geometry": {"coordinates":[127.32944000000001,39.45833],"type":"Point"}
}