{
  "type": "Feature",
  "properties": {
    "gn:admin1_code":"1.0",
    "gn:asciiname":"Paekchap'yong",
    "gn:country_code":"KP",
    "gn:dem":1022,
    "gn:feature_class":"P",
    "gn:feature_code":"PPL",
    "gn:name":"Paekchap\u2019y\u014fng",
    "gn:population":0,
    "gn:timezone":"Asia/Pyongyang",
    "iso:country":"KP",
    "name:und_x_variant":[
        "\ubc31\uc790\ud3c9",
        "Paekchap\u2019y\u014fng"
    ],
    "wof:name":"Paekchap'yong",
    "wof:placetype":"locality"
},
  "geometry": {"coordinates":[126.97778,40.49472],"type":"Point"}
}