{
  "type": "Feature",
  "properties": {
    "gn:admin1_code":"6.0",
    "gn:asciiname":"Chonsan-dong",
    "gn:country_code":"KP",
    "gn:dem":42,
    "gn:feature_class":"P",
    "gn:feature_code":"PPL",
    "gn:name":"Ch\u014fnsan-dong",
    "gn:population":0,
    "gn:timezone":"Asia/Pyongyang",
    "iso:country":"KP",
    "name:und_x_variant":[
        "\uc804\uc0b0\ub3d9",
        "Ch\u014fnsan-dong"
    ],
    "wof:name":"Chonsan-dong",
    "wof:placetype":"locality"
},
  "geometry": {"coordinates":[126.35389000000001,38.09667],"type":"Point"}
}