{
  "type": "Feature",
  "properties": {
    "gn:admin1_code":"6.0",
    "gn:asciiname":"Naejol",
    "gn:country_code":"KP",
    "gn:dem":134,
    "gn:feature_class":"P",
    "gn:feature_code":"PPL",
    "gn:name":"Naej\u014fl",
    "gn:population":0,
    "gn:timezone":"Asia/Pyongyang",
    "iso:country":"KP",
    "name:kor_x_preferred":[
        "\ub0b4\uc808"
    ],
    "name:kor_x_variant":[
        "Naej\u014fl"
    ],
    "name:und_x_variant":[
        "Naesa"
    ],
    "wof:name":"Naejol",
    "wof:placetype":"locality"
},
  "geometry": {"coordinates":[125.16194,38.40361],"type":"Point"}
}