{
  "type": "Feature",
  "properties": {
    "gn:admin1_code":"15.0",
    "gn:asciiname":"So-gol",
    "gn:country_code":"KP",
    "gn:dem":230,
    "gn:feature_class":"P",
    "gn:feature_code":"PPL",
    "gn:name":"S\u014f-gol",
    "gn:population":0,
    "gn:timezone":"Asia/Pyongyang",
    "iso:country":"KP",
    "wof:name":"So-gol",
    "wof:placetype":"locality"
},
  "geometry": {"coordinates":[126.11333,39.47194],"type":"Point"}
}