{
  "type": "Feature",
  "properties": {
    "gn:admin1_code":"17.0",
    "gn:asciiname":"Tok-kol",
    "gn:country_code":"KP",
    "gn:dem":182,
    "gn:feature_class":"P",
    "gn:feature_code":"PPL",
    "gn:name":"Tok-kol",
    "gn:population":0,
    "gn:timezone":"Asia/Pyongyang",
    "iso:country":"KP",
    "name:und_x_variant":[
        "\ub3c5\uace8",
        "Tok-kol"
    ],
    "wof:name":"Tok-kol",
    "wof:placetype":"locality"
},
  "geometry": {"coordinates":[129.32388999999998,41.00611],"type":"Point"}
}