{
  "type": "Feature",
  "properties": {
    "gn:admin1_code":"9.0",
    "gn:asciiname":"T'ogijom",
    "gn:country_code":"KP",
    "gn:dem":427,
    "gn:feature_class":"P",
    "gn:feature_code":"PPL",
    "gn:name":"T\u2019ogij\u014fm",
    "gn:population":0,
    "gn:timezone":"Asia/Pyongyang",
    "iso:country":"KP",
    "name:und_x_variant":[
        "\ud1a0\uae30\uc810",
        "T\u2019ogij\u014fm"
    ],
    "wof:name":"T'ogijom",
    "wof:placetype":"locality"
},
  "geometry": {"coordinates":[127.73721999999999,38.63389],"type":"Point"}
}