{
  "type": "Feature",
  "properties": {
    "gn:admin1_code":"17.0",
    "gn:asciiname":"Pisaek-tong",
    "gn:cc2":"KP",
    "gn:country_code":"KP",
    "gn:dem":1350,
    "gn:feature_class":"P",
    "gn:feature_code":"PPL",
    "gn:name":"Pisaek-tong",
    "gn:population":0,
    "gn:timezone":"Asia/Pyongyang",
    "iso:country":"KP",
    "name:und_x_variant":[
        "Pisaek-kol",
        "Pisaek-tong"
    ],
    "wof:name":"Pisaek-tong",
    "wof:placetype":"locality"
},
  "geometry": {"coordinates":[129.26667,41.53333],"type":"Point"}
}