{
  "type": "Feature",
  "properties": {
    "gn:admin1_code":"3.0",
    "gn:asciiname":"Kalgoch'i-ri",
    "gn:country_code":"KP",
    "gn:dem":21,
    "gn:feature_class":"P",
    "gn:feature_code":"PPL",
    "gn:name":"Kalgoch\u2019i-ri",
    "gn:population":0,
    "gn:timezone":"Asia/Pyongyang",
    "iso:country":"KP",
    "name:und_x_variant":[
        "Katsukoji",
        "Kalgoch\u2019wi-ri",
        "Kalgoji-ri",
        "Katsukochiri",
        "Katsukoji-ri",
        "\uac08\uace0\uce58\ub9ac",
        "Kalgoch\u2019i-ri"
    ],
    "wof:name":"Kalgoch'i-ri",
    "wof:placetype":"locality"
},
  "geometry": {"coordinates":[127.55722,39.31333],"type":"Point"}
}