{
  "type": "Feature",
  "properties": {
    "gn:admin1_code":"11.0",
    "gn:asciiname":"Pukhyon-dong",
    "gn:country_code":"KP",
    "gn:dem":32,
    "gn:feature_class":"P",
    "gn:feature_code":"PPL",
    "gn:name":"Pukhy\u014fn-dong",
    "gn:population":0,
    "gn:timezone":"Asia/Pyongyang",
    "iso:country":"KP",
    "name:und_x_variant":[
        "\ubd81\ud604\ub3d9",
        "Pukhy\u014fn-dong"
    ],
    "wof:name":"Pukhyon-dong",
    "wof:placetype":"locality"
},
  "geometry": {"coordinates":[124.43083,39.9425],"type":"Point"}
}