{
  "type": "Feature",
  "properties": {
    "gn:admin1_code":"15.0",
    "gn:asciiname":"Sinhung",
    "gn:country_code":"KP",
    "gn:dem":437,
    "gn:feature_class":"P",
    "gn:feature_code":"PPL",
    "gn:name":"Sinh\u016dng",
    "gn:population":0,
    "gn:timezone":"Asia/Pyongyang",
    "iso:country":"KP",
    "name:und_x_variant":[
        "\uc2e0\ud765",
        "Sinh\u016dng"
    ],
    "wof:name":"Sinhung",
    "wof:placetype":"locality"
},
  "geometry": {"coordinates":[126.75528,39.2275],"type":"Point"}
}