{
  "type": "Feature",
  "properties": {
    "gn:admin1_code":"17.0",
    "gn:asciiname":"P'och'on",
    "gn:country_code":"KP",
    "gn:dem":198,
    "gn:feature_class":"P",
    "gn:feature_code":"PPL",
    "gn:name":"P\u2019och\u2019on",
    "gn:population":0,
    "gn:timezone":"Asia/Pyongyang",
    "iso:country":"KP",
    "name:und_x_variant":[
        "\ud3ec\ucd0c",
        "P\u2019och\u2019on"
    ],
    "wof:name":"P'och'on",
    "wof:placetype":"locality"
},
  "geometry": {"coordinates":[129.26750000000001,40.99611],"type":"Point"}
}