{
  "type": "Feature",
  "properties": {
    "gn:admin1_code":"7.0",
    "gn:asciiname":"Hoe-dong",
    "gn:country_code":"KP",
    "gn:dem":124,
    "gn:feature_class":"P",
    "gn:feature_code":"PPL",
    "gn:name":"Hoe-dong",
    "gn:population":0,
    "gn:timezone":"Asia/Pyongyang",
    "iso:country":"KP",
    "name:kor_x_preferred":[
        "\ud68c\ub3d9"
    ],
    "wof:name":"Hoe-dong",
    "wof:placetype":"locality"
},
  "geometry": {"coordinates":[126.36417,38.68806],"type":"Point"}
}