{
  "type": "Feature",
  "properties": {
    "gn:admin1_code":"3.0",
    "gn:asciiname":"Songal-li",
    "gn:country_code":"KP",
    "gn:dem":53,
    "gn:feature_class":"P",
    "gn:feature_code":"PPL",
    "gn:name":"S\u014fngal-li",
    "gn:population":0,
    "gn:timezone":"Asia/Pyongyang",
    "iso:country":"KP",
    "name:und_x_variant":[
        "\uc131\uc548\ub9ac",
        "S\u014fngal-li"
    ],
    "wof:name":"Songal-li",
    "wof:placetype":"locality"
},
  "geometry": {"coordinates":[127.29139000000001,39.72417],"type":"Point"}
}