{
  "type": "Feature",
  "properties": {
    "gn:admin1_code":"7.0",
    "gn:asciiname":"Tok-tong",
    "gn:country_code":"KP",
    "gn:dem":279,
    "gn:feature_class":"P",
    "gn:feature_code":"PPL",
    "gn:name":"T\u014fk-tong",
    "gn:population":0,
    "gn:timezone":"Asia/Pyongyang",
    "iso:country":"KP",
    "name:kor_x_preferred":[
        "\ub355\ub3d9"
    ],
    "name:kor_x_variant":[
        "T\u014fk-tong"
    ],
    "wof:name":"Tok-tong",
    "wof:placetype":"locality"
},
  "geometry": {"coordinates":[126.36278,38.81278],"type":"Point"}
}