{
  "type": "Feature",
  "properties": {
    "gn:admin1_code":"15.0",
    "gn:asciiname":"Kogaean",
    "gn:country_code":"KP",
    "gn:dem":176,
    "gn:feature_class":"P",
    "gn:feature_code":"PPL",
    "gn:name":"Kogaean",
    "gn:population":0,
    "gn:timezone":"Asia/Pyongyang",
    "iso:country":"KP",
    "name:kor_x_preferred":[
        "\uace0\uac1c\uc548"
    ],
    "wof:name":"Kogaean",
    "wof:placetype":"locality"
},
  "geometry": {"coordinates":[126.48361,39.37639],"type":"Point"}
}