{
  "type": "Feature",
  "properties": {
    "gn:admin1_code":"7.0",
    "gn:asciiname":"Chit'am-ni",
    "gn:country_code":"KP",
    "gn:dem":12,
    "gn:feature_class":"P",
    "gn:feature_code":"PPL",
    "gn:name":"Chit\u2019am-ni",
    "gn:population":0,
    "gn:timezone":"Asia/Pyongyang",
    "iso:country":"KP",
    "name:eng_x_preferred":[
        "Chit'am"
    ],
    "name:eng_x_variant":[
        "Chit'am-ni"
    ],
    "name:kor_x_preferred":[
        "\uc9c0\ud0d0\ub9ac"
    ],
    "name:und_x_variant":[
        "Chit\u2019am-ni"
    ],
    "wof:name":"Chit'am",
    "wof:placetype":"locality"
},
  "geometry": {"coordinates":[125.80972,38.45],"type":"Point"}
}