{
  "type": "Feature",
  "properties": {
    "gn:admin1_code":"11.0",
    "gn:asciiname":"Yongdu-dong",
    "gn:country_code":"KP",
    "gn:dem":64,
    "gn:feature_class":"P",
    "gn:feature_code":"PPL",
    "gn:name":"Yongdu-dong",
    "gn:population":0,
    "gn:timezone":"Asia/Pyongyang",
    "iso:country":"KP",
    "name:fas_x_preferred":[
        "\u06cc\u0648\u0646\u06af\u062f\u0648-\u062f\u0648\u0646\u06af"
    ],
    "name:vie_x_preferred":[
        "Yongdu-dong"
    ],
    "wof:name":"Yongdu-dong",
    "wof:placetype":"locality"
},
  "geometry": {"coordinates":[125.73361,39.88917],"type":"Point"}
}