{
  "type": "Feature",
  "properties": {
    "gn:admin1_code":"11.0",
    "gn:asciiname":"Paemjae-ri",
    "gn:country_code":"KP",
    "gn:dem":7,
    "gn:feature_class":"P",
    "gn:feature_code":"PPL",
    "gn:name":"Paemjae-ri",
    "gn:population":0,
    "gn:timezone":"Asia/Pyongyang",
    "iso:country":"KP",
    "name:kor_x_preferred":[
        "\ubc40\uc7ac\ub9ac"
    ],
    "name:und_x_variant":[
        "Sap\u2019o-ri",
        "Paemjae-ri"
    ],
    "wof:name":"Paemjae-ri",
    "wof:placetype":"locality"
},
  "geometry": {"coordinates":[125.34389,39.56444000000001],"type":"Point"}
}