{
  "type": "Feature",
  "properties": {
    "gn:admin1_code":"9.0",
    "gn:asciiname":"Huch'ol-li",
    "gn:country_code":"KP",
    "gn:dem":290,
    "gn:feature_class":"P",
    "gn:feature_code":"PPL",
    "gn:name":"Huch\u2019\u014fl-li",
    "gn:population":0,
    "gn:timezone":"Asia/Pyongyang",
    "iso:country":"KP",
    "name:und_x_variant":[
        "Huch\u2019\u014fn-ni",
        "\ud6c4\ucc9c\ub9ac",
        "Huch\u2019\u014fl-li"
    ],
    "wof:name":"Huch'ol-li",
    "wof:placetype":"locality"
},
  "geometry": {"coordinates":[127.60167,38.40417],"type":"Point"}
}