{
  "type": "Feature",
  "properties": {
    "gn:admin1_code":"6.0",
    "gn:asciiname":"Yongmun-dong",
    "gn:cc2":"KP",
    "gn:country_code":"KP",
    "gn:dem":99,
    "gn:feature_class":"P",
    "gn:feature_code":"PPL",
    "gn:name":"Yongmun-dong",
    "gn:population":0,
    "gn:timezone":"Asia/Pyongyang",
    "iso:country":"KP",
    "name:ceb_x_preferred":[
        "Yongmun-dong"
    ],
    "name:kor_x_preferred":[
        "\uc6a9\ubb38\ub3d9"
    ],
    "name:und_x_variant":[
        "Ry\u016bmon-d\u014d",
        "Yongmun",
        "Ry\u016bmon",
        "Yongmun-dong"
    ],
    "name:urd_x_preferred":[
        "\u06cc\u0648\u0646\u06af\u0645\u0646-\u0688\u0648\u0646\u06af"
    ],
    "name:vie_x_preferred":[
        "Yongmun-dong"
    ],
    "name:zho_x_preferred":[
        "\u9f99\u95e8\u6d1e"
    ],
    "wof:name":"Yongmun-dong",
    "wof:placetype":"locality"
},
  "geometry": {"coordinates":[125.35138999999999,38.34083],"type":"Point"}
}