{
  "type": "Feature",
  "properties": {
    "gn:admin1_code":"1.0",
    "gn:asciiname":"Yujol-li",
    "gn:country_code":"KP",
    "gn:dem":562,
    "gn:feature_class":"P",
    "gn:feature_code":"PPL",
    "gn:name":"Yuj\u014fl-li",
    "gn:population":0,
    "gn:timezone":"Asia/Pyongyang",
    "iso:country":"KP",
    "name:und_x_variant":[
        "\uc720\uc804\ub9ac",
        "Yuj\u014fl-li",
        "\ub958\uc804\ub9ac"
    ],
    "wof:name":"Yujol-li",
    "wof:placetype":"locality"
},
  "geometry": {"coordinates":[126.21791,40.69985],"type":"Point"}
}