{
  "type": "Feature",
  "properties": {
    "gn:admin1_code":"11.0",
    "gn:asciiname":"Kuam-ni",
    "gn:country_code":"KP",
    "gn:dem":380,
    "gn:feature_class":"P",
    "gn:feature_code":"PPL",
    "gn:name":"Kuam-ni",
    "gn:population":0,
    "gn:timezone":"Asia/Pyongyang",
    "iso:country":"KP",
    "name:und_x_variant":[
        "\uad6c\uc554\ub9ac",
        "Kuam-ni"
    ],
    "wof:name":"Kuam-ni",
    "wof:placetype":"locality"
},
  "geometry": {"coordinates":[125.54111,40.41917],"type":"Point"}
}