{
  "type": "Feature",
  "properties": {
    "gn:admin1_code":"3.0",
    "gn:asciiname":"Yongdae",
    "gn:country_code":"KP",
    "gn:dem":17,
    "gn:feature_class":"P",
    "gn:feature_code":"PPL",
    "gn:name":"Y\u014fngdae",
    "gn:population":0,
    "gn:timezone":"Asia/Pyongyang",
    "iso:country":"KP",
    "name:und_x_variant":[
        "\uc601\ub300",
        "Y\u014fngdae"
    ],
    "wof:name":"Yongdae",
    "wof:placetype":"locality"
},
  "geometry": {"coordinates":[128.74638999999999,40.35972],"type":"Point"}
}