{
  "type": "Feature",
  "properties": {
    "gn:admin1_code":"6.0",
    "gn:asciiname":"T'ogok-kol",
    "gn:country_code":"KP",
    "gn:dem":62,
    "gn:feature_class":"P",
    "gn:feature_code":"PPL",
    "gn:name":"T\u2019ogok-kol",
    "gn:population":0,
    "gn:timezone":"Asia/Pyongyang",
    "iso:country":"KP",
    "name:kor_x_preferred":[
        "\ud1a0\uacf3\uace8"
    ],
    "name:kor_x_variant":[
        "T\u2019ogok-kol"
    ],
    "name:und_x_variant":[
        "Sanggwan-dong",
        "T\u2019ogot-tong"
    ],
    "wof:name":"T'ogok-kol",
    "wof:placetype":"locality"
},
  "geometry": {"coordinates":[125.33861,38.46083],"type":"Point"}
}