{
  "type": "Feature",
  "properties": {
    "gn:admin1_code":"0.0",
    "gn:asciiname":"Tokch'i",
    "gn:country_code":"KP",
    "gn:dem":169,
    "gn:feature_class":"P",
    "gn:feature_code":"PPL",
    "gn:name":"T\u014fkch\u2019i",
    "gn:population":0,
    "gn:timezone":"Asia/Pyongyang",
    "iso:country":"KP",
    "name:kor_x_preferred":[
        "\ub355\uce58"
    ],
    "name:und_x_variant":[
        "T\u014fkch\u2019i"
    ],
    "wof:name":"Tokch'i",
    "wof:placetype":"locality"
},
  "geometry": {"coordinates":[125.98333,38.86667],"type":"Point"}
}