{
  "type": "Feature",
  "properties": {
    "gn:admin1_code":"9.0",
    "gn:asciiname":"Hoejon-dong",
    "gn:country_code":"KP",
    "gn:dem":760,
    "gn:feature_class":"P",
    "gn:feature_code":"PPL",
    "gn:name":"Hoej\u014fn-dong",
    "gn:population":0,
    "gn:timezone":"Asia/Pyongyang",
    "iso:country":"KP",
    "name:kor_x_preferred":[
        "\ud68c\uc804\ub3d9"
    ],
    "name:und_x_variant":[
        "Hoej\u014fn-dong"
    ],
    "wof:name":"Hoejon-dong",
    "wof:placetype":"locality"
},
  "geometry": {"coordinates":[128.0625,38.43889],"type":"Point"}
}