{
  "type": "Feature",
  "properties": {
    "gn:admin1_code":"6.0",
    "gn:asciiname":"Hach'andol",
    "gn:country_code":"KP",
    "gn:dem":46,
    "gn:feature_class":"P",
    "gn:feature_code":"PPL",
    "gn:name":"Hach\u2019andol",
    "gn:population":0,
    "gn:timezone":"Asia/Pyongyang",
    "iso:country":"KP",
    "wof:name":"Hach'andol",
    "wof:placetype":"locality"
},
  "geometry": {"coordinates":[126.02222,38.03528],"type":"Point"}
}