{
  "type": "Feature",
  "properties": {
    "gn:admin1_code":"13.0",
    "gn:asciiname":"Puhuwon",
    "gn:country_code":"KP",
    "gn:dem":1209,
    "gn:feature_class":"P",
    "gn:feature_code":"PPL",
    "gn:name":"Puhuw\u014fn",
    "gn:population":0,
    "gn:timezone":"Asia/Pyongyang",
    "iso:country":"KP",
    "wof:name":"Puhuwon",
    "wof:placetype":"locality"
},
  "geometry": {"coordinates":[128.80000000000001,41.10361],"type":"Point"}
}