{
  "type": "Feature",
  "properties": {
    "gn:admin1_code":"9.0",
    "gn:asciiname":"Korim-ni",
    "gn:country_code":"KP",
    "gn:dem":42,
    "gn:feature_class":"P",
    "gn:feature_code":"PPL",
    "gn:name":"Korim-ni",
    "gn:population":0,
    "gn:timezone":"Asia/Pyongyang",
    "iso:country":"KP",
    "name:und_x_variant":[
        "\uace0\ub9bc\ub9ac",
        "Korim-ni"
    ],
    "wof:name":"Korim-ni",
    "wof:placetype":"locality"
},
  "geometry": {"coordinates":[127.88056,38.85583],"type":"Point"}
}