{
  "type": "Feature",
  "properties": {
    "gn:admin1_code":"6.0",
    "gn:asciiname":"Sajanggyo",
    "gn:country_code":"KP",
    "gn:dem":39,
    "gn:feature_class":"P",
    "gn:feature_code":"PPL",
    "gn:name":"Sajanggyo",
    "gn:population":0,
    "gn:timezone":"Asia/Pyongyang",
    "iso:country":"KP",
    "name:und_x_variant":[
        "\uc0ac\uc7a5\uad50",
        "Sajanggyo"
    ],
    "wof:name":"Sajanggyo",
    "wof:placetype":"locality"
},
  "geometry": {"coordinates":[125.47306,37.99167],"type":"Point"}
}