{
  "type": "Feature",
  "properties": {
    "gn:admin1_code":"17.0",
    "gn:asciiname":"Chonsan",
    "gn:cc2":"KP",
    "gn:country_code":"KP",
    "gn:dem":5,
    "gn:feature_class":"P",
    "gn:feature_code":"PPL",
    "gn:name":"Ch\u014fnsan",
    "gn:population":0,
    "gn:timezone":"Asia/Pyongyang",
    "iso:country":"KP",
    "name:und_x_variant":[
        "Sensan",
        "\uc804\uc0b0",
        "Ch\u014fnsan"
    ],
    "wof:name":"Chonsan",
    "wof:placetype":"locality"
},
  "geometry": {"coordinates":[129.64694,41.53583],"type":"Point"}
}