{
  "type": "Feature",
  "properties": {
    "gn:admin1_code":"6.0",
    "gn:asciiname":"Ch'imbangp'o",
    "gn:country_code":"KP",
    "gn:dem":12,
    "gn:feature_class":"P",
    "gn:feature_code":"PPL",
    "gn:name":"Ch\u2019imbangp\u2019o",
    "gn:population":0,
    "gn:timezone":"Asia/Pyongyang",
    "iso:country":"KP",
    "name:kor_x_preferred":[
        "\uce68\ubc29\ud3ec"
    ],
    "name:und_x_variant":[
        "Simbangp\u2019o",
        "Ch\u2019imbangp\u2019o"
    ],
    "wof:name":"Ch'imbangp'o",
    "wof:placetype":"locality"
},
  "geometry": {"coordinates":[124.92083,38.40556],"type":"Point"}
}