{
  "type": "Feature",
  "properties": {
    "gn:admin1_code":"3.0",
    "gn:asciiname":"Choga-gol",
    "gn:country_code":"KP",
    "gn:dem":416,
    "gn:feature_class":"P",
    "gn:feature_code":"PPL",
    "gn:name":"Choga-gol",
    "gn:population":0,
    "gn:timezone":"Asia/Pyongyang",
    "iso:country":"KP",
    "name:und_x_variant":[
        "\uc870\uac00\uace8",
        "Choga-gol"
    ],
    "wof:name":"Choga-gol",
    "wof:placetype":"locality"
},
  "geometry": {"coordinates":[128.69278,40.60611],"type":"Point"}
}