{
  "type": "Feature",
  "properties": {
    "gn:admin1_code":"13.0",
    "gn:asciiname":"Iptong-ni",
    "gn:country_code":"KP",
    "gn:dem":980,
    "gn:feature_class":"P",
    "gn:feature_code":"PPL",
    "gn:name":"Ipt\u014fng-ni",
    "gn:population":0,
    "gn:timezone":"Asia/Pyongyang",
    "iso:country":"KP",
    "name:kor_x_preferred":[
        "\uc785\ub355\ub9ac"
    ],
    "name:und_x_variant":[
        "Ipt\u014fng-ni"
    ],
    "wof:name":"Iptong-ni",
    "wof:placetype":"locality"
},
  "geometry": {"coordinates":[128.35028,41.14472],"type":"Point"}
}