{
  "type": "Feature",
  "properties": {
    "gn:admin1_code":"6.0",
    "gn:asciiname":"Kiam-ni",
    "gn:country_code":"KP",
    "gn:dem":62,
    "gn:feature_class":"P",
    "gn:feature_code":"PPL",
    "gn:name":"Kiam-ni",
    "gn:population":0,
    "gn:timezone":"Asia/Pyongyang",
    "iso:country":"KP",
    "name:und_x_variant":[
        "Kiyang-ni",
        "\uae30\uc554\ub9ac",
        "Kiam-ni"
    ],
    "wof:name":"Kiam-ni",
    "wof:placetype":"locality"
},
  "geometry": {"coordinates":[125.20694,38.13694],"type":"Point"}
}