{
  "type": "Feature",
  "properties": {
    "gn:admin1_code":"12.0",
    "gn:asciiname":"Wangnung-dong",
    "gn:country_code":"KP",
    "gn:dem":59,
    "gn:feature_class":"P",
    "gn:feature_code":"PPL",
    "gn:name":"Wangn\u016dng-dong",
    "gn:population":0,
    "gn:timezone":"Asia/Pyongyang",
    "iso:country":"KP",
    "name:kor_x_preferred":[
        "Wangr\u016dng-dong"
    ],
    "name:kor_x_variant":[
        "\uc655\ub989\ub3d9"
    ],
    "name:und_x_variant":[
        "Wangn\u016dng-dong",
        "Wangneungdong"
    ],
    "wof:name":"Wangnung-dong",
    "wof:placetype":"locality"
},
  "geometry": {"coordinates":[125.92718000000001,38.89375],"type":"Point"}
}