{
  "type": "Feature",
  "properties": {
    "gn:admin1_code":"17.0",
    "gn:asciiname":"Waryong-dong",
    "gn:country_code":"KP",
    "gn:dem":545,
    "gn:feature_class":"P",
    "gn:feature_code":"PPL",
    "gn:name":"Waryong-dong",
    "gn:population":0,
    "gn:timezone":"Asia/Pyongyang",
    "iso:country":"KP",
    "name:und_x_variant":[
        "\uc640\ub8e1\ub3d9",
        "Waryong-dong"
    ],
    "wof:name":"Waryong-dong",
    "wof:placetype":"locality"
},
  "geometry": {"coordinates":[129.8725,42.60861],"type":"Point"}
}