{
  "type": "Feature",
  "properties": {
    "gn:admin1_code":"11.0",
    "gn:asciiname":"Haksal-li",
    "gn:country_code":"KP",
    "gn:dem":17,
    "gn:feature_class":"P",
    "gn:feature_code":"PPL",
    "gn:name":"Haksal-li",
    "gn:population":0,
    "gn:timezone":"Asia/Pyongyang",
    "iso:country":"KP",
    "name:und_x_variant":[
        "Haksan-dong",
        "Haksan-ni",
        "\ud559\uc0b0\ub9ac",
        "Haksal-li"
    ],
    "wof:name":"Haksal-li",
    "wof:placetype":"locality"
},
  "geometry": {"coordinates":[124.61639,39.80417],"type":"Point"}
}