{
  "type": "Feature",
  "properties": {
    "gn:admin1_code":"3.0",
    "gn:asciiname":"Chungsu-ri",
    "gn:country_code":"KP",
    "gn:dem":10,
    "gn:feature_class":"P",
    "gn:feature_code":"PPL",
    "gn:name":"Chungsu-ri",
    "gn:population":0,
    "gn:timezone":"Asia/Pyongyang",
    "iso:country":"KP",
    "name:und_x_variant":[
        "\uc911\uc218\ub9ac",
        "Chungsu-ri"
    ],
    "wof:name":"Chungsu-ri",
    "wof:placetype":"locality"
},
  "geometry": {"coordinates":[127.57028,39.87083],"type":"Point"}
}