{
  "type": "Feature",
  "properties": {
    "gn:admin1_code":"3.0",
    "gn:asciiname":"Sindong-ni",
    "gn:country_code":"KP",
    "gn:dem":126,
    "gn:feature_class":"P",
    "gn:feature_code":"PPL",
    "gn:name":"Sind\u014fng-ni",
    "gn:population":0,
    "gn:timezone":"Asia/Pyongyang",
    "iso:country":"KP",
    "name:eng_x_preferred":[
        "Sindong"
    ],
    "name:eng_x_variant":[
        "Sindong-ni"
    ],
    "name:und_x_variant":[
        "\uc2e0\ub355\ub9ac",
        "Sind\u014fng-ni"
    ],
    "wof:name":"Sindong",
    "wof:placetype":"locality"
},
  "geometry": {"coordinates":[127.65111,40.05278],"type":"Point"}
}