{
  "type": "Feature",
  "properties": {
    "gn:admin1_code":"17.0",
    "gn:asciiname":"Ch'ojang-dong",
    "gn:country_code":"KP",
    "gn:dem":316,
    "gn:feature_class":"P",
    "gn:feature_code":"PPL",
    "gn:name":"Ch\u2019ojang-dong",
    "gn:population":0,
    "gn:timezone":"Asia/Pyongyang",
    "iso:country":"KP",
    "wof:name":"Ch'ojang-dong",
    "wof:placetype":"locality"
},
  "geometry": {"coordinates":[129.49833000000001,40.95333],"type":"Point"}
}