{
  "type": "Feature",
  "properties": {
    "gn:admin1_code":"3.0",
    "gn:asciiname":"Ch'angsil-li",
    "gn:country_code":"KP",
    "gn:dem":6,
    "gn:feature_class":"P",
    "gn:feature_code":"PPL",
    "gn:name":"Ch\u2019angsil-li",
    "gn:population":0,
    "gn:timezone":"Asia/Pyongyang",
    "iso:country":"KP",
    "name:und_x_variant":[
        "Ch\u2019angsin-ni",
        "\uc7a5\uc2e0\ub9ac",
        "Ch\u2019angsil-li"
    ],
    "wof:name":"Ch'angsil-li",
    "wof:placetype":"locality"
},
  "geometry": {"coordinates":[127.45667,39.7375],"type":"Point"}
}