{
  "type": "Feature",
  "properties": {
    "gn:admin1_code":"17.0",
    "gn:asciiname":"Sae-gol",
    "gn:country_code":"KP",
    "gn:dem":295,
    "gn:feature_class":"P",
    "gn:feature_code":"PPL",
    "gn:name":"Sae-gol",
    "gn:population":0,
    "gn:timezone":"Asia/Pyongyang",
    "iso:country":"KP",
    "name:und_x_variant":[
        "Sae-kol",
        "\uc0c8\uace8",
        "Sae-gol"
    ],
    "wof:name":"Sae-gol",
    "wof:placetype":"locality"
},
  "geometry": {"coordinates":[129.36750000000001,41.05083],"type":"Point"}
}