{
  "type": "Feature",
  "properties": {
    "gn:admin1_code":"1.0",
    "gn:asciiname":"Ohwa-dong",
    "gn:country_code":"KP",
    "gn:dem":598,
    "gn:feature_class":"P",
    "gn:feature_code":"PPL",
    "gn:name":"Ohwa-dong",
    "gn:population":0,
    "gn:timezone":"Asia/Pyongyang",
    "iso:country":"KP",
    "name:und_x_variant":[
        "\uc624\ud654\ub3d9",
        "Ohwa-dong"
    ],
    "wof:name":"Ohwa-dong",
    "wof:placetype":"locality"
},
  "geometry": {"coordinates":[125.98083,40.69972],"type":"Point"}
}