{
  "type": "Feature",
  "properties": {
    "gn:admin1_code":"1.0",
    "gn:asciiname":"Sobandok",
    "gn:country_code":"KP",
    "gn:dem":363,
    "gn:feature_class":"P",
    "gn:feature_code":"PPL",
    "gn:name":"Soband\u014fk",
    "gn:population":0,
    "gn:timezone":"Asia/Pyongyang",
    "iso:country":"KP",
    "name:und_x_variant":[
        "\uc18c\ubc18\ub355",
        "Soband\u014fk"
    ],
    "wof:name":"Sobandok",
    "wof:placetype":"locality"
},
  "geometry": {"coordinates":[126.62472,41.56472],"type":"Point"}
}