{
  "type": "Feature",
  "properties": {
    "gn:admin1_code":"9.0",
    "gn:asciiname":"Kwal-li",
    "gn:country_code":"KP",
    "gn:dem":391,
    "gn:feature_class":"P",
    "gn:feature_code":"PPL",
    "gn:name":"Kwal-li",
    "gn:population":0,
    "gn:timezone":"Asia/Pyongyang",
    "iso:country":"KP",
    "name:und_x_variant":[
        "Kwan-ni",
        "\uad00\ub9ac",
        "Kwal-li"
    ],
    "wof:name":"Kwal-li",
    "wof:placetype":"locality"
},
  "geometry": {"coordinates":[127.72083000000001,38.63889],"type":"Point"}
}