{
  "type": "Feature",
  "properties": {
    "gn:admin1_code":"1.0",
    "gn:asciiname":"Chik-kol",
    "gn:country_code":"KP",
    "gn:dem":733,
    "gn:feature_class":"P",
    "gn:feature_code":"PPL",
    "gn:name":"Chik-kol",
    "gn:population":0,
    "gn:timezone":"Asia/Pyongyang",
    "iso:country":"KP",
    "name:und_x_variant":[
        "\uc9c1\uace8",
        "Chik-kol"
    ],
    "wof:name":"Chik-kol",
    "wof:placetype":"locality"
},
  "geometry": {"coordinates":[126.63249999999999,40.4625],"type":"Point"}
}