{
  "type": "Feature",
  "properties": {
    "gn:admin1_code":"1.0",
    "gn:asciiname":"Yongyol-li",
    "gn:country_code":"KP",
    "gn:dem":286,
    "gn:feature_class":"P",
    "gn:feature_code":"PPL",
    "gn:name":"Yongy\u014fl-li",
    "gn:population":0,
    "gn:timezone":"Asia/Pyongyang",
    "iso:country":"KP",
    "name:und_x_variant":[
        "\uc6a9\uc5f0\ub9ac",
        "Yongy\u014fn-ni",
        "Yongy\u014fl-li"
    ],
    "wof:name":"Yongyol-li",
    "wof:placetype":"locality"
},
  "geometry": {"coordinates":[125.66777999999999,40.46889],"type":"Point"}
}