{
  "type": "Feature",
  "properties": {
    "gn:admin1_code":"6.0",
    "gn:asciiname":"Ki-dong",
    "gn:country_code":"KP",
    "gn:dem":76,
    "gn:feature_class":"P",
    "gn:feature_code":"PPL",
    "gn:name":"Ki-dong",
    "gn:population":0,
    "gn:timezone":"Asia/Pyongyang",
    "iso:country":"KP",
    "name:und_x_variant":[
        "\uae30\ub3d9",
        "Ki-dong"
    ],
    "wof:name":"Ki-dong",
    "wof:placetype":"locality"
},
  "geometry": {"coordinates":[125.38111000000001,38.20528],"type":"Point"}
}