{
  "type": "Feature",
  "properties": {
    "gn:admin1_code":"7.0",
    "gn:asciiname":"T'angji-dong",
    "gn:country_code":"KP",
    "gn:dem":58,
    "gn:feature_class":"P",
    "gn:feature_code":"PPL",
    "gn:name":"T\u2019angji-dong",
    "gn:population":0,
    "gn:timezone":"Asia/Pyongyang",
    "iso:country":"KP",
    "name:kor_x_preferred":[
        "\ud0d5\uc9c0\ub3d9"
    ],
    "name:kor_x_variant":[
        "T\u2019angji-dong"
    ],
    "wof:name":"T'angji-dong",
    "wof:placetype":"locality"
},
  "geometry": {"coordinates":[126.46693999999999,38.49944],"type":"Point"}
}