{
  "type": "Feature",
  "properties": {
    "gn:admin1_code":"15.0",
    "gn:asciiname":"galaenamumal",
    "gn:country_code":"KP",
    "gn:dem":291,
    "gn:feature_class":"P",
    "gn:feature_code":"PPL",
    "gn:name":"\uac00\ub798\ub098\ubb34\ub9d0",
    "gn:population":0,
    "gn:timezone":"Asia/Pyongyang",
    "iso:country":"KP",
    "wof:name":"galaenamumal",
    "wof:placetype":"locality"
},
  "geometry": {"coordinates":[126.62,39.40556],"type":"Point"}
}