{
  "type": "Feature",
  "properties": {
    "gn:admin1_code":"17.0",
    "gn:asciiname":"Hyondong-mal",
    "gn:cc2":"KP",
    "gn:country_code":"KP",
    "gn:dem":24,
    "gn:feature_class":"P",
    "gn:feature_code":"PPL",
    "gn:name":"Hy\u014fnd\u014fng-mal",
    "gn:population":0,
    "gn:timezone":"Asia/Pyongyang",
    "iso:country":"KP",
    "name:und_x_variant":[
        "Hy\u014fnd\u014fng-ni",
        "\ud604\ub355\ub9d0",
        "Hy\u014fnd\u014fng-mal"
    ],
    "wof:name":"Hyondong-mal",
    "wof:placetype":"locality"
},
  "geometry": {"coordinates":[129.66777999999999,41.63444000000001],"type":"Point"}
}