{
  "type": "Feature",
  "properties": {
    "gn:admin1_code":"3.0",
    "gn:admin2_code":"Kow\u014fn-gun",
    "gn:asciiname":"Hagodo-ri",
    "gn:cc2":"KP",
    "gn:country_code":"KP",
    "gn:dem":6,
    "gn:feature_class":"P",
    "gn:feature_code":"PPL",
    "gn:name":"Hagodo-ri",
    "gn:population":0,
    "gn:timezone":"Asia/Pyongyang",
    "iso:country":"KP",
    "name:und_x_variant":[
        "Hakodo-ri",
        "\ud558\uace0\ub3c4\ub9ac",
        "Hagodo-ri"
    ],
    "wof:name":"Hagodo-ri",
    "wof:placetype":"locality"
},
  "geometry": {"coordinates":[127.27500000000001,39.435],"type":"Point"}
}