{
  "type": "Feature",
  "properties": {
    "gn:admin1_code":"15.0",
    "gn:asciiname":"Kirhyol-li",
    "gn:country_code":"KP",
    "gn:dem":470,
    "gn:feature_class":"P",
    "gn:feature_code":"PPL",
    "gn:name":"Kirhy\u014fl-li",
    "gn:population":0,
    "gn:timezone":"Asia/Pyongyang",
    "iso:country":"KP",
    "name:und_x_variant":[
        "\uae38\ud604\ub9ac",
        "Kirhy\u014fl-li"
    ],
    "wof:name":"Kirhyol-li",
    "wof:placetype":"locality"
},
  "geometry": {"coordinates":[126.84583000000001,39.93083],"type":"Point"}
}