{
  "type": "Feature",
  "properties": {
    "gn:admin1_code":"12.0",
    "gn:asciiname":"T'aemoe",
    "gn:country_code":"KP",
    "gn:dem":27,
    "gn:feature_class":"P",
    "gn:feature_code":"PPL",
    "gn:name":"T\u2019aemoe",
    "gn:population":0,
    "gn:timezone":"Asia/Pyongyang",
    "iso:country":"KP",
    "name:und_x_variant":[
        "Taesan",
        "\ud0dc\ubafc",
        "T\u2019aemoe",
        "Taemoe"
    ],
    "wof:name":"T'aemoe",
    "wof:placetype":"locality"
},
  "geometry": {"coordinates":[125.73389,38.87083],"type":"Point"}
}