{
  "type": "Feature",
  "properties": {
    "gn:admin1_code":"7.0",
    "gn:asciiname":"Hadang-dong",
    "gn:country_code":"KP",
    "gn:dem":10,
    "gn:feature_class":"P",
    "gn:feature_code":"PPL",
    "gn:name":"Hadang-dong",
    "gn:population":0,
    "gn:timezone":"Asia/Pyongyang",
    "iso:country":"KP",
    "wof:name":"Hadang-dong",
    "wof:placetype":"locality"
},
  "geometry": {"coordinates":[125.78639,38.43306],"type":"Point"}
}