{
  "type": "Feature",
  "properties": {
    "gn:admin1_code":"6.0",
    "gn:asciiname":"Myongu-ri",
    "gn:country_code":"KP",
    "gn:dem":127,
    "gn:feature_class":"P",
    "gn:feature_code":"PPL",
    "gn:name":"My\u014fngu-ri",
    "gn:population":0,
    "gn:timezone":"Asia/Pyongyang",
    "iso:country":"KP",
    "name:kor_x_preferred":[
        "\uba85\uc6b0\ub9ac"
    ],
    "name:kor_x_variant":[
        "My\u014fngu-ri"
    ],
    "wof:name":"Myongu-ri",
    "wof:placetype":"locality"
},
  "geometry": {"coordinates":[125.12694,38.46722000000001],"type":"Point"}
}