{
  "type": "Feature",
  "properties": {
    "gn:admin1_code":"3.0",
    "gn:asciiname":"Mawidogi",
    "gn:country_code":"KP",
    "gn:dem":408,
    "gn:feature_class":"P",
    "gn:feature_code":"PPL",
    "gn:name":"Mawid\u014fgi",
    "gn:population":0,
    "gn:timezone":"Asia/Pyongyang",
    "iso:country":"KP",
    "name:und_x_variant":[
        "Mawid\u014fk",
        "Mawid\u014fgi",
        "\ub9c8\uc704\ub2e5\uc774"
    ],
    "wof:name":"Mawidogi",
    "wof:placetype":"locality"
},
  "geometry": {"coordinates":[128.39816999999999,40.39943],"type":"Point"}
}