{
  "type": "Feature",
  "properties": {
    "gn:admin1_code":"3.0",
    "gn:asciiname":"Changjong-ni",
    "gn:country_code":"KP",
    "gn:dem":5,
    "gn:feature_class":"P",
    "gn:feature_code":"PPL",
    "gn:name":"Changj\u014fng-ni",
    "gn:population":0,
    "gn:timezone":"Asia/Pyongyang",
    "iso:country":"KP",
    "name:eng_x_preferred":[
        "Changjong"
    ],
    "name:eng_x_variant":[
        "Changjong-ni"
    ],
    "name:und_x_variant":[
        "\uc7a5\uc815\ub9ac",
        "Changj\u014fng-ni"
    ],
    "wof:name":"Changjong",
    "wof:placetype":"locality"
},
  "geometry": {"coordinates":[127.97083000000001,40.02306],"type":"Point"}
}