{
  "type": "Feature",
  "properties": {
    "gn:admin1_code":"3.0",
    "gn:asciiname":"Poch'ol-li",
    "gn:country_code":"KP",
    "gn:dem":26,
    "gn:feature_class":"P",
    "gn:feature_code":"PPL",
    "gn:name":"Poch\u2019\u014fl-li",
    "gn:population":0,
    "gn:timezone":"Asia/Pyongyang",
    "iso:country":"KP",
    "name:und_x_variant":[
        "Poch\u2019\u014fn-ni",
        "Poch\u2019\u014fl-li",
        "\ubcf4\ucc9c\ub9ac"
    ],
    "wof:name":"Poch'ol-li",
    "wof:placetype":"locality"
},
  "geometry": {"coordinates":[128.40267,40.18683],"type":"Point"}
}