{
  "type": "Feature",
  "properties": {
    "gn:admin1_code":"6.0",
    "gn:asciiname":"Unghyon-dong",
    "gn:country_code":"KP",
    "gn:dem":61,
    "gn:feature_class":"P",
    "gn:feature_code":"PPL",
    "gn:name":"Unghy\u014fn-dong",
    "gn:population":0,
    "gn:timezone":"Asia/Pyongyang",
    "iso:country":"KP",
    "name:kor_x_preferred":[
        "\uc6c5\ud604\ub3d9"
    ],
    "name:kor_x_variant":[
        "Unghy\u014fn-dong"
    ],
    "wof:name":"Unghyon-dong",
    "wof:placetype":"locality"
},
  "geometry": {"coordinates":[125.13639000000001,38.31972],"type":"Point"}
}