{
  "type": "Feature",
  "properties": {
    "gn:admin1_code":"17.0",
    "gn:asciiname":"Imdong-ni",
    "gn:country_code":"KP",
    "gn:dem":430,
    "gn:feature_class":"P",
    "gn:feature_code":"PPL",
    "gn:name":"Imdong-ni",
    "gn:population":0,
    "gn:timezone":"Asia/Pyongyang",
    "iso:country":"KP",
    "name:eng_x_preferred":[
        "Imdong"
    ],
    "name:eng_x_variant":[
        "Imdong-ni"
    ],
    "name:kor_x_preferred":[
        "\ub9bc\ub3d9\ub9ac"
    ],
    "wof:name":"Imdong",
    "wof:placetype":"locality"
},
  "geometry": {"coordinates":[129.14523,41.03273],"type":"Point"}
}