{
  "type": "Feature",
  "properties": {
    "gn:admin1_code":"15.0",
    "gn:asciiname":"Chung-dong",
    "gn:country_code":"KP",
    "gn:dem":68,
    "gn:feature_class":"P",
    "gn:feature_code":"PPL",
    "gn:name":"Chung-dong",
    "gn:population":0,
    "gn:timezone":"Asia/Pyongyang",
    "iso:country":"KP",
    "wof:name":"Chung-dong",
    "wof:placetype":"locality"
},
  "geometry": {"coordinates":[125.86556000000002,39.34333],"type":"Point"}
}