{
  "type": "Feature",
  "properties": {
    "gn:admin1_code":"6.0",
    "gn:asciiname":"Sambong-dong",
    "gn:country_code":"KP",
    "gn:dem":72,
    "gn:feature_class":"P",
    "gn:feature_code":"PPL",
    "gn:name":"Sambong-dong",
    "gn:population":0,
    "gn:timezone":"Asia/Pyongyang",
    "iso:country":"KP",
    "name:und_x_variant":[
        "\uc0bc\ubd09\ub3d9",
        "Sambong-dong"
    ],
    "wof:name":"Sambong-dong",
    "wof:placetype":"locality"
},
  "geometry": {"coordinates":[125.22083000000001,38.21833],"type":"Point"}
}