{
  "type": "Feature",
  "properties": {
    "gn:admin1_code":"0.0",
    "gn:asciiname":"P'ungho-ri",
    "gn:country_code":"KP",
    "gn:dem":3,
    "gn:feature_class":"P",
    "gn:feature_code":"PPL",
    "gn:name":"P\u2019ungho-ri",
    "gn:population":0,
    "gn:timezone":"Asia/Pyongyang",
    "iso:country":"KP",
    "name:kor_x_preferred":[
        "\ud48d\ud638\ub9ac"
    ],
    "name:und_x_variant":[
        "P\u2019ungho-ri"
    ],
    "wof:name":"P'ungho-ri",
    "wof:placetype":"locality"
},
  "geometry": {"coordinates":[127.41667,39.75],"type":"Point"}
}