{
  "type": "Feature",
  "properties": {
    "gn:admin1_code":"15.0",
    "gn:asciiname":"Taesong-ni",
    "gn:country_code":"KP",
    "gn:dem":26,
    "gn:feature_class":"P",
    "gn:feature_code":"PPL",
    "gn:name":"Taes\u014fng-ni",
    "gn:population":0,
    "gn:timezone":"Asia/Pyongyang",
    "iso:country":"KP",
    "wof:name":"Taesong-ni",
    "wof:placetype":"locality"
},
  "geometry": {"coordinates":[125.41861000000002,38.82861],"type":"Point"}
}