{
  "type": "Feature",
  "properties": {
    "gn:admin1_code":"9.0",
    "gn:asciiname":"Songhang-ni",
    "gn:country_code":"KP",
    "gn:dem":8,
    "gn:feature_class":"P",
    "gn:feature_code":"PPL",
    "gn:name":"Songhang-ni",
    "gn:population":0,
    "gn:timezone":"Asia/Pyongyang",
    "iso:country":"KP",
    "name:und_x_variant":[
        "\uc1a1\ud559\ub9ac"
    ],
    "wof:name":"Songhang-ni",
    "wof:placetype":"locality"
},
  "geometry": {"coordinates":[127.50778,39.09111],"type":"Point"}
}