{
  "type": "Feature",
  "properties": {
    "gn:admin1_code":"15.0",
    "gn:admin2_code":"P\u2019\u014fngw\u014fn-gun",
    "gn:asciiname":"Sinhung-ni",
    "gn:country_code":"KP",
    "gn:dem":68,
    "gn:feature_class":"P",
    "gn:feature_code":"PPL",
    "gn:name":"Sinh\u016dng-ni",
    "gn:population":0,
    "gn:timezone":"Asia/Pyongyang",
    "iso:country":"KP",
    "wof:name":"Sinhung-ni",
    "wof:placetype":"locality"
},
  "geometry": {"coordinates":[125.625,39.27417],"type":"Point"}
}