{
  "type": "Feature",
  "properties": {
    "gn:admin1_code":"17.0",
    "gn:asciiname":"Ch'ayu-dong",
    "gn:country_code":"KP",
    "gn:dem":715,
    "gn:feature_class":"P",
    "gn:feature_code":"PPL",
    "gn:name":"Ch\u2019ayu-dong",
    "gn:population":0,
    "gn:timezone":"Asia/Pyongyang",
    "iso:country":"KP",
    "name:und_x_variant":[
        "Ch\u2019ary\u014fng-dong",
        "\ucc28\uc720\ub3d9",
        "Ch\u2019ayu-dong"
    ],
    "wof:name":"Ch'ayu-dong",
    "wof:placetype":"locality"
},
  "geometry": {"coordinates":[129.53749999999999,42.15806],"type":"Point"}
}