{
  "type": "Feature",
  "properties": {
    "gn:admin1_code":"11.0",
    "gn:asciiname":"Tokbawi",
    "gn:country_code":"KP",
    "gn:dem":2,
    "gn:feature_class":"P",
    "gn:feature_code":"PPL",
    "gn:name":"T\u014fkbawi",
    "gn:population":0,
    "gn:timezone":"Asia/Pyongyang",
    "iso:country":"KP",
    "name:und_x_variant":[
        "T\u014fgam",
        "T\u014fkbawi"
    ],
    "wof:name":"Tokbawi",
    "wof:placetype":"locality"
},
  "geometry": {"coordinates":[124.73333,39.75],"type":"Point"}
}