{
  "type": "Feature",
  "properties": {
    "gn:admin1_code":"17.0",
    "gn:asciiname":"Pak-kol",
    "gn:country_code":"KP",
    "gn:dem":268,
    "gn:feature_class":"P",
    "gn:feature_code":"PPL",
    "gn:name":"Pak-kol",
    "gn:population":0,
    "gn:timezone":"Asia/Pyongyang",
    "iso:country":"KP",
    "name:und_x_variant":[
        "\ubc15\uace8",
        "Pat-kol",
        "Pak-kol"
    ],
    "wof:name":"Pak-kol",
    "wof:placetype":"locality"
},
  "geometry": {"coordinates":[129.90778,42.72167],"type":"Point"}
}