{
  "type": "Feature",
  "properties": {
    "gn:admin1_code":"15.0",
    "gn:asciiname":"Hyangsang-ni",
    "gn:country_code":"KP",
    "gn:dem":224,
    "gn:feature_class":"P",
    "gn:feature_code":"PPL",
    "gn:name":"Hyangsang-ni",
    "gn:population":0,
    "gn:timezone":"Asia/Pyongyang",
    "iso:country":"KP",
    "name:eng_x_preferred":[
        "Hyangsang"
    ],
    "name:eng_x_variant":[
        "Hyangsang-ni"
    ],
    "name:und_x_variant":[
        "\ud5a5\uc0c1\ub9ac",
        "Hyangsang-ni"
    ],
    "wof:name":"Hyangsang",
    "wof:placetype":"locality"
},
  "geometry": {"coordinates":[126.24388999999999,39.82583],"type":"Point"}
}