{
  "type": "Feature",
  "properties": {
    "gn:admin1_code":"6.0",
    "gn:asciiname":"Hangnyong-dong",
    "gn:country_code":"KP",
    "gn:dem":45,
    "gn:feature_class":"P",
    "gn:feature_code":"PPL",
    "gn:name":"Hangny\u014fng-dong",
    "gn:population":0,
    "gn:timezone":"Asia/Pyongyang",
    "iso:country":"KP",
    "name:und_x_variant":[
        "\ud559\ub839\ub3d9",
        "Hangny\u014fng-dong"
    ],
    "wof:name":"Hangnyong-dong",
    "wof:placetype":"locality"
},
  "geometry": {"coordinates":[125.01721999999999,38.55472],"type":"Point"}
}