{
  "type": "Feature",
  "properties": {
    "gn:admin1_code":"11.0",
    "gn:asciiname":"Pulgurang",
    "gn:country_code":"KP",
    "gn:dem":11,
    "gn:feature_class":"P",
    "gn:feature_code":"PPL",
    "gn:name":"Pulgurang",
    "gn:population":0,
    "gn:timezone":"Asia/Pyongyang",
    "iso:country":"KP",
    "name:und_x_variant":[
        "\ubd88\uad6c\ub791",
        "Pulgurang"
    ],
    "wof:name":"Pulgurang",
    "wof:placetype":"locality"
},
  "geometry": {"coordinates":[124.22750000000001,39.7925],"type":"Point"}
}