{
  "type": "Feature",
  "properties": {
    "gn:admin1_code":"17.0",
    "gn:asciiname":"Tokch'ol-li",
    "gn:country_code":"KP",
    "gn:dem":97,
    "gn:feature_class":"P",
    "gn:feature_code":"PPL",
    "gn:name":"T\u014fkch\u2019ol-li",
    "gn:population":0,
    "gn:timezone":"Asia/Pyongyang",
    "iso:country":"KP",
    "name:und_x_variant":[
        "\ub355\ucd0c\ub9ac",
        "T\u014fkch\u2019ol-li"
    ],
    "wof:name":"Tokch'ol-li",
    "wof:placetype":"locality"
},
  "geometry": {"coordinates":[130.14639,42.64056],"type":"Point"}
}