{
  "type": "Feature",
  "properties": {
    "gn:admin1_code":"11.0",
    "gn:asciiname":"Ha-dong",
    "gn:country_code":"KP",
    "gn:dem":83,
    "gn:feature_class":"P",
    "gn:feature_code":"PPL",
    "gn:name":"Ha-dong",
    "gn:population":0,
    "gn:timezone":"Asia/Pyongyang",
    "iso:country":"KP",
    "wof:name":"Ha-dong",
    "wof:placetype":"locality"
},
  "geometry": {"coordinates":[125.81861000000001,39.97722],"type":"Point"}
}