{
  "type": "Feature",
  "properties": {
    "gn:admin1_code":"17.0",
    "gn:asciiname":"T'ongi-dong",
    "gn:country_code":"KP",
    "gn:dem":136,
    "gn:feature_class":"P",
    "gn:feature_code":"PPL",
    "gn:name":"T\u2019ongi-dong",
    "gn:population":0,
    "gn:timezone":"Asia/Pyongyang",
    "iso:country":"KP",
    "name:und_x_variant":[
        "\ud1b5\uc774\ub3d9",
        "T\u2019ongi-dong"
    ],
    "wof:name":"T'ongi-dong",
    "wof:placetype":"locality"
},
  "geometry": {"coordinates":[129.54443999999998,41.20194],"type":"Point"}
}