{
  "type": "Feature",
  "properties": {
    "gn:admin1_code":"6.0",
    "gn:asciiname":"Pullyok",
    "gn:country_code":"KP",
    "gn:dem":43,
    "gn:feature_class":"P",
    "gn:feature_code":"PPL",
    "gn:name":"Pully\u014fk",
    "gn:population":0,
    "gn:timezone":"Asia/Pyongyang",
    "iso:country":"KP",
    "wof:name":"Pullyok",
    "wof:placetype":"locality"
},
  "geometry": {"coordinates":[125.61472000000001,38.34583],"type":"Point"}
}