{
  "type": "Feature",
  "properties": {
    "gn:admin1_code":"3.0",
    "gn:asciiname":"Poju-ri",
    "gn:country_code":"KP",
    "gn:dem":159,
    "gn:feature_class":"P",
    "gn:feature_code":"PPL",
    "gn:name":"Poju-ri",
    "gn:population":0,
    "gn:timezone":"Asia/Pyongyang",
    "iso:country":"KP",
    "name:und_x_variant":[
        "\ud3ec\uc8fc\ub9ac"
    ],
    "wof:name":"Poju-ri",
    "wof:placetype":"locality"
},
  "geometry": {"coordinates":[128.17167000000001,40.04672],"type":"Point"}
}