{
  "type": "Feature",
  "properties": {
    "gn:admin1_code":"17.0",
    "gn:asciiname":"Kwaam-dong",
    "gn:country_code":"KP",
    "gn:dem":465,
    "gn:feature_class":"P",
    "gn:feature_code":"PPL",
    "gn:name":"Kwaam-dong",
    "gn:population":0,
    "gn:timezone":"Asia/Pyongyang",
    "iso:country":"KP",
    "name:und_x_variant":[
        "\uacfc\uc554\ub3d9",
        "Kwaam-dong"
    ],
    "wof:name":"Kwaam-dong",
    "wof:placetype":"locality"
},
  "geometry": {"coordinates":[129.94556,42.60333],"type":"Point"}
}