{
  "type": "Feature",
  "properties": {
    "gn:admin1_code":"9.0",
    "gn:asciiname":"Namch'on",
    "gn:country_code":"KP",
    "gn:dem":479,
    "gn:feature_class":"P",
    "gn:feature_code":"PPL",
    "gn:name":"Namch\u2019on",
    "gn:population":0,
    "gn:timezone":"Asia/Pyongyang",
    "iso:country":"KP",
    "name:und_x_variant":[
        "\ub0a8\ucd0c",
        "Namch\u2019on"
    ],
    "wof:name":"Namch'on",
    "wof:placetype":"locality"
},
  "geometry": {"coordinates":[127.58138999999998,38.62944],"type":"Point"}
}