{
  "type": "Feature",
  "properties": {
    "gn:admin1_code":"17.0",
    "gn:admin2_code":"Musan-gun",
    "gn:asciiname":"Ch'op'yong-dong",
    "gn:country_code":"KP",
    "gn:dem":839,
    "gn:feature_class":"P",
    "gn:feature_code":"PPL",
    "gn:name":"Ch\u2019op\u2019y\u014fng-dong",
    "gn:population":0,
    "gn:timezone":"Asia/Pyongyang",
    "iso:country":"KP",
    "wof:name":"Ch'op'yong-dong",
    "wof:placetype":"locality"
},
  "geometry": {"coordinates":[129.14944,41.99056],"type":"Point"}
}