{
  "type": "Feature",
  "properties": {
    "gn:admin1_code":"7.0",
    "gn:asciiname":"Konggit'o",
    "gn:country_code":"KP",
    "gn:dem":32,
    "gn:feature_class":"P",
    "gn:feature_code":"PPL",
    "gn:name":"Konggit\u2019\u014f",
    "gn:population":0,
    "gn:timezone":"Asia/Pyongyang",
    "iso:country":"KP",
    "name:und_x_variant":[
        "\uacf5\uae30\ud130",
        "Konggit\u2019\u014f"
    ],
    "wof:name":"Konggit'o",
    "wof:placetype":"locality"
},
  "geometry": {"coordinates":[126.44194,38.22944],"type":"Point"}
}