{
  "type": "Feature",
  "properties": {
    "gn:admin1_code":"13.0",
    "gn:asciiname":"Kyohangch'on",
    "gn:country_code":"KP",
    "gn:dem":1022,
    "gn:feature_class":"P",
    "gn:feature_code":"PPL",
    "gn:name":"Kyohangch\u2019on",
    "gn:population":0,
    "gn:timezone":"Asia/Pyongyang",
    "iso:country":"KP",
    "wof:name":"Kyohangch'on",
    "wof:placetype":"locality"
},
  "geometry": {"coordinates":[128.05111000000002,41.16806],"type":"Point"}
}