{
  "type": "Feature",
  "properties": {
    "gn:admin1_code":"1.0",
    "gn:asciiname":"T'akkoji",
    "gn:country_code":"KP",
    "gn:dem":402,
    "gn:feature_class":"P",
    "gn:feature_code":"PPL",
    "gn:name":"T\u2019akkoji",
    "gn:population":0,
    "gn:timezone":"Asia/Pyongyang",
    "iso:country":"KP",
    "name:kor_x_preferred":[
        "T\u2019akkoji"
    ],
    "name:kor_x_variant":[
        "\ud0c1\uace0\uc9c0",
        "T\u2019akk\u014f-ri",
        "\ud0c1\uac70\ub9ac"
    ],
    "name:und_x_variant":[
        "\ud0c1\uac70\ub9ac",
        "T\u2019akk\u014f-ri"
    ],
    "wof:name":"T'akkoji",
    "wof:placetype":"locality"
},
  "geometry": {"coordinates":[126.56728,40.75606],"type":"Point"}
}