{
  "type": "Feature",
  "properties": {
    "gn:admin1_code":"15.0",
    "gn:asciiname":"Mun-dong",
    "gn:country_code":"KP",
    "gn:dem":19,
    "gn:feature_class":"P",
    "gn:feature_code":"PPL",
    "gn:name":"Mun-dong",
    "gn:population":0,
    "gn:timezone":"Asia/Pyongyang",
    "iso:country":"KP",
    "wof:name":"Mun-dong",
    "wof:placetype":"locality"
},
  "geometry": {"coordinates":[125.56139,39.04889],"type":"Point"}
}