{
  "type": "Feature",
  "properties": {
    "gn:admin1_code":"15.0",
    "gn:asciiname":"Yu-dong",
    "gn:country_code":"KP",
    "gn:dem":23,
    "gn:feature_class":"P",
    "gn:feature_code":"PPL",
    "gn:name":"Yu-dong",
    "gn:population":0,
    "gn:timezone":"Asia/Pyongyang",
    "iso:country":"KP",
    "name:und_x_variant":[
        "\uc720\ub3d9",
        "Yu-dong"
    ],
    "wof:name":"Yu-dong",
    "wof:placetype":"locality"
},
  "geometry": {"coordinates":[125.39333000000001,38.78861],"type":"Point"}
}