{
  "type": "Feature",
  "properties": {
    "gn:admin1_code":"15.0",
    "gn:asciiname":"Hwangdang",
    "gn:country_code":"KP",
    "gn:dem":487,
    "gn:feature_class":"P",
    "gn:feature_code":"PPL",
    "gn:name":"Hwangdang",
    "gn:population":0,
    "gn:timezone":"Asia/Pyongyang",
    "iso:country":"KP",
    "name:kor_x_preferred":[
        "\ud669\ub2f9"
    ],
    "wof:name":"Hwangdang",
    "wof:placetype":"locality"
},
  "geometry": {"coordinates":[126.98917,39.20611],"type":"Point"}
}