{
  "type": "Feature",
  "properties": {
    "gn:admin1_code":"15.0",
    "gn:asciiname":"Songjang",
    "gn:country_code":"KP",
    "gn:dem":92,
    "gn:feature_class":"P",
    "gn:feature_code":"PPL",
    "gn:name":"S\u014fngjang",
    "gn:population":0,
    "gn:timezone":"Asia/Pyongyang",
    "iso:country":"KP",
    "wof:name":"Songjang",
    "wof:placetype":"locality"
},
  "geometry": {"coordinates":[125.3725,39.01417],"type":"Point"}
}