{
  "type": "Feature",
  "properties": {
    "gn:admin1_code":"3.0",
    "gn:asciiname":"Changhudok",
    "gn:country_code":"KP",
    "gn:dem":624,
    "gn:feature_class":"P",
    "gn:feature_code":"PPL",
    "gn:name":"Changhud\u014fk",
    "gn:population":0,
    "gn:timezone":"Asia/Pyongyang",
    "iso:country":"KP",
    "name:und_x_variant":[
        "\uc7a5\ud6c4\ub355",
        "Changhud\u014fk"
    ],
    "wof:name":"Changhudok",
    "wof:placetype":"locality"
},
  "geometry": {"coordinates":[128.97971999999999,40.68583],"type":"Point"}
}