{
  "type": "Feature",
  "properties": {
    "gn:admin1_code":"11.0",
    "gn:asciiname":"In'go-dong",
    "gn:country_code":"KP",
    "gn:dem":12,
    "gn:feature_class":"P",
    "gn:feature_code":"PPL",
    "gn:name":"In\u2019go-dong",
    "gn:population":0,
    "gn:timezone":"Asia/Pyongyang",
    "iso:country":"KP",
    "name:und_x_variant":[
        "\uc778\uace0\ub3d9",
        "In\u2019go-dong"
    ],
    "wof:name":"In'go-dong",
    "wof:placetype":"locality"
},
  "geometry": {"coordinates":[124.46693999999999,39.935],"type":"Point"}
}