{
  "type": "Feature",
  "properties": {
    "gn:admin1_code":"9.0",
    "gn:asciiname":"Samoktongnisesang-dong",
    "gn:country_code":"KP",
    "gn:dem":595,
    "gn:feature_class":"P",
    "gn:feature_code":"PPL",
    "gn:name":"Sam\u014fktongnisesang-dong",
    "gn:population":0,
    "gn:timezone":"Asia/Pyongyang",
    "iso:country":"KP",
    "wof:name":"Samoktongnisesang-dong",
    "wof:placetype":"locality"
},
  "geometry": {"coordinates":[128.04527999999999,38.57278],"type":"Point"}
}