{
  "type": "Feature",
  "properties": {
    "gn:admin1_code":"12.0",
    "gn:asciiname":"Sangdangjong",
    "gn:country_code":"KP",
    "gn:dem":19,
    "gn:feature_class":"P",
    "gn:feature_code":"PPL",
    "gn:name":"Sangdangj\u014fng",
    "gn:population":0,
    "gn:timezone":"Asia/Pyongyang",
    "iso:country":"KP",
    "name:kor_x_preferred":[
        "\uc0c1\ub2f9\uc815"
    ],
    "name:und_x_variant":[
        "Sangdangj\u014fng",
        "Sangdangjeong"
    ],
    "wof:name":"Sangdangjong",
    "wof:placetype":"locality"
},
  "geometry": {"coordinates":[125.81683,38.91949],"type":"Point"}
}