{
  "type": "Feature",
  "properties": {
    "gn:admin1_code":"12.0",
    "gn:asciiname":"Sangch'u-dong",
    "gn:country_code":"KP",
    "gn:dem":60,
    "gn:feature_class":"P",
    "gn:feature_code":"PPL",
    "gn:name":"Sangch\u2019u-dong",
    "gn:population":0,
    "gn:timezone":"Asia/Pyongyang",
    "iso:country":"KP",
    "name:kor_x_preferred":[
        "Sangch\u2019u-dong"
    ],
    "name:kor_x_variant":[
        "\uc0c1\ucd94\ub3d9",
        "\uc6c3\uac00\ub798\uc6b8"
    ],
    "name:und_x_variant":[
        "Ukkaraeul",
        "Sangchudong"
    ],
    "wof:name":"Sangch'u-dong",
    "wof:placetype":"locality"
},
  "geometry": {"coordinates":[125.80306000000002,39.14167],"type":"Point"}
}