{
  "type": "Feature",
  "properties": {
    "gn:admin1_code":"17.0",
    "gn:asciiname":"Sowonp'o",
    "gn:country_code":"KP",
    "gn:dem":318,
    "gn:feature_class":"P",
    "gn:feature_code":"PPL",
    "gn:name":"S\u014fw\u014fnp\u2019o",
    "gn:population":0,
    "gn:timezone":"Asia/Pyongyang",
    "iso:country":"KP",
    "name:und_x_variant":[
        "\uc11c\uc6d0\ud3ec",
        "S\u014fw\u014fnp\u2019o"
    ],
    "wof:name":"Sowonp'o",
    "wof:placetype":"locality"
},
  "geometry": {"coordinates":[129.89306000000002,42.56889],"type":"Point"}
}