{
  "type": "Feature",
  "properties": {
    "gn:admin1_code":"15.0",
    "gn:asciiname":"Soppak-kol",
    "gn:country_code":"KP",
    "gn:dem":92,
    "gn:feature_class":"P",
    "gn:feature_code":"PPL",
    "gn:name":"S\u014fppak-kol",
    "gn:population":0,
    "gn:timezone":"Asia/Pyongyang",
    "iso:country":"KP",
    "wof:name":"Soppak-kol",
    "wof:placetype":"locality"
},
  "geometry": {"coordinates":[125.59139,39.24056],"type":"Point"}
}