{
  "type": "Feature",
  "properties": {
    "gn:admin1_code":"11.0",
    "gn:asciiname":"Puhwang-ni",
    "gn:cc2":"KP",
    "gn:country_code":"KP",
    "gn:dem":34,
    "gn:feature_class":"P",
    "gn:feature_code":"PPL",
    "gn:name":"Puhwang-ni",
    "gn:population":0,
    "gn:timezone":"Asia/Pyongyang",
    "iso:country":"KP",
    "name:und_x_variant":[
        "Puwhang-dong",
        "Puhwang-ni"
    ],
    "wof:name":"Puhwang-ni",
    "wof:placetype":"locality"
},
  "geometry": {"coordinates":[124.76917,39.84111],"type":"Point"}
}