{
  "type": "Feature",
  "properties": {
    "gn:admin1_code":"11.0",
    "gn:asciiname":"Morae-dong",
    "gn:country_code":"KP",
    "gn:dem":7,
    "gn:feature_class":"P",
    "gn:feature_code":"PPL",
    "gn:name":"Morae-dong",
    "gn:population":0,
    "gn:timezone":"Asia/Pyongyang",
    "iso:country":"KP",
    "name:und_x_variant":[
        "\ubaa8\ub798\ub3d9",
        "Morae-dong"
    ],
    "wof:name":"Morae-dong",
    "wof:placetype":"locality"
},
  "geometry": {"coordinates":[124.21361,39.80194],"type":"Point"}
}