{
  "type": "Feature",
  "properties": {
    "gn:admin1_code":"3.0",
    "gn:asciiname":"Chon'ga-ri",
    "gn:country_code":"KP",
    "gn:dem":67,
    "gn:feature_class":"P",
    "gn:feature_code":"PPL",
    "gn:name":"Ch\u014fn\u2019ga-ri",
    "gn:population":0,
    "gn:timezone":"Asia/Pyongyang",
    "iso:country":"KP",
    "name:kor_x_preferred":[
        "\uc804\uac00\ub9ac"
    ],
    "name:kor_x_variant":[
        "Ch\u014fn\u2019ga-ri"
    ],
    "wof:name":"Chon'ga-ri",
    "wof:placetype":"locality"
},
  "geometry": {"coordinates":[127.08722,39.45167],"type":"Point"}
}