{
  "type": "Feature",
  "properties": {
    "gn:admin1_code":"11.0",
    "gn:asciiname":"P'iam",
    "gn:country_code":"KP",
    "gn:dem":18,
    "gn:feature_class":"P",
    "gn:feature_code":"PPL",
    "gn:name":"P\u2019iam",
    "gn:population":0,
    "gn:timezone":"Asia/Pyongyang",
    "iso:country":"KP",
    "name:kor_x_preferred":[
        "\ud53c\uc554"
    ],
    "name:kor_x_variant":[
        "P\u2019iam"
    ],
    "wof:name":"P'iam",
    "wof:placetype":"locality"
},
  "geometry": {"coordinates":[125.36667,39.61667],"type":"Point"}
}