{
  "type": "Feature",
  "properties": {
    "gn:admin1_code":"11.0",
    "gn:asciiname":"Namsan",
    "gn:country_code":"KP",
    "gn:dem":37,
    "gn:feature_class":"P",
    "gn:feature_code":"PPL",
    "gn:name":"Namsan",
    "gn:population":0,
    "gn:timezone":"Asia/Pyongyang",
    "iso:country":"KP",
    "name:kor_x_preferred":[
        "\ub0a8\uc0b0"
    ],
    "wof:name":"Namsan",
    "wof:placetype":"locality"
},
  "geometry": {"coordinates":[124.99527999999999,39.78056],"type":"Point"}
}