{
  "type": "Feature",
  "properties": {
    "gn:admin1_code":"1.0",
    "gn:asciiname":"Yonghae-ri",
    "gn:country_code":"KP",
    "gn:dem":165,
    "gn:feature_class":"P",
    "gn:feature_code":"PPL",
    "gn:name":"Yonghae-ri",
    "gn:population":0,
    "gn:timezone":"Asia/Pyongyang",
    "iso:country":"KP",
    "name:und_x_variant":[
        "\ub8e1\ud574\ub9ac",
        "Yonghae-ri"
    ],
    "wof:name":"Yonghae-ri",
    "wof:placetype":"locality"
},
  "geometry": {"coordinates":[125.72917,40.63694],"type":"Point"}
}