{
  "type": "Feature",
  "properties": {
    "gn:admin1_code":"15.0",
    "gn:admin2_code":"Pukch\u2019ang-gun",
    "gn:asciiname":"Myonghak-tong",
    "gn:country_code":"KP",
    "gn:dem":345,
    "gn:feature_class":"P",
    "gn:feature_code":"PPL",
    "gn:name":"My\u014fnghak-tong",
    "gn:population":0,
    "gn:timezone":"Asia/Pyongyang",
    "iso:country":"KP",
    "name:eng_x_preferred":[
        "Myonghak"
    ],
    "name:eng_x_variant":[
        "Myonghak-tong"
    ],
    "wof:name":"Myonghak",
    "wof:placetype":"locality"
},
  "geometry": {"coordinates":[126.15694000000001,39.54333],"type":"Point"}
}