{
  "type": "Feature",
  "properties": {
    "gn:admin1_code":"15.0",
    "gn:asciiname":"Tol-gol",
    "gn:country_code":"KP",
    "gn:dem":421,
    "gn:feature_class":"P",
    "gn:feature_code":"PPL",
    "gn:name":"Tol-gol",
    "gn:population":0,
    "gn:timezone":"Asia/Pyongyang",
    "iso:country":"KP",
    "name:kor_x_preferred":[
        "\ub3cc\uace8"
    ],
    "wof:name":"Tol-gol",
    "wof:placetype":"locality"
},
  "geometry": {"coordinates":[126.52361000000001,39.4725],"type":"Point"}
}