{
  "type": "Feature",
  "properties": {
    "gn:admin1_code":"1.0",
    "gn:asciiname":"Ch'onsong-ni",
    "gn:country_code":"KP",
    "gn:dem":327,
    "gn:feature_class":"P",
    "gn:feature_code":"PPL",
    "gn:name":"Ch\u2019\u014fns\u014fng-ni",
    "gn:population":0,
    "gn:timezone":"Asia/Pyongyang",
    "iso:country":"KP",
    "name:und_x_variant":[
        "Ch\u2019\u014fns\u014fng-dong",
        "\ucc9c\uc131\ub9ac",
        "Ch\u2019\u014fns\u014fng-ni"
    ],
    "wof:name":"Ch'onsong-ni",
    "wof:placetype":"locality"
},
  "geometry": {"coordinates":[126.37560999999999,40.97037],"type":"Point"}
}