{
  "type": "Feature",
  "properties": {
    "gn:admin1_code":"11.0",
    "gn:asciiname":"Yongdam-ni",
    "gn:country_code":"KP",
    "gn:dem":234,
    "gn:feature_class":"P",
    "gn:feature_code":"PPL",
    "gn:name":"Yongdam-ni",
    "gn:population":0,
    "gn:timezone":"Asia/Pyongyang",
    "iso:country":"KP",
    "name:und_x_variant":[
        "\uc6a9\ub2f4\ub9ac",
        "Yongdam-ni"
    ],
    "wof:name":"Yongdam-ni",
    "wof:placetype":"locality"
},
  "geometry": {"coordinates":[125.51694000000001,40.55583],"type":"Point"}
}