{
  "type": "Feature",
  "properties": {
    "gn:admin1_code":"15.0",
    "gn:asciiname":"Chongsal-li",
    "gn:country_code":"KP",
    "gn:dem":266,
    "gn:feature_class":"P",
    "gn:feature_code":"PPL",
    "gn:name":"Ch\u014fngsal-li",
    "gn:population":0,
    "gn:timezone":"Asia/Pyongyang",
    "iso:country":"KP",
    "name:kor_x_preferred":[
        "\uc815\uc0b0\ub9ac"
    ],
    "name:kor_x_variant":[
        "Ch\u014fngsal-li"
    ],
    "name:und_x_variant":[
        "Ch\u014fngsan-ni"
    ],
    "wof:name":"Chongsal-li",
    "wof:placetype":"locality"
},
  "geometry": {"coordinates":[126.58556000000002,39.04361],"type":"Point"}
}