{
  "type": "Feature",
  "properties": {
    "gn:admin1_code":"11.0",
    "gn:asciiname":"Tong-gol",
    "gn:country_code":"KP",
    "gn:dem":181,
    "gn:feature_class":"P",
    "gn:feature_code":"PPL",
    "gn:name":"Tong-gol",
    "gn:population":0,
    "gn:timezone":"Asia/Pyongyang",
    "iso:country":"KP",
    "name:kor_x_preferred":[
        "\ub3d9\uace8"
    ],
    "wof:name":"Tong-gol",
    "wof:placetype":"locality"
},
  "geometry": {"coordinates":[124.99111000000001,39.99861],"type":"Point"}
}