{
  "type": "Feature",
  "properties": {
    "gn:admin1_code":"3.0",
    "gn:asciiname":"Toksan",
    "gn:country_code":"KP",
    "gn:dem":14,
    "gn:feature_class":"P",
    "gn:feature_code":"PPL",
    "gn:name":"Toksan",
    "gn:population":0,
    "gn:timezone":"Asia/Pyongyang",
    "iso:country":"KP",
    "name:und_x_variant":[
        "\ub3c5\uc0b0",
        "Toksan"
    ],
    "wof:name":"Toksan",
    "wof:placetype":"locality"
},
  "geometry": {"coordinates":[127.40278000000001,39.72194],"type":"Point"}
}