{
  "type": "Feature",
  "properties": {
    "gn:admin1_code":"17.0",
    "gn:asciiname":"Pongam",
    "gn:country_code":"KP",
    "gn:dem":217,
    "gn:feature_class":"P",
    "gn:feature_code":"PPL",
    "gn:name":"Pongam",
    "gn:population":0,
    "gn:timezone":"Asia/Pyongyang",
    "iso:country":"KP",
    "name:und_x_variant":[
        "H\u014dgan",
        "\ubd09\uc554",
        "Pongam"
    ],
    "wof:name":"Pongam",
    "wof:placetype":"locality"
},
  "geometry": {"coordinates":[129.54611,41.155],"type":"Point"}
}