{
  "type": "Feature",
  "properties": {
    "gn:admin1_code":"13.0",
    "gn:asciiname":"Hoegol-li",
    "gn:cc2":"KP",
    "gn:country_code":"KP",
    "gn:dem":947,
    "gn:feature_class":"P",
    "gn:feature_code":"PPL",
    "gn:name":"Hoegol-li",
    "gn:population":0,
    "gn:timezone":"Asia/Pyongyang",
    "iso:country":"KP",
    "name:und_x_variant":[
        "Wangga-ri",
        "Hoegol-li"
    ],
    "wof:name":"Hoegol-li",
    "wof:placetype":"locality"
},
  "geometry": {"coordinates":[128.035,41.32417],"type":"Point"}
}