{
  "type": "Feature",
  "properties": {
    "gn:admin1_code":"11.0",
    "gn:asciiname":"Ha-gol",
    "gn:country_code":"KP",
    "gn:dem":14,
    "gn:feature_class":"P",
    "gn:feature_code":"PPL",
    "gn:name":"Ha-gol",
    "gn:population":0,
    "gn:timezone":"Asia/Pyongyang",
    "iso:country":"KP",
    "name:und_x_variant":[
        "\ud558\uace8",
        "Ha-gol"
    ],
    "wof:name":"Ha-gol",
    "wof:placetype":"locality"
},
  "geometry": {"coordinates":[124.53749999999999,40.15556],"type":"Point"}
}