{
  "type": "Feature",
  "properties": {
    "gn:admin1_code":"7.0",
    "gn:asciiname":"Hasuch'on",
    "gn:country_code":"KP",
    "gn:dem":276,
    "gn:feature_class":"P",
    "gn:feature_code":"PPL",
    "gn:name":"Hasuch\u2019on",
    "gn:population":0,
    "gn:timezone":"Asia/Pyongyang",
    "iso:country":"KP",
    "name:und_x_variant":[
        "\ud558\uc218\ucd0c",
        "Hasuch\u2019on"
    ],
    "wof:name":"Hasuch'on",
    "wof:placetype":"locality"
},
  "geometry": {"coordinates":[126.87139000000001,39.03917],"type":"Point"}
}