{
  "type": "Feature",
  "properties": {
    "gn:admin1_code":"15.0",
    "gn:asciiname":"Oun-dong",
    "gn:country_code":"KP",
    "gn:dem":390,
    "gn:feature_class":"P",
    "gn:feature_code":"PPL",
    "gn:name":"\u014e\u016dn-dong",
    "gn:population":0,
    "gn:timezone":"Asia/Pyongyang",
    "iso:country":"KP",
    "name:kor_x_preferred":[
        "\uc5b4\uc740\ub3d9"
    ],
    "name:kor_x_variant":[
        "\u014e\u016dn-dong"
    ],
    "wof:name":"Oun-dong",
    "wof:placetype":"locality"
},
  "geometry": {"coordinates":[126.91806,39.06667],"type":"Point"}
}