{
  "type": "Feature",
  "properties": {
    "gn:admin1_code":"6.0",
    "gn:asciiname":"Chunggan-dong",
    "gn:country_code":"KP",
    "gn:dem":37,
    "gn:feature_class":"P",
    "gn:feature_code":"PPL",
    "gn:name":"Chunggan-dong",
    "gn:population":0,
    "gn:timezone":"Asia/Pyongyang",
    "iso:country":"KP",
    "name:kor_x_preferred":[
        "\uc911\uac04\ub3d9"
    ],
    "wof:name":"Chunggan-dong",
    "wof:placetype":"locality"
},
  "geometry": {"coordinates":[125.88943999999999,38.05278],"type":"Point"}
}