{
  "type": "Feature",
  "properties": {
    "gn:admin1_code":"0.0",
    "gn:asciiname":"Yop'o-ri",
    "gn:country_code":"KP",
    "gn:dem":7,
    "gn:feature_class":"P",
    "gn:feature_code":"PPL",
    "gn:name":"Yop\u2019o-ri",
    "gn:population":0,
    "gn:timezone":"Asia/Pyongyang",
    "iso:country":"KP",
    "name:kor_x_preferred":[
        "\uc5ec\ud3ec\ub9ac"
    ],
    "name:und_x_variant":[
        "Y\u014dho-ri",
        "Yoppo Ri",
        "Yoppo",
        "Yop\u2019o-ri"
    ],
    "wof:name":"Yop'o-ri",
    "wof:placetype":"locality"
},
  "geometry": {"coordinates":[125.58333,38.81667],"type":"Point"}
}