{
  "type": "Feature",
  "properties": {
    "gn:admin1_code":"6.0",
    "gn:asciiname":"Muhang-ni",
    "gn:cc2":"KP",
    "gn:country_code":"KP",
    "gn:dem":98,
    "gn:feature_class":"P",
    "gn:feature_code":"PPL",
    "gn:name":"Muhang-ni",
    "gn:population":0,
    "gn:timezone":"Asia/Pyongyang",
    "iso:country":"KP",
    "name:und_x_variant":[
        "Muhak-tong",
        "Muhang-ni"
    ],
    "wof:name":"Muhang-ni",
    "wof:placetype":"locality"
},
  "geometry": {"coordinates":[125.70528,38.21389],"type":"Point"}
}