{
  "type": "Feature",
  "properties": {
    "gn:admin1_code":"3.0",
    "gn:asciiname":"Sinch'ang-nodongjagu",
    "gn:country_code":"KP",
    "gn:dem":4,
    "gn:feature_class":"P",
    "gn:feature_code":"PPL",
    "gn:name":"Sinch\u2019ang-nodongjagu",
    "gn:population":0,
    "gn:timezone":"Asia/Pyongyang",
    "iso:country":"KP",
    "name:und_x_variant":[
        "Sinch\u2019ang-ni",
        "Shinsh\u014d",
        "Sinch\u2019ang",
        "Sinsy\u014dri",
        "Shinsh\u014d-ri",
        "Sinch\u2019ang-nodongjagu",
        "\uc2e0\ucc3d\ub85c\ub3d9\uc790\uad6c"
    ],
    "wof:name":"Sinch'ang-nodongjagu",
    "wof:placetype":"locality"
},
  "geometry": {"coordinates":[128.46943999999999,40.13639000000001],"type":"Point"}
}