{
  "type": "Feature",
  "properties": {
    "gn:admin1_code":"3.0",
    "gn:asciiname":"Yun-dong",
    "gn:country_code":"KP",
    "gn:dem":572,
    "gn:feature_class":"P",
    "gn:feature_code":"PPL",
    "gn:name":"Yun-dong",
    "gn:population":0,
    "gn:timezone":"Asia/Pyongyang",
    "iso:country":"KP",
    "name:und_x_variant":[
        "\uc724\ub3d9",
        "Yun-dong"
    ],
    "wof:name":"Yun-dong",
    "wof:placetype":"locality"
},
  "geometry": {"coordinates":[126.8425,39.40917],"type":"Point"}
}