{
  "type": "Feature",
  "properties": {
    "gn:admin1_code":"0.0",
    "gn:asciiname":"Sin'gi",
    "gn:country_code":"KP",
    "gn:dem":7,
    "gn:feature_class":"P",
    "gn:feature_code":"PPL",
    "gn:name":"Sin\u2019gi",
    "gn:population":0,
    "gn:timezone":"Asia/Pyongyang",
    "iso:country":"KP",
    "name:kor_x_preferred":[
        "\uc2e0\uae30"
    ],
    "name:und_x_variant":[
        "Sin\u2019gi"
    ],
    "wof:name":"Sin'gi",
    "wof:placetype":"locality"
},
  "geometry": {"coordinates":[125.90000000000001,37.91667],"type":"Point"}
}