{
  "type": "Feature",
  "properties": {
    "gn:admin1_code":"9.0",
    "gn:asciiname":"Hyondae-dong",
    "gn:country_code":"KP",
    "gn:dem":174,
    "gn:feature_class":"P",
    "gn:feature_code":"PPL",
    "gn:name":"Hy\u014fndae-dong",
    "gn:population":0,
    "gn:timezone":"Asia/Pyongyang",
    "iso:country":"KP",
    "name:kor_x_preferred":[
        "\ud604\ub300\ub3d9"
    ],
    "name:kor_x_variant":[
        "Hy\u014fndae-dong"
    ],
    "wof:name":"Hyondae-dong",
    "wof:placetype":"locality"
},
  "geometry": {"coordinates":[127.42417,38.90083],"type":"Point"}
}