{
  "type": "Feature",
  "properties": {
    "gn:admin1_code":"7.0",
    "gn:asciiname":"Pomnae",
    "gn:country_code":"KP",
    "gn:dem":38,
    "gn:feature_class":"P",
    "gn:feature_code":"PPL",
    "gn:name":"P\u014fmnae",
    "gn:population":0,
    "gn:timezone":"Asia/Pyongyang",
    "iso:country":"KP",
    "name:kor_x_preferred":[
        "\ubc95\ub0b4"
    ],
    "name:kor_x_variant":[
        "P\u014fmnae"
    ],
    "wof:name":"Pomnae",
    "wof:placetype":"locality"
},
  "geometry": {"coordinates":[126.49666999999999,38.38278],"type":"Point"}
}