{
  "type": "Feature",
  "properties": {
    "gn:admin1_code":"3.0",
    "gn:asciiname":"Hungdong-ni",
    "gn:country_code":"KP",
    "gn:dem":678,
    "gn:feature_class":"P",
    "gn:feature_code":"PPL",
    "gn:name":"H\u016dngd\u014fng-ni",
    "gn:population":0,
    "gn:timezone":"Asia/Pyongyang",
    "iso:country":"KP",
    "name:eng_x_preferred":[
        "Hungdong"
    ],
    "name:eng_x_variant":[
        "Hungdong-ni"
    ],
    "name:und_x_variant":[
        "\ud765\ub355\ub9ac",
        "H\u016dngd\u014fng-ni"
    ],
    "wof:name":"Hungdong",
    "wof:placetype":"locality"
},
  "geometry": {"coordinates":[127.84305999999999,40.25667],"type":"Point"}
}