{
  "type": "Feature",
  "properties": {
    "gn:admin1_code":"7.0",
    "gn:asciiname":"Saekko-dong",
    "gn:country_code":"KP",
    "gn:dem":87,
    "gn:feature_class":"P",
    "gn:feature_code":"PPL",
    "gn:name":"Saekko-dong",
    "gn:population":0,
    "gn:timezone":"Asia/Pyongyang",
    "iso:country":"KP",
    "name:und_x_variant":[
        "Saeko-dong",
        "Saekko-dong"
    ],
    "wof:name":"Saekko-dong",
    "wof:placetype":"locality"
},
  "geometry": {"coordinates":[126.1125,38.46028],"type":"Point"}
}