{
  "type": "Feature",
  "properties": {
    "gn:admin1_code":"9.0",
    "gn:asciiname":"Tokp'yong-ni",
    "gn:country_code":"KP",
    "gn:dem":262,
    "gn:feature_class":"P",
    "gn:feature_code":"PPL",
    "gn:name":"T\u014fkp\u2019y\u014fng-ni",
    "gn:population":0,
    "gn:timezone":"Asia/Pyongyang",
    "iso:country":"KP",
    "name:kor_x_preferred":[
        "\ub355\ud3c9\ub9ac"
    ],
    "name:kor_x_variant":[
        "T\u014fkp\u2019y\u014fng-ni"
    ],
    "wof:name":"Tokp'yong-ni",
    "wof:placetype":"locality"
},
  "geometry": {"coordinates":[127.01917,39.26472],"type":"Point"}
}