{
  "type": "Feature",
  "properties": {
    "gn:admin1_code":"9.0",
    "gn:admin2_code":"1875980",
    "gn:asciiname":"Chang-gol",
    "gn:cc2":"KP",
    "gn:country_code":"KP",
    "gn:dem":519,
    "gn:feature_class":"P",
    "gn:feature_code":"PPL",
    "gn:name":"Chang-gol",
    "gn:population":0,
    "gn:timezone":"Asia/Pyongyang",
    "iso:country":"KP",
    "name:und_x_variant":[
        "Chang-kol",
        "Chang-gol"
    ],
    "wof:name":"Chang-gol",
    "wof:placetype":"locality"
},
  "geometry": {"coordinates":[127.48972000000001,38.40333],"type":"Point"}
}