{
  "type": "Feature",
  "properties": {
    "gn:admin1_code":"13.0",
    "gn:asciiname":"Sinhung-ni",
    "gn:country_code":"KP",
    "gn:dem":1023,
    "gn:feature_class":"P",
    "gn:feature_code":"PPL",
    "gn:name":"Sinh\u016dng-ni",
    "gn:population":0,
    "gn:timezone":"Asia/Pyongyang",
    "iso:country":"KP",
    "name:eng_x_preferred":[
        "Sinhung"
    ],
    "name:eng_x_variant":[
        "Sinhung-ni"
    ],
    "name:kor_x_preferred":[
        "\uc2e0\ud765\ub9ac"
    ],
    "name:und_x_variant":[
        "Sinh\u016dng-ni"
    ],
    "wof:name":"Sinhung",
    "wof:placetype":"locality"
},
  "geometry": {"coordinates":[128.39417,41.4825],"type":"Point"}
}