{
  "type": "Feature",
  "properties": {
    "gn:admin1_code":"9.0",
    "gn:asciiname":"Sindong-ni",
    "gn:country_code":"KP",
    "gn:dem":82,
    "gn:feature_class":"P",
    "gn:feature_code":"PPL",
    "gn:name":"Sindong-ni",
    "gn:population":0,
    "gn:timezone":"Asia/Pyongyang",
    "iso:country":"KP",
    "name:und_x_variant":[
        "\uc2e0\ub3d9\ub9ac"
    ],
    "wof:name":"Sindong-ni",
    "wof:placetype":"locality"
},
  "geometry": {"coordinates":[127.35927,39.15606],"type":"Point"}
}