{
  "type": "Feature",
  "properties": {
    "gn:admin1_code":"13.0",
    "gn:asciiname":"Hoebong-ni",
    "gn:country_code":"KP",
    "gn:dem":1442,
    "gn:feature_class":"P",
    "gn:feature_code":"PPL",
    "gn:name":"Hoebong-ni",
    "gn:population":0,
    "gn:timezone":"Asia/Pyongyang",
    "iso:country":"KP",
    "name:eng_x_preferred":[
        "Hoebong"
    ],
    "name:eng_x_variant":[
        "Hoebong-ni"
    ],
    "name:kor_x_preferred":[
        "\ud68c\ubcf5\ub9ac"
    ],
    "wof:name":"Hoebong",
    "wof:placetype":"locality"
},
  "geometry": {"coordinates":[128.06666999999999,41.05],"type":"Point"}
}