{
  "type": "Feature",
  "properties": {
    "gn:admin1_code":"11.0",
    "gn:asciiname":"Sangso-ri",
    "gn:country_code":"KP",
    "gn:dem":20,
    "gn:feature_class":"P",
    "gn:feature_code":"PPL",
    "gn:name":"Sangso-ri",
    "gn:population":0,
    "gn:timezone":"Asia/Pyongyang",
    "iso:country":"KP",
    "name:kor_x_preferred":[
        "\uc0c1\uc18c\ub9ac"
    ],
    "wof:name":"Sangso-ri",
    "wof:placetype":"locality"
},
  "geometry": {"coordinates":[125.37694,39.59333],"type":"Point"}
}