{
  "type": "Feature",
  "properties": {
    "gn:admin1_code":"15.0",
    "gn:asciiname":"Songnim-ni",
    "gn:country_code":"KP",
    "gn:dem":52,
    "gn:feature_class":"P",
    "gn:feature_code":"PPL",
    "gn:name":"Songnim-ni",
    "gn:population":0,
    "gn:timezone":"Asia/Pyongyang",
    "iso:country":"KP",
    "wof:name":"Songnim-ni",
    "wof:placetype":"locality"
},
  "geometry": {"coordinates":[125.90778,39.34222000000001],"type":"Point"}
}