{
  "type": "Feature",
  "properties": {
    "gn:admin1_code":"12.0",
    "gn:admin2_code":"Kangdong-gun",
    "gn:asciiname":"Ch'ungbi",
    "gn:country_code":"KP",
    "gn:dem":88,
    "gn:feature_class":"P",
    "gn:feature_code":"PPL",
    "gn:name":"Ch\u2019ungbi",
    "gn:population":0,
    "gn:timezone":"Asia/Pyongyang",
    "iso:country":"KP",
    "name:kor_x_preferred":[
        "\ucda9\ube44"
    ],
    "name:und_x_variant":[
        "Ch\u2019ungbi",
        "Chungbi"
    ],
    "wof:name":"Ch'ungbi",
    "wof:placetype":"locality"
},
  "geometry": {"coordinates":[126.09917,39.08889],"type":"Point"}
}