{
  "type": "Feature",
  "properties": {
    "gn:admin1_code":"6.0",
    "gn:asciiname":"Kalchong-gol",
    "gn:cc2":"KP",
    "gn:country_code":"KP",
    "gn:dem":17,
    "gn:feature_class":"P",
    "gn:feature_code":"PPL",
    "gn:name":"Kalch\u014fng-gol",
    "gn:population":0,
    "gn:timezone":"Asia/Pyongyang",
    "iso:country":"KP",
    "name:kor_x_preferred":[
        "\uac08\uc815\uace8"
    ],
    "name:und_x_variant":[
        "Haksan-ni",
        "Kassei-d\u014d",
        "Kamjy\u014fng-dong",
        "Kalch\u014fng-dong",
        "Kari-dong",
        "Kalch\u014fng-gol"
    ],
    "wof:name":"Kalchong-gol",
    "wof:placetype":"locality"
},
  "geometry": {"coordinates":[125.96972,37.83806],"type":"Point"}
}