{
  "type": "Feature",
  "properties": {
    "gn:admin1_code":"6.0",
    "gn:asciiname":"Konup-tong",
    "gn:country_code":"KP",
    "gn:dem":18,
    "gn:feature_class":"P",
    "gn:feature_code":"PPL",
    "gn:name":"K\u014fn\u016dp-tong",
    "gn:population":0,
    "gn:timezone":"Asia/Pyongyang",
    "iso:country":"KP",
    "name:eng_x_preferred":[
        "Konup"
    ],
    "name:eng_x_variant":[
        "Konup-tong"
    ],
    "name:kor_x_preferred":[
        "\uac70\ub2a1\ub3d9"
    ],
    "name:und_x_variant":[
        "K\u014fn\u016dp-tong"
    ],
    "wof:name":"Konup",
    "wof:placetype":"locality"
},
  "geometry": {"coordinates":[125.44694,38.43861],"type":"Point"}
}