{
  "type": "Feature",
  "properties": {
    "gn:admin1_code":"3.0",
    "gn:asciiname":"Chungdong-ni",
    "gn:country_code":"KP",
    "gn:dem":13,
    "gn:feature_class":"P",
    "gn:feature_code":"PPL",
    "gn:name":"Chungdong-ni",
    "gn:population":0,
    "gn:timezone":"Asia/Pyongyang",
    "iso:country":"KP",
    "name:eng_x_preferred":[
        "Chungdong"
    ],
    "name:eng_x_variant":[
        "Chungdong-ni"
    ],
    "name:und_x_variant":[
        "\uc911\ub3d9\ub9ac",
        "Chungdong-ni"
    ],
    "wof:name":"Chungdong",
    "wof:placetype":"locality"
},
  "geometry": {"coordinates":[127.44777999999999,39.59778],"type":"Point"}
}