{
  "type": "Feature",
  "properties": {
    "gn:admin1_code":"15.0",
    "gn:asciiname":"Sop'i",
    "gn:country_code":"KP",
    "gn:dem":274,
    "gn:feature_class":"P",
    "gn:feature_code":"PPL",
    "gn:name":"Sop\u2019i",
    "gn:population":0,
    "gn:timezone":"Asia/Pyongyang",
    "iso:country":"KP",
    "name:kor_x_preferred":[
        "\uc18c\ud53c"
    ],
    "name:kor_x_variant":[
        "Sop\u2019i"
    ],
    "wof:name":"Sop'i",
    "wof:placetype":"locality"
},
  "geometry": {"coordinates":[126.40194,39.26694000000001],"type":"Point"}
}