{
  "type": "Feature",
  "properties": {
    "gn:admin1_code":"15.0",
    "gn:asciiname":"Tok-tong",
    "gn:country_code":"KP",
    "gn:dem":354,
    "gn:feature_class":"P",
    "gn:feature_code":"PPL",
    "gn:name":"T\u014fk-tong",
    "gn:population":0,
    "gn:timezone":"Asia/Pyongyang",
    "iso:country":"KP",
    "name:kor_x_preferred":[
        "\ub355\ub3d9"
    ],
    "name:und_x_variant":[
        "T\u014fk-tong"
    ],
    "wof:name":"Tok-tong",
    "wof:placetype":"locality"
},
  "geometry": {"coordinates":[126.65333,39.43083],"type":"Point"}
}