{
  "type": "Feature",
  "properties": {
    "gn:admin1_code":"6.0",
    "gn:asciiname":"Unmaesong",
    "gn:country_code":"KP",
    "gn:dem":103,
    "gn:feature_class":"P",
    "gn:feature_code":"PPL",
    "gn:name":"Unmaes\u014fng",
    "gn:population":0,
    "gn:timezone":"Asia/Pyongyang",
    "iso:country":"KP",
    "name:und_x_variant":[
        "\uc6c3\ub9e4\uc131",
        "Unmaes\u014fng"
    ],
    "wof:name":"Unmaesong",
    "wof:placetype":"locality"
},
  "geometry": {"coordinates":[126.30944,38.0325],"type":"Point"}
}