{
  "type": "Feature",
  "properties": {
    "gn:admin1_code":"6.0",
    "gn:asciiname":"Saemal",
    "gn:cc2":"KP",
    "gn:country_code":"KP",
    "gn:dem":112,
    "gn:feature_class":"P",
    "gn:feature_code":"PPL",
    "gn:name":"Saemal",
    "gn:population":0,
    "gn:timezone":"Asia/Pyongyang",
    "iso:country":"KP",
    "name:und_x_variant":[
        "Sae-mol",
        "Saemal"
    ],
    "wof:name":"Saemal",
    "wof:placetype":"locality"
},
  "geometry": {"coordinates":[125.60527999999999,38.13361],"type":"Point"}
}