{
  "type": "Feature",
  "properties": {
    "gn:admin1_code":"9.0",
    "gn:admin2_code":"P\u2019y\u014fnggang-gun",
    "gn:asciiname":"Masal-li",
    "gn:country_code":"KP",
    "gn:dem":346,
    "gn:feature_class":"P",
    "gn:feature_code":"PPL",
    "gn:name":"Masal-li",
    "gn:population":0,
    "gn:timezone":"Asia/Pyongyang",
    "iso:country":"KP",
    "wof:name":"Masal-li",
    "wof:placetype":"locality"
},
  "geometry": {"coordinates":[127.33417,38.38528],"type":"Point"}
}