{
  "type": "Feature",
  "properties": {
    "gn:admin1_code":"7.0",
    "gn:asciiname":"Hadok-tong",
    "gn:country_code":"KP",
    "gn:dem":74,
    "gn:feature_class":"P",
    "gn:feature_code":"PPL",
    "gn:name":"Had\u014fk-tong",
    "gn:population":0,
    "gn:timezone":"Asia/Pyongyang",
    "iso:country":"KP",
    "name:eng_x_preferred":[
        "Hadok"
    ],
    "name:eng_x_variant":[
        "Hadok-tong"
    ],
    "wof:name":"Hadok",
    "wof:placetype":"locality"
},
  "geometry": {"coordinates":[125.79944,38.5225],"type":"Point"}
}