{
  "type": "Feature",
  "properties": {
    "gn:admin1_code":"9.0",
    "gn:asciiname":"Nolmak",
    "gn:country_code":"KP",
    "gn:dem":580,
    "gn:feature_class":"P",
    "gn:feature_code":"PPL",
    "gn:name":"N\u014flmak",
    "gn:population":0,
    "gn:timezone":"Asia/Pyongyang",
    "iso:country":"KP",
    "name:kor_x_preferred":[
        "\ub110\ub9c9"
    ],
    "name:kor_x_variant":[
        "N\u014flmak"
    ],
    "name:und_x_variant":[
        "P\u2019anmak"
    ],
    "wof:name":"Nolmak",
    "wof:placetype":"locality"
},
  "geometry": {"coordinates":[127.21056000000002,38.8925],"type":"Point"}
}