{
  "type": "Feature",
  "properties": {
    "gn:admin1_code":"3.0",
    "gn:asciiname":"Kal-tong",
    "gn:country_code":"KP",
    "gn:dem":223,
    "gn:feature_class":"P",
    "gn:feature_code":"PPL",
    "gn:name":"Kal-tong",
    "gn:population":0,
    "gn:timezone":"Asia/Pyongyang",
    "iso:country":"KP",
    "name:kor_x_preferred":[
        "\uac08\ub3d9"
    ],
    "wof:name":"Kal-tong",
    "wof:placetype":"locality"
},
  "geometry": {"coordinates":[127.0275,39.54583],"type":"Point"}
}