{
  "type": "Feature",
  "properties": {
    "gn:admin1_code":"6.0",
    "gn:asciiname":"Sema-ri",
    "gn:country_code":"KP",
    "gn:dem":80,
    "gn:feature_class":"P",
    "gn:feature_code":"PPL",
    "gn:name":"Sema-ri",
    "gn:population":0,
    "gn:timezone":"Asia/Pyongyang",
    "iso:country":"KP",
    "name:und_x_variant":[
        "\uc138\ub9c8\ub9ac",
        "Sema-ri"
    ],
    "wof:name":"Sema-ri",
    "wof:placetype":"locality"
},
  "geometry": {"coordinates":[125.1725,38.21083],"type":"Point"}
}