{
  "type": "Feature",
  "properties": {
    "gn:admin1_code":"11.0",
    "gn:asciiname":"Ohyon-dong",
    "gn:country_code":"KP",
    "gn:dem":293,
    "gn:feature_class":"P",
    "gn:feature_code":"PPL",
    "gn:name":"Ohy\u014fn-dong",
    "gn:population":0,
    "gn:timezone":"Asia/Pyongyang",
    "iso:country":"KP",
    "name:und_x_variant":[
        "\uc624\ud604\ub3d9",
        "Ohy\u014fn-dong"
    ],
    "wof:name":"Ohyon-dong",
    "wof:placetype":"locality"
},
  "geometry": {"coordinates":[125.79889,40.10833],"type":"Point"}
}