{
  "type": "Feature",
  "properties": {
    "gn:admin1_code":"17.0",
    "gn:asciiname":"Chungwol",
    "gn:country_code":"KP",
    "gn:dem":215,
    "gn:feature_class":"P",
    "gn:feature_code":"PPL",
    "gn:name":"Chungw\u014fl",
    "gn:population":0,
    "gn:timezone":"Asia/Pyongyang",
    "iso:country":"KP",
    "name:und_x_variant":[
        "\uc911\uc6d4",
        "Chungw\u014fl"
    ],
    "wof:name":"Chungwol",
    "wof:placetype":"locality"
},
  "geometry": {"coordinates":[129.40889000000001,41.16917],"type":"Point"}
}