{
  "type": "Feature",
  "properties": {
    "gn:admin1_code":"9.0",
    "gn:admin2_code":"1875980",
    "gn:asciiname":"Wonbung-ni",
    "gn:country_code":"KP",
    "gn:dem":340,
    "gn:feature_class":"P",
    "gn:feature_code":"PPL",
    "gn:name":"W\u014fnbung-ni",
    "gn:population":0,
    "gn:timezone":"Asia/Pyongyang",
    "iso:country":"KP",
    "name:eng_x_preferred":[
        "Wonbung"
    ],
    "name:eng_x_variant":[
        "Wonbung-ni"
    ],
    "wof:name":"Wonbung",
    "wof:placetype":"locality"
},
  "geometry": {"coordinates":[127.60250000000001,38.48722],"type":"Point"}
}