{
  "type": "Feature",
  "properties": {
    "gn:admin1_code":"17.0",
    "gn:asciiname":"Soch'ong-dong",
    "gn:country_code":"KP",
    "gn:dem":4,
    "gn:feature_class":"P",
    "gn:feature_code":"PPL",
    "gn:name":"Soch\u2019\u014fng-dong",
    "gn:population":0,
    "gn:timezone":"Asia/Pyongyang",
    "iso:country":"KP",
    "name:und_x_variant":[
        "\uc18c\uccad\ub3d9",
        "Soch\u2019\u014fng-dong"
    ],
    "wof:name":"Soch'ong-dong",
    "wof:placetype":"locality"
},
  "geometry": {"coordinates":[130.08638999999999,42.10111],"type":"Point"}
}