{
  "type": "Feature",
  "properties": {
    "gn:admin1_code":"1.0",
    "gn:asciiname":"Chungdal-li",
    "gn:country_code":"KP",
    "gn:dem":276,
    "gn:feature_class":"P",
    "gn:feature_code":"PPL",
    "gn:name":"Chungdal-li",
    "gn:population":0,
    "gn:timezone":"Asia/Pyongyang",
    "iso:country":"KP",
    "name:und_x_variant":[
        "\uc911\ub2e8\ub9ac",
        "Chungdal-li"
    ],
    "wof:name":"Chungdal-li",
    "wof:placetype":"locality"
},
  "geometry": {"coordinates":[126.02694,40.81889],"type":"Point"}
}