{
  "type": "Feature",
  "properties": {
    "gn:admin1_code":"1.0",
    "gn:asciiname":"Ungamch'am",
    "gn:country_code":"KP",
    "gn:dem":132,
    "gn:feature_class":"P",
    "gn:feature_code":"PPL",
    "gn:name":"\u016cngamch\u2019am",
    "gn:population":0,
    "gn:timezone":"Asia/Pyongyang",
    "iso:country":"KP",
    "name:und_x_variant":[
        "\uc751\uc554\ucc38",
        "\u016cngamch\u2019am"
    ],
    "wof:name":"Ungamch'am",
    "wof:placetype":"locality"
},
  "geometry": {"coordinates":[126.29167,40.15611],"type":"Point"}
}