{
  "type": "Feature",
  "properties": {
    "gn:admin1_code":"7.0",
    "gn:asciiname":"Ch'ogu",
    "gn:country_code":"KP",
    "gn:dem":28,
    "gn:feature_class":"P",
    "gn:feature_code":"PPL",
    "gn:name":"Ch\u2019ogu",
    "gn:population":0,
    "gn:timezone":"Asia/Pyongyang",
    "iso:country":"KP",
    "name:kor_x_preferred":[
        "\ucd08\uad6c"
    ],
    "name:kor_x_variant":[
        "Ch\u2019ogu"
    ],
    "wof:name":"Ch'ogu",
    "wof:placetype":"locality"
},
  "geometry": {"coordinates":[126.53139,38.30639],"type":"Point"}
}