{
  "type": "Feature",
  "properties": {
    "gn:admin1_code":"17.0",
    "gn:asciiname":"Hanch'amsu-dong",
    "gn:country_code":"KP",
    "gn:dem":505,
    "gn:feature_class":"P",
    "gn:feature_code":"PPL",
    "gn:name":"Hanch\u2019amsu-dong",
    "gn:population":0,
    "gn:timezone":"Asia/Pyongyang",
    "iso:country":"KP",
    "name:und_x_variant":[
        "Hansamsu-dong",
        "\ud55c\ucc38\uc218\ub3d9",
        "Hanch\u2019amsu-dong"
    ],
    "wof:name":"Hanch'amsu-dong",
    "wof:placetype":"locality"
},
  "geometry": {"coordinates":[129.11139,40.91944],"type":"Point"}
}