{
  "type": "Feature",
  "properties": {
    "gn:admin1_code":"17.0",
    "gn:admin2_code":"2038910",
    "gn:asciiname":"Kwangyang-ni",
    "gn:cc2":"KP",
    "gn:country_code":"KP",
    "gn:dem":745,
    "gn:feature_class":"P",
    "gn:feature_code":"PPL",
    "gn:name":"Kwangyang-ni",
    "gn:population":0,
    "gn:timezone":"Asia/Pyongyang",
    "iso:country":"KP",
    "name:und_x_variant":[
        "Kwangyang-dong",
        "Kwangyang-ni"
    ],
    "wof:name":"Kwangyang-ni",
    "wof:placetype":"locality"
},
  "geometry": {"coordinates":[129.00388999999998,41.86528],"type":"Point"}
}