{
  "type": "Feature",
  "properties": {
    "gn:admin1_code":"6.0",
    "gn:asciiname":"Chonghwaul",
    "gn:cc2":"KP",
    "gn:country_code":"KP",
    "gn:dem":26,
    "gn:feature_class":"P",
    "gn:feature_code":"PPL",
    "gn:name":"Chonghwaul",
    "gn:population":0,
    "gn:timezone":"Asia/Pyongyang",
    "iso:country":"KP",
    "name:kor_x_preferred":[
        "\uc885\ud654\uc6b8"
    ],
    "name:und_x_variant":[
        "Wanhwa-dong",
        "Chonghwa-dong",
        "Chonghwaul"
    ],
    "wof:name":"Chonghwaul",
    "wof:placetype":"locality"
},
  "geometry": {"coordinates":[125.88833,37.97306],"type":"Point"}
}