{
  "type": "Feature",
  "properties": {
    "gn:admin1_code":"7.0",
    "gn:asciiname":"Tongmang-ni",
    "gn:country_code":"KP",
    "gn:dem":122,
    "gn:feature_class":"P",
    "gn:feature_code":"PPL",
    "gn:name":"Tongmang-ni",
    "gn:population":0,
    "gn:timezone":"Asia/Pyongyang",
    "iso:country":"KP",
    "name:kor_x_preferred":[
        "\ub3d9\ub9c9\ub9ac"
    ],
    "wof:name":"Tongmang-ni",
    "wof:placetype":"locality"
},
  "geometry": {"coordinates":[126.41167,38.55194],"type":"Point"}
}