{
  "type": "Feature",
  "properties": {
    "gn:admin1_code":"3.0",
    "gn:asciiname":"Sadong-ni",
    "gn:country_code":"KP",
    "gn:dem":215,
    "gn:feature_class":"P",
    "gn:feature_code":"PPL",
    "gn:name":"Sadong-ni",
    "gn:population":0,
    "gn:timezone":"Asia/Pyongyang",
    "iso:country":"KP",
    "name:und_x_variant":[
        "\uc0ac\ub3d9\ub9ac"
    ],
    "wof:name":"Sadong-ni",
    "wof:placetype":"locality"
},
  "geometry": {"coordinates":[127.73444000000001,40.05611],"type":"Point"}
}