{
  "type": "Feature",
  "properties": {
    "gn:admin1_code":"11.0",
    "gn:asciiname":"Songi-ri",
    "gn:country_code":"KP",
    "gn:dem":196,
    "gn:feature_class":"P",
    "gn:feature_code":"PPL",
    "gn:name":"Songi-ri",
    "gn:population":0,
    "gn:timezone":"Asia/Pyongyang",
    "iso:country":"KP",
    "name:und_x_variant":[
        "\uc1a12\ub9ac",
        "Songi-ri"
    ],
    "wof:name":"Songi-ri",
    "wof:placetype":"locality"
},
  "geometry": {"coordinates":[125.33389,40.60444],"type":"Point"}
}