{
  "type": "Feature",
  "properties": {
    "gn:admin1_code":"3.0",
    "gn:asciiname":"Paean",
    "gn:country_code":"KP",
    "gn:dem":49,
    "gn:feature_class":"P",
    "gn:feature_code":"PPL",
    "gn:name":"Paean",
    "gn:population":0,
    "gn:timezone":"Asia/Pyongyang",
    "iso:country":"KP",
    "name:und_x_variant":[
        "\ubc30\uc548"
    ],
    "wof:name":"Paean",
    "wof:placetype":"locality"
},
  "geometry": {"coordinates":[128.27646999999999,40.22923],"type":"Point"}
}