{
  "type": "Feature",
  "properties": {
    "gn:admin1_code":"17.0",
    "gn:asciiname":"P'ungil-lodongjagu",
    "gn:country_code":"KP",
    "gn:dem":101,
    "gn:feature_class":"P",
    "gn:feature_code":"PPLL",
    "gn:name":"P\u2019ungil-lodongjagu",
    "gn:population":0,
    "gn:timezone":"Asia/Pyongyang",
    "iso:country":"KP",
    "name:und_x_variant":[
        "P\u2019ungin-dong",
        "P\u2019ungin-nodongjagu",
        "P\u2019ungin-ni",
        "\ud48d\uc778\ub85c\ub3d9\uc790\uad6c",
        "P\u2019ungil-lodongjagu"
    ],
    "wof:name":"P'ungil-lodongjagu",
    "wof:placetype":"locality"
},
  "geometry": {"coordinates":[130.03999999999999,42.93444],"type":"Point"}
}