{
  "type": "Feature",
  "properties": {
    "gn:admin1_code":"15.0",
    "gn:asciiname":"Chogaesom",
    "gn:cc2":"KP",
    "gn:country_code":"KP",
    "gn:dem":6,
    "gn:feature_class":"P",
    "gn:feature_code":"PPL",
    "gn:name":"Chogaes\u014fm",
    "gn:population":0,
    "gn:timezone":"Asia/Pyongyang",
    "iso:country":"KP",
    "name:und_x_variant":[
        "Hap-to",
        "Chogaes\u014fm"
    ],
    "wof:name":"Chogaesom",
    "wof:placetype":"locality"
},
  "geometry": {"coordinates":[125.57111,38.89722],"type":"Point"}
}