{
  "type": "Feature",
  "properties": {
    "gn:admin1_code":"7.0",
    "gn:asciiname":"Sangsaeng-gol",
    "gn:country_code":"KP",
    "gn:dem":162,
    "gn:feature_class":"P",
    "gn:feature_code":"PPL",
    "gn:name":"Sangsaeng-gol",
    "gn:population":0,
    "gn:timezone":"Asia/Pyongyang",
    "iso:country":"KP",
    "name:kor_x_preferred":[
        "\uc0c1\uc0dd\uace8"
    ],
    "wof:name":"Sangsaeng-gol",
    "wof:placetype":"locality"
},
  "geometry": {"coordinates":[126.29861,38.62278],"type":"Point"}
}