{
  "type": "Feature",
  "properties": {
    "gn:admin1_code":"0.0",
    "gn:asciiname":"Ch'angmae-ri",
    "gn:country_code":"KP",
    "gn:dem":37,
    "gn:feature_class":"P",
    "gn:feature_code":"PPL",
    "gn:name":"Ch\u2019angmae-ri",
    "gn:population":0,
    "gn:timezone":"Asia/Pyongyang",
    "iso:country":"KP",
    "name:kor_x_preferred":[
        "\ucc3d\ub9e4\ub9ac"
    ],
    "name:und_x_variant":[
        "Ch\u2019angmae-ri"
    ],
    "wof:name":"Ch'angmae-ri",
    "wof:placetype":"locality"
},
  "geometry": {"coordinates":[125.95,38.68333],"type":"Point"}
}