{
  "type": "Feature",
  "properties": {
    "gn:admin1_code":"11.0",
    "gn:asciiname":"Tongsam-gol",
    "gn:country_code":"KP",
    "gn:dem":11,
    "gn:feature_class":"P",
    "gn:feature_code":"PPL",
    "gn:name":"Tongsam-gol",
    "gn:population":0,
    "gn:timezone":"Asia/Pyongyang",
    "iso:country":"KP",
    "name:und_x_variant":[
        "Tongsam-kol",
        "\ub3d9\uc0bc\uace8",
        "Tongsam-gol"
    ],
    "wof:name":"Tongsam-gol",
    "wof:placetype":"locality"
},
  "geometry": {"coordinates":[124.49694,40.18056],"type":"Point"}
}