{
  "type": "Feature",
  "properties": {
    "gn:admin1_code":"3.0",
    "gn:asciiname":"Ussuk-kol",
    "gn:country_code":"KP",
    "gn:dem":29,
    "gn:feature_class":"P",
    "gn:feature_code":"PPL",
    "gn:name":"Ussuk-kol",
    "gn:population":0,
    "gn:timezone":"Asia/Pyongyang",
    "iso:country":"KP",
    "name:und_x_variant":[
        "\uc6c3\uc22b\uace8",
        "Ussuk-kol"
    ],
    "wof:name":"Ussuk-kol",
    "wof:placetype":"locality"
},
  "geometry": {"coordinates":[127.67194000000001,39.86444],"type":"Point"}
}