{
  "type": "Feature",
  "properties": {
    "gn:admin1_code":"3.0",
    "gn:asciiname":"Ch'ohung-ni",
    "gn:country_code":"KP",
    "gn:dem":66,
    "gn:feature_class":"P",
    "gn:feature_code":"PPL",
    "gn:name":"Ch\u2019oh\u016dng-ni",
    "gn:population":0,
    "gn:timezone":"Asia/Pyongyang",
    "iso:country":"KP",
    "name:und_x_variant":[
        "\ucd08\ud765\ub9ac",
        "Ch\u2019oh\u016dng-ni"
    ],
    "wof:name":"Ch'ohung-ni",
    "wof:placetype":"locality"
},
  "geometry": {"coordinates":[127.59833,40.015],"type":"Point"}
}