{
  "type": "Feature",
  "properties": {
    "gn:admin1_code":"12.0",
    "gn:asciiname":"Samsong-ni",
    "gn:country_code":"KP",
    "gn:dem":63,
    "gn:feature_class":"P",
    "gn:feature_code":"PPL",
    "gn:name":"Sams\u014fng-ni",
    "gn:population":0,
    "gn:timezone":"Asia/Pyongyang",
    "iso:country":"KP",
    "name:kor_x_preferred":[
        "Sams\u014fng-ni"
    ],
    "name:kor_x_variant":[
        "\uc0bc\uc11d\ub9ac"
    ],
    "name:und_x_variant":[
        "Samseongni"
    ],
    "wof:name":"Samsong-ni",
    "wof:placetype":"locality"
},
  "geometry": {"coordinates":[125.83608,39.12019],"type":"Point"}
}