{
  "type": "Feature",
  "properties": {
    "gn:admin1_code":"6.0",
    "gn:asciiname":"Manam-ni",
    "gn:cc2":"KP",
    "gn:country_code":"KP",
    "gn:dem":13,
    "gn:feature_class":"P",
    "gn:feature_code":"PPL",
    "gn:name":"Manam-ni",
    "gn:population":0,
    "gn:timezone":"Asia/Pyongyang",
    "iso:country":"KP",
    "name:und_x_variant":[
        "N\u016dngch\u2019on",
        "Mar\u016dmni",
        "Manam-ni"
    ],
    "wof:name":"Manam-ni",
    "wof:placetype":"locality"
},
  "geometry": {"coordinates":[126.23888999999998,37.88917],"type":"Point"}
}