{
  "type": "Feature",
  "properties": {
    "iso:country":"KP",
    "name:epo_x_preferred":[
        "Flughaveno Samjiy\u014fn"
    ],
    "name:fas_x_preferred":[
        "\u0641\u0631\u0648\u062f\u06af\u0627\u0647 \u0633\u0645\u062c\u06cc\u0648\u0646"
    ],
    "name:kor_x_preferred":[
        "\uc0bc\uc9c0\uc5f0\uacf5\ud56d"
    ],
    "name:pol_x_preferred":[
        "Port lotniczy Samjiy\u014fn"
    ],
    "name:spa_x_preferred":[
        "Aeropuerto de Samjiyon"
    ],
    "name:tgk_x_preferred":[
        "\u0424\u0443\u0440\u0443\u0434\u0433\u043e\u04b3\u0438 \u0441\u043c\u04b7\u044e\u043d"
    ],
    "name:vie_x_preferred":[
        "S\u00e2n bay Samjiy\u014fn"
    ],
    "name:zho_x_preferred":[
        "\u4e09\u6c60\u6df5\u6a5f\u5834"
    ],
    "oa:elevation_ft":"4547",
    "oa:type":"small_airport",
    "wd:wordcount":261,
    "woe:hierarchy":{
        "country_id":23424865,
        "planet_id":1,
        "state_id":2345956
    },
    "wof:name":"Samjiyon Airport",
    "wof:placetype":"campus"
},
  "geometry": {"coordinates":[128.40988888999999,41.90716667],"type":"Point"}
}