{
  "type": "Feature",
  "properties": {
    "gn:admin1_code":"3.0",
    "gn:admin2_code":"Tanch'\u014fn-si",
    "gn:asciiname":"Paekchon",
    "gn:country_code":"KP",
    "gn:dem":1244,
    "gn:feature_class":"P",
    "gn:feature_code":"PPL",
    "gn:name":"Paekch\u014fn",
    "gn:population":0,
    "gn:timezone":"Asia/Pyongyang",
    "iso:country":"KP",
    "name:und_x_variant":[
        "\ubc31\uc804",
        "Paekch\u014fn"
    ],
    "wof:name":"Paekchon",
    "wof:placetype":"locality"
},
  "geometry": {"coordinates":[128.89111,40.98639],"type":"Point"}
}