{
  "type": "Feature",
  "properties": {
    "gn:admin1_code":"15.0",
    "gn:asciiname":"Tapto-ri",
    "gn:country_code":"KP",
    "gn:dem":58,
    "gn:feature_class":"P",
    "gn:feature_code":"PPL",
    "gn:name":"Tapto-ri",
    "gn:population":0,
    "gn:timezone":"Asia/Pyongyang",
    "iso:country":"KP",
    "name:kor_x_preferred":[
        "\ub2f5\ub3c4\ub9ac"
    ],
    "wof:name":"Tapto-ri",
    "wof:placetype":"locality"
},
  "geometry": {"coordinates":[125.91306000000002,39.5625],"type":"Point"}
}