{
  "type": "Feature",
  "properties": {
    "gn:admin1_code":"3.0",
    "gn:asciiname":"Pyorhak-ch'on",
    "gn:country_code":"KP",
    "gn:dem":59,
    "gn:feature_class":"P",
    "gn:feature_code":"PPL",
    "gn:name":"Py\u014frhak-ch\u2019on",
    "gn:population":0,
    "gn:timezone":"Asia/Pyongyang",
    "iso:country":"KP",
    "name:und_x_variant":[
        "Betsukakuson",
        "Pingaech\u2019on",
        "\ubcc4\ud559\ucd0c",
        "Py\u014frhak-ch\u2019on"
    ],
    "wof:name":"Pyorhak-ch'on",
    "wof:placetype":"locality"
},
  "geometry": {"coordinates":[128.81999999999999,40.4975],"type":"Point"}
}