{
  "type": "Feature",
  "properties": {
    "gn:admin1_code":"9.0",
    "gn:asciiname":"Panghasal-li",
    "gn:cc2":"KP",
    "gn:country_code":"KP",
    "gn:dem":5,
    "gn:feature_class":"P",
    "gn:feature_code":"PPL",
    "gn:name":"Panghasal-li",
    "gn:population":0,
    "gn:timezone":"Asia/Pyongyang",
    "iso:country":"KP",
    "name:und_x_variant":[
        "Panghasan-ni",
        "Panghasal-li"
    ],
    "wof:name":"Panghasal-li",
    "wof:placetype":"locality"
},
  "geometry": {"coordinates":[127.38333,39.18333],"type":"Point"}
}