{
  "type": "Feature",
  "properties": {
    "gn:admin1_code":"9.0",
    "gn:asciiname":"Siphyon-dong",
    "gn:cc2":"KP",
    "gn:country_code":"KP",
    "gn:dem":126,
    "gn:feature_class":"P",
    "gn:feature_code":"PPL",
    "gn:name":"Siphy\u014fn-dong",
    "gn:population":0,
    "gn:timezone":"Asia/Pyongyang",
    "iso:country":"KP",
    "name:und_x_variant":[
        "P\u014flch\u014fng-dong",
        "Siphy\u014fn-dong"
    ],
    "wof:name":"Siphyon-dong",
    "wof:placetype":"locality"
},
  "geometry": {"coordinates":[126.96889,38.38944],"type":"Point"}
}