{
  "type": "Feature",
  "properties": {
    "gn:admin1_code":"9.0",
    "gn:asciiname":"Masan-dong",
    "gn:country_code":"KP",
    "gn:dem":390,
    "gn:feature_class":"P",
    "gn:feature_code":"PPL",
    "gn:name":"Masan-dong",
    "gn:population":0,
    "gn:timezone":"Asia/Pyongyang",
    "iso:country":"KP",
    "name:und_x_variant":[
        "\ub9c8\uc0b0\ub3d9",
        "Masan-dong"
    ],
    "wof:name":"Masan-dong",
    "wof:placetype":"locality"
},
  "geometry": {"coordinates":[127.60083,38.72361],"type":"Point"}
}