{
  "type": "Feature",
  "properties": {
    "gn:admin1_code":"15.0",
    "gn:asciiname":"Saen-mal",
    "gn:country_code":"KP",
    "gn:dem":93,
    "gn:feature_class":"P",
    "gn:feature_code":"PPL",
    "gn:name":"Saen-mal",
    "gn:population":0,
    "gn:timezone":"Asia/Pyongyang",
    "iso:country":"KP",
    "name:kor_x_preferred":[
        "\uc0db\ub9d0"
    ],
    "wof:name":"Saen-mal",
    "wof:placetype":"locality"
},
  "geometry": {"coordinates":[126.15917,39.36778],"type":"Point"}
}