{
  "type": "Feature",
  "properties": {
    "gn:admin1_code":"17.0",
    "gn:asciiname":"Kwirak-kol",
    "gn:country_code":"KP",
    "gn:dem":328,
    "gn:feature_class":"P",
    "gn:feature_code":"PPL",
    "gn:name":"Kwirak-kol",
    "gn:population":0,
    "gn:timezone":"Asia/Pyongyang",
    "iso:country":"KP",
    "wof:name":"Kwirak-kol",
    "wof:placetype":"locality"
},
  "geometry": {"coordinates":[129.54056,40.93667],"type":"Point"}
}