{
  "type": "Feature",
  "properties": {
    "gn:admin1_code":"9.0",
    "gn:asciiname":"Sinwagyo",
    "gn:country_code":"KP",
    "gn:dem":9,
    "gn:feature_class":"P",
    "gn:feature_code":"PPL",
    "gn:name":"Sinwagyo",
    "gn:population":0,
    "gn:timezone":"Asia/Pyongyang",
    "iso:country":"KP",
    "name:und_x_variant":[
        "\uc2e0\ud654\uad50"
    ],
    "wof:name":"Sinwagyo",
    "wof:placetype":"locality"
},
  "geometry": {"coordinates":[127.5475,39.1175],"type":"Point"}
}