{
  "type": "Feature",
  "properties": {
    "gn:admin1_code":"11.0",
    "gn:asciiname":"Puksam-ni",
    "gn:country_code":"KP",
    "gn:dem":17,
    "gn:feature_class":"P",
    "gn:feature_code":"PPL",
    "gn:name":"Puksam-ni",
    "gn:population":0,
    "gn:timezone":"Asia/Pyongyang",
    "iso:country":"KP",
    "name:eng_x_preferred":[
        "Puksam"
    ],
    "name:eng_x_variant":[
        "Puksam-ni"
    ],
    "name:kor_x_preferred":[
        "\ubd81\uc0bc\ub9ac"
    ],
    "wof:name":"Puksam",
    "wof:placetype":"locality"
},
  "geometry": {"coordinates":[125.54000000000001,39.64194],"type":"Point"}
}