{
  "type": "Feature",
  "properties": {
    "gn:admin1_code":"15.0",
    "gn:admin2_code":"T\u014fkch\u2019\u014fn-gun",
    "gn:asciiname":"Masal-li",
    "gn:country_code":"KP",
    "gn:dem":274,
    "gn:feature_class":"P",
    "gn:feature_code":"PPL",
    "gn:name":"Masal-li",
    "gn:population":0,
    "gn:timezone":"Asia/Pyongyang",
    "iso:country":"KP",
    "name:und_x_variant":[
        "Masan-ni",
        "Masal-li"
    ],
    "wof:name":"Masal-li",
    "wof:placetype":"locality"
},
  "geometry": {"coordinates":[126.39472000000001,39.83556],"type":"Point"}
}