{
  "type": "Feature",
  "properties": {
    "gn:admin1_code":"6.0",
    "gn:asciiname":"Pusal-li",
    "gn:cc2":"KP",
    "gn:country_code":"KP",
    "gn:dem":104,
    "gn:feature_class":"P",
    "gn:feature_code":"PPL",
    "gn:name":"Pusal-li",
    "gn:population":0,
    "gn:timezone":"Asia/Pyongyang",
    "iso:country":"KP",
    "name:und_x_variant":[
        "Pusan-ni",
        "Pusal-li"
    ],
    "wof:name":"Pusal-li",
    "wof:placetype":"locality"
},
  "geometry": {"coordinates":[125.72638999999999,38.15361],"type":"Point"}
}