{
  "type": "Feature",
  "properties": {
    "gn:admin1_code":"13.0",
    "gn:asciiname":"Choltong-ni",
    "gn:country_code":"KP",
    "gn:dem":840,
    "gn:feature_class":"P",
    "gn:feature_code":"PPL",
    "gn:name":"Ch\u014flt\u014fng-ni",
    "gn:population":0,
    "gn:timezone":"Asia/Pyongyang",
    "iso:country":"KP",
    "name:eng_x_preferred":[
        "Choltong"
    ],
    "name:eng_x_variant":[
        "Choltong-ni"
    ],
    "name:kor_x_preferred":[
        "\uc808\ub355\ub9ac"
    ],
    "name:und_x_variant":[
        "Oh\u014flt\u014fng-ni",
        "Ch\u014flt\u014fng-ni"
    ],
    "wof:name":"Choltong",
    "wof:placetype":"locality"
},
  "geometry": {"coordinates":[128.24021999999999,41.32932],"type":"Point"}
}